Workbook

Sheet 樣板單
A1: ZURU Rainbocorn 樣板訂單 | V1: 1代珠片公仔#9201 | AE1: 2代珠片公仔#9202 | AN1: #9204 | AW1: #9214 | BE1: #9209 | BV1: #9202 | CI1: #9204 | CO1: #9214（第二代） | CU1: #9209 | CX1: #9215 | DE1: #9212 | DK1: #9213 | DN1: #9207 | DO1: #9208
V2: 收縮膜 | Y2: 說明書 | AE2: 收縮膜 | AH2: 說明書 | AN2: A版本 | AP2: B版本 | BJ2: 3 | BL2: 4 | BN2: 5 | BP2: 5 | BR2: 4 | BT2: 3
A3: 香港接单日期 | B3: ZURU 跟单 | C3: ZURU PO NO# | D3: 第三方客户 PO NO# | E3: 第三方客户名称 | F3: ITEM# | G3: 中文名 | H3: PO数量 (pcs) | I3: 内箱装箱数量(pcs) | J3: 外箱装箱数量(pcs) | K3: 总箱数 | L3: 单价USD | M3: 金额USD | N3: ZURU验货 日期 | O3: 驗貨結果 | P3: 第三方客户公证行验货 | Q3: ZURU订单走货日期 | R3: ZURU确认走货日期 | S3: 箱唛资料(收到日期) | T3: 箱唛资料(确认日期) | U3: 客供贴纸AI(收到日期) | V3: MA 1語收縮膜 | W3: MA 3語收縮膜 | X3: 客版收縮膜 | Y3: MA 1語说明书 A版本 | Z3: MA 1語说明书 B版本 | AA3: MA 3語說明書 A版本 | AB3: MA 3語說明書 B版本 | AC3: 客版說明書 | AD3: 布標 | AE3: MA 1語收縮膜 | AF3: MA 3語收縮膜 | AG3: 客版收縮膜 | AH3: MA 1語说明书 A版本 | AI3: MA 1語说明书 B版本 | AJ3: MA 3語說明書 A版本 | AK3: MA 3語說明書 B版本 | AL3: 客版說明書 | AM3: 布標 | AN3: MA 1語收縮膜 | AO3: MA 1語說明書 | AP3: MA 1語收縮膜 | AQ3: MA 1語說明書 | AR3: MA 2語收縮膜（加拿大版本） | AS3: MA 2語說明書（加拿大版本） | AT3: 落加拿大 棉花泥 | AU3: 9201SQ1 | AV3: 9204UQ1 | AW3: MA 1語收縮膜 A | AX3: MA 1語收縮膜 B | AY3: MA 1語說明書 A | AZ3: MA 1語收縮膜 B | BA3: MA 1語說明書 B | BB3: MA领养卡 | BC3: 9214SQ1 MA PDQ盒 | BD3: 9214UQ1 客办PDQ盒 | BE3: MA 1語收縮膜 | BF3: MA 1語說明書 | BG3: MA 3語收縮膜 | BH3: MA 3語說明書 | BI3: 發票號 | BJ3: 玫紅猴子 Monkey（A） | BK3: 黃色猴子 Monkey（B） | BL3: 粉紅貓 Kitty （A） | BM3: 玫紅貓 Kitty （B） | BN3: 白色兔子 Rabbit （A） | BO3: 玫紅兔子 Rabbit （B） | BP3: 白色獨角獸 Unicorn （A） | BQ3: 玫紅獨角獸 Unicorn （B） | BR3: 紫色小狗 Puppy （A） | BS3: 藍色小狗 Puppy （B） | BT3: 粉色倉鼠 Hamster （A） | BU3: 橙色倉鼠 Hamster （B） | BV3: 羊駝 Llama（白色） | BW3: 羊駝 Llama（紫色） | BX3: 火烈鳥 Flamingo （玫紅色） | BY3: 火烈鳥 Flamingo （彩虹色） | BZ3: 火烈鳥 Flamingo （金色） | CA3: 熊貓 Panda （黑白色） | CB3: 熊貓 Panda （粉紅色） | CC3: 貓頭鷹 OWL （紫色） | CD3: 貓頭鷹 OWL （白色） | CE3: 獨角獸 Unicorn （白色） | CF3: 獨角獸 Unicorn （紫色） | CG3: 獅子 Lion （粉紅色） | CH3: 獅子 Lion （黃色） | CI3: 白色獨角獸 Unicorn | CJ3: 枚红色火烈鸟 Flamingo | CK3: 白色羊驼 Llama | CL3: 粉红色猫 Kitty | CM3: 紫色兔子 Bunny | CN3: 蓝色小狗 Puppy | CO3: 白色猫头鹰 White Owl | CP3: 粉色狮子 Pink Lion | CQ3: 黄色猴子 Yellow Monkey | CR3: 紫色独角兽 Purple Unicorn | CS3: 白色熊猫 White Panda | CT3: 彩色火烈鸟 Colour Flamingo | CU3: 獨角獸 Unicorn | CV3: 白色羊驼 Llama | CW3: 枚红色火烈鸟 Flamingo | CX3: 孔雀 Peacock | CY3: 火烈鸟 Toucan | CZ3: 树懒 Sloth | DA3: 大象 Elephant | DB3: 老虎 Tiger | DC3: 梅花鹿 Giraffe | DD3: 斑马 Zebra | DE3: 兔子 Bunny 含海绵 | DF3: 小狗 Puppy | DG3: 羊驼 Llama | DH3: 小猫 Kitty 含海绵 | DI3: 独角兽 Unicorn | DJ3: 猴子 Monkey | DK3: 小猫 Kitten | DL3: 独角兽 Unicorn | DM3: 大嘴鸟 Toucan | DN3: 2PK超小蛋殼公仔 | DO3: 4PK超小蛋殼公仔
A4: 43243 | B4: Binnie | C4: ZMPO18068 | F4: 9201-S001 | G4: 珠片公仔 | H4: 360 | V4: =H4 -> 360 | Y4: =H4 -> 360 | AD4: MA布標 | BI4: 19573 | BJ4: =H4/12 -> 30 | BK4: =H4/12 -> 30 | BL4: =H4/12 -> 30 | BM4: =H4/12 -> 30 | BN4: =H4/12 -> 30 | BO4: =H4/12 -> 30 | BP4: =H4/12 -> 30 | BQ4: =H4/12 -> 30 | BR4: =H4/12 -> 30 | BS4: =H4/12 -> 30 | BT4: =H4/12 -> 30 | BU4: =H4/12 -> 30
A5: 43265 | B5: Amanda | C5: ZMPO18078 | F5: 9201-S001 | G5: 珠片公仔 | H5: 480 | V5: =H5 -> 480 | Y5: =H5 -> 480 | AD5: MA布標 | BI5: 19654 | BJ5: =H5/12 -> 40 | BK5: =H5/12 -> 40 | BL5: =H5/12 -> 40 | BM5: =H5/12 -> 40 | BN5: =H5/12 -> 40 | BO5: =H5/12 -> 40 | BP5: =H5/12 -> 40 | BQ5: =H5/12 -> 40 | BR5: =H5/12 -> 40 | BS5: =H5/12 -> 40 | BT5: =H5/12 -> 40 | BU5: =H5/12 -> 40
A6: 43265 | B6: Angela | C6: 4500010393 | E6: 簽板 | F6: 9201-S001 | G6: 珠片公仔 | H6: 36 | V6: =H6 -> 36 | Y6: =H6 -> 36 | AD6: MA布標 | BJ6: =H6/12 -> 3 | BK6: =H6/12 -> 3 | BL6: =H6/12 -> 3 | BM6: =H6/12 -> 3 | BN6: =H6/12 -> 3 | BO6: =H6/12 -> 3 | BP6: =H6/12 -> 3 | BQ6: =H6/12 -> 3 | BR6: =H6/12 -> 3 | BS6: =H6/12 -> 3 | BT6: =H6/12 -> 3 | BU6: =H6/12 -> 3
A7: 43265 | B7: Lingly | C7: 4500010570 | E7: GP測試版 | F7: 9201-S001 | G7: 珠片公仔 | H7: 12 | V7: =H7 -> 12 | Y7: =H7 -> 12 | AD7: MA布標 | BJ7: =H7/12 -> 1 | BK7: =H7/12 -> 1 | BL7: =H7/12 -> 1 | BM7: =H7/12 -> 1 | BN7: =H7/12 -> 1 | BO7: =H7/12 -> 1 | BP7: =H7/12 -> 1 | BQ7: =H7/12 -> 1 | BR7: =H7/12 -> 1 | BS7: =H7/12 -> 1 | BT7: =H7/12 -> 1 | BU7: =H7/12 -> 1
A8: 43265 | B8: Holly | C8: 4500009837 | E8: 寄客版 | F8: 9201-S001 | G8: 珠片公仔 | H8: 12 | V8: =H8 -> 12 | Y8: =H8 -> 12 | AD8: MA布標 | BJ8: =H8/12 -> 1 | BK8: =H8/12 -> 1 | BL8: =H8/12 -> 1 | BM8: =H8/12 -> 1 | BN8: =H8/12 -> 1 | BO8: =H8/12 -> 1 | BP8: =H8/12 -> 1 | BQ8: =H8/12 -> 1 | BR8: =H8/12 -> 1 | BS8: =H8/12 -> 1 | BT8: =H8/12 -> 1 | BU8: =H8/12 -> 1
A9: 43270 | B9: Sara | C9: 郵件 | E9: Candide客户样品 | F9: 9201-S001 | G9: 珠片公仔 | H9: 6 | V9: =H9 -> 6 | Y9: =H9 -> 6 | AD9: MA布標 | BJ9: 1 | BL9: 1 | BN9: 1 | BP9: 1 | BR9: 1 | BT9: 1
A10: 43270 | B10: Sara | C10: 4500010598 | E10: WABRO | F10: 9201-S001 | G10: 珠片公仔 | H10: 24 | V10: =H10 -> 24 | Y10: =H10 -> 24 | AD10: MA布標 | BJ10: =H10/12 -> 2 | BK10: =H10/12 -> 2 | BL10: =H10/12 -> 2 | BM10: =H10/12 -> 2 | BN10: =H10/12 -> 2 | BO10: =H10/12 -> 2 | BP10: =H10/12 -> 2 | BQ10: =H10/12 -> 2 | BR10: =H10/12 -> 2 | BS10: =H10/12 -> 2 | BT10: =H10/12 -> 2 | BU10: =H10/12 -> 2
A11: 43277 | B11: Tiffany | C11: 4500010957 | D11: 大貨簽板 | E11: EURO TOYS EUROPE BV | F11: 9201-S001 | G11: 珠片公仔 | H11: 36 | X11: 36 | AC11: 36 | AD11: MA布標 | BJ11: =H11/12 -> 3 | BK11: =H11/12 -> 3 | BL11: =H11/12 -> 3 | BM11: =H11/12 -> 3 | BN11: =H11/12 -> 3 | BO11: =H11/12 -> 3 | BP11: =H11/12 -> 3 | BQ11: =H11/12 -> 3 | BR11: =H11/12 -> 3 | BS11: =H11/12 -> 3 | BT11: =H11/12 -> 3 | BU11: =H11/12 -> 3
A12: 43277 | B12: Lucky | C12: 450012096 | D12: 產前測試 | E12: CENCOSUD CHILE | F12: 9201-S001 | G12: 珠片公仔 | H12: 12 | V12: 12 | Y12: 12 | AD12: MA布標 | BJ12: =H12/12 -> 1 | BK12: =H12/12 -> 1 | BL12: =H12/12 -> 1 | BM12: =H12/12 -> 1 | BN12: =H12/12 -> 1 | BO12: =H12/12 -> 1 | BP12: =H12/12 -> 1 | BQ12: =H12/12 -> 1 | BR12: =H12/12 -> 1 | BS12: =H12/12 -> 1 | BT12: =H12/12 -> 1 | BU12: =H12/12 -> 1
A13: 43265 | B13: Lingly | C13: 4500010570 | E13: 年齡評估樣品 | F13: 9201-S001 | G13: 珠片公仔 | H13: 2 | V13: 12 | Y13: 12 | AD13: MA布標 | BN13: 1 | BO13: 1
A14: 43284 | C14: ZMPO18086 | F14: 9201-S001 | G14: 珠片公仔 | H14: 480 | V14: 480 | Y14: 480 | AD14: MA布標 | BI14: 19655 | BJ14: =H14/12 -> 40 | BK14: =H14/12 -> 40 | BL14: =H14/12 -> 40 | BM14: =H14/12 -> 40 | BN14: =H14/12 -> 40 | BO14: =H14/12 -> 40 | BP14: =H14/12 -> 40 | BQ14: =H14/12 -> 40 | BR14: =H14/12 -> 40 | BS14: =H14/12 -> 40 | BT14: =H14/12 -> 40 | BU14: =H14/12 -> 40
A15: 43286 | C15: 4500010467 | F15: 9201-S001 | G15: 珠片公仔 | H15: 10 | V15: 10 | Y15: 10 | AD15: MA布標 | BL15: 1 | BM15: 1 | BN15: 1 | BO15: 1 | BP15: 1 | BQ15: 1 | BR15: 1 | BS15: 1 | BT15: 1 | BU15: 1
A16: 43287 | C16: 4500010333 | F16: 9201-S001 | G16: 珠片公仔 | H16: 10 | V16: 10 | Y16: 10 | AD16: MA布標 | BL16: 1 | BM16: 1 | BN16: 1 | BO16: 1 | BP16: 1 | BQ16: 1 | BR16: 1 | BS16: 1 | BT16: 1 | BU16: 1
A17: 43302 | C17: 4500012533 | F17: 9201-S001 | G17: 珠片公仔 | H17: 12 | V17: 12 | Y17: 12 | AD17: MA布標 | BJ17: 1 | BK17: 1 | BL17: 1 | BM17: 1 | BN17: 1 | BO17: 1 | BP17: 1 | BQ17: 1 | BR17: 1 | BS17: 1 | BT17: 1 | BU17: 1
A18: 43302 | C18: 4500010568 | F18: 9201-S001 | G18: 珠片公仔 | H18: 4 | V18: 4 | AC18: 4 | AD18: 丹麥布標 | BJ18: 1 | BL18: 1 | BN18: 1 | BP18: 1
A19: 43306 | C19: 4500010570 | E19: GP FRANCE | F19: 9201-S001 | G19: 珠片公仔 | H19: 28 | X19: 28 | Y19: 28 | AD19: 法國布標 | BJ19: 3 | BK19: 2 | BL19: 3 | BM19: 2 | BN19: 3 | BO19: 2 | BP19: 3 | BQ19: 2 | BR19: 2 | BS19: 2 | BT19: 2 | BU19: 2
A20: 43306 | C20: 4500010574 | E20: GP ITALY | F20: 9201-S001 | G20: 珠片公仔 | H20: 25 | X20: 25 | Y20: 25 | AD20: 意大利布標 | BJ20: 2 | BK20: 2 | BL20: 2 | BM20: 2 | BN20: 2 | BO20: 2 | BP20: 3 | BQ20: 2 | BR20: 2 | BS20: 2 | BT20: 2 | BU20: 2
A21: 43313 | C21: 4500009768 | E21: TOY TRIANGLE CO.W.L.L | F21: 9201-S001 | G21: 珠片公仔 | H21: 2 | V21: 2 | Y21: 2 | AD21: MA布標 | BN21: 1 | BP21: 1
A22: 43313 | C22: 4500012277 | E22: Express Gifts Ltd | F22: 9201-S006 | G22: 珠片公仔 | H22: 10 | V22: 10 | Y22: 10 | AD22: MA布標 | BL22: 1 | BM22: 1 | BN22: 1 | BO22: 1 | BP22: 1 | BQ22: 1 | BR22: 1 | BS22: 1 | BT22: 1 | BU22: 1
A23: 43316 | C23: 4500009878 | E23: P.M.I TRADING & ENTERPRISE LTS34 | F23: 9201-S001 | G23: 珠片公仔 | H23: 2 | V23: 2 | Y23: 2 | AD23: MA布標
A24: 43318 | C24: 4500012769 | E24: TOYS kingdom | F24: 9201-S001 | G24: 珠片公仔 | H24: 2 | AD24: MA布標 | BT24: 2
A25: 43321 | C25: 4500012192 | D25: 簽板 | E25: CANDIDE IND E COM LTDA | F25: 9201-S001 | G25: 珠片公仔 | H25: 25 | X25: 25 | AC25: 25 | AD25: 巴西布標 | BJ25: 2 | BK25: 2 | BL25: 2 | BM25: 2 | BN25: 2 | BO25: 2 | BP25: 3 | BQ25: 2 | BR25: 2 | BS25: 2 | BT25: 2 | BU25: 2
A26: 43323 | C26: 4500012835 | D26: 產前測試 | E26: WAL-MART.COM | F26: 9201-S001 | G26: 珠片公仔 | H26: 18 | V26: 18 | Y26: 18 | AD26: MA布標 | BJ26: 3 | BL26: 3 | BN26: 3 | BP26: 3 | BR26: 3 | BT26: 3
A27: 43332 | C27: 4500010580 | D27: 大貨版、簽板 | E27: GP SPAIN | F27: 9201-S001 | G27: 珠片公仔 | H27: 12 | X27: 12 | Y27: 12 | AD27: 西班牙布標 | BJ27: 2 | BK27: 2 | BL27: 2 | BM27: 2 | BN27: 2 | BO27: 2 | BP27: 3 | BQ27: 2 | BR27: 2 | BS27: 2 | BT27: 2 | BU27: 2
A28: 43332 | C28: 4500011417 | D28: 大貨版、簽板 | E28: GP TURKEY | F28: 9201-S001 | G28: 珠片公仔 | H28: 12 | X28: 12 | Y28: 12 | AD28: 土耳其布標 | BJ28: 2 | BK28: 2 | BL28: 2 | BM28: 2 | BN28: 2 | BO28: 2 | BP28: 3 | BQ28: 2 | BR28: 2 | BS28: 2 | BT28: 2 | BU28: 2
A29: 43335 | C29: 4500012306 | D29: MA 3語簽板 | E29: 360 SALES SOLUTIONS INC | F29: 9201-S001 | G29: 珠片公仔 | H29: 24 | W29: 24 | AA29: 24 | AD29: MA布標 | BJ29: 2 | BK29: 2 | BL29: 2 | BM29: 2 | BN29: 2 | BO29: 2 | BP29: 2 | BQ29: 2 | BR29: 2 | BS29: 2 | BT29: 2 | BU29: 2
A30: 43336 | C30: 4500009673 | D30: 大貨樣板 | E30: B&M RETAIL LIMITED | F30: 9201-S003 | G30: 珠片公仔 | H30: 10 | V30: 10 | Y30: 10 | AD30: MA布標 | BL30: 1 | BM30: 1 | BN30: 1 | BO30: 1 | BP30: 1 | BQ30: 1 | BR30: 1 | BS30: 1 | BT30: 1 | BU30: 1
A31: 43336 | C31: 郵件 | D31: Intek 客户样品 | E31: Lucky | F31: 9201-S001 | G31: 珠片公仔 | H31: 24 | V31: 24 | Y31: 24 | AD31: MA布標 | BJ31: 2 | BK31: 2 | BL31: 2 | BM31: 2 | BN31: 2 | BO31: 2 | BP31: 2 | BQ31: 2 | BR31: 2 | BS31: 2 | BT31: 2 | BU31: 2
A32: 43342 | C32: ZMPO18108 | F32: 9201-S001 | G32: 珠片公仔 | H32: 360 | V32: 24 | Y32: 24 | BI32: 19952 | BJ32: =H32/24*3/2 -> 22.5 | BK32: =H32/24*3/2 -> 22.5 | BL32: =H32/24*4/2 -> 30 | BM32: =H32/24*4/2 -> 30 | BN32: =H32/24*5/2 -> 37.5 | BO32: =H32/24*5/2 -> 37.5 | BP32: =H32/24*5/2 -> 37.5 | BQ32: =H32/24*5/2 -> 37.5 | BR32: =H32/24*4/2 -> 30 | BS32: =H32/24*4/2 -> 30 | BT32: =H32/24*3/2 -> 22.5 | BU32: =H32/24*3/2 -> 22.5
A33: 43364 | C33: 4500011712 | D33: 大貨樣板 | E33: TARGET US | F33: 9201-S001 | G33: 珠片公仔 | H33: 9 | V33: 9 | Y33: 9 | AD33: MA布標 | BJ33: 1 | BK33: 1 | BL33: 1 | BM33: 1 | BQ33: 1 | BR33: 1 | BS33: 1 | BT33: 1 | BU33: 1
A34: 43364 | C34: 4500013372 | D34: 大貨樣板 | E34: DISTRIBUIDORA JUGUETRON S.A DE C.V | F34: 9201-S001 | G34: 珠片公仔 | H34: 2 | W34: 2 | AA34: 2 | AD34: MA布標 | BN34: 1 | BP34: 1
A35: 43369 | C35: 4500013085 | D35: 抽版 | F35: 9201-S001 | G35: 粉紅色獨角獸 | H35: 8 | V35: 8 | Y35: 8 | AD35: MA布標 | BQ35: 8
A36: 43382 | C36: 4500013648 | D36: 簽板 | F36: 9201-S001 | G36: 珠片公仔 | H36: 24 | V36: 24 | Y36: 24 | AD36: MA布標 | BJ36: 2 | BK36: 2 | BL36: 2 | BM36: 2 | BN36: 2 | BO36: 2 | BP36: 2 | BQ36: 2 | BR36: 2 | BS36: 2 | BT36: 2 | BU36: 2
A37: 43384 | C37: 4500013155 | D37: 大貨版 | F37: 9201-S001 | G37: 珠片公仔 | H37: 12 | V37: 12 | Y37: 12 | AD37: MA布標 | BJ37: 1 | BK37: 1 | BL37: 1 | BM37: 1 | BN37: 1 | BO37: 1 | BP37: 1 | BQ37: 1 | BR37: 1 | BS37: 1 | BT37: 1 | BU37: 1
A38: 43392 | C38: 4500013641 | D38: 大貨版 | F38: 9201-S001 | G38: 珠片公仔 | H38: 12 | X38: 12 | AC38: 12 | AD38: GP法國 | BJ38: 1 | BK38: 1 | BL38: 1 | BM38: 1 | BN38: 1 | BO38: 1 | BP38: 1 | BQ38: 1 | BR38: 1 | BS38: 1 | BT38: 1 | BU38: 1
A39: 43392 | C39: ZMPO18123 | D39: 樣品訂單 | F39: 9201-S001 | G39: 珠片公仔 | H39: 204 | V39: 204 | Y39: 204 | AD39: MA布標 | BJ39: 17 | BK39: 17 | BL39: 17 | BM39: 17 | BN39: 17 | BO39: 17 | BP39: 17 | BQ39: 17 | BR39: 17 | BS39: 17 | BT39: 17 | BU39: 17
A40: 43392 | C40: ZMPO18131 | D40: 樣品訂單 | F40: 9201-S001 | G40: 珠片公仔 | H40: 480 | V40: 480 | Y40: 480 | AD40: MA布標 | BJ40: 40 | BK40: 40 | BL40: 40 | BM40: 40 | BN40: 40 | BO40: 40 | BP40: 40 | BQ40: 40 | BR40: 40 | BS40: 40 | BT40: 40 | BU40: 40
A41: 43395 | C41: 4500013346 | D41: 簽板 | F41: 9201-S001 | G41: 珠片公仔 | H41: 24 | W41: 24 | Z41: 24 | AD41: MA布標 | BJ41: 2 | BK41: 2 | BL41: 2 | BM41: 2 | BN41: 2 | BO41: 2 | BP41: 2 | BQ41: 2 | BR41: 2 | BS41: 2 | BT41: 2 | BU41: 2
A42: 43417 | C42: 4500014341 | D42: 大貨樣板 | F42: 9201-S001 | G42: 珠片公仔 | H42: 2 | V42: 2 | Z42: 2 | AD42: MA布標 | BL42: 2
A43: 43419 | B43: Emily | D43: 測試樣品 | E43: C/Sam's club | F43: 9201-S001 | G43: 珠片公仔 | H43: 48 | V43: 48 | Z43: 48 | AD43: MA布標 | BJ43: 4 | BK43: 4 | BL43: 4 | BM43: 4 | BN43: 4 | BO43: 4 | BP43: 4 | BQ43: 4 | BR43: 4 | BS43: 4 | BT43: 4 | BU43: 4
A44: 43419 | B44: Emily | D44: 簽板 | E44: C/Sam's club | F44: 9201-S001 | G44: 珠片公仔 | H44: 24 | V44: 24 | Z44: 24 | AD44: MA布標 | BJ44: 2 | BK44: 2 | BL44: 2 | BM44: 2 | BN44: 2 | BO44: 2 | BP44: 2 | BQ44: 2 | BR44: 2 | BS44: 2 | BT44: 2 | BU44: 2
A45: 43427 | B45: Emily | C45: MO 20181120 | D45: 測試樣品 | E45: WMCA | F45: 9201-S001 | G45: 珠片公仔 | H45: 48 | W45: 48 | AB45: 48 | AD45: MA布標 | BJ45: 4 | BK45: 4 | BL45: 4 | BM45: 4 | BN45: 4 | BO45: 4 | BP45: 4 | BQ45: 4 | BR45: 4 | BS45: 4 | BT45: 4 | BU45: 4
A46: 43444 | B46: Ever | C46: 4500014867 | D46: 大貨版 | E46: GP法國 | F46: 9201-S001 | G46: 珠片公仔 | H46: 12 | V46: 12 | AC46: 12 | AD46: GP法國 | BJ46: 1 | BK46: 1 | BL46: 1 | BM46: 1 | BN46: 1 | BO46: 1 | BP46: 1 | BQ46: 1 | BR46: 1 | BS46: 1 | BT46: 1 | BU46: 1
A47: 43444 | B47: Ever | C47: 4500015110 | D47: 大貨版 | E47: GP西班牙 | F47: 9201-S001 | G47: 珠片公仔 | H47: 12 | V47: 12 | AC47: 12 | AD47: GP西班牙 | BJ47: 1 | BK47: 1 | BL47: 1 | BM47: 1 | BN47: 1 | BO47: 1 | BP47: 1 | BQ47: 1 | BR47: 1 | BS47: 1 | BT47: 1 | BU47: 1
A48: 43446 | B48: Aimee | C48: ZY#5700005 | D48: 筑愉 | E48: 筑愉 | F48: 9201EC-S002 | G48: 空展示櫃 | H48: 40 | BI48: 25917
A49: 43448 | B49: Emily | C49: 4500015267 | E49: SAM’S CLUB US | F49: 9201PL-S002 | G49: 珠片公仔 | H49: 48 | V49: 48 | Z49: 48 | AD49: MA布標 | BJ49: 4 | BK49: 4 | BL49: 4 | BM49: 4 | BN49: 4 | BO49: 4 | BP49: 4 | BQ49: 4 | BR49: 4 | BS49: 4 | BT49: 4 | BU49: 4
A50: 43454 | B50: Ada | C50: ZMPO18162 | D50: 樣品訂單 | E50: 庫有 | F50: 9201-S001 | G50: 珠片公仔 | H50: 480 | V50: 480 | Z50: 480 | AD50: MA布標 | BI50: 25944 | BJ50: 40 | BK50: 40 | BL50: 40 | BM50: 40 | BN50: 40 | BO50: 40 | BP50: 40 | BQ50: 40 | BR50: 40 | BS50: 40 | BT50: 40 | BU50: 40
A51: 43479 | B51: Aimee | C51: 4800007665 | D51: 筑愉 | E51: 筑愉 | F51: 9201EC-S002 | G51: 空展示櫃 | H51: 20 | BI51: 26075
A52: 43488 | B52: Aimee | C52: 4500007847 | D52: 筑愉 | E52: 筑愉 | F52: 9201EC-S002 | G52: 空展示櫃 | H52: 30 | BI52: 26074
A53: 43510 | B53: Tiffany | C53: 郵件 | E53: 廣州ITS測試版 | F53: 9201-S001 | G53: 珠片公仔 | H53: 48 | V53: =H53 -> 48 | Z53: =H53 -> 48 | AD53: MA布標 | BJ53: 4 | BK53: 4 | BL53: 4 | BM53: 4 | BN53: 4 | BO53: 4 | BP53: 4 | BQ53: 4 | BR53: 4 | BS53: 4 | BT53: 4 | BU53: 4
A54: 43514 | B54: holly | C54: 4500016381 | E54: 大貨樣板 | F54: 9201-S001 | G54: 珠片公仔 | H54: 12 | V54: 12 | Z54: 12 | AD54: MA布標 | BJ54: 1 | BK54: 1 | BL54: 1 | BM54: 1 | BN54: 1 | BO54: 1 | BP54: 1 | BQ54: 1 | BR54: 1 | BS54: 1 | BT54: 1 | BU54: 1
A55: 43518 | B55: Elaine | C55: 4500016832 | D55: 測試版 | E55: RELIANCE LIFESTYLE HOLDINGS LIMITED | F55: 9201-S001 | G55: 珠片公仔 | H55: 15 | V55: 15 | Z55: 15 | AD55: MA布標 | BJ55: 1 | BK55: 1 | BL55: 1 | BM55: 1 | BN55: 1 | BO55: 1 | BP55: 1 | BQ55: 1 | BR55: 4 | BS55: 1 | BT55: 1 | BU55: 1
A56: 43522 | B56: Christal | C56: 4500017093 | D56: WM簽板 | E56: WAL-MART STORES INC.USA | F56: 9201PL-S003 | G56: 珠片公仔 | H56: 24 | V56: 24 | Z56: 24 | AD56: MA布標 | BJ56: 2 | BK56: 2 | BL56: 2 | BM56: 2 | BN56: 2 | BO56: 2 | BP56: 2 | BQ56: 2 | BR56: 2 | BS56: 2 | BT56: 2 | BU56: 2
A57: 43522 | B57: Ever | C57: 4500016464 | E57: GP Spain | F57: 9201-S001 | G57: 珠片公仔 | H57: 12 | X57: 12 | Z57: 12 | AD57: GP西班牙 | BJ57: 1 | BK57: 1 | BL57: 1 | BM57: 1 | BN57: 1 | BO57: 1 | BP57: 1 | BQ57: 1 | BR57: 1 | BS57: 1 | BT57: 1 | BU57: 1
A58: 43529 | B58: Tiffany | C58: 4500016256 | D58: 大貨樣品 | E58: EUROPRIS | F58: 9201-S001 | G58: 珠片公仔 | H58: 24 | V58: 24 | Z58: 24 | AD58: MA布標 | BJ58: 2 | BK58: 2 | BL58: 2 | BM58: 2 | BN58: 2 | BO58: 2 | BP58: 2 | BQ58: 2 | BR58: 2 | BS58: 2 | BT58: 2 | BU58: 2
A59: 43542 | B59: Tony | C59: 郵件 | D59: BV測試版 | F59: 9201-S001 | G59: 珠片公仔 | H59: 24 | V59: 24 | Z59: 24 | AD59: MA布標 | BJ59: 2 | BK59: 2 | BL59: 2 | BM59: 2 | BN59: 2 | BO59: 2 | BP59: 2 | BQ59: 2 | BR59: 2 | BS59: 2 | BT59: 2 | BU59: 2
A60: 43573 | B60: Ever | C60: 4500018212 | D60: GP | E60: GP測試版 | F60: 9202-S001 | G60: 2代珠片公仔 | H60: 13 | AE60: 13 | AH60: 13 | AM60: MA布標 | BV60: 1 | BW60: 1 | BX60: 1 | BY60: 1 | BZ60: 1 | CA60: 1 | CB60: 1 | CC60: 1 | CD60: 1 | CE60: 1 | CF60: 1 | CG60: 1 | CH60: 1
A61: 43574 | B61: Tony | C61: 4500017981 | D61: ASDA STORES LTD | E61: 測試版 | F61: 9202-WMUS-S001 | G61: 2代珠片公仔 | H61: 33 | AE61: 33 | AH61: 33 | AM61: MA布標 | BV61: 3 | BW61: 3 | BX61: 3 | BY61: 3 | BZ61: 3 | CA61: 3 | CB61: 3 | CE61: 3 | CF61: 3 | CG61: 3 | CH61: 3
A62: 43574 | B62: Maria | C62: 450018388 | D62: TARGET AUSTRALIA PTY LTD | E62: QA測試版 | F62: 9202-S001 | G62: 2代珠片公仔 | H62: 13 | AE62: 13 | AH62: 13 | AM62: MA布標 | BV62: 1 | BW62: 1 | BX62: 1 | BY62: 1 | BZ62: 1 | CA62: 1 | CB62: 1 | CC62: 1 | CD62: 1 | CE62: 1 | CF62: 1 | CG62: 1 | CH62: 1
A63: 43574 | B63: Bella | C63: 4500016572 | D63: Express Gifts Ltd | E63: 大貨版 | F63: 9202-S005 | G63: 2代珠片公仔 | H63: 11 | AE63: 11 | AH63: 11 | AM63: MA布標 | BV63: 1 | BW63: 1 | BX63: 1 | BY63: 1 | BZ63: 1 | CA63: 1 | CB63: 1 | CE63: 1 | CF63: 1 | CG63: 1 | CH63: 1
A64: 43580 | B64: Lucky | C64: 4500017858 | D64: GRUPO RUZ | E64: 測試樣品 | F64: 9201-S001 | G64: 1代珠片公仔 | H64: 2 | V64: 2 | Z64: 2 | AD64: MA布標 | BO64: 1 | BR64: 1
A65: 43580 | B65: Lucky | C65: 4500017858 | D65: GRUPO RUZ | E65: 測試樣品 | F65: 9201-S001 | G65: 小蛋殼毛絨公仔 | H65: 2 | V65: 2 | Z65: 2 | AD65: MA布標 | CL65: 1 | CN65: 1
A66: 43580 | B66: Tony | C66: 4500018097 | D66: ASDA STORES LTD | E66: 測試版 | F66: 9204UQ3-S001 | G66: 小蛋殼毛絨公仔 | H66: 18 | AN66: =H66 -> 18 | AO66: =H66 -> 18 | CI66: 3 | CJ66: 3 | CK66: 3 | CL66: 3 | CM66: 3 | CN66: 3
A67: 43580 | B67: Holly | C67: 4500017238 | D67: Target US | E67: 大貨版 | F67: 9202-S002 | G67: 2代珠片公仔 | H67: 11 | AE67: =H67 -> 11 | AH67: =H67 -> 11 | AM67: MA布標 | BV67: 1 | BW67: 1 | BX67: 1 | BY67: 1 | BZ67: 1 | CC67: 1 | CD67: 1 | CE67: 1 | CF67: 1 | CG67: 1 | CH67: 1
A68: 43580 | B68: Holly | C68: 4500017239 | D68: Target US | E68: 大貨版 | F68: 9204UQ1-S002 | G68: 小蛋殼毛絨公仔 | H68: 6 | AN68: =H68 -> 6 | AO68: =H68 -> 6 | AV68: 1 | CI68: 1 | CJ68: 1 | CK68: 1 | CL68: 1 | CM68: 1 | CN68: 1
A69: 43580 | B69: Hailey | C69: 4500017957 | D69: DOLLAR GENERAL CORPORATION | E69: 大貨簽板 | F69: 9204-S004 | G69: 小蛋殼毛絨公仔 PDQ裝 | H69: 36 | AN69: =H69 -> 36 | AO69: =H69 -> 36 | CI69: 6 | CJ69: =CI69 -> 6 | CK69: =CJ69 -> 6 | CL69: =CK69 -> 6 | CM69: =CL69 -> 6 | CN69: =CM69 -> 6
A70: 43589 | B70: Maria | C70: 4500018388 | D70: TARGET AUSTRALIA PTY LTD | E70: 大貨簽板 | F70: 9202-S001 | G70: 2代珠片公仔 | H70: 39 | AE70: 39 | AH70: 39 | AM70: MA布標 | BV70: 3 | BW70: 3 | BX70: 3 | BY70: 3 | BZ70: 3 | CA70: 3 | CB70: 3 | CC70: 3 | CD70: 3 | CE70: 3 | CF70: 3 | CG70: 3 | CH70: 3
A71: 43589 | B71: Victoria | C71: 4500017956 | D71: WM CA | E71: 測試樣品 | F71: 9202-S001 | G71: 2代珠片公仔 | H71: 52 | AE71: 52 | AH71: 52 | AM71: MA布標 | BV71: 4 | BW71: 4 | BX71: 4 | BY71: 4 | BZ71: 4 | CA71: 4 | CB71: 4 | CC71: 4 | CD71: 4 | CE71: 4 | CF71: 4 | CG71: 4 | CH71: 4
A72: 43593 | B72: Christal | C72: 4500018397 | D72: WM US | E72: 測試樣+大貨樣 | F72: 9204UQ1-S002 | G72: 小蛋殼毛絨公仔 PDQ裝 | H72: 54 | AN72: 54 | AO72: 54 | AV72: =H72/6 -> 9 | CI72: 9 | CJ72: 9 | CK72: 9 | CL72: 9 | CM72: 9 | CN72: 9
A73: 43593 | B73: bella | C73: 4500017078 | D73: B&M | E73: 大貨版 | F73: 9204SQ1-S001 | G73: 小蛋殼毛絨公仔 | H73: 6 | AN73: 6 | AO73: 6 | CI73: 1 | CJ73: 1 | CK73: 1 | CL73: 1 | CM73: 1 | CN73: 1
A74: 43595 | B74: Ann | C74: 4500019662 | D74: Toy triangle | E74: 樣板 | F74: 9202 | G74: 2代珠片公仔 | H74: 4 | AE74: 4 | AH74: 4 | AM74: MA布標 | CA74: 1 | CB74: 1 | CG74: 1 | CH74: 1
A75: 43659 | B75: harmony | C75: 邮件 | E75: 广告样品 | F75: 9202-S001 | G75: 2代珠片公仔 | H75: 13 | AF75: 13 | AK75: 13 | BV75: 1 | BW75: 1 | BX75: 1 | BY75: 1 | BZ75: 1 | CA75: 1 | CB75: 1 | CC75: 1 | CD75: 1 | CE75: 1 | CF75: 1 | CG75: 1 | CH75: 1
A76: 43659 | B76: harmony | C76: 邮件 | E76: 广告样品 | F76: 9204-S004 | G76: 小蛋殼毛絨公仔 | H76: 6 | AO76: 6 | AQ76: 6 | CI76: 1 | CJ76: 1 | CK76: 1 | CL76: 1 | CM76: 1 | CN76: 1
A77: 43670 | B77: estate | C77: 4500020704 | D77: WM US | E77: 产前测试版 | F77: 9209-S001 | G77: 超大蛋壳 | H77: 9 | BE77: 9 | BF77: 9 | CU77: 4 | CV77: 4 | CW77: 4
A78: 43667 | B78: Lori | C78: 4500022133 | D78: TOY TRIANGLE COMPANY(UAE) | E78: 大货样板 | F78: 9209-S001 | G78: 超大蛋壳 | H78: 4 | BE78: 4 | BF78: 4 | CU78: 1 | CV78: 2 | CW78: 1
A79: 43671 | B79: Vivian | C79: 邮件 | E79: KC测试样品需求 | F79: 9209-S001 | G79: 超大蛋壳 | H79: 3 | CU79: 1 | CV79: 1 | CW79: 1
A80: 43671 | B80: Monica | C80: 4500021345 | E80: 大货样板 | F80: 9209-S001 | G80: 超大蛋壳 | H80: 1 | BE80: 1 | BF80: 1 | CW80: 1
A81: 43675 | B81: Emily | C81: 邮件 | D81: Sam's | E81: 见客版 | F81: 9202-S002 | G81: 2代珠片公仔 | H81: 18 | AE81: 2 | AH81: 2 | BV81: 2 | BW81: 2 | BX81: 2 | BY81: 2 | BZ81: 2 | CE81: 2 | CF81: 2 | CG81: 2 | CH81: 2
A82: 43672 | B82: Andy | C82: 450019786 | D82: GP | E82: 大货样板 | F82: 9202-S001 | G82: 2代珠片公仔 | H82: 13 | AE82: 13 | AH82: 13 | BV82: 1 | BW82: 1 | BX82: 1 | BY82: 1 | BZ82: 1 | CA82: 1 | CB82: 1 | CC82: 1 | CD82: 1 | CE82: 1 | CF82: 1 | CG82: 1 | CH82: 1
A83: 43678 | B83: Monica | C83: 4500019768 | D83: Colony Brands | E83: 测试样板 | F83: 9209A-S001 | G83: 火烈鸟 | H83: 1 | BE83: 1 | BF83: 1 | CW83: 1
A84: 43678 | B84: Daisy | C84: 4500022323 | D84: TOYS R US JAPAN LTD | E84: 大货样板 | F84: 9209-S001 | G84: 火烈鸟 | H84: 1 | BE84: 1 | BF84: 1 | CW84: 1
A85: 43678 | B85: Estate | C85: 4500020704 | D85: WAL-MART.COM | E85: 签版 | F85: 9209-S001 | G85: 超大蛋壳 | H85: 9 | BE85: 9 | BF85: 9 | CU85: 3 | CV85: 3 | CW85: 3
A86: 43679 | B86: Elaine | C86: 4500022498 | D86: RELIANCE LIFESTYLE HOLDINGS LIMITED | E86: 测试办 | F86: 9209-S001 | G86: 超大蛋壳 | H86: 9 | BE86: 9 | BF86: 9 | CU86: 3 | CV86: 3 | CW86: 3
A87: 43680 | B87: Holly | C87: 邮件 | D87: GSS | E87: 产前办 | F87: 9204SQ1-S001 | G87: 小蛋壳毛絨公仔 | H87: 12 | AP87: 12 | AQ87: 12 | CI87: 2 | CJ87: 2 | CK87: 2 | CL87: 2 | CM87: 2 | CN87: 2
A88: 43682 | B88: estate | C88: 4500020707 | D88: WAL-MART.COM | E88: 产中抽板 | F88: 9209-S001 | G88: 超大蛋壳 | H88: 12 | BE88: 12 | BF88: 12 | CU88: 4 | CV88: 4 | CW88: 4
A89: 43683 | B89: Estate | C89: 4500021874 | D89: WAL-MART.COM | E89: 签办 | F89: 9202-WMUS-S001 | G89: 2代珠片公仔 | H89: 22 | AE89: 22 | AH89: 22 | BV89: 2 | BW89: 2 | BX89: 2 | BY89: 2 | BZ89: 2 | CA89: 2 | CB89: 2 | CE89: 2 | CF89: 2 | CG89: 2 | CH89: 2
A90: 43683 | B90: Kalyn | C90: 4500021576 | D90: G.T. WHOLESALE LIMITED | E90: 大货办 | F90: 9202-S009 | G90: 2代珠片公仔 | H90: 13 | BV90: 1 | BW90: 1 | BX90: 1 | BY90: 1 | BZ90: 1 | CA90: 1 | CB90: 1 | CC90: 1 | CD90: 1 | CE90: 1 | CF90: 1 | CG90: 1 | CH90: 1
A91: 43686 | B91: Abbey | C91: 4500022135 | D91: THE FARMERS'TRADING COMPANY LIMITE | E91: 大货办 | F91: 9209-S001 | G91: 超大蛋壳 | H91: 3 | BE91: 3 | BF91: 3 | CU91: 1 | CV91: 1 | CW91: 1
A92: 43686 | B92: Kate | C92: 4500017857 | D92: 筑愉（深圳）贸易有限公司 | E92: 签办 | F92: 9204SQ1-S001 | G92: 小蛋殼毛絨公仔 PDQ裝 | H92: 12 | AP92: 12 | CI92: 2 | CJ92: 2 | CK92: 2 | CL92: 2 | CM92: 2 | CN92: 2
A93: 43687 | B93: IDA LI | C93: 4500022562 | D93: GP SPAIN | E93: 大货办 | F93: 9201-S001 | G93: 珠片公仔 | H93: 12 | W93: 12 | AB93: 12 | BJ93: 1 | BK93: 1 | BL93: 1 | BM93: 1 | BN93: 1 | BO93: 1 | BP93: 1 | BQ93: 1 | BR93: 1 | BS93: 1 | BT93: 1 | BU93: 1
A94: 43689 | B94: Lois | C94: 4500019647 | D94: A.S. WATSON RETAIL (HK) LIMITED | E94: 大货办 | F94: 9204SQ1-S002 | G94: 小蛋殼毛絨公仔 PDQ裝 | H94: 6 | AR94: 6 | AS94: 6 | AT94: 6 | CI94: 1 | CJ94: 1 | CK94: 1 | CL94: 1 | CM94: 1 | CN94: 1
A95: 43689 | B95: Lori | C95: 4500022128 | D95: ORBICO SP.Z O O | E95: 大货办 | F95: 9204SQ1-S001 | G95: 小蛋殼毛絨公仔 PDQ裝 | H95: 12 | AP95: 12 | AQ95: 12 | CI95: 2 | CJ95: 2 | CK95: 2 | CL95: 2 | CM95: 2 | CN95: 2
A96: 43689 | B96: Lori | C96: 4500022128 | D96: ORBICO SP.Z O O | E96: 大货办 | F96: 9202-S001 | G96: 2代珠片公仔 | H96: 4 | AE96: 4 | AI96: 4 | CA96: 1 | CD96: 1 | CF96: 1 | CH96: 1
A97: 43689 | B97: Kate | C97: 4500017361 | D97: 筑愉(深圳）贸易有限公司 | E97: 签办 | F97: 9202-S007 (A款） | G97: 2代珠片公仔 | H97: 26 | AE97: 26 | AL97: 26 | BV97: 2 | BW97: 2 | BX97: 2 | BY97: 2 | BZ97: 2 | CA97: 2 | CB97: 2 | CC97: 2 | CD97: 2 | CE97: 2 | CF97: 2 | CG97: 2 | CH97: 2
A98: 43689 | B98: Sherry | C98: 4500018407 | D98: Smyths Toys HQ UC | E98: 大货办 | F98: 9209B-S001 | G98: 羊駝 | H98: 1 | BE98: 1 | BF98: 1 | CV98: 1
A99: 43690 | B99: Angel | C99: 4500017962 | D99: WAL-MART CANADA CORP | E99: 签办 | F99: 9202A | G99: 2代珠片公仔 | H99: 1 | BV99: 1
A100: 43690 | B100: Lori | C100: 4500022128 | D100: ORBICO SP.Z O O | E100: 大货办 | F100: 9204SQ1-S001 | G100: 小蛋殼毛絨公仔 PDQ裝 | H100: 6 | AP100: 6 | AQ100: 6 | CI100: 1 | CJ100: 1 | CK100: 1 | CL100: 1 | CM100: 1 | CN100: 1
...

Sheet 71152
A2: =#REF! -> #REF! | I2: （黃色表示更改或增加） | L2: （蓝色表示已完货） | P2: （綠色表示調整貨期） | T2: 是否需要样板 | AJ2: 彩盒 | AN2: 收藏指南 | AQ2: 展示架
A3: 接单日期 | B3: 第三方客户名称 | C3: 国家 | D3: PO号 | E3: 客PO号 | F3: SKU | G3: 系统货号 | H3: ITEM# | I3: 中文名 | J3: PO数量 (pcs) | K3: 内箱装箱数量(pcs) | L3: 外箱装箱数量(pcs) | M3: 总箱数 | N3: 客PO期 | O3: 验货期 | P3: 第三方验货期 | Q3: 驗貨結果 | R3: 船期SO | S3: 贴纸情况 | T3: 蓝色表示已寄 黄色表示出单 | U3: 箱唛资料（收到箱唛日期） | V3: 外箱贴纸 | W3: 客贴纸资料 | X3: 客版资料 | Y3: 日期码 | Z3: 备注 | AA3: ZURU 跟单 | AB3: 单价USD | AC3: 金额USD | AD3: 發票號 | AE3: 是否入系统 | AF3: 装配采购单 | AG3: 已送数量 | AH3: 欠数 | AI3: 贴纸信息 | AJ3: MA 1语彩盒 A版本 | AK3: MA 1L 彩盒B版本 | AL3: MA 3L彩盒 A版本 | AM3: 客版彩盒 | AN3: MA 5说明书 | AO3: MA 5L 说明书B版 | AP3: 客版说明书 | AQ3: EC展示架 | AR3: 合计数量 | AS3: 累计数量
A4: 45623 | D4: ZPO2411014 | G4: * | H4: 71152-S001 | I4: 机械速龙 | J4: 600 | M4: 100 | Q4: PASS | Z4: STD PP 产品 500 件金印测试样品 2x 主箱开发实验室外测试-10套(如果FEP中未提供)商品团队:1套(Phoenix/Selina)客户化团队:1套(Sharon) 生产计划:1套(Tracy)设计/品牌团队:1套(Gretta/Amy)销售团队:4箱至4SR办公室。签署样品:4套。(5套用于I/H) 产用(用于QA/QC)个用于包装设计用于营销 个用于新产品开发和产品设计(用于 I/H 研发 剩余数量:营销样品 准:PP产品500件散装和250件套装。PP工艺中将包含A11标准SKU。 PD团队将协调PP支持卡材料的交货时间以及付款。 请注意，其中200pcs需在PP后空运至新西兰进行上架测试，务必保证功能外观都没问题 | AB4: 2.7 | AC4: =AB4*J4 -> 1620 | AE4: * | AN4: =J4 -> 600 | AR4: =J4 -> 600 | AS4: =AR4 -> 600
A5: 45701 | B5: THE WAREHOUSE LIMITED | C5: 新西兰 | D5: 4500157534 | F5: 4500157534-20 | G5: 71152-S001 | H5: 71152-S001 | I5: 机械速龙 | J5: 96 | K5: 0 | L5: 6 | M5: =J5/L5 -> 16 | N5: 45723 | O5: 45719 | Q5: PASS | R5: 4/3入仓 | U5: 加水贴纸 | Y5: 日期码格式：ZURU INC(BVI) 标准格式 日期：按实际生产日期 | Z5: 日期码格式：ZURU INC(BVI) 标准格式 日期：按实际生产日期 Packaging Info: MA UPC 英语包装（优先1L英语版本，或者3L/5L含英语都可） 此客人不接受易掉落或者剥落或者可直接触碰的闪粉，可降解也不行，但可以接受符合欧洲微塑料标准的珠光粉或者闪片。 77685GQ1: 要加UPC贴纸 77673：包装正面和说明书都需要加电池警告语贴纸（法规要求） 所有外箱上都要贴一张大黄贴："ZURU Product for NZ test " Remark: 71152：2PCS AAA BATTERIES(NOT INCLUDED) | AA5: Abby Liang | AB5: 2.767 | AC5: =AB5*J5 -> 265.632 | AD5: 94695-4.3 | AE5: 已入 | AG5: =J5 -> 96 | AH5: =AG5-J5 -> 0 | AJ5: =J5 -> 96 | AN5: =J5 -> 96 | AR5: =J5 -> 96 | AS5: =AS4+AR5 -> 696
A6: 45666 | B6: PT.MAP Aktif Adiperkasa, Tbk | C6: 印度尼西亚 | D6: 4500155574 | E6: 241227-2MAAJKTQ225-ZURU | F6: 4500155574-50 | G6: 71152-S001 | H6: 71152-S001 | I6: 机械速龙 | J6: 504 | K6: 0 | L6: 6 | M6: =J6/L6 -> 84 | N6: 45733 | O6: 45729 | Q6: PASS | U6: 45667 | V6: 无 | W6: 2/6 进口商贴纸 | Y6: 日期码格式：ZURU INC(BVI) 标准格式 日期：按实际生产日期 | Z6: 日期码格式：ZURU INC(BVI) 标准格式 日期：按实际生产日期 Packaging Info: MA UPC包装（优先1L)+1张进口商贴纸, 所有item使用含电池信息的进口商贴纸，贴纸待提供 1.可能会被抽大货样做测试，请多备料，CRD前半个月会通知是否有抽到该订单中的item。 2.此订单送普通仓，送仓后会有第三方验货，所以需要按CRD准时完货。 Remark: 9561-3pcs LR41 Batteries（included） | AA6: Emma Wu | AB6: 2.7 | AC6: =AB6*J6 -> 1360.8 | AD6: 94672-3.29 | AE6: 已入 | AG6: =J6 -> 504 | AH6: =AG6-J6 -> 0 | AJ6: =J6 -> 504 | AN6: =J6 -> 504 | AR6: =J6 -> 504 | AS6: =AS5+AR6 -> 1200
A7: 45681 | B7: ALL BRANDS TOYS PTY LTD | C7: 澳大利亚 | D7: 4500156597 | E7: 83575 | F7: 4500156597-10 | G7: 71152-S001 | H7: 71152-S001 | I7: 机械速龙 | J7: 2400 | K7: 0 | L7: 6 | M7: =J7/L7 -> 400 | N7: 45737 | O7: =N7-4 -> 45733 | Q7: PASS | U7: 45694 | V7: 无 | W7: 通用进口商贴纸 | Y7: 日期码格式：ZURU INC(BVI) 标准格式 日期：按实际生产日期 | Z7: 日期码格式：ZURU INC(BVI) 标准格式 日期：按实际生产日期 Packaging Info: 71152： MA_UPC版本包装（收缩膜/彩卡和说明书, MA首选1L，如无1L可用多语且含英语的配套多语UPC包装）+ 1张客人通用进口商贴纸 Remark: 1.按实际生产日期; 2.出澳大利亚，请按照相应标准生产; | AA7: Lydia Wu | AB7: 2.7 | AC7: =AB7*J7 -> 6480 | AD7: 94724-4.8 | AE7: 已入 | AG7: =J7 -> 2400 | AH7: =AG7-J7 -> 0 | AJ7: =J7 -> 2400 | AN7: =J7 -> 2400 | AR7: =J7 -> 2400 | AS7: =AS6+AR7 -> 3600
A8: 45698 | B8: Smyths Toys EU HQ UC | C8: 德国 | D8: 4500157159 | E8: 4400464033 | F8: 4500157159-10 | G8: 71152-S001-1 | H8: 71152-S001 | I8: 机械速龙 | J8: 2004 | K8: 0 | L8: 6 | M8: =J8/L8 -> 334 | N8: 45737 | O8: =N8-4 -> 45733 | Q8: PASS | U8: 45699 | V8: 无 | W8: 客版WEEE声明说明书纸(不带电池)+产品贴纸（翻450 0064042 ） | X8: 客版彩盒翻4500156690 | Y8: 日期码格式：ZURU INC(BVI) 标准格式 日期：按实际生产日期 | Z8: 日期码格式：ZURU INC(BVI) 标准格式 日期：按实际生产日期 Packaging Info: 71152: 客版彩盒(3L 英法德callout+EAN条码+法国回收logo) 翻UK单#4500156690 + MA 5L-9L Warning说明书+客版WEEE声明说明书纸(不带电池)+产品贴纸（翻450 0064042 ） Remark: 1. 此单出德国，需要满足Zuru Standard欧洲标准测试要求； 2. 请准时出货，推期会有罚款； 3. 出口欧洲，微塑料需符合法规； 4. 所有电子产品身上需要加字唛，为ZURU FRANCE 地址 (如无电子产品，或者产品布标有此地址，可忽略此信息) ZURU France 1/3, Rue d'Argenteuil 95210 SAINT-GRATIEN, FRANCE 5. 所有出往德国订单的电子产品需增加一张客版WEEE声明说明书纸，区分带电池和不带电池版本, 如已做客版说明书可忽略此要求。 6. 标准配比 | AA8: Shirley Zhou | AB8: 2.7 | AC8: =AB8*J8 -> 5410.8 | AD8: 94725-4.8 | AE8: 已入 | AG8: =J8 -> 2004 | AH8: =AG8-J8 -> 0 | AM8: =J8 -> 2004 | AN8: =J8 -> 2004 | AR8: =J8 -> 2004 | AS8: =AS7+AR8 -> 5604
A9: 45701 | B9: ZURU LLC | C9: 美国 | D9: 4500157378 | E9: 5200006139 | F9: 4500157378-10 | G9: 71152-S001 | H9: 71152-S001-MTS | I9: 机械速龙 | J9: 594 | K9: 0 | L9: 6 | M9: =J9/L9 -> 99 | N9: 45737 | O9: =N9-4 -> 45733 | Q9: PASS | U9: 45701 | V9: 无 | Y9: 日期码格式：ZURU INC(BVI) 标准格式 日期：按实际生产日期 | Z9: 日期码格式：ZURU INC(BVI) 标准格式 日期：按实际生产日期 Packaging Info: #71152 MA UPC版 (1L或3L都可) Remark: 1.Amazon domestic 订单。出口美国。外箱最长边不能超过25" （超过了，case pack只能为1），不符合要求的大货，一律不接受。 2.无第三方验货/测试要求。 3.日期码使用ZURU标准版本。 | AA9: SD24 | AB9: 2.7 | AC9: =AB9*J9 -> 1603.8 | AD9: ZB00056 | AE9: 已入 | AG9: =J9 -> 594 | AH9: =AG9-J9 -> 0 | AJ9: =J9 -> 594 | AN9: =J9 -> 594 | AR9: =J9 -> 594 | AS9: =AS8+AR9 -> 6198
A10: 45712 | B10: Multihexa Sdn Bhd | C10: 马来西亚 | D10: 4500158287 | F10: 4500158287-10 | G10: 71152-S001 | H10: 71152-S001 | I10: 机械速龙 | J10: 252 | K10: 0 | L10: 6 | M10: =J10/L10 -> 42 | N10: 45740 | O10: =N10-4 -> 45736 | Q10: PASS | R10: 3/23送货到新益豪 | U10: 45715 | V10: 无 | W10: 2/281张进口商贴纸 | Y10: 日期码格式：ZURU INC(BVI) 标准格式 日期：按实际生产日期 | Z10: 日期码格式：ZURU INC(BVI) 标准格式 日期：按实际生产日期 Packaging Info: 1.此单走20GP，因系统未维护暂时开15706UQ2的装运类型为40GP，后续会更改过来 2.MA UPC包装（优先1L)+1张进口商贴纸 Remark: 71152-2PCS AAA BATTERIES(NOT INCLUDED) | AA10: Emma Wu | AB10: 2.7 | AC10: =AB10*J10 -> 680.4 | AD10: 94658-3.28 | AE10: 已入 | AG10: =J10 -> 252 | AH10: =AG10-J10 -> 0 | AJ10: =J10 -> 252 | AN10: =J10 -> 252 | AR10: =J10 -> 252 | AS10: =AS9+AR10 -> 6450
A11: 45702 | B11: PPTOYS PTE LTD (SG) | C11: 新加坡 | D11: 4500157618 | E11: ZU25012002SG | F11: 4500157618-10 | G11: 71152-S001 | H11: 71152-S001 | I11: 机械速龙 | J11: 720 | K11: 0 | L11: 6 | M11: =J11/L11 -> 120 | N11: 45735 | O11: 45735 | Q11: PASS | U11: 45703 | V11: 无 | W11: 2/27进口商贴纸 | Y11: 日期码格式：ZURU INC(BVI) 标准格式 日期：按实际生产日期 | Z11: 日期码格式：ZURU INC(BVI) 标准格式 日期：按实际生产日期 Packaging Info: MA UPC包装（优先1L)+1张进口商贴纸 71152-贴纸AW、位置图待提供 此客人用的贴纸内容都是一样的，个别item可能存在尺寸差别，收到贴纸后如果尺寸没差别，请都统一订购节省成本 Remark: 71152-2PCS AAA BATTERIES(NOT INCLUDED) | AA11: Emma Wu | AB11: 2.7 | AC11: =AB11*J11 -> 1944 | AD11: 94603-3.21 | AE11: 已入 | AG11: =J11 -> 720 | AH11: =AG11-J11 -> 0 | AJ11: =J11 -> 720 | AN11: =J11 -> 720 | AR11: =J11 -> 720 | AS11: =AS10+AR11 -> 7170
A12: 45674 | B12: FYE | C12: 美国 | D12: 4500155999 | E12: 86466 | F12: 4500155999-10 | G12: 71152-S001 | H12: 71152-S001 | I12: 机械速龙 | J12: 474 | K12: 0 | L12: 6 | M12: =J12/L12 -> 79 | N12: 45742 | O12: 45738 | Q12: PASS | U12: 45674 | V12: 无 | W12: 1/26客版可移动价格贴纸(贴纸AWS 跟单提供) | Y12: 日期码格式：ZURU INC(BVI) 标准格式 日期：按实际生产日期 | Z12: 日期码格式：ZURU INC(BVI) 标准格式 日期：按实际生产日期 Packaging Info: 1.ZURU MA UPC 包装(优先使用最新版本1L) + 客版可移动价格贴纸(贴纸AWS 跟单提供), 工厂自行订购, 出口美国。 2.ZURU标准日期码格式,所有产品及包装都必须带有日期码，日期码必须一致(但日期不可为周末)。 Remark: 1.ZURU MA UPC 包装(优先使用最新版本1L) +客版可移动价格贴纸(贴纸AWS 跟单提供), 工厂自行订购, 出口美国。 2.ZURU标准日期码格式,所有产品及包装都必须带有日期码，日期码必须一致(但日期不可为周末)。 3.此单外箱不可有水贴纸。 4.可移价贴需贴在产品包装背面右下角的位置（位置图跟单提供）。 All Pre Price Tickets should be placed on the back of the product located in the lower right hand corner of the package #71152-S001 $14.99 5.出货配比： #71152-S001-ROBO ALIVE-DINOSAUR-SERIES 1-RAPTOR-WINDOW BOX,6PCS/CTN 6. 外箱packing slip: 按客户最新要求， 每款产品的尾箱上或者内，需要附上packing slip (文件有跟单提供，工厂帮打印)。 若附在外箱上，需要用信封透明袋装住packing slip， 并贴在外箱一面正唛上。 若附在尾箱箱内，外箱正唛上需要贴有"packing slip enclosed" 标识。 工厂可以选择以上任意一种方式。 | AA12: Hailey Yu | AB12: 2.7 | AC12: =AB12*J12 -> 1279.8 | AD12: ZB00042 | AE12: 已入 | AG12: =J12 -> 474 | AH12: =AG12-J12 -> 0 | AJ12: =J12 -> 474 | AN12: =J12 -> 474 | AR12: =J12 -> 474 | AS12: =AS11+AR12 -> 7644
A13: 45709 | B13: BRICKLAND LLC | C13: 蒙古 | D13: 4500158223 | E13: Zuru2025Q1(addon) | F13: 4500158223-10 | G13: 71152-S001 | H13: 71152-S001 | I13: 机械速龙 | J13: 360 | K13: 0 | L13: 6 | M13: =J13/L13 -> 60 | N13: 45742 | O13: 45738 | Q13: PASS | U13: 45713 | V13: 无 | W13: 2/28 1张进口商贴纸 | Y13: 日期码格式：ZURU INC(BVI) 标准格式 日期：按实际生产日期 | Z13: 日期码格式：ZURU INC(BVI) 标准格式 日期：按实际生产日期 Packaging Info: MA UPC包装(优先1L)+1张进口商贴纸,贴纸图稿及位置图待提供; Remark: | AA13: Emma Wu | AB13: 2.7 | AC13: =AB13*J13 -> 972 | AD13: 94746-4.10 | AE13: 已入 | AG13: =J13 -> 360 | AH13: =AG13-J13 -> 0 | AJ13: =J13 -> 360 | AN13: =J13 -> 360 | AR13: =J13 -> 360 | AS13: =AS12+AR13 -> 8004
A14: 45694 | B14: Smyths Toys HQ UC UK | C14: 英国 | D14: 4500156690 | E14: 4400462625 | F14: 4500156690-10 | G14: 71152-S001-1 | H14: 71152-S001 | I14: 机械速龙 | J14: 3000 | K14: 0 | L14: 6 | M14: =J14/L14 -> 500 | N14: 45740 | O14: =N14-4 -> 45736 | Q14: PASS | U14: 45699 | V14: 无 | X14: 客版彩盒 | Y14: 日期码格式：ZURU INC(BVI) 标准格式 日期：按实际生产日期 | Z14: 日期码格式：ZURU INC(BVI) 标准格式 日期：按实际生产日期 Packaging Info: 71152：客版彩卡(3L callout+EAN条码+法国回收logo)+MA 5L-9L Warning说明书 Remark: 1）包装日期码按ZURU格式即可，请确保不迟于外箱日期码，可等于或者早于外箱日期码，必须为法定工作日，印刷前请先检查外箱日期码。 2）订单出英国，请注意检查产品及包装应带UKCA图标（14+产品除外），包装显示ZURU UK LTD/ZURU France地址信息，QC部门请查核，如有问题与跟单确认 3）订单必须经过ZURU QC验货并且通过后方可出货 4) 需要完全符合欧洲标准(符合微塑料法规)，否则不合法规会有客诉产生 | AA14: May Wu | AB14: 2.7 | AC14: =AB14*J14 -> 8100 | AD14: 94641-3.26 | AE14: 已入 | AG14: =J14 -> 3000 | AH14: =AG14-J14 -> 0 | AM14: =J14 -> 3000 | AN14: =J14 -> 3000 | AR14: =J14 -> 3000 | AS14: =AS13+AR14 -> 11004
A15: 45694 | B15: Smyths Toys HQ UC IE | C15: 爱尔兰 | D15: 4500156692 | E15: PO4400465271 | F15: 4500156692-10 | G15: 71152-S001-1 | H15: 71152-S001 | I15: 机械速龙 | J15: 900 | K15: 0 | L15: 6 | M15: =J15/L15 -> 150 | N15: 45740 | O15: =N15-4 -> 45736 | Q15: PASS | R15: 3/29出盐田 | U15: 45699 | V15: 无 | X15: 客版彩盒翻4500156690 | Y15: 日期码格式：ZURU INC(BVI) 标准格式 日期：按实际生产日期 | Z15: 日期码格式：ZURU INC(BVI) 标准格式 日期：按实际生产日期 Packaging Info: 71152：客版彩卡(英法德3L callout+EAN条码+法国回收logo，翻4500156690)+MA 5L-9L Warning说明书 Remark: 1）包装日期码按ZURU格式即可，请确保不迟于外箱日期码，可等于或者早于外箱日期码，必须为法定工作日，印刷前请先检查外箱日期码。 2）订单出英国，请注意检查产品及包装应带UKCA图标（14+产品除外），包装显示ZURU UK LTD/ZURU France地址信息，QC部门请查核，如有问题与跟单确认 3）订单必须经过ZURU QC验货并且通过后方可出货 4) 需要完全符合欧洲标准(符合微塑料法规)，否则不合法规会有客诉产生 | AA15: May Wu | AB15: 2.7 | AC15: =AB15*J15 -> 2430 | AD15: 94666-3.29 | AE15: 已入 | AG15: =J15 -> 900 | AH15: =AG15-J15 -> 0 | AM15: =J15 -> 900 | AN15: =J15 -> 900 | AR15: =J15 -> 900 | AS15: =AS14+AR15 -> 11904
A16: 45696 | B16: SMYTHS TOYS HQ UC | C16: 法国 | D16: 4500156997 | F16: 4500156997-10 | G16: 71152-S001-1 | H16: 71152-S001 | I16: 机械速龙 | J16: 1002 | K16: 0 | L16: 6 | M16: =J16/L16 -> 167 | N16: 45748 | O16: 45744 | Q16: PASS | U16: 45701 | V16: 无 | X16: 客版彩盒翻4500156690 | Y16: 日期码格式：ZURU INC(BVI) 标准格式 日期：按实际生产日期 | Z16: 日期码格式：ZURU INC(BVI) 标准格式 日期：按实际生产日期 Packaging Info: 71152:客版彩卡翻4500156690+MA 5L(9L Warning)说明书 Remark: 1. 此单出法国，所有包装都需要含有法语，需要满足Zuru Standard欧洲标准测试要求； 2. 请准时出货，推期会有罚款； 3. 所有出口法国的产品, 法规规定禁止在包装和共公众用的印刷品中使用矿物油中含有的物质, 包装印刷油墨中含有的MOAH/MOSH的质量浓度不能超过1%, 否则出 货到法国被抽检出现问题, 供应商需要对此负责; | AA16: Ula Zhao | AB16: 2.7 | AC16: =AB16*J16 -> 2705.4 | AD16: 94661-3.28 | AE16: 已入 | AG16: =J16 -> 1002 | AH16: =AG16-J16 -> 0 | AM16: =J16 -> 1002 | AN16: =J16 -> 1002 | AR16: =J16 -> 1002 | AS16: =AS15+AR16 -> 12906
A17: 45709 | B17: MTA Trade | C17: 哈萨克斯坦 | D17: 4500158182 | F17: 4500158182-30 | G17: 71152-S001 | H17: 71152-S001 | I17: 机械速龙 | J17: 120 | K17: 0 | L17: 6 | M17: =J17/L17 -> 20 | N17: 45748 | O17: 45743 | Q17: PASS | U17: 45709 | V17: 无 | W17: 3/10进口商贴纸 | Y17: 日期码格式：ZURU INC(BVI) 标准格式 日期：按实际生产日期 | Z17: 日期码格式：ZURU INC(BVI) 标准格式 日期：按实际生产日期 Packaging Info: 71152 ： 1L MA 包装 + 进口商贴纸， MA 指南 /说明书（如有）； Remark: 整单货期4月1 标准配比 | AA17: Ann Zhang | AB17: 2.7 | AC17: =AB17*J17 -> 324 | AD17: 94763-4.14 | AE17: 已入 | AG17: =J17 -> 120 | AH17: =AG17-J17 -> 0 | AJ17: =J17 -> 120 | AN17: =J17 -> 120 | AR17: =J17 -> 120 | AS17: =AS16+AR17 -> 13026
A18: 45705 | B18: DIAMANT TOYS LTD | C18: 以色列 | D18: 4500153742 | E18: 56053 | F18: 4500153742-20 | G18: 71152-S001 | H18: 71152-S001 | I18: 机械速龙 | J18: 780 | K18: 0 | L18: 6 | M18: =J18/L18 -> 130 | N18: 45761 | O18: =N18-4 -> 45757 | Q18: PASS | U18: 45707 | V18: 无 | W18: 3/17进口商贴纸+彩色贴纸 | Y18: 日期码格式：ZURU INC(BVI) 标准格式 日期：按实际生产日期 | Z18: 日期码格式：ZURU INC(BVI) 标准格式 日期：按实际生产日期 Packaging Info: 71152:1L MA 彩卡+进口商贴纸+彩色贴纸; MA说明书 Remark: | AA18: Lena Huang | AB18: 2.7 | AC18: =AB18*J18 -> 2106 | AD18: 94787-4.17 | AE18: 已入 | AG18: 780 | AH18: =AG18-J18 -> 0 | AJ18: =J18 -> 780 | AN18: =J18 -> 780 | AR18: =J18 -> 780 | AS18: =AS17+AR18 -> 13806
A19: 45723 | B19: Amazon ES | C19: 西班牙 | D19: 4500159389 | E19: Amazon ES: 2ZNG9OOD | F19: 4500159389-10 | G19: 71152-S001-3L | H19: 71152-S001 | I19: 机械速龙 | J19: 750 | K19: 0 | L19: 6 | M19: =J19/L19 -> 125 | N19: 45757 | O19: 45754 | Q19: PASS | U19: 空白外箱 | V19: 有3/17 | W19: 3/10贴纸(UPC#+IT环保标) | Y19: 日期码格式：ZURU INC(BVI) 标准格式 日期：按实际生产日期 | Z19: 日期码格式：ZURU INC(BVI) 标准格式 日期：按实际生产日期 Packaging Info: Amazon ES(71152) 1. 71152：6PCS WINDOW BOX/CTN; MA 3L(23L warning EAN#)A window box+1张贴纸(UPC#+IT环保标)+MA 5L(9L warning)A 说明书 2. 最迟验货不得晚于2025/4/11; Remark: 1.空白外箱（加印带Zuru字样的最新logo，除了邮包盒直接做外箱的产品） + SSCC LABEL一张, 无箱唛，MADE IN CHINA 外箱只印一正一侧。箱唛资料按照给定的 标准去做即可，无需发回我方再行审批(新标准将另行通知)。 (SSCC LABEL竖贴在外箱正面的正中间，贴一面即可,贴纸离外箱边距必须至少3.2CM。如竖贴无法满足要求，则横贴。如横贴也无法满足要求，则竖贴，遮到ZURU lo go无影响), SSCC贴纸由工厂直接跟勤得采购或者工厂自行采购，每一张SSCC Label都是唯一且有不同流水及条码，且需要检查条码是否能正常扫描，另外，此贴纸 印刷不可出现模糊，溢出及粘胶不牢易脱落等现象，如工厂不按此要求导致贴纸有任何问题产生的罚款将由工厂承担一切责任 。 2.出往UK的产品+包装务必打上UKCA logo ，否则客人会退货且当地会有罚款。 3.订单必须经过ZURU QC验货并且通过后方可出货。 4.法国订单要求包装不使用矿物油，请按要求提供以下其中一份文件再出货 ，产品出到法国被相关部门抽检出现包装不符合此要求的，供应商需要为此承担责任， 故此请严格把关。 -油墨物质""由1 ~ 7个芳香环组成的MOAH""的包装检测报告，要求限值≤1.0%； -包装材料清单，包括包装油墨或物质的信息； -油墨制造商的证书； 5.每一批次出货只能有一个生产日期，不可多个生产日期混在同一批次出货；且邮包盒上必须统一加上日期码；外箱对于日期码没有硬性规定； 6.涉及到相关款式会有闪粉的或者微塑料的，请统一默认出无闪粉或者不含微塑料版本； 7.邮包盒及外箱封箱必须是工字型封箱方式； 8.5 Surprise or Mini Brands涉及包装是2个及2个以上的球入PVC桶包装时，单个球上若有UPC#或者EAN#，请用白色贴纸覆盖住； | AA19: Mandy Hu | AB19: 2.7663 | AC19: =AB19*J19 -> 2074.725 | AD19: 94831-4.24 | AE19: 已入 | AG19: 750 | AH19: =AG19-J19 -> 0 | AL19: =J19 -> 750 | AN19: =J19 -> 750 | AR19: =J19 -> 750 | AS19: =AS18+AR19 -> 14556
A20: 45723 | B20: AMAZON UK | C20: 英国 | D20: 4500159544 | E20: Amazon UK:4H6I8RZN | F20: 4500159544-10 | G20: 71152-S001-3L | H20: 71152-S001 | I20: 机械速龙 | J20: 630 | K20: 0 | L20: 6 | M20: =J20/L20 -> 105 | N20: 45757 | O20: 45754 | Q20: PASS | U20: 空白外箱（加印带Zuru字样的最新logo，除了邮包盒直接做外箱的产品） + SSCC LABEL一张, 无箱唛，MADE IN CHINA 外箱只印一正一侧 | V20: 有 | W20: 1张贴纸(UPC#+IT环保标，参考翻单PO#4500159389) | Y20: 日期码格式：ZURU INC(BVI) 标准格式 日期：按实际生产日期 | Z20: 日期码格式：ZURU INC(BVI) 标准格式 日期：按实际生产日期 Packaging Info: Amazon UK(71152)/FR(71152)/DE(71152) 1. 71152：6PCS WINDOW BOX/CTN; MA 3L(23L warning EAN#)A window box+1张贴纸(UPC#+IT环保标，参考翻单PO#4500159389)+MA 5L(9L warning)A 说明书 2.最迟验货不得晚于2025/4/11; Remark: 1.空白外箱（加印带Zuru字样的最新logo，除了邮包盒直接做外箱的产品） + SSCC LABEL一张, 无箱唛，MADE IN CHINA 外箱只印一正一侧。箱唛资料按照给定的 标准去做即可，无需发回我方再行审批(新标准将另行通知)。 (SSCC LABEL竖贴在外箱正面的正中间，贴一面即可,贴纸离外箱边距必须至少3.2CM。如竖贴无法满足要求，则横贴。如横贴也无法满足要求，则竖贴，遮到ZURU lo go无影响), SSCC贴纸由工厂直接跟勤得采购或者工厂自行采购，每一张SSCC Label都是唯一且有不同流水及条码，且需要检查条码是否能正常扫描，另外，此贴纸 印刷不可出现模糊，溢出及粘胶不牢易脱落等现象，如工厂不按此要求导致贴纸有任何问题产生的罚款将由工厂承担一切责任 。 2.出往UK的产品+包装务必打上UKCA logo ，否则客人会退货且当地会有罚款。 3.订单必须经过ZURU QC验货并且通过后方可出货。 4.法国订单要求包装不使用矿物油，请按要求提供以下其中一份文件再出货 ，产品出到法国被相关部门抽检出现包装不符合此要求的，供应商需要为此承担责任， 故此请严格把关。 -油墨物质""由1 ~ 7个芳香环组成的MOAH""的包装检测报告，要求限值≤1.0%； -包装材料清单，包括包装油墨或物质的信息； -油墨制造商的证书； 5.每一批次出货只能有一个生产日期，不可多个生产日期混在同一批次出货；且邮包盒上必须统一加上日期码；外箱对于日期码没有硬性规定； 6.涉及到相关款式会有闪粉的或者微塑料的，请统一默认出无闪粉或者不含微塑料版本； 7.邮包盒及外箱封箱必须是工字型封箱方式； 8.5 Surprise or Mini Brands涉及包装是2个及2个以上的球入PVC桶包装时，单个球上若有UPC#或者EAN#，请用白色贴纸覆盖住； | AA20: Crystal Chen | AB20: 2.6352 | AC20: =AB20*J20 -> 1660.176 | AD20: 94832-4.24 | AE20: 已入 | AG20: 630 | AH20: =AG20-J20 -> 0 | AL20: =J20 -> 630 | AN20: =J20 -> 630 | AR20: =J20 -> 630 | AS20: =AS19+AR20 -> 15186
A21: 45723 | B21: AMAZON UK | C21: 德国 | D21: 4500159544 | E21: Amazon DE:5AMWB58X | F21: 4500159544-20 | G21: 71152-S001-3L | H21: 71152-S001 | I21: 机械速龙 | J21: 498 | K21: 0 | L21: 6 | M21: =J21/L21 -> 83 | N21: 45757 | O21: 45754 | Q21: PASS | U21: 空白外箱（加印带Zuru字样的最新logo，除了邮包盒直接做外箱的产品） + SSCC LABEL一张, 无箱唛，MADE IN CHINA 外箱只印一正一侧 | V21: 有 | W21: 1张贴纸(UPC#+IT环保标，参考翻单PO#4500159389) | Y21: 日期码格式：ZURU INC(BVI) 标准格式 日期：按实际生产日期 | Z21: 日期码格式：ZURU INC(BVI) 标准格式 日期：按实际生产日期 Packaging Info: Amazon UK(71152)/FR(71152)/DE(71152) 1. 71152：6PCS WINDOW BOX/CTN; MA 3L(23L warning EAN#)A window box+1张贴纸(UPC#+IT环保标，参考翻单PO#4500159389)+MA 5L(9L warning)A 说明书 2.最迟验货不得晚于2025/4/11; Remark: 1.空白外箱（加印带Zuru字样的最新logo，除了邮包盒直接做外箱的产品） + SSCC LABEL一张, 无箱唛，MADE IN CHINA 外箱只印一正一侧。箱唛资料按照给定的 标准去做即可，无需发回我方再行审批(新标准将另行通知)。 (SSCC LABEL竖贴在外箱正面的正中间，贴一面即可,贴纸离外箱边距必须至少3.2CM。如竖贴无法满足要求，则横贴。如横贴也无法满足要求，则竖贴，遮到ZURU lo go无影响), SSCC贴纸由工厂直接跟勤得采购或者工厂自行采购，每一张SSCC Label都是唯一且有不同流水及条码，且需要检查条码是否能正常扫描，另外，此贴纸 印刷不可出现模糊，溢出及粘胶不牢易脱落等现象，如工厂不按此要求导致贴纸有任何问题产生的罚款将由工厂承担一切责任 。 2.出往UK的产品+包装务必打上UKCA logo ，否则客人会退货且当地会有罚款。 3.订单必须经过ZURU QC验货并且通过后方可出货。 4.法国订单要求包装不使用矿物油，请按要求提供以下其中一份文件再出货 ，产品出到法国被相关部门抽检出现包装不符合此要求的，供应商需要为此承担责任， 故此请严格把关。 -油墨物质""由1 ~ 7个芳香环组成的MOAH""的包装检测报告，要求限值≤1.0%； -包装材料清单，包括包装油墨或物质的信息； -油墨制造商的证书； 5.每一批次出货只能有一个生产日期，不可多个生产日期混在同一批次出货；且邮包盒上必须统一加上日期码；外箱对于日期码没有硬性规定； 6.涉及到相关款式会有闪粉的或者微塑料的，请统一默认出无闪粉或者不含微塑料版本； 7.邮包盒及外箱封箱必须是工字型封箱方式； 8.5 Surprise or Mini Brands涉及包装是2个及2个以上的球入PVC桶包装时，单个球上若有UPC#或者EAN#，请用白色贴纸覆盖住； | AA21: Crystal Chen | AB21: 2.6352 | AC21: =AB21*J21 -> 1312.3296 | AD21: 94832-4.24 | AE21: 已入 | AG21: 498 | AH21: =AG21-J21 -> 0 | AL21: =J21 -> 498 | AN21: =J21 -> 498 | AR21: =J21 -> 498 | AS21: =AS20+AR21 -> 15684
A22: 45723 | B22: AMAZON UK | C22: 法国 | D22: 4500159544 | E22: Amazon FR: 8X62JYRM | F22: 4500159544-30 | G22: 71152-S001-3L | H22: 71152-S001 | I22: 机械速龙 | J22: 750 | K22: 0 | L22: 6 | M22: =J22/L22 -> 125 | N22: 45757 | O22: 45754 | Q22: PASS | U22: 空白外箱（加印带Zuru字样的最新logo，除了邮包盒直接做外箱的产品） + SSCC LABEL一张, 无箱唛，MADE IN CHINA 外箱只印一正一侧 | V22: 有 | W22: 1张贴纸(UPC#+IT环保标，参考翻单PO#4500159389) | Y22: 日期码格式：ZURU INC(BVI) 标准格式 日期：按实际生产日期 | Z22: 日期码格式：ZURU INC(BVI) 标准格式 日期：按实际生产日期 Packaging Info: Amazon UK(71152)/FR(71152)/DE(71152) 1. 71152：6PCS WINDOW BOX/CTN; MA 3L(23L warning EAN#)A window box+1张贴纸(UPC#+IT环保标，参考翻单PO#4500159389)+MA 5L(9L warning)A 说明书 2.最迟验货不得晚于2025/4/11; Remark: 1.空白外箱（加印带Zuru字样的最新logo，除了邮包盒直接做外箱的产品） + SSCC LABEL一张, 无箱唛，MADE IN CHINA 外箱只印一正一侧。箱唛资料按照给定的 标准去做即可，无需发回我方再行审批(新标准将另行通知)。 (SSCC LABEL竖贴在外箱正面的正中间，贴一面即可,贴纸离外箱边距必须至少3.2CM。如竖贴无法满足要求，则横贴。如横贴也无法满足要求，则竖贴，遮到ZURU lo go无影响), SSCC贴纸由工厂直接跟勤得采购或者工厂自行采购，每一张SSCC Label都是唯一且有不同流水及条码，且需要检查条码是否能正常扫描，另外，此贴纸 印刷不可出现模糊，溢出及粘胶不牢易脱落等现象，如工厂不按此要求导致贴纸有任何问题产生的罚款将由工厂承担一切责任 。 2.出往UK的产品+包装务必打上UKCA logo ，否则客人会退货且当地会有罚款。 3.订单必须经过ZURU QC验货并且通过后方可出货。 4.法国订单要求包装不使用矿物油，请按要求提供以下其中一份文件再出货 ，产品出到法国被相关部门抽检出现包装不符合此要求的，供应商需要为此承担责任， 故此请严格把关。 -油墨物质""由1 ~ 7个芳香环组成的MOAH""的包装检测报告，要求限值≤1.0%； -包装材料清单，包括包装油墨或物质的信息； -油墨制造商的证书； 5.每一批次出货只能有一个生产日期，不可多个生产日期混在同一批次出货；且邮包盒上必须统一加上日期码；外箱对于日期码没有硬性规定； 6.涉及到相关款式会有闪粉的或者微塑料的，请统一默认出无闪粉或者不含微塑料版本； 7.邮包盒及外箱封箱必须是工字型封箱方式； 8.5 Surprise or Mini Brands涉及包装是2个及2个以上的球入PVC桶包装时，单个球上若有UPC#或者EAN#，请用白色贴纸覆盖住； | AA22: Crystal Chen | AB22: 2.6352 | AC22: =AB22*J22 -> 1976.4 | AD22: 94832-4.24 | AE22: 已入 | AG22: 750 | AH22: =AG22-J22 -> 0 | AL22: =J22 -> 750 | AN22: =J22 -> 750 | AR22: =J22 -> 750 | AS22: =AS21+AR22 -> 16434
A23: 45737 | B23: ASIA GOAL LIMITED | C23: 香港 | D23: 4500160929 | E23: AG240425-HK | F23: 4500160929-10 | G23: 71152-S001 | H23: 71152-S001 | I23: 机械速龙 | J23: 240 | K23: 0 | L23: 6 | M23: =J23/L23 -> 40 | N23: 45761 | O23: 45757 | Q23: PASS | U23: 45737 | V23: 无 | W23: 45749 | Y23: 日期码格式：ZURU INC(BVI) 标准格式 日期：按实际生产日期 | Z23: 日期码格式：ZURU INC(BVI) 标准格式 日期：按实际生产日期 Packaging Info: 71152：MA 1L PKG， MA 说明书+1张客供警语贴纸+1张客供电池警语贴纸+1张客供中文警语书 Remark: 此单出香港 | AA23: Doris Shou | AB23: 2.8165 | AC23: =AB23*J23 -> 675.96 | AD23: 94777-4.16 | AE23: 已入 | AG23: 240 | AH23: =AG23-J23 -> 0 | AJ23: =J23 -> 240 | AO23: =J23 -> 240 | AR23: =J23 -> 240 | AS23: =AS22+AR23 -> 16674
A24: 45761 | D24: ZMPO250315 | G24: 71152-S001 | H24: 71152-S001 | I24: 机械速龙 | J24: 120 | K24: 0 | L24: 6 | M24: =J24/L24 -> 20 | N24: 45771 | O24: 45768 | Q24: PASS | Z24: Remark:大货最新版本/大货标准箱装箱/箱唛参照邮件附件;备注： 收到样品订单后尽快安排 ，此订单麻烦在外箱上备注是海运订单/注意样板品质质量要求要高于大货品质质量 ，送货时必须要附带送货单(没有送货单和QC检验合格报告的仓库一律拒绝收货)，请知悉，谢谢！ | AA24: Angus | AD24: 95176-5.30 | AE24: 已入 | AG24: 120 | AH24: 0 | AK24: =J24 -> 120 | AO24: =J24 -> 120 | AR24: =J24 -> 120 | AS24: =AS23+AR24 -> 16794
A25: 45712 | B25: Walmart Central America-HN | C25: 洪都拉斯 | D25: 4500158415 | F25: 4500158415-120 | G25: 71152-S001 | H25: 71152-S001 | I25: 机械速龙 | J25: 72 | K25: 0 | L25: 6 | M25: =J25/L25 -> 12 | N25: 45763 | O25: 45759 | Q25: PASS | U25: 45740 | V25: 无 | W25: UPC条码贴纸+进口商贴纸所有贴纸翻单PO4500158302 | Y25: 日期码格式：ZURU INC(BVI) 标准格式 日期：按实际生产日期 | Z25: 日期码格式：ZURU INC(BVI) 标准格式 日期：按实际生产日期 Packaging Info: 10.71152：MA 3L EAN包装+UPC条码贴纸+MA 多语说明书+进口商贴纸+箱唛 以上所有贴纸翻单PO4500158302 Remark: 1.使用双坑外箱 2.请注意产品包装条形码必须是UPC 3.无第三方验货 15. 71152：2PCS AAA BATTERIES(NOT INCLUDED) | AA25: Ever Li | AB25: 2.7 | AC25: =AB25*J25 -> 194.4 | AD25: 94891-4.30 | AE25: 已入 | AG25: 72 | AH25: =AG25-J25 -> 0 | AL25: =J25 -> 72 | AN25: =J25 -> 72 | AR25: =J25 -> 72 | AS25: =AS24+AR25 -> 16866
A26: 45712 | B26: Walmart Central America-HN | C26: 萨尔瓦多 | D26: 4500158302 | F26: 4500158302-180 | G26: 71152-S001 | H26: 71152-S001 | I26: 机械速龙 | J26: 108 | K26: 0 | L26: 6 | M26: =J26/L26 -> 18 | N26: 45763 | O26: 45759 | Q26: PASS | U26: 45740 | V26: 无 | W26: 45737 | Y26: 日期码格式：ZURU INC(BVI) 标准格式 日期：按实际生产日期 | Z26: 日期码格式：ZURU INC(BVI) 标准格式 日期：按实际生产日期 Packaging Info: 10.71152：MA 3L EAN包装+UPC条码贴纸+MA 多语说明书+进口商贴纸+箱唛 Remark: 1.使用双坑外箱 2.请注意产品包装条形码必须是UPC 3.无第三方验货 15. 71152：2PCS AAA BATTERIES(NOT INCLUDED) 16. 71152：2PCS AAA BATTERIES(NOT INCLUDED) | AA26: Ever Li | AB26: 2.7 | AC26: =AB26*J26 -> 291.6 | AD26: 94865-4.28 | AE26: 已入 | AG26: 108 | AH26: =AG26-J26 -> 0 | AL26: =J26 -> 108 | AN26: =J26 -> 108 | AR26: =J26 -> 108 | AS26: =AS25+AR26 -> 16974
A27: 45714 | B27: Walmart Central America-GT | C27: 危地马拉 | D27: 4500158447 | F27: 4500158447-150 | G27: 71152-S001 | H27: 71152-S001 | I27: 机械速龙 | J27: 198 | K27: 0 | L27: 6 | M27: =J27/L27 -> 33 | N27: 45763 | O27: 45759 | Q27: PASS | U27: 45740 | V27: 无 | W27: UPC条码贴纸+进口商贴纸所有贴纸翻单PO4500158302 | Y27: 日期码格式：ZURU INC(BVI) 标准格式 日期：按实际生产日期 | Z27: 日期码格式：ZURU INC(BVI) 标准格式 日期：按实际生产日期 Packaging Info: 10.71152：MA 3L EAN包装+UPC条码贴纸+MA 多语说明书+进口商贴纸+箱唛 以上所有贴纸翻单PO4500158302 Remark: 1.使用双坑外箱 2.请注意产品包装条形码必须是UPC 3.无第三方验货 71152：2PCS AAA BATTERIES(NOT INCLUDED) | AA27: Ever Li | AB27: 2.7 | AC27: =AB27*J27 -> 534.6 | AD27: 94923-5.5 | AE27: 已入 | AG27: 198 | AH27: =AG27-J27 -> 0 | AL27: =J27 -> 198 | AN27: =J27 -> 198 | AR27: =J27 -> 198 | AS27: =AS26+AR27 -> 17172
A28: 45714 | B28: Walmart Central America-CR | C28: 哥斯达黎加 | D28: 4500158535 | F28: 4500158535-160 | G28: 71152-S001-3L | H28: 71152-S001 | I28: 机械速龙 | J28: 270 | K28: 0 | L28: 6 | M28: =J28/L28 -> 45 | N28: 45763 | O28: 45759 | Q28: PASS | U28: 45740 | V28: 无 | W28: UPC条码贴纸+进口商贴纸所有贴纸翻单PO4500158302 | Y28: 日期码格式：ZURU INC(BVI) 标准格式 日期：按实际生产日期 | Z28: 日期码格式：ZURU INC(BVI) 标准格式 日期：按实际生产日期 Packaging Info: 10.71152：MA 3L EAN包装+UPC条码贴纸+MA 多语说明书+进口商贴纸+箱唛 以上贴纸翻单PO 4500158302 Remark: 1.使用双坑外箱 2.请注意产品包装条形码必须是UPC 3.无第三方验货 71152：2PCS AAA BATTERIES(NOT INCLUDED) | AA28: Ever Li | AB28: 2.7 | AC28: =AB28*J28 -> 729 | AD28: 94882-4.29 | AE28: 已入 | AG28: 270 | AH28: =AG28-J28 -> 0 | AL28: =J28 -> 270 | AO28: =J28 -> 270 | AR28: =J28 -> 270 | AS28: =AS27+AR28 -> 17442
A29: 45756 | B29: DIAMANT TOYS LTD | C29: 以色列 | D29: 4500163062 | E29: 56053 | F29: 4500163062-20 | G29: 71152-S001 | H29: 71152-S001 | I29: 机械速龙 | J29: 2220 | K29: 0 | L29: 6 | M29: =J29/L29 -> 370 | N29: 45789 | O29: 45785 | Q29: PASS | U29: 45758 | V29: 无 | W29: 进口商贴纸(翻4500153742)+彩色贴纸(翻4500153742) | Z29: 日期码格式：ZURU INC(BVI) 标准格式 日期：按实际生产日期 Packaging Info: 71152：1L MA包装+进口商贴纸(翻4500153742)+彩色贴纸(翻4500153742); MA说明书 Remark: | AA29: Lena Huang | AB29: 2.6214 | AC29: =AB29*J29 -> 5819.508 | AD29: 94890-4.30 | AE29: 已入 | AG29: =1806+30+384 -> 2220 | AH29: =AG29-J29 -> 0 | AK29: =J29 -> 2220 | AO29: =J29 -> 2220 | AR29: =J29 -> 2220 | AS29: =AS28+AR29 -> 19662
A30: 45713 | B30: HEB GROCERY COMPANY, LP | C30: 美国 | D30: 4500158419 | E30: PO#60X273616 | F30: 4500158419-20 | G30: 71152-S003 | H30: 71152-S003 | I30: 机械速龙 | J30: 1272 | K30: 0 | L30: 4 | M30: =J30/L30 -> 318 | N30: 45769 | O30: 45765 | Q30: PASS | U30: 45720 | V30: 无 | W30: 无 | Y30: 日期码格式：ZURU INC(BVI) 标准格式 日期：按实际生产日期 | Z30: 日期码格式：ZURU INC(BVI) 标准格式 日期：按实际生产日期 Packaging Info: 1. 包材：ZURU MA 1L UPC最新版本，出口美国: Remark: 2. 日期跟踪码：ZURU标准格式日期码，产品包装及产品本身都必须有ZURU标准格式日期码，并且确保两者日期码的格式和时间保持一致(请自行调整具体年月日生 产期，但不能为周末） 3. 大货样 需4月15日前需寄出每款每色3套大货样板，样板须跟大货一模一样（含日期码）。 样板一套将给到美国HEB，两套寄到以下深圳利丰地址，到时利丰会回签一套用于第三方100%大货验货。 回签的样板工厂需要长期保存好，只要产品没更新每次的第三方验货都是用这套样板做参考不再走客户签样流程。 * 一套样板寄到以下地址 深圳雨禾伟业实业有限公司 地址：广东省深圳市罗湖区东门南路1006号文锦渡口岸大厦B栋7楼 收件人：Elsa 电话：0755 6688 1988 Ext3337 *2套寄到以下地址（因是签样，样板需寄齐大货会出的所有产品，包括散件/配件）： Li Fung 深圳市福田区绒花路8号深福保大厦附楼3楼。 收件人： Yoland Dai 电话：+0755 8825 3756 4. 验货+ 抽板 （同一天进行） 预约4月23日第三方（利丰）到工厂做100%大货现场验货和抽板，验货需打印EPM出来跟客户回签样板供第三方验货参考。 PS:EPM是跟单提供。 抽板： 利丰验货员现场针对指定款随机抽板6PCS 成品， 工厂需把抽板寄到以下MTS地址做测试，测试通过后才能出货；如产品有油漆的工厂需额外准备5G/色的油漆涂在 同材质胶件上(面积类似A4纸大小)一并寄出； 实验室收件地址： 东莞现代产品整理服务有限公司（MTS） 广东省东莞市寮步镇新旧围村良平路76号 收件人：Cherry Wang （汪单） Tel: +86 769- 8112 0818 ext.893 抽板有随样文件TRF（跟单提供），工厂在寄样时打印出来放纸箱内随样寄走 5. 出货配比： #71152-S003-ROBO ALIVE-DINOSAUR-SERIES 1-RAPTOR-WINDOW BOX,4PCS/CTN 6. ZURU QA验货时需拍齐每款角色的产品和产品包装上的日期码照片（供实验室review） | AA30: Elsa Zheng | AB30: 2.75 | AC30: =AB30*J30 -> 3498 | AD30: ZB00763-7.17 | AE30: 已入 | AG30: =1248+24 -> 1272 | AH30: =AG30-J30 -> 0 | AK30: =J30 -> 1272 | AO30: =J30 -> 1272 | AR30: =J30 -> 1272 | AS30: =AS29+AR30 -> 20934
A31: 45729 | B31: Babyhouse | C31: 乌兹别克斯坦 | D31: 4500159866 | F31: 4500159866-90 | G31: 71152-S001 | H31: 71152-S001 | I31: 机械速龙 | J31: 120 | K31: 0 | L31: 6 | M31: =J31/L31 -> 20 | N31: 45769 | O31: 45765 | Q31: PASS | T31: 否 | U31: 45729 | V31: 无 | W31: 3/14进口商贴纸 | Y31: 日期码格式：ZURU INC(BVI) 标准格式 日期：按实际生产日期 | Z31: 日期码格式：ZURU INC(BVI) 标准格式 日期：按实际生产日期 Packaging Info: 71152 : 1L MA 彩卡+ 进口商贴纸 ; MA 说明书/指南（如有）; Remark: 标准配比 | AA31: Ann Zhang | AB31: 2.7 | AC31: =AB31*J31 -> 324 | AD31: 94879-4.29 | AE31: 已入 | AG31: =J31 -> 120 | AH31: =AG31-J31 -> 0 | AK31: =J31 -> 120 | AO31: =J31 -> 120 | AR31: =J31 -> 120 | AS31: =AS30+AR31 -> 21054
A32: 45735 | B32: MTA Trade | C32: 哈萨克斯坦 | D32: 4500160671 | F32: 4500160671-100 | G32: 71152-S001 | H32: 71152-S001 | I32: 机械速龙 | J32: 276 | K32: 0 | L32: 6 | M32: =J32/L32 -> 46 | N32: 45772 | O32: 45768 | Q32: PASS | T32: 否 | U32: 45735 | V32: 无 | W32: 进口商贴纸(翻PO4500158182) | Y32: 日期码格式：ZURU INC(BVI) 标准格式 日期：按实际生产日期 | Z32: 日期码格式：ZURU INC(BVI) 标准格式 日期：按实际生产日期 Packaging Info: 71152：MA UPC 彩卡+进口商贴纸(翻PO4500158182)；MA说明书 Remark: 标准配比 | AA32: Cora Zhou | AB32: 2.6717 | AC32: =AB32*J32 -> 737.3892 | AD32: 94843-4.25 | AE32: 已入 | AG32: 276 | AH32: =AG32-J32 -> 0 | AK32: =J32 -> 276 | AO32: =J32 -> 276 | AR32: =J32 -> 276 | AS32: =AS31+AR32 -> 21330
A33: 45734 | B33: ZURU Germany GMBH | C33: 德国 | D33: 4500160629 | E33: 5200006404 | F33: 4500160629-10 | G33: 71152-S001-3L | H33: 71152-S001-MTS | I33: 机械速龙 | J33: 1200 | K33: 0 | L33: 6 | M33: =J33/L33 -> 200 | N33: 45772 | O33: 45768 | Q33: PASS | T33: 否 | U33: 45735 | V33: 无 | W33: 45740 | Y33: 日期码格式：ZURU INC(BVI) 标准格式 日期：按实际生产日期 | Z33: 日期码格式：ZURU INC(BVI) 标准格式 日期：按实际生产日期 Packaging Info: 71152: MA 3L_23L EAN 包装+意大利环保标贴纸 + 5L_9L MA说明书 +WEEE不带电池走货黑白说明书 EAN#4894680042742 Remark: 1.德国内销单，需要通过ZURU 验货结果后才能出货 (工厂需要主动提前同ZURU QC预约验货避免延期出货造成不必要麻烦)； 2. 若有特定款有特殊外箱条码要求时,需要明确列出产品款对应的具体外箱条码号码/条码类型 (若无,可以忽略此需求) 3.所有出口欧洲的产品, 法规规定禁止在包装和共公众用的印刷品中使用矿物油中含有的物质, 包装印刷油墨中含有的MOAH/MOSH的质量浓度不能超过1%, 否则出货 到法国被抽检出现问题, 供应商需要对此负责; 4. date code: 外箱日期码要晚于或等于产品日期码，不能早于产品的日期码 5. 所有电子产品身上需要加字唛，为ZURU FRANCE 地址 (如无电子产品，或者产品布标有此地址，可忽略此信息) ZURU France 1/3, Rue d'Argenteuil 95210 SAINT-GRATIEN, FRANCE 6. 装柜时需要按照款式号码从小到大一款款依次装,避免终端仓库卸货混乱.若一个柜子涉及到几个不同国家内销单,装柜时需要一个国家装完后再装另一个国家的 产品,依次装柜,避免终端仓库因不同国家不同库位位置卸货混乱. (此点需要同工厂装柜人员强调)" | AA33: SD04 | AB33: 2.5407 | AC33: =AB33*J33 -> 3048.84 | AD33: 94892-4.30 | AE33: 已入 | AG33: 1200 | AH33: =AG33-J33 -> 0 | AL33: =J33 -> 1200 | AO33: =J33 -> 1200 | AR33: =J33 -> 1200 | AS33: =AS32+AR33 -> 22530
A34: 45736 | B34: THE ENTERTAINER | C34: 英国 | D34: 4500160901 | E34: 4500160901-1: FB12977 | F34: 4500160901-90 | G34: 71152-S001 | H34: 71152-S001 | I34: 机械速龙 | J34: 996 | K34: 0 | L34: 6 | M34: =J34/L34 -> 166 | N34: 45772 | O34: 45768 | Q34: PASS | T34: 是 | U34: 45740 | V34: 无 | W34: 3/24一张2国语言电池说明书(英语+阿拉伯语) | Y34: 日期码格式：ZURU INC(BVI) 标准格式 日期：按实际生产日期 | Z34: 日期码格式：ZURU INC(BVI) 标准格式 日期：按实际生产日期 Packaging Info: 71152-S001: MA 最新1L UPC包装+一张2国语言电池说明书(英语+阿拉伯语); BARCODE: 193052079190 Remark: *MA版本按工厂现有最新库存即可，订单出英国，请注意检查产品及包装应带UKCA图标，包装显示ZURU UK LTD信息，QC同事请查核，如有问题与跟单确认 *生产日期按实际（法定工作日），按ZURU标准格式即可 ，但是请知悉包装日期码需要早于或者等于外箱日期码 ，不能晚于外箱日期码 *请注意所有订单都需要经过ZURU QC验货并且通过后方可出货 *所有产品按符合欧洲标准走货，需要是不含微塑料版本 。 *涉及到硼的，如可选择情况下应使用低硼版本 （slime 类别低硼一般低于300ppm)，无选择的应与跟单复核再安排 。 *条码以订单显示为准 ，请安排生产前先核对 ，有问题请提出。 *订单对应客户3个PO号 ，备注有显示 ，注意分开做货/验货/装柜 ，混装有罚款。 * 大货样： 请在4/10 前寄出每款1整套大货样到罗湖办公室7B Sandy Shao 收。 | AA34: Sandy Shao | AB34: 2.7663 | AC34: =AB34*J34 -> 2755.2348 | AD34: 94866-4.28 | AE34: 已入 | AG34: 996 | AH34: =AG34-J34 -> 0 | AK34: =J34 -> 996 | AO34: =J34 -> 996 | AR34: =J34 -> 996 | AS34: =AS33+AR34 -> 23526
A35: 45736 | B35: THE ENTERTAINER | C35: 英国 | D35: 4500160901 | E35: 4500160901-2: FB12978 | F35: 4500160901-180 | G35: 71152-S001 | H35: 71152-S001 | I35: 机械速龙 | J35: 1002 | K35: 0 | L35: 6 | M35: =J35/L35 -> 167 | N35: 45772 | O35: 45768 | Q35: PASS | T35: 是 | U35: 45740 | V35: 无 | W35: 3/24一张2国语言电池说明书(英语+阿拉伯语) | Y35: 日期码格式：ZURU INC(BVI) 标准格式 日期：按实际生产日期 | Z35: 日期码格式：ZURU INC(BVI) 标准格式 日期：按实际生产日期 Packaging Info: 71152-S001: MA 最新1L UPC包装+一张2国语言电池说明书(英语+阿拉伯语); BARCODE: 193052079190 Remark: *MA版本按工厂现有最新库存即可，订单出英国，请注意检查产品及包装应带UKCA图标，包装显示ZURU UK LTD信息，QC同事请查核，如有问题与跟单确认 *生产日期按实际（法定工作日），按ZURU标准格式即可 ，但是请知悉包装日期码需要早于或者等于外箱日期码 ，不能晚于外箱日期码 *请注意所有订单都需要经过ZURU QC验货并且通过后方可出货 *所有产品按符合欧洲标准走货，需要是不含微塑料版本 。 *涉及到硼的，如可选择情况下应使用低硼版本 （slime 类别低硼一般低于300ppm)，无选择的应与跟单复核再安排 。 *条码以订单显示为准 ，请安排生产前先核对 ，有问题请提出。 *订单对应客户3个PO号 ，备注有显示 ，注意分开做货/验货/装柜 ，混装有罚款。 * 大货样： 请在4/10 前寄出每款1整套大货样到罗湖办公室7B Sandy Shao 收。 | AA35: Sandy Shao | AB35: 2.6352 | AC35: =AB35*J35 -> 2640.4704 | AD35: 94866-4.28 | AE35: 已入 | AG35: 1002 | AH35: =AG35-J35 -> 0 | AK35: =J35 -> 1002 | AO35: =J35 -> 1002 | AR35: =J35 -> 1002 | AS35: =AS34+AR35 -> 24528
A36: 45736 | B36: THE ENTERTAINER | C36: 英国 | D36: 4500160901 | E36: 4500160901-3: FB12979 | F36: 4500160901-270 | G36: 71152-S001 | H36: 71152-S001 | I36: 机械速龙 | J36: 1002 | K36: 0 | L36: 6 | M36: =J36/L36 -> 167 | N36: 45772 | O36: 45768 | Q36: PASS | T36: 是 | U36: 45740 | V36: 无 | W36: 3/24一张2国语言电池说明书(英语+阿拉伯语) | Y36: 日期码格式：ZURU INC(BVI) 标准格式 日期：按实际生产日期 | Z36: 日期码格式：ZURU INC(BVI) 标准格式 日期：按实际生产日期 Packaging Info: 71152-S001: MA 最新1L UPC包装+一张2国语言电池说明书(英语+阿拉伯语); BARCODE: 193052079190 Remark: *MA版本按工厂现有最新库存即可，订单出英国，请注意检查产品及包装应带UKCA图标，包装显示ZURU UK LTD信息，QC同事请查核，如有问题与跟单确认 *生产日期按实际（法定工作日），按ZURU标准格式即可 ，但是请知悉包装日期码需要早于或者等于外箱日期码 ，不能晚于外箱日期码 *请注意所有订单都需要经过ZURU QC验货并且通过后方可出货 *所有产品按符合欧洲标准走货，需要是不含微塑料版本 。 *涉及到硼的，如可选择情况下应使用低硼版本 （slime 类别低硼一般低于300ppm)，无选择的应与跟单复核再安排 。 *条码以订单显示为准 ，请安排生产前先核对 ，有问题请提出。 *订单对应客户3个PO号 ，备注有显示 ，注意分开做货/验货/装柜 ，混装有罚款。 * 大货样： 请在4/10 前寄出每款1整套大货样到罗湖办公室7B Sandy Shao 收。 | AA36: Sandy Shao | AB36: 2.6352 | AC36: =AB36*J36 -> 2640.4704 | AD36: 94866-4.28 | AE36: 已入 | AG36: =996+6 -> 1002 | AH36: =AG36-J36 -> 0 | AK36: =J36 -> 1002 | AO36: =J36 -> 1002 | AR36: =J36 -> 1002 | AS36: =AS35+AR36 -> 25530
A37: 45733 | B37: WAL-MART CANADA CORP. | C37: 加拿大 | D37: 4500160504 | E37: 9900923487 | F37: 4500160504-10 | G37: 71152-S002 | H37: 71152-S002 | I37: 机械速龙 | J37: 2154 | K37: 0 | L37: 3 | M37: =J37/L37 -> 718 | N37: 45776 | O37: 45772 | Q37: PASS | T37: 是 | U37: 45750 | V37: 有 | W37: 3/16UPC贴纸(UPC:193052079190) | Y37: 日期码格式：ZURU INC(BVI) 标准格式 日期：按实际生产日期 | Z37: 日期码格式：ZURU INC(BVI) 标准格式 日期：按实际生产日期 Packaging Info: #71152： MA3L彩盒+UPC贴纸(UPC:193052079190)+MA5L说明书(B版) 产品配比： 7 Assortment, Polar bear: Penguin: Walrus: Mammoth: Owl: Seal: Snow man=10:10:10:10:10:8:2. Snow man is the rare item. Remark: 1. 此单有箱唛； 3. 此单有第三方验货，烦请多备包装物料； 4. #71152需于2025/4/18安排签版, 签样数量：大货样各3PCS； 8. #71152 需于2025/4/28安排抽办测试, 抽办数量：大货各4 pcs 11. UPC贴纸：必须在原来错误的条码上用黑色粗头笔涂黑直至不能扫描，再贴上正确的UPC; ********************* a. 请确保产品符合1999年版本的加拿大环境保护法(CEPA)和2012年禁止某些有毒物质法规的要求。该产品不含任何在加拿大禁用的化学物质，包括但不限于有毒物 质清单中列出的化学物质，并且在为加拿大沃尔玛生产产品期间没有使用任何禁用化学物质。 Supplier certify that the products comply with the requirements of Canadian Environmental Protection Act, 1999 (CEPA), Prohibition of Certain To xic Substances Regulations, 2012. The products do not contain any chemicals that are banned in Canada, including but not limited to those listed in the Toxic Substances List and no banned chemicals were used during the manufacturing of product for Walmart Canada. 附件列表： (1) Letter of Guarantee for Canada banned chemicals - (1-5CA) b. 请确保产品在均质材料中的汞浓度不超过0.1%（按重量计）。 Supplier certify that the WAL-MART vendor products does not have a mercury concentration of more than 0.1% by weight in homogeneous material. 附件列表： (1) Letter of Guarantee for Mercury COC c. 请确保产品的塑料材料不含以下物质（SOR 2011-17 27B): Supplier certify that the plastic materials do not contain the following substances(SOR 2011-17 27B): (a) carbon tetrachloride or any substance that contains it; (b) methyl alcohol or any substance thay contains >1.0%; (c) petroleum distillates or any substance that contains >10% weight to volume of petroleum distillates; (d) benzene; (e) turpentine or any substance that contains >10% weight to volume of turpentine; (f) boric acid or salts of boric acid; or (g) ethyl ether. 附件列表： (1) Letter of Guarantee for WM CA-Other prohibited substances in plastic(less than 3 years) | AA37: Monica Zhou | AB37: 2.75 | AC37: =AB37*J37 -> 5923.5 | AD37: 95077R1-5.27 | AE37: 已入 | AG37: 2154 | AH37: =AG37-J37 -> 0 | AL37: =J37 -> 2154 | AO37: =J37 -> 2154 | AR37: =J37 -> 2154 | AS37: =AS36+AR37 -> 27684
A38: 45744 | B38: AB Gee of Ripley Ltd. | C38: 英国 | D38: 4500161792 | E38: 777 1MAY25 | F38: 4500161792-80 | G38: 71152-S001 | H38: 71152-S001 | I38: 机械速龙 | J38: 504 | K38: 0 | L38: 6 | M38: =J38/L38 -> 84 | N38: 45789 | O38: 45785 | Q38: PASS | T38: 否 | U38: 45761 | V38: 无 | W38: ZURU地址贴纸 | Z38: 日期码格式：ZURU INC(BVI) 标准格式 日期：按实际生产日期 Packaging Info: MA 最新UPC包装，各款的条码如下，请先检查条码是否正确再安排做货，如有问题请告知 71152-S001:193052079190 配比跟MA Remark: 1.产品及包装需要印UKCA图标，包装需要有ZURU UK LTD/ZURU France地址信息，QC同事请核查，如有问题与跟单确认。 2. 需要符合欧洲标准不能含有闪粉和微塑料，否则不和法规会有客诉产生 | AA38: Yoga Huang | AB38: 2.7663 | AC38: =AB38*J38 -> 1394.2152 | AD38: 94978-5.14 | AE38: 已入 | AG38: 504 | AH38: =AG38-J38 -> 0 | AK38: =J38 -> 504 | AN38: =J38 -> 504 | AR38: =J38 -> 504 | AS38: =AS37+AR38 -> 28188
A39: 45748 | B39: T. PLANET SHOPS SL | C39: 西班牙 | D39: 4500162134 | F39: 4500162134-30 | G39: 71152-S001-3L | H39: 71152-S001 | I39: 机械速龙 | J39: 1200 | K39: 0 | L39: 6 | M39: =J39/L39 -> 200 | N39: 45789 | O39: 45785 | Q39: PASS | T39: 是 | U39: 45761 | V39: 无 | W39: 45768 | Z39: 日期码格式：20250202 日期： Packaging Info: 71152:MA A 3L彩盒含EAN条码+进口商贴纸+产品贴纸+MAB版5L+9L说明书 Remark: 1, 此货出西班牙，需满足EU测试标准要求<(>&<)> 微塑料需符合法规。另外请确保所有包装都有西班牙环保标。 2，出货前两周需寄2-3套大货样品，请多备料 3, 此客人推期有罚款，请按时完货 4, 出货前要验货图片给客人确认OK后才出货 6. 其他款，若产品有比例使用ZURU STD 比例 8. 客户指定日期码码20250202，包装/产品/外箱需保持一致 | AA39: Mary Zhong | AB39: 2.6352 | AC39: =AB39*J39 -> 3162.24 | AD39: 95140-5.30 | AE39: 已入 | AG39: 1200 | AH39: =AG39-J39 -> 0 | AL39: =J39 -> 1200 | AO39: =J39 -> 1200 | AR39: =J39 -> 1200 | AS39: =AS38+AR39 -> 29388
A40: 45729 | B40: WM MORRISON SUPERMARKET PLC | C40: 英国 | D40: 4500159816 | E40: 14292169 | F40: 4500159816-40 | G40: 71152-S001 | H40: 71152-S001 | I40: 机械速龙 | J40: 6030 | K40: 0 | L40: 6 | M40: =J40/L40 -> 1005 | N40: 45772 | O40: 45768 | Q40: PASS | T40: 否 | U40: 45740 | V40: 无 | W40: 5/7防盗贴纸 | Y40: 日期码格式：ZURU INC(BVI) 标准格式 日期：按实际生产日期 | Z40: 日期码格式：ZURU INC(BVI) 标准格式 日期：按实际生产日期 Packaging Info: 4.71152-S001:MA 1L 最新UPC包装+1张黄色小圆贴防盗贴纸(贴纸类型9472521: 18MM 18mm yellow EAS label)+1张白色长方形防盗贴（贴纸类型10111887：410 ECO N），请工厂自行跟checkpoint供应商订购贴纸 UPC#193052079190，请先检查包装条码是否正确再安排做货 Remark: 1）外箱有条码要求，排版时请留意并请确保条码清晰可扫描（封箱胶不要黏到条码上), 否则客人会有罚款。 2) 订单出英国，产品及包装需要印UKCA图标，包装需要有ZURU UK LTD/ZURU France地址信息，QC同事请查核，如有问题与跟单确认。 3) 箱唛日期码与包装保持一致 4) 若外箱重量超过16KGS，请提前告知ZURU跟单，需要客人批准才能出货，并且外箱需要印2 man lift标志 | AA40: Yoga Huang | AB40: 2.4786 | AC40: =AB40*J40 -> 14945.958 | AD40: 94975-5.12 | AE40: 已入 | AG40: =4884+1146 -> 6030 | AH40: =AG40-J40 -> 0 | AJ40: =J40 -> 6030 | AO40: =J40 -> 6030 | AR40: =J40 -> 6030 | AS40: =AS39+AR40 -> 35418
A41: 45737 | B41: PT.MAP Aktif Adiperkasa, Tbk | C41: 印度尼西亚 | D41: 4500161027 | E41: 250218-3MAAJKTQ325-ZURU | F41: 4500161027-80 | G41: 71152-S001 | H41: 71152-S001 | I41: 机械速龙 | J41: 252 | K41: 0 | L41: 6 | M41: =J41/L41 -> 42 | N41: 45784 | O41: 45780 | Q41: PASS | T41: 否 | U41: 45747 | V41: 无 | W41: 1张进口商贴纸贴纸AW、位置图翻单如下： 71152-4500155574 | Y41: 日期码格式：ZURU INC(BVI) 标准格式 日期：按实际生产日期 | Z41: 日期码格式：ZURU INC(BVI) 标准格式 日期：按实际生产日期 Packaging Info: MA UPC包装（优先1L)+1张进口商贴纸 所有item使用含电池信息的进口商贴纸 贴纸AW、位置图翻单如下： 71152-4500155574 其他items贴纸AW、位置图待提供 1.可能会被抽大货样做测试，请多备料，CRD前半个月会通知是否有抽到该订单中的item。 2.此订单送仓，送仓后会有第三方验货，所以需要按CRD准时完货。 Remark: 71152-2PCS AAA BATTERIES(NOT INCLUDED) | AA41: Emma Wu | AB41: 2.7663 | AC41: =AB41*J41 -> 697.1076 | AD41: 94972R1-5.12 | AE41: 已入 | AG41: 252 | AH41: =AG41-J41 -> 0 | AK41: =J41 -> 252 | AO41: =J41 -> 252 | AR41: =J41 -> 252 | AS41: =AS40+AR41 -> 35670
A42: 45734 | B42: ZURU LLC | C42: 美国 | D42: 4500160498 | E42: B0DRB9N8J4 | F42: 4500160498-40 | G42: 71152-S001 | H42: 71152-S001-MTS | I42: 机械速龙 | J42: 906 | K42: 0 | L42: 6 | M42: =J42/L42 -> 151 | N42: 45777 | O42: 45773 | Q42: PASS | T42: 否 | U42: 45735 | V42: 无 | W42: 无 | Y42: 日期码格式：ZURU INC(BVI) 标准格式 日期：按实际生产日期 | Z42: 日期码格式：ZURU INC(BVI) 标准格式 日期：按实际生产日期 Packaging Info: #71152 MA UPC版 (1L或3L都可) Remark: 1.Amazon domestic 订单。出口美国。外箱最长边不能超过25" （超过了，case pack只能为1），不符合要求的大货，一律不接受。 2.无第三方验货/测试要求。 3.日期码使用ZURU标准版本。 4.邮包盒要印刷日期码。 | AA42: Kelly Shen/Mia Pan/P | AB42: 2.7 | AC42: =AB42*J42 -> 2446.2 | AD42: ZB00241-5.13 | AE42: 已入 | AG42: 906 | AH42: =AG42-J42 -> 0 | AK42: =J42 -> 906 | AO42: =J42 -> 906 | AR42: =J42 -> 906 | AS42: =AS41+AR42 -> 36576
A43: 45742 | B43: ASIA GOAL LIMITED TAIWAN BRANCH (H. | C43: 台湾 | D43: 4500161426 | E43: AG240431-TW | F43: 4500161426-30 | G43: 71152-S001 | H43: 71152-S001 | I43: 机械速龙 | J43: 180 | K43: 0 | L43: 6 | M43: =J43/L43 -> 30 | N43: 45792 | O43: 45789 | Q43: PASS | T43: 否 | U43: 45742 | V43: 无 | W43: 45750 | Z43: 日期码格式：ZURU INC(BVI) 标准格式 日期：按实际生产日期 Packaging Info: 71152： MA 1L PKG+1张警语贴纸， MA 说明书 Remark: 此单出TW | AA43: Doris Shou | AB43: 2.6717 | AC43: =AB43*J43 -> 480.906 | AD43: 95068-5.26 | AE43: 已入 | AG43: 180 | AH43: =AG43-J43 -> 0 | AK43: =J43 -> 180 | AN43: =J43 -> 180 | AR43: =J43 -> 180 | AS43: =AS42+AR43 -> 36756
A44: 45756 | B44: ARGOS LIMITED | C44: 英国 | D44: 4500163082 | E44: 240291 | F44: 4500163082-10 | G44: 71152-S001 | H44: 71152-S001 | I44: 机械速龙 | J44: 1602 | K44: 0 | L44: 6 | M44: =J44/L44 -> 267 | N44: 45792 | O44: 45789 | Q44: PASS | T44: 否 | U44: 45756 | V44: 无 | W44: 45761 | Z44: 日期码格式：ZURU INC(BVI) 标准格式 日期：按实际生产日期 Packaging Info: 71152：MA -1L UPC包装+客人白色Cat.label 1张覆盖ZURU条码 注意Cat.label (要求易撕类贴纸，但是粘性不能过低），同时此贴纸每个订单都是不相同的(会显示客户对应的订单号），切勿翻旧订单购买，该贴纸由工厂自行 购买。 Remark: *MA包装按最新版本安排即可 *包装日期码按ZURU格式即可，请确保不迟于外箱日期码，可等于或者早于外箱日期码，必须为法定工作日。 *外箱尺寸任何一条边长度超过75cm或者每箱重量超过10KG,需要在外箱上加三脚架符号，有问题请与ZURU跟单同事核实。 *订单必须经过ZURU QC验货并且通过后方可出货。 *订单出英国，请注意检查产品及包装应带UKCA图标，包装显示ZURU UK LTD信息，QC同事请查核，如有问题与跟单确认。 *条码扫描会显示客户7位数产品号 ，忽略订单显示的MA条码 *所有产品按符合欧洲标准走货，微塑料需合规。 *涉及到硼的，需要符合欧洲标准 *客户不接受PVC材质包装 *外箱不得使用带金属夹子或带扣 | AA44: May Wu | AB44: 2.6352 | AC44: =AB44*J44 -> 4221.5904 | AD44: 95021-5.19 | AE44: 已入 | AG44: 1602 | AH44: =AG44-J44 -> 0 | AK44: =J44 -> 1602 | AO44: =J44 -> 1602 | AR44: =J44 -> 1602 | AS44: =AS43+AR44 -> 38358
A45: 45733 | B45: WAL-MART CANADA CORP. | C45: 加拿大 | D45: 4500160504 | E45: 9900923488 | F45: 4500160504-20 | G45: 71152-S002 | H45: 71152-S002 | I45: 机械速龙 | J45: 15 | K45: 0 | L45: 3 | M45: =J45/L45 -> 5 | N45: 45793 | O45: 45789 | Q45: PASS | T45: 是 | U45: 45750 | V45: 有 | W45: 3/16UPC贴纸(UPC:193052079190) | X45: 外箱四面须加一张黄色贴纸 | Y45: 日期码格式：ZURU INC(BVI) 标准格式 日期：2025-04-28 | Z45: 日期码格式：ZURU INC(BVI) 标准格式 日期：按实际生产日期 Packaging Info: #71152： MA3L彩盒+UPC贴纸(UPC:193052079190)+MA5L说明书(B版) 产品配比： 7 Assortment, Polar bear: Penguin: Walrus: Mammoth: Owl: Seal: Snow man=10:10:10:10:10:8:2. Snow man is the rare item. Remark: 1. 此单有箱唛； 2. 9900923488单为ECOM订单，外箱四面须加一张黄色贴纸； 3. 此单有第三方验货，烦请多备包装物料； 4. #71152需于2025/4/18安排签版, 签样数量：大货样各3PCS； 8. #71152 需于2025/4/28安排抽办测试, 抽办数量：大货各4 pcs 11. UPC贴纸：必须在原来错误的条码上用黑色粗头笔涂黑直至不能扫描，再贴上正确的UPC; ********************* a. 请确保产品符合1999年版本的加拿大环境保护法(CEPA)和2012年禁止某些有毒物质法规的要求。该产品不含任何在加拿大禁用的化学物质，包括但不限于有毒物 质清单中列出的化学物质，并且在为加拿大沃尔玛生产产品期间没有使用任何禁用化学物质。 Supplier certify that the products comply with the requirements of Canadian Environmental Protection Act, 1999 (CEPA), Prohibition of Certain To xic Substances Regulations, 2012. The products do not contain any chemicals that are banned in Canada, including but not limited to those listed in the Toxic Substances List and no banned chemicals were used during the manufacturing of product for Walmart Canada. 附件列表： (1) Letter of Guarantee for Canada banned chemicals - (1-5CA) b. 请确保产品在均质材料中的汞浓度不超过0.1%（按重量计）。 Supplier certify that the WAL-MART vendor products does not have a mercury concentration of more than 0.1% by weight in homogeneous material. 附件列表： (1) Letter of Guarantee for Mercury COC c. 请确保产品的塑料材料不含以下物质（SOR 2011-17 27B): Supplier certify that the plastic materials do not contain the following substances(SOR 2011-17 27B): (a) carbon tetrachloride or any substance that contains it; (b) methyl alcohol or any substance thay contains >1.0%; (c) petroleum distillates or any substance that contains >10% weight to volume of petroleum distillates; (d) benzene; (e) turpentine or any substance that contains >10% weight to volume of turpentine; (f) boric acid or salts of boric acid; or (g) ethyl ether. 附件列表： (1) Letter of Guarantee for WM CA-Other prohibited substances in plastic(less than 3 years) | AA45: Monica Zhou | AB45: 2.75 | AC45: =AB45*J45 -> 41.25 | AD45: 95066R1-5.26 | AE45: 已入 | AG45: 15 | AH45: =AG45-J45 -> 0 | AL45: =J45 -> 15 | AO45: =J45 -> 15 | AR45: =J45 -> 15 | AS45: =AS44+AR45 -> 38373
A46: 45733 | B46: WAL-MART CANADA CORP. | C46: 加拿大 | D46: 4500160504 | E46: 9900924299 | F46: 4500160504-30 | G46: 71152-S002 | H46: 71152-S002 | I46: 机械速龙 | J46: 2178 | K46: 0 | L46: 3 | M46: =J46/L46 -> 726 | N46: 45793 | O46: 45789 | Q46: PASS | T46: 是 | U46: 45750 | V46: 有 | W46: 3/16UPC贴纸(UPC:193052079190) | Y46: 日期码格式：ZURU INC(BVI) 标准格式 日期：2025-04-28 | Z46: 日期码格式：ZURU INC(BVI) 标准格式 日期：按实际生产日期 Packaging Info: #71152： MA3L彩盒+UPC贴纸(UPC:193052079190)+MA5L说明书(B版) 产品配比： 7 Assortment, Polar bear: Penguin: Walrus: Mammoth: Owl: Seal: Snow man=10:10:10:10:10:8:2. Snow man is the rare item. Remark: 1. 此单有箱唛； 3. 此单有第三方验货，烦请多备包装物料； 4. #71152需于2025/4/18安排签版, 签样数量：大货样各3PCS； 8. #71152 需于2025/4/28安排抽办测试, 抽办数量：大货各4 pcs 11. UPC贴纸：必须在原来错误的条码上用黑色粗头笔涂黑直至不能扫描，再贴上正确的UPC; ********************* a. 请确保产品符合1999年版本的加拿大环境保护法(CEPA)和2012年禁止某些有毒物质法规的要求。该产品不含任何在加拿大禁用的化学物质，包括但不限于有毒物 质清单中列出的化学物质，并且在为加拿大沃尔玛生产产品期间没有使用任何禁用化学物质。 Supplier certify that the products comply with the requirements of Canadian Environmental Protection Act, 1999 (CEPA), Prohibition of Certain To xic Substances Regulations, 2012. The products do not contain any chemicals that are banned in Canada, including but not limited to those listed in the Toxic Substances List and no banned chemicals were used during the manufacturing of product for Walmart Canada. 附件列表： (1) Letter of Guarantee for Canada banned chemicals - (1-5CA) b. 请确保产品在均质材料中的汞浓度不超过0.1%（按重量计）。 Supplier certify that the WAL-MART vendor products does not have a mercury concentration of more than 0.1% by weight in homogeneous material. 附件列表： (1) Letter of Guarantee for Mercury COC c. 请确保产品的塑料材料不含以下物质（SOR 2011-17 27B): Supplier certify that the plastic materials do not contain the following substances(SOR 2011-17 27B): (a) carbon tetrachloride or any substance that contains it; (b) methyl alcohol or any substance thay contains >1.0%; (c) petroleum distillates or any substance that contains >10% weight to volume of petroleum distillates; (d) benzene; (e) turpentine or any substance that contains >10% weight to volume of turpentine; (f) boric acid or salts of boric acid; or (g) ethyl ether. 附件列表： (1) Letter of Guarantee for WM CA-Other prohibited substances in plastic(less than 3 years) | AA46: Monica Zhou | AB46: 2.75 | AC46: =AB46*J46 -> 5989.5 | AD46: 95077R1-5.27 | AE46: 已入 | AG46: =1818+360 -> 2178 | AH46: =AG46-J46 -> 0 | AL46: =J46 -> 2178 | AO46: =J46 -> 2178 | AR46: =J46 -> 2178 | AS46: =AS45+AR46 -> 40551
A47: 45742 | B47: TAS IMPORT AS(Lekekassen) | C47: 挪威 | D47: 4500161075 | E47: 11098 | F47: 4500161075-130 | G47: 71152-S001-3L-1 | H47: 71152-S001 | I47: 机械速龙 | J47: 600 | K47: 0 | L47: 6 | M47: =J47/L47 -> 100 | N47: 45793 | O47: 45789 | Q47: PASS | T47: 否 | U47: 45770 | V47: 无 | W47: 45783 | X47: 客版说明书 | Y47: 日期码格式：ZURU INC(BVI) 标准格式 日期：按实际生产日期 | Z47: 日期码格式：ZURU INC(BVI) 标准格式 日期：按实际生产日期 Packaging Info: 13. 71152: MA_A_3L(23L warning) EAN版收缩膜+客人进口商地址贴纸+客版说明书(英语/丹麦/瑞典/芬兰/挪威/爱沙尼亚语言) 16. 配比跟MA Remark: 1. 包装如含PVC,请改为PET并第一时间通知跟单 2. 产品/包装要求无硼无香，出欧洲，微塑料需合规。 3.带电池出货的产品所用到的电池需要符合欧洲电池新规(EU) 2023-1542 4.有胶袋的产品：要求产品的胶袋厚度要大于等于0.05mm 5.关于贴纸，如果贴纸位置图的包装版本与大货不一致，请工厂第一时间提前提出。跟单会重新调整确认是否更新贴纸或调整位置图 6.产品/包装不含PFAS成分 7.产品条码如下: 请先检查条码是否正确再安排做货，如有问题请告知 ZURU ITEM#<(>&<)>EAN 71152:4894680042742 | AA47: Sheba | AB47: 2.7663 | AC47: =AB47*J47 -> 1659.78 | AD47: 95091R1-5.28 | AE47: 已入 | AG47: 600 | AH47: =AG47-J47 -> 0 | AL47: =J47 -> 600 | AP47: =J47 -> 600 | AR47: =J47 -> 600 | AS47: =AS46+AR47 -> 41151
A48: 45763 | B48: ZURU Denmark ApS | C48: 丹麦 | D48: 4500163403 | E48: 5200006595 | F48: 4500163403-40 | G48: 71152-S001-3L-1 | H48: 71152-S001-MTS | I48: 机械速龙 | J48: 108 | K48: 0 | L48: 6 | M48: =J48/L48 -> 18 | N48: 45796 | O48: 45792 | Q48: PASS | T48: 否 | U48: 45763 | V48: 无 | W48: 无 | X48: 客版说明书 + 北欧六语通用不带电池出货黑白电池说明书 （全部翻 4500162346） | Z48: 日期码格式：ZURU INC(BVI) 标准格式 日期：按实际生产日期 Packaging Info: 4.71152: MA 5L+23L警语 EAN A版包装 + 客版说明书 + 北欧六语通用不带电池出货黑白电池说明书 （全部翻 4500162346） EAN#4894680042742； Remark: 1.北欧内销单，需要通过ZURU 验货结果后才能出货 (工厂需要主动提前同ZURU QC预约验货避免延期出货造成不必要麻烦)； 2. 产品如含有化学品，需要无硼无香， 3.包装不能含有PVC，使用PET 4. date code: 外箱日期码要晚于产品日期码 5. 装柜时需要按照款式号码从小到大一款款依次装,避免终端仓库卸货混乱.若一个柜子涉及到几个不同国家内销单,装柜时需要一个国家装完后再装另一个国家的 产品,依次装柜,避免终端仓库因不同国家不同库位位置卸货混乱. (此点需要同工厂装柜人员强调)" 6.若有特定款有特殊外箱条码要求时,需要明确列出产品款对应的具体外箱条码号码/条码类型 (若无,可以忽略此需求) 7.所有出口欧洲的产品, 法规规定禁止在包装和共公众用的印刷品中使用矿物油中含有的物质, 包装印刷油墨中含有的MOAH/MOSH的质量浓度不能超过1%, 否则出货 到法国被抽检出现问题, 供应商需要对此负责; 8.带电池出货的产品所用到的电池需要符合欧洲电池新规(EU) 2023-1542。 9.ratio 同MA | AA48: AMY XIAO | AB48: 2.7663 | AC48: =AB48*J48 -> 298.7604 | AD48: 95028-5.20 | AE48: 已入 | AG48: 108 | AH48: =AG48-J48 -> 0 | AL48: =J48 -> 108 | AP48: =J48 -> 108 | AR48: =J48 -> 108 | AS48: =AS47+AR48 -> 41259
A49: 45755 | B49: CANDIDE IND E COM LTDA | C49: 巴西 | D49: 4500162877 | E49: BR25882 | F49: 4500162877-30 | G49: 71152-S001-3L-1 | H49: 71152-S001 | I49: 机械速龙 | J49: 2502 | K49: 0 | L49: 6 | M49: =J49/L49 -> 417 | N49: 45792 | O49: 45789 | Q49: PASS | T49: 否 | U49: 45770 | V49: 无 | W49: 45771 | X49: 客版说明书4500162245 | Z49: 日期码格式：ZURU INC(BVI) 标准格式 日期：按实际生产日期 Packaging Info: 71152::MA 3L EAN包装+客户条码贴纸+进口商贴纸+箱唛+客版说明书，说明书翻单PO4500162245 Remark: 外箱胶带要用CANDIDE格式 | AA49: Ava Liang | AB49: 2.5269 | AC49: =AB49*J49 -> 6322.3038 | AD49: 95020-5.19 | AE49: 已入 | AG49: =2490+12 -> 2502 | AH49: =AG49-J49 -> 0 | AL49: =J49 -> 2502 | AP49: =J49 -> 2502 | AR49: =J49 -> 2502 | AS49: =AS48+AR49 -> 43761
A50: 45749 | B50: Outlet Drift AS | C50: 挪威 | D50: 4500162375 | E50: 20106 | F50: 4500162375-90 | G50: 71152-S001-3L-1 | H50: 71152-S001 | I50: 机械速龙 | J50: 162 | K50: 0 | L50: 6 | M50: =J50/L50 -> 27 | N50: 45797 | O50: 45793 | Q50: PASS | T50: 否 | U50: 45750 | V50: 无 | W50: 无 | X50: 客版说明书翻4500161075 | Z50: 日期码格式：ZURU INC(BVI) 标准格式 日期：按实际生产日期 Packaging Info: 71152: 彩盒MA EAN 3L A+客版说明书（翻单4500161075） Remark: 1/配比: 2/产品和包装要求无硼无香，包装不能含有PVC 3/如有微塑料，必须合规欧洲标准，闪粉也是微塑料的一种，目前仅接受三张方式1.去除，2.用可降解材料，和3.永久封印在固体。 4/带电池出货的产品，所用到的电池需要符合欧洲电池新规(EU)2023-1542 | AA50: Zoe Zhou | AB50: 2.7663 | AC50: =AB50*J50 -> 448.1406 | AD50: 95040R1-5.22 | AE50: 已入 | AG50: 162 | AH50: =AG50-J50 -> 0 | AL50: =J50 -> 162 | AP50: =J50 -> 162 | AR50: =J50 -> 162 | AS50: =AS49+AR50 -> 43923
A51: 45772 | B51: 360 SALES SOLUTIONS INC | C51: 加拿大 | D51: 4500164965 | E51: 2025ZURU17 | F51: 4500164965-10 | G51: 71152-S001-3L | H51: 71152-S001 | I51: 机械速龙 | J51: 504 | K51: 0 | L51: 6 | M51: =J51/L51 -> 84 | N51: 45801 | O51: 45797 | Q51: PASS | T51: 否 | U51: 45772 | V51: 无 | W51: 45772 | Z51: 日期码格式：ZURU INC(BVI) 标准格式 日期：按实际生产日期 Packaging Info: 71152 MA 多语EAN+UPC贴纸，UPC号码 193052079190 Remark: 出加拿大 Zuru验货.日期跟踪码：产品外包装及产品本身都必须有日期跟踪码，ZURU标准格式日期码。（箱唛日期码按跟单提供格式） | AA51: Summer Mo | AB51: 2.76663 | AC51: =AB51*J51 -> 1394.3815 | AD51: 95056-5.24 | AE51: 已入 | AG51: 504 | AH51: =AG51-J51 -> 0 | AL51: =J51 -> 504 | AO51: =J51 -> 504 | AR51: =J51 -> 504 | AS51: =AS50+AR51 -> 44427
A52: 45749 | B52: K􀃤rkk􀃤inen Oy /Centrawla rehouse | C52: 芬兰 | D52: 4500161573 | E52: 4100411993 | F52: 4500161573-70 | G52: 71152-S001-3L | H52: 71152-S001 | I52: 机械速龙 | J52: 120 | K52: 0 | L52: 6 | M52: =J52/L52 -> 20 | N52: 45803 | O52: 45799 | Q52: PASS | T52: 否 | U52: 45769 | V52: 无 | W52: 无 | X52: 客版说明书翻4500161075 | Z52: 日期码格式：ZURU INC(BVI) 标准格式 日期：按实际生产日期 Packaging Info: 7. 71152: MA_A_3L(23L warning) EAN版彩盒+客版说明书(英语/丹麦/瑞典/芬兰/挪威/爱沙尼亚语言)--客版说明书翻TAS PO#4500161075 2. 配比跟MA Remark: 1. 包装如含PVC,请改为PET并第一时间通知跟单 2. 产品/包装要求无硼无香，出欧洲，微塑料需合规。 3.带电池出货的产品所用到的电池需要符合欧洲电池新规(EU) 2023-1542 4.有胶袋的产品：要求产品的胶袋厚度要大于等于0.05mm 5.关于贴纸，如果贴纸位置图的包装版本与大货不一致，请工厂第一时间提前提出。跟单会重新调整确认是否更新贴纸或调整位置图 6.产品/包装不含PFAS成分 7.产品条码如下: 请先检查条码是否正确再安排做货，如有问题请告知 ZURU ITEM#<(>&<)>EAN: 71152:4894680042742 | AA52: Sheba | AB52: 2.6717 | AC52: =AB52*J52 -> 320.604 | AD52: 95198-6.4 | AE52: 已入 | AG52: 120 | AH52: =AG52-J52 -> 0 | AL52: =J52 -> 120 | AO52: =J52 -> 120 | AR52: =J52 -> 120 | AS52: =AS51+AR52 -> 44547
A53: 45741 | B53: TOYS "R" US (CANADA) LTD. | C53: 加拿大 | D53: 4500161332 | E53: 3501527773 | F53: 4500161332-10 | G53: 71152-S001-3L | H53: 71152-S001 | I53: 机械速龙 | J53: 804 | K53: 0 | L53: 6 | M53: =J53/L53 -> 134 | N53: 45796 | O53: 45792 | P53: 5/23第三方 | Q53: PASS | T53: 否 | U53: 45754 | V53: 无 | W53: 45754 | Y53: 日期码格式：ZURU INC(BVI) 标准格式 日期：按实际生产日期 | Z53: 日期码格式：ZURU INC(BVI) 标准格式 日期：按实际生产日期 Packaging Info: 1. 出口加拿大市场，MA UPC版本包装。 #71152：彩盒MA 3L+23K Warning EAN 版本+UPC 贴纸,说明书MA 5L+9L(warning), UPC#193052079190; 2PCS AAA BATTERIES(NOT INCLUDED); 2. 产品、包装、外箱上面tracking code的时间格式需要一致 Remark: 3. 需要第三方SGS验货，验货时间2025/05/19，每款每色请备1PC完整带包装样品供验货人员参考。用完后若无损坏可以放回大货里。 | AA53: Abby Mai,Lluvia Zeng | AB53: 2.6717 | AC53: =AB53*J53 -> 2148.0468 | AD53: 95227R1-6.6 | AE53: 已入 | AG53: 804 | AH53: =AG53-J53 -> 0 | AL53: =J53 -> 804 | AO53: =J53 -> 804 | AR53: =J53 -> 804 | AS53: =AS52+AR53 -> 45351
A54: 45754 | B54: ZURU Denmark ApS | C54: 丹麦 | D54: 4500162346 | E54: 5200006527 | F54: 4500162346-120 | G54: 71152-S001-3L-1 | H54: 71152-S001-MTS | I54: 机械速龙 | J54: 1548 | K54: 0 | L54: 6 | M54: =J54/L54 -> 258 | N54: 45783 | O54: 45779 | Q54: PASS | T54: 否 | U54: 45757 | V54: 无 | X54: 客版说明书（翻单4500161075） | Z54: 日期码格式：ZURU INC(BVI) 标准格式 日期：按实际生产日期 Packaging Info: 71152: MA 5L+23L警语 EAN A版包装 + 客版说明书(翻单4500161075) + 北欧6语通用不带电池出货黑白电池说明书 Remark: 1.北欧内销单，需要通过ZURU 验货结果后才能出货 (工厂需要主动提前同ZURU QC预约验货避免延期出货造成不必要麻烦)； 2. 产品如含有化学品，需要无硼无香， 3.包装不能含有PVC，使用PET 4. date code: 外箱日期码要晚于产品日期码 5. 装柜时需要按照款式号码从小到大一款款依次装,避免终端仓库卸货混乱.若一个柜子涉及到几个不同国家内销单,装柜时需要一个国家装完后再装另一个国家的 产品,依次装柜,避免终端仓库因不同国家不同库位位置卸货混乱. (此点需要同工厂装柜人员强调)" 6.若有特定款有特殊外箱条码要求时,需要明确列出产品款对应的具体外箱条码号码/条码类型 (若无,可以忽略此需求) 7.所有出口欧洲的产品, 法规规定禁止在包装和共公众用的印刷品中使用矿物油中含有的物质, 包装印刷油墨中含有的MOAH/MOSH的质量浓度不能超过1%, 否则出货 到法国被抽检出现问题, 供应商需要对此负责; 8.带电池出货的产品所用到的电池需要符合欧洲电池新规(EU) 2023-1542。 9.ratio 同MA | AA54: SD04 | AB54: 2.6352 | AC54: =AB54*J54 -> 4079.2896 | AD54: 94941-5.7 | AE54: 已入 | AG54: 1548 | AH54: =AG54-J54 -> 0 | AL54: =J54 -> 1548 | AP54: =J54 -> 1548 | AR54: =J54 -> 1548 | AS54: =AS53+AR54 -> 46899
A55: 45755 | B55: BIG W | C55: 澳大利亚 | D55: 4500162809 | E55: 47815487 SYD | F55: 4500162809-10 | G55: 71152-S001 | H55: 71152-S001 | I55: 机械速龙 | J55: 702 | K55: 0 | L55: 6 | M55: =J55/L55 -> 117 | N55: 45793 | O55: 45789 | Q55: PASS | T55: 否 | U55: 45755 | V55: 无 | W55: 45755 | Z55: 日期码格式：ZURU INC(BVI) 标准格式 日期：按实际生产日期 Packaging Info: 1. 包装： 71152-S001: MA UPC PKG+1张进口商贴纸 2. 进口商贴纸上已经去掉日期码，产品和包装上的日期码一致，请按要求在包装上打日期码（进口商贴纸不覆盖日期码） 3. 使用ZURU标准日期码 Remark: 1. 共出4港口 (SYD, BNE, MEL, FRE)，不同港口数量信息请见订单行项目，并请参考箱唛资料，港口不同，箱唛资料也不同； 2. 箱唛不可出现任何手写内容（箱数除外），重量与实际一致且不可手写； 3. 此单出澳大利亚，请按澳洲标准生产并满足当地法规要求； 4. 出无闪粉版本，需符合欧洲微塑料法规。 | AA55: Christine Liao | AB55: 2.8222 | AC55: =AB55*J55 -> 1981.1844 | AD55: 95049-5.23 | AE55: 已入 | AG55: 702 | AH55: =AG55-J55 -> 0 | AK55: =J55 -> 702 | AO55: =J55 -> 702 | AR55: =J55 -> 702 | AS55: =AS54+AR55 -> 47601
A56: 45755 | B56: BIG W | C56: 澳大利亚 | D56: 4500162809 | E56: 47815488 BNE | F56: 4500162809-20 | G56: 71152-S001 | H56: 71152-S001 | I56: 机械速龙 | J56: 558 | K56: 0 | L56: 6 | M56: =J56/L56 -> 93 | N56: 45793 | O56: 45789 | Q56: PASS | T56: 否 | U56: 45755 | V56: 无 | W56: 45755 | Z56: 日期码格式：ZURU INC(BVI) 标准格式 日期：按实际生产日期 Packaging Info: 1. 包装： 71152-S001: MA UPC PKG+1张进口商贴纸 2. 进口商贴纸上已经去掉日期码，产品和包装上的日期码一致，请按要求在包装上打日期码（进口商贴纸不覆盖日期码） 3. 使用ZURU标准日期码 Remark: 1. 共出4港口 (SYD, BNE, MEL, FRE)，不同港口数量信息请见订单行项目，并请参考箱唛资料，港口不同，箱唛资料也不同； 2. 箱唛不可出现任何手写内容（箱数除外），重量与实际一致且不可手写； 3. 此单出澳大利亚，请按澳洲标准生产并满足当地法规要求； 4. 出无闪粉版本，需符合欧洲微塑料法规。 | AA56: Christine Liao | AB56: 2.8222 | AC56: =AB56*J56 -> 1574.7876 | AD56: 95049-5.23 | AE56: 已入 | AG56: 558 | AH56: =AG56-J56 -> 0 | AK56: =J56 -> 558 | AO56: =J56 -> 558 | AR56: =J56 -> 558 | AS56: =AS55+AR56 -> 48159
A57: 45755 | B57: BIG W | C57: 澳大利亚 | D57: 4500162809 | E57: 47824041 MEL | F57: 4500162809-30 | G57: 71152-S001 | H57: 71152-S001 | I57: 机械速龙 | J57: 540 | K57: 0 | L57: 6 | M57: =J57/L57 -> 90 | N57: 45793 | O57: 45789 | Q57: PASS | T57: 否 | U57: 45755 | V57: 无 | W57: 45755 | Z57: 日期码格式：ZURU INC(BVI) 标准格式 日期：按实际生产日期 Packaging Info: 1. 包装： 71152-S001: MA UPC PKG+1张进口商贴纸 2. 进口商贴纸上已经去掉日期码，产品和包装上的日期码一致，请按要求在包装上打日期码（进口商贴纸不覆盖日期码） 3. 使用ZURU标准日期码 Remark: 1. 共出4港口 (SYD, BNE, MEL, FRE)，不同港口数量信息请见订单行项目，并请参考箱唛资料，港口不同，箱唛资料也不同； 2. 箱唛不可出现任何手写内容（箱数除外），重量与实际一致且不可手写； 3. 此单出澳大利亚，请按澳洲标准生产并满足当地法规要求； 4. 出无闪粉版本，需符合欧洲微塑料法规。 | AA57: Christine Liao | AB57: 2.8222 | AC57: =AB57*J57 -> 1523.988 | AD57: 95033--5.21 | AE57: 已入 | AG57: 540 | AH57: =AG57-J57 -> 0 | AK57: =J57 -> 540 | AO57: =J57 -> 540 | AR57: =J57 -> 540 | AS57: =AS56+AR57 -> 48699
A58: 45755 | B58: BIG W | C58: 澳大利亚 | D58: 4500162809 | E58: 47815490 FRE | F58: 4500162809-40 | G58: 71152-S001 | H58: 71152-S001 | I58: 机械速龙 | J58: 204 | K58: 0 | L58: 6 | M58: =J58/L58 -> 34 | N58: 45793 | O58: 45789 | Q58: PASS | T58: 否 | U58: 45755 | V58: 无 | W58: 45755 | Z58: 日期码格式：ZURU INC(BVI) 标准格式 日期：按实际生产日期 Packaging Info: 1. 包装： 71152-S001: MA UPC PKG+1张进口商贴纸 2. 进口商贴纸上已经去掉日期码，产品和包装上的日期码一致，请按要求在包装上打日期码（进口商贴纸不覆盖日期码） 3. 使用ZURU标准日期码 Remark: 1. 共出4港口 (SYD, BNE, MEL, FRE)，不同港口数量信息请见订单行项目，并请参考箱唛资料，港口不同，箱唛资料也不同； 2. 箱唛不可出现任何手写内容（箱数除外），重量与实际一致且不可手写； 3. 此单出澳大利亚，请按澳洲标准生产并满足当地法规要求； 4. 出无闪粉版本，需符合欧洲微塑料法规。 | AA58: Christine Liao | AB58: 2.8222 | AC58: =AB58*J58 -> 575.7288 | AD58: 95005-5.17 | AE58: 已入 | AG58: 204 | AH58: =AG58-J58 -> 0 | AK58: =J58 -> 204 | AO58: =J58 -> 204 | AR58: =J58 -> 204 | AS58: =AS57+AR58 -> 48903
A59: 45756 | B59: Smyths Toys EU HQ UC | C59: 德国 | D59: 4500163031 | E59: 4400476746 | F59: 4500163031-10 | G59: 71152-S001-1 | H59: 71152-S001 | I59: 机械速龙 | J59: 2202 | K59: 0 | L59: 6 | M59: =J59/L59 -> 367 | N59: 45797 | O59: 45793 | Q59: PASS | R59: 45801 | T59: 否 | U59: 45756 | V59: 无 | W59: 45756 | X59: 客版彩盒(3L 英法德callout+EAN条码+法国回收logo) 翻UK单#4500156690，客版WEEE声明说明书纸(不带电池，翻4500159614) | Z59: 日期码格式：ZURU INC(BVI) 标准格式 日期：按实际生产日期 Packaging Info: 71152:客版彩盒(3L 英法德callout+EAN条码+法国回收logo) 翻UK单#4500156690 + MA 5L-9L Warning说明书+客版WEEE声明说明书纸(不带电池，翻4500159614)+Z URU FRANCE 地址贴纸（翻单4500064042） EAN# 4894680042742 Remark: 1. 此单出德国，需要满足Zuru Standard欧洲标准测试要求； 2. 请准时出货，推期会有罚款； 3. 出口欧洲，微塑料需符合法规； 4. 所有电子产品身上需要加字唛，为ZURU FRANCE 地址 (如无电子产品，产品布标有此地址，或产品太小无法增加可忽略此信息) ZURU France 1/3, Rue d'Argenteuil 95210 SAINT-GRATIEN, FRANCE 5. 所有出往德国订单的电子产品需增加一张客版WEEE声明说明书，区分带电池和不带电池版本, 如已做客版说明书可忽略此要求。 6. 标准配比 | AA59: Shirley Zhou | AB59: 2.6214 | AC59: =AB59*J59 -> 5772.3228 | AD59: 95062-5.26 | AE59: 已入 | AG59: =24+2178 -> 2202 | AH59: =AG59-J59 -> 0 | AM59: =J59 -> 2202 | AO59: =J59 -> 2202 | AR59: =J59 -> 2202 | AS59: =AS58+AR59 -> 51105
A60: 45750 | B60: ZURU France | C60: ZURU France | D60: 4500162314 | E60: 5200006540 | F60: 4500162314-40 | G60: 71152-S001-3L | H60: 71152-S001-MTS | I60: 机械速龙 | J60: 486 | K60: 0 | L60: 6 | M60: =J60/L60 -> 81 | N60: 45799 | O60: 45796 | Q60: PASS | R60: 45799 | T60: 否 | U60: 45750 | V60: 无 | W60: 45761 | Z60: 日期码格式：ZURU INC(BVI) 标准格式 日期：按实际生产日期 Packaging Info: 71152:最新MA 3L EAN（23L warning）彩盒+最新MA 5L说明书+ 一张意大利环保标贴纸+ 多语版WEEE电池垃圾桶的回收声明说明书（not included）,, Remark: 1. 法国国家内销单，需要通过ZURU 验货结果后才能出货 (工厂需要主动提前同ZURU QC预约验货避免延期出货造成不必要麻烦)； 2. 本订单所有 具有 baby items / assorted items 的款式，零售包装上都要用 母 EAN; 3. 若有特定款有特殊外箱条码要求时,需要明确列出产品款对应的具体外箱条码号码/条码类型 (若无,可以忽略此需求) 4. 所有出口欧洲的产品, 法规规定禁止在包装和共公众用的印刷品中使用矿物油中含有的物质, 包装印刷油墨中含有的MOAH/MOSH的质量浓度不能超过1%, 否则出 货到法国被抽检出现问题, 供应商需要对此负责; 5. Date code: 外箱/产品/包装 保持一致，完货后提供date code 信息以便我们保存记录做批次管理; 6. 装柜时需要按照款式号码从小到大一款款依次装,避免终端仓库卸货混乱.若一个柜子涉及到几个不同国家内销单,装柜时需要一个国家装完后再装另一个国家的 产品,依次装柜,避免终端仓库因不同国家不同库位位置卸货混乱. (此点需要同工厂装柜人员强调) | AA60: Jade Wang | AB60: 2.7663 | AC60: =AB60*J60 -> 1344.4218 | AD60: 95050-5.23 | AE60: 已入 | AG60: 486 | AH60: =AG60-J60 -> 0 | AL60: =J60 -> 486 | AO60: =J60 -> 486 | AR60: =J60 -> 486 | AS60: =AS59+AR60 -> 51591
A61: 45756 | B61: THE ENTERTAINER | C61: 英国 | D61: 4500161772 | E61: FB12981 | F61: 4500161772-40 | G61: 71152-S001 | H61: 71152-S001 | I61: 机械速龙 | J61: 3000 | K61: 0 | L61: 6 | M61: =J61/L61 -> 500 | N61: 45800 | O61: 45796 | Q61: PASS | R61: 45803 | T61: 是 | U61: 45756 | V61: 无 | W61: 一张2国语言电池说明书 | Z61: 日期码格式：ZURU INC(BVI) 标准格式 日期：按实际生产日期 Packaging Info: 71152-S001 MA 最新1L UPC包装+一张2国语言电池说明书(英语+阿拉伯语); BARCODE: 193052079190 请核对订单条码： 71152-S001 193052079190 Remark: *MA版本按工厂现有最新库存即可，订单出英国，请注意检查产品及包装应带UKCA图标，包装显示ZURU UK LTD信息，QC同事请查核，如有问题与跟单确认 *生产日期按实际（法定工作日），按ZURU标准格式即可 ，但是请知悉包装日期码需要早于或者等于外箱日期码 ，不能晚于外箱日期码 *请注意所有订单都需要经过ZURU QC验货并且通过后方可出货 *所有产品按符合欧洲标准走货，需要是不含微塑料版本 。 *涉及到硼的，如可选择情况下应使用低硼版本 （slime 类别低硼一般低于300ppm)，无选择的应与跟单复核再安排 。 *如果出运产品属于电子类产品需要在ZURU 包装基础上额外添加一张英文+阿拉伯文电池说明书。 *订单对应客户4个PO号 ，备注有显示 ，注意分开做货/验货/装柜 ，混装有罚款。 * 大货样： 请在5/10 前寄出每款1整套大货样到罗湖办公室7B Sandy Shao 收。 | AA61: Sandy Shao | AB61: 2.5939 | AC61: =AB61*J61 -> 7781.7 | AD61: 95074-5.27 | AE61: 已入 | AG61: =24+2976 -> 3000 | AH61: =AG61-J61 -> 0 | AK61: =J61 -> 3000 | AO61: =J61 -> 3000 | AR61: =J61 -> 3000 | AS61: =AS60+AR61 -> 54591
A62: 45728 | B62: TARGET US | C62: 美国 | D62: 4500159957 | E62: 10001255937-0581 | F62: 4500159957-10 | G62: 71152-S001 | H62: 71152-S001 | I62: 机械速龙 | J62: 10002 | K62: 0 | L62: 6 | M62: =J62/L62 -> 1667 | N62: 45770 | O62: 45766 | Q62: PASS | R62: 45803 | T62: 是 | U62: 45728 | V62: 有 | W62: 外箱正唛左上角粘贴条码箱贴纸，外箱贴纸显示DPCI#087-02-9998，来料贴纸UPC显示10193052079197； 4.外箱正唛右侧空白位置粘贴一张Event label 贴纸，由工厂自己订购。 | X62: 3/21外箱贴纸显示DPCI#087-02-9998，来料贴纸UPC显示10193052079197 | Y62: 日期码格式：ZURU INC(BVI) 标准格式 日期：按实际生产日期 | Z62: 日期码格式：ZURU INC(BVI) 标准格式 日期：按实际生产日期 Packaging Info: MA 1L包装 Remark: 1. 71152-S001-ROBO ALIVE-DINOSAUR-SERIES 1-RAPTOR-WINDOW BOX,6PCS/CTN； 2. MA 1L包装，UPC显示193052079190； 3. 外箱正唛左上角粘贴条码箱贴纸，外箱贴纸显示DPCI#087-02-9998，来料贴纸UPC显示10193052079197； 4.外箱正唛右侧空白位置粘贴一张Event label 贴纸，由工厂自己订购。 5 产品和包装上要印刷tracking code信息，格式为ZURU常规； 6 出货方式：货代自提 | AA62: Holly Zheng | AB62: 2.5407 | AC62: =AB62*J62 -> 25412.081 | AD62: ZB00353-5.28 | AE62: 已入 | AG62: =2250+4080+3672 -> 10002 | AH62: =AG62-J62 -> 0 | AJ62: =J62 -> 10002 | AO62: =J62 -> 10002 | AR62: =J62 -> 10002 | AS62: =AS61+AR62 -> 64593
A63: 45726 | B63: AMAZON UK | C63: 英国 | D63: 4500159549 | E63: Amazon UK:31XGVX7Q | F63: 4500159549-10 | G63: 71152-S001-3L | H63: 71152-S001 | I63: 机械速龙 | J63: 624 | K63: 0 | L63: 6 | M63: =J63/L63 -> 104 | N63: 45799 | O63: 45796 | Q63: PASS | R63: 45803 | T63: 否 | U63: 空白外箱 | V63: 有 | W63: 1张贴纸(UPC#+IT环保标，参考翻单PO#4500159389) | X63: 1.空白外箱（加印带Zuru字样的最新logo，除了邮包盒直接做外箱的产品） + SSCC LABEL一张, 无箱唛，MADE IN CHINA 外箱只印一正一侧 | Y63: 日期码格式：ZURU INC(BVI) 标准格式 日期：按实际生产日期 | Z63: 日期码格式：ZURU INC(BVI) 标准格式 日期：按实际生产日期 Packaging Info: Amazon UK(71152, 9561)/DE(71152, 9561) 1. 71152：6PCS WINDOW BOX/CTN; MA 3L(23L warning EAN#)A window box+1张贴纸(UPC#+IT环保标，参考翻单PO#4500159389)+MA 5L(9L warning)A 说明书 3. 最迟验货不得晚于2025/5/23; Remark: 1.空白外箱（加印带Zuru字样的最新logo，除了邮包盒直接做外箱的产品） + SSCC LABEL一张, 无箱唛，MADE IN CHINA 外箱只印一正一侧。箱唛资料按照给定的 标准去做即可，无需发回我方再行审批(新标准将另行通知)。 (SSCC LABEL竖贴在外箱正面的正中间，贴一面即可,贴纸离外箱边距必须至少3.2CM。如竖贴无法满足要求，则横贴。如横贴也无法满足要求，则竖贴，遮到ZURU lo go无影响), SSCC贴纸由工厂直接跟勤得采购或者工厂自行采购，每一张SSCC Label都是唯一且有不同流水及条码，且需要检查条码是否能正常扫描，另外，此贴纸 印刷不可出现模糊，溢出及粘胶不牢易脱落等现象，如工厂不按此要求导致贴纸有任何问题产生的罚款将由工厂承担一切责任 。 2.出往UK的产品+包装务必打上UKCA logo ，否则客人会退货且当地会有罚款。 3.订单必须经过ZURU QC验货并且通过后方可出货。 4.法国订单要求包装不使用矿物油，请按要求提供以下其中一份文件再出货 ，产品出到法国被相关部门抽检出现包装不符合此要求的，供应商需要为此承担责任， 故此请严格把关。 -油墨物质""由1 ~ 7个芳香环组成的MOAH""的包装检测报告，要求限值≤1.0%； -包装材料清单，包括包装油墨或物质的信息； -油墨制造商的证书； 5.每一批次出货只能有一个生产日期，不可多个生产日期混在同一批次出货；且邮包盒上必须统一加上日期码；外箱对于日期码没有硬性规定； 6.涉及到相关款式会有闪粉的或者微塑料的，请统一默认出无闪粉或者不含微塑料版本； 7.邮包盒及外箱封箱必须是工字型封箱方式； 8.5 Surprise or Mini Brands涉及包装是2个及2个以上的球入PVC桶包装时，单个球上若有UPC#或者EAN#，请用白色贴纸覆盖住； | AA63: Crystal Chen | AB63: 2.6352 | AC63: =AB63*J63 -> 1644.3648 | AD63: 95063R1-5.26 | AE63: 已入 | AG63: 624 | AH63: =AG63-J63 -> 0 | AL63: =J63 -> 624 | AO63: =J63 -> 624 | AR63: =J63 -> 624 | AS63: =AS62+AR63 -> 65217
A64: 45726 | B64: AMAZON UK | C64: 德国 | D64: 4500159549 | E64: Amazon DE:475LP6EN | F64: 4500159549-20 | G64: 71152-S001-3L | H64: 71152-S001 | I64: 机械速龙 | J64: 498 | K64: 0 | L64: 6 | M64: =J64/L64 -> 83 | N64: 45799 | O64: 45796 | Q64: PASS | R64: 45803 | T64: 否 | U64: 空白外箱 | V64: 有 | W64: 1张贴纸(UPC#+IT环保标，参考翻单PO#4500159389) | X64: 1.空白外箱（加印带Zuru字样的最新logo，除了邮包盒直接做外箱的产品） + SSCC LABEL一张, 无箱唛，MADE IN CHINA 外箱只印一正一侧 | Y64: 日期码格式：ZURU INC(BVI) 标准格式 日期：按实际生产日期 | Z64: 日期码格式：ZURU INC(BVI) 标准格式 日期：按实际生产日期 Packaging Info: Amazon UK(71152, 9561)/DE(71152, 9561) 1. 71152：6PCS WINDOW BOX/CTN; MA 3L(23L warning EAN#)A window box+1张贴纸(UPC#+IT环保标，参考翻单PO#4500159389)+MA 5L(9L warning)A 说明书 3. 最迟验货不得晚于2025/5/23; Remark: 1.空白外箱（加印带Zuru字样的最新logo，除了邮包盒直接做外箱的产品） + SSCC LABEL一张, 无箱唛，MADE IN CHINA 外箱只印一正一侧。箱唛资料按照给定的 标准去做即可，无需发回我方再行审批(新标准将另行通知)。 (SSCC LABEL竖贴在外箱正面的正中间，贴一面即可,贴纸离外箱边距必须至少3.2CM。如竖贴无法满足要求，则横贴。如横贴也无法满足要求，则竖贴，遮到ZURU lo go无影响), SSCC贴纸由工厂直接跟勤得采购或者工厂自行采购，每一张SSCC Label都是唯一且有不同流水及条码，且需要检查条码是否能正常扫描，另外，此贴纸 印刷不可出现模糊，溢出及粘胶不牢易脱落等现象，如工厂不按此要求导致贴纸有任何问题产生的罚款将由工厂承担一切责任 。 2.出往UK的产品+包装务必打上UKCA logo ，否则客人会退货且当地会有罚款。 3.订单必须经过ZURU QC验货并且通过后方可出货。 4.法国订单要求包装不使用矿物油，请按要求提供以下其中一份文件再出货 ，产品出到法国被相关部门抽检出现包装不符合此要求的，供应商需要为此承担责任， 故此请严格把关。 -油墨物质""由1 ~ 7个芳香环组成的MOAH""的包装检测报告，要求限值≤1.0%； -包装材料清单，包括包装油墨或物质的信息； -油墨制造商的证书； 5.每一批次出货只能有一个生产日期，不可多个生产日期混在同一批次出货；且邮包盒上必须统一加上日期码；外箱对于日期码没有硬性规定； 6.涉及到相关款式会有闪粉的或者微塑料的，请统一默认出无闪粉或者不含微塑料版本； 7.邮包盒及外箱封箱必须是工字型封箱方式； 8.5 Surprise or Mini Brands涉及包装是2个及2个以上的球入PVC桶包装时，单个球上若有UPC#或者EAN#，请用白色贴纸覆盖住； | AA64: Crystal Chen | AB64: 2.6352 | AC64: =AB64*J64 -> 1312.3296 | AD64: 95225-6.6 | AE64: 已入 | AG64: 498 | AH64: =AG64-J64 -> 0 | AL64: =J64 -> 498 | AO64: =J64 -> 498 | AR64: =J64 -> 498 | AS64: =AS63+AR64 -> 65715
A65: 45749 | B65: LLC SALUS | C65: 俄罗斯联邦 | D65: 4500162283 | F65: 4500162283-50 | G65: 71152-S001 | H65: 71152-S001 | I65: 机械速龙 | J65: 252 | K65: 0 | L65: 6 | M65: =J65/L65 -> 42 | N65: 45803 | O65: 45799 | Q65: PASS | R65: 45806 | T65: 否 | U65: 45771 | V65: 无 | W65: 45783 | Z65: 日期码格式：ZURU INC(BVI) 标准格式 日期：按实际生产日期 Packaging Info: 注意： 1. QR code 贴纸需要含item和序列号 ， 二维码部分要求尺寸大于1CM （正方形边长间于1-1.5cm），强粘不易脱落 ， 材质同进口商贴纸 ，印刷质量不低于1.5c . 2. 二维码贴纸位置要远离包装上的条码及其他二维码， 贴在背面。 3. QR code贴纸（要求每1PCS 的QR 不一样 ， 无法通过扫描核实内容）; 4. 包装上有两个条码： ZURU UPC 和 客户EAN条码 ， 不要覆盖MA 包装上的UPC 条码； 71152 ： 1L MA 包装+ 进口商贴纸（含客户EAN条码）+ QR code贴纸（要求每1PCS 的QR 不一样）， MA 说明书； Remark: 标准配比，出厂价 | AA65: Ann | AB65: 2.6717 | AC65: =AB65*J65 -> 673.2684 | AD65: 95114R1-5.29 | AE65: 已入 | AG65: 252 | AH65: =AG65-J65 -> 0 | AK65: =J65 -> 252 | AO65: =J65 -> 252 | AR65: =J65 -> 252 | AS65: =AS64+AR65 -> 65967
A66: 45749 | B66: COOP NORGE HANDEL AS - DOM | C66: 挪威 | D66: 4500162222 | E66: 32578100 | F66: 4500162222-10 | G66: 71152-S001-3L | H66: 71152-S001 | I66: 机械速龙 | J66: 750 | K66: 0 | L66: 6 | M66: =J66/L66 -> 125 | N66: 45803 | O66: 45799 | Q66: PASS | R66: 45810 | T66: 是 | U66: 45749 | V66: 无 | W66: 45777 | X66: 客版说明书翻4500161075 | Z66: 日期码格式：ZURU INC(BVI) 标准格式 日期：按实际生产日期 Packaging Info: 1.71152:MA_A EAN 3L+23L彩盒 +挪威语警语贴纸+客版说明书（翻单4500161075）； Remark: 1/产品和包装要求无硼无香，包装不能含有PVC； 2/如有微塑料，必须合规欧洲标准，闪粉也是微塑料的一种，目前仅接受三张方式1.去除，2.用可降解材料，和3.永久封印在固体； 3/此订单有第三方验货，请准备三套大货样并不迟于5-14寄出给ZURU 深圳办公室； 4/带电池出货的产品所用到的电池需要符合欧洲电池新规(EU)2023-1542； 5/工厂货号-客户货号彩盒条码-外箱条码：71152-7254580-4894680042742-10193052079197； 6/配比: | AA66: Zoe Zhou | AB66: 2.6717 | AC66: =AB66*J66 -> 2003.775 | AD66: 95224R1-6.6 | AE66: 已入 | AG66: 750 | AH66: =AG66-J66 -> 0 | AL66: =J66 -> 750 | AO66: =J66 -> 750 | AR66: =J66 -> 750 | AS66: =AS65+AR66 -> 66717
A67: 45741 | B67: Walmart Central America | C67: 萨尔瓦多 | D67: 4500161312 | E67: 5907181238 | F67: 4500161312-110 | G67: 71152-S001-3L | H67: 71152-S001 | I67: 机械速龙 | J67: 36 | K67: 0 | L67: 6 | M67: =J67/L67 -> 6 | N67: 45799 | O67: 45796 | Q67: PASS | R67: 45812 | T67: 否 | U67: 2025/4/21，用双坑 | V67: 无 | W67: UPC条码贴纸+进口商贴纸 翻单PO4500158302 | Y67: 日期码格式：ZURU INC(BVI) 标准格式 日期：按实际生产日期 | Z67: 日期码格式：ZURU INC(BVI) 标准格式 日期：按实际生产日期 Packaging Info: 8. 71152：MA 3L EAN包装+UPC条码贴纸+MA 多语说明书+进口商贴纸+箱唛，贴纸翻单PO4500158302 Remark: 1.使用双坑外箱 2.请注意产品包装条形码必须是UPC 3.无第三方验货 12. 71152：2PCS AAA BATTERIES(NOT INCLUDED) | AA67: Ever Li | AB67: 2.7663 | AC67: =AB67*J67 -> 99.5868 | AD67: 95361-6.9 | AE67: 已入 | AG67: 36 | AH67: =AG67-J67 -> 0 | AL67: =J67 -> 36 | AO67: =J67 -> 36 | AR67: =J67 -> 36 | AS67: =AS66+AR67 -> 66753
A68: 45755 | B68: Coop Danmark A/S | C68: 丹麦 | D68: 4500160515 | E68: 4508281081 | F68: 4500160515-20 | G68: 71152-S001-3L | H68: 71152-S001 | I68: 机械速龙 | J68: 600 | K68: 0 | L68: 6 | M68: =J68/L68 -> 100 | N68: 45803 | O68: 45799 | Q68: PASS | R68: 45810 | T68: 是 | U68: 45755 | V68: 无 | W68: 客版说明书翻4500161075 | X68: 客版说明书翻4500161075 | Z68: 日期码格式：ZURU INC(BVI) 标准格式 日期：按实际生产日期 Packaging Info: 4. 71152:MA_A_3L(23L warning) EAN版收彩盒+客版说明书(英语/丹麦/瑞典/芬兰/挪威/爱沙尼亚语言--客版说明书翻TAS PO#4500161075) Remark: 1. 包装如含PVC,请改为PET 2. 产品/包装要求无硼无香； 3. 出欧洲，微塑料需合规。 4.带电池出货的产品所用到的电池需要符合欧洲电池新规(EU) 2023-1542 5.关于贴纸，如果贴纸位置图的包装版本与大货不一致，请工厂提前提出。跟单会重新调整确认是否更新贴纸或调整位置图 6.产品/包装不含PFAS成分 7. ITEM-COOP ITEM-EAN-GTIN 71152-1000492500-4894680042742-10193052079197 8.比例： 9. 验货注意，警告语需要包含丹麦语 10，要求样品，寄出时间5/15前， 其它产品各2套 | AA68: Luna Lin | AB68: 2.7 | AC68: =AB68*J68 -> 1620 | AD68: 95186-6.3 | AE68: 已入 | AG68: 600 | AH68: =AG68-J68 -> 0 | AL68: =J68 -> 600 | AO68: =J68 -> 600 | AR68: =J68 -> 600 | AS68: =AS67+AR68 -> 67353
A69: 45748 | B69: AUCHAN FRANCE | C69: 法国 | D69: 4500162030 | E69: 865347 | F69: 4500162030-10 | G69: 71152-S001-3 | H69: 71152-S001 | I69: 机械速龙 | J69: 312 | K69: 0 | L69: 6 | M69: =J69/L69 -> 52 | N69: 45804 | O69: 45800 | P69: 5/27第三方 | Q69: PASS | T69: 是 | U69: 45756 | V69: 无 | W69: 45749 | X69: 客版彩卡 客版说明书(包装都翻4500160987) | Y69: DG20250520 | Z69: 日期码格式：DG20250520 日期： Packaging Info: 客版彩卡+客版说明书+1张30LWEEE声明书(不含电池版) - (包装都翻4500160987) Remark: 1. 预计5/27第三方验货，请多备料1-2套大货样； 2. 指定日期码：包装上的日期码需打在条码上方; 产品上的日期码直接打印在产品上 3. 所有包装材料不能含PVC <(>&<)> EPS材料，需改用PET，EPE，or EPP环保材料; 另外包装不要覆膜，如果一定要覆膜，就改水性光油; 表面处理，不使用 UV 清 漆，无覆膜层压，改用哑油。 4.有关胶水类的：不使用溶剂型粘合剂。 5.包装材料：需要使用FSC或PEFC认证纸张 6. 关于"包装新油墨规定"，根据法国新法规：禁止在包装印刷油墨中使用矿物油中含有的物质。 欧尚要求有关物质必须遵守以下限制: -油墨中MOAH的质量浓度(1-7个芳香环之和)≤0.1% -油墨中MOAH的质量浓度(3-7个芳香环之和)≤1PPM - MOSH油墨中的质量浓度(16 ~ 35个碳原子的总和)≤0.1% 7. 对于包装印刷, Auchan要求使用植物油，而非矿物油 8. 客户会突击检查<(>&<)>验厂，确保在本厂生产，禁止外包，一旦被发现，中止所有订单的合作 9.产品请确保符合EU微塑料法规 | AA69: Ula Zhao | AB69: 2.7663 | AC69: =AB69*J69 -> 863.0856 | AD69: 95335-6.18 | AE69: 已入 | AG69: 312 | AH69: =AG69-J69 -> 0 | AM69: =J69 -> 312 | AP69: =J69 -> 312 | AR69: =J69 -> 312 | AS69: =AS68+AR69 -> 67665
A70: 45771 | B70: ZURU Germany GMBH | C70: 德国 | D70: 4500164783 | E70: 5200006663 | F70: 4500164783-70 | G70: 71152-S001-3L | H70: 71152-S001-MTS | I70: 机械速龙 | J70: 480 | K70: 0 | L70: 6 | M70: =J70/L70 -> 80 | N70: 45804 | O70: 45800 | Q70: PASS | R70: 45804 | T70: 否 | U70: 45772 | V70: 无 | W70: 45783 | X70: 1*黑白5L（PL+HU+CZ+SK+RO)说明书/WEEE声明30L说明书纸(不带电池） | Z70: 日期码格式：ZURU INC(BVI) 标准格式 日期：按实际生产日期 Packaging Info: 7.71152： MA3L-23LEAN彩盒 + MA 5L-9L Warning说明书+1*黑白5L（PL+HU+CZ+SK+RO)说明书/WEEE声明30L说明书纸(不带电池）； Remark: 1.波兰内销单，需要通过ZURU 验货结果后才能出货 (工厂需要主动提前同ZURU QC预约验货避免延期出货造成不必要麻烦)； 2. 若有特定款有特殊外箱条码要求时,需要明确列出产品款对应的具体外箱条码号码/条码类型 (若无,可以忽略此需求) 3.所有出口欧洲的产品, 法规规定禁止在包装和共公众用的印刷品中使用矿物油中含有的物质, 包装印刷油墨中含有的MOAH/MOSH的质量浓度不能超过1%, 否则出货 到法国被抽检出现问题, 供应商需要对此负责; 4. date code: 外箱日期码要晚于或等于产品日期码，不能早于产品的日期码 5. 所有电子产品身上需要加字唛，为ZURU FRANCE 地址 (如无电子产品，或者产品布标有此地址，可忽略此信息) ZURU France 1/3, Rue d'Argenteuil 95210 SAINT-GRATIEN, FRANCE 6. 装柜时需要按照款式号码从小到大一款款依次装,避免终端仓库卸货混乱.若一个柜子涉及到几个不同国家内销单,装柜时需要一个国家装完后再装另一个国家的 产品,依次装柜,避免终端仓库因不同国家不同库位位置卸货混乱. (此点需要同工厂装柜人员强调) | AA70: Amy Xiao | AB70: 2.7663 | AC70: =AB70*J70 -> 1327.824 | AD70: 95149-5.30 | AE70: 已入 | AG70: 480 | AH70: =AG70-J70 -> 0 | AL70: =J70 -> 480 | AO70: =J70 -> 480 | AR70: =J70 -> 480 | AS70: =AS69+AR70 -> 68145
A71: 45771 | B71: SAINSBURY'S SUPERMARKET LTD | C71: 英国 | D71: 4500164063 | E71: 客户PO:待定 | F71: 4500164063-10 | G71: 71152-S001 | H71: 71152-S001 | I71: 机械速龙 | J71: 6000 | K71: 0 | L71: 6 | M71: =J71/L71 -> 1000 | N71: 45805 | O71: 45801 | Q71: PASS | R71: 45805 | T71: 否 | U71: 45771 | V71: 无 | W71: 45783 | Z71: 日期码格式：ZURU INC(BVI) 标准格式 日期：按实际生产日期 Packaging Info: MA 1L UPC 彩卡；MA说明书 Remark: "*胶带最少宽度要保证6.0CM,厚度最少0.05毫米,外箱不可以打钉/扎带；以工字型封箱； *如果重量超过5KGS，箱唛需加黄色警示图标志 ，有疑问请与ZURU跟单同事联系,十分重要！ *订单出英国，请注意检查产品及包装应带UKCA图标，包装需要显示ZURU UK LTD/ZURU France地址信息，QC同事请查核，如有问题与跟单确认。 *生产日期按实际的（法定工作日），按ZURU标准格式即可 ，但是请知悉包装日期码需要早于或者等于外箱日期码 ，不能晚于外箱日期码 *请注意所有订单都需要经过ZURU QC验货并且通过后方可出货 *产品条码以订单显示为准 ，请安排生产前先核对再生产。 *外箱上的条码请确保清晰可扫描 ，左上角的条码格式是UPC-A格式，下面14位数的条码格式是ITF-14格式，否则到目的仓无法扫描入仓由工厂承担责任 。 *所有产品按符合欧洲标准走货，微塑料需合规 。 *涉及到硼的，需要符合欧洲标准 *客户不接受PVC材质 *外箱不得使用带金属夹子或带扣" | AA71: CORA ZHOU | AB71: 2.5732 | AC71: =AB71*J71 -> 15439.2 | AD71: 95148-5.30 | AE71: 已入 | AG71: =3360+2640 -> 6000 | AH71: =AG71-J71 -> 0 | AJ71: =J71 -> 6000 | AO71: =J71 -> 6000 | AR71: =J71 -> 6000 | AS71: =AS70+AR71 -> 74145
A72: 45771 | B72: SAINSBURY'S SUPERMARKET LTD | C72: 英国 | D72: 4500164063 | E72: 客户PO:273714 0 | F72: 4500164063-20 | G72: 71152-S001 | H72: 71152-S001 | I72: 机械速龙 | J72: 1800 | K72: 0 | L72: 6 | M72: =J72/L72 -> 300 | N72: 45805 | O72: 45801 | Q72: PASS | R72: 45805 | T72: 否 | U72: 45771 | V72: 无 | W72: 45783 | Z72: 日期码格式：ZURU INC(BVI) 标准格式 日期：按实际生产日期 Packaging Info: MA 1L UPC 彩卡；MA说明书 Remark: "*胶带最少宽度要保证6.0CM,厚度最少0.05毫米,外箱不可以打钉/扎带；以工字型封箱； *如果重量超过5KGS，箱唛需加黄色警示图标志 ，有疑问请与ZURU跟单同事联系,十分重要！ *订单出英国，请注意检查产品及包装应带UKCA图标，包装需要显示ZURU UK LTD/ZURU France地址信息，QC同事请查核，如有问题与跟单确认。 *生产日期按实际的（法定工作日），按ZURU标准格式即可 ，但是请知悉包装日期码需要早于或者等于外箱日期码 ，不能晚于外箱日期码 *请注意所有订单都需要经过ZURU QC验货并且通过后方可出货 *产品条码以订单显示为准 ，请安排生产前先核对再生产。 *外箱上的条码请确保清晰可扫描 ，左上角的条码格式是UPC-A格式，下面14位数的条码格式是ITF-14格式，否则到目的仓无法扫描入仓由工厂承担责任 。 *所有产品按符合欧洲标准走货，微塑料需合规 。 *涉及到硼的，需要符合欧洲标准 *客户不接受PVC材质 *外箱不得使用带金属夹子或带扣" | AA72: CORA ZHOU | AB72: 2.6352 | AC72: =AB72*J72 -> 4743.36 | AD72: 95148-5.30 | AE72: 已入 | AG72: 1800 | AH72: =AG72-J72 -> 0 | AJ72: =J72 -> 1800 | AO72: =J72 -> 1800 | AR72: =J72 -> 1800 | AS72: =AS71+AR72 -> 75945
A73: 45723 | B73: FAMILY DOLLAR SERVICES, INC, | C73: 美国 | D73: 4500159444 | E73: 客户PO#375213 84 | F73: 4500159444-10 | G73: 71152-S003 | H73: 71152-S003 | I73: 机械速龙 | J73: 1996 | K73: 0 | L73: 4 | M73: =J73/L73 -> 499 | N73: 45806 | O73: 45803 | Q73: PASS | T73: 是 | U73: 45762 | V73: 有 | W73: 外箱箱唛正侧相邻两面粘贴产品彩色贴纸+印刷黑色标，每箱两张彩色贴纸, 彩色产品贴纸待跟单提供 | X73: 客版价格贴 | Y73: 日期码格式：ZURU INC(BVI) 标准格式 日期：2025-04-28 | Z73: 日期码格式：ZURU INC(BVI) 标准格式 日期：2025-04-28 Packaging Info: 1)最新版ZURU MA UPC包装(去掉社交媒体标志，优先1L)，出口美国。如有说明书请使用ZURU MA说明书，优先放1L英语。4pcs/CTN。 2)可移动不粘胶价格贴＄15(需要贴在彩盒上，1盒贴1张），客版价格贴以及具体位置，待跟单提供。 3)ZURU标准日期码格式：工厂城市缩写+生产年月日。此单指定日期码：DG20250428。 4) 外箱箱唛正侧相邻两面粘贴产品彩色贴纸+印刷黑色标，每箱两张彩色贴纸, 彩色产品贴纸待跟单提供。如侧唛位置放不下彩贴和唛头信息，可改为放两个正唛。 无论是正唛+侧唛或者是两个正唛，唛头信息和彩贴需放在同一个面，需要工厂根据外箱尺寸建议预估的彩贴尺寸给跟单。箱唛需排版给跟单确认。 Remark: 客户PO#37521384 客户SKU# 1096197 1) Item#71152-S003 2) 样品 产前样5套：产前样5套要求在2025/04/08前寄给深圳办公室跟单Jenny Liu，需转寄给美国客户确认，客户确认了产前样之后，会寄回一套给工厂，工厂需按照已确 认的产前样安 排大货生产。做产前样前需和跟单确认产品包装日期码和产品上日期码的打码位置+格式，要求是和大货一样的日期码，指定大货日期码为：DG20250 428)。此单客版包材"可移动不粘胶价格贴"需等客户确认产前样后才可以开始大货印刷。 大货样2套：大货样2套需在大货物料到厂后开始上线第一天寄出给深圳办公室；大货样需要同大货一个产线， 所有东西完全同大货一样, 1套我们需转寄客人审批出 货；1套跟单需留样（请尽量安排早点寄出以便客人早点批出货！） 1套样板 =一个带完整包装的恐龙 注意：彩盒需要带价格贴和指定日期码。 3) 此单无第三方验货+抽样测试，ZURU QC验货PASS后，跟单得到客户的approval之后方可安排出货 4)大货外箱材积绝对不可大于下述数据，材积只接受3%的变小；重量正负不得超过以下列出数据的5%，接受外箱以印章方式印上实际毛重。 大货外箱尺寸请保持： 38.0 x 32.0 x 23.0 cm(即14.96 x 12.60 x 9.06 inch)，材积必须不能大于0.9877CubeFeet（即0.0280CBM); 外箱毛重 4.0 LBS（即1.80 81 KGS）。 5) 大货配比： Item#71152-S003 S003-ROBO ALIVE-DINOSAUR-SERIES 1-RAPTOR-WINDOW BOX,4PCS/CTN UPC: 193052079190 Product color: White 6) 客户Family Dollar不允许少数出货，必须按照PO上的数量出货，也不允许延期，否则会有罚款。 7) 客户要求:"产品和包装不能含有PFAS 物质以及1,4 dioxane",请确保产品可以过美国标准测试。 8) 任何产品包装和日期码的变更，在收到ZURU的订单后，不管是MA包装还是客版包装，都需要及时告知跟单并在生产前重新签板留样。ZURU验货员验货以Family D ollar跟单寄给工厂的签板为准。如因工厂不及时告知变更而导致的无法出货，客诉或者罚款等，将保留对工厂追责的权利。请工厂务必重视和配合，避免任何额外 费用的产生。 | AA73: Jenny Liu/Shirley | AB73: 1.7249 | AC73: =AB73*J73 -> 3442.9004 | AD73: ZB00445-6.10 | AE73: 已入 | AG73: =J73 -> 1996 | AH73: =AG73-J73 -> 0 | AK73: =J73 -> 1996 | AO73: =J73 -> 1996 | AR73: =J73 -> 1996 | AS73: =AS72+AR73 -> 77941
A74: 45757 | B74: CARREFOUR FRANCE | C74: 法国 | D74: 4500163115 | E74: 43CHT25FRCA0392 | F74: 4500163115-10 | G74: 71152-S001-3L | H74: 71152-S001 | I74: 机械速龙 | J74: 2448 | K74: 0 | L74: 6 | M74: =J74/L74 -> 408 | N74: 45807 | O74: 45803 | Q74: PASS | T74: 是 | U74: 空白外箱，用双坑 | V74: 无 | W74: 无 | Z74: 日期码格式：ZURU INC(BVI) 标准格式 日期：按实际生产日期 Packaging Info: 71152：MA A版3L+23L EAN彩盒, MA B版5L+9L说明书+WEEE_不带电池走货 _ 说明书欧洲EN+30L Remark: 1.大货样品2套，请多备料。 2. 出口欧洲，所有产品微塑料需符合法规。 3. 产品、包装、外箱日期码需一致。 4. 空白纸箱: 在正唛（只1面）加多虚线15 x 10.5 cm ( 高x 宽) 距箱左边2cm， 距箱底 3cm，虚线内1张外箱贴纸（在checkpoint网站上订）Custeomer Service: Erica Lun Tel.+852 2995 8399/erica.lun@checkpt.com 5. 所有包装材料禁止使用PVC，需改用PET材料。 6. 要求使用双坑纸箱，外箱尺寸超出7%有350USD的罚款，请注意外箱尺寸变更不能超出7%。 7. 客人系统外箱尺寸: TY156268 71152-S001 31*28.8*42.1CM | AA74: Amber Zhang | AB74: 2.6214 | AC74: =AB74*J74 -> 6417.1872 | AD74: 95181-6.3 | AE74: 已入 | AG74: 2448 | AH74: =AG74-J74 -> 0 | AL74: =J74 -> 2448 | AO74: =J74 -> 2448 | AR74: =J74 -> 2448 | AS74: =AS73+AR74 -> 80389
A75: 45758 | B75: THE KROGER CO. | C75: 美国 | D75: 4500163428 | E75: PO#500-17176 | F75: 4500163428-10 | G75: 71152-S003 | H75: 71152-S003 | I75: 机械速龙 | J75: 408 | K75: 0 | L75: 4 | M75: =J75/L75 -> 102 | N75: 45824 | O75: 45820 | Q75: PASS | T75: 否 | U75: 45758 | V75: 无 | W75: 无 | Z75: 日期码格式：ZURU INC(BVI) 标准格式 日期：按实际生产日期 Packaging Info: 1、包装方式: MA UPC 优先1L最新版，出口美国 Remark: 2、无测试无验货要求 3、纸箱4面印ZURU LOGO + 箱唛 4、日期码请按ZURU标准版执行即可 5、ZURU OQC验货 | AA75: Vicky Wu | AB75: 2.75 | AC75: =AB75*J75 -> 1122 | AD75: ZB00668-7.7 | AE75: 已入 | AG75: 408 | AH75: =AG75-J75 -> 0 | AK75: =J75 -> 408 | AO75: =J75 -> 408 | AR75: =J75 -> 408 | AS75: =AS74+AR75 -> 80797
A76: 45758 | B76: THE KROGER CO. | C76: 美国 | D76: 4500163428 | E76: PO#600-55572 | F76: 4500163428-20 | G76: 71152-S003 | H76: 71152-S003 | I76: 机械速龙 | J76: 700 | K76: 0 | L76: 4 | M76: =J76/L76 -> 175 | N76: 45824 | O76: 45820 | Q76: PASS | T76: 否 | U76: 45758 | V76: 无 | W76: 无 | Z76: 日期码格式：ZURU INC(BVI) 标准格式 日期：按实际生产日期 Packaging Info: 1、包装方式: MA UPC 优先1L最新版，出口美国 Remark: 2、无测试无验货要求 3、纸箱4面印ZURU LOGO + 箱唛 4、日期码请按ZURU标准版执行即可 5、ZURU OQC验货 | AA76: Vicky Wu | AB76: 2.75 | AC76: =AB76*J76 -> 1925 | AD76: ZB00686-7.8 | AE76: 已入 | AG76: =700 -> 700 | AH76: =AG76-J76 -> 0 | AK76: =J76 -> 700 | AO76: =J76 -> 700 | AR76: =J76 -> 700 | AS76: =AS75+AR76 -> 81497
A77: 45811 | B77: FAMILY DOLLAR SERVICES, INC, | C77: 美国 | D77: 4500159444 | E77: 客户PO#375213 84 | F77: 4500159444-20 | G77: 71152-S003 | H77: 71152-S003 | I77: 机械速龙 | J77: 28804 | K77: 0 | L77: 4 | M77: =J77/L77 -> 7201 | N77: 45806 | O77: 45803 | Q77: PASS | T77: 是 | U77: 45762 | V77: 有 | W77: 外箱箱唛正侧相邻两面粘贴产品彩色贴纸+印刷黑色标，每箱两张彩色贴纸, 彩色产品贴纸待跟单提供 | X77: 客版价格贴 | Y77: 日期码格式：ZURU INC(BVI) 标准格式 日期：2025-04-28 | Z77: 日期码格式：ZURU INC(BVI) 标准格式 日期：2025-04-28 Packaging Info: 1)最新版ZURU MA UPC包装(去掉社交媒体标志，优先1L)，出口美国。如有说明书请使用ZURU MA说明书，优先放1L英语。4pcs/CTN。 2)可移动不粘胶价格贴＄15(需要贴在彩盒上，1盒贴1张），客版价格贴以及具体位置，待跟单提供。 3)ZURU标准日期码格式：工厂城市缩写+生产年月日。此单指定日期码：DG20250428。 4) 外箱箱唛正侧相邻两面粘贴产品彩色贴纸+印刷黑色标，每箱两张彩色贴纸, 彩色产品贴纸待跟单提供。如侧唛位置放不下彩贴和唛头信息，可改为放两个正唛。 无论是正唛+侧唛或者是两个正唛，唛头信息和彩贴需放在同一个面，需要工厂根据外箱尺寸建议预估的彩贴尺寸给跟单。箱唛需排版给跟单确认。 Remark: 客户PO#37521384 客户SKU# 1096197 1) Item#71152-S003 2) 样品 产前样5套：产前样5套要求在2025/04/08前寄给深圳办公室跟单Jenny Liu，需转寄给美国客户确认，客户确认了产前样之后，会寄回一套给工厂，工厂需按照已确 认的产前样安 排大货生产。做产前样前需和跟单确认产品包装日期码和产品上日期码的打码位置+格式，要求是和大货一样的日期码，指定大货日期码为：DG20250 428)。此单客版包材"可移动不粘胶价格贴"需等客户确认产前样后才可以开始大货印刷。 大货样2套：大货样2套需在大货物料到厂后开始上线第一天寄出给深圳办公室；大货样需要同大货一个产线， 所有东西完全同大货一样, 1套我们需转寄客人审批出 货；1套跟单需留样（请尽量安排早点寄出以便客人早点批出货！） 1套样板 =一个带完整包装的恐龙 注意：彩盒需要带价格贴和指定日期码。 3) 此单无第三方验货+抽样测试，ZURU QC验货PASS后，跟单得到客户的approval之后方可安排出货 4)大货外箱材积绝对不可大于下述数据，材积只接受3%的变小；重量正负不得超过以下列出数据的5%，接受外箱以印章方式印上实际毛重。 大货外箱尺寸请保持： 38.0 x 32.0 x 23.0 cm(即14.96 x 12.60 x 9.06 inch)，材积必须不能大于0.9877CubeFeet（即0.0280CBM); 外箱毛重 4.0 LBS（即1.80 81 KGS）。 5) 大货配比： Item#71152-S003 S003-ROBO ALIVE-DINOSAUR-SERIES 1-RAPTOR-WINDOW BOX,4PCS/CTN UPC: 193052079190 Product color: White 6) 客户Family Dollar不允许少数出货，必须按照PO上的数量出货，也不允许延期，否则会有罚款。 7) 客户要求:"产品和包装不能含有PFAS 物质以及1,4 dioxane",请确保产品可以过美国标准测试。 8) 任何产品包装和日期码的变更，在收到ZURU的订单后，不管是MA包装还是客版包装，都需要及时告知跟单并在生产前重新签板留样。ZURU验货员验货以Family D ollar跟单寄给工厂的签板为准。如因工厂不及时告知变更而导致的无法出货，客诉或者罚款等，将保留对工厂追责的权利。请工厂务必重视和配合，避免任何额外 费用的产生。 | AA77: Jenny Liu/Shirley | AB77: 1.5341 | AC77: =AB77*J77 -> 44188.216 | AD77: ZB00445-6.10/ZB00449-6.11/ZB00464-6.13 | AE77: 已入 | AG77: =J77 -> 28804 | AH77: =AG77-J77 -> 0 | AK77: =J77 -> 28804 | AO77: =J77 -> 28804 | AR77: =J77 -> 28804 | AS77: =AS76+AR77 -> 110301
A78: 45757 | B78: CARREFOUR FRANCE | C78: 法国 | D78: 4500163123 | E78: 43CHT25FRCA0399 | F78: 4500163123-10 | G78: 71152-S001-3L | H78: 71152-S001 | I78: 机械速龙 | J78: 1548 | K78: 0 | L78: 6 | M78: =J78/L78 -> 258 | N78: 45807 | O78: 45803 | Q78: PASS | T78: 是 | U78: 空白外箱，用双坑 | V78: 无 | W78: 无 | Z78: 日期码格式：ZURU INC(BVI) 标准格式 日期：按实际生产日期 Packaging Info: 71152：MA A版3L+23LEAN彩盒, MA B版5L+9L说明书+WEEE_不带电池走货 _ 说明书欧洲EN+30L Remark: 1.大货样品2套，请多备料。 2. 出口欧洲，所有产品微塑料需符合法规。 3. 产品、包装、外箱日期码需一致。 4. 空白纸箱: 在正唛（只1面）加多虚线15 x 10.5 cm ( 高x 宽) 距箱左边2cm， 距箱底 3cm，虚线内1张外箱贴纸（在checkpoint网站上订）Custeomer Service: Erica Lun Tel.+852 2995 8399/erica.lun@checkpt.com 5. 所有包装材料禁止使用PVC，需改用PET材料。 6. 要求使用双坑纸箱，外箱尺寸超出7%有350USD的罚款，请注意外箱尺寸变更不能超出7%。 7. 客人系统外箱尺寸: TY156268 71152-S001 31*28.8*42.1CM | AA78: Amber Zhang | AB78: 2.6352 | AC78: =AB78*J78 -> 4079.2896 | AD78: 95303-6.14 | AE78: 已入 | AG78: 1548 | AH78: =AG78-J78 -> 0 | AL78: =J78 -> 1548 | AO78: =J78 -> 1548 | AR78: =J78 -> 1548 | AS78: =AS77+AR78 -> 111849
A79: 45771 | B79: ARGOS LIMITED | C79: 英国 | D79: 4500164539 | E79: 253912 | F79: 4500164539-50 | G79: 71152-S001 | H79: 71152-S001 | I79: 机械速龙 | J79: 1932 | K79: 0 | L79: 6 | M79: =J79/L79 -> 322 | N79: 45807 | O79: 45803 | Q79: PASS | T79: 否 | U79: 45776 | V79: 无 | W79: 45776 | Z79: 日期码格式：ZURU INC(BVI) 标准格式 日期：按实际生产日期 Packaging Info: 71152 1.MA 1L UPC 最新全套包装+客人白色Cat.label 1张覆盖ZURU条码+WEEE不带电池走货欧洲30语通用黑白说明书 2.注意Cat.label （要求易撕类贴纸，但是粘性不能过低），同时此贴纸每个订单都是不相同的（会显示客户对应的订单号），切勿翻旧订单购买。此贴纸由ZURU 提供贴纸图稿和贴纸位置图给工厂后，工厂自行购买。 3.请先检查条码是否正确再安排做，标签上的目录编号数字（5799598）高度必须至少为5mm （14.17pt） 71152条码扫描结果应为：7729528 -此订单对应客户5个PO号 ，备注有显示 ，注意分开做货/验货/装柜，混装有罚款。 Remark: *MA包装按最新版本安排即可(只要MA包装上含英文信息就可以)。 *包装日期码按ZURU格式即可，请确保不迟于外箱日期码，可等于或者早于外箱日期码，必须为法定工作日。 *外箱尺寸任何一条边长度超过75cm或者每箱重量超过10KG，需要在外箱上加三脚架符号，有问题请与ZURU跟单同事核实。 *订单必须经过ZURU QC验货并且通过后方可出货。 *订单出英国，请注意检查产品及包装应带UKCA图标，包装显示ZURU UK LTD信息，QC同事请查核，如有问题与跟单确认。 *条码扫描会显示客户7位数产品号而不是客户的订单号码。 *标签上的目录编号数字高度必须至少为5mm （14.17pt）。 *所有产品按符合欧洲标准走货，需要是不含微塑料版本 。 *若任何产品涉及到硼的，请使用低硼版本(没有则忽略此要求) *客户不接受PVC材质包装。 *外箱不得使用带金属夹子或带扣。 | AA79: Ina Song | AB79: 2.6352 | AC79: =AB79*J79 -> 5091.2064 | AD79: 95285-6.12 | AE79: 已入 | AG79: 1932 | AH79: =AG79-J79 -> 0 | AK79: =J79 -> 1932 | AO79: =J79 -> 1932 | AR79: =J79 -> 1932 | AS79: =AS78+AR79 -> 113781
A80: 45776 | B80: G.T. WHOLESALE LIMITED | C80: 加拿大 | D80: 4500165391 | E80: 2924726-00 | F80: 4500165391-10 | G80: 71152-S001-3L | H80: 71152-S001 | I80: 机械速龙 | J80: 1950 | K80: 0 | L80: 6 | M80: =J80/L80 -> 325 | N80: 45807 | O80: 45803 | Q80: PASS | T80: 是 | U80: 45777 | V80: 无 | W80: 45785 | Z80: 日期码格式： 标准格式 日期：按实际生产日期 Packaging Info: 71152 MA 多语EAN+UPC贴纸，UPC号码 193052079190 Remark: 出口加拿大， 有 进口商贴纸 5/23前寄出大货样2套 Zuru验货 需要单个产品称重的图片和整箱产品称重的图片，还需要产品上made in China的晒字图片，包装上的警告语的清晰图片，以及单个产品的尺寸测量图片 和外箱的尺寸测量图片 日期跟踪码：产品外包装必须有日期跟踪码，ZURU标准格式日期码 | AA80: Summer Mo | AB80: 2.5407 | AC80: =AB80*J80 -> 4954.365 | AD80: 95223-6.6 | AE80: 已入 | AG80: =324+1626 -> 1950 | AH80: =AG80-J80 -> 0 | AL80: =J80 -> 1950 | AO80: =J80 -> 1950 | AR80: =J80 -> 1950 | AS80: =AS79+AR80 -> 115731
A81: 45764 | B81: ZURU France | C81: 法国 | D81: 4500163334 | E81: 5200006584 | F81: 4500163334-40 | G81: 71152-S001-3L | H81: 71152-S001-MTS | I81: 机械速龙 | J81: 744 | K81: 0 | L81: 6 | M81: =J81/L81 -> 124 | N81: 45808 | O81: 45804 | Q81: PASS | T81: 否 | U81: 45768 | V81: 无 | W81: 一张意大利环保标贴纸+ 多语版WEEE电池垃圾桶的回收声明说明书（not included）（贴纸和WEEE翻 4500162314） | Z81: 日期码格式：ZURU INC(BVI) 标准格式 日期：按实际生产日期 Packaging Info: 71152:最新MA 3L EAN（23L warning）彩盒+最新MA 5L说明书+ 一张意大利环保标贴纸+ 多语版WEEE电池垃圾桶的回收声明说明书（not included）（贴纸和WEEE翻 4500162314） Remark: 1. 法国国家内销单，需要通过ZURU 验货结果后才能出货 (工厂需要主动提前同ZURU QC预约验货避免延期出货造成不必要麻烦)； 2. 本订单所有 具有 baby items / assorted items 的款式，零售包装上都要用 母 EAN; 3. 若有特定款有特殊外箱条码要求时,需要明确列出产品款对应的具体外箱条码号码/条码类型 (若无,可以忽略此需求) 4. 所有出口欧洲的产品, 法规规定禁止在包装和共公众用的印刷品中使用矿物油中含有的物质, 包装印刷油墨中含有的MOAH/MOSH的质量浓度不能超过1%, 否则出 货到法国被抽检出现问题, 供应商需要对此负责; 5. Date code: 外箱/产品/包装 保持一致，完货后提供date code 信息以便我们保存记录做批次管理; 6. 装柜时需要按照款式号码从小到大一款款依次装,避免终端仓库卸货混乱.若一个柜子涉及到几个不同国家内销单,装柜时需要一个国家装完后再装另一个国家的 产品,依次装柜,避免终端仓库因不同国家不同库位位置卸货混乱. (此点需要同工厂装柜人员强调) | AA81: SD83 | AB81: 2.7663 | AC81: =AB81*J81 -> 2058.1272 | AD81: 95292-6.10 | AE81: 已入 | AG81: 744 | AH81: =AG81-J81 -> 0 | AL81: =J81 -> 744 | AO81: =J81 -> 744 | AR81: =J81 -> 744 | AS81: =AS80+AR81 -> 116475
A82: 45765 | B82: MAGGIO 3 SRL | C82: 意大利 | D82: 4500163950 | F82: 4500163950-60 | G82: 71152-S001-3L | H82: 71152-S001 | I82: 机械速龙 | J82: 1200 | K82: 0 | L82: 6 | M82: =J82/L82 -> 200 | N82: 45810 | O82: =N82-4 -> 45806 | Q82: PASS | T82: 否 | U82: 45777 | V82: 无 | W82: 45784 | Z82: 日期码格式：ZURU INC(BVI) 标准格式 日期：按实际生产日期 Packaging Info: 71152:MA 最新 3L彩盒含EAN条码+进口商含意大利环保标贴纸+MA最新5L+9L说明书 Remark: 1.此单出意大利，需满足EU测试标准要求<(>&<)> 微塑料需符合法规，如果有slime等化学品需要不含硼 2.需保证按期完货，延期罚款。 3.贴纸切勿盖住意大利警告语文字(QC 务必检查），特别是产品包装比较小的,如果会挡住产品上的警示语信息，在做大货前工厂需要提前告知跟单位置图是否OK， 需再次确认才能安排生产大货。 4. 标准配比 5. 需要ZURU OQC 验货， 需提供验货图片给到客户放货。 | AA82: Mary Zhong | AB82: 2.6352 | AC82: =AB82*J82 -> 3162.24 | AD82: 95665-7.17 | AE82: 已入 | AG82: 1200 | AH82: =AG82-J82 -> 0 | AL82: =J82 -> 1200 | AO82: =J82 -> 1200 | AR82: =J82 -> 1200 | AS82: =AS81+AR82 -> 117675
A83: 45763 | B83: NORWEGIAN TOY IMPORT AS - DOM | C83: 挪威 | D83: 4500163205 | E83: 14675. | F83: 4500163205-110 | G83: 71152-S001-3L | H83: 71152-S001 | I83: 机械速龙 | J83: 708 | K83: 0 | L83: 6 | M83: =J83/L83 -> 118 | N83: 45811 | O83: 45807 | Q83: PASS | T83: 否 | U83: 45763 | V83: 无 | W83: 45789 | X83: 客版说明书（翻单4500161075） | Z83: 日期码格式：ZURU INC(BVI) 标准格式 日期：按实际生产日期 Packaging Info: 71152：MA-A EAN 3L+23L彩盒+进口商贴纸+客版说明书（翻单4500161075） Remark: 1/配比： 2/产品和包装要求无硼无香，包装不能含有PVC; 如有微塑料，必须合规欧洲标准，闪粉也是微塑料的一种，目前仅接受三张方式1.去除，2.用可降解材料，和3. 永久封印在固体。 3/带电池出货的产品,电池需要符合欧洲电池新规(EU) 2023-1542. | AA83: Zoe Zhou | AB83: 2.7663 | AC83: =AB83*J83 -> 1958.5404 | AD83: 95231-6.6 | AE83: 已入 | AG83: 708 | AH83: =AG83-J83 -> 0 | AL83: =J83 -> 708 | AO83: =J83 -> 708 | AR83: =J83 -> 708 | AS83: =AS82+AR83 -> 118383
A84: 45748 | B84: AUCHAN FRANCE | C84: 法国 | D84: 4500162014 | E84: 865344 | F84: 4500162014-10 | G84: 71152-S001-3 | H84: 71152-S001 | I84: 机械速龙 | J84: 312 | K84: 0 | L84: 6 | M84: =J84/L84 -> 52 | N84: 45813 | O84: 45810 | P84: 6/5第三方 | Q84: PASS | T84: 是 | U84: 45756 | V84: 无 | W84: 无 | X84: 客版彩卡+客版说明书(包装都翻4500160987) | Y84: DG20250527 | Z84: 日期码格式：DG20250527 日期： Packaging Info: 客版彩卡+客版说明书+1张30LWEEE声明书(不含电池版) - (包装都翻4500160987) Remark: 1. 预计6/5第三方验货，请多备料1-2套大货样； 2. 指定日期码：包装上的日期码需打在条码上方; 产品上的日期码直接打印在产品上 3. 所有包装材料不能含PVC <(>&<)> EPS材料，需改用PET，EPE，or EPP环保材料; 另外包装不要覆膜，如果一定要覆膜，就改水性光油; 表面处理，不使用 UV 清 漆，无覆膜层压，改用哑油。 4.有关胶水类的：不使用溶剂型粘合剂。 5.包装材料：需要使用FSC或PEFC认证纸张 6. 关于"包装新油墨规定"，根据法国新法规：禁止在包装印刷油墨中使用矿物油中含有的物质。 欧尚要求有关物质必须遵守以下限制: -油墨中MOAH的质量浓度(1-7个芳香环之和)≤0.1% -油墨中MOAH的质量浓度(3-7个芳香环之和)≤1PPM - MOSH油墨中的质量浓度(16 ~ 35个碳原子的总和)≤0.1% 7. 对于包装印刷, Auchan要求使用植物油，而非矿物油 8. 客户会突击检查<(>&<)>验厂，确保在本厂生产，禁止外包，一旦被发现，中止所有订单的合作 9.产品请确保符合EU微塑料法规 | AA84: Ula Zhao | AB84: 2.7663 | AC84: =AB84*J84 -> 863.0856 | AD84: 95334-6.18 | AE84: 已入 | AG84: 312 | AH84: =AG84-J84 -> 0 | AM84: =J84 -> 312 | AP84: =J84 -> 312 | AR84: =J84 -> 312 | AS84: =AS83+AR84 -> 118695
A85: 45765 | B85: Jouets Broze Fils S.A. | C85: 比利时 | D85: 4500164137 | E85: ZURZUR0120250414 | F85: 4500164137-10 | G85: 71152-S001-3L | H85: 71152-S001 | I85: 机械速龙 | J85: 300 | K85: 0 | L85: 6 | M85: =J85/L85 -> 50 | N85: 45813 | O85: 45810 | Q85: PASS | T85: 否 | U85: 45765 | V85: 无 | W85: 无 | Z85: 日期码格式：ZURU INC(BVI) 标准格式 日期：按实际生产日期 Packaging Info: 71152：MA A版3L+23L EAN彩盒, MA B版5L+9L说明书+WEEE_不带电池走货 _ 说明书欧洲EN+30L Remark: 1.大于10*10 cm的MA塑料袋必须有德语/法语/荷兰语/英语的警告语，印刷内容请与跟单确认(如MA包装没有塑料袋，可以忽略此点) 2.出欧洲，微塑料需合规（如item本身不含微塑料，则忽略此要求） 3.外箱需要印条码，请确保条码可以清晰扫描，且条码内容正确 4.STD配比 5.所有出往欧洲市场订单的电子产品需增加一张WEEE声明说明书，区分带电池和不带电池版本, 如已做客版说明书可忽略此要求。 | AA85: Amber Zhang | AB85: 2.8404 | AC85: =AB85*J85 -> 852.12 | AD85: 95235-6.7 | AE85: 已入 | AG85: 300 | AH85: =AG85-J85 -> 0 | AL85: =J85 -> 300 | AO85: =J85 -> 300 | AR85: =J85 -> 300 | AS85: =AS84+AR85 -> 118995
A86: 45768 | B86: NORDIC TOY TEAM AS - DOM | C86: 挪威 | D86: 4500164402 | E86: 1310 | F86: 4500164402-10 | G86: 71152-S001-3L-1 | H86: 71152-S001 | I86: 机械速龙 | J86: 2004 | K86: 0 | L86: 6 | M86: =J86/L86 -> 334 | N86: 45814 | O86: 45810 | Q86: PASS | T86: 否 | U86: 45768 | V86: 无 | W86: 45786 | X86: 客版说明书（翻单4500161075 | Z86: 日期码格式：ZURU INC(BVI) 标准格式 日期：按实际生产日期 Packaging Info: 71152: MA-A EAN 3L+23L彩盒+客版说明书(翻单4500161075)+进口商贴纸 Remark: 1/产品和包装要求无硼无香，包装不能含有PVC 2/如有微塑料，必须合规欧洲标准，闪粉也是微塑料的一种，目前仅接受三张方式1.去除，2.用可降解材料，和3.永久封印在固体。 3/带电池出货的产品，所用到的电池需要符合欧洲电池新规(EU)2023-1542 4/产品配比 | AA86: Zoe Zhou | AB86: 2.5269 | AC86: =AB86*J86 -> 5063.9076 | AD86: 95230R1-6.6 | AE86: 已入 | AG86: 2004 | AH86: =AG86-J86 -> 0 | AL86: =J86 -> 2004 | AP86: =J86 -> 2004 | AR86: =J86 -> 2004 | AS86: =AS85+AR86 -> 120999
A87: 45765 | B87: Indeks Retail A/S | C87: 丹麦 | D87: 4500164118 | E87: 253501 | F87: 4500164118-20 | G87: 71152-S001-3L-1 | H87: 71152-S001 | I87: 机械速龙 | J87: 546 | K87: 0 | L87: 6 | M87: =J87/L87 -> 91 | N87: 45814 | O87: 45810 | Q87: PASS | T87: 否 | U87: 45775 | V87: 无 | W87: 无 | X87: 客版说明书翻TAS PO#4500161075) | Z87: 日期码格式：ZURU INC(BVI) 标准格式 日期：按实际生产日期 Packaging Info: 2. 71152-S001: MA_A_3L(23L warning) EAN版收缩膜+客版说明书(英语/丹麦/瑞典/芬兰/挪威/爱沙尼亚语言--客版说明书翻TAS PO#4500161075) Remark: 1. 包装如含PVC,请改为PET 2. 产品/包装要求无硼无香； 3. 出欧洲，微塑料需合规。 4.带电池出货的产品所用到的电池需要符合欧洲电池新规(EU) 2023-1542 5.关于贴纸，如果贴纸位置图的包装版本与大货不一致，请工厂提前提出。跟单会重新调整确认是否更新贴纸或调整位置图 6.产品/包装不含PFAS成分 7. 产品条码如下: 请先检查条码是否正确再安排做货，如有问题请告知: 71152-S001:4894680042742 | AA87: Sheba | AB87: 2.7663 | AC87: =AB87*J87 -> 1510.3998 | AD87: 95319-6.16 | AE87: 已入 | AG87: 546 | AH87: =AG87-J87 -> 0 | AL87: =J87 -> 546 | AP87: =J87 -> 546 | AR87: =J87 -> 546 | AS87: =AS86+AR87 -> 121545
A88: 45750 | B88: ESAL ENTERPRISES FZC | C88: 卡塔尔 | D88: 4500162472 | E88: QATAR | F88: 4500162472-30 | G88: 71152-S001 | H88: 71152-S001 | I88: 机械速龙 | J88: 480 | K88: 0 | L88: 6 | M88: =J88/L88 -> 80 | N88: 45805 | O88: 45801 | Q88: PASS | T88: 否 | U88: 45762 | V88: 无 | W88: 45770 | Z88: 日期码格式：ZURU INC(BVI) 标准格式 日期：按实际生产日期 Packaging Info: 71152：MA+进口商贴纸+说明书（加贴纸） Remark: | AA88: Lena Huang | AB88: 2.7663 | AC88: =AB88*J88 -> 1327.824 | AD88: 95384-6.23 | AE88: 已入 | AG88: 480 | AH88: =AG88-J88 -> 0 | AK88: =J88 -> 480 | AO88: =J88 -> 480 | AR88: =J88 -> 480 | AS88: =AS87+AR88 -> 122025
A89: 45750 | B89: ESAL TRADING L.L.C. | C89: 阿拉伯联合酋长国 | D89: 4500162345 | F89: 4500162345-50 | G89: 71152-S001 | H89: 71152-S001 | I89: 机械速龙 | J89: 960 | K89: 0 | L89: 6 | M89: =J89/L89 -> 160 | N89: 45805 | O89: 45801 | Q89: PASS | T89: 否 | U89: 45762 | V89: 无 | W89: 45770 | Z89: 日期码格式：ZURU INC(BVI) 标准格式 日期：按实际生产日期 Packaging Info: 71152：MA+进口商贴纸+说明书（加贴纸） Remark: | AA89: Lena Huang | AB89: 2.7663 | AC89: =AB89*J89 -> 2655.648 | AD89: 95349-6.19 | AE89: 已入 | AG89: 960 | AH89: =AG89-J89 -> 0 | AK89: =J89 -> 960 | AO89: =J89 -> 960 | AR89: =J89 -> 960 | AS89: =AS88+AR89 -> 122985
A90: 45784 | B90: Multihexa Sdn Bhd | C90: 马来西亚 | D90: 4500165640 | F90: 4500165640-10 | G90: 71152-S001 | H90: 71152-S001 | I90: 机械速龙 | J90: 204 | K90: 0 | L90: 6 | M90: =J90/L90 -> 34 | N90: 45818 | O90: 45814 | Q90: PASS | T90: 否 | U90: 45786 | V90: 无 | W90: 71152进口商贴纸图稿、位置图也翻单4500158287 | Z90: 日期码格式：ZURU INC(BVI) 标准格式 日期：按实际生产日期 Packaging Info: 1. 71152,77673-MA UPC包装（优先1L)+1张进口商贴纸。71152进口商贴纸图稿、位置图翻单4500158287. 3.因为此客人进口商贴纸是通用的，只可能因为item不同尺寸会有差别，如果发现尺寸一样就请统一订购节省成本。 Remark: 71152-2PCS AAA BATTERIES(NOT INCLUDED) | AA90: Emma Wu | AB90: 2.6717 | AC90: =AB90*J90 -> 545.0268 | AD90: 95362R1-6.11 | AE90: 已入 | AG90: 204 | AH90: =AG90-J90 -> 0 | AK90: =J90 -> 204 | AO90: =J90 -> 204 | AR90: =J90 -> 204 | AS90: =AS89+AR90 -> 123189
A91: 45741 | B91: MEIJER DISTRIBUTION, INC. | C91: 美国 | D91: 4500161652 | E91: 客户PO#：2168 88486 | F91: 4500161410-20 | G91: 71152-S003 | H91: 71152-S003 | I91: 机械速龙 | J91: 688 | K91: 0 | L91: 4 | M91: =J91/L91 -> 172 | N91: 45818 | O91: 45814 | Q91: PASS | T91: 否 | U91: 45757 | V91: 无 | W91: 无 | Y91: 日期码格式：ZURU INC(BVI) 标准格式 日期：按实际生产日期 | Z91: 日期码格式：ZURU INC(BVI) 标准格式 日期： Packaging Info: 1. MA 1L 包装 2. 客人指定箱唛排版 Remark: 出货前 Zuru QC 验货 | AA91: Cherie Li | AB91: 2.65 | AC91: =AB91*J91 -> 1823.2 | AD91: ZB00446-6.10 | AE91: 已入 | AG91: 688 | AH91: =AG91-J91 -> 0 | AK91: =J91 -> 688 | AO91: =J91 -> 688 | AR91: =J91 -> 688 | AS91: =AS90+AR91 -> 123877
A92: 45741 | B92: MEIJER DISTRIBUTION, INC. | C92: 美国 | D92: 4500161655 | E92: 客户PO#:21688 8488 | F92: 4500161411-20 | G92: 71152-S003 | H92: 71152-S003 | I92: 机械速龙 | J92: 372 | K92: 0 | L92: 4 | M92: =J92/L92 -> 93 | N92: 45818 | O92: 45814 | Q92: PASS | T92: 否 | U92: 45757 | V92: 无 | W92: 无 | Y92: 日期码格式：ZURU INC(BVI) 标准格式 日期：按实际生产日期 | Z92: 日期码格式：ZURU INC(BVI) 标准格式 日期： Packaging Info: 1. MA 1L 包装 2. 客人指定箱唛排版 Remark: 出货前 Zuru QC 验货 | AA92: Cherie Li | AB92: 2.65 | AC92: =AB92*J92 -> 985.8 | AD92: ZB00444-6.10 | AE92: 已入 | AG92: 372 | AH92: =AG92-J92 -> 0 | AK92: =J92 -> 372 | AO92: =J92 -> 372 | AR92: =J92 -> 372 | AS92: =AS91+AR92 -> 124249
A93: 45735 | B93: MILLS FLEET FARM | C93: 美国 | D93: 4500160726 | E93: PO#4647603 | F93: 4500160726-220 | G93: 71152-S001 | H93: 71152-S001 | I93: 机械速龙 | J93: 594 | K93: 0 | L93: 6 | M93: =J93/L93 -> 99 | N93: 45818 | O93: 45814 | Q93: PASS | T93: 否 | U93: 45742 | V93: 有 | W93: 45742 | Y93: 日期码格式：ZURU INC(BVI) 标准格式 日期：按实际生产日期 | Z93: 日期码格式：ZURU INC(BVI) 标准格式 日期：按实际生产日期 Packaging Info: 1. 包材：ZURU 最新 MA 1L UPC 版本，出口美国;| Remark: 2.日期跟踪码：产品包装及产品本身都必须有日期跟踪码，并且确保两者的日期跟踪码要一致；ZURU标准格式日期码(请自行调整具体年月日生产期，但不能为末). 3. 此单不同客户PO对应不同交期，PO详情看侧边remark ，交期请看PO上面的delivery date； 4. 外箱贴纸(请务必先发箱唛排版给跟单确认后再做印刷) 5. 出货配比：ZURU 标版配比 | AA93: Mila Yao | AB93: 2.7663 | AC93: =AB93*J93 -> 1643.1822 | AD93: ZB00470R1-6.14 | AE93: 已入 | AG93: 594 | AH93: =AG93-J93 -> 0 | AK93: =J93 -> 594 | AO93: =J93 -> 594 | AR93: =J93 -> 594 | AS93: =AS92+AR93 -> 124843
A94: 45748 | B94: AUCHAN FRANCE | C94: 法国 | D94: 4500161701 | E94: 864867 | F94: 4500161701-10 | G94: 71152-S001-3 | H94: 71152-S001 | I94: 机械速龙 | J94: 378 | K94: 0 | L94: 6 | M94: =J94/L94 -> 63 | N94: 45817 | O94: 45813 | Q94: PASS | R94: 6/10第三方+抽板 | T94: 是 | U94: 45756 | V94: 无 | W94: 无 | X94: 客版彩卡+客版说明书(包装都翻4500160987) | Y94: DG20250522 | Z94: 日期码格式：DG20250522 日期：05-22-2025 Packaging Info: 71152：客版彩卡+客版说明书+1张30LWEEE声明书(不含电池版) - (包装都翻4500160987) Remark: 1. 预计6/10第三方验货+抽板测试，请多备料； 2. 日期码：包装上的日期码需打在条码上方; 产品上的日期码直接打印在产品上 3. 所有包装材料不能含PVC <(>&<)> EPS材料，需改用PET，EPE，or EPP环保材料; 另外包装不要覆膜，如果一定要覆膜，就改水性光油; 表面处理，不使用 UV 清 漆，无覆膜层压，改用哑油。 4.有关胶水类的：不使用溶剂型粘合剂。 5.包装材料：需要使用FSC或PEFC认证纸张 6. 关于"包装新油墨规定"，根据法国新法规：禁止在包装印刷油墨中使用矿物油中含有的物质。 欧尚要求有关物质必须遵守以下限制: -油墨中MOAH的质量浓度(1-7个芳香环之和)≤0.1% -油墨中MOAH的质量浓度(3-7个芳香环之和)≤1PPM - MOSH油墨中的质量浓度(16 ~ 35个碳原子的总和)≤0.1% 7. 对于包装印刷, Auchan要求使用植物油，而非矿物油 8. 客户会突击检查<(><<)>(><(>&<)><(><<)>)>验厂，确保在本厂生产，禁止外包，一旦被发现，中止所有订单的合作 | AA94: Ula Zhao | AB94: 2.7663 | AC94: =AB94*J94 -> 1045.6614 | AD94: 95422-6.26 | AE94: 已入 | AG94: 378 | AH94: =AG94-J94 -> 0 | AM94: =J94 -> 378 | AP94: =J94 -> 378 | AR94: =J94 -> 378 | AS94: =AS93+AR94 -> 125221
A95: 45748 | B95: AUCHAN FRANCE | C95: 法国 | D95: 4500160987 | E95: 864883 | F95: 4500160987-10 | G95: 71152-S001-3 | H95: 71152-S001 | I95: 机械速龙 | J95: 312 | K95: 0 | L95: 6 | M95: =J95/L95 -> 52 | N95: 45817 | O95: 45813 | Q95: PASS | R95: 6/10第三方+抽板 | T95: 是 | U95: 45756 | V95: 无 | W95: 无 | X95: 客版彩卡+客版说明书(包装都翻4500160987) | Y95: DG20250522 | Z95: 日期码格式：DG20250522 日期：05-22-2025 Packaging Info: 客版彩卡+客版说明书+1张30LWEEE声明书(不含电池版) - (包装都翻4500160987) Remark: 1. 预计6/10第三方验货+抽板测试，请多备料； 2. 日期码：包装上的日期码需打在条码上方; 产品上的日期码直接打印在产品上 3. 所有包装材料不能含PVC <(>&<)> EPS材料，需改用PET，EPE，or EPP环保材料; 另外包装不要覆膜，如果一定要覆膜，就改水性光油; 表面处理，不使用 UV 清 漆，无覆膜层压，改用哑油。 4.有关胶水类的：不使用溶剂型粘合剂。 5.包装材料：需要使用FSC或PEFC认证纸张 6. 关于"包装新油墨规定"，根据法国新法规：禁止在包装印刷油墨中使用矿物油中含有的物质。 欧尚要求有关物质必须遵守以下限制: -油墨中MOAH的质量浓度(1-7个芳香环之和)≤0.1% -油墨中MOAH的质量浓度(3-7个芳香环之和)≤1PPM - MOSH油墨中的质量浓度(16 ~ 35个碳原子的总和)≤0.1% 7. 对于包装印刷, Auchan要求使用植物油，而非矿物油 8. 客户会突击检查<(><<)>(><(>&<)><(><<)>)>验厂，确保在本厂生产，禁止外包，一旦被发现，中止所有订单的合作 | AA95: Ula Zhao | AB95: 2.7663 | AC95: =AB95*J95 -> 863.0856 | AD95: 95333-6.18 | AE95: 已入 | AG95: 312 | AH95: =AG95-J95 -> 0 | AM95: =J95 -> 312 | AP95: =J95 -> 312 | AR95: =J95 -> 312 | AS95: =AS94+AR95 -> 125533
A96: 45748 | B96: AUCHAN FRANCE | C96: 法国 | D96: 4500161684 | E96: 864865 | F96: 4500161684-10 | G96: 71152-S001-3 | H96: 71152-S001 | I96: 机械速龙 | J96: 306 | K96: 0 | L96: 6 | M96: =J96/L96 -> 51 | N96: 45817 | O96: 45813 | Q96: PASS | R96: 6/10第三方+抽板 | T96: 是 | U96: 45756 | V96: 无 | W96: 无 | X96: 客版彩卡+客版说明书(包装都翻4500160987) | Y96: DG20250522 | Z96: 日期码格式：DG20250522 日期：05-22-2025 Packaging Info: 客版彩卡+客版说明书+1张30LWEEE声明书(不含电池版) - (包装都翻4500160987) Remark: 1. 预计6/10第三方验货+抽板测试，请多备料； 2. 日期码：包装上的日期码需打在条码上方; 产品上的日期码直接打印在产品上 3. 所有包装材料不能含PVC <(>&<)> EPS材料，需改用PET，EPE，or EPP环保材料; 另外包装不要覆膜，如果一定要覆膜，就改水性光油; 表面处理，不使用 UV 清 漆，无覆膜层压，改用哑油。 4.有关胶水类的：不使用溶剂型粘合剂。 5.包装材料：需要使用FSC或PEFC认证纸张 6. 关于"包装新油墨规定"，根据法国新法规：禁止在包装印刷油墨中使用矿物油中含有的物质。 欧尚要求有关物质必须遵守以下限制: -油墨中MOAH的质量浓度(1-7个芳香环之和)≤0.1% -油墨中MOAH的质量浓度(3-7个芳香环之和)≤1PPM - MOSH油墨中的质量浓度(16 ~ 35个碳原子的总和)≤0.1% 7. 对于包装印刷, Auchan要求使用植物油，而非矿物油 8. 客户会突击检查<(><<)>(><(>&<)><(><<)>)>验厂，确保在本厂生产，禁止外包，一旦被发现，中止所有订单的合作 | AA96: Ula Zhao | AB96: 2.7663 | AC96: =AB96*J96 -> 846.4878 | AD96: 95399-6.24 | AE96: 已入 | AG96: 320 | AH96: =AG96-J96 -> 14 | AM96: =J96 -> 306 | AP96: =J96 -> 306 | AR96: =J96 -> 306 | AS96: =AS95+AR96 -> 125839
A97: 45768 | B97: TOYS "R" US (CANADA) LTD. | C97: 加拿大 | D97: 4500164179 | E97: 3501527845 | F97: 4500164179-10 | G97: 71152-S001-3L | H97: 71152-S001 | I97: 机械速龙 | J97: 1002 | K97: 0 | L97: 6 | M97: =J97/L97 -> 167 | N97: 45817 | O97: 45813 | P97: 6/11第三方 | Q97: PASS | T97: 否 | U97: 45784 | V97: 无 | W97: 45784 | Z97: 日期码格式：ZURU INC(BVI) 标准格式 日期：按实际生产日期 Packaging Info: 1. 出口加拿大市场。 #71152: MA 3L EAN版本 + UPC贴纸；UPC#193052079190；2PCS AAA BATTERIES(NOT INCLUDED) 2. 产品、包装、外箱上面tracking code的时间格式需要一致，tracking code的时间为：DG20250526 Remark: 3. 需要第三方SGS验货，验货时间2025/06/09，每款每色请备1PC完整带包装样品供验货人员参考。用完后若无损坏可以放回大货里。 | AA97: Abby Mai,Lluvia Zeng | AB97: 2.5407 | AC97: =AB97*J97 -> 2545.7814 | AD97: 95403-6.24 | AE97: 已入 | AG97: 1002 | AH97: =AG97-J97 -> 0 | AL97: =J97 -> 1002 | AO97: =J97 -> 1002 | AR97: =J97 -> 1002 | AS97: =AS96+AR97 -> 126841
A98: 45774 | B98: UNFI WHOLESALE INC | C98: 美国 | D98: 4500165209 | E98: PO# 43359476 | F98: 4500165209-50 | G98: 71152-S001 | H98: 71152-S001 | I98: 机械速龙 | J98: 78 | K98: 0 | L98: 6 | M98: =J98/L98 -> 13 | N98: 45817 | O98: 45813 | Q98: PASS | T98: 否 | U98: 45784 | V98: 无 | W98: 无 | Z98: 日期码格式：ZURU INC(BVI) 标准格式 日期：按实际生产日期 Packaging Info: 优先ZURU MA 1L包装，显示ZURU UPC条码，出口美国 Remark: 1、无第三方测试和验货；Zuru QC 验货即可出货； 2、如果产品含塑胶袋，厚度小于1/1000 inch（0.0254 毫米），需印警告语 | AA98: Sia Liu | AB98: 1.6597 | AC98: =AB98*J98 -> 129.4566 | AD98: ZB00564-6.24 | AE98: 已入 | AG98: 78 | AH98: =AG98-J98 -> 0 | AK98: =J98 -> 78 | AO98: =J98 -> 78 | AR98: =J98 -> 78 | AS98: =AS97+AR98 -> 126919
A99: 45774 | B99: UNFI WHOLESALE INC | C99: 美国 | D99: 4500165209 | E99: PO# 91157512 | F99: 4500165209-100 | G99: 71152-S001 | H99: 71152-S001 | I99: 机械速龙 | J99: 120 | K99: 0 | L99: 6 | M99: =J99/L99 -> 20 | N99: 45817 | O99: 45813 | Q99: PASS | T99: 否 | U99: 45784 | V99: 无 | W99: 无 | Z99: 日期码格式：ZURU INC(BVI) 标准格式 日期：按实际生产日期 Packaging Info: 优先ZURU MA 1L包装，显示ZURU UPC条码，出口美国 Remark: 1、无第三方测试和验货；Zuru QC 验货即可出货； 2、如果产品含塑胶袋，厚度小于1/1000 inch（0.0254 毫米），需印警告语 | AA99: Sia Liu | AB99: 1.6597 | AC99: =AB99*J99 -> 199.164 | AD99: ZB00564-6.24 | AE99: 已入 | AG99: 120 | AH99: =AG99-J99 -> 0 | AK99: =J99 -> 120 | AO99: =J99 -> 120 | AR99: =J99 -> 120 | AS99: =AS98+AR99 -> 127039
A100: 45774 | B100: UNFI WHOLESALE INC | C100: 美国 | D100: 4500165209 | E100: PO# 96103059 | F100: 4500165209-150 | G100: 71152-S001 | H100: 71152-S001 | I100: 机械速龙 | J100: 222 | K100: 0 | L100: 6 | M100: =J100/L100 -> 37 | N100: 45817 | O100: 45813 | Q100: PASS | T100: 否 | U100: 45784 | V100: 无 | W100: 无 | Z100: 日期码格式：ZURU INC(BVI) 标准格式 日期：按实际生产日期 Packaging Info: 优先ZURU MA 1L包装，显示ZURU UPC条码，出口美国 Remark: 1、无第三方测试和验货；Zuru QC 验货即可出货； 2、如果产品含塑胶袋，厚度小于1/1000 inch（0.0254 毫米），需印警告语 | AA100: Sia Liu | AB100: 1.6597 | AC100: =AB100*J100 -> 368.4534 | AD100: ZB00564-6.24 | AE100: 已入 | AG100: 222 | AH100: =AG100-J100 -> 0 | AK100: =J100 -> 222 | AO100: =J100 -> 222 | AR100: =J100 -> 222 | AS100: =AS99+AR100 -> 127261
A101: 45775 | B101: GEKAS ULLAREED AB | C101: 瑞典 | D101: 4500160445 | E101: 300565966 | F101: 4500160445-10 | G101: 71152-S001-3L-1 | H101: 71152-S001 | I101: 机械速龙 | J101: 240 | K101: 0 | L101: 6 | M101: =J101/L101 -> 40 | N101: 45817 | O101: 45813 | Q101: PASS | T101: 否 | U101: 45775 | V101: 无 | W101: 45790 | X101: 客版说明书（翻单4500161075 | Z101: 日期码格式：ZURU INC(BVI) 标准格式 日期：按实际生产日期 Packaging Info: 71152-S001_3L EAN A版包装+客版说明书（翻单4500161075)+进口商贴纸 北欧五语通用Slime黑白说明书 带纽扣电池走货北欧六语通用黑白电池说明书 上述贴纸翻单4500162375，之前已经安排MA 采购，请不要重复采购 Remark: "1. 包装如含PVC,请改为PET，此单出瑞典，需要瑞典语警告语和进口商信息（贴纸需要加上） 2. 产品/包装要求无硼无香； 3. 出欧洲，微塑料需合规。 4.带电池出货的产品所用到的电池需要符合欧洲电池新规(EU) 2023-1542 5.关于贴纸，如果贴纸位置图的包装版本与大货不一致，请工厂提前提出。跟单会重新调整确认是否更新贴纸或调整位置图 6.产品/包装不含PFAS成分 7. 产品信息： 8. SKU-客户SKU-EAN-GTIN " 71152-S001-4894680042742 | AA101: Luna Lin | AB101: 2.7663 | AC101: =AB101*J101 -> 663.912 | AD101: 95343-6.18 | AE101: 已入 | AG101: 240 | AH101: =AG101-J101 -> 0 | AL101: =J101 -> 240 | AP101: =J101 -> 240 | AR101: =J101 -> 240 | AS101: =AS100+AR101 -> 127501
...

Sheet 半成品MA
B2: 71152机械龙 半成品生产MA
B3: 日期 | C3: MA订单号码 | D3: ITEM | E3: 名称 | H3: 合计 | I3: 要求完成日期 | J3: 备注
B4: 45678 | C4: MA_RR_1527 | D4: 71152 | E4: 机械龙 | H4: 50000 | I4: 45731
B5: 45729 | C5: MA_RR_1589 | D5: 71152 | E5: 机械龙 | H5: 100000 | I5: 45777
B6: 45764 | C6: MA_RR_1626 | D6: 71152 | E6: 机械龙 | H6: 40000 | I6: 45808
B7: 45785 | C7: MA_RR_1636 | D7: 71152 | E7: 机械龙 | H7: 50000 | I7: 45828
B8: 45804 | C8: MA_RR_1686 | D8: 71152 | E8: 机械龙 | H8: 100000 | I8: 45848
B9: 45827 | C9: MA_RR_1739 | D9: 71152 | E9: 机械龙 | H9: 50000 | I9: 45869
B10: 45847 | C10: MA_RR_1784 | D10: 71152 | E10: 机械龙 | H10: 50000 | I10: 45889
B11: 45896 | C11: MA_RR_1858 | D11: 71152 | E11: 机械龙 | H11: 50000 | I11: 45950
B12: 45923 | C12: MA_RR_1897 | D12: 71152 | E12: 机械龙 | H12: 40000 | I12: 45986
B13: 45951 | C13: MA_RR_1920 | D13: 71152 | E13: 机械龙 | H13: 30000 | I13: 46006
B14: 45992 | C14: MA_RR_1986 | D14: 71152 | E14: 机械龙 | H14: 50000 | I14: 45680
B15: 46017 | C15: MA_RR_2032 | D15: 71152 | E15: 机械龙 | H15: 40000 | I15: 46077
B16: 46051 | C16: MA_RR_2095 | D16: 71152 | E16: 机械龙 | H16: 30000 | I16: 46116
E23: MA合计 | F23: 0 | G23: =SUM(G4:G10) -> 0 | H23: =SUM(H4:H22) -> 680000
G24: 接单总数 | H24: ='71152'!AR557 -> 109073
G25: MA剩余 | H25: =H23-H24 -> 570927
G26: MA剩余占MA数比率 | H26: =H25/H23 -> 0.83959853

Sheet 包装MA
B1: 71152 彩盒/说明书 MA
B2: 放MA日期 | C2: MA订单号 | D2: 名称 | E2: MA订单号码 | F2: 货号 | G2: 数量 | H2: 语言 | I2: 版本号 | J2: 1L 标准版彩盒 | K2: 3L 标准版彩盒 | L2: 5L 说明书 | M2: 客版彩盒 | N2: 客版说明书 | O2: Endcap EC展架
B3: 45705 | D3: Window Box | E3: 1000025812 | F3: 71152 | G3: 20000 | H3: 1L彩盒 | I3: A | J3: 20000
B4: 45705 | D4: Instruction Sheet | E4: 1000025814 | F4: 71152 | G4: 30000 | H4: 说明书 | I4: A | L4: 30000
B5: 45727 | D5: Window Box | E5: 1000026190 | F5: 71152 | G5: 10000 | H5: 彩盒 | I5: A | K5: 10000
B6: 45729 | D6: Window Box | E6: 1000026284 | F6: 71152 | G6: 50000 | H6: 1L B版本彩盒 | I6: B | J6: =G6 -> 50000
B7: 45729 | D7: Instruction Sheet | E7: 1000026285 | F7: 71152 | G7: 60000 | H7: 5L B版本说明书 | I7: B | L7: =G7 -> 60000
B8: 45729 | D8: Window Box | E8: 1000026280 | F8: 71152 | G8: 10000 | H8: 3L 彩盒 | I8: A | K8: 10000
B9: 45749 | C9: 兴富利（B) | D9: Window Box | E9: 1000026874 | F9: 71152 | G9: 30000 | H9: 1L彩盒 | I9: B | J9: 30000
B10: 45749 | D10: Instruction Sheet | E10: 1000026875 | F10: 71152 | G10: 20000 | H10: 5L B版本说明书 | I10: B | L10: 80000
B11: 45749 | C11: 华茂（3L） | D11: Window Box | E11: 1000026875 | F11: 71152 | G11: 50000 | H11: 3L 彩盒 | I11: A | K11: 50000
B12: 45793 | D12: Instruction Sheet | E12: 1000026876 | F12: 71152 | G12: 50000 | H12: 1L B版本彩盒 | I12: B | J12: 50000 | L12: 50000 | P12: 说明书不放MA 自行订购
B13: 45804 | D13: Window Box | E13: 1000028455 | F13: 71152 | G13: 50000 | H13: 1L B版本彩盒 | I13: B | J13: 50000
B14: 45804 | D14: Window Box | E14: 1000028456 | F14: 71152 | G14: 10000 | H14: 3L 彩盒 | I14: A | K14: 10000 | L14: 60000
B15: 45827 | D15: Window Box | E15: 1000029146 | F15: 71152 | G15: 30000 | H15: 1L B版本彩盒 | I15: B | J15: 30000
B16: 45827 | D16: Window Box | E16: 1000029147 | F16: 71152 | G16: 20000 | H16: 3L 彩盒 | I16: A | K16: 20000 | L16: 50000
B17: 45847 | D17: Window Box | E17: 1000029906 | F17: 71152 | G17: 30000 | H17: 1L B版本彩盒 | I17: B | J17: 30000
B18: 45847 | D18: Window Box | E18: 1000029907 | F18: 71152 | G18: 10000 | H18: 3L 彩盒 | I18: A | K18: 10000 | L18: 40000
B19: 45870 | D19: Window Box | E19: 1000030640 | F19: 71152 | G19: 20000 | H19: 1L彩盒 | I19: B | J19: 20000
B20: 45870 | D20: Window Box | E20: 1000030641 | F20: 71152 | G20: 10000 | H20: 3L 彩盒 | I20: A | K20: 10000 | L20: 30000
B21: 45888 | D21: Window Box | E21: 1000031131 | F21: 71152 | G21: 20000 | H21: 1L B版本彩盒 | I21: B | J21: 20000
B22: 45898 | D22: Window Box | E22: 1000031568 | F22: 71152 | G22: 30000 | H22: 1L B版本彩盒 | I22: B | J22: 30000 | L22: 50000
B23: 45929 | D23: Window Box | E23: 1000032536 | F23: 71152 | G23: 30000 | H23: 1L B版本彩盒 | I23: B | J23: 30000
B24: 45929 | D24: Instruction sheet | F24: 71152 | G24: 3000 | H24: 6L客版说明书 | N24: 3000
B25: 45954 | D25: Window Box | E25: 1000033329 | F25: 71152 | G25: 10000 | H25: 1L B版本彩盒 | I25: B | J25: 10000 | L25: 40000
B26: 45954 | D26: Window Box | E26: 1000033330 | F26: 71152 | G26: 10000 | H26: 3L B版本彩盒 | I26: B | K26: 10000
B27: 45995 | D27: Window Box | E27: 1000034704 | F27: 71152 | G27: 50000 | H27: 1L B版本彩盒 | I27: B | J27: 50000 | L27: 50000
B28: 46022 | D28: Window Box | E28: 1000035473 | F28: 71152 | G28: 30000 | H28: 1L | I28: B | J28: 30000 | L28: 30000
I33: 合计 | J33: =SUM(J3:J31) -> 450000 | K33: =SUM(K4:K31) -> 130000 | L33: =SUM(L4:L31) -> 570000 | M33: =22512+SUM(M2:M32) -> 22512 | N33: =SUM(N3:N32) -> 3000
I34: 接单总数 | J34: ='71152'!AJ553+'71152'!AK553 -> 433535 | K34: ='71152'!AL553 -> 124377 | L34: =SUM('71152'!AN553:AO553) -> 538094 | M34: ='71152'!AM553 -> 23112 | N34: ='71152'!AP553 -> 0 | O34: ='71152'!AQ553 -> 0
I36: 剩余数 | J36: =J33-J34 -> 16465 | K36: =K33-K34 -> 5623 | L36: =L33-L34 -> 31906 | M36: =M33-M34 -> -600 | N36: =N33-N34 -> 3000 | O36: =O33-O34 -> 0

Sheet 取消單
A1: 接单日期 | B1: 第三方客户名称 | C1: 国家 | D1: PO号 | E1: 客PO号 | F1: SKU | G1: 系统货号 | H1: ITEM# | I1: 中文名 | J1: PO数量 (pcs) | K1: 内箱装箱数量(pcs) | L1: 外箱装箱数量(pcs) | M1: 总箱数 | N1: 客PO期 | O1: 验货期 | P1: 第三方验货期 | Q1: 驗貨結果 | R1: 船期SO | S1: 贴纸情况 | T1: 箱唛资料（收到箱唛日期） | U1: 外箱贴纸 | V1: 客贴纸资料 | W1: 客版资料 | X1: 日期码 | Y1: 备注 | Z1: ZURU 跟单 | AA1: 单价USD | AB1: 金额USD | AC1: 發票號 | AD1: 是否入系统 | AE1: 已送数量 | AF1: 欠数 | AG1: 贴纸信息 | AH1: MA 1语彩盒 A版本 | AI1: MA 1L 彩盒B版本 | AJ1: MA 3L彩盒 A版本 | AK1: 客版彩盒 | AL1: MA 5说明书 | AM1: MA 5L 说明书B版 | AN1: 客版说明书 | AO1: EC展示架 | AP1: 合计数量 | AQ1: 累计数量
A2: 45723 | B2: DIAMANT TOYS LTD | C2: 以色列 | D2: 4500157806 | E2: 56072 | F2: 4500157806-10 | G2: 71152-S001 | H2: 71152-S001 | I2: 机械速龙 | J2: 2220 | K2: 0 | L2: 6 | M2: 370 | N2: 45765 | O2: 45761 | T2: 45726 | U2: 无 | V2: 进口商贴纸翻4500153742+彩色贴纸翻4500153742 | X2: 日期码格式：ZURU INC(BVI) 标准格式 日期：按实际生产日期 | Y2: 日期码格式：ZURU INC(BVI) 标准格式 日期：按实际生产日期 Packaging Info: 1L MA包装+进口商贴纸翻4500153742+彩色贴纸翻4500153742; MA说明书 Remark: | Z2: Lena Huang | AA2: 2.7 | AB2: 5994 | AD2: 已入 | AF2: -2220 | AH2: 2220 | AL2: 2220 | AP2: 2220 | AQ2: 19302
A3: 45642 | B3: Inventive Toys | C3: 俄罗斯联邦 | D3: 4500153901 | F3: 4500153901-50 | G3: 71152-S001 | H3: 71152-S001 | I3: 机械速龙 | J3: 600 | K3: 0 | L3: 6 | M3: =J3/L3 -> 100 | N3: 45793 | O3: 45789 | T3: 46019 | U3: 无 | V3: 欠进口商贴纸 | X3: 外箱不要打ZURU标准日期码！胶件可以打日期码。 | Y3: 日期码格式：外包装/外箱不要打ZURU标准日期码 日期： Packaging Info: 注意:外包装 (指: 收缩膜/彩卡/铝箔袋/挂卡/PDQ)/外箱不要打ZURU标准日期码!胶件可以打日期码。 外包装(包括收缩膜/彩卡/PDQ)都不能含Instagram and facebook logo等社交logo ; 71152 ： MA 彩卡+ 进口商贴纸 ， MA 说明书/指南（如有）； Remark: 标准配比; | Z3: Ann Zhang | AA3: 2.7 | AB3: =AA3*J3 -> 1620 | AD3: 已入 | AF3: =AE3-J3 -> -600 | AI3: =J3 -> 600 | AM3: =J3 -> 600 | AP3: =J3 -> 600 | AQ3: ='71152'!AS46+AP3 -> 41151
A4: 45775 | B4: ZURU France | C4: 法国 | D4: 4500163394 | E4: 5200006588 | F4: 4500163394-20 | G4: 71152-S001-3L | H4: 71152-S001-MTS | I4: 机械速龙 | J4: 990 | K4: 0 | L4: 6 | M4: =J4/L4 -> 165 | N4: 45824 | O4: 45820 | P4: 5/30取消 | T4: 否 | U4: 45796 | V4: 无 | W4: 一张意大利环保标贴纸+ 多语版WEEE电池垃圾桶的回收声明说明书（not included）（贴纸和WEEE翻 4500162314） | Z4: 日期码格式：ZURU INC(BVI) 标准格式 日期：按实际生产日期 Packaging Info: 71152:最新MA 3L EAN（23L warning）彩盒+最新MA 5L说明书+ 一张意大利环保标贴纸+ 多语版WEEE电池垃圾桶的回收声明说明书（not included）（贴纸和WEEE翻 4500162314） Remark: 1. 法国国家内销单，需要通过ZURU 验货结果后才能出货 (工厂需要主动提前同ZURU QC预约验货避免延期出货造成不必要麻烦)； 2. 本订单所有 具有 baby items / assorted items 的款式，零售包装上都要用 母 EAN; 所有订单出口西班牙都需要有法国环保标。 3. 若有特定款有特殊外箱条码要求时,需要明确列出产品款对应的具体外箱条码号码/条码类型 (若无,可以忽略此需求) 4. 所有出口欧洲的产品, 法规规定禁止在包装和共公众用的印刷品中使用矿物油中含有的物质, 包装印刷油墨中含有的MOAH/MOSH的质量浓度不能超过1%, 否则出 货到法国被抽检出现问题, 供应商需要对此负责; 5. Date code: 外箱/产品/包装 保持一致，完货后提供date code 信息以便我们保存记录做批次管理; 6. 装柜时需要按照款式号码从小到大一款款依次装,避免终端仓库卸货混乱.若一个柜子涉及到几个不同国家内销单,装柜时需要一个国家装完后再装另一个国家的 产品,依次装柜,避免终端仓库因不同国家不同库位位置卸货混乱. (此点需要同工厂装柜人员强调) 7， 带电池产品都需要包含多语WEEE黑白说明书。 8，MTS所有订单，SMASHERS 或含Slime产品，所有化合物使用无硼版本出；如有香味产品，出无香版本; BOB系列要符合欧洲要求不含亚硝酸版本; XShot Hyper系列 ，统一出EN71版本。 | AA4: SD83 | AB4: 2.7663 | AC4: =AB4*J4 -> 2738.637 | AE4: 已入 | AG4: =AF4-J4 -> -990 | AK4: =J4 -> 990 | AN4: =J4 -> 990 | AQ4: =J4 -> 990 | AR4: ='71152'!AS118+AQ4 -> 146119
A5: 45765 | B5: WALMART INC. | C5: 美国 | D5: 4500164205 | E5: WM PO#0905014391 /WM item#67419606 0/GTIN#101930 52079197/STK# 71152 | F5: 4500164205-40 | G5: 71152-S002-2 | H5: 71152-S002 | I5: 机械速龙 | J5: 2268 | K5: 0 | L5: 3 | M5: =J5/L5 -> 756 | N5: 45811 | O5: 45807 | P5: 换单 | T5: 否 | U5: 71152箱唛排版可follow PO#4500163167 | V5: 无 | W5: 无 | X5: 45765 | Z5: 日期码格式：ZURU DGYYMMDD CHINA(日期避开周末和法定节假日） 日期：按实际生产日期 Packaging Info: "1.包装信息： 71152：MA 1L 彩盒+ MA 说明书" Remark: "71152： 2. 此单为散箱出货，外箱印刷RFID箱唛（四面右下角印ZURU logo并要有""""Made in China"""" 字样, 外箱一面正唛直接印刷订单内容（从每行remark处获取）， 不再贴贴纸)。 3. 在产品和包装上要有日期码、以及要有MADE IN CHINA和ZURU字样. 4. 产品如有扎带口要剪平，不能刮手. 5. 3pcs /CTN；not include 2pcs AAA battery. 6. 此单需要验货，烦请多备包装物料 7. 每PCS要加RFID 贴纸，严格按照我们提供的位置图，不可擅自调整位置，贴纸也不可有任何破损或折坏，不可淋湿!!" 8.此单每个运输箱加贴一张粉色贴纸 | AA5: Elena | AB5: 2.75 | AC5: =AB5*J5 -> 6237 | AE5: 已入 | AG5: =AF5-J5 -> -2268 | AH5: 欠 | AJ5: =J5 -> 2268 | AO5: =J5 -> 2268 | AQ5: =J5 -> 2268 | AR5: ='71152'!AS83+AQ5 -> 120651
A6: 45765 | B6: WALMART INC. | C6: 美国 | D6: 4500164205 | E6: WM PO#0905014290 /WM item#67419606 0/GTIN#101930 52079197/STK# 71152 | F6: 4500164205-50 | G6: 71152-S002-2 | H6: 71152-S002 | I6: 机械速龙 | J6: 3132 | K6: 0 | L6: 3 | M6: =J6/L6 -> 1044 | N6: 45811 | O6: 45807 | P6: 换单 | T6: 否 | U6: 71152箱唛排版可follow PO#4500163167 | V6: 无 | W6: 无 | X6: 45765 | Z6: 日期码格式：ZURU DGYYMMDD CHINA(日期避开周末和法定节假日） 日期：按实际生产日期 Packaging Info: "1.包装信息： 71152：MA 1L 彩盒+ MA 说明书" Remark: "71152： 2. 此单为散箱出货，外箱印刷RFID箱唛（四面右下角印ZURU logo并要有""""Made in China"""" 字样, 外箱一面正唛直接印刷订单内容（从每行remark处获取）， 不再贴贴纸)。 3. 在产品和包装上要有日期码、以及要有MADE IN CHINA和ZURU字样. 4. 产品如有扎带口要剪平，不能刮手. 5. 3pcs /CTN；not include 2pcs AAA battery. 6. 此单需要验货，烦请多备包装物料 7. 每PCS要加RFID 贴纸，严格按照我们提供的位置图，不可擅自调整位置，贴纸也不可有任何破损或折坏，不可淋湿!!" 8.此单每个运输箱加贴一张粉色贴纸 | AA6: Elena | AB6: 2.75 | AC6: =AB6*J6 -> 8613 | AE6: 已入 | AG6: =AF6-J6 -> -3132 | AH6: 欠 | AJ6: =J6 -> 3132 | AN6: =J6 -> 3132 | AQ6: =J6 -> 3132 | AR6: =AR5+AQ6 -> 123783
A7: 45765 | B7: WALMART INC. | C7: 美国 | D7: 4500164205 | E7: WM PO#0905014394 /WM item#67419606 0/GTIN#101930 52079197/STK# 71152 | F7: 4500164205-60 | G7: 71152-S002-2 | H7: 71152-S002 | I7: 机械速龙 | J7: 2802 | K7: 0 | L7: 3 | M7: =J7/L7 -> 934 | N7: 45811 | O7: 45807 | P7: 换单 | T7: 否 | U7: 71152箱唛排版可follow PO#4500163167 | V7: 无 | W7: 无 | X7: 45765 | Z7: 日期码格式：ZURU DGYYMMDD CHINA(日期避开周末和法定节假日） 日期：按实际生产日期 Packaging Info: "1.包装信息： 71152：MA 1L 彩盒+ MA 说明书" Remark: "71152： 2. 此单为散箱出货，外箱印刷RFID箱唛（四面右下角印ZURU logo并要有""""Made in China"""" 字样, 外箱一面正唛直接印刷订单内容（从每行remark处获取）， 不再贴贴纸)。 3. 在产品和包装上要有日期码、以及要有MADE IN CHINA和ZURU字样. 4. 产品如有扎带口要剪平，不能刮手. 5. 3pcs /CTN；not include 2pcs AAA battery. 6. 此单需要验货，烦请多备包装物料 7. 每PCS要加RFID 贴纸，严格按照我们提供的位置图，不可擅自调整位置，贴纸也不可有任何破损或折坏，不可淋湿!!" 8.此单每个运输箱加贴一张粉色贴纸 | AA7: Elena | AB7: 2.75 | AC7: =AB7*J7 -> 7705.5 | AE7: 已入 | AG7: =AF7-J7 -> -2802 | AH7: 欠 | AJ7: =J7 -> 2802 | AN7: =J7 -> 2802 | AQ7: =J7 -> 2802 | AR7: =AR6+AQ7 -> 126585
A8: 45769 | B8: WALMART INC. | C8: 美国 | D8: 4500164229 | E8: WM PO#0905014352 /WM item#67419606 0/GTIN#101930 52079197/STK# 71152 | F8: 4500164229-30 | G8: 71152-S002-2 | H8: 71152-S002 | I8: 机械速龙 | J8: 4104 | K8: 0 | L8: 3 | M8: =J8/L8 -> 1368 | N8: 45818 | O8: 45814 | P8: 6/11BV | Q8: 换单 | T8: 否 | U8: 71152箱唛排版可follow PO#4500163167 | V8: 无 | W8: 无 | X8: 45769 | Z8: 日期码格式：ZURU DGYYMMDD CHINA(日期避开周末和法定节假日） 日期：按实际生产日期 Packaging Info: "1.包装信息： 71152：MA 1L 彩盒+ MA 说明书" Remark: "71152： 2. 此单为散箱出货，外箱印刷RFID箱唛（四面右下角印ZURU logo并要有""""Made in China"""" 字样, 外箱一面正唛直接印刷订单内容（从每行remark处获取）， 不再贴贴纸)。 3. 在产品和包装上要有日期码、以及要有MADE IN CHINA和ZURU字样. 4. 产品如有扎带口要剪平，不能刮手. 5. 3pcs /CTN；not include 2pcs AAA battery. 6. 此单需要验货，烦请多备包装物料 7. 每PCS要加RFID 贴纸，严格按照我们提供的位置图，不可擅自调整位置，贴纸也不可有任何破损或折坏，不可淋湿!!" 8.此单每个运输箱加贴一张粉色贴纸 | AA8: Elena | AB8: 1.65 | AC8: =AB8*J8 -> 6771.6 | AE8: 已入 | AG8: =AF8-J8 -> -4104 | AJ8: =J8 -> 4104 | AN8: =J8 -> 4104 | AQ8: =J8 -> 4104 | AR8: ='71152'!AS152+AQ8 -> 178393
A9: 45769 | B9: WALMART INC. | C9: 美国 | D9: 4500164229 | E9: WM PO#0905014364 /WM item#67419606 0/GTIN#101930 52079197/STK# 71152 | F9: 4500164229-40 | G9: 71152-S002-2 | H9: 71152-S002 | I9: 机械速龙 | J9: 3594 | K9: 0 | L9: 3 | M9: =J9/L9 -> 1198 | N9: 45818 | O9: 45814 | P9: 6/11BV | Q9: 换单 | T9: 否 | U9: 71152箱唛排版可follow PO#4500163167 | V9: 无 | W9: 无 | X9: 45769 | Z9: 日期码格式：ZURU DGYYMMDD CHINA(日期避开周末和法定节假日） 日期：按实际生产日期 Packaging Info: "1.包装信息： 71152：MA 1L 彩盒+ MA 说明书" Remark: "71152： 2. 此单为散箱出货，外箱印刷RFID箱唛（四面右下角印ZURU logo并要有""""Made in China"""" 字样, 外箱一面正唛直接印刷订单内容（从每行remark处获取）， 不再贴贴纸)。 3. 在产品和包装上要有日期码、以及要有MADE IN CHINA和ZURU字样. 4. 产品如有扎带口要剪平，不能刮手. 5. 3pcs /CTN；not include 2pcs AAA battery. 6. 此单需要验货，烦请多备包装物料 7. 每PCS要加RFID 贴纸，严格按照我们提供的位置图，不可擅自调整位置，贴纸也不可有任何破损或折坏，不可淋湿!!" 8.此单每个运输箱加贴一张粉色贴纸 | AA9: Elena | AB9: 1.65 | AC9: =AB9*J9 -> 5930.1 | AE9: 已入 | AG9: =AF9-J9 -> -3594 | AJ9: =J9 -> 3594 | AN9: =J9 -> 3594 | AQ9: =J9 -> 3594 | AR9: =AR8+AQ9 -> 181987
A10: 45769 | B10: WALMART INC. | C10: 美国 | D10: 4500164240 | E10: WM PO#0905014309 /WM item#67419606 0/GTIN#101930 52079197/STK# 71152 | F10: 4500164240-30 | G10: 71152-S002-2 | H10: 71152-S002 | I10: 机械速龙 | J10: 2928 | K10: 0 | L10: 3 | M10: =J10/L10 -> 976 | N10: 45825 | O10: 45821 | P10: 6/18BV | Q10: 换单 | T10: 否 | U10: 71152箱唛排版可follow PO#4500163167 | V10: 无 | W10: 无 | X10: 45769 | Z10: 日期码格式：ZURU DGYYMMDD CHINA(日期避开周末和法定节假日） 日期：按实际生产日期 Packaging Info: "1.包装信息： 71152：MA 1L 彩盒+ MA 说明书：" Remark: "71152： 2. 此单为散箱出货，外箱印刷RFID箱唛（四面右下角印ZURU logo并要有""""Made in China"""" 字样, 外箱一面正唛直接印刷订单内容（从每行remark处获取）， 不再贴贴纸)。 3. 在产品和包装上要有日期码、以及要有MADE IN CHINA和ZURU字样. 4. 产品如有扎带口要剪平，不能刮手. 5. 3pcs /CTN；not include 2pcs AAA battery. 6. 此单需要验货，烦请多备包装物料 7. 每PCS要加RFID 贴纸，严格按照我们提供的位置图，不可擅自调整位置，贴纸也不可有任何破损或折坏，不可淋湿!!" 8.此单每个运输箱加贴一张粉色贴纸 | AA10: Elena | AB10: 1.65 | AC10: =AB10*J10 -> 4831.2 | AE10: 已入 | AG10: =AF10-J10 -> -2928 | AJ10: =J10 -> 2928 | AN10: =J10 -> 2928 | AQ10: =J10 -> 2928 | AR10: ='71152'!AS119+AQ10 -> 148561
A11: 45769 | B11: WALMART INC. | C11: 美国 | D11: 4500164240 | E11: WM PO#0905014311 /WM item#67419606 0/GTIN#101930 52079197/STK# 71152 | F11: 4500164240-40 | G11: 71152-S002-2 | H11: 71152-S002 | I11: 机械速龙 | J11: 2766 | K11: 0 | L11: 3 | M11: =J11/L11 -> 922 | N11: 45825 | O11: 45821 | P11: 6/18BV | Q11: 换单 | T11: 否 | U11: 71152箱唛排版可follow PO#4500163167 | V11: 无 | W11: 无 | X11: 45769 | Z11: 日期码格式：ZURU DGYYMMDD CHINA(日期避开周末和法定节假日） 日期：按实际生产日期 Packaging Info: "1.包装信息： 71152：MA 1L 彩盒+ MA 说明书：" Remark: "71152： 2. 此单为散箱出货，外箱印刷RFID箱唛（四面右下角印ZURU logo并要有""""Made in China"""" 字样, 外箱一面正唛直接印刷订单内容（从每行remark处获取）， 不再贴贴纸)。 3. 在产品和包装上要有日期码、以及要有MADE IN CHINA和ZURU字样. 4. 产品如有扎带口要剪平，不能刮手. 5. 3pcs /CTN；not include 2pcs AAA battery. 6. 此单需要验货，烦请多备包装物料 7. 每PCS要加RFID 贴纸，严格按照我们提供的位置图，不可擅自调整位置，贴纸也不可有任何破损或折坏，不可淋湿!!" 8.此单每个运输箱加贴一张粉色贴纸 | AA11: Elena | AB11: 1.65 | AC11: =AB11*J11 -> 4563.9 | AE11: 已入 | AG11: =AF11-J11 -> -2766 | AJ11: =J11 -> 2766 | AN11: =J11 -> 2766 | AQ11: =J11 -> 2766 | AR11: =AR10+AQ11 -> 151327
A12: 45765 | B12: WALMART INC. | C12: 美国 | D12: 4500164258 | E12: WM PO#0906596274 /WM item#67419606 0/GTIN#101930 52079197/STK# 71152 | F12: 4500164258-20 | G12: 71152-S002-2 | H12: 71152-S002 | I12: 机械速龙 | J12: 600 | K12: 0 | L12: 3 | M12: =J12/L12 -> 200 | N12: 45811 | O12: 45807 | P12: 6/4BV | Q12: 换单 | T12: 否 | U12: 71152箱唛排版可follow PO#4500163167 | V12: 无 | W12: 无 | X12: 45765 | Z12: 日期码格式：ZURU DGYYMMDD CHINA(日期避开周末和法定节假日） 日期：按实际生产日期 Packaging Info: "1.包装信息： 71152：MA 1L 彩盒+ MA 说明书" Remark: "71152： 2. 此单为散箱出货，外箱印刷RFID箱唛（四面右下角印ZURU logo并要有""""Made in China"""" 字样, 外箱一面正唛直接印刷订单内容（从每行remark处获取）， 不再贴贴纸)。 3. 在产品和包装上要有日期码、以及要有MADE IN CHINA和ZURU字样. 4. 产品如有扎带口要剪平，不能刮手. 5. 3pcs /CTN；not include 2pcs AAA battery. 6. 此单需要验货，烦请多备包装物料 7. 每PCS要加RFID 贴纸，严格按照我们提供的位置图，不可擅自调整位置，贴纸也不可有任何破损或折坏，不可淋湿!!" | AA12: Lorraine Liang | AB12: 2.75 | AC12: =AB12*J12 -> 1650 | AE12: 已入 | AG12: =AF12-J12 -> -600 | AJ12: =J12 -> 600 | AN12: =J12 -> 600 | AQ12: =J12 -> 600 | AR12: =取消單!AR7+AQ12 -> 127185
A13: 45765 | B13: WALMART INC. | C13: 美国 | D13: 4500164258 | E13: WM PO#0906596283 /WM item#67419606 0/GTIN#101930 52079197/STK#71152 | F13: 4500164258-30 | G13: 71152-S002-2 | H13: 71152-S002 | I13: 机械速龙 | J13: 906 | K13: 0 | L13: 3 | M13: =J13/L13 -> 302 | N13: 45811 | O13: 45807 | P13: 6/4BV | Q13: 换单 | T13: 否 | U13: 71152箱唛排版可follow PO#4500163167 | V13: 无 | W13: 无 | X13: 45765 | Z13: 日期码格式：ZURU DGYYMMDD CHINA(日期避开周末和法定节假日） 日期：按实际生产日期 Packaging Info: "1.包装信息： 71152：MA 1L 彩盒+ MA 说明书" Remark: "71152： 2. 此单为散箱出货，外箱印刷RFID箱唛（四面右下角印ZURU logo并要有""""Made in China"""" 字样, 外箱一面正唛直接印刷订单内容（从每行remark处获取）， 不再贴贴纸)。 3. 在产品和包装上要有日期码、以及要有MADE IN CHINA和ZURU字样. 4. 产品如有扎带口要剪平，不能刮手. 5. 3pcs /CTN；not include 2pcs AAA battery. 6. 此单需要验货，烦请多备包装物料 7. 每PCS要加RFID 贴纸，严格按照我们提供的位置图，不可擅自调整位置，贴纸也不可有任何破损或折坏，不可淋湿!!" | AA13: Lorraine Liang | AB13: 2.75 | AC13: =AB13*J13 -> 2491.5 | AE13: 已入 | AG13: =AF13-J13 -> -906 | AJ13: =J13 -> 906 | AN13: =J13 -> 906 | AQ13: =J13 -> 906 | AR13: =AR12+AQ13 -> 128091
A14: 45769 | B14: WALMART INC. | C14: 美国 | D14: 4500164334 | E14: WM PO#0906596254 /WM item#67419606 0/GTIN#101930 52079197/STK# 71152 | F14: 4500164334-60 | G14: 71152-S002-2 | H14: 71152-S002 | I14: 机械速龙 | J14: 570 | K14: 0 | L14: 3 | M14: =J14/L14 -> 190 | N14: 45818 | O14: 45814 | P14: 6/11BV | Q14: 换单 | T14: 否 | U14: 71152箱唛排版可follow PO#4500163167 | V14: 无 | W14: 无 | X14: 45769 | Z14: 日期码格式：ZURU DGYYMMDD CHINA(日期避开周末和法定节假日） 日期：按实际生产日期 Packaging Info: "1.包装信息： 71152：MA 1L 彩盒+ MA 说明书" Remark: "71152： 2. 此单为散箱出货，外箱印刷RFID箱唛（四面右下角印ZURU logo并要有""""Made in China"""" 字样, 外箱一面正唛直接印刷订单内容（从每行remark处获取）， 不再贴贴纸)。 3. 在产品和包装上要有日期码、以及要有MADE IN CHINA和ZURU字样. 4. 产品如有扎带口要剪平，不能刮手. 5. 3pcs /CTN；not include 2pcs AAA battery. 6. 此单需要验货，烦请多备包装物料 7. 每PCS要加RFID 贴纸，严格按照我们提供的位置图，不可擅自调整位置，贴纸也不可有任何破损或折坏，不可淋湿!!" | AA14: Lorraine Liang | AB14: 1.65 | AC14: =AB14*J14 -> 940.5 | AE14: 已入 | AG14: =AF14-J14 -> -570 | AJ14: =J14 -> 570 | AN14: =J14 -> 570 | AQ14: =J14 -> 570 | AR14: =取消單!AR9+AQ14 -> 182557
A15: 45769 | B15: WALMART INC. | C15: 美国 | D15: 4500164334 | E15: WM PO#0906596263 /WM item#67419606 0/GTIN#101930 52079197/STK# 71152 | F15: 4500164334-70 | G15: 71152-S002-2 | H15: 71152-S002 | I15: 机械速龙 | J15: 933 | K15: 0 | L15: 3 | M15: =J15/L15 -> 311 | N15: 45818 | O15: 45814 | P15: 6/11BV | Q15: 换单 | T15: 否 | U15: 71152箱唛排版可follow PO#4500163167 | V15: 无 | W15: 无 | X15: 45769 | Z15: 日期码格式：ZURU DGYYMMDD CHINA(日期避开周末和法定节假日） 日期：按实际生产日期 Packaging Info: "1.包装信息： 71152：MA 1L 彩盒+ MA 说明书" Remark: "71152： 2. 此单为散箱出货，外箱印刷RFID箱唛（四面右下角印ZURU logo并要有""""Made in China"""" 字样, 外箱一面正唛直接印刷订单内容（从每行remark处获取）， 不再贴贴纸)。 3. 在产品和包装上要有日期码、以及要有MADE IN CHINA和ZURU字样. 4. 产品如有扎带口要剪平，不能刮手. 5. 3pcs /CTN；not include 2pcs AAA battery. 6. 此单需要验货，烦请多备包装物料 7. 每PCS要加RFID 贴纸，严格按照我们提供的位置图，不可擅自调整位置，贴纸也不可有任何破损或折坏，不可淋湿!!" | AA15: Lorraine Liang | AB15: 1.65 | AC15: =AB15*J15 -> 1539.45 | AE15: 已入 | AG15: =AF15-J15 -> -933 | AJ15: =J15 -> 933 | AN15: =J15 -> 933 | AQ15: =J15 -> 933 | AR15: =AR14+AQ15 -> 183490
A16: 45769 | B16: WALMART INC. | C16: 美国 | D16: 4500164334 | E16: WM PO#0906596281 /WM item#67419606 0/GTIN#101930 52079197/STK# 71152 | F16: 4500164334-80 | G16: 71152-S002-2 | H16: 71152-S002 | I16: 机械速龙 | J16: 984 | K16: 0 | L16: 3 | M16: =J16/L16 -> 328 | N16: 45818 | O16: 45814 | P16: 6/11BV | Q16: 换单 | T16: 否 | U16: 71152箱唛排版可follow PO#4500163167 | V16: 无 | W16: 无 | X16: 45769 | Z16: 日期码格式：ZURU DGYYMMDD CHINA(日期避开周末和法定节假日） 日期：按实际生产日期 Packaging Info: "1.包装信息： 71152：MA 1L 彩盒+ MA 说明书" Remark: "71152： 2. 此单为散箱出货，外箱印刷RFID箱唛（四面右下角印ZURU logo并要有""""Made in China"""" 字样, 外箱一面正唛直接印刷订单内容（从每行remark处获取）， 不再贴贴纸)。 3. 在产品和包装上要有日期码、以及要有MADE IN CHINA和ZURU字样. 4. 产品如有扎带口要剪平，不能刮手. 5. 3pcs /CTN；not include 2pcs AAA battery. 6. 此单需要验货，烦请多备包装物料 7. 每PCS要加RFID 贴纸，严格按照我们提供的位置图，不可擅自调整位置，贴纸也不可有任何破损或折坏，不可淋湿!!" | AA16: Lorraine Liang | AB16: 1.65 | AC16: =AB16*J16 -> 1623.6 | AE16: 已入 | AG16: =AF16-J16 -> -984 | AJ16: =J16 -> 984 | AN16: =J16 -> 984 | AQ16: =J16 -> 984 | AR16: =AR15+AQ16 -> 184474
A17: 45769 | B17: WALMART INC. | C17: 美国 | D17: 4500164334 | E17: WM PO#0906596284 /WM item#67419606 0/GTIN#101930 52079197/STK# 71152 | F17: 4500164334-90 | G17: 71152-S002-2 | H17: 71152-S002 | I17: 机械速龙 | J17: 588 | K17: 0 | L17: 3 | M17: =J17/L17 -> 196 | N17: 45818 | O17: 45814 | P17: 6/11BV | Q17: 换单 | T17: 否 | U17: 71152箱唛排版可follow PO#4500163167 | V17: 无 | W17: 无 | X17: 45769 | Z17: 日期码格式：ZURU DGYYMMDD CHINA(日期避开周末和法定节假日） 日期：按实际生产日期 Packaging Info: "1.包装信息： 71152：MA 1L 彩盒+ MA 说明书" Remark: "71152： 2. 此单为散箱出货，外箱印刷RFID箱唛（四面右下角印ZURU logo并要有""""Made in China"""" 字样, 外箱一面正唛直接印刷订单内容（从每行remark处获取）， 不再贴贴纸)。 3. 在产品和包装上要有日期码、以及要有MADE IN CHINA和ZURU字样. 4. 产品如有扎带口要剪平，不能刮手. 5. 3pcs /CTN；not include 2pcs AAA battery. 6. 此单需要验货，烦请多备包装物料 7. 每PCS要加RFID 贴纸，严格按照我们提供的位置图，不可擅自调整位置，贴纸也不可有任何破损或折坏，不可淋湿!!" | AA17: Lorraine Liang | AB17: 1.65 | AC17: =AB17*J17 -> 970.2 | AE17: 已入 | AG17: =AF17-J17 -> -588 | AJ17: =J17 -> 588 | AN17: =J17 -> 588 | AQ17: =J17 -> 588 | AR17: =AR16+AQ17 -> 185062
A18: 45769 | B18: WALMART INC. | C18: 美国 | D18: 4500164334 | E18: WM PO#0906596287 /WM item#67419606 0/GTIN#101930 52079197/STK# 71152 | F18: 4500164334-100 | G18: 71152-S002-2 | H18: 71152-S002 | I18: 机械速龙 | J18: 756 | K18: 0 | L18: 3 | M18: =J18/L18 -> 252 | N18: 45818 | O18: 45814 | P18: 6/11BV | Q18: 换单 | T18: 否 | U18: 71152箱唛排版可follow PO#4500163167 | V18: 无 | W18: 无 | X18: 45769 | Z18: 日期码格式：ZURU DGYYMMDD CHINA(日期避开周末和法定节假日） 日期：按实际生产日期 Packaging Info: "1.包装信息： 71152：MA 1L 彩盒+ MA 说明书" Remark: "71152： 2. 此单为散箱出货，外箱印刷RFID箱唛（四面右下角印ZURU logo并要有""""Made in China"""" 字样, 外箱一面正唛直接印刷订单内容（从每行remark处获取）， 不再贴贴纸)。 3. 在产品和包装上要有日期码、以及要有MADE IN CHINA和ZURU字样. 4. 产品如有扎带口要剪平，不能刮手. 5. 3pcs /CTN；not include 2pcs AAA battery. 6. 此单需要验货，烦请多备包装物料 7. 每PCS要加RFID 贴纸，严格按照我们提供的位置图，不可擅自调整位置，贴纸也不可有任何破损或折坏，不可淋湿!!" | AA18: Lorraine Liang | AB18: 1.65 | AC18: =AB18*J18 -> 1247.4 | AE18: 已入 | AG18: =AF18-J18 -> -756 | AJ18: =J18 -> 756 | AN18: =J18 -> 756 | AQ18: =J18 -> 756 | AR18: =AR17+AQ18 -> 185818
A19: 45769 | B19: WALMART INC. | C19: 美国 | D19: 4500164340 | E19: WM PO#0906596275 /WM item#67419606 0/GTIN#101930 52079197/STK# 71152 | F19: 4500164340-30 | G19: 71152-S002-2 | H19: 71152-S002 | I19: 机械速龙 | J19: 1095 | K19: 0 | L19: 3 | M19: =J19/L19 -> 365 | N19: 45825 | O19: 45821 | P19: 6/18BV | Q19: 换单 | T19: 否 | U19: 71152箱唛排版可follow PO#4500163167 | V19: 无 | W19: 无 | X19: 45769 | Z19: 日期码格式：ZURU DGYYMMDD CHINA(日期避开周末和法定节假日） 日期：按实际生产日期 Packaging Info: "1.包装信息： 71152：MA 1L 彩盒+ MA 说明书" Remark: "71152： 2. 此单为散箱出货，外箱印刷RFID箱唛（四面右下角印ZURU logo并要有""""Made in China"""" 字样, 外箱一面正唛直接印刷订单内容（从每行remark处获取）， 不再贴贴纸)。 3. 在产品和包装上要有日期码、以及要有MADE IN CHINA和ZURU字样. 4. 产品如有扎带口要剪平，不能刮手. 5. 3pcs /CTN；not include 2pcs AAA battery. 6. 此单需要验货，烦请多备包装物料 7. 每PCS要加RFID 贴纸，严格按照我们提供的位置图，不可擅自调整位置，贴纸也不可有任何破损或折坏，不可淋湿!!" | AA19: Lorraine Liang | AB19: 1.65 | AC19: =AB19*J19 -> 1806.75 | AE19: 已入 | AG19: =AF19-J19 -> -1095 | AJ19: =J19 -> 1095 | AN19: =J19 -> 1095 | AQ19: =J19 -> 1095 | AR19: =取消單!AR11+AQ19 -> 152422
A20: 45769 | B20: WALMART INC. | C20: 美国 | D20: 4500164340 | E20: WM PO#0906596277 /WM item#67419606 0/GTIN#101930 52079197/STK# 71152 | F20: 4500164340-40 | G20: 71152-S002-2 | H20: 71152-S002 | I20: 机械速龙 | J20: 723 | K20: 0 | L20: 3 | M20: =J20/L20 -> 241 | N20: 45825 | O20: 45821 | P20: 6/18BV | Q20: 换单 | T20: 否 | U20: 71152箱唛排版可follow PO#4500163167 | V20: 无 | W20: 无 | X20: 45769 | Z20: 日期码格式：ZURU DGYYMMDD CHINA(日期避开周末和法定节假日） 日期：按实际生产日期 Packaging Info: "1.包装信息： 71152：MA 1L 彩盒+ MA 说明书" Remark: "71152： 2. 此单为散箱出货，外箱印刷RFID箱唛（四面右下角印ZURU logo并要有""""Made in China"""" 字样, 外箱一面正唛直接印刷订单内容（从每行remark处获取）， 不再贴贴纸)。 3. 在产品和包装上要有日期码、以及要有MADE IN CHINA和ZURU字样. 4. 产品如有扎带口要剪平，不能刮手. 5. 3pcs /CTN；not include 2pcs AAA battery. 6. 此单需要验货，烦请多备包装物料 7. 每PCS要加RFID 贴纸，严格按照我们提供的位置图，不可擅自调整位置，贴纸也不可有任何破损或折坏，不可淋湿!!" | AA20: Lorraine Liang | AB20: 1.65 | AC20: =AB20*J20 -> 1192.95 | AE20: 已入 | AG20: =AF20-J20 -> -723 | AJ20: =J20 -> 723 | AN20: =J20 -> 723 | AQ20: =J20 -> 723 | AR20: =AR19+AQ20 -> 153145
A21: 45776 | B21: WALMART INC. | C21: 美国 | D21: 4500165272 | E21: WM PO#0906596258 /WM item#67419606 0/GTIN#101930 52079197/STK# 71152 | F21: 4500165272-20 | G21: 71152-S002-2 | H21: 71152-S002 | I21: 机械速龙 | J21: 1053 | K21: 0 | L21: 3 | M21: =J21/L21 -> 351 | N21: 45832 | O21: 45828 | P21: 6/25BV | Q21: 换单 | T21: 否 | U21: 箱唛排版可follow PO#4500163167 | V21: 无 | W21: 每PCS要加RFID 贴纸 | Z21: 日期码格式：ZURU DGYYMMDD CHINA(日期避开周末和法定节假日） 日期：按实际生产日期 Packaging Info: "1.包装信息： 71152：MA 1L 彩盒+ MA 说明书" Remark: "71152： 2. 此单为散箱出货，外箱印刷RFID箱唛（四面右下角印ZURU logo并要有""""Made in China"""" 字样, 外箱一面正唛直接印刷订单内容（从每行remark处获取）， 不再贴贴纸)。 3. 在产品和包装上要有日期码、以及要有MADE IN CHINA和ZURU字样. 4. 产品如有扎带口要剪平，不能刮手. 5. 3pcs /CTN；not include 2pcs AAA battery. 6. 此单需要验货，烦请多备包装物料 7. 每PCS要加RFID 贴纸，严格按照我们提供的位置图，不可擅自调整位置，贴纸也不可有任何破损或折坏，不可淋湿!!" | AA21: Lorraine Liang | AB21: 1.65 | AC21: =AB21*J21 -> 1737.45 | AE21: 已入 | AG21: =AF21-J21 -> -1053 | AJ21: =J21 -> 1053 | AN21: =J21 -> 1053 | AQ21: =J21 -> 1053 | AR21: ='71152'!AS137+AQ21 -> 164140
A22: 45776 | B22: WALMART INC. | C22: 美国 | D22: 4500165272 | E22: WM PO#0906596224 /WM item#67419606 0/GTIN#101930 52079197/STK# 71152 | F22: 4500165272-50 | G22: 71152-S002-2 | H22: 71152-S002 | I22: 机械速龙 | J22: 687 | K22: 0 | L22: 3 | M22: =J22/L22 -> 229 | N22: 45832 | O22: 45828 | P22: 6/25BV | Q22: 换单 | T22: 否 | U22: 箱唛排版可follow PO#4500163167 | V22: 无 | W22: 每PCS要加RFID 贴纸 | Z22: 日期码格式：ZURU DGYYMMDD CHINA(日期避开周末和法定节假日） 日期：按实际生产日期 Packaging Info: "1.包装信息： 71152：MA 1L 彩盒+ MA 说明书" Remark: "71152： 2. 此单为散箱出货，外箱印刷RFID箱唛（四面右下角印ZURU logo并要有""""Made in China"""" 字样, 外箱一面正唛直接印刷订单内容（从每行remark处获取）， 不再贴贴纸)。 3. 在产品和包装上要有日期码、以及要有MADE IN CHINA和ZURU字样. 4. 产品如有扎带口要剪平，不能刮手. 5. 3pcs /CTN；not include 2pcs AAA battery. 6. 此单需要验货，烦请多备包装物料 7. 每PCS要加RFID 贴纸，严格按照我们提供的位置图，不可擅自调整位置，贴纸也不可有任何破损或折坏，不可淋湿!!" | AA22: Lorraine Liang | AB22: 1.65 | AC22: =AB22*J22 -> 1133.55 | AE22: 已入 | AG22: =AF22-J22 -> -687 | AJ22: =J22 -> 687 | AN22: =J22 -> 687 | AQ22: =J22 -> 687 | AR22: =AR21+AQ22 -> 164827
A23: 45776 | B23: WALMART INC. | C23: 美国 | D23: 4500165272 | E23: WM PO#0906596271 /WM item#67419606 0/GTIN#101930 52079197/STK# 71152 | F23: 4500165272-60 | G23: 71152-S002-2 | H23: 71152-S002 | I23: 机械速龙 | J23: 909 | K23: 0 | L23: 3 | M23: =J23/L23 -> 303 | N23: 45832 | O23: 45828 | P23: 6/25BV | Q23: 换单 | T23: 否 | U23: 箱唛排版可follow PO#4500163167 | V23: 无 | W23: 每PCS要加RFID 贴纸 | Z23: 日期码格式：ZURU DGYYMMDD CHINA(日期避开周末和法定节假日） 日期：按实际生产日期 Packaging Info: "1.包装信息： 71152：MA 1L 彩盒+ MA 说明书" Remark: "71152： 2. 此单为散箱出货，外箱印刷RFID箱唛（四面右下角印ZURU logo并要有""""Made in China"""" 字样, 外箱一面正唛直接印刷订单内容（从每行remark处获取）， 不再贴贴纸)。 3. 在产品和包装上要有日期码、以及要有MADE IN CHINA和ZURU字样. 4. 产品如有扎带口要剪平，不能刮手. 5. 3pcs /CTN；not include 2pcs AAA battery. 6. 此单需要验货，烦请多备包装物料 7. 每PCS要加RFID 贴纸，严格按照我们提供的位置图，不可擅自调整位置，贴纸也不可有任何破损或折坏，不可淋湿!!" | AA23: Lorraine Liang | AB23: 1.65 | AC23: =AB23*J23 -> 1499.85 | AE23: 已入 | AG23: =AF23-J23 -> -909 | AJ23: =J23 -> 909 | AN23: =J23 -> 909 | AQ23: =J23 -> 909 | AR23: =AR22+AQ23 -> 165736
A24: 45776 | B24: WALMART INC. | C24: 美国 | D24: 4500165272 | E24: WM PO#0906596267 /WM item#67419606 0/GTIN#101930 52079197/STK# 71152 | F24: 4500165272-90 | G24: 71152-S002-2 | H24: 71152-S002 | I24: 机械速龙 | J24: 639 | K24: 0 | L24: 3 | M24: =J24/L24 -> 213 | N24: 45832 | O24: 45828 | P24: 6/25BV | Q24: 换单 | T24: 否 | U24: 箱唛排版可follow PO#4500163167 | V24: 无 | W24: 每PCS要加RFID 贴纸 | Z24: 日期码格式：ZURU DGYYMMDD CHINA(日期避开周末和法定节假日） 日期：按实际生产日期 Packaging Info: "1.包装信息： 71152：MA 1L 彩盒+ MA 说明书" Remark: "71152： 2. 此单为散箱出货，外箱印刷RFID箱唛（四面右下角印ZURU logo并要有""""Made in China"""" 字样, 外箱一面正唛直接印刷订单内容（从每行remark处获取）， 不再贴贴纸)。 3. 在产品和包装上要有日期码、以及要有MADE IN CHINA和ZURU字样. 4. 产品如有扎带口要剪平，不能刮手. 5. 3pcs /CTN；not include 2pcs AAA battery. 6. 此单需要验货，烦请多备包装物料 7. 每PCS要加RFID 贴纸，严格按照我们提供的位置图，不可擅自调整位置，贴纸也不可有任何破损或折坏，不可淋湿!!" | AA24: Lorraine Liang | AB24: 1.65 | AC24: =AB24*J24 -> 1054.35 | AE24: 已入 | AG24: =AF24-J24 -> -639 | AJ24: =J24 -> 639 | AN24: =J24 -> 639 | AQ24: =J24 -> 639 | AR24: =AR23+AQ24 -> 166375
A25: 45776 | B25: WALMART INC. | C25: 美国 | D25: 4500165272 | E25: WM PO#0906596280 /WM item#67419606 0/GTIN#101930 52079197/STK# 71152 | F25: 4500165272-100 | G25: 71152-S002-2 | H25: 71152-S002 | I25: 机械速龙 | J25: 1002 | K25: 0 | L25: 3 | M25: =J25/L25 -> 334 | N25: 45832 | O25: 45828 | P25: 6/25BV | Q25: 换单 | T25: 否 | U25: 箱唛排版可follow PO#4500163167 | V25: 无 | W25: 每PCS要加RFID 贴纸 | Z25: 日期码格式：ZURU DGYYMMDD CHINA(日期避开周末和法定节假日） 日期：按实际生产日期 Packaging Info: "1.包装信息： 71152：MA 1L 彩盒+ MA 说明书" Remark: "71152： 2. 此单为散箱出货，外箱印刷RFID箱唛（四面右下角印ZURU logo并要有""""Made in China"""" 字样, 外箱一面正唛直接印刷订单内容（从每行remark处获取）， 不再贴贴纸)。 3. 在产品和包装上要有日期码、以及要有MADE IN CHINA和ZURU字样. 4. 产品如有扎带口要剪平，不能刮手. 5. 3pcs /CTN；not include 2pcs AAA battery. 6. 此单需要验货，烦请多备包装物料 7. 每PCS要加RFID 贴纸，严格按照我们提供的位置图，不可擅自调整位置，贴纸也不可有任何破损或折坏，不可淋湿!!" | AA25: Lorraine Liang | AB25: 1.65 | AC25: =AB25*J25 -> 1653.3 | AE25: 已入 | AG25: =AF25-J25 -> -1002 | AJ25: =J25 -> 1002 | AN25: =J25 -> 1002 | AQ25: =J25 -> 1002 | AR25: =AR24+AQ25 -> 167377
A26: 45792 | B26: WALMART INC. | C26: 美国 | D26: 4500166491 | E26: WM PO#0906596240 /WM item#67419606 0/GTIN#101930 52079197/STK# 71152 | F26: 4500166491-30 | G26: 71152-S002-2 | H26: 71152-S002 | I26: 机械速龙 | J26: 1518 | K26: 0 | L26: 3 | M26: =J26/L26 -> 506 | N26: 45841 | O26: =N26-3 -> 45838 | P26: 7、4BV验货 | Q26: 换单 | T26: 否 | U26: 箱唛排版可follow PO#4500163167 | V26: 无 | W26: 45802 | Z26: 日期码格式：ZURU DGYYMMDD CHINA(日期避开周末和法定节假日） 日期：按实际生产日期 Packaging Info: "1.包装信息： 71152：MA 1L 彩盒+ MA 说明书" Remark: "71152： 2. 此单为散箱出货，外箱印刷RFID箱唛（四面右下角印ZURU logo并要有""""Made in China"""" 字样, 外箱一面正唛直接印刷订单内容（从每行remark处获取）， 不再贴贴纸)。 3. 在产品和包装上要有日期码、以及要有MADE IN CHINA和ZURU字样. 4. 产品如有扎带口要剪平，不能刮手. 5. 3pcs /CTN；not include 2pcs AAA battery. 6. 此单需要验货，烦请多备包装物料 7. 每PCS要加RFID 贴纸，严格按照我们提供的位置图，不可擅自调整位置，贴纸也不可有任何破损或折坏，不可淋湿!!" | AA26: Lorraine Liang | AB26: 1.6015 | AC26: =AB26*J26 -> 2431.077 | AE26: 已入 | AG26: =AF26-J26 -> -1518 | AJ26: =J26 -> 1518 | AN26: =J26 -> 1518 | AQ26: =J26 -> 1518 | AR26: =AR28+AQ26 -> 179254
A27: 45792 | B27: WALMART INC. | C27: 美国 | D27: 4500166491 | E27: WM PO# 0906596272/WM item#67419606 0/GTIN#101930 52079197/STK# 71152 | F27: 4500166491-50 | G27: 71152-S002-2 | H27: 71152-S002 | I27: 机械速龙 | J27: 774 | K27: 0 | L27: 3 | M27: =J27/L27 -> 258 | N27: 45841 | O27: =N27-3 -> 45838 | P27: 7、4BV验货 | Q27: 换单 | T27: 否 | U27: 箱唛排版可follow PO#4500163167 | V27: 无 | W27: 45802 | Z27: 日期码格式：ZURU DGYYMMDD CHINA(日期避开周末和法定节假日） 日期：按实际生产日期 Packaging Info: "1.包装信息： 71152：MA 1L 彩盒+ MA 说明书" Remark: "71152： 2. 此单为散箱出货，外箱印刷RFID箱唛（四面右下角印ZURU logo并要有""""Made in China"""" 字样, 外箱一面正唛直接印刷订单内容（从每行remark处获取）， 不再贴贴纸)。 3. 在产品和包装上要有日期码、以及要有MADE IN CHINA和ZURU字样. 4. 产品如有扎带口要剪平，不能刮手. 5. 3pcs /CTN；not include 2pcs AAA battery. 6. 此单需要验货，烦请多备包装物料 7. 每PCS要加RFID 贴纸，严格按照我们提供的位置图，不可擅自调整位置，贴纸也不可有任何破损或折坏，不可淋湿!!" | AA27: Lorraine Liang | AB27: 1.6801 | AC27: =AB27*J27 -> 1300.3974 | AE27: 已入 | AG27: =AF27-J27 -> -774 | AJ27: =J27 -> 774 | AN27: =J27 -> 774 | AQ27: =J27 -> 774 | AR27: ='71152'!AS155+AQ27 -> 176563
A28: 45792 | B28: WALMART INC. | C28: 美国 | D28: 4500166491 | E28: WM PO#0906596279 /WM item#67419606 0/GTIN#101930 52079197/STK# 71152 | F28: 4500166491-60 | G28: 71152-S002-2 | H28: 71152-S002 | I28: 机械速龙 | J28: 1173 | K28: 0 | L28: 3 | M28: =J28/L28 -> 391 | N28: 45841 | O28: =N28-3 -> 45838 | P28: 7、4BV验货 | Q28: 换单 | T28: 否 | U28: 箱唛排版可follow PO#4500163167 | V28: 无 | W28: 45802 | Z28: 日期码格式：ZURU DGYYMMDD CHINA(日期避开周末和法定节假日） 日期：按实际生产日期 Packaging Info: "1.包装信息： 71152：MA 1L 彩盒+ MA 说明书" Remark: "71152： 2. 此单为散箱出货，外箱印刷RFID箱唛（四面右下角印ZURU logo并要有""""Made in China"""" 字样, 外箱一面正唛直接印刷订单内容（从每行remark处获取）， 不再贴贴纸)。 3. 在产品和包装上要有日期码、以及要有MADE IN CHINA和ZURU字样. 4. 产品如有扎带口要剪平，不能刮手. 5. 3pcs /CTN；not include 2pcs AAA battery. 6. 此单需要验货，烦请多备包装物料 7. 每PCS要加RFID 贴纸，严格按照我们提供的位置图，不可擅自调整位置，贴纸也不可有任何破损或折坏，不可淋湿!!" | AA28: Lorraine Liang | AB28: 1.6015 | AC28: =AB28*J28 -> 1878.5595 | AE28: 已入 | AG28: =AF28-J28 -> -1173 | AJ28: =J28 -> 1173 | AN28: =J28 -> 1173 | AQ28: =J28 -> 1173 | AR28: =AR27+AQ28 -> 177736
A29: 45796 | B29: WALMART INC. | C29: 美国 | D29: 4500166492 | E29: WM PO# 0906596257/WM item#67419606 0/GTIN#101930 52079197/STK# 71152 | F29: 4500166492-50 | G29: 71152-S002-2 | H29: 71152-S002 | I29: 机械速龙 | J29: 735 | K29: 0 | L29: 3 | M29: =J29/L29 -> 245 | N29: 45848 | O29: 45845 | P29: 7/11BV | Q29: 换单 | T29: 否 | U29: 箱唛排版可follow PO#4500163167 | V29: 无 | W29: RFID 贴纸 | Z29: 日期码格式：ZURU DGYYMMDD CHINA(日期避开周末和法定节假日） 日期：按实际生产日期 Packaging Info: "1.包装信息： 71152：MA 1L 彩盒+ MA 说明书" Remark: "71152： 2. 此单为散箱出货，外箱印刷RFID箱唛（四面右下角印ZURU logo并要有""""Made in China"""" 字样, 外箱一面正唛直接印刷订单内容（从每行remark处获取）， 不再贴贴纸)。 3. 在产品和包装上要有日期码、以及要有MADE IN CHINA和ZURU字样. 4. 产品如有扎带口要剪平，不能刮手. 5. 3pcs /CTN；not include 2pcs AAA battery. 6. 此单需要验货，烦请多备包装物料 7. 每PCS要加RFID 贴纸，严格按照我们提供的位置图，不可擅自调整位置，贴纸也不可有任何破损或折坏，不可淋湿!!" | AA29: Lorraine Liang | AB29: 1.6015 | AC29: =AB29*J29 -> 1177.1025 | AE29: 已入 | AJ29: =J29 -> 735 | AN29: =J29 -> 735 | AQ29: =J29 -> 735 | AR29: =取消單!AR37+AQ29 -> 207810
A30: 45796 | B30: WALMART INC. | C30: 美国 | D30: 4500166492 | E30: WM PO#0906596262 /WMitem#67419606 0/GTIN#101930 52079197/STK# 71152 | F30: 4500166492-60 | G30: 71152-S002-2 | H30: 71152-S002 | I30: 机械速龙 | J30: 1443 | K30: 0 | L30: 3 | M30: =J30/L30 -> 481 | N30: 45848 | O30: 45845 | P30: 7/11BV | Q30: 换单 | T30: 否 | U30: 箱唛排版可follow PO#4500163167 | V30: 无 | W30: RFID 贴纸 | Z30: 日期码格式：ZURU DGYYMMDD CHINA(日期避开周末和法定节假日） 日期：按实际生产日期 Packaging Info: "1.包装信息： 71152：MA 1L 彩盒+ MA 说明书" Remark: "71152： 2. 此单为散箱出货，外箱印刷RFID箱唛（四面右下角印ZURU logo并要有""""Made in China"""" 字样, 外箱一面正唛直接印刷订单内容（从每行remark处获取）， 不再贴贴纸)。 3. 在产品和包装上要有日期码、以及要有MADE IN CHINA和ZURU字样. 4. 产品如有扎带口要剪平，不能刮手. 5. 3pcs /CTN；not include 2pcs AAA battery. 6. 此单需要验货，烦请多备包装物料 7. 每PCS要加RFID 贴纸，严格按照我们提供的位置图，不可擅自调整位置，贴纸也不可有任何破损或折坏，不可淋湿!!" | AA30: Lorraine Liang | AB30: 1.5932 | AC30: =AB30*J30 -> 2298.9876 | AE30: 已入 | AJ30: =J30 -> 1443 | AN30: =J30 -> 1443 | AQ30: =J30 -> 1443 | AR30: =AR29+AQ30 -> 209253
A31: 45796 | B31: WALMART INC. | C31: 美国 | D31: 4500166492 | E31: WM PO# 0906596282/WM item#67419606 0/GTIN#101930 52079197/STK# 71152 | F31: 4500166492-70 | G31: 71152-S002-2 | H31: 71152-S002 | I31: 机械速龙 | J31: 975 | K31: 0 | L31: 3 | M31: =J31/L31 -> 325 | N31: 45848 | O31: 45845 | P31: 7/11BV | Q31: 换单 | T31: 否 | U31: 箱唛排版可follow PO#4500163167 | V31: 无 | W31: RFID 贴纸 | Z31: 日期码格式：ZURU DGYYMMDD CHINA(日期避开周末和法定节假日） 日期：按实际生产日期 Packaging Info: "1.包装信息： 71152：MA 1L 彩盒+ MA 说明书" Remark: "71152： 2. 此单为散箱出货，外箱印刷RFID箱唛（四面右下角印ZURU logo并要有""""Made in China"""" 字样, 外箱一面正唛直接印刷订单内容（从每行remark处获取）， 不再贴贴纸)。 3. 在产品和包装上要有日期码、以及要有MADE IN CHINA和ZURU字样. 4. 产品如有扎带口要剪平，不能刮手. 5. 3pcs /CTN；not include 2pcs AAA battery. 6. 此单需要验货，烦请多备包装物料 7. 每PCS要加RFID 贴纸，严格按照我们提供的位置图，不可擅自调整位置，贴纸也不可有任何破损或折坏，不可淋湿!!" | AA31: Lorraine Liang | AB31: 1.6015 | AC31: =AB31*J31 -> 1561.4625 | AE31: 已入 | AJ31: =J31 -> 975 | AN31: =J31 -> 975 | AQ31: =J31 -> 975 | AR31: =AR30+AQ31 -> 210228
A32: 45796 | B32: WALMART INC. | C32: 美国 | D32: 4500166492 | E32: WM PO# 0906596276/WM item#67419606 0/GTIN#101930 52079197/STK# 71152 | F32: 4500166492-80 | G32: 71152-S002-2 | H32: 71152-S002 | I32: 机械速龙 | J32: 918 | K32: 0 | L32: 3 | M32: =J32/L32 -> 306 | N32: 45848 | O32: 45845 | P32: 7/11BV | Q32: 换单 | T32: 否 | U32: 箱唛排版可follow PO#4500163167 | V32: 无 | W32: RFID 贴纸 | Z32: 日期码格式：ZURU DGYYMMDD CHINA(日期避开周末和法定节假日） 日期：按实际生产日期 Packaging Info: "1.包装信息： 71152：MA 1L 彩盒+ MA 说明书" Remark: "71152： 2. 此单为散箱出货，外箱印刷RFID箱唛（四面右下角印ZURU logo并要有""""Made in China"""" 字样, 外箱一面正唛直接印刷订单内容（从每行remark处获取）， 不再贴贴纸)。 3. 在产品和包装上要有日期码、以及要有MADE IN CHINA和ZURU字样. 4. 产品如有扎带口要剪平，不能刮手. 5. 3pcs /CTN；not include 2pcs AAA battery. 6. 此单需要验货，烦请多备包装物料 7. 每PCS要加RFID 贴纸，严格按照我们提供的位置图，不可擅自调整位置，贴纸也不可有任何破损或折坏，不可淋湿!!" | AA32: Lorraine Liang | AB32: 1.5932 | AC32: =AB32*J32 -> 1462.5576 | AE32: 已入 | AJ32: =J32 -> 918 | AN32: =J32 -> 918 | AQ32: =J32 -> 918 | AR32: =AR31+AQ32 -> 211146
A33: 45749 | B33: WALMART INC. | C33: 美国 | D33: 4500162378 | E33: WM PO#0906596265 /WM item#67419606 0/GTIN#101930 52079197/STK# 71152 | F33: 4500162378-20 | G33: 71152-S002-2 | H33: 71152-S002 | I33: 机械速龙 | J33: 816 | K33: 0 | L33: 3 | M33: =J33/L33 -> 272 | N33: 45792 | O33: 45789 | P33: 5/16抽板 | Q33: PASS | T33: 是 | U33: 45749 | V33: 无 | W33: 45761 | Y33: ZURU DGYYMMDD CHINA(日期避开周末和法定节假日） | Z33: 日期码格式：ZURU DGYYMMDD CHINA(日期避开周末和法定节假日） 日期：按实际生产日期 Packaging Info: "1.包装信息： 71152：MA 1L 彩盒+ MA 说明书 Remark: "71152： 2. 此单为散箱出货，外箱印刷RFID箱唛（四面右下角印ZURU logo并要有""""Made in China"""" 字样, 外箱一面正唛直接印刷订单内容（从每行remark处获取）， 不再贴贴纸)。 3. 在产品和包装上要有日期码、以及要有MADE IN CHINA和ZURU字样. 4. 产品如有扎带口要剪平，不能刮手. 5. 3pcs /CTN；not include 2pcs AAA battery. 6. 此单需要验货，烦请多备包装物料 7. 每PCS要加RFID 贴纸，严格按照我们提供的位置图，不可擅自调整位置，贴纸也不可有任何破损或折坏，不可淋湿!!" 8.此款需要签样，请最晚在4/20前让我们收到6pcs样板，收到后会回签1pcs以备抽板验货用。 此款需要产中抽板和测试，WMPO#0906596265 计划5/16安排抽板，需完成至少504pcs，其中4pcs需要在抽板完当天寄给实验室。 | AA33: Elena | AB33: 2.75 | AC33: =AB33*J33 -> 2244 | AE33: 已入 | AF33: 816 | AG33: =AF33-J33 -> 0 | AJ33: =J33 -> 816 | AN33: =J33 -> 816 | AQ33: =J33 -> 816 | AR33: ='71152'!AS43+AQ33 -> 37572
A34: 45757 | B34: WALMART INC. | C34: 美国 | D34: 4500163167 | E34: WM PO#0906596286 /WM item#67419606 0/GTIN#101930 52079197/STK# 71152 | F34: 4500163167-40 | G34: 71152-S002-2 | H34: 71152-S002 | I34: 机械速龙 | J34: 501 | K34: 0 | L34: 3 | M34: =J34/L34 -> 167 | N34: 45804 | O34: 45800 | Q34: PASS | T34: 否 | U34: 45757 | V34: 无 | W34: 无 | Z34: 日期码格式：ZURU DGYYMMDD CHINA(日期避开周末和法定节假日） 日期：按实际生产日期 Packaging Info: "1.包装信息： 71152：MA 1L 彩盒+ MA 说明书 Remark: "71152： 2. 此单为散箱出货，外箱印刷RFID箱唛（四面右下角印ZURU logo并要有""""Made in China"""" 字样, 外箱一面正唛直接印刷订单内容（从每行remark处获取）， 不再贴贴纸)。 3. 在产品和包装上要有日期码、以及要有MADE IN CHINA和ZURU字样. 4. 产品如有扎带口要剪平，不能刮手. 5. 3pcs /CTN；not include 2pcs AAA battery. 6. 此单需要验货，烦请多备包装物料 7. 每PCS要加RFID 贴纸，严格按照我们提供的位置图，不可擅自调整位置，贴纸也不可有任何破损或折坏，不可淋湿!!" | AA34: Elena | AB34: 2.75 | AC34: =AB34*J34 -> 1377.75 | AE34: 已入 | AF34: 501 | AG34: =AF34-J34 -> 0 | AJ34: =J34 -> 501 | AN34: =J34 -> 501 | AQ34: =J34 -> 501 | AR34: =取消單!AR35+AQ34 -> 68940
A35: 45757 | B35: WALMART INC. | C35: 美国 | D35: 4500163167 | E35: WM PO#0906596247 /WM item#67419606 0/GTIN#101930 52079197/STK# 71152 | F35: 4500163167-30 | G35: 71152-S002-2 | H35: 71152-S002 | I35: 机械速龙 | J35: 774 | K35: 0 | L35: 3 | M35: =J35/L35 -> 258 | N35: 45804 | O35: 45800 | P35: 5/28BV | Q35: PASS | T35: 否 | U35: 45757 | V35: 无 | W35: 无 | Z35: 日期码格式：ZURU DGYYMMDD CHINA(日期避开周末和法定节假日） 日期：按实际生产日期 Packaging Info: "1.包装信息： 71152：MA 1L 彩盒+ MA 说明书 Remark: "71152： 2. 此单为散箱出货，外箱印刷RFID箱唛（四面右下角印ZURU logo并要有""""Made in China"""" 字样, 外箱一面正唛直接印刷订单内容（从每行remark处获取）， 不再贴贴纸)。 3. 在产品和包装上要有日期码、以及要有MADE IN CHINA和ZURU字样. 4. 产品如有扎带口要剪平，不能刮手. 5. 3pcs /CTN；not include 2pcs AAA battery. 6. 此单需要验货，烦请多备包装物料 7. 每PCS要加RFID 贴纸，严格按照我们提供的位置图，不可擅自调整位置，贴纸也不可有任何破损或折坏，不可淋湿!!" | AA35: Elena | AB35: 2.75 | AC35: =AB35*J35 -> 2128.5 | AE35: 已入 | AF35: 774 | AG35: =AF35-J35 -> 0 | AJ35: =J35 -> 774 | AN35: =J35 -> 774 | AQ35: =J35 -> 774 | AR35: ='71152'!AS69+AQ35 -> 68439
A36: 45632 | B36: DM LLC | C36: 俄罗斯联邦 | D36: 4500153295 | E36: 出 Bekasovo 2 | F36: 4500153295-10 | G36: 71152-S001 | H36: 71152-S001 | I36: 机械速龙 | J36: 3246 | K36: 0 | L36: 6 | M36: =J36/L36 -> 541 | N36: 45817 | O36: 45813 | P36: 暂停生产 | T36: 否 | U36: 45701 | V36: 无 | W36: 进口商贴纸翻4500153227+EAN条码贴纸翻4500153227 | Y36: 外箱不要打ZURU标准日期码！胶件可以打日期码。 | Z36: 日期码格式：外包装/外箱不要打ZURU标准日期码 日期： Packaging Info: 注意 ：外包装 (指: 收缩膜/彩卡/铝箔袋/挂卡/PDQ) /外箱不要打ZURU标准日期码！胶件可以打日期码。 71152: MA 1L彩卡+进口商贴纸翻4500153227+EAN条码贴纸翻4500153227，MA说明书/指南(如有) 。 Remark: 标准配比 ； 请按期完货， 会有罚金。 出港口Bekasovo 2。 | AA36: Ann Zhang | AB36: 2.7 | AC36: =AB36*J36 -> 8764.2 | AE36: 已入 | AG36: =AF36-J36 -> -3246 | AJ36: =J36 -> 3246 | AN36: =J36 -> 3246 | AQ36: =J36 -> 3246 | AR36: ='71152'!AS87+AQ36 -> 124791
A37: 45632 | B37: DM LLC | C37: 俄罗斯联邦 | D37: 4500153374 | F37: 4500153374-10 | G37: 71152-S001 | H37: 71152-S001 | I37: 机械速龙 | J37: 4134 | K37: 0 | L37: 6 | M37: =J37/L37 -> 689 | N37: 45847 | O37: 45843 | Q37: 暂停生产 | T37: 否 | U37: 45701 | V37: 无 | W37: 45708 | Y37: 外箱不要打ZURU标准日期码！胶件可以打日期码。 | Z37: 日期码格式：外包装/外箱不要打ZURU标准日期码 日期： Packaging Info: 注意 ：外包装 (指: 收缩膜/彩卡/铝箔袋/挂卡/PDQ) /外箱不要打ZURU标准日期码！胶件可以打日期码。 71152: MA 1L彩卡+进口商贴纸翻4500153227+EAN条码贴纸翻4500153227，MA说明书/指南(如有) 。 Remark: 标准配比 ； 请按期完货， 会有罚金。 出港口Bekasovo 2 | AA37: Ann Zhang | AB37: 2.7 | AC37: =AB37*J37 -> 11161.8 | AE37: 已入 | AG37: =AF37-J37 -> -4134 | AJ37: =J37 -> 4134 | AN37: =J37 -> 4134 | AQ37: =J37 -> 4134 | AR37: ='71152'!AS185+AQ37 -> 207075
A38: 45928 | B38: ZURU SPAIN S.L. | C38: 西班牙 | D38: 4500180519 | E38: 5200007779 5200007784 | F38: 4500180519-70 | G38: 71152-S001-3L | H38: 71152-S001-MTS | I38: 机械速龙 | J38: 402 | K38: 0 | L38: 6 | M38: =J38/L38 -> 67 | N38: 45988 | O38: 45985 | U38: 45947 | V38: 无 | W38: 一张意大利环保标贴纸+ WEEE不带电池出货欧洲通用30L说明书B版（贴纸 翻4500162314 | Z38: 日期码格式：ZURU INC(BVI) 标准格式 日期：按实际生产日期 Packaging Info: 6. 71152:最新MA 3L EAN（23L warning）彩盒+最新MA 5L说明书+一张葡萄牙语说明书纸+ 一张意大利环保标贴纸+ WEEE不带电池出货欧洲通用30L说明书B版（贴纸 翻4500162314） Remark: 1.西班牙国家内销单，需要通过ZURU 验货结果后才能出货 (工厂需要主动提前同ZURU QC预约验货避免延期出货造成不必要麻烦)； 2.本订单所有 具有 baby items / assorted items 的款式，零售包装上都要用 母 EAN; 外包装警语/说明书都需要有西班牙语+葡萄牙语（简写"PT"或"P"） 3. 若有特定款有特殊外箱条码要求时,需要明确列出产品款对应的具体外箱条码号码/条码类型 (若无,可以忽略此需求) 4. 所有出口欧洲的产品, 法规规定禁止在包装和共公众用的印刷品中使用矿物油中含有的物质, 包装印刷油墨中含有的MOAH/MOSH的质量浓度不能超过1%, 否则出 货到西班牙被抽检出现问题, 供应商需要对此负责; 5. Date code: 外箱/产品/包装尽量保持一致，完货后提供date code 信息以便我们保存记录做批次管理；若MA物料因提前备料导致和外箱日期码不一致时，可以接 受出货 6. 装柜时需要按照款式号码从小到大一款款依次装,避免终端仓库卸货混乱.若一个柜子涉及到几个不同国家内销单,装柜时需要一个国家装完后再装另一个国家的 产品,依次装柜,避免终端仓库因不同国家不同库位位置卸货混乱. (此点需要同工厂装柜人员强调) 7. 所有带电池的产品请基于带/不带电池出货自行订购 "WEEE说明书欧洲EN+30L-B版"。 8. MTS所有订单，SMASHERS 或含Slime产品，所有化合物使用无硼版本出；如有香味产品，出无香版本; BOB系列要符合欧洲要求不含亚硝酸版本; XShot Hyper系列 ，统一出EN71版本；Slime Mart统一用EUR版本的包装。 9. 请每款寄一套给Lisa Yang 用于上传西班牙网站, 以下是地址和联系方式，样品相关细节请与Lisa沟通@Lisa Yang - Merchandising <(>&<)> Operations <(> <<)>Lisa.ywx@zuru.com>. Lisa.Yang (+86) 755 6688 1988 – 3327| +86 15012613809 广东省深圳市罗湖区东门南路1006号口岸大楼A座7楼 | AA38: Jade Wang | AB38: 2.6717 | AC38: =AB38*J38 -> 1074.0234 | AE38: 已入 | AG38: =AF38-J38 -> -402 | AK38: =J38 -> 402 | AN38: =J38 -> 402 | AQ38: =J38 -> 402 | AR38: ='71152'!AS432+AQ38 -> 460964
A39: 45964 | B39: ESAL TRADING L.L.C. | C39: 阿拉伯联合酋长国 | D39: 4500180717 | E39: UAE | F39: 4500180717-180 | G39: 71152-S001 | H39: 71152-S001 | I39: 机械速龙 | J39: 600 | K39: 0 | L39: 6 | M39: =J39/L39 -> 100 | N39: 46006 | O39: 46004 | Q39: PASS | U39: 45973 | V39: 无 | W39: 进口商贴纸 (含G Mark, QR code, 阿拉伯警语); 贴纸上的QR code需微信可扫，贴纸(说明书贴纸翻单4500162345) | Z39: 日期码格式：ZURU INC(BVI) 标准格式 日期：按实际生产日期 Packaging Info: 71152: MA 1L 收缩膜+进口商贴纸 (含G Mark, QR code, 阿拉伯警语)( 贴纸翻单4500162474); 贴纸上的QR code需微信可扫，扫描结果另外通知; 收缩膜上UPC条 码为193052079190；说明书+贴纸(说明书贴纸翻单4500162345); 产品年龄3+； 客人箱唛排版，印4面，条码内容193052079190； 需要增加一张WEEE声明（不带电池走货版本的通用30L说明书） Remark: | AA39: Nora Pan | AB39: 2.7663 | AC39: =AB39*J39 -> 1659.78 | AE39: 已入 | AG39: 600 | AH39: =AG39-J39 -> 0 | AK39: =J39 -> 600 | AO39: =J39 -> 600 | AR39: =J39 -> 600 | AS39: ='71152'!AS448+AR39 -> 478700
A40: 46038 | B40: DOLGENCORP, LLC | C40: 美国 | D40: 4500191701 | E40: 29BLM0 | F40: 4500191701-10 | H40: 71152-S005-PKC | I40: 机械速龙 | J40: 5004 | K40: 0 | L40: 6 | M40: =J40/L40 -> 834 | N40: 46090 | O40: 46086 | U40: 箱唛翻单4500164352 | V40: 无 | W40: 无 | Y40: 产品日期码： DOLGEN31328101D26 （打在dino上） | Z40: 日期码格式：DOLLAR GENERAL 格式日期码 日期： Packaging Info: 1.包装：客版包装+ZURU MA说明书，优先1L.（跟单邮件提供AWS） Remark: 1.包装：客版包装+ZURU MA说明书，优先1L.（跟单邮件提供AWS） 客户要求： "产品和包装不能含有PFAS 物质以及1,4 dioxane" 客户指定实验室做测试，请确保产品可以过美国标准ASTM F963-23测试。 必须是双坑外箱. 2.日期码：产品和包装上必须有客版格式日期码。 客版包装AWs上已印有客版日期码和客版UPC#，大货前需核对好这些信息，包装无需额外打ZURU日期码了。但是产品上需打客版日期码。 (1) 包装日期码（已印在包装UPC码旁边竖排那里，无需额外添加），内容如 31328101D26 ; (2)产品日期码： DOLGEN31328101D26 （打在dino上） (3)UPC条形码：430001727086 3. 无价贴。 4. 无样板需求 5. 验货抽样事宜： 3月10日早上进行客人指定TUV的VT抽测试样，随机抽取每款每色各12pcs + 足量干漆给实验室MTS ， 请在3月9前完成ZURU QC验货，并当天14点前提供验货报告+大货图片给跟单。 6. 箱唛：此客人要求严格，外箱不接受水贴纸，材积以及重量必须按照以下要求，否则不符会导致验货fail从而影响货期而产生罚款。大货外箱材积绝对不可大于 下述数据，材积只接受3%的变小；重量正负不得超过以下列出数据的5%，接受外箱以印章方式印上实际毛重。 大货外箱材积必须不能大于 1.46cbf（0.0413cbm），外箱毛重不能超过6.0lbs（2.71kgs）。如有变化，请收单后2周内告知跟单评估是否可行。 箱唛不需要印ZURU格式日期码，不需要印外箱环保标识。箱唛翻4500164352 重要提示：客人强制要求大货外箱必须是双层瓦楞纸的，否则会导致第三方验货fail，产生返工和罚款。 7.此客人不接受任何理由的延期，会有高额罚金产生. 8.如散货入仓需在货车上加防护网. 9.出货配比：ZURU MA配比 10. 内袋需要警示语，警示语内容为以下，内袋打孔，并用胶纸封口，因客户以内袋为单位往每家店分配。封住内袋口防止产品散落出来。 WARNING: TO AVOID DANGER OF SUFFOCATION, KEEP THIS BAG AWAY FROM BABIES AND CHILDREN. DO NOT USE IN CRIBS, BEDS, STROLLERS OR PLAY PENS. THIS B AG IS NOT A TOY. 内袋翻4500130706 | AA40: Hailey Yu | AB40: 1.5439 | AC40: =AB40*J40 -> 7725.6756 | AH40: =AG40-J40 -> -5004 | AM40: =J40 -> 5004 | AO40: =J40 -> 5004 | AR40: =J40 -> 5004 | AS40: =AS36+AR40 -> 5004
A41: 46015 | B41: TESCO CE | C41: 斯洛瓦克 | D41: 4500189742 | E41: 999-61860 | F41: 4500189742-30 | G41: 71152-S001 | H41: 71152-S001 | I41: 机械速龙 | J41: 1002 | K41: 0 | L41: 6 | M41: =J41/L41 -> 167 | N41: 46080 | O41: 46076 | U41: 46029 | V41: 无 | W41: 无 | Z41: 日期码格式：ZURU INC(BVI) 标准格式 日期：按实际生产日期 Packaging Info: 71152： MA B版1L彩卡含4国警告语(Czech-Hugarian-Polish-Slovak）+WEEE不带电池走货欧洲30语通用黑白说明书，UPC#193052079190，请先检查包装条码是否正 确再安排做货； Remark: 1.此单出欧洲国家，需满足EU测试标准，微塑料需满足EU法规要求； 2.产品及包装需要印CE <(>&<)> UKCA图标，包装需要有ZURU UK LTD/ZURU France地址信息，QC同事请核查，如有问题与跟单确认； 3.裝櫃必須按TPND順序(TPND的号码由大到小或由小到大) (條形碼貼紙或正嘜必須要朝外向車門外)； 4. 外箱上有条码要求，排版时请留意并请确保条码清晰可扫描（封箱胶不要黏到条码上), 否则客人会有罚款； 5.如含硼的话， 需用低硼版本(小于300ppm),硼含量需要符合欧洲标准,否则客人会退货有罚款产生; 6.标准配比； 7.货物不能用打包带缠绕外箱，否则会影响目的港派送及可能产生额外的拆打包带费用 | AA41: Grace He | AB41: 2.5407 | AC41: =AB41*J41 -> 2545.7814 | AE41: 已入 | AH41: =AG41-J41 -> -1002 | AK41: =J41 -> 1002 | AO41: =J41 -> 1002 | AR41: =J41 -> 1002 | AS41: =AS38+AR41 -> 1002
A42: 46028 | B42: DOLGENCORP, LLC | C42: 美国 | D42: 4500190696 | E42: 293MN2 | F42: 4500190696-10 | H42: 71152-S005-PKC | I42: 机械速龙 | J42: 13440 | K42: 0 | L42: 6 | M42: =J42/L42 -> 2240 | N42: 46085 | O42: =N42-4 -> 46081 | P42: 3月5日早上进行客人指定TUV的CT抽测试样+100%大货验货，随机抽取每款每色各12pcs + 足量干漆给实验室MTS ，2-3套封样。 请在3月4前完成ZURU QC验货，并当天14点前提供验货报告+大货图片给跟单。 | U42: 箱唛翻单4500164352 | V42: 无 | W42: 无 | Z42: 日期码格式：DOLLAR GENERAL 格式日期码 日期： Packaging Info: 1.包装：客版包装+ZURU MA说明书，优先1L.（跟单邮件提供AWS） Remark: 1.包装：客版包装+ZURU MA说明书，优先1L.（跟单邮件提供AWS） 客户要求： "产品和包装不能含有PFAS 物质以及1,4 dioxane" 客户指定实验室做测试，请确保产品可以过美国标准ASTM F963-23测试。 必须是双坑外箱. 2.日期码：产品和包装上必须有客版格式日期码。 客版包装AWs上已印有客版日期码和客版UPC#，大货前需核对好这些信息，包装无需额外打ZURU日期码了。但是产品上需打客版日期码。 (1) 包装日期码（已印在包装UPC码旁边竖排那里，无需额外添加），内容如 31328101C26 ; (2)产品日期码： DOLGEN31328101C26 （打在dino上） (3)UPC条形码：430001727086 3. 无价贴。 4. 样板：请尽力在2月1日前提供6套产前确认样，（确保产前样所有信息及质量务必同大货） .寄给ZURU深圳跟单Minny /hailey转寄客人签样。（跟单确认样板无 误后才可开始大货）。 5. 验货抽样事宜： 3月5日早上进行客人指定TUV的CT抽测试样+100%大货验货，随机抽取每款每色各12pcs + 足量干漆给实验室MTS ，2-3套封样。 请在3月4前完成ZURU QC验货，并当天14点前提供验货报告+大货图片给跟单。 6. 箱唛：此客人要求严格，外箱不接受水贴纸，材积以及重量必须按照以下要求，否则不符会导致验货fail从而影响货期而产生罚款。大货外箱材积绝对不可大于 下述数据，材积只接受3%的变小；重量正负不得超过以下列出数据的5%，接受外箱以印章方式印上实际毛重。 大货外箱材积必须不能大于 1.46cbf（0.0413cbm），外箱毛重不能超过6.0lbs（2.71kgs）。如有变化，请收单后2周内告知跟单评估是否可行。 箱唛不需要印ZURU格式日期码，不需要印外箱环保标识。 重要提示：客人强制要求大货外箱必须是双层瓦楞纸的，否则会导致第三方验货fail，产生返工和罚款。 7.此客人不接受任何理由的延期，会有高额罚金产生. 8.如散货入仓需在货车上加防护网. 9.出货配比：ZURU MA配比 10. 内袋需要警示语，警示语内容为以下，内袋打孔，并用胶纸封口，因客户以内袋为单位往每家店分配。封住内袋口防止产品散落出来。 WARNING: TO AVOID DANGER OF SUFFOCATION, KEEP THIS BAG AWAY FROM BABIES AND CHILDREN. DO NOT USE IN CRIBS, BEDS, STROLLERS OR PLAY PENS. THIS B AG IS NOT A TOY. 内袋翻4500130706 | AA42: Hailey Yu | AB42: 1.6437 | AC42: =AB42*J42 -> 22091.328 | AH42: =AG42-J42 -> -13440 | AM42: =J42 -> 13440 | AO42: =J42 -> 13440 | AR42: =J42 -> 13440 | AS42: =AS38+AR42 -> 13440
A43: 46028 | B43: DOLGENCORP, LLC | C43: 美国 | D43: 4500190696 | E43: 293MX8 | F43: 4500190696-20 | H43: 71152-S005-PKC | I43: 机械速龙 | J43: 10002 | K43: 0 | L43: 6 | M43: =J43/L43 -> 1667 | N43: 46085 | O43: =N43-4 -> 46081 | P43: 3月5日早上进行客人指定TUV的CT抽测试样+100%大货验货，随机抽取每款每色各12pcs + 足量干漆给实验室MTS ，2-3套封样。 请在3月4前完成ZURU QC验货，并当天14点前提供验货报告+大货图片给跟单。 | U43: 箱唛翻单4500164352 | V43: 无 | W43: 无 | Z43: 日期码格式：DOLLAR GENERAL 格式日期码 日期： Packaging Info: 1.包装：客版包装+ZURU MA说明书，优先1L.（跟单邮件提供AWS） Remark: 1.包装：客版包装+ZURU MA说明书，优先1L.（跟单邮件提供AWS） 客户要求： "产品和包装不能含有PFAS 物质以及1,4 dioxane" 客户指定实验室做测试，请确保产品可以过美国标准ASTM F963-23测试。 必须是双坑外箱. 2.日期码：产品和包装上必须有客版格式日期码。 客版包装AWs上已印有客版日期码和客版UPC#，大货前需核对好这些信息，包装无需额外打ZURU日期码了。但是产品上需打客版日期码。 (1) 包装日期码（已印在包装UPC码旁边竖排那里，无需额外添加），内容如 31328101C26 ; (2)产品日期码： DOLGEN31328101C26 （打在dino上） (3)UPC条形码：430001727086 3. 无价贴。 4. 样板：请尽力在2月1日前提供6套产前确认样，（确保产前样所有信息及质量务必同大货） .寄给ZURU深圳跟单Minny /hailey转寄客人签样。（跟单确认样板无 误后才可开始大货）。 5. 验货抽样事宜： 3月5日早上进行客人指定TUV的CT抽测试样+100%大货验货，随机抽取每款每色各12pcs + 足量干漆给实验室MTS ，2-3套封样。 请在3月4前完成ZURU QC验货，并当天14点前提供验货报告+大货图片给跟单。 6. 箱唛：此客人要求严格，外箱不接受水贴纸，材积以及重量必须按照以下要求，否则不符会导致验货fail从而影响货期而产生罚款。大货外箱材积绝对不可大于 下述数据，材积只接受3%的变小；重量正负不得超过以下列出数据的5%，接受外箱以印章方式印上实际毛重。 大货外箱材积必须不能大于 1.46cbf（0.0413cbm），外箱毛重不能超过6.0lbs（2.71kgs）。如有变化，请收单后2周内告知跟单评估是否可行。 箱唛不需要印ZURU格式日期码，不需要印外箱环保标识。 重要提示：客人强制要求大货外箱必须是双层瓦楞纸的，否则会导致第三方验货fail，产生返工和罚款。 7.此客人不接受任何理由的延期，会有高额罚金产生. 8.如散货入仓需在货车上加防护网. 9.出货配比：ZURU MA配比 10. 内袋需要警示语，警示语内容为以下，内袋打孔，并用胶纸封口，因客户以内袋为单位往每家店分配。封住内袋口防止产品散落出来。 WARNING: TO AVOID DANGER OF SUFFOCATION, KEEP THIS BAG AWAY FROM BABIES AND CHILDREN. DO NOT USE IN CRIBS, BEDS, STROLLERS OR PLAY PENS. THIS B AG IS NOT A TOY. 内袋翻4500130706 | AA43: Hailey Yu | AB43: 1.6437 | AC43: =AB43*J43 -> 16440.287 | AH43: =AG43-J43 -> -10002 | AM43: =J43 -> 10002 | AO43: =J43 -> 10002 | AR43: =J43 -> 10002 | AS43: =AS39+AR43 -> 488702
