Workbook

Sheet 樣板單
A1: ZURU Rainbocorn 樣板訂單 | V1: 1代珠片公仔#9201 | AE1: 2代珠片公仔#9202 | AN1: #9204 | AW1: #9214 | BE1: #9209 | BV1: #9202 | CI1: #9204 | CO1: #9214（第二代） | CU1: #9209 | CX1: #9215 | DE1: #9212 | DK1: #9213 | DN1: #9207 | DO1: #9208
V2: 收縮膜 | Y2: 說明書 | AE2: 收縮膜 | AH2: 說明書 | AN2: A版本 | AP2: B版本 | BJ2: 3 | BL2: 4 | BN2: 5 | BP2: 5 | BR2: 4 | BT2: 3
A3: 香港接单日期 | B3: ZURU 跟单 | C3: ZURU PO NO# | D3: 第三方客户 PO NO# | E3: 第三方客户名称 | F3: ITEM# | G3: 中文名 | H3: PO数量 (pcs) | I3: 内箱装箱数量(pcs) | J3: 外箱装箱数量(pcs) | K3: 总箱数 | L3: 单价USD | M3: 金额USD | N3: ZURU验货 日期 | O3: 驗貨結果 | P3: 第三方客户公证行验货 | Q3: ZURU订单走货日期 | R3: ZURU确认走货日期 | S3: 箱唛资料(收到日期) | T3: 箱唛资料(确认日期) | U3: 客供贴纸AI(收到日期) | V3: MA 1語收縮膜 | W3: MA 3語收縮膜 | X3: 客版收縮膜 | Y3: MA 1語说明书 A版本 | Z3: MA 1語说明书 B版本 | AA3: MA 3語說明書 A版本 | AB3: MA 3語說明書 B版本 | AC3: 客版說明書 | AD3: 布標 | AE3: MA 1語收縮膜 | AF3: MA 3語收縮膜 | AG3: 客版收縮膜 | AH3: MA 1語说明书 A版本 | AI3: MA 1語说明书 B版本 | AJ3: MA 3語說明書 A版本 | AK3: MA 3語說明書 B版本 | AL3: 客版說明書 | AM3: 布標 | AN3: MA 1語收縮膜 | AO3: MA 1語說明書 | AP3: MA 1語收縮膜 | AQ3: MA 1語說明書 | AR3: MA 2語收縮膜（加拿大版本） | AS3: MA 2語說明書（加拿大版本） | AT3: 落加拿大 棉花泥 | AU3: 9201SQ1 | AV3: 9204UQ1 | AW3: MA 1語收縮膜 A | AX3: MA 1語收縮膜 B | AY3: MA 1語說明書 A | AZ3: MA 1語收縮膜 B | BA3: MA 1語說明書 B | BB3: MA领养卡 | BC3: 9214SQ1 MA PDQ盒 | BD3: 9214UQ1 客办PDQ盒 | BE3: MA 1語收縮膜 | BF3: MA 1語說明書 | BG3: MA 3語收縮膜 | BH3: MA 3語說明書 | BI3: 發票號 | BJ3: 玫紅猴子 Monkey（A） | BK3: 黃色猴子 Monkey（B） | BL3: 粉紅貓 Kitty （A） | BM3: 玫紅貓 Kitty （B） | BN3: 白色兔子 Rabbit （A） | BO3: 玫紅兔子 Rabbit （B） | BP3: 白色獨角獸 Unicorn （A） | BQ3: 玫紅獨角獸 Unicorn （B） | BR3: 紫色小狗 Puppy （A） | BS3: 藍色小狗 Puppy （B） | BT3: 粉色倉鼠 Hamster （A） | BU3: 橙色倉鼠 Hamster （B） | BV3: 羊駝 Llama（白色） | BW3: 羊駝 Llama（紫色） | BX3: 火烈鳥 Flamingo （玫紅色） | BY3: 火烈鳥 Flamingo （彩虹色） | BZ3: 火烈鳥 Flamingo （金色） | CA3: 熊貓 Panda （黑白色） | CB3: 熊貓 Panda （粉紅色） | CC3: 貓頭鷹 OWL （紫色） | CD3: 貓頭鷹 OWL （白色） | CE3: 獨角獸 Unicorn （白色） | CF3: 獨角獸 Unicorn （紫色） | CG3: 獅子 Lion （粉紅色） | CH3: 獅子 Lion （黃色） | CI3: 白色獨角獸 Unicorn | CJ3: 枚红色火烈鸟 Flamingo | CK3: 白色羊驼 Llama | CL3: 粉红色猫 Kitty | CM3: 紫色兔子 Bunny | CN3: 蓝色小狗 Puppy | CO3: 白色猫头鹰 White Owl | CP3: 粉色狮子 Pink Lion | CQ3: 黄色猴子 Yellow Monkey | CR3: 紫色独角兽 Purple Unicorn | CS3: 白色熊猫 White Panda | CT3: 彩色火烈鸟 Colour Flamingo | CU3: 獨角獸 Unicorn | CV3: 白色羊驼 Llama | CW3: 枚红色火烈鸟 Flamingo | CX3: 孔雀 Peacock | CY3: 火烈鸟 Toucan | CZ3: 树懒 Sloth | DA3: 大象 Elephant | DB3: 老虎 Tiger | DC3: 梅花鹿 Giraffe | DD3: 斑马 Zebra | DE3: 兔子 Bunny 含海绵 | DF3: 小狗 Puppy | DG3: 羊驼 Llama | DH3: 小猫 Kitty 含海绵 | DI3: 独角兽 Unicorn | DJ3: 猴子 Monkey | DK3: 小猫 Kitten | DL3: 独角兽 Unicorn | DM3: 大嘴鸟 Toucan | DN3: 2PK超小蛋殼公仔 | DO3: 4PK超小蛋殼公仔
A4: 43243 | B4: Binnie | C4: ZMPO18068 | F4: 9201-S001 | G4: 珠片公仔 | H4: 360 | V4: =H4 -> 360 | Y4: =H4 -> 360 | AD4: MA布標 | BI4: 19573 | BJ4: =H4/12 -> 30 | BK4: =H4/12 -> 30 | BL4: =H4/12 -> 30 | BM4: =H4/12 -> 30 | BN4: =H4/12 -> 30 | BO4: =H4/12 -> 30 | BP4: =H4/12 -> 30 | BQ4: =H4/12 -> 30 | BR4: =H4/12 -> 30 | BS4: =H4/12 -> 30 | BT4: =H4/12 -> 30 | BU4: =H4/12 -> 30
A5: 43265 | B5: Amanda | C5: ZMPO18078 | F5: 9201-S001 | G5: 珠片公仔 | H5: 480 | V5: =H5 -> 480 | Y5: =H5 -> 480 | AD5: MA布標 | BI5: 19654 | BJ5: =H5/12 -> 40 | BK5: =H5/12 -> 40 | BL5: =H5/12 -> 40 | BM5: =H5/12 -> 40 | BN5: =H5/12 -> 40 | BO5: =H5/12 -> 40 | BP5: =H5/12 -> 40 | BQ5: =H5/12 -> 40 | BR5: =H5/12 -> 40 | BS5: =H5/12 -> 40 | BT5: =H5/12 -> 40 | BU5: =H5/12 -> 40
A6: 43265 | B6: Angela | C6: 4500010393 | E6: 簽板 | F6: 9201-S001 | G6: 珠片公仔 | H6: 36 | V6: =H6 -> 36 | Y6: =H6 -> 36 | AD6: MA布標 | BJ6: =H6/12 -> 3 | BK6: =H6/12 -> 3 | BL6: =H6/12 -> 3 | BM6: =H6/12 -> 3 | BN6: =H6/12 -> 3 | BO6: =H6/12 -> 3 | BP6: =H6/12 -> 3 | BQ6: =H6/12 -> 3 | BR6: =H6/12 -> 3 | BS6: =H6/12 -> 3 | BT6: =H6/12 -> 3 | BU6: =H6/12 -> 3
A7: 43265 | B7: Lingly | C7: 4500010570 | E7: GP測試版 | F7: 9201-S001 | G7: 珠片公仔 | H7: 12 | V7: =H7 -> 12 | Y7: =H7 -> 12 | AD7: MA布標 | BJ7: =H7/12 -> 1 | BK7: =H7/12 -> 1 | BL7: =H7/12 -> 1 | BM7: =H7/12 -> 1 | BN7: =H7/12 -> 1 | BO7: =H7/12 -> 1 | BP7: =H7/12 -> 1 | BQ7: =H7/12 -> 1 | BR7: =H7/12 -> 1 | BS7: =H7/12 -> 1 | BT7: =H7/12 -> 1 | BU7: =H7/12 -> 1
A8: 43265 | B8: Holly | C8: 4500009837 | E8: 寄客版 | F8: 9201-S001 | G8: 珠片公仔 | H8: 12 | V8: =H8 -> 12 | Y8: =H8 -> 12 | AD8: MA布標 | BJ8: =H8/12 -> 1 | BK8: =H8/12 -> 1 | BL8: =H8/12 -> 1 | BM8: =H8/12 -> 1 | BN8: =H8/12 -> 1 | BO8: =H8/12 -> 1 | BP8: =H8/12 -> 1 | BQ8: =H8/12 -> 1 | BR8: =H8/12 -> 1 | BS8: =H8/12 -> 1 | BT8: =H8/12 -> 1 | BU8: =H8/12 -> 1
A9: 43270 | B9: Sara | C9: 郵件 | E9: Candide客户样品 | F9: 9201-S001 | G9: 珠片公仔 | H9: 6 | V9: =H9 -> 6 | Y9: =H9 -> 6 | AD9: MA布標 | BJ9: 1 | BL9: 1 | BN9: 1 | BP9: 1 | BR9: 1 | BT9: 1
A10: 43270 | B10: Sara | C10: 4500010598 | E10: WABRO | F10: 9201-S001 | G10: 珠片公仔 | H10: 24 | V10: =H10 -> 24 | Y10: =H10 -> 24 | AD10: MA布標 | BJ10: =H10/12 -> 2 | BK10: =H10/12 -> 2 | BL10: =H10/12 -> 2 | BM10: =H10/12 -> 2 | BN10: =H10/12 -> 2 | BO10: =H10/12 -> 2 | BP10: =H10/12 -> 2 | BQ10: =H10/12 -> 2 | BR10: =H10/12 -> 2 | BS10: =H10/12 -> 2 | BT10: =H10/12 -> 2 | BU10: =H10/12 -> 2
A11: 43277 | B11: Tiffany | C11: 4500010957 | D11: 大貨簽板 | E11: EURO TOYS EUROPE BV | F11: 9201-S001 | G11: 珠片公仔 | H11: 36 | X11: 36 | AC11: 36 | AD11: MA布標 | BJ11: =H11/12 -> 3 | BK11: =H11/12 -> 3 | BL11: =H11/12 -> 3 | BM11: =H11/12 -> 3 | BN11: =H11/12 -> 3 | BO11: =H11/12 -> 3 | BP11: =H11/12 -> 3 | BQ11: =H11/12 -> 3 | BR11: =H11/12 -> 3 | BS11: =H11/12 -> 3 | BT11: =H11/12 -> 3 | BU11: =H11/12 -> 3
A12: 43277 | B12: Lucky | C12: 450012096 | D12: 產前測試 | E12: CENCOSUD CHILE | F12: 9201-S001 | G12: 珠片公仔 | H12: 12 | V12: 12 | Y12: 12 | AD12: MA布標 | BJ12: =H12/12 -> 1 | BK12: =H12/12 -> 1 | BL12: =H12/12 -> 1 | BM12: =H12/12 -> 1 | BN12: =H12/12 -> 1 | BO12: =H12/12 -> 1 | BP12: =H12/12 -> 1 | BQ12: =H12/12 -> 1 | BR12: =H12/12 -> 1 | BS12: =H12/12 -> 1 | BT12: =H12/12 -> 1 | BU12: =H12/12 -> 1
A13: 43265 | B13: Lingly | C13: 4500010570 | E13: 年齡評估樣品 | F13: 9201-S001 | G13: 珠片公仔 | H13: 2 | V13: 12 | Y13: 12 | AD13: MA布標 | BN13: 1 | BO13: 1
A14: 43284 | C14: ZMPO18086 | F14: 9201-S001 | G14: 珠片公仔 | H14: 480 | V14: 480 | Y14: 480 | AD14: MA布標 | BI14: 19655 | BJ14: =H14/12 -> 40 | BK14: =H14/12 -> 40 | BL14: =H14/12 -> 40 | BM14: =H14/12 -> 40 | BN14: =H14/12 -> 40 | BO14: =H14/12 -> 40 | BP14: =H14/12 -> 40 | BQ14: =H14/12 -> 40 | BR14: =H14/12 -> 40 | BS14: =H14/12 -> 40 | BT14: =H14/12 -> 40 | BU14: =H14/12 -> 40
A15: 43286 | C15: 4500010467 | F15: 9201-S001 | G15: 珠片公仔 | H15: 10 | V15: 10 | Y15: 10 | AD15: MA布標 | BL15: 1 | BM15: 1 | BN15: 1 | BO15: 1 | BP15: 1 | BQ15: 1 | BR15: 1 | BS15: 1 | BT15: 1 | BU15: 1
A16: 43287 | C16: 4500010333 | F16: 9201-S001 | G16: 珠片公仔 | H16: 10 | V16: 10 | Y16: 10 | AD16: MA布標 | BL16: 1 | BM16: 1 | BN16: 1 | BO16: 1 | BP16: 1 | BQ16: 1 | BR16: 1 | BS16: 1 | BT16: 1 | BU16: 1
A17: 43302 | C17: 4500012533 | F17: 9201-S001 | G17: 珠片公仔 | H17: 12 | V17: 12 | Y17: 12 | AD17: MA布標 | BJ17: 1 | BK17: 1 | BL17: 1 | BM17: 1 | BN17: 1 | BO17: 1 | BP17: 1 | BQ17: 1 | BR17: 1 | BS17: 1 | BT17: 1 | BU17: 1
A18: 43302 | C18: 4500010568 | F18: 9201-S001 | G18: 珠片公仔 | H18: 4 | V18: 4 | AC18: 4 | AD18: 丹麥布標 | BJ18: 1 | BL18: 1 | BN18: 1 | BP18: 1
A19: 43306 | C19: 4500010570 | E19: GP FRANCE | F19: 9201-S001 | G19: 珠片公仔 | H19: 28 | X19: 28 | Y19: 28 | AD19: 法國布標 | BJ19: 3 | BK19: 2 | BL19: 3 | BM19: 2 | BN19: 3 | BO19: 2 | BP19: 3 | BQ19: 2 | BR19: 2 | BS19: 2 | BT19: 2 | BU19: 2
A20: 43306 | C20: 4500010574 | E20: GP ITALY | F20: 9201-S001 | G20: 珠片公仔 | H20: 25 | X20: 25 | Y20: 25 | AD20: 意大利布標 | BJ20: 2 | BK20: 2 | BL20: 2 | BM20: 2 | BN20: 2 | BO20: 2 | BP20: 3 | BQ20: 2 | BR20: 2 | BS20: 2 | BT20: 2 | BU20: 2
A21: 43313 | C21: 4500009768 | E21: TOY TRIANGLE CO.W.L.L | F21: 9201-S001 | G21: 珠片公仔 | H21: 2 | V21: 2 | Y21: 2 | AD21: MA布標 | BN21: 1 | BP21: 1
A22: 43313 | C22: 4500012277 | E22: Express Gifts Ltd | F22: 9201-S006 | G22: 珠片公仔 | H22: 10 | V22: 10 | Y22: 10 | AD22: MA布標 | BL22: 1 | BM22: 1 | BN22: 1 | BO22: 1 | BP22: 1 | BQ22: 1 | BR22: 1 | BS22: 1 | BT22: 1 | BU22: 1
A23: 43316 | C23: 4500009878 | E23: P.M.I TRADING & ENTERPRISE LTS34 | F23: 9201-S001 | G23: 珠片公仔 | H23: 2 | V23: 2 | Y23: 2 | AD23: MA布標
A24: 43318 | C24: 4500012769 | E24: TOYS kingdom | F24: 9201-S001 | G24: 珠片公仔 | H24: 2 | AD24: MA布標 | BT24: 2
A25: 43321 | C25: 4500012192 | D25: 簽板 | E25: CANDIDE IND E COM LTDA | F25: 9201-S001 | G25: 珠片公仔 | H25: 25 | X25: 25 | AC25: 25 | AD25: 巴西布標 | BJ25: 2 | BK25: 2 | BL25: 2 | BM25: 2 | BN25: 2 | BO25: 2 | BP25: 3 | BQ25: 2 | BR25: 2 | BS25: 2 | BT25: 2 | BU25: 2
A26: 43323 | C26: 4500012835 | D26: 產前測試 | E26: WAL-MART.COM | F26: 9201-S001 | G26: 珠片公仔 | H26: 18 | V26: 18 | Y26: 18 | AD26: MA布標 | BJ26: 3 | BL26: 3 | BN26: 3 | BP26: 3 | BR26: 3 | BT26: 3
A27: 43332 | C27: 4500010580 | D27: 大貨版、簽板 | E27: GP SPAIN | F27: 9201-S001 | G27: 珠片公仔 | H27: 12 | X27: 12 | Y27: 12 | AD27: 西班牙布標 | BJ27: 2 | BK27: 2 | BL27: 2 | BM27: 2 | BN27: 2 | BO27: 2 | BP27: 3 | BQ27: 2 | BR27: 2 | BS27: 2 | BT27: 2 | BU27: 2
A28: 43332 | C28: 4500011417 | D28: 大貨版、簽板 | E28: GP TURKEY | F28: 9201-S001 | G28: 珠片公仔 | H28: 12 | X28: 12 | Y28: 12 | AD28: 土耳其布標 | BJ28: 2 | BK28: 2 | BL28: 2 | BM28: 2 | BN28: 2 | BO28: 2 | BP28: 3 | BQ28: 2 | BR28: 2 | BS28: 2 | BT28: 2 | BU28: 2
A29: 43335 | C29: 4500012306 | D29: MA 3語簽板 | E29: 360 SALES SOLUTIONS INC | F29: 9201-S001 | G29: 珠片公仔 | H29: 24 | W29: 24 | AA29: 24 | AD29: MA布標 | BJ29: 2 | BK29: 2 | BL29: 2 | BM29: 2 | BN29: 2 | BO29: 2 | BP29: 2 | BQ29: 2 | BR29: 2 | BS29: 2 | BT29: 2 | BU29: 2
A30: 43336 | C30: 4500009673 | D30: 大貨樣板 | E30: B&M RETAIL LIMITED | F30: 9201-S003 | G30: 珠片公仔 | H30: 10 | V30: 10 | Y30: 10 | AD30: MA布標 | BL30: 1 | BM30: 1 | BN30: 1 | BO30: 1 | BP30: 1 | BQ30: 1 | BR30: 1 | BS30: 1 | BT30: 1 | BU30: 1
A31: 43336 | C31: 郵件 | D31: Intek 客户样品 | E31: Lucky | F31: 9201-S001 | G31: 珠片公仔 | H31: 24 | V31: 24 | Y31: 24 | AD31: MA布標 | BJ31: 2 | BK31: 2 | BL31: 2 | BM31: 2 | BN31: 2 | BO31: 2 | BP31: 2 | BQ31: 2 | BR31: 2 | BS31: 2 | BT31: 2 | BU31: 2
A32: 43342 | C32: ZMPO18108 | F32: 9201-S001 | G32: 珠片公仔 | H32: 360 | V32: 24 | Y32: 24 | BI32: 19952 | BJ32: =H32/24*3/2 -> 22.5 | BK32: =H32/24*3/2 -> 22.5 | BL32: =H32/24*4/2 -> 30 | BM32: =H32/24*4/2 -> 30 | BN32: =H32/24*5/2 -> 37.5 | BO32: =H32/24*5/2 -> 37.5 | BP32: =H32/24*5/2 -> 37.5 | BQ32: =H32/24*5/2 -> 37.5 | BR32: =H32/24*4/2 -> 30 | BS32: =H32/24*4/2 -> 30 | BT32: =H32/24*3/2 -> 22.5 | BU32: =H32/24*3/2 -> 22.5
A33: 43364 | C33: 4500011712 | D33: 大貨樣板 | E33: TARGET US | F33: 9201-S001 | G33: 珠片公仔 | H33: 9 | V33: 9 | Y33: 9 | AD33: MA布標 | BJ33: 1 | BK33: 1 | BL33: 1 | BM33: 1 | BQ33: 1 | BR33: 1 | BS33: 1 | BT33: 1 | BU33: 1
A34: 43364 | C34: 4500013372 | D34: 大貨樣板 | E34: DISTRIBUIDORA JUGUETRON S.A DE C.V | F34: 9201-S001 | G34: 珠片公仔 | H34: 2 | W34: 2 | AA34: 2 | AD34: MA布標 | BN34: 1 | BP34: 1
A35: 43369 | C35: 4500013085 | D35: 抽版 | F35: 9201-S001 | G35: 粉紅色獨角獸 | H35: 8 | V35: 8 | Y35: 8 | AD35: MA布標 | BQ35: 8
A36: 43382 | C36: 4500013648 | D36: 簽板 | F36: 9201-S001 | G36: 珠片公仔 | H36: 24 | V36: 24 | Y36: 24 | AD36: MA布標 | BJ36: 2 | BK36: 2 | BL36: 2 | BM36: 2 | BN36: 2 | BO36: 2 | BP36: 2 | BQ36: 2 | BR36: 2 | BS36: 2 | BT36: 2 | BU36: 2
A37: 43384 | C37: 4500013155 | D37: 大貨版 | F37: 9201-S001 | G37: 珠片公仔 | H37: 12 | V37: 12 | Y37: 12 | AD37: MA布標 | BJ37: 1 | BK37: 1 | BL37: 1 | BM37: 1 | BN37: 1 | BO37: 1 | BP37: 1 | BQ37: 1 | BR37: 1 | BS37: 1 | BT37: 1 | BU37: 1
A38: 43392 | C38: 4500013641 | D38: 大貨版 | F38: 9201-S001 | G38: 珠片公仔 | H38: 12 | X38: 12 | AC38: 12 | AD38: GP法國 | BJ38: 1 | BK38: 1 | BL38: 1 | BM38: 1 | BN38: 1 | BO38: 1 | BP38: 1 | BQ38: 1 | BR38: 1 | BS38: 1 | BT38: 1 | BU38: 1
A39: 43392 | C39: ZMPO18123 | D39: 樣品訂單 | F39: 9201-S001 | G39: 珠片公仔 | H39: 204 | V39: 204 | Y39: 204 | AD39: MA布標 | BJ39: 17 | BK39: 17 | BL39: 17 | BM39: 17 | BN39: 17 | BO39: 17 | BP39: 17 | BQ39: 17 | BR39: 17 | BS39: 17 | BT39: 17 | BU39: 17
A40: 43392 | C40: ZMPO18131 | D40: 樣品訂單 | F40: 9201-S001 | G40: 珠片公仔 | H40: 480 | V40: 480 | Y40: 480 | AD40: MA布標 | BJ40: 40 | BK40: 40 | BL40: 40 | BM40: 40 | BN40: 40 | BO40: 40 | BP40: 40 | BQ40: 40 | BR40: 40 | BS40: 40 | BT40: 40 | BU40: 40
A41: 43395 | C41: 4500013346 | D41: 簽板 | F41: 9201-S001 | G41: 珠片公仔 | H41: 24 | W41: 24 | Z41: 24 | AD41: MA布標 | BJ41: 2 | BK41: 2 | BL41: 2 | BM41: 2 | BN41: 2 | BO41: 2 | BP41: 2 | BQ41: 2 | BR41: 2 | BS41: 2 | BT41: 2 | BU41: 2
A42: 43417 | C42: 4500014341 | D42: 大貨樣板 | F42: 9201-S001 | G42: 珠片公仔 | H42: 2 | V42: 2 | Z42: 2 | AD42: MA布標 | BL42: 2
A43: 43419 | B43: Emily | D43: 測試樣品 | E43: C/Sam's club | F43: 9201-S001 | G43: 珠片公仔 | H43: 48 | V43: 48 | Z43: 48 | AD43: MA布標 | BJ43: 4 | BK43: 4 | BL43: 4 | BM43: 4 | BN43: 4 | BO43: 4 | BP43: 4 | BQ43: 4 | BR43: 4 | BS43: 4 | BT43: 4 | BU43: 4
A44: 43419 | B44: Emily | D44: 簽板 | E44: C/Sam's club | F44: 9201-S001 | G44: 珠片公仔 | H44: 24 | V44: 24 | Z44: 24 | AD44: MA布標 | BJ44: 2 | BK44: 2 | BL44: 2 | BM44: 2 | BN44: 2 | BO44: 2 | BP44: 2 | BQ44: 2 | BR44: 2 | BS44: 2 | BT44: 2 | BU44: 2
A45: 43427 | B45: Emily | C45: MO 20181120 | D45: 測試樣品 | E45: WMCA | F45: 9201-S001 | G45: 珠片公仔 | H45: 48 | W45: 48 | AB45: 48 | AD45: MA布標 | BJ45: 4 | BK45: 4 | BL45: 4 | BM45: 4 | BN45: 4 | BO45: 4 | BP45: 4 | BQ45: 4 | BR45: 4 | BS45: 4 | BT45: 4 | BU45: 4
A46: 43444 | B46: Ever | C46: 4500014867 | D46: 大貨版 | E46: GP法國 | F46: 9201-S001 | G46: 珠片公仔 | H46: 12 | V46: 12 | AC46: 12 | AD46: GP法國 | BJ46: 1 | BK46: 1 | BL46: 1 | BM46: 1 | BN46: 1 | BO46: 1 | BP46: 1 | BQ46: 1 | BR46: 1 | BS46: 1 | BT46: 1 | BU46: 1
A47: 43444 | B47: Ever | C47: 4500015110 | D47: 大貨版 | E47: GP西班牙 | F47: 9201-S001 | G47: 珠片公仔 | H47: 12 | V47: 12 | AC47: 12 | AD47: GP西班牙 | BJ47: 1 | BK47: 1 | BL47: 1 | BM47: 1 | BN47: 1 | BO47: 1 | BP47: 1 | BQ47: 1 | BR47: 1 | BS47: 1 | BT47: 1 | BU47: 1
A48: 43446 | B48: Aimee | C48: ZY#5700005 | D48: 筑愉 | E48: 筑愉 | F48: 9201EC-S002 | G48: 空展示櫃 | H48: 40 | BI48: 25917
A49: 43448 | B49: Emily | C49: 4500015267 | E49: SAM’S CLUB US | F49: 9201PL-S002 | G49: 珠片公仔 | H49: 48 | V49: 48 | Z49: 48 | AD49: MA布標 | BJ49: 4 | BK49: 4 | BL49: 4 | BM49: 4 | BN49: 4 | BO49: 4 | BP49: 4 | BQ49: 4 | BR49: 4 | BS49: 4 | BT49: 4 | BU49: 4
A50: 43454 | B50: Ada | C50: ZMPO18162 | D50: 樣品訂單 | E50: 庫有 | F50: 9201-S001 | G50: 珠片公仔 | H50: 480 | V50: 480 | Z50: 480 | AD50: MA布標 | BI50: 25944 | BJ50: 40 | BK50: 40 | BL50: 40 | BM50: 40 | BN50: 40 | BO50: 40 | BP50: 40 | BQ50: 40 | BR50: 40 | BS50: 40 | BT50: 40 | BU50: 40
A51: 43479 | B51: Aimee | C51: 4800007665 | D51: 筑愉 | E51: 筑愉 | F51: 9201EC-S002 | G51: 空展示櫃 | H51: 20 | BI51: 26075
A52: 43488 | B52: Aimee | C52: 4500007847 | D52: 筑愉 | E52: 筑愉 | F52: 9201EC-S002 | G52: 空展示櫃 | H52: 30 | BI52: 26074
A53: 43510 | B53: Tiffany | C53: 郵件 | E53: 廣州ITS測試版 | F53: 9201-S001 | G53: 珠片公仔 | H53: 48 | V53: =H53 -> 48 | Z53: =H53 -> 48 | AD53: MA布標 | BJ53: 4 | BK53: 4 | BL53: 4 | BM53: 4 | BN53: 4 | BO53: 4 | BP53: 4 | BQ53: 4 | BR53: 4 | BS53: 4 | BT53: 4 | BU53: 4
A54: 43514 | B54: holly | C54: 4500016381 | E54: 大貨樣板 | F54: 9201-S001 | G54: 珠片公仔 | H54: 12 | V54: 12 | Z54: 12 | AD54: MA布標 | BJ54: 1 | BK54: 1 | BL54: 1 | BM54: 1 | BN54: 1 | BO54: 1 | BP54: 1 | BQ54: 1 | BR54: 1 | BS54: 1 | BT54: 1 | BU54: 1
A55: 43518 | B55: Elaine | C55: 4500016832 | D55: 測試版 | E55: RELIANCE LIFESTYLE HOLDINGS LIMITED | F55: 9201-S001 | G55: 珠片公仔 | H55: 15 | V55: 15 | Z55: 15 | AD55: MA布標 | BJ55: 1 | BK55: 1 | BL55: 1 | BM55: 1 | BN55: 1 | BO55: 1 | BP55: 1 | BQ55: 1 | BR55: 4 | BS55: 1 | BT55: 1 | BU55: 1
A56: 43522 | B56: Christal | C56: 4500017093 | D56: WM簽板 | E56: WAL-MART STORES INC.USA | F56: 9201PL-S003 | G56: 珠片公仔 | H56: 24 | V56: 24 | Z56: 24 | AD56: MA布標 | BJ56: 2 | BK56: 2 | BL56: 2 | BM56: 2 | BN56: 2 | BO56: 2 | BP56: 2 | BQ56: 2 | BR56: 2 | BS56: 2 | BT56: 2 | BU56: 2
A57: 43522 | B57: Ever | C57: 4500016464 | E57: GP Spain | F57: 9201-S001 | G57: 珠片公仔 | H57: 12 | X57: 12 | Z57: 12 | AD57: GP西班牙 | BJ57: 1 | BK57: 1 | BL57: 1 | BM57: 1 | BN57: 1 | BO57: 1 | BP57: 1 | BQ57: 1 | BR57: 1 | BS57: 1 | BT57: 1 | BU57: 1
A58: 43529 | B58: Tiffany | C58: 4500016256 | D58: 大貨樣品 | E58: EUROPRIS | F58: 9201-S001 | G58: 珠片公仔 | H58: 24 | V58: 24 | Z58: 24 | AD58: MA布標 | BJ58: 2 | BK58: 2 | BL58: 2 | BM58: 2 | BN58: 2 | BO58: 2 | BP58: 2 | BQ58: 2 | BR58: 2 | BS58: 2 | BT58: 2 | BU58: 2
A59: 43542 | B59: Tony | C59: 郵件 | D59: BV測試版 | F59: 9201-S001 | G59: 珠片公仔 | H59: 24 | V59: 24 | Z59: 24 | AD59: MA布標 | BJ59: 2 | BK59: 2 | BL59: 2 | BM59: 2 | BN59: 2 | BO59: 2 | BP59: 2 | BQ59: 2 | BR59: 2 | BS59: 2 | BT59: 2 | BU59: 2
A60: 43573 | B60: Ever | C60: 4500018212 | D60: GP | E60: GP測試版 | F60: 9202-S001 | G60: 2代珠片公仔 | H60: 13 | AE60: 13 | AH60: 13 | AM60: MA布標 | BV60: 1 | BW60: 1 | BX60: 1 | BY60: 1 | BZ60: 1 | CA60: 1 | CB60: 1 | CC60: 1 | CD60: 1 | CE60: 1 | CF60: 1 | CG60: 1 | CH60: 1
A61: 43574 | B61: Tony | C61: 4500017981 | D61: ASDA STORES LTD | E61: 測試版 | F61: 9202-WMUS-S001 | G61: 2代珠片公仔 | H61: 33 | AE61: 33 | AH61: 33 | AM61: MA布標 | BV61: 3 | BW61: 3 | BX61: 3 | BY61: 3 | BZ61: 3 | CA61: 3 | CB61: 3 | CE61: 3 | CF61: 3 | CG61: 3 | CH61: 3
A62: 43574 | B62: Maria | C62: 450018388 | D62: TARGET AUSTRALIA PTY LTD | E62: QA測試版 | F62: 9202-S001 | G62: 2代珠片公仔 | H62: 13 | AE62: 13 | AH62: 13 | AM62: MA布標 | BV62: 1 | BW62: 1 | BX62: 1 | BY62: 1 | BZ62: 1 | CA62: 1 | CB62: 1 | CC62: 1 | CD62: 1 | CE62: 1 | CF62: 1 | CG62: 1 | CH62: 1
A63: 43574 | B63: Bella | C63: 4500016572 | D63: Express Gifts Ltd | E63: 大貨版 | F63: 9202-S005 | G63: 2代珠片公仔 | H63: 11 | AE63: 11 | AH63: 11 | AM63: MA布標 | BV63: 1 | BW63: 1 | BX63: 1 | BY63: 1 | BZ63: 1 | CA63: 1 | CB63: 1 | CE63: 1 | CF63: 1 | CG63: 1 | CH63: 1
A64: 43580 | B64: Lucky | C64: 4500017858 | D64: GRUPO RUZ | E64: 測試樣品 | F64: 9201-S001 | G64: 1代珠片公仔 | H64: 2 | V64: 2 | Z64: 2 | AD64: MA布標 | BO64: 1 | BR64: 1
A65: 43580 | B65: Lucky | C65: 4500017858 | D65: GRUPO RUZ | E65: 測試樣品 | F65: 9201-S001 | G65: 小蛋殼毛絨公仔 | H65: 2 | V65: 2 | Z65: 2 | AD65: MA布標 | CL65: 1 | CN65: 1
A66: 43580 | B66: Tony | C66: 4500018097 | D66: ASDA STORES LTD | E66: 測試版 | F66: 9204UQ3-S001 | G66: 小蛋殼毛絨公仔 | H66: 18 | AN66: =H66 -> 18 | AO66: =H66 -> 18 | CI66: 3 | CJ66: 3 | CK66: 3 | CL66: 3 | CM66: 3 | CN66: 3
A67: 43580 | B67: Holly | C67: 4500017238 | D67: Target US | E67: 大貨版 | F67: 9202-S002 | G67: 2代珠片公仔 | H67: 11 | AE67: =H67 -> 11 | AH67: =H67 -> 11 | AM67: MA布標 | BV67: 1 | BW67: 1 | BX67: 1 | BY67: 1 | BZ67: 1 | CC67: 1 | CD67: 1 | CE67: 1 | CF67: 1 | CG67: 1 | CH67: 1
A68: 43580 | B68: Holly | C68: 4500017239 | D68: Target US | E68: 大貨版 | F68: 9204UQ1-S002 | G68: 小蛋殼毛絨公仔 | H68: 6 | AN68: =H68 -> 6 | AO68: =H68 -> 6 | AV68: 1 | CI68: 1 | CJ68: 1 | CK68: 1 | CL68: 1 | CM68: 1 | CN68: 1
A69: 43580 | B69: Hailey | C69: 4500017957 | D69: DOLLAR GENERAL CORPORATION | E69: 大貨簽板 | F69: 9204-S004 | G69: 小蛋殼毛絨公仔 PDQ裝 | H69: 36 | AN69: =H69 -> 36 | AO69: =H69 -> 36 | CI69: 6 | CJ69: =CI69 -> 6 | CK69: =CJ69 -> 6 | CL69: =CK69 -> 6 | CM69: =CL69 -> 6 | CN69: =CM69 -> 6
A70: 43589 | B70: Maria | C70: 4500018388 | D70: TARGET AUSTRALIA PTY LTD | E70: 大貨簽板 | F70: 9202-S001 | G70: 2代珠片公仔 | H70: 39 | AE70: 39 | AH70: 39 | AM70: MA布標 | BV70: 3 | BW70: 3 | BX70: 3 | BY70: 3 | BZ70: 3 | CA70: 3 | CB70: 3 | CC70: 3 | CD70: 3 | CE70: 3 | CF70: 3 | CG70: 3 | CH70: 3
A71: 43589 | B71: Victoria | C71: 4500017956 | D71: WM CA | E71: 測試樣品 | F71: 9202-S001 | G71: 2代珠片公仔 | H71: 52 | AE71: 52 | AH71: 52 | AM71: MA布標 | BV71: 4 | BW71: 4 | BX71: 4 | BY71: 4 | BZ71: 4 | CA71: 4 | CB71: 4 | CC71: 4 | CD71: 4 | CE71: 4 | CF71: 4 | CG71: 4 | CH71: 4
A72: 43593 | B72: Christal | C72: 4500018397 | D72: WM US | E72: 測試樣+大貨樣 | F72: 9204UQ1-S002 | G72: 小蛋殼毛絨公仔 PDQ裝 | H72: 54 | AN72: 54 | AO72: 54 | AV72: =H72/6 -> 9 | CI72: 9 | CJ72: 9 | CK72: 9 | CL72: 9 | CM72: 9 | CN72: 9
A73: 43593 | B73: bella | C73: 4500017078 | D73: B&M | E73: 大貨版 | F73: 9204SQ1-S001 | G73: 小蛋殼毛絨公仔 | H73: 6 | AN73: 6 | AO73: 6 | CI73: 1 | CJ73: 1 | CK73: 1 | CL73: 1 | CM73: 1 | CN73: 1
A74: 43595 | B74: Ann | C74: 4500019662 | D74: Toy triangle | E74: 樣板 | F74: 9202 | G74: 2代珠片公仔 | H74: 4 | AE74: 4 | AH74: 4 | AM74: MA布標 | CA74: 1 | CB74: 1 | CG74: 1 | CH74: 1
A75: 43659 | B75: harmony | C75: 邮件 | E75: 广告样品 | F75: 9202-S001 | G75: 2代珠片公仔 | H75: 13 | AF75: 13 | AK75: 13 | BV75: 1 | BW75: 1 | BX75: 1 | BY75: 1 | BZ75: 1 | CA75: 1 | CB75: 1 | CC75: 1 | CD75: 1 | CE75: 1 | CF75: 1 | CG75: 1 | CH75: 1
A76: 43659 | B76: harmony | C76: 邮件 | E76: 广告样品 | F76: 9204-S004 | G76: 小蛋殼毛絨公仔 | H76: 6 | AO76: 6 | AQ76: 6 | CI76: 1 | CJ76: 1 | CK76: 1 | CL76: 1 | CM76: 1 | CN76: 1
A77: 43670 | B77: estate | C77: 4500020704 | D77: WM US | E77: 产前测试版 | F77: 9209-S001 | G77: 超大蛋壳 | H77: 9 | BE77: 9 | BF77: 9 | CU77: 4 | CV77: 4 | CW77: 4
A78: 43667 | B78: Lori | C78: 4500022133 | D78: TOY TRIANGLE COMPANY(UAE) | E78: 大货样板 | F78: 9209-S001 | G78: 超大蛋壳 | H78: 4 | BE78: 4 | BF78: 4 | CU78: 1 | CV78: 2 | CW78: 1
A79: 43671 | B79: Vivian | C79: 邮件 | E79: KC测试样品需求 | F79: 9209-S001 | G79: 超大蛋壳 | H79: 3 | CU79: 1 | CV79: 1 | CW79: 1
A80: 43671 | B80: Monica | C80: 4500021345 | E80: 大货样板 | F80: 9209-S001 | G80: 超大蛋壳 | H80: 1 | BE80: 1 | BF80: 1 | CW80: 1
A81: 43675 | B81: Emily | C81: 邮件 | D81: Sam's | E81: 见客版 | F81: 9202-S002 | G81: 2代珠片公仔 | H81: 18 | AE81: 2 | AH81: 2 | BV81: 2 | BW81: 2 | BX81: 2 | BY81: 2 | BZ81: 2 | CE81: 2 | CF81: 2 | CG81: 2 | CH81: 2
A82: 43672 | B82: Andy | C82: 450019786 | D82: GP | E82: 大货样板 | F82: 9202-S001 | G82: 2代珠片公仔 | H82: 13 | AE82: 13 | AH82: 13 | BV82: 1 | BW82: 1 | BX82: 1 | BY82: 1 | BZ82: 1 | CA82: 1 | CB82: 1 | CC82: 1 | CD82: 1 | CE82: 1 | CF82: 1 | CG82: 1 | CH82: 1
A83: 43678 | B83: Monica | C83: 4500019768 | D83: Colony Brands | E83: 测试样板 | F83: 9209A-S001 | G83: 火烈鸟 | H83: 1 | BE83: 1 | BF83: 1 | CW83: 1
A84: 43678 | B84: Daisy | C84: 4500022323 | D84: TOYS R US JAPAN LTD | E84: 大货样板 | F84: 9209-S001 | G84: 火烈鸟 | H84: 1 | BE84: 1 | BF84: 1 | CW84: 1
A85: 43678 | B85: Estate | C85: 4500020704 | D85: WAL-MART.COM | E85: 签版 | F85: 9209-S001 | G85: 超大蛋壳 | H85: 9 | BE85: 9 | BF85: 9 | CU85: 3 | CV85: 3 | CW85: 3
A86: 43679 | B86: Elaine | C86: 4500022498 | D86: RELIANCE LIFESTYLE HOLDINGS LIMITED | E86: 测试办 | F86: 9209-S001 | G86: 超大蛋壳 | H86: 9 | BE86: 9 | BF86: 9 | CU86: 3 | CV86: 3 | CW86: 3
A87: 43680 | B87: Holly | C87: 邮件 | D87: GSS | E87: 产前办 | F87: 9204SQ1-S001 | G87: 小蛋壳毛絨公仔 | H87: 12 | AP87: 12 | AQ87: 12 | CI87: 2 | CJ87: 2 | CK87: 2 | CL87: 2 | CM87: 2 | CN87: 2
A88: 43682 | B88: estate | C88: 4500020707 | D88: WAL-MART.COM | E88: 产中抽板 | F88: 9209-S001 | G88: 超大蛋壳 | H88: 12 | BE88: 12 | BF88: 12 | CU88: 4 | CV88: 4 | CW88: 4
A89: 43683 | B89: Estate | C89: 4500021874 | D89: WAL-MART.COM | E89: 签办 | F89: 9202-WMUS-S001 | G89: 2代珠片公仔 | H89: 22 | AE89: 22 | AH89: 22 | BV89: 2 | BW89: 2 | BX89: 2 | BY89: 2 | BZ89: 2 | CA89: 2 | CB89: 2 | CE89: 2 | CF89: 2 | CG89: 2 | CH89: 2
A90: 43683 | B90: Kalyn | C90: 4500021576 | D90: G.T. WHOLESALE LIMITED | E90: 大货办 | F90: 9202-S009 | G90: 2代珠片公仔 | H90: 13 | BV90: 1 | BW90: 1 | BX90: 1 | BY90: 1 | BZ90: 1 | CA90: 1 | CB90: 1 | CC90: 1 | CD90: 1 | CE90: 1 | CF90: 1 | CG90: 1 | CH90: 1
A91: 43686 | B91: Abbey | C91: 4500022135 | D91: THE FARMERS'TRADING COMPANY LIMITE | E91: 大货办 | F91: 9209-S001 | G91: 超大蛋壳 | H91: 3 | BE91: 3 | BF91: 3 | CU91: 1 | CV91: 1 | CW91: 1
A92: 43686 | B92: Kate | C92: 4500017857 | D92: 筑愉（深圳）贸易有限公司 | E92: 签办 | F92: 9204SQ1-S001 | G92: 小蛋殼毛絨公仔 PDQ裝 | H92: 12 | AP92: 12 | CI92: 2 | CJ92: 2 | CK92: 2 | CL92: 2 | CM92: 2 | CN92: 2
A93: 43687 | B93: IDA LI | C93: 4500022562 | D93: GP SPAIN | E93: 大货办 | F93: 9201-S001 | G93: 珠片公仔 | H93: 12 | W93: 12 | AB93: 12 | BJ93: 1 | BK93: 1 | BL93: 1 | BM93: 1 | BN93: 1 | BO93: 1 | BP93: 1 | BQ93: 1 | BR93: 1 | BS93: 1 | BT93: 1 | BU93: 1
A94: 43689 | B94: Lois | C94: 4500019647 | D94: A.S. WATSON RETAIL (HK) LIMITED | E94: 大货办 | F94: 9204SQ1-S002 | G94: 小蛋殼毛絨公仔 PDQ裝 | H94: 6 | AR94: 6 | AS94: 6 | AT94: 6 | CI94: 1 | CJ94: 1 | CK94: 1 | CL94: 1 | CM94: 1 | CN94: 1
A95: 43689 | B95: Lori | C95: 4500022128 | D95: ORBICO SP.Z O O | E95: 大货办 | F95: 9204SQ1-S001 | G95: 小蛋殼毛絨公仔 PDQ裝 | H95: 12 | AP95: 12 | AQ95: 12 | CI95: 2 | CJ95: 2 | CK95: 2 | CL95: 2 | CM95: 2 | CN95: 2
A96: 43689 | B96: Lori | C96: 4500022128 | D96: ORBICO SP.Z O O | E96: 大货办 | F96: 9202-S001 | G96: 2代珠片公仔 | H96: 4 | AE96: 4 | AI96: 4 | CA96: 1 | CD96: 1 | CF96: 1 | CH96: 1
A97: 43689 | B97: Kate | C97: 4500017361 | D97: 筑愉(深圳）贸易有限公司 | E97: 签办 | F97: 9202-S007 (A款） | G97: 2代珠片公仔 | H97: 26 | AE97: 26 | AL97: 26 | BV97: 2 | BW97: 2 | BX97: 2 | BY97: 2 | BZ97: 2 | CA97: 2 | CB97: 2 | CC97: 2 | CD97: 2 | CE97: 2 | CF97: 2 | CG97: 2 | CH97: 2
A98: 43689 | B98: Sherry | C98: 4500018407 | D98: Smyths Toys HQ UC | E98: 大货办 | F98: 9209B-S001 | G98: 羊駝 | H98: 1 | BE98: 1 | BF98: 1 | CV98: 1
A99: 43690 | B99: Angel | C99: 4500017962 | D99: WAL-MART CANADA CORP | E99: 签办 | F99: 9202A | G99: 2代珠片公仔 | H99: 1 | BV99: 1
A100: 43690 | B100: Lori | C100: 4500022128 | D100: ORBICO SP.Z O O | E100: 大货办 | F100: 9204SQ1-S001 | G100: 小蛋殼毛絨公仔 PDQ裝 | H100: 6 | AP100: 6 | AQ100: 6 | CI100: 1 | CJ100: 1 | CK100: 1 | CL100: 1 | CM100: 1 | CN100: 1
...

Sheet 92119
A1: ZURU Rainbocorn 冰雪蛋系列排期#92119
A2: 45660 | I2: （黃色表示更改或增加） | L2: （蓝色表示已完货） | P2: （綠色表示調整貨期） | AH2: 收缩膜 | AM2: 收藏指南 | AP2: 口水胶 | AU2: 吊卡 | AW2: FROZENMANIA
A3: 接单日期 | B3: 第三方客户名称 | C3: 国家 | D3: PO号 | E3: 客PO号 | F3: SKU | G3: 系统货号 | H3: ITEM# | I3: 中文名 | J3: PO数量 (pcs) | K3: 内箱装箱数量(pcs) | L3: 外箱装箱数量(pcs) | M3: 总箱数 | N3: 客PO期 | O3: 验货期 | P3: 第三方验货期 | Q3: 驗貨結果 | R3: 船期SO | S3: 箱唛资料 | T3: 外箱贴纸 | U3: 客贴纸资料 | V3: 客供物料 | W3: 日期码 | X3: 备注 | Y3: ZURU 跟单 | Z3: 单价USD | AA3: 金额USD | AB3: 送货情况 | AC3: 欠数 | AD3: 贴纸情况 | AE3: 下单情况 | AF3: 發票號 | AG3: 是否入系统 | AH3: MA 1語收縮膜 A版本 | AI3: MA 1語收縮膜 B版本 | AJ3: MA 3語收縮膜 A版本 | AK3: MA 3語收縮膜 B版本 | AL3: 客版收縮膜 | AM3: MA 5語收藏指南 | AN3: MA 5語收藏指南-B版本 | AO3: 客版收藏指南 | AP3: 有硼 | AQ3: 有硼-B版本 | AR3: 无硼 | AS3: 无硼-B版本 | AT3: 客办蓬松泥 | AU3: 客版吊卡 | AV3: 布標 | AW3: 北极熊 A Polar Bear（10） | AX3: 企鹅 B Penguin（10） | AY3: 海豹 H Seal（8） | AZ3: 雪人 Snow man（2） | BA3: 海象 D Walrus（10） | BB3: 猛犸象 E Mammoth（10） | BC3: 猫头鹰 G Owl（10） | BD3: 总数 | BE3: 相差 | BG3: 包装更替 | BH3: 客户回复
A4: 46079 | B4: TJX CANADA | C4: 加拿大 | D4: 4500194379 | E4: 40320901 | F4: 4500194379-40 | H4: 92119-S001-NB | I4: S001-NB-RAINBOCORNS-EG GZANIA-SERIES 1-FROZEN MANIA-SHRINK WRAP,12PCS/CTN | J4: 720 | L4: 12 | M4: 46135 | O4: 46129 | X4: 日期码格式：标准格式 日期：按实际生产日期 92125 MA 多语EAN版本+UPC贴纸193052083951 77731 英法客版铜版纸，upc 193052085115, MA 2L 收缩膜 多语多明书 25251 英法客版包装 UPC 845218016418 翻单4500166055 25252 客版英法彩盒和说明书。UPC号码845218016425 25253 英法客版 UPC 845218016432，彩盒翻单4500158924，说明书翻单4500166055 7153 英法客版包装 翻单4500131680， 7149 UPC193052033499 7150UPC 193052033406 MA 多语说明书 92119 无硼版本 MA 3L B 版收缩膜 +UPC 贴纸 UPC 193052078391， B 版5L 收藏指南 9258 无硼版本 MA 3L B 版收缩膜 UPC 5L多语言收藏指南193052037640 9296 无硼版本 MA 3L 收缩膜+ 多语说明书 ， UPC 193052057129 9298 无硼版本 MA C 版3L 收缩膜 +UPC 贴纸 UPC 193052057426， B 版5L 收藏指南 9548 无硼版本 MA D 版本 5L 包装+D 版本 5L 收藏指南 +UPC 贴纸 UPC 193052064196 出加拿大 有客供价格贴 每行对应不同的客户PO，唛头要一一对应， 放唛头时跟单会提供清单 Zuru验货.日期跟踪码：产品外包装及产品本身都必须有日期跟踪码，ZURU标准格式 日期码 | Y4: Katrina Xie | Z4: 3.5671 | AA4: =Z4*J4 -> 2568.312 | AK4: =J4 -> 720 | AN4: =J4 -> 720 | AQ4: =J4 -> 720 | AW4: =J4/60*10 -> 120 | AX4: =J4/60*10 -> 120
D5: ZPO2411007 | G5: 过渡 | H5: 92119-S001 | I5: 冰雪蛋 | J5: 550 | K5: 0 | L5: 12 | M5: =J5/L5 -> 45.833333 | N5: 45667 | O5: 45667 | AG5: 过渡 | AH5: =J5 -> 550 | AV5: MA布标 | AW5: =J5/60*10 -> 91.666667 | AX5: =J5/60*10 -> 91.666667 | AY5: =J5/60*8 -> 73.333333 | AZ5: =J5/60*2 -> 18.333333 | BA5: =J5/60*10 -> 91.666667 | BB5: =J5/60*10 -> 91.666667 | BC5: =J5/60*10 -> 91.666667 | BD5: =SUM(AW5:BC5) -> 550 | BE5: =J5-BD5 -> 0
A6: 46079 | B6: TJX CANADA | C6: 加拿大 | D6: 4500194379 | F6: 4500194379-150 | H6: 92119-S001-NB | I6: S001-NB-RAINBOCORNS-EG GZANIA-SERIES 1-FROZEN MANIA-SHRINK WRAP,12PCS/CTN | J6: 180 | L6: 12 | M6: 46135 | O6: 46129 | X6: 日期码格式：标准格式 日期：按实际生产日期 92125 MA 多语EAN版本+UPC贴纸193052083951 77731 英法客版铜版纸，upc 193052085115, MA 2L 收缩膜 多语多明书 25251 英法客版包装 UPC 845218016418 翻单4500166055 25252 客版英法彩盒和说明书。UPC号码845218016425 25253 英法客版 UPC 845218016432，彩盒翻单4500158924，说明书翻单4500166055 7153 英法客版包装 翻单4500131680， 7149 UPC193052033499 7150UPC 193052033406 MA 多语说明书 92119 无硼版本 MA 3L B 版收缩膜 +UPC 贴纸 UPC 193052078391， B 版5L 收藏指南 9258 无硼版本 MA 3L B 版收缩膜 UPC 5L多语言收藏指南193052037640 9296 无硼版本 MA 3L 收缩膜+ 多语说明书 ， UPC 193052057129 9298 无硼版本 MA C 版3L 收缩膜 +UPC 贴纸 UPC 193052057426， B 版5L 收藏指南 9548 无硼版本 MA D 版本 5L 包装+D 版本 5L 收藏指南 +UPC 贴纸 UPC 193052064196 出加拿大 有客供价格贴 每行对应不同的客户PO，唛头要一一对应， 放唛头时跟单会提供清单 Zuru验货.日期跟踪码：产品外包装及产品本身都必须有日期跟踪码，ZURU标准格式 日期码 | Y6: Katrina Xie | Z6: 3.5671 | AA6: =Z6*J6 -> 642.078
A7: 45657 | B7: THE WAREHOUSE LIMITED | C7: 新西兰 | D7: 4500155047 | F7: 4500155047-10 | G7: 92119-S001 | H7: 92119-S001 | I7: 冰雪蛋 | J7: 120 | K7: 0 | L7: 12 | M7: =J7/L7 -> 10 | N7: 45674 | O7: 45670 | Q7: PASS | R7: 1/19出 | S7: 1/13收到 | U7: 无 | X7: 日期码格式：ZURU INC(BVI) 标准格式 日期：按实际生产日期 Packaging Info: MA UPC 英语包装（优先1L英语版本，或者3L/5L含英语都可） 此客人不接受易掉落或者剥落或者可直接触碰的闪粉，可降解也不行，但可以接受符合欧洲微塑料标准的珠光粉或者闪片。 Remark: 7 Assortment, Polar bear: Penguin: Walrus: Mammoth: Owl: Seal: Snow man=10:10:10:10:10:8:2. Snow man is the rare item. | Y7: Abby Liang | Z7: 3.4 | AA7: =Z7*J7 -> 408 | AE7: 车间生产 | AF7: 94791-4.18 | AG7: 已入 | AH7: =J7 -> 120 | AM7: =J7 -> 120 | AP7: =J7 -> 120 | AV7: MA布标 | AW7: =J7/60*10 -> 20 | AX7: =J7/60*10 -> 20 | AY7: =J7/60*8 -> 16 | AZ7: =J7/60*2 -> 4 | BA7: =J7/60*10 -> 20 | BB7: =J7/60*10 -> 20 | BC7: =J7/60*10 -> 20 | BD7: =SUM(AW7:BC7) -> 120 | BE7: =J7-BD7 -> 0
A8: 45636 | B8: THE WAREHOUSE LIMITED | C8: 新西兰 | D8: 4500153598 | E8: 28797909 | F8: 4500153598-20 | G8: 92119-S001 | H8: 92119-S001 | I8: 冰雪蛋 | J8: 444 | K8: 0 | L8: 12 | M8: =J8/L8 -> 37 | N8: 45726 | O8: 45722 | Q8: PASS | R8: 3/20出 | S8: 12/10收到 | U8: 无 | X8: 日期码格式：ZURU INC(BVI) 标准格式 日期：按实际生产日期 Packaging Info: MA UPC 英语包装（优先1L英语版本，或者3L/5L含英语都可） 此客人不接受易掉落或者剥落或者可直接触碰的闪粉，可降解也不行，但可以接受符合欧洲微塑料标准的珠光粉或者闪片。 Remark: 92119: 7 Assortment, Polar bear: Penguin: Walrus: Mammoth: Owl: Seal: Snow man=10:10:10:10:10:8:2. Snow man is the rare item. | Y8: Abby Liang | Z8: 3.4 | AA8: =Z8*J8 -> 1509.6 | AD8: 无 | AE8: 车间生产 | AF8: 94793-4.18 | AG8: 已入 | AH8: =J8 -> 444 | AM8: =J8 -> 444 | AR8: =J8 -> 444 | AV8: MA布标 | AW8: =J8/60*10 -> 74 | AX8: =J8/60*10 -> 74 | AY8: =J8/60*8 -> 59.2 | AZ8: =J8/60*2 -> 14.8 | BA8: =J8/60*10 -> 74 | BB8: =J8/60*10 -> 74 | BC8: =J8/60*10 -> 74 | BD8: =SUM(AW8:BC8) -> 444 | BE8: =J8-BD8 -> 0
A9: 45636 | B9: THE WAREHOUSE LIMITED | C9: 新西兰 | D9: 4500153593 | E9: 28797907 | F9: 4500153593-20 | G9: 92119-S001 | H9: 92119-S001 | I9: 冰雪蛋 | J9: 1356 | K9: 0 | L9: 12 | M9: =J9/L9 -> 113 | N9: 45726 | O9: 45722 | Q9: PASS | R9: 3/20出 | S9: 12/10收到 | U9: 无 | X9: 日期码格式：ZURU INC(BVI) 标准格式 日期：按实际生产日期 Packaging Info: MA UPC 英语包装（优先1L英语版本，或者3L/5L含英语都可） 此客人不接受易掉落或者剥落或者可直接触碰的闪粉，可降解也不行，但可以接受符合欧洲微塑料标准的珠光粉或者闪片。 Remark: 92119: 7 Assortment, Polar bear: Penguin: Walrus: Mammoth: Owl: Seal: Snow man=10:10:10:10:10:8:2. Snow man is the rare item. | Y9: Abby Liang | Z9: 3.4 | AA9: =Z9*J9 -> 4610.4 | AD9: 无 | AE9: 车间生产 | AF9: 94792-4.18 | AG9: 已入 | AH9: =J9 -> 1356 | AM9: =J9 -> 1356 | AR9: =J9 -> 1356 | AV9: MA布标 | AW9: =J9/60*10 -> 226 | AX9: =J9/60*10 -> 226 | AY9: =J9/60*8 -> 180.8 | AZ9: =J9/60*2 -> 45.2 | BA9: =J9/60*10 -> 226 | BB9: =J9/60*10 -> 226 | BC9: =J9/60*10 -> 226 | BD9: =SUM(AW9:BC9) -> 1356 | BE9: =J9-BD9 -> 0
A10: 45663 | B10: DOLGENCORP, LLC | C10: 美国 | D10: 4500155298 | E10: PO#2475S8 | F10: 4500155298-10 | G10: 92119-S004-PKC | H10: 92119-S004-PKC | I10: 冰雪蛋 | J10: 76464 | K10: 0 | L10: 2 | M10: =J10/L10 -> 38232 | N10: 45733 | O10: 45729 | P10: 3/18第三方-正常出货 | Q10: PASS | S10: 1/9收到 | U10: 2/12-可移动价格贴纸 | W10: 2/12-客办收缩膜文档 + 日期码：DOLGEN41199801E25 | X10: 日期码格式：DOLLAR GENERAL 格式日期码 日期： Packaging Info: 客版1L包装 +可移动价格贴纸$15,(客AW单稍后提供) + 如果有说明书或者收藏指南优先使用ZURU MA 1L的，如没有1L请邮件告知。 Remark: 1.包装： 客版1L收缩膜 +可移动价格贴纸$18（客AW单稍后提供) + 如果有说明书或者收藏指南优先使用ZURU MA 1L的，如没有1L请邮件告知。 客户要求： "产品和包装不能含有PFAS 物质以及1,4 dioxane" 客户指定TUV来厂抽样+验货，会做实际测试。请确保产品符合美国测试标准，可以pass测试。 外箱必须是双坑的。 2.日期码：产品和包装上必须有客版格式日期码。 （1）产品上需打客版日期码 内容： DOLGEN41199801D25 D代表ETD 4月。打在蛋壳底部。 （2）包装日期码41199801D25（已印在客版包装UPC条码旁竖排文字了，无需额外做日期码在包装上）。 （3）UPC#193052078391 3. 产品包装正面右上角需要贴客版可移动价贴$18，留意蓝色圆点的色号(Blue #279C)，材质必须是可移动的，贴上不能翘起，撕下不能留胶 。 4.客户指定TUV做100%大货验货+抽样： 3月18日早上进行客人指定TUV的100%大货验货+CT抽测试样（成品12pcs带包装产品+工厂提前准备好的5套光身板，即包装里面所有的随机toys + 足量干漆或油墨涂 在同底材A4大小）。请在3月17日前完成ZURU QC验货，并当天13点前提供验货报告+大货图片给跟单。 5.样板需求，需2月17左右寄出每款每色各6套样板给ZURU跟单转寄客人。 6.箱唛：此客人要求严格，外箱不接受水贴纸，材积以及重量必须按照以下要求，否则不符会导致验货fail从而影响货期而产生罚款。 大货外箱材积绝对不可大于下述数据，材积只接受3%的变小；重量正负不得超过以下列出数据的5%，接受外箱以印章方式印上实际毛重。 大货外箱材积必须不能大于0.75CubeFeet（0.0213CBM);外箱毛重4.6LBS（2.11KGS）。 如有尺寸变小，请提前通知Cora/Minny。 重要提醒：外箱材质必须是双层瓦楞纸，不接受单层，会导致第三方验货fail以及返工和罚款。 7.此客人不接受任何理由的延期，会有高额罚金产生. 8.如散货入仓需在货车上加防护网. 9.出货配比：ZURU MA配比 。 #92119-S004-PKC-RAINBOCORNS-EGGZANIA-SERIES 1-FROZEN MANIA-SHRINK WRAP,2pcs/CTN双坑外箱 7 Assortment, Polar bear: Penguin: Walrus: Mammoth: Owl: Seal: Snow man=10:10:10:10:10:8:2. Snow man is the rare item. | Y10: Hailey Yu | Z10: 3.6812 | AA10: =Z10*J10 -> 281479.28 | AB10: =50000+5320+7280+6914+6880+9008+3440 -> 88842 | AC10: =AB10-J10 -> 12378 | AD10: OK | AE10: 系统出单 | AF10: ZB00118-4.9 ZB00119-4.10 | AG10: 已入 | AL10: =J10 -> 76464 | AM10: =J10 -> 76464 | AP10: =J10 -> 76464 | AV10: MA布标 | AW10: =J10/60*10 -> 12744 | AX10: =J10/60*10 -> 12744 | AY10: =J10/60*8 -> 10195.2 | AZ10: =J10/60*2 -> 2548.8 | BA10: =J10/60*10 -> 12744 | BB10: =J10/60*10 -> 12744 | BC10: =J10/60*10 -> 12744 | BD10: =SUM(AW10:BC10) -> 76464 | BE10: =J10-BD10 -> 0
A11: 45741 | B11: DOLGENCORP, LLC | C11: 美国 | D11: 4500155298 | E11: PO#2475S8 | F11: 4500155298-20 | G11: 92119-S004-PKC | H11: 92119-S004-PKC | I11: 冰雪蛋 | J11: 12378 | K11: 0 | L11: 2 | M11: =J11/L11 -> 6189 | N11: 45733 | O11: 45729 | P11: 3/18第三方-正常出货 | Q11: PASS | S11: 1/9收到 | U11: 2/12-可移动价格贴纸 | W11: 2/12-客办收缩膜文档 + 日期码：DOLGEN41199801E25 | X11: 日期码格式：DOLLAR GENERAL 格式日期码 日期： Packaging Info: 客版1L包装 +可移动价格贴纸$15,(客AW单稍后提供) + 如果有说明书或者收藏指南优先使用ZURU MA 1L的，如没有1L请邮件告知。 Remark: 1.包装： 客版1L收缩膜 +可移动价格贴纸$18（客AW单稍后提供) + 如果有说明书或者收藏指南优先使用ZURU MA 1L的，如没有1L请邮件告知。 客户要求： "产品和包装不能含有PFAS 物质以及1,4 dioxane" 客户指定TUV来厂抽样+验货，会做实际测试。请确保产品符合美国测试标准，可以pass测试。 外箱必须是双坑的。 2.日期码：产品和包装上必须有客版格式日期码。 （1）产品上需打客版日期码 内容： DOLGEN41199801D25 D代表ETD 4月。打在蛋壳底部。 （2）包装日期码41199801D25（已印在客版包装UPC条码旁竖排文字了，无需额外做日期码在包装上）。 （3）UPC#193052078391 3. 产品包装正面右上角需要贴客版可移动价贴$18，留意蓝色圆点的色号(Blue #279C)，材质必须是可移动的，贴上不能翘起，撕下不能留胶 。 4.客户指定TUV做100%大货验货+抽样： 3月18日早上进行客人指定TUV的100%大货验货+CT抽测试样（成品12pcs带包装产品+工厂提前准备好的5套光身板，即包装里面所有的随机toys + 足量干漆或油墨涂 在同底材A4大小）。请在3月17日前完成ZURU QC验货，并当天13点前提供验货报告+大货图片给跟单。 5.样板需求，需2月17左右寄出每款每色各6套样板给ZURU跟单转寄客人。 6.箱唛：此客人要求严格，外箱不接受水贴纸，材积以及重量必须按照以下要求，否则不符会导致验货fail从而影响货期而产生罚款。 大货外箱材积绝对不可大于下述数据，材积只接受3%的变小；重量正负不得超过以下列出数据的5%，接受外箱以印章方式印上实际毛重。 大货外箱材积必须不能大于0.75CubeFeet（0.0213CBM);外箱毛重4.6LBS（2.11KGS）。 如有尺寸变小，请提前通知Cora/Minny。 重要提醒：外箱材质必须是双层瓦楞纸，不接受单层，会导致第三方验货fail以及返工和罚款。 7.此客人不接受任何理由的延期，会有高额罚金产生. 8.如散货入仓需在货车上加防护网. 9.出货配比：ZURU MA配比 。 #92119-S004-PKC-RAINBOCORNS-EGGZANIA-SERIES 1-FROZEN MANIA-SHRINK WRAP,2pcs/CTN双坑外箱 7 Assortment, Polar bear: Penguin: Walrus: Mammoth: Owl: Seal: Snow man=10:10:10:10:10:8:2. Snow man is the rare item. | Y11: Hailey Yu | Z11: 3.5512 | AA11: =Z11*J11 -> 43956.754 | AE11: 分单 | AG11: 已入 | AL11: =J11 -> 12378 | AM11: =J11 -> 12378 | AP11: =J11 -> 12378 | AV11: MA布标 | AW11: =J11/60*10 -> 2063 | AX11: =J11/60*10 -> 2063 | AY11: =J11/60*8 -> 1650.4 | AZ11: =J11/60*2 -> 412.6 | BA11: =J11/60*10 -> 2063 | BB11: =J11/60*10 -> 2063 | BC11: =J11/60*10 -> 2063 | BD11: =SUM(AW11:BC11) -> 12378 | BE11: =J11-BD11 -> 0
A12: 45722 | D12: ZMPO250187 | F12: 92119-S001 | G12: 92119-S001 | H12: 92119-S001 | I12: 冰雪蛋 | J12: 216 | K12: 0 | L12: 12 | M12: =J12/L12 -> 18 | N12: 45736 | O12: 45733 | Q12: PASS | S12: 周转箱 | U12: 无 | X12: Remark:大货最新版本/7款平均/请按款号装箱，并在外箱上注明款号/大货标准箱装箱/箱唛请参照邮件附件;备注：收到样品订单后尽快安排 ，注意样板品质质量要求要高于大货品质要求 ，送货时必须要附带送货单(没有送货单和QC检验合格报告的仓库一律拒绝收货)，请知悉，谢谢！ | Y12: Angus | AB12: 216 | AC12: =AB12-J12 -> 0 | AE12: 系统出单 | AG12: 已入 | AH12: =J12 -> 216 | AM12: =J12 -> 216 | AP12: =J12 -> 216 | AV12: MA布标 | AW12: =J12/7 -> 30.857143 | AX12: =J12/7 -> 30.857143 | AY12: =J12/7 -> 30.857143 | AZ12: =J12/7 -> 30.857143 | BA12: =J12/7 -> 30.857143 | BB12: =J12/7 -> 30.857143 | BC12: =J12/7 -> 30.857143 | BD12: =SUM(AW12:BC12) -> 216 | BE12: 0
A13: 45716 | B13: PRO & PACIFIC CO.,LTD | C13: 台湾 | D13: 4500158781 | E13: ZU25021702 | F13: 4500158781-10 | G13: 92119-S001 | H13: 92119-S001 | I13: 冰雪蛋 | J13: 2004 | K13: 0 | L13: 12 | M13: =J13/L13 -> 167 | N13: 45741 | O13: 45737 | Q13: PASS | R13: 4/24出 | S13: 3/3收到 | U13: 3/3-进口商贴纸 | X13: 日期码格式：ZURU INC(BVI) 标准格式 日期：按实际生产日期 Packaging Info: MA 1L UPC包装+1张进口商贴纸,贴纸资料待提供 Remark: 92119-7 Assortment, Polar bear: Penguin: Walrus: Mammoth: Owl: Seal: Snow man=10:10:10:10:10:8:2. Snow man is the rare item. | Y13: Emma Wu | Z13: 3.4 | AA13: =Z13*J13 -> 6813.6 | AB13: =1968+36 -> 2004 | AC13: =AB13-J13 -> 0 | AD13: OK | AE13: 系统出单 | AF13: 94827-4.22 | AG13: 已入 | AH13: =J13 -> 2004 | AM13: =J13 -> 2004 | AP13: =J13 -> 2004 | AV13: MA布标 | AW13: =J13/60*10 -> 334 | AX13: =J13/60*10 -> 334 | AY13: =J13/60*8 -> 267.2 | AZ13: =J13/60*2 -> 66.8 | BA13: =J13/60*10 -> 334 | BB13: =J13/60*10 -> 334 | BC13: =J13/60*10 -> 334 | BD13: =SUM(AW13:BC13) -> 2004 | BE13: =J13-BD13 -> 0
A14: 45707 | B14: ZURU Germany GMBH | C14: 德国 | D14: 4500157858 | E14: 5200006149 | F14: 4500157858-100 | G14: 92119-S006-NB-3L | H14: 92119-S006-NB-MTS | I14: 冰雪蛋 | J14: 600 | K14: 0 | L14: 4 | M14: =J14/L14 -> 150 | N14: 45747 | O14: 45743 | Q14: PASS | R14: 4/3出 | S14: 2/19收到 | U14: 无 | X14: 日期码格式：ZURU INC(BVI) 标准格式 日期：按实际生产日期 Packaging Info: 92119：MA最新版3L EAN收缩膜+MA 1L+23L warning收藏指南+MA 2L布标+MA 5L复合袋 Remark: "1.德国内销单，需要通过ZURU 验货结果后才能出货 (工厂需要主动提前同ZURU QC预约验货避免延期出货造成不必要麻烦)； 2. 若有特定款有特殊外箱条码要求时,需要明确列出产品款对应的具体外箱条码号码/条码类型 (若无,可以忽略此需求) 3.所有出口欧洲的产品, 法规规定禁止在包装和共公众用的印刷品中使用矿物油中含有的物质, 包装印刷油墨中含有的MOAH/MOSH的质量浓度不能超过1%, 否则出货 到法国被抽检出现问题, 供应商需要对此负责; 4. date code: 外箱日期码要晚于或等于产品日期码，不能早于产品的日期码 5. 所有电子产品身上需要加字唛，为ZURU FRANCE 地址 (如无电子产品，或者产品布标有此地址，可忽略此信息) ZURU France 1/3, Rue d'Argenteuil 95210 SAINT-GRATIEN, FRANCE 6. 装柜时需要按照款式号码从小到大一款款依次装,避免终端仓库卸货混乱.若一个柜子涉及到几个不同国家内销单,装柜时需要一个国家装完后再装另一个国家的 产品,依次装柜,避免终端仓库因不同国家不同库位位置卸货混乱. (此点需要同工厂装柜人员强调)" | Y14: SD82 | Z14: 3.6 | AA14: =Z14*J14 -> 2160 | AB14: =596+4 -> 600 | AC14: =AB14-J14 -> 0 | AD14: 无 | AE14: 系统出单 | AF14: 94875-4.29 | AG14: 已入 | AJ14: =J14 -> 600 | AM14: =J14 -> 600 | AR14: =J14 -> 600 | AV14: MA布标 | AW14: =J14/60*10 -> 100 | AX14: =J14/60*10 -> 100 | AY14: =J14/60*8 -> 80 | AZ14: =J14/60*2 -> 20 | BA14: =J14/60*10 -> 100 | BB14: =J14/60*10 -> 100 | BC14: =J14/60*10 -> 100 | BD14: =SUM(AW14:BC14) -> 600 | BE14: =J14-BD14 -> 0
A15: 45716 | B15: ZURU Germany GMBH | C15: 德国 | D15: 4500158832 | E15: 5200006286 | F15: 4500158832-10 | G15: 92119-S006-NB-3L | H15: 92119-S006-NB-MTS | I15: 冰雪蛋 | J15: 600 | K15: 0 | L15: 4 | M15: =J15/L15 -> 150 | N15: 45754 | O15: 45750 | Q15: PASS | R15: 4/11出 | S15: 2/28收到 | U15: 无 | X15: 日期码格式：ZURU INC(BVI) 标准格式 日期：按实际生产日期 Packaging Info: 92119:MA最新版3L EAN收缩膜+MA 1L+23L warning收藏指南+MA 2L布标+MA 5L复合袋 Remark: "1.德国内销单，需要通过ZURU 验货结果后才能出货 (工厂需要主动提前同ZURU QC预约验货避免延期出货造成不必要麻烦)； 2. 若有特定款有特殊外箱条码要求时,需要明确列出产品款对应的具体外箱条码号码/条码类型 (若无,可以忽略此需求) 3.所有出口欧洲的产品, 法规规定禁止在包装和共公众用的印刷品中使用矿物油中含有的物质, 包装印刷油墨中含有的MOAH/MOSH的质量浓度不能超过1%, 否则出货 到法国被抽检出现问题, 供应商需要对此负责; 4. date code: 外箱/产品/包装 保持一致，完货后提供date code 信息以便我们保存记录做批次管理 35. 装柜时需要按照款式号码从小到大一款款依次装,避免终端仓库卸货混乱.若一个柜子涉及到几个不同国家内销单,装柜时需要一个国家装完后再装另一个国家的 产品,依次装柜,避免终端仓库因不同国家不同库位位置卸货混乱. (此点需要同工厂装柜人员强调)" | Y15: SD82 | Z15: 3.6 | AA15: =Z15*J15 -> 2160 | AB15: 600 | AC15: =AB15-J15 -> 0 | AD15: 无 | AE15: 系统出单 | AF15: 94876-4.29 | AG15: 已入 | AJ15: =J15 -> 600 | AM15: =J15 -> 600 | AR15: =J15 -> 600 | AV15: MA布标 | AW15: =J15/60*10 -> 100 | AX15: =J15/60*10 -> 100 | AY15: =J15/60*8 -> 80 | AZ15: =J15/60*2 -> 20 | BA15: =J15/60*10 -> 100 | BB15: =J15/60*10 -> 100 | BC15: =J15/60*10 -> 100 | BD15: =SUM(AW15:BC15) -> 600 | BE15: =J15-BD15 -> 0
A16: 45723 | B16: ZURU LLC | C16: 美国 | D16: 4500159464 | E16: 5200006340 | F16: 4500159464-130 | G16: 92119E-S002 | H16: 92119E-S002-MTS | I16: 猛犸象 | J16: 492 | K16: 0 | L16: 12 | M16: =J16/L16 -> 41 | N16: 45758 | O16: 45754 | Q16: PASS | R16: 4/16出 | S16: 3/10收到 | U16: UPC贴纸翻4500158580 | X16: 日期码格式：ZURU INC(BVI) 标准格式 日期：按实际生产日期 Packaging Info: #92119 MA UPC版 (1L或3L都可)+UPC贴纸, 贴纸资料翻EU单4500158580 (但不需要印刷IT环保标贴纸)A:193052083821 B:193052083838 D:193052083845 E:19305208 3852 G:193052083869 H:193052083876 Remark: 1.Amazon domestic 订单。出口美国。外箱最长边不能超过25" （超过了，case pack只能为1），不符合要求的大货，一律不接受。 2.无第三方验货/测试要求。 3.日期码使用ZURU标准版本。 | Y16: Kelly Shen/Mia Pan/P | Z16: 3.4 | AA16: =Z16*J16 -> 1672.8 | AB16: =24+468 -> 492 | AC16: =AB16-J16 -> 0 | AD16: OK | AE16: 系统出单 | AF16: ZB00145-4.16 | AG16: 已入 | AH16: =J16 -> 492 | AM16: =J16 -> 492 | AP16: =J16 -> 492 | AV16: MA布标 | BB16: =J16 -> 492 | BD16: =SUM(AW16:BC16) -> 492 | BE16: =J16-BD16 -> 0
A17: 45723 | B17: ZURU LLC | C17: 美国 | D17: 4500159464 | E17: 5200006340 | F17: 4500159464-140 | G17: 92119G-S002 | H17: 92119G-S002-MTS | I17: 猫头鹰 | J17: 492 | K17: 0 | L17: 12 | M17: =J17/L17 -> 41 | N17: 45758 | O17: 45754 | Q17: PASS | R17: 4/16出 | S17: 3/10收到 | U17: UPC贴纸翻4500158580 | X17: 日期码格式：ZURU INC(BVI) 标准格式 日期：按实际生产日期 Packaging Info: #92119 MA UPC版 (1L或3L都可)+UPC贴纸, 贴纸资料翻EU单4500158580 (但不需要印刷IT环保标贴纸)A:193052083821 B:193052083838 D:193052083845 E:19305208 3852 G:193052083869 H:193052083876 Remark: 1.Amazon domestic 订单。出口美国。外箱最长边不能超过25" （超过了，case pack只能为1），不符合要求的大货，一律不接受。 2.无第三方验货/测试要求。 3.日期码使用ZURU标准版本。 | Y17: Kelly Shen/Mia Pan/P | Z17: 3.4 | AA17: =Z17*J17 -> 1672.8 | AB17: =24+468 -> 492 | AC17: =AB17-J17 -> 0 | AD17: OK | AE17: 系统出单 | AF17: ZB00145-4.16 | AG17: 已入 | AH17: =J17 -> 492 | AM17: =J17 -> 492 | AP17: =J17 -> 492 | AV17: MA布标 | BC17: =J17 -> 492 | BD17: =SUM(AW17:BC17) -> 492 | BE17: =J17-BD17 -> 0
A18: 45723 | B18: ZURU LLC | C18: 美国 | D18: 4500159464 | E18: 5200006340 | F18: 4500159464-150 | G18: 92119B-S002 | H18: 92119B-S002-MTS | I18: 企鹅 | J18: 492 | K18: 0 | L18: 12 | M18: =J18/L18 -> 41 | N18: 45758 | O18: 45754 | Q18: PASS | R18: 4/16出 | S18: 3/10收到 | U18: UPC贴纸翻4500158580 | X18: 日期码格式：ZURU INC(BVI) 标准格式 日期：按实际生产日期 Packaging Info: #92119 MA UPC版 (1L或3L都可)+UPC贴纸, 贴纸资料翻EU单4500158580 (但不需要印刷IT环保标贴纸)A:193052083821 B:193052083838 D:193052083845 E:19305208 3852 G:193052083869 H:193052083876 Remark: 1.Amazon domestic 订单。出口美国。外箱最长边不能超过25" （超过了，case pack只能为1），不符合要求的大货，一律不接受。 2.无第三方验货/测试要求。 3.日期码使用ZURU标准版本。 | Y18: Kelly Shen/Mia Pan/P | Z18: 3.4 | AA18: =Z18*J18 -> 1672.8 | AB18: =24+468 -> 492 | AC18: =AB18-J18 -> 0 | AD18: OK | AE18: 系统出单 | AF18: ZB00145-4.16 | AG18: 已入 | AH18: =J18 -> 492 | AM18: =J18 -> 492 | AP18: =J18 -> 492 | AV18: MA布标 | AX18: =J18 -> 492 | BD18: =SUM(AW18:BC18) -> 492 | BE18: =J18-BD18 -> 0
A19: 45723 | B19: ZURU LLC | C19: 美国 | D19: 4500159464 | E19: 5200006340 | F19: 4500159464-160 | G19: 92119A-S002 | H19: 92119A-S002-MTS | I19: 北极熊 | J19: 492 | K19: 0 | L19: 12 | M19: =J19/L19 -> 41 | N19: 45758 | O19: 45754 | Q19: PASS | R19: 4/16出 | S19: 3/10收到 | U19: UPC贴纸翻4500158580 | X19: 日期码格式：ZURU INC(BVI) 标准格式 日期：按实际生产日期 Packaging Info: #92119 MA UPC版 (1L或3L都可)+UPC贴纸, 贴纸资料翻EU单4500158580 (但不需要印刷IT环保标贴纸)A:193052083821 B:193052083838 D:193052083845 E:19305208 3852 G:193052083869 H:193052083876 Remark: 1.Amazon domestic 订单。出口美国。外箱最长边不能超过25" （超过了，case pack只能为1），不符合要求的大货，一律不接受。 2.无第三方验货/测试要求。 3.日期码使用ZURU标准版本。 | Y19: Kelly Shen/Mia Pan/P | Z19: 3.4 | AA19: =Z19*J19 -> 1672.8 | AB19: =24+468 -> 492 | AC19: =AB19-J19 -> 0 | AD19: OK | AE19: 系统出单 | AF19: ZB00145-4.16 | AG19: 已入 | AH19: =J19 -> 492 | AM19: =J19 -> 492 | AP19: =J19 -> 492 | AV19: MA布标 | AW19: =J19 -> 492 | BD19: =SUM(AW19:BC19) -> 492 | BE19: =J19-BD19 -> 0
A20: 45723 | B20: ZURU LLC | C20: 美国 | D20: 4500159464 | E20: 5200006340 | F20: 4500159464-170 | G20: 92119H-S002 | H20: 92119H-S002-MTS | I20: 海豹 | J20: 492 | K20: 0 | L20: 12 | M20: =J20/L20 -> 41 | N20: 45758 | O20: 45754 | Q20: PASS | R20: 4/16出 | S20: 3/10收到 | U20: UPC贴纸翻4500158580 | X20: 日期码格式：ZURU INC(BVI) 标准格式 日期：按实际生产日期 Packaging Info: #92119 MA UPC版 (1L或3L都可)+UPC贴纸, 贴纸资料翻EU单4500158580 (但不需要印刷IT环保标贴纸)A:193052083821 B:193052083838 D:193052083845 E:19305208 3852 G:193052083869 H:193052083876 Remark: 1.Amazon domestic 订单。出口美国。外箱最长边不能超过25" （超过了，case pack只能为1），不符合要求的大货，一律不接受。 2.无第三方验货/测试要求。 3.日期码使用ZURU标准版本。 | Y20: Kelly Shen/Mia Pan/P | Z20: 3.4 | AA20: =Z20*J20 -> 1672.8 | AB20: =24+468 -> 492 | AC20: =AB20-J20 -> 0 | AD20: OK | AE20: 系统出单 | AF20: ZB00145-4.16 | AG20: 已入 | AH20: =J20 -> 492 | AM20: =J20 -> 492 | AP20: =J20 -> 492 | AV20: MA布标 | AY20: =J20 -> 492 | BD20: =SUM(AW20:BC20) -> 492 | BE20: =J20-BD20 -> 0
A21: 45723 | B21: ZURU LLC | C21: 美国 | D21: 4500159464 | E21: 5200006340 | F21: 4500159464-180 | G21: 92119D-S002 | H21: 92119D-S002-MTS | I21: 海象 | J21: 492 | K21: 0 | L21: 12 | M21: =J21/L21 -> 41 | N21: 45758 | O21: 45754 | Q21: PASS | R21: 4/16出 | S21: 3/10收到 | U21: UPC贴纸翻4500158580 | X21: 日期码格式：ZURU INC(BVI) 标准格式 日期：按实际生产日期 Packaging Info: #92119 MA UPC版 (1L或3L都可)+UPC贴纸, 贴纸资料翻EU单4500158580 (但不需要印刷IT环保标贴纸)A:193052083821 B:193052083838 D:193052083845 E:19305208 3852 G:193052083869 H:193052083876 Remark: 1.Amazon domestic 订单。出口美国。外箱最长边不能超过25" （超过了，case pack只能为1），不符合要求的大货，一律不接受。 2.无第三方验货/测试要求。 3.日期码使用ZURU标准版本。 | Y21: Kelly Shen/Mia Pan/P | Z21: 3.4 | AA21: =Z21*J21 -> 1672.8 | AB21: =24+468 -> 492 | AC21: =AB21-J21 -> 0 | AD21: OK | AE21: 系统出单 | AF21: ZB00145-4.16 | AG21: 已入 | AH21: =J21 -> 492 | AM21: =J21 -> 492 | AP21: =J21 -> 492 | AV21: MA布标 | BA21: =J21 -> 492 | BD21: =SUM(AW21:BC21) -> 492 | BE21: =J21-BD21 -> 0
A22: 45705 | B22: DIAMANT TOYS LTD | C22: 以色列 | D22: 4500153742 | E22: 56053 | F22: 4500153742-10 | G22: 92119-S001 | H22: 92119-S001 | I22: 冰雪蛋 | J22: 3480 | K22: 0 | L22: 12 | M22: =J22/L22 -> 290 | N22: 45761 | O22: 45757 | Q22: PASS | R22: 4/18出 | S22: 2/20收到 | U22: 2/17-进口商贴纸+彩色贴纸 | X22: 日期码格式：ZURU INC(BVI) 标准格式 日期：按实际生产日期 Packaging Info: 92119:1L MA收缩膜+进口商贴纸+彩色贴纸; MA指南 Remark: 92119:7 Assortment, Polar bear: Penguin: Walrus: Mammoth: Owl: Seal: Snow man=10:10:10:10:10:8:2. Snow man is the rare item. | Y22: Lena Huang | Z22: 3.4 | AA22: =Z22*J22 -> 11832 | AB22: =3444+36 -> 3480 | AC22: =AB22-J22 -> 0 | AD22: OK | AE22: 系统出单 | AF22: 94787-4.17 | AG22: 已入 | AH22: =J22 -> 3480 | AM22: =J22 -> 3480 | AP22: =J22 -> 3480 | AV22: MA布标 | AW22: =J22/60*10 -> 580 | AX22: =J22/60*10 -> 580 | AY22: =J22/60*8 -> 464 | AZ22: =J22/60*2 -> 116 | BA22: =J22/60*10 -> 580 | BB22: =J22/60*10 -> 580 | BC22: =J22/60*10 -> 580 | BD22: =SUM(AW22:BC22) -> 3480 | BE22: =J22-BD22 -> 0
A23: 45716 | B23: TARGET US | C23: 美国 | D23: 4500158830 | E23: 10001240713-3890 | F23: 4500158830-10 | G23: 92119-S003 | H23: 92119-S003 | I23: 冰雪蛋 | J23: 18152 | K23: 0 | L23: 8 | M23: =J23/L23 -> 2269 | N23: 45761 | O23: 45757 | P23: 正常出货 | Q23: PASS | R23: 5/21出 | S23: 3/11收到 | U23: 无 | V23: 3/24-外箱贴纸 | X23: 日期码格式：ZURU INC(BVI) 标准格式 日期：按实际生产日期 Packaging Info: 92119：产品MA包装, MA 1L收缩膜(UPC版)； Remark: 92119: 1. 92119-S003-RAINBOCORNS-EGGZANIA-SERIES 1-FROZEN MANIA-SHRINK WRAP,8pcs/CTN 2. 产品MA包装, MA 1L收缩膜(UPC版)；收缩膜上的UPC显示193052078391； 7 Assortment, Polar bear: Penguin: Walrus: Mammoth: Owl: Seal: Snow man=10:10:10:10:10:8:2. Snow man is the rare item. 3. 外箱正唛左上角位置粘贴条码箱贴纸，每箱只贴一张，由ZURU订购。来料贴纸上显示的客户DPCI#086-08-4925, UPC显示10193052078398; 此订单所有item： 1. 外箱正唛箱唛内容右侧需贴一张Event label，内容显示Toys Set Date：7/20/2025，工厂自行订购； 2. 产品和包装上印刷 tracking code信息，格式为ZURU常规格式; 3. 出货方式：货代自提 | Y23: Holly Zheng | Z23: 3.35 | AA23: =Z23*J23 -> 60809.2 | AB23: =10080+672+2696+4704 -> 18152 | AC23: =AB23-J23 -> 0 | AD23: OK | AE23: 系统出单 | AG23: 已入 | AH23: =J23 -> 18152 | AM23: =J23 -> 18152 | AR23: =J23 -> 18152 | AV23: MA布标 | AW23: =J23/60*10 -> 3025.3333 | AX23: =J23/60*10 -> 3025.3333 | AY23: =J23/60*8 -> 2420.2667 | AZ23: =J23/60*2 -> 605.06667 | BA23: =J23/60*10 -> 3025.3333 | BB23: =J23/60*10 -> 3025.3333 | BC23: =J23/60*10 -> 3025.3333 | BD23: =SUM(AW23:BC23) -> 18152 | BE23: =J23-BD23 -> 0
A24: 45726 | B24: DM LLC | C24: 俄罗斯联邦 | D24: 4500159461 | E24: 出Bekasovo 2 | F24: 4500159461-40 | G24: 92119-S001 | H24: 92124-S001-92119 | I24: 冰雪蛋（92119+9298+92104） | J24: 4318 | K24: 0 | L24: 1 | M24: =J24/L24 -> 4318 | N24: 45756 | O24: 45752 | Q24: PASS | S24: 3/13收到 | U24: 空白贴纸 | W24: 外包装 (指: 收缩膜/彩卡/铝箔袋/挂卡/PDQ) /外箱不要打ZURU标准日期码！胶件可以打日期码-DG20250401 | X24: 日期码格式：外包装/外箱不要打ZURU标准日期码 日期： Packaging Info: 注意 ：外包装 (指: 收缩膜/彩卡/铝箔袋/挂卡/PDQ) /外箱不要打ZURU标准日期码！胶件可以打日期码。 92124/92123 ： 里面combo 产品1L MA 收缩膜（不含任何条码）+ 空白贴纸覆盖条码， 客版托盘 ， MA指南/说明书（如有）； Remark: 标准配比 ； 请按期完货， 会有罚金。 出2个港口Bekasovo 2 和Ural | Y24: Ann | Z24: 8.499 | AA24: =J24*Z24 -> 36698.682 | AB24: 4318 | AC24: =AB24-J24 -> 0 | AD24: OK | AE24: 系统出单 | AG24: 已入 | AH24: =J24 -> 4318 | AM24: =J24 -> 4318 | AP24: =J24 -> 4318 | AV24: MA布标 | AW24: =J24/60*10 -> 719.66667 | AX24: =J24/60*10 -> 719.66667 | AY24: =J24/60*8 -> 575.73333 | AZ24: =J24/60*2 -> 143.93333 | BA24: =J24/60*10 -> 719.66667 | BB24: =J24/60*10 -> 719.66667 | BC24: =J24/60*10 -> 719.66667 | BD24: =SUM(AW24:BC24) -> 4318 | BE24: =J24-BD24 -> 0
A25: 45726 | B25: DM LLC | C25: 俄罗斯联邦 | D25: 4500159461 | E25: 出Ural | F25: 4500159461-90 | G25: 92119-S001 | H25: 92124-S001-92119 | I25: 冰雪蛋（92119+9298+92104） | J25: 1679 | K25: 0 | L25: 1 | M25: =J25/L25 -> 1679 | N25: 45756 | O25: 45752 | Q25: PASS | S25: 3/13收到 | U25: 空白贴纸 | W25: 外包装 (指: 收缩膜/彩卡/铝箔袋/挂卡/PDQ) /外箱不要打ZURU标准日期码！胶件可以打日期码-DG20250401 | X25: 日期码格式：外包装/外箱不要打ZURU标准日期码 日期： Packaging Info: 注意 ：外包装 (指: 收缩膜/彩卡/铝箔袋/挂卡/PDQ) /外箱不要打ZURU标准日期码！胶件可以打日期码。 92124 ： 里面combo 产品1L MA 收缩膜（不含任何条码）， 客版托盘 ， MA指南/说明书（如有）； Remark: 标准配比 ； 请按期完货， 会有罚金。 出2个港口Bekasovo 2 和Ural | Y25: Ann | Z25: 8.499 | AA25: =J25*Z25 -> 14269.821 | AB25: 1679 | AC25: =AB25-J25 -> 0 | AD25: OK | AE25: 系统出单 | AG25: 已入 | AH25: =J25 -> 1679 | AM25: =J25 -> 1679 | AP25: =J25 -> 1679 | AV25: MA布标 | AW25: =J25/60*10 -> 279.83333 | AX25: =J25/60*10 -> 279.83333 | AY25: =J25/60*8 -> 223.86667 | AZ25: =J25/60*2 -> 55.966667 | BA25: =J25/60*10 -> 279.83333 | BB25: =J25/60*10 -> 279.83333 | BC25: =J25/60*10 -> 279.83333 | BD25: =SUM(AW25:BC25) -> 1679 | BE25: =J25-BD25 -> 0
A26: 45729 | B26: Smyths Toys HQ UC IE | C26: 爱尔兰 | D26: 4500160022 | E26: 4400471618 | F26: 4500160022-10 | G26: 92119A-S003-3L | H26: 92119A-S003 | I26: 北极熊 | J26: 288 | K26: 0 | L26: 6 | M26: =J26/L26 -> 48 | N26: 45759 | O26: 45755 | Q26: PASS | R26: 4/25出 | S26: 3/17收到 | U26: 4/1-EAN条码贴（含德语Callout+挂牌的德意荷警语）+配件袋荷兰语警告语贴纸 | X26: 日期码格式：ZURU INC(BVI) 标准格式 日期：按实际生产日期 Packaging Info: 92119A：MA 3-23L EAN包装+EAN条码贴（含德语Callout+挂牌的德意荷警语）+MA 3L挂牌+MA 3L配件袋+荷兰语警告语贴纸+MA 5L Slime bag+MA 5L-23L收藏指南+M A布标 Remark: 1) 包装日期码按ZURU格式即可，请确保不迟于外箱日期码，可等于或者早于外箱日期码，必须为法定工作日，印刷前请先检查外箱日期码。 2) 订单出英国，请注意检查产品及包装应带UKCA图标（14+产品除外），包装显示ZURU UK LTD/ZURU France地址信息，QC部门请查核，如有问题与跟单确认 3) 需要完全符合欧洲标准(符合微塑料法规)，否则不合法规会有客诉产生 | Y26: May Wu | Z26: 3.58 | AA26: =Z26*J26 -> 1031.04 | AB26: 288 | AC26: =AB26-J26 -> 0 | AD26: OK | AE26: 系统出单 | AF26: 94824-4.24 | AG26: 已入 | AJ26: =J26 -> 288 | AM26: =J26 -> 288 | AP26: =J26 -> 288 | AV26: MA布标 | AW26: =J26 -> 288 | BD26: =SUM(AW26:BC26) -> 288 | BE26: =J26-BD26 -> 0
A27: 45729 | B27: Smyths Toys HQ UC IE | C27: 爱尔兰 | D27: 4500160022 | E27: 4400471618 | F27: 4500160022-20 | G27: 92119B-S003-3L | H27: 92119B-S003 | I27: 企鹅 | J27: 288 | K27: 0 | L27: 6 | M27: =J27/L27 -> 48 | N27: 45759 | O27: 45755 | Q27: PASS | R27: 4/25出 | S27: 3/17收到 | U27: 4/1-EAN条码贴（含德语Callout+挂牌的德意荷警语）+配件袋荷兰语警告语贴纸 | X27: 日期码格式：ZURU INC(BVI) 标准格式 日期：按实际生产日期 Packaging Info: 92119B: MA 3-23L EAN包装+EAN条码贴（含德语Callout+挂牌的德意荷警语）+MA 3L挂牌+MA 3L配件袋+荷兰语警告语贴纸+MA 5L Slime bag+MA 5L-23L收藏指南+M A布标 Remark: 1) 包装日期码按ZURU格式即可，请确保不迟于外箱日期码，可等于或者早于外箱日期码，必须为法定工作日，印刷前请先检查外箱日期码。 2) 订单出英国，请注意检查产品及包装应带UKCA图标（14+产品除外），包装显示ZURU UK LTD/ZURU France地址信息，QC部门请查核，如有问题与跟单确认 3) 需要完全符合欧洲标准(符合微塑料法规)，否则不合法规会有客诉产生 | Y27: May Wu | Z27: 3.5 | AA27: =Z27*J27 -> 1008 | AB27: 288 | AC27: =AB27-J27 -> 0 | AD27: OK | AE27: 系统出单 | AF27: 94824-4.24 | AG27: 已入 | AJ27: =J27 -> 288 | AM27: =J27 -> 288 | AP27: =J27 -> 288 | AV27: MA布标 | AX27: =J27 -> 288 | BD27: =SUM(AW27:BC27) -> 288 | BE27: =J27-BD27 -> 0
A28: 45726 | B28: PPTOYS PTE LTD (SG) | C28: 新加坡 | D28: 4500159608 | E28: ZU25022002SG | F28: 4500159608-10 | G28: 92119-S001 | H28: 92119-S001 | I28: 冰雪蛋 | J28: 840 | K28: 0 | L28: 12 | M28: =J28/L28 -> 70 | N28: 45759 | O28: 45755 | Q28: PASS | R28: 收到SO | S28: 3/10收到 | U28: 3/13-进口商贴纸 | X28: 日期码格式：ZURU INC(BVI) 标准格式 日期：按实际生产日期 Packaging Info: MA UPC包装（优先1L)+1张进口商贴纸 其他item贴纸AW、位置图待提供 此客人用的贴纸内容都是一样的，个别item可能存在尺寸差别，如果发现贴纸尺寸没差别，就请都统一订购节省成本 Remark: 92119-7 Assortment, Polar bear: Penguin: Walrus: Mammoth: Owl: Seal: Snow man=10:10:10:10:10:8:2. Snow man is the rare item. | Y28: Emma Wu | Z28: 3.6923 | AA28: =Z28*J28 -> 3101.532 | AB28: 840 | AC28: =AB28-J28 -> 0 | AD28: OK | AE28: 系统出单 | AF28: 94794-4.18 | AG28: 已入 | AH28: =J28 -> 840 | AM28: =J28 -> 840 | AP28: =J28 -> 840 | AV28: MA布标 | AW28: =J28/60*10 -> 140 | AX28: =J28/60*10 -> 140 | AY28: =J28/60*8 -> 112 | AZ28: =J28/60*2 -> 28 | BA28: =J28/60*10 -> 140 | BB28: =J28/60*10 -> 140 | BC28: =J28/60*10 -> 140 | BD28: =SUM(AW28:BC28) -> 840 | BE28: =J28-BD28 -> 0
A29: 45714 | B29: Walmart Central America-CR | C29: 哥斯达黎加 | D29: 4500158535 | F29: 4500158535-90 | G29: 92119-S001-3L | H29: 92119-S001 | I29: 冰雪蛋 | J29: 816 | K29: 0 | L29: 12 | M29: =J29/L29 -> 68 | N29: 45763 | O29: 45759 | Q29: PASS | R29: 4/29出 | S29: 3/24收到-双坑纸箱 | U29: 3/21-UPC贴纸+进口商贴纸 | X29: 日期码格式：ZURU INC(BVI) 标准格式 日期：按实际生产日期 Packaging Info: 6. 92119: MA 3L EAN包装+UPC贴纸+MA 多语收藏指南+进口商贴纸+箱唛 以上贴纸翻单PO 4500158302 Remark: 1.使用双坑外箱 2.请注意产品包装条形码必须是UPC 3.无第三方验货 92119：7 Assortment, Polar bear: Penguin: Walrus: Mammoth: Owl: Seal: Snow man=10:10:10:10:10:8:2. Snow man is the rare item. | Y29: Ever Li | Z29: 3.4 | AA29: =Z29*J29 -> 2774.4 | AB29: 816 | AC29: =AB29-J29 -> 0 | AD29: OK | AE29: 系统出单 | AF29: 94882-4.29 | AG29: 已入 | AJ29: =J29 -> 816 | AM29: =J29 -> 816 | AP29: =J29 -> 816 | AV29: MA布标 | AW29: =J29/60*10 -> 136 | AX29: =J29/60*10 -> 136 | AY29: =J29/60*8 -> 108.8 | AZ29: =J29/60*2 -> 27.2 | BA29: =J29/60*10 -> 136 | BB29: =J29/60*10 -> 136 | BC29: =J29/60*10 -> 136 | BD29: =SUM(AW29:BC29) -> 816 | BE29: =J29-BD29 -> 0
A30: 45712 | B30: Walmart Central America | C30: 萨尔瓦多 | D30: 4500158302 | F30: 4500158302-90 | G30: 92119-S001-3L | H30: 92119-S001 | I30: 冰雪蛋 | J30: 348 | K30: 0 | L30: 12 | M30: =J30/L30 -> 29 | N30: 45763 | O30: 45759 | Q30: PASS | R30: 4/28出 | S30: 3/24收到-双坑纸箱 | U30: 3/21-UPC贴纸+进口商贴纸 | X30: 日期码格式：ZURU INC(BVI) 标准格式 日期：按实际生产日期 Packaging Info: 6. 92119: MA 3L EAN包装+UPC贴纸+MA 多语收藏指南+进口商贴纸+箱唛 Remark: 1.使用双坑外箱 2.请注意产品包装条形码必须是UPC 3.无第三方验货 6. 92119：7 Assortment, Polar bear: Penguin: Walrus: Mammoth: Owl: Seal: Snow man=10:10:10:10:10:8:2. Snow man is the rare item. | Y30: Ever Li | Z30: 3.4 | AA30: =Z30*J30 -> 1183.2 | AB30: 348 | AC30: =AB30-J30 -> 0 | AE30: 系统出单 | AF30: 94865-4.28 | AG30: 已入 | AJ30: =J30 -> 348 | AM30: =J30 -> 348 | AP30: =J30 -> 348 | AV30: MA布标 | AW30: =J30/60*10 -> 58 | AX30: =J30/60*10 -> 58 | AY30: =J30/60*8 -> 46.4 | AZ30: =J30/60*2 -> 11.6 | BA30: =J30/60*10 -> 58 | BB30: =J30/60*10 -> 58 | BC30: =J30/60*10 -> 58 | BD30: =SUM(AW30:BC30) -> 348 | BE30: =J30-BD30 -> 0
A31: 45730 | B31: KMART AUSTRALIA LTD | C31: 澳大利亚 | D31: 4500160268 | F31: 4500160268-10 | G31: 92119-S001 | H31: 92119-S001 | I31: 冰雪蛋 | J31: 3240 | K31: 0 | L31: 12 | M31: =J31/L31 -> 270 | N31: 45768 | O31: 45764 | Q31: PASS | R31: 4/22-4/25出 | S31: 3/20收到 | U31: 3/31-防盗贴纸+外箱贴纸 | X31: 日期码格式：ZURU INC(BVI) 标准格式 日期：按实际生产日期 Packaging Info: 92119-S001 : MA英语UPC版本包装（收缩膜和说明书, MA首选1L，如无1L可用多语且含英语的配套多语包装) + 1张防盗贴纸+ 箱唛 + 外箱SSCC Label 配比信息：7 Assortment, Polar bear: Penguin: Walrus: Mammoth: Owl: Seal: Snow man=10:10:10:10:10:8:2. Snow man is the rare item." Remark: 1.请务必按时完货，验货。并且按期送货入货代指定仓库，如果晚了导致船期Delay将会有罚金产生或者客户要求空运，所产生的罚金和空运费由工厂承担。 2.SSCC 外箱贴纸请同纸箱瓦楞纸方向（竖纹向）垂直，即外箱贴纸横着贴(注意条码不要被胶带粘住），贴1pc，贴1面正唛，封箱胶纸不能挡住贴纸内容。外箱贴纸 离外箱边距离不少于2cm。 3.外箱材质为ZURU标准； 4.此单需使用KMART封箱胶上下工字型封箱;从2019年6月开始，要用KMART 新版封箱胶带，此单要用"ANKO"封箱胶带 5.此单出口澳大利亚，请按相应的澳新标准生产； 6.产品和包装上生产批号的显示格式ZURU标准日期码格式 7.外箱信息不可手写，重量和体积需要与实际的一致(不可手写） 8. 每款item装箱后的G.W.超过10KG或者CBM超过0.13,(9.5KG或者以上，四舍五入后也属于10KG) 需在外箱上加印超 重或者Bulky LOGO，若发现我们资料没有，请 帮忙提醒 1)重量超过10kg但不超过16kg且CBM不超过0.13,10-16kg 超重logo 2）CBM超过0.13且重量少于17kg，bulky logo 3）不属于以上两种情况，需要使用相应重量范围内的超重logo 4）超重logo需要在外箱四面都印刷(箱唛右上角，两面侧唛超重logo需要尽量靠近毛重)，尺寸为:110mm height* 95mm width 9. 实际外箱重量跟印在箱唛上的数据差异不能超3%，尺寸按实际数据印刷 92119实际为LCL出货 | Y31: Lydia Wu | Z31: 3.4 | AA31: =Z31*J31 -> 11016 | AB31: =888+2352 -> 3240 | AC31: =AB31-J31 -> 0 | AD31: OK | AE31: 系统出单 | AF31: 94836-4.24 | AG31: 已入 | AH31: =J31 -> 3240 | AM31: =J31 -> 3240 | AP31: =J31 -> 3240 | AV31: MA布标 | AW31: =J31/60*10 -> 540 | AX31: =J31/60*10 -> 540 | AY31: =J31/60*8 -> 432 | AZ31: =J31/60*2 -> 108 | BA31: =J31/60*10 -> 540 | BB31: =J31/60*10 -> 540 | BC31: =J31/60*10 -> 540 | BD31: =SUM(AW31:BC31) -> 3240 | BE31: =J31-BD31 -> 0
A32: 45730 | B32: KMART AUSTRALIA LTD(NEW ZEALAND) | C32: 新西兰 | D32: 4500160271 | E32: 20676971 | F32: 4500160271-10 | G32: 92119-S001 | H32: 92119-S001 | I32: 冰雪蛋 | J32: 360 | K32: 0 | L32: 12 | M32: =J32/L32 -> 30 | N32: 45768 | O32: 45764 | Q32: PASS | R32: 4/22-4/25出 | S32: 3/20收到 | U32: 3/31-防盗贴纸+外箱贴纸 | X32: 日期码格式：ZURU INC(BVI) 标准格式 日期：按实际生产日期 Packaging Info: 92119-S001 : MA英语UPC版本包装（收缩膜和说明书, MA首选1L，如无1L可用多语且含英语的配套多语包装) + 1张防盗贴纸 (贴纸以及位置图翻单PO#4500160268） + 箱唛 + 外箱SSCC Label 配比信息：7 Assortment, Polar bear: Penguin: Walrus: Mammoth: Owl: Seal: Snow man=10:10:10:10:10:8:2. Snow man is the rare item. Remark: 1.请务必按时完货，验货。并且按期送货入货代指定仓库，如果晚了导致船期Delay将会有罚金产生或者客户要求空运，所产生的罚金和空运费由工厂承担。 2.SSCC 外箱贴纸请同纸箱瓦楞纸方向（竖纹向）垂直，即外箱贴纸横着贴(注意条码不要被胶带粘住），贴1pc，贴1面正唛，封箱胶纸不能挡住贴纸内容。外箱贴纸 离外箱边距离不少于2cm。 3.外箱材质为ZURU标准； 4.此单需使用KMART封箱胶上下工字型封箱;从2019年6月开始，要用KMART 新版封箱胶带，此单要用"ANKO"封箱胶带 5.此单出口新西兰，请按相应的澳新标准生产； 6.产品和包装上生产批号的显示格式ZURU标准日期码格式 7.外箱信息不可手写，重量和体积需要与实际的一致(不可手写） 8. 每款item装箱后的G.W.超过10KG或者CBM超过0.13,(9.5KG或者以上，四舍五入后也属于10KG) 需在外箱上加印超 重或者Bulky LOGO，若发现我们资料没有，请 帮忙提醒 1)重量超过10kg但不超过16kg且CBM不超过0.13,10-16kg 超重logo 2）CBM超过0.13且重量少于17kg，bulky logo 3）不属于以上两种情况，需要使用相应重量范围内的超重logo 4）超重logo需要在外箱四面都印刷(箱唛右上角，两面侧唛超重logo需要尽量靠近毛重)，尺寸为:110mm height* 95mm width 9. 实际外箱重量跟印在箱唛上的数据差异不能超3%，尺寸按实际数据印刷 92119实际为LCL出货 | Y32: Lydia Wu | Z32: 3.4 | AA32: =Z32*J32 -> 1224 | AB32: 360 | AC32: =AB32-J32 -> 0 | AD32: OK | AE32: 系统出单 | AF32: 94825-4.24 | AG32: 已入 | AH32: =J32 -> 360 | AM32: =J32 -> 360 | AP32: =J32 -> 360 | AV32: MA布标 | AW32: =J32/60*10 -> 60 | AX32: =J32/60*10 -> 60 | AY32: =J32/60*8 -> 48 | AZ32: =J32/60*2 -> 12 | BA32: =J32/60*10 -> 60 | BB32: =J32/60*10 -> 60 | BC32: =J32/60*10 -> 60 | BD32: =SUM(AW32:BC32) -> 360 | BE32: =J32-BD32 -> 0
A33: 45729 | B33: Smyths Toys HQ UC UK | C33: 英国 | D33: 4500160023 | E33: 客户PO4400471 627 | F33: 4500160023-10 | G33: 92119A-S003-3L | H33: 92119A-S003 | I33: 北极熊 | J33: 600 | K33: 0 | L33: 6 | M33: =J33/L33 -> 100 | N33: 45768 | O33: 45764 | Q33: PASS | R33: 4/28出 | S33: 3/17收到 | U33: 4/1-EAN条码贴（含德语Callout+挂牌的德意荷警语）+配件袋荷兰语警告语贴纸翻4500160022 | X33: 日期码格式：ZURU INC(BVI) 标准格式 日期：按实际生产日期 Packaging Info: 92119A：MA 3-23L EAN包装+EAN条码贴（含德语Callout+挂牌的德意荷警语）+MA 3L挂牌+MA 3L配件袋+荷兰语警告语贴纸+MA 5L Slime bag+MA 5L-23L收藏指南+M A布标（贴纸翻4500160022） Remark: 1) 包装日期码按ZURU格式即可，请确保不迟于外箱日期码，可等于或者早于外箱日期码，必须为法定工作日，印刷前请先检查外箱日期码。 2) 订单出英国，请注意检查产品及包装应带UKCA图标（14+产品除外），包装显示ZURU UK LTD/ZURU France地址信息，QC部门请查核，如有问题与跟单确认 3) 需要完全符合欧洲标准(符合微塑料法规)，否则不合法规会有客诉产生 | Y33: May Wu | Z33: 3.58 | AA33: =Z33*J33 -> 2148 | AB33: 600 | AC33: =AB33-J33 -> 0 | AD33: OK | AE33: 系统出单 | AF33: 94849-4.28 | AG33: 已入 | AJ33: =J33 -> 600 | AM33: =J33 -> 600 | AP33: =J33 -> 600 | AV33: MA布标 | AW33: =J33 -> 600 | BD33: =SUM(AW33:BC33) -> 600 | BE33: =J33-BD33 -> 0
A34: 45732 | B34: Smyths Toys HQ UC UK | C34: 英国 | D34: 4500160023 | E34: 客户PO4400471 628 | F34: 4500160023-30 | G34: 92119A-S003-3L | H34: 92119A-S003 | I34: 北极熊 | J34: 600 | K34: 0 | L34: 6 | M34: =J34/L34 -> 100 | N34: 45768 | O34: 45764 | Q34: PASS | R34: 4/28出 | S34: 3/17收到 | U34: 4/1-EAN条码贴（含德语Callout+挂牌的德意荷警语）+配件袋荷兰语警告语贴纸翻4500160022 | X34: 日期码格式：ZURU INC(BVI) 标准格式 日期：按实际生产日期 Packaging Info: 92119A：MA 3-23L EAN包装+EAN条码贴（含德语Callout+挂牌的德意荷警语）+MA 3L挂牌+MA 3L配件袋+荷兰语警告语贴纸+MA 5L Slime bag+MA 5L-23L收藏指南+M A布标（贴纸翻4500160022） Remark: 1) 包装日期码按ZURU格式即可，请确保不迟于外箱日期码，可等于或者早于外箱日期码，必须为法定工作日，印刷前请先检查外箱日期码。 2) 订单出英国，请注意检查产品及包装应带UKCA图标（14+产品除外），包装显示ZURU UK LTD/ZURU France地址信息，QC部门请查核，如有问题与跟单确认 3) 需要完全符合欧洲标准(符合微塑料法规)，否则不合法规会有客诉产生 | Y34: May Wu | Z34: 3.58 | AA34: =Z34*J34 -> 2148 | AB34: 600 | AC34: =AB34-J34 -> 0 | AD34: OK | AE34: 系统出单 | AF34: 94849-4.28 | AG34: 已入 | AJ34: =J34 -> 600 | AM34: =J34 -> 600 | AP34: =J34 -> 600 | AV34: MA布标 | AW34: =J34 -> 600 | BD34: =SUM(AW34:BC34) -> 600 | BE34: =J34-BD34 -> 0
A35: 45733 | B35: SMYTHS TOYS HQ UC | C35: 法国 | D35: 4500160446 | E35: 4400472143 | F35: 4500160446-20 | G35: 92119A-S003-3L | H35: 92119A-S003 | I35: 北极熊 | J35: 408 | K35: 0 | L35: 6 | M35: =J35/L35 -> 68 | N35: 45768 | O35: 45764 | Q35: PASS | S35: 3/17收到 | U35: 德语Callout贴纸+荷兰语警告语贴纸翻4500160022 | X35: 日期码格式：ZURU INC(BVI) 标准格式 日期：按实际生产日期 Packaging Info: 2.92119A:MA 3-23L EAN包装+1张德语Callout贴纸+MA 3L挂牌+MA 5L Slime bag+荷兰语警告语贴纸+MA 5L-23L收藏指南+MA布标 （贴纸都翻4500160022） Remark: 1. 此单出法国，所有包装都需要含有法语，需要满足Zuru Standard欧洲标准测试要求； 2. 请准时出货，推期会有罚款； 3. 所有出口法国的产品, 法规规定禁止在包装和共公众用的印刷品中使用矿物油中含有的物质, 包装印刷油墨中含有的MOAH/MOSH的质量浓度不能超过1%, 否则出 货到法国被抽检出现问题, 供应商需要对此负责; | Y35: Ula Zhao | Z35: 3.58 | AA35: =Z35*J35 -> 1460.64 | AB35: 408 | AC35: =AB35-J35 -> 0 | AD35: OK | AE35: 系统出单 | AF35: 94812-4.22 | AG35: 已入 | AJ35: =J35 -> 408 | AM35: =J35 -> 408 | AP35: =J35 -> 408 | AV35: MA布标 | AW35: =J35 -> 408 | BD35: =SUM(AW35:BC35) -> 408 | BE35: =J35-BD35 -> 0
A36: 45729 | B36: Babyhouse | C36: 乌兹别克斯坦 | D36: 4500159866 | F36: 4500159866-70 | G36: 92119-S001 | H36: 92119-S001 | I36: 冰雪蛋 | J36: 240 | K36: 0 | L36: 12 | M36: =J36/L36 -> 20 | N36: 45769 | O36: 45765 | Q36: PASS | R36: 4/24出 | S36: 3/13收到 | U36: 3/14-进口商贴纸 | X36: 日期码格式：ZURU INC(BVI) 标准格式 日期：按实际生产日期 Packaging Info: 92119 : 1L MA 收缩膜 + 进口商贴纸 ; MA 说明书/指南（如有）; Remark: 标准配比 | Y36: Ann Zhang | Z36: 3.4 | AA36: =Z36*J36 -> 816 | AB36: 240 | AC36: =AB36-J36 -> 0 | AD36: OK | AE36: 系统出单 | AF36: 94879-4.29 | AG36: 已入 | AH36: =J36 -> 240 | AM36: =J36 -> 240 | AP36: =J36 -> 240 | AV36: MA布标 | AW36: =J36/60*10 -> 40 | AX36: =J36/60*10 -> 40 | AY36: =J36/60*8 -> 32 | AZ36: =J36/60*2 -> 8 | BA36: =J36/60*10 -> 40 | BB36: =J36/60*10 -> 40 | BC36: =J36/60*10 -> 40 | BD36: =SUM(AW36:BC36) -> 240 | BE36: =J36-BD36 -> 0
A37: 45732 | B37: Smyths Toys HQ UC UK | C37: 英国 | D37: 4500160023 | E37: 客户PO4400471 628 | F37: 4500160023-40 | G37: 92119B-S003-3L | H37: 92119B-S003 | I37: 企鹅 | J37: 600 | K37: 0 | L37: 6 | M37: =J37/L37 -> 100 | N37: 45764 | O37: 45761 | Q37: PASS | R37: 4/28出 | S37: 3/17收到 | U37: 4/1-EAN条码贴（含德语Callout+挂牌的德意荷警语）+配件袋荷兰语警告语贴纸翻4500160022 | X37: 日期码格式：ZURU INC(BVI) 标准格式 日期：按实际生产日期 Packaging Info: 92119B: MA 3-23L EAN包装+EAN条码贴（含德语Callout+挂牌的德意荷警语）+MA 3L挂牌+MA 3L配件袋+荷兰语警告语贴纸+MA 5L Slime bag+MA 5L-23L收藏指南+M A布标（贴纸翻4500160022） Remark: 1) 包装日期码按ZURU格式即可，请确保不迟于外箱日期码，可等于或者早于外箱日期码，必须为法定工作日，印刷前请先检查外箱日期码。 2) 订单出英国，请注意检查产品及包装应带UKCA图标（14+产品除外），包装显示ZURU UK LTD/ZURU France地址信息，QC部门请查核，如有问题与跟单确认 3) 需要完全符合欧洲标准(符合微塑料法规)，否则不合法规会有客诉产生 | Y37: May Wu | Z37: 3.5 | AA37: =Z37*J37 -> 2100 | AB37: 600 | AC37: =AB37-J37 -> 0 | AD37: OK | AE37: 系统出单 | AF37: 94849-4.28 | AG37: 已入 | AJ37: =J37 -> 600 | AM37: =J37 -> 600 | AP37: =J37 -> 600 | AV37: MA布标 | AX37: =J37 -> 600 | BD37: =SUM(AW37:BC37) -> 600 | BE37: =J37-BD37 -> 0
A38: 45729 | B38: Smyths Toys HQ UC UK | C38: 英国 | D38: 4500160023 | E38: 客户PO4400471 627 | F38: 4500160023-20 | G38: 92119B-S003-3L | H38: 92119B-S003 | I38: 企鹅 | J38: 600 | K38: 0 | L38: 6 | M38: =J38/L38 -> 100 | N38: 45768 | O38: 45764 | Q38: PASS | R38: 4/28出 | S38: 3/17收到 | U38: 4/1-EAN条码贴（含德语Callout+挂牌的德意荷警语）+配件袋荷兰语警告语贴纸翻4500160022 | X38: 日期码格式：ZURU INC(BVI) 标准格式 日期：按实际生产日期 Packaging Info: 92119B: MA 3-23L EAN包装+EAN条码贴（含德语Callout+挂牌的德意荷警语）+MA 3L挂牌+MA 3L配件袋+荷兰语警告语贴纸+MA 5L Slime bag+MA 5L-23L收藏指南+M A布标（贴纸翻4500160022） Remark: 1) 包装日期码按ZURU格式即可，请确保不迟于外箱日期码，可等于或者早于外箱日期码，必须为法定工作日，印刷前请先检查外箱日期码。 2) 订单出英国，请注意检查产品及包装应带UKCA图标（14+产品除外），包装显示ZURU UK LTD/ZURU France地址信息，QC部门请查核，如有问题与跟单确认 3) 需要完全符合欧洲标准(符合微塑料法规)，否则不合法规会有客诉产生 | Y38: May Wu | Z38: 3.5 | AA38: =Z38*J38 -> 2100 | AB38: 600 | AC38: =AB38-J38 -> 0 | AD38: OK | AE38: 系统出单 | AF38: 94849-4.28 | AG38: 已入 | AJ38: =J38 -> 600 | AM38: =J38 -> 600 | AP38: =J38 -> 600 | AV38: MA布标 | AX38: =J38 -> 600 | BD38: =SUM(AW38:BC38) -> 600 | BE38: =J38-BD38 -> 0
A39: 45733 | B39: SMYTHS TOYS HQ UC | C39: 法国 | D39: 4500160446 | E39: 4400472143 | F39: 4500160446-30 | G39: 92119B-S003-3L | H39: 92119B-S003 | I39: 企鹅 | J39: 408 | K39: 0 | L39: 6 | M39: =J39/L39 -> 68 | N39: 45768 | O39: 45764 | Q39: PASS | S39: 3/17收到 | U39: 德语Callout贴纸+荷兰语警告语贴纸翻4500160022 | X39: 日期码格式：ZURU INC(BVI) 标准格式 日期：按实际生产日期 Packaging Info: 3.92119B:MA 3-23L EAN包装+1张德语Callout贴纸+MA 3L挂牌+MA 5L Slime bag+荷兰语警告语贴纸+MA 5L-23L收藏指南+MA布标 （贴纸都翻4500160022） Remark: 1. 此单出法国，所有包装都需要含有法语，需要满足Zuru Standard欧洲标准测试要求； 2. 请准时出货，推期会有罚款； 3. 所有出口法国的产品, 法规规定禁止在包装和共公众用的印刷品中使用矿物油中含有的物质, 包装印刷油墨中含有的MOAH/MOSH的质量浓度不能超过1%, 否则出 货到法国被抽检出现问题, 供应商需要对此负责; | Y39: Ula Zhao | Z39: 3.5 | AA39: =Z39*J39 -> 1428 | AB39: 408 | AC39: =AB39-J39 -> 0 | AD39: OK | AE39: 系统出单 | AF39: 94812-4.22 | AG39: 已入 | AJ39: =J39 -> 408 | AM39: =J39 -> 408 | AP39: =J39 -> 408 | AV39: MA布标 | AX39: =J39 -> 408 | BD39: =SUM(AW39:BC39) -> 408 | BE39: =J39-BD39 -> 0
A40: 45714 | B40: ALL BRANDS TOYS PTY LTD | C40: 澳大利亚 | D40: 4500158680 | E40: 83715 | F40: 4500158680-10 | G40: 92119-S001 | H40: 92119-S001 | I40: 冰雪蛋 | J40: 1440 | K40: 0 | L40: 12 | M40: =J40/L40 -> 120 | N40: 45771 | O40: 45768 | Q40: PASS | R40: 4/24出 | S40: 2/26收到 | U40: 2/26-客人通用进口商贴纸 | X40: 日期码格式：ZURU INC(BVI) 标准格式 日期：按实际生产日期 Packaging Info: 92119：MA_UPC版本包装（MA首选1L，如无1L可用多语且含英语的配套多语UPC包装）+ 1张客人通用进口商贴纸 (请提供贴纸位置图供确认) Remark: 1.按实际生产日期; 2.出澳大利亚，请按照相应标准生产; | Y40: Lydia Wu | Z40: 3.4 | AA40: =Z40*J40 -> 4896 | AB40: 1440 | AC40: =AB40-J40 -> 0 | AD40: OK | AE40: 系统出单 | AF40: 94811-4.22 | AG40: 已入 | AH40: =J40 -> 1440 | AM40: =J40 -> 1440 | AR40: =J40 -> 1440 | AV40: MA布标 | AW40: =J40/60*10 -> 240 | AX40: =J40/60*10 -> 240 | AY40: =J40/60*8 -> 192 | AZ40: =J40/60*2 -> 48 | BA40: =J40/60*10 -> 240 | BB40: =J40/60*10 -> 240 | BC40: =J40/60*10 -> 240 | BD40: =SUM(AW40:BC40) -> 1440 | BE40: =J40-BD40 -> 0
A41: 45735 | B41: Centro Atacadista Bar􀃣o Ltda | C41: 巴西 | D41: 4500160722 | E41: FUN 083/25 | F41: 4500160722-40 | G41: 92119-S001 | H41: 92119-S001 | I41: 冰雪蛋 | J41: 5004 | K41: 0 | L41: 12 | M41: =J41/L41 -> 417 | N41: 45768 | O41: 45764 | Q41: PASS | R41: 4/28出 | S41: 3/31收到 | U41: 4/3-进口商贴纸 | X41: 日期码格式：ZURU INC(BVI) 标准格式 日期：按实际生产日期 Packaging Info: MA 1L包装+进口商贴纸+箱唛 Remark: 92119：7 Assortment, Polar bear: Penguin: Walrus: Mammoth: Owl: Seal: Snow man=10:10:10:10:10:8:2. Snow man is the rare item. | Y41: Ava Liang | Z41: 3.4 | AA41: =Z41*J41 -> 17013.6 | AB41: =5004 -> 5004 | AC41: =AB41-J41 -> 0 | AD41: OK | AE41: 系统出单 | AF41: 94922-5.5 | AG41: 已入 | AH41: =J41 -> 5004 | AM41: =J41 -> 5004 | AR41: =J41 -> 5004 | AV41: MA布标 | AW41: =J41/60*10 -> 834 | AX41: =J41/60*10 -> 834 | AY41: =J41/60*8 -> 667.2 | AZ41: =J41/60*2 -> 166.8 | BA41: =J41/60*10 -> 834 | BB41: =J41/60*10 -> 834 | BC41: =J41/60*10 -> 834 | BD41: =SUM(AW41:BC41) -> 5004 | BE41: =J41-BD41 -> 0
A42: 45722 | B42: SCHEEL'S ALL SPORTS, INC. | C42: 美国 | D42: 4500159089 | E42: PO#019869339 | F42: 4500159089-10 | G42: 92119-S001-NB | H42: 92119-S001-NB | I42: 冰雪蛋 | J42: 2064 | K42: 0 | L42: 12 | M42: =J42/L42 -> 172 | N42: 45771 | O42: 45768 | Q42: PASS | R42: 4/30出 | S42: 3/6收到 | U42: 无 | X42: 日期码格式：ZURU INC(BVI) 标准格式 日期：按实际生产日期 Packaging Info: 1. 包装：ZURU MA 1L 最新UPC版本；出口美国<(>&<)>CA； #92119： 出无硼版本 Remark: 2. 日期跟踪码：产品包装及产品本身都必须有日期跟踪码，并且确保两者的日期跟踪码要一致；ZURU标准格式日期码(请自行调整具体年月日生产期，但不能为周 末）。 3. 此单有4个客户PO， 请见侧边备注； 4. 出货配比: Zuru 标版配比。 | Y42: Mila Yao | Z42: 3.4 | AA42: =Z42*J42 -> 7017.6 | AB42: =504+1560 -> 2064 | AC42: =AB42-J42 -> 0 | AD42: 无 | AE42: 系统出单 | AF42: ZB00187-4.28 | AG42: 已入 | AH42: =J42 -> 2064 | AM42: =J42 -> 2064 | AR42: =J42 -> 2064 | AV42: MA布标 | AW42: =J42/60*10 -> 344 | AX42: =J42/60*10 -> 344 | AY42: =J42/60*8 -> 275.2 | AZ42: =J42/60*2 -> 68.8 | BA42: =J42/60*10 -> 344 | BB42: =J42/60*10 -> 344 | BC42: =J42/60*10 -> 344 | BD42: =SUM(AW42:BC42) -> 2064 | BE42: =J42-BD42 -> 0
A43: 45729 | B43: WM MORRISON SUPERMARKET PLC | C43: 英国 | D43: 4500159816 | E43: 14292169 | F43: 4500159816-20 | G43: 92119-S006 | H43: 92119-S006 | I43: 冰雪蛋 | J43: 3092 | K43: 0 | L43: 4 | M43: =J43/L43 -> 773 | N43: 45772 | O43: 45768 | Q43: PASS | R43: 5/14出 | S43: 3/24收到 | U43: 4/14-大圆黄防盗贴纸 | X43: 日期码格式：ZURU INC(BVI) 标准格式 日期：按实际生产日期 Packaging Info: 2.92119-S006：MA 1L UPC包装+一张防盗贴纸(贴纸类型：10111896 40R Label)，请工厂自行跟checkpoint供应商订购贴纸 UPC#193052078391，请先检查包装条码是否正确再安排做货 Remark: 1）外箱有条码要求，排版时请留意并请确保条码清晰可扫描（封箱胶不要黏到条码上), 否则客人会有罚款。 2) 订单出英国，产品及包装需要印UKCA图标，包装需要有ZURU UK LTD/ZURU France地址信息，QC同事请查核，如有问题与跟单确认。 3) 箱唛日期码与包装保持一致 4) 若外箱重量超过16KGS，请提前告知ZURU跟单，需要客人批准才能出货，并且外箱需要印2 man lift标志 | Y43: Yoga Huang | Z43: 3.55 | AA43: =Z43*J43 -> 10976.6 | AB43: =2916+176 -> 3092 | AC43: =AB43-J43 -> 0 | AD43: OK | AE43: 系统出单 | AG43: 已入 | AH43: =J43 -> 3092 | AM43: =J43 -> 3092 | AP43: =J43 -> 3092 | AV43: MA布标 | AW43: =J43/60*10 -> 515.33333 | AX43: =J43/60*10 -> 515.33333 | AY43: =J43/60*8 -> 412.26667 | AZ43: =J43/60*2 -> 103.06667 | BA43: =J43/60*10 -> 515.33333 | BB43: =J43/60*10 -> 515.33333 | BC43: =J43/60*10 -> 515.33333 | BD43: =SUM(AW43:BC43) -> 3092 | BE43: =J43-BD43 -> 0
A44: 45736 | B44: THE ENTERTAINER | C44: 英国 | D44: 4500160901 | E44: 4500160901-1: FB12977 | F44: 4500160901-40 | G44: 92119-S001 | H44: 92119-S001 | I44: 冰雪蛋 | J44: 792 | K44: 0 | L44: 12 | M44: =J44/L44 -> 66 | N44: 45772 | O44: 45768 | Q44: PASS | R44: 4/29出 | S44: 3/24收到 | U44: 无 | X44: 日期码格式：ZURU INC(BVI) 标准格式 日期：按实际生产日期 Packaging Info: 92119-S001: MA 最新1L UPC包装; BARCODE: 193052078391 Remark: *MA版本按工厂现有最新库存即可，订单出英国，请注意检查产品及包装应带UKCA图标，包装显示ZURU UK LTD信息，QC同事请查核，如有问题与跟单确认 *生产日期按实际（法定工作日），按ZURU标准格式即可 ，但是请知悉包装日期码需要早于或者等于外箱日期码 ，不能晚于外箱日期码 *请注意所有订单都需要经过ZURU QC验货并且通过后方可出货 *所有产品按符合欧洲标准走货，需要是不含微塑料版本 。 *涉及到硼的，如可选择情况下应使用低硼版本 （slime 类别低硼一般低于300ppm)，无选择的应与跟单复核再安排 。 *条码以订单显示为准 ，请安排生产前先核对 ，有问题请提出。 *订单对应客户3个PO号 ，备注有显示 ，注意分开做货/验货/装柜 ，混装有罚款。 * 大货样： 请在4/10 前寄出每款1整套大货样到罗湖办公室7B Sandy Shao 收。 | Y44: Sandy Shao | Z44: 3.4 | AA44: =Z44*J44 -> 2692.8 | AB44: 792 | AC44: =AB44-J44 -> 0 | AD44: 无 | AE44: 系统出单 | AF44: 94866-4.29 | AG44: 已入 | AH44: =J44 -> 792 | AM44: =J44 -> 792 | AP44: =J44 -> 792 | AV44: MA布标 | AW44: =J44/60*10 -> 132 | AX44: =J44/60*10 -> 132 | AY44: =J44/60*8 -> 105.6 | AZ44: =J44/60*2 -> 26.4 | BA44: =J44/60*10 -> 132 | BB44: =J44/60*10 -> 132 | BC44: =J44/60*10 -> 132 | BD44: =SUM(AW44:BC44) -> 792 | BE44: =J44-BD44 -> 0
A45: 45736 | B45: THE ENTERTAINER | C45: 英国 | D45: 4500160901 | E45: 4500160901-2: FB12978 | F45: 4500160901-130 | G45: 92119-S001 | H45: 92119-S001 | I45: 冰雪蛋 | J45: 804 | K45: 0 | L45: 12 | M45: =J45/L45 -> 67 | N45: 45772 | O45: 45768 | Q45: PASS | R45: 4/29出 | S45: 3/24收到 | U45: 无 | X45: 日期码格式：ZURU INC(BVI) 标准格式 日期：按实际生产日期 Packaging Info: 92119-S001: MA 最新1L UPC包装; BARCODE: 193052078391 Remark: *MA版本按工厂现有最新库存即可，订单出英国，请注意检查产品及包装应带UKCA图标，包装显示ZURU UK LTD信息，QC同事请查核，如有问题与跟单确认 *生产日期按实际（法定工作日），按ZURU标准格式即可 ，但是请知悉包装日期码需要早于或者等于外箱日期码 ，不能晚于外箱日期码 *请注意所有订单都需要经过ZURU QC验货并且通过后方可出货 *所有产品按符合欧洲标准走货，需要是不含微塑料版本 。 *涉及到硼的，如可选择情况下应使用低硼版本 （slime 类别低硼一般低于300ppm)，无选择的应与跟单复核再安排 。 *条码以订单显示为准 ，请安排生产前先核对 ，有问题请提出。 *订单对应客户3个PO号 ，备注有显示 ，注意分开做货/验货/装柜 ，混装有罚款。 * 大货样： 请在4/10 前寄出每款1整套大货样到罗湖办公室7B Sandy Shao 收。 | Y45: Sandy Shao | Z45: 3.4 | AA45: =Z45*J45 -> 2733.6 | AB45: =768+36 -> 804 | AC45: =AB45-J45 -> 0 | AD45: 无 | AE45: 系统出单 | AF45: 94866-4.29 | AG45: 已入 | AH45: =J45 -> 804 | AM45: =J45 -> 804 | AP45: =J45 -> 804 | AV45: MA布标 | AW45: =J45/60*10 -> 134 | AX45: =J45/60*10 -> 134 | AY45: =J45/60*8 -> 107.2 | AZ45: =J45/60*2 -> 26.8 | BA45: =J45/60*10 -> 134 | BB45: =J45/60*10 -> 134 | BC45: =J45/60*10 -> 134 | BD45: =SUM(AW45:BC45) -> 804 | BE45: =J45-BD45 -> 0
A46: 45736 | B46: THE ENTERTAINER | C46: 英国 | D46: 4500160901 | E46: 4500160901-3: FB12979 | F46: 4500160901-220 | G46: 92119-S001 | H46: 92119-S001 | I46: 冰雪蛋 | J46: 804 | K46: 0 | L46: 12 | M46: =J46/L46 -> 67 | N46: 45772 | O46: 45768 | Q46: PASS | R46: 4/29出 | S46: 3/24收到 | U46: 无 | X46: 日期码格式：ZURU INC(BVI) 标准格式 日期：按实际生产日期 Packaging Info: 92119-S001: MA 最新1L UPC包装; BARCODE: 193052078391 Remark: *MA版本按工厂现有最新库存即可，订单出英国，请注意检查产品及包装应带UKCA图标，包装显示ZURU UK LTD信息，QC同事请查核，如有问题与跟单确认 *生产日期按实际（法定工作日），按ZURU标准格式即可 ，但是请知悉包装日期码需要早于或者等于外箱日期码 ，不能晚于外箱日期码 *请注意所有订单都需要经过ZURU QC验货并且通过后方可出货 *所有产品按符合欧洲标准走货，需要是不含微塑料版本 。 *涉及到硼的，如可选择情况下应使用低硼版本 （slime 类别低硼一般低于300ppm)，无选择的应与跟单复核再安排 。 *条码以订单显示为准 ，请安排生产前先核对 ，有问题请提出。 *订单对应客户3个PO号 ，备注有显示 ，注意分开做货/验货/装柜 ，混装有罚款。 * 大货样： 请在4/10 前寄出每款1整套大货样到罗湖办公室7B Sandy Shao 收。 | Y46: Sandy Shao | Z46: 3.4 | AA46: =Z46*J46 -> 2733.6 | AB46: 804 | AC46: =AB46-J46 -> 0 | AD46: 无 | AE46: 系统出单 | AF46: 94866-4.29 | AG46: 已入 | AH46: =J46 -> 804 | AM46: =J46 -> 804 | AP46: =J46 -> 804 | AV46: MA布标 | AW46: =J46/60*10 -> 134 | AX46: =J46/60*10 -> 134 | AY46: =J46/60*8 -> 107.2 | AZ46: =J46/60*2 -> 26.8 | BA46: =J46/60*10 -> 134 | BB46: =J46/60*10 -> 134 | BC46: =J46/60*10 -> 134 | BD46: =SUM(AW46:BC46) -> 804 | BE46: =J46-BD46 -> 0
A47: 45705 | B47: Ambiental Paraguay | C47: 巴拉圭 | D47: 4500157158 | F47: 4500157158-40 | G47: 92119-S001-3L | H47: 92119-S001 | I47: 冰雪蛋 | J47: 804 | K47: 0 | L47: 12 | M47: =J47/L47 -> 67 | N47: 45775 | O47: 45771 | Q47: PASS | R47: 5/5出 | S47: 3/19收到 | U47: 3/20-进口商贴纸 | X47: 日期码格式：ZURU INC(BVI) 标准格式 日期：按实际生产日期 Packaging Info: 92119; MA 3L EAN包装+MA多语收藏指南+进口商贴纸+箱唛(进口商贴纸和UPC贴纸合并为一张） Remark: 92119: 7 Assortment, Polar bear: Penguin: Walrus: Mammoth: Owl: Seal: Snow man=10:10:10:10:10:8:2. Snow man is the rare item. | Y47: Ava Liang | Z47: 3.4 | AA47: =Z47*J47 -> 2733.6 | AB47: 804 | AC47: =AB47-J47 -> 0 | AD47: OK | AE47: 系统出单 | AF47: 94962-5.10 | AG47: 已入 | AJ47: =J47 -> 804 | AM47: =J47 -> 804 | AP47: =J47 -> 804 | AV47: MA布标 | AW47: =J47/60*10 -> 134 | AX47: =J47/60*10 -> 134 | AY47: =J47/60*8 -> 107.2 | AZ47: =J47/60*2 -> 26.8 | BA47: =J47/60*10 -> 134 | BB47: =J47/60*10 -> 134 | BC47: =J47/60*10 -> 134 | BD47: =SUM(AW47:BC47) -> 804 | BE47: =J47-BD47 -> 0
A48: 45726 | B48: DM LLC | C48: 俄罗斯联邦 | D48: 4500159526 | E48: 去Ural | F48: 4500159526-130 | G48: 92119-S001 | H48: 92124-S001-92119 | I48: 冰雪蛋（92119+9298+92104） | J48: 406 | K48: 0 | L48: 1 | M48: =J48/L48 -> 406 | N48: 45775 | O48: 45771 | P48: 转4500176865 | S48: 3/13收到 | U48: 空白贴纸 | W48: 外包装 (指: 收缩膜/彩卡/铝箔袋/挂卡/PDQ) /外箱不要打ZURU标准日期码！胶件可以打日期码DG20250421 | X48: 日期码格式：外包装/外箱不要打ZURU标准日期码 日期： Packaging Info: 注意 ：外包装 (指: 收缩膜/彩卡/铝箔袋/挂卡/PDQ) /外箱不要打ZURU标准日期码！胶件可以打日期码。 92124 ： 里面combo 产品1L MA 收缩膜（不含任何条码）， 客版托盘翻4500159461 ，MA指南/说明书（如有）； Remark: 标准配比 ； 请按期完货， 会有罚金。 出2个港口Bekasovo 2 和Ural . | Y48: Ann | Z48: 8.499 | AA48: =Z48*J48 -> 3450.594 | AB48: 812 | AC48: =AB48-J48 -> 406 | AD48: OK | AE48: 系统出单 | AG48: 已入 | AH48: =J48 -> 406 | AM48: =J48 -> 406 | AP48: =J48 -> 406 | AV48: MA布标 | AW48: =J48/60*10 -> 67.666667 | AX48: =J48/60*10 -> 67.666667 | AY48: =J48/60*8 -> 54.133333 | AZ48: =J48/60*2 -> 13.533333 | BA48: =J48/60*10 -> 67.666667 | BB48: =J48/60*10 -> 67.666667 | BC48: =J48/60*10 -> 67.666667 | BD48: =SUM(AW48:BC48) -> 406 | BE48: =J48-BD48 -> 0
A49: 45705 | B49: DIAMANT TOYS LTD | C49: 以色列 | D49: 4500153783 | E49: 56053 | F49: 4500153783-10 | G49: 92119-S001 | H49: 92119-S001 | I49: 冰雪蛋 | J49: 2208 | K49: 0 | L49: 12 | M49: =J49/L49 -> 184 | N49: 45777 | O49: 45773 | Q49: PASS | R49: 5/13出 | S49: 2/17收到 | U49: 进口商贴纸+彩色贴纸翻4500153742 | X49: 日期码格式：ZURU INC(BVI) 标准格式 日期：按实际生产日期 Packaging Info: 92119：1L MA收缩膜+进口商贴纸翻4500153742+彩色贴纸翻4500153742；MA指南 Remark: 7 Assortment, Polar bear: Penguin: Walrus: Mammoth: Owl: Seal: Snow man=10:10:10:10:10:8:2. Snow man is the rare item. | Y49: Lena Huang | Z49: 3.4 | AA49: =Z49*J49 -> 7507.2 | AB49: =2016+192 -> 2208 | AC49: =AB49-J49 -> 0 | AE49: 系统出单 | AG49: 已入 | AH49: =J49 -> 2208 | AM49: =J49 -> 2208 | AP49: =J49 -> 2208 | AV49: MA布标 | AW49: =J49/60*10 -> 368 | AX49: =J49/60*10 -> 368 | AY49: =J49/60*8 -> 294.4 | AZ49: =J49/60*2 -> 73.6 | BA49: =J49/60*10 -> 368 | BB49: =J49/60*10 -> 368 | BC49: =J49/60*10 -> 368 | BD49: =SUM(AW49:BC49) -> 2208 | BE49: =J49-BD49 -> 0
A50: 45729 | B50: GP TURKEY | C50: 土耳其 | D50: 4500159880 | E50: 84060 | F50: 4500159880-40 | G50: 92119-S001-NB | H50: 92119-S001-NB | I50: 冰雪蛋 | J50: 6000 | K50: 0 | L50: 12 | M50: =J50/L50 -> 500 | N50: 45771 | O50: 45768 | Q50: PASS | R50: 4/30出 | S50: 3/14收到 | U50: 3/28-进口商贴纸含客户EAN条码+Slime polybag贴纸+slime beads bag贴纸 | W50: ZUR5114 #92119 | X50: 日期码格式：客户日期码ZUR5114 日期： Packaging Info: 92119: 7 Assortment, Polar bear: Penguin: Walrus: Mammoth: Owl: Seal: Snow man=10:10:10:10:10:8:2. Snow man is the rare item. Remark: 92119: 1L MA 收缩膜+进口商贴纸含客户EAN条码; MA指南;Slime需要无硼版本。MA Slime polybag+贴纸/ MA slime beads bag +贴纸 2.客户日期码：ZUR5114, 产品/包装/外箱请保持一致。产品蛋壳需要印日期ZUR5114和对应的item号码92104TQ1/92119/9258 3.92119需要两套完整大货样,92119需要1套MA 样品，寄到客户香港办公室，请多备料，地址如下： Attn: Sylvia Li Company name: GP Services HK Limited Company address: Suite 1502, 15th Floor, Chinachem Golden Plaza, 77 Mody Road, TST East, Kowloon, Hong Kong Company address (Chinese): 香港九龍尖沙咀東部麼地道77號華懋廣場1502室 Contact Tel: +852 2739 5363 4.大货验货需要由ZURU QC抽如下数量样板寄到广州ITS做EN 71-3测试 #92119-1pcs #92104TQ1-3pcs (含3不同个颜色slime的产品) #9285SQ-1pcs #9258-1 pcs | Y50: Lena Huang | Z50: 3.4 | AA50: =Z50*J50 -> 20400 | AB50: =4992+1008 -> 6000 | AC50: =AB50-J50 -> 0 | AD50: OK | AE50: 系统出单 | AF50: 94939-5.7 | AG50: 已入 | AH50: =J50 -> 6000 | AM50: =J50 -> 6000 | AR50: =J50 -> 6000 | AV50: MA布标 | AW50: =J50/60*10 -> 1000 | AX50: =J50/60*10 -> 1000 | AY50: =J50/60*8 -> 800 | AZ50: =J50/60*2 -> 200 | BA50: =J50/60*10 -> 1000 | BB50: =J50/60*10 -> 1000 | BC50: =J50/60*10 -> 1000 | BD50: =SUM(AW50:BC50) -> 6000 | BE50: =J50-BD50 -> 0
A51: 45733 | B51: WAL-MART CANADA CORP. | C51: 加拿大 | D51: 4500160504 | E51: 9900923473 | F51: 450016050-100 | G51: 92119-S002-NB | H51: 92119-S002-NB | I51: 冰雪蛋 | J51: 627 | K51: 0 | L51: 1 | M51: =J51/L51 -> 627 | N51: 45775 | O51: 45771 | P51: 4/28抽办-5/19第三方 | Q51: PASS | R51: 5/27出 | S51: 3/25收到 | U51: 3/17-UPC贴纸 | X51: 日期码格式：ZURU INC(BVI) 标准格式 日期：按实际生产日期 Packaging Info: #92119： MA3L收缩膜(B版)+UPC贴纸(UPC:193052078391)+MA3L吊牌+MA5L收藏指南(B版)+MA5L复合袋+MA配件袋+MA5L贴纸+MA2L布标 产品配比： 7 Assortment, Polar bear: Penguin: Walrus: Mammoth: Owl: Seal: Snow man=10:10:10:10:10:8:2. Snow man is the rare item. Remark: 1. 此单有箱唛； 2. 9900923488/9900923472/9900923470/9900923474单为ECOM订单，外箱四面须加一张黄色贴纸； 3. 此单有第三方验货，烦请多备包装物料； 7. #92119需于2025/4/18安排签版, 签样数量：大货样各3PCS+齐套散件2套； 10. #92119 需于2025/4/28安排抽办测试, 抽办数量：大货各5 PCS+齐套散件4 SETS; 11. UPC贴纸：必须在原来错误的条码上用黑色粗头笔涂黑直至不能扫描，再贴上正确的UPC; ********************* a. 请确保产品符合1999年版本的加拿大环境保护法(CEPA)和2012年禁止某些有毒物质法规的要求。该产品不含任何在加拿大禁用的化学物质，包括但不限于有毒物 质清单中列出的化学物质，并且在为加拿大沃尔玛生产产品期间没有使用任何禁用化学物质。 Supplier certify that the products comply with the requirements of Canadian Environmental Protection Act, 1999 (CEPA), Prohibition of Certain To xic Substances Regulations, 2012. The products do not contain any chemicals that are banned in Canada, including but not limited to those listed in the Toxic Substances List and no banned chemicals were used during the manufacturing of product for Walmart Canada. 附件列表： (1) Letter of Guarantee for Canada banned chemicals - (1-5CA) b. 请确保产品在均质材料中的汞浓度不超过0.1%（按重量计）。 Supplier certify that the WAL-MART vendor products does not have a mercury concentration of more than 0.1% by weight in homogeneous material. 附件列表： (1) Letter of Guarantee for Mercury COC c. 请确保产品的塑料材料不含以下物质（SOR 2011-17 27B): Supplier certify that the plastic materials do not contain the following substances(SOR 2011-17 27B): (a) carbon tetrachloride or any substance that contains it; (b) methyl alcohol or any substance thay contains >1.0%; (c) petroleum distillates or any substance that contains >10% weight to volume of petroleum distillates; (d) benzene; (e) turpentine or any substance that contains >10% weight to volume of turpentine; (f) boric acid or salts of boric acid; or (g) ethyl ether. 附件列表： (1) Letter of Guarantee for WM CA-Other prohibited substances in plastic(less than 3 years) | Y51: Monica Zhou | Z51: 3.6 | AA51: =Z51*J51 -> 2257.2 | AB51: 627 | AC51: =AB51-J51 -> 0 | AD51: OK | AE51: 系统出单 | AG51: 已入 | AK51: =J51 -> 627 | AN51: =J51 -> 627 | AR51: =J51 -> 627 | AV51: MA布标 | AW51: =J51/60*10 -> 104.5 | AX51: =J51/60*10 -> 104.5 | AY51: =J51/60*8 -> 83.6 | AZ51: =J51/60*2 -> 20.9 | BA51: =J51/60*10 -> 104.5 | BB51: =J51/60*10 -> 104.5 | BC51: =J51/60*10 -> 104.5 | BD51: =SUM(AW51:BC51) -> 627 | BE51: =J51-BD51 -> 0
A52: 45730 | B52: CORPORACION FAVORITA C.A. | C52: 厄瓜多尔 | D52: 4500160092 | E52: 25-2101100JEC | F52: 4500160092-170 | G52: 92119-S001-3L | H52: 92119-S001 | I52: 冰雪蛋 | J52: 960 | K52: 0 | L52: 12 | M52: =J52/L52 -> 80 | N52: 45775 | O52: 45783 | Q52: PASS | R52: 5/12出 | S52: 3/24收到 | U52: 4/15UPC贴纸+进口商贴纸 | W52: 日期码格式：2025-05 | X52: 日期码格式：2025-05 日期： Packaging Info: 92119; MA 3L EAN包装+UPC贴纸+MA多语收藏指南+进口商贴纸+箱唛 Remark: 1.指定日期码：2025-05（外箱/产品/包装/进口商贴纸 日期码要一致。 如果部分半成品已打ZURU 标准日期码，满足不了指定日期码的要求，可以接受标准日期码，不用重复确认。) 2.所有item的包装上的条码必须是UPC，如果后续提供的贴纸资料已将进口商贴纸和UPC条码合并到一张， 则不需要额外再订购UPC贴纸资料，仅需要订购一张进口商贴纸 92119: 7 Assortment, Polar bear: Penguin: Walrus: Mammoth: Owl: Seal: Snow man=10:10:10:10:10:8:2. Snow man is the rare item. | Y52: Ava Liang | Z52: 3.4 | AA52: =Z52*J52 -> 3264 | AB52: 960 | AC52: =AB52-J52 -> 0 | AD52: OK | AE52: 系统出单 | AG52: 已入 | AJ52: =J52 -> 960 | AM52: =J52 -> 960 | AP52: =J52 -> 960 | AV52: MA布标 | AW52: =J52/60*10 -> 160 | AX52: =J52/60*10 -> 160 | AY52: =J52/60*8 -> 128 | AZ52: =J52/60*2 -> 32 | BA52: =J52/60*10 -> 160 | BB52: =J52/60*10 -> 160 | BC52: =J52/60*10 -> 160 | BD52: =SUM(AW52:BC52) -> 960 | BE52: =J52-BD52 -> 0
A53: 45734 | B53: ZURU LLC | C53: 美国 | D53: 4500160498 | E53: B0DS4V62X1 | F53: 4500160498-50 | G53: 92119E-S002 | H53: 92119E-S002-MTS | I53: 猛犸象 | J53: 96 | K53: 0 | L53: 12 | M53: =J53/L53 -> 8 | N53: 45777 | O53: 45773 | Q53: PASS | R53: 4/30出 | S53: 3/18收到 | U53: UPC贴纸翻4500158580 | X53: 日期码格式：ZURU INC(BVI) 标准格式 日期：按实际生产日期 Packaging Info: #92119 MA UPC版 (1L或3L都可)+UPC贴纸, 贴纸资料翻EU单4500158580 (但不需要印刷IT环保标贴纸) E:19305208 3852 Remark: 1.Amazon domestic 订单。出口美国。外箱最长边不能超过25" （超过了，case pack只能为1），不符合要求的大货，一律不接受。 2.无第三方验货/测试要求。 3.日期码使用ZURU标准版本。 4.邮包盒要印刷日期码。 | Y53: Kelly Shen/Mia Pan/P | Z53: 3.4 | AA53: =Z53*J53 -> 326.4 | AB53: 96 | AC53: =AB53-J53 -> 0 | AD53: OK | AE53: 系统出单 | AG53: 已入 | AH53: =J53 -> 96 | AM53: =J53 -> 96 | AP53: =J53 -> 96 | AV53: MA布标 | BB53: =J53 -> 96 | BD53: =SUM(AW53:BC53) -> 96 | BE53: =J53-BD53 -> 0
A54: 45734 | B54: ZURU LLC | C54: 美国 | D54: 4500160498 | E54: B0DS515N11 | F54: 4500160498-70 | G54: 92119B-S002 | H54: 92119B-S002-MTS | I54: 企鹅 | J54: 96 | K54: 0 | L54: 12 | M54: =J54/L54 -> 8 | N54: 45777 | O54: 45773 | Q54: PASS | R54: 4/30出 | S54: 3/18收到 | U54: UPC贴纸翻4500158580 | X54: 日期码格式：ZURU INC(BVI) 标准格式 日期：按实际生产日期 Packaging Info: #92119 MA UPC版 (1L或3L都可)+UPC贴纸, 贴纸资料翻EU单4500158580 (但不需要印刷IT环保标贴纸) B:193052083838 Remark: 1.Amazon domestic 订单。出口美国。外箱最长边不能超过25" （超过了，case pack只能为1），不符合要求的大货，一律不接受。 2.无第三方验货/测试要求。 3.日期码使用ZURU标准版本。 4.邮包盒要印刷日期码。 | Y54: Kelly Shen/Mia Pan/P | Z54: 3.4 | AA54: =Z54*J54 -> 326.4 | AB54: 96 | AC54: =AB54-J54 -> 0 | AD54: OK | AE54: 系统出单 | AG54: 已入 | AH54: =J54 -> 96 | AM54: =J54 -> 96 | AP54: =J54 -> 96 | AV54: MA布标 | AX54: =J54 -> 96 | BD54: =SUM(AW54:BC54) -> 96 | BE54: =J54-BD54 -> 0
A55: 45734 | B55: ZURU LLC | C55: 美国 | D55: 4500160498 | E55: B0DS5WSJ61 | F55: 4500160498-80 | G55: 92119D-S002 | H55: 92119D-S002-MTS | I55: 海象 | J55: 96 | K55: 0 | L55: 12 | M55: =J55/L55 -> 8 | N55: 45777 | O55: 45773 | Q55: PASS | R55: 4/30出 | S55: 3/18收到 | U55: UPC贴纸翻4500158580 | X55: 日期码格式：ZURU INC(BVI) 标准格式 日期：按实际生产日期 Packaging Info: #92119 MA UPC版 (1L或3L都可)+UPC贴纸, 贴纸资料翻EU单4500158580 (但不需要印刷IT环保标贴纸) D:193052083845 Remark: 1.Amazon domestic 订单。出口美国。外箱最长边不能超过25" （超过了，case pack只能为1），不符合要求的大货，一律不接受。 2.无第三方验货/测试要求。 3.日期码使用ZURU标准版本。 4.邮包盒要印刷日期码。 | Y55: Kelly Shen/Mia Pan/P | Z55: 3.4 | AA55: =Z55*J55 -> 326.4 | AB55: 96 | AC55: =AB55-J55 -> 0 | AD55: OK | AE55: 系统出单 | AG55: 已入 | AH55: =J55 -> 96 | AM55: =J55 -> 96 | AP55: =J55 -> 96 | AV55: MA布标 | BA55: =J55 -> 96 | BD55: =SUM(AW55:BC55) -> 96 | BE55: =J55-BD55 -> 0
A56: 45734 | B56: ZURU LLC | C56: 美国 | D56: 4500160498 | E56: B0DS5X5YHT | F56: 4500160498-90 | G56: 92119H-S002 | H56: 92119H-S002-MTS | I56: 海豹 | J56: 96 | K56: 0 | L56: 12 | M56: =J56/L56 -> 8 | N56: 45777 | O56: 45773 | Q56: PASS | R56: 4/30出 | S56: 3/18收到 | U56: UPC贴纸翻4500158580 | X56: 日期码格式：ZURU INC(BVI) 标准格式 日期：按实际生产日期 Packaging Info: #92119 MA UPC版 (1L或3L都可)+UPC贴纸, 贴纸资料翻EU单4500158580 (但不需要印刷IT环保标贴纸)H:193052083876 Remark: 1.Amazon domestic 订单。出口美国。外箱最长边不能超过25" （超过了，case pack只能为1），不符合要求的大货，一律不接受。 2.无第三方验货/测试要求。 3.日期码使用ZURU标准版本。 4.邮包盒要印刷日期码。 | Y56: Kelly Shen/Mia Pan/P | Z56: 3.4 | AA56: =Z56*J56 -> 326.4 | AB56: 96 | AC56: =AB56-J56 -> 0 | AD56: OK | AE56: 系统出单 | AG56: 已入 | AH56: =J56 -> 96 | AM56: =J56 -> 96 | AP56: =J56 -> 96 | AV56: MA布标 | AY56: =J56 -> 96 | BD56: =SUM(AW56:BC56) -> 96 | BE56: =J56-BD56 -> 0
A57: 45734 | B57: ZURU LLC | C57: 美国 | D57: 4500160498 | E57: B0DS5Y6M2D | F57: 4500160498-100 | G57: 92119G-S002 | H57: 92119G-S002-MTS | I57: 猫头鹰 | J57: 96 | K57: 0 | L57: 12 | M57: =J57/L57 -> 8 | N57: 45777 | O57: 45773 | Q57: PASS | R57: 4/30出 | S57: 3/18收到 | U57: UPC贴纸翻4500158580 | X57: 日期码格式：ZURU INC(BVI) 标准格式 日期：按实际生产日期 Packaging Info: #92119 MA UPC版 (1L或3L都可)+UPC贴纸, 贴纸资料翻EU单4500158580 (但不需要印刷IT环保标贴纸)G:193052083869 Remark: 1.Amazon domestic 订单。出口美国。外箱最长边不能超过25" （超过了，case pack只能为1），不符合要求的大货，一律不接受。 2.无第三方验货/测试要求。 3.日期码使用ZURU标准版本。 4.邮包盒要印刷日期码。 | Y57: Kelly Shen/Mia Pan/P | Z57: 3.4 | AA57: =Z57*J57 -> 326.4 | AB57: 96 | AC57: =AB57-J57 -> 0 | AD57: OK | AE57: 系统出单 | AG57: 已入 | AH57: =J57 -> 96 | AM57: =J57 -> 96 | AP57: =J57 -> 96 | AV57: MA布标 | BC57: =J57 -> 96 | BD57: =SUM(AW57:BC57) -> 96 | BE57: =J57-BD57 -> 0
A58: 45734 | B58: ZURU LLC | C58: 美国 | D58: 4500160498 | E58: B0DS5YC48M | F58: 4500160498-110 | G58: 92119A-S002 | H58: 92119A-S002-MTS | I58: 北极熊 | J58: 96 | K58: 0 | L58: 12 | M58: =J58/L58 -> 8 | N58: 45777 | O58: 45773 | Q58: PASS | R58: 4/30出 | S58: 3/18收到 | U58: UPC贴纸翻4500158580 | X58: 日期码格式：ZURU INC(BVI) 标准格式 日期：按实际生产日期 Packaging Info: #92119 MA UPC版 (1L或3L都可)+UPC贴纸, 贴纸资料翻EU单4500158580 (但不需要印刷IT环保标贴纸)A:193052083821 Remark: 1.Amazon domestic 订单。出口美国。外箱最长边不能超过25" （超过了，case pack只能为1），不符合要求的大货，一律不接受。 2.无第三方验货/测试要求。 3.日期码使用ZURU标准版本。 4.邮包盒要印刷日期码。 | Y58: Kelly Shen/Mia Pan/P | Z58: 3.4 | AA58: =Z58*J58 -> 326.4 | AB58: 96 | AC58: =AB58-J58 -> 0 | AD58: OK | AE58: 系统出单 | AG58: 已入 | AH58: =J58 -> 96 | AM58: =J58 -> 96 | AP58: =J58 -> 96 | AV58: MA布标 | AW58: =J58 -> 96 | BD58: =SUM(AW58:BC58) -> 96 | BE58: =J58-BD58 -> 0
A59: 45741 | B59: KAUFHAUS MARTIN STOLZ GMBH | C59: 德国 | D59: 4500160738 | E59: 25-179 | F59: 4500160738-40 | G59: 92119-S001-3L-NB | H59: 92119-S001-NB | I59: 冰雪蛋 | J59: 504 | K59: 0 | L59: 12 | M59: =J59/L59 -> 42 | N59: 45777 | O59: 45773 | Q59: PASS | R59: 5/15出 | S59: 3/27收到 | U59: 4/1-德语吊牌警语贴纸+4/19-客供价格贴纸 | X59: 日期码格式：ZURU INC(BVI) 标准格式 日期：按实际生产日期 Packaging Info: 92119：最新MA A版 3L+23L警语 EAN收缩膜（4894680042247）+ A版 5L+23L收藏指南+A版 5L史莱姆袋子/纸袋+MA 贴纸/水洗标+MA 3L吊牌+德语吊牌警语贴纸+客 供价格贴纸 Remark: "1. 此单出德国，需要满足Zuru Standard欧洲标准测试要求； 2. 请准时出货，推期会有罚款； 3. 出口欧洲，微塑料需符合法规。 4. 配比：标准配比 5. 大货样品一套 6. 需提供验货图片给客人确认才可以安排出货 7. 所有包装警语部分需含德语警语" | Y59: Joyce Chen | Z59: 3.4 | AA59: =Z59*J59 -> 1713.6 | AB59: 504 | AC59: =AB59-J59 -> 0 | AD59: OK | AE59: 系统出单 | AF59: 94961-5.10 | AG59: 已入 | AJ59: =J59 -> 504 | AM59: =J59 -> 504 | AR59: =J59 -> 504 | AV59: MA布标 | AW59: =J59/60*10 -> 84 | AX59: =J59/60*10 -> 84 | AY59: =J59/60*8 -> 67.2 | AZ59: =J59/60*2 -> 16.8 | BA59: =J59/60*10 -> 84 | BB59: =J59/60*10 -> 84 | BC59: =J59/60*10 -> 84 | BD59: =SUM(AW59:BC59) -> 504 | BE59: =J59-BD59 -> 0
A60: 45744 | B60: TARGET US | C60: 美国 | D60: 4500161831 | E60: 10001260974-3758 | F60: 4500161831-10 | G60: 92119-S003 | H60: 92119-S003 | I60: 冰雪蛋 | J60: 2872 | K60: 0 | L60: 8 | M60: =J60/L60 -> 359 | N60: 45783 | O60: 45779 | P60: 正常生产 | Q60: PASS | R60: 收到SO | S60: 4/1收到 | U60: 无 | V60: 4/16-外箱贴纸 | X60: 日期码格式：ZURU INC(BVI) 标准格式 日期：按实际生产日期 Packaging Info: 产品MA包装, MA 1L收缩膜(UPC版)； Remark: 1. 92119-S003-RAINBOCORNS-EGGZANIA-SERIES 1-FROZEN MANIA-SHRINK WRAP,8pcs/CTN 2. 产品MA包装, MA 1L收缩膜(UPC版)；收缩膜上的UPC显示193052078391； 7 Assortment, Polar bear: Penguin: Walrus: Mammoth: Owl: Seal: Snow man=10:10:10:10:10:8:2. Snow man is the rare item. 3. 外箱正唛左上角位置粘贴条码箱贴纸，每箱只贴一张，由ZURU订购。来料贴纸上显示的客户DPCI#086-08-4925, UPC显示10193052078398; 4. 产品和包装上印刷 tracking code信息，格式为ZURU常规格式; 5. 出货方式：货代自提 | Y60: Holly Zheng | Z60: 3.35 | AA60: =Z60*J60 -> 9621.2 | AB60: =472+2400 -> 2872 | AC60: =AB60-J60 -> 0 | AD60: OK | AE60: 系统出单 | AG60: 已入 | AH60: =J60 -> 2872 | AM60: =J60 -> 2872 | AR60: =J60 -> 2872 | AV60: MA布标 | AW60: =J60/60*10 -> 478.66667 | AX60: =J60/60*10 -> 478.66667 | AY60: =J60/60*8 -> 382.93333 | AZ60: =J60/60*2 -> 95.733333 | BA60: =J60/60*10 -> 478.66667 | BB60: =J60/60*10 -> 478.66667 | BC60: =J60/60*10 -> 478.66667 | BD60: =SUM(AW60:BC60) -> 2872 | BE60: =J60-BD60 -> 0
A61: 45754 | B61: ZURU Denmark ApS | C61: 丹麦 | D61: 4500162731 | E61: 5200006547 | F61: 4500162731-10 | G61: 92119-S005-NB-3L | H61: 92119-S005-NB-MTS | I61: 冰雪蛋 | J61: 2742 | K61: 0 | L61: 6 | M61: =J61/L61 -> 457 | N61: 45783 | O61: 45779 | Q61: PASS | R61: 5/6出 | S61: 4/10收到 | U61: 4/11-多语警告语贴纸+北欧五语通用Slime黑白说明书 | X61: 日期码格式：ZURU INC(BVI) 标准格式 日期：按实际生产日期 Packaging Info: MA 3L+23L B EAN 版本收缩膜+1*多语警告语贴纸+MA B 5L 收藏指南+MA 布标+ MA B slime 袋子+北欧五语通用Slime黑白说明书 Remark: 1.北欧内销单，需要通过ZURU 验货结果后才能出货 (工厂需要主动提前同ZURU QC预约验货避免延期出货造成不必要麻烦)； 2. 产品如含有化学品，需要无硼无香， 3.包装不能含有PVC，使用PET 4. date code: 外箱日期码要晚于产品日期码 5. 装柜时需要按照款式号码从小到大一款款依次装,避免终端仓库卸货混乱.若一个柜子涉及到几个不同国家内销单,装柜时需要一个国家装完后再装另一个国家的 产品,依次装柜,避免终端仓库因不同国家不同库位位置卸货混乱. (此点需要同工厂装柜人员强调)" 6.若有特定款有特殊外箱条码要求时,需要明确列出产品款对应的具体外箱条码号码/条码类型 (若无,可以忽略此需求) 7.所有出口欧洲的产品, 法规规定禁止在包装和共公众用的印刷品中使用矿物油中含有的物质, 包装印刷油墨中含有的MOAH/MOSH的质量浓度不能超过1%, 否则出货 到法国被抽检出现问题, 供应商需要对此负责; 8.带电池出货的产品所用到的电池需要符合欧洲电池新规(EU) 2023-1542。 9.ratio 同MA | Y61: SD04 | Z61: 3.55 | AA61: =Z61*J61 -> 9734.1 | AB61: 2742 | AC61: =AB61-J61 -> 0 | AD61: OK | AE61: 系统出单 | AF61: 94938-5.7 | AG61: 已入 | AJ61: =J61 -> 2742 | AM61: =J61 -> 2742 | AR61: =J61 -> 2742 | AV61: MA布标 | AW61: =J61/60*10 -> 457 | AX61: =J61/60*10 -> 457 | AY61: =J61/60*8 -> 365.6 | AZ61: =J61/60*2 -> 91.4 | BA61: =J61/60*10 -> 457 | BB61: =J61/60*10 -> 457 | BC61: =J61/60*10 -> 457 | BD61: =SUM(AW61:BC61) -> 2742 | BE61: =J61-BD61 -> 0
A62: 45714 | B62: Amazon ES | C62: 西班牙 | D62: 4500158607 | E62: Amazon ES: 3FG4VJMD | F62: 4500158607-10 | G62: 92119B-S002-3L | H62: 92119B-S002 | I62: 企鹅 | J62: 492 | K62: 0 | L62: 12 | M62: =J62/L62 -> 41 | N62: 45785 | O62: 45781 | Q62: PASS | R62: 5/18-5/25出 | S62: 空白外箱（加印带Zuru字样的最新logo，除了邮包盒直接做外箱的产品）MADE IN CHINA 外箱只印一正一侧 | U62: UPC+IT环保标翻单4500158580 | V62: 4/14-外箱贴纸 | X62: 日期码格式：ZURU INC(BVI) 标准格式 日期：按实际生产日期 Packaging Info: Amazon ES(92119BD) 1. 92119BD --92119B：92119B, Penguin, 12pcs/CTN; MA 3L(23L warning EAN#)A 收缩膜+2张贴纸(1张UPC#，1张IT环保标；参考翻单PO#4500158580)+MA 5L(23L warning)A 收藏指南+MA 3L A 吊牌+MA 5L A bag+MA 2L A sewn in label+其他最新MA配套包装； 2. 最迟验货不得晚于2025/5/9; Remark: 1.空白外箱（加印带Zuru字样的最新logo，除了邮包盒直接做外箱的产品） + SSCC LABEL一张, 无箱唛，MADE IN CHINA 外箱只印一正一侧。箱唛资料按照给定的 标准去做即可，无需发回我方再行审批(新标准将另行通知)。 (SSCC LABEL竖贴在外箱正面的正中间，贴一面即可,贴纸离外箱边距必须至少3.2CM。如竖贴无法满足要求，则横贴。如横贴也无法满足要求，则竖贴，遮到ZURU lo go无影响), SSCC贴纸由工厂直接跟勤得采购或者工厂自行采购，每一张SSCC Label都是唯一且有不同流水及条码，且需要检查条码是否能正常扫描，另外，此贴纸 印刷不可出现模糊，溢出及粘胶不牢易脱落等现象，如工厂不按此要求导致贴纸有任何问题产生的罚款将由工厂承担一切责任 。 2.出往UK的产品+包装务必打上UKCA logo ，否则客人会退货且当地会有罚款。 3.订单必须经过ZURU QC验货并且通过后方可出货。 4.法国订单要求包装不使用矿物油，请按要求提供以下其中一份文件再出货 ，产品出到法国被相关部门抽检出现包装不符合此要求的，供应商需要为此承担责任， 故此请严格把关。 -油墨物质""由1 ~ 7个芳香环组成的MOAH""的包装检测报告，要求限值≤1.0%； -包装材料清单，包括包装油墨或物质的信息； -油墨制造商的证书； 5.每一批次出货只能有一个生产日期，不可多个生产日期混在同一批次出货；且邮包盒上必须统一加上日期码；外箱对于日期码没有硬性规定； 6.涉及到相关款式会有闪粉的或者微塑料的，请统一默认出无闪粉或者不含微塑料版本； 7.邮包盒及外箱封箱必须是工字型封箱方式； 8.5 Surprise or Mini Brands涉及包装是2个及2个以上的球入PVC桶包装时，单个球上若有UPC#或者EAN#，请用白色贴纸覆盖住； | Y62: Mandy Hu | Z62: 3.6923 | AA62: =Z62*J62 -> 1816.6116 | AB62: 492 | AC62: =AB62-J62 -> 0 | AD62: OK | AE62: 系统出单 | AG62: 已入 | AJ62: =J62 -> 492 | AM62: =J62 -> 492 | AP62: =J62 -> 492 | AV62: MA布标 | AX62: =J62 -> 492 | BD62: =SUM(AW62:BC62) -> 492 | BE62: =J62-BD62 -> 0
A63: 45714 | B63: Amazon ES | C63: 西班牙 | D63: 4500158607 | E63: Amazon ES: 3FG4VJMD | F63: 4500158607-20 | G63: 92119D-S002-3L | H63: 92119D-S002 | I63: 海象 | J63: 492 | K63: 0 | L63: 12 | M63: =J63/L63 -> 41 | N63: 45785 | O63: 45781 | Q63: PASS | R63: 5/18-5/25出 | S63: 空白外箱（加印带Zuru字样的最新logo，除了邮包盒直接做外箱的产品）MADE IN CHINA 外箱只印一正一侧 | U63: UPC+IT环保标翻单4500158580 | V63: 4/14-外箱贴纸 | X63: 日期码格式：ZURU INC(BVI) 标准格式 日期：按实际生产日期 Packaging Info: Amazon ES(92119BD) 1. 92119BD --92119D：92119D, Walrus, 12pcs/CTN; MA 3L(23L warning EAN#)A 收缩膜+2张贴纸(1张UPC#，1张IT环保标; 参考翻单PO#4500158580)+MA 5L(23L warning)A 收 藏指南+MA 3L A 吊牌+MA 5L A bag+MA 2L A sewn in label+其他最新MA配套包装； 2. 最迟验货不得晚于2025/5/9; Remark: 1.空白外箱（加印带Zuru字样的最新logo，除了邮包盒直接做外箱的产品） + SSCC LABEL一张, 无箱唛，MADE IN CHINA 外箱只印一正一侧。箱唛资料按照给定的 标准去做即可，无需发回我方再行审批(新标准将另行通知)。 (SSCC LABEL竖贴在外箱正面的正中间，贴一面即可,贴纸离外箱边距必须至少3.2CM。如竖贴无法满足要求，则横贴。如横贴也无法满足要求，则竖贴，遮到ZURU lo go无影响), SSCC贴纸由工厂直接跟勤得采购或者工厂自行采购，每一张SSCC Label都是唯一且有不同流水及条码，且需要检查条码是否能正常扫描，另外，此贴纸 印刷不可出现模糊，溢出及粘胶不牢易脱落等现象，如工厂不按此要求导致贴纸有任何问题产生的罚款将由工厂承担一切责任 。 2.出往UK的产品+包装务必打上UKCA logo ，否则客人会退货且当地会有罚款。 3.订单必须经过ZURU QC验货并且通过后方可出货。 4.法国订单要求包装不使用矿物油，请按要求提供以下其中一份文件再出货 ，产品出到法国被相关部门抽检出现包装不符合此要求的，供应商需要为此承担责任， 故此请严格把关。 -油墨物质""由1 ~ 7个芳香环组成的MOAH""的包装检测报告，要求限值≤1.0%； -包装材料清单，包括包装油墨或物质的信息； -油墨制造商的证书； 5.每一批次出货只能有一个生产日期，不可多个生产日期混在同一批次出货；且邮包盒上必须统一加上日期码；外箱对于日期码没有硬性规定； 6.涉及到相关款式会有闪粉的或者微塑料的，请统一默认出无闪粉或者不含微塑料版本； 7.邮包盒及外箱封箱必须是工字型封箱方式； 8.5 Surprise or Mini Brands涉及包装是2个及2个以上的球入PVC桶包装时，单个球上若有UPC#或者EAN#，请用白色贴纸覆盖住； | Y63: Mandy Hu | Z63: 3.6923 | AA63: =Z63*J63 -> 1816.6116 | AB63: 492 | AC63: =AB63-J63 -> 0 | AD63: OK | AE63: 系统出单 | AG63: 已入 | AJ63: =J63 -> 492 | AM63: =J63 -> 492 | AP63: =J63 -> 492 | AV63: MA布标 | BA63: =J63 -> 492 | BD63: =SUM(AW63:BC63) -> 492 | BE63: =J63-BD63 -> 0
A64: 45720 | B64: AMAZON UK | C64: 英国 | D64: 4500158580 | E64: Amazon UK: 4NJDZ3UL | F64: 4500158580-10 | G64: 92119A-S002-3L | H64: 92119A-S002 | I64: 北极熊 | J64: 1104 | K64: 0 | L64: 12 | M64: =J64/L64 -> 92 | N64: 45785 | O64: 45780 | Q64: PASS | R64: 5/19出 | S64: 空白外箱（加印带Zuru字样的最新logo，除了邮包盒直接做外箱的产品） + SSCC LABEL一张, 无箱唛，MADE IN CHINA 外箱只印一正一侧。 | U64: 3/27-UPC#+IT环保标 | V64: 4/14-外箱贴纸 | X64: 日期码格式：ZURU INC(BVI) 标准格式 日期：按实际生产日期 Packaging Info: Amazon UK(92119ABDH)/DE(92119ABDH)/FR(92119BDH) 1. 92119ABDH: ---92119A: 92119A, Polar bear, 12pcs/CTN; MA 3L(23L warning EAN#)A 收缩膜+2张贴纸(1张UPC#+1张IT环保标)+MA 5L(23L warning)A 收藏指南+MA 3L A 吊 牌+MA 5L A bag+MA 2L A sewn in label+其他最新MA配套包装； L A bag+MA 2L A sewn in label+其他最新MA配套包装； 2. 验货时间不迟于2025/5/9. Remark: 1.空白外箱（加印带Zuru字样的最新logo，除了邮包盒直接做外箱的产品） + SSCC LABEL一张, 无箱唛，MADE IN CHINA 外箱只印一正一侧。箱唛资料按照给定的 标准去做即可，无需发回我方再行审批(新标准将另行通知)。 (SSCC LABEL竖贴在外箱正面的正中间，贴一面即可,贴纸离外箱边距必须至少3.2CM。如竖贴无法满足要求，则横贴。如横贴也无法满足要求，则竖贴，遮到ZURU lo go无影响), SSCC贴纸由工厂直接跟勤得采购或者工厂自行采购，每一张SSCC Label都是唯一且有不同流水及条码，且需要检查条码是否能正常扫描，另外，此贴纸 印刷不可出现模糊，溢出及粘胶不牢易脱落等现象，如工厂不按此要求导致贴纸有任何问题产生的罚款将由工厂承担一切责任 。 2.出往UK的产品+包装务必打上UKCA logo ，否则客人会退货且当地会有罚款。 3.订单必须经过ZURU QC验货并且通过后方可出货。 4.法国订单要求包装不使用矿物油，请按要求提供以下其中一份文件再出货 ，产品出到法国被相关部门抽检出现包装不符合此要求的，供应商需要为此承担责任， 故此请严格把关。 -油墨物质""由1 ~ 7个芳香环组成的MOAH""的包装检测报告，要求限值≤1.0%； -包装材料清单，包括包装油墨或物质的信息； -油墨制造商的证书； 5.每一批次出货只能有一个生产日期，不可多个生产日期混在同一批次出货；且邮包盒上必须统一加上日期码；外箱对于日期码没有硬性规定； 6.涉及到相关款式会有闪粉的或者微塑料的，请统一默认出无闪粉或者不含微塑料版本； 7.邮包盒及外箱封箱必须是工字型封箱方式； 8.5 Surprise or Mini Brands涉及包装是2个及2个以上的球入PVC桶包装时，单个球上若有UPC#或者EAN#，请用白色贴纸覆盖住； | Y64: Crystal Chen | Z64: 3.6835 | AA64: =Z64*J64 -> 4066.584 | AB64: 1104 | AC64: =AB64-J64 -> 0 | AD64: OK | AE64: 系统出单 | AG64: 已入 | AJ64: =J64 -> 1104 | AM64: =J64 -> 1104 | AP64: =J64 -> 1104 | AV64: MA布标 | AW64: =J64 -> 1104 | BD64: =SUM(AW64:BC64) -> 1104 | BE64: =J64-BD64 -> 0
A65: 45720 | B65: AMAZON UK | C65: 德国 | D65: 4500158580 | E65: Amazon DE: 1CLNXZ3P | F65: 4500158580-70 | G65: 92119A-S002-3L | H65: 92119A-S002 | I65: 北极熊 | J65: 756 | K65: 0 | L65: 12 | M65: =J65/L65 -> 63 | N65: 45785 | O65: 45780 | Q65: PASS | R65: 5/26出 | S65: 空白外箱（加印带Zuru字样的最新logo，除了邮包盒直接做外箱的产品） + SSCC LABEL一张, 无箱唛，MADE IN CHINA 外箱只印一正一侧。 | U65: 3/27-UPC#+IT环保标 | V65: 4/14-外箱贴纸 | X65: 日期码格式：ZURU INC(BVI) 标准格式 日期：按实际生产日期 Packaging Info: Amazon UK(92119ABDH)/DE(92119ABDH)/FR(92119BDH) 1. 92119ABDH: ---92119A: 92119A, Polar bear, 12pcs/CTN; MA 3L(23L warning EAN#)A 收缩膜+2张贴纸(1张UPC#+1张IT环保标)+MA 5L(23L warning)A 收藏指南+MA 3L A 吊 牌+MA 5L A bag+MA 2L A sewn in label+其他最新MA配套包装； L A bag+MA 2L A sewn in label+其他最新MA配套包装； 2. 验货时间不迟于2025/5/9. Remark: 1.空白外箱（加印带Zuru字样的最新logo，除了邮包盒直接做外箱的产品） + SSCC LABEL一张, 无箱唛，MADE IN CHINA 外箱只印一正一侧。箱唛资料按照给定的 标准去做即可，无需发回我方再行审批(新标准将另行通知)。 (SSCC LABEL竖贴在外箱正面的正中间，贴一面即可,贴纸离外箱边距必须至少3.2CM。如竖贴无法满足要求，则横贴。如横贴也无法满足要求，则竖贴，遮到ZURU lo go无影响), SSCC贴纸由工厂直接跟勤得采购或者工厂自行采购，每一张SSCC Label都是唯一且有不同流水及条码，且需要检查条码是否能正常扫描，另外，此贴纸 印刷不可出现模糊，溢出及粘胶不牢易脱落等现象，如工厂不按此要求导致贴纸有任何问题产生的罚款将由工厂承担一切责任 。 2.出往UK的产品+包装务必打上UKCA logo ，否则客人会退货且当地会有罚款。 3.订单必须经过ZURU QC验货并且通过后方可出货。 4.法国订单要求包装不使用矿物油，请按要求提供以下其中一份文件再出货 ，产品出到法国被相关部门抽检出现包装不符合此要求的，供应商需要为此承担责任， 故此请严格把关。 -油墨物质""由1 ~ 7个芳香环组成的MOAH""的包装检测报告，要求限值≤1.0%； -包装材料清单，包括包装油墨或物质的信息； -油墨制造商的证书； 5.每一批次出货只能有一个生产日期，不可多个生产日期混在同一批次出货；且邮包盒上必须统一加上日期码；外箱对于日期码没有硬性规定； 6.涉及到相关款式会有闪粉的或者微塑料的，请统一默认出无闪粉或者不含微塑料版本； 7.邮包盒及外箱封箱必须是工字型封箱方式； 8.5 Surprise or Mini Brands涉及包装是2个及2个以上的球入PVC桶包装时，单个球上若有UPC#或者EAN#，请用白色贴纸覆盖住； | Y65: Crystal Chen | Z65: 3.6835 | AA65: =Z65*J65 -> 2784.726 | AB65: 756 | AC65: =AB65-J65 -> 0 | AD65: OK | AE65: 系统出单 | AG65: 已入 | AJ65: =J65 -> 756 | AM65: =J65 -> 756 | AP65: =J65 -> 756 | AV65: MA布标 | AW65: =J65 -> 756 | BD65: =SUM(AW65:BC65) -> 756 | BE65: =J65-BD65 -> 0
A66: 45720 | B66: AMAZON UK | C66: 英国 | D66: 4500158580 | E66: Amazon UK: 36Z33HCR | F66: 4500158580-20 | G66: 92119B-S002-3L | H66: 92119B-S002 | I66: 企鹅 | J66: 768 | K66: 0 | L66: 12 | M66: =J66/L66 -> 64 | N66: 45785 | O66: 45780 | Q66: PASS | R66: 5/19出 | S66: 空白外箱（加印带Zuru字样的最新logo，除了邮包盒直接做外箱的产品） + SSCC LABEL一张, 无箱唛，MADE IN CHINA 外箱只印一正一侧。 | U66: 3/27-UPC#+IT环保标 | V66: 4/14-外箱贴纸 | X66: 日期码格式：ZURU INC(BVI) 标准格式 日期：按实际生产日期 Packaging Info: Amazon UK(92119ABDH)/DE(92119ABDH)/FR(92119BDH) 1. 92119ABDH: ---92119B: 92119B, Penguin, 12pcs/CTN; MA 3L(23L warning EAN#)A 收缩膜+2张贴纸(1张UPC#+1张IT环保标)+MA 5L(23L warning)A 收藏指南+MA 3L A 吊牌+MA 5L A bag+MA 2L A sewn in label+其他最新MA配套包装； 2. 验货时间不迟于2025/5/9. Remark: 1.空白外箱（加印带Zuru字样的最新logo，除了邮包盒直接做外箱的产品） + SSCC LABEL一张, 无箱唛，MADE IN CHINA 外箱只印一正一侧。箱唛资料按照给定的 标准去做即可，无需发回我方再行审批(新标准将另行通知)。 (SSCC LABEL竖贴在外箱正面的正中间，贴一面即可,贴纸离外箱边距必须至少3.2CM。如竖贴无法满足要求，则横贴。如横贴也无法满足要求，则竖贴，遮到ZURU lo go无影响), SSCC贴纸由工厂直接跟勤得采购或者工厂自行采购，每一张SSCC Label都是唯一且有不同流水及条码，且需要检查条码是否能正常扫描，另外，此贴纸 印刷不可出现模糊，溢出及粘胶不牢易脱落等现象，如工厂不按此要求导致贴纸有任何问题产生的罚款将由工厂承担一切责任 。 2.出往UK的产品+包装务必打上UKCA logo ，否则客人会退货且当地会有罚款。 3.订单必须经过ZURU QC验货并且通过后方可出货。 4.法国订单要求包装不使用矿物油，请按要求提供以下其中一份文件再出货 ，产品出到法国被相关部门抽检出现包装不符合此要求的，供应商需要为此承担责任， 故此请严格把关。 -油墨物质""由1 ~ 7个芳香环组成的MOAH""的包装检测报告，要求限值≤1.0%； -包装材料清单，包括包装油墨或物质的信息； -油墨制造商的证书； 5.每一批次出货只能有一个生产日期，不可多个生产日期混在同一批次出货；且邮包盒上必须统一加上日期码；外箱对于日期码没有硬性规定； 6.涉及到相关款式会有闪粉的或者微塑料的，请统一默认出无闪粉或者不含微塑料版本； 7.邮包盒及外箱封箱必须是工字型封箱方式； 8.5 Surprise or Mini Brands涉及包装是2个及2个以上的球入PVC桶包装时，单个球上若有UPC#或者EAN#，请用白色贴纸覆盖住； | Y66: Crystal Chen | Z66: 3.6835 | AA66: =Z66*J66 -> 2828.928 | AB66: 768 | AC66: =AB66-J66 -> 0 | AD66: OK | AE66: 系统出单 | AG66: 已入 | AJ66: =J66 -> 768 | AM66: =J66 -> 768 | AP66: =J66 -> 768 | AV66: MA布标 | AX66: =J66 -> 768 | BD66: =SUM(AW66:BC66) -> 768 | BE66: =J66-BD66 -> 0
A67: 45720 | B67: AMAZON UK | C67: 德国 | D67: 4500158580 | E67: Amazon DE: 89G15MLQ | F67: 4500158580-50 | G67: 92119B-S002-3L | H67: 92119B-S002 | I67: 企鹅 | J67: 756 | K67: 0 | L67: 12 | M67: =J67/L67 -> 63 | N67: 45785 | O67: 45780 | Q67: PASS | R67: 5/26出 | S67: 空白外箱（加印带Zuru字样的最新logo，除了邮包盒直接做外箱的产品） + SSCC LABEL一张, 无箱唛，MADE IN CHINA 外箱只印一正一侧。 | U67: 3/27-UPC#+IT环保标 | V67: 4/14-外箱贴纸 | X67: 日期码格式：ZURU INC(BVI) 标准格式 日期：按实际生产日期 Packaging Info: Amazon UK(92119ABDH)/DE(92119ABDH)/FR(92119BDH) 1. 92119ABDH: ---92119B: 92119B, Penguin, 12pcs/CTN; MA 3L(23L warning EAN#)A 收缩膜+2张贴纸(1张UPC#+1张IT环保标)+MA 5L(23L warning)A 收藏指南+MA 3L A 吊牌+MA 5L A bag+MA 2L A sewn in label+其他最新MA配套包装； 2. 验货时间不迟于2025/5/9. Remark: 1.空白外箱（加印带Zuru字样的最新logo，除了邮包盒直接做外箱的产品） + SSCC LABEL一张, 无箱唛，MADE IN CHINA 外箱只印一正一侧。箱唛资料按照给定的 标准去做即可，无需发回我方再行审批(新标准将另行通知)。 (SSCC LABEL竖贴在外箱正面的正中间，贴一面即可,贴纸离外箱边距必须至少3.2CM。如竖贴无法满足要求，则横贴。如横贴也无法满足要求，则竖贴，遮到ZURU lo go无影响), SSCC贴纸由工厂直接跟勤得采购或者工厂自行采购，每一张SSCC Label都是唯一且有不同流水及条码，且需要检查条码是否能正常扫描，另外，此贴纸 印刷不可出现模糊，溢出及粘胶不牢易脱落等现象，如工厂不按此要求导致贴纸有任何问题产生的罚款将由工厂承担一切责任 。 2.出往UK的产品+包装务必打上UKCA logo ，否则客人会退货且当地会有罚款。 3.订单必须经过ZURU QC验货并且通过后方可出货。 4.法国订单要求包装不使用矿物油，请按要求提供以下其中一份文件再出货 ，产品出到法国被相关部门抽检出现包装不符合此要求的，供应商需要为此承担责任， 故此请严格把关。 -油墨物质""由1 ~ 7个芳香环组成的MOAH""的包装检测报告，要求限值≤1.0%； -包装材料清单，包括包装油墨或物质的信息； -油墨制造商的证书； 5.每一批次出货只能有一个生产日期，不可多个生产日期混在同一批次出货；且邮包盒上必须统一加上日期码；外箱对于日期码没有硬性规定； 6.涉及到相关款式会有闪粉的或者微塑料的，请统一默认出无闪粉或者不含微塑料版本； 7.邮包盒及外箱封箱必须是工字型封箱方式； 8.5 Surprise or Mini Brands涉及包装是2个及2个以上的球入PVC桶包装时，单个球上若有UPC#或者EAN#，请用白色贴纸覆盖住； | Y67: Crystal Chen | Z67: 3.6835 | AA67: =Z67*J67 -> 2784.726 | AB67: 756 | AC67: =AB67-J67 -> 0 | AD67: OK | AE67: 系统出单 | AG67: 已入 | AJ67: =J67 -> 756 | AM67: =J67 -> 756 | AP67: =J67 -> 756 | AV67: MA布标 | AX67: =J67 -> 756 | BD67: =SUM(AW67:BC67) -> 756 | BE67: =J67-BD67 -> 0
A68: 45720 | B68: AMAZON UK | C68: 法国 | D68: 4500158580 | E68: Amazon FR: 68VU9BSH | F68: 4500158580-90 | G68: 92119B-S002-3L | H68: 92119B-S002 | I68: 企鹅 | J68: 492 | K68: 0 | L68: 12 | M68: =J68/L68 -> 41 | N68: 45785 | O68: 45780 | Q68: PASS | R68: 5/21出 | S68: 空白外箱（加印带Zuru字样的最新logo，除了邮包盒直接做外箱的产品） + SSCC LABEL一张, 无箱唛，MADE IN CHINA 外箱只印一正一侧。 | U68: 3/27-UPC#+IT环保标 | V68: 4/14-外箱贴纸 | X68: 日期码格式：ZURU INC(BVI) 标准格式 日期：按实际生产日期 Packaging Info: Amazon UK(92119ABDH)/DE(92119ABDH)/FR(92119BDH) 1. 92119ABDH: ---92119B: 92119B, Penguin, 12pcs/CTN; MA 3L(23L warning EAN#)A 收缩膜+2张贴纸(1张UPC#+1张IT环保标)+MA 5L(23L warning)A 收藏指南+MA 3L A 吊牌+MA 5L A bag+MA 2L A sewn in label+其他最新MA配套包装； 2. 验货时间不迟于2025/5/9. Remark: 1.空白外箱（加印带Zuru字样的最新logo，除了邮包盒直接做外箱的产品） + SSCC LABEL一张, 无箱唛，MADE IN CHINA 外箱只印一正一侧。箱唛资料按照给定的 标准去做即可，无需发回我方再行审批(新标准将另行通知)。 (SSCC LABEL竖贴在外箱正面的正中间，贴一面即可,贴纸离外箱边距必须至少3.2CM。如竖贴无法满足要求，则横贴。如横贴也无法满足要求，则竖贴，遮到ZURU lo go无影响), SSCC贴纸由工厂直接跟勤得采购或者工厂自行采购，每一张SSCC Label都是唯一且有不同流水及条码，且需要检查条码是否能正常扫描，另外，此贴纸 印刷不可出现模糊，溢出及粘胶不牢易脱落等现象，如工厂不按此要求导致贴纸有任何问题产生的罚款将由工厂承担一切责任 。 2.出往UK的产品+包装务必打上UKCA logo ，否则客人会退货且当地会有罚款。 3.订单必须经过ZURU QC验货并且通过后方可出货。 4.法国订单要求包装不使用矿物油，请按要求提供以下其中一份文件再出货 ，产品出到法国被相关部门抽检出现包装不符合此要求的，供应商需要为此承担责任， 故此请严格把关。 -油墨物质""由1 ~ 7个芳香环组成的MOAH""的包装检测报告，要求限值≤1.0%； -包装材料清单，包括包装油墨或物质的信息； -油墨制造商的证书； 5.每一批次出货只能有一个生产日期，不可多个生产日期混在同一批次出货；且邮包盒上必须统一加上日期码；外箱对于日期码没有硬性规定； 6.涉及到相关款式会有闪粉的或者微塑料的，请统一默认出无闪粉或者不含微塑料版本； 7.邮包盒及外箱封箱必须是工字型封箱方式； 8.5 Surprise or Mini Brands涉及包装是2个及2个以上的球入PVC桶包装时，单个球上若有UPC#或者EAN#，请用白色贴纸覆盖住； | Y68: Crystal Chen | Z68: 3.6835 | AA68: =Z68*J68 -> 1812.282 | AB68: 492 | AC68: =AB68-J68 -> 0 | AD68: OK | AE68: 系统出单 | AG68: 已入 | AJ68: =J68 -> 492 | AM68: =J68 -> 492 | AP68: =J68 -> 492 | AV68: MA布标 | AX68: =J68 -> 492 | BD68: =SUM(AW68:BC68) -> 492 | BE68: =J68-BD68 -> 0
A69: 45720 | B69: AMAZON UK | C69: 英国 | D69: 4500158580 | E69: Amazon UK: 36Z33HCR | F69: 4500158580-30 | G69: 92119D-S002-3L | H69: 92119D-S002 | I69: 海象 | J69: 564 | K69: 0 | L69: 12 | M69: =J69/L69 -> 47 | N69: 45785 | O69: 45780 | Q69: PASS | R69: 5/19出 | S69: 空白外箱（加印带Zuru字样的最新logo，除了邮包盒直接做外箱的产品） + SSCC LABEL一张, 无箱唛，MADE IN CHINA 外箱只印一正一侧。 | U69: 3/27-UPC#+IT环保标 | V69: 4/14-外箱贴纸 | X69: 日期码格式：ZURU INC(BVI) 标准格式 日期：按实际生产日期 Packaging Info: Amazon UK(92119ABDH)/DE(92119ABDH)/FR(92119BDH) 1. 92119ABDH: ---92119D: 92119D, Walrus, 12pcs/CTN; MA 3L(23L warning EAN#)A 收缩膜+2张贴纸(1张UPC#+1张IT环保标)+MA 5L(23L warning)A 收藏指南+MA 3L A 吊牌+MA 5L A bag+MA 2L A sewn in label+其他最新MA配套包装； 2. 验货时间不迟于2025/5/9. Remark: 1.空白外箱（加印带Zuru字样的最新logo，除了邮包盒直接做外箱的产品） + SSCC LABEL一张, 无箱唛，MADE IN CHINA 外箱只印一正一侧。箱唛资料按照给定的 标准去做即可，无需发回我方再行审批(新标准将另行通知)。 (SSCC LABEL竖贴在外箱正面的正中间，贴一面即可,贴纸离外箱边距必须至少3.2CM。如竖贴无法满足要求，则横贴。如横贴也无法满足要求，则竖贴，遮到ZURU lo go无影响), SSCC贴纸由工厂直接跟勤得采购或者工厂自行采购，每一张SSCC Label都是唯一且有不同流水及条码，且需要检查条码是否能正常扫描，另外，此贴纸 印刷不可出现模糊，溢出及粘胶不牢易脱落等现象，如工厂不按此要求导致贴纸有任何问题产生的罚款将由工厂承担一切责任 。 2.出往UK的产品+包装务必打上UKCA logo ，否则客人会退货且当地会有罚款。 3.订单必须经过ZURU QC验货并且通过后方可出货。 4.法国订单要求包装不使用矿物油，请按要求提供以下其中一份文件再出货 ，产品出到法国被相关部门抽检出现包装不符合此要求的，供应商需要为此承担责任， 故此请严格把关。 -油墨物质""由1 ~ 7个芳香环组成的MOAH""的包装检测报告，要求限值≤1.0%； -包装材料清单，包括包装油墨或物质的信息； -油墨制造商的证书； 5.每一批次出货只能有一个生产日期，不可多个生产日期混在同一批次出货；且邮包盒上必须统一加上日期码；外箱对于日期码没有硬性规定； 6.涉及到相关款式会有闪粉的或者微塑料的，请统一默认出无闪粉或者不含微塑料版本； 7.邮包盒及外箱封箱必须是工字型封箱方式； 8.5 Surprise or Mini Brands涉及包装是2个及2个以上的球入PVC桶包装时，单个球上若有UPC#或者EAN#，请用白色贴纸覆盖住； | Y69: Crystal Chen | Z69: 3.6835 | AA69: =Z69*J69 -> 2077.494 | AB69: 564 | AC69: =AB69-J69 -> 0 | AD69: OK | AE69: 系统出单 | AG69: 已入 | AJ69: =J69 -> 564 | AM69: =J69 -> 564 | AP69: =J69 -> 564 | AV69: MA布标 | BA69: =J69 -> 564 | BD69: =SUM(AW69:BC69) -> 564 | BE69: =J69-BD69 -> 0
A70: 45720 | B70: AMAZON UK | C70: 德国 | D70: 4500158580 | E70: Amazon DE: 1CLNXZ3P | F70: 4500158580-60 | G70: 92119D-S002-3L | H70: 92119D-S002 | I70: 海象 | J70: 576 | K70: 0 | L70: 12 | M70: =J70/L70 -> 48 | N70: 45785 | O70: 45780 | Q70: PASS | R70: 5/26出 | S70: 空白外箱（加印带Zuru字样的最新logo，除了邮包盒直接做外箱的产品） + SSCC LABEL一张, 无箱唛，MADE IN CHINA 外箱只印一正一侧。 | U70: 3/27-UPC#+IT环保标 | V70: 4/14-外箱贴纸 | X70: 日期码格式：ZURU INC(BVI) 标准格式 日期：按实际生产日期 Packaging Info: Amazon UK(92119ABDH)/DE(92119ABDH)/FR(92119BDH) 1. 92119ABDH: ---92119D: 92119D, Walrus, 12pcs/CTN; MA 3L(23L warning EAN#)A 收缩膜+2张贴纸(1张UPC#+1张IT环保标)+MA 5L(23L warning)A 收藏指南+MA 3L A 吊牌+MA 5L A bag+MA 2L A sewn in label+其他最新MA配套包装； 2. 验货时间不迟于2025/5/9. Remark: 1.空白外箱（加印带Zuru字样的最新logo，除了邮包盒直接做外箱的产品） + SSCC LABEL一张, 无箱唛，MADE IN CHINA 外箱只印一正一侧。箱唛资料按照给定的 标准去做即可，无需发回我方再行审批(新标准将另行通知)。 (SSCC LABEL竖贴在外箱正面的正中间，贴一面即可,贴纸离外箱边距必须至少3.2CM。如竖贴无法满足要求，则横贴。如横贴也无法满足要求，则竖贴，遮到ZURU lo go无影响), SSCC贴纸由工厂直接跟勤得采购或者工厂自行采购，每一张SSCC Label都是唯一且有不同流水及条码，且需要检查条码是否能正常扫描，另外，此贴纸 印刷不可出现模糊，溢出及粘胶不牢易脱落等现象，如工厂不按此要求导致贴纸有任何问题产生的罚款将由工厂承担一切责任 。 2.出往UK的产品+包装务必打上UKCA logo ，否则客人会退货且当地会有罚款。 3.订单必须经过ZURU QC验货并且通过后方可出货。 4.法国订单要求包装不使用矿物油，请按要求提供以下其中一份文件再出货 ，产品出到法国被相关部门抽检出现包装不符合此要求的，供应商需要为此承担责任， 故此请严格把关。 -油墨物质""由1 ~ 7个芳香环组成的MOAH""的包装检测报告，要求限值≤1.0%； -包装材料清单，包括包装油墨或物质的信息； -油墨制造商的证书； 5.每一批次出货只能有一个生产日期，不可多个生产日期混在同一批次出货；且邮包盒上必须统一加上日期码；外箱对于日期码没有硬性规定； 6.涉及到相关款式会有闪粉的或者微塑料的，请统一默认出无闪粉或者不含微塑料版本； 7.邮包盒及外箱封箱必须是工字型封箱方式； 8.5 Surprise or Mini Brands涉及包装是2个及2个以上的球入PVC桶包装时，单个球上若有UPC#或者EAN#，请用白色贴纸覆盖住； | Y70: Crystal Chen | Z70: 3.6835 | AA70: =Z70*J70 -> 2121.696 | AB70: =504+72 -> 576 | AC70: =AB70-J70 -> 0 | AD70: OK | AE70: 系统出单 | AG70: 已入 | AJ70: =J70 -> 576 | AM70: =J70 -> 576 | AP70: =J70 -> 576 | AV70: MA布标 | BA70: =J70 -> 576 | BD70: =SUM(AW70:BC70) -> 576 | BE70: =J70-BD70 -> 0
A71: 45720 | B71: AMAZON UK | C71: 法国 | D71: 4500158580 | E71: Amazon FR: 68VU9BSH | F71: 4500158580-100 | G71: 92119D-S002-3L | H71: 92119D-S002 | I71: 海象 | J71: 492 | K71: 0 | L71: 12 | M71: =J71/L71 -> 41 | N71: 45785 | O71: 45780 | Q71: PASS | R71: 5/21出 | S71: 空白外箱（加印带Zuru字样的最新logo，除了邮包盒直接做外箱的产品） + SSCC LABEL一张, 无箱唛，MADE IN CHINA 外箱只印一正一侧。 | U71: 3/27-UPC#+IT环保标 | V71: 4/14-外箱贴纸 | X71: 日期码格式：ZURU INC(BVI) 标准格式 日期：按实际生产日期 Packaging Info: Amazon UK(92119ABDH)/DE(92119ABDH)/FR(92119BDH) 1. 92119ABDH: ---92119D: 92119D, Walrus, 12pcs/CTN; MA 3L(23L warning EAN#)A 收缩膜+2张贴纸(1张UPC#+1张IT环保标)+MA 5L(23L warning)A 收藏指南+MA 3L A 吊牌+MA 5L A bag+MA 2L A sewn in label+其他最新MA配套包装； 2. 验货时间不迟于2025/5/9. Remark: 1.空白外箱（加印带Zuru字样的最新logo，除了邮包盒直接做外箱的产品） + SSCC LABEL一张, 无箱唛，MADE IN CHINA 外箱只印一正一侧。箱唛资料按照给定的 标准去做即可，无需发回我方再行审批(新标准将另行通知)。 (SSCC LABEL竖贴在外箱正面的正中间，贴一面即可,贴纸离外箱边距必须至少3.2CM。如竖贴无法满足要求，则横贴。如横贴也无法满足要求，则竖贴，遮到ZURU lo go无影响), SSCC贴纸由工厂直接跟勤得采购或者工厂自行采购，每一张SSCC Label都是唯一且有不同流水及条码，且需要检查条码是否能正常扫描，另外，此贴纸 印刷不可出现模糊，溢出及粘胶不牢易脱落等现象，如工厂不按此要求导致贴纸有任何问题产生的罚款将由工厂承担一切责任 。 2.出往UK的产品+包装务必打上UKCA logo ，否则客人会退货且当地会有罚款。 3.订单必须经过ZURU QC验货并且通过后方可出货。 4.法国订单要求包装不使用矿物油，请按要求提供以下其中一份文件再出货 ，产品出到法国被相关部门抽检出现包装不符合此要求的，供应商需要为此承担责任， 故此请严格把关。 -油墨物质""由1 ~ 7个芳香环组成的MOAH""的包装检测报告，要求限值≤1.0%； -包装材料清单，包括包装油墨或物质的信息； -油墨制造商的证书； 5.每一批次出货只能有一个生产日期，不可多个生产日期混在同一批次出货；且邮包盒上必须统一加上日期码；外箱对于日期码没有硬性规定； 6.涉及到相关款式会有闪粉的或者微塑料的，请统一默认出无闪粉或者不含微塑料版本； 7.邮包盒及外箱封箱必须是工字型封箱方式； 8.5 Surprise or Mini Brands涉及包装是2个及2个以上的球入PVC桶包装时，单个球上若有UPC#或者EAN#，请用白色贴纸覆盖住； | Y71: Crystal Chen | Z71: 3.6835 | AA71: =Z71*J71 -> 1812.282 | AB71: 492 | AC71: =AB71-J71 -> 0 | AD71: OK | AE71: 系统出单 | AG71: 已入 | AJ71: =J71 -> 492 | AM71: =J71 -> 492 | AP71: =J71 -> 492 | AV71: MA布标 | BA71: =J71 -> 492 | BD71: =SUM(AW71:BC71) -> 492 | BE71: =J71-BD71 -> 0
A72: 45720 | B72: AMAZON UK | C72: 英国 | D72: 4500158580 | E72: Amazon UK: 36Z33HCR | F72: 4500158580-40 | G72: 92119H-S002-3L | H72: 92119H-S002 | I72: 海豹 | J72: 900 | K72: 0 | L72: 12 | M72: =J72/L72 -> 75 | N72: 45785 | O72: 45780 | Q72: PASS | R72: 5/19出 | S72: 空白外箱（加印带Zuru字样的最新logo，除了邮包盒直接做外箱的产品） + SSCC LABEL一张, 无箱唛，MADE IN CHINA 外箱只印一正一侧。 | U72: 3/27-UPC#+IT环保标 | V72: 4/14-外箱贴纸 | X72: 日期码格式：ZURU INC(BVI) 标准格式 日期：按实际生产日期 Packaging Info: Amazon UK(92119ABDH)/DE(92119ABDH)/FR(92119BDH) 1. 92119ABDH: ---92119H: 92119H, Seal, 12pcs/CTN; MA 3L(23L warning EAN#)A 收缩膜+2张贴纸(1张UPC#+1张IT环保标)+MA 5L(23L warning)A 收藏指南+MA 3L A 吊牌+MA 5 L A bag+MA 2L A sewn in label+其他最新MA配套包装； 2. 验货时间不迟于2025/5/9. Remark: 1.空白外箱（加印带Zuru字样的最新logo，除了邮包盒直接做外箱的产品） + SSCC LABEL一张, 无箱唛，MADE IN CHINA 外箱只印一正一侧。箱唛资料按照给定的 标准去做即可，无需发回我方再行审批(新标准将另行通知)。 (SSCC LABEL竖贴在外箱正面的正中间，贴一面即可,贴纸离外箱边距必须至少3.2CM。如竖贴无法满足要求，则横贴。如横贴也无法满足要求，则竖贴，遮到ZURU lo go无影响), SSCC贴纸由工厂直接跟勤得采购或者工厂自行采购，每一张SSCC Label都是唯一且有不同流水及条码，且需要检查条码是否能正常扫描，另外，此贴纸 印刷不可出现模糊，溢出及粘胶不牢易脱落等现象，如工厂不按此要求导致贴纸有任何问题产生的罚款将由工厂承担一切责任 。 2.出往UK的产品+包装务必打上UKCA logo ，否则客人会退货且当地会有罚款。 3.订单必须经过ZURU QC验货并且通过后方可出货。 4.法国订单要求包装不使用矿物油，请按要求提供以下其中一份文件再出货 ，产品出到法国被相关部门抽检出现包装不符合此要求的，供应商需要为此承担责任， 故此请严格把关。 -油墨物质""由1 ~ 7个芳香环组成的MOAH""的包装检测报告，要求限值≤1.0%； -包装材料清单，包括包装油墨或物质的信息； -油墨制造商的证书； 5.每一批次出货只能有一个生产日期，不可多个生产日期混在同一批次出货；且邮包盒上必须统一加上日期码；外箱对于日期码没有硬性规定； 6.涉及到相关款式会有闪粉的或者微塑料的，请统一默认出无闪粉或者不含微塑料版本； 7.邮包盒及外箱封箱必须是工字型封箱方式； 8.5 Surprise or Mini Brands涉及包装是2个及2个以上的球入PVC桶包装时，单个球上若有UPC#或者EAN#，请用白色贴纸覆盖住； | Y72: Crystal Chen | Z72: 3.6835 | AA72: =Z72*J72 -> 3315.15 | AB72: 900 | AC72: =AB72-J72 -> 0 | AD72: OK | AE72: 系统出单 | AG72: 已入 | AJ72: =J72 -> 900 | AM72: =J72 -> 900 | AP72: =J72 -> 900 | AV72: MA布标 | AY72: =J72 -> 900 | BD72: =SUM(AW72:BC72) -> 900 | BE72: =J72-BD72 -> 0
A73: 45720 | B73: AMAZON UK | C73: 德国 | D73: 4500158580 | E73: Amazon DE: 1CLNXZ3P | F73: 4500158580-80 | G73: 92119H-S002-3L | H73: 92119H-S002 | I73: 海豹 | J73: 576 | K73: 0 | L73: 12 | M73: =J73/L73 -> 48 | N73: 45785 | O73: 45780 | Q73: PASS | R73: 5/26出 | S73: 空白外箱（加印带Zuru字样的最新logo，除了邮包盒直接做外箱的产品） + SSCC LABEL一张, 无箱唛，MADE IN CHINA 外箱只印一正一侧。 | U73: 3/27-UPC#+IT环保标 | V73: 4/14-外箱贴纸 | X73: 日期码格式：ZURU INC(BVI) 标准格式 日期：按实际生产日期 Packaging Info: Amazon UK(92119ABDH)/DE(92119ABDH)/FR(92119BDH) 1. 92119ABDH: ---92119H: 92119H, Seal, 12pcs/CTN; MA 3L(23L warning EAN#)A 收缩膜+2张贴纸(1张UPC#+1张IT环保标)+MA 5L(23L warning)A 收藏指南+MA 3L A 吊牌+MA 5 L A bag+MA 2L A sewn in label+其他最新MA配套包装； 2. 验货时间不迟于2025/5/9. Remark: 1.空白外箱（加印带Zuru字样的最新logo，除了邮包盒直接做外箱的产品） + SSCC LABEL一张, 无箱唛，MADE IN CHINA 外箱只印一正一侧。箱唛资料按照给定的 标准去做即可，无需发回我方再行审批(新标准将另行通知)。 (SSCC LABEL竖贴在外箱正面的正中间，贴一面即可,贴纸离外箱边距必须至少3.2CM。如竖贴无法满足要求，则横贴。如横贴也无法满足要求，则竖贴，遮到ZURU lo go无影响), SSCC贴纸由工厂直接跟勤得采购或者工厂自行采购，每一张SSCC Label都是唯一且有不同流水及条码，且需要检查条码是否能正常扫描，另外，此贴纸 印刷不可出现模糊，溢出及粘胶不牢易脱落等现象，如工厂不按此要求导致贴纸有任何问题产生的罚款将由工厂承担一切责任 。 2.出往UK的产品+包装务必打上UKCA logo ，否则客人会退货且当地会有罚款。 3.订单必须经过ZURU QC验货并且通过后方可出货。 4.法国订单要求包装不使用矿物油，请按要求提供以下其中一份文件再出货 ，产品出到法国被相关部门抽检出现包装不符合此要求的，供应商需要为此承担责任， 故此请严格把关。 -油墨物质""由1 ~ 7个芳香环组成的MOAH""的包装检测报告，要求限值≤1.0%； -包装材料清单，包括包装油墨或物质的信息； -油墨制造商的证书； 5.每一批次出货只能有一个生产日期，不可多个生产日期混在同一批次出货；且邮包盒上必须统一加上日期码；外箱对于日期码没有硬性规定； 6.涉及到相关款式会有闪粉的或者微塑料的，请统一默认出无闪粉或者不含微塑料版本； 7.邮包盒及外箱封箱必须是工字型封箱方式； 8.5 Surprise or Mini Brands涉及包装是2个及2个以上的球入PVC桶包装时，单个球上若有UPC#或者EAN#，请用白色贴纸覆盖住； | Y73: Crystal Chen | Z73: 3.6835 | AA73: =Z73*J73 -> 2121.696 | AB73: 576 | AC73: =AB73-J73 -> 0 | AD73: OK | AE73: 系统出单 | AG73: 已入 | AJ73: =J73 -> 576 | AM73: =J73 -> 576 | AP73: =J73 -> 576 | AV73: MA布标 | AY73: =J73 -> 576 | BD73: =SUM(AW73:BC73) -> 576 | BE73: =J73-BD73 -> 0
A74: 45720 | B74: AMAZON UK | C74: 法国 | D74: 4500158580 | E74: Amazon FR: 68VU9BSH | F74: 4500158580-110 | G74: 92119H-S002-3L | H74: 92119H-S002 | I74: 海豹 | J74: 492 | K74: 0 | L74: 12 | M74: =J74/L74 -> 41 | N74: 45785 | O74: 45780 | Q74: PASS | R74: 5/21出 | S74: 空白外箱（加印带Zuru字样的最新logo，除了邮包盒直接做外箱的产品） + SSCC LABEL一张, 无箱唛，MADE IN CHINA 外箱只印一正一侧。 | U74: 3/27-UPC#+IT环保标 | V74: 4/14-外箱贴纸 | X74: 日期码格式：ZURU INC(BVI) 标准格式 日期：按实际生产日期 Packaging Info: Amazon UK(92119ABDH)/DE(92119ABDH)/FR(92119BDH) 1. 92119ABDH: ---92119H: 92119H, Seal, 12pcs/CTN; MA 3L(23L warning EAN#)A 收缩膜+2张贴纸(1张UPC#+1张IT环保标)+MA 5L(23L warning)A 收藏指南+MA 3L A 吊牌+MA 5 L A bag+MA 2L A sewn in label+其他最新MA配套包装； 2. 验货时间不迟于2025/5/9. Remark: 1.空白外箱（加印带Zuru字样的最新logo，除了邮包盒直接做外箱的产品） + SSCC LABEL一张, 无箱唛，MADE IN CHINA 外箱只印一正一侧。箱唛资料按照给定的 标准去做即可，无需发回我方再行审批(新标准将另行通知)。 (SSCC LABEL竖贴在外箱正面的正中间，贴一面即可,贴纸离外箱边距必须至少3.2CM。如竖贴无法满足要求，则横贴。如横贴也无法满足要求，则竖贴，遮到ZURU lo go无影响), SSCC贴纸由工厂直接跟勤得采购或者工厂自行采购，每一张SSCC Label都是唯一且有不同流水及条码，且需要检查条码是否能正常扫描，另外，此贴纸 印刷不可出现模糊，溢出及粘胶不牢易脱落等现象，如工厂不按此要求导致贴纸有任何问题产生的罚款将由工厂承担一切责任 。 2.出往UK的产品+包装务必打上UKCA logo ，否则客人会退货且当地会有罚款。 3.订单必须经过ZURU QC验货并且通过后方可出货。 4.法国订单要求包装不使用矿物油，请按要求提供以下其中一份文件再出货 ，产品出到法国被相关部门抽检出现包装不符合此要求的，供应商需要为此承担责任， 故此请严格把关。 -油墨物质""由1 ~ 7个芳香环组成的MOAH""的包装检测报告，要求限值≤1.0%； -包装材料清单，包括包装油墨或物质的信息； -油墨制造商的证书； 5.每一批次出货只能有一个生产日期，不可多个生产日期混在同一批次出货；且邮包盒上必须统一加上日期码；外箱对于日期码没有硬性规定； 6.涉及到相关款式会有闪粉的或者微塑料的，请统一默认出无闪粉或者不含微塑料版本； 7.邮包盒及外箱封箱必须是工字型封箱方式； 8.5 Surprise or Mini Brands涉及包装是2个及2个以上的球入PVC桶包装时，单个球上若有UPC#或者EAN#，请用白色贴纸覆盖住； | Y74: Crystal Chen | Z74: 3.6835 | AA74: =Z74*J74 -> 1812.282 | AB74: 492 | AC74: =AB74-J74 -> 0 | AD74: OK | AE74: 系统出单 | AG74: 已入 | AJ74: =J74 -> 492 | AM74: =J74 -> 492 | AP74: =J74 -> 492 | AV74: MA布标 | AY74: =J74 -> 492 | BD74: =SUM(AW74:BC74) -> 492 | BE74: =J74-BD74 -> 0
A75: 45726 | B75: 360 SALES SOLUTIONS INC | C75: 加拿大 | D75: 4500159666 | E75: 2025ZURU11 | F75: 4500159666-30 | G75: 92119-S005-NB-3L | H75: 92119-S005-NB | I75: 冰雪蛋 | J75: 1200 | K75: 0 | L75: 6 | M75: =J75/L75 -> 200 | N75: 45786 | O75: 45782 | Q75: PASS | R75: 5/20出 | S75: 3/11收到 | U75: 3/10-UPC贴纸 | X75: 日期码格式： 标准格式 日期：按实际生产日期 Packaging Info: 92119 无硼版本。MA 多语EAN+UPC贴纸， UPC号码193052078391 Remark: 出加拿大 Zuru验货.日期跟踪码：产品外包装及产品本身都必须有日期跟踪码，ZURU标准格式日期码。（箱唛日期码按跟单提供格式） | Y75: Summer Mo | Z75: 3.55 | AA75: =Z75*J75 -> 4260 | AB75: 1200 | AC75: =AB75-J75 -> 0 | AD75: OK | AE75: 系统出单 | AG75: 已入 | AJ75: =J75 -> 1200 | AM75: =J75 -> 1200 | AR75: =J75 -> 1200 | AV75: MA布标 | AW75: =J75/60*10 -> 200 | AX75: =J75/60*10 -> 200 | AY75: =J75/60*8 -> 160 | AZ75: =J75/60*2 -> 40 | BA75: =J75/60*10 -> 200 | BB75: =J75/60*10 -> 200 | BC75: =J75/60*10 -> 200 | BD75: =SUM(AW75:BC75) -> 1200 | BE75: =J75-BD75 -> 0
A76: 45750 | B76: HARVEY WHOLESALE LTD | C76: 新西兰 | D76: 4500162561 | E76: 3004 | F76: 4500162561-10 | G76: 92119-S005 | H76: 92119-S005 | I76: 冰雪蛋 | J76: 504 | K76: 0 | L76: 6 | M76: =J76/L76 -> 84 | N76: 45786 | O76: 45782 | Q76: PASS | R76: 5/17出 | S76: 4/3收到 | U76: 无 | X76: 日期码格式：ZURU INC(BVI) 标准格式 日期：按实际生产日期 Packaging Info: #92119:7 Assortment, Polar bear: Penguin: Walrus: Mammoth: Owl: Seal: Snow man=10:10:10:10:10:8:2. Snow man is the rare item. Remark: MA UPC 英语包装（优先1L英语版本,或者3L/L含英语即可 | Y76: Abby Liang | Z76: 3.5 | AA76: =Z76*J76 -> 1764 | AB76: 504 | AC76: =AB76-J76 -> 0 | AD76: 无 | AE76: 系统出单 | AG76: 已入 | AH76: =J76 -> 504 | AM76: =J76 -> 504 | AP76: =J76 -> 504 | AV76: MA布标 | AW76: =J76/60*10 -> 84 | AX76: =J76/60*10 -> 84 | AY76: =J76/60*8 -> 67.2 | AZ76: =J76/60*2 -> 16.8 | BA76: =J76/60*10 -> 84 | BB76: =J76/60*10 -> 84 | BC76: =J76/60*10 -> 84 | BD76: =SUM(AW76:BC76) -> 504 | BE76: =J76-BD76 -> 0
A77: 45747 | B77: MEIJER DISTRIBUTION, INC. | C77: 美国 | D77: 4500161445 | E77: 216951853 | F77: 4500161445-20 | G77: 92119-S006 | H77: 92119-S006 | I77: 冰雪蛋 | J77: 800 | K77: 0 | L77: 4 | M77: =J77/L77 -> 200 | N77: 45790 | O77: 45786 | Q77: PASS | R77: 5/22出 | S77: 4/9收到 | U77: 无 | X77: 日期码格式：ZURU INC(BVI) 标准格式 日期： Packaging Info: 1. MA 1L 包装 2. 客人指定箱唛排版 Remark: 出货前 Zuru QC 验货 | Y77: Cherie Li | Z77: 3.55 | AA77: =Z77*J77 -> 2840 | AB77: 800 | AC77: =AB77-J77 -> 0 | AD77: 无 | AE77: 系统出单 | AG77: 已入 | AH77: =J77 -> 800 | AM77: =J77 -> 800 | AP77: =J77 -> 800 | AV77: MA布标 | AW77: =J77/60*10 -> 133.33333 | AX77: =J77/60*10 -> 133.33333 | AY77: =J77/60*8 -> 106.66667 | AZ77: =J77/60*2 -> 26.666667 | BA77: =J77/60*10 -> 133.33333 | BB77: =J77/60*10 -> 133.33333 | BC77: =J77/60*10 -> 133.33333 | BD77: =SUM(AW77:BC77) -> 800 | BE77: =J77-BD77 -> 0
A78: 45748 | B78: T. PLANET SHOPS SL | C78: 西班牙 | D78: 4500162134 | F78: 4500162134-20 | G78: 92119-S001-3L | H78: 92119-S001 | I78: 冰雪蛋 | J78: 1500 | K78: 0 | L78: 12 | M78: =J78/L78 -> 125 | N78: 45789 | O78: 45785 | Q78: PASS | R78: 5/15出 | S78: 4/16收到 | U78: 4/21-进口商贴纸+产品贴纸 | W78: 指定20250202 | X78: 日期码格式：20250202 日期： Packaging Info: 92119:MA B 3L收缩膜含EAN条码+进口商贴纸+MA B 5L收藏指南+MA最新5L纸袋/polybag+MA布标 Remark: 1, 此货出西班牙，需满足EU测试标准要求<(>&<)> 微塑料需符合法规。另外请确保所有包装都有西班牙环保标。 2，出货前两周需寄2-3套大货样品，请多备料 3, 此客人推期有罚款，请按时完货 4, 出货前要验货图片给客人确认OK后才出货 6. 其他款，若产品有比例使用ZURU STD 比例 8. 客户指定日期码码20250202，包装/产品/外箱需保持一致 | Y78: Mary Zhong | Z78: 3.4 | AA78: =Z78*J78 -> 5100 | AB78: =468+936+24+72 -> 1500 | AC78: =AB78-J78 -> 0 | AD78: OK | AE78: 系统出单 | AG78: 已入 | AJ78: =J78 -> 1500 | AM78: =J78 -> 1500 | AP78: =J78 -> 1500 | AV78: MA布标 | AW78: =J78/60*10 -> 250 | AX78: =J78/60*10 -> 250 | AY78: =J78/60*8 -> 200 | AZ78: =J78/60*2 -> 50 | BA78: =J78/60*10 -> 250 | BB78: =J78/60*10 -> 250 | BC78: =J78/60*10 -> 250 | BD78: =SUM(AW78:BC78) -> 1500 | BE78: =J78-BD78 -> 0
A79: 45756 | B79: DIAMANT TOYS LTD | C79: 以色列 | D79: 4500163062 | E79: 56053 | F79: 4500163062-10 | G79: 92119-S001 | H79: 92119-S001 | I79: 冰雪蛋 | J79: 4320 | K79: 0 | L79: 12 | M79: =J79/L79 -> 360 | N79: 45789 | O79: 45785 | Q79: PASS | R79: 5/30出 | S79: 4/11收到 | U79: 进口商贴纸+彩色贴纸翻4500153742 | X79: 日期码格式：ZURU INC(BVI) 标准格式 日期：按实际生产日期 Packaging Info: 92119：1L MA收缩膜+进口商贴纸(翻4500153742)+彩色贴纸(翻4500153742)；MA指南 Remark: 92119：7 Assortment, Polar bear: Penguin: Walrus: Mammoth: Owl: Seal: Snow man=10:10:10:10:10:8:2. Snow man is the rare item. | Y79: Lena Huang | Z79: 3.4 | AA79: =Z79*J79 -> 14688 | AB79: =4032+36+252 -> 4320 | AC79: =AB79-J79 -> 0 | AD79: OK | AE79: 系统出单 | AG79: 已入 | AH79: =J79 -> 4320 | AM79: =J79 -> 4320 | AP79: =J79 -> 4320 | AV79: MA布标 | AW79: =J79/60*10 -> 720 | AX79: =J79/60*10 -> 720 | AY79: =J79/60*8 -> 576 | AZ79: =J79/60*2 -> 144 | BA79: =J79/60*10 -> 720 | BB79: =J79/60*10 -> 720 | BC79: =J79/60*10 -> 720 | BD79: =SUM(AW79:BC79) -> 4320 | BE79: =J79-BD79 -> 0
A80: 45749 | B80: SAINSBURY'S SUPERMARKET LTD | C80: 英国 | D80: 4500162070 | E80: PO2734192 | F80: 4500162070-20 | G80: 92119-S001 | H80: 92119-S001 | I80: 冰雪蛋 | J80: 4992 | K80: 0 | L80: 12 | M80: =J80/L80 -> 416 | N80: 45789 | O80: 45785 | Q80: PASS | R80: 5/19出 | S80: 4/2收到 | U80: 无 | X80: 日期码格式：ZURU INC(BVI) 标准格式 日期：按实际生产日期 Packaging Info: 2.92119：MA 1L UPC包装 Remark: *胶带最少宽度要保证6.0CM,厚度最少0.05毫米,外箱不可以打钉/扎带；以工字型封箱； *如果重量超过5KGS，箱唛需加黄色警示图标志 ，有疑问请与ZURU跟单同事联系,十分重要！ *订单出英国，请注意检查产品及包装应带UKCA图标，包装显示ZURU UK LTD信息，QC同事请查核，如有问题与跟单确认。 *MA版本按工厂现有最新库存即可，订单出英国，请注意检查产品及包装应带UKCA图标，包装显示ZURU UK LTD信息，QC同事请查核，如有问题与跟单确认。 *生产日期按实际的（法定工作日），按ZURU标准格式即可 ，但是请知悉包装日期码需要早于或者等于外箱日期码 ，不能晚于外箱日期码 *请注意所有订单都需要经过ZURU QC验货并且通过后方可出货 *产品条码以订单显示为准 ，请安排生产前先核对再生产或者与Sherry 复核再安排 。 *外箱上的条码请确保清晰可扫描 ，否则到目的仓无法扫描入仓由工厂承担责任 。 *所有产品按符合欧洲标准走货，需要是不含微塑料版本 。 *涉及到硼的，请使用低硼版本 *客户不接受PVC材质 *外箱不得使用带金属夹子或带扣 | Y80: May Wu | Z80: 3.4 | AA80: =Z80*J80 -> 16972.8 | AB80: =480+4512 -> 4992 | AC80: =AB80-J80 -> 0 | AD80: 无 | AE80: 系统出单 | AG80: 已入 | AH80: =J80 -> 4992 | AM80: =J80 -> 4992 | AP80: =J80 -> 4992 | AV80: MA布标 | AW80: =J80/60*10 -> 832 | AX80: =J80/60*10 -> 832 | AY80: =J80/60*8 -> 665.6 | AZ80: =J80/60*2 -> 166.4 | BA80: =J80/60*10 -> 832 | BB80: =J80/60*10 -> 832 | BC80: =J80/60*10 -> 832 | BD80: =SUM(AW80:BC80) -> 4992 | BE80: =J80-BD80 -> 0
A81: 45747 | B81: KMART AUSTRALIA LTD(NEW ZEALAND) | C81: 新西兰 | D81: 4500161963 | E81: 20739449 | F81: 4500161963-50 | G81: 92119-S001 | H81: 92119-S001 | I81: 冰雪蛋 | J81: 96 | K81: 0 | L81: 12 | M81: =J81/L81 -> 8 | N81: 45789 | O81: 45785 | Q81: PASS | R81: 5/14-5/16出 | S81: 4/10收到 | U81: 4/25-防盗贴纸+4/21-外箱贴纸 | X81: 日期码格式：ZURU INC(BVI) 标准格式 日期：按实际生产日期 Packaging Info: 92119-S001 : MA英语UPC版本包装（收缩膜和说明书, MA首选1L，如无1L可用多语且含英语的配套多语包装) + 1张防盗贴纸 (贴纸以及位置图翻单PO#4500160268） + 箱唛 + 外箱SSCC Label 配比信息：7 Assortment, Polar bear: Penguin: Walrus: Mammoth: Owl: Seal: Snow man=10:10:10:10:10:8:2. Snow man is the rare item. Remark: 1.请务必按时完货，验货。并且按期送货入货代指定仓库，如果晚了导致船期Delay将会有罚金产生或者客户要求空运，所产生的罚金和空运费由工厂承担。 2.SSCC 外箱贴纸请同纸箱瓦楞纸方向（竖纹向）垂直，即外箱贴纸横着贴(注意条码不要被胶带粘住），贴1pc，贴1面正唛，封箱胶纸不能挡住贴纸内容。外箱贴纸 离外箱边距离不少于2cm。 3.外箱材质为ZURU标准； 4.此单需使用KMART封箱胶上下工字型封箱;从2019年6月开始，要用KMART 新版封箱胶带，此单要用"ANKO"封箱胶带 5.此单出口新西兰，请按相应的澳新标准生产； 6.产品和包装上生产批号的显示格式ZURU标准日期码格式 7.外箱信息不可手写，重量和体积需要与实际的一致(不可手写） 8. 每款item装箱后的G.W.超过10KG或者CBM超过0.13,(9.5KG或者以上，四舍五入后也属于10KG) 需在外箱上加印超 重或者Bulky LOGO，若发现我们资料没有，请 帮忙提醒 1)重量超过10kg但不超过16kg且CBM不超过0.13,10-16kg 超重logo 2）CBM超过0.13且重量少于17kg，bulky logo 3）不属于以上两种情况，需要使用相应重量范围内的超重logo 4）超重logo需要在外箱四面都印刷(箱唛右上角，两面侧唛超重logo需要尽量靠近毛重)，尺寸为:110mm height* 95mm width 9. 实际外箱重量跟印在箱唛上的数据差异不能超3%，尺寸按实际数据印刷 | Y81: Lydia Wu | Z81: 3.67 | AA81: =Z81*J81 -> 352.32 | AB81: 96 | AC81: =AB81-J81 -> 0 | AD81: OK | AE81: 系统出单 | AG81: 已入 | AH81: =J81 -> 96 | AM81: =J81 -> 96 | AP81: =J81 -> 96 | AV81: MA布标 | AW81: =J81/60*10 -> 16 | AX81: =J81/60*10 -> 16 | AY81: =J81/60*8 -> 12.8 | AZ81: =J81/60*2 -> 3.2 | BA81: =J81/60*10 -> 16 | BB81: =J81/60*10 -> 16 | BC81: =J81/60*10 -> 16 | BD81: =SUM(AW81:BC81) -> 96 | BE81: =J81-BD81 -> 0
A82: 45747 | B82: KMART AUSTRALIA LTD | C82: 澳大利亚 | D82: 4500161960 | E82: 20739448 | F82: 4500161960-60 | G82: 92119-S001 | H82: 92119-S001 | I82: 冰雪蛋 | J82: 1668 | K82: 0 | L82: 12 | M82: =J82/L82 -> 139 | N82: 45789 | O82: 45785 | Q82: PASS | R82: 5/14-5/16出 | S82: 4/10收到 | U82: 4/25-防盗贴纸+4/21-外箱贴纸 | X82: 日期码格式：ZURU INC(BVI) 标准格式 日期：按实际生产日期 Packaging Info: 92119-S001 : MA英语UPC版本包装（收缩膜和说明书, MA首选1L，如无1L可用多语且含英语的配套多语包装) + 1张防盗贴纸 (贴纸以及位置图翻单PO#4500160268） + 箱唛 + 外箱SSCC Label 配比信息：7 Assortment, Polar bear: Penguin: Walrus: Mammoth: Owl: Seal: Snow man=10:10:10:10:10:8:2. Snow man is the rare item. Remark: 1.请务必按时完货，验货。并且按期送货入货代指定仓库，如果晚了导致船期Delay将会有罚金产生或者客户要求空运，所产生的罚金和空运费由工厂承担。 2.SSCC 外箱贴纸请同纸箱瓦楞纸方向（竖纹向）垂直，即外箱贴纸横着贴(注意条码不要被胶带粘住），贴1pc，贴1面正唛，封箱胶纸不能挡住贴纸内容。外箱贴纸 离外箱边距离不少于2cm。 3.外箱材质为ZURU标准； 4.此单需使用KMART封箱胶上下工字型封箱;从2019年6月开始，要用KMART 新版封箱胶带，此单要用"ANKO"封箱胶带 5.此单出口澳大利亚，请按相应的澳新标准生产； 6.产品和包装上生产批号的显示格式ZURU标准日期码格式 7.外箱信息不可手写，重量和体积需要与实际的一致(不可手写） 8. 每款item装箱后的G.W.超过10KG或者CBM超过0.13,(9.5KG或者以上，四舍五入后也属于10KG) 需在外箱上加印超 重或者Bulky LOGO，若发现我们资料没有，请 帮忙提醒 1)重量超过10kg但不超过16kg且CBM不超过0.13,10-16kg 超重logo 2）CBM超过0.13且重量少于17kg，bulky logo 3）不属于以上两种情况，需要使用相应重量范围内的超重logo 4）超重logo需要在外箱四面都印刷(箱唛右上角，两面侧唛超重logo需要尽量靠近毛重)，尺寸为:110mm height* 95mm width 9. 实际外箱重量跟印在箱唛上的数据差异不能超3%，尺寸按实际数据印刷 | Y82: Lydia Wu | Z82: 3.67 | AA82: =Z82*J82 -> 6121.56 | AB82: 1668 | AC82: =AB82-J82 -> 0 | AD82: OK | AE82: 系统出单 | AG82: 已入 | AH82: =J82 -> 1668 | AM82: =J82 -> 1668 | AP82: =J82 -> 1668 | AV82: MA布标 | AW82: =J82/60*10 -> 278 | AX82: =J82/60*10 -> 278 | AY82: =J82/60*8 -> 222.4 | AZ82: =J82/60*2 -> 55.6 | BA82: =J82/60*10 -> 278 | BB82: =J82/60*10 -> 278 | BC82: =J82/60*10 -> 278 | BD82: =SUM(AW82:BC82) -> 1668 | BE82: =J82-BD82 -> 0
A83: 45747 | B83: MEIJER DISTRIBUTION, INC. | C83: 美国 | D83: 4500161496 | E83: 216951858 | F83: 4500161496-20 | G83: 92119-S006 | H83: 92119-S006 | I83: 冰雪蛋 | J83: 428 | K83: 0 | L83: 4 | M83: =J83/L83 -> 107 | N83: 45790 | O83: 45786 | Q83: PASS | R83: 5/22出 | S83: 4/9收到 | U83: 无 | X83: 日期码格式：ZURU INC(BVI) 标准格式 日期： Packaging Info: 1. MA 1L 包装 2. 客人指定箱唛排版 Remark: 出货前 Zuru QC 验货 | Y83: Cherie Li | Z83: 3.55 | AA83: =Z83*J83 -> 1519.4 | AB83: 428 | AC83: =AB83-J83 -> 0 | AD83: 无 | AE83: 系统出单 | AG83: 已入 | AH83: =J83 -> 428 | AM83: =J83 -> 428 | AP83: =J83 -> 428 | AV83: MA布标 | AW83: =J83/60*10 -> 71.333333 | AX83: =J83/60*10 -> 71.333333 | AY83: =J83/60*8 -> 57.066667 | AZ83: =J83/60*2 -> 14.266667 | BA83: =J83/60*10 -> 71.333333 | BB83: =J83/60*10 -> 71.333333 | BC83: =J83/60*10 -> 71.333333 | BD83: =SUM(AW83:BC83) -> 428 | BE83: =J83-BD83 -> 0
A84: 45755 | B84: Smyths Toys EU HQ UC | C84: 德国 | D84: 4500162774 | E84: 4400475592 | F84: 4500162774-10 | G84: 92119A-S003-3L | H84: 92119A-S003 | I84: 北极熊 | J84: 1200 | K84: 0 | L84: 6 | M84: =J84/L84 -> 200 | N84: 45791 | O84: 45787 | Q84: PASS | R84: 5/15出 | S84: 4/8收到 | U84: 德语Callout贴纸+荷兰语警告语贴纸翻4500160022 | X84: 日期码格式：ZURU INC(BVI) 标准格式 日期：按实际生产日期 Packaging Info: 92119A:最新MA 3-23L EAN包装+1张德语Callout贴纸+MA 3L挂牌+MA 5L Slime bag+荷兰语警告语贴纸+MA 5L-23L收藏指南 （贴纸都翻4500160022）,EAN 条码： 489 4680046177 Remark: 1. 此单出德国，需要满足Zuru Standard欧洲标准测试要求； 2. 请准时出货，推期会有罚款； 3. 出口欧洲，微塑料需符合法规； 4. 所有电子产品身上需要加字唛，为ZURU FRANCE 地址 (如无电子产品，产品布标有此地址，或产品太小无法增加可忽略此信息) ZURU France 1/3, Rue d'Argenteuil 95210 SAINT-GRATIEN, FRANCE 5. 所有出往德国订单的电子产品需增加一张客版WEEE声明说明书，区分带电池和不带电池版本, 如已做客版说明书可忽略此要求。 6. 标准配比 | Y84: Shirley Zhou | Z84: 3.58 | AA84: =Z84*J84 -> 4296 | AB84: 1200 | AC84: =AB84-J84 -> 0 | AD84: OK | AE84: 系统出单 | AG84: 已入 | AJ84: =J84 -> 1200 | AM84: =J84 -> 1200 | AP84: =J84 -> 1200 | AV84: MA布标 | AW84: =J84 -> 1200 | BD84: =SUM(AW84:BC84) -> 1200 | BE84: =J84-BD84 -> 0
A85: 45755 | B85: Smyths Toys EU HQ UC | C85: 德国 | D85: 4500162774 | E85: 4400475593 | F85: 4500162774-20 | G85: 92119B-S003-3L | H85: 92119B-S003 | I85: 企鹅 | J85: 1404 | K85: 0 | L85: 6 | M85: =J85/L85 -> 234 | N85: 45791 | O85: 45787 | Q85: PASS | R85: 5/15出 | S85: 4/8收到 | U85: 德语Callout贴纸+荷兰语警告语贴纸翻4500160022 | X85: 日期码格式：ZURU INC(BVI) 标准格式 日期：按实际生产日期 Packaging Info: 92119B:最新MA 3-23L EAN包装+1张德语Callout贴纸+MA 3L挂牌+MA 5L Slime bag+荷兰语警告语贴纸+MA 5L-23L收藏指南 （贴纸都翻4500160022），EAN 条码： 48 94680046184 Remark: 1. 此单出德国，需要满足Zuru Standard欧洲标准测试要求； 2. 请准时出货，推期会有罚款； 3. 出口欧洲，微塑料需符合法规； 4. 所有电子产品身上需要加字唛，为ZURU FRANCE 地址 (如无电子产品，产品布标有此地址，或产品太小无法增加可忽略此信息) ZURU France 1/3, Rue d'Argenteuil 95210 SAINT-GRATIEN, FRANCE 5. 所有出往德国订单的电子产品需增加一张客版WEEE声明说明书，区分带电池和不带电池版本, 如已做客版说明书可忽略此要求。 6. 标准配比 | Y85: Shirley Zhou | Z85: 3.5 | AA85: =Z85*J85 -> 4914 | AB85: 1404 | AC85: =AB85-J85 -> 0 | AD85: OK | AE85: 系统出单 | AG85: 已入 | AJ85: =J85 -> 1404 | AM85: =J85 -> 1404 | AP85: =J85 -> 1404 | AV85: MA布标 | AX85: =J85 -> 1404 | BD85: =SUM(AW85:BC85) -> 1404 | BE85: =J85-BD85 -> 0
A86: 45736 | B86: Dirk Rossmann GmbH | C86: 德国 | D86: 4500160877 | E86: 30250400 | F86: 4500160877-20 | G86: 92119-S001-NB | H86: 92119-S001-NB.PKC | I86: 冰雪蛋(干燥剂） | J86: 9504 | K86: 0 | L86: 12 | M86: =J86/L86 -> 792 | N86: 45793 | O86: 45789 | P86: 5/21第三方 | Q86: PASS | R86: 5/22出 | S86: 4/1- 外箱上下需加保护卡，以防开箱时产品被划破。 外箱需要是5层瓦楞纸，厚度在5-9mm | U86: 3/28-德语callout/警语/EAN条码贴纸+吊牌德语警告语贴纸(翻4500149853) | X86: 日期码格式：ZURU INC(BVI) 标准格式 日期：按实际生产日期 Packaging Info: 92119: 最新MA 1L包装+德语callout/警语/EAN条码贴纸+5L(23L警语)收藏指南+5LBEADS BAG+5L(9L警语)SLIME POLYBAG+MA 3L TAG + 吊牌德语警告语贴纸(翻单:45 00149853), EAN: 4894680042247 Remark: 1. 出口欧洲，微塑料需符合法规，电池符合欧洲法规要求(如有) 2. 此客户要求：化学品无硼无香。 3. 外箱上下需加保护卡，以防开箱时产品被划破。（保护卡需要时整面） 4. 此单在出货前4周提供大货样品给Rossmann德国客人安排第三方验货。 请备额外物料。 5. 此单需要第三方验货，验货时间为完货后第二天，验货OK待客人放货后才能安排走货。 6. 所有包装材料都需要用PET材质。 7. 每箱需要放一包干燥剂（不能是silicon) 。品牌SUPER DRY，规格：10g/pc 。 8. 外箱需要是5层瓦楞纸，厚度在5-9mm。 9. 此单出德国，走整柜请知悉。 10. 标准配比 11. 所有电子产品身上需要加字唛，为ZURU FRANCE 地址 (如无电子产品，产品布标有此地址，或产品太小无法增加可忽略此信息) ZURU France 1/3, Rue d'Argenteuil 95210 SAINT-GRATIEN, FRANCE 12. 所有出往德国订单的电子产品需增加一张客版WEEE声明说明书，区分带电池和不带电池版本, 如已做客版说明书可忽略此要求。 | Y86: Shirley Zhou | Z86: 3.52 | AA86: =Z86*J86 -> 33454.08 | AB86: =7380+1080+1044 -> 9504 | AC86: =AB86-J86 -> 0 | AD86: OK | AE86: 系统出单 | AG86: 已入 | AH86: =J86 -> 9504 | AM86: =J86 -> 9504 | AR86: =J86 -> 9504 | AV86: MA布标 | AW86: =J86/60*10 -> 1584 | AX86: =J86/60*10 -> 1584 | AY86: =J86/60*8 -> 1267.2 | AZ86: =J86/60*2 -> 316.8 | BA86: =J86/60*10 -> 1584 | BB86: =J86/60*10 -> 1584 | BC86: =J86/60*10 -> 1584 | BD86: =SUM(AW86:BC86) -> 9504 | BE86: =J86-BD86 -> 0
A87: 45733 | B87: WAL-MART CANADA CORP. | C87: 加拿大 | D87: 4500160504 | E87: 9900923474 | F87: 4500160504-110 | G87: 92119-S002-NB | H87: 92119-S002-NB | I87: 冰雪蛋 | J87: 5 | K87: 0 | L87: 1 | M87: =J87/L87 -> 5 | N87: 45793 | O87: 45789 | P87: 5/19第三方 | Q87: PASS | R87: 5/27出 | S87: 3/25收到 | U87: 3/17-UPC贴纸 | X87: 日期码格式：ZURU INC(BVI) 标准格式 日期：按实际生产日期 Packaging Info: #92119： MA3L收缩膜(B版)+UPC贴纸(UPC:193052078391)+MA3L吊牌+MA5L收藏指南(B版)+MA5L复合袋+MA配件袋+MA5L贴纸+MA2L布标 产品配比： 7 Assortment, Polar bear: Penguin: Walrus: Mammoth: Owl: Seal: Snow man=10:10:10:10:10:8:2. Snow man is the rare item. Remark: 1. 此单有箱唛； 2. 9900923488/9900923472/9900923470/9900923474单为ECOM订单，外箱四面须加一张黄色贴纸； 3. 此单有第三方验货，烦请多备包装物料； 7. #92119需于2025/4/18安排签版, 签样数量：大货样各3PCS+齐套散件2套； 10. #92119 需于2025/4/28安排抽办测试, 抽办数量：大货各5 PCS+齐套散件4 SETS; 11. UPC贴纸：必须在原来错误的条码上用黑色粗头笔涂黑直至不能扫描，再贴上正确的UPC; ********************* a. 请确保产品符合1999年版本的加拿大环境保护法(CEPA)和2012年禁止某些有毒物质法规的要求。该产品不含任何在加拿大禁用的化学物质，包括但不限于有毒物 质清单中列出的化学物质，并且在为加拿大沃尔玛生产产品期间没有使用任何禁用化学物质。 Supplier certify that the products comply with the requirements of Canadian Environmental Protection Act, 1999 (CEPA), Prohibition of Certain To xic Substances Regulations, 2012. The products do not contain any chemicals that are banned in Canada, including but not limited to those listed in the Toxic Substances List and no banned chemicals were used during the manufacturing of product for Walmart Canada. 附件列表： (1) Letter of Guarantee for Canada banned chemicals - (1-5CA) b. 请确保产品在均质材料中的汞浓度不超过0.1%（按重量计）。 Supplier certify that the WAL-MART vendor products does not have a mercury concentration of more than 0.1% by weight in homogeneous material. 附件列表： (1) Letter of Guarantee for Mercury COC c. 请确保产品的塑料材料不含以下物质（SOR 2011-17 27B): Supplier certify that the plastic materials do not contain the following substances(SOR 2011-17 27B): (a) carbon tetrachloride or any substance that contains it; (b) methyl alcohol or any substance thay contains >1.0%; (c) petroleum distillates or any substance that contains >10% weight to volume of petroleum distillates; (d) benzene; (e) turpentine or any substance that contains >10% weight to volume of turpentine; (f) boric acid or salts of boric acid; or (g) ethyl ether. 附件列表： (1) Letter of Guarantee for WM CA-Other prohibited substances in plastic(less than 3 years) | Y87: Monica Zhou | Z87: 3.6 | AA87: =Z87*J87 -> 18 | AB87: 5 | AC87: =AB87-J87 -> 0 | AE87: 系统出单 | AG87: 已入 | AK87: =J87 -> 5 | AN87: =J87 -> 5 | AR87: =J87 -> 5 | AV87: MA布标 | AW87: =J87/60*10 -> 0.83333333 | AX87: =J87/60*10 -> 0.83333333 | AY87: =J87/60*8 -> 0.66666667 | AZ87: =J87/60*2 -> 0.16666667 | BA87: =J87/60*10 -> 0.83333333 | BB87: =J87/60*10 -> 0.83333333 | BC87: =J87/60*10 -> 0.83333333 | BD87: =SUM(AW87:BC87) -> 5 | BE87: =J87-BD87 -> 0
A88: 45733 | B88: WAL-MART CANADA CORP. | C88: 加拿大 | D88: 4500160504 | E88: 9900924264 | F88: 4500160504-120 | G88: 92119-S002-NB | H88: 92119-S002-NB | I88: 冰雪蛋 | J88: 1682 | K88: 0 | L88: 1 | M88: =J88/L88 -> 1682 | N88: 45793 | O88: 45789 | P88: 5/19第三方 | Q88: PASS | R88: 5/20出 | S88: 3/25收到 | U88: 3/17-UPC贴纸 | X88: 日期码格式：ZURU INC(BVI) 标准格式 日期：按实际生产日期 Packaging Info: #92119： MA3L收缩膜(B版)+UPC贴纸(UPC:193052078391)+MA3L吊牌+MA5L收藏指南(B版)+MA5L复合袋+MA配件袋+MA5L贴纸+MA2L布标 产品配比： 7 Assortment, Polar bear: Penguin: Walrus: Mammoth: Owl: Seal: Snow man=10:10:10:10:10:8:2. Snow man is the rare item. Remark: 1. 此单有箱唛； 2. 9900923488/9900923472/9900923470/9900923474单为ECOM订单，外箱四面须加一张黄色贴纸； 3. 此单有第三方验货，烦请多备包装物料； 7. #92119需于2025/4/18安排签版, 签样数量：大货样各3PCS+齐套散件2套； 10. #92119 需于2025/4/28安排抽办测试, 抽办数量：大货各5 PCS+齐套散件4 SETS; 11. UPC贴纸：必须在原来错误的条码上用黑色粗头笔涂黑直至不能扫描，再贴上正确的UPC; ********************* a. 请确保产品符合1999年版本的加拿大环境保护法(CEPA)和2012年禁止某些有毒物质法规的要求。该产品不含任何在加拿大禁用的化学物质，包括但不限于有毒物 质清单中列出的化学物质，并且在为加拿大沃尔玛生产产品期间没有使用任何禁用化学物质。 Supplier certify that the products comply with the requirements of Canadian Environmental Protection Act, 1999 (CEPA), Prohibition of Certain To xic Substances Regulations, 2012. The products do not contain any chemicals that are banned in Canada, including but not limited to those listed in the Toxic Substances List and no banned chemicals were used during the manufacturing of product for Walmart Canada. 附件列表： (1) Letter of Guarantee for Canada banned chemicals - (1-5CA) b. 请确保产品在均质材料中的汞浓度不超过0.1%（按重量计）。 Supplier certify that the WAL-MART vendor products does not have a mercury concentration of more than 0.1% by weight in homogeneous material. 附件列表： (1) Letter of Guarantee for Mercury COC c. 请确保产品的塑料材料不含以下物质（SOR 2011-17 27B): Supplier certify that the plastic materials do not contain the following substances(SOR 2011-17 27B): (a) carbon tetrachloride or any substance that contains it; (b) methyl alcohol or any substance thay contains >1.0%; (c) petroleum distillates or any substance that contains >10% weight to volume of petroleum distillates; (d) benzene; (e) turpentine or any substance that contains >10% weight to volume of turpentine; (f) boric acid or salts of boric acid; or (g) ethyl ether. 附件列表： (1) Letter of Guarantee for WM CA-Other prohibited substances in plastic(less than 3 years) | Y88: Monica Zhou | Z88: 3.6 | AA88: =Z88*J88 -> 6055.2 | AB88: 1682 | AC88: =AB88-J88 -> 0 | AE88: 系统出单 | AG88: 已入 | AK88: =J88 -> 1682 | AN88: =J88 -> 1682 | AR88: =J88 -> 1682 | AV88: MA布标 | AW88: =J88/60*10 -> 280.33333 | AX88: =J88/60*10 -> 280.33333 | AY88: =J88/60*8 -> 224.26667 | AZ88: =J88/60*2 -> 56.066667 | BA88: =J88/60*10 -> 280.33333 | BB88: =J88/60*10 -> 280.33333 | BC88: =J88/60*10 -> 280.33333 | BD88: =SUM(AW88:BC88) -> 1682 | BE88: =J88-BD88 -> 0
A89: 45742 | B89: TAS IMPORT AS(Lekekassen) | C89: 挪威 | D89: 4500161075 | E89: 11098 | F89: 4500161075-130 | G89: 92119-S005-NB-3L | H89: 92119-S005-NB | I89: 冰雪蛋 | J89: 600 | K89: 0 | L89: 6 | M89: =J89/L89 -> 100 | N89: 45793 | O89: 45789 | Q89: PASS | R89: 5/28出 | S89: 4/11收到 | U89: 4/11-客人进口商地址贴纸+挪威瑞典丹麦警告语贴在beads bag袋子上+北欧五语通用Slime黑白说明书 | X89: 日期码格式：ZURU INC(BVI) 标准格式 日期：按实际生产日期 Packaging Info: 12. 92119: MA_A Version_3L(EAN)-Warning 23L收缩膜+客人进口商地址贴纸+MA_A Version_5L(23L warning)收藏指南+SLIME POLYBAG_MA_A Version_5L(WARNING 9L)+MA 5L SLIME BEADS BAG+挪威瑞典丹麦芬兰爱沙尼亚警告语贴在beads bag袋子上+北欧五语通用Slime黑白说明书+MA布标； 16. 配比跟MA Remark: 1. 包装如含PVC,请改为PET并第一时间通知跟单 2. 产品/包装要求无硼无香，出欧洲，微塑料需合规。 3.带电池出货的产品所用到的电池需要符合欧洲电池新规(EU) 2023-1542 4.有胶袋的产品：要求产品的胶袋厚度要大于等于0.05mm 5.关于贴纸，如果贴纸位置图的包装版本与大货不一致，请工厂第一时间提前提出。跟单会重新调整确认是否更新贴纸或调整位置图 6.产品/包装不含PFAS成分 7.产品条码如下: 请先检查条码是否正确再安排做货，如有问题请告知 ZURU ITEM#<(>&<)>EAN 92119:4894680042247 | Y89: Sheba | Z89: 3.55 | AA89: =Z89*J89 -> 2130 | AB89: 600 | AC89: =AB89-J89 -> 0 | AD89: OK | AE89: 系统出单 | AG89: 已入 | AJ89: =J89 -> 600 | AM89: =J89 -> 600 | AR89: =J89 -> 600 | AV89: MA布标 | AW89: =J89/60*10 -> 100 | AX89: =J89/60*10 -> 100 | AY89: =J89/60*8 -> 80 | AZ89: =J89/60*2 -> 20 | BA89: =J89/60*10 -> 100 | BB89: =J89/60*10 -> 100 | BC89: =J89/60*10 -> 100 | BD89: =SUM(AW89:BC89) -> 600 | BE89: =J89-BD89 -> 0
A90: 45768 | D90: ZMPO250335 | G90: 92119-S001 | H90: 92119-S001 | I90: 冰雪蛋 | J90: 216 | K90: 0 | L90: 12 | M90: =J90/L90 -> 18 | N90: 45777 | O90: 45773 | Q90: PASS | S90: 周转箱 | U90: 无 | X90: Remark:大货最新版本/请按款号装箱，并在外箱上注明款号/大货标准箱装箱/箱唛请参照邮件附件;备注： 收到样品订单后尽快安排 ，注意样板品质质量要求要高于大货品质要求 ，送货时必须要附带送货单(没有送货单和QC检验合格报告的仓库一律拒绝收货)，请知悉，谢谢！ | Y90: Angus | AB90: 216 | AC90: =AB90-J90 -> 0 | AE90: 系统出单 | AG90: 已入 | AH90: =J90 -> 216 | AM90: =J90 -> 216 | AP90: =J90 -> 216 | AV90: MA布标 | AW90: =J90/60*10 -> 36 | AX90: =J90/60*10 -> 36 | AY90: =J90/60*8 -> 28.8 | AZ90: =J90/60*2 -> 7.2 | BA90: =J90/60*10 -> 36 | BB90: =J90/60*10 -> 36 | BC90: =J90/60*10 -> 36 | BD90: =SUM(AW90:BC90) -> 216 | BE90: =J90-BD90 -> 0
A91: 45713 | B91: TOY TRIANGLE COMPANY (UAE) | C91: 阿拉伯联合酋长国 | D91: 4500158495 | E91: 2025TTC055 | F91: 4500158495-10 | G91: 92132-S001 | H91: 92132-S001-PRODCC | I91: 冰雪蛋 | J91: 20400 | K91: 0 | L91: 12 | M91: =J91/L91 -> 1700 | N91: 45790 | O91: 45786 | Q91: PASS | R91: 5/16出 | S91: 2/25收到 | U91: 无 | X91: 日期码格式：ZURU INC(BVI) 标准格式 日期：按实际生产日期 Packaging Info: 客版收缩膜（改彩虹颜色:彩虹改成粉色，不含slime和希伯来警告语)，需要印G MARK，含进口商贴纸，含QR code), QR code要求印刷清晰且手机可扫描，扫描结果 为38711;客版挂卡; 客版指南（改彩虹颜色:彩虹改成粉色，不含slime和希伯来警告语);其他包材用MA版本 Remark: 7 Assortment, Polar bear: Penguin: Walrus: Mammoth: Owl: Seal: Snow man=10:10:10:10:10:8:2. Snow man is the rare item. Base on 92119 replace Slime with Dough for customer Toy Triangle | Y91: Lena Huang | Z91: 3.4 | AA91: =Z91*J91 -> 69360 | AB91: =10320+10080 -> 20400 | AC91: =AB91-J91 -> 0 | AD91: 无 | AE91: 系统出单 | AG91: 已入 | AL91: =J91 -> 20400 | AO91: =J91 -> 20400 | AT91: =J91 -> 20400 | AU91: =J91 -> 20400 | AV91: MA布标 | AW91: =J91/60*10 -> 3400 | AX91: =J91/60*10 -> 3400 | AY91: =J91/60*8 -> 2720 | AZ91: =J91/60*2 -> 680 | BA91: =J91/60*10 -> 3400 | BB91: =J91/60*10 -> 3400 | BC91: =J91/60*10 -> 3400 | BD91: =SUM(AW91:BC91) -> 20400 | BE91: =J91-BD91 -> 0
A92: 45741 | B92: TOYS "R" US (CANADA) LTD. | C92: 加拿大 | D92: 4500161369 | E92: 3501527775 | F92: 4500161369-10 | G92: 92119-S001-3L-NB | H92: 92119-S001-NB | I92: 冰雪蛋 | J92: 1608 | K92: 0 | L92: 12 | M92: =J92/L92 -> 134 | N92: 45796 | O92: 45792 | P92: 5/7第三方 | Q92: PASS | R92: 6/6出 | S92: 4/7收到 | U92: 4/7-UPC 贴纸 | X92: 日期码格式：ZURU INC(BVI) 标准格式 日期：按实际生产日期 Packaging Info: 1. 出口加拿大市场，MA UPC版本包装. #92119: MA 3L EAN 版本+UPC 贴纸，无硼口水胶; UPC#193052078391; 7 Assortment, Polar bear: Penguin: Walrus: Mammoth: Owl: Seal: Snow man=10:10:10: 10:10:8:2. Snow man is the rare item. 2. 产品、包装、外箱上面tracking code的时间格式需要一致。 Remark: 3. 需要第三方SGS验货，验货时间2025/05/19，每款每色请备1PC完整带包装样品供验货人员参考。用完后若无损坏可以放回大货里. | Y92: Abby Mai,Lluvia Zeng | Z92: 3.4 | AA92: =Z92*J92 -> 5467.2 | AB92: 1608 | AC92: =AB92-J92 -> 0 | AD92: OK | AE92: 系统出单 | AG92: 已入 | AJ92: =J92 -> 1608 | AM92: =J92 -> 1608 | AR92: =J92 -> 1608 | AV92: MA布标 | AW92: =J92/60*10 -> 268 | AX92: =J92/60*10 -> 268 | AY92: =J92/60*8 -> 214.4 | AZ92: =J92/60*2 -> 53.6 | BA92: =J92/60*10 -> 268 | BB92: =J92/60*10 -> 268 | BC92: =J92/60*10 -> 268 | BD92: =SUM(AW92:BC92) -> 1608 | BE92: =J92-BD92 -> 0
A93: 45729 | B93: COMSED PLC | C93: 保加利亚 | D93: 4500159898 | F93: 4500159898-40 | G93: 92119-S001 | H93: 92119-S001 | I93: 冰雪蛋 | J93: 1200 | K93: 0 | L93: 12 | M93: =J93/L93 -> 100 | N93: 45800 | O93: 45776 | Q93: PASS | R93: 6/9出 | S93: 3/13收到 | U93: 4/11-进口商贴纸 | X93: 日期码格式：ZURU INC(BVI) 标准格式 日期：按实际生产日期 Packaging Info: 92119:1L MA 收缩膜+进口商贴纸；A 版 3L MA 挂卡/A 版 5L MA 收藏指南 Remark: "1、所有item 均用MA UPC 条码，若包装不是UPC 条码的请告知 2、此单出欧洲需满足EU测试标准要求" | Y93: Snowy | Z93: 3.7075 | AA93: =Z93*J93 -> 4449 | AB93: =1188+12 -> 1200 | AC93: =AB93-J93 -> 0 | AD93: OK | AE93: 系统出单 | AG93: 已入 | AH93: =J93 -> 1200 | AM93: =J93 -> 1200 | AP93: =J93 -> 1200 | AV93: MA布标 | AW93: =J93/60*10 -> 200 | AX93: =J93/60*10 -> 200 | AY93: =J93/60*8 -> 160 | AZ93: =J93/60*2 -> 40 | BA93: =J93/60*10 -> 200 | BB93: =J93/60*10 -> 200 | BC93: =J93/60*10 -> 200 | BD93: =SUM(AW93:BC93) -> 1200 | BE93: =J93-BD93 -> 0
A94: 45750 | B94: ZURU France | C94: 法国 | D94: 4500162314 | E94: 5200006540 | F94: 4500162314-20 | G94: 92119-S006-NB-3L | H94: 92119-S006-NB-MTS | I94: 冰雪蛋 | J94: 384 | K94: 0 | L94: 4 | M94: =J94/L94 -> 96 | N94: 45799 | O94: 45796 | Q94: PASS | R94: 5/22出 | S94: 4/3收到 | U94: 4/11-多语警语折叠贴纸（含包装缺失的法/意/西环保标） | X94: 日期码格式：ZURU INC(BVI) 标准格式 日期：按实际生产日期 Packaging Info: 92119:最新MA 3L EAN收缩膜+最新MA 3L贴纸+最新MA 5L收藏指南+最新MA 布标+最新MA 5L包装+多语警语折叠贴纸（含包装缺失的法/意/西环保标）,, Remark: 1. 法国国家内销单，需要通过ZURU 验货结果后才能出货 (工厂需要主动提前同ZURU QC预约验货避免延期出货造成不必要麻烦)； 2. 本订单所有 具有 baby items / assorted items 的款式，零售包装上都要用 母 EAN; 3. 若有特定款有特殊外箱条码要求时,需要明确列出产品款对应的具体外箱条码号码/条码类型 (若无,可以忽略此需求) 4. 所有出口欧洲的产品, 法规规定禁止在包装和共公众用的印刷品中使用矿物油中含有的物质, 包装印刷油墨中含有的MOAH/MOSH的质量浓度不能超过1%, 否则出 货到法国被抽检出现问题, 供应商需要对此负责; 5. Date code: 外箱/产品/包装 保持一致，完货后提供date code 信息以便我们保存记录做批次管理; 6. 装柜时需要按照款式号码从小到大一款款依次装,避免终端仓库卸货混乱.若一个柜子涉及到几个不同国家内销单,装柜时需要一个国家装完后再装另一个国家的 产品,依次装柜,避免终端仓库因不同国家不同库位位置卸货混乱. (此点需要同工厂装柜人员强调) | Y94: Jade Wang | Z94: 3.6 | AA94: =Z94*J94 -> 1382.4 | AB94: 384 | AC94: =AB94-J94 -> 0 | AD94: OK | AE94: 系统出单 | AG94: 已入 | AJ94: =J94 -> 384 | AM94: =M94 -> 96 | AR94: =J94 -> 384 | AV94: MA布标 | AW94: =J94/60*10 -> 64 | AX94: =J94/60*10 -> 64 | AY94: =J94/60*8 -> 51.2 | AZ94: =J94/60*2 -> 12.8 | BA94: =J94/60*10 -> 64 | BB94: =J94/60*10 -> 64 | BC94: =J94/60*10 -> 64 | BD94: =SUM(AW94:BC94) -> 384 | BE94: =J94-BD94 -> 0 | BF94: 物料已发 | BG94: =VLOOKUP(D94&F94&H94&J94&Y94,转B版本!C:AK,35,FALSE) -> 全套A版本 | BH94: ok
A95: 45741 | B95: Walmart Central America | C95: 萨尔瓦多 | D95: 4500161312 | E95: 5907181238 | F95: 4500161312-50 | G95: 92119-S001-3L | H95: 92119-S001 | I95: 冰雪蛋 | J95: 348 | K95: 0 | L95: 12 | M95: =J95/L95 -> 29 | N95: 45799 | O95: 45796 | Q95: PASS | R95: 6/6出 | S95: 翻4500158302 | U95: UPC贴纸+进口商贴纸翻4500158302 | X95: 日期码格式：ZURU INC(BVI) 标准格式 日期：按实际生产日期 Packaging Info: 4. 92119: MA 3L EAN包装+UPC贴纸+MA 多语收藏指南+进口商贴纸+箱唛，贴纸翻单PO4500158302 Remark: 1.使用双坑外箱 2.请注意产品包装条形码必须是UPC 3.无第三方验货 6. 92119：7 Assortment, Polar bear: Penguin: Walrus: Mammoth: Owl: Seal: Snow man=10:10:10:10:10:8:2. Snow man is the rare item | Y95: Ever Li | Z95: 3.4 | AA95: =Z95*J95 -> 1183.2 | AB95: 348 | AC95: =AB95-J95 -> 0 | AD95: OK | AE95: 系统出单 | AG95: 已入 | AJ95: =J95 -> 348 | AM95: =J95 -> 348 | AP95: =J95 -> 348 | AV95: MA布标 | AW95: =J95/60*10 -> 58 | AX95: =J95/60*10 -> 58 | AY95: =J95/60*8 -> 46.4 | AZ95: =J95/60*2 -> 11.6 | BA95: =J95/60*10 -> 58 | BB95: =J95/60*10 -> 58 | BC95: =J95/60*10 -> 58 | BD95: =SUM(AW95:BC95) -> 348 | BE95: =J95-BD95 -> 0 | BF95: 物料已发 | BG95: =VLOOKUP(D95&F95&H95&J95&Y95,转B版本!C:AK,35,FALSE) -> 全套A版本 | BH95: ok
A96: 45741 | B96: Walmart Central America-GT | C96: 危地马拉 | D96: 4500161302 | E96: 4407181237 | F96: 4500161302-30 | G96: 92119-S001-3L | H96: 92119-S001 | I96: 冰雪蛋 | J96: 588 | K96: 0 | L96: 12 | M96: =J96/L96 -> 49 | N96: 45799 | O96: 45796 | Q96: PASS | R96: 6/6出 | S96: 翻4500158302 | U96: UPC贴纸+进口商贴纸翻4500158302 | X96: 日期码格式：ZURU INC(BVI) 标准格式 日期：按实际生产日期 Packaging Info: 3. 92119: MA 3L EAN包装+UPC贴纸+MA 多语收藏指南+进口商贴纸+箱唛，贴纸翻单PO4500158302 Remark: 1.使用双坑外箱 2.请注意产品包装条形码必须是UPC 3.无第三方验货 6. 92119：7 Assortment, Polar bear: Penguin: Walrus: Mammoth: Owl: Seal: Snow man=10:10:10:10:10:8:2. Snow man is the rare item | Y96: Ever Li | Z96: 3.4 | AA96: =Z96*J96 -> 1999.2 | AB96: 588 | AC96: =AB96-J96 -> 0 | AD96: OK | AE96: 系统出单 | AG96: 已入 | AJ96: =J96 -> 588 | AM96: =J96 -> 588 | AP96: =J96 -> 588 | AV96: MA布标 | AW96: =J96/60*10 -> 98 | AX96: =J96/60*10 -> 98 | AY96: =J96/60*8 -> 78.4 | AZ96: =J96/60*2 -> 19.6 | BA96: =J96/60*10 -> 98 | BB96: =J96/60*10 -> 98 | BC96: =J96/60*10 -> 98 | BD96: =SUM(AW96:BC96) -> 588 | BE96: =J96-BD96 -> 0 | BF96: 物料已发 | BG96: =VLOOKUP(D96&F96&H96&J96&Y96,转B版本!C:AK,35,FALSE) -> 全套A版本 | BH96: ok
A97: 45764 | B97: ZURU Italy SRL | C97: 意大利 | D97: 4500163993 | E97: 5200006585 | F97: 4500163993-10 | G97: 92119-S006-NB-3L | H97: 92119-S006-NB-MTS | I97: 冰雪蛋 | J97: 2040 | K97: 0 | L97: 4 | M97: =J97/L97 -> 510 | N97: 45801 | O97: 45797 | Q97: PASS | R97: 6/7出 | S97: 4/21收到 | U97: 多语警语折叠贴纸翻4500162314 | X97: 日期码格式：ZURU INC(BVI) 标准格式 日期：按实际生产日期 Packaging Info: 1.92119:最新MA 3L EAN收缩膜+最新MA 3L贴纸+最新MA 5L收藏指南+最新MA 布标+最新MA 5L包装+多语警语折叠贴纸（含包装缺失的法/意/西环保标）,翻450016231 4 Remark: 1.意大利国家内销单，需要通过ZURU 验货结果后才能出货 (工厂需要主动提前同ZURU QC预约验货避免延期出货造成不必要麻烦)； 2. SMASHERS 或含Slime产品，所有化合物使用无硼版本出意大利。 3. 本订单所有 具有 baby items / assorted items 的款式，零售包装上都要用 母 EAN; 4.所有出口欧洲的产品, 法规规定禁止在包装和共公众用的印刷品中使用矿物油中含有的物质, 包装印刷油墨中含有的MOAH/MOSH的质量浓度不能超过1%, 否则出货 到意大利被抽检出现问题, 供应商需要对此负责; 5. Date code: 外箱/产品/包装 保持一致，完货后提供date code 信息以便我们保存记录做批次管理； 6. 装柜时需要按照款式号码从小到大一款款依次装,避免终端仓库卸货混乱.若一个柜子涉及到几个不同国家内销单,装柜时需要一个国家装完后再装另一个国家的 产品,依次装柜,避免终端仓库因不同国家不同库位位置卸货混乱. (此点需要同工厂装柜人员强调)" 7. 意大利订单包装彩卡请确保含法规要求的环保回收logo。 | Y97: Christine He | Z97: 3.7065 | AA97: =Z97*J97 -> 7561.26 | AB97: =1176+864 -> 2040 | AC97: =AB97-J97 -> 0 | AD97: OK | AE97: 系统出单 | AG97: 已入 | AJ97: =J97 -> 2040 | AM97: =J97 -> 2040 | AR97: =J97 -> 2040 | AV97: MA布标 | AW97: =J97/60*10 -> 340 | AX97: =J97/60*10 -> 340 | AY97: =J97/60*8 -> 272 | AZ97: =J97/60*2 -> 68 | BA97: =J97/60*10 -> 340 | BB97: =J97/60*10 -> 340 | BC97: =J97/60*10 -> 340 | BD97: =SUM(AW97:BC97) -> 2040 | BE97: =J97-BD97 -> 0 | BF97: 物料已发 | BG97: =VLOOKUP(D97&F97&H97&J97&Y97,转B版本!C:AK,35,FALSE) -> 全套A版本 | BH97: ok
A98: 45750 | B98: Dino LLC | C98: 亚美尼亚 | D98: 4500162547 | F98: 4500162547-70 | G98: 92119-S001 | H98: 92119-S001 | I98: 冰雪蛋 | J98: 240 | K98: 0 | L98: 12 | M98: =J98/L98 -> 20 | N98: 45800 | O98: 45796 | Q98: PASS | R98: 5/30出 | S98: 4/16收到 | U98: 4/16-进口商贴纸 | X98: 日期码格式：ZURU INC(BVI) 标准格式 日期：按实际生产日期 Packaging Info: 1L MA UPC 收缩膜+ 进口商贴纸， MA PDQ/说明书/指南（如有） Remark: 标准配比 | Y98: Ann | Z98: 3.4 | AA98: =Z98*J98 -> 816 | AB98: 240 | AC98: =AB98-J98 -> 0 | AD98: OK | AE98: 系统出单 | AG98: 已入 | AH98: =J98 -> 240 | AM98: =J98 -> 240 | AP98: =J98 -> 240 | AV98: MA布标 | AW98: =J98/60*10 -> 40 | AX98: =J98/60*10 -> 40 | AY98: =J98/60*8 -> 32 | AZ98: =J98/60*2 -> 8 | BA98: =J98/60*10 -> 40 | BB98: =J98/60*10 -> 40 | BC98: =J98/60*10 -> 40 | BD98: =SUM(AW98:BC98) -> 240 | BE98: =J98-BD98 -> 0 | BF98: 物料已发 | BG98: =VLOOKUP(D98&F98&H98&J98&Y98,转B版本!C:AK,35,FALSE) -> 全套A版本 | BH98: ok
A99: 45757 | B99: Concentra, S.A. | C99: 葡萄牙 | D99: 4500163149 | E99: F202/20250026 | F99: 4500163149-30 | G99: 92119-S001-3L | H99: 92119-S001 | I99: 冰雪蛋 | J99: 300 | K99: 0 | L99: 12 | M99: =J99/L99 -> 25 | N99: 45799 | O99: 45801 | Q99: PASS | S99: 4/27收到 | U99: 4/22-CONCENTRA logo彩色贴纸+进口商黑白贴纸 | X99: 日期码格式：ZURU INC(BVI) 标准格式 日期：按实际生产日期 Packaging Info: 92119: 最新MA3L (24L warning)收缩膜 +最新MA 5L(23L warning)收藏指南+MA布标 +1*CONCENTRA" logo 彩色贴纸 + 1*进口商黑白贴纸 Remark: 1, 所有产品不带闪粉和微塑料，客人需要验货图片确认OK 才能放货，请务必按时完货。 | Y99: Jade Wang | Z99: 3.4 | AA99: =Z99*J99 -> 1020 | AB99: 300 | AC99: =AB99-J99 -> 0 | AD99: OK | AE99: 系统出单 | AG99: 已入 | AJ99: =J99 -> 300 | AM99: =J99 -> 300 | AP99: =J99 -> 300 | AV99: MA布标 | AW99: =J99/60*10 -> 50 | AX99: =J99/60*10 -> 50 | AY99: =J99/60*8 -> 40 | AZ99: =J99/60*2 -> 10 | BA99: =J99/60*10 -> 50 | BB99: =J99/60*10 -> 50 | BC99: =J99/60*10 -> 50 | BD99: =SUM(AW99:BC99) -> 300 | BE99: =J99-BD99 -> 0 | BF99: 物料已发 | BG99: =VLOOKUP(D99&F99&H99&J99&Y99,转B版本!C:AK,35,FALSE) -> 全套A版本 | BH99: ok
A100: 45749 | B100: LLC SALUS | C100: 俄罗斯联邦 | D100: 4500162283 | F100: 4500162283-20 | G100: 92119-S001 | H100: 92119-S001 | I100: 冰雪蛋 | J100: 252 | K100: 0 | L100: 12 | M100: =J100/L100 -> 21 | N100: 45803 | O100: 45799 | Q100: PASS | R100: 5/29出 | S100: 4/24收到 | U100: 5/6-进口商贴纸+ QR code贴纸 | X100: 日期码格式：ZURU INC(BVI) 标准格式 日期：按实际生产日期 Packaging Info: 注意： 1. QR code 贴纸需要含item和序列号 ， 二维码部分要求尺寸大于1CM （正方形边长间于1-1.5cm），强粘不易脱落 ， 材质同进口商贴纸 ，印刷质量不低于1.5c. 2. 二维码贴纸位置要远离包装上的条码及其他二维码， 贴在背面。 3. QR code贴纸（要求每1PCS 的QR 不一样 ， 无法通过扫描核实内容）; 4. 包装上有两个条码： ZURU UPC 和 客户EAN条码 ， 不要覆盖MA 包装上的UPC 条码； 92119 ： 1L MA 包装+ 进口商贴纸（含客户EAN条码）+ QR code贴纸（要求每1PCS 的QR 不一样）， MA 指南； Remark: 标准配比，出厂价 | Y100: Ann | Z100: 3.6923 | AA100: =Z100*J100 -> 930.4596 | AB100: 252 | AC100: =AB100-J100 -> 0 | AD100: OK | AE100: 系统出单 | AG100: 已入 | AH100: =J100 -> 252 | AM100: =J100 -> 252 | AP100: =J100 -> 252 | AV100: MA布标 | AW100: =J100/60*10 -> 42 | AX100: =J100/60*10 -> 42 | AY100: =J100/60*8 -> 33.6 | AZ100: =J100/60*2 -> 8.4 | BA100: =J100/60*10 -> 42 | BB100: =J100/60*10 -> 42 | BC100: =J100/60*10 -> 42 | BD100: =SUM(AW100:BC100) -> 252 | BE100: =J100-BD100 -> 0 | BF100: 物料已发 | BG100: =VLOOKUP(D100&F100&H100&J100&Y100,转B版本!C:AK,35,FALSE) -> 全套A版本 | BH100: ok
...

Sheet 92125
A1: ZURU Rainbocorn 大猫蛋系列排期#92125 | AW1: 剩余MA | AX1: =半成品MA!S18-AX2 -> 59671 | AY1: =半成品MA!T18-AY2 -> 58837 | AZ1: =半成品MA!U18-AZ2 -> 59211 | BA1: =半成品MA!V18-BA2 -> 58014 | BB1: =半成品MA!W18-BB2 -> 53800 | BC1: =半成品MA!X18-BC2 -> 55495 | BD1: =SUM(AX1:BC1) -> 345028
A2: 45660 | I2: （黃色表示更改或增加） | L2: （蓝色表示已完货） | P2: （綠色表示調整貨期） | AD2: 收缩膜 | AG2: 收藏指南 | AI2: 太空沙 | AJ2: PDQ | AM2: 吊卡 | AO2: 1 | AP2: 1 | AQ2: 1 | AR2: 1 | AS2: 1 | AT2: 1 | AW2: 毛绒交货数 | AX2: 50329 | AY2: 51163 | AZ2: 50789 | BA2: 51986 | BB2: 56200 | BC2: 59505 | BD2: =SUM(AX2:BC2) -> 319972
A3: 接单日期 | B3: 第三方客户名称 | C3: 国家 | D3: PO号 | E3: 客PO号 | F3: SKU | G3: 系统货号 | H3: ITEM# | I3: 中文名 | J3: PO数量 (pcs) | K3: 内箱装箱数量(pcs) | L3: 外箱装箱数量(pcs) | M3: 总箱数 | N3: 客PO期 | O3: 验货期 | P3: 第三方验货期 | Q3: 驗貨結果 | R3: 船期SO | S3: 箱唛资料 | T3: 外箱贴纸 | U3: 客贴纸资料 | V3: 客供物料 | W3: 日期码 | X3: 备注 | Y3: ZURU 跟单 | Z3: 单价USD | AA3: 金额USD | AB3: 發票號 | AC3: 是否入系统 | AD3: MA 1語收縮膜 A版本 | AE3: MA 3語收縮膜 A版本 | AF3: 客版收縮膜 | AG3: MA 5語收藏指南 | AH3: 客版收藏指南 | AI3: 无硼 | AJ3: UQ1 | AK3: SLD展示架 | AL3: 客版领养卡 | AM3: 客版吊卡 | AN3: 布標 | AO3: 暹罗猫-A | AP3: 黑猫-E | AQ3: 粉白猫-B | AR3: 紫猫-D | AS3: 棕黄猫-G | AT3: 橘猫-H | AU3: 总数 | AV3: 相差 | AX3: 暹罗猫-A | AY3: 黑猫-E | AZ3: 粉白猫-B | BA3: 紫猫-D | BB3: 棕黄猫-G | BC3: 橘猫-H
A4: 45805 | B4: PP-订单 | D4: ZPO2505005 | G4: 过渡 | H4: 92125-S001 | J4: 576 | K4: 0 | L4: 6 | M4: =J4/L4 -> 96 | N4: 45811 | O4: =N4-4 -> 45807 | S4: 周转箱 | U4: 无 | Y4: Nicole Yu | AD4: =J4 -> 576 | AG4: =J4 -> 576 | AI4: =J4 -> 576 | AN4: MA布标 | AX4: =AX2-AO4 -> 50329 | AY4: =AY2-AP4 -> 51163 | AZ4: =AZ2-AQ4 -> 50789 | BA4: =BA2-AR4 -> 51986 | BB4: =BB2-AS4 -> 56200 | BC4: =BC2-AT4 -> 59505
A5: 46079 | B5: TJX CANADA | C5: 加拿大 | D5: 4500194379 | E5: 40320901 | F5: 4500194379-60 | H5: 92125-S001 | I5: S001-RAINBOCORNS-EGGZA NIA-SERIES 2-PLUSH SOFT MEDIUM-SHRINK WRAP,6PCS/CTN | J5: 720 | L5: 6 | M5: 46135 | O5: 46129 | X5: 日期码格式：标准格式 日期：按实际生产日期 92125 MA 多语EAN版本+UPC贴纸193052083951 77731 英法客版铜版纸，upc 193052085115, MA 2L 收缩膜 多语多明书 25251 英法客版包装 UPC 845218016418 翻单4500166055 25252 客版英法彩盒和说明书。UPC号码845218016425 25253 英法客版 UPC 845218016432，彩盒翻单4500158924，说明书翻单4500166055 7153 英法客版包装 翻单4500131680， 7149 UPC193052033499 7150UPC 193052033406 MA 多语说明书 92119 无硼版本 MA 3L B 版收缩膜 +UPC 贴纸 UPC 193052078391， B 版5L 收藏指南 9258 无硼版本 MA 3L B 版收缩膜 UPC 5L多语言收藏指南193052037640 9296 无硼版本 MA 3L 收缩膜+ 多语说明书 ， UPC 193052057129 9298 无硼版本 MA C 版3L 收缩膜 +UPC 贴纸 UPC 193052057426， B 版5L 收藏指南 9548 无硼版本 MA D 版本 5L 包装+D 版本 5L 收藏指南 +UPC 贴纸 UPC 193052064196 出加拿大 有客供价格贴 每行对应不同的客户PO，唛头要一一对应， 放唛头时跟单会提供清单 Zuru验货.日期跟踪码：产品外包装及产品本身都必须有日期跟踪码，ZURU标准格式 日期码 | Y5: Katrina Xie | Z5: 5.2547 | AX5: =AX1048509-AO5 -> 0
A6: 45805 | B6: PP-订单 | D6: ZPO2505005 | G6: 过渡 | H6: 92125SLD-S001 | J6: 36 | K6: 0 | L6: 36 | M6: =J6/L6 -> 1 | N6: 45811 | O6: =N6-4 -> 45807 | S6: 周转箱 | U6: 无 | Y6: Nicole Yu | AN6: MA布标 | AX6: =AX4-AO6 -> 50329 | AY6: =AY4-AP6 -> 51163 | AZ6: =AZ4-AQ6 -> 50789 | BA6: =BA4-AR6 -> 51986 | BB6: =BB4-AS6 -> 56200 | BC6: =BC4-AT6 -> 59505
A7: 46079 | B7: TJX CANADA | C7: 加拿大 | D7: 4500194379 | F7: 4500194379-170 | H7: 92125-S001 | I7: S001-RAINBOCORNS-EGGZA NIA-SERIES 2-PLUSH SOFT MEDIUM-SHRINK WRAP,6PCS/CTN | J7: 180 | L7: 6 | M7: 46135 | O7: 46129 | X7: 日期码格式：标准格式 日期：按实际生产日期 92125 MA 多语EAN版本+UPC贴纸193052083951 77731 英法客版铜版纸，upc 193052085115, MA 2L 收缩膜 多语多明书 25251 英法客版包装 UPC 845218016418 翻单4500166055 25252 客版英法彩盒和说明书。UPC号码845218016425 25253 英法客版 UPC 845218016432，彩盒翻单4500158924，说明书翻单4500166055 7153 英法客版包装 翻单4500131680， 7149 UPC193052033499 7150UPC 193052033406 MA 多语说明书 92119 无硼版本 MA 3L B 版收缩膜 +UPC 贴纸 UPC 193052078391， B 版5L 收藏指南 9258 无硼版本 MA 3L B 版收缩膜 UPC 5L多语言收藏指南193052037640 9296 无硼版本 MA 3L 收缩膜+ 多语说明书 ， UPC 193052057129 9298 无硼版本 MA C 版3L 收缩膜 +UPC 贴纸 UPC 193052057426， B 版5L 收藏指南 9548 无硼版本 MA D 版本 5L 包装+D 版本 5L 收藏指南 +UPC 贴纸 UPC 193052064196 出加拿大 有客供价格贴 每行对应不同的客户PO，唛头要一一对应， 放唛头时跟单会提供清单 Zuru验货.日期跟踪码：产品外包装及产品本身都必须有日期跟踪码，ZURU标准格式 日期码 | Y7: Katrina Xie | Z7: 5.2547 | AX7: =AX6-AO7 -> 50329
A8: 45790 | B8: KMART AUSTRALIA LTD | C8: 澳大利亚 | D8: 4500166286 | E8: 20846869 | F8: 4500166286-10 | G8: 92125-S001 | H8: 92125-S001 | I8: 一窝猫蛋 | J8: 954 | K8: 0 | L8: 6 | M8: =J8/L8 -> 159 | N8: 45843 | O8: 45841 | Q8: PASS | R8: 7/2-7/4出 | S8: 5/13收到 | U8: 5/19防盗贴纸+6/9-外箱SSCC | X8: 日期码格式：ZURU INC(BVI) 标准格式 日期：按实际生产日期 Packaging Info: 92125:MA英语UPC版本包装（收缩膜和说明书, MA首选1L，如无1L可用多语且含英语的配套多语包装) + 1张防盗贴纸 + 箱唛 + 外箱SSCC Label 配比信息：6 Assortments,siamese cat:pink-white cat:purple cat:black cat:brown-white cat:orange cat=1:1:1:1:1:1 此订单有分两种装运类型，请注意外箱贴纸需要按贴纸文件顺序安排贴纸顺序，先贴整柜的数量，剩下的贴散货的数量。 如：柜货+散货： 以此类推，如不按此安排，此次出货请自行记录好外箱对应贴纸的相关信息。如客户收到后有贴纸重复或贴纸顺序记录错误等问题产生的相关费用需由工厂自己承担 。 Remark: 1.请务必按时完货，验货。并且按期送货入货代指定仓库，如果晚了导致船期Delay将会有罚金产生或者客户要求空运，所产生的罚金和空运费由工厂承担。 2.SSCC 外箱贴纸请同纸箱瓦楞纸方向（竖纹向）垂直，即外箱贴纸横着贴(注意条码不要被胶带粘住），贴1pc，贴1面正唛，封箱胶纸不能挡住贴纸内容。外箱贴纸 离外箱边距离不少于2cm。 3.外箱材质为ZURU标准； 4.此单需使用KMART封箱胶上下工字型封箱;从2019年6月开始，要用KMART 新版封箱胶带，此单要用"ANKO"封箱胶带 5.此单出口澳大利亚，请按相应的澳新标准生产； 6.产品和包装上生产批号的显示格式ZURU标准日期码格式 7.外箱信息不可手写，重量和体积需要与实际的一致(不可手写） 8. 每款item装箱后的G.W.超过10KG或者CBM超过0.13,(9.5KG或者以上，四舍五入后也属于10KG) 需在外箱上加印超 重或者Bulky LOGO，若发现我们资料没有，请 帮忙提醒 1)重量超过10kg但不超过16kg且CBM不超过0.13,10-16kg 超重logo 2）CBM超过0.13且重量少于17kg，bulky logo 3）不属于以上两种情况，需要使用相应重量范围内的超重logo 4）超重logo需要在外箱四面都印刷(箱唛右上角，两面侧唛超重logo需要尽量靠近毛重)，尺寸为:110mm height* 95mm width 9. 实际外箱重量跟印在箱唛上的数据差异不能超3%，尺寸按实际数据印刷 | Y8: Lydia Wu | Z8: 5.2 | AA8: =Z8*J8 -> 4960.8 | AB8: 95855-7.31 | AC8: 已入 | AD8: =J8 -> 954 | AG8: =J8 -> 954 | AI8: =J8 -> 954 | AN8: MA布标 | AO8: =J8/6 -> 159 | AP8: =J8/6 -> 159 | AQ8: =J8/6 -> 159 | AR8: =J8/6 -> 159 | AS8: =J8/6 -> 159 | AT8: =J8/6 -> 159 | AU8: =SUM(AO8:AT8) -> 954 | AV8: =J8-AU8 -> 0 | AX8: =AX6-AO8 -> 50170 | AY8: =AY6-AP8 -> 51004 | AZ8: =AZ6-AQ8 -> 50630 | BA8: =BA6-AR8 -> 51827 | BB8: =BB6-AS8 -> 56041 | BC8: =BC6-AT8 -> 59346
A9: 45790 | B9: Salling Group A/S | C9: 丹麦 | D9: 4500166233 | E9: 4041588208 | F9: 4500166233-30 | G9: 92125-S001-3L | H9: 92125-S001 | I9: 一窝猫蛋 | J9: 1962 | K9: 0 | L9: 6 | M9: =J9/L9 -> 327 | N9: 45840 | O9: 45841 | Q9: PASS | R9: 7/4出 | S9: 5/23收到 | U9: 5/23-挪威瑞典丹麦芬兰爱沙尼亚警告语贴纸贴 | X9: 日期码格式：ZURU INC(BVI) 标准格式 日期：按实际生产日期 Packaging Info: 3. 92125: MA A 3L(23L warning) EAN版收缩膜+MA KITTY LITTER BAG_MA_A_5L(Warning 9L)+挪威瑞典丹麦芬兰爱沙尼亚警告语贴纸贴在袋子上+MA_A Version_5L( WARNING 23L)收藏指南+MA布标+MA ACCESSORIES BAGS_MA_A_5L(23L warning) Remark: 92125是新品，请在6/25各寄两套大货样给客人留底 1. 包装如含PVC,请改为PET 2. 产品/包装要求无硼无香； 3. 出欧洲，微塑料需合规。 4.带电池出货的产品所用到的电池需要符合欧洲电池新规(EU) 2023-1542 5.关于贴纸，如果贴纸位置图的包装版本与大货不一致，请工厂提前提出。跟单会重新调整确认是否更新贴纸或调整位置图 6.产品/包装不含PFAS成分 7. 产品条码如下: 请先检查条码是否正确再安排做货，如有问题请告知: 92125-S001:4894680046306 | Y9: Sheba | Z9: 4.4 | AA9: =Z9*J9 -> 8632.8 | AB9: 95854-7.31 | AC9: 已入 | AE9: =J9 -> 1962 | AG9: =J9 -> 1962 | AI9: =J9 -> 1962 | AN9: MA布标 | AO9: =J9/6 -> 327 | AP9: =J9/6 -> 327 | AQ9: =J9/6 -> 327 | AR9: =J9/6 -> 327 | AS9: =J9/6 -> 327 | AT9: =J9/6 -> 327 | AU9: =SUM(AO9:AT9) -> 1962 | AV9: =J9-AU9 -> 0 | AX9: =AX8-AO9 -> 49843 | AY9: =AY8-AP9 -> 50677 | AZ9: =AZ8-AQ9 -> 50303 | BA9: =BA8-AR9 -> 51500 | BB9: =BB8-AS9 -> 55714 | BC9: =BC8-AT9 -> 59019
A10: 45737 | B10: WAL-MART CANADA CORP. | C10: 加拿大 | D10: 4500160934 | E10: 9900923467 | F10: 4500160934-10 | G10: 92125-S002-3L | H10: 92125-S002 | I10: 一窝猫蛋 | J10: 1209 | K10: 0 | L10: 1 | M10: =J10/L10 -> 1209 | N10: 45838 | O10: 45842 | P10: 7/7抽办 7/9第三方 | Q10: PASS | R10: 7/17出 | S10: 5/21收到 | U10: 6/9-UPC贴纸 | X10: 日期码格式：ZURU INC(BVI) 标准格式 日期：按实际生产日期 Packaging Info: MA3L收缩膜+UPC贴纸(UPC:193052083951)+MA3L吊牌+MA5L收藏指南+MA5L收养卡+MA5L贴纸+MA配件袋+MA2L布标 产品配比：6 Assortments,siamese cat:pink-white cat:purple cat:black cat:brown-white cat:orange cat=1:1:1:1:1:1, no rare. Remark: 1. 此单有箱唛,客PO 9900923468为ECOM订单,外箱需加黄色贴纸; 2. 此单有第三方验货，烦请多备包装物料； 4. #92125 需于2025/6/23安排签版, 签样数量：大货样各3 SETS+散件2 SETS; 5. #92125 需于2025/6/30安排抽办测试, 抽办数量：大货各5 SETS+散件4 SETS; 6. UPC贴纸：必须在原来错误的条码上用黑色粗头笔涂黑直至不能扫描，再贴上正确的UPC; ********************* a. 请确保产品符合1999年版本的加拿大环境保护法(CEPA)和2012年禁止某些有毒物质法规的要求。该产品不含任何在加拿大禁用的化学物质，包括但不限于有毒物 质清单中列出的化学物质，并且在为加拿大沃尔玛生产产品期间没有使用任何禁用化学物质。 Supplier certify that the products comply with the requirements of Canadian Environmental Protection Act, 1999 (CEPA), Prohibition of Certain To xic Substances Regulations, 2012. The products do not contain any chemicals that are banned in Canada, including but not limited to those listed in the Toxic Substances List and no banned chemicals were used during the manufacturing of product for Walmart Canada. 附件列表： (1) Letter of Guarantee for Canada banned chemicals - (1-5CA) b. 请确保产品在均质材料中的汞浓度不超过0.1%（按重量计）。 Supplier certify that the WAL-MART vendor products does not have a mercury concentration of more than 0.1% by weight in homogeneous material. 附件列表： (1) Letter of Guarantee for Mercury COC c. 请确保产品的塑料材料不含以下物质（SOR 2011-17 27B): Supplier certify that the plastic materials do not contain the following substances(SOR 2011-17 27B): (a) carbon tetrachloride or any substance that contains it; (b) methyl alcohol or any substance thay contains >1.0%; (c) petroleum distillates or any substance that contains >10% weight to volume of petroleum distillates; (d) benzene; (e) turpentine or any substance that contains >10% weight to volume of turpentine; (f) boric acid or salts of boric acid; or (g) ethyl ether. 附件列表： (1) Letter of Guarantee for WM CA-Other prohibited substances in plastic(less than 3 years) | Y10: Monica Zhou | Z10: 4.6 | AA10: =Z10*J10 -> 5561.4 | AB10: 95808-7.29 | AC10: 已入 | AE10: =J10 -> 1209 | AG10: =J10 -> 1209 | AI10: =J10 -> 1209 | AN10: MA布标 | AO10: =J10/6 -> 201.5 | AP10: =J10/6 -> 201.5 | AQ10: =J10/6 -> 201.5 | AR10: =J10/6 -> 201.5 | AS10: =J10/6 -> 201.5 | AT10: =J10/6 -> 201.5 | AU10: =SUM(AO10:AT10) -> 1209 | AV10: =J10-AU10 -> 0 | AX10: =AX9-AO10 -> 49641.5 | AY10: =AY9-AP10 -> 50475.5 | AZ10: =AZ9-AQ10 -> 50101.5 | BA10: =BA9-AR10 -> 51298.5 | BB10: =BB9-AS10 -> 55512.5 | BC10: =BC9-AT10 -> 58817.5
A11: 45790 | B11: KMART AUSTRALIA LTD | C11: 澳大利亚 | D11: 4500166286 | E11: 20846869 | F11: 4500166286-70 | G11: 92125-S001 | H11: 92125-S001 | I11: 一窝猫蛋 | J11: 546 | K11: 0 | L11: 6 | M11: =J11/L11 -> 91 | N11: 45843 | O11: 45842 | Q11: PASS | R11: 7/7出 | S11: 5/13收到 | U11: 5/19防盗贴纸+6/9-外箱SSCC | X11: 日期码格式：ZURU INC(BVI) 标准格式 日期：按实际生产日期 Packaging Info: 92125:MA英语UPC版本包装（收缩膜和说明书, MA首选1L，如无1L可用多语且含英语的配套多语包装) + 1张防盗贴纸 + 箱唛 + 外箱SSCC Label 配比信息：6 Assortments,siamese cat:pink-white cat:purple cat:black cat:brown-white cat:orange cat=1:1:1:1:1:1 此订单有分两种装运类型，请注意外箱贴纸需要按贴纸文件顺序安排贴纸顺序，先贴整柜的数量，剩下的贴散货的数量。 如：柜货+散货： 以此类推，如不按此安排，此次出货请自行记录好外箱对应贴纸的相关信息。如客户收到后有贴纸重复或贴纸顺序记录错误等问题产生的相关费用需由工厂自己承担 。 Remark: 1.请务必按时完货，验货。并且按期送货入货代指定仓库，如果晚了导致船期Delay将会有罚金产生或者客户要求空运，所产生的罚金和空运费由工厂承担。 2.SSCC 外箱贴纸请同纸箱瓦楞纸方向（竖纹向）垂直，即外箱贴纸横着贴(注意条码不要被胶带粘住），贴1pc，贴1面正唛，封箱胶纸不能挡住贴纸内容。外箱贴纸 离外箱边距离不少于2cm。 3.外箱材质为ZURU标准； 4.此单需使用KMART封箱胶上下工字型封箱;从2019年6月开始，要用KMART 新版封箱胶带，此单要用"ANKO"封箱胶带 5.此单出口澳大利亚，请按相应的澳新标准生产； 6.产品和包装上生产批号的显示格式ZURU标准日期码格式 7.外箱信息不可手写，重量和体积需要与实际的一致(不可手写） 8. 每款item装箱后的G.W.超过10KG或者CBM超过0.13,(9.5KG或者以上，四舍五入后也属于10KG) 需在外箱上加印超 重或者Bulky LOGO，若发现我们资料没有，请 帮忙提醒 1)重量超过10kg但不超过16kg且CBM不超过0.13,10-16kg 超重logo 2）CBM超过0.13且重量少于17kg，bulky logo 3）不属于以上两种情况，需要使用相应重量范围内的超重logo 4）超重logo需要在外箱四面都印刷(箱唛右上角，两面侧唛超重logo需要尽量靠近毛重)，尺寸为:110mm height* 95mm width 9. 实际外箱重量跟印在箱唛上的数据差异不能超3%，尺寸按实际数据印刷 | Y11: Lydia Wu | Z11: 5.2 | AA11: =Z11*J11 -> 2839.2 | AB11: 95856-7.31 | AC11: 已入 | AD11: =J11 -> 546 | AG11: =J11 -> 546 | AI11: =J11 -> 546 | AN11: MA布标 | AO11: =J11/6 -> 91 | AP11: =J11/6 -> 91 | AQ11: =J11/6 -> 91 | AR11: =J11/6 -> 91 | AS11: =J11/6 -> 91 | AT11: =J11/6 -> 91 | AU11: =SUM(AO11:AT11) -> 546 | AV11: =J11-AU11 -> 0 | AX11: =AX10-AO11 -> 49550.5 | AY11: =AY10-AP11 -> 50384.5 | AZ11: =AZ10-AQ11 -> 50010.5 | BA11: =BA10-AR11 -> 51207.5 | BB11: =BB10-AS11 -> 55421.5 | BC11: =BC10-AT11 -> 58726.5
A12: 45796 | B12: MEIJER DISTRIBUTION, INC. | C12: 美国 | D12: 4500166931 | E12: 217025711 | F12: 4500166931-10 | G12: 92125-S004 | H12: 92125-S004 | I12: 一窝猫蛋 | J12: 214 | K12: 0 | L12: 2 | M12: =J12/L12 -> 107 | N12: 45842 | O12: 45845 | Q12: PASS | R12: 7/8出 | S12: 6/4收到 | U12: 无 | X12: 日期码格式：ZURU INC(BVI) 标准格式 日期： Packaging Info: 1. MA 1L 包装 2. 客人指定箱唛排版 Remark: 出货前 Zuru QC 验货 | Y12: Cherie Li | Z12: 3.24 | AA12: =Z12*J12 -> 693.36 | AC12: 已入 | AD12: =J12 -> 214 | AG12: =J12 -> 214 | AI12: =J12 -> 214 | AN12: MA布标 | AO12: =J12/6 -> 35.666667 | AP12: =J12/6 -> 35.666667 | AQ12: =J12/6 -> 35.666667 | AR12: =J12/6 -> 35.666667 | AS12: =J12/6 -> 35.666667 | AT12: =J12/6 -> 35.666667 | AU12: =SUM(AO12:AT12) -> 214 | AV12: =J12-AU12 -> 0 | AX12: =AX11-AO12 -> 49514.833 | AY12: =AY11-AP12 -> 50348.833 | AZ12: =AZ11-AQ12 -> 49974.833 | BA12: =BA11-AR12 -> 51171.833 | BB12: =BB11-AS12 -> 55385.833 | BC12: =BC11-AT12 -> 58690.833
A13: 45796 | B13: MEIJER DISTRIBUTION, INC. | C13: 美国 | D13: 4500166930 | E13: 217025603 | F13: 4500166930-10 | G13: 92125-S004 | H13: 92125-S004 | I13: 一窝猫蛋 | J13: 400 | K13: 0 | L13: 2 | M13: =J13/L13 -> 200 | N13: 45842 | O13: 45845 | Q13: PASS | R13: 7/8出 | S13: 6/4收到 | U13: 无 | X13: 日期码格式：ZURU INC(BVI) 标准格式 日期： Packaging Info: 1. MA 1L 包装 2. 客人指定箱唛排版 Remark: 出货前 Zuru QC 验货 | Y13: Cherie Li | Z13: 3.24 | AA13: =Z13*J13 -> 1296 | AC13: 已入 | AD13: =J13 -> 400 | AG13: =J13 -> 400 | AI13: =J13 -> 400 | AN13: MA布标 | AO13: =J13/6 -> 66.666667 | AP13: =J13/6 -> 66.666667 | AQ13: =J13/6 -> 66.666667 | AR13: =J13/6 -> 66.666667 | AS13: =J13/6 -> 66.666667 | AT13: =J13/6 -> 66.666667 | AU13: =SUM(AO13:AT13) -> 400 | AV13: =J13-AU13 -> 0 | AX13: =AX12-AO13 -> 49448.167 | AY13: =AY12-AP13 -> 50282.167 | AZ13: =AZ12-AQ13 -> 49908.167 | BA13: =BA12-AR13 -> 51105.167 | BB13: =BB12-AS13 -> 55319.167 | BC13: =BC12-AT13 -> 58624.167
A14: 45737 | B14: WAL-MART CANADA CORP. | C14: 加拿大 | D14: 4500160934 | E14: 9900923468 | F14: 4500160934-20 | G14: 92125-S002-3L | H14: 92125-S002 | I14: 一窝猫蛋 | J14: 5 | K14: 0 | L14: 1 | M14: =J14/L14 -> 5 | N14: 45842 | O14: 45845 | P14: 7/9第三方 | Q14: PASS | R14: 7/17出 | S14: 5/21收到 | U14: 6/9-UPC贴纸 | X14: 日期码格式：ZURU INC(BVI) 标准格式 日期：按实际生产日期 Packaging Info: MA3L收缩膜+UPC贴纸(UPC:193052083951)+MA3L吊牌+MA5L收藏指南+MA5L收养卡+MA5L贴纸+MA配件袋+MA2L布标 产品配比：6 Assortments,siamese cat:pink-white cat:purple cat:black cat:brown-white cat:orange cat=1:1:1:1:1:1, no rare. Remark: 1. 此单有箱唛,客PO 9900923468为ECOM订单,外箱需加黄色贴纸; 2. 此单有第三方验货，烦请多备包装物料； 4. #92125 需于2025/6/23安排签版, 签样数量：大货样各3 SETS+散件2 SETS; 5. #92125 需于2025/6/30安排抽办测试, 抽办数量：大货各5 SETS+散件4 SETS; 6. UPC贴纸：必须在原来错误的条码上用黑色粗头笔涂黑直至不能扫描，再贴上正确的UPC; ********************* a. 请确保产品符合1999年版本的加拿大环境保护法(CEPA)和2012年禁止某些有毒物质法规的要求。该产品不含任何在加拿大禁用的化学物质，包括但不限于有毒物 质清单中列出的化学物质，并且在为加拿大沃尔玛生产产品期间没有使用任何禁用化学物质。 Supplier certify that the products comply with the requirements of Canadian Environmental Protection Act, 1999 (CEPA), Prohibition of Certain To xic Substances Regulations, 2012. The products do not contain any chemicals that are banned in Canada, including but not limited to those listed in the Toxic Substances List and no banned chemicals were used during the manufacturing of product for Walmart Canada. 附件列表： (1) Letter of Guarantee for Canada banned chemicals - (1-5CA) b. 请确保产品在均质材料中的汞浓度不超过0.1%（按重量计）。 Supplier certify that the WAL-MART vendor products does not have a mercury concentration of more than 0.1% by weight in homogeneous material. 附件列表： (1) Letter of Guarantee for Mercury COC c. 请确保产品的塑料材料不含以下物质（SOR 2011-17 27B): Supplier certify that the plastic materials do not contain the following substances(SOR 2011-17 27B): (a) carbon tetrachloride or any substance that contains it; (b) methyl alcohol or any substance thay contains >1.0%; (c) petroleum distillates or any substance that contains >10% weight to volume of petroleum distillates; (d) benzene; (e) turpentine or any substance that contains >10% weight to volume of turpentine; (f) boric acid or salts of boric acid; or (g) ethyl ether. 附件列表： (1) Letter of Guarantee for WM CA-Other prohibited substances in plastic(less than 3 years) | Y14: Monica Zhou | Z14: 4.6 | AA14: =Z14*J14 -> 23 | AB14: 95808-7.29 | AC14: 已入 | AE14: =J14 -> 5 | AG14: =J14 -> 5 | AI14: =J14 -> 5 | AN14: MA布标 | AO14: =J14/6 -> 0.83333333 | AP14: =J14/6 -> 0.83333333 | AQ14: =J14/6 -> 0.83333333 | AR14: =J14/6 -> 0.83333333 | AS14: =J14/6 -> 0.83333333 | AT14: =J14/6 -> 0.83333333 | AU14: =SUM(AO14:AT14) -> 5 | AV14: =J14-AU14 -> 0 | AX14: =AX13-AO14 -> 49447.333 | AY14: =AY13-AP14 -> 50281.333 | AZ14: =AZ13-AQ14 -> 49907.333 | BA14: =BA13-AR14 -> 51104.333 | BB14: =BB13-AS14 -> 55318.333 | BC14: =BC13-AT14 -> 58623.333
A15: 45737 | B15: WAL-MART CANADA CORP. | C15: 加拿大 | D15: 4500160934 | E15: 9900924249 | F15: 4500160934-30 | G15: 92125-S002-3L | H15: 92125-S002 | I15: 一窝猫蛋 | J15: 2205 | K15: 0 | L15: 1 | M15: =J15/L15 -> 2205 | N15: 45842 | O15: 45845 | P15: 7/9第三方 | Q15: PASS | R15: 7/15出 | S15: 5/21收到 | U15: 6/9-UPC贴纸 | X15: 日期码格式：ZURU INC(BVI) 标准格式 日期：按实际生产日期 Packaging Info: MA3L收缩膜+UPC贴纸(UPC:193052083951)+MA3L吊牌+MA5L收藏指南+MA5L收养卡+MA5L贴纸+MA配件袋+MA2L布标 产品配比：6 Assortments,siamese cat:pink-white cat:purple cat:black cat:brown-white cat:orange cat=1:1:1:1:1:1, no rare. Remark: 1. 此单有箱唛,客PO 9900923468为ECOM订单,外箱需加黄色贴纸; 2. 此单有第三方验货，烦请多备包装物料； 4. #92125 需于2025/6/23安排签版, 签样数量：大货样各3 SETS+散件2 SETS; 5. #92125 需于2025/6/30安排抽办测试, 抽办数量：大货各5 SETS+散件4 SETS; 6. UPC贴纸：必须在原来错误的条码上用黑色粗头笔涂黑直至不能扫描，再贴上正确的UPC; ********************* a. 请确保产品符合1999年版本的加拿大环境保护法(CEPA)和2012年禁止某些有毒物质法规的要求。该产品不含任何在加拿大禁用的化学物质，包括但不限于有毒物 质清单中列出的化学物质，并且在为加拿大沃尔玛生产产品期间没有使用任何禁用化学物质。 Supplier certify that the products comply with the requirements of Canadian Environmental Protection Act, 1999 (CEPA), Prohibition of Certain To xic Substances Regulations, 2012. The products do not contain any chemicals that are banned in Canada, including but not limited to those listed in the Toxic Substances List and no banned chemicals were used during the manufacturing of product for Walmart Canada. 附件列表： (1) Letter of Guarantee for Canada banned chemicals - (1-5CA) b. 请确保产品在均质材料中的汞浓度不超过0.1%（按重量计）。 Supplier certify that the WAL-MART vendor products does not have a mercury concentration of more than 0.1% by weight in homogeneous material. 附件列表： (1) Letter of Guarantee for Mercury COC c. 请确保产品的塑料材料不含以下物质（SOR 2011-17 27B): Supplier certify that the plastic materials do not contain the following substances(SOR 2011-17 27B): (a) carbon tetrachloride or any substance that contains it; (b) methyl alcohol or any substance thay contains >1.0%; (c) petroleum distillates or any substance that contains >10% weight to volume of petroleum distillates; (d) benzene; (e) turpentine or any substance that contains >10% weight to volume of turpentine; (f) boric acid or salts of boric acid; or (g) ethyl ether. 附件列表： (1) Letter of Guarantee for WM CA-Other prohibited substances in plastic(less than 3 years) | Y15: Monica Zhou | Z15: 4.6 | AA15: =Z15*J15 -> 10143 | AB15: 95809-7.29 | AC15: 已入 | AE15: =J15 -> 2205 | AG15: =J15 -> 2205 | AI15: =J15 -> 2205 | AN15: MA布标 | AO15: =J15/6 -> 367.5 | AP15: =J15/6 -> 367.5 | AQ15: =J15/6 -> 367.5 | AR15: =J15/6 -> 367.5 | AS15: =J15/6 -> 367.5 | AT15: =J15/6 -> 367.5 | AU15: =SUM(AO15:AT15) -> 2205 | AV15: =J15-AU15 -> 0 | AX15: =AX14-AO15 -> 49079.833 | AY15: =AY14-AP15 -> 49913.833 | AZ15: =AZ14-AQ15 -> 49539.833 | BA15: =BA14-AR15 -> 50736.833 | BB15: =BB14-AS15 -> 54950.833 | BC15: =BC14-AT15 -> 58255.833
A16: 45793 | B16: BJ'S WHOLESALE CLUB, INC. | C16: 美国 | D16: 4500166734 | E16: 116571779 | F16: 4500166734-10 | G16: 92125UQ1-S001 | H16: 92125UQ1-S001 | I16: 一窝猫蛋(PDQ装） | J16: 3084 | K16: 0 | L16: 4 | M16: =J16/L16 -> 771 | N16: 45841 | O16: 45846 | P16: 6/9-PDQ文档 | Q16: PASS | R16: 7/9出 | S16: 6/9收到 | U16: 无 | X16: 日期码格式：ZURU INC(BVI) 标准格式 日期：按实际生产日期 Packaging Info: MA UPC版本包装+客版PDQ。 Remark: 1. 此单大概6月9日需寄6套左右大货样给UL实验室做测试，具体的后面邮件会再通知。另外，还需要再备多4套大货样板到时候寄给客户。 2. 此单需一个40GP装完，但需超过客户要求的最少立方数，40GP最少要50CBM。箱唛上体积数和实际要相符，如体积数和PO上有不一致，客人会有罚款。 3. 产品和包装上的日期按照ZURU标准格式。 4. 产品不含以下物质： a. 不含任何的美国优先化学品priority chemicals； b. 不含或者不超过美国缅因州的高度关注化学品Chemicals of High Concern清单中的最低水平(100mg/kg)； c. 不含化学阻燃剂：TDCPP，TCEP，Antimony trioxide，HBCD，TBPH，TBB，SCCP，TCPP，Penta-BDE，Octa-BDE，TBBPA等。 | Y16: Emily Wu | Z16: 2.76 | AA16: =Z16*J16 -> 8511.84 | AC16: 已入 | AD16: =J16 -> 3084 | AG16: =J16 -> 3084 | AI16: =J16 -> 3084 | AJ16: =J16/4 -> 771 | AN16: MA布标 | AO16: =J16/6 -> 514 | AP16: =J16/6 -> 514 | AQ16: =J16/6 -> 514 | AR16: =J16/6 -> 514 | AS16: =J16/6 -> 514 | AT16: =J16/6 -> 514 | AU16: =SUM(AO16:AT16) -> 3084 | AV16: =J16-AU16 -> 0 | AX16: =AX15-AO16 -> 48565.833 | AY16: =AY15-AP16 -> 49399.833 | AZ16: =AZ15-AQ16 -> 49025.833 | BA16: =BA15-AR16 -> 50222.833 | BB16: =BB15-AS16 -> 54436.833 | BC16: =BC15-AT16 -> 57741.833
A17: 45793 | B17: BJ'S WHOLESALE CLUB, INC. | C17: 美国 | D17: 4500166736 | E17: 116571780 | F17: 4500166736-10 | G17: 92125UQ1-S001 | H17: 92125UQ1-S001 | I17: 一窝猫蛋(PDQ装） | J17: 3084 | K17: 0 | L17: 4 | M17: =J17/L17 -> 771 | N17: 45843 | O17: 45846 | Q17: PASS | R17: 7/10出 | S17: 6/9收到 | U17: 无 | X17: 日期码格式：ZURU INC(BVI) 标准格式 日期：按实际生产日期 Packaging Info: MA UPC版本包装+客版PDQ，PDQ AW 翻单PO#4500166734。 Remark: 1. 此单需一个40GP装完，但需超过客户要求的最少立方数，40GP最少要50CBM。箱唛上体积数和实际要相符，如体积数和PO上有不一致，客人会有罚款。 2. 产品和包装上的日期按照ZURU标准格式。 3. 产品不含以下物质： a. 不含任何的美国优先化学品priority chemicals； b. 不含或者不超过美国缅因州的高度关注化学品Chemicals of High Concern清单中的最低水平(100mg/kg)； c. 不含化学阻燃剂：TDCPP，TCEP，Antimony trioxide，HBCD，TBPH，TBB，SCCP，TCPP，Penta-BDE，Octa-BDE，TBBPA等。 | Y17: Emily Wu | Z17: 2.76 | AA17: =Z17*J17 -> 8511.84 | AC17: 已入 | AD17: =J17 -> 3084 | AG17: =J17 -> 3084 | AI17: =J17 -> 3084 | AJ17: =J17/4 -> 771 | AN17: MA布标 | AO17: =J17/6 -> 514 | AP17: =J17/6 -> 514 | AQ17: =J17/6 -> 514 | AR17: =J17/6 -> 514 | AS17: =J17/6 -> 514 | AT17: =J17/6 -> 514 | AU17: =SUM(AO17:AT17) -> 3084 | AV17: =J17-AU17 -> 0 | AX17: =AX16-AO17 -> 48051.833 | AY17: =AY16-AP17 -> 48885.833 | AZ17: =AZ16-AQ17 -> 48511.833 | BA17: =BA16-AR17 -> 49708.833 | BB17: =BB16-AS17 -> 53922.833 | BC17: =BC16-AT17 -> 57227.833
A18: 45790 | B18: KMART AUSTRALIA LTD | C18: 澳大利亚 | D18: 4500166289 | E18: 20676964 | F18: 4500166289-10 | G18: 92125-S001 | H18: 92125-S001 | I18: 一窝猫蛋 | J18: 2700 | K18: 0 | L18: 6 | M18: =J18/L18 -> 450 | N18: 45846 | O18: 45842 | Q18: PASS | R18: 7/9-7/11出 | S18: 5/26收到 | U18: 5/19-防盗贴纸+6/16-外箱SSCC | X18: 日期码格式：ZURU INC(BVI) 标准格式 日期：按实际生产日期 Packaging Info: "92125:MA英语UPC版本包装（收缩膜和说明书, MA首选1L，如无1L可用多语且含英语的配套多语包装) + 1张防盗贴纸 (贴纸以及位置图翻单PO#4500166286）+ 箱唛 + 外箱SSCC Label 配比信息：6 Assortments,siamese cat:pink-white cat:purple cat:black cat:brown-white cat:orange cat=1:1:1:1:1:1" Remark: 1.请务必按时完货，验货。并且按期送货入货代指定仓库，如果晚了导致船期Delay将会有罚金产生或者客户要求空运，所产生的罚金和空运费由工厂承担。 2.SSCC 外箱贴纸请同纸箱瓦楞纸方向（竖纹向）垂直，即外箱贴纸横着贴(注意条码不要被胶带粘住），贴1pc，贴1面正唛，封箱胶纸不能挡住贴纸内容。外箱贴纸 离外箱边距离不少于2cm。 3.外箱材质为ZURU标准； 4.此单需使用KMART封箱胶上下工字型封箱;从2019年6月开始，要用KMART 新版封箱胶带，此单要用"ANKO"封箱胶带 5.此单出口澳大利亚，请按相应的澳新标准生产； 6.产品和包装上生产批号的显示格式ZURU标准日期码格式 7.外箱信息不可手写，重量和体积需要与实际的一致(不可手写） 8. 每款item装箱后的G.W.超过10KG或者CBM超过0.13,(9.5KG或者以上，四舍五入后也属于10KG) 需在外箱上加印超 重或者Bulky LOGO，若发现我们资料没有，请 帮忙提醒 1)重量超过10kg但不超过16kg且CBM不超过0.13,10-16kg 超重logo 2）CBM超过0.13且重量少于17kg，bulky logo 3）不属于以上两种情况，需要使用相应重量范围内的超重logo 4）超重logo需要在外箱四面都印刷(箱唛右上角，两面侧唛超重logo需要尽量靠近毛重)，尺寸为:110mm height* 95mm width 9. 实际外箱重量跟印在箱唛上的数据差异不能超3%，尺寸按实际数据印刷 | Y18: Lydia Wu | Z18: 5.2 | AA18: =Z18*J18 -> 14040 | AB18: 95857-7.31 | AC18: 已入 | AD18: =J18 -> 2700 | AG18: =J18 -> 2700 | AI18: =J18 -> 2700 | AN18: MA布标 | AO18: =J18/6 -> 450 | AP18: =J18/6 -> 450 | AQ18: =J18/6 -> 450 | AR18: =J18/6 -> 450 | AS18: =J18/6 -> 450 | AT18: =J18/6 -> 450 | AU18: =SUM(AO18:AT18) -> 2700 | AV18: =J18-AU18 -> 0 | AX18: =AX17-AO18 -> 47601.833 | AY18: =AY17-AP18 -> 48435.833 | AZ18: =AZ17-AQ18 -> 48061.833 | BA18: =BA17-AR18 -> 49258.833 | BB18: =BB17-AS18 -> 53472.833 | BC18: =BC17-AT18 -> 56777.833
A19: 45797 | B19: ToyChamp Belgium nv | C19: 比利时 | D19: 4500166992 | E19: 250400000359 | F19: 4500166992-100 | G19: 92125-S001 | H19: 92125-S001 | I19: 一窝猫蛋 | J19: 2160 | K19: 0 | L19: 6 | M19: =J19/L19 -> 360 | N19: 45842 | O19: 45846 | Q19: PASS | R19: 7/10出 | S19: 5/20收到 | U19: 5/30-EAN贴纸+警告语贴纸 | X19: 日期码格式：ZURU INC(BVI) 标准格式 日期：按实际生产日期 Packaging Info: 10.92125：MA 最新版 1L UPC收缩膜+1张EAN贴纸+1张3L(FR+NL+DE)警告语贴纸+MA 5L+23L收藏指南+其他MA 包材EAN 4894680046306； Remark: 1.STD配比； 2.外箱需要印条码，请确保条码可以清晰扫描且条码内容正确； 3.出欧洲，微塑料需合规（如item本身不含微塑料,则忽略此要求）; 4.所有产品需要符合REACH申明。 | Y19: Bella Wang | Z19: 4.4 | AA19: =Z19*J19 -> 9504 | AB19: 95850-7.31 | AC19: 已入 | AD19: =J19 -> 2160 | AG19: =J19 -> 2160 | AI19: =J19 -> 2160 | AN19: MA布标 | AO19: =J19/6 -> 360 | AP19: =J19/6 -> 360 | AQ19: =J19/6 -> 360 | AR19: =J19/6 -> 360 | AS19: =J19/6 -> 360 | AT19: =J19/6 -> 360 | AU19: =SUM(AO19:AT19) -> 2160 | AV19: =J19-AU19 -> 0 | AX19: =AX18-AO19 -> 47241.833 | AY19: =AY18-AP19 -> 48075.833 | AZ19: =AZ18-AQ19 -> 47701.833 | BA19: =BA18-AR19 -> 48898.833 | BB19: =BB18-AS19 -> 53112.833 | BC19: =BC18-AT19 -> 56417.833
A20: 45749 | B20: COOP NORGE HANDEL AS - DOM | C20: 挪威 | D20: 4500162232 | E20: 32580048 | F20: 4500162232-10 | G20: 92125-S001-3L | H20: 92125-S001 | I20: 一窝猫蛋 | J20: 210 | K20: 0 | L20: 6 | M20: =J20/L20 -> 35 | N20: 45843 | O20: 45846 | P20: 7/11第三方 | Q20: PASS | R20: 6/30-7/18出 | S20: 4/2收到 | U20: 6/13-警语贴纸+布标贴纸 | X20: 日期码格式：ZURU INC(BVI) 标准格式 日期：按实际生产日期 Packaging Info: 92125： MA EAN 3L+警语贴纸+布标贴纸 Remark: 1/产品和包装要求无硼无香，包装不能含有PVC； 2/如有微塑料，必须合规欧洲标准，闪粉也是微塑料的一种，目前仅接受三张方式1.去除，2.用可降解材料，和3.永久封印在固体； 3/此订单有第三方验货，请准备三套大货样并不迟于5-14寄出给ZURU 深圳办公室； 4/带电池出货的产品所用到的电池需要符合欧洲电池新规(EU)2023-1542； 5/工厂货号-客户货号彩盒条码-外箱条码 92125-7254571-4894680046306-10193052083958 6/配比: 6 Assortments,siamese cat:pink-white cat:purple cat:black cat:brown-white cat:orange cat=1:1:1:1:1:1, no rare. | Y20: Zoe Zhou | Z20: 4.48 | AA20: =Z20*J20 -> 940.8 | AB20: 95716-7.21 | AC20: 已入 | AE20: =J20 -> 210 | AG20: =J20 -> 210 | AI20: =J20 -> 210 | AN20: MA布标+布标贴纸 | AO20: =J20/6 -> 35 | AP20: =J20/6 -> 35 | AQ20: =J20/6 -> 35 | AR20: =J20/6 -> 35 | AS20: =J20/6 -> 35 | AT20: =J20/6 -> 35 | AU20: =SUM(AO20:AT20) -> 210 | AV20: =J20-AU20 -> 0 | AX20: =AX19-AO20 -> 47206.833 | AY20: =AY19-AP20 -> 48040.833 | AZ20: =AZ19-AQ20 -> 47666.833 | BA20: =BA19-AR20 -> 48863.833 | BB20: =BB19-AS20 -> 53077.833 | BC20: =BC19-AT20 -> 56382.833
A21: 45790 | B21: KMART AUSTRALIA LTD(NEW ZEALAND) | C21: 新西兰 | D21: 4500166290 | E21: 20676969 | F21: 4500166290-10 | G21: 92125-S001 | H21: 92125-S001 | I21: 一窝猫蛋 | J21: 300 | K21: 0 | L21: 6 | M21: =J21/L21 -> 50 | N21: 45846 | O21: 45842 | Q21: PASS | R21: 7/9-7/11出 | S21: 5/26收到 | U21: 5/19-防盗贴纸+6/16-外箱SSCC | X21: 日期码格式：ZURU INC(BVI) 标准格式 日期：按实际生产日期 Packaging Info: "92125:MA英语UPC版本包装（收缩膜和说明书, MA首选1L，如无1L可用多语且含英语的配套多语包装) + 1张防盗贴纸 (贴纸以及位置图翻单PO#4500166286）+ 箱唛 + 外箱SSCC Label 配比信息：6 Assortments,siamese cat:pink-white cat:purple cat:black cat:brown-white cat:orange cat=1:1:1:1:1:1" Remark: 1.请务必按时完货，验货。并且按期送货入货代指定仓库，如果晚了导致船期Delay将会有罚金产生或者客户要求空运，所产生的罚金和空运费由工厂承担。 2.SSCC 外箱贴纸请同纸箱瓦楞纸方向（竖纹向）垂直，即外箱贴纸横着贴(注意条码不要被胶带粘住），贴1pc，贴1面正唛，封箱胶纸不能挡住贴纸内容。外箱贴纸 离外箱边距离不少于2cm。 3.外箱材质为ZURU标准； 4.此单需使用KMART封箱胶上下工字型封箱;从2019年6月开始，要用KMART 新版封箱胶带，此单要用"ANKO"封箱胶带 5.此单出口新西兰，请按相应的澳新标准生产； 6.产品和包装上生产批号的显示格式ZURU标准日期码格式 7.外箱信息不可手写，重量和体积需要与实际的一致(不可手写） 8. 每款item装箱后的G.W.超过10KG或者CBM超过0.13,(9.5KG或者以上，四舍五入后也属于10KG) 需在外箱上加印超 重或者Bulky LOGO，若发现我们资料没有，请 帮忙提醒 1)重量超过10kg但不超过16kg且CBM不超过0.13,10-16kg 超重logo 2）CBM超过0.13且重量少于17kg，bulky logo 3）不属于以上两种情况，需要使用相应重量范围内的超重logo 4）超重logo需要在外箱四面都印刷(箱唛右上角，两面侧唛超重logo需要尽量靠近毛重)，尺寸为:110mm height* 95mm width 9. 实际外箱重量跟印在箱唛上的数据差异不能超3%，尺寸按实际数据印刷 | Y21: Lydia Wu | Z21: 5.2 | AA21: =Z21*J21 -> 1560 | AB21: 95858-7.31 | AC21: 已入 | AD21: =J21 -> 300 | AG21: =J21 -> 300 | AI21: =J21 -> 300 | AN21: MA布标 | AO21: =J21/6 -> 50 | AP21: =J21/6 -> 50 | AQ21: =J21/6 -> 50 | AR21: =J21/6 -> 50 | AS21: =J21/6 -> 50 | AT21: =J21/6 -> 50 | AU21: =SUM(AO21:AT21) -> 300 | AV21: =J21-AU21 -> 0 | AX21: =AX20-AO21 -> 47156.833 | AY21: =AY20-AP21 -> 47990.833 | AZ21: =AZ20-AQ21 -> 47616.833 | BA21: =BA20-AR21 -> 48813.833 | BB21: =BB20-AS21 -> 53027.833 | BC21: =BC20-AT21 -> 56332.833
A22: 45722 | B22: SCHEEL'S ALL SPORTS, INC. | C22: 美国 | D22: 4500159089 | E22: PO#019848154 | F22: 4500159089-60 | G22: 92125-S001 | H22: 92125-S001 | I22: 一窝猫蛋 | J22: 948 | K22: 0 | L22: 6 | M22: =J22/L22 -> 158 | N22: 45848 | O22: 45845 | Q22: PASS | R22: 7/14出 | S22: 3/6收到 | U22: 无 | X22: 日期码格式：ZURU INC(BVI) 标准格式 日期：按实际生产日期 Packaging Info: 1. 包装：ZURU MA 1L 最新UPC版本；出口美国<(>&<)>CA； Remark: 2. 日期跟踪码：产品包装及产品本身都必须有日期跟踪码，并且确保两者的日期跟踪码要一致；ZURU标准格式日期码(请自行调整具体年月日生产期，但不能为周 末）。 3. 此单有4个客户PO， 请见侧边备注； 4. 出货配比: Zuru 标版配比。 | Y22: Mila Yao | Z22: 4.4 | AA22: =J22*Z22 -> 4171.2 | AC22: 已入 | AD22: =J22 -> 948 | AG22: =J22 -> 948 | AI22: =J22 -> 948 | AN22: MA布标 | AO22: =J22/6 -> 158 | AP22: =J22/6 -> 158 | AQ22: =J22/6 -> 158 | AR22: =J22/6 -> 158 | AS22: =J22/6 -> 158 | AT22: =J22/6 -> 158 | AU22: =SUM(AO22:AT22) -> 948 | AV22: =J22-AU22 -> 0 | AX22: =AX21-AO22 -> 46998.833 | AY22: =AY21-AP22 -> 47832.833 | AZ22: =AZ21-AQ22 -> 47458.833 | BA22: =BA21-AR22 -> 48655.833 | BB22: =BB21-AS22 -> 52869.833 | BC22: =BC21-AT22 -> 56174.833
A23: 45814 | B23: N.V. DREAMLAND | C23: 比利时 | D23: 4500169127 | E23: 4500061206 | F23: 4500169127-20 | G23: 92125-S001 | H23: 92125-S001 | I23: 一窝猫蛋 | J23: 2400 | K23: 0 | L23: 6 | M23: =J23/L23 -> 400 | N23: 45849 | O23: 45845 | Q23: PASS | S23: 6/6收到 | U23: EAN贴纸+3L(FR+NL+DE)警告语贴纸翻4500166992 | X23: 日期码格式：ZURU INC(BVI) 标准格式 日期：按实际生产日期 Packaging Info: 2.92125：MA 最新版 1L UPC收缩膜+1张EAN贴纸（翻单4500166992）+1张3L(FR+NL+DE)警告语贴纸（翻单4500166992）+MA 5L+23L收藏指南+其他MA 包材； Remark: 1. 如MA 产品中有大于10*10cm的塑料袋，必须印上英语/荷兰语/法语/德语的防窒息警告语，印刷内容请与跟单确认； 2. 所有塑料袋的厚度不小于0.038mm； 3. 订单出比利时，产品及包装需要印CE图标；包装需要有ZURU France地址信息，QC同事请核查，如有问题与跟单确认； 4. 标准配比； 5. 出欧洲，微塑料需合规（如item本身不含微塑料 则忽略此要求）。 | Y23: Bella Wang | Z23: 4.18 | AA23: =J23*Z23 -> 10032 | AC23: 已入 | AD23: =J23 -> 2400 | AG23: =J23 -> 2400 | AI23: =J23 -> 2400 | AN23: MA布标 | AO23: =J23/6 -> 400 | AP23: =J23/6 -> 400 | AQ23: =J23/6 -> 400 | AR23: =J23/6 -> 400 | AS23: =J23/6 -> 400 | AT23: =J23/6 -> 400 | AU23: =SUM(AO23:AT23) -> 2400 | AV23: =J23-AU23 -> 0 | AX23: =AX22-AO23 -> 46598.833 | AY23: =AY22-AP23 -> 47432.833 | AZ23: =AZ22-AQ23 -> 47058.833 | BA23: =BA22-AR23 -> 48255.833 | BB23: =BB22-AS23 -> 52469.833 | BC23: =BC22-AT23 -> 55774.833
A24: 45764 | B24: THE ENTERTAINER | C24: 英国 | D24: 4500163498 | E24: FB13240 | F24: 4500163498-10 | G24: 92125-S001 | H24: 92125-S001 | I24: 一窝猫蛋 | J24: 4590 | K24: 0 | L24: 6 | M24: =J24/L24 -> 765 | N24: 45853 | O24: 45849 | Q24: PASS | R24: 7/16出 | S24: 4/17收到 | U24: 6/23-客户EAN 条码贴纸 | X24: 日期码格式：ZURU INC(BVI) 标准格式 日期：按实际生产日期 Packaging Info: MA 1L+客户EAN 条码贴纸 （EAN: 5056296049921） Remark: *MA版本按工厂现有最新库存即可，订单出英国，请注意检查产品及包装应带UKCA图标，包装显示ZURU UK LTD信息，QC同事请查核，如有问题与跟单确认 *生产日期按实际（法定工作日），按ZURU标准格式即可 ，但是请知悉包装日期码需要早于或者等于外箱日期码 ，不能晚于外箱日期码 *请注意所有订单都需要经过ZURU QC验货并且通过后方可出货 *所有产品按符合欧洲标准走货，需要是不含微塑料版本 。 *涉及到硼的，如可选择情况下应使用低硼版本 （slime 类别低硼一般低于300ppm)，无选择的应与跟单复核再安排 。 *如果出运产品属于电子类产品需要在ZURU 包装基础上额外添加一张英文+阿拉伯文电池说明书。 *大货样： 请在6/15 前寄出随机2pcs大货样到罗湖办公室7B Sandy Shao 收。 | Y24: Sandy Shao | Z24: 4.4 | AA24: =J24*Z24 -> 20196 | AB24: 95806-7.29 | AC24: 已入 | AD24: =J24 -> 4590 | AG24: =J24 -> 4590 | AI24: =J24 -> 4590 | AN24: MA布标 | AO24: =J24/6 -> 765 | AP24: =J24/6 -> 765 | AQ24: =J24/6 -> 765 | AR24: =J24/6 -> 765 | AS24: =J24/6 -> 765 | AT24: =J24/6 -> 765 | AU24: =SUM(AO24:AT24) -> 4590 | AV24: =J24-AU24 -> 0 | AX24: =AX23-AO24 -> 45833.833 | AY24: =AY23-AP24 -> 46667.833 | AZ24: =AZ23-AQ24 -> 46293.833 | BA24: =BA23-AR24 -> 47490.833 | BB24: =BB23-AS24 -> 51704.833 | BC24: =BC23-AT24 -> 55009.833
A25: 45860 | B25: THE ENTERTAINER | C25: 英国 | D25: 4500163498 | E25: FB13334 | F25: 4500163498-10 | G25: 92125-S001 | H25: 92125-S001 | I25: 一窝猫蛋 | J25: 102 | K25: 0 | L25: 6 | M25: =J25/L25 -> 17 | N25: 45853 | O25: 45849 | P25: 4500163498拆分数量 | Q25: PASS | R25: 7/16出 | S25: 4/17收到 | U25: 6/23-客户EAN 条码贴纸 | X25: 日期码格式：ZURU INC(BVI) 标准格式 日期：按实际生产日期 Packaging Info: MA 1L+客户EAN 条码贴纸 （EAN: 5056296049921） Remark: *MA版本按工厂现有最新库存即可，订单出英国，请注意检查产品及包装应带UKCA图标，包装显示ZURU UK LTD信息，QC同事请查核，如有问题与跟单确认 *生产日期按实际（法定工作日），按ZURU标准格式即可 ，但是请知悉包装日期码需要早于或者等于外箱日期码 ，不能晚于外箱日期码 *请注意所有订单都需要经过ZURU QC验货并且通过后方可出货 *所有产品按符合欧洲标准走货，需要是不含微塑料版本 。 *涉及到硼的，如可选择情况下应使用低硼版本 （slime 类别低硼一般低于300ppm)，无选择的应与跟单复核再安排 。 *如果出运产品属于电子类产品需要在ZURU 包装基础上额外添加一张英文+阿拉伯文电池说明书。 *大货样： 请在6/15 前寄出随机2pcs大货样到罗湖办公室7B Sandy Shao 收。 | Y25: Sandy Shao | Z25: 4.4 | AA25: =J25*Z25 -> 448.8 | AB25: 95806-7.29 | AC25: 已入 | AD25: =J25 -> 102 | AG25: =J25 -> 102 | AI25: =J25 -> 102 | AN25: MA布标 | AO25: =J25/6 -> 17 | AP25: =J25/6 -> 17 | AQ25: =J25/6 -> 17 | AR25: =J25/6 -> 17 | AS25: =J25/6 -> 17 | AT25: =J25/6 -> 17 | AU25: =SUM(AO25:AT25) -> 102 | AV25: =J25-AU25 -> 0 | AX25: =AX24-AO25 -> 45816.833 | AY25: =AY24-AP25 -> 46650.833 | AZ25: =AZ24-AQ25 -> 46276.833 | BA25: =BA24-AR25 -> 47473.833 | BB25: =BB24-AS25 -> 51687.833 | BC25: =BC24-AT25 -> 54992.833
A26: 45712 | B26: ZURU Germany GMBH | C26: 德国 | D26: 4500158412 | E26: 5200006231 | F26: 4500158412-10 | G26: 92125-S005-MTS-3L | H26: 92125-S005-MTS | I26: 一窝猫蛋 | J26: 2400 | K26: 0 | L26: 3 | M26: =J26/L26 -> 800 | N26: 45852 | O26: 45848 | Q26: PASS | R26: 7/21出 | S26: 2/24收到 | U26: 多语警语贴纸 | X26: 日期码格式：ZURU INC(BVI) 标准格式 日期：按实际生产日期 Packaging Info: 92125：MA3+23L EAN 收缩膜+1*多语警语贴纸+MA5L+23L 收藏指南+MA 23L 配件袋+MA 布标 +其他MA 包材 Remark: "1.德国内销单，需要通过ZURU 验货结果后才能出货 (工厂需要主动提前同ZURU QC预约验货避免延期出货造成不必要麻烦)； 2. 若有特定款有特殊外箱条码要求时,需要明确列出产品款对应的具体外箱条码号码/条码类型 (若无,可以忽略此需求) 3.所有出口欧洲的产品, 法规规定禁止在包装和共公众用的印刷品中使用矿物油中含有的物质, 包装印刷油墨中含有的MOAH/MOSH的质量浓度不能超过1%, 否则出货 到法国被抽检出现问题, 供应商需要对此负责; 4. date code: 外箱日期码要晚于或等于产品日期码，不能早于产品的日期码 5. 所有电子产品身上需要加字唛，为ZURU FRANCE 地址 (如无电子产品，或者产品布标有此地址，可忽略此信息) ZURU France 1/3, Rue d'Argenteuil 95210 SAINT-GRATIEN, FRANCE 6. 装柜时需要按照款式号码从小到大一款款依次装,避免终端仓库卸货混乱.若一个柜子涉及到几个不同国家内销单,装柜时需要一个国家装完后再装另一个国家的 产品,依次装柜,避免终端仓库因不同国家不同库位位置卸货混乱. (此点需要同工厂装柜人员强调)" | Y26: SD82 | Z26: 4.8 | AA26: =Z26*J26 -> 11520 | AB26: 95750-7.24 | AC26: 已入 | AE26: =J26 -> 2400 | AG26: =J26 -> 2400 | AI26: =J26 -> 2400 | AN26: MA布标 | AO26: =J26/6 -> 400 | AP26: =J26/6 -> 400 | AQ26: =J26/6 -> 400 | AR26: =J26/6 -> 400 | AS26: =J26/6 -> 400 | AT26: =J26/6 -> 400 | AU26: =SUM(AO26:AT26) -> 2400 | AV26: =J26-AU26 -> 0 | AX26: =AX25-AO26 -> 45416.833 | AY26: =AY25-AP26 -> 46250.833 | AZ26: =AZ25-AQ26 -> 45876.833 | BA26: =BA25-AR26 -> 47073.833 | BB26: =BB25-AS26 -> 51287.833 | BC26: =BC25-AT26 -> 54592.833
A27: 45748 | B27: PRO & PACIFIC CO.,LTD | C27: 台湾 | D27: 4500162246 | E27: ZU25031901 | F27: 4500162246-20 | G27: 92125-S001 | H27: 92125-S001 | I27: 一窝猫蛋 | J27: 360 | K27: 0 | L27: 6 | M27: =J27/L27 -> 60 | N27: 45853 | O27: 45849 | Q27: PASS | R27: 7/25出 | S27: 4/15收到 | U27: 4/11-进口商贴纸 | X27: 日期码格式：ZURU INC(BVI) 标准格式 日期：按实际生产日期 Packaging Info: MA UPC包装（优先1L)+1张进口商贴纸 92125贴纸AW、位置图待提供 Remark: 92125-6 Assortments,siamese cat:pink-white cat:purple cat:black cat:brown-white cat:orange cat=1:1:1:1:1:1, no rare. | Y27: Emma Wu | Z27: 4.4 | AA27: =J27*Z27 -> 1584 | AB27: 95769-7.25 | AC27: 已入 | AD27: =J27 -> 360 | AG27: =J27 -> 360 | AI27: =J27 -> 360 | AN27: MA布标 | AO27: =J27/6 -> 60 | AP27: =J27/6 -> 60 | AQ27: =J27/6 -> 60 | AR27: =J27/6 -> 60 | AS27: =J27/6 -> 60 | AT27: =J27/6 -> 60 | AU27: =SUM(AO27:AT27) -> 360 | AV27: =J27-AU27 -> 0 | AX27: =AX26-AO27 -> 45356.833 | AY27: =AY26-AP27 -> 46190.833 | AZ27: =AZ26-AQ27 -> 45816.833 | BA27: =BA26-AR27 -> 47013.833 | BB27: =BB26-AS27 -> 51227.833 | BC27: =BC26-AT27 -> 54532.833
A28: 45757 | B28: ZURU Denmark ApS | C28: 丹麦 | D28: 4500162275 | E28: 5200006533 | F28: 4500162275-10 | G28: 92125-S005-MTS-3L | H28: 92125-S005-MTS | I28: 一窝猫蛋 | J28: 1314 | K28: 0 | L28: 3 | M28: =J28/L28 -> 438 | N28: 45853 | O28: 45849 | Q28: PASS | R28: 7/30出 | S28: 4/22收到 | U28: 5/13-多语警告语贴纸+ | X28: 日期码格式：ZURU INC(BVI) 标准格式 日期：按实际生产日期 Packaging Info: MA 多语EAN 包装+1*多语警告语贴纸+其他MA 多语包材 EAN 4894680046306 Remark: 1.北欧内销单，需要通过ZURU 验货结果后才能出货 (工厂需要主动提前同ZURU QC预约验货避免延期出货造成不必要麻烦)； 2. 产品如含有化学品，需要无硼无香， 3.包装不能含有PVC，使用PET 4. date code: 外箱日期码要晚于产品日期码 5. 装柜时需要按照款式号码从小到大一款款依次装,避免终端仓库卸货混乱.若一个柜子涉及到几个不同国家内销单,装柜时需要一个国家装完后再装另一个国家的 产品,依次装柜,避免终端仓库因不同国家不同库位位置卸货混乱. (此点需要同工厂装柜人员强调)" 6.若有特定款有特殊外箱条码要求时,需要明确列出产品款对应的具体外箱条码号码/条码类型 (若无,可以忽略此需求) 7.所有出口欧洲的产品, 法规规定禁止在包装和共公众用的印刷品中使用矿物油中含有的物质, 包装印刷油墨中含有的MOAH/MOSH的质量浓度不能超过1%, 否则出货 到法国被抽检出现问题, 供应商需要对此负责; 8.带电池出货的产品所用到的电池需要符合欧洲电池新规(EU) 2023-1542。 9.ratio 同MA | Y28: SD04 | Z28: 4.8 | AA28: =Z28*J28 -> 6307.2 | AB28: 95807-7.29 | AC28: 已入 | AE28: =J28 -> 1314 | AG28: =J28 -> 1314 | AI28: =J28 -> 1314 | AN28: MA布标 | AO28: =J28/6 -> 219 | AP28: =J28/6 -> 219 | AQ28: =J28/6 -> 219 | AR28: =J28/6 -> 219 | AS28: =J28/6 -> 219 | AT28: =J28/6 -> 219 | AU28: =SUM(AO28:AT28) -> 1314 | AV28: =J28-AU28 -> 0 | AX28: =AX27-AO28 -> 45137.833 | AY28: =AY27-AP28 -> 45971.833 | AZ28: =AZ27-AQ28 -> 45597.833 | BA28: =BA27-AR28 -> 46794.833 | BB28: =BB27-AS28 -> 51008.833 | BC28: =BC27-AT28 -> 54313.833
A29: 45792 | B29: PRO & PACIFIC CO.,LTD | C29: 台湾 | D29: 4500166599 | E29: ZU25041801 | F29: 4500166599-40 | G29: 92125-S001 | H29: 92125-S001 | I29: 一窝猫蛋 | J29: 240 | K29: 0 | L29: 6 | M29: =J29/L29 -> 40 | N29: 45853 | O29: 45849 | Q29: PASS | R29: 7/25出 | S29: 5/15收到 | U29: 6/23-进口商贴纸 | X29: 日期码格式：ZURU INC(BVI) 标准格式 日期：按实际生产日期 Packaging Info: 1.MA UPC包装（优先1L)+1张进口商贴纸 其他item贴纸AW、位置图待提供 3.此单分批出货，92125 7月出货，走20GP Remark: 92125-6 Assortments,siamese cat:pink-white cat:purple cat:black cat:brown-white cat:orange cat=1:1:1:1:1:1, no rare. | Y29: Emma Wu | Z29: 4.48 | AA29: =J29*Z29 -> 1075.2 | AB29: 95770-7.25 | AC29: 已入 | AD29: =J29 -> 240 | AG29: =J29 -> 240 | AI29: =J29 -> 240 | AN29: MA布标 | AO29: =J29/6 -> 40 | AP29: =J29/6 -> 40 | AQ29: =J29/6 -> 40 | AR29: =J29/6 -> 40 | AS29: =J29/6 -> 40 | AT29: =J29/6 -> 40 | AU29: =SUM(AO29:AT29) -> 240 | AV29: =J29-AU29 -> 0 | AX29: =AX28-AO29 -> 45097.833 | AY29: =AY28-AP29 -> 45931.833 | AZ29: =AZ28-AQ29 -> 45557.833 | BA29: =BA28-AR29 -> 46754.833 | BB29: =BB28-AS29 -> 50968.833 | BC29: =BC28-AT29 -> 54273.833
A30: 45797 | B30: BRICKLAND LLC | C30: 蒙古 | D30: 4500167048 | E30: Zuru.2025Q3 | F30: 4500167048-20 | G30: 92125-S001 | H30: 92125-S001 | I30: 一窝猫蛋 | J30: 600 | K30: 0 | L30: 6 | M30: =J30/L30 -> 100 | N30: 45856 | O30: 45852 | Q30: PASS | R30: 7/19出 | S30: 5/20收到 | U30: 5/27-进口商贴纸 | X30: 日期码格式：ZURU INC(BVI) 标准格式 日期：按实际生产日期 Packaging Info: MA UPC包装(优先1L)+1张进口商贴纸 Remark: 92125-6 Assortments,siamese cat:pink-white cat:purple cat:black cat:brown-white cat:orange cat=1:1:1:1:1:1, no rare. | Y30: Emma Wu | Z30: 4.4 | AA30: =J30*Z30 -> 2640 | AB30: 95715-7.21 | AC30: 已入 | AD30: =J30 -> 600 | AG30: =J30 -> 600 | AI30: =J30 -> 600 | AN30: MA布标 | AO30: =J30/6 -> 100 | AP30: =J30/6 -> 100 | AQ30: =J30/6 -> 100 | AR30: =J30/6 -> 100 | AS30: =J30/6 -> 100 | AT30: =J30/6 -> 100 | AU30: =SUM(AO30:AT30) -> 600 | AV30: =J30-AU30 -> 0 | AX30: =AX29-AO30 -> 44997.833 | AY30: =AY29-AP30 -> 45831.833 | AZ30: =AZ29-AQ30 -> 45457.833 | BA30: =BA29-AR30 -> 46654.833 | BB30: =BB29-AS30 -> 50868.833 | BC30: =BC29-AT30 -> 54173.833
A31: 45805 | B31: Lekia AB | C31: 瑞典 | D31: 4500168129 | E31: 156653-4 | F31: 4500168129-10 | G31: 92125-S006-3L | H31: 92125-S006 | I31: 一窝猫蛋 | J31: 564 | K31: 0 | L31: 4 | M31: =J31/L31 -> 141 | N31: 45856 | O31: 45856 | Q31: PASS | R31: 7/19出 | S31: 6/23收到 | U31: 6/27-进口商贴纸 | X31: 日期码格式：ZURU INC(BVI) 标准格式 日期：按实际生产日期 Packaging Info: 92125: 3L EAN 包装+进口商贴纸 Remark: 1. 包装如含PVC,请改为PET 2. 产品/包装要求无硼无香； 3. 出欧洲，微塑料需合规。 4.带电池出货的产品所用到的电池需要符合欧洲电池新规(EU) 2023-1542 5.关于贴纸，如果贴纸位置图的包装版本与大货不一致，请工厂提前提出。跟单会重新调整确认是否更新贴纸或调整位置图 6.产品/包装不含PFAS成分 6 Assortments,siamese cat:pink-white cat:purple cat:black cat:brown-white cat:orange cat=1:1:1:1:1:1 7.SKU-客户款号-条码 92125//100-264011493//4894680046306 | Y31: Luna Lin | Z31: 5.2 | AA31: =J31*Z31 -> 2932.8 | AB31: 95749-7.24 | AC31: 已入 | AE31: =J31 -> 564 | AG31: =J31 -> 564 | AI31: =J31 -> 564 | AN31: MA布标 | AO31: =J31/6 -> 94 | AP31: =J31/6 -> 94 | AQ31: =J31/6 -> 94 | AR31: =J31/6 -> 94 | AS31: =J31/6 -> 94 | AT31: =J31/6 -> 94 | AU31: =SUM(AO31:AT31) -> 564 | AV31: =J31-AU31 -> 0 | AX31: =AX30-AO31 -> 44903.833 | AY31: =AY30-AP31 -> 45737.833 | AZ31: =AZ30-AQ31 -> 45363.833 | BA31: =BA30-AR31 -> 46560.833 | BB31: =BB30-AS31 -> 50774.833 | BC31: =BC30-AT31 -> 54079.833
A32: 45726 | B32: B&M RETAIL LIMITED | C32: 英国 | D32: 4500159310 | E32: 客户PO:019225 69/1 | F32: 4500159310-10 | G32: 92125-S001 | H32: 92125-S001 | I32: 一窝猫蛋 | J32: 4002 | K32: 0 | L32: 6 | M32: =J32/L32 -> 667 | N32: 45854 | O32: 45850 | Q32: PASS | R32: 7/22出 | S32: 3/10收到 | U32: 无 | X32: 日期码格式：ZURU INC(BVI) 标准格式 日期：按实际生产日期 Packaging Info: 6 Assortments,siamese cat:pink-white cat:purple cat:black cat:brown-white cat:orange cat=1:1:1:1:1:1, no rare. Remark: *此单对应2个客户PO，请分开做货不要混装，单独装柜 *MA UPC版本按工厂现有最新库存即可，订单出英国，请注意检查产品及包装应带UKCA图标，包装显示ZURU UK LTD信息，QC同事请查核，如有问题与跟单确认。 *生产日期按实际（法定工作日），按ZURU标准格式即可 ，但是请知悉包装日期码需要早于或者等于外箱日期码 ，不能晚于外箱日期码 *请注意所有订单都需要经过ZURU QC验货并且通过后方可出货 *条码以订单显示为准 ，请安排生产前先核对 ，有问题请提出。 *所有产品按符合欧洲标准走货，需要是不含微塑料版本 。 *涉及到硼的，如可选择情况下应使用低硼版本 （slime 类别低硼一般低于300ppm)，无选择的应与跟单复核再安排 。 *大货完成后请及时提供shipment images 供客户批复 ，如未提供照片就直接走柜，有问题由工厂负责 。 *最终出货工厂需要按船务要求为集装箱挂网，如不按要求挂网导致罚款由工厂承担 。 | Y32: CORA ZHOU | Z32: 4.4 | AA32: =J32*Z32 -> 17608.8 | AB32: 95725-7.22 | AC32: 已入 | AD32: =J32 -> 4002 | AG32: =J32 -> 4002 | AI32: =J32 -> 4002 | AN32: MA布标 | AO32: =J32/6 -> 667 | AP32: =J32/6 -> 667 | AQ32: =J32/6 -> 667 | AR32: =J32/6 -> 667 | AS32: =J32/6 -> 667 | AT32: =J32/6 -> 667 | AU32: =SUM(AO32:AT32) -> 4002 | AV32: =J32-AU32 -> 0 | AX32: =AX31-AO32 -> 44236.833 | AY32: =AY31-AP32 -> 45070.833 | AZ32: =AZ31-AQ32 -> 44696.833 | BA32: =BA31-AR32 -> 45893.833 | BB32: =BB31-AS32 -> 50107.833 | BC32: =BC31-AT32 -> 53412.833
A33: 45726 | B33: B&M RETAIL LIMITED | C33: 英国 | D33: 4500159310 | E33: 客户PO:019225 70/1 | F33: 4500159310-20 | G33: 92125-S001 | H33: 92125-S001 | I33: 一窝猫蛋 | J33: 4002 | K33: 0 | L33: 6 | M33: =J33/L33 -> 667 | N33: 45854 | O33: 45850 | Q33: PASS | R33: 7/22出 | S33: 3/10收到 | U33: 无 | X33: 日期码格式：ZURU INC(BVI) 标准格式 日期：按实际生产日期 Packaging Info: 6 Assortments,siamese cat:pink-white cat:purple cat:black cat:brown-white cat:orange cat=1:1:1:1:1:1, no rare. Remark: *此单对应2个客户PO，请分开做货不要混装，单独装柜 *MA UPC版本按工厂现有最新库存即可，订单出英国，请注意检查产品及包装应带UKCA图标，包装显示ZURU UK LTD信息，QC同事请查核，如有问题与跟单确认。 *生产日期按实际（法定工作日），按ZURU标准格式即可 ，但是请知悉包装日期码需要早于或者等于外箱日期码 ，不能晚于外箱日期码 *请注意所有订单都需要经过ZURU QC验货并且通过后方可出货 *条码以订单显示为准 ，请安排生产前先核对 ，有问题请提出。 *所有产品按符合欧洲标准走货，需要是不含微塑料版本 。 *涉及到硼的，如可选择情况下应使用低硼版本 （slime 类别低硼一般低于300ppm)，无选择的应与跟单复核再安排 。 *大货完成后请及时提供shipment images 供客户批复 ，如未提供照片就直接走柜，有问题由工厂负责 。 *最终出货工厂需要按船务要求为集装箱挂网，如不按要求挂网导致罚款由工厂承担 。 | Y33: CORA ZHOU | Z33: 4.4 | AA33: =J33*Z33 -> 17608.8 | AB33: 95725-7.22 | AC33: 已入 | AD33: =J33 -> 4002 | AG33: =J33 -> 4002 | AI33: =J33 -> 4002 | AN33: MA布标 | AO33: =J33/6 -> 667 | AP33: =J33/6 -> 667 | AQ33: =J33/6 -> 667 | AR33: =J33/6 -> 667 | AS33: =J33/6 -> 667 | AT33: =J33/6 -> 667 | AU33: =SUM(AO33:AT33) -> 4002 | AV33: =J33-AU33 -> 0 | AX33: =AX32-AO33 -> 43569.833 | AY33: =AY32-AP33 -> 44403.833 | AZ33: =AZ32-AQ33 -> 44029.833 | BA33: =BA32-AR33 -> 45226.833 | BB33: =BB32-AS33 -> 49440.833 | BC33: =BC32-AT33 -> 52745.833
A34: 45813 | B34: Concentra, S.A. | C34: 葡萄牙 | D34: 4500163278 | F34: 4500163278-20 | G34: 92125-S001-3L | H34: 92125-S001 | I34: 一窝猫蛋 | J34: 360 | K34: 0 | L34: 6 | M34: =J34/L34 -> 60 | N34: 45859 | O34: 45854 | Q34: PASS | R34: 7/27出 | S34: 6/18收到 | U34: 6/5-CONCENTRA"logo彩色贴纸+1*进口商黑白贴纸 | X34: 日期码格式：ZURU INC(BVI) 标准格式 日期：按实际生产日期 Packaging Info: 92125:最新MA3L(24Lwarning)收缩膜+最新MA5L(23Lwarning)收藏指南+1*CONCENTRA"logo彩色贴纸+1*进口商黑白贴纸 Remark: 1, 所有产品不带闪粉和微塑料，客人需要验货图片确认OK 才能放货，请务必按时完货。 | Y34: Jade Wang | Z34: 5.5009 | AA34: =J34*Z34 -> 1980.324 | AB34: 95782-7.26 | AC34: 已入 | AE34: =J34 -> 360 | AG34: =J34 -> 360 | AI34: =J34 -> 360 | AN34: MA布标 | AO34: =J34/6 -> 60 | AP34: =J34/6 -> 60 | AQ34: =J34/6 -> 60 | AR34: =J34/6 -> 60 | AS34: =J34/6 -> 60 | AT34: =J34/6 -> 60 | AU34: =SUM(AO34:AT34) -> 360 | AV34: =J34-AU34 -> 0 | AX34: =AX33-AO34 -> 43509.833 | AY34: =AY33-AP34 -> 44343.833 | AZ34: =AZ33-AQ34 -> 43969.833 | BA34: =BA33-AR34 -> 45166.833 | BB34: =BB33-AS34 -> 49380.833 | BC34: =BC33-AT34 -> 52685.833
A35: 45820 | B35: NORWEGIAN TOY IMPORT AS - DOM | C35: 挪威 | D35: 4500169836 | E35: 14675 | F35: 4500169836-10 | G35: 92125-S001-3L | H35: 92125-S001 | I35: 一窝猫蛋 | J35: 210 | K35: 0 | L35: 6 | M35: =J35/L35 -> 35 | N35: 45860 | O35: 45856 | Q35: PASS | R35: 7/30出 | S35: 6/12收到 | U35: 6/19-进口商贴纸 | X35: 日期码格式：ZURU INC(BVI) 标准格式 日期：按实际生产日期 Packaging Info: 92125: MA EAN 3L +1进口商贴纸 Remark: 1/ 92125 配比：6 Assortments,siamese cat:pink-white cat:purple cat:black cat:brown-white cat:orange cat=1:1:1:1:1:1, no rare. 2/ 产品和包装要求无硼无香，包装不能含有PVC; 3/ 如有微塑料，必须合规欧洲标准，闪粉也是微塑料的一种，目前仅接受三张方式1.去除，2.用可降解材料，和3. 永久封印在固体。 4/ 带电池出货的产品<(>,<)>电池需要符合欧洲电池新规(EU) 2023-1542. | Y35: Zoe Zhou | Z35: 4.4 | AA35: =J35*Z35 -> 924 | AB35: 95793-7.28 | AC35: 已入 | AE35: =J35 -> 210 | AG35: =J35 -> 210 | AI35: =J35 -> 210 | AN35: MA布标 | AO35: =J35/6 -> 35 | AP35: =J35/6 -> 35 | AQ35: =J35/6 -> 35 | AR35: =J35/6 -> 35 | AS35: =J35/6 -> 35 | AT35: =J35/6 -> 35 | AU35: =SUM(AO35:AT35) -> 210 | AV35: =J35-AU35 -> 0 | AX35: =AX34-AO35 -> 43474.833 | AY35: =AY34-AP35 -> 44308.833 | AZ35: =AZ34-AQ35 -> 43934.833 | BA35: =BA34-AR35 -> 45131.833 | BB35: =BB34-AS35 -> 49345.833 | BC35: =BC34-AT35 -> 52650.833
A36: 45820 | B36: NORWEGIAN TOY IMPORT AS - DOM | C36: 挪威 | D36: 4500169836 | E36: 14675 | F36: 4500169836-20 | G36: 92125SLD-S001-3L | H36: 92125SLD-S001 | I36: 一窝猫蛋展示架 | J36: 1008 | K36: 0 | L36: 36 | M36: =J36/L36 -> 28 | N36: 45860 | O36: 45856 | Q36: PASS | R36: 7/30出 | S36: 6/12收到 | U36: 6/19-进口商贴纸 | X36: 日期码格式：ZURU INC(BVI) 标准格式 日期：按实际生产日期 Packaging Info: 92125SLD: MA EAN 3L +1进口商贴纸+MA 展示架 Remark: 1/ 92125 配比：6 Assortments,siamese cat:pink-white cat:purple cat:black cat:brown-white cat:orange cat=1:1:1:1:1:1, no rare. 2/ 产品和包装要求无硼无香，包装不能含有PVC; 3/ 如有微塑料，必须合规欧洲标准，闪粉也是微塑料的一种，目前仅接受三张方式1.去除，2.用可降解材料，和3. 永久封印在固体。 4/ 带电池出货的产品<(>,<)>电池需要符合欧洲电池新规(EU) 2023-1542. | Y36: Zoe Zhou | Z36: 183.48 | AA36: =Z36*M36 -> 5137.44 | AB36: 95793-7.28 | AC36: 已入 | AE36: =J36 -> 1008 | AG36: =J36 -> 1008 | AI36: =J36 -> 1008 | AK36: =J36/36 -> 28 | AN36: MA布标 | AO36: =J36/6 -> 168 | AP36: =J36/6 -> 168 | AQ36: =J36/6 -> 168 | AR36: =J36/6 -> 168 | AS36: =J36/6 -> 168 | AT36: =J36/6 -> 168 | AU36: =SUM(AO36:AT36) -> 1008 | AV36: =J36-AU36 -> 0 | AX36: =AX35-AO36 -> 43306.833 | AY36: =AY35-AP36 -> 44140.833 | AZ36: =AZ35-AQ36 -> 43766.833 | BA36: =BA35-AR36 -> 44963.833 | BB36: =BB35-AS36 -> 49177.833 | BC36: =BC35-AT36 -> 52482.833
A37: 45797 | B37: CRG | C37: 哥斯达黎加 | D37: 4500167463 | E37: ZU02-2025 | F37: 4500167463-130 | G37: 92125-S001 | H37: 92125-S001 | I37: 一窝猫蛋 | J37: 504 | K37: 0 | L37: 6 | M37: =J37/L37 -> 84 | N37: 45856 | O37: 45852 | P37: 4500167152转单 | Q37: PASS | R37: 8/1出 | S37: 5/22收到 | U37: 6/3-进口商贴纸 | X37: 日期码格式：ZURU INC(BVI) 标准格式 日期：按实际生产日期 Packaging Info: 92125：MA 1L UPC包装+MA多语收藏指南+进口商贴纸+箱唛 Remark: | Y37: Ava Liang | Z37: 4.4 | AA37: =Z37*J37 -> 2217.6 | AC37: 已入 | AD37: =J37 -> 504 | AG37: =J37 -> 504 | AI37: =J37 -> 504 | AN37: MA布标 | AO37: =J37/6 -> 84 | AP37: =J37/6 -> 84 | AQ37: =J37/6 -> 84 | AR37: =J37/6 -> 84 | AS37: =J37/6 -> 84 | AT37: =J37/6 -> 84 | AU37: =SUM(AO37:AT37) -> 504 | AV37: =J37-AU37 -> 0 | AX37: =AX36-AO37 -> 43222.833 | AY37: =AY36-AP37 -> 44056.833 | AZ37: =AZ36-AQ37 -> 43682.833 | BA37: =BA36-AR37 -> 44879.833 | BB37: =BB36-AS37 -> 49093.833 | BC37: =BC36-AT37 -> 52398.833
A38: 45824 | B38: AMAZON CA (VENDOR CENTER) | C38: 加拿大 | D38: 4500170160 | E38: 8DTX81EZ | F38: 4500170160-360 | G38: 92125H-S003-MB-MTS | H38: 92125H-S003-MB | I38: 橘猫邮包盒 | J38: 4 | K38: 0 | L38: 4 | M38: 1 | N38: 45856 | O38: 45852 | P38: 邮包盒图稿同4500160539 | Q38: PASS | R38: 7/24出 | S38: 6/19收到 | U38: 无 | V38: 7/11外箱贴纸 | X38: 日期码格式：ZURU INC(BVI) 标准格式 日期：按实际生产日期 Packaging Info: #92125:MA 3L包装入邮包盒, 邮包盒图稿同订单#4500160539。 92125H:193052086983 Remark: 1. Amazon FOB订单，出口CA。外箱最长边不能超过25" （超过了，case pack只能为1），不符合要求的大货，一律不接受。 2. 外箱正面印ZURU Logo + SSCC LABEL（客供贴纸)，侧面印item#（订单上显示的SKU#) + carton size(以工厂实际尺寸为准，单位: inch) + MADE IN CHINA， 日期使用ZURU 标准版本 SSCC Label 显示的是客人自己的item#，SSCC Label 贴在外箱正面的正中间，贴一面即可，跟单订购，贴纸离外箱距必须至少3cm，每一 张SSCC label 都是唯一且有不同流水及条码的，没有损耗，绝对不可贴错 ，否则贴错或损坏一张会导致全部都错，千万要注意: SSCC 贴纸务必要在正中间(可以覆 盖Logo <(>&<)> 箱唛)，否则会影响到仓库扫描识别。 3. 日期码使用ZURU标准版本。 4. 如果大货有要求入邮包盒，则对应的邮包盒上面要打上日期码。 5. 按照客户PO# 装柜/箱号顺序装柜，跟单会提前给到装柜计划。在大货生产/仓库存放时，请留意该装柜要求，以便装柜时不混乱（避免装错/装漏/找不到货号等 ）。 6. 出口加拿大，包装需要至少2/3L UPC版，无硼版本。 7.邮包盒上要印刷日期码 | Y38: Kelly Shen | Z38: 4.6 | AA38: =Z38*J38 -> 18.4 | AC38: 已入 | AE38: =J38 -> 4 | AG38: =J38 -> 4 | AI38: =J38 -> 4 | AN38: MA布标 | AT38: =J38 -> 4 | AU38: =SUM(AO38:AT38) -> 4 | AV38: =J38-AU38 -> 0 | AX38: =AX37-AO38 -> 43222.833 | AY38: =AY37-AP38 -> 44056.833 | AZ38: =AZ37-AQ38 -> 43682.833 | BA38: =BA37-AR38 -> 44879.833 | BB38: =BB37-AS38 -> 49093.833 | BC38: =BC37-AT38 -> 52394.833
A39: 45824 | B39: AMAZON CA (VENDOR CENTER) | C39: 加拿大 | D39: 4500170160 | E39: 6YWABXMJ | F39: 4500170160-370 | G39: 92125H-S003-MB-MTS | H39: 92125H-S003-MB | I39: 橘猫邮包盒 | J39: 4 | K39: 0 | L39: 4 | M39: 1 | N39: 45856 | O39: 45852 | P39: 邮包盒图稿同4500160539 | Q39: PASS | R39: 7/24出 | S39: 6/19收到 | U39: 无 | V39: 7/11外箱贴纸 | X39: 日期码格式：ZURU INC(BVI) 标准格式 日期：按实际生产日期 Packaging Info: #92125:MA 3L包装入邮包盒, 邮包盒图稿同订单#4500160539。 92125H:193052086983 Remark: 1. Amazon FOB订单，出口CA。外箱最长边不能超过25" （超过了，case pack只能为1），不符合要求的大货，一律不接受。 2. 外箱正面印ZURU Logo + SSCC LABEL（客供贴纸)，侧面印item#（订单上显示的SKU#) + carton size(以工厂实际尺寸为准，单位: inch) + MADE IN CHINA， 日期使用ZURU 标准版本 SSCC Label 显示的是客人自己的item#，SSCC Label 贴在外箱正面的正中间，贴一面即可，跟单订购，贴纸离外箱距必须至少3cm，每一 张SSCC label 都是唯一且有不同流水及条码的，没有损耗，绝对不可贴错 ，否则贴错或损坏一张会导致全部都错，千万要注意: SSCC 贴纸务必要在正中间(可以覆 盖Logo <(>&<)> 箱唛)，否则会影响到仓库扫描识别。 3. 日期码使用ZURU标准版本。 4. 如果大货有要求入邮包盒，则对应的邮包盒上面要打上日期码。 5. 按照客户PO# 装柜/箱号顺序装柜，跟单会提前给到装柜计划。在大货生产/仓库存放时，请留意该装柜要求，以便装柜时不混乱（避免装错/装漏/找不到货号等 ）。 6. 出口加拿大，包装需要至少2/3L UPC版，无硼版本。 7.邮包盒上要印刷日期码 | Y39: Kelly Shen | Z39: 4.6 | AA39: =Z39*J39 -> 18.4 | AC39: 已入 | AE39: =J39 -> 4 | AG39: =J39 -> 4 | AI39: =J39 -> 4 | AN39: MA布标 | AT39: =J39 -> 4 | AU39: =SUM(AO39:AT39) -> 4 | AV39: =J39-AU39 -> 0 | AX39: =AX38-AO39 -> 43222.833 | AY39: =AY38-AP39 -> 44056.833 | AZ39: =AZ38-AQ39 -> 43682.833 | BA39: =BA38-AR39 -> 44879.833 | BB39: =BB38-AS39 -> 49093.833 | BC39: =BC38-AT39 -> 52390.833
A40: 45777 | B40: DISTRIBUIDORA JUGUETRON S.A. DE C.V | C40: 墨西哥 | D40: 4500165447 | E40: 50212501521 | F40: 4500165447-10 | G40: 92125-S001-3L | H40: 92125-S001 | I40: 一窝猫蛋 | J40: 1320 | K40: 0 | L40: 6 | M40: =J40/L40 -> 220 | N40: 45859 | O40: =N40-4 -> 45855 | Q40: PASS | R40: 8/15出 | S40: 6/10收到 | U40: 6/10-UPC贴纸+进口商贴纸+外箱贴纸 | X40: 日期码格式：ZURU INC(BVI) 标准格式 日期：按实际生产日期 Packaging Info: MA 3LEAN包装+UPC贴纸+进口商贴纸+外箱贴纸+箱唛 Remark: 此单有第三方监柜，需要每款多备1套完整物料 | Y40: Ava Liang | Z40: 4.4 | AA40: =J40*Z40 -> 5808 | AC40: 已入 | AE40: =J40 -> 1320 | AG40: =J40 -> 1320 | AI40: =J40 -> 1320 | AN40: MA布标 | AO40: =J40/6 -> 220 | AP40: =J40/6 -> 220 | AQ40: =J40/6 -> 220 | AR40: =J40/6 -> 220 | AS40: =J40/6 -> 220 | AT40: =J40/6 -> 220 | AU40: =SUM(AO40:AT40) -> 1320 | AV40: =J40-AU40 -> 0 | AX40: =AX39-AO40 -> 43002.833 | AY40: =AY39-AP40 -> 43836.833 | AZ40: =AZ39-AQ40 -> 43462.833 | BA40: =BA39-AR40 -> 44659.833 | BB40: =BB39-AS40 -> 48873.833 | BC40: =BC39-AT40 -> 52170.833
A41: 45796 | B41: SUPERMERCADOS INTERNACIONALES H.E.B | C41: 墨西哥 | D41: 4500166920 | E41: MX-530-CH-ZURU25B | F41: 4500166920-40 | G41: 92125-S001-3L | H41: 92125-S001 | I41: 一窝猫蛋 | J41: 504 | K41: 0 | L41: 6 | M41: =J41/L41 -> 84 | N41: 45860 | O41: 45856 | Q41: PASS | R41: 8/4出 | S41: 6/28收到 | U41: 6/20-(进口商贴跟UPC贴纸合并一张） | X41: 日期码格式：ZURU INC(BVI) 标准格式 日期：按实际生产日期 Packaging Info: 92125: MA 3L EAN包装+进口商贴纸(进口商贴跟UPC贴纸合并一张）+箱唛 Remark: 1. 此单有第三方监柜，多备一套样品随货送出 5. 92125: 6 Assortments,siamese cat:pink-white cat:purple cat:black cat:brown-white cat:orange cat=1:1:1:1:1:1, no rare. | Y41: Ever Li | Z41: 4.4 | AA41: =J41*Z41 -> 2217.6 | AB41: 95841-7.31 | AC41: 已入 | AE41: =J41 -> 504 | AG41: =J41 -> 504 | AI41: =J41 -> 504 | AN41: MA布标 | AO41: =J41/6 -> 84 | AP41: =J41/6 -> 84 | AQ41: =J41/6 -> 84 | AR41: =J41/6 -> 84 | AS41: =J41/6 -> 84 | AT41: =J41/6 -> 84 | AU41: =SUM(AO41:AT41) -> 504 | AV41: =J41-AU41 -> 0 | AX41: =AX40-AO41 -> 42918.833 | AY41: =AY40-AP41 -> 43752.833 | AZ41: =AZ40-AQ41 -> 43378.833 | BA41: =BA40-AR41 -> 44575.833 | BB41: =BB40-AS41 -> 48789.833 | BC41: =BC40-AT41 -> 52086.833
A42: 45820 | B42: COMERCIALIZADORA MEXICO AMERICANA S | C42: 墨西哥 | D42: 4500169691 | E42: 5251217447 | F42: 4500169691-120 | G42: 92125-S001-3L | H42: 92125-S001 | I42: 一窝猫蛋(干燥剂） | J42: 60 | K42: 0 | L42: 6 | M42: =J42/L42 -> 10 | N42: 45870 | O42: =N42-4 -> 45866 | Q42: PASS | R42: 8/2出 | S42: 6/25收到 | U42: 进口商贴纸翻单4500169797 | W42: 例如(LOTDG20240920) | X42: 日期码格式：LOTDGYYYYMMDD 日期：按实际生产日期 Packaging Info: 92125: 3L EAN收缩膜+UPC 贴纸+ MA5L收藏指南+进口商贴纸+箱唛，进口商贴纸要贴在收缩膜上，贴纸全部翻单4500169797 Remark: 1. 客版日期码要求：LOT+ZURU标准日期码格式。东莞生产的格式：LOTDGYYYYMMDD, DG是东莞拼音首字母，YYYYMMDD是实际的年月日，例如(LOTDG20240920) 2. 92125 ：6 Assortments,siamese cat:pink-white cat:purple cat:black cat:brown-white cat:orange cat=1:1:1:1:1:1, no rare. 3.此单有第三方监柜，至少多备一套完整的物料用于监柜，请多备料。 4. WM墨西哥防霉的新要求:货物必须在出货主箱和集装箱中按要求放置干燥剂，干燥剂指定品牌干霸 92125每箱放置14小包干燥剂，每包干燥剂重量2g 如走柜货等loading plan 确认后再通知集装箱干燥剂数量 此单工厂将与其他单合并安排1*40HQ，每个HQ需要放置10包干燥剂，每包干燥剂1KG； | Y42: Ever Li | Z42: 4.4 | AA42: =J42*Z42 -> 264 | AC42: 已入 | AE42: =J42 -> 60 | AG42: =J42 -> 60 | AI42: =J42 -> 60 | AN42: MA布标 | AO42: =J42/6 -> 10 | AP42: =J42/6 -> 10 | AQ42: =J42/6 -> 10 | AR42: =J42/6 -> 10 | AS42: =J42/6 -> 10 | AT42: =J42/6 -> 10 | AU42: =SUM(AO42:AT42) -> 60 | AV42: =J42-AU42 -> 0 | AX42: =AX41-AO42 -> 42908.833 | AY42: =AY41-AP42 -> 43742.833 | AZ42: =AZ41-AQ42 -> 43368.833 | BA42: =BA41-AR42 -> 44565.833 | BB42: =BB41-AS42 -> 48779.833 | BC42: =BC41-AT42 -> 52076.833
