Workbook

Sheet 鴨子、鱷魚、金魚排期
A1: ZURU 游水动物生产排期表
A2: 44982 | AH2: 訂單數量 | AK2: 說明書 | AN2: MA A版本彩盒2000set | AQ2: MA B版本彩盒 | AT2: MA C/D版本彩盒 | AW2: MA E版本彩盒 | AZ2: 客版包装 | BA2: 客版包装
A3: 香港接单日期 | B3: 第三方客户名称 | C3: 走货国家 | D3: ZURU PO NO# | E3: 第三方客户 PO NO# | F3: SUK号 | G3: 系统货号 | H3: ITEM# | I3: 中文名 | J3: PO数量 (pcs) | K3: 外箱装箱数量(pcs) | L3: 外箱装箱数量(pcs) | M3: 总箱数 | N3: 计划出货期 | O3: 计划验货期 | P3: 第三方客户公证行验货 | Q3: 驗貨結果 | R3: ZURU确认走货日期 | S3: 箱唛资料(收到日期) | T3: 外箱贴纸 | U3: 客供贴纸AI(收到日期) | V3: 包装 | W3: 备注 | X3: ZURU 跟单 | Y3: 单价USD | Z3: 金额USD | AA3: 發票號 | AB3: 送货情况 | AC3: 欠数 | AD3: 贴纸 | AE3: 是否入系统 | AF3: 系统出单 | AG3: 纸箱 | AH3: #25251鴨子 | AI3: #25252鱷魚 | AJ3: #25253金魚 | AK3: MA说明书 | AL3: MA说明书D版本 | AM3: 客版說明書 | AN3: #25251鴨子 | AO3: #25252鱷魚 | AP3: #25253金魚 | AQ3: #25251鴨子 | AR3: #25252鱷魚 | AS3: #25253金魚 | AT3: #25251鴨子 | AU3: #25252鱷魚 | AV3: #25253金魚 | AW3: #25251鴨子 | AX3: #25252鱷魚 | AY3: #25253金魚 | BA3: #25251鴨子 | BB3: #25252鱷魚 | BC3: #25253金魚 | BD3: 总数 | BE3: 相差
A4: 45625 | B4: ZURU | C4: 库有 | D4: ZMPO24898 | G4: 25251-S001 | H4: 25251-S001 | I4: 鸭子 | J4: 96 | K4: 0 | L4: 12 | M4: =J4/L4 -> 8 | N4: 45642 | O4: 45638 | Q4: Pass | S4: 周转箱 | U4: 无 | V4: 大货最新版本 | W4: Remark:大货最新版本/请用大货标准箱装箱/箱唛请参照邮件附件 备注：收到样品订单后尽快安排 ，注意样板品质质量要求要高于大货品质要求 ，送货时必须要附带送货单(没有送货单和QC检验合格报告的仓库一律拒绝收货)，请知悉，谢谢！ | X4: Angus | AA4: 94395-2.27 | AB4: 96 | AC4: =AB4-J4 -> 0 | AD4: 无 | AE4: 已入 | AF4: 系统出单 | AH4: =J4 -> 96 | AL4: =J4 -> 96 | AW4: =J4 -> 96 | BD4: =SUM(AH4:AJ4) -> 96 | BE4: =BD4-J4 -> 0
A5: 45625 | B5: ZURU | C5: 库有 | D5: ZMPO24898 | G5: 25252-S001 | H5: 25252-S001 | I5: 鱷魚 | J5: 96 | K5: 0 | L5: 12 | M5: =J5/L5 -> 8 | N5: 45642 | O5: 45638 | Q5: Pass | S5: 周转箱 | U5: 无 | V5: 大货最新版本 | W5: Remark:大货最新版本/请用大货标准箱装箱/箱唛请参照邮件附件 备注：收到样品订单后尽快安排 ，注意样板品质质量要求要高于大货品质要求 ，送货时必须要附带送货单(没有送货单和QC检验合格报告的仓库一律拒绝收货)，请知悉，谢谢！ | X5: Angus | AA5: 94395-2.27 | AB5: 96 | AC5: =AB5-J5 -> 0 | AD5: 无 | AE5: 已入 | AF5: 系统出单 | AI5: =J5 -> 96 | AL5: =J5 -> 96 | AX5: =J5 -> 96 | BD5: =SUM(AH5:AJ5) -> 96 | BE5: =BD5-J5 -> 0
A6: 45625 | B6: ZURU | C6: 库有 | D6: ZMPO24898 | G6: 25253-S001 | H6: 25253-S001 | I6: 金魚 | J6: 96 | K6: 0 | L6: 12 | M6: =J6/L6 -> 8 | N6: 45642 | O6: 45638 | Q6: Pass | S6: 周转箱 | U6: 无 | V6: 大货最新版本 | W6: Remark:大货最新版本/请用大货标准箱装箱/箱唛请参照邮件附件 备注：收到样品订单后尽快安排 ，注意样板品质质量要求要高于大货品质要求 ，送货时必须要附带送货单(没有送货单和QC检验合格报告的仓库一律拒绝收货)，请知悉，谢谢！ | X6: Angus | AA6: 94395-2.27 | AB6: 96 | AC6: =AB6-J6 -> 0 | AD6: 无 | AE6: 已入 | AF6: 系统出单 | AJ6: =J6 -> 96 | AL6: =J6 -> 96 | AY6: =J6 -> 96 | BD6: =SUM(AH6:AJ6) -> 96 | BE6: =BD6-J6 -> 0
A7: 45575 | B7: CARREFOUR CORA | C7: 法国 | D7: 4500147031 | E7: 48STY25CORA0091 | F7: 4500147031-10 | G7: 25251-S001-6 | H7: 25251-S001 | I7: 鸭子 | J7: 240 | K7: 0 | L7: 12 | M7: =J7/L7 -> 20 | N7: 45643 | O7: 45639 | P7: PET吸塑 | Q7: Pass | R7: 1/3出 | S7: 空白纸箱+双坑纸箱 | T7: 45616 | U7: EAN条码贴纸翻4500144921 | V7: 25251: MA E_1L-23L彩卡+客版说明书(EN/FR/RO), -翻PO#4500144921 | W7: 日期码格式：ZURU INC(BVI) 标准格式 日期：按实际生产日期 Packaging Info: 25251: MA E_1L-23L彩卡+EAN条码贴纸+法国环保logo+客版说明书(EN/FR/RO), -翻PO#4500144921 Remark: 1.大货样品2套，请多备料。 2. 出口欧洲，所有产品微塑料需符合法规。 3. 产品、包装、外箱日期码需一致。 4. 空白纸箱: 在正唛（只1面）加多虚线15 x 10.5 cm ( 高x 宽) 距箱左边2cm， 距箱底 3cm，虚线内1张外箱贴纸（在checkpoint网站上订）Custeomer Service: Erica Lun Tel.+852 2995 8399/erica.lun@checkpt.com 5. 所有包装材料禁止使用PVC，需改用PET材料。 6. 要求使用双坑纸箱，外箱尺寸超出7%有350USD的罚款，请注意外箱尺寸变更不能超出7%。 7. 客人系统外箱尺寸: 25251: 42*39.5*45.5CM | X7: Ula Zhao | Y7: 3.9118 | Z7: =Y7*J7 -> 938.832 | AA7: 88833-1.2 | AB7: 240 | AC7: =AB7-J7 -> 0 | AD7: ok | AE7: 已入 | AF7: 系统出单 | AH7: =J7 -> 240 | AM7: =J7 -> 240 | AW7: =J7 -> 240 | BD7: =SUM(AH7:AJ7) -> 240 | BE7: =BD7-J7 -> 0
A8: 45575 | B8: CARREFOUR CORA | C8: 法国 | D8: 4500147031 | E8: 48STY25CORA0091 | F8: 4500147031-20 | G8: 25252-S001-3 | H8: 25252-S001 | I8: 鱷魚 | J8: 240 | K8: 0 | L8: 12 | M8: =J8/L8 -> 20 | N8: 45643 | O8: 45639 | P8: PET吸塑 | Q8: Pass | R8: 1/3出 | S8: 空白纸箱+双坑纸箱 | T8: 45616 | U8: EAN条码贴纸翻4500144921 | V8: 25252: MA E_1L-23L彩卡+客版说明书(EN/FR/RO), -翻PO#4500144921 | W8: 日期码格式：ZURU INC(BVI) 标准格式 日期：按实际生产日期 Packaging Info: 25252: MA E_1L-23L彩卡+EAN条码贴纸+法国环保logo+客版说明书(EN/FR/RO), -翻PO#4500144921 Remark: 1.大货样品2套，请多备料。 2. 出口欧洲，所有产品微塑料需符合法规。 3. 产品、包装、外箱日期码需一致。 4. 空白纸箱: 在正唛（只1面）加多虚线15 x 10.5 cm ( 高x 宽) 距箱左边2cm， 距箱底 3cm，虚线内1张外箱贴纸（在checkpoint网站上订）Custeomer Service: Erica Lun Tel.+852 2995 8399/erica.lun@checkpt.com 5. 所有包装材料禁止使用PVC，需改用PET材料。 6. 要求使用双坑纸箱，外箱尺寸超出7%有350USD的罚款，请注意外箱尺寸变更不能超出7%。 7. 客人系统外箱尺寸: 25252: 42*39.5*45.5CM | X8: Ula Zhao | Y8: 4.0344 | Z8: =Y8*J8 -> 968.256 | AA8: 88833-1.2 | AB8: 240 | AC8: =AB8-J8 -> 0 | AD8: ok | AE8: 已入 | AF8: 系统出单 | AI8: =J8 -> 240 | AM8: =J8 -> 240 | AX8: =J8 -> 240 | BD8: =SUM(AH8:AJ8) -> 240 | BE8: =BD8-J8 -> 0
A9: 45575 | B9: CARREFOUR CORA | C9: 法国 | D9: 4500147031 | E9: 48STY25CORA0091 | F9: 4500147031-30 | G9: 25253-S001-3 | H9: 25253-S001 | I9: 金魚 | J9: 240 | K9: 0 | L9: 12 | M9: =J9/L9 -> 20 | N9: 45643 | O9: 45639 | P9: PET吸塑 | Q9: Pass | R9: 1/3出 | S9: 空白纸箱+双坑纸箱 | T9: 45616 | U9: EAN条码贴纸翻4500144921 | V9: 25253: MA E_1L-23L彩卡+客版说明书(EN/FR/RO), -翻PO#4500144921 | W9: 日期码格式：ZURU INC(BVI) 标准格式 日期：按实际生产日期 Packaging Info: 25253: MA E_1L-23L彩卡+EAN条码贴纸+法国环保logo+客版说明书(EN/FR/RO), 翻PO#4500144921 Remark: 1.大货样品2套，请多备料。 2. 出口欧洲，所有产品微塑料需符合法规。 3. 产品、包装、外箱日期码需一致。 4. 空白纸箱: 在正唛（只1面）加多虚线15 x 10.5 cm ( 高x 宽) 距箱左边2cm， 距箱底 3cm，虚线内1张外箱贴纸（在checkpoint网站上订）Custeomer Service: Erica Lun Tel.+852 2995 8399/erica.lun@checkpt.com 5. 所有包装材料禁止使用PVC，需改用PET材料。 6. 要求使用双坑纸箱，外箱尺寸超出7%有350USD的罚款，请注意外箱尺寸变更不能超出7%。 7. 客人系统外箱尺寸: 25253: 42*39.5*45.5CM | X9: Ula Zhao | Y9: 3.7168 | Z9: =Y9*J9 -> 892.032 | AA9: 88833-1.2 | AB9: 240 | AC9: =AB9-J9 -> 0 | AD9: ok | AE9: 已入 | AF9: 系统出单 | AJ9: =J9 -> 240 | AM9: =J9 -> 240 | AY9: =J9 -> 240 | BD9: =SUM(AH9:AJ9) -> 240 | BE9: =BD9-J9 -> 0
A10: 45590 | B10: WAL-MART STORES INC. USA | C10: 美国 | D10: 4500148810 | E10: 0870169770 | F10: 4500148810-10 | G10: 25251-S002 | H10: 25251-S002 | I10: 鸭子 | J10: 3740 | K10: 0 | L10: 2 | M10: =J10/L10 -> 1870 | N10: 45646 | O10: 45642 | P10: 12/20 BV（自检） | Q10: Pass | R10: 1/6出 | S10: 外箱四面印刷RFID箱唛 + 顶部ZURU logo黑色色带。主唛右下角加印 MADE IN CHINA | U10: 11/29-RFID贴纸 | V10: 最新扶正ZURU LOGO客版彩盒 | W10: 日期码格式：DGYYYYMMDD(日期避开周末和法定节假日) 日期：按实际生产日期 Packaging Info: 翻单：4500147361 1.包装方式： 25251：最新扶正ZURU LOGO客版彩盒（客版UPC）1L+23L警告语 + MA D版1L说明书 Remark: 2. 外箱四面印刷青色RFID箱唛 + 顶部ZURU logo黑色色带。 主唛左前下角印刷艾利贴纸替代标箱唛(ITF-14格式)，条码只印刷一面。 主唛右下角加印 MADE IN CHINA 3. WM#25251 NEW UPC：193052056092 4. Include 3pcs AAA carbon batteries; 5.此单需要验货，请自行多备包装物料。 6.在产品上和包装上要有日期码、MADE IN CHINA和ZURU字样。 7.此批单都为散箱出货 8.每PCS要加RFID 贴纸，严格按照我们提供的位置图，不可擅自调整位置，贴纸也不可有任何破损或折坏，不可淋湿!!（如缺数请及时告知） | X10: Nikki Mo | Y10: 3.514 | Z10: =Y10*J10 -> 13142.36 | AA10: 88868-1.4 | AB10: 3740 | AC10: =AB10-J10 -> 0 | AD10: ok | AE10: 已入 | AF10: 系统出单 | AH10: =J10 -> 3740 | AL10: =J10 -> 3740 | BA10: =J10 -> 3740 | BD10: =SUM(AH10:AJ10) -> 3740 | BE10: =BD10-J10 -> 0
A11: 45590 | B11: WAL-MART STORES INC. USA | C11: 美国 | D11: 4500148811 | E11: 0870169797 | F11: 4500148811-10 | G11: 25251-S002 | H11: 25251-S002 | I11: 鸭子 | J11: 4108 | K11: 0 | L11: 2 | M11: =J11/L11 -> 2054 | N11: 45646 | O11: 45642 | P11: 12/20 BV（自检） | Q11: Pass | R11: 1/21出 | S11: 外箱四面印刷RFID箱唛 + 顶部ZURU logo黑色色带。主唛右下角加印 MADE IN CHINA | U11: 11/29-RFID贴纸 | V11: 最新扶正ZURU LOGO客版彩盒 | W11: 日期码格式：DGYYYYMMDD(日期避开周末和法定节假日) 日期：按实际生产日期 Packaging Info: 翻单：4500147361 1.包装方式： 25251：最新扶正ZURU LOGO客版彩盒（客版UPC）1L+23L警告语 + MA D版1L说明书 Remark: 2. 外箱四面印刷青色RFID箱唛 + 顶部ZURU logo黑色色带。 主唛左前下角印刷艾利贴纸替代标箱唛(ITF-14格式)，条码只印刷一面。 主唛右下角加印 MADE IN CHINA 3. WM#25251 NEW UPC：193052056092 4. Include 3pcs AAA carbon batteries; 5.此单需要验货，请自行多备包装物料。 6.在产品上和包装上要有日期码、MADE IN CHINA和ZURU字样。 7.此批单都为散箱出货 8.每PCS要加RFID 贴纸，严格按照我们提供的位置图，不可擅自调整位置，贴纸也不可有任何破损或折坏，不可淋湿!!（如缺数请及时告知） | X11: Nikki Mo | Y11: 3.514 | Z11: =Y11*J11 -> 14435.512 | AA11: 94185-2.8 | AB11: 4108 | AC11: =AB11-J11 -> 0 | AD11: ok | AE11: 已入 | AF11: 系统出单 | AH11: =J11 -> 4108 | AL11: =J11 -> 4108 | BA11: =J11 -> 4108 | BD11: =SUM(AH11:AJ11) -> 4108 | BE11: =BD11-J11 -> 0
A12: 45590 | B12: WAL-MART STORES INC. USA | C12: 美国 | D12: 4500148812 | E12: 0870169800 | F12: 4500148812-10 | G12: 25251-S002 | H12: 25251-S002 | I12: 鸭子 | J12: 2922 | K12: 0 | L12: 2 | M12: =J12/L12 -> 1461 | N12: 45646 | O12: 45642 | P12: 12/20 BV（自检） | Q12: Pass | R12: 1/14出 | S12: 外箱四面印刷RFID箱唛 + 顶部ZURU logo黑色色带。主唛右下角加印 MADE IN CHINA | U12: 11/29-RFID贴纸 | V12: 最新扶正ZURU LOGO客版彩盒 | W12: 日期码格式：DGYYYYMMDD(日期避开周末和法定节假日) 日期：按实际生产日期 Packaging Info: 翻单：4500147361 1.包装方式： 25251：最新扶正ZURU LOGO客版彩盒（客版UPC）1L+23L警告语 + MA D版1L说明书 Remark: 2. 外箱四面印刷青色RFID箱唛 + 顶部ZURU logo黑色色带。 主唛左前下角印刷艾利贴纸替代标箱唛(ITF-14格式)，条码只印刷一面。 主唛右下角加印 MADE IN CHINA 3. WM#25251 NEW UPC：193052056092 4. Include 3pcs AAA carbon batteries; 5.此单需要验货，请自行多备包装物料。 6.在产品上和包装上要有日期码、MADE IN CHINA和ZURU字样。 7.此批单都为散箱出货 8.每PCS要加RFID 贴纸，严格按照我们提供的位置图，不可擅自调整位置，贴纸也不可有任何破损或折坏，不可淋湿!!（如缺数请及时告知） | X12: Nikki Mo | Y12: 3.5075 | Z12: =Y12*J12 -> 10248.915 | AA12: 94041-1.15 | AB12: =1422+1500 -> 2922 | AC12: =AB12-J12 -> 0 | AD12: ok | AE12: 已入 | AF12: 系统出单 | AH12: =J12 -> 2922 | AL12: =J12 -> 2922 | BA12: =J12 -> 2922 | BD12: =SUM(AH12:AJ12) -> 2922 | BE12: =BD12-J12 -> 0
A13: 45602 | B13: DM LLC | C13: 俄罗斯联邦 | D13: 4500150264 | E13: 出Bekasovo 2 | F13: 4500150264-10 | G13: 25252-S001 | H13: 25252-S001 | I13: 鱷魚 | J13: 756 | K13: 0 | L13: 12 | M13: =J13/L13 -> 63 | N13: 45652 | O13: 45649 | Q13: Pass | R13: 12/28出 | S13: 11/14收到 | U13: 11/22收到进口商贴纸+ EAN条码贴纸 | V13: 日期码格式：外包装/外箱不要打ZURU标准日期码 | W13: 日期码格式：外包装/外箱不要打ZURU标准日期码 日期： Packaging Info: 注意 ：外包装 (指: 收缩膜/彩卡/铝箔袋/挂卡/PDQ) /外箱不要打ZURU标准日期码！胶件可以打日期码 . 25252 ： MA 彩卡+ 进口商贴纸+ EAN条码贴纸， MA 说明书 ： Remark: 标准配比 ； 请按期完货， 会有罚金。 出港口Bekasovo 2. | X13: Ann Zhang | Y13: 4.0344 | Z13: =Y13*J13 -> 3050.0064 | AA13: 94035-1.15 | AB13: 756 | AC13: =AB13-J13 -> 0 | AD13: ok | AE13: 已入 | AF13: 系统出单 | AI13: =J13 -> 756 | AL13: =J13 -> 756 | AX13: =J13 -> 756 | BD13: =SUM(AH13:AJ13) -> 756 | BE13: =BD13-J13 -> 0
A14: 45596 | B14: Smyths Toys HQ UC UK | C14: 英国 | D14: 4500149773 | E14: 4400444865 | F14: 4500149773-10 | G14: 25251-S001-5 | H14: 25251-S001 | I14: 鸭子 | J14: 3000 | K14: 0 | L14: 12 | M14: =J14/L14 -> 250 | N14: 45653 | O14: 45649 | Q14: Pass | R14: 1/15出 | S14: 11/25收到 | U14: 德语<(>&<)>法语callout贴纸和位置图翻4500138425 | V14: 客版说明书都翻PO#4500138425 | W14: 日期码格式：ZURU INC(BVI) 标准格式 日期：按实际生产日期 Packaging Info: 1.25251: MA 1L-23L Warning+德语<(>&<)>法语callout贴纸+客版说明书（英法德意荷语言) 贴纸和位置图/客版说明书都翻PO#4500138425 Remark: 1）包装日期码按ZURU格式即可，请确保不迟于外箱日期码，可等于或者早于外箱日期码，必须为法定工作日，印刷前请先检查外箱日期码。 2）订单出英国，请注意检查产品及包装应带UKCA图标（14+产品除外），包装显示ZURU UK LTD/ZURU France地址信息，QC部门请查核，如有问题与跟单确认 3）订单必须经过ZURU QC验货并且通过后方可出货 4) 需要符合欧洲标准不能含有闪粉和微塑料，否则不和法规会有客诉产生 | X14: Amy Ding | Y14: 3.4606 | Z14: =Y14*J14 -> 10381.8 | AA14: 88975-1.10 | AB14: =2208+792 -> 3000 | AC14: =AB14-J14 -> 0 | AD14: ok | AE14: 已入 | AF14: 系统出单 | AH14: =J14 -> 3000 | AM14: =J14 -> 3000 | AW14: =J14 -> 3000 | BD14: =SUM(AH14:AJ14) -> 3000 | BE14: =BD14-J14 -> 0
A15: 45623 | B15: TJX COMPANIES, INC | C15: 美国 | D15: 4500152570 | E15: Marshalls DC#881-168PCS , DC#884-132PCS , DC#886-180PCS , DC#887-156PCS , DC#888-168PCS | F15: 4500152570-20 | G15: 25251-S001 | H15: 25251-S001 | I15: 鸭子 | J15: 804 | K15: 0 | L15: 12 | M15: =J15/L15 -> 67 | N15: 45651 | O15: 45647 | Q15: Pass | S15: 45623 | U15: 12/6-客供价格贴纸 | V15: MA UPC包装 | W15: 日期码格式：ZURU INC(BVI) 标准格式 日期：按实际生产日期 Packaging Info: MA UPC包装+价格贴纸，价格贴纸客供。 Remark: 1. 产品和包装上印刷tracking code信息，格式为ZURU常规格式。 2. 分5个DC出货，每款产品每个DC的箱唛资料不同。具体分DC数量，请参考后面行项目备注。 3. ZURU QC验货。 Order | X15: Emily Wu | Y15: 3.9118 | Z15: =Y15*J15 -> 3145.0872 | AA15: 94168-1.23 | AB15: 804 | AC15: =AB15-J15 -> 0 | AD15: ok | AE15: 已入 | AF15: 系统出单 | AH15: =J15 -> 804 | AL15: =J15 -> 804 | AW15: =J15 -> 804 | BD15: =SUM(AH15:AJ15) -> 804 | BE15: =BD15-J15 -> 0
A16: 45590 | B16: WAL-MART STORES INC. USA | C16: 美国 | D16: 4500148814 | E16: 0870169764 | F16: 4500148814-10 | G16: 25251-S002 | H16: 25251-S002 | I16: 鸭子 | J16: 2888 | K16: 0 | L16: 2 | M16: =J16/L16 -> 1444 | N16: 45653 | O16: 45649 | P16: 12/27 BV（自检） | Q16: Pass | R16: 1/14出 | S16: 外箱四面印刷RFID箱唛 + 顶部ZURU logo黑色色带。主唛右下角加印 MADE IN CHINA | U16: 12/10-RFID贴纸 | V16: 最新扶正ZURU LOGO客版彩盒 | W16: 日期码格式：DGYYYYMMDD(日期避开周末和法定节假日) 日期：按实际生产日期 Packaging Info: 翻单：4500147361 1.包装方式： 25251：最新扶正ZURU LOGO客版彩盒（客版UPC）1L+23L警告语 + MA D版1L说明书 Remark: 2. 外箱四面印刷青色RFID箱唛 + 顶部ZURU logo黑色色带。 主唛左前下角印刷艾利贴纸替代标箱唛(ITF-14格式)，条码只印刷一面。 主唛右下角加印 MADE IN CHINA 3. WM#25251 NEW UPC：193052056092 4. Include 3pcs AAA carbon batteries; 5.此单需要验货，请自行多备包装物料。 6.在产品上和包装上要有日期码、MADE IN CHINA和ZURU字样。 7.此批单都为散箱出货 8.每PCS要加RFID 贴纸，严格按照我们提供的位置图，不可擅自调整位置，贴纸也不可有任何破损或折坏，不可淋湿!!（如缺数请及时告知） | X16: Nikki Mo | Y16: 3.6259 | Z16: =Y16*J16 -> 10471.599 | AA16: 94028-1.14 | AB16: 2888 | AC16: =AB16-J16 -> 0 | AD16: ok | AE16: 已入 | AF16: 系统出单 | AH16: =J16 -> 2888 | AL16: =J16 -> 2888 | BA16: =J16 -> 2888 | BD16: =SUM(AH16:AJ16) -> 2888 | BE16: =BD16-J16 -> 0
A17: 45623 | B17: TJX COMPANIES, INC | C17: 美国 | D17: 4500152572 | E17: Marshalls DC#881-216PCS , DC#884-156PCS , DC#886-228PCS , DC#887-192PCS , DC#888-204PCS | F17: 4500152572-10 | G17: 25251-S001 | H17: 25251-S001 | I17: 鸭子 | J17: 996 | K17: 0 | L17: 12 | M17: =J17/L17 -> 83 | N17: 45657 | O17: 45653 | Q17: Pass | R17: 1/8出 | S17: 45623 | U17: 12/6-客供价格贴纸 | V17: MA UPC包装 | W17: 日期码格式：ZURU INC(BVI) 标准格式 日期：按实际生产日期 Packaging Info: MA UPC包装+价格贴纸，价格贴纸客供。 Remark: 1. 产品和包装上印刷tracking code信息，格式为ZURU常规格式。 2. 分5个DC出货，每款产品每个DC的箱唛资料不同。具体分DC数量，请参考后面行项目备注。 3. ZURU QC验货。 | X17: Emily Wu | Y17: 3.8242 | Z17: =Y17*J17 -> 3808.9032 | AA17: 94165-1.23 | AB17: 996 | AC17: =AB17-J17 -> 0 | AD17: ok | AE17: 已入 | AF17: 系统出单 | AH17: =J17 -> 996 | AL17: =J17 -> 996 | AW17: =J17 -> 996 | BD17: =SUM(AH17:AJ17) -> 996 | BE17: =BD17-J17 -> 0
A18: 45623 | B18: TJX COMPANIES, INC | C18: 美国 | D18: 4500152573 | E18: TJ MAXX DC#891-240PCS , DC#894-204PCS , DC#896-192PCS , DC#897-372PCS , DC#898-192PCS | F18: 4500152573-10 | G18: 25251-S001 | H18: 25251-S001 | I18: 鸭子 | J18: 1200 | K18: 0 | L18: 12 | M18: =J18/L18 -> 100 | N18: 45657 | O18: 45653 | Q18: Pass | R18: 1/8出 | S18: 45623 | U18: 12/6-客供价格贴纸 | V18: MA UPC包装 | W18: 日期码格式：ZURU INC(BVI) 标准格式 日期：按实际生产日期 Packaging Info: MA UPC包装+价格贴纸，价格贴纸客供。 Remark: 1. 产品和包装上印刷tracking code信息，格式为ZURU常规格式。 2. 分5个DC出货，每款产品每个DC的箱唛资料不同。具体分DC数量，请参考后面行项目备注。 3. ZURU QC验货。 | X18: Emily Wu | Y18: 3.4616 | Z18: =Y18*J18 -> 4153.92 | AA18: 94173-1.23 | AB18: 1200 | AC18: =AB18-J18 -> 0 | AD18: ok | AE18: 已入 | AF18: 系统出单 | AH18: =J18 -> 1200 | AL18: =J18 -> 1200 | AW18: =J18 -> 1200 | BD18: =SUM(AH18:AJ18) -> 1200 | BE18: =BD18-J18 -> 0
A19: 45623 | B19: TJX COMPANIES, INC | C19: 美国 | D19: 4500152575 | E19: TJ MAXX DC#891-240PCS , DC#894-204PCS , DC#896-192PCS , DC#897-372PCS , DC#898-192PCS | F19: 4500152575-20 | G19: 25251-S001 | H19: 25251-S001 | I19: 鸭子 | J19: 1200 | K19: 0 | L19: 12 | M19: =J19/L19 -> 100 | N19: 45657 | O19: 45653 | Q19: Pass | R19: 1/8出 | S19: 45623 | U19: 12/6-客供价格贴纸 | V19: MA UPC包装 | W19: 日期码格式：ZURU INC(BVI) 标准格式 日期：按实际生产日期 Packaging Info: MA UPC包装+价格贴纸，价格贴纸客供。 Remark: 1. 产品和包装上印刷tracking code信息，格式为ZURU常规格式。 2. 分5个DC出货，每款产品每个DC的箱唛资料不同。具体分DC数量，请参考后面行项目备注。 3. ZURU QC验货。 | X19: Emily Wu | Y19: 3.5492 | Z19: =Y19*J19 -> 4259.04 | AA19: 94172-1.23 | AB19: 1200 | AC19: =AB19-J19 -> 0 | AD19: ok | AE19: 已入 | AF19: 系统出单 | AH19: =J19 -> 1200 | AL19: =J19 -> 1200 | AW19: =J19 -> 1200 | BD19: =SUM(AH19:AJ19) -> 1200 | BE19: =BD19-J19 -> 0
A20: 45623 | B20: TJX COMPANIES, INC | C20: 美国 | D20: 4500152574 | E20: Marshalls DC#881-216PCS , DC#884-156PCS , DC#886-228PCS , DC#887-192PCS , DC#888-204PCS | F20: 4500152574-20 | G20: 25251-S001 | H20: 25251-S001 | I20: 鸭子 | J20: 996 | K20: 0 | L20: 12 | M20: =J20/L20 -> 83 | N20: 45657 | O20: 45653 | Q20: Pass | R20: 1/8出 | S20: 45623 | U20: 12/6-客供价格贴纸 | V20: MA UPC包装 | W20: 日期码格式：ZURU INC(BVI) 标准格式 日期：按实际生产日期 Packaging Info: MA UPC包装+价格贴纸，价格贴纸客供。 Remark: 1. 产品和包装上印刷tracking code信息，格式为ZURU常规格式。 2. 分5个DC出货，每款产品每个DC的箱唛资料不同。具体分DC数量，请参考后面行项目备注。 3. ZURU QC验货。 | X20: Emily Wu | Y20: 3.8242 | Z20: =Y20*J20 -> 3808.9032 | AA20: 94167-1.23 | AB20: 996 | AC20: =AB20-J20 -> 0 | AD20: ok | AE20: 已入 | AF20: 系统出单 | AH20: =J20 -> 996 | AL20: =J20 -> 996 | AW20: =J20 -> 996 | BD20: =SUM(AH20:AJ20) -> 996 | BE20: =BD20-J20 -> 0
A21: 45590 | B21: WAL-MART STORES INC. USA | C21: 美国 | D21: 4500149172 | E21: 0870169815 | F21: 4500149172-10 | G21: 25251-S002 | H21: 25251-S002 | I21: 鸭子 | J21: 4712 | K21: 0 | L21: 2 | M21: =J21/L21 -> 2356 | N21: 45659 | O21: 45656 | P21: 1/3 BV（自检） | Q21: Pass | R21: 1/13出 | S21: 外箱四面印刷RFID箱唛 + 顶部ZURU logo黑色色带。主唛右下角加印 MADE IN CHINA | U21: 12/10-RFID贴纸 | V21: 最新扶正ZURU LOGO客版彩盒 | W21: 日期码格式：DGYYYYMMDD(日期避开周末和法定节假日) 日期：按实际生产日期 Packaging Info: 翻单：4500147361 1.包装方式： 25251：最新扶正ZURU LOGO客版彩盒（客版UPC）1L+23L警告语 + MA D版1L说明书 Remark: 2. 外箱四面印刷青色RFID箱唛 + 顶部ZURU logo黑色色带。 主唛左前下角印刷艾利贴纸替代标箱唛(ITF-14格式)，条码只印刷一面。 主唛右下角加印 MADE IN CHINA 3. WM#25251 NEW UPC：193052056092 4. Include 3pcs AAA carbon batteries; 5.此单需要验货，请自行多备包装物料。 6.在产品上和包装上要有日期码、MADE IN CHINA和ZURU字样。 7.此批单都为散箱出货 8.每PCS要加RFID 贴纸，严格按照我们提供的位置图，不可擅自调整位置，贴纸也不可有任何破损或折坏，不可淋湿!!（如缺数请及时告知） | X21: Nikki Mo | Y21: 3.514 | Z21: =Y21*J21 -> 16557.968 | AA21: 94186-2.8 | AB21: 4712 | AC21: =AB21-J21 -> 0 | AD21: ok | AE21: 已入 | AF21: 系统出单 | AH21: =J21 -> 4712 | AL21: =J21 -> 4712 | BA21: =J21 -> 4712 | BD21: =SUM(AH21:AJ21) -> 4712 | BE21: =BD21-J21 -> 0
A22: 45624 | B22: WAL-MART STORES INC. USA | C22: 美国 | D22: 4500152364 | E22: 0869333766 | F22: 4500152364-10 | G22: 25251-S002 | H22: 25251-S002 | I22: 鸭子 | J22: 980 | K22: 0 | L22: 2 | M22: =J22/L22 -> 490 | N22: 45659 | O22: 45656 | P22: 1/3 BV（自检） | Q22: Pass | R22: 1/16出 | S22: 外箱四面印刷RFID箱唛 + 顶部ZURU logo黑色色带。主唛右下角加印 MADE IN CHINA | U22: 12/10-RFID贴纸 | V22: 最新扶正ZURU LOGO客版彩盒 | W22: 日期码格式：DGYYYYMMDD(日期避开周末和法定节假日) 日期：按实际生产日期 Packaging Info: 翻单：4500147361 1.包装方式： 25251：最新扶正ZURU LOGO客版彩盒（客版UPC）1L+23L警告语 + MA D版1L说明书 Remark: 2. 外箱四面印刷青色RFID箱唛 + 顶部ZURU logo黑色色带 主唛左前下角印刷艾利贴纸替代标箱唛(ITF-14格式)，条码只印刷一面 主唛右下角加印 MADE IN CHINA，对角线位置加贴一张粉色MOD艾利贴纸（工厂自行打印或订购） 3. WM#25251 NEW UPC：193052056092 4. Include 3pcs AAA carbon batteries; 5.此单需要验货，请自行多备包装物料。 6.在产品上和包装上要有日期码、MADE IN CHINA和ZURU字样。 7.此批单都为散箱出货 8.每PCS要加RFID 贴纸，严格按照我们提供的位置图，不可擅自调整位置，贴纸也不可有任何破损或折坏，不可淋湿!!（如缺数请及时告知） | X22: Nikki Mo | Y22: 4.0771 | Z22: =Y22*J22 -> 3995.558 | AA22: 94073-1.17 | AB22: 980 | AC22: =AB22-J22 -> 0 | AD22: ok | AE22: 已入 | AF22: 系统出单 | AH22: =J22 -> 980 | AL22: =J22 -> 980 | BA22: =J22 -> 980 | BD22: =SUM(AH22:AJ22) -> 980 | BE22: =BD22-J22 -> 0
A23: 45624 | B23: WAL-MART STORES INC. USA | C23: 美国 | D23: 4500152363 | E23: 0869333777 | F23: 4500152363-10 | G23: 25251-S002 | H23: 25251-S002 | I23: 鸭子 | J23: 1182 | K23: 0 | L23: 2 | M23: =J23/L23 -> 591 | N23: 45659 | O23: 45656 | P23: 1/3 BV（自检） | Q23: Pass | R23: 1/18出 | S23: 外箱四面印刷RFID箱唛 + 顶部ZURU logo黑色色带。主唛右下角加印 MADE IN CHINA | U23: 12/10-RFID贴纸 | V23: 最新扶正ZURU LOGO客版彩盒 | W23: 日期码格式：DGYYYYMMDD(日期避开周末和法定节假日) 日期：按实际生产日期 Packaging Info: 翻单：4500147361 1.包装方式： 25251：最新扶正ZURU LOGO客版彩盒（客版UPC）1L+23L警告语 + MA D版1L说明书 Remark: 2. 外箱四面印刷青色RFID箱唛 + 顶部ZURU logo黑色色带 主唛左前下角印刷艾利贴纸替代标箱唛(ITF-14格式)，条码只印刷一面 主唛右下角加印 MADE IN CHINA，对角线位置加贴一张粉色MOD艾利贴纸（工厂自行打印或订购） 3. WM#25251 NEW UPC：193052056092 4. Include 3pcs AAA carbon batteries; 5.此单需要验货，请自行多备包装物料。 6.在产品上和包装上要有日期码、MADE IN CHINA和ZURU字样。 7.此批单都为散箱出货 8.每PCS要加RFID 贴纸，严格按照我们提供的位置图，不可擅自调整位置，贴纸也不可有任何破损或折坏，不可淋湿!!（如缺数请及时告知） | X23: Nikki Mo | Y23: 3.7145 | Z23: =Y23*J23 -> 4390.539 | AA23: 94074-1.17 | AB23: 1182 | AC23: =AB23-J23 -> 0 | AD23: ok | AE23: 已入 | AF23: 系统出单 | AH23: =J23 -> 1182 | AL23: =J23 -> 1182 | BA23: =J23 -> 1182 | BD23: =SUM(AH23:AJ23) -> 1182 | BE23: =BD23-J23 -> 0
A24: 45624 | B24: WAL-MART STORES INC. USA | C24: 美国 | D24: 4500152365 | E24: 0869333761 | F24: 4500152365-10 | G24: 25251-S002 | H24: 25251-S002 | I24: 鸭子 | J24: 1352 | K24: 0 | L24: 2 | M24: =J24/L24 -> 676 | N24: 45659 | O24: 45656 | P24: 1/3 BV（自检） | Q24: Pass | R24: 1/20出 | S24: 外箱四面印刷RFID箱唛 + 顶部ZURU logo黑色色带。主唛右下角加印 MADE IN CHINA | U24: 12/10-RFID贴纸 | V24: 最新扶正ZURU LOGO客版彩盒 | W24: 日期码格式：DGYYYYMMDD(日期避开周末和法定节假日) 日期：按实际生产日期 Packaging Info: 翻单：4500147361 1.包装方式： 25251：最新扶正ZURU LOGO客版彩盒（客版UPC）1L+23L警告语 + MA D版1L说明书 Remark: 2. 外箱四面印刷青色RFID箱唛 + 顶部ZURU logo黑色色带 主唛左前下角印刷艾利贴纸替代标箱唛(ITF-14格式)，条码只印刷一面 主唛右下角加印 MADE IN CHINA，对角线位置加贴一张粉色MOD艾利贴纸（工厂自行打印或订购） 3. WM#25251 NEW UPC：193052056092 4. Include 3pcs AAA carbon batteries; 5.此单需要验货，请自行多备包装物料。 6.在产品上和包装上要有日期码、MADE IN CHINA和ZURU字样。 7.此批单都为散箱出货 8.每PCS要加RFID 贴纸，严格按照我们提供的位置图，不可擅自调整位置，贴纸也不可有任何破损或折坏，不可淋湿!!（如缺数请及时告知） | X24: Nikki Mo | Y24: 3.7145 | Z24: =Y24*J24 -> 5022.004 | AA24: 94056-1.16 | AB24: 1352 | AC24: =AB24-J24 -> 0 | AD24: ok | AE24: 已入 | AF24: 系统出单 | AH24: =J24 -> 1352 | AL24: =J24 -> 1352 | BA24: =J24 -> 1352 | BD24: =SUM(AH24:AJ24) -> 1352 | BE24: =BD24-J24 -> 0
A25: 45625 | B25: Smyths Toys HQ UC IE | C25: 爱尔兰 | D25: 4500153056 | E25: 4400452589 | F25: 4500153056-20 | G25: 25253-S001-7 | H25: 25253-S001 | I25: 金魚 | J25: 708 | K25: 0 | L25: 12 | M25: =J25/L25 -> 59 | N25: 45659 | O25: 45656 | Q25: Pass | R25: 1/6出 | S25: 12/3收到 | U25: 12/10-德语<(>&<)>法语callout贴纸 | V25: 25253:MA 1L-23L Warning+客版说明书翻4500138425 | W25: 日期码格式：ZURU INC(BVI) 标准格式 日期：按实际生产日期 Packaging Info: 2.25253:MA 1L-23L Warning+德语<(>&<)>法语callout贴纸+客版说明书（英法德意荷语言),客版说明书翻PO#4500138425 Remark: 1）包装日期码按ZURU格式即可，请确保不迟于外箱日期码，可等于或者早于外箱日期码，必须为法定工作日，印刷前请先检查外箱日期码。 2）订单出英国，请注意检查产品及包装应带UKCA图标（14+产品除外），包装显示ZURU UK LTD/ZURU France地址信息，QC部门请查核，如有问题与跟单确认 3) 需要符合欧洲标准不能含有闪粉和微塑料，否则不和法规会有客诉产生 | X25: Amy Ding | Y25: 3.7168 | Z25: =Y25*J25 -> 2631.4944 | AA25: 88855-1.3 | AB25: 708 | AC25: =AB25-J25 -> 0 | AD25: ok | AE25: 已入 | AF25: 系统出单 | AJ25: =J25 -> 708 | AM25: =J25 -> 708 | AY25: =J25 -> 708 | BD25: =SUM(AH25:AJ25) -> 708 | BE25: =BD25-J25 -> 0
A26: 45590 | B26: WAL-MART STORES INC. USA | C26: 美国 | D26: 4500149173 | E26: 870169769 | F26: 4500149173-10 | G26: 25251-S002 | H26: 25251-S002 | I26: 鸭子 | J26: 3530 | K26: 0 | L26: 2 | M26: =J26/L26 -> 1765 | N26: 45663 | O26: 45659 | P26: 1/7 BV（自检） | Q26: Pass | R26: 1/20出 | S26: 外箱四面印刷RFID箱唛 + 顶部ZURU logo黑色色带。主唛右下角加印 MADE IN CHINA | U26: 12/10-RFID贴纸 | V26: 最新扶正ZURU LOGO客版彩盒 | W26: 日期码格式：DGYYYYMMDD(日期避开周末和法定节假日) 日期：按实际生产日期 Packaging Info: 翻单：4500147361 1.包装方式： 25251：最新扶正ZURU LOGO客版彩盒（客版UPC）1L+23L警告语 + MA D版1L说明书 Remark: 2. 外箱四面印刷青色RFID箱唛 + 顶部ZURU logo黑色色带。 主唛左前下角印刷艾利贴纸替代标箱唛(ITF-14格式)，条码只印刷一面。 主唛右下角加印 MADE IN CHINA 3. WM#25251 NEW UPC：193052056092 4. Include 3pcs AAA carbon batteries; 5.此单需要验货，请自行多备包装物料。 6.在产品上和包装上要有日期码、MADE IN CHINA和ZURU字样。 7.此批单都为散箱出货 8.每PCS要加RFID 贴纸，严格按照我们提供的位置图，不可擅自调整位置，贴纸也不可有任何破损或折坏，不可淋湿!!（如缺数请及时告知） | X26: Nikki Mo | Y26: 3.514 | Z26: =Y26*J26 -> 12404.42 | AA26: 94058-1.16 | AB26: =3526+4 -> 3530 | AC26: =AB26-J26 -> 0 | AD26: ok | AE26: 已入 | AF26: 系统出单 | AH26: =J26 -> 3530 | AL26: =J26 -> 3530 | BA26: =J26 -> 3530 | BD26: =SUM(AH26:AJ26) -> 3530 | BE26: =BD26-J26 -> 0
A27: 45590 | B27: WAL-MART STORES INC. USA | C27: 美国 | D27: 4500149174 | E27: 0870169775 | F27: 4500149174-10 | G27: 25251-S002 | H27: 25251-S002 | I27: 鸭子 | J27: 1630 | K27: 0 | L27: 2 | M27: =J27/L27 -> 815 | N27: 45663 | O27: 45659 | P27: 1/7 BV（自检） | Q27: Pass | R27: 1/27出 | S27: 外箱四面印刷RFID箱唛 + 顶部ZURU logo黑色色带。主唛右下角加印 MADE IN CHINA | U27: 12/10-RFID贴纸 | V27: 最新扶正ZURU LOGO客版彩盒 | W27: 日期码格式：DGYYYYMMDD(日期避开周末和法定节假日) 日期：按实际生产日期 Packaging Info: 翻单：4500147361 1.包装方式： 25251：最新扶正ZURU LOGO客版彩盒（客版UPC）1L+23L警告语 + MA D版1L说明书 Remark: 2. 外箱四面印刷青色RFID箱唛 + 顶部ZURU logo黑色色带。 主唛左前下角印刷艾利贴纸替代标箱唛(ITF-14格式)，条码只印刷一面。 主唛右下角加印 MADE IN CHINA 3. WM#25251 NEW UPC：193052056092 4. Include 3pcs AAA carbon batteries; 5.此单需要验货，请自行多备包装物料。 6.在产品上和包装上要有日期码、MADE IN CHINA和ZURU字样。 7.此批单都为散箱出货 8.每PCS要加RFID 贴纸，严格按照我们提供的位置图，不可擅自调整位置，贴纸也不可有任何破损或折坏，不可淋湿!!（如缺数请及时告知） | X27: Nikki Mo | Y27: 3.7145 | Z27: =Y27*J27 -> 6054.635 | AA27: 94096-1.18 | AB27: 1630 | AC27: =AB27-J27 -> 0 | AD27: ok | AE27: 已入 | AF27: 系统出单 | AH27: =J27 -> 1630 | AL27: =J27 -> 1630 | BA27: =J27 -> 1630 | BD27: =SUM(AH27:AJ27) -> 1630 | BE27: =BD27-J27 -> 0
A28: 45590 | B28: WAL-MART STORES INC. USA | C28: 美国 | D28: 4500149176 | E28: 0870169805 | F28: 4500149176-10 | G28: 25251-S002 | H28: 25251-S002 | I28: 鸭子 | J28: 5496 | K28: 0 | L28: 2 | M28: =J28/L28 -> 2748 | N28: 45663 | O28: 45659 | P28: 1/7 BV（自检） | Q28: Pass | R28: 1/20出 | S28: 外箱四面印刷RFID箱唛 + 顶部ZURU logo黑色色带。主唛右下角加印 MADE IN CHINA | U28: 12/10-RFID贴纸 | V28: 最新扶正ZURU LOGO客版彩盒 | W28: 日期码格式：DGYYYYMMDD(日期避开周末和法定节假日) 日期：按实际生产日期 Packaging Info: 翻单：4500147361 1.包装方式： 25251：最新扶正ZURU LOGO客版彩盒（客版UPC）1L+23L警告语 + MA D版1L说明书 Remark: 2. 外箱四面印刷青色RFID箱唛 + 顶部ZURU logo黑色色带。 主唛左前下角印刷艾利贴纸替代标箱唛(ITF-14格式)，条码只印刷一面。 主唛右下角加印 MADE IN CHINA 3. WM#25251 NEW UPC：193052056092 4. Include 3pcs AAA carbon batteries; 5.此单需要验货，请自行多备包装物料。 6.在产品上和包装上要有日期码、MADE IN CHINA和ZURU字样。 7.此批单都为散箱出货 8.每PCS要加RFID 贴纸，严格按照我们提供的位置图，不可擅自调整位置，贴纸也不可有任何破损或折坏，不可淋湿!!（如缺数请及时告知） | X28: Nikki Mo | Y28: 3.4312 | Z28: =Y28*J28 -> 18857.875 | AA28: 94125-1.20 | AB28: 5496 | AC28: =AB28-J28 -> 0 | AD28: ok | AE28: 已入 | AF28: 系统出单 | AH28: =J28 -> 5496 | AL28: =J28 -> 5496 | BA28: =J28 -> 5496 | BD28: =SUM(AH28:AJ28) -> 5496 | BE28: =BD28-J28 -> 0
A29: 45590 | B29: WAL-MART STORES INC. USA | C29: 美国 | D29: 4500149177 | E29: 0870169847 | F29: 4500149177-10 | G29: 25251-S002 | H29: 25251-S002 | I29: 鸭子 | J29: 3370 | K29: 0 | L29: 2 | M29: =J29/L29 -> 1685 | N29: 45663 | O29: 45659 | P29: 1/7 BV（自检） | Q29: Pass | R29: 1/20出 | S29: 外箱四面印刷RFID箱唛 + 顶部ZURU logo黑色色带。主唛右下角加印 MADE IN CHINA | U29: 12/10-RFID贴纸 | V29: 最新扶正ZURU LOGO客版彩盒 | W29: 日期码格式：DGYYYYMMDD(日期避开周末和法定节假日) 日期：按实际生产日期 Packaging Info: 翻单：4500147361 1.包装方式： 25251：最新扶正ZURU LOGO客版彩盒（客版UPC）1L+23L警告语 + MA D版1L说明书 Remark: 2. 外箱四面印刷青色RFID箱唛 + 顶部ZURU logo黑色色带。 主唛左前下角印刷艾利贴纸替代标箱唛(ITF-14格式)，条码只印刷一面。 主唛右下角加印 MADE IN CHINA 3. WM#25251 NEW UPC：193052056092 4. Include 3pcs AAA carbon batteries; 5.此单需要验货，请自行多备包装物料。 6.在产品上和包装上要有日期码、MADE IN CHINA和ZURU字样。 7.此批单都为散箱出货 8.每PCS要加RFID 贴纸，严格按照我们提供的位置图，不可擅自调整位置，贴纸也不可有任何破损或折坏，不可淋湿!!（如缺数请及时告知） | X29: Nikki Mo | Y29: 3.514 | Z29: =Y29*J29 -> 11842.18 | AA29: 94072-1.17 | AB29: =2970+400 -> 3370 | AC29: =AB29-J29 -> 0 | AD29: ok | AE29: 已入 | AF29: 系统出单 | AH29: =J29 -> 3370 | AL29: =J29 -> 3370 | BA29: =J29 -> 3370 | BD29: =SUM(AH29:AJ29) -> 3370 | BE29: =BD29-J29 -> 0
A30: 45590 | B30: WAL-MART STORES INC. USA | C30: 美国 | D30: 4500149178 | E30: 0870169798 | F30: 4500149178-10 | G30: 25251-S002 | H30: 25251-S002 | I30: 鸭子 | J30: 4364 | K30: 0 | L30: 2 | M30: =J30/L30 -> 2182 | N30: 45663 | O30: 45659 | P30: 1/7 BV（自检） | Q30: Pass | R30: 1/20出 | S30: 外箱四面印刷RFID箱唛 + 顶部ZURU logo黑色色带。主唛右下角加印 MADE IN CHINA | U30: 12/10-RFID贴纸 | V30: 最新扶正ZURU LOGO客版彩盒 | W30: 日期码格式：DGYYYYMMDD(日期避开周末和法定节假日) 日期：按实际生产日期 Packaging Info: 翻单：4500147361 1.包装方式： 25251：最新扶正ZURU LOGO客版彩盒（客版UPC）1L+23L警告语 + MA D版1L说明书 Remark: 2. 外箱四面印刷青色RFID箱唛 + 顶部ZURU logo黑色色带。 主唛左前下角印刷艾利贴纸替代标箱唛(ITF-14格式)，条码只印刷一面。 主唛右下角加印 MADE IN CHINA 3. WM#25251 NEW UPC：193052056092 4. Include 3pcs AAA carbon batteries; 5.此单需要验货，请自行多备包装物料。 6.在产品上和包装上要有日期码、MADE IN CHINA和ZURU字样。 7.此批单都为散箱出货 8.每PCS要加RFID 贴纸，严格按照我们提供的位置图，不可擅自调整位置，贴纸也不可有任何破损或折坏，不可淋湿!!（如缺数请及时告知） | X30: Nikki Mo | Y30: 3.514 | Z30: =Y30*J30 -> 15335.096 | AA30: 94057-1.16 | AB30: 4364 | AC30: =AB30-J30 -> 0 | AD30: ok | AE30: 已入 | AF30: 系统出单 | AH30: =J30 -> 4364 | AL30: =J30 -> 4364 | BA30: =J30 -> 4364 | BD30: =SUM(AH30:AJ30) -> 4364 | BE30: =BD30-J30 -> 0
A31: 45590 | B31: WAL-MART STORES INC. USA | C31: 美国 | D31: 4500149179 | E31: 0870169788 | F31: 4500149179-10 | G31: 25251-S002 | H31: 25251-S002 | I31: 鸭子 | J31: 4792 | K31: 0 | L31: 2 | M31: =J31/L31 -> 2396 | N31: 45663 | O31: 45659 | P31: 1/7 BV（自检） | Q31: Pass | R31: 1/16出 | S31: 外箱四面印刷RFID箱唛 + 顶部ZURU logo黑色色带。主唛右下角加印 MADE IN CHINA | U31: 12/10-RFID贴纸 | V31: 最新扶正ZURU LOGO客版彩盒 | W31: 日期码格式：DGYYYYMMDD(日期避开周末和法定节假日) 日期：按实际生产日期 Packaging Info: 翻单：4500147361 1.包装方式： 25251：最新扶正ZURU LOGO客版彩盒（客版UPC）1L+23L警告语 + MA D版1L说明书 Remark: 2. 外箱四面印刷青色RFID箱唛 + 顶部ZURU logo黑色色带。 主唛左前下角印刷艾利贴纸替代标箱唛(ITF-14格式)，条码只印刷一面。 主唛右下角加印 MADE IN CHINA 3. WM#25251 NEW UPC：193052056092 4. Include 3pcs AAA carbon batteries; 5.此单需要验货，请自行多备包装物料。 6.在产品上和包装上要有日期码、MADE IN CHINA和ZURU字样。 7.此批单都为散箱出货 8.每PCS要加RFID 贴纸，严格按照我们提供的位置图，不可擅自调整位置，贴纸也不可有任何破损或折坏，不可淋湿!!（如缺数请及时告知） | X31: Nikki Mo | Y31: 3.514 | Z31: =Y31*J31 -> 16839.088 | AA31: 94140-1.21 | AB31: 4792 | AC31: =AB31-J31 -> 0 | AD31: ok | AE31: 已入 | AF31: 系统出单 | AH31: =J31 -> 4792 | AL31: =J31 -> 4792 | BA31: =J31 -> 4792 | BD31: =SUM(AH31:AJ31) -> 4792 | BE31: =BD31-J31 -> 0
A32: 45590 | B32: WAL-MART STORES INC. USA | C32: 美国 | D32: 4500149180 | E32: 0870169784 | F32: 4500149180-10 | G32: 25251-S002 | H32: 25251-S002 | I32: 鸭子 | J32: 3408 | K32: 0 | L32: 2 | M32: =J32/L32 -> 1704 | N32: 45663 | O32: 45659 | P32: 1/7 BV（自检） | Q32: Pass | R32: 1/7出 | S32: 外箱四面印刷RFID箱唛 + 顶部ZURU logo黑色色带。主唛右下角加印 MADE IN CHINA | U32: 12/10-RFID贴纸 | V32: 最新扶正ZURU LOGO客版彩盒 | W32: 日期码格式：DGYYYYMMDD(日期避开周末和法定节假日) 日期：按实际生产日期 Packaging Info: 翻单：4500147361 1.包装方式： 25251：最新扶正ZURU LOGO客版彩盒（客版UPC）1L+23L警告语 + MA D版1L说明书 Remark: 2. 外箱四面印刷青色RFID箱唛 + 顶部ZURU logo黑色色带。 主唛左前下角印刷艾利贴纸替代标箱唛(ITF-14格式)，条码只印刷一面。 主唛右下角加印 MADE IN CHINA 3. WM#25251 NEW UPC：193052056092 4. Include 3pcs AAA carbon batteries; 5.此单需要验货，请自行多备包装物料。 6.在产品上和包装上要有日期码、MADE IN CHINA和ZURU字样。 7.此批单都为散箱出货 8.每PCS要加RFID 贴纸，严格按照我们提供的位置图，不可擅自调整位置，贴纸也不可有任何破损或折坏，不可淋湿!!（如缺数请及时告知） | X32: Nikki Mo | Y32: 3.514 | Z32: =Y32*J32 -> 11975.712 | AA32: 94055-1.16 | AB32: 3408 | AC32: =AB32-J32 -> 0 | AD32: ok | AE32: 已入 | AF32: 系统出单 | AH32: =J32 -> 3408 | AL32: =J32 -> 3408 | BA32: =J32 -> 3408 | BD32: =SUM(AH32:AJ32) -> 3408 | BE32: =BD32-J32 -> 0
A33: 45623 | B33: AMAZON.COM.DEDC,LLC | C33: 美国 | D33: 4500152379 | E33: 2AIAHAQL | F33: 4500152379-110 | G33: 25253-S003-MTS | H33: 25253-S003 | I33: 金魚（邮包盒新稿） | J33: 160 | K33: 0 | L33: 4 | M33: =J33/L33 -> 40 | N33: 45664 | O33: 45660 | Q33: pass | R33: 2/7出 | U33: 12/20-外箱贴纸 | V33: 邮包盒图稿翻单4500131106-ZURU MA 1L | W33: 日期码格式： 标准格式 日期：按实际生产日期 Packaging Info: 25253：MA入邮包盒，邮包盒图稿翻单4500131106. Remark: 1. Amazon FOB订单，出口US。 2. 日期码使用ZURU标准版本。 3. 如果大货有要求入邮包盒，则对应的邮包盒上面要打上日期码。 4. 箱尺寸要求：外箱最长边不能超过25" （超过了，case pack只能为1），不符合要求的大货，一律不接受。 5. 外箱箱唛要求： ①外箱正面印ZURU Logo+SSCC Label（客供贴纸，由跟单订购)。关于 SSCC Label 请注意： SSCC Label 显示的是客人自己的item#。每一张SSCC label 都是唯一且有不同流水及条码的，没有损耗，绝对不可贴错 。如果贴错或损坏任何一张，都会导致全 部都错，千万要注意！ SSCC Label 必须贴在外箱正面的正中间位置（贴一面即可），并且贴纸离外箱边距必须至少3cm(可以覆盖Logo<(>&<)>箱唛)，否则会影响到客户那边仓库的扫描识 别。 ②外箱侧面印item#（订单上显示的SKU#)+carton size(以工厂实际尺寸为准,单位: inch) +MADE IN CHINA,日期使用ZURU 标准版本。 6. 装柜要求：按照客户PO# 装柜/箱号顺序装柜，跟单会提前给到装柜计划。 在大货生产/仓库存放时，请留意该装柜要求，以便装柜时不混乱（避免装错/装漏/找不到货号等）。 | X33: Kelly Shen | Y33: 4.0861 | Z33: =Y33*J33 -> 653.776 | AA33: 94201-2.10 | AB33: 160 | AC33: =AB33-J33 -> 0 | AD33: ok | AE33: 已入 | AF33: 系统出单 | AJ33: =J33 -> 160 | AL33: =J33 -> 160 | AY33: =J33 -> 160 | BD33: =SUM(AH33:AJ33) -> 160 | BE33: =BD33-J33 -> 0
A34: 45623 | B34: AMAZON.COM.DEDC,LLC | C34: 美国 | D34: 4500152379 | E34: 2ASXTO3R | F34: 4500152379-120 | G34: 25253-S003-MTS | H34: 25253-S003 | I34: 金魚（邮包盒新稿） | J34: 48 | K34: 0 | L34: 4 | M34: =J34/L34 -> 12 | N34: 45664 | O34: 45660 | Q34: pass | R34: 2/7出 | U34: 12/20-外箱贴纸 | V34: 邮包盒图稿翻单4500131106-ZURU MA 1L | W34: 日期码格式： 标准格式 日期：按实际生产日期 Packaging Info: 25253：MA入邮包盒，邮包盒图稿翻单4500131106. Remark: 1. Amazon FOB订单，出口US。 2. 日期码使用ZURU标准版本。 3. 如果大货有要求入邮包盒，则对应的邮包盒上面要打上日期码。 4. 箱尺寸要求：外箱最长边不能超过25" （超过了，case pack只能为1），不符合要求的大货，一律不接受。 5. 外箱箱唛要求： ①外箱正面印ZURU Logo+SSCC Label（客供贴纸，由跟单订购)。关于 SSCC Label 请注意： SSCC Label 显示的是客人自己的item#。每一张SSCC label 都是唯一且有不同流水及条码的，没有损耗，绝对不可贴错 。如果贴错或损坏任何一张，都会导致全 部都错，千万要注意！ SSCC Label 必须贴在外箱正面的正中间位置（贴一面即可），并且贴纸离外箱边距必须至少3cm(可以覆盖Logo<(>&<)>箱唛)，否则会影响到客户那边仓库的扫描识 别。 ②外箱侧面印item#（订单上显示的SKU#)+carton size(以工厂实际尺寸为准,单位: inch) +MADE IN CHINA,日期使用ZURU 标准版本。 6. 装柜要求：按照客户PO# 装柜/箱号顺序装柜，跟单会提前给到装柜计划。 在大货生产/仓库存放时，请留意该装柜要求，以便装柜时不混乱（避免装错/装漏/找不到货号等）。 | X34: Kelly Shen | Y34: 4.0861 | Z34: =Y34*J34 -> 196.1328 | AA34: 94201-2.10 | AB34: 48 | AC34: =AB34-J34 -> 0 | AD34: ok | AE34: 已入 | AF34: 系统出单 | AJ34: =J34 -> 48 | AL34: =J34 -> 48 | AY34: =J34 -> 48 | BD34: =SUM(AH34:AJ34) -> 48 | BE34: =BD34-J34 -> 0
A35: 45623 | B35: AMAZON.COM.DEDC,LLC | C35: 美国 | D35: 4500152379 | E35: 2KTUDAOR | F35: 4500152379-130 | G35: 25253-S003-MTS | H35: 25253-S003 | I35: 金魚（邮包盒新稿） | J35: 208 | K35: 0 | L35: 4 | M35: =J35/L35 -> 52 | N35: 45664 | O35: 45660 | Q35: pass | R35: 2/7出 | U35: 12/20-外箱贴纸 | V35: 邮包盒图稿翻单4500131106-ZURU MA 1L | W35: 日期码格式： 标准格式 日期：按实际生产日期 Packaging Info: 25253：MA入邮包盒，邮包盒图稿翻单4500131106. Remark: 1. Amazon FOB订单，出口US。 2. 日期码使用ZURU标准版本。 3. 如果大货有要求入邮包盒，则对应的邮包盒上面要打上日期码。 4. 箱尺寸要求：外箱最长边不能超过25" （超过了，case pack只能为1），不符合要求的大货，一律不接受。 5. 外箱箱唛要求： ①外箱正面印ZURU Logo+SSCC Label（客供贴纸，由跟单订购)。关于 SSCC Label 请注意： SSCC Label 显示的是客人自己的item#。每一张SSCC label 都是唯一且有不同流水及条码的，没有损耗，绝对不可贴错 。如果贴错或损坏任何一张，都会导致全 部都错，千万要注意！ SSCC Label 必须贴在外箱正面的正中间位置（贴一面即可），并且贴纸离外箱边距必须至少3cm(可以覆盖Logo<(>&<)>箱唛)，否则会影响到客户那边仓库的扫描识 别。 ②外箱侧面印item#（订单上显示的SKU#)+carton size(以工厂实际尺寸为准,单位: inch) +MADE IN CHINA,日期使用ZURU 标准版本。 6. 装柜要求：按照客户PO# 装柜/箱号顺序装柜，跟单会提前给到装柜计划。 在大货生产/仓库存放时，请留意该装柜要求，以便装柜时不混乱（避免装错/装漏/找不到货号等）。 | X35: Kelly Shen | Y35: 4.0861 | Z35: =Y35*J35 -> 849.9088 | AA35: 94201-2.10 | AB35: 208 | AC35: =AB35-J35 -> 0 | AD35: ok | AE35: 已入 | AF35: 系统出单 | AJ35: =J35 -> 208 | AL35: =J35 -> 208 | AY35: =J35 -> 208 | BD35: =SUM(AH35:AJ35) -> 208 | BE35: =BD35-J35 -> 0
A36: 45623 | B36: AMAZON.COM.DEDC,LLC | C36: 美国 | D36: 4500152657 | E36: 5M78WMIT | F36: 4500152657-10 | G36: 25253-S003-MTS | H36: 25253-S003 | I36: 金魚（邮包盒新稿） | J36: 512 | K36: 0 | L36: 4 | M36: =J36/L36 -> 128 | N36: 45664 | O36: 45660 | Q36: pass | R36: 2/13出 | U36: 12/20-外箱贴纸 | V36: 邮包盒图稿翻单4500131106-ZURU MA 1L | W36: 日期码格式： 标准格式 日期：按实际生产日期 Packaging Info: 25253：MA入邮包盒，邮包盒图稿翻单4500131106. Remark: 1. Amazon FOB订单，出口US。 2. 日期码使用ZURU标准版本。 3. 如果大货有要求入邮包盒，则对应的邮包盒上面要打上日期码。 4. 箱尺寸要求：外箱最长边不能超过25" （超过了，case pack只能为1），不符合要求的大货，一律不接受。 5. 外箱箱唛要求： ①外箱正面印ZURU Logo+SSCC Label（客供贴纸，由跟单订购)。关于 SSCC Label 请注意： SSCC Label 显示的是客人自己的item#。每一张SSCC label 都是唯一且有不同流水及条码的，没有损耗，绝对不可贴错 。如果贴错或损坏任何一张，都会导致全 部都错，千万要注意！ SSCC Label 必须贴在外箱正面的正中间位置（贴一面即可），并且贴纸离外箱边距必须至少3cm(可以覆盖Logo<(>&<)>箱唛)，否则会影响到客户那边仓库的扫描识 别。 ②外箱侧面印item#（订单上显示的SKU#)+carton size(以工厂实际尺寸为准,单位: inch) +MADE IN CHINA,日期使用ZURU 标准版本。 6. 装柜要求：按照客户PO# 装柜/箱号顺序装柜，跟单会提前给到装柜计划。 在大货生产/仓库存放时，请留意该装柜要求，以便装柜时不混乱（避免装错/装漏/找不到货号等）。 | X36: Kelly Shen | Y36: 3.9511 | Z36: =Y36*J36 -> 2022.9632 | AA36: 94229-2.12 | AB36: 512 | AC36: =AB36-J36 -> 0 | AD36: ok | AE36: 已入 | AF36: 系统出单 | AJ36: =J36 -> 512 | AL36: =J36 -> 512 | AY36: =J36 -> 512 | BD36: =SUM(AH36:AJ36) -> 512 | BE36: =BD36-J36 -> 0
A37: 45603 | B37: ROSS PROCUREMENT.INC | C37: 美国 | D37: 4500150300 | E37: 60188336 | F37: 4500150300-20 | G37: 25251-S001 | H37: 25251-S001 | I37: 鸭子 | J37: 4992 | K37: 0 | L37: 12 | M37: =J37/L37 -> 416 | N37: 45664 | O37: 45660 | Q37: Pass | R37: 1/17出 | S37: 2024/11/14收到 | U37: 12/2-客供价格贴纸 | V37: ZURU MA UPC 现有版本包装 | W37: 日期码格式： 标准格式 日期：按实际生产日期 Packaging Info: 1.ZURU MA UPC 现有版本包装 + 客供价格贴纸，出口美国 , 优先使用MA 1L 最新版本 。 Remark: 1.ZURU MA UPC 现有版本包装 + 客供价格贴纸，出口美国 , 优先使用MA 1L 最新版本 。 2.价格贴纸位于包装正面右下角，不挡住重要信息即可，可适当调整 ，价格贴纸由跟单提供。 3.标准日期码格式，产品和包装必须有日期码 。 4.同个产品同个货期不可出现不同的包装。 5. 跟单提供ROSS通用的箱唛模版，工厂按实际45 PO上客户PO/Item号/装箱数 提供箱唛排版来确认 6.#25251 和 #25253用英法包装，翻单4500132627 | X37: Taylor Liao | Y37: 3.3487 | Z37: =Y37*J37 -> 16716.71 | AA37: 94097-1.18 | AB37: =540+408+2472+1212+360 -> 4992 | AC37: =AB37-J37 -> 0 | AD37: ok | AE37: 已入 | AF37: 系统出单 | AH37: =J37 -> 4992 | AL37: =J37 -> 4992 | AW37: =J37 -> 4992 | BD37: =SUM(AH37:AJ37) -> 4992 | BE37: =BD37-J37 -> 0
A38: 45603 | B38: ROSS PROCUREMENT.INC | C38: 美国 | D38: 4500150300 | E38: 60188336 | F38: 4500150300-30 | G38: 25253-S001 | H38: 25253-S001 | I38: 金魚 | J38: 2496 | K38: 0 | L38: 12 | M38: =J38/L38 -> 208 | N38: 45664 | O38: 45660 | Q38: Pass | R38: 1/17出 | S38: 11/14收到 | U38: 12/2-客供价格贴纸 | V38: ZURU MA UPC 现有版本包装 | W38: 日期码格式： 标准格式 日期：按实际生产日期 Packaging Info: 1.ZURU MA UPC 现有版本包装 + 客供价格贴纸，出口美国 , 优先使用MA 1L 最新版本 。 Remark: 1.ZURU MA UPC 现有版本包装 + 客供价格贴纸，出口美国 , 优先使用MA 1L 最新版本 。 2.价格贴纸位于包装正面右下角，不挡住重要信息即可，可适当调整 ，价格贴纸由跟单提供。 3.标准日期码格式，产品和包装必须有日期码 。 4.同个产品同个货期不可出现不同的包装。 5. 跟单提供ROSS通用的箱唛模版，工厂按实际45 PO上客户PO/Item号/装箱数 提供箱唛排版来确认 6.#25251 和 #25253用英法包装，翻单4500132627 | X38: Taylor Liao | Y38: 3.0492 | Z38: =Y38*J38 -> 7610.8032 | AA38: 94097-1.18 | AB38: 2496 | AC38: =AB38-J38 -> 0 | AD38: ok | AE38: 已入 | AF38: 系统出单 | AJ38: =J38 -> 2496 | AL38: =J38 -> 2496 | AY38: =J38 -> 2496 | BD38: =SUM(AH38:AJ38) -> 2496 | BE38: =BD38-J38 -> 0
A39: 45625 | B39: Smyths Toys HQ UC UK | C39: 英国 | D39: 4500153057 | E39: 4400452592 | F39: 4500153057-10 | G39: 25253-S001-7 | H39: 25253-S001 | I39: 金魚 | J39: 3000 | K39: 0 | L39: 12 | M39: =J39/L39 -> 250 | N39: 45666 | O39: 45663 | Q39: Pass | R39: 1/13出 | S39: 12/4收到 | U39: 德语<(>&<)>法语callout贴纸翻4500153056 | V39: 25253:MA 1L-23L Warning+客版说明书翻4500138425 | W39: 日期码格式：ZURU INC(BVI) 标准格式 日期：按实际生产日期 Packaging Info: 2.25253:MA 1L-23L Warning+德语<(>&<)>法语callout贴纸(贴纸及位置图翻PO#4500153056)+客版说明书（英法德意荷语言),客版说明书翻PO#4500138425 UPC#845218016432请先检查条码是否正确再安排做货如有问题请告知 | X39: Amy Ding | Y39: 3.1368 | Z39: =Y39*J39 -> 9410.4 | AA39: 94098-1.18 | AB39: =1380+1620 -> 3000 | AC39: =AB39-J39 -> 0 | AD39: ok | AE39: 已入 | AF39: 系统出单 | AJ39: =J39 -> 3000 | AM39: =J39 -> 3000 | AY39: =J39 -> 3000 | BD39: =SUM(AH39:AJ39) -> 3000 | BE39: =BD39-J39 -> 0
A40: 45590 | B40: WAL-MART STORES INC. USA | C40: 美国 | D40: 4500149181 | E40: 0870169836 | F40: 4500149181-10 | G40: 25251-S002 | H40: 25251-S002 | I40: 鸭子 | J40: 1902 | K40: 0 | L40: 2 | M40: =J40/L40 -> 951 | N40: 45681 | O40: 45677 | P40: 1/22 BV（自检） | Q40: Pass | R40: 2/18出 | S40: 外箱四面印刷RFID箱唛 + 顶部ZURU logo黑色色带。主唛右下角加印 MADE IN CHINA | U40: 12/10-RFID贴纸 | V40: 最新扶正ZURU LOGO客版彩盒 | W40: 日期码格式：DGYYYYMMDD(日期避开周末和法定节假日) 日期：按实际生产日期 Packaging Info: 翻单：4500147361 1.包装方式： 25251：最新扶正ZURU LOGO客版彩盒（客版UPC）1L+23L警告语 + MA D版1L说明书 Remark: 2. 外箱四面印刷青色RFID箱唛 + 顶部ZURU logo黑色色带。 主唛左前下角印刷艾利贴纸替代标箱唛(ITF-14格式)，条码只印刷一面。 主唛右下角加印 MADE IN CHINA 3. WM#25251 NEW UPC：193052056092 4. Include 3pcs AAA carbon batteries; 5.此单需要验货，请自行多备包装物料。 6.在产品上和包装上要有日期码、MADE IN CHINA和ZURU字样。 7.此批单都为散箱出货 8.每PCS要加RFID 贴纸，严格按照我们提供的位置图，不可擅自调整位置，贴纸也不可有任何破损或折坏，不可淋湿!!（如缺数请及时告知） | X40: Nikki Mo | Y40: 3.7145 | Z40: =Y40*J40 -> 7064.979 | AA40: 94270-2.18 | AB40: 1902 | AC40: =AB40-J40 -> 0 | AD40: ok | AE40: 已入 | AF40: 系统出单 | AH40: =J40 -> 1902 | AL40: =J40 -> 1902 | BA40: =J40 -> 1902 | BD40: =SUM(AH40:AJ40) -> 1902 | BE40: =BD40-J40 -> 0
A41: 45624 | B41: WAL-MART STORES INC. USA | C41: 美国 | D41: 4500152367 | E41: 0869333773 | F41: 4500152367-10 | G41: 25251-S002 | H41: 25251-S002 | I41: 鸭子 | J41: 1790 | K41: 0 | L41: 2 | M41: =J41/L41 -> 895 | N41: 45681 | O41: 45677 | P41: 1/22 BV（自检） | Q41: Pass | R41: 2/15出 | S41: 外箱四面印刷RFID箱唛 + 顶部ZURU logo黑色色带。主唛右下角加印 MADE IN CHINA | U41: 12/10-RFID贴纸 | V41: 最新扶正ZURU LOGO客版彩盒 | W41: 日期码格式：DGYYYYMMDD(日期避开周末和法定节假日) 日期：按实际生产日期 Packaging Info: 翻单：4500147361 1.包装方式： 25251：最新扶正ZURU LOGO客版彩盒（客版UPC）1L+23L警告语 + MA D版1L说明书 Remark: 2. 外箱四面印刷青色RFID箱唛 + 顶部ZURU logo黑色色带 主唛左前下角印刷艾利贴纸替代标箱唛(ITF-14格式)，条码只印刷一面 主唛右下角加印 MADE IN CHINA，对角线位置加贴一张粉色MOD艾利贴纸（工厂自行打印或订购） 3. WM#25251 NEW UPC：193052056092 4. Include 3pcs AAA carbon batteries; 5.此单需要验货，请自行多备包装物料。 6.在产品上和包装上要有日期码、MADE IN CHINA和ZURU字样。 7.此批单都为散箱出货 8.每PCS要加RFID 贴纸，严格按照我们提供的位置图，不可擅自调整位置，贴纸也不可有任何破损或折坏，不可淋湿!!（如缺数请及时告知） | X41: Nikki Mo | Y41: 3.7145 | Z41: =Y41*J41 -> 6648.955 | AA41: 94243-2.14 | AB41: 1790 | AC41: =AB41-J41 -> 0 | AD41: ok | AE41: 已入 | AF41: 系统出单 | AH41: =J41 -> 1790 | AL41: =J41 -> 1790 | BA41: =J41 -> 1790 | BD41: =SUM(AH41:AJ41) -> 1790 | BE41: =BD41-J41 -> 0
A42: 45624 | B42: WAL-MART STORES INC. USA | C42: 美国 | D42: 4500152368 | E42: 0869333776 | F42: 4500152368-10 | G42: 25251-S002 | H42: 25251-S002 | I42: 鸭子 | J42: 1576 | K42: 0 | L42: 2 | M42: =J42/L42 -> 788 | N42: 45681 | O42: 45677 | P42: 1/22 BV（自检） | Q42: Pass | R42: 2/15出 | S42: 外箱四面印刷RFID箱唛 + 顶部ZURU logo黑色色带。主唛右下角加印 MADE IN CHINA | U42: 12/10-RFID贴纸 | V42: 最新扶正ZURU LOGO客版彩盒 | W42: 日期码格式：DGYYYYMMDD(日期避开周末和法定节假日) 日期：按实际生产日期 Packaging Info: 翻单：4500147361 1.包装方式： 25251：最新扶正ZURU LOGO客版彩盒（客版UPC）1L+23L警告语 + MA D版1L说明书 Remark: 2. 外箱四面印刷青色RFID箱唛 + 顶部ZURU logo黑色色带 主唛左前下角印刷艾利贴纸替代标箱唛(ITF-14格式)，条码只印刷一面 主唛右下角加印 MADE IN CHINA，对角线位置加贴一张粉色MOD艾利贴纸（工厂自行打印或订购） 3. WM#25251 NEW UPC：193052056092 4. Include 3pcs AAA carbon batteries; 5.此单需要验货，请自行多备包装物料。 6.在产品上和包装上要有日期码、MADE IN CHINA和ZURU字样。 7.此批单都为散箱出货 8.每PCS要加RFID 贴纸，严格按照我们提供的位置图，不可擅自调整位置，贴纸也不可有任何破损或折坏，不可淋湿!!（如缺数请及时告知） | X42: Nikki Mo | Y42: 3.7145 | Z42: =Y42*J42 -> 5854.052 | AA42: 94242-2.14 | AB42: 1576 | AC42: =AB42-J42 -> 0 | AD42: ok | AE42: 已入 | AF42: 系统出单 | AH42: =J42 -> 1576 | AL42: =J42 -> 1576 | BA42: =J42 -> 1576 | BD42: =SUM(AH42:AJ42) -> 1576 | BE42: =BD42-J42 -> 0
A43: 45621 | B43: THE WAREHOUSE LIMITED | C43: 新西兰 | D43: 4500152186 | E43: 28659769 | F43: 4500152186-10 | G43: 25251-S001 | H43: 25251-S001 | I43: 鸭子 | J43: 228 | K43: 0 | L43: 12 | M43: =J43/L43 -> 19 | N43: 45691 | O43: 45688 | Q43: Pass | R43: 2/11出 | S43: 11/25收到 | U43: 无 | V43: MA UPC 英语包装 | W43: 日期码格式：ZURU INC(BVI) 标准格式 日期：按实际生产日期 Packaging Info: MA UPC 英语包装（优先1L英语版本，或者3L/5L含英语都可） 此客人不接受易掉落或者剥落或者可直接触碰的闪粉，可降解也不行，但可以接受符合欧洲微塑料标准的珠光粉或者闪片。 Remark: 25251: 3PCS AAA Batteries(Include) | X43: Abby Liang | Y43: 3.9118 | Z43: =Y43*J43 -> 891.8904 | AA43: 94214-2.11 | AB43: 228 | AC43: =AB43-J43 -> 0 | AD43: 无 | AE43: 已入 | AF43: 系统出单 | AH43: =J43 -> 228 | AL43: =J43 -> 228 | AW43: =J43 -> 228 | BD43: =SUM(AH43:AJ43) -> 228 | BE43: =BD43-J43 -> 0
A44: 45621 | B44: THE WAREHOUSE LIMITED | C44: 新西兰 | D44: 4500152185 | E44: 28659768 | F44: 4500152185-10 | G44: 25251-S001 | H44: 25251-S001 | I44: 鸭子 | J44: 672 | K44: 0 | L44: 12 | M44: =J44/L44 -> 56 | N44: 45691 | O44: 45688 | Q44: Pass | R44: 2/13出 | S44: 11/25收到 | U44: 无 | V44: MA UPC 英语包装 | W44: 日期码格式：ZURU INC(BVI) 标准格式 日期：按实际生产日期 Packaging Info: MA UPC 英语包装（优先1L英语版本，或者3L/5L含英语都可） 此客人不接受易掉落或者剥落或者可直接触碰的闪粉，可降解也不行，但可以接受符合欧洲微塑料标准的珠光粉或者闪片。 Remark: 25251: 3PCS AAA Batteries(Include) | X44: Abby Liang | Y44: 3.9118 | Z44: =Y44*J44 -> 2628.7296 | AA44: 94226-2.12 | AB44: 672 | AC44: =AB44-J44 -> 0 | AD44: 无 | AE44: 已入 | AF44: 系统出单 | AH44: =J44 -> 672 | AL44: =J44 -> 672 | AW44: =J44 -> 672 | BD44: =SUM(AH44:AJ44) -> 672 | BE44: =BD44-J44 -> 0
A45: 45586 | B45: TJX COMPANIES, INC | C45: 美国 | D45: 4500147801 | E45: TJ MAXX DC#891-156PCS , DC#894-132PCS , DC#896-132PCS , DC#897-252PCS , DC#898-132PCS | F45: 4500147801-90 | G45: 25252-S001 | H45: 25252-S001 | I45: 鱷魚 | J45: 804 | K45: 0 | L45: 12 | M45: =J45/L45 -> 67 | N45: 45677 | O45: 45673 | Q45: Pass | R45: 2/11出 | S45: 11/4收到 | U45: 12/20-客供价格贴纸 | V45: MA UPC包装 | W45: 日期码格式：ZURU INC(BVI) 标准格式 日期：按实际生产日期 Packaging Info: MA UPC包装+价格贴纸，价格贴纸客供。 Remark: 1. 产品和包装上印刷tracking code信息，格式为ZURU常规格式。 2. 分5个DC出货，每款产品每个DC的箱唛资料不同。具体分DC数量，请参考后面行项目备注。 3. ZURU QC验货。 | X45: Emily Wu | Y45: 4.0344 | Z45: =Y45*J45 -> 3243.6576 | AA45: 94280-2.18 | AB45: 804 | AC45: =AB45-J45 -> 0 | AD45: ok | AE45: 已入 | AF45: 系统出单 | AI45: =J45 -> 804 | AL45: =J45 -> 804 | AX45: =J45 -> 804 | BD45: =SUM(AH45:AJ45) -> 804 | BE45: =BD45-J45 -> 0
A46: 45586 | B46: TJX COMPANIES, INC | C46: 美国 | D46: 4500147801 | E46: TJ MAXX DC#891-156PCS , DC#894-132PCS , DC#896-132PCS , DC#897-252PCS , DC#898-132PCS | F46: 4500147801-100 | G46: 25253-S001 | H46: 25253-S001 | I46: 金魚 | J46: 804 | K46: 0 | L46: 12 | M46: =J46/L46 -> 67 | N46: 45677 | O46: 45673 | Q46: Pass | R46: 2/11出 | S46: 11/4收到 | U46: 12/20-客供价格贴纸 | V46: MA UPC包装 | W46: 日期码格式：ZURU INC(BVI) 标准格式 日期：按实际生产日期 Packaging Info: MA UPC包装+价格贴纸，价格贴纸客供。 Remark: 1. 产品和包装上印刷tracking code信息，格式为ZURU常规格式。 2. 分5个DC出货，每款产品每个DC的箱唛资料不同。具体分DC数量，请参考后面行项目备注。 3. ZURU QC验货。 | X46: Emily Wu | Y46: 3.7168 | Z46: =Y46*J46 -> 2988.3072 | AA46: 94280-2.18 | AB46: 804 | AC46: =AB46-J46 -> 0 | AD46: ok | AE46: 已入 | AF46: 系统出单 | AJ46: =J46 -> 804 | AL46: =J46 -> 804 | AY46: =J46 -> 804 | BD46: =SUM(AH46:AJ46) -> 804 | BE46: =BD46-J46 -> 0
A47: 45586 | B47: TJX COMPANIES, INC | C47: 美国 | D47: 4500147799 | E47: Marshalls DC#881-120PCS , DC#884-96PCS, DC#886-144PCS , DC#887-120PCS , DC#888-120PCS | F47: 4500147799-90 | G47: 25252-S001 | H47: 25252-S001 | I47: 鱷魚 | J47: 600 | K47: 0 | L47: 12 | M47: =J47/L47 -> 50 | N47: 45677 | O47: 45673 | Q47: Pass | R47: 2/14出 | S47: 11/4收到 | U47: 12/20-客供价格贴纸 | V47: MA UPC包装 | W47: 日期码格式：ZURU INC(BVI) 标准格式 日期：按实际生产日期 Packaging Info: MA UPC包装+价格贴纸，价格贴纸客供。 Remark: 1. 产品和包装上印刷tracking code信息，格式为ZURU常规格式。 2. 分5个DC出货，每款产品每个DC的箱唛资料不同。具体分DC数量，请参考后面行项目备注。 3. ZURU QC验货。 | X47: Emily Wu | Y47: 3.9468 | Z47: =Y47*J47 -> 2368.08 | AA47: 94278-2.18 | AB47: 600 | AC47: =AB47-J47 -> 0 | AD47: ok | AE47: 已入 | AF47: 系统出单 | AI47: =J47 -> 600 | AL47: =J47 -> 600 | AX47: =J47 -> 600 | BD47: =SUM(AH47:AJ47) -> 600 | BE47: =BD47-J47 -> 0
A48: 45586 | B48: TJX COMPANIES, INC | C48: 美国 | D48: 4500147799 | E48: Marshalls DC#881-120PCS , DC#884-96PCS, DC#886-132PCS , DC#887-120PCS , DC#888-132PCS | F48: 4500147799-100 | G48: 25253-S001 | H48: 25253-S001 | I48: 金魚 | J48: 600 | K48: 0 | L48: 12 | M48: =J48/L48 -> 50 | N48: 45677 | O48: 45673 | Q48: Pass | R48: 2/14出 | S48: 11/4收到 | U48: 12/20-客供价格贴纸 | V48: MA UPC包装 | W48: 日期码格式：ZURU INC(BVI) 标准格式 日期：按实际生产日期 Packaging Info: MA UPC包装+价格贴纸，价格贴纸客供。 Remark: 1. 产品和包装上印刷tracking code信息，格式为ZURU常规格式。 2. 分5个DC出货，每款产品每个DC的箱唛资料不同。具体分DC数量，请参考后面行项目备注。 3. ZURU QC验货。 | X48: Emily Wu | Y48: 3.6292 | Z48: =Y48*J48 -> 2177.52 | AA48: 94278-2.18 | AB48: 600 | AC48: =AB48-J48 -> 0 | AD48: ok | AE48: 已入 | AF48: 系统出单 | AJ48: =J48 -> 600 | AL48: =J48 -> 600 | AY48: =J48 -> 600 | BD48: =SUM(AH48:AJ48) -> 600 | BE48: =BD48-J48 -> 0
A49: 45615 | B49: ROSS PROCUREMENT.INC | C49: 美国 | D49: 4500151489 | E49: 60188340 | F49: 4500151489-20 | G49: 25251-S001 | H49: 25251-S001 | I49: 鸭子 | J49: 3096 | K49: 0 | L49: 12 | M49: =J49/L49 -> 258 | N49: 45695 | O49: 45691 | Q49: Pass | R49: 3/12出 | S49: 指定箱唛格式 | U49: 1/3-客供价格贴纸 | V49: ZURU MA UPC 现有版本包装 | W49: 日期码格式：ZURU INC(BVI) 标准格式 日期：按实际生产日期 Packaging Info: 1.ZURU MA UPC 现有版本包装 + 客供价格贴纸，出口美国 , 优先使用MA 1L 最新版本 。 Remark: 1.ZURU MA UPC 现有版本包装 + 客供价格贴纸，出口美国 , 优先使用MA 1L 最新版本 。 2.价格贴纸位于包装正面右下角，不挡住重要信息即可，可适当调整 ，价格贴纸由跟单提供。 3.标准日期码格式，产品和包装必须有日期码 。 4.同个产品同个货期不可出现不同的包装。 5. 跟单提供ROSS通用的箱唛模版，工厂按实际45 PO上客户PO/Item号/装箱数 提供箱唛排版来确认 | X49: Taylor Liao | Y49: 3.2611 | Z49: =Y49*J49 -> 10096.366 | AA49: 94529-3.13 | AB49: =288+612+2196 -> 3096 | AC49: =AB49-J49 -> 0 | AD49: ok | AE49: 已入 | AF49: 系统出单 | AH49: =J49 -> 3096 | AL49: =J49 -> 3096 | AW49: =J49 -> 3096 | BD49: =SUM(AH49:AJ49) -> 3096 | BE49: =BD49-J49 -> 0
A50: 45615 | B50: ROSS PROCUREMENT.INC | C50: 美国 | D50: 4500151489 | E50: 60188340 | F50: 4500151489-30 | G50: 25253-S001 | H50: 25253-S001 | I50: 金魚 | J50: 1548 | K50: 0 | L50: 12 | M50: =J50/L50 -> 129 | N50: 45695 | O50: 45691 | Q50: Pass | R50: 3/12出 | S50: 指定箱唛格式 | U50: 1/3-客供价格贴纸 | V50: ZURU MA UPC 现有版本包装 | W50: 日期码格式：ZURU INC(BVI) 标准格式 日期：按实际生产日期 Packaging Info: 1.ZURU MA UPC 现有版本包装 + 客供价格贴纸，出口美国 , 优先使用MA 1L 最新版本 。 Remark: 1.ZURU MA UPC 现有版本包装 + 客供价格贴纸，出口美国 , 优先使用MA 1L 最新版本 。 2.价格贴纸位于包装正面右下角，不挡住重要信息即可，可适当调整 ，价格贴纸由跟单提供。 3.标准日期码格式，产品和包装必须有日期码 。 4.同个产品同个货期不可出现不同的包装。 5. 跟单提供ROSS通用的箱唛模版，工厂按实际45 PO上客户PO/Item号/装箱数 提供箱唛排版来确认 | X50: Taylor Liao | Y50: 3.6292 | Z50: =Y50*J50 -> 5618.0016 | AA50: 94529-3.13 | AB50: 1548 | AC50: =AB50-J50 -> 0 | AD50: ok | AE50: 已入 | AF50: 系统出单 | AJ50: =J50 -> 1548 | AL50: =J50 -> 1548 | AY50: =J50 -> 1548 | BD50: =SUM(AH50:AJ50) -> 1548 | BE50: =BD50-J50 -> 0
A51: 45586 | B51: TJX COMPANIES, INC | C51: 美国 | D51: 4500147806 | E51: TJ MAXX DC#891-156PCS , DC#894-132PCS , DC#896-132PCS , DC#897-252PCS , DC#898-132PCS | F51: 4500147806-100 | G51: 25252-S001 | H51: 25252-S001 | I51: 鱷魚 | J51: 804 | K51: 0 | L51: 12 | M51: =J51/L51 -> 67 | N51: 45698 | O51: 45694 | Q51: Pass | R51: 2/21出 | S51: 11/4收到 | U51: 12/20-客供价格贴纸 | V51: MA UPC包装 | W51: 日期码格式：ZURU INC(BVI) 标准格式 日期：按实际生产日期 Packaging Info: MA UPC包装+价格贴纸，价格贴纸客供。 Remark: 1. 产品和包装上印刷tracking code信息，格式为ZURU常规格式。 2. 分5个DC出货，每款产品每个DC的箱唛资料不同。具体分DC数量，请参考后面行项目备注。 3. ZURU QC验货。 | X51: Emily Wu | Y51: 4.0344 | Z51: =Y51*J51 -> 3243.6576 | AA51: 94380-2.27 | AB51: 804 | AC51: =AB51-J51 -> 0 | AD51: ok | AE51: 已入 | AF51: 系统出单 | AI51: =J51 -> 804 | AL51: =J51 -> 804 | AX51: =J51 -> 804 | BD51: =SUM(AH51:AJ51) -> 804 | BE51: =BD51-J51 -> 0
A52: 45586 | B52: TJX COMPANIES, INC | C52: 美国 | D52: 4500147804 | E52: Marshalls DC#881-120PCS , DC#884-96PCS, DC#886-144PCS , DC#887-120PCS , DC#888-120PCS | F52: 4500147804-100 | G52: 25252-S001 | H52: 25252-S001 | I52: 鱷魚 | J52: 600 | K52: 0 | L52: 12 | M52: =J52/L52 -> 50 | N52: 45698 | O52: 45694 | Q52: Pass | R52: 2/18出 | S52: 11/4收到 | U52: 12/20-客供价格贴纸 | V52: MA UPC包装 | W52: 日期码格式：ZURU INC(BVI) 标准格式 日期：按实际生产日期 Packaging Info: MA UPC包装+价格贴纸，价格贴纸客供。 Remark: 1. 产品和包装上印刷tracking code信息，格式为ZURU常规格式。 2. 分5个DC出货，每款产品每个DC的箱唛资料不同。具体分DC数量，请参考后面行项目备注。 3. ZURU QC验货。 | X52: Emily Wu | Y52: 4.0344 | Z52: =Y52*J52 -> 2420.64 | AA52: 94381-2.27 | AB52: 600 | AC52: =AB52-J52 -> 0 | AD52: ok | AE52: 已入 | AF52: 系统出单 | AI52: =J52 -> 600 | AL52: =J52 -> 600 | AX52: =J52 -> 600 | BD52: =SUM(AH52:AJ52) -> 600 | BE52: =BD52-J52 -> 0
A53: 45624 | B53: WAL-MART STORES INC. USA | C53: 美国 | D53: 4500152369 | E53: 0869333770 | F53: 4500152369-10 | G53: 25251-S002 | H53: 25251-S002 | I53: 鸭子 | J53: 1222 | K53: 0 | L53: 2 | M53: =J53/L53 -> 611 | N53: 45698 | O53: 45694 | P53: 2/10 BV（自检） | Q53: Pass | R53: 2/18出 | S53: 外箱四面印刷RFID箱唛 + 顶部ZURU logo黑色色带。主唛右下角加印 MADE IN CHINA | U53: 12/10-RFID贴纸 | V53: 最新扶正ZURU LOGO客版彩盒 | W53: 日期码格式：DGYYYYMMDD(日期避开周末和法定节假日) 日期：按实际生产日期 Packaging Info: 翻单：4500147361 1.包装方式： 25251：最新扶正ZURU LOGO客版彩盒（客版UPC）1L+23L警告语 + MA D版1L说明书 Remark: 2. 外箱四面印刷青色RFID箱唛 + 顶部ZURU logo黑色色带 主唛左前下角印刷艾利贴纸替代标箱唛(ITF-14格式)，条码只印刷一面 主唛右下角加印 MADE IN CHINA，对角线位置加贴一张粉色MOD艾利贴纸（工厂自行打印或订购） 3. WM#25251 NEW UPC：193052056092 4. Include 3pcs AAA carbon batteries; 5.此单需要验货，请自行多备包装物料。 6.在产品上和包装上要有日期码、MADE IN CHINA和ZURU字样。 7.此批单都为散箱出货 8.每PCS要加RFID 贴纸，严格按照我们提供的位置图，不可擅自调整位置，贴纸也不可有任何破损或折坏，不可淋湿!!（如缺数请及时告知） | X53: Nikki Mo | Y53: 3.7145 | Z53: =Y53*J53 -> 4539.119 | AA53: 94269-2.18 | AB53: 1222 | AC53: =AB53-J53 -> 0 | AD53: ok | AE53: 已入 | AF53: 系统出单 | AH53: =J53 -> 1222 | AL53: =J53 -> 1222 | BA53: =J53 -> 1222 | BD53: =SUM(AH53:AJ53) -> 1222 | BE53: =BD53-J53 -> 0
A54: 45624 | B54: WAL-MART STORES INC. USA | C54: 美国 | D54: 4500152846 | E54: 0870169772 | F54: 4500152846-10 | G54: 25251-S002 | H54: 25251-S002 | I54: 鸭子 | J54: 4118 | K54: 0 | L54: 2 | M54: =J54/L54 -> 2059 | N54: 45698 | O54: 45694 | P54: 2/10 BV（自检） | Q54: Pass | R54: 2/28出 | S54: 外箱四面印刷RFID箱唛 + 顶部ZURU logo黑色色带。主唛右下角加印 MADE IN CHINA | U54: 12/10-RFID贴纸 | V54: 最新扶正ZURU LOGO客版彩盒 | W54: 日期码格式：DGYYYYMMDD(日期避开周末和法定节假日) 日期：按实际生产日期 Packaging Info: 翻单：4500147361 1.包装方式： 25251：最新扶正ZURU LOGO客版彩盒（客版UPC）1L+23L警告语 + MA D版1L说明书 Remark: 2. 外箱四面印刷青色RFID箱唛 + 顶部ZURU logo黑色色带。 主唛左前下角印刷艾利贴纸替代标箱唛(ITF-14格式)，条码只印刷一面。 主唛右下角加印 MADE IN CHINA 3. WM#25251 NEW UPC：193052056092 4. Include 3pcs AAA carbon batteries; 5.此单需要验货，请自行多备包装物料。 6.在产品上和包装上要有日期码、MADE IN CHINA和ZURU字样。 7.此批单都为散箱出货 8.每PCS要加RFID 贴纸，严格按照我们提供的位置图，不可擅自调整位置，贴纸也不可有任何破损或折坏，不可淋湿!!（如缺数请及时告知） | X54: Nikki Mo | Y54: 3.514 | Z54: =Y54*J54 -> 14470.652 | AA54: 94341-2.25 | AB54: =2800+1318 -> 4118 | AC54: =AB54-J54 -> 0 | AD54: ok | AE54: 已入 | AF54: 系统出单 | AH54: =J54 -> 4118 | AL54: =J54 -> 4118 | BA54: =J54 -> 4118 | BD54: =SUM(AH54:AJ54) -> 4118 | BE54: =BD54-J54 -> 0
A55: 45624 | B55: WAL-MART STORES INC. USA | C55: 美国 | D55: 4500152370 | E55: 0869333759 | F55: 4500152370-10 | G55: 25251-S002 | H55: 25251-S002 | I55: 鸭子 | J55: 1234 | K55: 0 | L55: 2 | M55: =J55/L55 -> 617 | N55: 45705 | O55: 45701 | P55: 2/13 BV（自检） | Q55: Pass | R55: 2/22出 | S55: 外箱四面印刷RFID箱唛 + 顶部ZURU logo黑色色带。主唛右下角加印 MADE IN CHINA | U55: 12/10-RFID贴纸 | V55: 最新扶正ZURU LOGO客版彩盒 | W55: 日期码格式：DGYYYYMMDD(日期避开周末和法定节假日) 日期：按实际生产日期 Packaging Info: 翻单：4500147361 1.包装方式： 25251：最新扶正ZURU LOGO客版彩盒（客版UPC）1L+23L警告语 + MA D版1L说明书 Remark: 2. 外箱四面印刷青色RFID箱唛 + 顶部ZURU logo黑色色带 主唛左前下角印刷艾利贴纸替代标箱唛(ITF-14格式)，条码只印刷一面 主唛右下角加印 MADE IN CHINA，对角线位置加贴一张粉色MOD艾利贴纸（工厂自行打印或订购） 3. WM#25251 NEW UPC：193052056092 4. Include 3pcs AAA carbon batteries; 5.此单需要验货，请自行多备包装物料。 6.在产品上和包装上要有日期码、MADE IN CHINA和ZURU字样。 7.此批单都为散箱出货 8.每PCS要加RFID 贴纸，严格按照我们提供的位置图，不可擅自调整位置，贴纸也不可有任何破损或折坏，不可淋湿!!（如缺数请及时告知） | X55: Nikki Mo | Y55: 3.7145 | Z55: =Y55*J55 -> 4583.693 | AA55: 94306-2.20 | AB55: 1234 | AC55: =AB55-J55 -> 0 | AD55: ok | AE55: 已入 | AF55: 系统出单 | AH55: =J55 -> 1234 | AL55: =J55 -> 1234 | BA55: =J55 -> 1234 | BD55: =SUM(AH55:AJ55) -> 1234 | BE55: =BD55-J55 -> 0
A56: 45624 | B56: WAL-MART STORES INC. USA | C56: 美国 | D56: 4500152848 | E56: 0870169782 | F56: 4500152848-10 | G56: 25251-S002 | H56: 25251-S002 | I56: 鸭子 | J56: 2434 | K56: 0 | L56: 2 | M56: =J56/L56 -> 1217 | N56: 45705 | O56: 45701 | P56: 2/19 BV（自检） | Q56: Pass | R56: 2/27出 | S56: 外箱四面印刷RFID箱唛 + 顶部ZURU logo黑色色带。主唛右下角加印 MADE IN CHINA | U56: 12/10-RFID贴纸 | V56: 最新扶正ZURU LOGO客版彩盒 | W56: 日期码格式：DGYYYYMMDD(日期避开周末和法定节假日) 日期：按实际生产日期 Packaging Info: 翻单：4500147361 1.包装方式： 25251：最新扶正ZURU LOGO客版彩盒（客版UPC）1L+23L警告语 + MA D版1L说明书 Remark: 2. 外箱四面印刷青色RFID箱唛 + 顶部ZURU logo黑色色带。 主唛左前下角印刷艾利贴纸替代标箱唛(ITF-14格式)，条码只印刷一面。 主唛右下角加印 MADE IN CHINA 3. WM#25251 NEW UPC：193052056092 4. Include 3pcs AAA carbon batteries; 5.此单需要验货，请自行多备包装物料。 6.在产品上和包装上要有日期码、MADE IN CHINA和ZURU字样。 7.此批单都为散箱出货 8.每PCS要加RFID 贴纸，严格按照我们提供的位置图，不可擅自调整位置，贴纸也不可有任何破损或折坏，不可淋湿!!（如缺数请及时告知） | X56: Nikki Mo | Y56: 3.6259 | Z56: =Y56*J56 -> 8825.4406 | AA56: 94340-2.25 | AB56: 2434 | AC56: =AB56-J56 -> 0 | AD56: ok | AE56: 已入 | AF56: 系统出单 | AH56: =J56 -> 2434 | AL56: =J56 -> 2434 | BA56: =J56 -> 2434 | BD56: =SUM(AH56:AJ56) -> 2434 | BE56: =BD56-J56 -> 0
A57: 45624 | B57: WAL-MART STORES INC. USA | C57: 美国 | D57: 4500152847 | E57: 0870169796 | F57: 4500152847-10 | G57: 25251-S002 | H57: 25251-S002 | I57: 鸭子 | J57: 3422 | K57: 0 | L57: 2 | M57: =J57/L57 -> 1711 | N57: 45705 | O57: 45701 | P57: 2/19 BV（自检） | Q57: Pass | R57: 3/7出 | S57: 外箱四面印刷RFID箱唛 + 顶部ZURU logo黑色色带。主唛右下角加印 MADE IN CHINA | U57: 12/10-RFID贴纸 | V57: 最新扶正ZURU LOGO客版彩盒 | W57: 日期码格式：DGYYYYMMDD(日期避开周末和法定节假日) 日期：按实际生产日期 Packaging Info: 翻单：4500147361 1.包装方式： 25251：最新扶正ZURU LOGO客版彩盒（客版UPC）1L+23L警告语 + MA D版1L说明书 Remark: 2. 外箱四面印刷青色RFID箱唛 + 顶部ZURU logo黑色色带。 主唛左前下角印刷艾利贴纸替代标箱唛(ITF-14格式)，条码只印刷一面。 主唛右下角加印 MADE IN CHINA 3. WM#25251 NEW UPC：193052056092 4. Include 3pcs AAA carbon batteries; 5.此单需要验货，请自行多备包装物料。 6.在产品上和包装上要有日期码、MADE IN CHINA和ZURU字样。 7.此批单都为散箱出货 8.每PCS要加RFID 贴纸，严格按照我们提供的位置图，不可擅自调整位置，贴纸也不可有任何破损或折坏，不可淋湿!!（如缺数请及时告知） | X57: Nikki Mo | Y57: 3.514 | Z57: =Y57*J57 -> 12024.908 | AA57: 94480-3.7 | AB57: 3422 | AC57: =AB57-J57 -> 0 | AD57: ok | AE57: 已入 | AF57: 系统出单 | AH57: =J57 -> 3422 | AL57: =J57 -> 3422 | BA57: =J57 -> 3422 | BD57: =SUM(AH57:AJ57) -> 3422 | BE57: =BD57-J57 -> 0
A58: 45624 | B58: WAL-MART STORES INC. USA | C58: 美国 | D58: 4500152849 | E58: 0870169822 | F58: 4500152849-10 | G58: 25251-S002 | H58: 25251-S002 | I58: 鸭子 | J58: 3116 | K58: 0 | L58: 2 | M58: =J58/L58 -> 1558 | N58: 45705 | O58: 45701 | P58: 2/19 BV（自检） | Q58: Pass | R58: 2/24出 | S58: 外箱四面印刷RFID箱唛 + 顶部ZURU logo黑色色带。主唛右下角加印 MADE IN CHINA | U58: 12/10-RFID贴纸 | V58: 最新扶正ZURU LOGO客版彩盒 | W58: 日期码格式：DGYYYYMMDD(日期避开周末和法定节假日) 日期：按实际生产日期 Packaging Info: 翻单：4500147361 1.包装方式： 25251：最新扶正ZURU LOGO客版彩盒（客版UPC）1L+23L警告语 + MA D版1L说明书 Remark: 2. 外箱四面印刷青色RFID箱唛 + 顶部ZURU logo黑色色带。 主唛左前下角印刷艾利贴纸替代标箱唛(ITF-14格式)，条码只印刷一面。 主唛右下角加印 MADE IN CHINA 3. WM#25251 NEW UPC：193052056092 4. Include 3pcs AAA carbon batteries; 5.此单需要验货，请自行多备包装物料。 6.在产品上和包装上要有日期码、MADE IN CHINA和ZURU字样。 7.此批单都为散箱出货 8.每PCS要加RFID 贴纸，严格按照我们提供的位置图，不可擅自调整位置，贴纸也不可有任何破损或折坏，不可淋湿!!（如缺数请及时告知） | X58: Nikki Mo | Y58: 3.514 | Z58: =Y58*J58 -> 10949.624 | AA58: 94330-2.24 | AB58: 3116 | AC58: =AB58-J58 -> 0 | AD58: ok | AE58: 已入 | AF58: 系统出单 | AH58: =J58 -> 3116 | AL58: =J58 -> 3116 | BA58: =J58 -> 3116 | BD58: =SUM(AH58:AJ58) -> 3116 | BE58: =BD58-J58 -> 0
A59: 45586 | B59: TJX COMPANIES, INC | C59: 美国 | D59: 4500147806 | E59: TJ MAXX DC#891-156PCS , DC#894-132PCS , DC#896-132PCS , DC#897-252PCS , DC#898-132PCS | F59: 4500147806-110 | G59: 25253-S001 | H59: 25253-S001 | I59: 金魚 | J59: 804 | K59: 0 | L59: 12 | M59: =J59/L59 -> 67 | N59: 45698 | O59: 45694 | Q59: Pass | R59: 2/21出 | S59: 11/4收到 | U59: 12/20-客供价格贴纸 | V59: MA UPC包装 | W59: 日期码格式：ZURU INC(BVI) 标准格式 日期：按实际生产日期 Packaging Info: MA UPC包装+价格贴纸，价格贴纸客供。 Remark: 1. 产品和包装上印刷tracking code信息，格式为ZURU常规格式。 2. 分5个DC出货，每款产品每个DC的箱唛资料不同。具体分DC数量，请参考后面行项目备注。 3. ZURU QC验货。 | X59: Emily Wu | Y59: 3.7168 | Z59: =Y59*J59 -> 2988.3072 | AA59: 94380-2.27 | AB59: 804 | AC59: =AB59-J59 -> 0 | AD59: ok | AE59: 已入 | AF59: 系统出单 | AJ59: =J59 -> 804 | AL59: =J59 -> 804 | AY59: =J59 -> 804 | BD59: =SUM(AH59:AJ59) -> 804 | BE59: =BD59-J59 -> 0
A60: 45586 | B60: TJX COMPANIES, INC | C60: 美国 | D60: 4500147804 | E60: Marshalls DC#881-120PCS , DC#884-96PCS, DC#886-132PCS , DC#887-120PCS , DC#888-132PCS | F60: 4500147804-110 | G60: 25253-S001 | H60: 25253-S001 | I60: 金魚 | J60: 600 | K60: 0 | L60: 12 | M60: =J60/L60 -> 50 | N60: 45698 | O60: 45694 | Q60: Pass | R60: 2/18出 | S60: 11/4收到 | U60: 12/20-客供价格贴纸 | V60: MA UPC包装 | W60: 日期码格式：ZURU INC(BVI) 标准格式 日期：按实际生产日期 Packaging Info: MA UPC包装+价格贴纸，价格贴纸客供。 Remark: 1. 产品和包装上印刷tracking code信息，格式为ZURU常规格式。 2. 分5个DC出货，每款产品每个DC的箱唛资料不同。具体分DC数量，请参考后面行项目备注。 3. ZURU QC验货。 | X60: Emily Wu | Y60: 3.7168 | Z60: =Y60*J60 -> 2230.08 | AA60: 94381-2.27 | AB60: 600 | AC60: =AB60-J60 -> 0 | AD60: ok | AE60: 已入 | AF60: 系统出单 | AJ60: =J60 -> 600 | AL60: =J60 -> 600 | AY60: =J60 -> 600 | BD60: =SUM(AH60:AJ60) -> 600 | BE60: =BD60-J60 -> 0
A61: 45659 | B61: TJX COMPANIES, INC | C61: 美国 | D61: 4500155119 | E61: 325570 | F61: 4500155119-20 | G61: 25251-S001 | H61: 25251-S001 | I61: 鸭子 | J61: 2400 | K61: 0 | L61: 12 | M61: =J61/L61 -> 200 | N61: 45698 | O61: 45694 | Q61: Pass | S61: 1/2收到 | U61: 1/10-客供价格贴纸 | V61: MA UPC包装 | W61: 日期码格式：ZURU INC(BVI) 标准格式 日期：按实际生产日期 Packaging Info: MA UPC包装+价格贴纸，价格贴纸客供。 Remark: 1. 产品和包装上印刷tracking code信息，格式为ZURU常规格式。 2. 1个DC出货: Marshalls DC#882 3. ZURU QC验货。 | X61: Emily Wu | Y61: 3.373 | Z61: =Y61*J61 -> 8095.2 | AA61: 94247-2.14 | AB61: 2400 | AC61: =AB61-J61 -> 0 | AD61: OK | AE61: 已入 | AF61: 系统出单 | AH61: =J61 -> 2400 | AL61: =J61 -> 2400 | AW61: =J61 -> 2400 | BD61: =SUM(AH61:AJ61) -> 2400 | BE61: =BD61-J61 -> 0
A62: 45659 | B62: TJX COMPANIES, INC | C62: 美国 | D62: 4500155120 | E62: TJ MAXX DC#891-564PCS , DC#894-480PCS , DC#896-444PCS , DC#897-864PCS , DC#898-444PCS | F62: 4500155120-20 | G62: 25251-S001 | H62: 25251-S001 | I62: 鸭子 | J62: 2796 | K62: 0 | L62: 12 | M62: =J62/L62 -> 233 | N62: 45698 | O62: 45694 | Q62: Pass | R62: 2/21出 | S62: 1/2收到 | U62: 1/10-客供价格贴纸 | V62: MA UPC包装 | W62: 日期码格式：ZURU INC(BVI) 标准格式 日期：按实际生产日期 Packaging Info: MA UPC包装+价格贴纸，价格贴纸客供。 Remark: 1. 产品和包装上印刷tracking code信息，格式为ZURU常规格式。 2. 分5个DC出货，每款产品每个DC的箱唛资料不同。具体分DC数量，请参考后面行项目备注。 3. ZURU QC验货。 | X62: Emily Wu | Y62: 3.373 | Z62: =Y62*J62 -> 9430.908 | AA62: 94378-2.27 | AB62: 2796 | AC62: =AB62-J62 -> 0 | AD62: OK | AE62: 已入 | AF62: 系统出单 | AH62: =J62 -> 2796 | AL62: =J62 -> 2796 | AW62: =J62 -> 2796 | BD62: =SUM(AH62:AJ62) -> 2796 | BE62: =BD62-J62 -> 0
A63: 45624 | B63: Smyths Toys HQ UC IE | C63: 英国 | D63: 4500152768 | E63: 4400450816 | F63: 4500152768-10 | G63: 25251-S001-5 | H63: 25251-S001 | I63: 鸭子 | J63: 708 | K63: 0 | L63: 12 | M63: =J63/L63 -> 59 | N63: 45701 | O63: 45698 | Q63: Pass | R63: 2/17出 | S63: 12/11收到 | U63: 德语法语callout贴纸翻4500138425 | V63: 客版说明书都翻PO#4500138425 | W63: 日期码格式：ZURU INC(BVI) 标准格式 日期：按实际生产日期 Packaging Info: 1.25251: MA 1L-23L Warning+德语<(>&<)>法语callout贴纸+客版说明书（英法德意荷语言) 贴纸和位置图/客版说明书都翻PO#4500138425 Remark: 1）包装日期码按ZURU格式即可，请确保不迟于外箱日期码，可等于或者早于外箱日期码，必须为法定工作日，印刷前请先检查外箱日期码。 2）订单出英国，请注意检查产品及包装应带UKCA图标（14+产品除外），包装显示ZURU UK LTD/ZURU France地址信息，QC部门请查核，如有问题与跟单确认 3）订单必须经过ZURU QC验货并且通过后方可出货 4) 需要符合欧洲标准不能含有闪粉和微塑料，否则不和法规会有客诉产生 | X63: Amy Ding | Y63: 3.9118 | Z63: =Y63*J63 -> 2769.5544 | AA63: 94265-2.17 | AB63: 708 | AC63: =AB63-J63 -> 0 | AD63: ok | AE63: 已入 | AF63: 系统出单 | AH63: =J63 -> 708 | AM63: =J63 -> 708 | AW63: =J63 -> 708 | BD63: =SUM(AH63:AJ63) -> 708 | BE63: =BD63-J63 -> 0
A64: 45659 | B64: TJX COMPANIES, INC | C64: 美国 | D64: 4500155121 | E64: 325571 | F64: 4500155121-20 | G64: 25251-S001 | H64: 25251-S001 | I64: 鸭子 | J64: 2004 | K64: 0 | L64: 12 | M64: =J64/L64 -> 167 | N64: 45702 | O64: 45698 | Q64: Pass | R64: 2/21出 | S64: 1/2收到 | U64: 1/10-客供价格贴纸 | V64: MA UPC包装 | W64: 日期码格式：ZURU INC(BVI) 标准格式 日期：按实际生产日期 Tracking Code: Packaging Info: MA UPC包装+价格贴纸，价格贴纸客供。 Remark: 1. 产品和包装上印刷tracking code信息，格式为ZURU常规格式。 2. 1个DC出货: Marshalls DC#882 3. ZURU QC验货。 | X64: Emily Wu | Y64: 3.4606 | Z64: =Y64*J64 -> 6935.0424 | AA64: 94325-2.22 | AB64: =1464+540 -> 2004 | AC64: =AB64-J64 -> 0 | AD64: OK | AE64: 已入 | AF64: 系统出单 | AH64: =J64 -> 2004 | AL64: =J64 -> 2004 | AW64: =J64 -> 2004 | BD64: =SUM(AH64:AJ64) -> 2004 | BE64: =BD64-J64 -> 0
A65: 45659 | B65: TJX COMPANIES, INC | C65: 美国 | D65: 4500155123 | E65: TJ MAXX DC#891-480PCS , DC#894-408PCS , DC#896-384PCS , DC#897-744PCS , DC#898-384PCS | F65: 4500155123-20 | G65: 25251-S001 | H65: 25251-S001 | I65: 鸭子 | J65: 2400 | K65: 0 | L65: 12 | M65: =J65/L65 -> 200 | N65: 45702 | O65: 45698 | Q65: Pass | R65: 2/21出 | S65: 1/2收到 | U65: 1/10-客供价格贴纸 | V65: MA UPC包装 | W65: 日期码格式：ZURU INC(BVI) 标准格式 日期：按实际生产日期 Packaging Info: MA UPC包装+价格贴纸，价格贴纸客供。 Remark: 1. 产品和包装上印刷tracking code信息，格式为ZURU常规格式。 2. 分5个DC出货，每款产品每个DC的箱唛资料不同。具体分DC数量，请参考后面行项目备注。 3. ZURU QC验货。 | X65: Emily Wu | Y65: 3.4606 | Z65: =Y65*J65 -> 8305.44 | AA65: 94379-2.27 | AB65: 2400 | AC65: =AB65-J65 -> 0 | AD65: OK | AE65: 已入 | AF65: 系统出单 | AH65: =J65 -> 2400 | AL65: =J65 -> 2400 | AW65: =J65 -> 2400 | BD65: =SUM(AH65:AJ65) -> 2400 | BE65: =BD65-J65 -> 0
A66: 45637 | B66: BURLINGTON COAT FACTORY | C66: 美国 | D66: 4500153662 | E66: 383095202 | F66: 4500153662-20 | G66: 25251-S001 | H66: 25251-S001 | I66: 鸭子 | J66: 2460 | K66: 0 | L66: 12 | M66: =J66/L66 -> 205 | N66: 45705 | O66: 45701 | Q66: Pass | R66: 收到S0 | S66: 12/11收到 | U66: 1/3-客供价格贴纸+外箱贴纸 | V66: ZURU MA （首选1L）UPC版本 | W66: 日期码格式：ZURU INC(BVI) 标准格式 日期：按实际生产日期 Packaging Info: 1，ZURU MA （首选1L）UPC版本+客供价格贴纸+外箱贴纸，出口美国 Remark: 2，产品和包装上印刷ZURU 标准日期码； 3，纸箱中间靠上沿印刷ZURU LOGO，见箱唛资料 4、外箱UCC 条码贴纸，尺寸: 4*6inch，贴在其中一面正唛右下角，贴纸距离外箱底部3.5cm, 侧边距离3.5cm。外箱贴纸由跟单提供电子版, 工厂自行安排，不可用 封箱胶覆盖贴纸条码，贴纸需要可以扫描且无损坏. 5，每个产品有一个价格贴纸， 价格贴纸覆盖UPC条码上 （若UPC 条码太大，可以露出ITEM#, 覆盖条码即可），若价格贴纸覆盖UPC 会挡住文字/图案，在产品背面 找空白处粘贴价格贴纸即可。贴的时候要是会覆盖包装上重要的信息和图案，需要告知跟单。 | X66: Jessi Xu | Y66: 3.373 | Z66: =Y66*J66 -> 8297.58 | AA66: 94318-2.21 | AB66: 2460 | AC66: =AB66-J66 -> 0 | AD66: ok | AE66: 已入 | AF66: 系统出单 | AH66: =J66 -> 2460 | AL66: =J66 -> 2460 | AW66: =J66 -> 2460 | BD66: =SUM(AH66:AJ66) -> 2460 | BE66: =BD66-J66 -> 0
A67: 45637 | B67: BURLINGTON COAT FACTORY | C67: 美国 | D67: 4500153662 | E67: 383095203 | F67: 4500153662-30 | G67: 25253-S001 | H67: 25253-S001 | I67: 金魚 | J67: 2460 | K67: 0 | L67: 12 | M67: =J67/L67 -> 205 | N67: 45705 | O67: 45701 | Q67: Pass | R67: 收到S0 | S67: 12/11收到 | U67: 1/3-客供价格贴纸+外箱贴纸 | V67: ZURU MA （首选1L）UPC版本 | W67: 日期码格式：ZURU INC(BVI) 标准格式 日期：按实际生产日期 Packaging Info: 1，ZURU MA （首选1L）UPC版本+客供价格贴纸+外箱贴纸，出口美国 Remark: 2，产品和包装上印刷ZURU 标准日期码； 3，纸箱中间靠上沿印刷ZURU LOGO，见箱唛资料 4、外箱UCC 条码贴纸，尺寸: 4*6inch，贴在其中一面正唛右下角，贴纸距离外箱底部3.5cm, 侧边距离3.5cm。外箱贴纸由跟单提供电子版, 工厂自行安排，不可用 封箱胶覆盖贴纸条码，贴纸需要可以扫描且无损坏. 5，每个产品有一个价格贴纸， 价格贴纸覆盖UPC条码上 （若UPC 条码太大，可以露出ITEM#, 覆盖条码即可），若价格贴纸覆盖UPC 会挡住文字/图案，在产品背面 找空白处粘贴价格贴纸即可。贴的时候要是会覆盖包装上重要的信息和图案，需要告知跟单。 | X67: Jessi Xu | Y67: 3.1368 | Z67: =Y67*J67 -> 7716.528 | AA67: 94318-2.21 | AB67: 2460 | AC67: =AB67-J67 -> 0 | AD67: ok | AE67: 已入 | AF67: 系统出单 | AJ67: =J67 -> 2460 | AL67: =J67 -> 2460 | AY67: =J67 -> 2460 | BD67: =SUM(AH67:AJ67) -> 2460 | BE67: =BD67-J67 -> 0
A68: 45624 | B68: Smyths Toys HQ UC IE | C68: 英国 | D68: 4500152768 | E68: 4400450817 | F68: 4500152768-20 | G68: 25251-S001-5 | H68: 25251-S001 | I68: 鸭子 | J68: 3000 | K68: 0 | L68: 12 | M68: =J68/L68 -> 250 | N68: 45705 | O68: 45702 | Q68: Pass | R68: 2/18出 | S68: 12/11收到 | U68: 德语法语callout贴纸翻4500138425 | V68: 客版说明书都翻PO#4500138425 | W68: 日期码格式：ZURU INC(BVI) 标准格式 日期：按实际生产日期 Tracking Code: Packaging Info: 1.25251: MA 1L-23L Warning+德语<(>&<)>法语callout贴纸+客版说明书（英法德意荷语言) 贴纸和位置图/客版说明书都翻PO#4500138425 Remark: 1）包装日期码按ZURU格式即可，请确保不迟于外箱日期码，可等于或者早于外箱日期码，必须为法定工作日，印刷前请先检查外箱日期码。 2）订单出英国，请注意检查产品及包装应带UKCA图标（14+产品除外），包装显示ZURU UK LTD/ZURU France地址信息，QC部门请查核，如有问题与跟单确认 3）订单必须经过ZURU QC验货并且通过后方可出货 4) 需要符合欧洲标准不能含有闪粉和微塑料，否则不和法规会有客诉产生 | X68: Amy Ding | Y68: 3.4606 | Z68: =Y68*J68 -> 10381.8 | AA68: 94271-2.18 | AB68: 3000 | AC68: =AB68-J68 -> 0 | AD68: ok | AE68: 已入 | AF68: 系统出单 | AH68: =J68 -> 3000 | AM68: =J68 -> 3000 | AW68: =J68 -> 3000 | BD68: =SUM(AH68:AJ68) -> 3000 | BE68: =BD68-J68 -> 0
A69: 45615 | B69: ROSS PROCUREMENT.INC | C69: 美国 | D69: 4500151566 | E69: 60188350 | F69: 4500151566-20 | G69: 25251-S001 | H69: 25251-S001 | I69: 鸭子 | J69: 2400 | K69: 0 | L69: 12 | M69: =J69/L69 -> 200 | N69: 45707 | O69: 45703 | Q69: Pass | R69: 3/14出 | S69: 指定箱唛格式 | U69: 1/22-客供价格贴纸 | V69: ZURU MA UPC 现有版本包装 | W69: 日期码格式： 标准格式 日期：按实际生产日期 Packaging Info: 1.ZURU MA UPC 现有版本包装 + 客供价格贴纸，出口美国 , 优先使用MA 1L 最新版本 。 Remark: 1.ZURU MA UPC 现有版本包装 + 客供价格贴纸，出口美国 , 优先使用MA 1L 最新版本 。 2.价格贴纸位于包装正面右下角，不挡住重要信息即可，可适当调整 ，价格贴纸由跟单提供。 3.标准日期码格式，产品和包装必须有日期码 。 4.同个产品同个货期不可出现不同的包装。 5. 跟单提供ROSS通用的箱唛模版，工厂按实际45 PO上客户PO/Item号/装箱数 提供箱唛排版来确认 | X69: Taylor Liao | Y69: 3.4606 | Z69: =Y69*J69 -> 8305.44 | AA69: 94530-3.13 | AB69: 2400 | AC69: =AB69-J69 -> 0 | AD69: ok | AE69: 已入 | AF69: 系统出单 | AH69: =J69 -> 2400 | AL69: =J69 -> 2400 | AW69: =J69 -> 2400 | BD69: =SUM(AH69:AJ69) -> 2400 | BE69: =BD69-J69 -> 0
A70: 45642 | B70: AMAZON.COM.DEDC,LLC | C70: 美国 | D70: 4500154101 | E70: 54HP1UHU | F70: 4500154101-10 | G70: 25253-S003-MTS | H70: 25253-S003 | I70: 金魚（邮包盒新稿） | J70: 352 | K70: 0 | L70: 4 | M70: =J70/L70 -> 88 | N70: 45707 | O70: 45703 | Q70: Pass | R70: 2/25出 | S70: 12/16收到 | U70: 1/17-外箱贴纸 | V70: 25253：MA入邮包盒，邮包盒图稿翻单4500131106 | W70: 日期码格式： 标准格式 日期：按实际生产日期 Packaging Info: #25253：MA入邮包盒，邮包盒图稿翻单4500131106。 Remark: 1. Amazon FOB订单，出口US。 2. 日期码使用ZURU标准版本。 3. 如果大货有要求入邮包盒，则对应的邮包盒上面要打上日期码。 4. 箱尺寸要求：外箱最长边不能超过25"(超过了，case pack只能为1)，不符合要求的大货，一律不接受。 5. 外箱箱唛要求： ①外箱正面印ZURU Logo+SSCC Label(客供贴纸，由跟单订购)。关于 SSCC Label 请注意： SSCC Label显示的是客人自己的item#。每一张SSCC label都是唯一且有不同流水及条码的，没有损耗，绝对不可贴错。如果贴错或损坏任何一张，都会导致全部都 错，千万要注意！SSCC Label必须贴在外箱正面的正中间位置(贴一面即可)，并且贴纸离外箱边距必须至少3cm(可以覆盖Logo<(>&<)>箱唛)，否则会影响到客户那边 仓库的扫描识别。 ②外箱侧面印item#(订单上显示的SKU#)+carton size(以工厂实际尺寸为准，单位: inch)+MADE IN CHINA，日期使用ZURU 标准版本。 6. 装柜要求：按照客户PO#装柜/箱号顺序装柜，跟单会提前给到装柜计划。 在大货生产/仓库存放时，请留意该装柜要求，以便装柜时不混乱(避免装错/装漏/找不到货号等)。 | X70: kelly/Mia | Y70: 4.0861 | Z70: =Y70*J70 -> 1438.3072 | AA70: 94337-2.24 | AB70: 352 | AC70: =AB70-J70 -> 0 | AD70: ok | AE70: 已入 | AF70: 系统出单 | AJ70: =J70 -> 352 | AL70: =J70 -> 352 | AY70: =J70 -> 352 | BD70: =SUM(AH70:AJ70) -> 352 | BE70: =BD70-J70 -> 0
A71: 45642 | B71: AMAZON.COM.DEDC,LLC | C71: 美国 | D71: 4500154032 | E71: 8UE7E2SF | F71: 4500154032-10 | G71: 25253-S003-MTS | H71: 25253-S003 | I71: 金魚（邮包盒新稿） | J71: 16 | K71: 0 | L71: 4 | M71: =J71/L71 -> 4 | N71: 45707 | O71: 45703 | Q71: Pass | R71: 2/21出 | S71: 12/16收到 | U71: 1/17-外箱贴纸 | V71: 25253：MA入邮包盒，邮包盒图稿翻单4500131106 | W71: 日期码格式： 标准格式 日期：按实际生产日期 Packaging Info: #25253：MA入邮包盒，邮包盒图稿翻单4500131106。 Remark: 1. Amazon FOB订单，出口US。 2. 日期码使用ZURU标准版本。 3. 如果大货有要求入邮包盒，则对应的邮包盒上面要打上日期码。 4. 箱尺寸要求：外箱最长边不能超过25"(超过了，case pack只能为1)，不符合要求的大货，一律不接受。 5. 外箱箱唛要求： ①外箱正面印ZURU Logo+SSCC Label(客供贴纸，由跟单订购)。关于 SSCC Label 请注意： SSCC Label显示的是客人自己的item#。每一张SSCC label都是唯一且有不同流水及条码的，没有损耗，绝对不可贴错。如果贴错或损坏任何一张，都会导致全部都 错，千万要注意！SSCC Label必须贴在外箱正面的正中间位置(贴一面即可)，并且贴纸离外箱边距必须至少3cm(可以覆盖Logo<(>&<)>箱唛)，否则会影响到客户那边 仓库的扫描识别。 ②外箱侧面印item#(订单上显示的SKU#)+carton size(以工厂实际尺寸为准，单位: inch)+MADE IN CHINA，日期使用ZURU 标准版本。 6. 装柜要求：按照客户PO#装柜/箱号顺序装柜，跟单会提前给到装柜计划。 在大货生产/仓库存放时，请留意该装柜要求，以便装柜时不混乱(避免装错/装漏/找不到货号等)。 | X71: kelly/Mia | Y71: 3.9511 | Z71: =Y71*J71 -> 63.2176 | AA71: 94313-2.21 | AB71: 16 | AC71: =AB71-J71 -> 0 | AD71: ok | AE71: 已入 | AF71: 系统出单 | AJ71: =J71 -> 16 | AL71: =J71 -> 16 | AY71: =J71 -> 16 | BD71: =SUM(AH71:AJ71) -> 16 | BE71: =BD71-J71 -> 0
A72: 45642 | B72: AMAZON.COM.DEDC,LLC | C72: 美国 | D72: 4500154144 | E72: 4P6HT29K | F72: 4500154144-10 | G72: 25253-S003-MTS | H72: 25253-S003 | I72: 金魚（邮包盒新稿） | J72: 16 | K72: 0 | L72: 4 | M72: =J72/L72 -> 4 | N72: 45707 | O72: 45703 | Q72: Pass | R72: 2/21出 | S72: 12/16收到 | U72: 1/17-外箱贴纸 | V72: 25253：MA入邮包盒，邮包盒图稿翻单4500131106 | W72: 日期码格式： 标准格式 日期：按实际生产日期 Packaging Info: #25253：MA入邮包盒，邮包盒图稿翻单4500131106。 Remark: 1. Amazon FOB订单，出口US。 2. 日期码使用ZURU标准版本。 3. 如果大货有要求入邮包盒，则对应的邮包盒上面要打上日期码。 4. 箱尺寸要求：外箱最长边不能超过25"(超过了，case pack只能为1)，不符合要求的大货，一律不接受。 5. 外箱箱唛要求： ①外箱正面印ZURU Logo+SSCC Label(客供贴纸，由跟单订购)。关于 SSCC Label 请注意： SSCC Label显示的是客人自己的item#。每一张SSCC label都是唯一且有不同流水及条码的，没有损耗，绝对不可贴错。如果贴错或损坏任何一张，都会导致全部都 错，千万要注意！SSCC Label必须贴在外箱正面的正中间位置(贴一面即可)，并且贴纸离外箱边距必须至少3cm(可以覆盖Logo<(>&<)>箱唛)，否则会影响到客户那边 仓库的扫描识别。 ②外箱侧面印item#(订单上显示的SKU#)+carton size(以工厂实际尺寸为准，单位: inch)+MADE IN CHINA，日期使用ZURU 标准版本。 6. 装柜要求：按照客户PO#装柜/箱号顺序装柜，跟单会提前给到装柜计划。 在大货生产/仓库存放时，请留意该装柜要求，以便装柜时不混乱(避免装错/装漏/找不到货号等)。 | X72: kelly/Mia | Y72: 4.0861 | Z72: =Y72*J72 -> 65.3776 | AA72: 94314-2.21 | AB72: 16 | AC72: =AB72-J72 -> 0 | AD72: ok | AE72: 已入 | AF72: 系统出单 | AJ72: =J72 -> 16 | AL72: =J72 -> 16 | AY72: =J72 -> 16 | BD72: =SUM(AH72:AJ72) -> 16 | BE72: =BD72-J72 -> 0
A73: 45642 | B73: AMAZON.COM.DEDC,LLC | C73: 美国 | D73: 4500154124 | E73: 8FACFEHM | F73: 4500154124-90 | G73: 25253-S003-MTS | H73: 25253-S003 | I73: 金魚（邮包盒新稿） | J73: 144 | K73: 0 | L73: 4 | M73: =J73/L73 -> 36 | N73: 45707 | O73: 45703 | Q73: Pass | R73: 2/21出 | S73: 12/16收到 | U73: 1/17-外箱贴纸 | V73: 25253：MA入邮包盒，邮包盒图稿翻单4500131106 | W73: 日期码格式：ZURU INC(BVI) 标准格式 日期：按实际生产日期 Packaging Info: #25253：MA入邮包盒，邮包盒图稿翻单4500131106。 Remark: 1. Amazon FOB订单，出口US。 2. 日期码使用ZURU标准版本。 3. 如果大货有要求入邮包盒，则对应的邮包盒上面要打上日期码。 4. 箱尺寸要求：外箱最长边不能超过25"(超过了，case pack只能为1)，不符合要求的大货，一律不接受。 5. 外箱箱唛要求： ①外箱正面印ZURU Logo+SSCC Label(客供贴纸，由跟单订购)。关于 SSCC Label 请注意： SSCC Label显示的是客人自己的item#。每一张SSCC label都是唯一且有不同流水及条码的，没有损耗，绝对不可贴错。如果贴错或损坏任何一张，都会导致全部都 错，千万要注意！SSCC Label必须贴在外箱正面的正中间位置(贴一面即可)，并且贴纸离外箱边距必须至少3cm(可以覆盖Logo<(>&<)>箱唛)，否则会影响到客户那边 仓库的扫描识别。 ②外箱侧面印item#(订单上显示的SKU#)+carton size(以工厂实际尺寸为准，单位: inch)+MADE IN CHINA，日期使用ZURU 标准版本。 6. 装柜要求：按照客户PO#装柜/箱号顺序装柜，跟单会提前给到装柜计划。 在大货生产/仓库存放时，请留意该装柜要求，以便装柜时不混乱(避免装错/装漏/找不到货号等)。 | X73: kelly/Mia | Y73: 4.0861 | Z73: =Y73*J73 -> 588.3984 | AA73: 94315-2.21 | AB73: 144 | AC73: =AB73-J73 -> 0 | AD73: ok | AE73: 已入 | AF73: 系统出单 | AJ73: =J73 -> 144 | AL73: =J73 -> 144 | AY73: =J73 -> 144 | BD73: =SUM(AH73:AJ73) -> 144 | BE73: =BD73-J73 -> 0
A74: 45624 | B74: WAL-MART STORES INC. USA | C74: 美国 | D74: 4500152850 | E74: 0870169808 | F74: 4500152850-10 | G74: 25251-S002 | H74: 25251-S002 | I74: 鸭子 | J74: 3926 | K74: 0 | L74: 2 | M74: =J74/L74 -> 1963 | N74: 45712 | O74: 45708 | P74: 2/25 BV(自检） | Q74: Pass | R74: 3/14出 | S74: 外箱四面印刷RFID箱唛 + 顶部ZURU logo黑色色带。主唛右下角加印 MADE IN CHINA | U74: 12/10-RFID贴纸 | V74: 最新扶正ZURU LOGO客版彩盒 | W74: 日期码格式：DGYYYYMMDD(日期避开周末和法定节假日) 日期：按实际生产日期 Packaging Info: 翻单：4500147361 1.包装方式： 25251：最新扶正ZURU LOGO客版彩盒（客版UPC）1L+23L警告语 + MA D版1L说明书 Remark: 2. 外箱四面印刷青色RFID箱唛 + 顶部ZURU logo黑色色带。 主唛左前下角印刷艾利贴纸替代标箱唛(ITF-14格式)，条码只印刷一面。 主唛右下角加印 MADE IN CHINA 3. WM#25251 NEW UPC：193052056092 4. Include 3pcs AAA carbon batteries; 5.此单需要验货，请自行多备包装物料。 6.在产品上和包装上要有日期码、MADE IN CHINA和ZURU字样。 7.此批单都为散箱出货 8.每PCS要加RFID 贴纸，严格按照我们提供的位置图，不可擅自调整位置，贴纸也不可有任何破损或折坏，不可淋湿!!（如缺数请及时告知） | X74: Nikki Mo | Y74: 3.514 | Z74: =Y74*J74 -> 13795.964 | AA74: 94557-3.14 | AB74: 3926 | AC74: =AB74-J74 -> 0 | AD74: ok | AE74: 已入 | AF74: 系统出单 | AH74: =J74 -> 3926 | AL74: =J74 -> 3926 | BA74: =J74 -> 3926 | BD74: =SUM(AH74:AJ74) -> 3926 | BE74: =BD74-J74 -> 0
A75: 45624 | B75: WAL-MART STORES INC. USA | C75: 美国 | D75: 4500152851 | E75: 0870169818 | F75: 4500152851-10 | G75: 25251-S002 | H75: 25251-S002 | I75: 鸭子 | J75: 2406 | K75: 0 | L75: 2 | M75: =J75/L75 -> 1203 | N75: 45712 | O75: 45708 | P75: 2/25 BV（自检） | Q75: Pass | S75: 外箱四面印刷RFID箱唛 + 顶部ZURU logo黑色色带。主唛右下角加印 MADE IN CHINA | U75: 12/10-RFID贴纸 | V75: 最新扶正ZURU LOGO客版彩盒 | W75: 日期码格式：DGYYYYMMDD(日期避开周末和法定节假日) 日期：按实际生产日期 Packaging Info: 翻单：4500147361 1.包装方式： 25251：最新扶正ZURU LOGO客版彩盒（客版UPC）1L+23L警告语 + MA D版1L说明书 Remark: 2. 外箱四面印刷青色RFID箱唛 + 顶部ZURU logo黑色色带。 主唛左前下角印刷艾利贴纸替代标箱唛(ITF-14格式)，条码只印刷一面。 主唛右下角加印 MADE IN CHINA 3. WM#25251 NEW UPC：193052056092 4. Include 3pcs AAA carbon batteries; 5.此单需要验货，请自行多备包装物料。 6.在产品上和包装上要有日期码、MADE IN CHINA和ZURU字样。 7.此批单都为散箱出货 8.每PCS要加RFID 贴纸，严格按照我们提供的位置图，不可擅自调整位置，贴纸也不可有任何破损或折坏，不可淋湿!!（如缺数请及时告知） | X75: Nikki Mo | Y75: 3.6259 | Z75: =Y75*J75 -> 8723.9154 | AA75: 94415-3.3 | AB75: 2406 | AC75: =AB75-J75 -> 0 | AD75: ok | AE75: 已入 | AF75: 系统出单 | AH75: =J75 -> 2406 | AL75: =J75 -> 2406 | BA75: =J75 -> 2406 | BD75: =SUM(AH75:AJ75) -> 2406 | BE75: =BD75-J75 -> 0
A76: 45652 | B76: «Market Group» LLC | C76: 俄罗斯联邦 | D76: 4500154753 | F76: 4500154753-10 | G76: 25253-S006 | H76: 25253-S006 | I76: 金鱼 | J76: 408 | K76: 4 | L76: 12 | M76: =J76/L76 -> 34 | N76: 45712 | O76: 45708 | Q76: Pass | R76: 2/28出 | S76: 12/26收到 | U76: 1/13-进口商贴纸 +EAN贴纸 | V76: 25253：MA 彩卡 | W76: 日期码格式：ZURU INC(BVI) 标准格式 日期：按实际生产日期 Packaging Info: 1. 25253：MA 彩卡+ 进口商贴纸 +EAN贴纸,+MA说明书 2. 货期不能延后，客人有罚金。 3.需要安排3套大货样，请多备料。 Remark: 标准标配 | X76: Ann Zhang | Y76: 3.5163 | Z76: =Y76*J76 -> 1434.6504 | AA76: 94386-2.27 | AB76: 408 | AC76: =AB76-J76 -> 0 | AD76: ok | AE76: 已入 | AF76: 系统出单 | AJ76: =J76 -> 408 | AL76: =J76 -> 408 | AY76: =J76 -> 408 | BD76: =SUM(AH76:AJ76) -> 408 | BE76: =BD76-J76 -> 0
A77: 45631 | B77: TOYS "R" US (CANADA) LTD. | C77: 加拿大 | D77: 4500153261 | E77: 3501527611 | F77: 4500153261-10 | G77: 25257-S012 | H77: 25257-S012 | I77: 二款混裝 | J77: 996 | K77: 0 | L77: 12 | M77: =J77/L77 -> 83 | N77: 45714 | O77: 45710 | P77: 3/3第三方 | Q77: Pass | R77: 3/5-3/11出 | S77: 1/6收到 | U77: 无 | V77: #25257: 客版英法双语，彩盒说明书翻单4500113747 | W77: 日期码格式：ZURU INC(BVI) 标准格式 日期：按实际生产日期 Packaging Info: 1. 出口加拿大市场 #25257: 客版英法双语，彩盒说明书翻单4500113747。鳄鱼 UPC#845218016425， 鸭子 UPC#845218016418。included 3pcs AAA battery; #25251 Duck/ #25252 Crocodile=6:6. Remark: 2. 需要第三方SGS验货，验货时间暂定2025/02/26，每款每色请备1PC完整带包装样品供验货人员参考。用完后若无损坏可以放回大货里。 | X77: Abby Mai, Lluviazeng | Y77: 23.5305 | Z77: =Y77*M77 -> 1953.0315 | AA77: 94517-3.11 | AB77: 996 | AC77: =AB77-J77 -> 0 | AE77: 已入 | AF77: 系统出单 | AH77: =J77/2 -> 498 | AI77: =J77/2 -> 498 | AM77: =J77 -> 996 | BA77: =J77/2 -> 498 | BB77: =BA77 -> 498 | BD77: =SUM(AH77:AJ77) -> 996 | BE77: =BD77-J77 -> 0
A78: 45674 | B78: WAL-MART STORES INC. USA | C78: 美国 | D78: 4500155349 | E78: 0870169828 | F78: 4500155349-10 | G78: 25251-S002 | H78: 25251-S002 | I78: 鸭子 | J78: 2940 | K78: 0 | L78: 2 | M78: =J78/L78 -> 1470 | N78: 45720 | O78: 45716 | P78: 3/7 BV（自检） | Q78: Pass | R78: 3/24出 | S78: 外箱四面印刷RFID箱唛 + 顶部ZURU logo黑色色带。主唛右下角加印 MADE IN CHINA | U78: 2/18-RFID贴纸 | V78: 最新扶正ZURU LOGO客版彩盒（客版UPC）1L+23L警告语翻单：4500147361 | W78: 日期码格式：DGYYYYMMDD(日期避开周末和法定节假日) 日期：按实际生产日期 Packaging Info: 翻单：4500147361 1.包装方式： 25251：最新扶正ZURU LOGO客版彩盒（客版UPC）1L+23L警告语 + MA D版1L说明书 Remark: 2. 外箱四面印刷青色RFID箱唛 + 顶部ZURU logo黑色色带。 主唛左前下角印刷艾利贴纸替代标箱唛(ITF-14格式)，条码只印刷一面。 主唛右下角加印 MADE IN CHINA 3. WM#25251 NEW UPC：193052056092 4. Include 3pcs AAA carbon batteries; 5.此单需要验货，请自行多备包装物料。 6.在产品上和包装上要有日期码、MADE IN CHINA和ZURU字样。 7.此批单都为散箱出货 8.每PCS要加RFID 贴纸，严格按照我们提供的位置图，不可擅自调整位置，贴纸也不可有任何破损或折坏，不可淋湿!!（如缺数请及时告知） | X78: Nikki Mo | Y78: 3.6259 | Z78: =Y78*J78 -> 10660.146 | AA78: ZB00026-3.21 | AB78: 2940 | AC78: =AB78-J78 -> 0 | AD78: ok | AE78: 已入 | AF78: 系统出单 | AH78: =J78 -> 2940 | AL78: =J78 -> 2940 | BA78: =J78 -> 2940 | BD78: =SUM(AH78:AJ78) -> 2940 | BE78: =BD78-J78 -> 0
A79: 45674 | B79: WAL-MART STORES INC. USA | C79: 美国 | D79: 4500155344 | E79: 0870169817 | F79: 4500155344-10 | G79: 25251-S002 | H79: 25251-S002 | I79: 鸭子 | J79: 1358 | K79: 0 | L79: 2 | M79: =J79/L79 -> 679 | N79: 45720 | O79: 45716 | P79: 3/7 BV（自检） | Q79: Pass | R79: 3/18出 | S79: 外箱四面印刷RFID箱唛 + 顶部ZURU logo黑色色带。主唛右下角加印 MADE IN CHINA | U79: 2/18-RFID贴纸 | V79: 最新扶正ZURU LOGO客版彩盒（客版UPC）1L+23L警告语翻单：4500147361 | W79: 日期码格式：DGYYYYMMDD(日期避开周末和法定节假日) 日期：按实际生产日期 Packaging Info: 翻单：4500147361 1.包装方式： 25251：最新扶正ZURU LOGO客版彩盒（客版UPC）1L+23L警告语 + MA D版1L说明书 Remark: 2. 外箱四面印刷青色RFID箱唛 + 顶部ZURU logo黑色色带。 主唛左前下角印刷艾利贴纸替代标箱唛(ITF-14格式)，条码只印刷一面。 主唛右下角加印 MADE IN CHINA 3. WM#25251 NEW UPC：193052056092 4. Include 3pcs AAA carbon batteries; 5.此单需要验货，请自行多备包装物料。 6.在产品上和包装上要有日期码、MADE IN CHINA和ZURU字样。 7.此批单都为散箱出货 8.每PCS要加RFID 贴纸，严格按照我们提供的位置图，不可擅自调整位置，贴纸也不可有任何破损或折坏，不可淋湿!!（如缺数请及时告知） | X79: Nikki Mo | Y79: 3.7145 | Z79: =Y79*J79 -> 5044.291 | AA79: 94569-3.17 | AB79: 1358 | AC79: =AB79-J79 -> 0 | AD79: ok | AE79: 已入 | AF79: 系统出单 | AH79: =J79 -> 1358 | AL79: =J79 -> 1358 | BA79: =J79 -> 1358 | BD79: =SUM(AH79:AJ79) -> 1358 | BE79: =BD79-J79 -> 0
A80: 45657 | B80: ROSS PROCUREMENT.INC | C80: 美国 | D80: 4500155011 | E80: 60188344 | F80: 4500155011-20 | G80: 25251-S001 | H80: 25251-S001 | I80: 鸭子 | J80: 3408 | K80: 0 | L80: 12 | M80: =J80/L80 -> 284 | N80: 45722 | O80: 45719 | Q80: pass | R80: 3/21出 | S80: 12/31收到 | U80: 2/18-客供价格贴纸 | V80: 1.ZURU MA UPC 现有版本包装 | W80: 日期码格式：ZURU INC(BVI) 标准格式 日期：按实际生产日期 Packaging Info: 1.ZURU MA UPC 现有版本包装 + 客供价格贴纸，出口美国 , 优先使用MA 1L 最新版本 。 Remark: 1.ZURU MA UPC 现有版本包装 + 客供价格贴纸，出口美国 , 优先使用MA 1L 最新版本 。 2.价格贴纸位于包装正面右下角，不挡住重要信息即可，可适当调整 ，价格贴纸由跟单提供。 3.标准日期码格式，产品和包装必须有日期码 。 4.同个产品同个货期不可出现不同的包装。 5. 跟单提供ROSS通用的箱唛模版，工厂按实际45 PO上客户PO/Item号/装箱数 提供箱唛排版来确认。 | X80: Taylor Liao | Y80: 3.2611 | Z80: =Y80*J80 -> 11113.829 | AA80: ZB00028-3.21 | AB80: 3408 | AC80: =AB80-J80 -> 0 | AD80: ok | AE80: 已入 | AF80: 系统出单 | AH80: =J80 -> 3408 | AL80: =J80 -> 3408 | AW80: =J80 -> 3408 | BD80: =SUM(AH80:AJ80) -> 3408 | BE80: =BD80-J80 -> 0
A81: 45657 | B81: ROSS PROCUREMENT.INC | C81: 美国 | D81: 4500155011 | E81: 60188344 | F81: 4500155011-30 | G81: 25253-S001 | H81: 25253-S001 | I81: 金魚 | J81: 1704 | K81: 0 | L81: 12 | M81: =J81/L81 -> 142 | N81: 45722 | O81: 45719 | Q81: pass | R81: 3/21出 | S81: 12/31收到 | U81: 2/18-客供价格贴纸 | V81: 1.ZURU MA UPC 现有版本包装 | W81: 日期码格式：ZURU INC(BVI) 标准格式 日期：按实际生产日期 Packaging Info: 1.ZURU MA UPC 现有版本包装 + 客供价格贴纸，出口美国 , 优先使用MA 1L 最新版本 。 Remark: 1.ZURU MA UPC 现有版本包装 + 客供价格贴纸，出口美国 , 优先使用MA 1L 最新版本 。 2.价格贴纸位于包装正面右下角，不挡住重要信息即可，可适当调整 ，价格贴纸由跟单提供。 3.标准日期码格式，产品和包装必须有日期码 。 4.同个产品同个货期不可出现不同的包装。 5. 跟单提供ROSS通用的箱唛模版，工厂按实际45 PO上客户PO/Item号/装箱数 提供箱唛排版来确认。 | X81: Taylor Liao | Y81: 3.3019 | Z81: =Y81*J81 -> 5626.4376 | AA81: ZB00028-3.21 | AB81: 1704 | AC81: =AB81-J81 -> 0 | AD81: ok | AE81: 已入 | AF81: 系统出单 | AJ81: =J81 -> 1704 | AL81: =J81 -> 1704 | AY81: =J81 -> 1704 | BD81: =SUM(AH81:AJ81) -> 1704 | BE81: =BD81-J81 -> 0
A82: 45666 | B82: PT.MAP Aktif Adiperkasa, Tbk | C82: 印度尼西亚 | D82: 4500155574 | E82: 241227-2MAAJKTQ225-ZURU | F82: 4500155574-30 | G82: 25253-S001 | H82: 25253-S001 | I82: 金魚 | J82: 468 | K82: 0 | L82: 12 | M82: =J82/L82 -> 39 | N82: 45733 | O82: 45729 | Q82: pass | R82: 3/18出 | S82: 1/9收到 | U82: 2/6-进口商贴纸 | W82: 日期码格式：ZURU INC(BVI) 标准格式 日期：按实际生产日期 Packaging Info: MA UPC包装（优先1L)+1张进口商贴纸, 所有item使用含电池信息的进口商贴纸，贴纸待提供 1.可能会被抽大货样做测试，请多备料，CRD前半个月会通知是否有抽到该订单中的item。 2.此订单送普通仓，送仓后会有第三方验货，所以需要按CRD准时完货。 Remark: 25253-3PCS AAA Batteries(Include) | X82: Emma Wu | Y82: 3.8029 | Z82: =Y82*J82 -> 1779.7572 | AB82: 468 | AC82: =AB82-J82 -> 0 | AD82: ok | AE82: 已入 | AF82: 系统出单 | AJ82: =J82 -> 468 | AL82: =J82 -> 468 | AY82: =J82 -> 468 | BD82: =SUM(AH82:AJ82) -> 468 | BE82: =BD82-J82 -> 0
A83: 45674 | B83: WAL-MART STORES INC. USA | C83: 美国 | D83: 4500155352 | E83: 0870169767 | F83: 4500155352-10 | G83: 25251-S002 | H83: 25251-S002 | I83: 鸭子 | J83: 1246 | K83: 0 | L83: 2 | M83: =J83/L83 -> 623 | N83: 45733 | O83: 45729 | P83: 3/18 BV（自检） | Q83: Pass | R83: 3/18出 | S83: 外箱四面印刷RFID箱唛 + 顶部ZURU logo黑色色带。主唛右下角加印 MADE IN CHINA | U83: 2/18-RFID贴纸 | V83: 最新扶正ZURU LOGO客版彩盒（客版UPC）1L+23L警告语翻单：4500147361 | W83: 日期码格式：DGYYYYMMDD(日期避开周末和法定节假日) 日期：按实际生产日期 Packaging Info: 翻单：4500147361 1.包装方式： 25251：最新扶正ZURU LOGO客版彩盒（客版UPC）1L+23L警告语 + MA D版1L说明书 Remark: 2. 外箱四面印刷青色RFID箱唛 + 顶部ZURU logo黑色色带。 主唛左前下角印刷艾利贴纸替代标箱唛(ITF-14格式)，条码只印刷一面。 主唛右下角加印 MADE IN CHINA 3. WM#25251 NEW UPC：193052056092 4. Include 3pcs AAA carbon batteries; 5.此单需要验货，请自行多备包装物料。 6.在产品上和包装上要有日期码、MADE IN CHINA和ZURU字样。 7.此批单都为散箱出货 8.每PCS要加RFID 贴纸，严格按照我们提供的位置图，不可擅自调整位置，贴纸也不可有任何破损或折坏，不可淋湿!!（如缺数请及时告知） | X83: Nikki Mo | Y83: 3.7145 | Z83: =Y83*J83 -> 4628.267 | AA83: ZB00010-3.19 | AB83: =1244+2 -> 1246 | AC83: =AB83-J83 -> 0 | AD83: ok | AE83: 已入 | AF83: 系统出单 | AH83: =J83 -> 1246 | AL83: =J83 -> 1246 | BA83: =J83 -> 1246 | BD83: =SUM(AH83:AJ83) -> 1246 | BE83: =BD83-J83 -> 0
A84: 45674 | B84: WAL-MART STORES INC. USA | C84: 美国 | D84: 4500155351 | E84: 0870169776 | F84: 4500155351-10 | G84: 25251-S002 | H84: 25251-S002 | I84: 鸭子 | J84: 976 | K84: 0 | L84: 2 | M84: =J84/L84 -> 488 | N84: 45734 | O84: 45730 | P84: 3/18 BV（自检） | Q84: Pass | S84: 外箱四面印刷RFID箱唛 + 顶部ZURU logo黑色色带。主唛右下角加印 MADE IN CHINA | U84: 2/18-RFID贴纸 | V84: 最新扶正ZURU LOGO客版彩盒（客版UPC）1L+23L警告语翻单：4500147361 | W84: 日期码格式：DGYYYYMMDD(日期避开周末和法定节假日) 日期：按实际生产日期 Packaging Info: 翻单：4500147361 1.包装方式： 25251：最新扶正ZURU LOGO客版彩盒（客版UPC）1L+23L警告语 + MA D版1L说明书 Remark: 2. 外箱四面印刷青色RFID箱唛 + 顶部ZURU logo黑色色带。 主唛左前下角印刷艾利贴纸替代标箱唛(ITF-14格式)，条码只印刷一面。 主唛右下角加印 MADE IN CHINA 3. WM#25251 NEW UPC：193052056092 4. Include 3pcs AAA carbon batteries; 5.此单需要验货，请自行多备包装物料。 6.在产品上和包装上要有日期码、MADE IN CHINA和ZURU字样。 7.此批单都为散箱出货 8.每PCS要加RFID 贴纸，严格按照我们提供的位置图，不可擅自调整位置，贴纸也不可有任何破损或折坏，不可淋湿!!（如缺数请及时告知） | X84: Nikki Mo | Y84: 4.0771 | Z84: =Y84*J84 -> 3979.2496 | AA84: ZB00048-3.26 | AB84: 976 | AC84: =AB84-J84 -> 0 | AD84: ok | AE84: 已入 | AF84: 系统出单 | AH84: =J84 -> 976 | AL84: =J84 -> 976 | BA84: =J84 -> 976 | BD84: =SUM(AH84:AJ84) -> 976 | BE84: =BD84-J84 -> 0
A85: 45674 | B85: WAL-MART STORES INC. USA | C85: 美国 | D85: 4500155350 | E85: 0870169821 | F85: 4500155350-10 | G85: 25251-S002 | H85: 25251-S002 | I85: 鸭子 | J85: 1370 | K85: 0 | L85: 2 | M85: =J85/L85 -> 685 | N85: 45734 | O85: 45730 | P85: 3/18 BV（自检） | Q85: Pass | R85: 3/29出 | S85: 外箱四面印刷RFID箱唛 + 顶部ZURU logo黑色色带。主唛右下角加印 MADE IN CHINA | U85: 2/18-RFID贴纸 | V85: 最新扶正ZURU LOGO客版彩盒（客版UPC）1L+23L警告语翻单：4500147361 | W85: 日期码格式：DGYYYYMMDD(日期避开周末和法定节假日) 日期：按实际生产日期 Packaging Info: 翻单：4500147361 1.包装方式： 25251：最新扶正ZURU LOGO客版彩盒（客版UPC）1L+23L警告语 + MA D版1L说明书 Remark: 2. 外箱四面印刷青色RFID箱唛 + 顶部ZURU logo黑色色带。 主唛左前下角印刷艾利贴纸替代标箱唛(ITF-14格式)，条码只印刷一面。 主唛右下角加印 MADE IN CHINA 3. WM#25251 NEW UPC：193052056092 4. Include 3pcs AAA carbon batteries; 5.此单需要验货，请自行多备包装物料。 6.在产品上和包装上要有日期码、MADE IN CHINA和ZURU字样。 7.此批单都为散箱出货 8.每PCS要加RFID 贴纸，严格按照我们提供的位置图，不可擅自调整位置，贴纸也不可有任何破损或折坏，不可淋湿!!（如缺数请及时告知） | X85: Nikki Mo | Y85: 3.7145 | Z85: =Y85*J85 -> 5088.865 | AA85: ZB00049-3.26 | AB85: 1370 | AC85: =AB85-J85 -> 0 | AD85: ok | AE85: 已入 | AF85: 系统出单 | AH85: =J85 -> 1370 | AL85: =J85 -> 1370 | BA85: =J85 -> 1370 | BD85: =SUM(AH85:AJ85) -> 1370 | BE85: =BD85-J85 -> 0
A86: 45674 | B86: WAL-MART STORES INC. USA | C86: 美国 | D86: 4500155368 | E86: 0870169793 | F86: 4500155368-10 | G86: 25251-S002 | H86: 25251-S002 | I86: 鸭子 | J86: 962 | K86: 0 | L86: 2 | M86: =J86/L86 -> 481 | N86: 45740 | O86: 45736 | P86: 3/26 BV（自检） | Q86: Pass | R86: 3/29出 | S86: 外箱四面印刷RFID箱唛 + 顶部ZURU logo黑色色带。主唛右下角加印 MADE IN CHINA | U86: 2/18-RFID贴纸 | V86: 最新扶正ZURU LOGO客版彩盒（客版UPC）1L+23L警告语翻单：4500147361 | W86: 日期码格式：DGYYYYMMDD(日期避开周末和法定节假日) 日期：按实际生产日期 Packaging Info: 翻单：4500147361 1.包装方式： 25251：最新扶正ZURU LOGO客版彩盒（客版UPC）1L+23L警告语 + MA D版1L说明书 Remark: 2. 外箱四面印刷青色RFID箱唛 + 顶部ZURU logo黑色色带。 主唛左前下角印刷艾利贴纸替代标箱唛(ITF-14格式)，条码只印刷一面。 主唛右下角加印 MADE IN CHINA 3. WM#25251 NEW UPC：193052056092 4. Include 3pcs AAA carbon batteries; 5.此单需要验货，请自行多备包装物料。 6.在产品上和包装上要有日期码、MADE IN CHINA和ZURU字样。 7.此批单都为散箱出货 8.每PCS要加RFID 贴纸，严格按照我们提供的位置图，不可擅自调整位置，贴纸也不可有任何破损或折坏，不可淋湿!!（如缺数请及时告知） | X86: Nikki Mo | Y86: 4.0771 | Z86: =Y86*J86 -> 3922.1702 | AA86: ZB00075-3.29 | AB86: 962 | AC86: =AB86-J86 -> 0 | AD86: ok | AE86: 已入 | AF86: 系统出单 | AH86: =J86 -> 962 | AL86: =J86 -> 962 | BA86: =J86 -> 962 | BD86: =SUM(AH86:AJ86) -> 962 | BE86: =BD86-J86 -> 0
A87: 45674 | B87: WAL-MART STORES INC. USA | C87: 美国 | D87: 4500155353 | E87: 0870169779 | F87: 4500155353-10 | G87: 25251-S002 | H87: 25251-S002 | I87: 鸭子 | J87: 1570 | K87: 0 | L87: 2 | M87: =J87/L87 -> 785 | N87: 45742 | O87: 45738 | P87: 3/26 BV（自检） | Q87: Pass | R87: 4/1出 | S87: 外箱四面印刷RFID箱唛 + 顶部ZURU logo黑色色带。主唛右下角加印 MADE IN CHINA | U87: 2/18-RFID贴纸 | V87: 最新扶正ZURU LOGO客版彩盒（客版UPC）1L+23L警告语翻单：4500147361 | W87: 日期码格式：DGYYYYMMDD(日期避开周末和法定节假日) 日期：按实际生产日期 Packaging Info: 翻单：4500147361 1.包装方式： 25251：最新扶正ZURU LOGO客版彩盒（客版UPC）1L+23L警告语 + MA D版1L说明书 Remark: 2. 外箱四面印刷青色RFID箱唛 + 顶部ZURU logo黑色色带。 主唛左前下角印刷艾利贴纸替代标箱唛(ITF-14格式)，条码只印刷一面。 主唛右下角加印 MADE IN CHINA 3. WM#25251 NEW UPC：193052056092 4. Include 3pcs AAA carbon batteries; 5.此单需要验货，请自行多备包装物料。 6.在产品上和包装上要有日期码、MADE IN CHINA和ZURU字样。 7.此批单都为散箱出货 8.每PCS要加RFID 贴纸，严格按照我们提供的位置图，不可擅自调整位置，贴纸也不可有任何破损或折坏，不可淋湿!!（如缺数请及时告知） | X87: Nikki Mo | Y87: 3.7145 | Z87: =Y87*J87 -> 5831.765 | AA87: ZB00124-4.10 | AB87: 1570 | AC87: =AB87-J87 -> 0 | AD87: ok | AE87: 已入 | AF87: 系统出单 | AH87: =J87 -> 1570 | AL87: =J87 -> 1570 | BA87: =J87 -> 1570 | BD87: =SUM(AH87:AJ87) -> 1570 | BE87: =BD87-J87 -> 0
A88: 45701 | B88: TJX COMPANIES, INC | C88: 美国 | D88: 4500157297 | E88: Marshalls DC#881-132PCS , DC#884-96PCS, DC#886-144PCS , DC#887-108PCS , DC#888-120PCS | F88: 4500157297-110 | G88: 25252-S001 | H88: 25252-S001 | I88: 鱷魚 | J88: 600 | K88: 0 | L88: 12 | M88: =J88/L88 -> 50 | N88: 45742 | O88: 45738 | Q88: Pass | R88: 3/27出 | S88: 2/13收到 | T88: 无 | U88: 3/4-价格贴纸 | W88: 日期码格式：ZURU INC(BVI) 标准格式 日期：按实际生产日期 Packaging Info: MA UPC包装+价格贴纸，价格贴纸客供。 Remark: 1. 产品和包装上印刷tracking code信息，格式为ZURU常规格式。 2. 分5个DC出货，每款产品每个DC的箱唛资料不同。具体分DC数量，请参考后面行项目备注。 3. ZURU QC验货。 | X88: Emily Wu | Y88: 4.0344 | Z88: =Y88*J88 -> 2420.64 | AA88: ZB00100-4.3/ZB00053-3.27 | AB88: 600 | AC88: =AB88-J88 -> 0 | AD88: OK | AE88: 已入 | AF88: 系统出单 | AI88: =J88 -> 600 | AL88: =J88 -> 600 | AX88: =J88 -> 600 | BD88: =SUM(AH88:AJ88) -> 600 | BE88: =BD88-J88 -> 0
A89: 45701 | B89: TJX COMPANIES, INC | C89: 美国 | D89: 4500157297 | E89: Marshalls DC#881-132PCS , DC#884-96PCS, DC#886-132PCS , DC#887-120PCS, DC#888-120PCS | F89: 4500157297-120 | G89: 25253-S001 | H89: 25253-S001 | I89: 金魚 | J89: 600 | K89: 0 | L89: 12 | M89: =J89/L89 -> 50 | N89: 45742 | O89: 45738 | Q89: Pass | R89: 3/27出 | S89: 2/13收到 | T89: 无 | U89: 3/4-价格贴纸 | W89: 日期码格式：ZURU INC(BVI) 标准格式 日期：按实际生产日期 Packaging Info: MA UPC包装+价格贴纸，价格贴纸客供。 Remark: 1. 产品和包装上印刷tracking code信息，格式为ZURU常规格式。 2. 分5个DC出货，每款产品每个DC的箱唛资料不同。具体分DC数量，请参考后面行项目备注。 3. ZURU QC验货。 | X89: Emily Wu | Y89: 3.7168 | Z89: =Y89*J89 -> 2230.08 | AA89: ZB00100-4.3/ZB00053-3.27 | AB89: 600 | AC89: =AB89-J89 -> 0 | AD89: OK | AE89: 已入 | AF89: 系统出单 | AJ89: =J89 -> 600 | AL89: =J89 -> 600 | AY89: =J89 -> 600 | BD89: =SUM(AH89:AJ89) -> 600 | BE89: =BD89-J89 -> 0
A90: 45701 | B90: TJX COMPANIES, INC | C90: 美国 | D90: 4500157300 | E90: TJ MAXX DC#891-168PCS , DC#894-132PCS , DC#896-120PCS , DC#897-252PCS , DC#898-132PCS | F90: 4500157300-110 | G90: 25252-S001 | H90: 25252-S001 | I90: 鱷魚 | J90: 804 | K90: 0 | L90: 12 | M90: =J90/L90 -> 67 | N90: 45742 | O90: 45738 | Q90: Pass | R90: 3/31出 | S90: 2/13收到 | T90: 无 | U90: 3/6-价格贴纸 | W90: 日期码格式：ZURU INC(BVI) 标准格式 日期：按实际生产日期 Packaging Info: MA UPC包装+价格贴纸，价格贴纸客供。 Remark: 1. 产品和包装上印刷tracking code信息，格式为ZURU常规格式。 2. 分5个DC出货，每款产品每个DC的箱唛资料不同。具体分DC数量，请参考后面行项目备注。 3. ZURU QC验货。 | X90: Emily Wu | Y90: 4.0344 | Z90: =Y90*J90 -> 3243.6576 | AA90: ZB00099-4.3/ZB00060-3.28/ZB00074-3.29 | AB90: 804 | AC90: =AB90-J90 -> 0 | AD90: OK | AE90: 已入 | AF90: 系统出单 | AI90: =J90 -> 804 | AL90: =J90 -> 804 | AX90: =J90 -> 804 | BD90: =SUM(AH90:AJ90) -> 804 | BE90: =BD90-J90 -> 0
A91: 45701 | B91: TJX COMPANIES, INC | C91: 美国 | D91: 4500157300 | E91: TJ MAXX DC#891-168PCS , DC#894-132PCS , DC#896-120PCS , DC#897-252PCS , DC#898-132PCS | F91: 4500157300-120 | G91: 25253-S001 | H91: 25253-S001 | I91: 金魚 | J91: 804 | K91: 0 | L91: 12 | M91: =J91/L91 -> 67 | N91: 45742 | O91: 45738 | Q91: Pass | R91: 3/31出 | S91: 2/13收到 | T91: 无 | U91: 3/6-价格贴纸 | W91: 日期码格式：ZURU INC(BVI) 标准格式 日期：按实际生产日期 Packaging Info: MA UPC包装+价格贴纸，价格贴纸客供。 Remark: 1. 产品和包装上印刷tracking code信息，格式为ZURU常规格式。 2. 分5个DC出货，每款产品每个DC的箱唛资料不同。具体分DC数量，请参考后面行项目备注。 3. ZURU QC验货。 | X91: Emily Wu | Y91: 3.7168 | Z91: =Y91*J91 -> 2988.3072 | AA91: ZB00099-4.3/ZB00060-3.28/ZB00074-3.29 | AB91: 804 | AC91: =AB91-J91 -> 0 | AD91: OK | AE91: 已入 | AF91: 系统出单 | AJ91: =J91 -> 804 | AL91: =J91 -> 804 | AY91: =J91 -> 804 | BD91: =SUM(AH91:AJ91) -> 804 | BE91: =BD91-J91 -> 0
A92: 45674 | B92: WAL-MART STORES INC. USA | C92: 美国 | D92: 4500155356 | E92: 0870169786 | F92: 4500155356-10 | G92: 25251-S002 | H92: 25251-S002 | I92: 鸭子 | J92: 544 | K92: 0 | L92: 2 | M92: =J92/L92 -> 272 | N92: 45748 | O92: 45745 | P92: 4/2 BV（自检） | Q92: Pass | R92: 4/4-4/6出 | S92: 外箱四面印刷RFID箱唛 + 顶部ZURU logo黑色色带。主唛右下角加印 MADE IN CHINA | U92: 2/18-RFID贴纸 | V92: 最新扶正ZURU LOGO客版彩盒（客版UPC）1L+23L警告语翻单：4500147361 | W92: 日期码格式：DGYYYYMMDD(日期避开周末和法定节假日) 日期：按实际生产日期 Packaging Info: 翻单：4500147361 1.包装方式： 25251：最新扶正ZURU LOGO客版彩盒（客版UPC）1L+23L警告语 + MA D版1L说明书 Remark: 2. 外箱四面印刷青色RFID箱唛 + 顶部ZURU logo黑色色带。 主唛左前下角印刷艾利贴纸替代标箱唛(ITF-14格式)，条码只印刷一面。 主唛右下角加印 MADE IN CHINA 3. WM#25251 NEW UPC：193052056092 4. Include 3pcs AAA carbon batteries; 5.此单需要验货，请自行多备包装物料。 6.在产品上和包装上要有日期码、MADE IN CHINA和ZURU字样。 7.此批单都为散箱出货 8.每PCS要加RFID 贴纸，严格按照我们提供的位置图，不可擅自调整位置，贴纸也不可有任何破损或折坏，不可淋湿!!（如缺数请及时告知） | X92: Nikki Mo | Y92: 4.0771 | Z92: =Y92*J92 -> 2217.9424 | AA92: ZB00109-4.8 | AB92: =542+2 -> 544 | AC92: =AB92-J92 -> 0 | AD92: ok | AE92: 已入 | AF92: 系统出单 | AH92: =J92 -> 544 | AL92: =J92 -> 544 | BA92: =J92 -> 544 | BD92: =SUM(AH92:AJ92) -> 544 | BE92: =BD92-J92 -> 0
A93: 45674 | B93: WAL-MART STORES INC. USA | C93: 美国 | D93: 4500155357 | E93: 0870169846 | F93: 4500155357-10 | G93: 25251-S002 | H93: 25251-S002 | I93: 鸭子 | J93: 1176 | K93: 0 | L93: 2 | M93: =J93/L93 -> 588 | N93: 45748 | O93: 45745 | P93: 4/2 BV（自检） | Q93: Pass | R93: 4/16出 | S93: 外箱四面印刷RFID箱唛 + 顶部ZURU logo黑色色带。主唛右下角加印 MADE IN CHINA | U93: 2/18-RFID贴纸 | V93: 最新扶正ZURU LOGO客版彩盒（客版UPC）1L+23L警告语翻单：4500147361 | W93: 日期码格式：DGYYYYMMDD(日期避开周末和法定节假日) 日期：按实际生产日期 Packaging Info: 翻单：4500147361 1.包装方式： 25251：最新扶正ZURU LOGO客版彩盒（客版UPC）1L+23L警告语 + MA D版1L说明书 Remark: 2. 外箱四面印刷青色RFID箱唛 + 顶部ZURU logo黑色色带。 主唛左前下角印刷艾利贴纸替代标箱唛(ITF-14格式)，条码只印刷一面。 主唛右下角加印 MADE IN CHINA 3. WM#25251 NEW UPC：193052056092 4. Include 3pcs AAA carbon batteries; 5.此单需要验货，请自行多备包装物料。 6.在产品上和包装上要有日期码、MADE IN CHINA和ZURU字样。 7.此批单都为散箱出货 8.每PCS要加RFID 贴纸，严格按照我们提供的位置图，不可擅自调整位置，贴纸也不可有任何破损或折坏，不可淋湿!!（如缺数请及时告知） | X93: Nikki Mo | Y93: 3.7145 | Z93: =Y93*J93 -> 4368.252 | AA93: ZB00139-4.16 | AB93: 1176 | AC93: =AB93-J93 -> 0 | AD93: ok | AE93: 已入 | AF93: 系统出单 | AH93: =J93 -> 1176 | AL93: =J93 -> 1176 | BA93: =J93 -> 1176 | BD93: =SUM(AH93:AJ93) -> 1176 | BE93: =BD93-J93 -> 0
A94: 45677 | B94: ICA Sverige AB | C94: 美国 | D94: 4500156207 | E94: 751436/32407 | F94: 4500156207-10 | G94: 25257-S001-1 | H94: 25257-S001 | I94: 三款混裝 | J94: 1170 | K94: 0 | L94: 6 | M94: =J94/L94 -> 195 | N94: 45748 | O94: 45745 | Q94: Pass | R94: 4/8出 | S94: 2/24收到 | U94: EAN贴纸翻4500145931 | V94: 2/20-客办收藏指南文档 | W94: 日期码格式：ZURU INC(BVI) 标准格式 日期：按实际生产日期 Packaging Info: 1.25257: (25251+25252+25253) MA 1L-23warning 包装+EAN贴纸(贴纸和位置图翻PO#4500145931)+客版说明书(英语/瑞典语/芬兰语/冰岛语/丹麦语) Duck/ Crocodile/ Fish=2:2:2 Remark: 1. 包装如含PVC,请改为PET并第一时间通知跟单 2. 产品/包装要求无硼无香，出欧洲，微塑料需合规。 3. ICA针对带电池出货的产品，都要用碱性电池 4. 不能出带军事元素的产品，如有:请拿掉并告知跟单 5.带电池出货的产品所用到的电池需要符合欧洲电池新规(EU) 2023-1542 6.有胶袋的产品：要求产品的胶袋厚度要大于等于0.05mm 7.关于贴纸，如果贴纸位置图的包装版本与大货不一致，请工厂第一时间提前提出。跟单会重新调整确认是否更新贴纸或调整位置图 8.产品/包装不含PFAS成分 9.产品条码如下: 请先检查条码是否正确再安排做货，如有问题请告知 ZURU ITEM#<(>&<)>Customer SKU#<(>&<)>EAN#<(>&<)>GTIN# 25257-S001<(>&<)>616086<(>&<)>6946441305844<(>&<)>26946441305848 | X94: Sheba Ye | Y94: 24.2136 | Z94: =Y94*M94 -> 4721.652 | AA94: 94708-4.7 | AB94: 1170 | AC94: =AB94-J94 -> 0 | AD94: ok | AE94: 已入 | AF94: 系统出单 | AH94: =J94/3 -> 390 | AI94: =J94/3 -> 390 | AJ94: =J94/3 -> 390 | AM94: =J94 -> 1170 | AW94: =J94/3 -> 390 | AX94: =J94/3 -> 390 | AY94: =J94/3 -> 390 | BD94: =SUM(AH94:AJ94) -> 1170 | BE94: =BD94-J94 -> 0
A95: 45716 | B95: Smyths Toys EU HQ UC | C95: 德国 | D95: 4500158935 | E95: 4400468554 | F95: 4500158935-30 | G95: 25251-S001-7 | H95: 25251-S001 | I95: 鸭子 | J95: 2208 | K95: 0 | L95: 12 | M95: =J95/L95 -> 184 | N95: 45750 | O95: 45747 | Q95: Pass | S95: 3/4收到 | U95: 德语/法语callout贴纸翻4500138425+客版说明书+（英法德意荷含WEEE声明) | V95: 所有电子产品身上需要加字唛，为ZURU FRANCE 地址 (如无电子产品，或者产品布标有此地址，可忽略此信息) ZURU France 1/3, Rue d'Argenteuil 95210 SAINT-GRATIEN, FRANCE | W95: 日期码格式：ZURU INC(BVI) 标准格式 日期：按实际生产日期 Packaging Info: 25251: 最新MA 1L-23L Warning UPC版包装+德语/法语callout贴纸翻PO#4500138425+客版说明书（英法德意荷含WEEE声明) UPC#845218016418 Remark: 1. 此单出德国，需要满足Zuru Standard欧洲标准测试要求； 2. 请准时出货，推期会有罚款； 3. 出口欧洲，微塑料需符合法规。 4. 大货样品一套 5. 所有电子产品身上需要加字唛，为ZURU FRANCE 地址 (如无电子产品，或者产品布标有此地址，可忽略此信息) ZURU France 1/3, Rue d'Argenteuil 95210 SAINT-GRATIEN, FRANCE 6. 标准配比 7. 所有出往德国订单的电子产品需增加一张客版WEEE声明通用说明书纸，区分带电池和不带电池版本。如已做客版说明书可忽略此要求。 | X95: Shirley Zhou | Y95: 3.4606 | Z95: =Y95*J95 -> 7641.0048 | AA95: 94729-4.9 | AB95: =1080+1128 -> 2208 | AC95: =AB95-J95 -> 0 | AD95: ok | AE95: 已入 | AF95: 系统出单 | AH95: =J95 -> 2208 | AM95: =J95 -> 2208 | BD95: =SUM(AH95:AJ95) -> 2208 | BE95: =BD95-J95 -> 0
A96: 45765 | B96: DM LLC | C96: 俄罗斯联邦 | D96: 4500163959 | E96: 包装要求参考4 500150271, 出 Bekasovo 2 | F96: 4500163959-10 | G96: 25252-S001 | H96: 25252-S001 | I96: 鱷魚 | J96: 96 | K96: 0 | L96: 12 | M96: =J96/L96 -> 8 | N96: 45765 | O96: 45761 | P96: 原4500150271 转单-注意不要重复生产 | Q96: Pass | R96: 4/28出 | S96: 11/4收到 | U96: 11/26-进口商贴纸+ EAN条码贴纸 | V96: 日期码格式：外包装/外箱不要打ZURU标准日期码 | W96: 日期码格式：外包装/外箱不要打ZURU标准日期码 日期： Packaging Info: 取代4500150271/4500157991/4500146630/4500159461/4500158543中 对应的款 ; 包装要求参考4500150271/4500157991/4500146630/4500159461/4500158543 Remark: | X96: Ann | Y96: 3.9509 | Z96: =Y96*J96 -> 379.2864 | AA96: 94862-4.28 | AB96: 96 | AC96: =AB96-J96 -> 0 | AE96: 已入 | AF96: 系统出单 | AI96: =J96 -> 96 | AL96: =J96 -> 96 | AX96: =J96 -> 96 | BD96: =SUM(AH96:AJ96) -> 96 | BE96: =BD96-J96 -> 0
A97: 45720 | B97: TJX CANADA | C97: 加拿大 | D97: 4500158924 | E97: 客户PO 30369077 | F97: 4500158924-30 | G97: 25252-S001-5 | H97: 25252-S001 | I97: 鱷魚 | J97: 600 | K97: 0 | L97: 12 | M97: =J97/L97 -> 50 | N97: 45768 | O97: 45764 | Q97: Pass | S97: 3/4收到 | U97: 3/31-客供价格贴纸 | V97: 3/13-客版英法包装（新稿）说明书翻单4500132627 | W97: 日期码格式：ZURU INC(BVI) 标准格式 日期：按实际生产日期 Packaging Info: 25252 客版英法彩盒，说明书翻单4500132627。UPC号码845218016425 Remark: 出加拿大 有客供价格贴 每行对应不同的客户PO， 客户PO已分别备注 Zuru验货.日期跟踪码：产品外包装及产品本身都必须有日期跟踪码，ZURU标准格式 日期码 | X97: Summer Mo | Y97: 3.6195 | Z97: =Y97*J97 -> 2171.7 | AA97: 94814-4.22 | AB97: 600 | AC97: =AB97-J97 -> 0 | AD97: OK | AE97: 已入 | AF97: 系统出单 | AI97: =J97 -> 600 | AM97: =J97 -> 600 | BB97: =J97 -> 600 | BD97: =SUM(AH97:AJ97) -> 600 | BE97: =BD97-J97 -> 0
A98: 45720 | B98: TJX CANADA | C98: 加拿大 | D98: 4500158924 | E98: 客户PO 30369077 | F98: 4500158924-40 | G98: 25253-S001-7 | H98: 25253-S001 | I98: 金魚 | J98: 600 | K98: 0 | L98: 12 | M98: =J98/L98 -> 50 | N98: 45768 | O98: 45764 | Q98: Pass | S98: 3/4收到 | U98: 3/31-客供价格贴纸 | V98: 3/13-客版英法包装（新稿）说明书翻单4500132627 | W98: 日期码格式：ZURU INC(BVI) 标准格式 日期：按实际生产日期 Packaging Info: 25253 客版英法彩盒，说明书翻单4500132627。UPC号码845218016432 Remark: 出加拿大 有客供价格贴 每行对应不同的客户PO， 客户PO已分别备注 Zuru验货.日期跟踪码：产品外包装及产品本身都必须有日期跟踪码，ZURU标准格式 日期码 | X98: Summer Mo | Y98: 3.3019 | Z98: =Y98*J98 -> 1981.14 | AA98: 94814-4.22 | AB98: 600 | AC98: =AB98-J98 -> 0 | AD98: OK | AE98: 已入 | AF98: 系统出单 | AJ98: =J98 -> 600 | AM98: =J98 -> 600 | BC98: =J98 -> 600 | BD98: =SUM(AH98:AJ98) -> 600 | BE98: =BD98-J98 -> 0
A99: 45720 | B99: TJX CANADA | C99: 加拿大 | D99: 4500158924 | E99: 客户PO 30369179 | F99: 4500158924-130 | G99: 25252-S001-5 | H99: 25252-S001 | I99: 鱷魚 | J99: 216 | K99: 0 | L99: 12 | M99: =J99/L99 -> 18 | N99: 45768 | O99: 45764 | Q99: Pass | S99: 3/4收到 | U99: 3/31-客供价格贴纸 | V99: 3/13-客版英法包装（新稿）说明书翻单4500132627 | W99: 日期码格式：ZURU INC(BVI) 标准格式 日期：按实际生产日期 Packaging Info: 25252 客版英法彩盒，说明书翻单4500132627。UPC号码845218016425 Remark: 出加拿大 有客供价格贴 每行对应不同的客户PO， 客户PO已分别备注 Zuru验货.日期跟踪码：产品外包装及产品本身都必须有日期跟踪码，ZURU标准格式 日期码 | X99: Summer Mo | Y99: 3.6195 | Z99: =Y99*J99 -> 781.812 | AA99: 94814-4.22 | AB99: 216 | AC99: =AB99-J99 -> 0 | AD99: OK | AE99: 已入 | AF99: 系统出单 | AI99: =J99 -> 216 | AM99: =J99 -> 216 | BB99: =J99 -> 216 | BD99: =SUM(AH99:AJ99) -> 216 | BE99: =BD99-J99 -> 0
A100: 45720 | B100: TJX CANADA | C100: 加拿大 | D100: 4500158924 | E100: 客户PO 30369212 | F100: 4500158924-140 | G100: 25253-S001-7 | H100: 25253-S001 | I100: 金魚 | J100: 216 | K100: 0 | L100: 12 | M100: =J100/L100 -> 18 | N100: 45768 | O100: 45764 | Q100: Pass | S100: 3/4收到 | U100: 3/31-客供价格贴纸 | V100: 3/13-客版英法包装（新稿）说明书翻单4500132627 | W100: 日期码格式：ZURU INC(BVI) 标准格式 日期：按实际生产日期 Packaging Info: 25253 客版英法彩盒，说明书翻单4500132627。UPC号码845218016432 Remark: 出加拿大 有客供价格贴 每行对应不同的客户PO， 客户PO已分别备注 Zuru验货.日期跟踪码：产品外包装及产品本身都必须有日期跟踪码，ZURU标准格式 日期码 | X100: Summer Mo | Y100: 3.3019 | Z100: =Y100*J100 -> 713.2104 | AA100: 94814-4.22 | AB100: 216 | AC100: =AB100-J100 -> 0 | AD100: OK | AE100: 已入 | AF100: 系统出单 | AJ100: =J100 -> 216 | AM100: =J100 -> 216 | BC100: =J100 -> 216 | BD100: =SUM(AH100:AJ100) -> 216 | BE100: =BD100-J100 -> 0
...

Sheet 7163-66
A1: ZURU Baby shark playset 滑道鲨鱼生产排期表 #25291
A2: =鴨子、鱷魚、金魚排期!A2 -> 44982 | AJ2: 7163 | AR2: 7175A | AS2: 7175B | AT2: 7166
A3: 香港接单日期 | B3: 第三方客户名称 | C3: 走货国家 | D3: ZURU PO NO# | E3: 第三方客户 PO NO# | F3: SKU | G3: 系统货号 | H3: ITEM# | I3: 中文名 | J3: PO数量 (pcs) | K3: 外箱装箱数量(pcs) | L3: 外箱装箱数量(pcs) | M3: 总箱数 | N3: 计划出货期 | O3: 计划验货期 | P3: 第三方客户公证行验货 | Q3: 驗貨結果 | R3: ZURU确认走货日期 | S3: 箱唛资料(收到日期) | T3: 外箱贴纸 | U3: 客供贴纸AI(收到日期) | V3: 包装 | W3: 备注 | X3: ZURU 跟单 | Y3: 单价USD | Z3: 金额USD | AA3: 發票號 | AB3: 送货情况 | AC3: 欠数 | AD3: 贴纸情况 | AE3: 是否入系统 | AF3: 系统出单 | AG3: 黄色小鲨鱼 | AH3: 蓝色小鲨鱼 | AI3: 粉色小鲨鱼 | AJ3: 2023-MA-1L彩盒 | AK3: 2023-MA-3L彩盒 | AL3: 2023-MA-9L说明书(7163/7175/7166)共用 | AM3: MA 1L-3L (共用PDQ）（2023新） | AN3: MA 1L-3L (共用PDQ）（2025新） | AO3: 客版彩盒 | AP3: 客版说明书 | AQ3: 客版PDQ | AR3: WM客版彩盒 | AS3: WM客版彩盒 | AT3: MA 1语彩盒 B版本 | AU3: MA 3语彩盒 B版本 | AV3: PDQ-7175/7166共用
A4: 45608 | B4: CMS FAMOUS TOYS | C4: 加拿大 | D4: 4500151018 | E4: PO0000475 | F4: 4500151018-50 | G4: 7163-2023-S003-3L-V1 | H4: 7163-2023-S003 | I4: 小鲨鱼 | J4: 240 | K4: 0 | L4: 24 | M4: =J4/L4 -> 10 | N4: 45651 | O4: 45647 | Q4: PASS | S4: 11/25收到 | U4: 11/25-UPC 贴纸 | V4: 7163 MA 多语版包装 | W4: 日期码格式： 标准格式 日期：按实际生产日期 Packaging Info: 7163 MA 多语版包装+UPC 贴纸。UPC号码193052062604 Remark: 出加拿大 每款产品都需要加进口商贴纸 Zuru验货.日期跟踪码：产品外包装及产品本身都必须有日期跟踪码，ZURU标准格式日期码 | X4: Summer Mo | Y4: 1.4655 | Z4: =Y4*J4 -> 351.72 | AA4: 88842-1.2 | AB4: 240 | AC4: =AB4-J4 -> 0 | AD4: OK | AE4: 已入 | AF4: 系统出单 | AG4: =J4/3 -> 80 | AH4: =J4/3 -> 80 | AI4: =J4/3 -> 80 | AK4: =J4 -> 240 | AL4: =J4 -> 240
A5: 45608 | B5: Amazon CA (Vendor Center) | C5: 加拿大 | D5: 4500150978 | E5: 222PB6UC | F5: 4500150978-160 | G5: 7166-2023-S002-V1-3L | H5: 7166-2023-S002 | I5: 小鲨鱼3PK | J5: 18 | K5: 0 | L5: 18 | M5: =J5/L5 -> 1 | N5: 45653 | O5: 45649 | Q5: PASS | R5: 1/1-1/7出 | S5: 11/12收到 | U5: 2024/11/25+UPC贴纸+外箱贴 | V5: 7166 MA 3L UPC版本 | W5: 日期码格式：ZURU INC(BVI) 标准格式 日期：按实际生产日期 Packaging Info: 出口加拿大，包装需要至少2/3L UPC版，无硼版本 #7166 MA 3L 加UPC贴纸，UPC贴纸资料翻单4500148503.。需要加一张客供防伪帖纸，贴纸跟单提供。与Amazon US 合并订料。 Remark: 1. Amazon FOB订单，出口CA。外箱最长边不能超过25" （超过了，case pack只能为1），不符合要求的大货，一律不接受。 2. 外箱正面印ZURU Logo + SSCC LABEL（客供贴纸)，侧面印item#（订单上显示的SKU#) + carton size(以工厂实际尺寸为准，单位: inch) + MADE IN CHINA， 日期使用ZURU 标准版本 SSCC Label 显示的是客人自己的item#，SSCC Label 贴在外箱正面的正中间，贴一面即可，跟单订购，贴纸离外箱距必须至少3cm，每一 张SSCC label 都是唯一且有不同流水及条码的，没有损耗，绝对不可贴错 ，否则贴错或损坏一张会导致全部都错，千万要注意: SSCC 贴纸务必要在正中间(可以覆 盖Logo <(>&<)> 箱唛)，否则会影响到仓库扫描识别。 3. 日期码使用ZURU标准版本。 4. 如果大货有要求入邮包盒，则对应的邮包盒上面要打上日期码。 5. 按照客户PO# 装柜/箱号顺序装柜，跟单会提前给到装柜计划。在大货生产/仓库存放时，请留意该装柜要求，以便装柜时不混乱（避免装错/装漏/找不到货号等 ）。 6. 出口加拿大，包装需要至少2/3L UPC版，无硼版本。 7.邮包盒上要印刷日期码 | X5: Kelly/Mia | Y5: 3.5384 | Z5: =Y5*J5 -> 63.6912 | AA5: 88919-1.7 | AB5: 18 | AC5: =AB5-J5 -> 0 | AD5: ok | AE5: 已入 | AF5: 系统出单 | AG5: =J5 -> 18 | AH5: =J5 -> 18 | AI5: =J5 -> 18 | AL5: =J5 -> 18 | AU5: =J5 -> 18
A6: 45623 | B6: AMAZON.COM.DEDC,LLC | C6: 美国 | D6: 4500152379 | E6: 3HLAV7WC | F6: 4500152379-130 | G6: 7166-2023-S002-V1-3L | H6: 7166-2023-S002 | I6: 小鲨鱼3PK | J6: 216 | K6: 0 | L6: 18 | M6: =J6/L6 -> 12 | N6: 45664 | O6: 45660 | Q6: PASS | S6: 45623 | U6: 12/20-客供防伪帖纸+12/20外箱贴+UPC贴纸翻4500148503 | V6: 7166 MA 3L UPC版本 | W6: 日期码格式： 标准格式 日期：按实际生产日期 Packaging Info:#7166 MA 3L 加UPC贴纸，UPC贴纸资料翻单4500148503.。需要加一张客供防伪帖纸，贴纸跟单提供。 Remark: 1. Amazon FOB订单，出口US。 2. 日期码使用ZURU标准版本。 3. 如果大货有要求入邮包盒，则对应的邮包盒上面要打上日期码。 4. 箱尺寸要求：外箱最长边不能超过25"（超过了，case pack只能为1），不符合要求的大货，一律不接受。 5. 外箱箱唛要求： ①外箱正面印ZURU Logo+SSCC Label（客供贴纸，由跟单订购)。关于 SSCC Label 请注意： SSCC Label 显示的是客人自己的item#。每一张SSCC label 都是唯一且有不同流水及条码的，没有损耗，绝对不可贴错 。如果贴错或损坏任何一张，都会导致全部都错，千万要注意！ SSCC Label 必须贴在外箱正面的正中间位置（贴一面即可），并且贴纸离外箱边距必须至少3cm(可以覆盖Logo<(>&<)>箱唛)，否则会影响到客户那边仓库的扫描识别。 ②外箱侧面印item#（订单上显示的SKU#)+carton size(以工厂实际尺寸为准,单位: inch) +MADE IN CHINA,日期使用ZURU 标准版本。 6. 装柜要求：按照客户PO# 装柜/箱号顺序装柜，跟单会提前给到装柜计划。 在大货生产/仓库存放时，请留意该装柜要求，以便装柜时不混乱（避免装错/装漏/找不到货号等）。 | X6: Kelly Shen | Y6: 3.5711 | Z6: =Y6*J6 -> 771.3576 | AA6: 94201-2.10 | AB6: 216 | AC6: =AB6-J6 -> 0 | AD6: ok | AE6: 已入 | AF6: 系统出单 | AG6: =J6 -> 216 | AH6: =J6 -> 216 | AI6: =J6 -> 216 | AL6: =J6 -> 216 | AU6: =J6 -> 216
A7: 45623 | B7: AMAZON.COM.DEDC,LLC | C7: 美国 | D7: 4500152657 | E7: 6JHFI1AV | F7: 4500152657-20 | G7: 7166-2023-S002-V1-3L | H7: 7166-2023-S002 | I7: 小鲨鱼3PK | J7: 180 | K7: 0 | L7: 18 | M7: =J7/L7 -> 10 | N7: 45664 | O7: 45660 | Q7: PASS | S7: 45623 | U7: 12/20-客供防伪帖纸+12/20外箱贴+UPC贴纸翻4500148503 | V7: 7166 MA 3L UPC版本 | W7: 日期码格式： 标准格式 日期：按实际生产日期 Packaging Info:#7166 MA 3L 加UPC贴纸，UPC贴纸资料翻单4500148503.。需要加一张客供防伪帖纸，贴纸跟单提供。 Remark: 1. Amazon FOB订单，出口US。 2. 日期码使用ZURU标准版本。 3. 如果大货有要求入邮包盒，则对应的邮包盒上面要打上日期码。 4. 箱尺寸要求：外箱最长边不能超过25"（超过了，case pack只能为1），不符合要求的大货，一律不接受。 5. 外箱箱唛要求： ①外箱正面印ZURU Logo+SSCC Label（客供贴纸，由跟单订购)。关于 SSCC Label 请注意： SSCC Label 显示的是客人自己的item#。每一张SSCC label 都是唯一且有不同流水及条码的，没有损耗，绝对不可贴错 。如果贴错或损坏任何一张，都会导致全部都错，千万要注意！ SSCC Label 必须贴在外箱正面的正中间位置（贴一面即可），并且贴纸离外箱边距必须至少3cm(可以覆盖Logo<(>&<)>箱唛)，否则会影响到客户那边仓库的扫描识别。 ②外箱侧面印item#（订单上显示的SKU#)+carton size(以工厂实际尺寸为准,单位: inch) +MADE IN CHINA,日期使用ZURU 标准版本。 6. 装柜要求：按照客户PO# 装柜/箱号顺序装柜，跟单会提前给到装柜计划。 在大货生产/仓库存放时，请留意该装柜要求，以便装柜时不混乱（避免装错/装漏/找不到货号等）。 | X7: Kelly Shen | Y7: 3.5711 | Z7: =Y7*J7 -> 642.798 | AA7: 94229-2.12 | AB7: 180 | AC7: =AB7-J7 -> 0 | AD7: ok | AE7: 已入 | AF7: 系统出单 | AG7: =J7 -> 180 | AH7: =J7 -> 180 | AI7: =J7 -> 180 | AL7: =J7 -> 180 | AU7: =J7 -> 180
A8: 45623 | B8: AMAZON.COM.DEDC,LLC | C8: 美国 | D8: 4500152439 | E8: 3OLDBHZT | F8: 4500152439-20 | G8: 7166-2023-S002-V1-3L | H8: 7166-2023-S002 | I8: 小鲨鱼3PK | J8: 792 | K8: 0 | L8: 18 | M8: =J8/L8 -> 44 | N8: 45666 | O8: 45663 | Q8: PASS | S8: 45623 | U8: 12/20-客供防伪帖纸+12/20外箱贴+UPC贴纸翻4500148503 | V8: 7166 MA 3L UPC版本 | W8: 日期码格式： 标准格式 日期：按实际生产日期 Packaging Info: #7166：MA 3L 加UPC贴纸，UPC贴纸资料翻单4500148503.。需要加一张客供防伪帖纸，贴纸跟单提供。 Remark: 1. Amazon FOB订单，出口US。 2. 日期码使用ZURU标准版本。 3. 如果大货有要求入邮包盒，则对应的邮包盒上面要打上日期码。 4. 箱尺寸要求：外箱最长边不能超过25"(超过了，case pack只能为1)，不符合要求的大货，一律不接受。 5. 外箱箱唛要求： ①外箱正面印ZURU Logo+SSCC Label(客供贴纸，由跟单订购)。关于 SSCC Label 请注意： SSCC Label显示的是客人自己的item#。每一张SSCC label都是唯一且有不同流水及条码的，没有损耗，绝对不可贴错。如果贴错或损坏任何一张，都会导致全部都 错，千万要注意！SSCC Label必须贴在外箱正面的正中间位置(贴一面即可)，并且贴纸离外箱边距必须至少3cm(可以覆盖Logo<(>&<)>箱唛)，否则会影响到客户那边 仓库的扫描识别。 ②外箱侧面印item#(订单上显示的SKU#)+carton size(以工厂实际尺寸为准，单位: inch)+MADE IN CHINA，日期使用ZURU 标准版本。 6. 装柜要求：按照客户PO#装柜/箱号顺序装柜，跟单会提前给到装柜计划。 在大货生产/仓库存放时，请留意该装柜要求，以便装柜时不混乱(避免装错/装漏/找不到货号等)。 | X8: Kelly Shen | Y8: 3.5384 | Z8: =Y8*J8 -> 2802.4128 | AA8: 94019-1.13 | AB8: 792 | AC8: =AB8-J8 -> 0 | AD8: ok | AE8: 已入 | AF8: 系统出单 | AG8: =J8 -> 792 | AH8: =J8 -> 792 | AI8: =J8 -> 792 | AL8: =J8 -> 792 | AU8: =J8 -> 792
A9: 45623 | B9: Amazon CA (Vendor Center) | C9: 加拿大 | D9: 4500152544 | E9: 2SEV5TYK | F9: 4500152544-50 | G9: 7166-2023-S002-V1-3L | H9: 7166-2023-S002 | I9: 小鲨鱼3PK | J9: 18 | K9: 0 | L9: 18 | M9: =J9/L9 -> 1 | N9: 45670 | O9: 45666 | Q9: PASS | R9: 1/16-1/21出 | S9: 45623 | U9: 12/20-客供防伪帖纸+12/20外箱贴+UPC贴纸翻4500148503 | V9: 7166 MA 3L UPC版本 | W9: 日期码格式：ZURU INC(BVI) 标准格式 日期：按实际生产日期 Packaging Info: 出口加拿大，包装需要至少2/3L UPC版，无硼版本。 #7166 MA 3L 加UPC贴纸，UPC贴纸资料翻单4500148503。需要加一张客供防伪帖纸，贴纸跟单提供。与Amazon US 合并订料。 Remark: 1. Amazon FOB订单，出口CA。外箱最长边不能超过25" （超过了，case pack只能为1），不符合要求的大货，一律不接受。 2. 外箱正面印ZURU Logo + SSCC LABEL（客供贴纸)，侧面印item#（订单上显示的SKU#) + carton size(以工厂实际尺寸为准，单位: inch) + MADE IN CHINA， 日期使用ZURU 标准版本 SSCC Label 显示的是客人自己的item#，SSCC Label 贴在外箱正面的正中间，贴一面即可，跟单订购，贴纸离外箱距必须至少3cm，每一 张SSCC label 都是唯一且有不同流水及条码的，没有损耗，绝对不可贴错 ，否则贴错或损坏一张会导致全部都错，千万要注意: SSCC 贴纸务必要在正中间(可以覆 盖Logo <(>&<)> 箱唛)，否则会影响到仓库扫描识别。 3. 日期码使用ZURU标准版本。 4. 如果大货有要求入邮包盒，则对应的邮包盒上面要打上日期码。 5. 按照客户PO# 装柜/箱号顺序装柜，跟单会提前给到装柜计划。在大货生产/仓库存放时，请留意该装柜要求，以便装柜时不混乱（避免装错/装漏/找不到货号等 ）。 6. 出口加拿大，包装需要至少2/3L UPC版，无硼版本。 7.邮包盒上要印刷日期码 | X9: Kelly/Mia | Y9: 3.5384 | Z9: =Y9*J9 -> 63.6912 | AA9: 94134-1.21 | AB9: 18 | AC9: =AB9-J9 -> 0 | AD9: ok | AE9: 已入 | AF9: 系统出单 | AG9: =J9 -> 18 | AH9: =J9 -> 18 | AI9: =J9 -> 18 | AL9: =J9 -> 18 | AU9: =J9 -> 18
A10: 45623 | B10: Amazon CA (Vendor Center) | C10: 加拿大 | D10: 4500152544 | E10: 5E1J4Q8W | F10: 4500152544-100 | G10: 7166-2023-S002-V1-3L | H10: 7166-2023-S002 | I10: 小鲨鱼3PK | J10: 18 | K10: 0 | L10: 18 | M10: =J10/L10 -> 1 | N10: 45670 | O10: 45666 | Q10: PASS | R10: 1/16-1/21出 | S10: 45623 | U10: 12/20-客供防伪帖纸+12/20外箱贴+UPC贴纸翻4500148503 | V10: 7166 MA 3L UPC版本 | W10: 日期码格式：ZURU INC(BVI) 标准格式 日期：按实际生产日期 Packaging Info: 出口加拿大，包装需要至少2/3L UPC版，无硼版本。 #7166 MA 3L 加UPC贴纸，UPC贴纸资料翻单4500148503。需要加一张客供防伪帖纸，贴纸跟单提供。与Amazon US 合并订料。 Remark: 1. Amazon FOB订单，出口CA。外箱最长边不能超过25" （超过了，case pack只能为1），不符合要求的大货，一律不接受。 2. 外箱正面印ZURU Logo + SSCC LABEL（客供贴纸)，侧面印item#（订单上显示的SKU#) + carton size(以工厂实际尺寸为准，单位: inch) + MADE IN CHINA， 日期使用ZURU 标准版本 SSCC Label 显示的是客人自己的item#，SSCC Label 贴在外箱正面的正中间，贴一面即可，跟单订购，贴纸离外箱距必须至少3cm，每一 张SSCC label 都是唯一且有不同流水及条码的，没有损耗，绝对不可贴错 ，否则贴错或损坏一张会导致全部都错，千万要注意: SSCC 贴纸务必要在正中间(可以覆 盖Logo <(>&<)> 箱唛)，否则会影响到仓库扫描识别。 3. 日期码使用ZURU标准版本。 4. 如果大货有要求入邮包盒，则对应的邮包盒上面要打上日期码。 5. 按照客户PO# 装柜/箱号顺序装柜，跟单会提前给到装柜计划。在大货生产/仓库存放时，请留意该装柜要求，以便装柜时不混乱（避免装错/装漏/找不到货号等 ）。 6. 出口加拿大，包装需要至少2/3L UPC版，无硼版本。 7.邮包盒上要印刷日期码 | X10: Kelly/Mia | Y10: 3.5384 | Z10: =Y10*J10 -> 63.6912 | AA10: 94134-1.21 | AB10: 18 | AC10: =AB10-J10 -> 0 | AD10: ok | AE10: 已入 | AF10: 系统出单 | AG10: =J10 -> 18 | AH10: =J10 -> 18 | AI10: =J10 -> 18 | AL10: =J10 -> 18 | AU10: =J10 -> 18
A11: 45558 | B11: ACADEMY LTD | C11: 美国 | D11: 4500145922 | E11: 10858892 | F11: 4500145922-20 | G11: 7163TQ1-2023-S001-V1 | H11: 7163TQ1-2023-S001 | I11: 小鲨鱼 | J11: 510 | K11: 0 | L11: 6 | M11: =J11/L11 -> 85 | N11: 45693 | O11: 45689 | Q11: PASS | R11: 2/13出 | S11: 12/25收到 | U11: 12/25-UCC外箱贴纸 | V11: MA UPC 版本包装 | W11: 日期码格式：ZURU INC(BVI) 标准格式 日期：按实际生产日期 Packaging Info:#7163TQ1: MA UPC 版本包装; UPC#193052062604; 3PCS LR44 batteries;(included); 3 assortment Remark: 2 .外箱正唛的右下角需贴一个UCC贴纸（4x6inch,距离右边和底边2inch,UCC贴纸为流水号的，每一箱都不一样。 3. 请按期完货，延期有罚金。 4. 我司验货即可。 5. 产品和包装上有tracking code信息，格式为ZURU常规。 | X11: Abby Mai, Lluviazeng | Y11: 1.6244 | Z11: =Y11*J11 -> 828.444 | AA11: 94236-2.13 | AB11: 510 | AC11: =AB11-J11 -> 0 | AD11: OK | AE11: 已入 | AF11: 系统出单 | AG11: =J11/3 -> 170 | AH11: =J11/3 -> 170 | AI11: =J11/3 -> 170 | AJ11: =J11 -> 510 | AL11: =J11 -> 510 | AM11: =J11/6 -> 85
A12: 45558 | B12: ACADEMY LTD | C12: 美国 | D12: 4500145919 | E12: 10858893 | F12: 4500145919-20 | G12: 7163TQ1-2023-S001-V1 | H12: 7163TQ1-2023-S001 | I12: 小鲨鱼 | J12: 570 | K12: 0 | L12: 6 | M12: =J12/L12 -> 95 | N12: 45693 | O12: 45689 | Q12: PASS | R12: 2/13-2/15出 | S12: 12/25收到 | U12: 12/25-UCC外箱贴纸 | V12: MA UPC 版本包装 | W12: 日期码格式：ZURU INC(BVI) 标准格式 日期：按实际生产日期 Packaging Info:#7163TQ1: MA UPC 版本包装; UPC#193052062604; 3PCS LR44 batteries;(included); 3 assortment Remark: 2 .外箱正唛的右下角需贴一个UCC贴纸（4x6inch,距离右边和底边2inch,UCC贴纸为流水号的，每一箱都不一样。 3. 请按期完货，延期有罚金。 4. 我司验货即可。 5. 产品和包装上有tracking code信息，格式为ZURU常规。 | X12: Abby Mai, Lluviazeng | Y12: 1.6244 | Z12: =Y12*J12 -> 925.908 | AA12: 94241-2.14 | AB12: 570 | AC12: =AB12-J12 -> 0 | AD12: OK | AE12: 已入 | AF12: 系统出单 | AG12: =J12/3 -> 190 | AH12: =J12/3 -> 190 | AI12: =J12/3 -> 190 | AJ12: =J12 -> 570 | AL12: =J12 -> 570 | AM12: =J12/6 -> 95
A13: 45558 | B13: ACADEMY LTD | C13: 美国 | D13: 4500145925 | E13: 10858891 | F13: 4500145925-20 | G13: 7163TQ1-2023-S001-V1 | H13: 7163TQ1-2023-S001 | I13: 小鲨鱼 | J13: 1134 | K13: 0 | L13: 6 | M13: =J13/L13 -> 189 | N13: 45699 | O13: 45695 | Q13: PASS | R13: 2/18出 | S13: 12/25收到 | U13: 12/25-UCC外箱贴纸 | V13: MA UPC 版本包装 | W13: 日期码格式：ZURU INC(BVI) 标准格式 日期：按实际生产日期 Packaging Info:#7163TQ1: MA UPC 版本包装; UPC#193052062604; 3PCS LR44 batteries;(included); 3 assortment Remark: 2 .外箱正唛的右下角需贴一个UCC贴纸（4x6inch,距离右边和底边2inch,UCC贴纸为流水号的，每一箱都不一样。 3. 请按期完货，延期有罚金。 4. 我司验货即可。 5. 产品和包装上有tracking code信息，格式为ZURU常规。 | X13: Abby Mai, Lluviazeng | Y13: 1.6189 | Z13: =Y13*J13 -> 1835.8326 | AA13: 94264-2.17 | AB13: 1134 | AC13: =AB13-J13 -> 0 | AD13: OK | AE13: 已入 | AF13: 系统出单 | AG13: =J13/3 -> 378 | AH13: =J13/3 -> 378 | AI13: =J13/3 -> 378 | AJ13: =J13 -> 1134 | AL13: =J13 -> 1134 | AM13: =J13/6 -> 189
A14: 45643 | B14: Dirk Rossmann GmbH | C14: 德国 | D14: 4500153297 | E14: 30241062 | F14: 4500153297-10 | G14: 7163-2023-S003-V1-1 | H14: 7163-2023-S003 | I14: 小鲨鱼 | J14: 5016 | K14: 0 | L14: 24 | M14: =J14/L14 -> 209 | N14: 45709 | O14: 45705 | P14: 2/21第三方 | Q14: PASS | R14: 2/24出 | S14: 12/26收到 | U14: 产品电池盖需要添加ZURU FRANCE地址字唛+1/15收到文档 | V14: 客版彩盒+产品电池盖需要添加ZURU FRANCE地址字唛+客版说明书 | W14: 日期码格式：ZURU INC(BVI) 标准格式 日期：按实际生产日期 Packaging Info: 客版彩盒+产品电池盖需要添加ZURU FRANCE地址字唛+客版说明书 Remark: 1. 出口欧洲，微塑料需符合法规 2. 所有包装材料都需要用PET材质。 3. 外箱上下需加保护卡，以防开箱时产品被划破。（保护卡需要时整面） 4. 此单在出货前4周提供完整的3套大货样品给Rossmann德国客人.请备额外物料。 5. 此单需要第三方验货，验货时间为完货后第二天，验货OK待客人放货后才能安排走货。 6. 此单出德国走散货，请知悉。 7. 每箱需要放一包干燥剂（不能是silicon) 。品牌SUPER DRY，规格：10g/pc 。 8. 外箱需要是5层瓦楞纸，厚度在5-9mm" | X14: Shirley Zhou | Y14: 1.2898 | Z14: =Y14*J14 -> 6469.6368 | AA14: 94339-2.25 | AB14: 5016 | AC14: =AB14-J14 -> 0 | AD14: 无 | AE14: 已入 | AF14: 系统出单 | AG14: =J14/3 -> 1672 | AH14: =J14/3 -> 1672 | AI14: =J14/3 -> 1672 | AO14: =J14 -> 5016 | AP14: =J14 -> 5016
A15: 45558 | B15: ACADEMY LTD | C15: 美国 | D15: 4500145932 | E15: 10858931 | F15: 4500145932-20 | G15: 7163TQ1-2023-S001-V1 | H15: 7163TQ1-2023-S001 | I15: 小鲨鱼 | J15: 516 | K15: 0 | L15: 6 | M15: =J15/L15 -> 86 | N15: 45712 | O15: 45708 | Q15: PASS | R15: 3/3出 | S15: 12/25收到 | U15: 12/25-UCC外箱贴纸 | V15: MA UPC 版本包装 | W15: 日期码格式：ZURU INC(BVI) 标准格式 日期：按实际生产日期 Packaging Info:#7163TQ1: MA UPC 版本包装; UPC#193052062604; 3PCS LR44 batteries;(included); 3 assortment Remark: 2 .外箱正唛的右下角需贴一个UCC贴纸（4x6inch,距离右边和底边2inch,UCC贴纸为流水号的，每一箱都不一样。 3. 请按期完货，延期有罚金。 4. 我司验货即可。 5. 产品和包装上有tracking code信息，格式为ZURU常规。 | X15: Abby Mai, Lluviazeng | Y15: 1.6244 | Z15: =Y15*J15 -> 838.1904 | AA15: 94417-3.3 | AB15: 516 | AC15: =AB15-J15 -> 0 | AD15: OK | AE15: 已入 | AF15: 系统出单 | AG15: =J15/3 -> 172 | AH15: =J15/3 -> 172 | AI15: =J15/3 -> 172 | AJ15: =J15 -> 516 | AL15: =J15 -> 516 | AM15: =J15/6 -> 86
A16: 45558 | B16: ACADEMY LTD | C16: 美国 | D16: 4500145929 | E16: 10858932 | F16: 4500145929-20 | G16: 7163TQ1-2023-S001-V1 | H16: 7163TQ1-2023-S001 | I16: 小鲨鱼 | J16: 564 | K16: 0 | L16: 6 | M16: =J16/L16 -> 94 | N16: 45712 | O16: 45708 | Q16: PASS | S16: 12/25收到 | U16: 12/25-UCC外箱贴纸 | V16: MA UPC 版本包装 | W16: 日期码格式：ZURU INC(BVI) 标准格式 日期：按实际生产日期 Packaging Info:#7163TQ1: MA UPC 版本包装; UPC#193052062604; 3PCS LR44 batteries;(included); 3 assortment Remark: 2 .外箱正唛的右下角需贴一个UCC贴纸（4x6inch,距离右边和底边2inch,UCC贴纸为流水号的，每一箱都不一样。 3. 请按期完货，延期有罚金。 4. 我司验货即可。 5. 产品和包装上有tracking code信息，格式为ZURU常规。 | X16: Abby Mai, Lluviazeng | Y16: 1.6244 | Z16: =Y16*J16 -> 916.1616 | AA16: 94416-3.3 | AB16: 564 | AC16: =AB16-J16 -> 0 | AD16: OK | AE16: 已入 | AF16: 系统出单 | AG16: =J16/3 -> 188 | AH16: =J16/3 -> 188 | AI16: =J16/3 -> 188 | AJ16: =J16 -> 564 | AL16: =J16 -> 564 | AM16: =J16/6 -> 94
A17: 45631 | B17: TOYS "R" US (CANADA) LTD. | C17: 加拿大 | D17: 4500153261 | E17: 3501527611 | F17: 4500153261-20 | G17: 7163TQ1-2023-S001-V1-3L | H17: 7163TQ1-2023-S001 | I17: 小鲨鱼 | J17: 1002 | K17: 0 | L17: 6 | M17: =J17/L17 -> 167 | N17: 45714 | O17: 45710 | P17: 2/27第三方 | Q17: PASS | R17: 3/5-3/11出 | S17: 1/6收到 | U17: 2/10收到 UPC 贴纸 | V17: 彩盒MA 3L | W17: 日期码格式：ZURU INC(BVI) 标准格式 日期：按实际生产日期 Packaging Info: 1. 出口加拿大市场 #7163TQ1: 彩盒MA 3L + UPC 贴纸，PDQ MA 版本; UPC#193052062604; 3PCS LR44 batteries;(included) Remark: 2. 需要第三方SGS验货，验货时间暂定2025/02/26，每款每色请备1PC完整带包装样品供验货人员参考。用完后若无损坏可以放回大货里。 | X17: Abby Mai, Lluviazeng | Y17: 1.6189 | Z17: =Y17*J17 -> 1622.1378 | AA17: 94517-3.11 | AB17: 1002 | AC17: =AB17-J17 -> 0 | AD17: ok | AE17: 已入 | AF17: 系统出单 | AG17: =J17/3 -> 334 | AH17: =J17/3 -> 334 | AI17: =J17/3 -> 334 | AK17: =J17 -> 1002 | AL17: =J17 -> 1002 | AM17: =J17/6 -> 167
A18: 45657 | B18: AMAZON.COM.DEDC,LLC | C18: 美国 | D18: 4500155048 | E18: 5EURH4TO | F18: 4500155048-10 | G18: 7166-2023-S002-V1-3L | H18: 7166-2023-S002 | I18: 小鲨鱼3PK | J18: 36 | K18: 0 | L18: 18 | M18: =J18/L18 -> 2 | N18: 45715 | O18: 45712 | Q18: PASS | R18: 收到SO | S18: 12/31收到 | U18: 1/13客供防伪帖纸+外箱贴纸 | V18: 7166 MA 3L UPC版本 | W18: 日期码格式：ZURU INC(BVI) 标准格式 日期：按实际生产日期 Packaging Info: #7166 MA 3L UPC版本。需要加一张客供防伪帖纸，贴纸跟单提供。 Remark: 1. Amazon FOB订单，出口US。 2. 日期码使用ZURU标准版本。 3. 如果大货有要求入邮包盒，则对应的邮包盒上面要打上日期码。 4. 箱尺寸要求：外箱最长边不能超过25" （超过了，case pack只能为1），不符合要求的大货，一律不接受。 5. 外箱箱唛要求： ①外箱正面印ZURU Logo+SSCC Label（客供贴纸，由跟单订购)。关于 SSCC Label 请注意： SSCC Label 显示的是客人自己的item#。每一张SSCC label 都是唯一且有不同流水及条码的，没有损耗，绝对不可贴错 。如果贴错或损坏任何一张，都会导致全 部都错，千万要注意！ SSCC Label 必须贴在外箱正面的正中间位置（贴一面即可），并且贴纸离外箱边距必须至少3cm(可以覆盖Logo<(>&<)>箱唛)，否则会影响到客户那边仓库的扫描识 别。 ②外箱侧面印item#（订单上显示的SKU#)+carton size(以工厂实际尺寸为准,单位: inch) +MADE IN CHINA,日期使用ZURU 标准版本。 6. 装柜要求：按照客户PO# 装柜/箱号顺序装柜，跟单会提前给到装柜计划。 在大货生产/仓库存放时，请留意该装柜要求，以便装柜时不混乱（避免装错/装漏/找不到货号等）。 | X18: Kelly Shen/Mia Pan | Y18: 3.5711 | Z18: =Y18*J18 -> 128.5596 | AA18: 94483-3.7 | AB18: 36 | AC18: =AB18-J18 -> 0 | AD18: OK | AE18: 已入 | AF18: 系统出单 | AG18: =J18 -> 36 | AH18: =J18 -> 36 | AI18: =J18 -> 36 | AL18: =J18 -> 36 | AU18: =J18 -> 36
A19: 45657 | B19: AMAZON.COM.DEDC,LLC | C19: 美国 | D19: 4500155020 | E19: 5MKL1CPZ | F19: 4500155020-20 | G19: 7166-2023-S002-V1-3L | H19: 7166-2023-S002 | I19: 小鲨鱼3PK | J19: 342 | K19: 0 | L19: 18 | M19: =J19/L19 -> 19 | N19: 45715 | O19: 45712 | Q19: PASS | R19: 收到SO | S19: 12/31收到 | U19: 1/13客供防伪帖纸+外箱贴纸+UPC贴纸翻4500148503 | V19: 7166 MA 3L UPC版本 | W19: 日期码格式：ZURU INC(BVI) 标准格式 日期：按实际生产日期 Packaging Info: #7166 MA 3L UPC版本。需要加一张客供防伪帖纸，贴纸跟单提供。 Remark: 1. Amazon FOB订单，出口US。 2. 日期码使用ZURU标准版本。 3. 如果大货有要求入邮包盒，则对应的邮包盒上面要打上日期码。 4. 箱尺寸要求：外箱最长边不能超过25" （超过了，case pack只能为1），不符合要求的大货，一律不接受。 5. 外箱箱唛要求： ①外箱正面印ZURU Logo+SSCC Label（客供贴纸，由跟单订购)。关于 SSCC Label 请注意： SSCC Label 显示的是客人自己的item#。每一张SSCC label 都是唯一且有不同流水及条码的，没有损耗，绝对不可贴错 。如果贴错或损坏任何一张，都会导致全 部都错，千万要注意！ SSCC Label 必须贴在外箱正面的正中间位置（贴一面即可），并且贴纸离外箱边距必须至少3cm(可以覆盖Logo<(>&<)>箱唛)，否则会影响到客户那边仓库的扫描识 别。 ②外箱侧面印item#（订单上显示的SKU#)+carton size(以工厂实际尺寸为准,单位: inch) +MADE IN CHINA,日期使用ZURU 标准版本。 6. 装柜要求：按照客户PO# 装柜/箱号顺序装柜，跟单会提前给到装柜计划。 在大货生产/仓库存放时，请留意该装柜要求，以便装柜时不混乱（避免装错/装漏/找不到货号等）。 | X19: Kelly Shen/Mia Pan | Y19: 3.5711 | Z19: =Y19*J19 -> 1221.3162 | AA19: 94452-3.5 | AB19: 342 | AC19: =AB19-J19 -> 0 | AD19: ok | AE19: 已入 | AF19: 系统出单 | AG19: =J19 -> 342 | AH19: =J19 -> 342 | AI19: =J19 -> 342 | AL19: =J19 -> 342 | AU19: =J19 -> 342
A20: 45558 | B20: ACADEMY LTD | C20: 美国 | D20: 4500145933 | E20: 10858930 | F20: 4500145933-20 | G20: 7163TQ1-2023-S001-V1 | H20: 7163TQ1-2023-S001 | I20: 小鲨鱼 | J20: 1092 | K20: 0 | L20: 6 | M20: =J20/L20 -> 182 | N20: 45728 | O20: 45724 | Q20: PASS | R20: 3/17-3/19出 | S20: 12/25收到 | U20: 12/25-UCC外箱贴纸 | V20: MA UPC 版本包装 | W20: 日期码格式：ZURU INC(BVI) 标准格式 日期：按实际生产日期 Packaging Info:#7163TQ1: MA UPC 版本包装; UPC#193052062604; 3PCS LR44 batteries;(included); 3 assortment Remark: 2 .外箱正唛的右下角需贴一个UCC贴纸（4x6inch,距离右边和底边2inch,UCC贴纸为流水号的，每一箱都不一样。 3. 请按期完货，延期有罚金。 4. 我司验货即可。 5. 产品和包装上有tracking code信息，格式为ZURU常规。 | X20: Abby Mai, Lluviazeng | Y20: 1.6189 | Z20: =Y20*J20 -> 1767.8388 | AA20: ZB00070-3.28 | AB20: 1092 | AC20: =AB20-J20 -> 0 | AD20: OK | AE20: 已入 | AF20: 系统出单 | AG20: =J20/3 -> 364 | AH20: =J20/3 -> 364 | AI20: =J20/3 -> 364 | AJ20: =J20 -> 1092 | AL20: =J20 -> 1092 | AM20: =J20/6 -> 182
A21: 45723 | B21: Miniso Depot CA Inc. | C21: 美国 | D21: 4500159501 | E21: Customer PO# 4341950649 | F21: 4500159501-20 | G21: 7163TQ1-2023-S002-V1 | H21: 7163TQ1-2023-S002 | I21: 小鲨鱼 | J21: 1824 | K21: 0 | L21: 24 | M21: =J21/L21 -> 76 | N21: 45798 | O21: 45794 | Q21: PASS | R21: 5/21出 | S21: 4/25收到 | U21: 4/29-UPC 条码贴纸+外箱贴纸 | V21: MA UPC 优先1L 最新包装 | W21: 日期码格式：ZURU INC(BVI) 标准格式 日期：按实际生产日期 Packaging Info: 1. 包装方式：MA UPC 优先1L 最新包装，出口美国； 2. 产品和包装上印刷tracking code信息，格式为ZURU常规. Remark: 4. 外箱加贴一张外箱贴纸，贴纸箱正唛一面，位置不限，不遮挡箱唛内容即可，贴纸AW跟单提供，工厂自行采购。 | X21: Iris Yuan | Y21: 0.9444 | Z21: =Y21*J21 -> 1722.5856 | AB21: 1824 | AC21: =AB21-J21 -> 0 | AD21: ok | AE21: 已入 | AF21: 系统出单 | AG21: =J21/3 -> 608 | AH21: =J21/3 -> 608 | AI21: =J21/3 -> 608 | AJ21: =J21 -> 1824 | AL21: =J21 -> 1824 | AM21: =J21/6 -> 304
A22: 45723 | B22: Miniso Depot CA Inc. | C22: 美国 | D22: 4500165182 | E22: CUSTOMER PO# 4341950650 | F22: 4500159501-20 | G22: 7163TQ1-2023-S002-V1 | H22: 7163TQ1-2023-S002 | I22: 小鲨鱼 | J22: 1536 | K22: 0 | L22: 24 | M22: =J22/L22 -> 64 | N22: 45798 | O22: 45794 | Q22: PASS | R22: 5/21出 | S22: 4/25收到 | U22: 4/29-UPC 条码贴纸 | V22: MA UPC 优先1L 最新包装 | W22: 日期码格式：ZURU INC(BVI) 标准格式 日期：按实际生产日期 Packaging Info: 1. 包装方式：MA UPC 优先1L 最新包装，出口美国； 2. 产品和包装上印刷tracking code信息，格式为ZURU常规. Remark: 3. #7163TQ1-2023-S002的PDQ上需要贴一张UPC 条码贴纸,UPC显示：193052062604；贴纸AW和位置图跟单提供，工厂自行采购。 4. 外箱加贴一张外箱贴纸，贴纸箱正唛一面，位置不限，不遮挡箱唛内容即可，贴纸AW跟单提供，工厂自行采购。 | X22: Iris Yuan | Y22: 0.9444 | Z22: =Y22*J22 -> 1450.5984 | AB22: 1536 | AC22: =AB22-J22 -> 0 | AD22: ok | AE22: 已入 | AF22: 系统出单 | AG22: =J22/3 -> 512 | AH22: =J22/3 -> 512 | AI22: =J22/3 -> 512 | AJ22: =J22 -> 1536 | AL22: =J22 -> 1536 | AM22: =J22/6 -> 256
A23: 45750 | B23: 360 SALES SOLUTIONS INC | C23: 加拿大 | D23: 4500162525 | E23: 2025ZURU16 | F23: 4500162525-20 | G23: 7163TQ1-2023-S001-V1-3L | H23: 7163TQ1-2023-S001 | I23: 小鲨鱼 | J23: 3402 | K23: 0 | L23: 6 | M23: =J23/L23 -> 567 | N23: 45800 | O23: 45796 | Q23: Pass | R23: 5/26出 | S23: 4/3收到 | U23: 4/3-UPC贴纸 | V23: 7163TQ1 MA 多语EAN | W23: 日期码格式：ZURU INC(BVI) 标准格式 日期：按实际生产日期 Packaging Info: 7163TQ1 MA 多语EAN+UPC贴纸， UPC号码193052062604 Remark: 出加拿大 Zuru验货.日期跟踪码：产品外包装及产品本身都必须有日期跟踪码，ZURU标准格式日期码。（箱唛日期码按跟单提供格式） | X23: Summer Mo | Y23: 1.4338 | Z23: =Y23*J23 -> 4877.7876 | AB23: 3402 | AC23: =AB23-J23 -> 0 | AD23: ok | AE23: 已入 | AF23: 系统出单 | AG23: =J23/3 -> 1134 | AH23: =J23/3 -> 1134 | AI23: =J23/3 -> 1134 | AK23: =J23 -> 3402 | AL23: =J23 -> 3402 | AM23: =J23/6 -> 567
A24: 45770 | B24: Planet of Toys Ltd | C24: 吉尔吉斯斯坦 | D24: 4500164616 | F24: 4500164616-110 | G24: 7163TQ1-2023-S002-V1 | H24: 7163TQ1-2023-S002 | I24: 小鲨鱼 | J24: 120 | K24: 0 | L24: 24 | M24: =J24/L24 -> 5 | N24: 45810 | O24: =N24-4 -> 45806 | Q24: Pass | R24: 收到SO | S24: 4/23收到 | U24: 4/30-通用贴纸 | V24: 1L MA UPC 包装 | W24: 日期码格式：ZURU INC(BVI) 标准格式 日期：按实际生产日期 Packaging Info: 1L MA UPC 包装 + 通用贴纸 ， MA 说明书/指南/PDQ （如有）； Remark: 标准配比 | X24: Ann | Y24: 1.5793 | Z24: =Y24*J24 -> 189.516 | AB24: 120 | AC24: =AB24-J24 -> 0 | AD24: ok | AE24: 已入 | AF24: 系统出单 | AG24: =J24/3 -> 40 | AH24: =J24/3 -> 40 | AI24: =J24/3 -> 40 | AJ24: =J24 -> 120 | AL24: =J24 -> 120 | AM24: =J24/6 -> 20
A25: 45770 | B25: Planet of Toys Ltd | C25: 吉尔吉斯斯坦 | D25: 4500164616 | F25: 4500164616-120 | G25: 7166-2023-S002-V1-3L | H25: 7166-2023-S002 | I25: 小鲨鱼3PK | J25: 108 | K25: 0 | L25: 18 | M25: =J25/L25 -> 6 | N25: 45810 | O25: =N25-4 -> 45806 | Q25: Pass | R25: 收到SO | S25: 4/23收到 | U25: 4/30-通用贴纸 | V25: 1L MA UPC 包装 | W25: 日期码格式：ZURU INC(BVI) 标准格式 日期：按实际生产日期 Packaging Info: 1L MA UPC 包装 + 通用贴纸 ， MA 说明书/指南/PDQ （如有）； Remark: 标准配比 | X25: Ann | Y25: 3.5711 | Z25: =Y25*J25 -> 385.6788 | AB25: 108 | AC25: =AB25-J25 -> 0 | AD25: ok | AE25: 已入 | AF25: 系统出单 | AG25: =J25 -> 108 | AH25: =J25 -> 108 | AI25: =J25 -> 108 | AL25: =J25 -> 108 | AU25: =J25 -> 108
A26: 45776 | B26: Amazon CA (Vendor Center) | C26: 加拿大 | D26: 4500165380 | E26: 7D6OB25V | F26: 4500165380-10 | G26: 7166-2023-S002-V1-3L | H26: 7166-2023-S002 | I26: 小鲨鱼3PK | J26: 306 | K26: 0 | L26: 18 | M26: =J26/L26 -> 17 | N26: 45813 | O26: 45810 | Q26: Pass | R26: 6/9-6/14出 | S26: 4/29收到 | U26: UPC贴纸翻4500148503+5/17-客供防伪帖纸 | V26: #7166 MA 3L | W26: 日期码格式：ZURU INC(BVI) 标准格式 日期：按实际生产日期 Packaging Info: #7166 MA 3L 加UPC贴纸，UPC贴纸资料翻单4500148503。需要加一张客供防伪帖纸，贴纸跟单提供。3L 彩卡 消耗PO#4500155812 取消的订单物料。 Remark: 1. Amazon FOB订单，出口CA。外箱最长边不能超过25" （超过了，case pack只能为1），不符合要求的大货，一律不接受。 2. 外箱正面印ZURU Logo + SSCC LABEL（客供贴纸)，侧面印item#（订单上显示的SKU#) + carton size(以工厂实际尺寸为准，单位: inch) + MADE IN CHINA， 日期使用ZURU 标准版本 SSCC Label 显示的是客人自己的item#，SSCC Label 贴在外箱正面的正中间，贴一面即可，跟单订购，贴纸离外箱距必须至少3cm，每一 张SSCC label 都是唯一且有不同流水及条码的，没有损耗，绝对不可贴错 ，否则贴错或损坏一张会导致全部都错，千万要注意: SSCC 贴纸务必要在正中间(可以覆 盖Logo <(>&<)> 箱唛)，否则会影响到仓库扫描识别。 3. 日期码使用ZURU标准版本。 4. 如果大货有要求入邮包盒，则对应的邮包盒上面要打上日期码。 5. 按照客户PO# 装柜/箱号顺序装柜，跟单会提前给到装柜计划。在大货生产/仓库存放时，请留意该装柜要求，以便装柜时不混乱（避免装错/装漏/找不到货号等 ）。 6. 出口加拿大，包装需要至少2/3L UPC版，无硼版本。 7.邮包盒上要印刷日期码 | X26: Kelly Shen/Mia Pan/P | Y26: 3.5384 | Z26: =Y26*J26 -> 1082.7504 | AB26: =288+18 -> 306 | AC26: =AB26-J26 -> 0 | AD26: ok | AE26: 已入 | AF26: 系统出单 | AG26: =J26 -> 306 | AH26: =J26 -> 306 | AI26: =J26 -> 306 | AL26: =J26 -> 306 | AU26: =J26 -> 306
A27: 45774 | B27: SUOMEN OSUUSKAUPPOJEN KESKUSKUNTA | C27: 芬兰 | D27: 4500161056 | E27: 164147 | F27: 4500161056-20 | G27: 7166-2023-S002-V1-3L | H27: 7166-2023-S002 | I27: 小鲨鱼3PK | J27: 54 | K27: 0 | L27: 18 | M27: =J27/L27 -> 3 | N27: 45818 | O27: 45814 | P27: PET吸塑 | Q27: Pass | S27: 5/8收到 | U27: 5/22-瑞典芬兰爱沙尼亚警告语/made in China和产品包含信息翻译成瑞典芬兰爱沙尼亚语/care@zuru.com邮箱地址贴纸+玩法和更换电池说明翻译成瑞典芬兰爱沙尼亚语做成黑白说明书+带干电池走货北欧六语通用黑白电池说明书翻4500161075 | V27: 7166: MA 3L+3L EAN彩卡 | W27: 日期码格式：ZURU INC(BVI) 标准格式 日期：按实际生产日期 Packaging Info: 2. 7166: MA 3L+3L EAN彩卡+瑞典芬兰爱沙尼亚警告语/made in China和产品包含信息翻译成瑞典芬兰爱沙尼亚语/care@zuru.com邮箱地址做成一张贴纸贴在彩卡上 +MA C9L说明书+一张玩法和更换电池说明翻译成瑞典芬兰爱沙尼亚语做成黑白说明书加在大货中+带干电池走货北欧六语通用黑白电池说明书（翻PO#4500161075) Remark: *. 71152+15704UQ1 需要在6/11安排ITS第三方验货，请多备料 请在6/2之前各提供一套大货签板给我们签回供第三方验货用，签板必须跟大货完全一致，否则验货会不合格 *.71152+7166+15704UQ1+15733+15728新款: 请在6/2之前各提供两套大货样给我们寄给客人留底 *. 包装如含PVC,请改为PET并第一时间通知跟单 *. 产品/包装要求无硼无香，出欧洲，微塑料需合规。 *.带电池出货的产品所用到的电池需要符合欧洲电池新规(EU) 2023-1542 *.有胶袋的产品：要求产品的胶袋厚度要大于等于0.05mm *.关于贴纸，如果贴纸位置图的包装版本与大货不一致，请工厂第一时间提前提出。跟单会重新调整确认是否更新贴纸或调整位置图 *.产品/包装不含PFAS成分 *.产品条码如下: 请先检查条码是否正确再安排做货，如有问题请告知 ZURU ITEM#<(>&<)>EAN | X27: Sheba Ye | Y27: 3.5711 | Z27: =Y27*J27 -> 192.8394 | AA27: 95518-7.1 | AB27: 54 | AC27: =AB27-J27 -> 0 | AD27: ok | AE27: 已入 | AF27: 系统出单 | AG27: =J27 -> 54 | AH27: =J27 -> 54 | AI27: =J27 -> 54 | AL27: =J27 -> 54 | AU27: =J27 -> 54
A28: 45798 | B28: Amazon CA (Vendor Center) | C28: 加拿大 | D28: 4500167361 | E28: 2PEFCZEJ | F28: 4500167361-230 | G28: 7166-2023-S002-V1-3L | H28: 7166-2023-S002 | I28: 小鲨鱼3PK | J28: 18 | K28: 0 | L28: 18 | M28: =J28/L28 -> 1 | N28: 45834 | O28: 45831 | Q28: Pass | R28: 收到SO | S28: 5/21收到 | U28: UPC贴纸翻4500148503+6/11-客供防伪帖纸 | V28: 7166 MA 3L UPC版本 | W28: 日期码格式：ZURU INC(BVI) 标准格式 日期：按实际生产日期 Packaging Info: 出口加拿大，包装需要至少2/3L UPC版，无硼版本。 #7166 MA 3L 加UPC贴纸，UPC贴纸资料翻单4500148503。需要加一张客供防伪帖纸，贴纸跟单提供。 Remark: 1. Amazon FOB订单，出口CA。外箱最长边不能超过25" （超过了，case pack只能为1），不符合要求的大货，一律不接受。 2. 外箱正面印ZURU Logo + SSCC LABEL（客供贴纸)，侧面印item#（订单上显示的SKU#) + carton size(以工厂实际尺寸为准，单位: inch) + MADE IN CHINA， 日期使用ZURU 标准版本 SSCC Label 显示的是客人自己的item#，SSCC Label 贴在外箱正面的正中间，贴一面即可，跟单订购，贴纸离外箱距必须至少3cm，每一 张SSCC label 都是唯一且有不同流水及条码的，没有损耗，绝对不可贴错 ，否则贴错或损坏一张会导致全部都错，千万要注意: SSCC 贴纸务必要在正中间(可以覆 盖Logo <(>&<)> 箱唛)，否则会影响到仓库扫描识别。 3. 日期码使用ZURU标准版本。 4. 如果大货有要求入邮包盒，则对应的邮包盒上面要打上日期码。 5. 按照客户PO# 装柜/箱号顺序装柜，跟单会提前给到装柜计划。在大货生产/仓库存放时，请留意该装柜要求，以便装柜时不混乱（避免装错/装漏/找不到货号等 ）。 6. 出口加拿大，包装需要至少2/3L UPC版，无硼版本。 7.邮包盒上要印刷日期码 | X28: Kelly Shen | Y28: 3.5384 | Z28: =Y28*J28 -> 63.6912 | AB28: 18 | AC28: =AB28-J28 -> 0 | AD28: ok | AE28: 已入 | AF28: 系统出单 | AG28: =J28 -> 18 | AH28: =J28 -> 18 | AI28: =J28 -> 18 | AL28: =J28 -> 18 | AU28: =J28 -> 18
A29: 45798 | B29: Amazon CA (Vendor Center) | C29: 加拿大 | D29: 4500167361 | E29: 3CRZKD6M | F29: 4500167361-240 | G29: 7166-2023-S002-V1-3L | H29: 7166-2023-S002 | I29: 小鲨鱼3PK | J29: 18 | K29: 0 | L29: 18 | M29: =J29/L29 -> 1 | N29: 45834 | O29: 45831 | Q29: Pass | R29: 收到SO | S29: 5/21收到 | U29: UPC贴纸翻4500148503+6/11-客供防伪帖纸 | V29: 7166 MA 3L UPC版本 | W29: 日期码格式：ZURU INC(BVI) 标准格式 日期：按实际生产日期 Packaging Info: 出口加拿大，包装需要至少2/3L UPC版，无硼版本。 #7166 MA 3L 加UPC贴纸，UPC贴纸资料翻单4500148503。需要加一张客供防伪帖纸，贴纸跟单提供。 Remark: 1. Amazon FOB订单，出口CA。外箱最长边不能超过25" （超过了，case pack只能为1），不符合要求的大货，一律不接受。 2. 外箱正面印ZURU Logo + SSCC LABEL（客供贴纸)，侧面印item#（订单上显示的SKU#) + carton size(以工厂实际尺寸为准，单位: inch) + MADE IN CHINA， 日期使用ZURU 标准版本 SSCC Label 显示的是客人自己的item#，SSCC Label 贴在外箱正面的正中间，贴一面即可，跟单订购，贴纸离外箱距必须至少3cm，每一 张SSCC label 都是唯一且有不同流水及条码的，没有损耗，绝对不可贴错 ，否则贴错或损坏一张会导致全部都错，千万要注意: SSCC 贴纸务必要在正中间(可以覆 盖Logo <(>&<)> 箱唛)，否则会影响到仓库扫描识别。 3. 日期码使用ZURU标准版本。 4. 如果大货有要求入邮包盒，则对应的邮包盒上面要打上日期码。 5. 按照客户PO# 装柜/箱号顺序装柜，跟单会提前给到装柜计划。在大货生产/仓库存放时，请留意该装柜要求，以便装柜时不混乱（避免装错/装漏/找不到货号等 ）。 6. 出口加拿大，包装需要至少2/3L UPC版，无硼版本。 7.邮包盒上要印刷日期码 | X29: Kelly Shen | Y29: 3.5384 | Z29: =Y29*J29 -> 63.6912 | AB29: 18 | AC29: =AB29-J29 -> 0 | AD29: ok | AE29: 已入 | AF29: 系统出单 | AG29: =J29 -> 18 | AH29: =J29 -> 18 | AI29: =J29 -> 18 | AL29: =J29 -> 18 | AU29: =J29 -> 18
A30: 45798 | B30: Amazon CA (Vendor Center) | C30: 加拿大 | D30: 4500167361 | E30: 7Y62KSOR | F30: 4500167361-250 | G30: 7166-2023-S002-V1-3L | H30: 7166-2023-S002 | I30: 小鲨鱼3PK | J30: 18 | K30: 0 | L30: 18 | M30: =J30/L30 -> 1 | N30: 45834 | O30: 45831 | Q30: Pass | R30: 收到SO | S30: 5/21收到 | U30: UPC贴纸翻4500148503+6/11-客供防伪帖纸 | V30: 7166 MA 3L UPC版本 | W30: 日期码格式：ZURU INC(BVI) 标准格式 日期：按实际生产日期 Packaging Info: 出口加拿大，包装需要至少2/3L UPC版，无硼版本。 #7166 MA 3L 加UPC贴纸，UPC贴纸资料翻单4500148503。需要加一张客供防伪帖纸，贴纸跟单提供。 Remark: 1. Amazon FOB订单，出口CA。外箱最长边不能超过25" （超过了，case pack只能为1），不符合要求的大货，一律不接受。 2. 外箱正面印ZURU Logo + SSCC LABEL（客供贴纸)，侧面印item#（订单上显示的SKU#) + carton size(以工厂实际尺寸为准，单位: inch) + MADE IN CHINA， 日期使用ZURU 标准版本 SSCC Label 显示的是客人自己的item#，SSCC Label 贴在外箱正面的正中间，贴一面即可，跟单订购，贴纸离外箱距必须至少3cm，每一 张SSCC label 都是唯一且有不同流水及条码的，没有损耗，绝对不可贴错 ，否则贴错或损坏一张会导致全部都错，千万要注意: SSCC 贴纸务必要在正中间(可以覆 盖Logo <(>&<)> 箱唛)，否则会影响到仓库扫描识别。 3. 日期码使用ZURU标准版本。 4. 如果大货有要求入邮包盒，则对应的邮包盒上面要打上日期码。 5. 按照客户PO# 装柜/箱号顺序装柜，跟单会提前给到装柜计划。在大货生产/仓库存放时，请留意该装柜要求，以便装柜时不混乱（避免装错/装漏/找不到货号等 ）。 6. 出口加拿大，包装需要至少2/3L UPC版，无硼版本。 7.邮包盒上要印刷日期码 | X30: Kelly Shen | Y30: 3.5384 | Z30: =Y30*J30 -> 63.6912 | AB30: 18 | AC30: =AB30-J30 -> 0 | AD30: ok | AE30: 已入 | AF30: 系统出单 | AG30: =J30 -> 18 | AH30: =J30 -> 18 | AI30: =J30 -> 18 | AL30: =J30 -> 18 | AU30: =J30 -> 18
A31: 45792 | B31: Sirius Sales (PTY) Ltd | C31: 南非 | D31: 4500166516 | F31: 4500166516-140 | G31: 7163TQ1-2023-S002-V1 | H31: 7163TQ1-2023-S002 | I31: 小鲨鱼 | J31: 600 | K31: 0 | L31: 24 | M31: =J31/L31 -> 25 | N31: 45838 | O31: 45834 | Q31: Pass | R31: 7/2出 | S31: 5/19收到 | U31: 无 | V31: MA UPC PKG(优先1L) | W31: 日期码格式：ZURU INC(BVI) 标准格式 日期：按实际生产日期 Packaging Info: 1. MA UPC PKG(优先1L) Remark: | X31: Doris Shou | Y31: 1.5793 | Z31: =Y31*J31 -> 947.58 | AA31: 95520-7.1 | AB31: 600 | AC31: =AB31-J31 -> 0 | AD31: 无 | AE31: 已入 | AF31: 系统出单 | AG31: =J31/3 -> 200 | AH31: =J31/3 -> 200 | AI31: =J31/3 -> 200 | AJ31: =J31 -> 600 | AL31: =J31 -> 600 | AM31: =J31/6 -> 100
A32: 45797 | B32: Lidl Hong Kong Limited-GB | C32: 西班牙 | D32: 4500159874 | E32: Ship to CB5-OSES (TO BCN) | F32: 4500159874-40 | G32: 7163A-2023-S007-V1 | H32: 7163A-2023-S001 | I32: 小鲨鱼胶袋装 | J32: 328 | K32: 0 | L32: 8 | M32: =J32/L32 -> 41 | N32: 45841 | O32: 45838 | Q32: Pass | S32: 5/30-FSC认证+上下保护卡 | U32: 5/21-胶袋条码贴纸 | V32: ZURU FRANCE 1/3, Rue d'Argenteuil 95210 SAINT-GRATIEN FRANCE. care@zuru.com | W32: 日期码格式：ZURU INC(BVI) 标准格式 日期：按实际生产日期 Packaging Info: 7163： 客版彩盒+客版说明书(+WEEE 带电池走货 通用30L 说明书) ship to CB5 和CB8 的订单（40-90行）： 需要要入包装后再加一个Polgbag+BABY GTIN Stciker (与彩盒上的一致） 电池盖需要印如下 ZURU FRANCE 1/3, Rue d'Argenteuil 95210 SAINT-GRATIEN FRANCE. care@zuru.com 不同颜色鲨鱼的彩盒上面的条码不同 40-90行为单独一个颜色一箱 都需要入 Polybag + BABY GTIN Stciker Blue BABY EAN : 4052916857670 -7163B- HG13558 Pink BABY EAN : 4052916857687 -7163D- HG13559 Yellow BABY EAN : 4052916857694 -7163A-HG13560 Remark: 1 产品带电池出货，电池需要符合欧洲标准； 2 客户可能会有抽板测试， 3 CB5，CB6 ，CB8的箱唛不相同，请参考具体的箱唛资料。 且各个国家外箱颜色，色号：鹿特丹 (黑色 2C)，備用產品Free of charge (黑色 2C) 4.外箱必须为FSC MIX坚固5层纸及再造纸材料造成，外箱上下必须各放上一张可遮盖全层面积的瓦楞纸板（至少450g/m2）以作开箱之保护。 箱唛上面箱规和重量与实际的箱唛箱规和重量差值不能超过3%。外箱上的条码需要确保能扫描。 外箱需做"工"字型封箱。外箱里面如果需要加拷贝纸或者保护卡，请提前通知跟单。 外箱需要是FSC MIX L纸箱厂 . 5. 产品，包装，外箱等所有包装上要打ZURU date code 6. 此单需要在兴信生产，需多备包材物料，客人每一款会抽50PCS的样品做产前和产中测试以及封版留底。客户不接受少出货。 验货分为： 0% 试产验货（LIDL QC) 30% 验货（LIDL QC) 50% 验货（LIDL QC) 100%验货（LIDL QC) 7. 货柜里面需放干燥剂，客户指定唯一品牌：Micro-Pak牌 45" 集装箱: 8KG Micro-Pak牌 (8條 x 每條1kg)， 40" HQ 集装箱: 7KG Micro-Pak牌 (7條 x 每條1kg)， 40" GP 集装箱: 6KG Micro-Pak牌(6條 x 每條1kg)， 20" GP 集装箱: 4KG Micro-Pak牌(4條x每條1kg) 装柜的时候需按箱号顺序装柜，即1号柜为1~500箱，2号柜为501~1000箱，3号柜为1001~1500箱。每个货柜里面可以不按外箱箱号的顺序大小进行排列。 8. 每个货柜柜尾需要加LOADING NET。 9. 此单出德国和欧洲，所有原材料和产品需满足德国和欧洲以及LIDL客人相关测试要求。 10. LIDL客人订单所有原材料/成品都需放置在雨禾室内仓库中，不能放于室外。 | X32: Amy Xiao | Y32: 1.5174 | Z32: =Y32*J32 -> 497.7072 | AB32: 东莞包装 | AC32: =AB32-J32 -> #VALUE! | AD32: ok | AE32: 已入 | AG32: =J32 -> 328 | AO32: =J32 -> 328 | AP32: =J32 -> 328
A33: 45797 | B33: Lidl Hong Kong Limited-GB | C33: 西班牙 | D33: 4500159874 | E33: Ship to CB5-OSES (TO BCN) | F33: 4500159874-50 | G33: 7163B-2023-S007-V1 | H33: 7163B-2023-S001 | I33: 小鲨鱼胶袋装 | J33: 488 | K33: 0 | L33: 8 | M33: =J33/L33 -> 61 | N33: 45841 | O33: 45838 | Q33: Pass | S33: 5/30-FSC认证+上下保护卡 | U33: 5/21-胶袋条码贴纸 | V33: ZURU FRANCE 1/3, Rue d'Argenteuil 95210 SAINT-GRATIEN FRANCE. care@zuru.com | W33: 日期码格式：ZURU INC(BVI) 标准格式 日期：按实际生产日期 Packaging Info: 7163： 客版彩盒+客版说明书(+WEEE 带电池走货 通用30L 说明书) ship to CB5 和CB8 的订单（40-90行）： 需要要入包装后再加一个Polgbag+BABY GTIN Stciker (与彩盒上的一致） 电池盖需要印如下 ZURU FRANCE 1/3, Rue d'Argenteuil 95210 SAINT-GRATIEN FRANCE. care@zuru.com 不同颜色鲨鱼的彩盒上面的条码不同 40-90行为单独一个颜色一箱 都需要入 Polybag + BABY GTIN Stciker Blue BABY EAN : 4052916857670 -7163B- HG13558 Pink BABY EAN : 4052916857687 -7163D- HG13559 Yellow BABY EAN : 4052916857694 -7163A-HG13560 Remark: 1 产品带电池出货，电池需要符合欧洲标准； 2 客户可能会有抽板测试， 3 CB5，CB6 ，CB8的箱唛不相同，请参考具体的箱唛资料。 且各个国家外箱颜色，色号：鹿特丹 (黑色 2C)，備用產品Free of charge (黑色 2C) 4.外箱必须为FSC MIX坚固5层纸及再造纸材料造成，外箱上下必须各放上一张可遮盖全层面积的瓦楞纸板（至少450g/m2）以作开箱之保护。 箱唛上面箱规和重量与实际的箱唛箱规和重量差值不能超过3%。外箱上的条码需要确保能扫描。 外箱需做"工"字型封箱。外箱里面如果需要加拷贝纸或者保护卡，请提前通知跟单。 外箱需要是FSC MIX L纸箱厂 . 5. 产品，包装，外箱等所有包装上要打ZURU date code 6. 此单需要在兴信生产，需多备包材物料，客人每一款会抽50PCS的样品做产前和产中测试以及封版留底。客户不接受少出货。 验货分为： 0% 试产验货（LIDL QC) 30% 验货（LIDL QC) 50% 验货（LIDL QC) 100%验货（LIDL QC) 7. 货柜里面需放干燥剂，客户指定唯一品牌：Micro-Pak牌 45" 集装箱: 8KG Micro-Pak牌 (8條 x 每條1kg)， 40" HQ 集装箱: 7KG Micro-Pak牌 (7條 x 每條1kg)， 40" GP 集装箱: 6KG Micro-Pak牌(6條 x 每條1kg)， 20" GP 集装箱: 4KG Micro-Pak牌(4條x每條1kg) 装柜的时候需按箱号顺序装柜，即1号柜为1~500箱，2号柜为501~1000箱，3号柜为1001~1500箱。每个货柜里面可以不按外箱箱号的顺序大小进行排列。 8. 每个货柜柜尾需要加LOADING NET。 9. 此单出德国和欧洲，所有原材料和产品需满足德国和欧洲以及LIDL客人相关测试要求。 10. LIDL客人订单所有原材料/成品都需放置在雨禾室内仓库中，不能放于室外。 | X33: Amy Xiao | Y33: 1.5174 | Z33: =Y33*J33 -> 740.4912 | AB33: 东莞包装 | AC33: =AB33-J33 -> #VALUE! | AD33: ok | AE33: 已入 | AH33: =J33 -> 488 | AO33: =J33 -> 488 | AP33: =J33 -> 488
A34: 45797 | B34: Lidl Hong Kong Limited-GB | C34: 西班牙 | D34: 4500159874 | E34: Ship to CB5-OSES (TO BCN) | F34: 4500159874-60 | G34: 7163D-2023-S007-V1 | H34: 7163D-2023-S001 | I34: 小鲨鱼胶袋装 | J34: 488 | K34: 0 | L34: 8 | M34: =J34/L34 -> 61 | N34: 45841 | O34: 45838 | Q34: Pass | S34: 5/30-FSC认证+上下保护卡 | U34: 5/21-胶袋条码贴纸 | V34: ZURU FRANCE 1/3, Rue d'Argenteuil 95210 SAINT-GRATIEN FRANCE. care@zuru.com | W34: 日期码格式：ZURU INC(BVI) 标准格式 日期：按实际生产日期 Packaging Info: 7163： 客版彩盒+客版说明书(+WEEE 带电池走货 通用30L 说明书) ship to CB5 和CB8 的订单（40-90行）： 需要要入包装后再加一个Polgbag+BABY GTIN Stciker (与彩盒上的一致） 电池盖需要印如下 ZURU FRANCE 1/3, Rue d'Argenteuil 95210 SAINT-GRATIEN FRANCE. care@zuru.com 不同颜色鲨鱼的彩盒上面的条码不同 40-90行为单独一个颜色一箱 都需要入 Polybag + BABY GTIN Stciker Blue BABY EAN : 4052916857670 -7163B- HG13558 Pink BABY EAN : 4052916857687 -7163D- HG13559 Yellow BABY EAN : 4052916857694 -7163A-HG13560 Remark: 1 产品带电池出货，电池需要符合欧洲标准； 2 客户可能会有抽板测试， 3 CB5，CB6 ，CB8的箱唛不相同，请参考具体的箱唛资料。 且各个国家外箱颜色，色号：鹿特丹 (黑色 2C)，備用產品Free of charge (黑色 2C) 4.外箱必须为FSC MIX坚固5层纸及再造纸材料造成，外箱上下必须各放上一张可遮盖全层面积的瓦楞纸板（至少450g/m2）以作开箱之保护。 箱唛上面箱规和重量与实际的箱唛箱规和重量差值不能超过3%。外箱上的条码需要确保能扫描。 外箱需做"工"字型封箱。外箱里面如果需要加拷贝纸或者保护卡，请提前通知跟单。 外箱需要是FSC MIX L纸箱厂 . 5. 产品，包装，外箱等所有包装上要打ZURU date code 6. 此单需要在兴信生产，需多备包材物料，客人每一款会抽50PCS的样品做产前和产中测试以及封版留底。客户不接受少出货。 验货分为： 0% 试产验货（LIDL QC) 30% 验货（LIDL QC) 50% 验货（LIDL QC) 100%验货（LIDL QC) 7. 货柜里面需放干燥剂，客户指定唯一品牌：Micro-Pak牌 45" 集装箱: 8KG Micro-Pak牌 (8條 x 每條1kg)， 40" HQ 集装箱: 7KG Micro-Pak牌 (7條 x 每條1kg)， 40" GP 集装箱: 6KG Micro-Pak牌(6條 x 每條1kg)， 20" GP 集装箱: 4KG Micro-Pak牌(4條x每條1kg) 装柜的时候需按箱号顺序装柜，即1号柜为1~500箱，2号柜为501~1000箱，3号柜为1001~1500箱。每个货柜里面可以不按外箱箱号的顺序大小进行排列。 8. 每个货柜柜尾需要加LOADING NET。 9. 此单出德国和欧洲，所有原材料和产品需满足德国和欧洲以及LIDL客人相关测试要求。 10. LIDL客人订单所有原材料/成品都需放置在雨禾室内仓库中，不能放于室外。 | X34: Amy Xiao | Y34: 1.5174 | Z34: =Y34*J34 -> 740.4912 | AB34: 东莞包装 | AC34: =AB34-J34 -> #VALUE! | AD34: ok | AE34: 已入 | AI34: =J34 -> 488 | AO34: =J34 -> 488 | AP34: =J34 -> 488
A35: 45797 | B35: Lidl Hong Kong Limited-GB | C35: 德国/英国/西班牙 | D35: 4500159874 | E35: SHIP TO CB8- OSBE/NL/CZ/FR /PL/SK (TO RTM) | F35: 4500159874-70 | G35: 7163A-2023-S007-V1 | H35: 7163A-2023-S001 | I35: 小鲨鱼胶袋装 | J35: 64 | K35: 0 | L35: 8 | M35: =J35/L35 -> 8 | N35: 45841 | O35: 45838 | Q35: Pass | S35: 5/30-FSC认证+上下保护卡 | U35: 5/21-胶袋条码贴纸 | V35: ZURU FRANCE 1/3, Rue d'Argenteuil 95210 SAINT-GRATIEN FRANCE. care@zuru.com | W35: 日期码格式：ZURU INC(BVI) 标准格式 日期：按实际生产日期 Packaging Info: 7163： 客版彩盒+客版说明书(+WEEE 带电池走货 通用30L 说明书) ship to CB5 和CB8 的订单（40-90行）： 需要要入包装后再加一个Polgbag+BABY GTIN Stciker (与彩盒上的一致） 电池盖需要印如下 ZURU FRANCE 1/3, Rue d'Argenteuil 95210 SAINT-GRATIEN FRANCE. care@zuru.com 不同颜色鲨鱼的彩盒上面的条码不同 40-90行为单独一个颜色一箱 都需要入 Polybag + BABY GTIN Stciker Blue BABY EAN : 4052916857670 -7163B- HG13558 Pink BABY EAN : 4052916857687 -7163D- HG13559 Yellow BABY EAN : 4052916857694 -7163A-HG13560 Remark: 1 产品带电池出货，电池需要符合欧洲标准； 2 客户可能会有抽板测试， 3 CB5，CB6 ，CB8的箱唛不相同，请参考具体的箱唛资料。 且各个国家外箱颜色，色号：鹿特丹 (黑色 2C)，備用產品Free of charge (黑色 2C) 4.外箱必须为FSC MIX坚固5层纸及再造纸材料造成，外箱上下必须各放上一张可遮盖全层面积的瓦楞纸板（至少450g/m2）以作开箱之保护。 箱唛上面箱规和重量与实际的箱唛箱规和重量差值不能超过3%。外箱上的条码需要确保能扫描。 外箱需做"工"字型封箱。外箱里面如果需要加拷贝纸或者保护卡，请提前通知跟单。 外箱需要是FSC MIX L纸箱厂 . 5. 产品，包装，外箱等所有包装上要打ZURU date code 6. 此单需要在兴信生产，需多备包材物料，客人每一款会抽50PCS的样品做产前和产中测试以及封版留底。客户不接受少出货。 验货分为： 0% 试产验货（LIDL QC) 30% 验货（LIDL QC) 50% 验货（LIDL QC) 100%验货（LIDL QC) 7. 货柜里面需放干燥剂，客户指定唯一品牌：Micro-Pak牌 45" 集装箱: 8KG Micro-Pak牌 (8條 x 每條1kg)， 40" HQ 集装箱: 7KG Micro-Pak牌 (7條 x 每條1kg)， 40" GP 集装箱: 6KG Micro-Pak牌(6條 x 每條1kg)， 20" GP 集装箱: 4KG Micro-Pak牌(4條x每條1kg) 装柜的时候需按箱号顺序装柜，即1号柜为1~500箱，2号柜为501~1000箱，3号柜为1001~1500箱。每个货柜里面可以不按外箱箱号的顺序大小进行排列。 8. 每个货柜柜尾需要加LOADING NET。 9. 此单出德国和欧洲，所有原材料和产品需满足德国和欧洲以及LIDL客人相关测试要求。 10. LIDL客人订单所有原材料/成品都需放置在雨禾室内仓库中，不能放于室外。 | X35: Amy Xiao | Y35: 1.5174 | Z35: =Y35*J35 -> 97.1136 | AB35: 东莞包装 | AC35: =AB35-J35 -> #VALUE! | AD35: ok | AE35: 已入 | AG35: =J35 -> 64 | AO35: =J35 -> 64 | AP35: =J35 -> 64
A36: 45797 | B36: Lidl Hong Kong Limited-GB | C36: 德国/英国/西班牙 | D36: 4500159874 | E36: SHIP TO CB8- OSBE/NL/CZ/FR /PL/SK (TO RTM) | F36: 4500159874-80 | G36: 7163B-2023-S007-V1 | H36: 7163B-2023-S001 | I36: 小鲨鱼胶袋装 | J36: 96 | K36: 0 | L36: 8 | M36: =J36/L36 -> 12 | N36: 45841 | O36: 45838 | Q36: Pass | S36: 5/30-FSC认证+上下保护卡 | U36: 5/21-胶袋条码贴纸 | V36: ZURU FRANCE 1/3, Rue d'Argenteuil 95210 SAINT-GRATIEN FRANCE. care@zuru.com | W36: 日期码格式：ZURU INC(BVI) 标准格式 日期：按实际生产日期 Packaging Info: 7163： 客版彩盒+客版说明书(+WEEE 带电池走货 通用30L 说明书) ship to CB5 和CB8 的订单（40-90行）： 需要要入包装后再加一个Polgbag+BABY GTIN Stciker (与彩盒上的一致） 电池盖需要印如下 ZURU FRANCE 1/3, Rue d'Argenteuil 95210 SAINT-GRATIEN FRANCE. care@zuru.com 不同颜色鲨鱼的彩盒上面的条码不同 40-90行为单独一个颜色一箱 都需要入 Polybag + BABY GTIN Stciker Blue BABY EAN : 4052916857670 -7163B- HG13558 Pink BABY EAN : 4052916857687 -7163D- HG13559 Yellow BABY EAN : 4052916857694 -7163A-HG13560 Remark: 1 产品带电池出货，电池需要符合欧洲标准； 2 客户可能会有抽板测试， 3 CB5，CB6 ，CB8的箱唛不相同，请参考具体的箱唛资料。 且各个国家外箱颜色，色号：鹿特丹 (黑色 2C)，備用產品Free of charge (黑色 2C) 4.外箱必须为FSC MIX坚固5层纸及再造纸材料造成，外箱上下必须各放上一张可遮盖全层面积的瓦楞纸板（至少450g/m2）以作开箱之保护。 箱唛上面箱规和重量与实际的箱唛箱规和重量差值不能超过3%。外箱上的条码需要确保能扫描。 外箱需做"工"字型封箱。外箱里面如果需要加拷贝纸或者保护卡，请提前通知跟单。 外箱需要是FSC MIX L纸箱厂 . 5. 产品，包装，外箱等所有包装上要打ZURU date code 6. 此单需要在兴信生产，需多备包材物料，客人每一款会抽50PCS的样品做产前和产中测试以及封版留底。客户不接受少出货。 验货分为： 0% 试产验货（LIDL QC) 30% 验货（LIDL QC) 50% 验货（LIDL QC) 100%验货（LIDL QC) 7. 货柜里面需放干燥剂，客户指定唯一品牌：Micro-Pak牌 45" 集装箱: 8KG Micro-Pak牌 (8條 x 每條1kg)， 40" HQ 集装箱: 7KG Micro-Pak牌 (7條 x 每條1kg)， 40" GP 集装箱: 6KG Micro-Pak牌(6條 x 每條1kg)， 20" GP 集装箱: 4KG Micro-Pak牌(4條x每條1kg) 装柜的时候需按箱号顺序装柜，即1号柜为1~500箱，2号柜为501~1000箱，3号柜为1001~1500箱。每个货柜里面可以不按外箱箱号的顺序大小进行排列。 8. 每个货柜柜尾需要加LOADING NET。 9. 此单出德国和欧洲，所有原材料和产品需满足德国和欧洲以及LIDL客人相关测试要求。 10. LIDL客人订单所有原材料/成品都需放置在雨禾室内仓库中，不能放于室外。 | X36: Amy Xiao | Y36: 1.5174 | Z36: =Y36*J36 -> 145.6704 | AB36: 东莞包装 | AC36: =AB36-J36 -> #VALUE! | AD36: ok | AE36: 已入 | AH36: =J36 -> 96 | AO36: =J36 -> 96 | AP36: =J36 -> 96
A37: 45797 | B37: Lidl Hong Kong Limited-GB | C37: 德国/英国/西班牙 | D37: 4500159874 | E37: SHIP TO CB8- OSBE/NL/CZ/FR /PL/SK (TO RTM) | F37: 4500159874-90 | G37: 7163D-2023-S007-V1 | H37: 7163D-2023-S001 | I37: 小鲨鱼胶袋装 | J37: 96 | K37: 0 | L37: 8 | M37: =J37/L37 -> 12 | N37: 45841 | O37: 45838 | Q37: Pass | S37: 5/30-FSC认证+上下保护卡 | U37: 5/21-胶袋条码贴纸 | V37: ZURU FRANCE 1/3, Rue d'Argenteuil 95210 SAINT-GRATIEN FRANCE. care@zuru.com | W37: 日期码格式：ZURU INC(BVI) 标准格式 日期：按实际生产日期 Packaging Info: 7163： 客版彩盒+客版说明书(+WEEE 带电池走货 通用30L 说明书) ship to CB5 和CB8 的订单（40-90行）： 需要要入包装后再加一个Polgbag+BABY GTIN Stciker (与彩盒上的一致） 电池盖需要印如下 ZURU FRANCE 1/3, Rue d'Argenteuil 95210 SAINT-GRATIEN FRANCE. care@zuru.com 不同颜色鲨鱼的彩盒上面的条码不同 40-90行为单独一个颜色一箱 都需要入 Polybag + BABY GTIN Stciker Blue BABY EAN : 4052916857670 -7163B- HG13558 Pink BABY EAN : 4052916857687 -7163D- HG13559 Yellow BABY EAN : 4052916857694 -7163A-HG13560 Remark: 1 产品带电池出货，电池需要符合欧洲标准； 2 客户可能会有抽板测试， 3 CB5，CB6 ，CB8的箱唛不相同，请参考具体的箱唛资料。 且各个国家外箱颜色，色号：鹿特丹 (黑色 2C)，備用產品Free of charge (黑色 2C) 4.外箱必须为FSC MIX坚固5层纸及再造纸材料造成，外箱上下必须各放上一张可遮盖全层面积的瓦楞纸板（至少450g/m2）以作开箱之保护。 箱唛上面箱规和重量与实际的箱唛箱规和重量差值不能超过3%。外箱上的条码需要确保能扫描。 外箱需做"工"字型封箱。外箱里面如果需要加拷贝纸或者保护卡，请提前通知跟单。 外箱需要是FSC MIX L纸箱厂 . 5. 产品，包装，外箱等所有包装上要打ZURU date code 6. 此单需要在兴信生产，需多备包材物料，客人每一款会抽50PCS的样品做产前和产中测试以及封版留底。客户不接受少出货。 验货分为： 0% 试产验货（LIDL QC) 30% 验货（LIDL QC) 50% 验货（LIDL QC) 100%验货（LIDL QC) 7. 货柜里面需放干燥剂，客户指定唯一品牌：Micro-Pak牌 45" 集装箱: 8KG Micro-Pak牌 (8條 x 每條1kg)， 40" HQ 集装箱: 7KG Micro-Pak牌 (7條 x 每條1kg)， 40" GP 集装箱: 6KG Micro-Pak牌(6條 x 每條1kg)， 20" GP 集装箱: 4KG Micro-Pak牌(4條x每條1kg) 装柜的时候需按箱号顺序装柜，即1号柜为1~500箱，2号柜为501~1000箱，3号柜为1001~1500箱。每个货柜里面可以不按外箱箱号的顺序大小进行排列。 8. 每个货柜柜尾需要加LOADING NET。 9. 此单出德国和欧洲，所有原材料和产品需满足德国和欧洲以及LIDL客人相关测试要求。 10. LIDL客人订单所有原材料/成品都需放置在雨禾室内仓库中，不能放于室外。 | X37: Amy Xiao | Y37: 1.5174 | Z37: =Y37*J37 -> 145.6704 | AB37: 东莞包装 | AC37: =AB37-J37 -> #VALUE! | AD37: ok | AE37: 已入 | AI37: =J37 -> 96 | AO37: =J37 -> 96 | AP37: =J37 -> 96
A38: 45729 | B38: Lidl Hong Kong Limited-ES | C38: 英国 | D38: 4500159874 | E38: Ship to CB6-GB | F38: 4500159874-20 | G38: 7163-2023-S007-V1 | H38: 7163-2023-S007 | I38: 小鲨鱼-干燥剂指定品牌 | J38: 19960 | K38: 0 | L38: 8 | M38: =J38/L38 -> 2495 | N38: 45841 | O38: 45838 | P38: 来料抽查：6/23 上产线时间 ：6/24号 30%抽查时间 ：6/26号 50%抽查时间 ：6/27号 100%抽查的时间 :7/3号 | Q38: Pass | S38: 5/30-FSC认证+上下保护卡 | U38: 无 | V38: ZURU FRANCE 1/3, Rue d'Argenteuil 95210 SAINT-GRATIEN FRANCE. care@zuru.com | W38: 日期码格式：ZURU INC(BVI) 标准格式 日期：按实际生产日期 Packaging Info: 7163： 客版彩盒+客版说明书(+WEEE 带电池走货 通用30L 说明书) ship to CB5 和CB8 的订单（40-90行）： 需要要入包装后再加一个Polgbag+BABY GTIN Stciker (与彩盒上的一致） 电池盖需要印如下 ZURU FRANCE 1/3, Rue d'Argenteuil 95210 SAINT-GRATIEN FRANCE. care@zuru.com 不同颜色鲨鱼的彩盒上面的条码不同 20 行的配比如下： 3pcs Blue BABY EAN : 4052916857670 -7163B- HG13558 3pcs Pink BABY EAN : 4052916857687 -7163D- HG13559 2pcs Yellow BABY EAN : 4052916857694 -7163A-HG13560 Remark: 1 产品带电池出货，电池需要符合欧洲标准； 2 客户可能会有抽板测试， 3 CB5，CB6 ，CB8的箱唛不相同，请参考具体的箱唛资料。 且各个国家外箱颜色，色号：鹿特丹 (黑色 2C)，備用產品Free of charge (黑色 2C) 4.外箱必须为FSC MIX坚固5层纸及再造纸材料造成，外箱上下必须各放上一张可遮盖全层面积的瓦楞纸板（至少450g/m2）以作开箱之保护。 箱唛上面箱规和重量与实际的箱唛箱规和重量差值不能超过3%。外箱上的条码需要确保能扫描。 外箱需做"工"字型封箱。外箱里面如果需要加拷贝纸或者保护卡，请提前通知跟单。 外箱需要是FSC MIX L纸箱厂 . 5. 产品，包装，外箱等所有包装上要打ZURU date code 6. 此单需要在兴信生产，需多备包材物料，客人每一款会抽50PCS的样品做产前和产中测试以及封版留底。客户不接受少出货。 验货分为： 0% 试产验货（LIDL QC) 30% 验货（LIDL QC) 50% 验货（LIDL QC) 100%验货（LIDL QC) 7. 货柜里面需放干燥剂，客户指定唯一品牌：Micro-Pak牌 45" 集装箱: 8KG Micro-Pak牌 (8條 x 每條1kg)， 40" HQ 集装箱: 7KG Micro-Pak牌 (7條 x 每條1kg)， 40" GP 集装箱: 6KG Micro-Pak牌(6條 x 每條1kg)， 20" GP 集装箱: 4KG Micro-Pak牌(4條x每條1kg) 装柜的时候需按箱号顺序装柜，即1号柜为1~500箱，2号柜为501~1000箱，3号柜为1001~1500箱。每个货柜里面可以不按外箱箱号的顺序大小进行排列。 8. 每个货柜柜尾需要加LOADING NET。 9. 此单出德国和欧洲，所有原材料和产品需满足德国和欧洲以及LIDL客人相关测试要求。 10. LIDL客人订单所有原材料/成品都需放置在雨禾室内仓库中，不能放于室外。 | X38: Amy Xiao | Y38: 1.2953 | Z38: =Y38*J38 -> 25854.188 | AB38: 东莞包装 | AC38: =AB38-J38 -> #VALUE! | AD38: OK | AE38: 已入 | AG38: =J38/8*2 -> 4990 | AH38: =J38/8*3 -> 7485 | AI38: =J38/8*3 -> 7485 | AO38: =J38 -> 19960 | AP38: =J38 -> 19960
A39: 45812 | B39: SUBURBIA S DE R. L. DE C. V. | C39: 墨西哥 | D39: 4500168910 | E39: 6000056638 | F39: 4500168910-40 | G39: 7163TQ1-2023-S002-V1-3L | H39: 7163TQ1-2023-S002 | I39: 小鲨鱼 | J39: 504 | K39: 0 | L39: 24 | M39: =J39/L39 -> 21 | N39: 45841 | O39: 45846 | Q39: Pass | R39: 7/10出 | S39: 外箱只需四面印Zurulogo， | U39: 进口商贴纸+价标贴纸+说明书贴纸+Hu贴纸+ASN贴纸 | V39: 7163TQ1:MA 3L EAN包装 | W39: 日期码格式：ZURU INC(BVI) 标准格式 日期：按实际生产日期 Packaging Info: 7163TQ1:MA 3L EAN包装+MA 9L说明书+MA 3L PDQ+进口商贴纸+价标贴纸+说明书贴纸 1. 外箱只需四面印Zurulogo，再加2张贴纸，1张Hu贴纸（条码贴,尺寸103*51mm），1张ASN贴纸（尺寸6.5cm*6.3cm,潘通色号2597C），都贴于侧唛，只需贴1面(HU 贴纸和ASN贴纸客供） 2. 一个外箱对应一个HU’S(条形码),不可以混条码包装 3.含有说明书需要增加说明书贴纸 4.价格贴纸覆盖原有包装的条形码 Remark: 7163TQ1: 3 assortment,3PCS LR44 BATTERIES(INCLUDED) 此单有监柜要求，需要每款多准备一套完整物料，用于监柜，不可以随大货走 | X39: Ever Li | Y39: 1.5793 | Z39: =Y39*J39 -> 795.9672 | AA39: 95616-7.11 | AB39: 504 | AC39: =AB39-J39 -> 0 | AD39: ok | AE39: 已入 | AF39: 系统出单 | AG39: =J39/3 -> 168 | AH39: =J39/3 -> 168 | AI39: =J39/3 -> 168 | AK39: =J39 -> 504 | AL39: =J39 -> 504 | AM39: =J39/6 -> 84
A40: 45805 | B40: Amazon CA (Vendor Center) | C40: 加拿大 | D40: 4500168205 | E40: B0CCGTNC3D | F40: 4500168205-10 | G40: 7166-2023-S002-V1-3L | H40: 7166-2023-S002 | I40: 小鲨鱼3PK | J40: 54 | K40: 0 | L40: 18 | M40: =J40/L40 -> 3 | N40: 45842 | O40: =N40-4 -> 45838 | Q40: Pass | S40: 5/29收到 | U40: UPC贴纸翻单4500148503+6/18客供防伪帖纸， | V40: 7166 MA 3L 加UPC贴纸 | W40: 日期码格式：ZURU INC(BVI) 标准格式 日期：按实际生产日期 Packaging Info: 出口加拿大，包装需要至少2/3L UPC版，无硼版本。 #7166 MA 3L 加UPC贴纸，UPC贴纸资料翻单4500148503。需要加一张客供防伪帖纸，贴纸跟单提供。 Remark: 1. Amazon FOB订单，出口CA。外箱最长边不能超过25" （超过了，case pack只能为1），不符合要求的大货，一律不接受。 2. 外箱正面印ZURU Logo + SSCC LABEL（客供贴纸)，侧面印item#（订单上显示的SKU#) + carton size(以工厂实际尺寸为准，单位: inch) + MADE IN CHINA， 日期使用ZURU 标准版本 SSCC Label 显示的是客人自己的item#，SSCC Label 贴在外箱正面的正中间，贴一面即可，跟单订购，贴纸离外箱距必须至少3cm，每一 张SSCC label 都是唯一且有不同流水及条码的，没有损耗，绝对不可贴错 ，否则贴错或损坏一张会导致全部都错，千万要注意: SSCC 贴纸务必要在正中间(可以覆 盖Logo <(>&<)> 箱唛)，否则会影响到仓库扫描识别。 3. 日期码使用ZURU标准版本。 4. 如果大货有要求入邮包盒，则对应的邮包盒上面要打上日期码。 5. 按照客户PO# 装柜/箱号顺序装柜，跟单会提前给到装柜计划。在大货生产/仓库存放时，请留意该装柜要求，以便装柜时不混乱（避免装错/装漏/找不到货号等 ）。 6. 出口加拿大，包装需要至少2/3L UPC版，无硼版本。 7.邮包盒上要印刷日期码 | X40: Kelly Shen | Y40: 3.5384 | Z40: =Y40*J40 -> 191.0736 | AA40: 95673-7.17 | AB40: 54 | AC40: =AB40-J40 -> 0 | AD40: ok | AE40: 已入 | AF40: 系统出单 | AG40: =J40 -> 54 | AH40: =J40 -> 54 | AI40: =J40 -> 54 | AL40: =J40 -> 54 | AU40: =J40 -> 54
A41: 45818 | B41: ZURU LLC | C41: 美国 | D41: 4500169495 | E41: B0CCGTNC3D | F41: 4500169495-170 | G41: 7166-2023-S002-V1-3L | H41: 7166-2023-S002-MTS | I41: 小鲨鱼3PK | J41: 1998 | K41: 0 | L41: 18 | M41: =J41/L41 -> 111 | N41: 45855 | O41: 45852 | Q41: Pass | S41: 6/10收到 | U41: 7/9-客供防伪帖纸 | V41: 7166 MA 3L UPC版本 | W41: 日期码格式：ZURU INC(BVI) 标准格式 日期：按实际生产日期 Packaging Info: #7166 MA 3L UPC版本。需要加一张客供防伪帖纸，贴纸跟单提供。 Remark: 1.Amazon domestic 订单。出口美国。外箱最长边不能超过25" （超过了，case pack只能为1），不符合要求的大货，一律不接受。 2.无第三方验货/测试要求。 3.日期码使用ZURU标准版本。 4.邮包盒要印刷日期码。 | X41: Kelly Shen/Mia Pan/P | Y41: 2.2485 | Z41: =Y41*J41 -> 4492.503 | AA41: ZB01104R1-8.6 | AB41: 1998 | AC41: =AB41-J41 -> 0 | AD41: ok | AE41: 已入 | AF41: 系统出单 | AG41: =J41 -> 1998 | AH41: =J41 -> 1998 | AI41: =J41 -> 1998 | AL41: =J41 -> 1998 | AU41: =J41 -> 1998
A42: 45741 | B42: Andrés Dauhajre SA (LA NOVIA DE VIL | C42: 多米尼加共和国 | D42: 4500160544 | F42: 4500160544-40 | G42: 7163TQ1-2023-S002-V1-3L | H42: 7163TQ1-2023-S002 | I42: 小鲨鱼 | J42: 48 | K42: 0 | L42: 24 | M42: =J42/L42 -> 2 | N42: 45856 | O42: 45852 | Q42: Pass | S42: 6/11收到 | U42: 3/31-UPC贴纸 | V42: MA 3L EAN包装 | W42: 日期码格式：ZURU INC(BVI) 标准格式 日期：按实际生产日期 Packaging Info: 7163TQ1：MA 3L EAN包装+UPC贴纸+MA PDQ包装+MA 多语收藏指南+箱唛 Remark: | X42: Ava Liang | Y42: 1.5793 | Z42: =Y42*J42 -> 75.8064 | AA42: 95728-7.22 | AB42: 48 | AC42: =AB42-J42 -> 0 | AD42: ok | AE42: 已入 | AF42: 系统出单 | AG42: =J42/3 -> 16 | AH42: =J42/3 -> 16 | AI42: =J42/3 -> 16 | AK42: =J42 -> 48 | AL42: =J42 -> 48 | AM42: =J42/6 -> 8
A43: 45821 | B43: AMAZON CA (VENDOR CENTER) | C43: 加拿大 | D43: 4500169971 | E43: 77QW6TOE | F43: 4500169971-100 | G43: 7166-2023-S002-V1-3L | H43: 7166-2023-S002 | I43: 小鲨鱼3PK | J43: 54 | K43: 0 | L43: 18 | M43: 3 | N43: 45856 | O43: 45852 | Q43: PASS | S43: 6/13收到 | U43: UPC贴纸翻4500148503+7/9-客供防伪帖纸+7/11外箱贴纸 | V43: #7166 MA 3L 加UPC贴纸 | W43: 日期码格式：ZURU INC(BVI) 标准格式 日期：按实际生产日期 Packaging Info: #7166 MA 3L 加UPC贴纸，UPC贴纸资料翻单4500148503。需要加一张客供防伪帖纸，贴纸跟单提供。 Remark: 1. Amazon FOB订单，出口CA。外箱最长边不能超过25" （超过了，case pack只能为1），不符合要求的大货，一律不接受。 2. 外箱正面印ZURU Logo + SSCC LABEL（客供贴纸)，侧面印item#（订单上显示的SKU#) + carton size(以工厂实际尺寸为准，单位: inch) + MADE IN CHINA， 日期使用ZURU 标准版本 SSCC Label 显示的是客人自己的item#，SSCC Label 贴在外箱正面的正中间，贴一面即可，跟单订购，贴纸离外箱距必须至少3cm，每一 张SSCC label 都是唯一且有不同流水及条码的，没有损耗，绝对不可贴错 ，否则贴错或损坏一张会导致全部都错，千万要注意: SSCC 贴纸务必要在正中间(可以覆 盖Logo <(>&<)> 箱唛)，否则会影响到仓库扫描识别。 3. 日期码使用ZURU标准版本。 4. 如果大货有要求入邮包盒，则对应的邮包盒上面要打上日期码。 5. 按照客户PO# 装柜/箱号顺序装柜，跟单会提前给到装柜计划。在大货生产/仓库存放时，请留意该装柜要求，以便装柜时不混乱（避免装错/装漏/找不到货号等 ）。 6. 出口加拿大，包装需要至少2/3L UPC版，无硼版本。 7.邮包盒上要印刷日期码 | X43: Kelly Shen | Y43: 3.5711 | Z43: =Y43*J43 -> 192.8394 | AB43: 54 | AC43: =AB43-J43 -> 0 | AD43: ok | AE43: 已入 | AF43: 系统出单 | AG43: =J43 -> 54 | AH43: =J43 -> 54 | AI43: =J43 -> 54 | AL43: =J43 -> 54 | AU43: =J43 -> 54
A44: 45821 | B44: AMAZON CA (VENDOR CENTER) | C44: 加拿大 | D44: 4500169971 | E44: 6UABWYFZ | F44: 4500169971-110 | G44: 7166-2023-S002-V1-3L | H44: 7166-2023-S002 | I44: 小鲨鱼3PK | J44: 36 | K44: 0 | L44: 18 | M44: 2 | N44: 45856 | O44: 45852 | Q44: PASS | S44: 6/13收到 | U44: UPC贴纸翻4500148503+7/9-客供防伪帖纸+7/11外箱贴纸 | V44: #7166 MA 3L 加UPC贴纸 | W44: 日期码格式：ZURU INC(BVI) 标准格式 日期：按实际生产日期 Packaging Info: #7166 MA 3L 加UPC贴纸，UPC贴纸资料翻单4500148503。需要加一张客供防伪帖纸，贴纸跟单提供。 Remark: 1. Amazon FOB订单，出口CA。外箱最长边不能超过25" （超过了，case pack只能为1），不符合要求的大货，一律不接受。 2. 外箱正面印ZURU Logo + SSCC LABEL（客供贴纸)，侧面印item#（订单上显示的SKU#) + carton size(以工厂实际尺寸为准，单位: inch) + MADE IN CHINA， 日期使用ZURU 标准版本 SSCC Label 显示的是客人自己的item#，SSCC Label 贴在外箱正面的正中间，贴一面即可，跟单订购，贴纸离外箱距必须至少3cm，每一 张SSCC label 都是唯一且有不同流水及条码的，没有损耗，绝对不可贴错 ，否则贴错或损坏一张会导致全部都错，千万要注意: SSCC 贴纸务必要在正中间(可以覆 盖Logo <(>&<)> 箱唛)，否则会影响到仓库扫描识别。 3. 日期码使用ZURU标准版本。 4. 如果大货有要求入邮包盒，则对应的邮包盒上面要打上日期码。 5. 按照客户PO# 装柜/箱号顺序装柜，跟单会提前给到装柜计划。在大货生产/仓库存放时，请留意该装柜要求，以便装柜时不混乱（避免装错/装漏/找不到货号等 ）。 6. 出口加拿大，包装需要至少2/3L UPC版，无硼版本。 7.邮包盒上要印刷日期码 | X44: Kelly Shen | Y44: 3.5711 | Z44: =Y44*J44 -> 128.5596 | AB44: 36 | AC44: =AB44-J44 -> 0 | AD44: ok | AE44: 已入 | AF44: 系统出单 | AG44: =J44 -> 36 | AH44: =J44 -> 36 | AI44: =J44 -> 36 | AL44: =J44 -> 36 | AU44: =J44 -> 36
A45: 45821 | B45: AMAZON CA (VENDOR CENTER) | C45: 加拿大 | D45: 4500169971 | E45: 5SOY56BN | F45: 4500169971-120 | G45: 7166-2023-S002-V1-3L | H45: 7166-2023-S002 | I45: 小鲨鱼3PK | J45: 108 | K45: 0 | L45: 18 | M45: 6 | N45: 45856 | O45: 45852 | Q45: PASS | S45: 6/13收到 | U45: UPC贴纸翻4500148503+7/9-客供防伪帖纸+7/11外箱贴纸 | V45: #7166 MA 3L 加UPC贴纸 | W45: 日期码格式：ZURU INC(BVI) 标准格式 日期：按实际生产日期 Packaging Info: #7166 MA 3L 加UPC贴纸，UPC贴纸资料翻单4500148503。需要加一张客供防伪帖纸，贴纸跟单提供。 Remark: 1. Amazon FOB订单，出口CA。外箱最长边不能超过25" （超过了，case pack只能为1），不符合要求的大货，一律不接受。 2. 外箱正面印ZURU Logo + SSCC LABEL（客供贴纸)，侧面印item#（订单上显示的SKU#) + carton size(以工厂实际尺寸为准，单位: inch) + MADE IN CHINA， 日期使用ZURU 标准版本 SSCC Label 显示的是客人自己的item#，SSCC Label 贴在外箱正面的正中间，贴一面即可，跟单订购，贴纸离外箱距必须至少3cm，每一 张SSCC label 都是唯一且有不同流水及条码的，没有损耗，绝对不可贴错 ，否则贴错或损坏一张会导致全部都错，千万要注意: SSCC 贴纸务必要在正中间(可以覆 盖Logo <(>&<)> 箱唛)，否则会影响到仓库扫描识别。 3. 日期码使用ZURU标准版本。 4. 如果大货有要求入邮包盒，则对应的邮包盒上面要打上日期码。 5. 按照客户PO# 装柜/箱号顺序装柜，跟单会提前给到装柜计划。在大货生产/仓库存放时，请留意该装柜要求，以便装柜时不混乱（避免装错/装漏/找不到货号等 ）。 6. 出口加拿大，包装需要至少2/3L UPC版，无硼版本。 7.邮包盒上要印刷日期码 | X45: Kelly Shen | Y45: 3.5711 | Z45: =Y45*J45 -> 385.6788 | AB45: 108 | AC45: =AB45-J45 -> 0 | AD45: ok | AE45: 已入 | AF45: 系统出单 | AG45: =J45 -> 108 | AH45: =J45 -> 108 | AI45: =J45 -> 108 | AL45: =J45 -> 108 | AU45: =J45 -> 108
A46: 45821 | B46: AMAZON CA (VENDOR CENTER) | C46: 加拿大 | D46: 4500169971 | E46: 5YPGJDMJ | F46: 4500169971-130 | G46: 7166-2023-S002-V1-3L | H46: 7166-2023-S002 | I46: 小鲨鱼3PK | J46: 54 | K46: 0 | L46: 18 | M46: 3 | N46: 45856 | O46: 45852 | Q46: PASS | S46: 6/13收到 | U46: UPC贴纸翻4500148503+7/9-客供防伪帖纸+7/11外箱贴纸 | V46: #7166 MA 3L 加UPC贴纸 | W46: 日期码格式：ZURU INC(BVI) 标准格式 日期：按实际生产日期 Packaging Info: #7166 MA 3L 加UPC贴纸，UPC贴纸资料翻单4500148503。需要加一张客供防伪帖纸，贴纸跟单提供。 Remark: 1. Amazon FOB订单，出口CA。外箱最长边不能超过25" （超过了，case pack只能为1），不符合要求的大货，一律不接受。 2. 外箱正面印ZURU Logo + SSCC LABEL（客供贴纸)，侧面印item#（订单上显示的SKU#) + carton size(以工厂实际尺寸为准，单位: inch) + MADE IN CHINA， 日期使用ZURU 标准版本 SSCC Label 显示的是客人自己的item#，SSCC Label 贴在外箱正面的正中间，贴一面即可，跟单订购，贴纸离外箱距必须至少3cm，每一 张SSCC label 都是唯一且有不同流水及条码的，没有损耗，绝对不可贴错 ，否则贴错或损坏一张会导致全部都错，千万要注意: SSCC 贴纸务必要在正中间(可以覆 盖Logo <(>&<)> 箱唛)，否则会影响到仓库扫描识别。 3. 日期码使用ZURU标准版本。 4. 如果大货有要求入邮包盒，则对应的邮包盒上面要打上日期码。 5. 按照客户PO# 装柜/箱号顺序装柜，跟单会提前给到装柜计划。在大货生产/仓库存放时，请留意该装柜要求，以便装柜时不混乱（避免装错/装漏/找不到货号等 ）。 6. 出口加拿大，包装需要至少2/3L UPC版，无硼版本。 7.邮包盒上要印刷日期码 | X46: Kelly Shen | Y46: 3.5711 | Z46: =Y46*J46 -> 192.8394 | AB46: 54 | AC46: =AB46-J46 -> 0 | AD46: ok | AE46: 已入 | AF46: 系统出单 | AG46: =J46 -> 54 | AH46: =J46 -> 54 | AI46: =J46 -> 54 | AL46: =J46 -> 54 | AU46: =J46 -> 54
A47: 45821 | B47: AMAZON CA (VENDOR CENTER) | C47: 加拿大 | D47: 4500169971 | E47: 8C5EI7LQ | F47: 4500169971-140 | G47: 7166-2023-S002-V1-3L | H47: 7166-2023-S002 | I47: 小鲨鱼3PK | J47: 36 | K47: 0 | L47: 18 | M47: 2 | N47: 45856 | O47: 45852 | Q47: PASS | S47: 6/13收到 | U47: UPC贴纸翻4500148503+7/9-客供防伪帖纸+7/11外箱贴纸 | V47: #7166 MA 3L 加UPC贴纸 | W47: 日期码格式：ZURU INC(BVI) 标准格式 日期：按实际生产日期 Packaging Info: #7166 MA 3L 加UPC贴纸，UPC贴纸资料翻单4500148503。需要加一张客供防伪帖纸，贴纸跟单提供。 Remark: 1. Amazon FOB订单，出口CA。外箱最长边不能超过25" （超过了，case pack只能为1），不符合要求的大货，一律不接受。 2. 外箱正面印ZURU Logo + SSCC LABEL（客供贴纸)，侧面印item#（订单上显示的SKU#) + carton size(以工厂实际尺寸为准，单位: inch) + MADE IN CHINA， 日期使用ZURU 标准版本 SSCC Label 显示的是客人自己的item#，SSCC Label 贴在外箱正面的正中间，贴一面即可，跟单订购，贴纸离外箱距必须至少3cm，每一 张SSCC label 都是唯一且有不同流水及条码的，没有损耗，绝对不可贴错 ，否则贴错或损坏一张会导致全部都错，千万要注意: SSCC 贴纸务必要在正中间(可以覆 盖Logo <(>&<)> 箱唛)，否则会影响到仓库扫描识别。 3. 日期码使用ZURU标准版本。 4. 如果大货有要求入邮包盒，则对应的邮包盒上面要打上日期码。 5. 按照客户PO# 装柜/箱号顺序装柜，跟单会提前给到装柜计划。在大货生产/仓库存放时，请留意该装柜要求，以便装柜时不混乱（避免装错/装漏/找不到货号等 ）。 6. 出口加拿大，包装需要至少2/3L UPC版，无硼版本。 7.邮包盒上要印刷日期码 | X47: Kelly Shen | Y47: 3.5711 | Z47: =Y47*J47 -> 128.5596 | AB47: 36 | AC47: =AB47-J47 -> 0 | AD47: ok | AE47: 已入 | AF47: 系统出单 | AG47: =J47 -> 36 | AH47: =J47 -> 36 | AI47: =J47 -> 36 | AL47: =J47 -> 36 | AU47: =J47 -> 36
A48: 45821 | B48: AMAZON CA (VENDOR CENTER) | C48: 加拿大 | D48: 4500169971 | E48: 4OEKYI5B | F48: 4500169971-150 | G48: 7166-2023-S002-V1-3L | H48: 7166-2023-S002 | I48: 小鲨鱼3PK | J48: 72 | K48: 0 | L48: 18 | M48: 4 | N48: 45856 | O48: 45852 | Q48: PASS | S48: 6/13收到 | U48: UPC贴纸翻4500148503+7/9-客供防伪帖纸+7/11外箱贴纸 | V48: #7166 MA 3L 加UPC贴纸 | W48: 日期码格式：ZURU INC(BVI) 标准格式 日期：按实际生产日期 Packaging Info: #7166 MA 3L 加UPC贴纸，UPC贴纸资料翻单4500148503。需要加一张客供防伪帖纸，贴纸跟单提供。 Remark: 1. Amazon FOB订单，出口CA。外箱最长边不能超过25" （超过了，case pack只能为1），不符合要求的大货，一律不接受。 2. 外箱正面印ZURU Logo + SSCC LABEL（客供贴纸)，侧面印item#（订单上显示的SKU#) + carton size(以工厂实际尺寸为准，单位: inch) + MADE IN CHINA， 日期使用ZURU 标准版本 SSCC Label 显示的是客人自己的item#，SSCC Label 贴在外箱正面的正中间，贴一面即可，跟单订购，贴纸离外箱距必须至少3cm，每一 张SSCC label 都是唯一且有不同流水及条码的，没有损耗，绝对不可贴错 ，否则贴错或损坏一张会导致全部都错，千万要注意: SSCC 贴纸务必要在正中间(可以覆 盖Logo <(>&<)> 箱唛)，否则会影响到仓库扫描识别。 3. 日期码使用ZURU标准版本。 4. 如果大货有要求入邮包盒，则对应的邮包盒上面要打上日期码。 5. 按照客户PO# 装柜/箱号顺序装柜，跟单会提前给到装柜计划。在大货生产/仓库存放时，请留意该装柜要求，以便装柜时不混乱（避免装错/装漏/找不到货号等 ）。 6. 出口加拿大，包装需要至少2/3L UPC版，无硼版本。 7.邮包盒上要印刷日期码 | X48: Kelly Shen | Y48: 3.5711 | Z48: =Y48*J48 -> 257.1192 | AB48: 72 | AC48: =AB48-J48 -> 0 | AD48: ok | AE48: 已入 | AF48: 系统出单 | AG48: =J48 -> 72 | AH48: =J48 -> 72 | AI48: =J48 -> 72 | AL48: =J48 -> 72 | AU48: =J48 -> 72
A49: 45824 | B49: AMAZON CA (VENDOR CENTER) | C49: 加拿大 | D49: 4500170137 | E49: 3B9C3X9T | F49: 4500170137-130 | G49: 7166-2023-S002-V1-3L | H49: 7166-2023-S002 | I49: 小鲨鱼3PK | J49: 36 | K49: 0 | L49: 18 | M49: 2 | N49: 45859 | O49: 45855 | Q49: PASS | S49: 6/16收到 | U49: UPC贴纸翻4500148503+7/9客供防伪帖纸+7/11外箱贴纸 | V49: #7166 MA 3L 加UPC贴纸 | W49: 日期码格式：ZURU INC(BVI) 标准格式 日期：按实际生产日期 Packaging Info: #7166 MA 3L 加UPC贴纸，UPC贴纸资料翻单4500148503。需要加一张客供防伪帖纸，贴纸跟单提供。 Remark: 1. Amazon FOB订单，出口CA。外箱最长边不能超过25" （超过了，case pack只能为1），不符合要求的大货，一律不接受。 2. 外箱正面印ZURU Logo + SSCC LABEL（客供贴纸)，侧面印item#（订单上显示的SKU#) + carton size(以工厂实际尺寸为准，单位: inch) + MADE IN CHINA， 日期使用ZURU 标准版本 SSCC Label 显示的是客人自己的item#，SSCC Label 贴在外箱正面的正中间，贴一面即可，跟单订购，贴纸离外箱距必须至少3cm，每一 张SSCC label 都是唯一且有不同流水及条码的，没有损耗，绝对不可贴错 ，否则贴错或损坏一张会导致全部都错，千万要注意: SSCC 贴纸务必要在正中间(可以覆 盖Logo <(>&<)> 箱唛)，否则会影响到仓库扫描识别。 3. 日期码使用ZURU标准版本。 4. 如果大货有要求入邮包盒，则对应的邮包盒上面要打上日期码。 5. 按照客户PO# 装柜/箱号顺序装柜，跟单会提前给到装柜计划。在大货生产/仓库存放时，请留意该装柜要求，以便装柜时不混乱（避免装错/装漏/找不到货号等 ）。 6. 出口加拿大，包装需要至少2/3L UPC版，无硼版本。 7.邮包盒上要印刷日期码 | X49: Kelly Shen | Y49: 3.5711 | Z49: =Y49*J49 -> 128.5596 | AB49: 36 | AC49: =AB49-J49 -> 0 | AD49: ok | AE49: 已入 | AF49: 系统出单 | AG49: =J49 -> 36 | AH49: =J49 -> 36 | AI49: =J49 -> 36 | AL49: =J49 -> 36 | AU49: =J49 -> 36
A50: 45824 | B50: AMAZON CA (VENDOR CENTER) | C50: 加拿大 | D50: 4500170137 | E50: 2D13RWAM | F50: 4500170137-140 | G50: 7166-2023-S002-V1-3L | H50: 7166-2023-S002 | I50: 小鲨鱼3PK | J50: 18 | K50: 0 | L50: 18 | M50: 1 | N50: 45859 | O50: 45855 | Q50: PASS | S50: 6/16收到 | U50: UPC贴纸翻4500148503+7/9客供防伪帖纸+7/11外箱贴纸 | V50: #7166 MA 3L 加UPC贴纸 | W50: 日期码格式：ZURU INC(BVI) 标准格式 日期：按实际生产日期 Packaging Info: #7166 MA 3L 加UPC贴纸，UPC贴纸资料翻单4500148503。需要加一张客供防伪帖纸，贴纸跟单提供。 Remark: 1. Amazon FOB订单，出口CA。外箱最长边不能超过25" （超过了，case pack只能为1），不符合要求的大货，一律不接受。 2. 外箱正面印ZURU Logo + SSCC LABEL（客供贴纸)，侧面印item#（订单上显示的SKU#) + carton size(以工厂实际尺寸为准，单位: inch) + MADE IN CHINA， 日期使用ZURU 标准版本 SSCC Label 显示的是客人自己的item#，SSCC Label 贴在外箱正面的正中间，贴一面即可，跟单订购，贴纸离外箱距必须至少3cm，每一 张SSCC label 都是唯一且有不同流水及条码的，没有损耗，绝对不可贴错 ，否则贴错或损坏一张会导致全部都错，千万要注意: SSCC 贴纸务必要在正中间(可以覆 盖Logo <(>&<)> 箱唛)，否则会影响到仓库扫描识别。 3. 日期码使用ZURU标准版本。 4. 如果大货有要求入邮包盒，则对应的邮包盒上面要打上日期码。 5. 按照客户PO# 装柜/箱号顺序装柜，跟单会提前给到装柜计划。在大货生产/仓库存放时，请留意该装柜要求，以便装柜时不混乱（避免装错/装漏/找不到货号等 ）。 6. 出口加拿大，包装需要至少2/3L UPC版，无硼版本。 7.邮包盒上要印刷日期码 | X50: Kelly Shen | Y50: 3.5711 | Z50: =Y50*J50 -> 64.2798 | AB50: 18 | AC50: =AB50-J50 -> 0 | AD50: ok | AE50: 已入 | AF50: 系统出单 | AG50: =J50 -> 18 | AH50: =J50 -> 18 | AI50: =J50 -> 18 | AL50: =J50 -> 18 | AU50: =J50 -> 18
A51: 45824 | B51: AMAZON CA (VENDOR CENTER) | C51: 加拿大 | D51: 4500170137 | E51: 78OH3BVV | F51: 4500170137-150 | G51: 7166-2023-S002-V1-3L | H51: 7166-2023-S002 | I51: 小鲨鱼3PK | J51: 18 | K51: 0 | L51: 18 | M51: 1 | N51: 45859 | O51: 45855 | Q51: PASS | S51: 6/16收到 | U51: UPC贴纸翻4500148503+7/9客供防伪帖纸+7/11外箱贴纸 | V51: #7166 MA 3L 加UPC贴纸 | W51: 日期码格式：ZURU INC(BVI) 标准格式 日期：按实际生产日期 Packaging Info: #7166 MA 3L 加UPC贴纸，UPC贴纸资料翻单4500148503。需要加一张客供防伪帖纸，贴纸跟单提供。 Remark: 1. Amazon FOB订单，出口CA。外箱最长边不能超过25" （超过了，case pack只能为1），不符合要求的大货，一律不接受。 2. 外箱正面印ZURU Logo + SSCC LABEL（客供贴纸)，侧面印item#（订单上显示的SKU#) + carton size(以工厂实际尺寸为准，单位: inch) + MADE IN CHINA， 日期使用ZURU 标准版本 SSCC Label 显示的是客人自己的item#，SSCC Label 贴在外箱正面的正中间，贴一面即可，跟单订购，贴纸离外箱距必须至少3cm，每一 张SSCC label 都是唯一且有不同流水及条码的，没有损耗，绝对不可贴错 ，否则贴错或损坏一张会导致全部都错，千万要注意: SSCC 贴纸务必要在正中间(可以覆 盖Logo <(>&<)> 箱唛)，否则会影响到仓库扫描识别。 3. 日期码使用ZURU标准版本。 4. 如果大货有要求入邮包盒，则对应的邮包盒上面要打上日期码。 5. 按照客户PO# 装柜/箱号顺序装柜，跟单会提前给到装柜计划。在大货生产/仓库存放时，请留意该装柜要求，以便装柜时不混乱（避免装错/装漏/找不到货号等 ）。 6. 出口加拿大，包装需要至少2/3L UPC版，无硼版本。 7.邮包盒上要印刷日期码 | X51: Kelly Shen | Y51: 3.5711 | Z51: =Y51*J51 -> 64.2798 | AB51: 18 | AC51: =AB51-J51 -> 0 | AD51: ok | AE51: 已入 | AF51: 系统出单 | AG51: =J51 -> 18 | AH51: =J51 -> 18 | AI51: =J51 -> 18 | AL51: =J51 -> 18 | AU51: =J51 -> 18
A52: 45824 | B52: AMAZON CA (VENDOR CENTER) | C52: 加拿大 | D52: 4500170137 | E52: 4G1XO7KI | F52: 4500170137-160 | G52: 7166-2023-S002-V1-3L | H52: 7166-2023-S002 | I52: 小鲨鱼3PK | J52: 18 | K52: 0 | L52: 18 | M52: 1 | N52: 45859 | O52: 45855 | Q52: PASS | S52: 6/16收到 | U52: UPC贴纸翻4500148503+7/9客供防伪帖纸+7/11外箱贴纸 | V52: #7166 MA 3L 加UPC贴纸 | W52: 日期码格式：ZURU INC(BVI) 标准格式 日期：按实际生产日期 Packaging Info: #7166 MA 3L 加UPC贴纸，UPC贴纸资料翻单4500148503。需要加一张客供防伪帖纸，贴纸跟单提供。 Remark: 1. Amazon FOB订单，出口CA。外箱最长边不能超过25" （超过了，case pack只能为1），不符合要求的大货，一律不接受。 2. 外箱正面印ZURU Logo + SSCC LABEL（客供贴纸)，侧面印item#（订单上显示的SKU#) + carton size(以工厂实际尺寸为准，单位: inch) + MADE IN CHINA， 日期使用ZURU 标准版本 SSCC Label 显示的是客人自己的item#，SSCC Label 贴在外箱正面的正中间，贴一面即可，跟单订购，贴纸离外箱距必须至少3cm，每一 张SSCC label 都是唯一且有不同流水及条码的，没有损耗，绝对不可贴错 ，否则贴错或损坏一张会导致全部都错，千万要注意: SSCC 贴纸务必要在正中间(可以覆 盖Logo <(>&<)> 箱唛)，否则会影响到仓库扫描识别。 3. 日期码使用ZURU标准版本。 4. 如果大货有要求入邮包盒，则对应的邮包盒上面要打上日期码。 5. 按照客户PO# 装柜/箱号顺序装柜，跟单会提前给到装柜计划。在大货生产/仓库存放时，请留意该装柜要求，以便装柜时不混乱（避免装错/装漏/找不到货号等 ）。 6. 出口加拿大，包装需要至少2/3L UPC版，无硼版本。 7.邮包盒上要印刷日期码 | X52: Kelly Shen | Y52: 3.5711 | Z52: =Y52*J52 -> 64.2798 | AB52: 18 | AC52: =AB52-J52 -> 0 | AD52: ok | AE52: 已入 | AF52: 系统出单 | AG52: =J52 -> 18 | AH52: =J52 -> 18 | AI52: =J52 -> 18 | AL52: =J52 -> 18 | AU52: =J52 -> 18
A53: 45824 | B53: AMAZON CA (VENDOR CENTER) | C53: 加拿大 | D53: 4500170137 | E53: 11NGUJCZ | F53: 4500170137-170 | G53: 7166-2023-S002-V1-3L | H53: 7166-2023-S002 | I53: 小鲨鱼3PK | J53: 18 | K53: 0 | L53: 18 | M53: 1 | N53: 45859 | O53: 45855 | Q53: PASS | S53: 6/16收到 | U53: UPC贴纸翻4500148503+7/9客供防伪帖纸+7/11外箱贴纸 | V53: #7166 MA 3L 加UPC贴纸 | W53: 日期码格式：ZURU INC(BVI) 标准格式 日期：按实际生产日期 Packaging Info: #7166 MA 3L 加UPC贴纸，UPC贴纸资料翻单4500148503。需要加一张客供防伪帖纸，贴纸跟单提供。 Remark: 1. Amazon FOB订单，出口CA。外箱最长边不能超过25" （超过了，case pack只能为1），不符合要求的大货，一律不接受。 2. 外箱正面印ZURU Logo + SSCC LABEL（客供贴纸)，侧面印item#（订单上显示的SKU#) + carton size(以工厂实际尺寸为准，单位: inch) + MADE IN CHINA， 日期使用ZURU 标准版本 SSCC Label 显示的是客人自己的item#，SSCC Label 贴在外箱正面的正中间，贴一面即可，跟单订购，贴纸离外箱距必须至少3cm，每一 张SSCC label 都是唯一且有不同流水及条码的，没有损耗，绝对不可贴错 ，否则贴错或损坏一张会导致全部都错，千万要注意: SSCC 贴纸务必要在正中间(可以覆 盖Logo <(>&<)> 箱唛)，否则会影响到仓库扫描识别。 3. 日期码使用ZURU标准版本。 4. 如果大货有要求入邮包盒，则对应的邮包盒上面要打上日期码。 5. 按照客户PO# 装柜/箱号顺序装柜，跟单会提前给到装柜计划。在大货生产/仓库存放时，请留意该装柜要求，以便装柜时不混乱（避免装错/装漏/找不到货号等 ）。 6. 出口加拿大，包装需要至少2/3L UPC版，无硼版本。 7.邮包盒上要印刷日期码 | X53: Kelly Shen | Y53: 3.5711 | Z53: =Y53*J53 -> 64.2798 | AB53: 18 | AC53: =AB53-J53 -> 0 | AD53: ok | AE53: 已入 | AF53: 系统出单 | AG53: =J53 -> 18 | AH53: =J53 -> 18 | AI53: =J53 -> 18 | AL53: =J53 -> 18 | AU53: =J53 -> 18
A54: 45807 | B54: AMAZON.COM SERVICES LLC | C54: 美国 | D54: 4500168600 | E54: 4GAN42YV | F54: 4500168600-60 | G54: 7166-2023-S002-V1-3L | H54: 7166-2023-S002 | I54: 小鲨鱼3PK | J54: 522 | K54: 0 | L54: 18 | M54: =J54/L54 -> 29 | N54: 45860 | O54: =N54-4 -> 45856 | Q54: PASS | S54: 5/30收到 | U54: UPC贴纸翻4500148503+7/9客供防伪帖纸+7/11外箱贴纸 | V54: #7166 MA 3L UPC版 | W54: 日期码格式：ZURU INC(BVI) 标准格式 日期：按实际生产日期 Packaging Info: #7166 MA 3L UPC版本。需要加一张客供防伪帖纸，贴纸跟单提供。 Remark: 1. Amazon MDDP订单，出口US。 2. 日期码使用ZURU标准版本。 3. 如果大货有要求入邮包盒，则对应的邮包盒上面要打上日期码。 4. 箱尺寸要求：外箱最长边不能超过25"(超过了，case pack只能为1)，不符合要求的大货，一律不接受。 5. 外箱箱唛要求： ①外箱正面印ZURU Logo+SSCC Label(客供贴纸，由跟单订购)。关于 SSCC Label 请注意： SSCC Label显示的是客人自己的item#。每一张SSCC label都是唯一且有不同流水及条码的，没有损耗，绝对不可贴错。如果贴错或损坏任何一张，都会导致全部都 错，千万要注意！SSCC Label必须贴在外箱正面的正中间位置(贴一面即可)，并且贴纸离外箱边距必须至少3cm(可以覆盖Logo<(>&<)>箱唛)，否则会影响到客户那边 仓库的扫描识别。 ②外箱侧面印item#(订单上显示的SKU#)+carton size(以工厂实际尺寸为准，单位: inch)+MADE IN CHINA，日期使用ZURU 标准版本。 6. 装柜要求：按照客户PO#装柜/箱号顺序装柜，跟单会提前给到装柜计划。 在大货生产/仓库存放时，请留意该装柜要求，以便装柜时不混乱(避免装错/装漏/找不到货号等)。 | X54: Kelly Shen/Mia Pan/P | Y54: 3.5711 | Z54: =Y54*J54 -> 1864.1142 | AB54: =504+18 -> 522 | AC54: =AB54-J54 -> 0 | AD54: ok | AE54: 已入 | AF54: 系统出单 | AG54: =J54 -> 522 | AH54: =J54 -> 522 | AI54: =J54 -> 522 | AL54: =J54 -> 522 | AU54: =J54 -> 522
A55: 45811 | B55: AMAZON.COM SERVICES LLC | C55: 美国 | D55: 4500168775 | E55: 3THD3DBC | F55: 4500168775-140 | G55: 7166-2023-S002-V1-3L | H55: 7166-2023-S002 | I55: 小鲨鱼3PK | J55: 36 | K55: 0 | L55: 18 | M55: =J55/L55 -> 2 | N55: 45866 | O55: 45862 | Q55: PASS | R55: 8/7出 | S55: 6/3收到 | U55: UPC贴纸翻4500148503+7/9客供防伪帖纸+7/11外箱贴纸 | V55: #7166 MA 3L UPC版 | W55: 日期码格式：ZURU INC(BVI) 标准格式 日期：按实际生产日期 Packaging Info: #7166 MA 3L UPC版本。需要加一张客供防伪帖纸，贴纸跟单提供。 Remark: 1. Amazon MDDP订单，出口US。 2. 日期码使用ZURU标准版本。 3. 如果大货有要求入邮包盒，则对应的邮包盒上面要打上日期码。 4. 箱尺寸要求：外箱最长边不能超过25"(超过了，case pack只能为1)，不符合要求的大货，一律不接受。 5. 外箱箱唛要求： ①外箱正面印ZURU Logo+SSCC Label(客供贴纸，由跟单订购)。关于 SSCC Label 请注意： SSCC Label显示的是客人自己的item#。每一张SSCC label都是唯一且有不同流水及条码的，没有损耗，绝对不可贴错。如果贴错或损坏任何一张，都会导致全部都 错，千万要注意！SSCC Label必须贴在外箱正面的正中间位置(贴一面即可)，并且贴纸离外箱边距必须至少3cm(可以覆盖Logo<(>&<)>箱唛)，否则会影响到客户那边 仓库的扫描识别。 ②外箱侧面印item#(订单上显示的SKU#)+carton size(以工厂实际尺寸为准，单位: inch)+MADE IN CHINA，日期使用ZURU 标准版本。 6. 装柜要求：按照客户PO#装柜/箱号顺序装柜，跟单会提前给到装柜计划。 在大货生产/仓库存放时，请留意该装柜要求，以便装柜时不混乱(避免装错/装漏/找不到货号等)。 | X55: Kelly Shen/Mia Pan/P | Y55: 3.5711 | Z55: =Y55*J55 -> 128.5596 | AA55: ZB01122-8.7 | AB55: 36 | AC55: =AB55-J55 -> 0 | AD55: ok | AE55: 已入 | AF55: 系统出单 | AG55: =J55 -> 36 | AH55: =J55 -> 36 | AI55: =J55 -> 36 | AL55: =J55 -> 36 | AU55: =J55 -> 36
A56: 45813 | B56: AMAZON.COM SERVICES LLC | C56: 美国 | D56: 4500169031 | E56: 41SCEYKI | F56: 4500169031-30 | G56: 7166-2023-S002-V1-3L | H56: 7166-2023-S002 | I56: 小鲨鱼3PK | J56: 648 | K56: 0 | L56: 18 | M56: =J56/L56 -> 36 | N56: 45866 | O56: 45862 | Q56: PASS | S56: 6/5收到 | U56: UPC贴纸翻4500148503+7/9客供防伪帖纸+7/11外箱贴纸 | V56: #7166 MA 3L UPC版 | W56: 日期码格式：ZURU INC(BVI) 标准格式 日期：按实际生产日期 Packaging Info: 7166 MA 3L 加UPC贴纸，UPC贴纸资料翻单4500152657.需要加一张客供防伪帖纸，贴纸跟单提供。 Remark: 1. Amazon MDDP订单，出口US。 2. 日期码使用ZURU标准版本。 3. 如果大货有要求入邮包盒，则对应的邮包盒上面要打上日期码。 4. 箱尺寸要求：外箱最长边不能超过25"(超过了，case pack只能为1)，不符合要求的大货，一律不接受。 5. 外箱箱唛要求： ①外箱正面印ZURU Logo+SSCC Label(客供贴纸，由跟单订购)。关于 SSCC Label 请注意： SSCC Label显示的是客人自己的item#。每一张SSCC label都是唯一且有不同流水及条码的，没有损耗，绝对不可贴错。如果贴错或损坏任何一张，都会导致全部都 错，千万要注意！SSCC Label必须贴在外箱正面的正中间位置(贴一面即可)，并且贴纸离外箱边距必须至少3cm(可以覆盖Logo<(>&<)>箱唛)，否则会影响到客户那边 仓库的扫描识别。 ②外箱侧面印item#(订单上显示的SKU#)+carton size(以工厂实际尺寸为准，单位: inch)+MADE IN CHINA，日期使用ZURU 标准版本。 6. 装柜要求：按照客户PO#装柜/箱号顺序装柜，跟单会提前给到装柜计划。 在大货生产/仓库存放时，请留意该装柜要求，以便装柜时不混乱(避免装错/装漏/找不到货号等)。 | X56: Kelly Shen/Mia Pan/P | Y56: 3.5711 | Z56: =Y56*J56 -> 2314.0728 | AA56: ZB01037-8.4 | AB56: 648 | AC56: =AB56-J56 -> 0 | AD56: ok | AE56: 已入 | AF56: 系统出单 | AG56: =J56 -> 648 | AH56: =J56 -> 648 | AI56: =J56 -> 648 | AL56: =J56 -> 648 | AU56: =J56 -> 648
A57: 45813 | B57: AMAZON.COM SERVICES LLC | C57: 美国 | D57: 4500168994 | E57: 47STT6VE | F57: 4500168994-160 | G57: 7166-2023-S002-V1-3L | H57: 7166-2023-S002 | I57: 小鲨鱼3PK | J57: 630 | K57: 0 | L57: 18 | M57: =J57/L57 -> 35 | N57: 45866 | O57: 45862 | Q57: PASS | R57: 8/1出 | S57: 6/5收到 | U57: UPC贴纸翻4500148503+7/9客供防伪帖纸+7/11外箱贴纸 | V57: #7166 MA 3L UPC版 | W57: 日期码格式：ZURU INC(BVI) 标准格式 日期：按实际生产日期 Packaging Info: #7166 MA 3L 加UPC贴纸，UPC贴纸资料翻单4500152657。需要加一张客供防伪帖纸，贴纸跟单提供。 Remark: 1. Amazon MDDP订单，出口US。 2. 日期码使用ZURU标准版本。 3. 如果大货有要求入邮包盒，则对应的邮包盒上面要打上日期码。 4. 箱尺寸要求：外箱最长边不能超过25"(超过了，case pack只能为1)，不符合要求的大货，一律不接受。 5. 外箱箱唛要求： ①外箱正面印ZURU Logo+SSCC Label(客供贴纸，由跟单订购)。关于 SSCC Label 请注意： SSCC Label显示的是客人自己的item#。每一张SSCC label都是唯一且有不同流水及条码的，没有损耗，绝对不可贴错。如果贴错或损坏任何一张，都会导致全部都 错，千万要注意！SSCC Label必须贴在外箱正面的正中间位置(贴一面即可)，并且贴纸离外箱边距必须至少3cm(可以覆盖Logo<(>&<)>箱唛)，否则会影响到客户那边 仓库的扫描识别。 ②外箱侧面印item#(订单上显示的SKU#)+carton size(以工厂实际尺寸为准，单位: inch)+MADE IN CHINA，日期使用ZURU 标准版本。 6. 装柜要求：按照客户PO#装柜/箱号顺序装柜，跟单会提前给到装柜计划。 在大货生产/仓库存放时，请留意该装柜要求，以便装柜时不混乱(避免装错/装漏/找不到货号等)。 | X57: Kelly Shen/Mia Pan/P | Y57: 3.5711 | Z57: =Y57*J57 -> 2249.793 | AB57: 630 | AC57: =AB57-J57 -> 0 | AD57: ok | AE57: 已入 | AF57: 系统出单 | AG57: =J57 -> 630 | AH57: =J57 -> 630 | AI57: =J57 -> 630 | AL57: =J57 -> 630 | AU57: =J57 -> 630
A58: 45828 | B58: AMIC TRADING (PTY) LTD | C58: 南非 | D58: 4500170860 | E58: 6006-007765 | F58: 4500170860-30 | G58: 7166-2023-S002-V1 | H58: 7166-2023-S002 | I58: 小鲨鱼3PK | J58: 504 | K58: 0 | L58: 18 | M58: =J58/L58 -> 28 | N58: 45873 | O58: =N58-4 -> 45869 | Q58: PASS | S58: 6/24收到 | U58: 进口商贴纸翻4500154694） | V58: nfo: MA PKG, 优先1L | W58: 日期码格式：ZURU INC(BVI) 标准格式 日期：按实际生产日期 Packaging Info: MA PKG, 优先1L +1张进口商贴纸（通用进口商贴纸翻单4500154694） #7151 进口商贴纸位置图翻单4500154694 Remark: | X58: Doris Shou | Y58: 3.6743 | Z58: =Y58*J58 -> 1851.8472 | AB58: 504 | AC58: =AB58-J58 -> 0 | AD58: OK | AE58: 已入 | AF58: 系统出单 | AG58: =J58 -> 504 | AH58: =J58 -> 504 | AI58: =J58 -> 504 | AL58: =J58 -> 504 | AT58: =J58 -> 504
A59: 45838 | B59: BEALL'S OUTLET STORES, INC. | C59: 美国 | D59: 4500171200 | E59: 1613019 | F59: 4500171200-30 | G59: 7163-2023-S003-3L-V1 | H59: 7163-2023-S003 | I59: 小鲨鱼 | J59: 816 | K59: 0 | L59: 24 | M59: =J59/L59 -> 34 | N59: 45875 | O59: 45871 | P59: 客户可以接受3L彩盒 | Q59: PASS | R59: 8/6出 | S59: 7/3收到 | U59: 7/9-客供价格贴纸 | V59: ZURU最新MA UPC包装(优先1L) | W59: 日期码格式：ZURU INC(BVI) 标准格式 日期：按实际生产日期 Packaging Info: 1.ZURU最新MA UPC包装(优先1L) + 客供价格贴纸（贴在产品包装右下角，跟单找第三方订购贴纸寄到工厂） Remark: 1.ZURU最新MA UPC包装(优先1L) + 客供价格贴纸（贴在产品包装右下角，跟单找第三方订购贴纸寄到工厂）。 2. 所有产品外包装及产品本身都必须有日期跟踪码(ZURU标准日期码格式，年月日的日期自行调整，但不能为周末)，并且确保产品及外包装的日期跟踪码要一致 | X59: Hailey Yu | Y59: 0.9025 | Z59: =Y59*J59 -> 736.44 | AA59: ZB01206-8.12 | AB59: 816 | AC59: =AB59-J59 -> 0 | AD59: OK | AE59: 已入 | AF59: 系统出单 | AG59: =J59/3 -> 272 | AH59: =J59/3 -> 272 | AI59: =J59/3 -> 272 | AK59: =J59 -> 816 | AL59: =J59 -> 816
A60: 45863 | B60: TJX UK C/O TJX DISTRIBUTION LTD & C | C60: 德国 | D60: 4500175056 | E60: 55255876 | F60: 4500175056-10 | G60: 7163-2023-S003-1L-V1 | H60: 7163-2023-S003 | I60: 小鲨鱼 | J60: 1008 | K60: 0 | L60: 24 | M60: =J60/L60 -> 42 | N60: 45891 | O60: 45887 | P60: 箱唛更新内容 | Q60: PASS | S60: 7/25收到 | U60: ZURU标准格式的30语带电池出货版本WEEE说明书+7/31-贴纸（含德语+荷兰语+波兰语警告语） | V60: 7163: MA1L (1L warning) 最新UPC包装 | W60: 日期码格式：ZURU INC(BVI) 标准格式 日期：按实际生产日期 Packaging Info: SKU#7163: MA1L (3L warning) 最新UPC包装+ZURU标准格式的30语带电池出货版本WEEE说明书+1张贴纸（含德语+荷兰语+波兰语警告语） Remark: "1. 出往UK的产品+包装务必打上UKCA logo ，否则客人会退货且当地会有罚款； 2. 订单必须经过ZURU QC验货并且通过后方可出货； 3. 订单每行对应客人不同的PO， 箱唛也有不同，做货的时候请分开堆放； 4. 包装条码请按包装备注上的对应的警示语语种包装，出德国的订单(订单备注为TJX Europe-DE)需要确保有英语+德语+荷兰语+波兰语警示语； 5. 订单每行对应客人不同的PO（客人PO号请参考PO最后一栏remark）； 6. 涉及到相关款式会有闪粉的或者微塑料的，请统一默认出无闪粉或者不含微塑料版本; 7. 外箱封箱必须是工字型封箱方式；" | X60: AaronXia | Y60: 1.5121 | Z60: =Y60*J60 -> 1524.1968 | AB60: 1008 | AC60: =AB60-J60 -> 0 | AD60: OK | AE60: 已入 | AF60: 系统出单 | AG60: =J60/3 -> 336 | AH60: =J60/3 -> 336 | AI60: =J60/3 -> 336 | AJ60: =J60 -> 1008 | AL60: =J60 -> 1008
A61: 45863 | B61: TJX UK | C61: 英国 | D61: 4500175035 | E61: 50077882 | F61: 4500175035-10 | G61: 7163-2023-S003-1L-V1 | H61: 7163-2023-S003 | I61: 小鲨鱼 | J61: 1008 | K61: 0 | L61: 24 | M61: =J61/L61 -> 42 | N61: 45891 | O61: 45887 | P61: 箱唛更新内容 | Q61: PASS | S61: 7/25收到 | U61: ZURU标准格式的30语带电池出货版本WEEE说明书+1张贴纸（含德语+荷兰语+波兰语警告语） | V61: 7163: MA1L (1L warning) 最新UPC包装 | W61: 日期码格式：ZURU INC(BVI) 标准格式 日期：按实际生产日期 Packaging Info: SKU#7163: MA1L (1L warning) 最新UPC包装+ZURU标准格式的30语带电池出货版本WEEE说明书 Remark: 1. 出往UK的产品+包装务必打上UKCA logo ，否则客人会退货且当地会有罚款； 2. 订单必须经过ZURU QC验货并且通过后方可出货； 3. 订单每行对应客人不同的PO， 箱唛也有不同，做货的时候请分开堆放； 4. 包装条码请按包装备注上的对应的警示语语种包装，出德国的订单(订单备注为TJX Europe-DE)需要确保有英语+德语+荷兰语+波兰语警示语； 5. 订单每行对应客人不同的PO（客人PO号请参考PO最后一栏remark）； 6. 涉及到相关款式会有闪粉的或者微塑料的，请统一默认出无闪粉或者不含微塑料版本; 7. 外箱封箱必须是工字型封箱方式；" | X61: AaronXia | Y61: 1.5121 | Z61: =Y61*J61 -> 1524.1968 | AB61: 1008 | AC61: =AB61-J61 -> 0 | AD61: ok | AE61: 已入 | AF61: 系统出单 | AG61: =J61/3 -> 336 | AH61: =J61/3 -> 336 | AI61: =J61/3 -> 336 | AJ61: =J61 -> 1008 | AL61: =J61 -> 1008
A62: 45860 | B62: BEALL'S OUTLET STORES, INC. | C62: 美国 | D62: 4500174533 | E62: 1613020 | F62: 4500174533-30 | G62: 7163-2023-S003-1L-V1 | H62: 7163-2023-S003 | I62: 小鲨鱼 | J62: 408 | K62: 0 | L62: 24 | M62: =J62/L62 -> 17 | N62: 45903 | O62: =N62-4 -> 45899 | P62: 1L/3L彩盒都可用，3L需要加贴UPC贴纸 | Q62: PASS | R62: 9/3出 | S62: 7/31收到 | U62: 8/13-客供价格贴纸 | V62: .ZURU最新MA UPC包装(优先1L) | W62: 日期码格式：ZURU INC(BVI) 标准格式 日期：按实际生产日期 Packaging Info: 1.ZURU最新MA UPC包装(优先1L) +客供价格贴纸（贴在产品包装右下角，跟单找第三方订购贴纸寄到工厂）。 Remark: 1.ZURU最新MA UPC包装(优先1L) +客供价格贴纸（贴在产品包装右下角，跟单找第三方订购贴纸寄到工厂）。 2. 所有产品外包装及产品本身都必须有日期跟踪码(ZURU标准日期码格式，年月日的日期自行调整，但不能为周末)，并且确保产品及外包装的日期跟踪码要一致. | X62: Hailey Yu | Y62: 0.9025 | Z62: =Y62*J62 -> 368.22 | AA62: ZB01732-9.6 | AB62: 408 | AC62: =AB62-J62 -> 0 | AD62: ok | AE62: 已入 | AF62: 系统出单 | AG62: =J62/3 -> 136 | AH62: =J62/3 -> 136 | AI62: =J62/3 -> 136 | AJ62: =J62 -> 408 | AL62: =J62 -> 408
A63: 45855 | B63: AMIC TRADING (PTY) LTD | C63: 南非 | D63: 4500174099 | E63: 6006-008172 | F63: 4500174099-60 | G63: 7166-2023-S002-V1 | H63: 7166-2023-S002 | I63: 小鲨鱼3PK | J63: 180 | K63: 0 | L63: 18 | M63: =J63/L63 -> 10 | N63: 45905 | O63: 45901 | Q63: PASS | S63: 7/18收到 | U63: 进口商贴纸翻4500170860 | V63: MA PKG, 优先1L | W63: 日期码格式：ZURU INC(BVI) 标准格式 日期：按实际生产日期 Packaging Info: MA PKG, 优先1L +1张进口商贴纸（通用进口商贴纸新稿，适用订单所有产品） 7166进口商贴纸位置图翻单4500170860 Remark: 此单Customer PO#6006-008172 PI#1100029505-1 | X63: Doris Shou | Y63: 3.6437 | Z63: =Y63*J63 -> 655.866 | AB63: 180 | AC63: =AB63-J63 -> 0 | AD63: ok | AE63: 已入 | AF63: 系统出单 | AG63: =J63 -> 180 | AH63: =J63 -> 180 | AI63: =J63 -> 180 | AL63: =J63 -> 180 | AT63: =J63 -> 180
A64: 45881 | D64: ZMPO250685 | G64: 7163TQ1-2023-S002-V1 | H64: 7163TQ1-2023-S002 | I64: 小鲨鱼 | J64: 168 | K64: 0 | L64: 24 | M64: =J64/L64 -> 7 | N64: 45902 | O64: =N64-4 -> 45898 | Q64: PASS | S64: 周转箱 | U64: 无 | V64: 大货最新版本 | W64: Remark:大货最新版本/款号平均/请用大货标准箱装箱唛请参照邮件附件;备注： 收到样品订单后尽快安排 ，此订单麻烦在外箱上备注是海运订单/注意样板品质质量要求要高于大货品质质量 ，送货时必须要附带送货单(没有送货单和QC检验合格报告的仓库一律拒绝收货)，请知悉，谢谢！ | X64: Angus | AB64: 168 | AC64: =AB64-J64 -> 0 | AD64: 无 | AE64: 已入 | AF64: 系统出单 | AG64: =J64/3 -> 56 | AH64: =J64/3 -> 56 | AI64: =J64/3 -> 56 | AJ64: =J64 -> 168 | AL64: =J64 -> 168 | AM64: =J64/6 -> 28
A65: 45868 | B65: AMAZON.COM SERVICES LLC | C65: 美国 | D65: 4500175579 | E65: 67BF3WHQ | F65: 4500175579-10 | G65: 7166-2023-S002-V1-3L | H65: 7166-2023-S002 | I65: 小鲨鱼3PK | J65: 828 | K65: 0 | L65: 18 | M65: =J65/L65 -> 46 | N65: 45903 | O65: =N65-4 -> 45899 | Q65: PASS | R65: 收到SO | S65: 7/30收到 | U65: UPC贴纸资料翻单4500152657+8/18-客供外箱贴纸+8/21-客供防伪帖纸 | V65: #7166 MA 3L 加UPC贴纸 | W65: 日期码格式：ZURU INC(BVI) 标准格式 日期：按实际生产日期 Packaging Info: #7166 MA 3L 加UPC贴纸，UPC贴纸资料翻单4500152657.需要加一张客供防伪帖纸，贴纸跟单提供。 Remark: 1. Amazon MDDP订单，出口US。 2. 日期码使用ZURU标准版本。 3. 如果大货有要求入邮包盒，则对应的邮包盒上面要打上日期码。 4. 箱尺寸要求：外箱最长边不能超过25"(超过了，case pack只能为1)，不符合要求的大货，一律不接受。 5. 外箱箱唛要求： ①外箱正面印ZURU Logo+SSCC Label(客供贴纸，由跟单订购)。关于 SSCC Label 请注意： SSCC Label显示的是客人自己的item#。每一张SSCC label都是唯一且有不同流水及条码的，没有损耗，绝对不可贴错。如果贴错或损坏任何一张，都会导致全部都 错，千万要注意！SSCC Label必须贴在外箱正面的正中间位置(贴一面即可)，并且贴纸离外箱边距必须至少3cm(可以覆盖Logo<(>&<)>箱唛)，否则会影响到客户那边 仓库的扫描识别。 ②外箱侧面印item#(订单上显示的SKU#)+carton size(以工厂实际尺寸为准，单位: inch)+MADE IN CHINA，日期使用ZURU 标准版本。 6. 装柜要求：按照客户PO#装柜/箱号顺序装柜，跟单会提前给到装柜计划。 在大货生产/仓库存放时，请留意该装柜要求，以便装柜时不混乱(避免装错/装漏/找不到货号等)。 | X65: Kelly Shen | Y65: 2.2046 | Z65: =Y65*J65 -> 1825.4088 | AA65: ZB01641-9.2 | AB65: 828 | AC65: =AB65-J65 -> 0 | AD65: OK | AE65: 已入 | AF65: 系统出单 | AG65: =J65 -> 828 | AH65: =J65 -> 828 | AI65: =J65 -> 828 | AL65: =J65 -> 828 | AU65: =J65 -> 828
A66: 45868 | B66: AMAZON.COM SERVICES LLC | C66: 美国 | D66: 4500175571 | E66: 88XY3RGL | F66: 4500175571-30 | G66: 7166-2023-S002-V1-3L | H66: 7166-2023-S002 | I66: 小鲨鱼3PK | J66: 2448 | K66: 0 | L66: 18 | M66: =J66/L66 -> 136 | N66: 45903 | O66: =N66-4 -> 45899 | Q66: PASS | R66: 9/5出 | S66: 7/30收到 | U66: UPC贴纸资料翻单4500152657+8/18-客供外箱贴纸+8/21-客供防伪帖纸 | V66: #7166 MA 3L 加UPC贴纸 | W66: 日期码格式：ZURU INC(BVI) 标准格式 日期：按实际生产日期 Packaging Info: #7166 MA 3L 加UPC贴纸，UPC贴纸资料翻单4500152657.需要加一张客供防伪帖纸，贴纸跟单提供。 Remark: 1. Amazon MDDP订单，出口US。 2. 日期码使用ZURU标准版本。 3. 如果大货有要求入邮包盒，则对应的邮包盒上面要打上日期码。 4. 箱尺寸要求：外箱最长边不能超过25"(超过了，case pack只能为1)，不符合要求的大货，一律不接受。 5. 外箱箱唛要求： ①外箱正面印ZURU Logo+SSCC Label(客供贴纸，由跟单订购)。关于 SSCC Label 请注意： SSCC Label显示的是客人自己的item#。每一张SSCC label都是唯一且有不同流水及条码的，没有损耗，绝对不可贴错。如果贴错或损坏任何一张，都会导致全部都 错，千万要注意！SSCC Label必须贴在外箱正面的正中间位置(贴一面即可)，并且贴纸离外箱边距必须至少3cm(可以覆盖Logo<(>&<)>箱唛)，否则会影响到客户那边 仓库的扫描识别。 ②外箱侧面印item#(订单上显示的SKU#)+carton size(以工厂实际尺寸为准，单位: inch)+MADE IN CHINA，日期使用ZURU 标准版本。 6. 装柜要求：按照客户PO#装柜/箱号顺序装柜，跟单会提前给到装柜计划。 在大货生产/仓库存放时，请留意该装柜要求，以便装柜时不混乱(避免装错/装漏/找不到货号等)。 | X66: Kelly Shen | Y66: 2.1722 | Z66: =Y66*J66 -> 5317.5456 | AA66: ZB01704-9.5 ZB01716(REV1)-9.6 | AB66: 2448 | AC66: =AB66-J66 -> 0 | AD66: ok | AE66: 已入 | AF66: 系统出单 | AG66: =J66 -> 2448 | AH66: =J66 -> 2448 | AI66: =J66 -> 2448 | AL66: =J66 -> 2448 | AU66: =J66 -> 2448
A67: 45868 | B67: AMAZON.COM SERVICES LLC | C67: 美国 | D67: 4500175571 | E67: 6BX9PHKD | F67: 4500175571-60 | G67: 7166-2023-S002-V1-3L | H67: 7166-2023-S002 | I67: 小鲨鱼3PK | J67: 2376 | K67: 0 | L67: 18 | M67: =J67/L67 -> 132 | N67: 45903 | O67: =N67-4 -> 45899 | Q67: PASS | R67: 9/5出 | S67: 7/30收到 | U67: UPC贴纸资料翻单4500152657+8/18-客供外箱贴纸+8/21-客供防伪帖纸 | V67: #7166 MA 3L 加UPC贴纸 | W67: 日期码格式：ZURU INC(BVI) 标准格式 日期：按实际生产日期 Packaging Info: #7166 MA 3L 加UPC贴纸，UPC贴纸资料翻单4500152657.需要加一张客供防伪帖纸，贴纸跟单提供。 Remark: 1. Amazon MDDP订单，出口US。 2. 日期码使用ZURU标准版本。 3. 如果大货有要求入邮包盒，则对应的邮包盒上面要打上日期码。 4. 箱尺寸要求：外箱最长边不能超过25"(超过了，case pack只能为1)，不符合要求的大货，一律不接受。 5. 外箱箱唛要求： ①外箱正面印ZURU Logo+SSCC Label(客供贴纸，由跟单订购)。关于 SSCC Label 请注意： SSCC Label显示的是客人自己的item#。每一张SSCC label都是唯一且有不同流水及条码的，没有损耗，绝对不可贴错。如果贴错或损坏任何一张，都会导致全部都 错，千万要注意！SSCC Label必须贴在外箱正面的正中间位置(贴一面即可)，并且贴纸离外箱边距必须至少3cm(可以覆盖Logo<(>&<)>箱唛)，否则会影响到客户那边 仓库的扫描识别。 ②外箱侧面印item#(订单上显示的SKU#)+carton size(以工厂实际尺寸为准，单位: inch)+MADE IN CHINA，日期使用ZURU 标准版本。 6. 装柜要求：按照客户PO#装柜/箱号顺序装柜，跟单会提前给到装柜计划。 在大货生产/仓库存放时，请留意该装柜要求，以便装柜时不混乱(避免装错/装漏/找不到货号等)。 | X67: Kelly Shen | Y67: 2.1722 | Z67: =Y67*J67 -> 5161.1472 | AA67: ZB01704-9.5 | AB67: 2376 | AC67: =AB67-J67 -> 0 | AD67: ok | AE67: 已入 | AF67: 系统出单 | AG67: =J67 -> 2376 | AH67: =J67 -> 2376 | AI67: =J67 -> 2376 | AL67: =J67 -> 2376 | AU67: =J67 -> 2376
A68: 45884 | B68: SINGLETON TRADING LTD | C68: 英国 | D68: 4500177103 | E68: 对应客人PO#12 109(请忽略抬 头部分显示的1 2109-1) | F68: 4500177103-10 | G68: 7163-2023-S003-3L-V1 | H68: 7163-2023-S003 | I68: 小鲨鱼 | J68: 18216 | K68: 0 | L68: 24 | M68: =J68/L68 -> 759 | N68: 45922 | O68: 45918 | P68: DG20250910 | Q68: PASS | S68: 8/21收到 | U68: 欧洲电子产品WEEE声明B版通用说明书(带电池) | V68: 7163：MA-3L EAN配套包装 | W68: 日期码格式：ZURU INC(BVI) 标准格式 日期： Packaging Info: 7163：MA-3L EAN配套包装+欧洲电子产品WEEE声明B版通用说明书(带电池) Remark: *包装日期码按ZURU格式即可， 见指定日期码 DG20250910 *订单出英国，请注意检查产品及包装应带UKCA图标（14+产品除外），包装显示ZURU UK LTD地址信息，QC部门请查核，如有问题与跟单确认 *订单必须经过ZURU QC验货并且通过后方可出货。 *条码以订单显示为准 ，请安排生产前先核对 ，有问题请提出。 *微塑料需符合欧洲标准，否则不合法规会有客诉产生 | X68: Sandy Shao | Y68: 1.2953 | Z68: =Y68*J68 -> 23595.185 | AB68: 18216 | AC68: =AB68-J68 -> 0 | AD68: ok | AE68: 已入 | AF68: 系统出单 | AG68: =J68/3 -> 6072 | AH68: =J68/3 -> 6072 | AI68: =J68/3 -> 6072 | AK68: =J68 -> 18216 | AL68: =J68 -> 18216
A69: 45876 | B69: DISCHEM SOUTH AFRICA | C69: 南非 | D69: 4500176287 | F69: 4500176287-20 | G69: 7163-2023-S003-1L-V1 | H69: 7163-2023-S003 | I69: 小鲨鱼 | J69: 1200 | K69: 0 | L69: 24 | M69: =J69/L69 -> 50 | N69: 45929 | O69: 45925 | Q69: PASS | S69: 8/30收到 | U69: 无 | V69: MA UPC pkg (1L优先） | W69: 日期码格式：ZURU INC(BVI) 标准格式 日期：按实际生产日期 Packaging Info: MA UPC pkg (1L优先） Remark: 2. 7163: 3 assortment | X69: Doris Shou | Y69: 1.5121 | Z69: =Y69*J69 -> 1814.52 | AA69: A96624-10.10 | AB69: 1200 | AC69: =AB69-J69 -> 0 | AD69: 无 | AE69: 已入 | AF69: 系统出单 | AG69: =J69/3 -> 400 | AH69: =J69/3 -> 400 | AI69: =J69/3 -> 400 | AJ69: =J69 -> 1200 | AL69: =J69 -> 1200
A70: 45896 | B70: AMAZON.COM SERVICES LLC | C70: 美国 | D70: 4500178034 | E70: 368BUZJH | F70: 4500178034-100 | G70: 7166-2023-S002-V1-3L | H70: 7166-2023-S002 | I70: 小鲨鱼3PK | J70: 54 | K70: 0 | L70: 18 | M70: =J70/L70 -> 3 | N70: 45939 | O70: 45936 | Q70: PASS | R70: 10/20出 | S70: 8/27收到 | U70: UPC贴纸资料翻单4500175579+9/15-客供防伪帖纸 | V70: 7166 MA 3L 加UPC贴纸 | W70: 日期码格式：ZURU INC(BVI) 标准格式 日期：按实际生产日期 Packaging Info: #7166 MA 3L 加UPC贴纸，UPC贴纸资料翻单4500175579.需要加一张客供防伪帖纸，贴纸跟单提供。 Remark: 1. Amazon MDDP订单，出口US。 2. 日期码使用ZURU标准版本。 3. 如果大货有要求入邮包盒，则对应的邮包盒上面要打上日期码。 4. 箱尺寸要求：外箱最长边不能超过25"(超过了，case pack只能为1)，不符合要求的大货，一律不接受。 5. 外箱箱唛要求： ①外箱正面印ZURU Logo+SSCC Label(客供贴纸，由跟单订购)。关于 SSCC Label 请注意： SSCC Label显示的是客人自己的item#。每一张SSCC label都是唯一且有不同流水及条码的，没有损耗，绝对不可贴错。如果贴错或损坏任何一张，都会导致全部都 错，千万要注意！SSCC Label必须贴在外箱正面的正中间位置(贴一面即可)，并且贴纸离外箱边距必须至少3cm(可以覆盖Logo<(>&<)>箱唛)，否则会影响到客户那边 仓库的扫描识别。 ②外箱侧面印item#(订单上显示的SKU#)+carton size(以工厂实际尺寸为准，单位: inch)+MADE IN CHINA，日期使用ZURU 标准版本。 6. 装柜要求：按照客户PO#装柜/箱号顺序装柜，跟单会提前给到装柜计划。 在大货生产/仓库存放时，请留意该装柜要求，以便装柜时不混乱(避免装错/装漏/找不到货号等)。 | X70: Kelly Shen/Mia Pan/P | Y70: 2.1722 | Z70: =Y70*J70 -> 117.2988 | AA70: ZB02522-10.20 | AB70: 54 | AC70: =AB70-J70 -> 0 | AD70: ok | AE70: 已入 | AF70: 系统出单 | AG70: =J70 -> 54 | AH70: =J70 -> 54 | AI70: =J70 -> 54 | AL70: =J70 -> 54 | AU70: =J70 -> 54
A71: 45896 | B71: AMAZON.COM SERVICES LLC | C71: 美国 | D71: 4500178034 | E71: 5KHU1O4R | F71: 4500178034-110 | G71: 7166-2023-S002-V1-3L | H71: 7166-2023-S002 | I71: 小鲨鱼3PK | J71: 2430 | K71: 0 | L71: 18 | M71: =J71/L71 -> 135 | N71: 45939 | O71: 45936 | Q71: PASS | R71: 10/20出 | S71: 8/27收到 | U71: UPC贴纸资料翻单4500175579+9/15-客供防伪帖纸 | V71: 7166 MA 3L 加UPC贴纸 | W71: 日期码格式：ZURU INC(BVI) 标准格式 日期：按实际生产日期 Packaging Info: #7166 MA 3L 加UPC贴纸，UPC贴纸资料翻单4500175579.需要加一张客供防伪帖纸，贴纸跟单提供。 Remark: 1. Amazon MDDP订单，出口US。 2. 日期码使用ZURU标准版本。 3. 如果大货有要求入邮包盒，则对应的邮包盒上面要打上日期码。 4. 箱尺寸要求：外箱最长边不能超过25"(超过了，case pack只能为1)，不符合要求的大货，一律不接受。 5. 外箱箱唛要求： ①外箱正面印ZURU Logo+SSCC Label(客供贴纸，由跟单订购)。关于 SSCC Label 请注意： SSCC Label显示的是客人自己的item#。每一张SSCC label都是唯一且有不同流水及条码的，没有损耗，绝对不可贴错。如果贴错或损坏任何一张，都会导致全部都 错，千万要注意！SSCC Label必须贴在外箱正面的正中间位置(贴一面即可)，并且贴纸离外箱边距必须至少3cm(可以覆盖Logo<(>&<)>箱唛)，否则会影响到客户那边 仓库的扫描识别。 ②外箱侧面印item#(订单上显示的SKU#)+carton size(以工厂实际尺寸为准，单位: inch)+MADE IN CHINA，日期使用ZURU 标准版本。 6. 装柜要求：按照客户PO#装柜/箱号顺序装柜，跟单会提前给到装柜计划。 在大货生产/仓库存放时，请留意该装柜要求，以便装柜时不混乱(避免装错/装漏/找不到货号等)。 | X71: Kelly Shen/Mia Pan/P | Y71: 2.1722 | Z71: =Y71*J71 -> 5278.446 | AA71: ZB02522-10.20 | AB71: 2430 | AC71: =AB71-J71 -> 0 | AD71: OK | AE71: 已入 | AF71: 系统出单 | AG71: =J71 -> 2430 | AH71: =J71 -> 2430 | AI71: =J71 -> 2430 | AL71: =J71 -> 2430 | AU71: =J71 -> 2430
A72: 45896 | B72: AMAZON.COM SERVICES LLC | C72: 美国 | D72: 4500178034 | E72: 5UTEWO2X | F72: 4500178034-120 | G72: 7166-2023-S002-V1-3L | H72: 7166-2023-S002 | I72: 小鲨鱼3PK | J72: 1440 | K72: 0 | L72: 18 | M72: =J72/L72 -> 80 | N72: 45939 | O72: 45936 | Q72: PASS | R72: 10/20出 | S72: 8/27收到 | U72: UPC贴纸资料翻单4500175579+9/15-客供防伪帖纸 | V72: 7166 MA 3L 加UPC贴纸 | W72: 日期码格式：ZURU INC(BVI) 标准格式 日期：按实际生产日期 Packaging Info: #7166 MA 3L 加UPC贴纸，UPC贴纸资料翻单4500175579.需要加一张客供防伪帖纸，贴纸跟单提供。 Remark: 1. Amazon MDDP订单，出口US。 2. 日期码使用ZURU标准版本。 3. 如果大货有要求入邮包盒，则对应的邮包盒上面要打上日期码。 4. 箱尺寸要求：外箱最长边不能超过25"(超过了，case pack只能为1)，不符合要求的大货，一律不接受。 5. 外箱箱唛要求： ①外箱正面印ZURU Logo+SSCC Label(客供贴纸，由跟单订购)。关于 SSCC Label 请注意： SSCC Label显示的是客人自己的item#。每一张SSCC label都是唯一且有不同流水及条码的，没有损耗，绝对不可贴错。如果贴错或损坏任何一张，都会导致全部都 错，千万要注意！SSCC Label必须贴在外箱正面的正中间位置(贴一面即可)，并且贴纸离外箱边距必须至少3cm(可以覆盖Logo<(>&<)>箱唛)，否则会影响到客户那边 仓库的扫描识别。 ②外箱侧面印item#(订单上显示的SKU#)+carton size(以工厂实际尺寸为准，单位: inch)+MADE IN CHINA，日期使用ZURU 标准版本。 6. 装柜要求：按照客户PO#装柜/箱号顺序装柜，跟单会提前给到装柜计划。 在大货生产/仓库存放时，请留意该装柜要求，以便装柜时不混乱(避免装错/装漏/找不到货号等)。 | X72: Kelly Shen/Mia Pan/P | Y72: 2.1722 | Z72: =Y72*J72 -> 3127.968 | AA72: ZB02522-10.20 | AB72: =1422+18 -> 1440 | AC72: =AB72-J72 -> 0 | AD72: OK | AE72: 已入 | AF72: 系统出单 | AG72: =J72 -> 1440 | AH72: =J72 -> 1440 | AI72: =J72 -> 1440 | AL72: =J72 -> 1440 | AU72: =J72 -> 1440
A73: 45896 | B73: AMAZON.COM SERVICES LLC | C73: 美国 | D73: 4500178020 | E73: 2NEM1ETK | F73: 4500178020-270 | G73: 7166-2023-S002-V1-3L | H73: 7166-2023-S002 | I73: 小鲨鱼3PK | J73: 1620 | K73: 0 | L73: 18 | M73: =J73/L73 -> 90 | N73: 45939 | O73: 45936 | Q73: PASS | R73: 收到SO | S73: 8/27收到 | U73: UPC贴纸资料翻单4500175579+9/15-客供防伪帖纸 | V73: 7166 MA 3L 加UPC贴纸 | W73: 日期码格式：ZURU INC(BVI) 标准格式 日期：按实际生产日期 Packaging Info: #7166 MA 3L 加UPC贴纸，UPC贴纸资料翻单4500175579.需要加一张客供防伪帖纸，贴纸跟单提供。 Remark: 1. Amazon MDDP订单，出口US。 2. 日期码使用ZURU标准版本。 3. 如果大货有要求入邮包盒，则对应的邮包盒上面要打上日期码。 4. 箱尺寸要求：外箱最长边不能超过25"(超过了，case pack只能为1)，不符合要求的大货，一律不接受。 5. 外箱箱唛要求： ①外箱正面印ZURU Logo+SSCC Label(客供贴纸，由跟单订购)。关于 SSCC Label 请注意： SSCC Label显示的是客人自己的item#。每一张SSCC label都是唯一且有不同流水及条码的，没有损耗，绝对不可贴错。如果贴错或损坏任何一张，都会导致全部都 错，千万要注意！SSCC Label必须贴在外箱正面的正中间位置(贴一面即可)，并且贴纸离外箱边距必须至少3cm(可以覆盖Logo<(>&<)>箱唛)，否则会影响到客户那边 仓库的扫描识别。 ②外箱侧面印item#(订单上显示的SKU#)+carton size(以工厂实际尺寸为准，单位: inch)+MADE IN CHINA，日期使用ZURU 标准版本。 6. 装柜要求：按照客户PO#装柜/箱号顺序装柜，跟单会提前给到装柜计划。 在大货生产/仓库存放时，请留意该装柜要求，以便装柜时不混乱(避免装错/装漏/找不到货号等)。 | X73: Kelly Shen/Mia Pan/P | Y73: 2.2046 | Z73: =Y73*J73 -> 3571.452 | AA73: ZB02447-10.15 | AB73: 1620 | AC73: =AB73-J73 -> 0 | AD73: OK | AE73: 已入 | AF73: 系统出单 | AG73: =J73 -> 1620 | AH73: =J73 -> 1620 | AI73: =J73 -> 1620 | AL73: =J73 -> 1620 | AU73: =J73 -> 1620
A74: 45896 | B74: AMAZON.COM SERVICES LLC | C74: 美国 | D74: 4500177996 | E74: 2EWL6PIZ | F74: 4500177996-30 | G74: 7166-2023-S002-V1-3L | H74: 7166-2023-S002 | I74: 小鲨鱼3PK | J74: 1008 | K74: 0 | L74: 18 | M74: =J74/L74 -> 56 | N74: 45939 | O74: 45936 | Q74: PASS | R74: 10/15出 | S74: 8/27收到 | U74: UPC贴纸资料翻单4500175579+9/15-客供防伪帖纸 | V74: 7166 MA 3L 加UPC贴纸 | W74: 日期码格式：ZURU INC(BVI) 标准格式 日期：按实际生产日期 Packaging Info: #7166 MA 3L 加UPC贴纸，UPC贴纸资料翻单4500175579.需要加一张客供防伪帖纸，贴纸跟单提供。 Remark: 1. Amazon MDDP订单，出口US。 2. 日期码使用ZURU标准版本。 3. 如果大货有要求入邮包盒，则对应的邮包盒上面要打上日期码。 4. 箱尺寸要求：外箱最长边不能超过25"(超过了，case pack只能为1)，不符合要求的大货，一律不接受。 5. 外箱箱唛要求： ①外箱正面印ZURU Logo+SSCC Label(客供贴纸，由跟单订购)。关于 SSCC Label 请注意： SSCC Label显示的是客人自己的item#。每一张SSCC label都是唯一且有不同流水及条码的，没有损耗，绝对不可贴错。如果贴错或损坏任何一张，都会导致全部都 错，千万要注意！SSCC Label必须贴在外箱正面的正中间位置(贴一面即可)，并且贴纸离外箱边距必须至少3cm(可以覆盖Logo<(>&<)>箱唛)，否则会影响到客户那边 仓库的扫描识别。 ②外箱侧面印item#(订单上显示的SKU#)+carton size(以工厂实际尺寸为准，单位: inch)+MADE IN CHINA，日期使用ZURU 标准版本。 6. 装柜要求：按照客户PO#装柜/箱号顺序装柜，跟单会提前给到装柜计划。 在大货生产/仓库存放时，请留意该装柜要求，以便装柜时不混乱(避免装错/装漏/找不到货号等)。 | X74: Kelly Shen/Mia Pan/P | Y74: 2.2046 | Z74: =Y74*J74 -> 2222.2368 | AA74: ZB02421-10.14 | AB74: 1008 | AC74: =AB74-J74 -> 0 | AD74: OK | AE74: 已入 | AF74: 系统出单 | AG74: =J74 -> 1008 | AH74: =J74 -> 1008 | AI74: =J74 -> 1008 | AL74: =J74 -> 1008 | AU74: =J74 -> 1008
A75: 45896 | B75: AMAZON.COM SERVICES LLC | C75: 美国 | D75: 4500177996 | E75: 5D95AWUM | F75: 4500177996-40 | G75: 7166-2023-S002-V1-3L | H75: 7166-2023-S002 | I75: 小鲨鱼3PK | J75: 954 | K75: 0 | L75: 18 | M75: =J75/L75 -> 53 | N75: 45939 | O75: 45936 | Q75: PASS | R75: 10/15出 | S75: 8/27收到 | U75: UPC贴纸资料翻单4500175579+9/15-客供防伪帖纸 | V75: 7166 MA 3L 加UPC贴纸 | W75: 日期码格式：ZURU INC(BVI) 标准格式 日期：按实际生产日期 Packaging Info: #7166 MA 3L 加UPC贴纸，UPC贴纸资料翻单4500175579.需要加一张客供防伪帖纸，贴纸跟单提供。 Remark: 1. Amazon MDDP订单，出口US。 2. 日期码使用ZURU标准版本。 3. 如果大货有要求入邮包盒，则对应的邮包盒上面要打上日期码。 4. 箱尺寸要求：外箱最长边不能超过25"(超过了，case pack只能为1)，不符合要求的大货，一律不接受。 5. 外箱箱唛要求： ①外箱正面印ZURU Logo+SSCC Label(客供贴纸，由跟单订购)。关于 SSCC Label 请注意： SSCC Label显示的是客人自己的item#。每一张SSCC label都是唯一且有不同流水及条码的，没有损耗，绝对不可贴错。如果贴错或损坏任何一张，都会导致全部都 错，千万要注意！SSCC Label必须贴在外箱正面的正中间位置(贴一面即可)，并且贴纸离外箱边距必须至少3cm(可以覆盖Logo<(>&<)>箱唛)，否则会影响到客户那边 仓库的扫描识别。 ②外箱侧面印item#(订单上显示的SKU#)+carton size(以工厂实际尺寸为准，单位: inch)+MADE IN CHINA，日期使用ZURU 标准版本。 6. 装柜要求：按照客户PO#装柜/箱号顺序装柜，跟单会提前给到装柜计划。 在大货生产/仓库存放时，请留意该装柜要求，以便装柜时不混乱(避免装错/装漏/找不到货号等)。 | X75: Kelly Shen/Mia Pan/P | Y75: 2.2046 | Z75: =Y75*J75 -> 2103.1884 | AA75: ZB02421-10.14 | AB75: 954 | AC75: =AB75-J75 -> 0 | AD75: OK | AE75: 已入 | AF75: 系统出单 | AG75: =J75 -> 954 | AH75: =J75 -> 954 | AI75: =J75 -> 954 | AL75: =J75 -> 954 | AU75: =J75 -> 954
A76: 45896 | B76: AMAZON.COM SERVICES LLC | C76: 美国 | D76: 4500177996 | E76: 5B9214TU | F76: 4500177996-130 | G76: 7166-2023-S002-V1-3L | H76: 7166-2023-S002 | I76: 小鲨鱼3PK | J76: 18 | K76: 0 | L76: 18 | M76: =J76/L76 -> 1 | N76: 45939 | O76: 45936 | Q76: PASS | R76: 10/15出 | S76: 8/27收到 | U76: UPC贴纸资料翻单4500175579+9/15-客供防伪帖纸 | V76: 7166 MA 3L 加UPC贴纸 | W76: 日期码格式：ZURU INC(BVI) 标准格式 日期：按实际生产日期 Packaging Info: #7166 MA 3L 加UPC贴纸，UPC贴纸资料翻单4500175579.需要加一张客供防伪帖纸，贴纸跟单提供。 Remark: 1. Amazon MDDP订单，出口US。 2. 日期码使用ZURU标准版本。 3. 如果大货有要求入邮包盒，则对应的邮包盒上面要打上日期码。 4. 箱尺寸要求：外箱最长边不能超过25"(超过了，case pack只能为1)，不符合要求的大货，一律不接受。 5. 外箱箱唛要求： ①外箱正面印ZURU Logo+SSCC Label(客供贴纸，由跟单订购)。关于 SSCC Label 请注意： SSCC Label显示的是客人自己的item#。每一张SSCC label都是唯一且有不同流水及条码的，没有损耗，绝对不可贴错。如果贴错或损坏任何一张，都会导致全部都 错，千万要注意！SSCC Label必须贴在外箱正面的正中间位置(贴一面即可)，并且贴纸离外箱边距必须至少3cm(可以覆盖Logo<(>&<)>箱唛)，否则会影响到客户那边 仓库的扫描识别。 ②外箱侧面印item#(订单上显示的SKU#)+carton size(以工厂实际尺寸为准，单位: inch)+MADE IN CHINA，日期使用ZURU 标准版本。 6. 装柜要求：按照客户PO#装柜/箱号顺序装柜，跟单会提前给到装柜计划。 在大货生产/仓库存放时，请留意该装柜要求，以便装柜时不混乱(避免装错/装漏/找不到货号等)。 | X76: Kelly Shen/Mia Pan/P | Y76: 2.2046 | Z76: =Y76*J76 -> 39.6828 | AA76: ZB02421-10.14 | AB76: 18 | AC76: =AB76-J76 -> 0 | AD76: OK | AE76: 已入 | AF76: 系统出单 | AG76: =J76 -> 18 | AH76: =J76 -> 18 | AI76: =J76 -> 18 | AL76: =J76 -> 18 | AU76: =J76 -> 18
A77: 45897 | B77: ACADEMY LTD | C77: 美国 | D77: 4500178115 | E77: 11874313 | F77: 4500178115-10 | G77: 7163TQ1-2023-S001-V1 | H77: 7163TQ1-2023-S001 | I77: 小鲨鱼 | J77: 222 | K77: 0 | L77: 6 | M77: =J77/L77 -> 37 | N77: 45954 | O77: 45950 | Q77: PASS | R77: 10/28出 | S77: 9/12收到 | U77: 9/12-UCC贴纸 | V77: MA UPC 版本包装 | W77: 日期码格式：ZURU INC(BVI) 标准格式 日期：按实际生产日期 Packaging Info: 1. 出口美国，MA UPC 版本包装 #7163TQ1: UPC#193052062604; 3 assortment; 3PCS LR44 BATTERIES(INCLUDED); Remark: 2 .外箱正唛的右下角需贴一个UCC贴纸（4x6inch,距离右边和底边2inch,UCC贴纸为流水号的，每一箱都不一样。 3. 请按期完货，延期有罚金。 4. 我司验货即可。 5. 产品和包装上有tracking code信息，格式为ZURU常规。 | X77: Abby mai,Lluvia zeng | Y77: 0.9545 | Z77: =Y77*J77 -> 211.899 | AA77: ZB02662-10.28 | AB77: 222 | AC77: =AB77-J77 -> 0 | AD77: ok | AE77: 已入 | AF77: 系统出单 | AG77: =J77/3 -> 74 | AH77: =J77/3 -> 74 | AI77: =J77/3 -> 74 | AJ77: =J77 -> 222 | AL77: =J77 -> 222 | AM77: =J77/6 -> 37
A78: 45908 | B78: ACADEMY LTD | C78: 美国 | D78: 4500179025 | E78: 11874305 | F78: 4500179025-10 | G78: 7163TQ1-2023-S001-V1 | H78: 7163TQ1-2023-S001 | I78: 小鲨鱼 | J78: 258 | K78: 0 | L78: 6 | M78: =J78/L78 -> 43 | N78: 45954 | O78: 45950 | Q78: PASS | R78: 10/28出 | S78: 9/12收到 | U78: 9/12-UCC贴纸 | V78: MA UPC 版本包装 | W78: 日期码格式：ZURU INC(BVI) 标准格式 日期：按实际生产日期 Packaging Info: 1. 出口美国，MA UPC 版本包装 #7163TQ1: UPC#193052062604; 3 assortment; 3PCS LR44 BATTERIES(INCLUDED); Remark: 2 .外箱正唛的右下角需贴一个UCC贴纸（4x6inch,距离右边和底边2inch,UCC贴纸为流水号的，每一箱都不一样。 3. 请按期完货，延期有罚金。 4. 我司验货即可。 5. 产品和包装上有tracking code信息，格式为ZURU常规。 | X78: Abby mai,Lluvia zeng | Y78: 0.9545 | Z78: =Y78*J78 -> 246.261 | AA78: ZB02663-10.28 | AB78: 258 | AC78: =AB78-J78 -> 0 | AD78: ok | AE78: 已入 | AF78: 系统出单 | AG78: =J78/3 -> 86 | AH78: =J78/3 -> 86 | AI78: =J78/3 -> 86 | AJ78: =J78 -> 258 | AL78: =J78 -> 258 | AM78: =J78/6 -> 43
A79: 45940 | B79: GABRIEL BROTHERS, INC. | C79: 美国 | D79: 4500181336 | E79: 84006700 | F79: 4500181336-60 | G79: 7163TQ1-2023-S002-V1 | H79: 7163TQ1-2023-S002 | I79: 小鲨鱼 | J79: 1512 | K79: 0 | L79: 24 | M79: =J79/L79 -> 63 | N79: 46006 | O79: 46002 | Q79: PASS | S79: 10/11收到 | U79: 无 | V79: . ZURU MA UPC (首选1L / 多语可以接受)包装 | W79: 日期码格式：ZURU INC(BVI) 标准格式 日期：按实际生产日期 Packaging Info: 1. ZURU MA UPC (首选1L / 多语可以接受)包装, Remark: 2. 产品和包装上印刷tracking code信息，格式为ZURU常规 3. 整柜FCL 出货，（装柜工厂）装柜时最后一箱正唛贴上装箱单 (不是装柜工厂忽略即可），装箱单需要用透明的袋子装好， 剩下三面贴上'' PACKING LIST ENC LOSED '' 的字样 （可以用A4 纸打印）- 船务会发出。 4. 需ZURU QC 验货合格后方可出货 | X79: Jessi Xu | Y79: 0.9312 | Z79: =Y79*J79 -> 1407.9744 | AB79: 1512 | AC79: =AB79-J79 -> 0 | AD79: 无 | AE79: 已入 | AF79: 系统出单 | AG79: =J79/3 -> 504 | AH79: =J79/3 -> 504 | AI79: =J79/3 -> 504 | AJ79: =J79 -> 1512 | AL79: =J79 -> 1512 | AM79: =J79/6 -> 252
A80: 45915 | B80: ACADEMY LTD | C80: 美国 | D80: 4500179509 | E80: 11919214 | F80: 4500179509-10 | G80: 7163TQ1-2023-S001-V1 | H80: 7163TQ1-2023-S001 | I80: 小鲨鱼 | J80: 174 | K80: 0 | L80: 6 | M80: =J80/L80 -> 29 | N80: 45999 | O80: 45995 | Q80: PASS | R80: 12/19出 | S80: 10/22收到 | U80: 10/22-UCC贴纸 | V80: MA UPC 版本包装 | W80: 日期码格式：ZURU INC(BVI) 标准格式 日期：按实际生产日期 Packaging Info: 1. 出口美国，MA UPC 版本包装 #7163TQ1: UPC#193052062604; 3 assortment; 3PCS LR44 BATTERIES(INCLUDED); Remark: 2 .外箱正唛的右下角需贴一个UCC贴纸（4x6inch,距离右边和底边2inch,UCC贴纸为流水号的，每一箱都不一样。 3. 请按期完货，延期有罚金。 4. 我司验货即可。 5. 产品和包装上有tracking code信息，格式为ZURU常规。 | X80: Abby Mai,Lluvia Zeng | Y80: 0.9426 | Z80: =Y80*J80 -> 164.0124 | AB80: 174 | AC80: =AB80-J80 -> 0 | AD80: ok | AE80: 已入 | AF80: 系统出单 | AG80: =J80/3 -> 58 | AH80: =J80/3 -> 58 | AI80: =J80/3 -> 58 | AJ80: =J80 -> 174 | AL80: =J80 -> 174 | AM80: =J80/6 -> 29
A81: 45915 | B81: ACADEMY LTD | C81: 美国 | D81: 4500179523 | E81: 11919212 | F81: 4500179523-10 | G81: 7163TQ1-2023-S001-V1 | H81: 7163TQ1-2023-S001 | I81: 小鲨鱼 | J81: 330 | K81: 0 | L81: 6 | M81: =J81/L81 -> 55 | N81: 45999 | O81: 45995 | Q81: PASS | R81: 12/21出 | S81: 10/22收到 | U81: 10/22-UCC贴纸 | V81: MA UPC 版本包装 | W81: 日期码格式：ZURU INC(BVI) 标准格式 日期：按实际生产日期 Packaging Info: 1. 出口美国，MA UPC 版本包装 #7163TQ1: UPC#193052062604; 3 assortment; 3PCS LR44 BATTERIES(INCLUDED); Remark: 2 .外箱正唛的右下角需贴一个UCC贴纸（4x6inch,距离右边和底边2inch,UCC贴纸为流水号的，每一箱都不一样。 3. 请按期完货，延期有罚金。 4. 我司验货即可。 5. 产品和包装上有tracking code信息，格式为ZURU常规。 | X81: Abby Mai,Lluvia Zeng | Y81: 0.9426 | Z81: =Y81*J81 -> 311.058 | AB81: 330 | AC81: =AB81-J81 -> 0 | AD81: ok | AE81: 已入 | AF81: 系统出单 | AG81: =J81/3 -> 110 | AH81: =J81/3 -> 110 | AI81: =J81/3 -> 110 | AJ81: =J81 -> 330 | AL81: =J81 -> 330 | AM81: =J81/6 -> 55
A82: 45915 | B82: ACADEMY LTD | C82: 美国 | D82: 4500179529 | E82: 11919213 | F82: 4500179529-10 | G82: 7163TQ1-2023-S001-V1 | H82: 7163TQ1-2023-S001 | I82: 小鲨鱼 | J82: 144 | K82: 0 | L82: 6 | M82: =J82/L82 -> 24 | N82: 45999 | O82: 45995 | Q82: PASS | R82: 12/19出 | S82: 10/22收到 | U82: 10/22-UCC贴纸 | V82: MA UPC 版本包装 | W82: 日期码格式：ZURU INC(BVI) 标准格式 日期：按实际生产日期 Packaging Info: 1. 出口美国，MA UPC 版本包装 #7163TQ1: UPC#193052062604; 3 assortment; 3PCS LR44 BATTERIES(INCLUDED); Remark: 2 .外箱正唛的右下角需贴一个UCC贴纸（4x6inch,距离右边和底边2inch,UCC贴纸为流水号的，每一箱都不一样。 3. 请按期完货，延期有罚金。 4. 我司验货即可。 5. 产品和包装上有tracking code信息，格式为ZURU常规。 | X82: Abby Mai | Y82: 0.9545 | Z82: =Y82*J82 -> 137.448 | AB82: 144 | AC82: =AB82-J82 -> 0 | AD82: ok | AE82: 已入 | AF82: 系统出单 | AG82: =J82/3 -> 48 | AH82: =J82/3 -> 48 | AI82: =J82/3 -> 48 | AJ82: =J82 -> 144 | AL82: =J82 -> 144 | AM82: =J82/6 -> 24
A83: 45968 | B83: AMAZON CA (VENDOR CENTER) | C83: 加拿大 | D83: 4500184827 | E83: 7EF4IG9H | F83: 4500184827-210 | G83: 7166-2023-S002-V1-3L | H83: 7166-2023-S002 | I83: 小鲨鱼3PK | J83: 54 | K83: 0 | L83: 18 | M83: =J83/L83 -> 3 | N83: 46009 | O83: 46007 | Q83: PASS | S83: 11/7收到 | U83: UPC贴纸翻4500148503+11/26-客供防伪帖纸+外箱贴纸 | V83: 7166 MA 3L 加UPC贴纸 | W83: 日期码格式：ZURU INC(BVI) 标准格式 日期：按实际生产日期 Packaging Info: 出口加拿大，包装需要至少2/3L UPC版，无硼版本。 #7166 MA 3L 加UPC贴纸，UPC贴纸资料翻单4500148503。需要加一张客供防伪帖纸，贴纸跟单提供。 Remark: 1. Amazon FOB订单，出口CA。外箱最长边不能超过25" （超过了，case pack只能为1），不符合要求的大货，一律不接受。 2. 外箱正面印ZURU Logo + SSCC LABEL（客供贴纸)，侧面印item#（订单上显示的SKU#) + carton size(以工厂实际尺寸为准，单位: inch) + MADE IN CHINA， 日期使用ZURU 标准版本 SSCC Label 显示的是客人自己的item#，SSCC Label 贴在外箱正面的正中间，贴一面即可，跟单订购，贴纸离外箱距必须至少3cm，每一 张SSCC label 都是唯一且有不同流水及条码的，没有损耗，绝对不可贴错 ，否则贴错或损坏一张会导致全部都错，千万要注意: SSCC 贴纸务必要在正中间(可以覆 盖Logo <(>&<)> 箱唛)，否则会影响到仓库扫描识别。 3. 日期码使用ZURU标准版本。 4. 如果大货有要求入邮包盒，则对应的邮包盒上面要打上日期码。 5. 按照客户PO# 装柜/箱号顺序装柜，跟单会提前给到装柜计划。在大货生产/仓库存放时，请留意该装柜要求，以便装柜时不混乱（避免装错/装漏/找不到货号等 ）。 6. 出口加拿大，包装需要至少2/3L UPC版，无硼版本。 7.邮包盒上要印刷日期码 | X83: Kelly Shen | Y83: 3.7299 | Z83: =Y83*J83 -> 201.4146 | AB83: 54 | AC83: =AB83-J83 -> 0 | AD83: OK | AE83: 已入 | AF83: 系统出单 | AG83: =J83 -> 54 | AH83: =J83 -> 54 | AI83: =J83 -> 54 | AL83: =J83 -> 54 | AU83: =J83 -> 54
A84: 45968 | B84: AMAZON CA (VENDOR CENTER) | C84: 加拿大 | D84: 4500184827 | E84: 75MJ3RPN | F84: 4500184827-220 | G84: 7166-2023-S002-V1-3L | H84: 7166-2023-S002 | I84: 小鲨鱼3PK | J84: 18 | K84: 0 | L84: 18 | M84: =J84/L84 -> 1 | N84: 46009 | O84: 46007 | Q84: PASS | S84: 11/7收到 | U84: UPC贴纸翻4500148503+11/26-客供防伪帖纸+外箱贴纸 | V84: 7166 MA 3L 加UPC贴纸 | W84: 日期码格式：ZURU INC(BVI) 标准格式 日期：按实际生产日期 Packaging Info: 出口加拿大，包装需要至少2/3L UPC版，无硼版本。 #7166 MA 3L 加UPC贴纸，UPC贴纸资料翻单4500148503。需要加一张客供防伪帖纸，贴纸跟单提供。 Remark: 1. Amazon FOB订单，出口CA。外箱最长边不能超过25" （超过了，case pack只能为1），不符合要求的大货，一律不接受。 2. 外箱正面印ZURU Logo + SSCC LABEL（客供贴纸)，侧面印item#（订单上显示的SKU#) + carton size(以工厂实际尺寸为准，单位: inch) + MADE IN CHINA， 日期使用ZURU 标准版本 SSCC Label 显示的是客人自己的item#，SSCC Label 贴在外箱正面的正中间，贴一面即可，跟单订购，贴纸离外箱距必须至少3cm，每一 张SSCC label 都是唯一且有不同流水及条码的，没有损耗，绝对不可贴错 ，否则贴错或损坏一张会导致全部都错，千万要注意: SSCC 贴纸务必要在正中间(可以覆 盖Logo <(>&<)> 箱唛)，否则会影响到仓库扫描识别。 3. 日期码使用ZURU标准版本。 4. 如果大货有要求入邮包盒，则对应的邮包盒上面要打上日期码。 5. 按照客户PO# 装柜/箱号顺序装柜，跟单会提前给到装柜计划。在大货生产/仓库存放时，请留意该装柜要求，以便装柜时不混乱（避免装错/装漏/找不到货号等 ）。 6. 出口加拿大，包装需要至少2/3L UPC版，无硼版本。 7.邮包盒上要印刷日期码 | X84: Kelly Shen | Y84: 3.7299 | Z84: =Y84*J84 -> 67.1382 | AB84: 18 | AC84: =AB84-J84 -> 0 | AD84: ok | AE84: 已入 | AF84: 系统出单 | AG84: =J84 -> 18 | AH84: =J84 -> 18 | AI84: =J84 -> 18 | AL84: =J84 -> 18 | AU84: =J84 -> 18
A85: 45968 | B85: AMAZON CA (VENDOR CENTER) | C85: 加拿大 | D85: 4500184827 | E85: 15YIGJTB | F85: 4500184827-230 | G85: 7166-2023-S002-V1-3L | H85: 7166-2023-S002 | I85: 小鲨鱼3PK | J85: 36 | K85: 0 | L85: 18 | M85: =J85/L85 -> 2 | N85: 46009 | O85: 46007 | Q85: PASS | S85: 11/7收到 | U85: UPC贴纸翻4500148503+11/26-客供防伪帖纸+外箱贴纸 | V85: 7166 MA 3L 加UPC贴纸 | W85: 日期码格式：ZURU INC(BVI) 标准格式 日期：按实际生产日期 Packaging Info: 出口加拿大，包装需要至少2/3L UPC版，无硼版本。 #7166 MA 3L 加UPC贴纸，UPC贴纸资料翻单4500148503。需要加一张客供防伪帖纸，贴纸跟单提供。 Remark: 1. Amazon FOB订单，出口CA。外箱最长边不能超过25" （超过了，case pack只能为1），不符合要求的大货，一律不接受。 2. 外箱正面印ZURU Logo + SSCC LABEL（客供贴纸)，侧面印item#（订单上显示的SKU#) + carton size(以工厂实际尺寸为准，单位: inch) + MADE IN CHINA， 日期使用ZURU 标准版本 SSCC Label 显示的是客人自己的item#，SSCC Label 贴在外箱正面的正中间，贴一面即可，跟单订购，贴纸离外箱距必须至少3cm，每一 张SSCC label 都是唯一且有不同流水及条码的，没有损耗，绝对不可贴错 ，否则贴错或损坏一张会导致全部都错，千万要注意: SSCC 贴纸务必要在正中间(可以覆 盖Logo <(>&<)> 箱唛)，否则会影响到仓库扫描识别。 3. 日期码使用ZURU标准版本。 4. 如果大货有要求入邮包盒，则对应的邮包盒上面要打上日期码。 5. 按照客户PO# 装柜/箱号顺序装柜，跟单会提前给到装柜计划。在大货生产/仓库存放时，请留意该装柜要求，以便装柜时不混乱（避免装错/装漏/找不到货号等 ）。 6. 出口加拿大，包装需要至少2/3L UPC版，无硼版本。 7.邮包盒上要印刷日期码 | X85: Kelly Shen | Y85: 3.7299 | Z85: =Y85*J85 -> 134.2764 | AB85: 36 | AC85: =AB85-J85 -> 0 | AD85: ok | AE85: 已入 | AF85: 系统出单 | AG85: =J85 -> 36 | AH85: =J85 -> 36 | AI85: =J85 -> 36 | AL85: =J85 -> 36 | AU85: =J85 -> 36
A86: 45968 | B86: AMAZON CA (VENDOR CENTER) | C86: 加拿大 | D86: 4500184827 | E86: 7CV524UV | F86: 4500184827-240 | G86: 7166-2023-S002-V1-3L | H86: 7166-2023-S002 | I86: 小鲨鱼3PK | J86: 18 | K86: 0 | L86: 18 | M86: =J86/L86 -> 1 | N86: 46009 | O86: 46007 | Q86: PASS | S86: 11/7收到 | U86: UPC贴纸翻4500148503+11/26-客供防伪帖纸+外箱贴纸 | V86: 7166 MA 3L 加UPC贴纸 | W86: 日期码格式：ZURU INC(BVI) 标准格式 日期：按实际生产日期 Packaging Info: 出口加拿大，包装需要至少2/3L UPC版，无硼版本。 #7166 MA 3L 加UPC贴纸，UPC贴纸资料翻单4500148503。需要加一张客供防伪帖纸，贴纸跟单提供。 Remark: 1. Amazon FOB订单，出口CA。外箱最长边不能超过25" （超过了，case pack只能为1），不符合要求的大货，一律不接受。 2. 外箱正面印ZURU Logo + SSCC LABEL（客供贴纸)，侧面印item#（订单上显示的SKU#) + carton size(以工厂实际尺寸为准，单位: inch) + MADE IN CHINA， 日期使用ZURU 标准版本 SSCC Label 显示的是客人自己的item#，SSCC Label 贴在外箱正面的正中间，贴一面即可，跟单订购，贴纸离外箱距必须至少3cm，每一 张SSCC label 都是唯一且有不同流水及条码的，没有损耗，绝对不可贴错 ，否则贴错或损坏一张会导致全部都错，千万要注意: SSCC 贴纸务必要在正中间(可以覆 盖Logo <(>&<)> 箱唛)，否则会影响到仓库扫描识别。 3. 日期码使用ZURU标准版本。 4. 如果大货有要求入邮包盒，则对应的邮包盒上面要打上日期码。 5. 按照客户PO# 装柜/箱号顺序装柜，跟单会提前给到装柜计划。在大货生产/仓库存放时，请留意该装柜要求，以便装柜时不混乱（避免装错/装漏/找不到货号等 ）。 6. 出口加拿大，包装需要至少2/3L UPC版，无硼版本。 7.邮包盒上要印刷日期码 | X86: Kelly Shen | Y86: 3.7299 | Z86: =Y86*J86 -> 67.1382 | AB86: 18 | AC86: =AB86-J86 -> 0 | AD86: ok | AE86: 已入 | AF86: 系统出单 | AG86: =J86 -> 18 | AH86: =J86 -> 18 | AI86: =J86 -> 18 | AL86: =J86 -> 18 | AU86: =J86 -> 18
A87: 45968 | B87: AMAZON CA (VENDOR CENTER) | C87: 加拿大 | D87: 4500184827 | E87: 6ZP5IRSI | F87: 4500184827-250 | G87: 7166-2023-S002-V1-3L | H87: 7166-2023-S002 | I87: 小鲨鱼3PK | J87: 54 | K87: 0 | L87: 18 | M87: =J87/L87 -> 3 | N87: 46009 | O87: 46007 | Q87: PASS | S87: 11/7收到 | U87: UPC贴纸翻4500148503+11/26-客供防伪帖纸+外箱贴纸 | V87: 7166 MA 3L 加UPC贴纸 | W87: 日期码格式：ZURU INC(BVI) 标准格式 日期：按实际生产日期 Packaging Info: 出口加拿大，包装需要至少2/3L UPC版，无硼版本。 #7166 MA 3L 加UPC贴纸，UPC贴纸资料翻单4500148503。需要加一张客供防伪帖纸，贴纸跟单提供。 Remark: 1. Amazon FOB订单，出口CA。外箱最长边不能超过25" （超过了，case pack只能为1），不符合要求的大货，一律不接受。 2. 外箱正面印ZURU Logo + SSCC LABEL（客供贴纸)，侧面印item#（订单上显示的SKU#) + carton size(以工厂实际尺寸为准，单位: inch) + MADE IN CHINA， 日期使用ZURU 标准版本 SSCC Label 显示的是客人自己的item#，SSCC Label 贴在外箱正面的正中间，贴一面即可，跟单订购，贴纸离外箱距必须至少3cm，每一 张SSCC label 都是唯一且有不同流水及条码的，没有损耗，绝对不可贴错 ，否则贴错或损坏一张会导致全部都错，千万要注意: SSCC 贴纸务必要在正中间(可以覆 盖Logo <(>&<)> 箱唛)，否则会影响到仓库扫描识别。 3. 日期码使用ZURU标准版本。 4. 如果大货有要求入邮包盒，则对应的邮包盒上面要打上日期码。 5. 按照客户PO# 装柜/箱号顺序装柜，跟单会提前给到装柜计划。在大货生产/仓库存放时，请留意该装柜要求，以便装柜时不混乱（避免装错/装漏/找不到货号等 ）。 6. 出口加拿大，包装需要至少2/3L UPC版，无硼版本。 7.邮包盒上要印刷日期码 | X87: Kelly Shen | Y87: 3.7299 | Z87: =Y87*J87 -> 201.4146 | AB87: 54 | AC87: =AB87-J87 -> 0 | AD87: ok | AE87: 已入 | AF87: 系统出单 | AG87: =J87 -> 54 | AH87: =J87 -> 54 | AI87: =J87 -> 54 | AL87: =J87 -> 54 | AU87: =J87 -> 54
A88: 45968 | B88: BURLINGTON STORES, INC. | C88: 美国 | D88: 4500184950 | E88: 384174102 | F88: 4500184950-20 | G88: 7163-2023-S003-1L-V1 | H88: 7163-2023-S003 | I88: 小鲨鱼 | J88: 1200 | K88: 0 | L88: 24 | M88: =J88/L88 -> 50 | N88: 46013 | O88: 46009 | Q88: PASS | R88: 12/30出 | S88: 11/10收到 | U88: 11/28外箱贴纸 | V88: ZURU MA （首选1L）UPC版本 | W88: 日期码格式：ZURU INC(BVI) 标准格式 日期：按实际生产日期 Packaging Info: 1. ZURU MA （首选1L）UPC版本+外箱贴纸为方便进行装柜区分，请按照后续提供的外箱贴纸文档去粘贴外箱），出口美国 Remark: 2. 产品和包装上印刷ZURU 标准日期码； 3. 纸箱中间靠上沿印刷ZURU LOGO，见箱唛资料 4. 外箱UCC 条码贴纸，尺寸: 4*6inch，贴在其中一面正唛右下角，贴纸距离外箱底部3.5cm, 侧边距离3.5cm。外箱贴纸由跟单提供电子版, 工厂自行安排，不可用 封箱胶覆盖贴纸条码，贴纸需要可以扫描且无损坏. 很重要： 每份贴纸文档的数量对应的是装柜数量，一个ID对应一个柜子，外箱贴纸需要按照SHIPMENT ID (不会显示在贴纸上，在贴纸资料文档上命名上）去区分 ，也就是同个item line 但是SHIPMENT ID 不一样不可以混在一起，贴纸和大货需要区分开，最后装柜会在不同的柜子里面。 | X88: Jessi Xu | Y88: 0.9073 | Z88: =Y88*J88 -> 1088.76 | AB88: 1200 | AC88: =AB88-J88 -> 0 | AD88: ok | AE88: 已入 | AF88: 系统出单 | AG88: =J88/3 -> 400 | AH88: =J88/3 -> 400 | AI88: =J88/3 -> 400 | AJ88: =J88 -> 1200 | AL88: =J88 -> 1200
A89: 45968 | B89: BURLINGTON STORES, INC. | C89: 美国 | D89: 4500184953 | E89: 384192802 | F89: 4500184953-20 | G89: 7163-2023-S003-1L-V1 | H89: 7163-2023-S003 | I89: 小鲨鱼 | J89: 1200 | K89: 0 | L89: 24 | M89: =J89/L89 -> 50 | N89: 46013 | O89: 46009 | Q89: PASS | R89: 12/30出 | S89: 11/10收到 | U89: 11/28外箱贴纸 | V89: ZURU MA （首选1L）UPC版本 | W89: 日期码格式：ZURU INC(BVI) 标准格式 日期：按实际生产日期 Packaging Info: 1. ZURU MA （首选1L）UPC版本+外箱贴纸为方便进行装柜区分，请按照后续提供的外箱贴纸文档去粘贴外箱），出口美国 Remark: 2. 产品和包装上印刷ZURU 标准日期码； 3. 纸箱中间靠上沿印刷ZURU LOGO，见箱唛资料 4. 外箱UCC 条码贴纸，尺寸: 4*6inch，贴在其中一面正唛右下角，贴纸距离外箱底部3.5cm, 侧边距离3.5cm。外箱贴纸由跟单提供电子版, 工厂自行安排，不可用 封箱胶覆盖贴纸条码，贴纸需要可以扫描且无损坏. 很重要： 每份贴纸文档的数量对应的是装柜数量，一个ID对应一个柜子，外箱贴纸需要按照SHIPMENT ID (不会显示在贴纸上，在贴纸资料文档上命名上）去区分 ，也就是同个item line 但是SHIPMENT ID 不一样不可以混在一起，贴纸和大货需要区分开，最后装柜会在不同的柜子里面。 | X89: Jessi Xu | Y89: 0.8993 | Z89: =Y89*J89 -> 1079.16 | AB89: 1200 | AC89: =AB89-J89 -> 0 | AD89: ok | AE89: 已入 | AF89: 系统出单 | AG89: =J89/3 -> 400 | AH89: =J89/3 -> 400 | AI89: =J89/3 -> 400 | AJ89: =J89 -> 1200 | AL89: =J89 -> 1200
A90: 45917 | B90: ACADEMY LTD | C90: 美国 | D90: 4500179708 | E90: 11919217 | F90: 4500179708-10 | G90: 7163TQ1-2023-S001-V1 | H90: 7163TQ1-2023-S001 | I90: 小鲨鱼 | J90: 378 | K90: 0 | L90: 6 | M90: =J90/L90 -> 63 | N90: 46029 | O90: 46025 | Q90: PASS | R90: 1/14出 | S90: 10/22收到 | U90: 10/22-UCC贴纸 | V90: MA UPC 版本包装 | W90: 日期码格式：ZURU INC(BVI) 标准格式 日期：按实际生产日期 Packaging Info: 1. 出口美国，MA UPC 版本包装 #7163TQ1: UPC#193052062604; 3 assortment; 3PCS LR44 BATTERIES(INCLUDED); Remark: 2 .外箱正唛的右下角需贴一个UCC贴纸（4x6inch,距离右边和底边2inch,UCC贴纸为流水号的，每一箱都不一样。 3. 请按期完货，延期有罚金。 4. 我司验货即可。 5. 产品和包装上有tracking code信息，格式为ZURU常规。 | X90: Abby Mai,Lluvia Zeng | Y90: 0.9545 | Z90: =Y90*J90 -> 360.801 | AB90: 378 | AC90: =AB90-J90 -> 0 | AD90: ok | AE90: 已入 | AF90: 系统出单 | AG90: =J90/3 -> 126 | AH90: =J90/3 -> 126 | AI90: =J90/3 -> 126 | AJ90: =J90 -> 378 | AL90: =J90 -> 378 | AM90: =J90/6 -> 63
A91: 45918 | B91: ACADEMY LTD | C91: 美国 | D91: 4500179767 | E91: 11919215 | F91: 4500179767-10 | G91: 7163TQ1-2023-S001-V1 | H91: 7163TQ1-2023-S001 | I91: 小鲨鱼 | J91: 690 | K91: 0 | L91: 6 | M91: =J91/L91 -> 115 | N91: 46029 | O91: 46025 | Q91: PASS | R91: 1/20出 | S91: 10/22收到 | U91: 10/22-UCC贴纸 | V91: MA UPC 版本包装 | W91: 日期码格式：ZURU INC(BVI) 标准格式 日期：按实际生产日期 Packaging Info: 1. 出口美国，MA UPC 版本包装 #7163TQ1: UPC#193052062604; 3 assortment; 3PCS LR44 BATTERIES(INCLUDED); Remark: 2 .外箱正唛的右下角需贴一个UCC贴纸（4x6inch,距离右边和底边2inch,UCC贴纸为流水号的，每一箱都不一样。 3. 请按期完货，延期有罚金。 4. 我司验货即可。 5. 产品和包装上有tracking code信息，格式为ZURU常规。 | X91: Abby Mai,Lluvia Zeng | Y91: 0.9545 | Z91: =Y91*J91 -> 658.605 | AB91: 690 | AC91: =AB91-J91 -> 0 | AD91: ok | AE91: 已入 | AF91: 系统出单 | AG91: =J91/3 -> 230 | AH91: =J91/3 -> 230 | AI91: =J91/3 -> 230 | AJ91: =J91 -> 690 | AL91: =J91 -> 690 | AM91: =J91/6 -> 115
A92: 45918 | B92: ACADEMY LTD | C92: 美国 | D92: 4500179772 | E92: 11919216 | F92: 4500179772-10 | G92: 7163TQ1-2023-S001-V1 | H92: 7163TQ1-2023-S001 | I92: 小鲨鱼 | J92: 318 | K92: 0 | L92: 6 | M92: =J92/L92 -> 53 | N92: 46029 | O92: 46025 | Q92: PASS | R92: 1/14出 | S92: 10/22收到 | U92: 10/22-UCC贴纸 | V92: MA UPC 版本包装 | W92: 日期码格式：ZURU INC(BVI) 标准格式 日期：按实际生产日期 Packaging Info: 1. 出口美国，MA UPC 版本包装 #7163TQ1: UPC#193052062604; 3 assortment; 3PCS LR44 BATTERIES(INCLUDED); Remark: 2 .外箱正唛的右下角需贴一个UCC贴纸（4x6inch,距离右边和底边2inch,UCC贴纸为流水号的，每一箱都不一样。 3. 请按期完货，延期有罚金。 4. 我司验货即可。 5. 产品和包装上有tracking code信息，格式为ZURU常规。 | X92: Abby Mai,Lluvia Zeng | Y92: 0.9545 | Z92: =Y92*J92 -> 303.531 | AB92: 318 | AC92: =AB92-J92 -> 0 | AD92: ok | AE92: 已入 | AF92: 系统出单 | AG92: =J92/3 -> 106 | AH92: =J92/3 -> 106 | AI92: =J92/3 -> 106 | AJ92: =J92 -> 318 | AL92: =J92 -> 318 | AM92: =J92/6 -> 53
A93: 45989 | B93: AMAZON CA (VENDOR CENTER) | C93: 加拿大 | D93: 4500187446 | E93: 16B2363J | F93: 4500187446-10 | G93: 7166-2023-S002-V1-3L | H93: 7166-2023-S002 | I93: 小鲨鱼3PK | J93: 18 | K93: 0 | L93: 18 | M93: =J93/L93 -> 1 | N93: 46038 | O93: 46034 | Q93: PASS | R93: 1/18-1/21出 | S93: 11/28收到 | U93: UPC贴纸翻4500148503+12/30客供防伪帖纸+12/22-外箱贴纸 | V93: 7166 MA 3L | W93: 日期码格式：ZURU INC(BVI) 标准格式 日期：按实际生产日期 Packaging Info: #7166 MA 3L 加UPC贴纸，UPC贴纸资料翻单4500148503。需要加一张客供防伪帖纸，贴纸跟单提供。 Remark: 1. Amazon FOB订单，出口CA。外箱最长边不能超过25" （超过了，case pack只能为1），不符合要求的大货，一律不接受。 2. 外箱正面印ZURU Logo + SSCC LABEL（客供贴纸)，侧面印item#（订单上显示的SKU#) + carton size(以工厂实际尺寸为准，单位: inch) + MADE IN CHINA， 日期使用ZURU 标准版本 SSCC Label 显示的是客人自己的item#，SSCC Label 贴在外箱正面的正中间，贴一面即可，跟单订购，贴纸离外箱距必须至少3cm，每一 张SSCC label 都是唯一且有不同流水及条码的，没有损耗，绝对不可贴错 ，否则贴错或损坏一张会导致全部都错，千万要注意: SSCC 贴纸务必要在正中间(可以覆 盖Logo <(>&<)> 箱唛)，否则会影响到仓库扫描识别。 3. 日期码使用ZURU标准版本。 4. 如果大货有要求入邮包盒，则对应的邮包盒上面要打上日期码。 5. 按照客户PO# 装柜/箱号顺序装柜，跟单会提前给到装柜计划。在大货生产/仓库存放时，请留意该装柜要求，以便装柜时不混乱（避免装错/装漏/找不到货号等 ）。 6. 出口加拿大，包装需要至少2/3L UPC版，无硼版本。 7.邮包盒上要印刷日期码 | X93: Kelly Shen | Y93: 3.7299 | Z93: =Y93*J93 -> 67.1382 | AB93: 18 | AC93: =AB93-J93 -> 0 | AD93: ok | AE93: 已入 | AF93: 系统出单 | AG93: =J93 -> 18 | AH93: =J93 -> 18 | AI93: =J93 -> 18 | AL93: =J93 -> 18 | AU93: =J93 -> 18
