Workbook

Sheet 92107
A1: ZURU Babycorns Surprise - S1 #92107 | BI1: 中东客 | BT1: 蝴蝶 | BU1: 瓢虫 | BV1: 长颈鹿 | BW1: 大象
AI2: 收缩膜 | AO2: 收藏指南 | AT2: 阅读卡 MA 5L | AX2: 阅读卡 MA 5L B版 | BB2: 阅读卡 中文 | BG2: 展示架F | BI2: 134696 | BJ2: 口水胶 | BL2: 布标 | BS2: 总MA | BT2: =生产MA!D19 -> 245000 | BU2: =生产MA!E19 -> 245000 | BV2: =生产MA!F19 -> 242000 | BW2: =生产MA!G19 -> 241000 | BX2: =SUM(BT2:BW2) -> 973000
A3: 接单日期 | B3: 第三方客户名称 | C3: 国家 | D3: PO号 | E3: 客PO号 | F3: SKU | G3: ITEM# | H3: 中文名 | I3: PO数量 (pcs) | J3: 内箱装箱数量(pcs) | K3: 外箱装箱数量(pcs) | L3: 总箱数 | M3: ZURU订单走货日期 | N3: ZURU验货 日期 | O3: 第三方验货 | P3: 驗貨結果 | Q3: 送货情况 | R3: 欠数 | S3: 贴纸 | T3: 出单情况 | U3: 船期SO | V3: 车间回复完成时间 | W3: 箱唛资料 | X3: 是否有外箱贴 | Y3: 贴纸资料 | Z3: 客供物料 | AA3: 日期码 | AB3: 备注 | AC3: ZURU跟单 | AD3: 单价USD | AE3: 金额USD | AF3: 發票號 | AG3: 系统货号 | AH3: 是否入系统 | AI3: MA 1L | AJ3: MA 1L B版 | AK3: MA 3L | AL3: MA 3L B版 | AM3: 134696中东客 客版 | AN3: 客版 | AO3: MA 5L | AP3: MA 5L B版 | AQ3: 134696中东客 客版 | AR3: 中文 | AS3: 客版 | AT3: Butterfly 蝴蝶 D | AU3: Ladybug瓢虫 E | AV3: Giraffe长颈鹿 B | AW3: Elephant大象 A | AX3: Butterfly 蝴蝶 D | AY3: Ladybug瓢虫 E | AZ3: Giraffe长颈鹿 B | BA3: Elephant大象 A | BB3: Butterfly 蝴蝶 | BC3: Ladybug瓢虫 | BD3: Giraffe长颈鹿 | BE3: Elephant大象 | BF3: 相差 | BG3: MA 1L | BH3: MA 3L | BI3: #9283中的两款沙子代替slime | BJ3: 有硼 | BK3: 无硼 | BL3: MA/客版 | BN3: Butterfly 蝴蝶 D | BO3: Ladybug 瓢虫 E | BP3: Giraffe 长颈鹿 B | BQ3: Elephant 大象 A | BS3: 合计 | BT3: MA剩余 | BU3: MA剩余 | BV3: MA剩余 | BW3: MA剩余
A4: 45289 | B4: ZURU | C4: 库有 | D4: ZPO2312005 | E4: PP订单 | G4: 92107-S001 | H4: 摇篮公子 | I4: 284 | J4: 0 | K4: 8 | L4: =I4/K4 -> 35.5 | M4: 45313 | N4: 45309 | W4: 无 | X4: 无 | Y4: 无 | AB4: 1.OA Testing Samples (BULK)：数量 16；地址 深圳市罗湖区东门南路106号口岸大楼17B ，Angus 2 CTN 2.QA Testing samples (FSDU)：数量 30；地址 深圳市罗湖区东门南路106号口岸大楼17B ，Angus 1FSDU 3.Signed Sample (6套签+1套用于拆办)：数量 28；地址 深圳市罗湖区东门南路1006号口岸大楼A栋3楼，Jessy Zhang 13421384408 ，7套*4款=28 4.Show room：数量 80；地址 清溪镇光朗村易京街25号《库有样板房) 收件人:李志强电话: 18328402533 ，20套 注：开PP时候帮忙额外准备3套散件邮寄到深圳办公室 5.Sample room samples：数量 280；地址 清溪镇光朗村易京街25号《库有样板房) 收件人:李志强电话: 18328402533 ，70套 注：开PP时候帮忙额外准备3套散件邮寄到深圳办公室 6.散件：数量 12；地址 深圳市罗湖区东门南路1006号口岸大楼A栋16楼，Max Mlai 13632761211 2 CTN 3套散件（除蛋壳外的所有内含物），每套单独装好 合计数量434；PP订单数量合计 500PCS 注:PP PO数量含buffer，请按PP PO数量准备物料 | AG4: # | AH4: # | BF4: =SUM(AT4:BE4)-I4 -> -284 | BN4: 0 | BO4: 0 | BP4: 0 | BQ4: 0 | BR4: =BN4+BO4+BP4+BQ4-I4 -> -284 | BS4: =BN4+BO4+BP4+BQ4+$BS$290 -> 512480 | BT4: =$BT$2-$BT$290-BN4 -> 131789.33 | BU4: =$BT$2-$BT$290-BO4 -> 131789.33 | BV4: =$BT$2-$BT$290-BP4 -> 131789.33 | BW4: =$BT$2-$BT$290-BQ4 -> 131789.33
A5: 45561 | B5: WAL-MART CANADA CORP. | C5: 加拿大 | D5: 4500146212 | F5: 4500146212-20 | G5: 92107-S003-NB | H5: 摇篮公子 | I5: 1707 | J5: 0 | K5: 1 | L5: =I5/K5 -> 1707 | M5: 45621 | N5: 45617 | O5: 11/25抽办 12/18第三方 | P5: PASS | U5: 1/6出 | W5: 10/31收到 | X5: 无 | Y5: UPC条码贴纸9/26 | AB5: 日期码格式：ZURU INC(BVI) 标准格式 日期：按实际生产日期 Packaging Info: #92107: MA3L收缩膜+UPC条码贴纸(UPC: 193052064738)+MA5L收藏指南+MA5L资料卡+MA5L胶袋+MA配件袋+MA2L布标 -产品配比: 4 Assortment Ratio (Ladybug: Giraffe: Butterfly: Elephant)=1:1:1:1 Remark: 1. 92107 须使用无硼slime; 3. 此单有箱唛； 4. 此单有第三方验货，烦请多备包装物料； 5. 此单#92108/92107/92105/9296/9554/15714 需签办；签办数量：大货样各3套; 6. 此单#92108/92107/92105/9296/9554 需于2024/11/25 抽办做测试；抽办数量：大货各5套; ********************* a. 请确保产品符合1999年版本的加拿大环境保护法(CEPA)和2012年禁止某些有毒物质法规的要求。该产品不含任何在加拿大禁用的化学物质，包括但不限于有毒物 质清单中列出的化学物质，并且在为加拿大沃尔玛生产产品期间没有使用任何禁用化学物质。 Supplier certify that the products comply with the requirements of Canadian Environmental Protection Act, 1999 (CEPA), Prohibition of Certain To xic Substances Regulations, 2012. The products do not contain any chemicals that are banned in Canada, including but not limited to those listed in the Toxic Substances List and no banned chemicals were used during the manufacturing of product for Walmart Canada. 附件列表： (1) Letter of Guarantee for Canada banned chemicals - (1-5CA) b. 请确保产品在均质材料中的汞浓度不超过0.1%（按重量计）。 Supplier certify that the WAL-MART vendor products does not have a mercury concentration of more than 0.1% by weight in homogeneous material. 附件列表： (1) Letter of Guarantee for Mercury COC c. 请确保产品的塑料材料不含以下物质（SOR 2011-17 27B): Supplier certify that the plastic materials do not contain the following substances(SOR 2011-17 27B): (a) carbon tetrachloride or any substance that contains it; (b) methyl alcohol or any substance thay contains >1.0%; (c) petroleum distillates or any substance that contains >10% weight to volume of petroleum distillates; (d) benzene; (e) turpentine or any substance that contains >10% weight to volume of turpentine; (f) boric acid or salts of boric acid; or (g) ethyl ether. 附件列表： (1) Letter of Guarantee for WM CA-Other prohibited substances in plastic(less than 3 years) | AC5: Monica Zhou | AD5: 4.3993 | AE5: =AD5*I5 -> 7509.6051 | AF5: 94003-1.13 | AG5: 92107-S003-NB-3L | AH5: 已入 | AL5: =I5 -> 1707 | AP5: =I5 -> 1707 | AT5: =I5/4 -> 426.75 | AU5: =AT5 -> 426.75 | AV5: =AU5 -> 426.75 | AW5: =AV5 -> 426.75 | BF5: =SUM(AT5:BE5)-I5 -> 0 | BK5: =I5 -> 1707 | BL5: MA | BN5: =I5/4 -> 426.75 | BO5: =I5/4 -> 426.75 | BP5: =I5/4 -> 426.75 | BQ5: =I5/4 -> 426.75 | BR5: =BN5+BO5+BP5+BQ5-I5 -> 0 | BS5: =BN5+BO5+BP5+BQ5+$BS$290 -> 514187 | BT5: =BT4-BN5 -> 131362.58 | BU5: =BU4-BO5 -> 131362.58 | BV5: =BV4-BP5 -> 131362.58 | BW5: =BW4-BQ5 -> 131362.58
A6: 45523 | B6: DM LLC | C6: 俄罗斯 | D6: 4500143263 | E6: 出Bekasovo 2 | F6: 4500143263-30 | G6: 92107-S001 | H6: 摇篮公子 | I6: 2320 | J6: 0 | K6: 8 | L6: =I6/K6 -> 290 | M6: 45667 | N6: 45663 | P6: PASS | U6: 2/10出 | W6: 10/28收到 | X6: 无 | Y6: 进口商贴纸（翻4500143236）+EAN条码贴纸（翻4500143236） | Z6: 客版收缩膜翻4500143236 | AA6: 外包装(指: 收缩膜/彩卡/吊牌/PDQ)/外箱不要打ZURU标准日期码！ | AB6: 日期码格式：注意:外包装(指: 收缩膜/彩卡/吊牌/PDQ)/外箱不要打ZURU标准日期码！ 日期： Packaging Info: 出Bekasovo 2 和Ural 2 个港口； LC 货期不可延期有罚款 ； 92107 : 客版收缩膜翻4500143236 ， MA 指南 。 注意 ：外包装 (指: 收缩膜/彩卡/吊牌/PDQ) /外箱不要打ZURU标准日期码！ Remark: 标准配比 | AC6: Ann Zhang | AD6: 4.2362 | AE6: =AD6*I6 -> 9827.984 | AF6: 94200-2.10 | AG6: 92107-S001-2 | AH6: 已入 | AN6: =I6 -> 2320 | AO6: =I6 -> 2320 | AT6: =I6/4 -> 580 | AU6: =AT6 -> 580 | AV6: =AU6 -> 580 | AW6: =AV6 -> 580 | BF6: =SUM(AT6:BE6)-I6 -> 0 | BJ6: =I6 -> 2320 | BL6: MA | BN6: =I6/4 -> 580 | BO6: =I6/4 -> 580 | BP6: =I6/4 -> 580 | BQ6: =I6/4 -> 580 | BR6: =BN6+BO6+BP6+BQ6-I6 -> 0 | BS6: =BN6+BO6+BP6+BQ6+$BS$290 -> 514800 | BT6: =BT5-BN6 -> 130782.58 | BU6: =BU5-BO6 -> 130782.58 | BV6: =BV5-BP6 -> 130782.58 | BW6: =BW5-BQ6 -> 130782.58
A7: 45523 | B7: DM LLC | C7: 俄罗斯 | D7: 4500143263 | E7: 出Ural | F7: 4500143263-60 | G7: 92107-S001 | H7: 摇篮公子 | I7: 1160 | J7: 0 | K7: 8 | L7: =I7/K7 -> 145 | M7: 45667 | N7: 45663 | P7: PASS | U7: 2/10出 | W7: 10/28收到 | X7: 无 | Y7: 进口商贴纸（翻4500143236）+EAN条码贴纸（翻4500143236） | Z7: 客版收缩膜翻4500143236 | AA7: 外包装(指: 收缩膜/彩卡/吊牌/PDQ)/外箱不要打ZURU标准日期码！ | AB7: 日期码格式：注意:外包装(指: 收缩膜/彩卡/吊牌/PDQ)/外箱不要打ZURU标准日期码！ 日期： Packaging Info: 出Bekasovo 2 和Ural 2 个港口； LC 货期不可延期有罚款 ； 92107 : 客版收缩膜翻4500143236 ， MA 指南 。 注意 ：外包装 (指: 收缩膜/彩卡/吊牌/PDQ) /外箱不要打ZURU标准日期码！ Remark: 标准配比 | AC7: Ann Zhang | AD7: 4.2362 | AE7: =AD7*I7 -> 4913.992 | AF7: 94200-2.10 | AG7: 92107-S001-2 | AH7: 已入 | AN7: =I7 -> 1160 | AO7: =I7 -> 1160 | AT7: =I7/4 -> 290 | AU7: =AT7 -> 290 | AV7: =AU7 -> 290 | AW7: =AV7 -> 290 | BF7: =SUM(AT7:BE7)-I7 -> 0 | BJ7: =I7 -> 1160 | BL7: MA | BN7: =I7/4 -> 290 | BO7: =I7/4 -> 290 | BP7: =I7/4 -> 290 | BQ7: =I7/4 -> 290 | BR7: =BN7+BO7+BP7+BQ7-I7 -> 0 | BS7: =BN7+BO7+BP7+BQ7+$BS$290 -> 513640 | BT7: =BT6-BN7 -> 130492.58 | BU7: =BU6-BO7 -> 130492.58 | BV7: =BV6-BP7 -> 130492.58 | BW7: =BW6-BQ7 -> 130492.58
A8: 45601 | B8: DD’S DISCOUNTS | C8: 美国 | D8: 4500150187 | E8: 70054066 | F8: 4500150187-40 | G8: 92107-S001 | H8: 摇篮公子 | I8: 600 | J8: 0 | K8: 8 | L8: =I8/K8 -> 75 | M8: 45653 | N8: 45649 | P8: PASS | U8: 1/7出 | W8: ROSS指定箱唛格式 | Y8: 11/19收到价格贴纸客供 | AB8: 日期码格式：ZURU INC(BVI) 标准格式 日期：按实际生产日期 Packaging Info: 1.ZURU MA UPC 现有版本包装 + 客供价格贴纸，出口美国 , 优先使用MA 1L 最新版本 。 Remark: 1.ZURU MA UPC 现有版本包装 + 客供价格贴纸，出口美国 , 优先使用MA 1L 最新版本 。 2.价格贴纸位于包装正面右下角，不挡住重要信息即可，可适当调整 ，价格贴纸由跟单提供。 3.标准日期码格式，产品和包装必须有日期码 。 4.同个产品同个货期不可出现不同的包装。 5. 跟单提供ROSS通用的箱唛模版，工厂按实际45 PO上客户PO/Item号/装箱数 提供箱唛排版来确认。 | AC8: Taylor Liao | AD8: 4.0921 | AE8: =AD8*I8 -> 2455.26 | AF8: 88917-1.7 | AG8: 92107-S001 | AH8: 已入 | AI8: =I8 -> 600 | AO8: =I8 -> 600 | AT8: =I8/4 -> 150 | AU8: =AT8 -> 150 | AV8: =AU8 -> 150 | AW8: =AV8 -> 150 | BF8: =SUM(AT8:BE8)-I8 -> 0 | BJ8: =I8 -> 600 | BL8: MA | BN8: =I8/4 -> 150 | BO8: =I8/4 -> 150 | BP8: =I8/4 -> 150 | BQ8: =I8/4 -> 150 | BR8: =BN8+BO8+BP8+BQ8-I8 -> 0 | BS8: =BN8+BO8+BP8+BQ8+$BS$290 -> 513080 | BT8: =BT7-BN8 -> 130342.58 | BU8: =BU7-BO8 -> 130342.58 | BV8: =BV7-BP8 -> 130342.58 | BW8: =BW7-BQ8 -> 130342.58
A9: 45621 | B9: TOYS "R" US – JAPAN, LTD | C9: 日本 | D9: 4500152217 | E9: 47:0003108131 | F9: 4500152217-10 | G9: 92107-S008 | H9: 摇篮公子 (三款公仔） | I9: 552 | J9: 0 | K9: 8 | L9: =I9/K9 -> 69 | M9: 45656 | N9: 45652 | P9: PASS | U9: 1/5出 | W9: 11/25收到 | Y9: 日语贴纸翻4500135847）+6+贴纸 | AB9: 日期码格式：ZURU INC(BVI) 标准格式 日期：按实际生产日期 Tracking Code: Packaging Info: MA 1L UPC PKG A版收缩膜+MA 5L+23L Warning A版收藏指南 +日语贴纸(贴纸AW翻单4500135847）+1张6+贴纸覆盖3+。 Remark: 出日本， 大货品质/包装必须严格跟到PO#4500135847。 请特别留意此单仅出以下3款， 按以下的数量分配。 Ladybug: 184pcs Giraffe: 184pcs Butterfly: 184pcs 装箱按以下配比。 3 Assortment Ratio (Ladybug: Giraffe: Butterfly)=1:1:1, 2pcs of each+2pcs random=8pcs/CTN | AC9: Doris Shou | AD9: 4.0839 | AE9: =AD9*I9 -> 2254.3128 | AF9: 88889-1.6 | AG9: 92107-S001 | AH9: 已入 | AI9: =I9 -> 552 | AO9: =I9 -> 552 | AT9: =I9/3 -> 184 | AU9: =AT9 -> 184 | AV9: =AU9 -> 184 | BF9: =SUM(AT9:BE9)-I9 -> 0 | BJ9: =I9 -> 552 | BL9: MA | BN9: =I9/3 -> 184 | BO9: =I9/3 -> 184 | BP9: =I9/3 -> 184 | BR9: =BN9+BO9+BP9+BQ9-I9 -> 0 | BS9: =BN9+BO9+BP9+BQ9+$BS$290 -> 513032 | BT9: =BT8-BN9 -> 130158.58 | BU9: =BU8-BO9 -> 130158.58 | BV9: =BV8-BP9 -> 130158.58 | BW9: =BW8-BQ9 -> 130342.58
A10: 45621 | B10: TOYS "R" US – JAPAN, LTD | C10: 日本 | D10: 4500152215 | E10: 46:0003108129 | F10: 4500152215-10 | G10: 92107-S008 | H10: 摇篮公子 (三款公仔） | I10: 448 | J10: 0 | K10: 8 | L10: =I10/K10 -> 56 | M10: 45656 | N10: 45652 | P10: PASS | U10: 1/5出 | W10: 11/25收到 | Y10: 日语贴纸翻4500135847）+6+贴纸 | AB10: 日期码格式：ZURU INC(BVI) 标准格式 日期：按实际生产日期 Packaging Info: MA 1L UPC PKG A版收缩膜+MA 5L+23L Warning A版收藏指南 +日语贴纸(贴纸AW翻单4500135847）+1张6+贴纸覆盖3+。 Remark: 出日本， 大货品质/包装必须严格跟到PO#4500135847。 请特别留意此单仅出以下3款， 按以下的数量分配。 Ladybug: 149pcs Giraffe: 149pcs Butterfly: 150pcs 装箱按以下配比。 3 Assortment Ratio (Ladybug: Giraffe: Butterfly)=1:1:1, 2pcs of each+2pcs random=8pcs/CTN | AC10: Doris Shou | AD10: 4.0953 | AE10: =AD10*I10 -> 1834.6944 | AF10: 88888-1.6 | AG10: 92107-S001 | AH10: 已入 | AI10: =I10 -> 448 | AO10: =I10 -> 448 | AT10: =I10/3 -> 149.33333 | AU10: =AT10 -> 149.33333 | AV10: =AU10 -> 149.33333 | BF10: =SUM(AT10:BE10)-I10 -> 0 | BJ10: =I10 -> 448 | BL10: MA | BN10: =I10/3 -> 149.33333 | BO10: =I10/3 -> 149.33333 | BP10: =I10/3 -> 149.33333 | BR10: =BN10+BO10+BP10+BQ10-I10 -> 0 | BS10: =BN10+BO10+BP10+BQ10+$BS$290 -> 512928 | BT10: =BT9-BN10 -> 130009.25 | BU10: =BU9-BO10 -> 130009.25 | BV10: =BV9-BP10 -> 130009.25 | BW10: =BW9-BQ10 -> 130342.58
A11: 45586 | B11: TJX COMPANIES, INC | C11: 美国 | D11: 4500147789 | E11: Marshalls DC#881-128PCS , DC#884-96PCS, DC#886-136PCS , DC#887-120PCS , DC#888-120PCS | F11: 4500147789-70 | G11: 92107-S001 | H11: 摇篮公子 | I11: 600 | J11: 0 | K11: 8 | L11: =I11/K11 -> 75 | M11: 45649 | N11: 45645 | P11: PASS | U11: 1/2出 | W11: 11/4收到 | X11: 无 | Y11: 11/19收到价格贴纸客供 | AB11: 日期码格式：ZURU INC(BVI) 标准格式 日期：按实际生产日期 Packaging Info: MA UPC包装+价格贴纸，价格贴纸客供。 Remark: 1. 产品和包装上印刷tracking code信息，格式为ZURU常规格式。 2. 分5个DC出货，每款产品每个DC的箱唛资料不同。具体分DC数量，请参考后面行项目备注。 3. ZURU QC验货。 | AC11: Emily Wu | AD11: 4.2475 | AE11: =AD11*I11 -> 2548.5 | AF11: 94169-1.23 | AG11: 92107-S001 | AH11: 已入 | AI11: =I11 -> 600 | AO11: =I11 -> 600 | AT11: =I11/4 -> 150 | AU11: =AT11 -> 150 | AV11: =AU11 -> 150 | AW11: =AV11 -> 150 | BF11: =SUM(AT11:BE11)-I11 -> 0 | BJ11: =I11 -> 600 | BL11: MA | BN11: =I11/4 -> 150 | BO11: =I11/4 -> 150 | BP11: =I11/4 -> 150 | BQ11: =I11/4 -> 150 | BR11: =BN11+BO11+BP11+BQ11-I11 -> 0 | BS11: =BN11+BO11+BP11+BQ11+$BS$290 -> 513080 | BT11: =BT10-BN11 -> 129859.25 | BU11: =BU10-BO11 -> 129859.25 | BV11: =BV10-BP11 -> 129859.25 | BW11: =BW10-BQ11 -> 130192.58
A12: 45608 | B12: Amazon CA (Vendor Center) | C12: 加拿大 | D12: 4500150978 | E12: 5R6F4YLI | F12: 4500150978-10 | G12: 92107E-S001-NB | H12: 瓢虫 | I12: 8 | J12: 0 | K12: 8 | L12: =I12/K12 -> 1 | M12: 45653 | N12: 45649 | P12: PASS | U12: 1/1-1/7出 | W12: 11/12收到 | Y12: UPC贴纸翻4500134367 | AB12: 日期码格式：ZURU INC(BVI) 标准格式 日期：按实际生产日期 Packaging Info: 出口加拿大，包装需要至少2/3L UPC版，无硼版本 #92107 MA 1L UPC版本+ UPC贴纸跟返单4500134367；92107A:193052066817, 92107B:193052066824, 92107D:193052066831, 92107E:193052066848; Remark: 1. Amazon FOB订单，出口CA。外箱最长边不能超过25" （超过了，case pack只能为1），不符合要求的大货，一律不接受。 2. 外箱正面印ZURU Logo + SSCC LABEL（客供贴纸)，侧面印item#（订单上显示的SKU#) + carton size(以工厂实际尺寸为准，单位: inch) + MADE IN CHINA， 日期使用ZURU 标准版本 SSCC Label 显示的是客人自己的item#，SSCC Label 贴在外箱正面的正中间，贴一面即可，跟单订购，贴纸离外箱距必须至少3cm，每一 张SSCC label 都是唯一且有不同流水及条码的，没有损耗，绝对不可贴错 ，否则贴错或损坏一张会导致全部都错，千万要注意: SSCC 贴纸务必要在正中间(可以覆 盖Logo <(>&<)> 箱唛)，否则会影响到仓库扫描识别。 3. 日期码使用ZURU标准版本。 4. 如果大货有要求入邮包盒，则对应的邮包盒上面要打上日期码。 5. 按照客户PO# 装柜/箱号顺序装柜，跟单会提前给到装柜计划。在大货生产/仓库存放时，请留意该装柜要求，以便装柜时不混乱（避免装错/装漏/找不到货号等 ）。 6. 出口加拿大，包装需要至少2/3L UPC版，无硼版本。 7.邮包盒上要印刷日期码 | AC12: Kelly/Mia | AD12: 4.1036 | AE12: =AD12*I12 -> 32.8288 | AF12: 88919-1.7 | AG12: 92107E-S001-3L-NB | AH12: 已入 | AL12: =I12 -> 8 | AP12: =I12 -> 8 | AT12: =I12/4 -> 2 | AU12: =AT12 -> 2 | AV12: =AU12 -> 2 | AW12: =AV12 -> 2 | BF12: =SUM(AT12:BE12)-I12 -> 0 | BK12: =I12 -> 8 | BL12: MA | BO12: =I12 -> 8 | BR12: =BN12+BO12+BP12+BQ12-I12 -> 0 | BS12: =BN12+BO12+BP12+BQ12+$BS$290 -> 512488 | BT12: =BT11-BN12 -> 129859.25 | BU12: =BU11-BO12 -> 129851.25 | BV12: =BV11-BP12 -> 129859.25 | BW12: =BW11-BQ12 -> 130192.58
A13: 45608 | B13: Amazon CA (Vendor Center) | C13: 加拿大 | D13: 4500150978 | E13: 5GDMN3WZ | F13: 4500150978-20 | G13: 92107D-S001-NB | H13: 蝴蝶 | I13: 8 | J13: 0 | K13: 8 | L13: =I13/K13 -> 1 | M13: 45653 | N13: 45649 | P13: PASS | U13: 1/1-1/7出 | W13: 11/12收到 | Y13: UPC贴纸翻4500134367 | AB13: 日期码格式：ZURU INC(BVI) 标准格式 日期：按实际生产日期 Packaging Info: 出口加拿大，包装需要至少2/3L UPC版，无硼版本 #92107 MA 1L UPC版本+ UPC贴纸跟返单4500134367；92107A:193052066817, 92107B:193052066824, 92107D:193052066831, 92107E:193052066848; Remark: 1. Amazon FOB订单，出口CA。外箱最长边不能超过25" （超过了，case pack只能为1），不符合要求的大货，一律不接受。 2. 外箱正面印ZURU Logo + SSCC LABEL（客供贴纸)，侧面印item#（订单上显示的SKU#) + carton size(以工厂实际尺寸为准，单位: inch) + MADE IN CHINA， 日期使用ZURU 标准版本 SSCC Label 显示的是客人自己的item#，SSCC Label 贴在外箱正面的正中间，贴一面即可，跟单订购，贴纸离外箱距必须至少3cm，每一 张SSCC label 都是唯一且有不同流水及条码的，没有损耗，绝对不可贴错 ，否则贴错或损坏一张会导致全部都错，千万要注意: SSCC 贴纸务必要在正中间(可以覆 盖Logo <(>&<)> 箱唛)，否则会影响到仓库扫描识别。 3. 日期码使用ZURU标准版本。 4. 如果大货有要求入邮包盒，则对应的邮包盒上面要打上日期码。 5. 按照客户PO# 装柜/箱号顺序装柜，跟单会提前给到装柜计划。在大货生产/仓库存放时，请留意该装柜要求，以便装柜时不混乱（避免装错/装漏/找不到货号等 ）。 6. 出口加拿大，包装需要至少2/3L UPC版，无硼版本。 7.邮包盒上要印刷日期码 | AC13: Kelly/Mia | AD13: 4.1036 | AE13: =AD13*I13 -> 32.8288 | AF13: 88919-1.7 | AG13: 92107D-S001-3L-NB | AH13: 已入 | AL13: =I13 -> 8 | AP13: =I13 -> 8 | AT13: =I13/4 -> 2 | AU13: =AT13 -> 2 | AV13: =AU13 -> 2 | AW13: =AV13 -> 2 | BF13: =SUM(AT13:BE13)-I13 -> 0 | BK13: =I13 -> 8 | BL13: MA | BN13: =I13 -> 8 | BR13: =BN13+BO13+BP13+BQ13-I13 -> 0 | BS13: =BN13+BO13+BP13+BQ13+$BS$290 -> 512488 | BT13: =BT12-BN13 -> 129851.25 | BU13: =BU12-BO13 -> 129851.25 | BV13: =BV12-BP13 -> 129859.25 | BW13: =BW12-BQ13 -> 130192.58
A14: 45586 | B14: TJX COMPANIES, INC | C14: 美国 | D14: 4500147792 | E14: Marshalls DC#881-128PCS , DC#884-96PCS, DC#886-136PCS , DC#887-120PCS , DC#888-120PCS | F14: 4500147792-70 | G14: 92107-S001 | H14: 摇篮公子 | I14: 600 | J14: 0 | K14: 8 | L14: =I14/K14 -> 75 | M14: 45656 | N14: 45652 | P14: PASS | U14: 1/9出 | W14: 11/4收到 | X14: 无 | Y14: 无 | Z14: 12/6-价格贴纸客供 | AB14: 日期码格式：ZURU INC(BVI) 标准格式 日期：按实际生产日期 Packaging Info: MA UPC包装+价格贴纸，价格贴纸客供。 Remark: 1. 产品和包装上印刷tracking code信息，格式为ZURU常规格式。 2. 分5个DC出货，每款产品每个DC的箱唛资料不同。具体分DC数量，请参考后面行项目备注。 3. ZURU QC验货。 | AC14: Emily Wu | AD14: 4.2475 | AE14: =AD14*I14 -> 2548.5 | AF14: 94166-1.23 | AG14: 92107-S001 | AH14: 已入 | AI14: =I14 -> 600 | AO14: =I14 -> 600 | AT14: =I14/4 -> 150 | AU14: =AT14 -> 150 | AV14: =AU14 -> 150 | AW14: =AV14 -> 150 | BF14: =SUM(AT14:BE14)-I14 -> 0 | BJ14: =I14 -> 600 | BL14: MA | BN14: =I14/4 -> 150 | BO14: =I14/4 -> 150 | BP14: =I14/4 -> 150 | BQ14: =I14/4 -> 150 | BR14: =BN14+BO14+BP14+BQ14-I14 -> 0 | BS14: =BN14+BO14+BP14+BQ14+$BS$290 -> 513080 | BT14: =BT13-BN14 -> 129701.25 | BU14: =BU13-BO14 -> 129701.25 | BV14: =BV13-BP14 -> 129709.25 | BW14: =BW13-BQ14 -> 130042.58
A15: 45586 | B15: TJX COMPANIES, INC | C15: 美国 | D15: 4500147795 | E15: TJ MAXX DC#891-160PCS , DC#894-136PCS , DC#896-128PCS , DC#897-248PCS , DC#898-128PCS | F15: 4500147795-70 | G15: 92107-S001 | H15: 摇篮公子 | I15: 800 | J15: 0 | K15: 8 | L15: =I15/K15 -> 100 | M15: 45656 | N15: 45652 | P15: PASS | U15: 1/8出 | W15: 11/4收到 | X15: 无 | Y15: 无 | Z15: 12/6-价格贴纸客供 | AB15: 日期码格式：ZURU INC(BVI) 标准格式 日期：按实际生产日期 Packaging Info: MA UPC包装+价格贴纸，价格贴纸客供。 Remark: 1. 产品和包装上印刷tracking code信息，格式为ZURU常规格式。 2. 分5个DC出货，每款产品每个DC的箱唛资料不同。具体分DC数量，请参考后面行项目备注。 3. ZURU QC验货。 | AC15: Emily Wu | AD15: 4.2475 | AE15: =AD15*I15 -> 3398 | AF15: 94175-1.23 | AG15: 92107-S001 | AH15: 已入 | AI15: =I15 -> 800 | AO15: =I15 -> 800 | AT15: =I15/4 -> 200 | AU15: =AT15 -> 200 | AV15: =AU15 -> 200 | AW15: =AV15 -> 200 | BF15: =SUM(AT15:BE15)-I15 -> 0 | BJ15: =I15 -> 800 | BL15: MA | BN15: =I15/4 -> 200 | BO15: =I15/4 -> 200 | BP15: =I15/4 -> 200 | BQ15: =I15/4 -> 200 | BR15: =BN15+BO15+BP15+BQ15-I15 -> 0 | BS15: =BN15+BO15+BP15+BQ15+$BS$290 -> 513280 | BT15: =BT14-BN15 -> 129501.25 | BU15: =BU14-BO15 -> 129501.25 | BV15: =BV14-BP15 -> 129509.25 | BW15: =BW14-BQ15 -> 129842.58
A16: 45586 | B16: TJX COMPANIES, INC | C16: 美国 | D16: 4500147793 | E16: Marshalls DC#881-168PCS , DC#884-128PCS , DC#886-184PCS , DC#887-152PCS , DC#888-168PCS | F16: 4500147793-90 | G16: 92107-S001 | H16: 摇篮公子 | I16: 800 | J16: 0 | K16: 8 | L16: =I16/K16 -> 100 | M16: 45656 | N16: 45652 | P16: PASS | U16: 1/10出 | W16: 11/4收到 | X16: 无 | Y16: 无 | Z16: 12/6-价格贴纸客供 | AB16: 日期码格式：ZURU INC(BVI) 标准格式 日期：按实际生产日期 Packaging Info: MA UPC包装+价格贴纸，价格贴纸客供。 Remark: 1. 产品和包装上印刷tracking code信息，格式为ZURU常规格式。 2. 分5个DC出货，每款产品每个DC的箱唛资料不同。具体分DC数量，请参考后面行项目备注。 3. ZURU QC验货。 | AC16: Emily Wu | AD16: 4.2475 | AE16: =AD16*I16 -> 3398 | AF16: 94171-1.23 | AG16: 92107-S001 | AH16: 已入 | AI16: =I16 -> 800 | AO16: =I16 -> 800 | AT16: =I16/4 -> 200 | AU16: =AT16 -> 200 | AV16: =AU16 -> 200 | AW16: =AV16 -> 200 | BF16: =SUM(AT16:BE16)-I16 -> 0 | BJ16: =I16 -> 800 | BL16: MA | BN16: =I16/4 -> 200 | BO16: =I16/4 -> 200 | BP16: =I16/4 -> 200 | BQ16: =I16/4 -> 200 | BR16: =BN16+BO16+BP16+BQ16-I16 -> 0 | BS16: =BN16+BO16+BP16+BQ16+$BS$290 -> 513280 | BT16: =BT15-BN16 -> 129301.25 | BU16: =BU15-BO16 -> 129301.25 | BV16: =BV15-BP16 -> 129309.25 | BW16: =BW15-BQ16 -> 129642.58
A17: 45586 | B17: TJX COMPANIES, INC | C17: 美国 | D17: 4500147796 | E17: TJ MAXX DC#891-200PCS , DC#894-168PCS , DC#896-160PCS , DC#897-312PCS , DC#898-160PCS | F17: 4500147796-90 | G17: 92107-S001 | H17: 摇篮公子 | I17: 1000 | J17: 0 | K17: 8 | L17: =I17/K17 -> 125 | M17: 45656 | N17: 45652 | P17: PASS | U17: 1/8出 | W17: 11/4收到 | X17: 无 | Y17: 无 | Z17: 12/6-价格贴纸客供 | AB17: 日期码格式：ZURU INC(BVI) 标准格式 日期：按实际生产日期 Packaging Info: MA UPC包装+价格贴纸，价格贴纸客供。 Remark: 1. 产品和包装上印刷tracking code信息，格式为ZURU常规格式。 2. 分5个DC出货，每款产品每个DC的箱唛资料不同。具体分DC数量，请参考后面行项目备注。 3. ZURU QC验货。 | AC17: Emily Wu | AD17: 4.2475 | AE17: =AD17*I17 -> 4247.5 | AF17: 94170-1.23 | AG17: 92107-S001 | AH17: 已入 | AI17: =I17 -> 1000 | AO17: =I17 -> 1000 | AT17: =I17/4 -> 250 | AU17: =AT17 -> 250 | AV17: =AU17 -> 250 | AW17: =AV17 -> 250 | BF17: =SUM(AT17:BE17)-I17 -> 0 | BJ17: =I17 -> 1000 | BL17: MA | BN17: =I17/4 -> 250 | BO17: =I17/4 -> 250 | BP17: =I17/4 -> 250 | BQ17: =I17/4 -> 250 | BR17: =BN17+BO17+BP17+BQ17-I17 -> 0 | BS17: =BN17+BO17+BP17+BQ17+$BS$290 -> 513480 | BT17: =BT16-BN17 -> 129051.25 | BU17: =BU16-BO17 -> 129051.25 | BV17: =BV16-BP17 -> 129059.25 | BW17: =BW16-BQ17 -> 129392.58
A18: 45604 | B18: ASDA STORES LTD | C18: 英国 | D18: 4500150696 | E18: 2950866103 | F18: 4500150696-70 | G18: 92107SLB-S001 | H18: 摇篮公子88PCS/ctn/卡板 | I18: 968 | J18: 0 | K18: 88 | L18: =I18/K18 -> 11 | M18: 45656 | N18: 45652 | P18: PASS | U18: 1/8出 | W18: 11/29收到 | Y18: 11/29-卡板贴纸 | AB18: 日期码格式：ZURU INC(BVI) 标准格式 日期：按实际生产日期 Packaging Info: 5.92107SLB 92107-S003：MA最新1L UPC包装 UPC#193052064738, 请先检查条码是否正确再安排做货； 4 Assortment Ratio (Ladybug: Giraffe: Butterfly: Elephant)=1:1:1:1 Slip Sheet: 1 PCS/CTN, 22*4=88ctn=88pcs/slip sheet, 一共需要11套slip sheet; Slip Sheet打包好后，需要在正唛、侧唛右下角各贴一张slip sheet贴纸，直接用A4纸打印出来即可，贴纸尺寸160mm width x 140mm high； Slip Sheet尺寸限制为100*115*130CM，一旦实际SLIP SHEET尺寸超过这个尺寸，请提前通知ZURU跟单，需同客人确认才能量产和出货; Remark: 1. 产品及包装需要印UKCA图标，包装需要有ZURU UK LTD/ZURU France地址信息，QC同事请核查，如有问题与跟单确认 2. 产品/包装/外箱都需要打ZURU格式日期码，日期必须为法定工作日。 3. 需要符合欧洲标准不能含有闪粉和微塑料，否则不合法规会有客诉产生 | AC18: Amy Ding | AD18: 392.7986 | AE18: =AD18*I18 -> 380229.04 | AF18: 88944-1.8 | AG18: 92107SLB-S001 | AH18: 已入 | AI18: =I18 -> 968 | AO18: =I18 -> 968 | AT18: =I18/4 -> 242 | AU18: =AT18 -> 242 | AV18: =AU18 -> 242 | AW18: =AV18 -> 242 | BF18: =SUM(AT18:BE18)-I18 -> 0 | BJ18: =I18 -> 968 | BL18: MA | BN18: =I18/4 -> 242 | BO18: =I18/4 -> 242 | BP18: =I18/4 -> 242 | BQ18: =I18/4 -> 242 | BR18: =BN18+BO18+BP18+BQ18-I18 -> 0 | BS18: =BN18+BO18+BP18+BQ18+$BS$290 -> 513448 | BT18: =BT17-BN18 -> 128809.25 | BU18: =BU17-BO18 -> 128809.25 | BV18: =BV17-BP18 -> 128817.25 | BW18: =BW17-BQ18 -> 129150.58
A19: 45586 | B19: TJX COMPANIES, INC | C19: 美国 | D19: 4500147794 | E19: Marshalls DC#881-168PCS , DC#884-128PCS , DC#886-184PCS , DC#887-160PCS , DC#888-160PCS | F19: 4500147794-100 | G19: 92107-S001 | H19: 摇篮公子 | I19: 800 | J19: 0 | K19: 8 | L19: =I19/K19 -> 100 | M19: 45657 | N19: 45653 | P19: PASS | U19: 1/9出 | W19: 11/4收到 | X19: 无 | Y19: 无 | Z19: 12/6-价格贴纸客供 | AB19: 日期码格式：ZURU INC(BVI) 标准格式 日期：按实际生产日期 Packaging Info: MA UPC包装+价格贴纸，价格贴纸客供。 Remark: 1. 产品和包装上印刷tracking code信息，格式为ZURU常规格式。 2. 分5个DC出货，每款产品每个DC的箱唛资料不同。具体分DC数量，请参考后面行项目备注。 3. ZURU QC验货。 | AC19: Emily Wu | AD19: 4.2475 | AE19: =AD19*I19 -> 3398 | AF19: 94176-1.23 | AG19: 92107-S001 | AH19: 已入 | AI19: =I19 -> 800 | AO19: =I19 -> 800 | AT19: =I19/4 -> 200 | AU19: =AT19 -> 200 | AV19: =AU19 -> 200 | AW19: =AV19 -> 200 | BF19: =SUM(AT19:BE19)-I19 -> 0 | BJ19: =I19 -> 800 | BL19: MA | BN19: =I19/4 -> 200 | BO19: =I19/4 -> 200 | BP19: =I19/4 -> 200 | BQ19: =I19/4 -> 200 | BR19: =BN19+BO19+BP19+BQ19-I19 -> 0 | BS19: =BN19+BO19+BP19+BQ19+$BS$290 -> 513280 | BT19: =BT18-BN19 -> 128609.25 | BU19: =BU18-BO19 -> 128609.25 | BV19: =BV18-BP19 -> 128617.25 | BW19: =BW18-BQ19 -> 128950.58
A20: 45586 | B20: TJX COMPANIES, INC | C20: 美国 | D20: 4500147798 | E20: TJ MAXX DC#891-200PCS , DC#894-168PCS , DC#896-160PCS , DC#897-312PCS , DC#898-160PCS | F20: 4500147798-100 | G20: 92107-S001 | H20: 摇篮公子 | I20: 1000 | J20: 0 | K20: 8 | L20: =I20/K20 -> 125 | M20: 45657 | N20: 45653 | P20: PASS | U20: 1/8出 | W20: 11/4收到 | X20: 无 | Y20: 无 | Z20: 12/6-价格贴纸客供 | AB20: 日期码格式：ZURU INC(BVI) 标准格式 日期：按实际生产日期 Packaging Info: MA UPC包装+价格贴纸，价格贴纸客供。 Remark: 1. 产品和包装上印刷tracking code信息，格式为ZURU常规格式。 2. 分5个DC出货，每款产品每个DC的箱唛资料不同。具体分DC数量，请参考后面行项目备注。 3. ZURU QC验货。 | AC20: Emily Wu | AD20: 4.2475 | AE20: =AD20*I20 -> 4247.5 | AF20: 94174-1.23 | AG20: 92107-S001 | AH20: 已入 | AI20: =I20 -> 1000 | AO20: =I20 -> 1000 | AT20: =I20/4 -> 250 | AU20: =AT20 -> 250 | AV20: =AU20 -> 250 | AW20: =AV20 -> 250 | BF20: =SUM(AT20:BE20)-I20 -> 0 | BJ20: =I20 -> 1000 | BL20: MA | BN20: =I20/4 -> 250 | BO20: =I20/4 -> 250 | BP20: =I20/4 -> 250 | BQ20: =I20/4 -> 250 | BR20: =BN20+BO20+BP20+BQ20-I20 -> 0 | BS20: =BN20+BO20+BP20+BQ20+$BS$290 -> 513480 | BT20: =BT19-BN20 -> 128359.25 | BU20: =BU19-BO20 -> 128359.25 | BV20: =BV19-BP20 -> 128367.25 | BW20: =BW19-BQ20 -> 128700.58
A21: 45624 | B21: BIG W | C21: 澳大利亚 | D21: 4500152763 | E21: CUS PO#47779210 SYD | F21: 4500152763-20 | G21: 92107-S001 | H21: 摇篮公子 | I21: 656 | J21: 0 | K21: 8 | L21: =I21/K21 -> 82 | M21: 45657 | N21: 45653 | P21: PASS | U21: 1/3出 | W21: 11/28收到 | Y21: 进口商贴纸翻4500129569 | AB21: 日期码格式：ZURU INC(BVI) 标准格式 日期：按实际生产日期 Tracking Code: Packaging Info: 1. 包装 92107：英文MA包装 (UPC版本，首选1L，无1L可用多L含英语)+1张进口商贴纸，贴纸翻单4500129569 2. 产品和包装上的日期码一致，请按要求在包装上打日期码（进口商贴纸不覆盖日期码） 3. 使用ZURU标准日期码 Remark: 1. 共出4港口(SYD, BNE, MEL, FRE), 不同港口数量信息请见订单行项目，并请参考箱唛资料，港口不同，箱唛资料也不同； 2. 箱唛不可出现任何手写内容（箱数除外），重量与实际一致且不可手写; 3. 此单出澳大利亚，请按澳洲标准生产并满足当地法规要求; 4. 出无闪粉版本，需符合欧洲微塑料法规 | AC21: Christine Liao | AD21: 4.5774 | AE21: =AD21*I21 -> 3002.7744 | AF21: 88832-1.2 | AG21: 92107-S001 | AH21: 已入 | AI21: =I21 -> 656 | AO21: =I21 -> 656 | AT21: =I21/4 -> 164 | AU21: =I21/4 -> 164 | AV21: =I21/4 -> 164 | AW21: =I21/4 -> 164 | BF21: =SUM(AT21:BE21)-I21 -> 0 | BJ21: =I21 -> 656 | BL21: MA | BN21: =I21/4 -> 164 | BO21: =I21/4 -> 164 | BP21: =I21/4 -> 164 | BQ21: =I21/4 -> 164 | BR21: =BN21+BO21+BP21+BQ21-I21 -> 0 | BS21: =BN21+BO21+BP21+BQ21+$BS$290 -> 513136 | BT21: =BT20-BN21 -> 128195.25 | BU21: =BU20-BO21 -> 128195.25 | BV21: =BV20-BP21 -> 128203.25 | BW21: =BW20-BQ21 -> 128536.58
A22: 45624 | B22: BIG W | C22: 澳大利亚 | D22: 4500152763 | E22: CUS PO#47779211 BNE | F22: 4500152763-40 | G22: 92107-S001 | H22: 摇篮公子 | I22: 504 | J22: 0 | K22: 8 | L22: =I22/K22 -> 63 | M22: 45657 | N22: 45653 | P22: PASS | W22: 11/28收到 | Y22: 进口商贴纸翻4500129569 | AB22: 日期码格式：ZURU INC(BVI) 标准格式 日期：按实际生产日期 Tracking Code: Packaging Info: 1. 包装 92107：英文MA包装 (UPC版本，首选1L，无1L可用多L含英语)+1张进口商贴纸，贴纸翻单4500129569 2. 产品和包装上的日期码一致，请按要求在包装上打日期码（进口商贴纸不覆盖日期码） 3. 使用ZURU标准日期码 Remark: 1. 共出4港口(SYD, BNE, MEL, FRE), 不同港口数量信息请见订单行项目，并请参考箱唛资料，港口不同，箱唛资料也不同； 2. 箱唛不可出现任何手写内容（箱数除外），重量与实际一致且不可手写; 3. 此单出澳大利亚，请按澳洲标准生产并满足当地法规要求; 4. 出无闪粉版本，需符合欧洲微塑料法规 | AC22: Christine Liao | AD22: 4.5774 | AE22: =AD22*I22 -> 2307.0096 | AF22: 88853-1.3 | AG22: 92107-S001 | AH22: 已入 | AI22: =I22 -> 504 | AO22: =I22 -> 504 | AT22: =I22/4 -> 126 | AU22: =I22/4 -> 126 | AV22: =I22/4 -> 126 | AW22: =I22/4 -> 126 | BF22: =SUM(AT22:BE22)-I22 -> 0 | BJ22: =I22 -> 504 | BL22: MA | BN22: =I22/4 -> 126 | BO22: =I22/4 -> 126 | BP22: =I22/4 -> 126 | BQ22: =I22/4 -> 126 | BR22: =BN22+BO22+BP22+BQ22-I22 -> 0 | BS22: =BN22+BO22+BP22+BQ22+$BS$290 -> 512984 | BT22: =BT21-BN22 -> 128069.25 | BU22: =BU21-BO22 -> 128069.25 | BV22: =BV21-BP22 -> 128077.25 | BW22: =BW21-BQ22 -> 128410.58
A23: 45624 | B23: BIG W | C23: 澳大利亚 | D23: 4500152763 | E23: CUS PO#47779212 MEL | F23: 4500152763-60 | G23: 92107-S001 | H23: 摇篮公子 | I23: 504 | J23: 0 | K23: 8 | L23: =I23/K23 -> 63 | M23: 45657 | N23: 45653 | P23: PASS | U23: 1/4出 | W23: 11/28收到 | Y23: 进口商贴纸翻4500129569 | AB23: 日期码格式：ZURU INC(BVI) 标准格式 日期：按实际生产日期 Tracking Code: Packaging Info: 1. 包装 92107：英文MA包装 (UPC版本，首选1L，无1L可用多L含英语)+1张进口商贴纸，贴纸翻单4500129569 2. 产品和包装上的日期码一致，请按要求在包装上打日期码（进口商贴纸不覆盖日期码） 3. 使用ZURU标准日期码 Remark: 1. 共出4港口(SYD, BNE, MEL, FRE), 不同港口数量信息请见订单行项目，并请参考箱唛资料，港口不同，箱唛资料也不同； 2. 箱唛不可出现任何手写内容（箱数除外），重量与实际一致且不可手写; 3. 此单出澳大利亚，请按澳洲标准生产并满足当地法规要求; 4. 出无闪粉版本，需符合欧洲微塑料法规 | AC23: Christine Liao | AD23: 4.5774 | AE23: =AD23*I23 -> 2307.0096 | AF23: 88887-1.6 | AG23: 92107-S001 | AH23: 已入 | AI23: =I23 -> 504 | AO23: =I23 -> 504 | AT23: =I23/4 -> 126 | AU23: =I23/4 -> 126 | AV23: =I23/4 -> 126 | AW23: =I23/4 -> 126 | BF23: =SUM(AT23:BE23)-I23 -> 0 | BJ23: =I23 -> 504 | BL23: MA | BN23: =I23/4 -> 126 | BO23: =I23/4 -> 126 | BP23: =I23/4 -> 126 | BQ23: =I23/4 -> 126 | BR23: =BN23+BO23+BP23+BQ23-I23 -> 0 | BS23: =BN23+BO23+BP23+BQ23+$BS$290 -> 512984 | BT23: =BT22-BN23 -> 127943.25 | BU23: =BU22-BO23 -> 127943.25 | BV23: =BV22-BP23 -> 127951.25 | BW23: =BW22-BQ23 -> 128284.58
A24: 45624 | B24: BIG W | C24: 澳大利亚 | D24: 4500152763 | E24: CUS PO#47779213 FRE | F24: 4500152763-80 | G24: 92107-S001 | H24: 摇篮公子 | I24: 176 | J24: 0 | K24: 8 | L24: =I24/K24 -> 22 | M24: 45657 | N24: 45653 | P24: PASS | U24: 1/4出 | W24: 11/28收到 | Y24: 进口商贴纸翻4500129569 | AB24: 日期码格式：ZURU INC(BVI) 标准格式 日期：按实际生产日期 Tracking Code: Packaging Info: 1. 包装 92107：英文MA包装 (UPC版本，首选1L，无1L可用多L含英语)+1张进口商贴纸，贴纸翻单4500129569 2. 产品和包装上的日期码一致，请按要求在包装上打日期码（进口商贴纸不覆盖日期码） 3. 使用ZURU标准日期码 Remark: 1. 共出4港口(SYD, BNE, MEL, FRE), 不同港口数量信息请见订单行项目，并请参考箱唛资料，港口不同，箱唛资料也不同； 2. 箱唛不可出现任何手写内容（箱数除外），重量与实际一致且不可手写; 3. 此单出澳大利亚，请按澳洲标准生产并满足当地法规要求; 4. 出无闪粉版本，需符合欧洲微塑料法规 | AC24: Christine Liao | AD24: 4.5774 | AE24: =AD24*I24 -> 805.6224 | AF24: 88867-1.4 | AG24: 92107-S001 | AH24: 已入 | AI24: =I24 -> 176 | AO24: =I24 -> 176 | AT24: =I24/4 -> 44 | AU24: =I24/4 -> 44 | AV24: =I24/4 -> 44 | AW24: =I24/4 -> 44 | BF24: =SUM(AT24:BE24)-I24 -> 0 | BJ24: =I24 -> 176 | BL24: MA | BN24: =I24/4 -> 44 | BO24: =I24/4 -> 44 | BP24: =I24/4 -> 44 | BQ24: =I24/4 -> 44 | BR24: =BN24+BO24+BP24+BQ24-I24 -> 0 | BS24: =BN24+BO24+BP24+BQ24+$BS$290 -> 512656 | BT24: =BT23-BN24 -> 127899.25 | BU24: =BU23-BO24 -> 127899.25 | BV24: =BV23-BP24 -> 127907.25 | BW24: =BW23-BQ24 -> 128240.58
A25: 45604 | B25: THE ENTERTAINER | C25: 英国 | D25: 4500150141 | E25: 4500150141-1 | F25: 4500150141-20 | G25: 92107-S001 | H25: 摇篮公子 | I25: 2800 | J25: 0 | K25: 8 | L25: =I25/K25 -> 350 | M25: 45657 | N25: 45653 | P25: PASS | U25: 1/4出 | W25: 11/14收到 | Y25: 客户EAN条码贴翻4500148687 | AB25: 日期码格式：ZURU INC(BVI) 标准格式 日期：按实际生产日期 Packaging Info: 92107：MA最新1L-UPC配套包装+客户EAN条码贴一张覆盖ZURU 原条码，条码贴翻订单4500148687 4 Assortment Ratio (Ladybug: Giraffe: Butterfly: Elephant)=1:1:1:1 Remark: *MA版本按工厂现有最新库存即可，订单出英国，请注意检查产品及包装应带UKCA图标，包装显示ZURU UK LTD信息，QC同事请查核，如有问题与跟单确认。 *生产日期按实际（法定工作日），按ZURU标准格式即可 ，但是请知悉包装日期码需要早于或者等于外箱日期码 ，不能晚于外箱日期码 *请注意所有订单都需要经过ZURU QC验货并且通过后方可出货 *条码以订单显示为准 ，请安排生产前先核对 ，有问题请提出。 *所有产品按符合欧洲标准走货，需要是不含微塑料版本 。 *涉及到硼的，如可选择情况下应使用低硼版本 （slime 类别低硼一般低于300ppm)，无选择的应与跟单复核再安排 。 | AC25: Sherry Lu | AD25: 4.0808 | AE25: =AD25*I25 -> 11426.24 | AF25: 88877-1.4 | AG25: 92107-S001 | AH25: 已入 | AI25: =I25 -> 2800 | AP25: =I25 -> 2800 | AT25: =I25/4 -> 700 | AU25: =I25/4 -> 700 | AV25: =I25/4 -> 700 | AW25: =I25/4 -> 700 | BF25: =SUM(AT25:BE25)-I25 -> 0 | BJ25: =I25 -> 2800 | BL25: MA | BN25: =I25/4 -> 700 | BO25: =I25/4 -> 700 | BP25: =I25/4 -> 700 | BQ25: =I25/4 -> 700 | BR25: =BN25+BO25+BP25+BQ25-I25 -> 0 | BS25: =BN25+BO25+BP25+BQ25+$BS$290 -> 515280 | BT25: =BT24-BN25 -> 127199.25 | BU25: =BU24-BO25 -> 127199.25 | BV25: =BV24-BP25 -> 127207.25 | BW25: =BW24-BQ25 -> 127540.58
A26: 45618 | B26: CRG | C26: 哥斯达黎加 | D26: 4500152087 | E26: ZU01-25 | F26: 4500152087-120 | G26: 92107-S001 | H26: 摇篮公子 | I26: 504 | J26: 0 | K26: 8 | L26: =I26/K26 -> 63 | M26: 45660 | N26: 45656 | P26: PASS | U26: 1/8出 | W26: 11/27收到 | Y26: 12/10-进口商贴纸 | AB26: 日期码格式：ZURU INC(BVI) 标准格式 日期：按实际生产日期 Packaging Info: 92107:MA 1L包装+进口商贴纸+箱唛 Remark: | AC26: Ava Liang | AD26: 4.2475 | AE26: =AD26*I26 -> 2140.74 | AF26: 88961-1.9 | AG26: 92107-S001 | AH26: 已入 | AI26: =I26 -> 504 | AP26: =I26 -> 504 | AT26: =I26/4 -> 126 | AU26: =I26/4 -> 126 | AV26: =I26/4 -> 126 | AW26: =I26/4 -> 126 | BF26: =SUM(AT26:BE26)-I26 -> 0 | BJ26: =I26 -> 504 | BL26: MA | BN26: =I26/4 -> 126 | BO26: =I26/4 -> 126 | BP26: =I26/4 -> 126 | BQ26: =I26/4 -> 126 | BR26: =BN26+BO26+BP26+BQ26-I26 -> 0 | BS26: =BN26+BO26+BP26+BQ26+$BS$290 -> 512984 | BT26: =BT25-BN26 -> 127073.25 | BU26: =BU25-BO26 -> 127073.25 | BV26: =BV25-BP26 -> 127081.25 | BW26: =BW25-BQ26 -> 127414.58
A27: 45625 | B27: TJX UK | C27: 英国 | D27: 4500152937 | E27: PO#50343349 | F27: 4500152937-60 | G27: 92107-S001 | H27: 摇篮公子 | I27: 600 | J27: 0 | K27: 8 | L27: =I27/K27 -> 75 | M27: 45660 | N27: 45656 | P27: PASS | U27: 1/10出 | W27: 12/5收到 | Y27: 12/6-客供价格贴纸 | AB27: 日期码格式：ZURU INC(BVI) 标准格式 日期：按实际生产日期 Packaging Info: TJX UK: PO#50343294(9283) <(>&<)> PO#50343296(9258) <(>&<)> PO#50343296(9281) <(>&<)> PO#50343305(9298) <(>&<)> PO#50343349(7132) <(>&<)> PO#503 43349(92107) <(>&<)> PO#50343392(9279) <(>&<)> PO#50343399(9279) 6) 92107: MA3L (9Lwanrning) B版收缩膜+其他最新MA配套包装+1张客供价格贴纸 8) 最迟验货时间不得晚于1/4 Remark: 1. 出往UK的产品+包装务必打上UKCA logo ，否则客人会退货且当地会有罚款； 2. 订单必须经过ZURU QC验货并且通过后方可出货； 3. 订单每行对应客人不同的PO， 箱唛也有不同，做货的时候请分开堆放； 4. 订单每行对应客人不同的PO，即同款item的价格贴纸都不相同，请注意收到贴纸后不要弄混!（客人PO号请参考PO最后一栏remark）； 5. 价格贴纸位置为产品正面右上角，不能遮住产品信息，大货生产前，请把贴纸位置先发给跟单确认 6. 涉及到相关款式会有闪粉的或 者微塑料的，请统一默认出无闪粉或者不含微塑料 版本; 7. 外箱封箱必须是工字型封箱方式； | AC27: Zoe Chen | AD27: 4.2475 | AE27: =AD27*I27 -> 2548.5 | AF27: 88937-1.8 | AG27: 92107-S001-3L | AH27: 已入 | AL27: =I27 -> 600 | AP27: =I27 -> 600 | AT27: =I27/4 -> 150 | AU27: =I27/4 -> 150 | AV27: =I27/4 -> 150 | AW27: =I27/4 -> 150 | BF27: =SUM(AT27:BE27)-I27 -> 0 | BJ27: =I27 -> 600 | BL27: MA | BN27: =I27/4 -> 150 | BO27: =I27/4 -> 150 | BP27: =I27/4 -> 150 | BQ27: =I27/4 -> 150 | BR27: =BN27+BO27+BP27+BQ27-I27 -> 0 | BS27: =BN27+BO27+BP27+BQ27+$BS$290 -> 513080 | BT27: =BT26-BN27 -> 126923.25 | BU27: =BU26-BO27 -> 126923.25 | BV27: =BV26-BP27 -> 126931.25 | BW27: =BW26-BQ27 -> 127264.58
A28: 45625 | B28: TJX UK c/o TJX Distribution Ltd & C | C28: 德国 | D28: 4500152906 | E28: TJX Europe(DE): PO#55343920 | F28: 4500152906-90 | G28: 92107-S001 | H28: 摇篮公子 | I28: 704 | J28: 0 | K28: 8 | L28: =I28/K28 -> 88 | M28: 45660 | N28: 45656 | P28: PASS | U28: 1/9出 | W28: 12/5收到 | Y28: 12/6-客供价格贴纸+含波兰语警告语翻4500150830 | AB28: 日期码格式：ZURU INC(BVI) 标准格式 日期：按实际生产日期 Packaging Info: TJX Europe(DE): PO#55343895(9283) <(>&<)> PO#55343898(9258) <(>&<)> PO#55343898(9281) <(>&<)> PO#55343901(9281) <(>&<)> PO#55343906(9298) <(>& <)> PO#55343909(9298) <(>&<)> PO#55343918(7132) <(>&<)> PO#55343920(7132) <(>&<)> PO#55343920(92107) <(>&<)> PO#55343844(9279) <(>&<)> PO#553438 77(9279) 6) 92107: MA3L (9Lwanrning) B版收缩膜+其他最新MA配套包装+1张客供价格贴纸+1张贴纸（含波兰语警告语) 8) 最迟验货时间不得晚于1/4 Remark: 1. 出往UK的产品+包装务必打上UKCA logo ，否则客人会退货且当地会有罚款； 2.订单必须经过ZURU QC验货并且通过后方可出货； 3. 订单每行对应客人不同的PO， 箱唛也有不同，做货的时候请分开堆放； 4. 订单每行对应客人不同的PO，即同款item的价格贴纸都不相同，请注意收到贴纸后不要弄混!（客人PO号请参考PO最后一栏remark）； 5. 价格贴纸位置为产品正面右上角，不能遮住产品信息，大货生产前，请把贴纸位置先发给跟单确认 6. 涉及到相关款式会有闪粉的或者微塑料的，请统一默认出无闪粉或者不含微塑料版本; 7. 外箱封箱必须是工字型封箱方式； | AC28: Zoe Chen | AD28: 4.2475 | AE28: =AD28*I28 -> 2990.24 | AF28: 88936-1.8 | AG28: 92107-S001-3L | AH28: 已入 | AL28: =I28 -> 704 | AP28: =I28 -> 704 | AT28: =I28/4 -> 176 | AU28: =I28/4 -> 176 | AV28: =I28/4 -> 176 | AW28: =I28/4 -> 176 | BF28: =SUM(AT28:BE28)-I28 -> 0 | BJ28: =I28 -> 704 | BL28: MA | BN28: =I28/4 -> 176 | BO28: =I28/4 -> 176 | BP28: =I28/4 -> 176 | BQ28: =I28/4 -> 176 | BR28: =BN28+BO28+BP28+BQ28-I28 -> 0 | BS28: =BN28+BO28+BP28+BQ28+$BS$290 -> 513184 | BT28: =BT27-BN28 -> 126747.25 | BU28: =BU27-BO28 -> 126747.25 | BV28: =BV27-BP28 -> 126755.25 | BW28: =BW27-BQ28 -> 127088.58
A29: 45623 | B29: MEIJER | C29: 美国 | D29: 4500152685 | E29: 216641089 | F29: 4500152685-10 | G29: 92107-S005 | H29: 摇篮公子 | I29: 852 | J29: 0 | K29: 2 | L29: =I29/K29 -> 426 | M29: 45662 | N29: 45658 | P29: PASS | U29: 收到SO | W29: 11/28收到 | Y29: 无 | AB29: 日期码格式：ZURU INC(BVI) 标准格式 日期：按实际生产日期 Packaging Info: 1. MA 1L 包装 2. 客人指定箱唛排版 Remark: 出货前 Zuru QC 验货 | AC29: Sophia Zhou | AD29: 4.7334 | AE29: =AD29*I29 -> 4032.8568 | AF29: 88932-1.8 | AG29: 92107-S005 | AH29: 已入 | AI29: =I29 -> 852 | AP29: =I29 -> 852 | AT29: =I29/4 -> 213 | AU29: =I29/4 -> 213 | AV29: =I29/4 -> 213 | AW29: =I29/4 -> 213 | BF29: =SUM(AT29:BE29)-I29 -> 0 | BJ29: =I29 -> 852 | BL29: MA | BN29: =I29/4 -> 213 | BO29: =I29/4 -> 213 | BP29: =I29/4 -> 213 | BQ29: =I29/4 -> 213 | BR29: =BN29+BO29+BP29+BQ29-I29 -> 0 | BS29: =BN29+BO29+BP29+BQ29+$BS$290 -> 513332 | BT29: =BT28-BN29 -> 126534.25 | BU29: =BU28-BO29 -> 126534.25 | BV29: =BV28-BP29 -> 126542.25 | BW29: =BW28-BQ29 -> 126875.58
A30: 45623 | B30: MEIJER | C30: 美国 | D30: 4500152678 | E30: 216641085 | F30: 4500152678-10 | G30: 92107-S005 | H30: 摇篮公子 | I30: 1548 | J30: 0 | K30: 2 | L30: =I30/K30 -> 774 | M30: 45662 | N30: 45658 | P30: PASS | U30: 收到SO | W30: 11/28收到 | Y30: 无 | AB30: 日期码格式：ZURU INC(BVI) 标准格式 日期：按实际生产日期 Packaging Info: 1. MA 1L 包装 2. 客人指定箱唛排版 Remark: 出货前 Zuru QC 验货 | AC30: Sophia Zhou | AD30: 4.7221 | AE30: =AD30*I30 -> 7309.8108 | AF30: 88931-1.8 | AG30: 92107-S005 | AH30: 已入 | AI30: =I30 -> 1548 | AP30: =I30 -> 1548 | AT30: =I30/4 -> 387 | AU30: =I30/4 -> 387 | AV30: =I30/4 -> 387 | AW30: =I30/4 -> 387 | BF30: =SUM(AT30:BE30)-I30 -> 0 | BJ30: =I30 -> 1548 | BL30: MA | BN30: =I30/4 -> 387 | BO30: =I30/4 -> 387 | BP30: =I30/4 -> 387 | BQ30: =I30/4 -> 387 | BR30: =BN30+BO30+BP30+BQ30-I30 -> 0 | BS30: =BN30+BO30+BP30+BQ30+$BS$290 -> 514028 | BT30: =BT29-BN30 -> 126147.25 | BU30: =BU29-BO30 -> 126147.25 | BV30: =BV29-BP30 -> 126155.25 | BW30: =BW29-BQ30 -> 126488.58
A31: 45604 | B31: AEON TOPVALU (HONG KONG) CO.,LTD | C31: 柬埔寨 | D31: 4500150770 | E31: SDN24-0024 | F31: 4500150770-10 | G31: 92107-S001 | H31: 摇篮公子 | I31: 256 | J31: 0 | K31: 8 | L31: =I31/K31 -> 32 | M31: 45663 | N31: 45659 | P31: PASS | U31: 1/15出 | W31: 11/11收到 | Y31: 无 | AB31: 日期码格式：ZURU INC(BVI) 标准格式 日期：按实际生产日期 Packaging Info: MA PKG, 优先1L Remark: 出柬埔寨 | AC31: Doris Shou | AD31: 4.3169 | AE31: =AD31*I31 -> 1105.1264 | AF31: 94063-1.16 | AG31: 92107-S001 | AH31: 已入 | AI31: =I31 -> 256 | AP31: =I31 -> 256 | AT31: =I31/4 -> 64 | AU31: =AT31 -> 64 | AV31: =AU31 -> 64 | AW31: =AV31 -> 64 | BF31: =SUM(AT31:BE31)-I31 -> 0 | BJ31: =I31 -> 256 | BL31: MA | BN31: =I31/4 -> 64 | BO31: =I31/4 -> 64 | BP31: =I31/4 -> 64 | BQ31: =I31/4 -> 64 | BR31: =BN31+BO31+BP31+BQ31-I31 -> 0 | BS31: =BN31+BO31+BP31+BQ31+$BS$290 -> 512736 | BT31: =BT30-BN31 -> 126083.25 | BU31: =BU30-BO31 -> 126083.25 | BV31: =BV30-BP31 -> 126091.25 | BW31: =BW30-BQ31 -> 126424.58
A32: 45623 | B32: AMAZON.COM.DEDC,LLC | C32: 美国 | D32: 4500152379 | E32: 5NFG96GC | F32: 4500152379-230 | G32: 92107D-S001 | H32: 蝴蝶 | I32: 240 | J32: 0 | K32: 8 | L32: =I32/K32 -> 30 | M32: 45664 | N32: 45660 | P32: PASS | U32: 2/7出 | W32: 11/27收到 | Y32: UPC贴纸翻450013436 | Z32: 12/20-外箱贴纸 | AB32: 日期码格式： 标准格式 日期：按实际生产日期 Packaging Info: #92107 MA 1L UPC版本+ UPC贴纸跟返单4500134367；92107A:193052066817, 92107D:193052066831, 92107E:193052066848; Remark: 1. Amazon FOB订单，出口US。 2. 日期码使用ZURU标准版本。 3. 如果大货有要求入邮包盒，则对应的邮包盒上面要打上日期码。 4. 箱尺寸要求：外箱最长边不能超过25" （超过了，case pack只能为1），不符合要求的大货，一律不接受。 5. 外箱箱唛要求： ①外箱正面印ZURU Logo+SSCC Label（客供贴纸，由跟单订购)。关于 SSCC Label 请注意： SSCC Label 显示的是客人自己的item#。每一张SSCC label 都是唯一且有不同流水及条码的，没有损耗，绝对不可贴错 。如果贴错或损坏任何一张，都会导致全 部都错，千万要注意！ SSCC Label 必须贴在外箱正面的正中间位置（贴一面即可），并且贴纸离外箱边距必须至少3cm(可以覆盖Logo<(>&<)>箱唛)，否则会影响到客户那边仓库的扫描识 别。 ②外箱侧面印item#（订单上显示的SKU#)+carton size(以工厂实际尺寸为准,单位: inch) +MADE IN CHINA,日期使用ZURU 标准版本。 6. 装柜要求：按照客户PO# 装柜/箱号顺序装柜，跟单会提前给到装柜计划。 在大货生产/仓库存放时，请留意该装柜要求，以便装柜时不混乱（避免装错/装漏/找不到货号等）。 | AC32: Kelly Shen | AD32: 4.2589 | AE32: =AD32*I32 -> 1022.136 | AF32: 94201-2.10 | AG32: 92107D-S001 | AH32: 已入 | AI32: =I32 -> 240 | AP32: =I32 -> 240 | AX32: =I32 -> 240 | BF32: =SUM(AT32:BE32)-I32 -> 0 | BJ32: =I32 -> 240 | BL32: MA | BN32: =I32 -> 240 | BR32: =BN32+BO32+BP32+BQ32-I32 -> 0 | BS32: =BN32+BO32+BP32+BQ32+$BS$290 -> 512720 | BT32: =BT31-BN32 -> 125843.25 | BU32: =BU31-BO32 -> 126083.25 | BV32: =BV31-BP32 -> 126091.25 | BW32: =BW31-BQ32 -> 126424.58
A33: 45623 | B33: AMAZON.COM.DEDC,LLC | C33: 美国 | D33: 4500152379 | E33: 2LWM8QCA | F33: 4500152379-240 | G33: 92107D-S001 | H33: 蝴蝶 | I33: 208 | J33: 0 | K33: 8 | L33: =I33/K33 -> 26 | M33: 45664 | N33: 45660 | P33: PASS | U33: 2/7出 | W33: 11/27收到 | Y33: UPC贴纸翻450013436 | Z33: 12/20-外箱贴纸 | AB33: 日期码格式： 标准格式 日期：按实际生产日期 Packaging Info: #92107 MA 1L UPC版本+ UPC贴纸跟返单4500134367；92107A:193052066817, 92107D:193052066831, 92107E:193052066848; Remark: 1. Amazon FOB订单，出口US。 2. 日期码使用ZURU标准版本。 3. 如果大货有要求入邮包盒，则对应的邮包盒上面要打上日期码。 4. 箱尺寸要求：外箱最长边不能超过25" （超过了，case pack只能为1），不符合要求的大货，一律不接受。 5. 外箱箱唛要求： ①外箱正面印ZURU Logo+SSCC Label（客供贴纸，由跟单订购)。关于 SSCC Label 请注意： SSCC Label 显示的是客人自己的item#。每一张SSCC label 都是唯一且有不同流水及条码的，没有损耗，绝对不可贴错 。如果贴错或损坏任何一张，都会导致全 部都错，千万要注意！ SSCC Label 必须贴在外箱正面的正中间位置（贴一面即可），并且贴纸离外箱边距必须至少3cm(可以覆盖Logo<(>&<)>箱唛)，否则会影响到客户那边仓库的扫描识 别。 ②外箱侧面印item#（订单上显示的SKU#)+carton size(以工厂实际尺寸为准,单位: inch) +MADE IN CHINA,日期使用ZURU 标准版本。 6. 装柜要求：按照客户PO# 装柜/箱号顺序装柜，跟单会提前给到装柜计划。 在大货生产/仓库存放时，请留意该装柜要求，以便装柜时不混乱（避免装错/装漏/找不到货号等）。 | AC33: Kelly Shen | AD33: 4.2589 | AE33: =AD33*I33 -> 885.8512 | AF33: 94201-2.10 | AG33: 92107D-S001 | AH33: 已入 | AI33: =I33 -> 208 | AP33: =I33 -> 208 | AX33: =I33 -> 208 | BF33: =SUM(AT33:BE33)-I33 -> 0 | BJ33: =I33 -> 208 | BL33: MA | BN33: =I33 -> 208 | BR33: =BN33+BO33+BP33+BQ33-I33 -> 0 | BS33: =BN33+BO33+BP33+BQ33+$BS$290 -> 512688 | BT33: =BT32-BN33 -> 125635.25 | BU33: =BU32-BO33 -> 126083.25 | BV33: =BV32-BP33 -> 126091.25 | BW33: =BW32-BQ33 -> 126424.58
A34: 45623 | B34: AMAZON.COM.DEDC,LLC | C34: 美国 | D34: 4500152657 | E34: 5WZ1EI7C | F34: 4500152657-60 | G34: 92107D-S001 | H34: 蝴蝶 | I34: 760 | J34: 0 | K34: 8 | L34: =I34/K34 -> 95 | M34: 45664 | N34: 45660 | P34: PASS | U34: 1/15-1/20出 | W34: 11/27收到 | Y34: UPC贴纸翻450013436 | Z34: 12/20-外箱贴纸 | AB34: 日期码格式： 标准格式 日期：按实际生产日期 Packaging Info: #92107 MA 1L UPC版本+ UPC贴纸跟返单4500134367；92107A:193052066817, 92107D:193052066831, 92107E:193052066848; Remark: 1. Amazon FOB订单，出口US。 2. 日期码使用ZURU标准版本。 3. 如果大货有要求入邮包盒，则对应的邮包盒上面要打上日期码。 4. 箱尺寸要求：外箱最长边不能超过25" （超过了，case pack只能为1），不符合要求的大货，一律不接受。 5. 外箱箱唛要求： ①外箱正面印ZURU Logo+SSCC Label（客供贴纸，由跟单订购)。关于 SSCC Label 请注意： SSCC Label 显示的是客人自己的item#。每一张SSCC label 都是唯一且有不同流水及条码的，没有损耗，绝对不可贴错 。如果贴错或损坏任何一张，都会导致全 部都错，千万要注意！ SSCC Label 必须贴在外箱正面的正中间位置（贴一面即可），并且贴纸离外箱边距必须至少3cm(可以覆盖Logo<(>&<)>箱唛)，否则会影响到客户那边仓库的扫描识 别。 ②外箱侧面印item#（订单上显示的SKU#)+carton size(以工厂实际尺寸为准,单位: inch) +MADE IN CHINA,日期使用ZURU 标准版本。 6. 装柜要求：按照客户PO# 装柜/箱号顺序装柜，跟单会提前给到装柜计划。 在大货生产/仓库存放时，请留意该装柜要求，以便装柜时不混乱（避免装错/装漏/找不到货号等）。 | AC34: Kelly Shen | AD34: 4.2475 | AE34: =AD34*I34 -> 3228.1 | AF34: 94229-2.12 | AG34: 92107D-S001 | AH34: 已入 | AI34: =I34 -> 760 | AP34: =I34 -> 760 | AX34: =I34 -> 760 | BF34: =SUM(AT34:BE34)-I34 -> 0 | BJ34: =I34 -> 760 | BL34: MA | BN34: =I34 -> 760 | BR34: =BN34+BO34+BP34+BQ34-I34 -> 0 | BS34: =BN34+BO34+BP34+BQ34+$BS$290 -> 513240 | BT34: =BT33-BN34 -> 124875.25 | BU34: =BU33-BO34 -> 126083.25 | BV34: =BV33-BP34 -> 126091.25 | BW34: =BW33-BQ34 -> 126424.58
A35: 45623 | B35: HEB GROCERY COMPANY, LP | C35: 美国 | D35: 4500152429 | E35: PO#60X356498 | F35: 4500152429-60 | G35: 92107-S005 | H35: 摇篮公子 | I35: 590 | J35: 0 | K35: 2 | L35: =I35/K35 -> 295 | M35: 45665 | N35: 45661 | O35: 1/9第三方 | P35: PASS | U35: 1/16出 | W35: 11/27收到 | Y35: 无 | AB35: 日期码格式：ZURU INC(BVI) 标准格式 日期：按实际生产日期 Packaging Info: 1. ZURU MA UPC版本，出口美国. Remark: 2. 日期跟踪码：ZURU标准格式日期码，产品包装及产品本身都必须有ZURU标准格式日期码，并且确保两者信息保持一致(请自行调整具体年月日生产期，但不能为周末）。 针对你们目前没办法保持日期码一致的做法是： * 大货：可以按照实际生产的日期码打，毛绒布标和蛋壳上的日期码格式和时间这次特例可以不保持一致出货；但到时需手动贴一套公仔的布标贴纸，使布标跟蛋壳 日期码格式和时间一样，拍照给我们发给实验室review 日期码，让实验室知道订单大货出的日期码格式和时间是跟抽板指定款的保持一样。 * 指定款抽板：需手动贴布标贴纸，保证布标跟蛋壳上的日期码格式和时间都一样，且这个时间要跟大货的时间一样。 3. 大货样 4. 验货+ 抽板 （同一天进行） 预约1月9日第三方（利丰）到工厂做100%大货现场验货和抽板，验货需打印EPM出来跟客户回签样板供第三方验货参考。 PS:EPM是跟单提供。 抽板： 因#92107的ZURU测试报告上被客户指定实验室发现产品和产品包装上的日期码不一致，所以这款寄样给实验室的是按照 利丰验货员现场针对指定款随机抽板6PCS（须带包装）;其他利丰验货员现场针对指定款随机抽板6PCS。 工厂需把抽板寄到以下MTS 地址做测试，测试通过后才能出货；如产品有油漆的工厂需额外准备5G/色的油漆涂在同材质胶件上(面积类似A4纸大小)一并寄出； 实验室收件地址： 东莞现代产品整理服务有限公司（MTS） 广东省东莞市寮步镇新旧围村良平路76号 收件人：Cherry Wang （汪单） Tel: +86 769- 8112 0818 ext.893 抽板有随样文件TRF（跟单提供），工厂在寄样时打印出来放纸箱内随样寄走。 5. 出货配比：ZURU 标版配比 6. ZURU QA 验货时需拍齐每款角色的产品和产品包装上的日期码照片（供实验室review） | AC35: Elsa Zheng | AD35: 4.3446 | AE35: =AD35*I35 -> 2563.314 | AF35: 94152-1.22 | AG35: 92107-S005 | AH35: 已入 | AJ35: =I35 -> 590 | AP35: =I35 -> 590 | AX35: =I35/4 -> 147.5 | AY35: =I35/4 -> 147.5 | AZ35: =AY35 -> 147.5 | BA35: =I35/4 -> 147.5 | BF35: =SUM(AT35:BE35)-I35 -> 0 | BJ35: =I35 -> 590 | BL35: MA | BN35: =I35/4 -> 147.5 | BO35: =I35/4 -> 147.5 | BP35: =I35/4 -> 147.5 | BQ35: =I35/4 -> 147.5 | BR35: =BN35+BO35+BP35+BQ35-I35 -> 0 | BS35: =BN35+BO35+BP35+BQ35+$BS$290 -> 513070 | BT35: =BT34-BN35 -> 124727.75 | BU35: =BU34-BO35 -> 125935.75 | BV35: =BV34-BP35 -> 125943.75 | BW35: =BW34-BQ35 -> 126277.08
A36: 45645 | D36: ZMPO24972 | G36: 92107-S001 | H36: 摇篮公子 | I36: 120 | J36: 0 | K36: 8 | L36: =I36/K36 -> 15 | M36: 45665 | N36: 45661 | P36: PASS | W36: 周转箱 | Y36: 无 | AB36: Remark：大货最新版本/请用大货标准箱装箱/箱唛请参照邮件附件 备注： 收到样品订单后尽快安排 ，注意样板品质质量要求要高于大货品质要求 ，送货时必须要附带送货单(没有送货单和QC检验合格报告的仓库一律拒绝收货)，请知悉，谢谢！ | AC36: Angus | AG36: 92107-S001 | AH36: 已入 | AJ36: =I36 -> 120 | AP36: =I36 -> 120 | AX36: =I36/4 -> 30 | AY36: =AX36 -> 30 | AZ36: =AX36 -> 30 | BA36: =AX36 -> 30 | BJ36: =I36 -> 120 | BL36: MA | BN36: =I36/4 -> 30 | BO36: =I36/4 -> 30 | BP36: =I36/4 -> 30 | BQ36: =I36/4 -> 30 | BR36: =BN36+BO36+BP36+BQ36-I36 -> 0 | BS36: =BN36+BO36+BP36+BQ36+$BS$290 -> 512600 | BT36: =BT35-BN36 -> 124697.75 | BU36: =BU35-BO36 -> 125905.75 | BV36: =BV35-BP36 -> 125913.75 | BW36: =BW35-BQ36 -> 126247.08
A37: 45615 | B37: VM INTERNATIONAL | C37: 美国 | D37: 4500151779 | F37: 4500151779-30 | G37: 92107-S001 | H37: 摇篮公子 | I37: 640 | J37: 0 | K37: 8 | L37: 80 | M37: 45666 | N37: 45663 | P37: PASS | U37: 1/13出 | W37: 12/11收到 | Y37: 无 | AB37: 日期码格式：ZURU INC(BVI) 标准格式 日期：按实际生产日期 Packaging Info: 1.ZURU 标准日期码格式， 2.无第三方测试和验货，ZURU 内部QC验货即可出货 Remark: 3. 优先 MA 1L UPC包装; 4. 纸箱印ZURU LOGO，出口美国； | AC37: Iris Yuan | AD37: 4.2475 | AE37: 2718.4 | AF37: 94112-1.18 | AG37: 92107-S001 | AH37: 已入 | AI37: =I37 -> 640 | AO37: =I37 -> 640 | AT37: =I37/4 -> 160 | AU37: =AT37 -> 160 | AV37: =AU37 -> 160 | AW37: =AV37 -> 160 | BF37: =SUM(AT37:BE37)-I37 -> 0 | BJ37: =I37 -> 640 | BL37: MA | BM37: 160 | BN37: =I37/4 -> 160 | BO37: =I37/4 -> 160 | BP37: =I37/4 -> 160 | BQ37: =I37/4 -> 160 | BR37: =BN37+BO37+BP37+BQ37-I37 -> 0 | BS37: =BN37+BO37+BP37+BQ37+$BS$290 -> 513120 | BT37: =BT36-BN37 -> 124537.75 | BU37: =BU36-BO37 -> 125745.75 | BV37: =BV36-BP37 -> 125753.75 | BW37: =BW36-BQ37 -> 126087.08
A38: 45629 | B38: FREDMEYER INC | C38: 美国 | D38: 4500153169 | E38: PO#0000373341 06 | F38: 4500153169-40 | G38: 92107-S002 | H38: 摇篮公子 | I38: 300 | J38: 0 | K38: 4 | L38: =I38/K38 -> 75 | M38: 45670 | N38: 45666 | P38: PASS | U38: 1/16出 | W38: 12/3收到 | Y38: 无 | AB38: 日期码格式：ZURU INC(BVI) 标准格式 日期：按实际生产日期 Packaging Info: 1、包装方式: MA UPC优先1L最新版本，出口美国 Remark: 2、无测试无第三方验货要求。 3、纸箱4面印ZURU LOGO + 箱唛 4、日期码请按ZURU标准版执行即可。 5、ZURU QC验货。 6、Ratio: #92107: 4 Assortment Ratio (Ladybug: Giraffe: Butterfly: Elephant)=1:1:1:1 | AC38: Vicky Wu | AD38: 4.1317 | AE38: =AD38*I38 -> 1239.51 | AF38: 94067-1.16 | AG38: 92107-S002 | AH38: 已入 | AJ38: =I38 -> 300 | AP38: =I38 -> 300 | AX38: =I38/4 -> 75 | AY38: =I38/4 -> 75 | AZ38: =I38/4 -> 75 | BA38: =I38/4 -> 75 | BF38: =SUM(AT38:BE38)-I38 -> 0 | BJ38: =I38 -> 300 | BL38: MA | BN38: =I38/4 -> 75 | BO38: =I38/4 -> 75 | BP38: =I38/4 -> 75 | BQ38: =I38/4 -> 75 | BR38: =BN38+BO38+BP38+BQ38-I38 -> 0 | BS38: =BN38+BO38+BP38+BQ38+$BS$290 -> 512780 | BT38: =BT37-BN38 -> 124462.75 | BU38: =BU37-BO38 -> 125670.75 | BV38: =BV37-BP38 -> 125678.75 | BW38: =BW37-BQ38 -> 126012.08
A39: 45635 | B39: BINGO GLOBAL GROUP FOR TRADING SUPP | C39: 埃及 | D39: 4500153513 | F39: 4500153513-50 | G39: 92107-S001 | H39: 摇篮公子 | I39: 800 | J39: 0 | K39: 8 | L39: =I39/K39 -> 100 | M39: 45672 | N39: 45668 | P39: PASS | U39: 收到SO | W39: 12/12收到 | Y39: 12-12进口商贴纸 | AB39: 日期码格式：ZURU INC(BVI) 标准格式 日期：按实际生产日期 Packaging Info: 92107:3L MA EAN 收缩膜+进口商贴纸;MA指南 Remark: 标准产品标准配比 | AC39: Lena Huang | AD39: 4.2475 | AE39: =AD39*I39 -> 3398 | AF39: 94081-1.17 | AG39: 92107-S001-3L | AH39: 已入 | AL39: =I39 -> 800 | AP39: =I39 -> 800 | AX39: =I39/4 -> 200 | AY39: =AX39 -> 200 | AZ39: =AX39 -> 200 | BA39: =AX39 -> 200 | BF39: =SUM(AT39:BE39)-I39 -> 0 | BJ39: =I39 -> 800 | BL39: MA | BN39: =I39/4 -> 200 | BO39: =I39/4 -> 200 | BP39: =I39/4 -> 200 | BQ39: =I39/4 -> 200 | BR39: =BN39+BO39+BP39+BQ39-I39 -> 0 | BS39: =BN39+BO39+BP39+BQ39+$BS$290 -> 513280 | BT39: =BT38-BN39 -> 124262.75 | BU39: =BU38-BO39 -> 125470.75 | BV39: =BV38-BP39 -> 125478.75 | BW39: =BW38-BQ39 -> 125812.08
A40: 45636 | D40: ZMPO24940 | G40: 92107-S003-NB | H40: 摇篮公子 | I40: 2 | J40: 0 | K40: 1 | L40: =I40/K40 -> 2 | M40: 45649 | N40: 45645 | P40: 已送货 | W40: 周转箱 | Y40: UPC条码贴纸 | AB40: Remark：跟订单4500146212一起安排/MA3L收缩膜+UPC条码贴纸(UPC: 193052064738)+MA5L收藏指南+MA5L资料卡+MA5L胶袋+MA配件袋+MA2L布标 备注： 收到样品订单后尽快安排 ，注意样板品质质量要求要高于大货品质要求 ，送货时必须要附带送货单(没有送货单和QC检验合格报告的仓库一律拒绝收货)，请知悉，谢谢！ | AG40: 92107-S003-NB-3L | AH40: 已入 | AL40: =I40 -> 2 | AP40: =I40 -> 2 | AT40: 1 | AU40: 1 | BF40: =SUM(AT40:BE40)-I40 -> 0 | BK40: =I40 -> 2 | BL40: MA | BN40: 1 | BO40: 1 | BR40: =BN40+BO40+BP40+BQ40-I40 -> 0 | BS40: =BN40+BO40+BP40+BQ40+$BS$290 -> 512482 | BT40: =BT39-BN40 -> 124261.75 | BU40: =BU39-BO40 -> 125469.75 | BV40: =BV39-BP40 -> 125478.75 | BW40: =BW39-BQ40 -> 125812.08
A41: 45615 | B41: COMERCIALIZADORA MEXICO AMERICANA S | C41: 墨西哥 | D41: 4500151758 | E41: SUPERCENTER | F41: 4500151758-30 | G41: 92107-S001 | H41: 摇篮公子(干燥剂） | I41: 632 | J41: 0 | K41: 8 | L41: =I41/K41 -> 79 | M41: 45665 | N41: 45661 | P41: PASS | U41: 1/10出 | W41: 12/9收到 | Y41: 进口商和UPC条码贴纸翻单4500136632 | AA41: LOTDGYYYYMMDD | AB41: 日期码格式：LOTDGYYYYMMDD 日期：按实际生产日期 Packaging Info: 2. 92107： MA 3L EAN包装+UPC条码贴纸+MA 5L 收藏指南+进口商贴纸+箱唛，进口商和UPC条码贴纸翻单4500136632 Remark: 1. 客版日期码要求：LOT+ZURU标准日期码格式。东莞生产的格式：LOTDGYYYYMMDD, DG是东莞拼音首字母， YYYYMMDD是实际的年月日，例如(LOTDG20240920) 2.92107： 4 Assortment Ratio (Ladybug: Giraffe: Butterfly: Elephant)=1:1:1:1 4. 此单有第三方监柜，至少多备一套完整的物料用于监柜，请多备料。 5.WM墨西哥防霉的新要求:货物必须在出货主箱和集装箱中按要求放置干燥剂，干燥剂指定品牌干霸 92107：需要在每箱放入14小包干燥剂，每包干燥剂重量2-3g 如走柜货等loading plan 确认后再通知集装箱干燥剂数量 此单兴信将安排1*40HC，每个HC需要放置10包干燥剂，每包干燥剂1KG | AC41: Ever Li | AD41: 4.2362 | AE41: =AD41*I41 -> 2677.2784 | AF41: 94014-1.13 | AG41: 92107-S001-3L | AH41: 已入 | AL41: 632 | AP41: =I41 -> 632 | AT41: =I41/4 -> 158 | AU41: =AT41 -> 158 | AV41: =AU41 -> 158 | AW41: =AV41 -> 158 | BF41: =SUM(AT41:BE41)-I41 -> 0 | BJ41: =I41 -> 632 | BL41: MA | BM41: 158 | BN41: =I41/4 -> 158 | BO41: =I41/4 -> 158 | BP41: =I41/4 -> 158 | BQ41: =I41/4 -> 158 | BR41: =BN41+BO41+BP41+BQ41-I41 -> 0 | BS41: =BN41+BO41+BP41+BQ41+$BS$290 -> 513112 | BT41: =BT40-BN41 -> 124103.75 | BU41: =BU40-BO41 -> 125311.75 | BV41: =BV40-BP41 -> 125320.75 | BW41: =BW40-BQ41 -> 125654.08
A42: 45615 | B42: COMERCIALIZADORA MEXICO AMERICANA S | C42: 墨西哥 | D42: 4500151758 | E42: BODEGA | F42: 4500151758-40 | G42: 92107-S001 | H42: 摇篮公子(干燥剂） | I42: 2000 | J42: 0 | K42: 8 | L42: =I42/K42 -> 250 | M42: 45665 | N42: 45661 | P42: PASS | U42: 1/10出 | W42: 12/9收到 | Y42: 进口商和UPC条码贴纸翻单4500136632 | AA42: LOTDGYYYYMMDD | AB42: 日期码格式：LOTDGYYYYMMDD 日期：按实际生产日期 Packaging Info: 2. 92107： MA 3L EAN包装+UPC条码贴纸+MA 5L 收藏指南+进口商贴纸+箱唛，进口商和UPC条码贴纸翻单4500136632 Remark: 1. 客版日期码要求：LOT+ZURU标准日期码格式。东莞生产的格式：LOTDGYYYYMMDD, DG是东莞拼音首字母， YYYYMMDD是实际的年月日，例如(LOTDG20240920) 2.92107： 4 Assortment Ratio (Ladybug: Giraffe: Butterfly: Elephant)=1:1:1:1 4. 此单有第三方监柜，至少多备一套完整的物料用于监柜，请多备料。 5.WM墨西哥防霉的新要求:货物必须在出货主箱和集装箱中按要求放置干燥剂，干燥剂指定品牌干霸 92107：需要在每箱放入14小包干燥剂，每包干燥剂重量2-3g 如走柜货等loading plan 确认后再通知集装箱干燥剂数量 此单兴信将安排1*40HC，每个HC需要放置10包干燥剂，每包干燥剂1KG | AC42: Ever Li | AD42: 4.2362 | AE42: =AD42*I42 -> 8472.4 | AF42: 94014-1.13 | AG42: 92107-S001-3L | AH42: 已入 | AL42: 2000 | AP42: =I42 -> 2000 | AT42: =I42/4 -> 500 | AU42: =AT42 -> 500 | AV42: =AU42 -> 500 | AW42: =AV42 -> 500 | BF42: =SUM(AT42:BE42)-I42 -> 0 | BJ42: =I42 -> 2000 | BL42: MA | BM42: 500 | BN42: =I42/4 -> 500 | BO42: =I42/4 -> 500 | BP42: =I42/4 -> 500 | BQ42: =I42/4 -> 500 | BR42: =BN42+BO42+BP42+BQ42-I42 -> 0 | BS42: =BN42+BO42+BP42+BQ42+$BS$290 -> 514480 | BT42: =BT41-BN42 -> 123603.75 | BU42: =BU41-BO42 -> 124811.75 | BV42: =BV41-BP42 -> 124820.75 | BW42: =BW41-BQ42 -> 125154.08
A43: 45579 | B43: WAL-MART CANADA CORP. | C43: 加拿大 | D43: 4500147521 | E43: 9650903907 | F43: 4500147521-20 | G43: 92107-S003-NB | H43: 摇篮公子 | I43: 1219 | J43: 0 | K43: 1 | L43: =I43/K43 -> 1219 | M43: 45666 | N43: 45663 | O43: 第三方验货1/10（自检） | P43: PASS | U43: 1/27出 | W43: 12/2收到 | X43: 无 | Y43: UPC条码贴纸翻单：4500146212 | AB43: 日期码格式：ZURU INC(BVI) 标准格式 日期：按实际生产日期 Packaging Info: #92107: MA3L收缩膜+UPC条码贴纸(UPC: 193052064738)+MA5L收藏指南+MA5L资料卡+MA5L胶袋+MA配件袋+MA2L布标 -产品配比: 4 Assortment Ratio (Ladybug: Giraffe: Butterfly: Elephant)=1:1:1:1 -翻单：4500146212 Remark: 1. #92108/92107/9296 须使用无硼slime; 2. 此单有箱唛； 3. 此单有第三方验货，烦请多备包装物料； ********************* a. 请确保产品符合1999年版本的加拿大环境保护法(CEPA)和2012年禁止某些有毒物质法规的要求。该产品不含任何在加拿大禁用的化学物质，包括但不限于有毒物 质清单中列出的化学物质，并且在为加拿大沃尔玛生产产品期间没有使用任何禁用化学物质。 Supplier certify that the products comply with the requirements of Canadian Environmental Protection Act, 1999 (CEPA), Prohibition of Certain To xic Substances Regulations, 2012. The products do not contain any chemicals that are banned in Canada, including but not limited to those listed in the Toxic Substances List and no banned chemicals were used during the manufacturing of product for Walmart Canada. 附件列表： (1) Letter of Guarantee for Canada banned chemicals - (1-5CA) b. 请确保产品在均质材料中的汞浓度不超过0.1%（按重量计）。 Supplier certify that the WAL-MART vendor products does not have a mercury concentration of more than 0.1% by weight in homogeneous material. 附件列表： (1) Letter of Guarantee for Mercury COC c. 请确保产品的塑料材料不含以下物质（SOR 2011-17 27B): Supplier certify that the plastic materials do not contain the following substances(SOR 2011-17 27B): (a) carbon tetrachloride or any substance that contains it; (b) methyl alcohol or any substance thay contains >1.0%; (c) petroleum distillates or any substance that contains >10% weight to volume of petroleum distillates; (d) benzene; (e) turpentine or any substance that contains >10% weight to volume of turpentine; (f) boric acid or salts of boric acid; or (g) ethyl ether. 附件列表： (1) Letter of Guarantee for WM CA-Other prohibited substances in plastic(less than 3 years) | AC43: Monica Zhou | AD43: 4.2109 | AE43: =AD43*I43 -> 5133.0871 | AF43: 94179-1.23 | AG43: 92107-S003-NB-3L | AH43: 已入 | AL43: =I43 -> 1219 | AP43: =I43 -> 1219 | AX43: =I43/4 -> 304.75 | AY43: =I43/4 -> 304.75 | AZ43: =AY43 -> 304.75 | BA43: =I43/4 -> 304.75 | BF43: =SUM(AT43:BE43)-I43 -> 0 | BK43: =I43 -> 1219 | BL43: MA | BN43: =I43/4 -> 304.75 | BO43: =I43/4 -> 304.75 | BP43: =I43/4 -> 304.75 | BQ43: =I43/4 -> 304.75 | BR43: =BN43+BO43+BP43+BQ43-I43 -> 0 | BS43: =BN43+BO43+BP43+BQ43+$BS$290 -> 513699 | BT43: =BT42-BN43 -> 123299 | BU43: =BU42-BO43 -> 124507 | BV43: =BV42-BP43 -> 124516 | BW43: =BW42-BQ43 -> 124849.33
A44: 45609 | B44: TOY TRIANGLE COMPANY (UAE) | C44: 阿拉伯联合酋长国 | D44: 4500151230 | E44: 2025TTC006 | F44: 4500151230-30 | G44: 92117-S001 | H44: 摇篮公子 | I44: 6000 | J44: 0 | K44: 8 | L44: =I44/K44 -> 750 | M44: 45666 | N44: 45663 | P44: PASS | W44: 11/13收到 | Y44: 无 | AA44: 客版收缩膜翻4500134696+客版指南翻4500134696 | AB44: 日期码格式：ZURU INC(BVI) 标准格式 日期：按实际生产日期 Packaging Info: 92117：客版收缩膜翻4500134696（改彩虹颜色，不含slime和希伯来警告语，需含阿拉伯警告语，印G mark+TTC panel 信息，客版指南翻4500134696（改彩 虹颜色，不含slime和希伯来警告语）;；客版收缩膜上的二维码微信可扫, 扫描结果38711. 客版沙子PE POLYBAG 含阿拉伯警语翻4500134696 Remark: 92117:#92107 Smart Sandy replaces slime 4 Assortment Ratio (Ladybug: Giraffe: Butterfly: Elephant)=1:1:1:1 | AC44: Lena Huang | AD44: 4.2296 | AE44: =AD44*I44 -> 25377.6 | AF44: 94062-1.16 | AG44: 92117-S001 | AH44: 已入 | AN44: =I44 -> 6000 | AS44: =I44 -> 6000 | AW44: =I44/4 -> 1500 | AX44: =I44/4 -> 1500 | AY44: =I44/4 -> 1500 | AZ44: =I44/4 -> 1500 | BF44: =SUM(AT44:BE44)-I44 -> 0 | BI44: =I44 -> 6000 | BL44: MA | BN44: =I44/4 -> 1500 | BO44: =I44/4 -> 1500 | BP44: =I44/4 -> 1500 | BQ44: =I44/4 -> 1500 | BR44: =BN44+BO44+BP44+BQ44-I44 -> 0 | BS44: =BN44+BO44+BP44+BQ44+$BS$290 -> 518480 | BT44: =BT43-BN44 -> 121799 | BU44: =BU43-BO44 -> 123007 | BV44: =BV43-BP44 -> 123016 | BW44: =BW43-BQ44 -> 123349.33
A45: 45579 | B45: WAL-MART CANADA CORP. | C45: 加拿大 | D45: 4500147521 | E45: 9650903908 | F45: 4500147521-70 | G45: 92107-S003-NB | H45: 摇篮公子 | I45: 732 | J45: 0 | K45: 1 | L45: =I45/K45 -> 732 | M45: 45672 | N45: 45668 | O45: 第三方验货1/17（自检） | P45: PASS | U45: 2/13出 | W45: 12/2收到 | X45: 无 | Y45: UPC条码贴纸翻单：4500146212 | AB45: 日期码格式：ZURU INC(BVI) 标准格式 日期：按实际生产日期 Packaging Info: #92107: MA3L收缩膜+UPC条码贴纸(UPC: 193052064738)+MA5L收藏指南+MA5L资料卡+MA5L胶袋+MA配件袋+MA2L布标 -产品配比: 4 Assortment Ratio (Ladybug: Giraffe: Butterfly: Elephant)=1:1:1:1 -翻单：4500146212 Remark: 1. #92108/92107/9296 须使用无硼slime; 2. 此单有箱唛； 3. 此单有第三方验货，烦请多备包装物料； ********************* a. 请确保产品符合1999年版本的加拿大环境保护法(CEPA)和2012年禁止某些有毒物质法规的要求。该产品不含任何在加拿大禁用的化学物质，包括但不限于有毒物 质清单中列出的化学物质，并且在为加拿大沃尔玛生产产品期间没有使用任何禁用化学物质。 Supplier certify that the products comply with the requirements of Canadian Environmental Protection Act, 1999 (CEPA), Prohibition of Certain To xic Substances Regulations, 2012. The products do not contain any chemicals that are banned in Canada, including but not limited to those listed in the Toxic Substances List and no banned chemicals were used during the manufacturing of product for Walmart Canada. 附件列表： (1) Letter of Guarantee for Canada banned chemicals - (1-5CA) b. 请确保产品在均质材料中的汞浓度不超过0.1%（按重量计）。 Supplier certify that the WAL-MART vendor products does not have a mercury concentration of more than 0.1% by weight in homogeneous material. 附件列表： (1) Letter of Guarantee for Mercury COC c. 请确保产品的塑料材料不含以下物质（SOR 2011-17 27B): Supplier certify that the plastic materials do not contain the following substances(SOR 2011-17 27B): (a) carbon tetrachloride or any substance that contains it; (b) methyl alcohol or any substance thay contains >1.0%; (c) petroleum distillates or any substance that contains >10% weight to volume of petroleum distillates; (d) benzene; (e) turpentine or any substance that contains >10% weight to volume of turpentine; (f) boric acid or salts of boric acid; or (g) ethyl ether. 附件列表： (1) Letter of Guarantee for WM CA-Other prohibited substances in plastic(less than 3 years) | AC45: Monica Zhou | AD45: 4.2109 | AE45: =AD45*I45 -> 3082.3788 | AF45: 94237-2.13 | AG45: 92107-S003-NB-3L | AH45: 已入 | AL45: =I45 -> 732 | AP45: =I45 -> 732 | AX45: =I45/4 -> 183 | AY45: =AX45 -> 183 | AZ45: =AX45 -> 183 | BA45: =AX45 -> 183 | BF45: =SUM(AT45:BE45)-I45 -> 0 | BK45: =I45 -> 732 | BL45: MA | BN45: =I45/4 -> 183 | BO45: =I45/4 -> 183 | BP45: =I45/4 -> 183 | BQ45: =I45/4 -> 183 | BR45: =BN45+BO45+BP45+BQ45-I45 -> 0 | BS45: =BN45+BO45+BP45+BQ45+$BS$290 -> 513212 | BT45: =BT44-BN45 -> 121616 | BU45: =BU44-BO45 -> 122824 | BV45: =BV44-BP45 -> 122833 | BW45: =BW44-BQ45 -> 123166.33
A46: 45603 | B46: ROSS PROCUREMENT.INC | C46: 美国 | D46: 4500150480 | E46: 60190302 | F46: 4500150480-10 | G46: 92107-S001 | H46: 摇篮公子 | I46: 1600 | J46: 0 | K46: 8 | L46: =I46/K46 -> 200 | M46: 45677 | N46: 45673 | P46: PASS | U46: 2/11出 | W46: ROSS指定箱唛格式 | Y46: 无 | Z46: 12/19-客供价格贴纸 | AB46: 日期码格式： 标准格式 日期：按实际生产日期 Packaging Info: 1.ZURU MA UPC 现有版本包装 + 客供价格贴纸，出口美国 , 优先使用MA 1L 最新版本 。 Remark: 1.ZURU MA UPC 现有版本包装 + 客供价格贴纸，出口美国 , 优先使用MA 1L 最新版本 。 2.价格贴纸位于包装正面右下角，不挡住重要信息即可，可适当调整 ，价格贴纸由跟单提供。 3.标准日期码格式，产品和包装必须有日期码 。 4.同个产品同个货期不可出现不同的包装。 5. 跟单提供ROSS通用的箱唛模版，工厂按实际45 PO上客户PO/Item号/装箱数 提供箱唛排版来确认 | AC46: Minny Peng | AD46: 4.2475 | AE46: =AD46*I46 -> 6796 | AF46: 94470-3.6 | AG46: 92107-S001 | AH46: 已入 | AJ46: =I46 -> 1600 | AP46: =I46 -> 1600 | AX46: =I46/4 -> 400 | AY46: =AX46 -> 400 | AZ46: =AX46 -> 400 | BA46: =AX46 -> 400 | BF46: =SUM(AT46:BE46)-I46 -> 0 | BJ46: =I46 -> 1600 | BL46: MA | BN46: =I46/4 -> 400 | BO46: =I46/4 -> 400 | BP46: =I46/4 -> 400 | BQ46: =I46/4 -> 400 | BR46: =BN46+BO46+BP46+BQ46-I46 -> 0 | BS46: =BN46+BO46+BP46+BQ46+$BS$290 -> 514080 | BT46: =BT45-BN46 -> 121216 | BU46: =BU45-BO46 -> 122424 | BV46: =BV45-BP46 -> 122433 | BW46: =BW45-BQ46 -> 122766.33
A47: 45621 | B47: THE WAREHOUSE LIMITED | C47: 新西兰 | D47: 4500152174 | E47: 28659766 | F47: 4500152174-10 | G47: 92107-S001 | H47: 摇篮公子 | I47: 128 | J47: 0 | K47: 8 | L47: =I47/K47 -> 16 | M47: 45684 | N47: 45680 | P47: PASS | U47: 2/11出 | W47: 11/25收到 | Y47: 无 | AB47: 日期码格式：ZURU INC(BVI) 标准格式 日期：按实际生产日期 Packaging Info: MA UPC 英语包装（优先1L英语版本，或者3L/5L含英语都可） 此客人不接受易掉落或者剥落或者可直接触碰的闪粉，可降解也不行，但可以接受符合欧洲微塑料标准的珠光粉或者闪片。 Remark: 92107: 4 Assortment Ratio (Ladybug: Giraffe: Butterfly: Elephant)=1:1:1:1 | AC47: Abby Liang | AD47: 4.2589 | AE47: =AD47*I47 -> 545.1392 | AF47: 94213-2.11 | AG47: 92107-S001 | AH47: 已入 | AJ47: =I47 -> 128 | AP47: =I47 -> 128 | AX47: =I47/4 -> 32 | AY47: =AX47 -> 32 | AZ47: =AX47 -> 32 | BA47: =AX47 -> 32 | BF47: =SUM(AT47:BE47)-I47 -> 0 | BJ47: =I47 -> 128 | BL47: MA | BN47: =I47/4 -> 32 | BO47: =I47/4 -> 32 | BP47: =I47/4 -> 32 | BQ47: =I47/4 -> 32 | BR47: =BN47+BO47+BP47+BQ47-I47 -> 0 | BS47: =BN47+BO47+BP47+BQ47+$BS$290 -> 512608 | BT47: =BT46-BN47 -> 121184 | BU47: =BU46-BO47 -> 122392 | BV47: =BV46-BP47 -> 122401 | BW47: =BW46-BQ47 -> 122734.33
A48: 45621 | B48: THE WAREHOUSE LIMITED | C48: 新西兰 | D48: 4500152173 | E48: 28659765 | F48: 4500152173-10 | G48: 92107-S001 | H48: 摇篮公子 | I48: 376 | J48: 0 | K48: 8 | L48: =I48/K48 -> 47 | M48: 45684 | N48: 45680 | P48: PASS | U48: 2/13出 | W48: 11/25收到 | Y48: 无 | AB48: 日期码格式：ZURU INC(BVI) 标准格式 日期：按实际生产日期 Tracking Code: Packaging Info: MA UPC 英语包装（优先1L英语版本，或者3L/5L含英语都可） 此客人不接受易掉落或者剥落或者可直接触碰的闪粉，可降解也不行，但可以接受符合欧洲微塑料标准的珠光粉或者闪片。 Remark: 92107: 4 Assortment Ratio (Ladybug: Giraffe: Butterfly: Elephant)=1:1:1:1 | AC48: Abby Liang | AD48: 4.2589 | AE48: =AD48*I48 -> 1601.3464 | AF48: 94227-2.12 | AG48: 92107-S001 | AH48: 已入 | AJ48: =I48 -> 376 | AP48: =I48 -> 376 | AX48: =I48/4 -> 94 | AY48: =AX48 -> 94 | AZ48: =AX48 -> 94 | BA48: =AX48 -> 94 | BF48: =SUM(AT48:BE48)-I48 -> 0 | BJ48: =I48 -> 376 | BL48: MA | BN48: =I48/4 -> 94 | BO48: =I48/4 -> 94 | BP48: =I48/4 -> 94 | BQ48: =I48/4 -> 94 | BR48: =BN48+BO48+BP48+BQ48-I48 -> 0 | BS48: =BN48+BO48+BP48+BQ48+$BS$290 -> 512856 | BT48: =BT47-BN48 -> 121090 | BU48: =BU47-BO48 -> 122298 | BV48: =BV47-BP48 -> 122307 | BW48: =BW47-BQ48 -> 122640.33
A49: 45586 | B49: TJX COMPANIES, INC | C49: 美国 | D49: 4500147799 | E49: Marshalls DC#881-168PCS , DC#884-128PCS , DC#886-184PCS , DC#887-152PCS , DC#888-168PCS | F49: 4500147799-80 | G49: 92107-S001 | H49: 摇篮公子 | I49: 800 | J49: 0 | K49: 8 | L49: =I49/K49 -> 100 | M49: 45677 | N49: 45673 | P49: PASS | U49: 2/14出 | W49: 11/4收到 | X49: 无 | Y49: 无 | Z49: 12/20-价格贴纸客供 | AB49: 日期码格式：ZURU INC(BVI) 标准格式 日期：按实际生产日期 Packaging Info: MA UPC包装+价格贴纸，价格贴纸客供。 Remark: 1. 产品和包装上印刷tracking code信息，格式为ZURU常规格式。 2. 分5个DC出货，每款产品每个DC的箱唛资料不同。具体分DC数量，请参考后面行项目备注。 3. ZURU QC验货。 | AC49: Emily Wu | AD49: 4.0921 | AE49: =AD49*I49 -> 3273.68 | AG49: 92107-S001 | AH49: 已入 | AJ49: =I49 -> 800 | AP49: =I49 -> 800 | AX49: =I49/4 -> 200 | AY49: =AX49 -> 200 | AZ49: =AX49 -> 200 | BA49: =AX49 -> 200 | BF49: =SUM(AT49:BE49)-I49 -> 0 | BJ49: =I49 -> 800 | BL49: MA | BN49: =I49/4 -> 200 | BO49: =I49/4 -> 200 | BP49: =I49/4 -> 200 | BQ49: =I49/4 -> 200 | BR49: =BN49+BO49+BP49+BQ49-I49 -> 0 | BS49: =BN49+BO49+BP49+BQ49+$BS$290 -> 513280 | BT49: =BT48-BN49 -> 120890 | BU49: =BU48-BO49 -> 122098 | BV49: =BV48-BP49 -> 122107 | BW49: =BW48-BQ49 -> 122440.33
A50: 45586 | B50: TJX COMPANIES, INC | C50: 美国 | D50: 4500147801 | E50: TJ MAXX DC#891-200PCS , DC#894-168PCS , DC#896-160PCS , DC#897-312PCS , DC#898-160PCS | F50: 4500147801-80 | G50: 92107-S001 | H50: 摇篮公子 | I50: 1000 | J50: 0 | K50: 8 | L50: =I50/K50 -> 125 | M50: 45677 | N50: 45673 | P50: PASS | U50: 2/11出 | W50: 11/4收到 | X50: 无 | Y50: 无 | Z50: 12/20-价格贴纸客供 | AB50: 日期码格式：ZURU INC(BVI) 标准格式 日期：按实际生产日期 Packaging Info: MA UPC包装+价格贴纸，价格贴纸客供。 Remark: 1. 产品和包装上印刷tracking code信息，格式为ZURU常规格式。 2. 分5个DC出货，每款产品每个DC的箱唛资料不同。具体分DC数量，请参考后面行项目备注。 3. ZURU QC验货。 | AC50: Emily Wu | AD50: 4.2475 | AE50: =AD50*I50 -> 4247.5 | AG50: 92107-S001 | AH50: 已入 | AJ50: =I50 -> 1000 | AP50: =I50 -> 1000 | AX50: =I50/4 -> 250 | AY50: =AX50 -> 250 | AZ50: =AX50 -> 250 | BA50: =AX50 -> 250 | BF50: =SUM(AT50:BE50)-I50 -> 0 | BJ50: =I50 -> 1000 | BL50: MA | BN50: =I50/4 -> 250 | BO50: =I50/4 -> 250 | BP50: =I50/4 -> 250 | BQ50: =I50/4 -> 250 | BR50: =BN50+BO50+BP50+BQ50-I50 -> 0 | BS50: =BN50+BO50+BP50+BQ50+$BS$290 -> 513480 | BT50: =BT49-BN50 -> 120640 | BU50: =BU49-BO50 -> 121848 | BV50: =BV49-BP50 -> 121857 | BW50: =BW49-BQ50 -> 122190.33
A51: 45586 | B51: TJX COMPANIES, INC | C51: 美国 | D51: 4500147803 | E51: TJ MAXX DC#891-200PCS , DC#894-168PCS , DC#896-160PCS , DC#897-312PCS , DC#898-160PCS | F51: 4500147803-100 | G51: 92107-S001 | H51: 摇篮公子 | I51: 1000 | J51: 0 | K51: 8 | L51: =I51/K51 -> 125 | M51: 45677 | N51: 45673 | P51: PASS | U51: 2/13出 | W51: 11/4收到 | X51: 无 | Y51: 无 | Z51: 12/20-价格贴纸客供 | AB51: 日期码格式：ZURU INC(BVI) 标准格式 日期：按实际生产日期 Packaging Info: MA UPC包装+价格贴纸，价格贴纸客供。 Remark: 1. 产品和包装上印刷tracking code信息，格式为ZURU常规格式。 2. 分5个DC出货，每款产品每个DC的箱唛资料不同。具体分DC数量，请参考后面行项目备注。 3. ZURU QC验货。 | AC51: Emily Wu | AD51: 4.2475 | AE51: =AD51*I51 -> 4247.5 | AG51: 92107-S001 | AH51: 已入 | AJ51: =I51 -> 1000 | AP51: =I51 -> 1000 | AX51: =I51/4 -> 250 | AY51: =AX51 -> 250 | AZ51: =AX51 -> 250 | BA51: =AX51 -> 250 | BF51: =SUM(AT51:BE51)-I51 -> 0 | BJ51: =I51 -> 1000 | BL51: MA | BN51: =I51/4 -> 250 | BO51: =I51/4 -> 250 | BP51: =I51/4 -> 250 | BQ51: =I51/4 -> 250 | BR51: =BN51+BO51+BP51+BQ51-I51 -> 0 | BS51: =BN51+BO51+BP51+BQ51+$BS$290 -> 513480 | BT51: =BT50-BN51 -> 120390 | BU51: =BU50-BO51 -> 121598 | BV51: =BV50-BP51 -> 121607 | BW51: =BW50-BQ51 -> 121940.33
A52: 45586 | B52: TJX COMPANIES, INC | C52: 美国 | D52: 4500147800 | E52: Marshalls DC#881-168PCS , DC#884-128PCS , DC#886-184PCS , DC#887-152PCS , DC#888-168PCS | F52: 4500147800-100 | G52: 92107-S001 | H52: 摇篮公子 | I52: 800 | J52: 0 | K52: 8 | L52: =I52/K52 -> 100 | M52: 45677 | N52: 45673 | P52: PASS | U52: 2/14出 | W52: 11/4收到 | X52: 无 | Y52: 无 | Z52: 12/20-价格贴纸客供 | AB52: 日期码格式：ZURU INC(BVI) 标准格式 日期：按实际生产日期 Packaging Info: MA UPC包装+价格贴纸，价格贴纸客供。 Remark: 1. 产品和包装上印刷tracking code信息，格式为ZURU常规格式。 2. 分5个DC出货，每款产品每个DC的箱唛资料不同。具体分DC数量，请参考后面行项目备注。 3. ZURU QC验货。 | AC52: Emily Wu | AD52: 4.2475 | AE52: =AD52*I52 -> 3398 | AG52: 92107-S001 | AH52: 已入 | AJ52: =I52 -> 800 | AP52: =I52 -> 800 | AX52: =I52/4 -> 200 | AY52: =AX52 -> 200 | AZ52: =AX52 -> 200 | BA52: =AX52 -> 200 | BF52: =SUM(AT52:BE52)-I52 -> 0 | BJ52: =I52 -> 800 | BL52: MA | BN52: =I52/4 -> 200 | BO52: =I52/4 -> 200 | BP52: =I52/4 -> 200 | BQ52: =I52/4 -> 200 | BR52: =BN52+BO52+BP52+BQ52-I52 -> 0 | BS52: =BN52+BO52+BP52+BQ52+$BS$290 -> 513280 | BT52: =BT51-BN52 -> 120190 | BU52: =BU51-BO52 -> 121398 | BV52: =BV51-BP52 -> 121407 | BW52: =BW51-BQ52 -> 121740.33
A53: 45623 | B53: THE ENTERTAINER | C53: 英国 | D53: 4500152538 | E53: 4500152538-3: FB12155 | F53: 4500152538-190 | G53: 92107-S001 | H53: 摇篮公子 | I53: 496 | J53: 0 | K53: 8 | L53: =I53/K53 -> 62 | M53: 45696 | N53: 45692 | P53: PASS | U53: 2/19出 | W53: 11/28收到 | Y53: 客户EAN条码贴翻4500148687 | AB53: 日期码格式：ZURU INC(BVI) 标准格式 日期：按实际生产日期 Packaging Info: 92107：MA最新1L-UPC配套包装+客户EAN条码贴一张覆盖ZURU 原条码，条码贴翻订单4500148687 4 Assortment Ratio (Ladybug: Giraffe: Butterfly: Elephant)=1:1:1:1 Remark: *MA版本按工厂现有最新库存即可，订单出英国，请注意检查产品及包装应带UKCA图标，包装显示ZURU UK LTD信息，QC同事请查核，如有问题与跟单确认。 *生产日期按实际（法定工作日），按ZURU标准格式即可 ，但是请知悉包装日期码需要早于或者等于外箱日期码 ，不能晚于外箱日期码 *请注意所有订单都需要经过ZURU QC验货并且通过后方可出货 *条码以订单显示为准 ，请安排生产前先核对 ，有问题请提出。 *所有产品按符合欧洲标准走货，需要是不含微塑料版本 。 *涉及到硼的，如可选择情况下应使用低硼版本 （slime 类别低硼一般低于300ppm)，无选择的应与跟单复核再安排 。 | AC53: Amy Ding | AD53: 4.2589 | AE53: =AD53*I53 -> 2112.4144 | AG53: 92107-S001 | AH53: 已入 | AJ53: =I53 -> 496 | AP53: =I53 -> 496 | AX53: =I53/4 -> 124 | AY53: =AX53 -> 124 | AZ53: =AX53 -> 124 | BA53: =AX53 -> 124 | BF53: =SUM(AT53:BE53)-I53 -> 0 | BJ53: =I53 -> 496 | BL53: MA | BN53: =I53/4 -> 124 | BO53: =I53/4 -> 124 | BP53: =I53/4 -> 124 | BQ53: =I53/4 -> 124 | BR53: =BN53+BO53+BP53+BQ53-I53 -> 0 | BS53: =BN53+BO53+BP53+BQ53+$BS$290 -> 512976 | BT53: =BT52-BN53 -> 120066 | BU53: =BU52-BO53 -> 121274 | BV53: =BV52-BP53 -> 121283 | BW53: =BW52-BQ53 -> 121616.33
A54: 45623 | B54: THE ENTERTAINER | C54: 英国 | D54: 4500152538 | E54: 4500152538-4: FB12134 | F54: 4500152538-270 | G54: 92107-S001 | H54: 摇篮公子 | I54: 200 | J54: 0 | K54: 8 | L54: =I54/K54 -> 25 | M54: 45696 | N54: 45692 | P54: PASS | U54: 2/18出 | W54: 11/28收到 | Y54: 客户EAN条码贴翻4500148687 | AB54: 日期码格式：ZURU INC(BVI) 标准格式 日期：按实际生产日期 Packaging Info: 92107：MA最新1L-UPC配套包装+客户EAN条码贴一张覆盖ZURU 原条码，条码贴翻订单4500148687 4 Assortment Ratio (Ladybug: Giraffe: Butterfly: Elephant)=1:1:1:1 Remark: *MA版本按工厂现有最新库存即可，订单出英国，请注意检查产品及包装应带UKCA图标，包装显示ZURU UK LTD信息，QC同事请查核，如有问题与跟单确认。 *生产日期按实际（法定工作日），按ZURU标准格式即可 ，但是请知悉包装日期码需要早于或者等于外箱日期码 ，不能晚于外箱日期码 *请注意所有订单都需要经过ZURU QC验货并且通过后方可出货 *条码以订单显示为准 ，请安排生产前先核对 ，有问题请提出。 *所有产品按符合欧洲标准走货，需要是不含微塑料版本 。 *涉及到硼的，如可选择情况下应使用低硼版本 （slime 类别低硼一般低于300ppm)，无选择的应与跟单复核再安排 。 | AC54: Amy Ding | AD54: 4.2589 | AE54: =AD54*I54 -> 851.78 | AG54: 92107-S001 | AH54: 已入 | AJ54: =I54 -> 200 | AP54: =I54 -> 200 | AX54: =I54/4 -> 50 | AY54: =AX54 -> 50 | AZ54: =AX54 -> 50 | BA54: =AX54 -> 50 | BF54: =SUM(AT54:BE54)-I54 -> 0 | BJ54: =I54 -> 200 | BL54: MA | BN54: =I54/4 -> 50 | BO54: =I54/4 -> 50 | BP54: =I54/4 -> 50 | BQ54: =I54/4 -> 50 | BR54: =BN54+BO54+BP54+BQ54-I54 -> 0 | BS54: =BN54+BO54+BP54+BQ54+$BS$290 -> 512680 | BT54: =BT53-BN54 -> 120016 | BU54: =BU53-BO54 -> 121224 | BV54: =BV53-BP54 -> 121233 | BW54: =BW53-BQ54 -> 121566.33
A55: 45586 | B55: TJX COMPANIES, INC | C55: 美国 | D55: 4500147806 | E55: TJ MAXX DC#891-200PCS , DC#894-168PCS , DC#896-160PCS , DC#897-312PCS , DC#898-160PCS | F55: 4500147806-90 | G55: 92107-S001 | H55: 摇篮公子 | I55: 1000 | J55: 0 | K55: 8 | L55: =I55/K55 -> 125 | M55: 45698 | N55: 45694 | P55: PASS | U55: 2/21出 | W55: 11/4收到 | X55: 无 | Y55: 12/20-价格贴纸客供 | AB55: 日期码格式：ZURU INC(BVI) 标准格式 日期：按实际生产日期 Packaging Info: MA UPC包装+价格贴纸，价格贴纸客供。 Remark: 1. 产品和包装上印刷tracking code信息，格式为ZURU常规格式。 2. 分5个DC出货，每款产品每个DC的箱唛资料不同。具体分DC数量，请参考后面行项目备注。 3. ZURU QC验货。 | AC55: Emily Wu | AD55: 4.2475 | AE55: =AD55*I55 -> 4247.5 | AF55: 94380-2.27 | AG55: 92107-S001 | AH55: 已入 | AJ55: =I55 -> 1000 | AP55: =I55 -> 1000 | AX55: =I55/4 -> 250 | AY55: =AX55 -> 250 | AZ55: =AX55 -> 250 | BA55: =AX55 -> 250 | BF55: =SUM(AT55:BE55)-I55 -> 0 | BJ55: =I55 -> 1000 | BL55: MA | BN55: =I55/4 -> 250 | BO55: =I55/4 -> 250 | BP55: =I55/4 -> 250 | BQ55: =I55/4 -> 250 | BR55: =BN55+BO55+BP55+BQ55-I55 -> 0 | BS55: =BN55+BO55+BP55+BQ55+$BS$290 -> 513480 | BT55: =BT54-BN55 -> 119766 | BU55: =BU54-BO55 -> 120974 | BV55: =BV54-BP55 -> 120983 | BW55: =BW54-BQ55 -> 121316.33
A56: 45586 | B56: TJX COMPANIES, INC | C56: 美国 | D56: 4500147804 | E56: Marshalls DC#881-168PCS , DC#884-128PCS , DC#886-184PCS , DC#887-152PCS , DC#888-168PCS | F56: 4500147804-90 | G56: 92107-S001 | H56: 摇篮公子 | I56: 800 | J56: 0 | K56: 8 | L56: =I56/K56 -> 100 | M56: 45698 | N56: 45694 | P56: PASS | U56: 2/18出 | W56: 11/4收到 | X56: 无 | Y56: 12/20-价格贴纸客供 | AB56: 日期码格式：ZURU INC(BVI) 标准格式 日期：按实际生产日期 Packaging Info: MA UPC包装+价格贴纸，价格贴纸客供。 Remark: 1. 产品和包装上印刷tracking code信息，格式为ZURU常规格式。 2. 分5个DC出货，每款产品每个DC的箱唛资料不同。具体分DC数量，请参考后面行项目备注。 3. ZURU QC验货。 | AC56: Emily Wu | AD56: 4.2475 | AE56: =AD56*I56 -> 3398 | AF56: 94381-2.27 | AG56: 92107-S001 | AH56: 已入 | AJ56: =I56 -> 800 | AP56: =I56 -> 800 | AX56: =I56/4 -> 200 | AY56: =AX56 -> 200 | AZ56: =AX56 -> 200 | BA56: =AX56 -> 200 | BF56: =SUM(AT56:BE56)-I56 -> 0 | BJ56: =I56 -> 800 | BL56: MA | BN56: =I56/4 -> 200 | BO56: =I56/4 -> 200 | BP56: =I56/4 -> 200 | BQ56: =I56/4 -> 200 | BR56: =BN56+BO56+BP56+BQ56-I56 -> 0 | BS56: =BN56+BO56+BP56+BQ56+$BS$290 -> 513280 | BT56: =BT55-BN56 -> 119566 | BU56: =BU55-BO56 -> 120774 | BV56: =BV55-BP56 -> 120783 | BW56: =BW55-BQ56 -> 121116.33
A57: 45644 | B57: TJX Australia Pty Limited | C57: 澳大利亚 | D57: 4500154316 | E57: CUS PO#885182 | F57: 4500154316-20 | G57: 92107-S001 | H57: 摇篮公子 | I57: 256 | J57: 0 | K57: 8 | L57: =I57/K57 -> 32 | M57: 45698 | N57: 45694 | P57: PASS | U57: 2/18出 | W57: 12/19收到 | Y57: 无 | Z57: 1/3-客供价格贴纸 | AB57: 日期码格式：ZURU INC(BVI) 标准格式 日期：按实际生产日期 Packaging Info: 包装： 92107：英文MA包装(UPC版本，首选1L，无1L可用多L含英语)+箱唛+1张客供价格贴纸； Ratio： 92107-S001:4 Assortment Ratio (Ladybug: Giraffe: Butterfly: Elephant)=1:1:1:1; Remark: 1.箱唛不可出现任何手写内容，重量与实际须一致且不可手写; 2.产品上贴客供价格贴纸，贴纸位置为产品正面右上角，不能遮住产品信息；请与跟单确认贴纸位置后再生产大货； 3.订单每行对应客人不同的PO，即同款item的价格贴纸都不相同，请注意收到贴纸后不要弄混!（CUS PO号请参考行项目Remark） 4. 此单去澳大利亚，请按相应澳新标准生产并满足当地法规要求; 5.ZURU QC验货。 6.产品和包装上要有tracking label信息：日期码格式为Zuru标准格式； | AC57: Christine Liao | AD57: 4.2475 | AE57: =AD57*I57 -> 1087.36 | AG57: 92107-S001 | AH57: 已入 | AJ57: =I57 -> 256 | AP57: =I57 -> 256 | AX57: =I57/4 -> 64 | AY57: =AX57 -> 64 | AZ57: =AX57 -> 64 | BA57: =AX57 -> 64 | BF57: =SUM(AT57:BE57)-I57 -> 0 | BJ57: =I57 -> 256 | BL57: MA | BN57: =I57/4 -> 64 | BO57: =I57/4 -> 64 | BP57: =I57/4 -> 64 | BQ57: =I57/4 -> 64 | BR57: =BN57+BO57+BP57+BQ57-I57 -> 0 | BS57: =BN57+BO57+BP57+BQ57+$BS$290 -> 512736 | BT57: =BT56-BN57 -> 119502 | BU57: =BU56-BO57 -> 120710 | BV57: =BV56-BP57 -> 120719 | BW57: =BW56-BQ57 -> 121052.33
A58: 45644 | B58: TJX Australia Pty Limited | C58: 澳大利亚 | D58: 4500154316 | E58: CUS PO#885186 | F58: 4500154316-60 | G58: 92107-S001 | H58: 摇篮公子 | I58: 256 | J58: 0 | K58: 8 | L58: =I58/K58 -> 32 | M58: 45698 | N58: 45694 | P58: PASS | U58: 2/18出 | W58: 12/19收到 | Y58: 无 | Z58: 1/3-客供价格贴纸 | AB58: 日期码格式：ZURU INC(BVI) 标准格式 日期：按实际生产日期 Packaging Info: 包装： 92107：英文MA包装(UPC版本，首选1L，无1L可用多L含英语)+箱唛+1张客供价格贴纸； Ratio： 92107-S001:4 Assortment Ratio (Ladybug: Giraffe: Butterfly: Elephant)=1:1:1:1; Remark: 1.箱唛不可出现任何手写内容，重量与实际须一致且不可手写; 2.产品上贴客供价格贴纸，贴纸位置为产品正面右上角，不能遮住产品信息；请与跟单确认贴纸位置后再生产大货； 3.订单每行对应客人不同的PO，即同款item的价格贴纸都不相同，请注意收到贴纸后不要弄混!（CUS PO号请参考行项目Remark） 4. 此单去澳大利亚，请按相应澳新标准生产并满足当地法规要求; 5.ZURU QC验货。 6.产品和包装上要有tracking label信息：日期码格式为Zuru标准格式； | AC58: Christine Liao | AD58: 4.2475 | AE58: =AD58*I58 -> 1087.36 | AG58: 92107-S001 | AH58: 已入 | AJ58: =I58 -> 256 | AP58: =I58 -> 256 | AX58: =I58/4 -> 64 | AY58: =AX58 -> 64 | AZ58: =AX58 -> 64 | BA58: =AX58 -> 64 | BF58: =SUM(AT58:BE58)-I58 -> 0 | BJ58: =I58 -> 256 | BL58: MA | BN58: =I58/4 -> 64 | BO58: =I58/4 -> 64 | BP58: =I58/4 -> 64 | BQ58: =I58/4 -> 64 | BR58: =BN58+BO58+BP58+BQ58-I58 -> 0 | BS58: =BN58+BO58+BP58+BQ58+$BS$290 -> 512736 | BT58: =BT57-BN58 -> 119438 | BU58: =BU57-BO58 -> 120646 | BV58: =BV57-BP58 -> 120655 | BW58: =BW57-BQ58 -> 120988.33
A59: 45644 | B59: TJX Australia Pty Limited | C59: 澳大利亚 | D59: 4500154316 | E59: CUS PO#885190 | F59: 4500154316-100 | G59: 92107-S001 | H59: 摇篮公子 | I59: 256 | J59: 0 | K59: 8 | L59: =I59/K59 -> 32 | M59: 45698 | N59: 45694 | P59: PASS | U59: 2/18出 | W59: 12/19收到 | Y59: 无 | Z59: 1/3-客供价格贴纸 | AB59: 日期码格式：ZURU INC(BVI) 标准格式 日期：按实际生产日期 Packaging Info: 包装： 92107：英文MA包装(UPC版本，首选1L，无1L可用多L含英语)+箱唛+1张客供价格贴纸； Ratio： 92107-S001:4 Assortment Ratio (Ladybug: Giraffe: Butterfly: Elephant)=1:1:1:1; Remark: 1.箱唛不可出现任何手写内容，重量与实际须一致且不可手写; 2.产品上贴客供价格贴纸，贴纸位置为产品正面右上角，不能遮住产品信息；请与跟单确认贴纸位置后再生产大货； 3.订单每行对应客人不同的PO，即同款item的价格贴纸都不相同，请注意收到贴纸后不要弄混!（CUS PO号请参考行项目Remark） 4. 此单去澳大利亚，请按相应澳新标准生产并满足当地法规要求; 5.ZURU QC验货。 6.产品和包装上要有tracking label信息：日期码格式为Zuru标准格式； | AC59: Christine Liao | AD59: 4.2475 | AE59: =AD59*I59 -> 1087.36 | AG59: 92107-S001 | AH59: 已入 | AJ59: =I59 -> 256 | AP59: =I59 -> 256 | AX59: =I59/4 -> 64 | AY59: =AX59 -> 64 | AZ59: =AX59 -> 64 | BA59: =AX59 -> 64 | BF59: =SUM(AT59:BE59)-I59 -> 0 | BJ59: =I59 -> 256 | BL59: MA | BN59: =I59/4 -> 64 | BO59: =I59/4 -> 64 | BP59: =I59/4 -> 64 | BQ59: =I59/4 -> 64 | BR59: =BN59+BO59+BP59+BQ59-I59 -> 0 | BS59: =BN59+BO59+BP59+BQ59+$BS$290 -> 512736 | BT59: =BT58-BN59 -> 119374 | BU59: =BU58-BO59 -> 120582 | BV59: =BV58-BP59 -> 120591 | BW59: =BW58-BQ59 -> 120924.33
A60: 45642 | B60: TJX UK c/o TJX Distribution Ltd & C | C60: 德国 | D60: 4500154045 | E60: Europe-DE: PO#55471275 | F60: 4500154045-60 | G60: 92107-S001 | H60: 摇篮公子 | I60: 504 | J60: 0 | K60: 8 | L60: =I60/K60 -> 63 | M60: 45699 | N60: 45695 | P60: PASS | U60: 2/17出 | W60: 12/25收到 | Y60: 12/25-贴纸（含波兰语警告语) | Z60: 1/3-客供价格贴纸 | AB60: 日期码格式：ZURU INC(BVI) 标准格式 日期：按实际生产日期 Packaging Info: TJX Europe-DE: PO#55471297(7132) + PO#55471301(9298) + PO#55471302(9298) + PO#55471303(9279) + PO#55471304(9279) + PO#55471275(92107) 4) 92107: MA3L (9Lwanrning)最新EAN包装+1张客供价格贴纸+1张贴纸（含波兰语警告语) Remark: 1. 出往UK的产品+包装务必打上UKCA logo ，否则客人会退货且当地会有罚款； 2. 订单必须经过ZURU QC验货并且通过后方可出货； 3. 订单每行对应客人不同的PO， 箱唛也有不同，做货的时候请分开堆放； 4. 包装条码请按包装备注上的对应的警示语语种包装，出德国的订单(订单备注为TJX Europe-DE)需要确保有英语+德语+荷兰语+波兰语警示语； 5. 订单每行对应客人不同的PO，即同款item的价格贴纸都不相同，请注意收到贴纸后不要弄混!（客人PO号请参考PO最后一栏remark）； 6. 客供价格贴纸位置为产品正面右上角，不能遮住产品信息，大货生产前，请把贴纸位置先发给跟单确认 7. 涉及到相关款式会有闪粉的或者微塑料的，请统一默认出无闪粉或者不含微塑料版本; 8. 外箱封箱必须是工字型封箱方式； | AC60: Sandy Shao | AD60: 4.2475 | AE60: =AD60*I60 -> 2140.74 | AG60: 92107-S001-3L | AH60: 已入 | AL60: =I60 -> 504 | AP60: =I60 -> 504 | AX60: =I60/4 -> 126 | AY60: =AX60 -> 126 | AZ60: =AX60 -> 126 | BA60: =AX60 -> 126 | BF60: =SUM(AT60:BE60)-I60 -> 0 | BJ60: =I60 -> 504 | BL60: MA | BN60: =I60/4 -> 126 | BO60: =I60/4 -> 126 | BP60: =I60/4 -> 126 | BQ60: =I60/4 -> 126 | BR60: =BN60+BO60+BP60+BQ60-I60 -> 0 | BS60: =BN60+BO60+BP60+BQ60+$BS$290 -> 512984 | BT60: =BT59-BN60 -> 119248 | BU60: =BU59-BO60 -> 120456 | BV60: =BV59-BP60 -> 120465 | BW60: =BW59-BQ60 -> 120798.33
A61: 45652 | B61: KOTRYNA GROUP, UAB | C61: 立陶宛 | D61: 4500154811 | F61: 4500154811-30 | G61: 92107-S001 | H61: 摇篮公子 | I61: 504 | J61: 0 | K61: 8 | L61: =I61/K61 -> 63 | M61: 45705 | N61: 45701 | P61: PASS | U61: 2/19出 | W61: 12/26收到 | Y61: 进口商贴纸翻4500135339 | AB61: 日期码格式：ZURU INC(BVI) 标准格式 日期：按实际生产日期 Packaging Info: 92107：B 版 1L MA UPC 收缩膜+进口商贴纸（贴纸翻4500135339）；B 版 5L MA 收藏指南 Remark: 1、若产品有比例使用ZURU STD 比例 2、所有item 均用MA UPC 条码，若包装不是UPC 条码的请告知 3、此单出欧洲需满足EU测试标准要求。另外若产品本身含闪粉则需要出符合欧洲微塑料版本的产品 | AC61: Snowy | AD61: 4.2475 | AE61: =AD61*I61 -> 2140.74 | AG61: 92107-S001 | AH61: 已入 | AJ61: =I61 -> 504 | AP61: =I61 -> 504 | AX61: =I61/4 -> 126 | AY61: =AX61 -> 126 | AZ61: =AX61 -> 126 | BA61: =AX61 -> 126 | BF61: =SUM(AT61:BE61)-I61 -> 0 | BJ61: =I61 -> 504 | BL61: MA | BN61: =I61/4 -> 126 | BO61: =I61/4 -> 126 | BP61: =I61/4 -> 126 | BQ61: =I61/4 -> 126 | BR61: =BN61+BO61+BP61+BQ61-I61 -> 0 | BS61: =BN61+BO61+BP61+BQ61+$BS$290 -> 512984 | BT61: =BT60-BN61 -> 119122 | BU61: =BU60-BO61 -> 120330 | BV61: =BV60-BP61 -> 120339 | BW61: =BW60-BQ61 -> 120672.33
A62: 45623 | B62: KAUFHAUS MARTIN STOLZ GMBH | C62: 德国 | D62: 4500145550 | E62: 25-49 | F62: 4500145550-10 | G62: 92107-S001 | H62: 摇篮公子 | I62: 504 | J62: 0 | K62: 8 | L62: =I62/K62 -> 63 | M62: 45702 | N62: 45698 | P62: PASS | U62: 收到SO | W62: 11/28收到 | Y62: Top 10贴纸翻4500137432 格贴纸 | Z62: 11/29-客供价格贴纸 | AB62: 日期码格式：ZURU INC(BVI) 标准格式 日期：按实际生产日期 Packaging Info: 92107: 最新MA 3L(9L warining)EAN 收缩膜+MA 5L(23L warning)收藏指南+MA 5L (9L warning)slime_polybag+MA布标+Top 10贴纸(翻单#4500137432)+1张客供价 格贴纸 Remark: 1. 此单出德国，需要满足Zuru Standard欧洲标准测试要求； 2. 请准时出货，推期会有罚款； 3. 出口欧洲，微塑料需符合法规。 4. 配比：标准配比 5. 大货样品一套 6. 需提供验货图片给客人确认才可以安排出货 | AC62: Shirley Zhou | AD62: 4.2475 | AE62: =AD62*I62 -> 2140.74 | AG62: 92107-S001-3L | AH62: 已入 | AL62: =I62 -> 504 | AP62: =I62 -> 504 | AX62: =I62/4 -> 126 | AY62: =AX62 -> 126 | AZ62: =AX62 -> 126 | BA62: =AX62 -> 126 | BF62: =SUM(AT62:BE62)-I62 -> 0 | BJ62: =I62 -> 504 | BL62: MA | BN62: =I62/4 -> 126 | BO62: =I62/4 -> 126 | BP62: =I62/4 -> 126 | BQ62: =I62/4 -> 126 | BR62: =BN62+BO62+BP62+BQ62-I62 -> 0 | BS62: =BN62+BO62+BP62+BQ62+$BS$290 -> 512984 | BT62: =BT61-BN62 -> 118996 | BU62: =BU61-BO62 -> 120204 | BV62: =BV61-BP62 -> 120213 | BW62: =BW61-BQ62 -> 120546.33
A63: 45639 | B63: ASDA STORES LTD | C63: 英国 | D63: 4500151765 | E63: 2950866131 | F63: 4500151765-50 | G63: 92107SLB-S001 | H63: 摇篮公子88PCS/ctn/卡板 | I63: 968 | J63: 0 | K63: 88 | L63: =I63/K63 -> 11 | M63: 45705 | N63: 45701 | P63: PASS | U63: 2/25出 | W63: 12/25收到 | Y63: 卡板贴纸 | AB63: 日期码格式：ZURU INC(BVI) 标准格式 日期：按实际生产日期 Packaging Info: 5.92107SLB 92107-S003：MA最新1L UPC包装 UPC#193052064738, 请先检查条码是否正确再安排做货； 4 Assortment Ratio (Ladybug: Giraffe: Butterfly: Elephant)=1:1:1:1 Slip Sheet: 1 PCS/CTN, 22*4=88ctn=88pcs/slip sheet, 一共需要11套slip sheet; Slip Sheet打包好后，需要在正唛、侧唛右下角各贴一张slip sheet贴纸，直接用A4纸打印出来即可，贴纸尺寸160mm width x 140mm high； Slip Sheet尺寸限制为100*115*130CM，一旦实际SLIP SHEET尺寸超过这个尺寸，请提前通知ZURU跟单，需同客人确认才能量产和出货; 6.7151SLB 7151-S005:MA 1L最新UPC包装 UPC#193052033482, 请先检查条码是否正确再安排做货； Slip Sheet:3pcs/CTN, (5x7+7)x4H=168carton=504pcs/Slip Sheet,一共需要4套slip sheet Slip Sheet打包好后，需要在正唛、侧唛右下角各贴一张slip sheet贴纸，直接用A4纸打印出来即可，贴纸尺寸160mm width x 140mm high； Slip Sheet尺寸限制为100*115*130CM，一旦实际SLIP SHEET尺寸超过这个尺寸，请提前通知ZURU跟单，需同客人确认才能量产和出货; Remark: 1. 产品及包装需要印UKCA图标，包装需要有ZURU UK LTD/ZURU France地址信息，QC同事请核查，如有问题与跟单确认。 2. 产品/包装/外箱都需要打ZURU格式日期码，日期必须为法定工作日。 3. 需要符合欧洲标准不能含有闪粉和微塑料，否则不合法规会有客诉产生 | AC63: Amy Ding | AD63: 374.5982 | AE63: =AD63*L63 -> 4120.5802 | AF63: 94349-2.25 | AG63: 92107SLB-S001 | AH63: 已入 | AJ63: =I63 -> 968 | AP63: =I63 -> 968 | AX63: =I63/4 -> 242 | AY63: =AX63 -> 242 | AZ63: =AX63 -> 242 | BA63: =AX63 -> 242 | BF63: =SUM(AT63:BE63)-I63 -> 0 | BJ63: =I63 -> 968 | BL63: MA | BN63: =I63/4 -> 242 | BO63: =I63/4 -> 242 | BP63: =I63/4 -> 242 | BQ63: =I63/4 -> 242 | BR63: =BN63+BO63+BP63+BQ63-I63 -> 0 | BS63: =BN63+BO63+BP63+BQ63+$BS$290 -> 513448 | BT63: =BT62-BN63 -> 118754 | BU63: =BU62-BO63 -> 119962 | BV63: =BV62-BP63 -> 119971 | BW63: =BW62-BQ63 -> 120304.33
A64: 45635 | B64: COMERCIALIZADORA MEXICO AMERICANA S | C64: 墨西哥 | D64: 4500153580 | E64: 5251214458 | F64: 4500153580-10 | G64: 92107-S001 | H64: 摇篮公子(干燥剂） | I64: 632 | J64: 0 | K64: 8 | L64: =I64/K64 -> 79 | M64: 45706 | N64: 45702 | P64: PASS | U64: 3/3出 | W64: 12/19收到 | Y64: 进口商和UPC条码贴纸翻单4500136632 | AB64: 日期码格式：LOTDGYYYYMMDD 日期：按实际生产日期 Packaging Info: 1. 92107： MA 3L EAN包装+UPC条码贴纸+MA 5L 收藏指南+进口商贴纸+箱唛，进口商和UPC条码贴纸翻单4500136632 Remark: 1. 客版日期码要求：LOT+ZURU标准日期码格式。东莞生产的格式：LOTDGYYYYMMDD, DG是东莞拼音首字母， YYYYMMDD是实际的年月日，例如(LOTDG20240920) 2. 92107： 4 Assortment Ratio (Ladybug: Giraffe: Butterfly: Elephant)=1:1:1:1 4. 此单有第三方监柜，至少多备一套完整的物料用于监柜，请多备料。 5.WM墨西哥防霉的新要求:货物必须在出货主箱和集装箱中按要求放置干燥剂，干燥剂指定品牌干霸 92107：需要在每箱放入14小包干燥剂，每包干燥剂重量2-3g 如走柜货等loading plan 确认后再通知集装箱干燥剂数量 此单兴信将安排1*40HC，每个HC需要放置10包干燥剂，每包干燥剂1KG | AC64: Ever Li | AD64: 4.0808 | AE64: =AD64*I64 -> 2579.0656 | AF64: 94405-2.28 | AG64: 92107-S001-3L | AH64: 已入 | AL64: =I64 -> 632 | AP64: =I64 -> 632 | AX64: =I64/4 -> 158 | AY64: =AX64 -> 158 | AZ64: =AX64 -> 158 | BA64: =AX64 -> 158 | BF64: =SUM(AT64:BE64)-I64 -> 0 | BJ64: =I64 -> 632 | BL64: MA | BN64: =I64/4 -> 158 | BO64: =I64/4 -> 158 | BP64: =I64/4 -> 158 | BQ64: =I64/4 -> 158 | BR64: =BN64+BO64+BP64+BQ64-I64 -> 0 | BS64: =BN64+BO64+BP64+BQ64+$BS$290 -> 513112 | BT64: =BT63-BN64 -> 118596 | BU64: =BU63-BO64 -> 119804 | BV64: =BV63-BP64 -> 119813 | BW64: =BW63-BQ64 -> 120146.33
A65: 45635 | B65: COMERCIALIZADORA MEXICO AMERICANA S | C65: 墨西哥 | D65: 4500153580 | E65: 5251214459 | F65: 4500153580-20 | G65: 92107-S001 | H65: 摇篮公子(干燥剂） | I65: 2000 | J65: 0 | K65: 8 | L65: =I65/K65 -> 250 | M65: 45706 | N65: 45702 | P65: PASS | U65: 3/3出 | W65: 12/19收到 | Y65: 进口商和UPC条码贴纸翻单4500136632 | AB65: 日期码格式：LOTDGYYYYMMDD 日期：按实际生产日期 Packaging Info: 1. 92107： MA 3L EAN包装+UPC条码贴纸+MA 5L 收藏指南+进口商贴纸+箱唛，进口商和UPC条码贴纸翻单4500136632 Remark: 1. 客版日期码要求：LOT+ZURU标准日期码格式。东莞生产的格式：LOTDGYYYYMMDD, DG是东莞拼音首字母， YYYYMMDD是实际的年月日，例如(LOTDG20240920) 2. 92107： 4 Assortment Ratio (Ladybug: Giraffe: Butterfly: Elephant)=1:1:1:1 4. 此单有第三方监柜，至少多备一套完整的物料用于监柜，请多备料。 5.WM墨西哥防霉的新要求:货物必须在出货主箱和集装箱中按要求放置干燥剂，干燥剂指定品牌干霸 92107：需要在每箱放入14小包干燥剂，每包干燥剂重量2-3g 如走柜货等loading plan 确认后再通知集装箱干燥剂数量 此单兴信将安排1*40HC，每个HC需要放置10包干燥剂，每包干燥剂1KG | AC65: Ever Li | AD65: 4.0808 | AE65: =AD65*I65 -> 8161.6 | AF65: 94405-2.28 | AG65: 92107-S001-3L | AH65: 已入 | AL65: =I65 -> 2000 | AP65: =I65 -> 2000 | AX65: =I65/4 -> 500 | AY65: =AX65 -> 500 | AZ65: =AX65 -> 500 | BA65: =AX65 -> 500 | BF65: =SUM(AT65:BE65)-I65 -> 0 | BJ65: =I65 -> 2000 | BL65: MA | BN65: =I65/4 -> 500 | BO65: =I65/4 -> 500 | BP65: =I65/4 -> 500 | BQ65: =I65/4 -> 500 | BR65: =BN65+BO65+BP65+BQ65-I65 -> 0 | BS65: =BN65+BO65+BP65+BQ65+$BS$290 -> 514480 | BT65: =BT64-BN65 -> 118096 | BU65: =BU64-BO65 -> 119304 | BV65: =BV64-BP65 -> 119313 | BW65: =BW64-BQ65 -> 119646.33
A66: 45608 | B66: CMS FAMOUS TOYS | C66: 加拿大 | D66: 4500151019 | E66: PO0000476 | F66: 4500151019-30 | G66: 92107-S001-NB | H66: 摇篮公子-无硼 | I66: 320 | J66: 0 | K66: 8 | L66: =I66/K66 -> 40 | M66: 45709 | N66: 45705 | P66: PASS | W66: 12/2收到 | Y66: 12/25-UPC贴纸 | AB66: 日期码格式： 标准格式 日期：按实际生产日期 Packaging Info: 92107 MA 多语EAN+UPC贴纸,无硼版本。UPC号码193052064738 Remark: 出加拿大 每款产品都需要加进口商贴纸 Zuru验货.日期跟踪码：产品外包装及产品本身都必须有日期跟踪码，ZURU标准格式日期码 | AC66: Summer Mo | AD66: 4.2589 | AE66: =AD66*I66 -> 1362.848 | AF66: 94383-2.27 | AG66: 92107-S001-NB-3L | AH66: 已入 | AL66: =I66 -> 320 | AP66: =I66 -> 320 | AX66: =I66/4 -> 80 | AY66: =AX66 -> 80 | AZ66: =AX66 -> 80 | BA66: =AX66 -> 80 | BF66: =SUM(AT66:BE66)-I66 -> 0 | BK66: =I66 -> 320 | BL66: MA | BN66: =I66/4 -> 80 | BO66: =I66/4 -> 80 | BP66: =I66/4 -> 80 | BQ66: =I66/4 -> 80 | BR66: =BN66+BO66+BP66+BQ66-I66 -> 0 | BS66: =BN66+BO66+BP66+BQ66+$BS$290 -> 512800 | BT66: =BT65-BN66 -> 118016 | BU66: =BU65-BO66 -> 119224 | BV66: =BV65-BP66 -> 119233 | BW66: =BW65-BQ66 -> 119566.33
A67: 45651 | B67: Zhuyu(Shenzhen)Trading Co.,Ltd. | C67: 中国 | D67: 4500154728 | E67: 5000001743 | F67: 4500154728-70 | G67: 92107-S002 | H67: 摇篮公子 | I67: 1200 | J67: 0 | K67: 4 | L67: =I67/K67 -> 300 | M67: 45713 | N67: 45709 | P67: PASS | U67: 2/26出 | W67: 翻4500146389 | Y67: 中文布标(可用布标贴纸)+CCC贴纸+ 年龄贴（8+）翻4500146389 | Z67: 1/7-客供芯片码 | AB67: 日期码格式：ZURU INC(BVI) 标准格式 日期：按实际生产日期 Packaging Info: 物料要求 SKU 所有款号务必使用带有CCC 标识的AW 6 92107 MA+中文布标(可用布标贴纸)+中文收藏指南+ 中文资料卡+CCC贴纸+ 年龄贴（8+）+客供芯片码 翻单： 4500146389 Remark: 2.外箱材质如下： 1）毛重小于5kg 外箱纸质 K=B 爆破:1000Kpa 边压:4400N/M; 2）毛重大于5kg 外箱纸质 K636K 爆破:1400Kpa 边压:6300N/M; 3. 产品/销售包装/外箱日期码要一致， 4.芯片码横向平贴在上半部分蛋壳/彩盒内侧立面处，注意事项请见跟单提供文档资料。 5.此产品务必满足国内6P 测试标准，因为可能会被市场监督局抽查，如有问题产生，工厂要负全责 6. 这张订单做出厂价，我司自行安排车辆去贵司提货，贵司需要配合提供出口报关 | AC67: Tina Chen | AD67: 4.1202 | AE67: =AD67*I67 -> 4944.24 | AF67: 94357-2.26 | AG67: 92107-S002-1 | AH67: 已入 | AJ67: =I67 -> 1200 | AR67: =I67 -> 1200 | BB67: =I67/4 -> 300 | BC67: =I67/4 -> 300 | BD67: =I67/4 -> 300 | BE67: =I67/4 -> 300 | BF67: =SUM(AT67:BE67)-I67 -> 0 | BJ67: =I67 -> 1200 | BL67: MA | BN67: =I67/4 -> 300 | BO67: =I67/4 -> 300 | BP67: =I67/4 -> 300 | BQ67: =I67/4 -> 300 | BR67: =BN67+BO67+BP67+BQ67-I67 -> 0 | BS67: =BN67+BO67+BP67+BQ67+$BS$290 -> 513680 | BT67: =BT66-BN67 -> 117716 | BU67: =BU66-BO67 -> 118924 | BV67: =BV66-BP67 -> 118933 | BW67: =BW66-BQ67 -> 119266.33
A68: 45651 | B68: AMIC TRADING (PTY) LTD | C68: 南非 | D68: 4500154694 | E68: PO#6006-00522 6PI#110002571 5-2 | F68: 4500154694-10 | G68: 92107-S001 | H68: 摇篮公子 | I68: 208 | J68: 0 | K68: 8 | L68: =I68/K68 -> 26 | M68: 45713 | N68: 45709 | P68: PASS | U68: 2/25出 | W68: 12/25收到 | Y68: 1/6-进口商贴纸 | AB68: 日期码格式：ZURU INC(BVI) 标准格式 日期：按实际生产日期 Packaging Info: MA PKG, 优先1L +1张进口商贴纸（贴条码附近空白处，不得遮挡日期码） 该客户只有一款进口商贴纸，所有款通用，进口商贴纸AW可翻此客户旧订单 Remark: | AC68: Doris Shou | AD68: 4.1036 | AE68: =AD68*I68 -> 853.5488 | AF68: 94351-2.25 | AG68: 92107-S001 | AH68: 已入 | AJ68: =I68 -> 208 | AP68: =I68 -> 208 | AX68: =I68/4 -> 52 | AY68: =AX68 -> 52 | AZ68: =AX68 -> 52 | BA68: =AX68 -> 52 | BF68: =SUM(AT68:BE68)-I68 -> 0 | BJ68: =I68 -> 208 | BL68: MA | BN68: =I68/4 -> 52 | BO68: =I68/4 -> 52 | BP68: =I68/4 -> 52 | BQ68: =I68/4 -> 52 | BR68: =BN68+BO68+BP68+BQ68-I68 -> 0 | BS68: =BN68+BO68+BP68+BQ68+$BS$290 -> 512688 | BT68: =BT67-BN68 -> 117664 | BU68: =BU67-BO68 -> 118872 | BV68: =BV67-BP68 -> 118881 | BW68: =BW67-BQ68 -> 119214.33
A69: 45643 | B69: Asmodee Czech Republic s.r.o. | C69: 捷克共和国 | D69: 4500154192 | F69: 4500154192-40 | G69: 92107-S001 | H69: 摇篮公子 | I69: 2400 | J69: 0 | K69: 8 | L69: =I69/K69 -> 300 | M69: 45716 | N69: 45712 | P69: PASS | W69: 12/17收到 | Y69: 1/2-进口商贴纸 | AB69: 日期码格式：ZURU INC(BVI) 标准格式 日期：按实际生产日期 Packaging Info: 92107：B 版 1L MA UPC 收缩膜+进口商贴纸；B 版 5L MA 收藏指南 Remark: 1、若产品有比例使用ZURU STD 比例 2、所有item 均用MA UPC 条码，若包装不是UPC 条码的请告知 3、此单出欧洲需满足EU测试标准要求，另外不能出闪粉（若产品本身不含闪粉则忽略这句话） | AC69: Snowy Wu | AD69: 4.0808 | AE69: =AD69*I69 -> 9793.92 | AF69: 94440-3.5 | AG69: 92107-S001 | AH69: 已入 | AJ69: =I69 -> 2400 | AP69: =I69 -> 2400 | AX69: =I69/4 -> 600 | AY69: =AX69 -> 600 | AZ69: =AX69 -> 600 | BA69: =AX69 -> 600 | BF69: =SUM(AT69:BE69)-I69 -> 0 | BJ69: =I69 -> 2400 | BL69: MA | BN69: =I69/4 -> 600 | BO69: =I69/4 -> 600 | BP69: =I69/4 -> 600 | BQ69: =I69/4 -> 600 | BR69: =BN69+BO69+BP69+BQ69-I69 -> 0 | BS69: =BN69+BO69+BP69+BQ69+$BS$290 -> 514880 | BT69: =BT68-BN69 -> 117064 | BU69: =BU68-BO69 -> 118272 | BV69: =BV68-BP69 -> 118281 | BW69: =BW68-BQ69 -> 118614.33
A70: 45650 | B70: TARGET AUSTRALIA PTY LTD | C70: 澳大利亚 | D70: 4500154618 | E70: 2385667 | F70: 4500154618-50 | G70: 92107-S001 | H70: 摇篮公子 | I70: 1504 | J70: 0 | K70: 8 | L70: =I70/K70 -> 188 | M70: 45712 | N70: 45708 | P70: PASS | U70: 2/26-2/28出 | W70: 12/24收到 | Y70: 2/12-外箱贴纸SSCC | AB70: 日期码格式：ZURU INC(BVI) 标准格式 日期：按实际生产日期 Packaging Info: 4. 92107:MA_1L UPC版本包装（收缩膜和收藏指南, MA首选1L，如无1L可用多语且含英语的配套多语包装）+ 箱唛 +外箱贴纸SSCC Label；4 Assortment Ratio (Ladybug: Giraffe: Butterfly: Elephant)=1:1:1:1; Remark: 1. 客人要求箱唛不可出现任何手写内容，重量与实际一致且不可手写; 2. 此单去澳大利亚，请按相应澳新标准生产; 3. 使用普通透明封箱胶封箱（若有客版封箱胶带库存可先消耗完库存） 4. 外箱需要贴Target SSCC LABEL,客供PDF文档，工厂自行订购。请贴在正唛右下角（一箱一张，贴1面正唛右下角,封箱胶纸不能挡住贴纸内容。)；外箱贴纸距离外箱边缘应在2cm以上。如果正唛无位置可以贴在侧唛。 5. 外箱材质为ZURU标准； 6. 产品和包装上要有tracking label信息：格式为Zuru标准格式（可以自行调整具体年月日生产日期,避开节假期日）； 7. SSCC Label 尺寸更新为：4x4 inch。 8. 请务必按时完货，验货PASS后请按时送货入货代指定仓库，如果晚了导致船期Delay将会有罚金产生或者客户要求空运，所产生的罚金和空运费由工厂承担。 | AC70: Christine Liao | AD70: 4.0921 | AE70: =AD70*I70 -> 6154.5184 | AF70: 94374-2.27 | AG70: 92107-S001 | AH70: 已入 | AJ70: =I70 -> 1504 | AP70: =I70 -> 1504 | AX70: =I70/4 -> 376 | AY70: =AX70 -> 376 | AZ70: =AX70 -> 376 | BA70: =AX70 -> 376 | BF70: =SUM(AT70:BE70)-I70 -> 0 | BJ70: =I70 -> 1504 | BL70: MA | BN70: =I70/4 -> 376 | BO70: =I70/4 -> 376 | BP70: =I70/4 -> 376 | BQ70: =I70/4 -> 376 | BR70: =BN70+BO70+BP70+BQ70-I70 -> 0 | BS70: =BN70+BO70+BP70+BQ70+$BS$290 -> 513984 | BT70: =BT69-BN70 -> 116688 | BU70: =BU69-BO70 -> 117896 | BV70: =BV69-BP70 -> 117905 | BW70: =BW69-BQ70 -> 118238.33
A71: 45660 | B71: THE ENTERTAINER | C71: 英国 | D71: 4500154847 | E71: FB12130 | F71: 4500154847-10 | G71: 92107-S001 | H71: 摇篮公子 | I71: 856 | J71: 0 | K71: 8 | L71: =I71/K71 -> 107 | M71: 45716 | N71: 45712 | P71: PASS | W71: 1/6收到 | Y71: 客户EAN条码(翻单4500148687) | AB71: 日期码格式：ZURU INC(BVI) 标准格式 日期：按实际生产日期 Packaging Info: 92107: MA最新1L-UPC配套包装+客户EAN条码（翻单4500148687）覆盖ZURU 原条码 Remark: *MA版本按工厂现有最新库存即可，订单出英国，请注意检查产品及包装应带UKCA图标，包装显示ZURU UK LTD信息，QC同事请查核，如有问题与跟单确认 *生产日期按实际（法定工作日），按ZURU标准格式即可 ，但是请知悉包装日期码需要早于或者等于外箱日期码 ，不能晚于外箱日期码 *请注意所有订单都需要经过ZURU QC验货并且通过后方可出货 *条码以订单显示为准 ，请安排生产前先核对 ，有问题请提出。 *所有产品按符合欧洲标准走货，需要是不含微塑料版本 。 *涉及到硼的，如可选择情况下应使用低硼版本 （slime 类别低硼一般低于300ppm)，无选择的应与跟单复核再安排 。 *条码以订单显示为准 ，请安排生产前先核对 ，有问题请提出。 *订单对应客户2个PO号 ，备注有显示 ，注意分开做货/验货/装柜 ，混装有罚款。 *样板： 请在1/20前每款寄出2pcs大货样到罗湖办公室 7B Sandy Shao收 | AC71: Sandy Shao | AD71: 4.0921 | AE71: =AD71*I71 -> 3502.8376 | AF71: 94436-3.4 | AG71: 92107-S001 | AH71: 已入 | AJ71: =I71 -> 856 | AP71: =I71 -> 856 | AX71: =I71/4 -> 214 | AY71: =AX71 -> 214 | AZ71: =AX71 -> 214 | BA71: =AX71 -> 214 | BF71: =SUM(AT71:BE71)-I71 -> 0 | BJ71: =I71 -> 856 | BL71: MA | BN71: =I71/4 -> 214 | BO71: =I71/4 -> 214 | BP71: =I71/4 -> 214 | BQ71: =I71/4 -> 214 | BR71: =BN71+BO71+BP71+BQ71-I71 -> 0 | BS71: =BN71+BO71+BP71+BQ71+$BS$290 -> 513336 | BT71: =BT70-BN71 -> 116474 | BU71: =BU70-BO71 -> 117682 | BV71: =BV70-BP71 -> 117691 | BW71: =BW70-BQ71 -> 118024.33
A72: 45665 | B72: TJX UK | C72: 英国 | D72: 4500155467 | E72: TJX UK: PO#50565022 | F72: 4500155467-60 | G72: 92107-S001 | H72: 摇篮公子 | I72: 528 | J72: 0 | K72: 8 | L72: =I72/K72 -> 66 | M72: 45719 | N72: 45715 | P72: PASS | U72: 3/13出 | W72: 1/8收到 | Y72: 无 | Z72: 1/10-客供价格贴纸 | AB72: 日期码格式：ZURU INC(BVI) 标准格式 日期：按实际生产日期 Packaging Info: TJX UK: PO#50565022(92107) 92107: MA3L (9Lwanrning)最新EAN包装+1张客供价格贴纸 Remark: 1. 出往UK的产品+包装务必打上UKCA logo ，否则客人会退货且当地会有罚款； 2. 订单必须经过ZURU QC验货并且通过后方可出货； 3. 订单每行对应客人不同的PO， 箱唛也有不同，做货的时候请分开堆放； 4. 订单每行对应客人不同的PO，即同款item的价格贴纸都不相同，请注意收到贴纸后不要弄混!（客人PO号请参考PO最后一栏remark）； 5. 价格贴纸位置为产品正面右上角，不能遮住产品信息，大货生产前，请把贴纸位置先发给跟单确认 6. 涉及到相关款式会有闪粉的或者微塑料的，请统一默认出无闪粉或者不含微塑料版本; 7. 外箱封箱必须是工字型封箱方式； | AC72: Sandy Shao | AD72: 4.2475 | AE72: =AD72*I72 -> 2242.68 | AF72: 94522-3.12 | AG72: 92107-S001-3L | AH72: 已入 | AL72: =I72 -> 528 | AP72: =I72 -> 528 | AX72: =I72/4 -> 132 | AY72: =AX72 -> 132 | AZ72: =AX72 -> 132 | BA72: =AX72 -> 132 | BF72: =SUM(AT72:BE72)-I72 -> 0 | BJ72: =I72 -> 528 | BL72: MA | BN72: =I72/4 -> 132 | BO72: =I72/4 -> 132 | BP72: =I72/4 -> 132 | BQ72: =I72/4 -> 132 | BR72: =BN72+BO72+BP72+BQ72-I72 -> 0 | BS72: =BN72+BO72+BP72+BQ72+$BS$290 -> 513008 | BT72: =BT71-BN72 -> 116342 | BU72: =BU71-BO72 -> 117550 | BV72: =BV71-BP72 -> 117559 | BW72: =BW71-BQ72 -> 117892.33
A73: 45666 | B73: KMART AUSTRALIA LTD | C73: 澳大利亚 | D73: 4500155599 | E73: 20604120 | F73: 4500155599-20 | G73: 92107-S001 | H73: 摇篮公子 | I73: 1504 | J73: 0 | K73: 8 | L73: =I73/K73 -> 188 | M73: 45719 | N73: 45716 | P73: PASS | U73: 3/5-3/7出 | W73: 1/9收到 | Y73: 2/10-防盗+1/9-外箱贴纸 | AB73: 日期码格式：ZURU INC(BVI) 标准格式 日期：按实际生产日期 Packaging Info: 92107: MA英语UPC版本包装（收缩膜和说明书, MA首选1L，如无1L可用多语且含英语的配套多语包装) + 1张防盗贴纸 (贴纸以及位置图翻单PO#4500125858）+ 箱唛 + 外箱SSCC Label Remark: 1.请务必按时完货，验货。并且按期送货入货代指定仓库，如果晚了导致船期Delay将会有罚金产生或者客户要求空运，所产生的罚金和空运费由工厂承担。 2.SSCC 外箱贴纸请同纸箱瓦楞纸方向（竖纹向）垂直，即外箱贴纸横着贴(注意条码不要被胶带粘住），贴1pc，贴1面正唛，封箱胶纸不能挡住贴纸内容。外箱贴纸 离外箱边距离不少于2cm。 3.外箱材质为ZURU标准； 4.此单需使用KMART封箱胶上下工字型封箱;从2019年6月开始，要用KMART 新版封箱胶带，此单要用"ANKO"封箱胶带 5.此单出口澳大利亚，请按相应的澳新标准生产； 6.产品和包装上生产批号的显示格式ZURU标准日期码格式 7.外箱信息不可手写，重量和体积需要与实际的一致(不可手写） 8. 每款item装箱后的G.W.超过10KG或者CBM超过0.13,(9.5KG或者以上，四舍五入后也属于10KG) 需在外箱上加印超 重或者Bulky LOGO，若发现我们资料没有，请 帮忙提醒 1)重量超过10kg但不超过16kg且CBM不超过0.13,10-16kg 超重logo 2）CBM超过0.13且重量少于17kg，bulky logo 3）不属于以上两种情况，需要使用相应重量范围内的超重logo 4）超重logo需要在外箱四面都印刷(箱唛右上角，两面侧唛超重logo需要尽量靠近毛重)，尺寸为:110mm height* 95mm width 9. 实际外箱重量跟印在箱唛上的数据差异不能超3%，尺寸按实际数据印刷 | AC73: Lydia Wu | AD73: 4.5774 | AE73: =AD73*I73 -> 6884.4096 | AF73: 94471-3.6 | AG73: 92107-S001 | AH73: 已入 | AJ73: =I73 -> 1504 | AP73: =I73 -> 1504 | AX73: =I73/4 -> 376 | AY73: =AX73 -> 376 | AZ73: =AX73 -> 376 | BA73: =AX73 -> 376 | BF73: =SUM(AT73:BE73)-I73 -> 0 | BJ73: =I73 -> 1504 | BL73: MA | BN73: =I73/4 -> 376 | BO73: =I73/4 -> 376 | BP73: =I73/4 -> 376 | BQ73: =I73/4 -> 376 | BR73: =BN73+BO73+BP73+BQ73-I73 -> 0 | BS73: =BN73+BO73+BP73+BQ73+$BS$290 -> 513984 | BT73: =BT72-BN73 -> 115966 | BU73: =BU72-BO73 -> 117174 | BV73: =BV72-BP73 -> 117183 | BW73: =BW72-BQ73 -> 117516.33
A74: 45579 | B74: WAL-MART CANADA CORP. | C74: 加拿大 | D74: 4500147525 | E74: 9650903909 | F74: 4500147525-20 | G74: 92107-S003-NB | H74: 摇篮公子 | I74: 400 | J74: 0 | K74: 1 | L74: =I74/K74 -> 400 | M74: 45722 | N74: 45719 | O74: 3/7-第三方验货 | P74: PASS | U74: 3/26出 | W74: 1/7收到 | X74: 无 | Y74: UPC条码贴纸翻单：4500146212 | AB74: 日期码格式：ZURU INC(BVI) 标准格式 日期：按实际生产日期 Packaging Info: #92107: MA3L收缩膜+UPC条码贴纸(UPC: 193052064738)+MA5L收藏指南+MA5L资料卡+MA5L胶袋+MA配件袋+MA2L布标 -产品配比: 4 Assortment Ratio (Ladybug: Giraffe: Butterfly: Elephant)=1:1:1:1 -翻单：4500146212 Remark: 1. #92108/92107/9296 须使用无硼slime; 2. 此单有箱唛； 4. 此单有第三方验货，烦请多备包装物料； ********************* a. 请确保产品符合1999年版本的加拿大环境保护法(CEPA)和2012年禁止某些有毒物质法规的要求。该产品不含任何在加拿大禁用的化学物质，包括但不限于有毒物 质清单中列出的化学物质，并且在为加拿大沃尔玛生产产品期间没有使用任何禁用化学物质。 Supplier certify that the products comply with the requirements of Canadian Environmental Protection Act, 1999 (CEPA), Prohibition of Certain To xic Substances Regulations, 2012. The products do not contain any chemicals that are banned in Canada, including but not limited to those listed in the Toxic Substances List and no banned chemicals were used during the manufacturing of product for Walmart Canada. 附件列表： (1) Letter of Guarantee for Canada banned chemicals - (1-5CA) b. 请确保产品在均质材料中的汞浓度不超过0.1%（按重量计）。 Supplier certify that the WAL-MART vendor products does not have a mercury concentration of more than 0.1% by weight in homogeneous material. 附件列表： (1) Letter of Guarantee for Mercury COC c. 请确保产品的塑料材料不含以下物质（SOR 2011-17 27B): Supplier certify that the plastic materials do not contain the following substances(SOR 2011-17 27B): (a) carbon tetrachloride or any substance that contains it; (b) methyl alcohol or any substance thay contains >1.0%; (c) petroleum distillates or any substance that contains >10% weight to volume of petroleum distillates; (d) benzene; (e) turpentine or any substance that contains >10% weight to volume of turpentine; (f) boric acid or salts of boric acid; or (g) ethyl ether. 附件列表： (1) Letter of Guarantee for WM CA-Other prohibited substances in plastic(less than 3 years) | AC74: Monica Zhou | AD74: 4.2223 | AE74: =AD74*I74 -> 1688.92 | AF74: ZB00027-3.21 | AG74: 92107-S003-NB-3L | AH74: 已入 | AL74: =I74 -> 400 | AP74: =I74 -> 400 | AX74: =I74/4 -> 100 | AY74: =AX74 -> 100 | AZ74: =AX74 -> 100 | BA74: =AX74 -> 100 | BF74: =SUM(AT74:BE74)-I74 -> 0 | BK74: =I74 -> 400 | BL74: MA | BN74: =I74/4 -> 100 | BO74: =I74/4 -> 100 | BP74: =I74/4 -> 100 | BQ74: =I74/4 -> 100 | BR74: =BN74+BO74+BP74+BQ74-I74 -> 0 | BS74: =BN74+BO74+BP74+BQ74+$BS$290 -> 512880 | BT74: =BT73-BN74 -> 115866 | BU74: =BU73-BO74 -> 117074 | BV74: =BV73-BP74 -> 117083 | BW74: =BW73-BQ74 -> 117416.33
A75: 45621 | B75: TOYS "R" US – JAPAN, LTD | C75: 日本 | D75: 4500152218 | E75: 46:0003108130 | F75: 4500152218-10 | G75: 92107-S008 | H75: 摇篮公子 (三款公仔） | I75: 448 | J75: 0 | K75: 8 | L75: =I75/K75 -> 56 | M75: 45723 | N75: 45719 | P75: PASS | U75: 3/21出 | W75: 11/25收到 | Y75: 日语贴纸翻4500135847）+6+贴纸 | AB75: 日期码格式：ZURU INC(BVI) 标准格式 日期：按实际生产日期 Tracking Code: Packaging Info: MA 1L UPC PKG A版收缩膜+MA 5L+23L Warning A版收藏指南 +日语贴纸(贴纸AW翻单4500135847）+1张6+贴纸覆盖3+。 Remark: 出日本， 大货品质/包装必须严格跟到PO#4500135847。 请特别留意此单仅出以下3款， 按以下的数量分配。 Ladybug: 149pcs Giraffe: 149pcs Butterfly: 150pcs 装箱按以下配比。 3 Assortment Ratio (Ladybug: Giraffe: Butterfly)=1:1:1, 2pcs of each+2pcs random=8pcs/CTN | AC75: Doris Shou | AD75: 4.0953 | AE75: =AD75*I75 -> 1834.6944 | AF75: 94586-3.21 | AG75: 92107-S001 | AH75: 已入 | AJ75: =I75 -> 448 | AP75: =I75 -> 448 | AX75: =I75/3 -> 149.33333 | AY75: =AX75 -> 149.33333 | AZ75: =AX75 -> 149.33333 | BF75: =SUM(AT75:BE75)-I75 -> 0 | BJ75: =I75 -> 448 | BL75: MA | BN75: =I75/3 -> 149.33333 | BO75: =I75/3 -> 149.33333 | BP75: =I75/3 -> 149.33333 | BR75: =BN75+BO75+BP75+BQ75-I75 -> 0 | BS75: =BN75+BO75+BP75+BQ75+$BS$290 -> 512928 | BT75: =BT74-BN75 -> 115716.67 | BU75: =BU74-BO75 -> 116924.67 | BV75: =BV74-BP75 -> 116933.67 | BW75: =BW74-BQ75 -> 117416.33
A76: 45621 | B76: TOYS "R" US – JAPAN, LTD | C76: 日本 | D76: 4500152221 | E76: 47:0003108132 | F76: 4500152221-10 | G76: 92107-S008 | H76: 摇篮公子 (三款公仔） | I76: 552 | J76: 0 | K76: 8 | L76: =I76/K76 -> 69 | M76: 45723 | N76: 45719 | P76: PASS | U76: 3/24出 | W76: 11/25收到 | Y76: 日语贴纸翻4500135847）+6+贴纸 | AB76: 日期码格式：ZURU INC(BVI) 标准格式 日期：按实际生产日期 Tracking Code: Packaging Info: MA 1L UPC PKG A版收缩膜+MA 5L+23L Warning A版收藏指南 +日语贴纸(贴纸AW翻单4500135847）+1张6+贴纸覆盖3+。 Remark: 出日本， 大货品质/包装必须严格跟到PO#4500135847。 请特别留意此单仅出以下3款， 按以下的数量分配。 Ladybug: 184pcs Giraffe: 184pcs Butterfly: 184pcs 装箱按以下配比。 3 Assortment Ratio (Ladybug: Giraffe: Butterfly)=1:1:1, 2pcs of each+2pcs random=8pcs/CTN | AC76: Doris Shou | AD76: 4.0839 | AE76: =AD76*I76 -> 2254.3128 | AF76: 94587-3.21 | AG76: 92107-S001 | AH76: 已入 | AJ76: =I76 -> 552 | AP76: =I76 -> 552 | AX76: =I76/3 -> 184 | AY76: =AX76 -> 184 | AZ76: =AX76 -> 184 | BF76: =SUM(AT76:BE76)-I76 -> 0 | BJ76: =I76 -> 552 | BL76: MA | BN76: =I76/3 -> 184 | BO76: =I76/3 -> 184 | BP76: =I76/3 -> 184 | BR76: =BN76+BO76+BP76+BQ76-I76 -> 0 | BS76: =BN76+BO76+BP76+BQ76+$BS$290 -> 513032 | BT76: =BT75-BN76 -> 115532.67 | BU76: =BU75-BO76 -> 116740.67 | BV76: =BV75-BP76 -> 116749.67 | BW76: =BW75-BQ76 -> 117416.33
A77: 45637 | B77: THE WAREHOUSE LIMITED | C77: 新西兰 | D77: 4500153609 | E77: 28662059 | F77: 4500153609-10 | G77: 92107-S001 | H77: 摇篮公子 | I77: 376 | J77: 0 | K77: 8 | L77: =I77/K77 -> 47 | M77: 45726 | N77: 45722 | P77: PASS | U77: 3/20出 | W77: 12/12收到 | Y77: 无 | AB77: 日期码格式：ZURU INC(BVI) 标准格式 日期：按实际生产日期 Packaging Info: MA UPC 英语包装（优先1L英语版本，或者3L/5L含英语都可） 此客人不接受易掉落或者剥落或者可直接触碰的闪粉，可降解也不行，但可以接受符合欧洲微塑料标准的珠光粉或者闪片。 Remark: 92107: 4 Assortment Ratio (Ladybug: Giraffe: Butterfly: Elephant)=1:1:1:1 | AC77: Abby Liang | AD77: 4.2589 | AE77: =AD77*I77 -> 1601.3464 | AF77: 94582-3.19 | AG77: 92107-S001 | AH77: 已入 | AJ77: =I77 -> 376 | AP77: =I77 -> 376 | AX77: =I77/4 -> 94 | AY77: =AX77 -> 94 | AZ77: =AX77 -> 94 | BA77: =AX77 -> 94 | BF77: =SUM(AT77:BE77)-I77 -> 0 | BJ77: =I77 -> 376 | BL77: MA | BN77: =I77/4 -> 94 | BO77: =I77/4 -> 94 | BP77: =I77/4 -> 94 | BQ77: =I77/4 -> 94 | BR77: =BN77+BO77+BP77+BQ77-I77 -> 0 | BS77: =BN77+BO77+BP77+BQ77+$BS$290 -> 512856 | BT77: =BT76-BN77 -> 115438.67 | BU77: =BU76-BO77 -> 116646.67 | BV77: =BV76-BP77 -> 116655.67 | BW77: =BW76-BQ77 -> 117322.33
A78: 45637 | B78: THE WAREHOUSE LIMITED | C78: 新西兰 | D78: 4500153723 | E78: 28659771 | F78: 4500153723-10 | G78: 92107-S001 | H78: 摇篮公子 | I78: 128 | J78: 0 | K78: 8 | L78: =I78/K78 -> 16 | M78: 45726 | N78: 45722 | P78: PASS | U78: 3/20出 | W78: 12/12收到 | Y78: 无 | AB78: 日期码格式：ZURU INC(BVI) 标准格式 日期：按实际生产日期 Packaging Info: MA UPC 英语包装（优先1L英语版本，或者3L/5L含英语都可） 此客人不接受易掉落或者剥落或者可直接触碰的闪粉，可降解也不行，但可以接受符合欧洲微塑料标准的珠光粉或者闪片。 Remark: 92107: 4 Assortment Ratio (Ladybug: Giraffe: Butterfly: Elephant)=1:1:1:1 | AC78: Abby Liang | AD78: 4.1036 | AE78: =AD78*I78 -> 525.2608 | AF78: 94598-3.21 | AG78: 92107-S001 | AH78: 已入 | AJ78: =I78 -> 128 | AP78: =I78 -> 128 | AX78: =I78/4 -> 32 | AY78: =AX78 -> 32 | AZ78: =AX78 -> 32 | BA78: =AX78 -> 32 | BF78: =SUM(AT78:BE78)-I78 -> 0 | BJ78: =I78 -> 128 | BL78: MA | BN78: =I78/4 -> 32 | BO78: =I78/4 -> 32 | BP78: =I78/4 -> 32 | BQ78: =I78/4 -> 32 | BR78: =BN78+BO78+BP78+BQ78-I78 -> 0 | BS78: =BN78+BO78+BP78+BQ78+$BS$290 -> 512608 | BT78: =BT77-BN78 -> 115406.67 | BU78: =BU77-BO78 -> 116614.67 | BV78: =BV77-BP78 -> 116623.67 | BW78: =BW77-BQ78 -> 117290.33
A79: 45674 | B79: ZURU Germany GMBH | C79: 德国 | D79: 4500156082 | E79: 5200006028 | F79: 4500156082-10 | G79: 92107-S002-NB-MTS | H79: 摇篮公子-无硼 | I79: 300 | J79: 0 | K79: 4 | L79: =I79/K79 -> 75 | M79: 45729 | N79: 45724 | P79: PASS | W79: 1/21收到 | Y79: 1/22-PL/HU/SK/CZ/RO警语贴纸 | AB79: 日期码格式：ZURU INC(BVI) 标准格式 日期：按实际生产日期 Packaging Info: 92107:MA 最新版版 3L-9Lwarning EAN 收缩膜+PL/HU/SK/CZ/RO警语贴纸+MA 最新版纸袋+MA 最新版5L Library Card+MA 最新版 5L-23L 收藏指南 + 最新 MA布标; Remark: 1.波兰内销单，需要通过ZURU 验货结果后才能出货 (工厂需要主动提前同ZURU QC预约验货避免延期出货造成不必要麻烦)； 2. 若有特定款有特殊外箱条码要求时,需要明确列出产品款对应的具体外箱条码号码/条码类型 (若无,可以忽略此需求) 3.所有出口欧洲的产品, 法规规定禁止在包装和共公众用的印刷品中使用矿物油中含有的物质, 包装印刷油墨中含有的MOAH/MOSH的质量浓度不能超过1%, 否则出货 到法国被抽检出现问题, 供应商需要对此负责; 4. date code: 外箱日期码要晚于或等于产品日期码，不能早于产品的日期码 5. 所有电子产品身上需要加字唛，为ZURU FRANCE 地址 (如无电子产品，或者产品布标有此地址，可忽略此信息) ZURU France 1/3, Rue d'Argenteuil 95210 SAINT-GRATIEN, FRANCE 6. 装柜时需要按照款式号码从小到大一款款依次装,避免终端仓库卸货混乱.若一个柜子涉及到几个不同国家内销单,装柜时需要一个国家装完后再装另一个国家的 产品,依次装柜,避免终端仓库因不同国家不同库位位置卸货混乱. (此点需要同工厂装柜人员强调) | AC79: SD82 | AD79: 4.1317 | AE79: =AD79*I79 -> 1239.51 | AF79: 94597-3.21 | AG79: 92107-S002-NB-3L | AH79: 已入 | AL79: =I79 -> 300 | AP79: =I79 -> 300 | AX79: =I79/4 -> 75 | AY79: =I79/4 -> 75 | AZ79: =I79/4 -> 75 | BA79: =I79/4 -> 75 | BF79: =SUM(AT79:BE79)-I79 -> 0 | BK79: =I79 -> 300 | BL79: MA | BN79: =I79/4 -> 75 | BO79: =I79/4 -> 75 | BP79: =I79/4 -> 75 | BQ79: =I79/4 -> 75 | BR79: =BN79+BO79+BP79+BQ79-I79 -> 0 | BS79: =BN79+BO79+BP79+BQ79+$BS$290 -> 512780 | BT79: =BT78-BN79 -> 115331.67 | BU79: =BU78-BO79 -> 116539.67 | BV79: =BV78-BP79 -> 116548.67 | BW79: =BW78-BQ79 -> 117215.33
A80: 45681 | B80: I-VISION TOYS.INC | C80: 韩国 | D80: 4500156433 | E80: IVI-0117BC | F80: 4500156433-10 | G80: 92107-S002-NB | H80: 摇篮公子—无硼 | I80: 2320 | J80: 0 | K80: 4 | L80: =I80/K80 -> 580 | M80: 45729 | N80: 45724 | P80: PASS | U80: 3/14出 | W80: 箱唛翻单4500141184 | Y80: 2/8-2张韩语贴纸 | AA80: 客版韩语收藏指南翻单4500141184 | AB80: 日期码格式：ZURU INC(BVI) 标准格式 日期：按实际生产日期 Packaging Info: 此单出韩国，92107/92108 需出新版口水胶（无硼版，无MIT） 92107:MA 1L PKG+2张韩语贴纸(正面一张韩语logo 贴纸，背面一张韩语警语贴纸（新稿）+客版韩语收藏指南翻单4500141184 ， 箱唛翻单4500141184 请确保大货包装的生产年月 信息跟到到贴纸上的一致。确保生产年份"2025" 月份"03" Remark: 由于韩国法律法规要求，吸塑需PET材质，产品需符合韩国KC测试标准。 92107 需出新版口水胶（无硼版，无MIT） | AC80: Doris Shou | AD80: 4.1089 | AE80: =AD80*I80 -> 9532.648 | AF80: 94520-3.12 | AG80: 92107-S002-NB-1 | AH80: 已入 | AJ80: =I80 -> 2320 | AS80: =I80 -> 2320 | AX80: =I80/4 -> 580 | AY80: =I80/4 -> 580 | AZ80: =I80/4 -> 580 | BA80: =I80/4 -> 580 | BF80: =SUM(AT80:BE80)-I80 -> 0 | BK80: =I80 -> 2320 | BL80: MA | BN80: =I80/4 -> 580 | BO80: =I80/4 -> 580 | BP80: =I80/4 -> 580 | BQ80: =I80/4 -> 580 | BR80: =BN80+BO80+BP80+BQ80-I80 -> 0 | BS80: =BN80+BO80+BP80+BQ80+$BS$290 -> 514800 | BT80: =BT79-BN80 -> 114751.67 | BU80: =BU79-BO80 -> 115959.67 | BV80: =BV79-BP80 -> 115968.67 | BW80: =BW79-BQ80 -> 116635.33
A81: 45677 | B81: Bol.com | C81: 新西兰 | D81: 4500156115 | E81: 7631985 | F81: 4500156115-10 | G81: 92107B-S001 | H81: 长颈鹿 | I81: 104 | J81: 0 | K81: 8 | L81: =I81/K81 -> 13 | M81: 45730 | N81: 45726 | P81: PASS | U81: 3/17出 | W81: 1/20收到 | Y81: 2/22-EAN条码贴纸 | AB81: 日期码格式：ZURU INC(BVI) 标准格式 日期：按实际生产日期 Tracking Code: Packaging Info: BOL NL(92107ABDE) 4. 92107ABDE ---92107B: 8PCS/CTN, Giraffe, Non-glitter; MA 3L(9L warning, EAN版本)B收缩膜+EAN条码贴纸(贴在收缩膜上)+MA 2L A布标+MA 5L(23L warning)B收藏指南+M A 5L B图书卡+MA 5L(9L warning)B Slime胶袋+MA B配件袋; 13. 验货时间不迟于2025/3/17. Remark: 1. 出欧洲产品不可含闪粉或者微塑料，若所涉产品无闪粉或不含微塑料可忽略此点； 2. 5 Surprise or Mini Brands涉及包装是2个及2个以上的球入PVC桶包装时，单个球上若有UPC#或者EAN#，请用白色贴纸覆盖住； 3. 箱唛资料按照提供的要求去做即可，无需再发回我方确认； 4.柜货产品务必拉网且要拉紧，拉网要求： A: 网要结实同时网格要细，纸箱不能从网格处跌落下来 B: 打网固定8-10个点。请提供拉网的装柜照片给船务确认 后柜子再离厂。" | AC81: Crystal Chen | AD81: 4.1036 | AE81: =AD81*I81 -> 426.7744 | AF81: 94548-3.14 | AG81: 92107B-S001-3L | AH81: 已入 | AL81: =I81 -> 104 | AP81: =I81 -> 104 | AZ81: =I81 -> 104 | BF81: =SUM(AT81:BE81)-I81 -> 0 | BJ81: =I81 -> 104 | BL81: MA | BP81: =I81 -> 104 | BR81: =BN81+BO81+BP81+BQ81-I81 -> 0 | BS81: =BN81+BO81+BP81+BQ81+$BS$290 -> 512584 | BT81: =BT80-BN81 -> 114751.67 | BU81: =BU80-BO81 -> 115959.67 | BV81: =BV80-BP81 -> 115864.67 | BW81: =BW80-BQ81 -> 116635.33
A82: 45677 | B82: Bol.com | C82: 新西兰 | D82: 4500156115 | E82: 7631985 | F82: 4500156115-20 | G82: 92107A-S001 | H82: 大象 | I82: 104 | J82: 0 | K82: 8 | L82: =I82/K82 -> 13 | M82: 45730 | N82: 45726 | P82: PASS | U82: 3/17出 | W82: 1/20收到 | Y82: 2/22-EAN条码贴纸 | AB82: 日期码格式：ZURU INC(BVI) 标准格式 日期：按实际生产日期 Tracking Code: Packaging Info: BOL NL(92107ABDE) 4. 92107ABDE ---92107A: 8PCS/CTN, Elephant<(>,<)> Non-glitter; MA 3L(9L warning, EAN版本)B收缩膜+EAN条码贴纸(贴在收缩膜上)+MA 2L A布标+MA 5L(23L warning)B收 藏指南+MA 5L B图书卡+MA 5L(9L warning)B Slime胶袋+MA B配件袋; 13. 验货时间不迟于2025/3/17. Remark: 1. 出欧洲产品不可含闪粉或者微塑料，若所涉产品无闪粉或不含微塑料可忽略此点； 2. 5 Surprise or Mini Brands涉及包装是2个及2个以上的球入PVC桶包装时，单个球上若有UPC#或者EAN#，请用白色贴纸覆盖住； 3. 箱唛资料按照提供的要求去做即可，无需再发回我方确认； 4.柜货产品务必拉网且要拉紧，拉网要求： A: 网要结实同时网格要细，纸箱不能从网格处跌落下来 B: 打网固定8-10个点。请提供拉网的装柜照片给船务确认 后柜子再离厂。" | AC82: Crystal Chen | AD82: 4.1036 | AE82: =AD82*I82 -> 426.7744 | AF82: 94548-3.14 | AG82: 92107A-S001-3L | AH82: 已入 | AL82: =I82 -> 104 | AP82: =I82 -> 104 | BA82: =I82 -> 104 | BF82: =SUM(AT82:BE82)-I82 -> 0 | BJ82: =I82 -> 104 | BL82: MA | BQ82: =I82 -> 104 | BR82: =BN82+BO82+BP82+BQ82-I82 -> 0 | BS82: =BN82+BO82+BP82+BQ82+$BS$290 -> 512584 | BT82: =BT81-BN82 -> 114751.67 | BU82: =BU81-BO82 -> 115959.67 | BV82: =BV81-BP82 -> 115864.67 | BW82: =BW81-BQ82 -> 116531.33
A83: 45677 | B83: Bol.com | C83: 新西兰 | D83: 4500156115 | E83: 7631985 | F83: 4500156115-40 | G83: 92107D-S001 | H83: 蝴蝶 | I83: 104 | J83: 0 | K83: 8 | L83: =I83/K83 -> 13 | M83: 45730 | N83: 45726 | P83: PASS | U83: 3/17出 | W83: 1/20收到 | Y83: 2/22-EAN条码贴纸 | AB83: 日期码格式：ZURU INC(BVI) 标准格式 日期：按实际生产日期 Tracking Code: Packaging Info: BOL NL(92107ABDE) 4. 92107ABDE ---92107D: 8PCS/CTN, Butterfly, Non-glitter; MA 3L(9L warning, EAN版本)B收缩膜+EAN条码贴纸(贴在收缩膜上)+MA 2L A布标+MA 5L(23L warning)B收藏指南 +MA 5L B图书卡+MA 5L(9L warning)B Slime胶袋+MA B配件袋; 13. 验货时间不迟于2025/3/17. Remark: 1. 出欧洲产品不可含闪粉或者微塑料，若所涉产品无闪粉或不含微塑料可忽略此点； 2. 5 Surprise or Mini Brands涉及包装是2个及2个以上的球入PVC桶包装时，单个球上若有UPC#或者EAN#，请用白色贴纸覆盖住； 3. 箱唛资料按照提供的要求去做即可，无需再发回我方确认； 4.柜货产品务必拉网且要拉紧，拉网要求： A: 网要结实同时网格要细，纸箱不能从网格处跌落下来 B: 打网固定8-10个点。请提供拉网的装柜照片给船务确认 后柜子再离厂。" | AC83: Crystal Chen | AD83: 4.1036 | AE83: =AD83*I83 -> 426.7744 | AF83: 94548-3.14 | AG83: 92107D-S001-3L | AH83: 已入 | AL83: =I83 -> 104 | AP83: =I83 -> 104 | AX83: =I83 -> 104 | BF83: =SUM(AT83:BE83)-I83 -> 0 | BJ83: =I83 -> 104 | BL83: MA | BN83: =I83 -> 104 | BR83: =BN83+BO83+BP83+BQ83-I83 -> 0 | BS83: =BN83+BO83+BP83+BQ83+$BS$290 -> 512584 | BT83: =BT82-BN83 -> 114647.67 | BU83: =BU82-BO83 -> 115959.67 | BV83: =BV82-BP83 -> 115864.67 | BW83: =BW82-BQ83 -> 116531.33
A84: 45677 | B84: Bol.com | C84: 新西兰 | D84: 4500156115 | E84: 7631985 | F84: 4500156115-80 | G84: 92107E-S001 | H84: 瓢虫 | I84: 104 | J84: 0 | K84: 8 | L84: =I84/K84 -> 13 | M84: 45730 | N84: 45726 | P84: PASS | U84: 3/17出 | W84: 1/20收到 | Y84: 2/22-EAN条码贴纸 | AB84: 日期码格式：ZURU INC(BVI) 标准格式 日期：按实际生产日期 Tracking Code: Packaging Info: BOL NL(92107ABDE) 4. 92107ABDE ---92107E: 8PCS/CTN, Ladybug, Non-glitter; MA 3L(9L warning, EAN版本)B收缩膜+EAN条码贴纸(贴在收缩膜上)+MA 2L A布标+MA 5L(23L warning)B收藏指南+M A 5L B图书卡+MA 5L(9L warning)B Slime胶袋+MA B配件袋; 13. 验货时间不迟于2025/3/17. Remark: 1. 出欧洲产品不可含闪粉或者微塑料，若所涉产品无闪粉或不含微塑料可忽略此点； 2. 5 Surprise or Mini Brands涉及包装是2个及2个以上的球入PVC桶包装时，单个球上若有UPC#或者EAN#，请用白色贴纸覆盖住； 3. 箱唛资料按照提供的要求去做即可，无需再发回我方确认； 4.柜货产品务必拉网且要拉紧，拉网要求： A: 网要结实同时网格要细，纸箱不能从网格处跌落下来 B: 打网固定8-10个点。请提供拉网的装柜照片给船务确认 后柜子再离厂。" | AC84: Crystal Chen | AD84: 4.1036 | AE84: =AD84*I84 -> 426.7744 | AF84: 94548-3.14 | AG84: 92107E-S001-3L | AH84: 已入 | AL84: =I84 -> 104 | AP84: =I84 -> 104 | AY84: =I84 -> 104 | BF84: =SUM(AT84:BE84)-I84 -> 0 | BJ84: =I84 -> 104 | BL84: MA | BO84: =I84 -> 104 | BR84: =BN84+BO84+BP84+BQ84-I84 -> 0 | BS84: =BN84+BO84+BP84+BQ84+$BS$290 -> 512584 | BT84: =BT83-BN84 -> 114647.67 | BU84: =BU83-BO84 -> 115855.67 | BV84: =BV83-BP84 -> 115864.67 | BW84: =BW83-BQ84 -> 116531.33
A85: 45694 | B85: ZETA | C85: 阿塞拜疆 | D85: 4500156829 | F85: 4500156829-20 | G85: 92107-S001 | H85: 摇篮公子 | I85: 120 | J85: 0 | K85: 8 | L85: =I85/K85 -> 15 | M85: 45736 | N85: 45733 | P85: PASS | U85: 收到SO | W85: 2/10收到 | Y85: 无 | AB85: 日期码格式：ZURU INC(BVI) 标准格式 日期：按实际生产日期 Packaging Info: 1. 无进口商贴纸 2. 1L MA 包装/PDQ Remark: 标准配比 | AC85: Ann Zhang | AD85: 4.1036 | AE85: =AD85*I85 -> 492.432 | AG85: 92107-S001 | AH85: 已入 | AJ85: =I85 -> 120 | AP85: =I85 -> 120 | AX85: =I85/4 -> 30 | AY85: =I85/4 -> 30 | AZ85: =I85/4 -> 30 | BA85: =I85/4 -> 30 | BF85: =SUM(AT85:BE85)-I85 -> 0 | BJ85: =I85 -> 120 | BL85: MA | BN85: =I85/4 -> 30 | BO85: =I85/4 -> 30 | BP85: =I85/4 -> 30 | BQ85: =I85/4 -> 30 | BR85: =BN85+BO85+BP85+BQ85-I85 -> 0 | BS85: =BN85+BO85+BP85+BQ85+$BS$290 -> 512600 | BT85: =BT163-BN85 -> 114467.67 | BU85: =BU163-BO85 -> 115675.67 | BV85: =BV163-BP85 -> 115684.67 | BW85: =BW163-BQ85 -> 116351.33
A86: 45683 | B86: MTA Trade | C86: 哈萨克斯坦 | D86: 4500156659 | F86: 4500156659-40 | G86: 92107-S001 | H86: 摇篮公子 | I86: 264 | J86: 0 | K86: 8 | L86: =I86/K86 -> 33 | M86: 45736 | N86: 45733 | P86: PASS | U86: 3/27出 | W86: 2/17收到 | Y86: 2/17-进口商贴纸 | AB86: 日期码格式：ZURU INC(BVI) 标准格式 日期：按实际生产日期 Packaging Info: 92107: 1L MA 收缩膜+进口商贴纸; MA指南; Remark: 标准配比 | AC86: Ann Zhang | AD86: 4.2589 | AE86: =AD86*I86 -> 1124.3496 | AF86: 94654-3.27 | AG86: 92107-S001 | AH86: 已入 | AJ86: =I86 -> 264 | AP86: =I86 -> 264 | AX86: =I86/4 -> 66 | AY86: =I86/4 -> 66 | AZ86: =I86/4 -> 66 | BA86: =I86/4 -> 66 | BF86: =SUM(AT86:BE86)-I86 -> 0 | BJ86: =I86 -> 264 | BL86: MA | BN86: =I86/4 -> 66 | BO86: =I86/4 -> 66 | BP86: =I86/4 -> 66 | BQ86: =I86/4 -> 66 | BR86: =BN86+BO86+BP86+BQ86-I86 -> 0 | BS86: =BN86+BO86+BP86+BQ86+$BS$290 -> 512744 | BT86: =BT85-BN86 -> 114401.67 | BU86: =BU85-BO86 -> 115609.67 | BV86: =BV85-BP86 -> 115618.67 | BW86: =BW85-BQ86 -> 116285.33
A87: 45695 | B87: DD’S DISCOUNTS | C87: 美国 | D87: 4500156873 | E87: 70058002 | F87: 4500156873-30 | G87: 92107-S001 | H87: 摇篮公子 | I87: 600 | J87: 0 | K87: 8 | L87: =I87/K87 -> 75 | M87: 45737 | N87: 45733 | P87: PASS | U87: 3/28出 | W87: 2/7收到 | Y87: 无 | Z87: 2/26- 客供价格贴纸 | AB87: 日期码格式：ZURU INC(BVI) 标准格式 日期：按实际生产日期 Packaging Info: 1.ZURU MA UPC 现有版本包装 + 客供价格贴纸，出口美国 , 优先使用MA 1L 最新版本 。 Remark: 1.ZURU MA UPC 现有版本包装 + 客供价格贴纸，出口美国 , 优先使用MA 1L 最新版本 。 2.价格贴纸位于包装正面右下角，不挡住重要信息即可，可适当调整 ，价格贴纸由跟单提供。 3.标准日期码格式，产品和包装必须有日期码 。 4.同个产品同个货期不可出现不同的包装。 5. 跟单提供ROSS通用的箱唛模版，工厂按实际45 PO上客户PO/Item号/装箱数 提供箱唛排版来确认。 | AC87: Taylor Liao | AD87: 4.2475 | AE87: =AD87*I87 -> 2548.5 | AF87: ZB00059-3.28 | AG87: 92107-S001 | AH87: 已入 | AJ87: =I87 -> 600 | AP87: =I87 -> 600 | AX87: =I87/4 -> 150 | AY87: =I87/4 -> 150 | AZ87: =I87/4 -> 150 | BA87: =I87/4 -> 150 | BF87: =SUM(AT87:BE87)-I87 -> 0 | BJ87: =I87 -> 600 | BL87: MA | BN87: =I87/4 -> 150 | BO87: =I87/4 -> 150 | BP87: =I87/4 -> 150 | BQ87: =I87/4 -> 150 | BR87: =BN87+BO87+BP87+BQ87-I87 -> 0 | BS87: =BN87+BO87+BP87+BQ87+$BS$290 -> 513080 | BT87: =BT86-BN87 -> 114251.67 | BU87: =BU86-BO87 -> 115459.67 | BV87: =BV86-BP87 -> 115468.67 | BW87: =BW86-BQ87 -> 116135.33
A88: 45700 | B88: FREDMEYER INC | C88: 美国 | D88: 4500157247 | E88: 000038358088 | F88: 4500157247-10 | G88: 92107-S002 | H88: 摇篮公子 | I88: 600 | J88: 0 | K88: 4 | L88: =I88/K88 -> 150 | M88: 45737 | N88: =M88-4 -> 45733 | P88: PASS | U88: 3/21出 | W88: 2/12收到 | Y88: 无 | AB88: 日期码格式：ZURU INC(BVI) 标准格式 日期：按实际生产日期 Packaging Info: 1、包装方式: MA UPC优先1L最新版本，出口美国 Remark: 2、无测试无第三方验货要求。 3、纸箱4面印ZURU LOGO + 箱唛 4、日期码请按ZURU标准版执行即可。 5、ZURU QC验货。 6、Ratio:#92107: 4 Assortment Ratio (Ladybug: Giraffe: Butterfly: Elephant)=1:1:1:1 | AC88: Vicky Wu | AD88: 4.2738 | AE88: =AD88*I88 -> 2564.28 | AF88: ZB00058-3.28 | AG88: 92107-S002 | AH88: 已入 | AJ88: =I88 -> 600 | AP88: =I88 -> 600 | AX88: =I88/4 -> 150 | AY88: =I88/4 -> 150 | AZ88: =I88/4 -> 150 | BA88: =I88/4 -> 150 | BF88: =SUM(AT88:BE88)-I88 -> 0 | BJ88: =I88 -> 600 | BL88: MA | BN88: =I88/4 -> 150 | BO88: =I88/4 -> 150 | BP88: =I88/4 -> 150 | BQ88: =I88/4 -> 150 | BR88: =BN88+BO88+BP88+BQ88-I88 -> 0 | BS88: =BN88+BO88+BP88+BQ88+$BS$290 -> 513080 | BT88: =BT87-BN88 -> 114101.67 | BU88: =BU87-BO88 -> 115309.67 | BV88: =BV87-BP88 -> 115318.67 | BW88: =BW87-BQ88 -> 115985.33
A89: 45707 | B89: BRICKLAND LLC | C89: 蒙古 | D89: 4500158005 | E89: 2025Q1 | F89: 4500158005-20 | G89: 92107-S001 | H89: 摇篮公子 | I89: 360 | J89: 0 | K89: 8 | L89: =I89/K89 -> 45 | M89: 45738 | N89: 45734 | P89: PASS | U89: 3/26出 | W89: 3/24收到 | Y89: 进口商贴纸翻450014205 | AB89: 日期码格式：ZURU INC(BVI) 标准格式 日期：按实际生产日期 Packaging Info: MA UPC包装(优先1L)+1张进口商贴纸,贴纸aw及位置图翻单如下 92107-4500142053 Remark: 92107-4 Assortment Ratio (Ladybug: Giraffe: Butterfly: Elephant)=1:1:1:1 | AC89: Emma Wu | AD89: 4.2589 | AE89: =AD89*I89 -> 1533.204 | AF89: 94648-3.27 | AG89: 92107-S001 | AH89: 已入 | AJ89: =I89 -> 360 | AP89: =I89 -> 360 | AX89: =I89/4 -> 90 | AY89: =I89/4 -> 90 | AZ89: =I89/4 -> 90 | BA89: =I89/4 -> 90 | BJ89: =I89 -> 360 | BL89: MA | BN89: =I89/4 -> 90 | BO89: =I89/4 -> 90 | BP89: =I89/4 -> 90 | BQ89: =I89/4 -> 90 | BR89: =BN89+BO89+BP89+BQ89-I89 -> 0 | BS89: =BN89+BO89+BP89+BQ89+$BS$290 -> 512840 | BT89: =BT88-BN89 -> 114011.67 | BU89: =BU88-BO89 -> 115219.67 | BV89: =BV88-BP89 -> 115228.67 | BW89: =BW88-BQ89 -> 115895.33
A90: 45705 | B90: Royal Foods LLC | C90: 阿塞拜疆 | D90: 4500157780 | F90: 4500157780-20 | G90: 92107-S001 | H90: 摇篮公子 | I90: 136 | J90: 0 | K90: 8 | L90: =I90/K90 -> 17 | M90: 45741 | N90: 45737 | P90: PASS | U90: 4/17出 | W90: 2/17收到 | Y90: 无 | AB90: 日期码格式：ZURU INC(BVI) 标准格式 日期：按实际生产日期 Packaging Info: 1. 无进口商贴纸； 2. 92107 ： 1L MA UPC 包装， MA PDQ/说明书/指南（如有）； Remark: 标准配比 | AC90: Ann Zhang | AD90: 4.1036 | AE90: =AD90*I90 -> 558.0896 | AF90: 94710-4.7 | AG90: 92107-S001 | AH90: 已入 | AJ90: =I90 -> 136 | AP90: =I90 -> 136 | AX90: =I90/4 -> 34 | AY90: =I90/4 -> 34 | AZ90: =I90/4 -> 34 | BA90: =I90/4 -> 34 | BJ90: =I90 -> 136 | BL90: MA | BN90: =I90/4 -> 34 | BO90: =I90/4 -> 34 | BP90: =I90/4 -> 34 | BQ90: =I90/4 -> 34 | BR90: =BN90+BO90+BP90+BQ90-I90 -> 0 | BS90: =BN90+BO90+BP90+BQ90+$BS$290 -> 512616 | BT90: =BT89-BN90 -> 113977.67 | BU90: =BU89-BO90 -> 115185.67 | BV90: =BV89-BP90 -> 115194.67 | BW90: =BW89-BQ90 -> 115861.33
A91: 45652 | B91: CARREFOUR ARGENTINA | C91: 阿根廷 | D91: 4500154827 | F91: 4500154827-20 | G91: 92107F-S001 | H91: 摇篮公子展示架 | I91: 600 | J91: 0 | K91: 30 | L91: =I91/K91 -> 20 | M91: 45737 | N91: 45733 | O91: 3/25第三方 | P91: PASS | U91: 4/1出 | W91: 2/19收到-双坑纸箱 | Y91: 3/7-进口商贴纸+警告语贴纸+EAN贴纸 | Z91: 3/18-外箱贴纸 | AA91: DG20250213 | AB91: 日期码格式：ZURU INC(BVI) 标准格式 日期：按实际生产日期 Packaging Info: 1.92107F:MA 3L EAN包装+进口商贴纸+警告语贴纸（警告语贴纸贴于产品正面，不需要贴展示架）+EAN贴纸+色丁贴纸(贴MA布标上） 2.箱唛：在正唛（只1面）加多虚线15 X 10.5 CM ( 高X 宽) 距左箱边2CM， 距箱底 3CM,1张外箱贴纸Carrefour master carton label（在CHECKPOINT网站上订）, 工厂自行订购,可参照家乐福其他地区的。请检查贴纸上的外箱尺寸和重量是否和实际一致，如果材积超出正负7%，订购时要在系统更新资料并且通知给跟单。如果 第三方验货时发现与实际超出7%，会产生罚款USD300/每款ITEM。 3.产品/包装/外箱都要打上日期码，产品、包装和外箱的日期码要一致。 4.外箱纸箱要用双坑的，否则会影响出货。 5.此单有API第三方验货，，提供1套大货签板留底，请在大货前两周寄给我们，工厂需提交签板图片给客户审核。 6.签版要与大货一致。 7.此单因验厂问题，搏锐/沙沙岛/百炼需要送到兴信验货，验货时间待通知。 92107F 条码：4894680033603 Remark:92107F 包装条码：489469033603 | AC91: Ava Liang | AD91: 156.8365 | AE91: =AD91*L91 -> 3136.73 | AF91: 94681-4.1 | AG91: 92107F-S001-3L-NB-B | AH91: 已入 | AL91: =I91 -> 600 | AP91: =I91 -> 600 | AX91: =I91/4 -> 150 | AY91: =I91/4 -> 150 | AZ91: =I91/4 -> 150 | BA91: =I91/4 -> 150 | BF91: =SUM(AT91:BE91)-I91 -> 0 | BG91: =L91 -> 20 | BJ91: =I91 -> 600 | BL91: MA | BN91: =I91/4 -> 150 | BO91: =I91/4 -> 150 | BP91: =I91/4 -> 150 | BQ91: =I91/4 -> 150 | BR91: =BN91+BO91+BP91+BQ91-I91 -> 0 | BS91: =BN91+BO91+BP91+BQ91+$BS$290 -> 513080 | BT91: =BT90-BN91 -> 113827.67 | BU91: =BU90-BO91 -> 115035.67 | BV91: =BV90-BP91 -> 115044.67 | BW91: =BW90-BQ91 -> 115711.33
A92: 45698 | B92: CARREFOUR ARGENTINA | C92: 阿根廷 | D92: 4500154827 | F92: 4500154827-30 | G92: 92107-S001 | H92: 摇篮公子 | I92: 480 | J92: 0 | K92: 8 | L92: =I92/K92 -> 60 | M92: 45737 | N92: 45733 | O92: 3/25第三方 | P92: PASS | U92: 4/1出 | W92: 2/19收到-双坑纸箱 | Y92: 3/7-进口商贴纸+警告语贴纸+EAN贴纸 | Z92: 3/18-外箱贴纸 | AA92: DG20250213 | AB92: 日期码格式：ZURU INC(BVI) 标准格式 日期：按实际生产日期 Packaging Info: 1.92107:MA 3L EAN包装+进口商贴纸+警告语贴纸（警告语贴纸贴于产品正面，不需要贴展示架）+EAN贴纸+色丁贴纸(贴MA布标上） 2.箱唛：在正唛（只1面）加多虚线15 X 10.5 CM ( 高X 宽) 距左箱边2CM， 距箱底 3CM,1张外箱贴纸Carrefour master carton label（在CHECKPOINT网站上订）, 工厂自行订购,可参照家乐福其他地区的。请检查贴纸上的外箱尺寸和重量是否和实际一致，如果材积超出正负7%，订购时要在系统更新资料并且通知给跟单。如果 第三方验货时发现与实际超出7%，会产生罚款USD300/每款ITEM。 3.产品/包装/外箱都要打上日期码，产品、包装和外箱的日期码要一致。 4.外箱纸箱要用双坑的，否则会影响出货。 5.此单有API第三方验货，，提供1套大货签板留底，请在大货前两周寄给我们，工厂需提交签板图片给客户审核。 6.签版要与大货一致。 7.此单因验厂问题，搏锐/沙沙岛/百炼需要送到兴信验货，验货时间待通知。 Remark: 92107包装条码：489469033603 | AC92: Ava Liang | AD92: 4.1036 | AE92: =AD92*I92 -> 1969.728 | AF92: 94681-4.1 | AG92: 92107-S001-3L | AH92: 已入 | AL92: =I92 -> 480 | AP92: =I92 -> 480 | AX92: =I92/4 -> 120 | AY92: =I92/4 -> 120 | AZ92: =I92/4 -> 120 | BA92: =I92/4 -> 120 | BF92: =SUM(AT92:BE92)-I92 -> 0 | BJ92: =I92 -> 480 | BL92: MA | BN92: =I92/4 -> 120 | BO92: =I92/4 -> 120 | BP92: =I92/4 -> 120 | BQ92: =I92/4 -> 120 | BR92: =BN92+BO92+BP92+BQ92-I92 -> 0 | BS92: =BN92+BO92+BP92+BQ92+$BS$290 -> 512960 | BT92: =BT91-BN92 -> 113707.67 | BU92: =BU91-BO92 -> 114915.67 | BV92: =BV91-BP92 -> 114924.67 | BW92: =BW91-BQ92 -> 115591.33
A93: 45698 | B93: Ambiental Paraguay | C93: 巴拉圭 | D93: 4500156544 | F93: 4500156544-40 | G93: 92107-S001 | H93: 摇篮公子 | I93: 600 | J93: 0 | K93: 8 | L93: =I93/K93 -> 75 | M93: 45737 | N93: 45733 | P93: PASS | U93: 3/27出 | W93: 2/10收到 | Y93: 2/19-进口商贴纸 | AB93: 日期码格式：ZURU INC(BVI) 标准格式 日期：按实际生产日期 Packaging Info: 92107:MA 3L EAN包装+进口商贴纸（进口商贴纸+UPC贴纸合并为一张）+箱唛 Remark: | AC93: Ava Liang | AD93: 4.2475 | AE93: =AD93*I93 -> 2548.5 | AF93: 94726-4.8 | AG93: 92107-S001-3L | AH93: 已入 | AL93: =I93 -> 600 | AP93: =I93 -> 600 | AX93: =I93/4 -> 150 | AY93: =I93/4 -> 150 | AZ93: =I93/4 -> 150 | BA93: =I93/4 -> 150 | BF93: =SUM(AT93:BE93)-I93 -> 0 | BJ93: =I93 -> 600 | BL93: MA | BN93: =I93/4 -> 150 | BO93: =I93/4 -> 150 | BP93: =I93/4 -> 150 | BQ93: =I93/4 -> 150 | BR93: =BN93+BO93+BP93+BQ93-I93 -> 0 | BS93: =BN93+BO93+BP93+BQ93+$BS$290 -> 513080 | BT93: =BT92-BN93 -> 113557.67 | BU93: =BU92-BO93 -> 114765.67 | BV93: =BV92-BP93 -> 114774.67 | BW93: =BW92-BQ93 -> 115441.33
A94: 45701 | B94: TJX UK | C94: 英国 | D94: 4500157606 | E94: TJX UK: PO#50565115 | F94: 4500157606-40 | G94: 92107-S001 | H94: 摇篮公子 | I94: 680 | J94: 0 | K94: 8 | L94: =I94/K94 -> 85 | M94: 45747 | N94: 45743 | P94: PASS | U94: 4/2出 | W94: 2/24收到 | Y94: 无 | Z94: 3/10-客供价格贴纸 | AB94: 日期码格式：ZURU INC(BVI) 标准格式 日期：按实际生产日期 Packaging Info: TJX UK: PO#50565115(92107) 92107: MA3L (9Lwanrning)最新EAN包装+1张客供价格贴纸 Remark: 1. 出往UK的产品+包装务必打上UKCA logo ，否则客人会退货且当地会有罚款； 2. 订单必须经过ZURU QC验货并且通过后方可出货； 3. 订单每行对应客人不同的PO， 箱唛也有不同，做货的时候请分开堆放； 4. 包装条码请按包装备注上的对应的警示语语种包装，出德国的订单(订单备注为TJX Europe-DE)需要确保有英语+德语+荷兰语+波兰语警示语； 5. 订单每行对应客人不同的PO，即同款item的价格贴纸都不相同，请注意收到贴纸后不要弄混!（客人PO号请参考PO最后一栏remark）； 6. 客供价格贴纸位置为产品正面右上角，不能遮住产品信息，大货生产前，请把贴纸位置先发给跟单确认 7. 涉及到相关款式会有闪粉的或者微塑料的，请统一默认出无闪粉或者不含微塑料版本; 8. 外箱封箱必须是工字型封箱方式； | AC94: Sandy Shao | AD94: 4.0921 | AE94: =AD94*I94 -> 2782.628 | AF94: 94686-4.1 | AG94: 92107-S001-3L | AH94: 已入 | AL94: =I94 -> 680 | AP94: =I94 -> 680 | AX94: =I94/4 -> 170 | AY94: =I94/4 -> 170 | AZ94: =I94/4 -> 170 | BA94: =I94/4 -> 170 | BF94: =SUM(AT94:BE94)-I94 -> 0 | BJ94: =I94 -> 680 | BL94: MA | BN94: =I94/4 -> 170 | BO94: =I94/4 -> 170 | BP94: =I94/4 -> 170 | BQ94: =I94/4 -> 170 | BR94: =BN94+BO94+BP94+BQ94-I94 -> 0 | BS94: =BN94+BO94+BP94+BQ94+$BS$290 -> 513160 | BT94: =BT93-BN94 -> 113387.67 | BU94: =BU93-BO94 -> 114595.67 | BV94: =BV93-BP94 -> 114604.67 | BW94: =BW93-BQ94 -> 115271.33
A95: 45701 | B95: TJX UK c/o TJX Distribution Ltd & C | C95: 德国 | D95: 4500157593 | E95: TJX UK c/o TJX Distribution Ltd & C | F95: 4500157593-90 | G95: 92107-S001 | H95: 摇篮公子 | I95: 504 | J95: 0 | K95: 8 | L95: =I95/K95 -> 63 | M95: 45747 | N95: 45743 | P95: PASS | W95: 2/24收到 | Y95: 2/13-波兰语警告语 | Z95: 3/10-客供价格贴纸 | AB95: 日期码格式：ZURU INC(BVI) 标准格式 日期：按实际生产日期 Packaging Info: TJX Eur ope-DE: PO#55565212(92107) 92107: MA3L (9Lwanrning)最新EAN包装+1张客供价格贴纸+1张贴纸（含波兰语警告语) Remark: 1. 出往UK的产品+包装务必打上UKCA logo ，否则客人会退货且当地会有罚款； 2. 订单必须经过ZURU QC验货并且通过后方可出货； 3. 订单每行对应客人不同的PO， 箱唛也有不同，做货的时候请分开堆放； 4. 包装条码请按包装备注上的对应的警示语语种包装，出德国的订单(订单备注为TJX Europe-DE)需要确保有英语+德语+荷兰语+波兰语警示语； 5. 订单每行对应客人不同的PO，即同款item的价格贴纸都不相同，请注意收到贴纸后不要弄混!（客人PO号请参考PO最后一栏remark）； 6. 客供价格贴纸位置为产品正面右上角，不能遮住产品信息，大货生产前，请把贴纸位置先发给跟单确认 7. 涉及到相关款式会有闪粉的或者微塑料的，请统一默认出无闪粉或者不含微塑料版本; 8. 外箱封箱必须是工字型封箱方式； | AC95: Sandy Shao | AD95: 4.2475 | AE95: =AD95*I95 -> 2140.74 | AF95: 94685-4.1 | AG95: 92107-S001-3L | AH95: 已入 | AL95: =I95 -> 504 | AP95: =I95 -> 504 | AX95: =I95/4 -> 126 | AY95: =I95/4 -> 126 | AZ95: =I95/4 -> 126 | BA95: =I95/4 -> 126 | BF95: =SUM(AT95:BE95)-I95 -> 0 | BJ95: =I95 -> 504 | BL95: MA | BN95: =I95/4 -> 126 | BO95: =I95/4 -> 126 | BP95: =I95/4 -> 126 | BQ95: =I95/4 -> 126 | BR95: =BN95+BO95+BP95+BQ95-I95 -> 0 | BS95: =BN95+BO95+BP95+BQ95+$BS$290 -> 512984 | BT95: =BT94-BN95 -> 113261.67 | BU95: =BU94-BO95 -> 114469.67 | BV95: =BV94-BP95 -> 114478.67 | BW95: =BW94-BQ95 -> 115145.33
A96: 45579 | B96: WAL-MART CANADA CORP. | C96: 加拿大 | D96: 4500147528 | E96: 9650903910 | F96: 4500147528-20 | G96: 92107-S003-NB | H96: 摇篮公子 | I96: 400 | J96: 0 | K96: 1 | L96: =I96/K96 -> 400 | M96: 45748 | N96: 45744 | O96: 3/31第三方（自检） | P96: PASS | U96: 4/15出 | W96: 2/24收到 | X96: 无 | Y96: UPC条码贴纸翻单：4500146212 | AB96: 日期码格式：ZURU INC(BVI) 标准格式 日期：按实际生产日期 Packaging Info: #92107: MA3L收缩膜+UPC条码贴纸(UPC: 193052064738)+MA5L收藏指南+MA5L资料卡+MA5L胶袋+MA配件袋+MA2L布标 -产品配比: 4 Assortment Ratio (Ladybug: Giraffe: Butterfly: Elephant)=1:1:1:1 -翻单：4500146212 Remark: 1. #92108/92107/9296 须使用无硼slime; 2. 此单有箱唛； 4. 此单有第三方验货，烦请多备包装物料； ********************* a. 请确保产品符合1999年版本的加拿大环境保护法(CEPA)和2012年禁止某些有毒物质法规的要求。该产品不含任何在加拿大禁用的化学物质，包括但不限于有毒物 质清单中列出的化学物质，并且在为加拿大沃尔玛生产产品期间没有使用任何禁用化学物质。 Supplier certify that the products comply with the requirements of Canadian Environmental Protection Act, 1999 (CEPA), Prohibition of Certain To xic Substances Regulations, 2012. The products do not contain any chemicals that are banned in Canada, including but not limited to those listed in the Toxic Substances List and no banned chemicals were used during the manufacturing of product for Walmart Canada. 附件列表： (1) Letter of Guarantee for Canada banned chemicals - (1-5CA) b. 请确保产品在均质材料中的汞浓度不超过0.1%（按重量计）。 Supplier certify that the WAL-MART vendor products does not have a mercury concentration of more than 0.1% by weight in homogeneous material. 附件列表： (1) Letter of Guarantee for Mercury COC c. 请确保产品的塑料材料不含以下物质（SOR 2011-17 27B): Supplier certify that the plastic materials do not contain the following substances(SOR 2011-17 27B): (a) carbon tetrachloride or any substance that contains it; (b) methyl alcohol or any substance thay contains >1.0%; (c) petroleum distillates or any substance that contains >10% weight to volume of petroleum distillates; (d) benzene; (e) turpentine or any substance that contains >10% weight to volume of turpentine; (f) boric acid or salts of boric acid; or (g) ethyl ether. 附件列表： (1) Letter of Guarantee for WM CA-Other prohibited substances in plastic(less than 3 years) | AC96: Monica Zhou | AD96: 4.4107 | AE96: =AD96*I96 -> 1764.28 | AF96: 94761-4.14 | AG96: 92107-S003-NB-3L | AH96: 已入 | AL96: =I96 -> 400 | AP96: =I96 -> 400 | AX96: =I96/4 -> 100 | AY96: =AX96 -> 100 | AZ96: =AX96 -> 100 | BA96: =AX96 -> 100 | BF96: =SUM(AT96:BE96)-I96 -> 0 | BK96: =I96 -> 400 | BL96: MA | BN96: =I96/4 -> 100 | BO96: =I96/4 -> 100 | BP96: =I96/4 -> 100 | BQ96: =I96/4 -> 100 | BR96: =BN96+BO96+BP96+BQ96-I96 -> 0 | BS96: =BN96+BO96+BP96+BQ96+$BS$290 -> 512880 | BT96: =BT95-BN96 -> 113161.67 | BU96: =BU95-BO96 -> 114369.67 | BV96: =BV95-BP96 -> 114378.67 | BW96: =BW95-BQ96 -> 115045.33
A97: 45715 | B97: KMART AUSTRALIA LTD | C97: 澳大利亚 | D97: 4500158785 | E97: 20661144 | F97: 4500158785-70 | G97: 92107-S001 | H97: 摇篮公子 | I97: 1504 | J97: 0 | K97: 8 | L97: =I97/K97 -> 188 | M97: 45754 | N97: 45750 | P97: PASS | U97: 4/9-4/11出 | W97: 3/3收到 | Y97: 3/10-防盗贴纸+3/17-外箱贴纸 | AB97: 日期码格式：ZURU INC(BVI) 标准格式 日期：按实际生产日期 Packaging Info: 92107: MA英语UPC版本包装（收缩膜和说明书, MA首选1L，如无1L可用多语且含英语的配套多语包装) + 1张防盗贴纸 (贴纸以及位置图翻单PO#4500125858）+ 箱唛 + 外箱SSCC Label Remark: 1.请务必按时完货，验货。并且按期送货入货代指定仓库，如果晚了导致船期Delay将会有罚金产生或者客户要求空运，所产生的罚金和空运费由工厂承担。 2.SSCC 外箱贴纸请同纸箱瓦楞纸方向（竖纹向）垂直，即外箱贴纸横着贴(注意条码不要被胶带粘住），贴1pc，贴1面正唛，封箱胶纸不能挡住贴纸内容。外箱贴纸 离外箱边距离不少于2cm。 3.外箱材质为ZURU标准； 4.此单需使用KMART封箱胶上下工字型封箱;从2019年6月开始，要用KMART 新版封箱胶带，此单要用"ANKO"封箱胶带 5.此单出口澳大利亚，请按相应的澳新标准生产； 6.产品和包装上生产批号的显示格式ZURU标准日期码格式 7.外箱信息不可手写，重量和体积需要与实际的一致(不可手写） 8. 每款item装箱后的G.W.超过10KG或者CBM超过0.13,(9.5KG或者以上，四舍五入后也属于10KG) 需在外箱上加印超 重或者Bulky LOGO，若发现我们资料没有，请 帮忙提醒 1)重量超过10kg但不超过16kg且CBM不超过0.13,10-16kg 超重logo 2）CBM超过0.13且重量少于17kg，bulky logo 3）不属于以上两种情况，需要使用相应重量范围内的超重logo 4）超重logo需要在外箱四面都印刷(箱唛右上角，两面侧唛超重logo需要尽量靠近毛重)，尺寸为:110mm height* 95mm width 9. 实际外箱重量跟印在箱唛上的数据差异不能超3%，尺寸按实际数据印刷 | AC97: Lydia Wu | AD97: 4.5774 | AE97: =AD97*I97 -> 6884.4096 | AF97: 94744-4.10 | AG97: 92107-S001 | AH97: 已入 | AJ97: =I97 -> 1504 | AP97: =I97 -> 1504 | AX97: =I97/4 -> 376 | AY97: =AX97 -> 376 | AZ97: =AX97 -> 376 | BA97: =AX97 -> 376 | BF97: =SUM(AT97:BE97)-I97 -> 0 | BJ97: =I97 -> 1504 | BL97: MA | BN97: =I97/4 -> 376 | BO97: =I97/4 -> 376 | BP97: =I97/4 -> 376 | BQ97: =I97/4 -> 376 | BR97: =BN97+BO97+BP97+BQ97-I97 -> 0 | BS97: =BN97+BO97+BP97+BQ97+$BS$290 -> 513984 | BT97: =BT96-BN97 -> 112785.67 | BU97: =BU96-BO97 -> 113993.67 | BV97: =BV96-BP97 -> 114002.67 | BW97: =BW96-BQ97 -> 114669.33
A98: 45716 | B98: MTA Trade | C98: 哈萨克斯坦 | D98: 4500158504 | F98: 4500158504-20 | G98: 92107D-S001 | H98: 蝴蝶 | I98: 200 | J98: 0 | K98: 8 | L98: =I98/K98 -> 25 | M98: 45756 | N98: 45752 | P98: PASS | U98: 4/16出 | W98: 3/4收到 | Y98: 3/7-进口商贴纸 | AB98: 日期码格式：ZURU INC(BVI) 标准格式 日期：按实际生产日期 Packaging Info: 1L MA 收缩膜+进口商贴纸; MA指南; Remark: 标准配比 | AC98: Cors Zhou | AD98: 4.2589 | AE98: =AD98*I98 -> 851.78 | AF98: 94776-4.16 | AG98: 92107D-S001 | AH98: 已入 | AJ98: =I98 -> 200 | AP98: =I98 -> 200 | AX98: =I98 -> 200 | BF98: =SUM(AT98:BE98)-I98 -> 0 | BJ98: =I98 -> 200 | BL98: MA | BN98: =I98 -> 200 | BR98: =BN98+BO98+BP98+BQ98-I98 -> 0 | BS98: =BN98+BO98+BP98+BQ98+$BS$290 -> 512680 | BT98: =BT97-BN98 -> 112585.67 | BU98: =BU97-BO98 -> 113993.67 | BV98: =BV97-BP98 -> 114002.67 | BW98: =BW97-BQ98 -> 114669.33
A99: 45716 | B99: MTA Trade | C99: 哈萨克斯坦 | D99: 4500158504 | F99: 4500158504-10 | G99: 92107B-S001 | H99: 长颈鹿 | I99: 200 | J99: 0 | K99: 8 | L99: =I99/K99 -> 25 | M99: 45756 | N99: 45752 | P99: PASS | U99: 4/16出 | W99: 3/4收到 | Y99: 3/7-进口商贴纸 | AB99: 日期码格式：ZURU INC(BVI) 标准格式 日期：按实际生产日期 Packaging Info: 1L MA 收缩膜+进口商贴纸; MA指南; Remark: 标准配比 | AC99: Cors Zhou | AD99: 4.2589 | AE99: =AD99*I99 -> 851.78 | AF99: 94776-4.16 | AG99: 92107B-S001 | AH99: 已入 | AJ99: =I99 -> 200 | AP99: =I99 -> 200 | AZ99: =I99 -> 200 | BF99: =SUM(AT99:BE99)-I99 -> 0 | BJ99: =I99 -> 200 | BL99: MA | BP99: =I99 -> 200 | BR99: =BN99+BO99+BP99+BQ99-I99 -> 0 | BS99: =BN99+BO99+BP99+BQ99+$BS$290 -> 512680 | BT99: =BT98-BN99 -> 112585.67 | BU99: =BU98-BO99 -> 113993.67 | BV99: =BV98-BP99 -> 113802.67 | BW99: =BW98-BQ99 -> 114669.33
A100: 45716 | B100: MTA Trade | C100: 哈萨克斯坦 | D100: 4500158504 | F100: 4500158504-30 | G100: 92107E-S001 | H100: 瓢虫 | I100: 200 | J100: 0 | K100: 8 | L100: =I100/K100 -> 25 | M100: 45756 | N100: 45752 | P100: PASS | U100: 4/16出 | W100: 3/4收到 | Y100: 3/7-进口商贴纸 | AB100: 日期码格式：ZURU INC(BVI) 标准格式 日期：按实际生产日期 Packaging Info: 1L MA 收缩膜+进口商贴纸; MA指南; Remark: 标准配比 | AC100: Cors Zhou | AD100: 4.2589 | AE100: =AD100*I100 -> 851.78 | AF100: 94776-4.16 | AG100: 92107E-S001 | AH100: 已入 | AJ100: =I100 -> 200 | AP100: =I100 -> 200 | AY100: =I100 -> 200 | BF100: =SUM(AT100:BE100)-I100 -> 0 | BJ100: =I100 -> 200 | BL100: MA | BO100: =I100 -> 200 | BR100: =BN100+BO100+BP100+BQ100-I100 -> 0 | BS100: =BN100+BO100+BP100+BQ100+$BS$290 -> 512680 | BT100: =BT99-BN100 -> 112585.67 | BU100: =BU99-BO100 -> 113793.67 | BV100: =BV99-BP100 -> 113802.67 | BW100: =BW99-BQ100 -> 114669.33
...

Sheet 92108
A1: ZURU Babycorns Surprise - S1生产排期表 #92108 | J1: 不带电出货 | BC1: 中东客 | BF1: ICMA剩余 | BG1: ='IC MA'!S10-'IC MA'!S6-BF111 -> 1035615 | BR1: 兔子（机芯款） | BS1: 兔子（小公仔） | BT1: 独角兽（机芯款） | BU1: 独角兽（小公仔） | BV1: 小猫（机芯款） | BW1: 美国猫（小公仔） | BX1: 斑点狗（机芯款） | BY1: 斑点狗（小公仔）
AD2: 收缩膜 | AJ2: 收藏指南 | AO2: 阅读卡 MA 5L | AS2: 阅读卡 MA 5L B版 | AW2: 阅读卡 中文 | BA2: 92108F | BC2: 134696 | BD2: 口水胶 | BF2: IC | BG2: 布标 | BI2: 兔子（机芯款） | BJ2: 兔子（小公仔） | BK2: 独角兽（机芯款） | BL2: 独角兽（小公仔） | BM2: 小猫（机芯款） | BN2: 美国猫（小公仔） | BO2: 斑点狗（机芯款） | BP2: 斑点狗（小公仔） | BQ2: 总MA | BR2: =生产MA!O19 -> 80000 | BS2: =生产MA!P19 -> 80000 | BT2: =生产MA!Q19 -> 80000 | BU2: =生产MA!R19 -> 80000 | BV2: =生产MA!S19 -> 122000 | BW2: =生产MA!T19 -> 122000 | BX2: =生产MA!U19 -> 80000 | BY2: =生产MA!V19 -> 80000 | BZ2: =SUM(BR2:BY2)/2 -> 362000
A3: 接单日期 | B3: 第三方客户名称 | C3: 国家 | D3: PO号 | E3: 173317 | F3: SKU | G3: ITEM# | H3: 中文名 | I3: PO数量 (pcs) | J3: 内箱装箱数量(pcs) | K3: 外箱装箱数量(pcs) | L3: 总箱数 | M3: ZURU订单走货日期 | N3: ZURU验货 日期 | O3: 第三方验货 | P3: 驗貨結果 | Q3: 船期SO | R3: 箱唛资料 | S3: 是否有外箱贴 | T3: 贴纸资料 | U3: 客供物料 | V3: 日期码 | W3: 备注 | X3: ZURU跟单 | Y3: 单价USD | Z3: 金额USD | AA3: 發票號 | AB3: 系统货号 | AC3: 是否入系统 | AD3: MA 1L | AE3: MA 1L B版 | AF3: MA 3L | AG3: MA 3L B版 | AH3: 134696中东客 客版 | AI3: 客版 | AJ3: MA 5L | AK3: MA 5L B版 | AL3: 134696中东客 客版 | AM3: 中文 | AN3: 客版 | AO3: bunny兔子A | AP3: unicorn独角兽D | AQ3: kitten小猫E | AR3: puppy斑点狗B | AS3: bunny兔子A | AT3: unicorn独角兽D | AU3: kitten小猫E | AV3: puppy斑点狗B | AW3: bunny兔子 | AX3: unicorn独角兽 | AY3: kitten小猫 | AZ3: puppy斑点狗 | BA3: 展示架-1L | BB3: 展示架-3L | BC3: #9283中的两款沙子代替slime | BD3: 有硼 | BE3: 无硼 | BF3: MA | BG3: MA/客版 | BI3: bunny 兔子 A | BK3: unicorn 独角兽 D | BM3: kitten 小猫 E | BO3: puppy 斑点狗 B | BQ3: 公仔合计 | BR3: MA剩余 | BS3: MA剩余 | BT3: MA剩余 | BU3: MA剩余 | BV3: MA剩余 | BW3: MA剩余 | BX3: MA剩余 | BY3: MA剩余
A4: 45289 | B4: ZURU | C4: 库有 | D4: ZPO2312006 | E4: PP订单 | G4: 92108-S001 | H4: 摇篮公子 | I4: 294 | J4: 0 | K4: 4 | L4: =I4/K4 -> 73.5 | M4: 45316 | N4: 45313 | R4: 无 | S4: 无 | T4: 无 | W4: 1.OA Testing Samples (BULK)：数量 8；地址 深圳市罗湖区东门南路106号口岸大楼17B ，Angus 2 CTN 2.QA Testing samples (FSDU)：数量 24；地址 深圳市罗湖区东门南路106号口岸大楼17B ，Angus 1FSDU 3.Signed Sample (6套签+1套用于拆办)：数量 28；地址 深圳市罗湖区东门南路1006号口岸大楼A栋3楼，Jessy Zhang 13421384408 ，7套*4款=28 4.Show room：数量 28；地址 清溪镇光朗村易京街25号《库有样板房) 收件人:李志强电话: 18328402533 ，7套 注：开PP时候帮忙额外准备3套散件邮寄到深圳办公室 5.Sample room samples：数量 292；地址 清溪镇光朗村易京街25号《库有样板房) 收件人:李志强电话: 18328402533 ，73套 注：开PP时候帮忙额外准备3套散件邮寄到深圳办公室 6.散件：数量 12；地址 深圳市罗湖区东门南路1006号口岸大楼A栋16楼，Max Mlai 13632761211 2 CTN 3套散件（除蛋壳外的所有内含物），每套单独装好 合计数量392；PP订单数量合计 500PCS 注:PP PO数量含buffer，请按PP PO数量准备物料 PP 数量包括了:QA 测试办、签样办、板房展厅样板 | AB4: 过渡 | AC4: 过渡 | BG4: MA | BI4: 0 | BJ4: 0 | BK4: 0 | BL4: 0 | BM4: 0 | BN4: 0 | BO4: 0 | BP4: 0 | BQ4: =$BQ$119+BJ4+BL4+BN4+BP4 -> 238025 | BR4: =$BR$2-BR119-BI4 -> 27131.75 | BS4: =$BR$2-BS119-BJ4 -> 27131.75 | BT4: =$BT$2-BT119-BK4 -> 27003.75 | BU4: =$BU$2-BU119-BL4 -> 27003.75 | BV4: =$BV$2-BV119-BM4 -> 42215.75 | BW4: =$BW$2-BW119-BN4 -> 42215.75 | BX4: =$BX$2-BX119-BO4 -> 27623.75 | BY4: =$BY$2-BY119-BP4 -> 27623.75
A5: 45390 | B5: ZURU | C5: 库有 | D5: ZMPO24254 | G5: 92108E-S003 | H5: 小猫 邮包盒装 | I5: 6 | J5: 0 | K5: 2 | L5: =I5/K5 -> 3 | M5: 45399 | N5: 45395 | R5: 无 | S5: 无 | T5: 无 | W5: 大货版本-UPC 193052067111 | AB5: 92108E-S003 | AC5: 已入 | AD5: =I5 -> 6 | AJ5: =AD5 -> 6 | AQ5: =AJ5 -> 6 | BD5: =I5 -> 6 | BF5: =I5 -> 6 | BG5: MA | BM5: =I5 -> 6 | BN5: =BM5 -> 6 | BQ5: =$BQ$119+BJ5+BL5+BN5+BP5 -> 238031 | BR5: =BR4-BI5 -> 27131.75 | BS5: =BS4-BJ5 -> 27131.75 | BT5: =BT4-BK5 -> 27003.75 | BU5: =BU4-BL5 -> 27003.75 | BV5: =BV4-BM5 -> 42209.75 | BW5: =BW4-BN5 -> 42209.75 | BX5: =BX4-BO5 -> 27623.75 | BY5: =BY4-BP5 -> 27623.75
A6: 45516 | B6: ZURU | C6: 库有 | D6: ZMPO24638 | G6: 92108-S001 | H6: 摇篮公子 | I6: 180 | J6: 0 | K6: 4 | L6: =I6/K6 -> 45 | M6: 45531 | N6: 45527 | P6: PAss | R6: 45516 | W6: 大货最新版本/款号平均/麻烦按款号装箱/并在外箱上注明款款号/请用大货标准箱装箱/箱唛请参照邮件附件;备注： 收到样品订单后尽快安排 ，注意样板品质质量要求要高于大货品质要求 ，送货时必须要附带送货单(没有送货单和QC检验合格报告的仓库一律拒绝收货)，请知悉，谢谢！ | AB6: 92108-S001 | AC6: 已入 | AD6: =I6 -> 180 | AJ6: =I6 -> 180 | AO6: =I6/4 -> 45 | AP6: =AO6 -> 45 | AQ6: =AP6 -> 45 | AR6: =AQ6 -> 45 | BD6: =I6 -> 180 | BF6: =I6 -> 180 | BG6: MA | BI6: =I6/4 -> 45 | BJ6: =BI6 -> 45 | BK6: =I6/4 -> 45 | BL6: =BK6 -> 45 | BM6: =I6/4 -> 45 | BN6: =BM6 -> 45 | BO6: =BN6 -> 45 | BP6: =BO6 -> 45 | BQ6: =$BQ$119+BJ6+BL6+BN6+BP6 -> 238205 | BR6: =BR5-BI6 -> 27086.75 | BS6: =BS5-BJ6 -> 27086.75 | BT6: =BT5-BK6 -> 26958.75 | BU6: =BU5-BL6 -> 26958.75 | BV6: =BV5-BM6 -> 42164.75 | BW6: =BW5-BN6 -> 42164.75 | BX6: =BX5-BO6 -> 27578.75 | BY6: =BY5-BP6 -> 27578.75
A7: 45561 | B7: WAL-MART CANADA CORP. | C7: 加拿大 | D7: 4500146212 | F7: 4500146212-10 | G7: 92108-S002-NB | H7: 摇篮公子 | I7: 1218 | J7: 0 | K7: 1 | L7: =I7/K7 -> 1218 | M7: 45621 | N7: 45617 | O7: 11/25抽办 12/18第三方 | P7: PAss | Q7: 1/6出 | R7: 10/31收到 | S7: 无 | T7: UPC条码贴纸9/26 | W7: 日期码格式：ZURU INC(BVI) 标准格式 日期：按实际生产日期 Packaging Info: #92108: MA3L收缩膜+UPC条码贴纸(UPC: 193052064721)+MA5L收藏指南+MA5L资料卡+MA5L胶袋+MA配件袋+MA2L布标 -产品配比: 4 Assortments (bunny: puppy: unicorn: kitten)=1:1:1:1 Remark: 1. #92108 须使用无硼slime; 3. 此单有箱唛； 4. 此单有第三方验货，烦请多备包装物料； 5. 此单#92108/92107/92105/9296/9554/15714 需签办；签办数量：大货样各3套; 6. 此单#92108/92107/92105/9296/9554 需于2024/11/25 抽办做测试；抽办数量：大货各5套; ********************* a. 请确保产品符合1999年版本的加拿大环境保护法(CEPA)和2012年禁止某些有毒物质法规的要求。该产品不含任何在加拿大禁用的化学物质，包括但不限于有毒物 质清单中列出的化学物质，并且在为加拿大沃尔玛生产产品期间没有使用任何禁用化学物质。 Supplier certify that the products comply with the requirements of Canadian Environmental Protection Act, 1999 (CEPA), Prohibition of Certain To xic Substances Regulations, 2012. The products do not contain any chemicals that are banned in Canada, including but not limited to those listed in the Toxic Substances List and no banned chemicals were used during the manufacturing of product for Walmart Canada. 附件列表： (1) Letter of Guarantee for Canada banned chemicals - (1-5CA) b. 请确保产品在均质材料中的汞浓度不超过0.1%（按重量计）。 Supplier certify that the WAL-MART vendor products does not have a mercury concentration of more than 0.1% by weight in homogeneous material. 附件列表： (1) Letter of Guarantee for Mercury COC c. 请确保产品的塑料材料不含以下物质（SOR 2011-17 27B): Supplier certify that the plastic materials do not contain the following substances(SOR 2011-17 27B): (a) carbon tetrachloride or any substance that contains it; (b) methyl alcohol or any substance thay contains >1.0%; (c) petroleum distillates or any substance that contains >10% weight to volume of petroleum distillates; (d) benzene; (e) turpentine or any substance that contains >10% weight to volume of turpentine; (f) boric acid or salts of boric acid; or (g) ethyl ether. 附件列表： (1) Letter of Guarantee for WM CA-Other prohibited substances in plastic(less than 3 years) | X7: Monica Zhou | Y7: 7.4679 | Z7: =Y7*I7 -> 9095.9022 | AA7: 94003-1.13 | AB7: 92108-S002-NB-3L | AC7: 已入 | AF7: =I7 -> 1218 | AJ7: =I7 -> 1218 | AO7: =I7/4 -> 304.5 | AP7: =AO7 -> 304.5 | AQ7: =AP7 -> 304.5 | AR7: =AQ7 -> 304.5 | BE7: =I7 -> 1218 | BF7: =I7 -> 1218 | BG7: MA | BI7: =I7/4 -> 304.5 | BJ7: =BI7 -> 304.5 | BK7: =BJ7 -> 304.5 | BL7: =BK7 -> 304.5 | BM7: =BL7 -> 304.5 | BN7: =BM7 -> 304.5 | BO7: =BN7 -> 304.5 | BP7: =BO7 -> 304.5 | BQ7: =$BQ$119+BJ7+BL7+BN7+BP7 -> 239243 | BR7: =BR6-BI7 -> 26782.25 | BS7: =BS6-BJ7 -> 26782.25 | BT7: =BT6-BK7 -> 26654.25 | BU7: =BU6-BL7 -> 26654.25 | BV7: =BV6-BM7 -> 41860.25 | BW7: =BW6-BN7 -> 41860.25 | BX7: =BX6-BO7 -> 27274.25 | BY7: =BY6-BP7 -> 27274.25
A8: 45602 | B8: DM LLC | C8: 俄罗斯联邦 | D8: 4500150264 | E8: 出Bekasovo 2 | F8: 4500150264-20 | G8: 92108-S001 | H8: 摇篮公子 | I8: 472 | J8: 0 | K8: 4 | L8: =I8/K8 -> 118 | M8: 45652 | N8: 45638 | P8: PAss | Q8: 12/28出 | R8: 11/14收到 | T8: 11/26-进口商贴纸+ EAN条码贴纸 | V8: 外包装 (指: 收缩膜/彩卡/铝箔袋/挂卡/PDQ) /外箱不要打ZURU标准日期码！胶件可以打日期码 | W8: 日期码格式：外包装/外箱不要打ZURU标准日期码 日期： Packaging Info: 注意 ：外包装 (指: 收缩膜/彩卡/铝箔袋/挂卡/PDQ) /外箱不要打ZURU标准日期码！胶件可以打日期码 . 92108 ： 1L MA 收缩膜+ 进口商贴纸+ EAN条码贴纸， MA 说明书or 指南（如有） ： Remark: 标准配比 ； 请按期完货， 会有罚金。 出港口Bekasovo 2. | X8: Ann Zhang | Y8: 7.3277 | Z8: =Y8*I8 -> 3458.6744 | AA8: 94035-1.15 | AB8: 92108-S001 | AC8: 已入 | AD8: =I8 -> 472 | AJ8: =I8 -> 472 | AQ8: =I8/4 -> 118 | AR8: =I8/4 -> 118 | AS8: =I8/4 -> 118 | AT8: =AS8 -> 118 | BD8: =I8 -> 472 | BF8: =I8 -> 472 | BG8: MA | BI8: =I8/4 -> 118 | BJ8: =BI8 -> 118 | BK8: =BJ8 -> 118 | BL8: =BK8 -> 118 | BM8: =BL8 -> 118 | BN8: =BM8 -> 118 | BO8: =BN8 -> 118 | BP8: =BO8 -> 118 | BQ8: =$BQ$119+BJ8+BL8+BN8+BP8 -> 238497 | BR8: =BR7-BI8 -> 26664.25 | BS8: =BS7-BJ8 -> 26664.25 | BT8: =BT7-BK8 -> 26536.25 | BU8: =BU7-BL8 -> 26536.25 | BV8: =BV7-BM8 -> 41742.25 | BW8: =BW7-BN8 -> 41742.25 | BX8: =BX7-BO8 -> 27156.25 | BY8: =BY7-BP8 -> 27156.25
A9: 45601 | B9: DD’S DISCOUNTS | C9: 美国 | D9: 4500150187 | E9: 70054066 | F9: 4500150187-50 | G9: 92108-S001 | H9: 摇篮公子 | I9: 360 | J9: 0 | K9: 4 | L9: =I9/K9 -> 90 | M9: 45653 | N9: 45649 | P9: PAss | Q9: 1/7出 | R9: ROSS指定箱唛格式 | T9: 11/19收到价格贴纸客供 | W9: 日期码格式：ZURU INC(BVI) 标准格式 日期：按实际生产日期 Packaging Info: 1.ZURU MA UPC 现有版本包装 + 客供价格贴纸，出口美国 , 优先使用MA 1L 最新版本 。 Remark: 1.ZURU MA UPC 现有版本包装 + 客供价格贴纸，出口美国 , 优先使用MA 1L 最新版本 。 2.价格贴纸位于包装正面右下角，不挡住重要信息即可，可适当调整 ，价格贴纸由跟单提供。 3.标准日期码格式，产品和包装必须有日期码 。 4.同个产品同个货期不可出现不同的包装。 5. 跟单提供ROSS通用的箱唛模版，工厂按实际45 PO上客户PO/Item号/装箱数 提供箱唛排版来确认。 | X9: Taylor Liao | Y9: 7.3277 | Z9: =Y9*I9 -> 2637.972 | AA9: 88917-1.7 | AB9: 92108-S001 | AC9: 已入 | AD9: =I9 -> 360 | AJ9: =I9 -> 360 | AQ9: =I9/4 -> 90 | AR9: =I9/4 -> 90 | AS9: =I9/4 -> 90 | AT9: =AS9 -> 90 | BD9: =I9 -> 360 | BF9: =I9 -> 360 | BG9: MA | BI9: =I9/4 -> 90 | BJ9: =BI9 -> 90 | BK9: =BJ9 -> 90 | BL9: =BK9 -> 90 | BM9: =BL9 -> 90 | BN9: =BM9 -> 90 | BO9: =BN9 -> 90 | BP9: =BO9 -> 90 | BQ9: =$BQ$119+BJ9+BL9+BN9+BP9 -> 238385 | BR9: =BR8-BI9 -> 26574.25 | BS9: =BS8-BJ9 -> 26574.25 | BT9: =BT8-BK9 -> 26446.25 | BU9: =BU8-BL9 -> 26446.25 | BV9: =BV8-BM9 -> 41652.25 | BW9: =BW8-BN9 -> 41652.25 | BX9: =BX8-BO9 -> 27066.25 | BY9: =BY8-BP9 -> 27066.25
A10: 45614 | B10: BURLINGTON COAT FACTORY | C10: 美国 | D10: 4500151479 | E10: 383017704 | F10: 4500151479 | G10: 92108-S001 | H10: 摇篮公子 | I10: 1800 | J10: 0 | K10: 4 | L10: =I10/K10 -> 450 | M10: 45663 | N10: 45659 | P10: PAss | Q10: 收到SO | R10: 11/18收到 | T10: 12/13-客供价格贴纸+12/11-外箱贴纸 | W10: 日期码格式：ZURU INC(BVI) 标准格式 日期：按实际生产日期 Packaging Info: 1. ZURU MA （首选1L）UPC版本+客供价格贴纸+外箱贴纸，出口美国 有PVC桶的价格贴纸贴在PVC桶上面 Remark: 2. 产品和包装上印刷ZURU 标准日期码； 3. 纸箱中间靠上沿印刷ZURU LOGO，见箱唛资料 4. 外箱UCC 条码贴纸，尺寸: 4*6inch，贴在其中一面正唛右下角，贴纸距离外箱底部3.5cm, 侧边距离3.5cm。外箱贴纸由跟单提供电子版, 工厂自行安排，不可用 封箱胶覆盖贴纸条码，贴纸需要可以扫描且无损坏. 5. 每个产品有一个价格贴纸，价格贴纸覆盖UPC条码上 （若UPC 条码太大，可以露出ITEM#, 覆盖条码即可）贴的时候要是会覆盖包装上重要的信息和图案，需要 告知跟单。 | X10: Jessi Xu | Y10: 7.0129 | Z10: =Y10*I10 -> 12623.22 | AA10: 94086-1.17 | AB10: 92108-S001 | AC10: 已入 | AD10: =I10 -> 1800 | AJ10: =I10 -> 1800 | AQ10: =I10/4 -> 450 | AS10: =I10/4 -> 450 | AT10: =AS10 -> 450 | AV10: =AS10 -> 450 | BD10: =I10 -> 1800 | BF10: =I10 -> 1800 | BG10: MA | BI10: =I10/4 -> 450 | BJ10: =BI10 -> 450 | BK10: =BJ10 -> 450 | BL10: =BK10 -> 450 | BM10: =BL10 -> 450 | BN10: =BM10 -> 450 | BO10: =BN10 -> 450 | BP10: =BO10 -> 450 | BQ10: =$BQ$119+BJ10+BL10+BN10+BP10 -> 239825 | BR10: =BR9-BI10 -> 26124.25 | BS10: =BS9-BJ10 -> 26124.25 | BT10: =BT9-BK10 -> 25996.25 | BU10: =BU9-BL10 -> 25996.25 | BV10: =BV9-BM10 -> 41202.25 | BW10: =BW9-BN10 -> 41202.25 | BX10: =BX9-BO10 -> 26616.25 | BY10: =BY9-BP10 -> 26616.25
A11: 45615 | B11: Wonderland Toys Inc DBA The Zoofy G | C11: 美国 | D11: 4500151635 | E11: 4357 | F11: 4500151635-30 | G11: 92108-S001 | H11: 摇篮公子 | I11: 1980 | J11: 0 | K11: 4 | L11: =I11/K11 -> 495 | M11: 45665 | N11: 45661 | P11: PAss | Q11: 1/20出 | R11: 11/27收到 | T11: 11/27-价格贴+外箱需要UCC贴纸 | W11: 日期码格式：ZURU INC(BVI) 标准格式 日期：按实际生产日期 Packaging Info: 1. 出口美国，MA UPC 版本包装，优先1L。 #92108: PRICER TICK-32.99; 4 Assortments (bunny: puppy: unicorn: kitten)=1:1:1:1; 3pcs AAA batteries (not included); 2. 产品需要价格贴纸， 贴纸资料后面提供。 3. 外箱需要UCC贴纸。贴纸资料后面提供。 Remark: 4. Zuru QC 验货即可。 | X11: Abby Mai, Lluviazeng | Y11: 7.0129 | Z11: =Y11*I11 -> 13885.542 | AA11: 94108-1.18 | AB11: 92108-S001 | AC11: 已入 | AD11: =I11 -> 1980 | AJ11: =I11 -> 1980 | AQ11: =I11/4 -> 495 | AS11: =I11/4 -> 495 | AT11: =AS11 -> 495 | AV11: =AS11 -> 495 | BD11: =I11 -> 1980 | BF11: =I11 -> 1980 | BG11: MA | BI11: =I11/4 -> 495 | BJ11: =BI11 -> 495 | BK11: =BJ11 -> 495 | BL11: =BK11 -> 495 | BM11: =BL11 -> 495 | BN11: =BM11 -> 495 | BO11: =BN11 -> 495 | BP11: =BO11 -> 495 | BQ11: =$BQ$119+BJ11+BL11+BN11+BP11 -> 240005 | BR11: =BR10-BI11 -> 25629.25 | BS11: =BS10-BJ11 -> 25629.25 | BT11: =BT10-BK11 -> 25501.25 | BU11: =BU10-BL11 -> 25501.25 | BV11: =BV10-BM11 -> 40707.25 | BW11: =BW10-BN11 -> 40707.25 | BX11: =BX10-BO11 -> 26121.25 | BY11: =BY10-BP11 -> 26121.25
A12: 45579 | B12: WAL-MART CANADA CORP. | C12: 加拿大 | D12: 4500147521 | E12: 9650903902 | F12: 4500147521-10 | G12: 92108-S002-NB | H12: 摇篮公子 | I12: 870 | J12: 0 | K12: 1 | L12: =I12/K12 -> 870 | M12: 45666 | N12: 45663 | O12: 第三方验货1/10（自检） | P12: PAss | Q12: 1/27出 | R12: 12/2收到 | S12: 无 | T12: UPC条码贴纸翻单：4500146212 | W12: 日期码格式：ZURU INC(BVI) 标准格式 日期：按实际生产日期 Packaging Info: #92108: MA3L收缩膜+UPC条码贴纸(UPC: 193052064721)+MA5L收藏指南+MA5L资料卡+MA5L胶袋+MA配件袋+MA2L布标 -产品配比: 4 Assortments (bunny: puppy: unicorn: kitten)=1:1:1:1 -翻单： 4500146212 Remark: 1. #92108/92107/9296 须使用无硼slime; 2. 此单有箱唛； 3. 此单有第三方验货，烦请多备包装物料； ********************* a. 请确保产品符合1999年版本的加拿大环境保护法(CEPA)和2012年禁止某些有毒物质法规的要求。该产品不含任何在加拿大禁用的化学物质，包括但不限于有毒物 质清单中列出的化学物质，并且在为加拿大沃尔玛生产产品期间没有使用任何禁用化学物质。 Supplier certify that the products comply with the requirements of Canadian Environmental Protection Act, 1999 (CEPA), Prohibition of Certain To xic Substances Regulations, 2012. The products do not contain any chemicals that are banned in Canada, including but not limited to those listed in the Toxic Substances List and no banned chemicals were used during the manufacturing of product for Walmart Canada. 附件列表： (1) Letter of Guarantee for Canada banned chemicals - (1-5CA) b. 请确保产品在均质材料中的汞浓度不超过0.1%（按重量计）。 Supplier certify that the WAL-MART vendor products does not have a mercury concentration of more than 0.1% by weight in homogeneous material. 附件列表： (1) Letter of Guarantee for Mercury COC c. 请确保产品的塑料材料不含以下物质（SOR 2011-17 27B): Supplier certify that the plastic materials do not contain the following substances(SOR 2011-17 27B): (a) carbon tetrachloride or any substance that contains it; (b) methyl alcohol or any substance thay contains >1.0%; (c) petroleum distillates or any substance that contains >10% weight to volume of petroleum distillates; (d) benzene; (e) turpentine or any substance that contains >10% weight to volume of turpentine; (f) boric acid or salts of boric acid; or (g) ethyl ether. 附件列表： (1) Letter of Guarantee for WM CA-Other prohibited substances in plastic(less than 3 years) | X12: Monica Zhou | Y12: 7.1318 | Z12: =Y12*I12 -> 6204.666 | AA12: 94179-1.23 | AB12: 92108-S002-NB-3L | AC12: 已入 | AF12: =I12 -> 870 | AJ12: =I12 -> 870 | AQ12: =I12/4 -> 217.5 | AS12: =I12/4 -> 217.5 | AT12: =AS12 -> 217.5 | AV12: =AS12 -> 217.5 | BE12: =I12 -> 870 | BF12: =I12 -> 870 | BG12: MA | BI12: =I12/4 -> 217.5 | BJ12: =BI12 -> 217.5 | BK12: =BJ12 -> 217.5 | BL12: =BK12 -> 217.5 | BM12: =BL12 -> 217.5 | BN12: =BM12 -> 217.5 | BO12: =BN12 -> 217.5 | BP12: =BO12 -> 217.5 | BQ12: =$BQ$119+BJ12+BL12+BN12+BP12 -> 238895 | BR12: =BR11-BI12 -> 25411.75 | BS12: =BS11-BJ12 -> 25411.75 | BT12: =BT11-BK12 -> 25283.75 | BU12: =BU11-BL12 -> 25283.75 | BV12: =BV11-BM12 -> 40489.75 | BW12: =BW11-BN12 -> 40489.75 | BX12: =BX11-BO12 -> 25903.75 | BY12: =BY11-BP12 -> 25903.75
A13: 45579 | B13: WAL-MART CANADA CORP. | C13: 加拿大 | D13: 4500147521 | E13: 9650903903 | F13: 4500147521-60 | G13: 92108-S002-NB | H13: 摇篮公子 | I13: 522 | J13: 0 | K13: 1 | L13: =I13/K13 -> 522 | M13: 45672 | N13: 45668 | O13: 第三方验货1/17（自检） | P13: PAss | Q13: 2/13出 | R13: 12/2收到 | S13: 无 | T13: UPC条码贴纸翻单：4500146212 | W13: 日期码格式：ZURU INC(BVI) 标准格式 日期：按实际生产日期 Packaging Info: #92108: MA3L收缩膜+UPC条码贴纸(UPC: 193052064721)+MA5L收藏指南+MA5L资料卡+MA5L胶袋+MA配件袋+MA2L布标 -产品配比: 4 Assortments (bunny: puppy: unicorn: kitten)=1:1:1:1 -翻单： 4500146212 Remark: 1. #92108/92107/9296 须使用无硼slime; 2. 此单有箱唛； 3. 此单有第三方验货，烦请多备包装物料； ********************* a. 请确保产品符合1999年版本的加拿大环境保护法(CEPA)和2012年禁止某些有毒物质法规的要求。该产品不含任何在加拿大禁用的化学物质，包括但不限于有毒物 质清单中列出的化学物质，并且在为加拿大沃尔玛生产产品期间没有使用任何禁用化学物质。 Supplier certify that the products comply with the requirements of Canadian Environmental Protection Act, 1999 (CEPA), Prohibition of Certain To xic Substances Regulations, 2012. The products do not contain any chemicals that are banned in Canada, including but not limited to those listed in the Toxic Substances List and no banned chemicals were used during the manufacturing of product for Walmart Canada. 附件列表： (1) Letter of Guarantee for Canada banned chemicals - (1-5CA) b. 请确保产品在均质材料中的汞浓度不超过0.1%（按重量计）。 Supplier certify that the WAL-MART vendor products does not have a mercury concentration of more than 0.1% by weight in homogeneous material. 附件列表： (1) Letter of Guarantee for Mercury COC c. 请确保产品的塑料材料不含以下物质（SOR 2011-17 27B): Supplier certify that the plastic materials do not contain the following substances(SOR 2011-17 27B): (a) carbon tetrachloride or any substance that contains it; (b) methyl alcohol or any substance thay contains >1.0%; (c) petroleum distillates or any substance that contains >10% weight to volume of petroleum distillates; (d) benzene; (e) turpentine or any substance that contains >10% weight to volume of turpentine; (f) boric acid or salts of boric acid; or (g) ethyl ether. 附件列表： (1) Letter of Guarantee for WM CA-Other prohibited substances in plastic(less than 3 years) | X13: Monica Zhou | Y13: 7.1318 | Z13: =Y13*I13 -> 3722.7996 | AA13: 94237-2.13 | AB13: 92108-S002-NB-3L | AC13: 已入 | AF13: =I13 -> 522 | AJ13: =I13 -> 522 | AQ13: =I13/4 -> 130.5 | AS13: =I13/4 -> 130.5 | AT13: =AS13 -> 130.5 | AV13: =AS13 -> 130.5 | BE13: =I13 -> 522 | BF13: =I13 -> 522 | BG13: MA | BI13: =I13/4 -> 130.5 | BJ13: =BI13 -> 130.5 | BK13: =BJ13 -> 130.5 | BL13: =BK13 -> 130.5 | BM13: =BL13 -> 130.5 | BN13: =BM13 -> 130.5 | BO13: =BN13 -> 130.5 | BP13: =BO13 -> 130.5 | BQ13: =$BQ$119+BJ13+BL13+BN13+BP13 -> 238547 | BR13: =BR12-BI13 -> 25281.25 | BS13: =BS12-BJ13 -> 25281.25 | BT13: =BT12-BK13 -> 25153.25 | BU13: =BU12-BL13 -> 25153.25 | BV13: =BV12-BM13 -> 40359.25 | BW13: =BW12-BN13 -> 40359.25 | BX13: =BX12-BO13 -> 25773.25 | BY13: =BY12-BP13 -> 25773.25
A14: 45636 | D14: ZMPO24940 | G14: 92108-S002-NB | H14: 摇篮公子 | I14: 2 | J14: 0 | K14: 1 | L14: =I14/K14 -> 2 | M14: 45649 | N14: 45645 | P14: 已送货 | R14: 周转箱 | T14: UPC条码贴纸 | W14: Remark：跟订单4500146212一起安排/MA3L收缩膜+UPC条码贴纸(UPC: 193052064721)+MA5L收藏指南+MA5L资料卡+MA5L胶袋+MA配件袋+MA2L布标 备注： 收到样品订单后尽快安排 ，注意样板品质质量要求要高于大货品质要求 ，送货时必须要附带送货单(没有送货单和QC检验合格报告的仓库一律拒绝收货)，请知悉，谢谢！ | AB14: 过渡 | AC14: 过渡 | BF14: =I14 -> 2 | BG14: MA | BQ14: =$BQ$119+BJ14+BL14+BN14+BP14 -> 238025 | BR14: =BR13-BI14 -> 25281.25 | BS14: =BS13-BJ14 -> 25281.25 | BT14: =BT13-BK14 -> 25153.25 | BU14: =BU13-BL14 -> 25153.25 | BV14: =BV13-BM14 -> 40359.25 | BW14: =BW13-BN14 -> 40359.25 | BX14: =BX13-BO14 -> 25773.25 | BY14: =BY13-BP14 -> 25773.25
A15: 45638 | B15: VM INTERNATIONAL | C15: 美国 | D15: 4500151779 | E15: 31200 | F15: 4500151779-90 | G15: 92108-S001 | H15: 摇篮公子 | I15: 336 | J15: 0 | K15: 4 | L15: =I15/K15 -> 84 | M15: 45666 | N15: 45663 | P15: PAss | Q15: 1/13出 | R15: 12/12收到 | T15: 无 | W15: 日期码格式：ZURU INC(BVI) 标准格式 日期：按实际生产日期 Packaging Info: 1.ZURU 标准日期码格式， 2.无第三方测试和验货，ZURU 内部QC验货即可出货 Remark: 3. 优先 MA 1L UPC包装; 4. 纸箱印ZURU LOGO，出口美国； | X15: Iris Yuan | Y15: 7.3277 | Z15: =Y15*I15 -> 2462.1072 | AA15: 94112-1.18 | AB15: 92108-S001 | AC15: 已入 | AD15: =I15 -> 336 | AJ15: =I15 -> 336 | AQ15: =I15/4 -> 84 | AS15: =I15/4 -> 84 | AT15: =AS15 -> 84 | AV15: =AS15 -> 84 | BD15: =I15 -> 336 | BF15: =I15 -> 336 | BG15: MA | BI15: =I15/4 -> 84 | BJ15: =BI15 -> 84 | BK15: =BJ15 -> 84 | BL15: =BK15 -> 84 | BM15: =BL15 -> 84 | BN15: =BM15 -> 84 | BO15: =BN15 -> 84 | BP15: =BO15 -> 84 | BQ15: =$BQ$119+BJ15+BL15+BN15+BP15 -> 238361 | BR15: =BR14-BI15 -> 25197.25 | BS15: =BS14-BJ15 -> 25197.25 | BT15: =BT14-BK15 -> 25069.25 | BU15: =BU14-BL15 -> 25069.25 | BV15: =BV14-BM15 -> 40275.25 | BW15: =BW14-BN15 -> 40275.25 | BX15: =BX14-BO15 -> 25689.25 | BY15: =BY14-BP15 -> 25689.25
A16: 45616 | B16: COOLSHOP(ENTERTAINMENT TRADINGS APS | C16: 丹麦 | D16: 4500151829 | E16: 257441 | F16: 4500151829-40 | G16: 92108-S001-NB | H16: 摇篮公子-无硼 | I16: 160 | J16: 0 | K16: 4 | L16: =I16/K16 -> 40 | M16: 45660 | N16: 45656 | P16: PAss | Q16: 1/8出 | R16: 11/28收到 | T16: 贴纸和位置图/电池说明书/slime说明书都翻4500129340 | W16: 日期码格式：ZURU INC(BVI) 标准格式 日期：按实际生产日期 Packaging Info: 4. 92108: MA 3L EAN 包装+MA 收藏指南+AAA电池黑白说明书+黑白slime警语说明书(和slime袋子放一起)+进口商警语贴纸 --贴纸和位置图/电池说明书/slime说明书都翻PO#4500129340 Remark: 1. 包装如含PVC,请改为PET 2. 产品/包装要求无硼无香； 3. 出欧洲，微塑料需合规。 4.带电池出货的产品所用到的电池需要符合欧洲电池新规(EU) 2023-1542 5.关于贴纸，如果贴纸位置图的包装版本与大货不一致，请工厂提前提出。跟单会重新调整确认是否更新贴纸或调整位置图 6.产品/包装不含PFAS成分 7. 产品信息： 92108:4 Assortments (bunny: puppy: unicorn: kitten)=1:1:1:1 8.SKU-客户款号-条码 92108-1254086-4894680033597 | X16: Sheba Ye | Y16: 7.3277 | Z16: =Y16*I16 -> 1172.432 | AA16: 88933-1.8 | AB16: 92108-S001-NB-3L | AC16: 已入 | AF16: =I16 -> 160 | AJ16: =I16 -> 160 | AQ16: =I16/4 -> 40 | AR16: =I16/4 -> 40 | AS16: =I16/4 -> 40 | AT16: =AS16 -> 40 | BE16: =I16 -> 160 | BF16: =I16 -> 160 | BG16: MA | BI16: =I16/4 -> 40 | BJ16: =BI16 -> 40 | BK16: =BJ16 -> 40 | BL16: =BK16 -> 40 | BM16: =BL16 -> 40 | BN16: =BM16 -> 40 | BO16: =BN16 -> 40 | BP16: =BO16 -> 40 | BQ16: =$BQ$119+BJ16+BL16+BN16+BP16 -> 238185 | BR16: =BR15-BI16 -> 25157.25 | BS16: =BS15-BJ16 -> 25157.25 | BT16: =BT15-BK16 -> 25029.25 | BU16: =BU15-BL16 -> 25029.25 | BV16: =BV15-BM16 -> 40235.25 | BW16: =BW15-BN16 -> 40235.25 | BX16: =BX15-BO16 -> 25649.25 | BY16: =BY15-BP16 -> 25649.25
A17: 45609 | B17: TOY TRIANGLE COMPANY (UAE) | C17: 阿拉伯联合酋长国 | D17: 4500151230 | E17: 2025TTC006 | F17: 4500151230-40 | G17: 92118-S001 | H17: 摇篮公子 | I17: 3000 | J17: 0 | K17: 4 | L17: =I17/K17 -> 750 | M17: 45666 | N17: 45663 | P17: PAss | R17: 11/13收到 | T17: 无 | V17: 客版收缩膜翻4500134696+客版指南翻4500134696 | W17: 日期码格式：ZURU INC(BVI) 标准格式 日期：按实际生产日期 Packaging Info: 92118：客版收缩膜翻4500134696（改彩虹颜色，不含slime和希伯来警告语，需含阿拉伯警告语，印G mark+TTC panel 信息，客版指南翻4500134696（改彩 虹颜色，不含slime和希伯来警告语）;；客版收缩膜上的二维码微信可扫, 扫描结果38711. 客版沙子PE POLYBAG 含阿拉伯警语翻4500134696 Remark: 92118:#92108 Smart Sandy replaces slime 4 Assortments (bunny: puppy: unicorn: kitten)=1:1:1:1 3pcs AAA batteries (not included) | X17: Lena Huang | Y17: 7.3188 | Z17: =Y17*I17 -> 21956.4 | AA17: 94062-1.16 | AB17: 92118-S001 | AC17: 已入 | AH17: =I17 -> 3000 | AL17: =I17 -> 3000 | AQ17: =I17/4 -> 750 | AS17: =I17/4 -> 750 | AT17: =AS17 -> 750 | AV17: =AS17 -> 750 | BC17: =I17 -> 3000 | BF17: =I17 -> 3000 | BG17: MA | BI17: =I17/4 -> 750 | BJ17: =BI17 -> 750 | BK17: =BJ17 -> 750 | BL17: =BK17 -> 750 | BM17: =BL17 -> 750 | BN17: =BM17 -> 750 | BO17: =BN17 -> 750 | BP17: =BO17 -> 750 | BQ17: =$BQ$119+BJ17+BL17+BN17+BP17 -> 241025 | BR17: =BR16-BI17 -> 24407.25 | BS17: =BS16-BJ17 -> 24407.25 | BT17: =BT16-BK17 -> 24279.25 | BU17: =BU16-BL17 -> 24279.25 | BV17: =BV16-BM17 -> 39485.25 | BW17: =BW16-BN17 -> 39485.25 | BX17: =BX16-BO17 -> 24899.25 | BY17: =BY16-BP17 -> 24899.25
A18: 45637 | B18: MTA Trade | C18: 哈萨克斯坦 | D18: 4500153567 | F18: 4500153567-50 | G18: 92108-S001 | H18: 摇篮公子 | I18: 280 | J18: 0 | K18: 4 | L18: =I18/K18 -> 70 | M18: 45670 | N18: 45666 | P18: PAss | Q18: 1/14出 | R18: 12/13收到 | T18: 12/13-进口商贴纸 | W18: 日期码格式：ZURU INC(BVI) 标准格式 日期：按实际生产日期 Packaging Info: 92108：1L MA 最新收缩膜+进口商贴纸, MA 指南 Remark: 标准配比 | X18: Ann Zhang | Y18: 7.3277 | Z18: =Y18*I18 -> 2051.756 | AA18: 94029-1.14 | AB18: 92108-S001 | AC18: 已入 | AD18: =I18 -> 280 | AJ18: =I18 -> 280 | AQ18: =I18/4 -> 70 | AS18: =I18/4 -> 70 | AT18: =AS18 -> 70 | AV18: =AS18 -> 70 | BD18: =I18 -> 280 | BF18: =I18 -> 280 | BG18: MA | BI18: =I18/4 -> 70 | BJ18: =BI18 -> 70 | BK18: =BJ18 -> 70 | BL18: =BK18 -> 70 | BM18: =BL18 -> 70 | BN18: =BM18 -> 70 | BO18: =BN18 -> 70 | BP18: =BO18 -> 70 | BQ18: =$BQ$119+BJ18+BL18+BN18+BP18 -> 238305 | BR18: =BR17-BI18 -> 24337.25 | BS18: =BS17-BJ18 -> 24337.25 | BT18: =BT17-BK18 -> 24209.25 | BU18: =BU17-BL18 -> 24209.25 | BV18: =BV17-BM18 -> 39415.25 | BW18: =BW17-BN18 -> 39415.25 | BX18: =BX17-BO18 -> 24829.25 | BY18: =BY17-BP18 -> 24829.25
A19: 45635 | B19: BINGO GLOBAL GROUP FOR TRADING SUPP | C19: 埃及 | D19: 4500153513 | F19: 4500153513-60 | G19: 92108-S001 | H19: 摇篮公子 | I19: 600 | J19: 0 | K19: 4 | L19: =I19/K19 -> 150 | M19: 45672 | N19: 45668 | P19: PAss | Q19: 收到SO | R19: 12/12收到 | T19: 12-12进口商贴纸 | W19: 日期码格式：ZURU INC(BVI) 标准格式 日期：按实际生产日期 Packaging Info: 92108:3L MA EAN 收缩膜+进口商贴纸;MA指南 Remark: 标准产品标准配比 | X19: Lena Huang | Y19: 7.3108 | Z19: =Y19*I19 -> 4386.48 | AA19: 94060-1.16 | AB19: 92108-S001-3L | AC19: 已入 | AF19: =I19 -> 600 | AJ19: =I19 -> 600 | AQ19: =I19/4 -> 150 | AS19: =I19/4 -> 150 | AT19: =AS19 -> 150 | AV19: =AS19 -> 150 | BD19: =I19 -> 600 | BF19: =I19 -> 600 | BG19: MA | BI19: =I19/4 -> 150 | BJ19: =BI19 -> 150 | BK19: =BJ19 -> 150 | BL19: =BK19 -> 150 | BM19: =BL19 -> 150 | BN19: =BM19 -> 150 | BO19: =BN19 -> 150 | BP19: =BO19 -> 150 | BQ19: =$BQ$119+BJ19+BL19+BN19+BP19 -> 238625 | BR19: =BR18-BI19 -> 24187.25 | BS19: =BS18-BJ19 -> 24187.25 | BT19: =BT18-BK19 -> 24059.25 | BU19: =BU18-BL19 -> 24059.25 | BV19: =BV18-BM19 -> 39265.25 | BW19: =BW18-BN19 -> 39265.25 | BX19: =BX18-BO19 -> 24679.25 | BY19: =BY18-BP19 -> 24679.25
A20: 45603 | B20: ROSS PROCUREMENT.INC | C20: 美国 | D20: 4500150480 | E20: 60190302 | F20: 4500150480-20 | G20: 92108-S001 | H20: 摇篮公子 | I20: 800 | J20: 0 | K20: 4 | L20: =I20/K20 -> 200 | M20: 45677 | N20: 45673 | P20: PAss | Q20: 2/11出 | R20: ROSS指定箱唛格式 | T20: 无 | U20: 12/19-客供价格贴纸 | W20: 日期码格式： 标准格式 日期：按实际生产日期 Packaging Info: 1.ZURU MA UPC 现有版本包装 + 客供价格贴纸，出口美国 , 优先使用MA 1L 最新版本 。 Remark: 1.ZURU MA UPC 现有版本包装 + 客供价格贴纸，出口美国 , 优先使用MA 1L 最新版本 。 2.价格贴纸位于包装正面右下角，不挡住重要信息即可，可适当调整 ，价格贴纸由跟单提供。 3.标准日期码格式，产品和包装必须有日期码 。 4.同个产品同个货期不可出现不同的包装。 5. 跟单提供ROSS通用的箱唛模版，工厂按实际45 PO上客户PO/Item号/装箱数 提供箱唛排版来确认 | X20: Minny Peng | Y20: 7.0129 | Z20: =Y20*I20 -> 5610.32 | AA20: 94470-3.6 | AB20: 92108-S001 | AC20: 已入 | AD20: =I20 -> 800 | AJ20: =I20 -> 800 | AQ20: =I20/4 -> 200 | AS20: =I20/4 -> 200 | AT20: =AS20 -> 200 | AV20: =AS20 -> 200 | BD20: =I20 -> 800 | BF20: =I20 -> 800 | BG20: MA | BI20: =I20/4 -> 200 | BJ20: =BI20 -> 200 | BK20: =BJ20 -> 200 | BL20: =BK20 -> 200 | BM20: =BL20 -> 200 | BN20: =BM20 -> 200 | BO20: =BN20 -> 200 | BP20: =BO20 -> 200 | BQ20: =$BQ$119+BJ20+BL20+BN20+BP20 -> 238825 | BR20: =BR19-BI20 -> 23987.25 | BS20: =BS19-BJ20 -> 23987.25 | BT20: =BT19-BK20 -> 23859.25 | BU20: =BU19-BL20 -> 23859.25 | BV20: =BV19-BM20 -> 39065.25 | BW20: =BW19-BN20 -> 39065.25 | BX20: =BX19-BO20 -> 24479.25 | BY20: =BY19-BP20 -> 24479.25
A21: 45645 | D21: ZMPO24972 | G21: 92108-S001 | H21: 摇篮公子 | I21: 120 | J21: 0 | K21: 4 | L21: =I21/K21 -> 30 | M21: 45665 | N21: 45661 | P21: 完成 | R21: 周转箱 | T21: 无 | W21: Remark：大货最新版本/款号平均/麻烦按款号装箱/并在外箱上注明款款号/请用大货标准箱装箱/箱唛请参照邮件附件 备注： 收到样品订单后尽快安排 ，注意样板品质质量要求要高于大货品质要求 ，送货时必须要附带送货单(没有送货单和QC检验合格报告的仓库一律拒绝收货)，请知悉，谢谢！ | X21: Angus | AB21: 92108-S001 | AC21: 已入 | AD21: =I21 -> 120 | AJ21: =I21 -> 120 | AQ21: =I21/4 -> 30 | AS21: =I21/4 -> 30 | AT21: =AS21 -> 30 | AV21: =AS21 -> 30 | BD21: =I21 -> 120 | BF21: =I21 -> 120 | BG21: MA | BI21: =I21/4 -> 30 | BJ21: =BI21 -> 30 | BK21: =BJ21 -> 30 | BL21: =BK21 -> 30 | BM21: =BL21 -> 30 | BN21: =BM21 -> 30 | BO21: =BN21 -> 30 | BP21: =BO21 -> 30 | BQ21: =$BQ$119+BJ21+BL21+BN21+BP21 -> 238145 | BR21: =BR20-BI21 -> 23957.25 | BS21: =BS20-BJ21 -> 23957.25 | BT21: =BT20-BK21 -> 23829.25 | BU21: =BU20-BL21 -> 23829.25 | BV21: =BV20-BM21 -> 39035.25 | BW21: =BW20-BN21 -> 39035.25 | BX21: =BX20-BO21 -> 24449.25 | BY21: =BY20-BP21 -> 24449.25
A22: 45602 | B22: DM LLC | C22: 俄罗斯联邦 | D22: 4500150271 | E22: 出Bekasovo 2 | F22: 4500150271-20 | G22: 92108-S001 | H22: 摇篮公子 | I22: 56 | J22: 0 | K22: 4 | L22: =I22/K22 -> 14 | M22: 45697 | N22: =M22-4 -> 45693 | P22: PAss | Q22: 2/27出 | R22: 11/14收到 | T22: 进口商贴纸翻4500150264+ EAN条码贴纸翻4500150264 | V22: 外包装 (指: 收缩膜/彩卡/铝箔袋/挂卡/PDQ) /外箱不要打ZURU标准日期码！胶件可以打日期码 | W22: 日期码格式：外包装/外箱不要打ZURU标准日期码 日期： Packaging Info: 注意 ：外包装 (指: 收缩膜/彩卡/铝箔袋/挂卡/PDQ) /外箱不要打ZURU标准日期码！胶件可以打日期码 . 92108 ： 1L MA 收缩膜+ 进口商贴纸翻4500150264+ EAN条码贴纸翻4500150264， MA 说明书or 指南（如有） ： Remark: 标准配比 ； 请按期完货， 会有罚金。 出港口Bekasovo 2. | X22: Ann Zhang | Y22: 7.3277 | Z22: =Y22*I22 -> 410.3512 | AA22: 94369-2.27 | AB22: 92108-S001 | AC22: 已入 | AD22: =I22 -> 56 | AJ22: =I22 -> 56 | AQ22: =I22/4 -> 14 | AS22: =I22/4 -> 14 | AT22: =AS22 -> 14 | AV22: =AS22 -> 14 | BD22: =I22 -> 56 | BF22: =I22 -> 56 | BG22: MA | BI22: =I22/4 -> 14 | BJ22: =BI22 -> 14 | BK22: =BJ22 -> 14 | BL22: =BK22 -> 14 | BM22: =BL22 -> 14 | BN22: =BM22 -> 14 | BO22: =BN22 -> 14 | BP22: =BO22 -> 14 | BQ22: =$BQ$119+BJ22+BL22+BN22+BP22 -> 238081 | BR22: =BR21-BI22 -> 23943.25 | BS22: =BS21-BJ22 -> 23943.25 | BT22: =BT21-BK22 -> 23815.25 | BU22: =BU21-BL22 -> 23815.25 | BV22: =BV21-BM22 -> 39021.25 | BW22: =BW21-BN22 -> 39021.25 | BX22: =BX21-BO22 -> 24435.25 | BY22: =BY21-BP22 -> 24435.25
A23: 45651 | B23: AMIC TRADING (PTY) LTD | C23: 南非 | D23: 4500154694 | E23: PO#6006-00522 6PI#110002571 5-2 | F23: 4500154694-20 | G23: 92108-S001 | H23: 摇篮公子 | I23: 284 | J23: 0 | K23: 4 | L23: =I23/K23 -> 71 | M23: 45713 | N23: 45709 | P23: PAss | Q23: 2/25出 | R23: 12/25收到 | T23: 1/6-进口商贴纸 | W23: 日期码格式：ZURU INC(BVI) 标准格式 日期：按实际生产日期 Packaging Info: MA PKG, 优先1L +1张进口商贴纸（贴条码附近空白处，不得遮挡日期码） 该客户只有一款进口商贴纸，所有款通用，进口商贴纸AW可翻此客户旧订单 Remark: | X23: Doris Shou | Y23: 7.0298 | Z23: =Y23*I23 -> 1996.4632 | AA23: 94351-2.25 | AB23: 92108-S001 | AC23: 已入 | AD23: =I23 -> 284 | AJ23: =I23 -> 284 | AQ23: =I23/4 -> 71 | AS23: =I23/4 -> 71 | AT23: =AS23 -> 71 | AV23: =AS23 -> 71 | BD23: =I23 -> 284 | BF23: =I23 -> 284 | BG23: MA | BI23: =I23/4 -> 71 | BJ23: =BI23 -> 71 | BK23: =BJ23 -> 71 | BL23: =BK23 -> 71 | BM23: =BL23 -> 71 | BN23: =BM23 -> 71 | BO23: =BN23 -> 71 | BP23: =BO23 -> 71 | BQ23: =$BQ$119+BJ23+BL23+BN23+BP23 -> 238309 | BR23: =BR22-BI23 -> 23872.25 | BS23: =BS22-BJ23 -> 23872.25 | BT23: =BT22-BK23 -> 23744.25 | BU23: =BU22-BL23 -> 23744.25 | BV23: =BV22-BM23 -> 38950.25 | BW23: =BW22-BN23 -> 38950.25 | BX23: =BX22-BO23 -> 24364.25 | BY23: =BY22-BP23 -> 24364.25
A24: 45643 | B24: Asmodee Czech Republic s.r.o. | C24: 捷克共和国 | D24: 4500154192 | F24: 4500154192-50 | G24: 92108-S001 | H24: 摇篮公子 | I24: 960 | J24: 0 | K24: 4 | L24: =I24/K24 -> 240 | M24: 45716 | N24: 45712 | P24: PAss | R24: 12/17收到 | T24: 1/2-进口商贴纸 | W24: 日期码格式：ZURU INC(BVI) 标准格式 日期：按实际生产日期 Packaging Info: 92108：B 版 1L MA 收缩膜+进口商贴纸；B 版 5L MA 收藏指南 Remark: 1、若产品有比例使用ZURU STD 比例 2、所有item 均用MA UPC 条码，若包装不是UPC 条码的请告知 3、此单出欧洲需满足EU测试标准要求，另外不能出闪粉（若产品本身不含闪粉则忽略这句话） | X24: Snowy Wu | Y24: 7.3108 | Z24: =Y24*I24 -> 7018.368 | AA24: 94440-3.5 | AB24: 92108-S001 | AC24: 已入 | AD24: =I24 -> 960 | AJ24: =I24 -> 960 | AQ24: =I24/4 -> 240 | AS24: =I24/4 -> 240 | AT24: =AS24 -> 240 | AV24: =AS24 -> 240 | BD24: =I24 -> 960 | BF24: =I24 -> 960 | BG24: MA | BI24: =I24/4 -> 240 | BJ24: =BI24 -> 240 | BK24: =BJ24 -> 240 | BL24: =BK24 -> 240 | BM24: =BL24 -> 240 | BN24: =BM24 -> 240 | BO24: =BN24 -> 240 | BP24: =BO24 -> 240 | BQ24: =$BQ$119+BJ24+BL24+BN24+BP24 -> 238985 | BR24: =BR23-BI24 -> 23632.25 | BS24: =BS23-BJ24 -> 23632.25 | BT24: =BT23-BK24 -> 23504.25 | BU24: =BU23-BL24 -> 23504.25 | BV24: =BV23-BM24 -> 38710.25 | BW24: =BW23-BN24 -> 38710.25 | BX24: =BX23-BO24 -> 24124.25 | BY24: =BY23-BP24 -> 24124.25
A25: 45579 | B25: WAL-MART CANADA CORP. | C25: 加拿大 | D25: 4500147525 | E25: 9650903904 | F25: 4500147525-10 | G25: 92108-S002-NB | H25: 摇篮公子 | I25: 466 | J25: 0 | K25: 1 | L25: =I25/K25 -> 466 | M25: 45722 | N25: 45719 | O25: 3/7-第三方验货（自检） | P25: PAss | Q25: 3/26出 | R25: 1/7收到 | S25: 无 | T25: UPC条码贴纸翻单：4500146212 | W25: 日期码格式：ZURU INC(BVI) 标准格式 日期：按实际生产日期 Packaging Info: #92108: MA3L收缩膜+UPC条码贴纸(UPC: 193052064721)+MA5L收藏指南+MA5L资料卡+MA5L胶袋+MA配件袋+MA2L布标 -产品配比: 4 Assortments (bunny: puppy: unicorn: kitten)=1:1:1:1 -翻单： 4500146212 Remark: 1. #92108/92107/9296 须使用无硼slime; 2. 此单有箱唛； 4. 此单有第三方验货，烦请多备包装物料； ********************* a. 请确保产品符合1999年版本的加拿大环境保护法(CEPA)和2012年禁止某些有毒物质法规的要求。该产品不含任何在加拿大禁用的化学物质，包括但不限于有毒物 质清单中列出的化学物质，并且在为加拿大沃尔玛生产产品期间没有使用任何禁用化学物质。 Supplier certify that the products comply with the requirements of Canadian Environmental Protection Act, 1999 (CEPA), Prohibition of Certain To xic Substances Regulations, 2012. The products do not contain any chemicals that are banned in Canada, including but not limited to those listed in the Toxic Substances List and no banned chemicals were used during the manufacturing of product for Walmart Canada. 附件列表： (1) Letter of Guarantee for Canada banned chemicals - (1-5CA) b. 请确保产品在均质材料中的汞浓度不超过0.1%（按重量计）。 Supplier certify that the WAL-MART vendor products does not have a mercury concentration of more than 0.1% by weight in homogeneous material. 附件列表： (1) Letter of Guarantee for Mercury COC c. 请确保产品的塑料材料不含以下物质（SOR 2011-17 27B): Supplier certify that the plastic materials do not contain the following substances(SOR 2011-17 27B): (a) carbon tetrachloride or any substance that contains it; (b) methyl alcohol or any substance thay contains >1.0%; (c) petroleum distillates or any substance that contains >10% weight to volume of petroleum distillates; (d) benzene; (e) turpentine or any substance that contains >10% weight to volume of turpentine; (f) boric acid or salts of boric acid; or (g) ethyl ether. 附件列表： (1) Letter of Guarantee for WM CA-Other prohibited substances in plastic(less than 3 years) | X25: Monica Zhou | Y25: 7.1318 | Z25: =Y25*I25 -> 3323.4188 | AA25: ZB00027-3.21 | AB25: 92108-S002-NB-3L | AC25: 已入 | AF25: =I25 -> 466 | AJ25: =I25 -> 466 | AQ25: =I25/4 -> 116.5 | AS25: =I25/4 -> 116.5 | AT25: =AS25 -> 116.5 | AV25: =AS25 -> 116.5 | BE25: =I25 -> 466 | BF25: =I25 -> 466 | BG25: MA | BI25: =I25/4 -> 116.5 | BJ25: =BI25 -> 116.5 | BK25: =BJ25 -> 116.5 | BL25: =BK25 -> 116.5 | BM25: =BL25 -> 116.5 | BN25: =BM25 -> 116.5 | BO25: =BN25 -> 116.5 | BP25: =BO25 -> 116.5 | BQ25: =$BQ$119+BJ25+BL25+BN25+BP25 -> 238491 | BR25: =BR24-BI25 -> 23515.75 | BS25: =BS24-BJ25 -> 23515.75 | BT25: =BT24-BK25 -> 23387.75 | BU25: =BU24-BL25 -> 23387.75 | BV25: =BV24-BM25 -> 38593.75 | BW25: =BW24-BN25 -> 38593.75 | BX25: =BX24-BO25 -> 24007.75 | BY25: =BY24-BP25 -> 24007.75
A26: 45637 | B26: THE WAREHOUSE LIMITED | C26: 新西兰 | D26: 4500153609 | E26: 28662059 | F26: 4500153609-20 | G26: 92108-S001 | H26: 摇篮公子 | I26: 376 | J26: 0 | K26: 4 | L26: =I26/K26 -> 94 | M26: 45726 | N26: 45722 | P26: PAss | Q26: 3/20出 | R26: 12/12收到 | T26: 无 | W26: 日期码格式：ZURU INC(BVI) 标准格式 日期：按实际生产日期 Packaging Info: MA UPC 英语包装（优先1L英语版本，或者3L/5L含英语都可） 此客人不接受易掉落或者剥落或者可直接触碰的闪粉，可降解也不行，但可以接受符合欧洲微塑料标准的珠光粉或者闪片。 Remark: 92108: 4 Assortments (bunny: puppy: unicorn: kitten)=1:1:1:1; 3pcs AAA batteries (not included) | X26: Abby Liang | Y26: 7.3277 | Z26: =Y26*I26 -> 2755.2152 | AA26: 94582-3.19 | AB26: 92108-S001 | AC26: 已入 | AD26: =I26 -> 376 | AJ26: =I26 -> 376 | AQ26: =I26/4 -> 94 | AS26: =I26/4 -> 94 | AT26: =AS26 -> 94 | AV26: =AS26 -> 94 | BD26: =I26 -> 376 | BF26: =I26 -> 376 | BG26: MA | BI26: =I26/4 -> 94 | BJ26: =BI26 -> 94 | BK26: =BJ26 -> 94 | BL26: =BK26 -> 94 | BM26: =BL26 -> 94 | BN26: =BM26 -> 94 | BO26: =BN26 -> 94 | BP26: =BO26 -> 94 | BQ26: =$BQ$119+BJ26+BL26+BN26+BP26 -> 238401 | BR26: =BR25-BI26 -> 23421.75 | BS26: =BS25-BJ26 -> 23421.75 | BT26: =BT25-BK26 -> 23293.75 | BU26: =BU25-BL26 -> 23293.75 | BV26: =BV25-BM26 -> 38499.75 | BW26: =BW25-BN26 -> 38499.75 | BX26: =BX25-BO26 -> 23913.75 | BY26: =BY25-BP26 -> 23913.75
A27: 45637 | B27: THE WAREHOUSE LIMITED | C27: 新西兰 | D27: 4500153723 | E27: 28659771 | F27: 4500153723-20 | G27: 92108-S001 | H27: 摇篮公子 | I27: 124 | J27: 0 | K27: 4 | L27: =I27/K27 -> 31 | M27: 45726 | N27: 45722 | P27: PAss | Q27: 3/20出 | R27: 12/12收到 | T27: 无 | W27: 日期码格式：ZURU INC(BVI) 标准格式 日期：按实际生产日期 Packaging Info: MA UPC 英语包装（优先1L英语版本，或者3L/5L含英语都可） 此客人不接受易掉落或者剥落或者可直接触碰的闪粉，可降解也不行，但可以接受符合欧洲微塑料标准的珠光粉或者闪片。 Remark: 92108: 4 Assortments (bunny: puppy: unicorn: kitten)=1:1:1:1; 3pcs AAA batteries (not included) | X27: Abby Liang | Y27: 7.0298 | Z27: =Y27*I27 -> 871.6952 | AA27: 94598-3.21 | AB27: 92108-S001 | AC27: 已入 | AD27: =I27 -> 124 | AJ27: =I27 -> 124 | AQ27: =I27/4 -> 31 | AS27: =I27/4 -> 31 | AT27: =AS27 -> 31 | AV27: =AS27 -> 31 | BD27: =I27 -> 124 | BF27: =I27 -> 124 | BG27: MA | BI27: =I27/4 -> 31 | BJ27: =BI27 -> 31 | BK27: =BJ27 -> 31 | BL27: =BK27 -> 31 | BM27: =BL27 -> 31 | BN27: =BM27 -> 31 | BO27: =BN27 -> 31 | BP27: =BO27 -> 31 | BQ27: =$BQ$119+BJ27+BL27+BN27+BP27 -> 238149 | BR27: =BR26-BI27 -> 23390.75 | BS27: =BS26-BJ27 -> 23390.75 | BT27: =BT26-BK27 -> 23262.75 | BU27: =BU26-BL27 -> 23262.75 | BV27: =BV26-BM27 -> 38468.75 | BW27: =BW26-BN27 -> 38468.75 | BX27: =BX26-BO27 -> 23882.75 | BY27: =BY26-BP27 -> 23882.75
A28: 45681 | B28: I-VISION TOYS.INC | C28: 韩国 | D28: 4500156433 | E28: IVI-0117BC | F28: 4500156433-20 | G28: 92108-S001-NB | H28: 摇篮公子-无硼 | I28: 2400 | J28: 0 | K28: 4 | L28: =I28/K28 -> 600 | M28: 45729 | N28: 45726 | P28: PAss | Q28: 3/14出 | R28: 箱唛翻单4500141184 | T28: 2/8-2张韩语贴纸 | V28: 客版韩语收藏指南翻单4500141184 | W28: 日期码格式：ZURU INC(BVI) 标准格式 日期：按实际生产日期 Packaging Info: 此单出韩国，92108 需出新版口水胶（无硼版，无MIT） 92108:MA 1L PKG+2张韩语贴纸(正面一张韩语logo 贴纸，背面一张韩语警语贴纸（新稿）+客版韩语收藏指南翻单4500141184 ， 箱唛翻单4500141184 请确保大货包装的生产年月 信息跟到到贴纸上的一致。确保生产年份"2025" 月份"03" Remark: 由于韩国法律法规要求，吸塑需PET材质，产品需符合韩国KC测试标准。 92108 需出新版口水胶（无硼版，无MIT） | X28: Doris Shou | Y28: 7.294 | Z28: =Y28*I28 -> 17505.6 | AA28: 94520-3.12 | AB28: 92108-S001-NB-1 | AC28: 已入 | AD28: =I28 -> 2400 | AN28: =I28 -> 2400 | AQ28: =I28/4 -> 600 | AS28: =I28/4 -> 600 | AT28: =I28/4 -> 600 | AV28: =I28/4 -> 600 | BE28: =I28 -> 2400 | BF28: =I28 -> 2400 | BG28: MA | BI28: =I28/4 -> 600 | BJ28: =BI28 -> 600 | BK28: =BJ28 -> 600 | BL28: =BK28 -> 600 | BM28: =BL28 -> 600 | BN28: =BM28 -> 600 | BO28: =BN28 -> 600 | BP28: =BO28 -> 600 | BQ28: =$BQ$119+BJ28+BL28+BN28+BP28 -> 240425 | BR28: =BR27-BI28 -> 22790.75 | BS28: =BS27-BJ28 -> 22790.75 | BT28: =BT27-BK28 -> 22662.75 | BU28: =BU27-BL28 -> 22662.75 | BV28: =BV27-BM28 -> 37868.75 | BW28: =BW27-BN28 -> 37868.75 | BX28: =BX27-BO28 -> 23282.75 | BY28: =BY27-BP28 -> 23282.75
A29: 45677 | B29: Bol.com | C29: 新西兰 | D29: 4500156115 | E29: 7631985 | F29: 4500156115-50 | G29: 92108D-S003 | H29: 独角兽 邮包盒装 | I29: 100 | J29: 1 | K29: 2 | L29: =I29/K29 -> 50 | M29: 45730 | N29: 45726 | P29: PAss | Q29: 3/17出 | R29: 1/20收到 | T29: 2/8-贴纸1张(含NL警告 语+EAN#条码贴纸 | V29: 客版邮包盒(参考Amazon PO#4500124874 | W29: 日期码格式：ZURU INC(BVI) 标准格式 日期：按实际生产日期 Packaging Info: BOL NL(92108ABDE) 5. 92108ABDE ---92108D:1 PCS/MAIL BOX, 2PCS/2MAIL BOX/CTN<(>,<)>unicorn, Non-glitter;magnet,3pcs AAA batteries (not included); MA 3L(9L warning EAN版本)B收缩 膜+MA 2L A布标+MA 5L(9L warning)B收藏指南+MA 5L B图书卡+MA 5L(9L warning)B Slime胶袋+MA B配件袋+客版邮包盒(参考Amazon PO#4500124874)+贴纸1张(含N L警告语+EAN#条码贴纸，直接覆盖在邮包盒原警告语等位置) 13. 验货时间不迟于2025/3/17. Remark: 1. 出欧洲产品不可含闪粉或者微塑料，若所涉产品无闪粉或不含微塑料可忽略此点； 2. 5 Surprise or Mini Brands涉及包装是2个及2个以上的球入PVC桶包装时，单个球上若有UPC#或者EAN#，请用白色贴纸覆盖住； 3. 箱唛资料按照提供的要求去做即可，无需再发回我方确认； 4.柜货产品务必拉网且要拉紧，拉网要求： A: 网要结实同时网格要细，纸箱不能从网格处跌落下来 B: 打网固定8-10个点。请提供拉网的装柜照片给船务确认 后柜子再离厂。" | X29: Crystal Chen | Y29: 7.3794 | Z29: =Y29*I29 -> 737.94 | AA29: 94548-3.14 | AB29: 92108D-S001-3L新（V1） | AC29: 已入 | AG29: =I29 -> 100 | AJ29: =I29 -> 100 | AT29: =I29 -> 100 | AV29: =I29/4 -> 25 | BD29: =I29 -> 100 | BF29: =I29 -> 100 | BG29: MA | BK29: =I29 -> 100 | BL29: =BK29 -> 100 | BQ29: =$BQ$119+BJ29+BL29+BN29+BP29 -> 238125 | BR29: =BR28-BI29 -> 22790.75 | BS29: =BS28-BJ29 -> 22790.75 | BT29: =BT28-BK29 -> 22562.75 | BU29: =BU28-BL29 -> 22562.75 | BV29: =BV28-BM29 -> 37868.75 | BW29: =BW28-BN29 -> 37868.75 | BX29: =BX28-BO29 -> 23282.75 | BY29: =BY28-BP29 -> 23282.75
A30: 45677 | B30: Bol.com | C30: 新西兰 | D30: 4500156115 | E30: 7631985 | F30: 4500156115-60 | G30: 92108A-S003 | H30: 兔子 邮包盒装 | I30: 100 | J30: 1 | K30: 2 | L30: =I30/K30 -> 50 | M30: 45730 | N30: 45726 | P30: PAss | Q30: 3/17出 | R30: 1/20收到 | T30: 2/8-贴纸1张(含NL警告 语+EAN#条码贴纸 | V30: 客版邮包盒(参考Amazon PO#4500124874 | W30: 日期码格式：ZURU INC(BVI) 标准格式 日期：按实际生产日期 Packaging Info: BOL NL(71126/77515/92104ABDEGH/92107ABDE/92108ABDE/9258ABDEGH/9281BDEGH/9283ABDE/9296ABDEGH/9298ABDEGH/9543ABDE/9548/9549ABD) 5. 92108ABDE ---92108D:1 PCS/MAIL BOX, 2PCS/2MAIL BOX/CTN<(>,<)>unicorn, Non-glitter;magnet,3pcs AAA batteries (not included); MA 3L(9L warning EAN版本)B收缩 膜+MA 2L A布标+MA 5L(9L warning)B收藏指南+MA 5L B图书卡+MA 5L(9L warning)B Slime胶袋+MA B配件袋+客版邮包盒(参考Amazon PO#4500124874)+贴纸1张(含N L警告语+EAN#条码贴纸，直接覆盖在邮包盒原警告语等位置) 13. 验货时间不迟于2025/3/17. Remark: 1. 出欧洲产品不可含闪粉或者微塑料，若所涉产品无闪粉或不含微塑料可忽略此点； 2. 5 Surprise or Mini Brands涉及包装是2个及2个以上的球入PVC桶包装时，单个球上若有UPC#或者EAN#，请用白色贴纸覆盖住； 3. 箱唛资料按照提供的要求去做即可，无需再发回我方确认； 4.柜货产品务必拉网且要拉紧，拉网要求： A: 网要结实同时网格要细，纸箱不能从网格处跌落下来 B: 打网固定8-10个点。请提供拉网的装柜照片给船务确认 后柜子再离厂。" | X30: Crystal Chen | Y30: 7.3794 | Z30: =Y30*I30 -> 737.94 | AA30: 94548-3.14 | AB30: 92108A-S001-3L新（V1） | AC30: 已入 | AG30: =I30 -> 100 | AJ30: =I30 -> 100 | AS30: =I30 -> 100 | BD30: =I30 -> 100 | BF30: =I30 -> 100 | BG30: MA | BI30: =I30 -> 100 | BJ30: =BI30 -> 100 | BQ30: =$BQ$119+BJ30+BL30+BN30+BP30 -> 238125 | BR30: =BR29-BI30 -> 22690.75 | BS30: =BS29-BJ30 -> 22690.75 | BT30: =BT29-BK30 -> 22562.75 | BU30: =BU29-BL30 -> 22562.75 | BV30: =BV29-BM30 -> 37868.75 | BW30: =BW29-BN30 -> 37868.75 | BX30: =BX29-BO30 -> 23282.75 | BY30: =BY29-BP30 -> 23282.75
A31: 45677 | B31: Bol.com | C31: 新西兰 | D31: 4500156115 | E31: 7631985 | F31: 4500156115-70 | G31: 92108B-S003 | H31: 斑点狗 邮包盒装 | I31: 100 | J31: 1 | K31: 2 | L31: =I31/K31 -> 50 | M31: 45730 | N31: 45726 | P31: PAss | Q31: 3/17出 | R31: 1/20收到 | T31: 2/8-贴纸1张(含NL警告 语+EAN#条码贴纸 | V31: 客版邮包盒(参考Amazon PO#4500124874 | W31: 日期码格式：ZURU INC(BVI) 标准格式 日期：按实际生产日期 Packaging Info: BOL NL(71126/77515/92104ABDEGH/92107ABDE/92108ABDE/9258ABDEGH/9281BDEGH/9283ABDE/9296ABDEGH/9298ABDEGH/9543ABDE/9548/9549ABD) 5. 92108ABDE ---92108B: 1 PCS/MAIL BOX, 2PCS/2MAIL BOX/CTN,unicorn, Non-glitter;magnet,3pcs AAA batteries (not included); MA 3L(9L warning EAN版本)B收缩膜+MA 2L A布标+MA 5L(9L warning)B收藏指南+MA 5L B图书卡+MA 5L(9L warning)B Slime胶袋+MA B配件袋+客版邮包盒(参考Amazon PO#4500124874)+贴纸1张(含NL警告 语+EAN#条码贴纸，直接覆盖在邮包盒原警告语等位置) 13. 验货时间不迟于2025/3/17. Remark: 1. 出欧洲产品不可含闪粉或者微塑料，若所涉产品无闪粉或不含微塑料可忽略此点； 2. 5 Surprise or Mini Brands涉及包装是2个及2个以上的球入PVC桶包装时，单个球上若有UPC#或者EAN#，请用白色贴纸覆盖住； 3. 箱唛资料按照提供的要求去做即可，无需再发回我方确认； 4.柜货产品务必拉网且要拉紧，拉网要求： A: 网要结实同时网格要细，纸箱不能从网格处跌落下来 B: 打网固定8-10个点。请提供拉网的装柜照片给船务确认 后柜子再离厂。" | X31: Crystal Chen | Y31: 7.3794 | Z31: =Y31*I31 -> 737.94 | AA31: 94548-3.14 | AB31: 92108B-S001-3L新（V1） | AC31: 已入 | AG31: =I31 -> 100 | AJ31: =I31 -> 100 | AV31: =I31 -> 100 | BD31: =I31 -> 100 | BF31: =I31 -> 100 | BG31: MA | BO31: =I31 -> 100 | BP31: =BO31 -> 100 | BQ31: =$BQ$119+BJ31+BL31+BN31+BP31 -> 238125 | BR31: =BR30-BI31 -> 22690.75 | BS31: =BS30-BJ31 -> 22690.75 | BT31: =BT30-BK31 -> 22562.75 | BU31: =BU30-BL31 -> 22562.75 | BV31: =BV30-BM31 -> 37868.75 | BW31: =BW30-BN31 -> 37868.75 | BX31: =BX30-BO31 -> 23182.75 | BY31: =BY30-BP31 -> 23182.75
A32: 45677 | B32: Bol.com | C32: 新西兰 | D32: 4500156115 | E32: 7631985 | F32: 4500156115-90 | G32: 92108E-S003 | H32: 小猫 邮包盒装 | I32: 100 | J32: 0 | K32: 2 | L32: =I32/K32 -> 50 | M32: 45730 | N32: 45726 | P32: PAss | Q32: 3/17出 | R32: 1/20收到 | T32: 2/8-贴纸1张(含NL警告 语+EAN#条码贴纸 | V32: 客版邮包盒(参考Amazon PO#4500124874 | W32: 日期码格式：ZURU INC(BVI) 标准格式 日期：按实际生产日期 Packaging Info: BOL NL(71126/77515/92104ABDEGH/92107ABDE/92108ABDE/9258ABDEGH/9281BDEGH/9283ABDE/9296ABDEGH/9298ABDEGH/9543ABDE/9548/9549ABD) 5. 92108ABDE ---92108E: 1 PCS/MAIL BOX, 2PCS/2MAIL BOX/CTN,unicorn, Non-glitter;magnet,3pcs AAA batteries (not included); MA 3L(9L warning EAN版本)B收缩膜+MA 2L A布标+MA 5L(9L warning)B收藏指南+MA 5L B图书卡+MA 5L(9L warning)B Slime胶袋+MA B配件袋+客版邮包盒(参考Amazon PO#4500124874)+贴纸1张(含NL警告 语+EAN#条码贴纸，直接覆盖在邮包盒原警告语等位置) 13. 验货时间不迟于2025/3/17. Remark: 1. 出欧洲产品不可含闪粉或者微塑料，若所涉产品无闪粉或不含微塑料可忽略此点； 2. 5 Surprise or Mini Brands涉及包装是2个及2个以上的球入PVC桶包装时，单个球上若有UPC#或者EAN#，请用白色贴纸覆盖住； 3. 箱唛资料按照提供的要求去做即可，无需再发回我方确认； 4.柜货产品务必拉网且要拉紧，拉网要求： A: 网要结实同时网格要细，纸箱不能从网格处跌落下来 B: 打网固定8-10个点。请提供拉网的装柜照片给船务确认 后柜子再离厂。" | X32: Crystal Chen | Y32: 7.3794 | Z32: =Y32*I32 -> 737.94 | AA32: 94548-3.14 | AB32: 92108E-S003-3L | AC32: 已入 | AG32: =I32 -> 100 | AJ32: =I32 -> 100 | AQ32: =I32 -> 100 | BD32: =I32 -> 100 | BF32: =I32 -> 100 | BG32: MA | BM32: =I32 -> 100 | BN32: =BM32 -> 100 | BQ32: =$BQ$119+BJ32+BL32+BN32+BP32 -> 238125 | BR32: =BR31-BI32 -> 22690.75 | BS32: =BS31-BJ32 -> 22690.75 | BT32: =BT31-BK32 -> 22562.75 | BU32: =BU31-BL32 -> 22562.75 | BV32: =BV31-BM32 -> 37768.75 | BW32: =BW31-BN32 -> 37768.75 | BX32: =BX31-BO32 -> 23182.75 | BY32: =BY31-BP32 -> 23182.75
A33: 45683 | B33: MTA Trade | C33: 哈萨克斯坦 | D33: 4500156659 | F33: 4500156659-90 | G33: 92108D-S001 | H33: 独角兽 | I33: 460 | J33: 0 | K33: 4 | L33: =I33/K33 -> 115 | M33: 45734 | N33: 45730 | P33: PAss | Q33: 3/27出 | R33: 2/17收到 | T33: 2/17-进口商贴纸(共用贴纸)+UPC条码贴纸 | W33: 日期码格式：ZURU INC(BVI) 标准格式 日期：按实际生产日期 Packaging Info: 92108D：1L MA 最新收缩膜+进口商贴纸(共用贴纸)+UPC条码贴纸, MA 指南 Remark: 标准配比 | X33: Ann Zhang | Y33: 7.3277 | Z33: =Y33*I33 -> 3370.742 | AA33: 94654-3.27 | AB33: 92108D-S001 | AC33: 已入 | AD33: =I33 -> 460 | AJ33: =I33 -> 460 | AT33: =I33 -> 460 | BD33: =I33 -> 460 | BF33: =I33 -> 460 | BG33: MA | BK33: =I33 -> 460 | BL33: =I33 -> 460 | BQ33: =$BQ$119+BJ33+BL33+BN33+BP33 -> 238485 | BR33: =BR32-BI33 -> 22690.75 | BS33: =BS32-BJ33 -> 22690.75 | BT33: =BT32-BK33 -> 22102.75 | BU33: =BU32-BL33 -> 22102.75 | BV33: =BV32-BM33 -> 37768.75 | BW33: =BW32-BN33 -> 37768.75 | BX33: =BX32-BO33 -> 23182.75 | BY33: =BY32-BP33 -> 23182.75
A34: 45683 | B34: MTA Trade | C34: 哈萨克斯坦 | D34: 4500156659 | F34: 4500156659-100 | G34: 92108E-S001 | H34: 小猫 | I34: 460 | J34: 0 | K34: 4 | L34: =I34/K34 -> 115 | M34: 45734 | N34: 45730 | P34: PAss | Q34: 3/27出 | R34: 2/17收到 | T34: 2/17-进口商贴纸(共用贴纸)+UPC条码贴纸 | W34: 日期码格式：ZURU INC(BVI) 标准格式 日期：按实际生产日期 Packaging Info: 92108E：1L MA 最新收缩膜+进口商贴纸(共用贴纸)+UPC条码贴纸, MA 指南 Remark: 标准配比 | X34: Ann Zhang | Y34: 7.3277 | Z34: =Y34*I34 -> 3370.742 | AA34: 94654-3.27 | AB34: 92108E-S001 | AC34: 已入 | AD34: =I34 -> 460 | AJ34: =I34 -> 460 | AQ34: =I34 -> 460 | BD34: =I34 -> 460 | BF34: =I34 -> 460 | BG34: MA | BM34: =I34 -> 460 | BN34: =I34 -> 460 | BQ34: =$BQ$119+BJ34+BL34+BN34+BP34 -> 238485 | BR34: =BR33-BI34 -> 22690.75 | BS34: =BS33-BJ34 -> 22690.75 | BT34: =BT33-BK34 -> 22102.75 | BU34: =BU33-BL34 -> 22102.75 | BV34: =BV33-BM34 -> 37308.75 | BW34: =BW33-BN34 -> 37308.75 | BX34: =BX33-BO34 -> 23182.75 | BY34: =BY33-BP34 -> 23182.75
A35: 45683 | B35: MTA Trade | C35: 哈萨克斯坦 | D35: 4500156659 | F35: 4500156659-30 | G35: 92108-S001 | H35: 摇篮公子 | I35: 568 | J35: 0 | K35: 4 | L35: =I35/K35 -> 142 | M35: 45736 | N35: 45733 | P35: PAss | Q35: 3/27出 | R35: 2/17收到 | T35: 进口商贴纸（翻PO4500153567) | W35: 日期码格式：ZURU INC(BVI) 标准格式 日期：按实际生产日期 Packaging Info: 92108：1L MA 最新收缩膜+进口商贴纸（翻PO4500153567), MA 指南 Remark: 标准配比 | X35: Ann Zhang | Y35: 7.3108 | Z35: =Y35*I35 -> 4152.5344 | AA35: 94654-3.27 | AB35: 92108-S001 | AC35: 已入 | AD35: =I35 -> 568 | AJ35: =I35 -> 568 | AQ35: =I35/4 -> 142 | AS35: =I35/4 -> 142 | AT35: =I35/4 -> 142 | AV35: =I35/4 -> 142 | BD35: =I35 -> 568 | BF35: =I35 -> 568 | BG35: MA | BI35: =I35/4 -> 142 | BJ35: =BI35 -> 142 | BK35: =BJ35 -> 142 | BL35: =BK35 -> 142 | BM35: =BL35 -> 142 | BN35: =BM35 -> 142 | BO35: =BN35 -> 142 | BP35: =BO35 -> 142 | BQ35: =$BQ$119+BJ35+BL35+BN35+BP35 -> 238593 | BR35: =BR34-BI35 -> 22548.75 | BS35: =BS34-BJ35 -> 22548.75 | BT35: =BT34-BK35 -> 21960.75 | BU35: =BU34-BL35 -> 21960.75 | BV35: =BV34-BM35 -> 37166.75 | BW35: =BW34-BN35 -> 37166.75 | BX35: =BX34-BO35 -> 23040.75 | BY35: =BY34-BP35 -> 23040.75
A36: 45652 | B36: CARREFOUR ARGENTINA | C36: 阿根廷 | D36: 4500154827 | F36: 4500154827-10 | G36: 92108-S001 | H36: 摇篮公子 | I36: 300 | J36: 0 | K36: 4 | L36: =I36/K36 -> 75 | M36: 45737 | N36: 45733 | O36: 3/25第三方 | P36: PAss | Q36: 4/1出 | R36: 2/19收到-双坑纸箱 | T36: 3/7-进口商贴纸+警告语贴纸+EAN贴纸+色丁贴纸 | U36: 3/18-外箱贴纸 | V36: DG20250213 | W36: 日期码格式：ZURU INC(BVI) 标准格式 日期：按实际生产日期 Packaging Info: 1.92108:MA 3L EAN包装+进口商贴纸+警告语贴纸（警告语贴纸贴于产品正面，不需要贴展示架）+EAN贴纸+色丁贴纸(贴MA布标上） 2.箱唛：在正唛（只1面）加多虚线15 X 10.5 CM ( 高X 宽) 距左箱边2CM， 距箱底 3CM,1张外箱贴纸Carrefour master carton label（在CHECKPOINT网站上订）, 工厂自行订购,可参照家乐福其他地区的。请检查贴纸上的外箱尺寸和重量是否和实际一致，如果材积超出正负7%，订购时要在系统更新资料并且通知给跟单。如果 第三方验货时发现与实际超出7%，会产生罚款USD300/每款ITEM。 3.产品/包装/外箱都要打上日期码，产品、包装和外箱的日期码要一致。 4.外箱纸箱要用双坑的，否则会影响出货。 5.此单有API第三方验货，，提供1套大货签板留底，请在大货前两周寄给我们，工厂需提交签板图片给客户审核。 6.签版要与大货一致。 7.此单因验厂问题，搏锐/沙沙岛/百炼需要送到兴信验货，验货时间待通知。 Remark: 92108包装条码：3617702057606 | X36: Ava Liang | Y36: 7.0298 | Z36: =Y36*I36 -> 2108.94 | AA36: 94681-4.1 | AB36: 92108-S001-3L | AC36: 已入 | AG36: =I36 -> 300 | AJ36: =I36 -> 300 | AQ36: =I36/4 -> 75 | AS36: =I36/4 -> 75 | AT36: =I36/4 -> 75 | AV36: =AS36 -> 75 | BD36: =I36 -> 300 | BF36: =I36 -> 300 | BG36: MA | BI36: =I36/4 -> 75 | BJ36: =BI36 -> 75 | BK36: =BJ36 -> 75 | BL36: =BK36 -> 75 | BM36: =BL36 -> 75 | BN36: =BM36 -> 75 | BO36: =BN36 -> 75 | BP36: =BO36 -> 75 | BQ36: =$BQ$119+BJ36+BL36+BN36+BP36 -> 238325 | BR36: =BR35-BI36 -> 22473.75 | BS36: =BS35-BJ36 -> 22473.75 | BT36: =BT35-BK36 -> 21885.75 | BU36: =BU35-BL36 -> 21885.75 | BV36: =BV35-BM36 -> 37091.75 | BW36: =BW35-BN36 -> 37091.75 | BX36: =BX35-BO36 -> 22965.75 | BY36: =BY35-BP36 -> 22965.75
A37: 45698 | B37: CARREFOUR ARGENTINA | C37: 阿根廷 | D37: 4500154827 | F37: 4500154827-40 | G37: 92108F-S001 | H37: 摇篮公子展示架 | I37: 360 | J37: 0 | K37: 24 | L37: =I37/K37 -> 15 | M37: 45737 | N37: 45733 | O37: 3/25第三方 | P37: PAss | Q37: 4/1出 | R37: 2/19收到-双坑纸箱 | T37: 3/7-进口商贴纸+警告语贴纸+EAN贴纸+色丁贴纸 | U37: 3/18-外箱贴纸 | V37: DG20250213 | W37: 日期码格式：ZURU INC(BVI) 标准格式 日期：按实际生产日期 Packaging Info: 1.92108F:MA 3L EAN包装+进口商贴纸+警告语贴纸（警告语贴纸贴于产品正面，不需要贴展示架）+EAN贴纸+色丁贴纸(贴MA布标上） 2.箱唛：在正唛（只1面）加多虚线15 X 10.5 CM ( 高X 宽) 距左箱边2CM， 距箱底 3CM,1张外箱贴纸Carrefour master carton label（在CHECKPOINT网站上订）, 工厂自行订购,可参照家乐福其他地区的。请检查贴纸上的外箱尺寸和重量是否和实际一致，如果材积超出正负7%，订购时要在系统更新资料并且通知给跟单。如果 第三方验货时发现与实际超出7%，会产生罚款USD300/每款ITEM。 3.产品/包装/外箱都要打上日期码，产品、包装和外箱的日期码要一致。 4.外箱纸箱要用双坑的，否则会影响出货。 5.此单有API第三方验货，，提供1套大货签板留底，请在大货前两周寄给我们，工厂需提交签板图片给客户审核。 6.签版要与大货一致。 7.此单因验厂问题，搏锐/沙沙岛/百炼需要送到兴信验货，验货时间待通知。 92108F 条码：3617702057606 Remark: 92108F包装条码：3617702057606 | X37: Ava Liang | Y37: 34.2746 | Z37: =Y37*L37 -> 514.119 | AA37: 94681-4.1 | AB37: 92108F-S001-3L新（V1） | AC37: 已入 | AG37: =I37 -> 360 | AJ37: =I37 -> 360 | AQ37: =I37/4 -> 90 | AS37: =I37/4 -> 90 | AT37: =I37/4 -> 90 | AV37: =AS37 -> 90 | BA37: =L37 -> 15 | BD37: =I37 -> 360 | BF37: =I37 -> 360 | BG37: MA | BI37: =I37/4 -> 90 | BJ37: =BI37 -> 90 | BK37: =BJ37 -> 90 | BL37: =BK37 -> 90 | BM37: =BL37 -> 90 | BN37: =BM37 -> 90 | BO37: =BN37 -> 90 | BP37: =BO37 -> 90 | BQ37: =$BQ$119+BJ37+BL37+BN37+BP37 -> 238385 | BR37: =BR36-BI37 -> 22383.75 | BS37: =BS36-BJ37 -> 22383.75 | BT37: =BT36-BK37 -> 21795.75 | BU37: =BU36-BL37 -> 21795.75 | BV37: =BV36-BM37 -> 37001.75 | BW37: =BW36-BN37 -> 37001.75 | BX37: =BX36-BO37 -> 22875.75 | BY37: =BY36-BP37 -> 22875.75
A38: 45705 | B38: Royal Foods LLC | C38: 阿塞拜疆 | D38: 4500157780 | F38: 4500157780-30 | G38: 92108-S001 | H38: 摇篮公子 | I38: 120 | J38: 0 | K38: 4 | L38: =I38/K38 -> 30 | M38: 45741 | N38: 45737 | P38: PAss | Q38: 4/17出 | R38: 2/17收到 | T38: 无 | W38: 日期码格式：ZURU INC(BVI) 标准格式 日期：按实际生产日期 Packaging Info: 1. 无进口商贴纸； 2. 92108 ： 1L MA UPC 包装， MA PDQ/说明书/指南（如有）； Remark: 标准配比 | X38: Ann Zhang | Y38: 7.0298 | Z38: =Y38*I38 -> 843.576 | AA38: 94710-4.7 | AB38: 92108-S001新（V1） | AC38: 已入 | AD38: =I38 -> 120 | AJ38: =I38 -> 120 | AQ38: =I38/4 -> 30 | AS38: =I38/4 -> 30 | AT38: =I38/4 -> 30 | AV38: =AS38 -> 30 | BD38: =I38 -> 120 | BF38: =I38 -> 120 | BG38: MA | BI38: =I38/4 -> 30 | BJ38: =BI38 -> 30 | BK38: =BJ38 -> 30 | BL38: =BK38 -> 30 | BM38: =BL38 -> 30 | BN38: =BM38 -> 30 | BO38: =BN38 -> 30 | BP38: =BO38 -> 30 | BQ38: =$BQ$119+BJ38+BL38+BN38+BP38 -> 238145 | BR38: =BR37-BI38 -> 22353.75 | BS38: =BS37-BJ38 -> 22353.75 | BT38: =BT37-BK38 -> 21765.75 | BU38: =BU37-BL38 -> 21765.75 | BV38: =BV37-BM38 -> 36971.75 | BW38: =BW37-BN38 -> 36971.75 | BX38: =BX37-BO38 -> 22845.75 | BY38: =BY37-BP38 -> 22845.75
A39: 45579 | B39: WAL-MART CANADA CORP. | C39: 加拿大 | D39: 4500147528 | E39: 9650903905 | F39: 4500147528-10 | G39: 92108-S002-NB | H39: 摇篮公子 | I39: 305 | J39: 0 | K39: 1 | L39: =I39/K39 -> 305 | M39: 45748 | N39: 45744 | O39: 3/31第三方（自检） | P39: PAss | Q39: 4/15出 | R39: 2/24收到 | S39: 无 | T39: UPC条码贴纸翻单：4500146212 | W39: 日期码格式：ZURU INC(BVI) 标准格式 日期：按实际生产日期 Packaging Info: #92108: MA3L收缩膜+UPC条码贴纸(UPC: 193052064721)+MA5L收藏指南+MA5L资料卡+MA5L胶袋+MA配件袋+MA2L布标 -产品配比: 4 Assortments (bunny: puppy: unicorn: kitten)=1:1:1:1 -翻单： 4500146212 Remark: 1. #92108/92107/9296 须使用无硼slime; 2. 此单有箱唛； 4. 此单有第三方验货，烦请多备包装物料； ********************* a. 请确保产品符合1999年版本的加拿大环境保护法(CEPA)和2012年禁止某些有毒物质法规的要求。该产品不含任何在加拿大禁用的化学物质，包括但不限于有毒物 质清单中列出的化学物质，并且在为加拿大沃尔玛生产产品期间没有使用任何禁用化学物质。 Supplier certify that the products comply with the requirements of Canadian Environmental Protection Act, 1999 (CEPA), Prohibition of Certain To xic Substances Regulations, 2012. The products do not contain any chemicals that are banned in Canada, including but not limited to those listed in the Toxic Substances List and no banned chemicals were used during the manufacturing of product for Walmart Canada. 附件列表： (1) Letter of Guarantee for Canada banned chemicals - (1-5CA) b. 请确保产品在均质材料中的汞浓度不超过0.1%（按重量计）。 Supplier certify that the WAL-MART vendor products does not have a mercury concentration of more than 0.1% by weight in homogeneous material. 附件列表： (1) Letter of Guarantee for Mercury COC c. 请确保产品的塑料材料不含以下物质（SOR 2011-17 27B): Supplier certify that the plastic materials do not contain the following substances(SOR 2011-17 27B): (a) carbon tetrachloride or any substance that contains it; (b) methyl alcohol or any substance thay contains >1.0%; (c) petroleum distillates or any substance that contains >10% weight to volume of petroleum distillates; (d) benzene; (e) turpentine or any substance that contains >10% weight to volume of turpentine; (f) boric acid or salts of boric acid; or (g) ethyl ether. 附件列表： (1) Letter of Guarantee for WM CA-Other prohibited substances in plastic(less than 3 years) | X39: Monica Zhou | Y39: 7.4848 | Z39: =Y39*I39 -> 2282.864 | AA39: 94761-4.14 | AB39: 92108-S002-NB-3L | AC39: 已入 | AG39: =I39 -> 305 | AJ39: =I39 -> 305 | AQ39: =I39/4 -> 76.25 | AS39: =I39/4 -> 76.25 | AT39: =I39/4 -> 76.25 | AV39: =AS39 -> 76.25 | BE39: =I39 -> 305 | BF39: =I39 -> 305 | BG39: MA | BI39: =I39/4 -> 76.25 | BJ39: =BI39 -> 76.25 | BK39: =BJ39 -> 76.25 | BL39: =BK39 -> 76.25 | BM39: =BL39 -> 76.25 | BN39: =BM39 -> 76.25 | BO39: =BN39 -> 76.25 | BP39: =BO39 -> 76.25 | BQ39: =$BQ$119+BJ39+BL39+BN39+BP39 -> 238330 | BR39: =BR38-BI39 -> 22277.5 | BS39: =BS38-BJ39 -> 22277.5 | BT39: =BT38-BK39 -> 21689.5 | BU39: =BU38-BL39 -> 21689.5 | BV39: =BV38-BM39 -> 36895.5 | BW39: =BW38-BN39 -> 36895.5 | BX39: =BX38-BO39 -> 22769.5 | BY39: =BY38-BP39 -> 22769.5
A40: 45765 | B40: DM LLC | C40: 俄罗斯联邦 | D40: 4500163959 | E40: 包装要求参考4 500158543，出 Bekasovo 2 | F40: 4500163959-70 | G40: 92108-S001 | H40: 摇篮公子 | I40: 1420 | J40: 0 | K40: 4 | L40: =I40/K40 -> 355 | M40: 45765 | N40: 45761 | O40: 原4500158543转单-注意不要重复生产 | P40: PAss | Q40: 4/28出 | R40: 3/3收到 | T40: 3/4-进口商贴纸+ EAN条码贴纸 | V40: 外包装/外箱不要打ZURU标准日期码 日期 | W40: 日期码格式：外包装/外箱不要打ZURU标准日期码 日期： Packaging Info: 取代4500150271/4500157991/4500146630/4500159461/4500158543中 对应的款 ; 包装要求参考4500150271/4500157991/4500146630/4500159461/4500158543 Remark: | X40: Ann | Y40: 7.1595 | Z40: =Y40*I40 -> 10166.49 | AA40: 94862-4.28 | AB40: 92108-S001新（V1） | AC40: 已入 | AD40: =I40 -> 1420 | AJ40: =I40 -> 1420 | AQ40: =I40/4 -> 355 | AS40: =I40/4 -> 355 | AT40: =I40/4 -> 355 | AV40: =AS40 -> 355 | BD40: =I40 -> 1420 | BF40: =I40 -> 1420 | BG40: MA | BI40: =I40/4 -> 355 | BJ40: =BI40 -> 355 | BK40: =BJ40 -> 355 | BL40: =BK40 -> 355 | BM40: =BL40 -> 355 | BN40: =BM40 -> 355 | BO40: =BN40 -> 355 | BP40: =BO40 -> 355 | BQ40: =$BQ$119+BJ40+BL40+BN40+BP40 -> 239445 | BR40: =BR39-BI40 -> 21922.5 | BS40: =BS39-BJ40 -> 21922.5 | BT40: =BT39-BK40 -> 21334.5 | BU40: =BU39-BL40 -> 21334.5 | BV40: =BV39-BM40 -> 36540.5 | BW40: =BW39-BN40 -> 36540.5 | BX40: =BX39-BO40 -> 22414.5 | BY40: =BY39-BP40 -> 22414.5
A41: 45765 | B41: DM LLC | C41: 俄罗斯联邦 | D41: 4500163959 | E41: 包装要求参考4 500158543，出 Ural | F41: 4500163959-90 | G41: 92108-S001 | H41: 摇篮公子 | I41: 580 | J41: 0 | K41: 4 | L41: =I41/K41 -> 145 | M41: 45765 | N41: 45761 | O41: 原4500158543转单-注意不要重复生产 | P41: PAss | Q41: 4/28出 | R41: 3/3收到 | T41: 3/4-进口商贴纸+ EAN条码贴纸 | V41: 外包装/外箱不要打ZURU标准日期码 日期 | W41: 日期码格式：外包装/外箱不要打ZURU标准日期码 日期： Packaging Info: 取代4500150271/4500157991/4500146630/4500159461/4500158543中 对应的款 ; 包装要求参考4500150271/4500157991/4500146630/4500159461/4500158543 Remark: | X41: Ann | Y41: 7.1595 | Z41: =Y41*I41 -> 4152.51 | AA41: 94862-4.28 | AB41: 92108-S001新（V1） | AC41: 已入 | AD41: =I41 -> 580 | AJ41: =I41 -> 580 | AQ41: =I41/4 -> 145 | AS41: =I41/4 -> 145 | AT41: =I41/4 -> 145 | AV41: =AS41 -> 145 | BD41: =I41 -> 580 | BF41: =I41 -> 580 | BG41: MA | BI41: =I41/4 -> 145 | BJ41: =BI41 -> 145 | BK41: =BJ41 -> 145 | BL41: =BK41 -> 145 | BM41: =BL41 -> 145 | BN41: =BM41 -> 145 | BO41: =BN41 -> 145 | BP41: =BO41 -> 145 | BQ41: =$BQ$119+BJ41+BL41+BN41+BP41 -> 238605 | BR41: =BR40-BI41 -> 21777.5 | BS41: =BS40-BJ41 -> 21777.5 | BT41: =BT40-BK41 -> 21189.5 | BU41: =BU40-BL41 -> 21189.5 | BV41: =BV40-BM41 -> 36395.5 | BW41: =BW40-BN41 -> 36395.5 | BX41: =BX40-BO41 -> 22269.5 | BY41: =BY40-BP41 -> 22269.5
A42: 45765 | B42: DM LLC | C42: 俄罗斯联邦 | D42: 4500164028 | E42: 包装要求参考4 500158543，出 Ural | F42: 4500164028-90 | G42: 92108-S001 | H42: 摇篮公子 | I42: 860 | J42: 0 | K42: 4 | L42: =I42/K42 -> 215 | M42: 45765 | N42: 45761 | O42: 原4500158543转单-注意不要重复生产 | P42: PAss | R42: 3/3收到 | T42: 3/4-进口商贴纸+ EAN条码贴纸 | V42: 外包装/外箱不要打ZURU标准日期码 日期 | W42: 日期码格式：外包装/外箱不要打ZURU标准日期码 日期： Packaging Info: 取代4500150271/4500157991/4500146630/4500159461/4500158543中 对应的款 ; 包装要求参考4500150271/4500157991/4500146630/4500159461/4500158543 Remark: | X42: Ann | Y42: 7.1595 | Z42: =Y42*I42 -> 6157.17 | AB42: 92108-S001新（V1） | AC42: 已入 | AD42: =I42 -> 860 | AJ42: =I42 -> 860 | AQ42: =I42/4 -> 215 | AS42: =I42/4 -> 215 | AT42: =I42/4 -> 215 | AV42: =AS42 -> 215 | BD42: =I42 -> 860 | BF42: =I42 -> 860 | BG42: MA | BI42: =I42/4 -> 215 | BJ42: =BI42 -> 215 | BK42: =BJ42 -> 215 | BL42: =BK42 -> 215 | BM42: =BL42 -> 215 | BN42: =BM42 -> 215 | BO42: =BN42 -> 215 | BP42: =BO42 -> 215 | BQ42: =$BQ$119+BJ42+BL42+BN42+BP42 -> 238885 | BR42: =BR41-BI42 -> 21562.5 | BS42: =BS41-BJ42 -> 21562.5 | BT42: =BT41-BK42 -> 20974.5 | BU42: =BU41-BL42 -> 20974.5 | BV42: =BV41-BM42 -> 36180.5 | BW42: =BW41-BN42 -> 36180.5 | BX42: =BX41-BO42 -> 22054.5 | BY42: =BY41-BP42 -> 22054.5
A43: 45765 | B43: DM LLC | C43: 俄罗斯联邦 | D43: 4500164028 | E43: 包装要求参考4 500158543，出 Ural | F43: 4500164028-110 | G43: 92108-S001 | H43: 摇篮公子 | I43: 312 | J43: 0 | K43: 4 | L43: =I43/K43 -> 78 | M43: 45765 | N43: 45761 | O43: 原4500158543转单-注意不要重复生产 | P43: PAss | Q43: 5/19出 | R43: 3/3收到 | T43: 3/4-进口商贴纸+ EAN条码贴纸 | V43: 外包装/外箱不要打ZURU标准日期码 日期 | W43: 日期码格式：外包装/外箱不要打ZURU标准日期码 日期： Packaging Info: 取代4500150271/4500157991/4500146630/4500159461/4500158543中 对应的款 ; 包装要求参考4500150271/4500157991/4500146630/4500159461/4500158543 Remark: | X43: Ann | Y43: 7.1595 | Z43: =Y43*I43 -> 2233.764 | AB43: 92108-S001新（V1） | AC43: 已入 | AD43: =I43 -> 312 | AJ43: =I43 -> 312 | AQ43: =I43/4 -> 78 | AS43: =I43/4 -> 78 | AT43: =I43/4 -> 78 | AV43: =AS43 -> 78 | BD43: =I43 -> 312 | BF43: =I43 -> 312 | BG43: MA | BI43: =I43/4 -> 78 | BJ43: =BI43 -> 78 | BK43: =BJ43 -> 78 | BL43: =BK43 -> 78 | BM43: =BL43 -> 78 | BN43: =BM43 -> 78 | BO43: =BN43 -> 78 | BP43: =BO43 -> 78 | BQ43: =$BQ$119+BJ43+BL43+BN43+BP43 -> 238337 | BR43: =BR42-BI43 -> 21484.5 | BS43: =BS42-BJ43 -> 21484.5 | BT43: =BT42-BK43 -> 20896.5 | BU43: =BU42-BL43 -> 20896.5 | BV43: =BV42-BM43 -> 36102.5 | BW43: =BW42-BN43 -> 36102.5 | BX43: =BX42-BO43 -> 21976.5 | BY43: =BY42-BP43 -> 21976.5
A44: 45743 | B44: WAL-MART CANADA CORP. | C44: 加拿大 | D44: 4500161639 | E44: 9900926594 | F44: 4500161639-10 | G44: 92108-S002-NB | H44: 摇篮公子 | I44: 200 | J44: 0 | K44: 1 | L44: =I44/K44 -> 200 | M44: 45772 | N44: 45768 | O44: 4/25第三方自检 | P44: PAss | Q44: 5/5出 | R44: 3/28收到 | T44: UPC贴纸翻4500146212 | W44: 日期码格式：ZURU INC(BVI) 标准格式 日期：按实际生产日期 Packaging Info: #92108: MA3L收缩膜+UPC条码贴纸(UPC: 193052064721)+MA5L收藏指南+MA5L资料卡+MA5L胶袋+MA配件袋+MA2L布标 (UPC贴纸翻单: 4500146212) -产品配比: 4 Assortments (bunny: puppy: unicorn: kitten)=1:1:1:1 Remark: 1. 此单有箱唛； 2. 此单有第三方验货，烦请多备包装物料； 3. 必须在原来错误的UPC/EAN条码上用黑色粗头笔涂黑直至不能扫描，再贴上正确的UPC。 | X44: Monica Zhou | Y44: 7.4848 | Z44: =Y44*I44 -> 1496.96 | AA44: 94935-5.6 | AB44: 92108-S002-NB-3L新（V1） | AC44: 已入 | AG44: =I44 -> 200 | AJ44: =I44 -> 200 | AQ44: =I44/4 -> 50 | AS44: =I44/4 -> 50 | AT44: =I44/4 -> 50 | AV44: =AS44 -> 50 | BE44: =I44 -> 200 | BF44: =I44 -> 200 | BG44: MA | BI44: =I44/4 -> 50 | BJ44: =BI44 -> 50 | BK44: =BJ44 -> 50 | BL44: =BK44 -> 50 | BM44: =BL44 -> 50 | BN44: =BM44 -> 50 | BO44: =BN44 -> 50 | BP44: =BO44 -> 50 | BQ44: =$BQ$119+BJ44+BL44+BN44+BP44 -> 238225 | BR44: =BR43-BI44 -> 21434.5 | BS44: =BS43-BJ44 -> 21434.5 | BT44: =BT43-BK44 -> 20846.5 | BU44: =BU43-BL44 -> 20846.5 | BV44: =BV43-BM44 -> 36052.5 | BW44: =BW43-BN44 -> 36052.5 | BX44: =BX43-BO44 -> 21926.5 | BY44: =BY43-BP44 -> 21926.5
A45: 45737 | B45: TOY KINGDOM (PTY) LTD | C45: 南非 | D45: 4500161136 | F45: 4500161136-50 | G45: 92108-S001 | H45: 摇篮公子 | I45: 240 | J45: 0 | K45: 4 | L45: =I45/K45 -> 60 | M45: 45770 | N45: 45766 | P45: PAss | Q45: 4/24出 | R45: 3/21收到 | T45: 无 | W45: 日期码格式：ZURU INC(BVI) 标准格式 日期：按实际生产日期 Packaging Info: MA PKG ,优先1L Remark: | X45: Doris Shou | Y45: 6.8843 | Z45: =Y45*I45 -> 1652.232 | AA45: 94837-4.24 | AB45: 92108-S001新（V1） | AC45: 已入 | AD45: =I45 -> 240 | AJ45: =I45 -> 240 | AQ45: =I45/4 -> 60 | AS45: =I45/4 -> 60 | AT45: =I45/4 -> 60 | AV45: =AS45 -> 60 | BD45: =I45 -> 240 | BF45: =I45 -> 240 | BG45: MA | BI45: =I45/4 -> 60 | BJ45: =BI45 -> 60 | BK45: =BJ45 -> 60 | BL45: =BK45 -> 60 | BM45: =BL45 -> 60 | BN45: =BM45 -> 60 | BO45: =BN45 -> 60 | BP45: =BO45 -> 60 | BQ45: =$BQ$119+BJ45+BL45+BN45+BP45 -> 238265 | BR45: =BR44-BI45 -> 21374.5 | BS45: =BS44-BJ45 -> 21374.5 | BT45: =BT44-BK45 -> 20786.5 | BU45: =BU44-BL45 -> 20786.5 | BV45: =BV44-BM45 -> 35992.5 | BW45: =BW44-BN45 -> 35992.5 | BX45: =BX44-BO45 -> 21866.5 | BY45: =BY44-BP45 -> 21866.5
A46: 45722 | B46: WOOLWORTH TRADING S.A. DE C.V. | C46: 墨西哥 | D46: 4500159263 | E46: 25/223 CVH | F46: 4500159263-30 | G46: 92108-S001 | H46: 摇篮公子 | I46: 256 | J46: 0 | K46: 4 | L46: =I46/K46 -> 64 | M46: 45771 | N46: 45768 | P46: PAss | Q46: 4/27出 | R46: 3/14收到 | T46: 进口商贴纸+Rating Labe翻4500159234 | W46: 日期码格式：ZURU INC(BVI) 标准格式 日期：按实际生产日期 Packaging Info: 3. 92108：MA 3L EAN包装+MA多语收藏指南+进口商贴纸+Rating Label(贴产品上)+warning warranty card+箱唛，warning warranty card(警告保修卡可用A4纸双 面打印)，所有贴纸和warning warranty card翻单PO4500159234 Remark: 1. 此单需提交自检报告给客户确认，待客户确认放货后，才允许出货。 3. 92108：4 Assortments (bunny: puppy: unicorn: kitten)=1:1:1:1；3PCS AAA BATTERIES (NOT INCLUDED) | X46: Ever Li | Y46: 7.0298 | Z46: =Y46*I46 -> 1799.6288 | AA46: 94859-4.28 | AB46: 92108-S001-3L新（V1） | AC46: 已入 | AG46: =I46 -> 256 | AJ46: =I46 -> 256 | AQ46: =I46/4 -> 64 | AS46: =I46/4 -> 64 | AT46: =I46/4 -> 64 | AV46: =AS46 -> 64 | BD46: =I46 -> 256 | BF46: =I46 -> 256 | BG46: MA | BI46: =I46/4 -> 64 | BJ46: =BI46 -> 64 | BK46: =BJ46 -> 64 | BL46: =BK46 -> 64 | BM46: =BL46 -> 64 | BN46: =BM46 -> 64 | BO46: =BN46 -> 64 | BP46: =BO46 -> 64 | BQ46: =$BQ$119+BJ46+BL46+BN46+BP46 -> 238281 | BR46: =BR45-BI46 -> 21310.5 | BS46: =BS45-BJ46 -> 21310.5 | BT46: =BT45-BK46 -> 20722.5 | BU46: =BU45-BL46 -> 20722.5 | BV46: =BV45-BM46 -> 35928.5 | BW46: =BW45-BN46 -> 35928.5 | BX46: =BX45-BO46 -> 21802.5 | BY46: =BY45-BP46 -> 21802.5
A47: 45722 | B47: WOOLWORTH TRADING S.A. DE C.V. | C47: 墨西哥 | D47: 4500159262 | E47: 25/222 CL | F47: 4500159262-30 | G47: 92108-S001 | H47: 摇篮公子 | I47: 428 | J47: 0 | K47: 4 | L47: =I47/K47 -> 107 | M47: 45771 | N47: 45768 | P47: PAss | Q47: 4/28出 | R47: 3/14收到 | T47: 进口商贴纸+Rating Labe翻4500159234 | W47: 日期码格式：ZURU INC(BVI) 标准格式 日期：按实际生产日期 Packaging Info: 3. 92108：MA 3L EAN包装+MA多语收藏指南+进口商贴纸+Rating Label(贴产品上)+warning warranty card+箱唛，warning warranty card(警告保修卡可用A4纸双 面打印)，所有贴纸和warning warranty card翻单PO4500159234 Remark: 1. 此单需提交自检报告给客户确认，待客户确认放货后，才允许出货。 3. 92108：4 Assortments (bunny: puppy: unicorn: kitten)=1:1:1:1；3PCS AAA BATTERIES (NOT INCLUDED) | X47: Ever Li | Y47: 7.3277 | Z47: =Y47*I47 -> 3136.2556 | AA47: 94858-4.28 | AB47: 92108-S001-3L新（V1） | AC47: 已入 | AG47: =I47 -> 428 | AJ47: =I47 -> 428 | AQ47: =I47/4 -> 107 | AS47: =I47/4 -> 107 | AT47: =I47/4 -> 107 | AV47: =AS47 -> 107 | BD47: =I47 -> 428 | BF47: =I47 -> 428 | BG47: MA | BI47: =I47/4 -> 107 | BJ47: =BI47 -> 107 | BK47: =BJ47 -> 107 | BL47: =BK47 -> 107 | BM47: =BL47 -> 107 | BN47: =BM47 -> 107 | BO47: =BN47 -> 107 | BP47: =BO47 -> 107 | BQ47: =$BQ$119+BJ47+BL47+BN47+BP47 -> 238453 | BR47: =BR46-BI47 -> 21203.5 | BS47: =BS46-BJ47 -> 21203.5 | BT47: =BT46-BK47 -> 20615.5 | BU47: =BU46-BL47 -> 20615.5 | BV47: =BV46-BM47 -> 35821.5 | BW47: =BW46-BN47 -> 35821.5 | BX47: =BX46-BO47 -> 21695.5 | BY47: =BY46-BP47 -> 21695.5
A48: 45722 | B48: WOOLWORTH TRADING S.A. DE C.V. | C48: 墨西哥 | D48: 4500159256 | E48: 25/221 CM | F48: 4500159256-30 | G48: 92108-S001 | H48: 摇篮公子 | I48: 616 | J48: 0 | K48: 4 | L48: =I48/K48 -> 154 | M48: 45771 | N48: 45768 | P48: PAss | Q48: 4/29出 | R48: 3/14收到 | T48: 进口商贴纸+Rating Labe翻4500159234 | W48: 日期码格式：ZURU INC(BVI) 标准格式 日期：按实际生产日期 Packaging Info: 3. 92108：MA 3L EAN包装+MA多语收藏指南+进口商贴纸+Rating Label(贴产品上)+warning warranty card+箱唛，warning warranty card(警告保修卡可用A4纸双 面打印)，所有贴纸和warning warranty card翻单PO4500159234 Remark: 1. 此单需提交自检报告给客户确认，待客户确认放货后，才允许出货。 3. 92108：4 Assortments (bunny: puppy: unicorn: kitten)=1:1:1:1；3PCS AAA BATTERIES (NOT INCLUDED) | X48: Ever Li | Y48: 7.3108 | Z48: =Y48*I48 -> 4503.4528 | AA48: 94873-4.29 | AB48: 92108-S001-3L新（V1） | AC48: 已入 | AG48: =I48 -> 616 | AJ48: =I48 -> 616 | AQ48: =I48/4 -> 154 | AS48: =I48/4 -> 154 | AT48: =I48/4 -> 154 | AV48: =AS48 -> 154 | BD48: =I48 -> 616 | BF48: =I48 -> 616 | BG48: MA | BI48: =I48/4 -> 154 | BJ48: =BI48 -> 154 | BK48: =BJ48 -> 154 | BL48: =BK48 -> 154 | BM48: =BL48 -> 154 | BN48: =BM48 -> 154 | BO48: =BN48 -> 154 | BP48: =BO48 -> 154 | BQ48: =$BQ$119+BJ48+BL48+BN48+BP48 -> 238641 | BR48: =BR47-BI48 -> 21049.5 | BS48: =BS47-BJ48 -> 21049.5 | BT48: =BT47-BK48 -> 20461.5 | BU48: =BU47-BL48 -> 20461.5 | BV48: =BV47-BM48 -> 35667.5 | BW48: =BW47-BN48 -> 35667.5 | BX48: =BX47-BO48 -> 21541.5 | BY48: =BY47-BP48 -> 21541.5
A49: 45722 | B49: WOOLWORTH TRADING S.A. DE C.V. | C49: 墨西哥 | D49: 4500159248 | E49: 25/220 CT | F49: 4500159248-30 | G49: 92108-S001 | H49: 摇篮公子 | I49: 396 | J49: 0 | K49: 4 | L49: =I49/K49 -> 99 | M49: 45771 | N49: 45768 | P49: PAss | R49: 3/14收到 | T49: 进口商贴纸+Rating Labe翻4500159234 | W49: 日期码格式：ZURU INC(BVI) 标准格式 日期：按实际生产日期 Packaging Info: 3. 92108：MA 3L EAN包装+MA多语收藏指南+进口商贴纸+Rating Label(贴产品上)+warning warranty card+箱唛，warning warranty card(警告保修卡可用A4纸双 面打印)，所有贴纸和warning warranty card翻单PO4500159234 Remark: 1. 此单需提交自检报告给客户确认，待客户确认放货后，才允许出货。 3. 92108：4 Assortments (bunny: puppy: unicorn: kitten)=1:1:1:1；3PCS AAA BATTERIES (NOT INCLUDED) | X49: Ever Li | Y49: 7.3277 | Z49: =Y49*I49 -> 2901.7692 | AA49: 94857-4.28 | AB49: 92108-S001-3L新（V1） | AC49: 已入 | AG49: =I49 -> 396 | AJ49: =I49 -> 396 | AQ49: =I49/4 -> 99 | AS49: =I49/4 -> 99 | AT49: =I49/4 -> 99 | AV49: =AS49 -> 99 | BD49: =I49 -> 396 | BF49: =I49 -> 396 | BG49: MA | BI49: =I49/4 -> 99 | BJ49: =BI49 -> 99 | BK49: =BJ49 -> 99 | BL49: =BK49 -> 99 | BM49: =BL49 -> 99 | BN49: =BM49 -> 99 | BO49: =BN49 -> 99 | BP49: =BO49 -> 99 | BQ49: =$BQ$119+BJ49+BL49+BN49+BP49 -> 238421 | BR49: =BR48-BI49 -> 20950.5 | BS49: =BS48-BJ49 -> 20950.5 | BT49: =BT48-BK49 -> 20362.5 | BU49: =BU48-BL49 -> 20362.5 | BV49: =BV48-BM49 -> 35568.5 | BW49: =BW48-BN49 -> 35568.5 | BX49: =BX48-BO49 -> 21442.5 | BY49: =BY48-BP49 -> 21442.5
A50: 45722 | B50: WOOLWORTH TRADING S.A. DE C.V. | C50: 墨西哥 | D50: 4500159234 | E50: 25/196 CC | F50: 4500159234-30 | G50: 92108-S001 | H50: 摇篮公子 | I50: 244 | J50: 0 | K50: 4 | L50: =I50/K50 -> 61 | M50: 45771 | N50: 45768 | P50: PAss | Q50: 4/28出 | R50: 3/14收到 | T50: 进口商贴纸+Rating Labe翻4500159234 | W50: 日期码格式：ZURU INC(BVI) 标准格式 日期：按实际生产日期 Packaging Info: 3. 92108：MA 3L EAN包装+MA多语收藏指南+进口商贴纸+Rating Label(贴产品上)+warning warranty card+箱唛，warning warranty card(警告保修卡可用A4纸双 面打印) Remark: 1. 此单需提交自检报告给客户确认，待客户确认放货后，才允许出货。 3. 92108：4 Assortments (bunny: puppy: unicorn: kitten)=1:1:1:1；3PCS AAA BATTERIES (NOT INCLUDED) | X50: Ever Li | Y50: 7.3277 | Z50: =Y50*I50 -> 1787.9588 | AA50: 94856-4.28 | AB50: 92108-S001-3L新（V1） | AC50: 已入 | AG50: =I50 -> 244 | AJ50: =I50 -> 244 | AQ50: =I50/4 -> 61 | AS50: =I50/4 -> 61 | AT50: =I50/4 -> 61 | AV50: =AS50 -> 61 | BD50: =I50 -> 244 | BF50: =I50 -> 244 | BG50: MA | BI50: =I50/4 -> 61 | BJ50: =BI50 -> 61 | BK50: =BJ50 -> 61 | BL50: =BK50 -> 61 | BM50: =BL50 -> 61 | BN50: =BM50 -> 61 | BO50: =BN50 -> 61 | BP50: =BO50 -> 61 | BQ50: =$BQ$119+BJ50+BL50+BN50+BP50 -> 238269 | BR50: =BR49-BI50 -> 20889.5 | BS50: =BS49-BJ50 -> 20889.5 | BT50: =BT49-BK50 -> 20301.5 | BU50: =BU49-BL50 -> 20301.5 | BV50: =BV49-BM50 -> 35507.5 | BW50: =BW49-BN50 -> 35507.5 | BX50: =BX49-BO50 -> 21381.5 | BY50: =BY49-BP50 -> 21381.5
A51: 45735 | B51: MTA Trade | C51: 哈萨克斯坦 | D51: 4500160671 | F51: 4500160671-40 | G51: 92108B-S001 | H51: 斑点狗 | I51: 200 | J51: 0 | K51: 4 | L51: =I51/K51 -> 50 | M51: 45772 | N51: 45768 | P51: PAss | Q51: 4/25出 | R51: 3/19收到 | T51: 进口商贴纸翻4500158504 | W51: 日期码格式：ZURU INC(BVI) 标准格式 日期：按实际生产日期 Packaging Info: 92108 ：MA UPC 收缩膜(优先1L)+进口商贴纸(三款进口商贴纸翻PO-4500158504)+UPC条码贴；MA指南 Remark: 标准配比 | X51: Cora Zhou | Y51: 7.3277 | Z51: =Y51*I51 -> 1465.54 | AA51: 94843-4.25 | AB51: 92108B-S001新（V1） | AC51: 已入 | AD51: =I51 -> 200 | AJ51: =I51 -> 200 | AV51: =I51 -> 200 | BD51: =I51 -> 200 | BF51: =I51 -> 200 | BG51: MA | BO51: =I51 -> 200 | BP51: =I51 -> 200 | BQ51: =$BQ$119+BJ51+BL51+BN51+BP51 -> 238225 | BR51: =BR50-BI51 -> 20889.5 | BS51: =BS50-BJ51 -> 20889.5 | BT51: =BT50-BK51 -> 20301.5 | BU51: =BU50-BL51 -> 20301.5 | BV51: =BV50-BM51 -> 35507.5 | BW51: =BW50-BN51 -> 35507.5 | BX51: =BX50-BO51 -> 21181.5 | BY51: =BY50-BP51 -> 21181.5
A52: 45735 | B52: MTA Trade | C52: 哈萨克斯坦 | D52: 4500160671 | F52: 4500160671-50 | G52: 92108D-S001 | H52: 独角兽 | I52: 200 | J52: 0 | K52: 4 | L52: =I52/K52 -> 50 | M52: 45772 | N52: 45768 | P52: PAss | Q52: 4/25出 | R52: 3/19收到 | T52: 进口商贴纸翻4500158504 | W52: 日期码格式：ZURU INC(BVI) 标准格式 日期：按实际生产日期 Packaging Info: 92108 ：MA UPC 收缩膜(优先1L)+进口商贴纸(三款进口商贴纸翻PO-4500158504)+UPC条码贴；MA指南 Remark: 标准配比 | X52: Cora Zhou | Y52: 7.0298 | Z52: =Y52*I52 -> 1405.96 | AA52: 94843-4.25 | AB52: 92108D-S001新（V1） | AC52: 已入 | AD52: =I52 -> 200 | AJ52: =I52 -> 200 | AT52: =I52 -> 200 | BD52: =I52 -> 200 | BF52: =I52 -> 200 | BG52: MA | BK52: =I52 -> 200 | BL52: =I52 -> 200 | BQ52: =$BQ$119+BJ52+BL52+BN52+BP52 -> 238225 | BR52: =BR51-BI52 -> 20889.5 | BS52: =BS51-BJ52 -> 20889.5 | BT52: =BT51-BK52 -> 20101.5 | BU52: =BU51-BL52 -> 20101.5 | BV52: =BV51-BM52 -> 35507.5 | BW52: =BW51-BN52 -> 35507.5 | BX52: =BX51-BO52 -> 21181.5 | BY52: =BY51-BP52 -> 21181.5
A53: 45735 | B53: MTA Trade | C53: 哈萨克斯坦 | D53: 4500160671 | F53: 4500160671-60 | G53: 92108E-S001 | H53: 小猫 | I53: 200 | J53: 0 | K53: 4 | L53: =I53/K53 -> 50 | M53: 45772 | N53: 45768 | P53: PAss | Q53: 4/25出 | R53: 3/19收到 | T53: 进口商贴纸翻4500158504 | W53: 日期码格式：ZURU INC(BVI) 标准格式 日期：按实际生产日期 Packaging Info: 92108 ：MA UPC 收缩膜(优先1L)+进口商贴纸(三款进口商贴纸翻PO-4500158504)+UPC条码贴；MA指南 Remark: 标准配比 | X53: Cora Zhou | Y53: 7.0298 | Z53: =Y53*I53 -> 1405.96 | AA53: 94843-4.25 | AB53: 92108E-S001新（V1） | AC53: 已入 | AD53: =I53 -> 200 | AJ53: =I53 -> 200 | AQ53: =I53 -> 200 | BD53: =I53 -> 200 | BF53: =I53 -> 200 | BG53: MA | BM53: =I53 -> 200 | BN53: =I53 -> 200 | BQ53: =$BQ$119+BJ53+BL53+BN53+BP53 -> 238225 | BR53: =BR52-BI53 -> 20889.5 | BS53: =BS52-BJ53 -> 20889.5 | BT53: =BT52-BK53 -> 20101.5 | BU53: =BU52-BL53 -> 20101.5 | BV53: =BV52-BM53 -> 35307.5 | BW53: =BW52-BN53 -> 35307.5 | BX53: =BX52-BO53 -> 21181.5 | BY53: =BY52-BP53 -> 21181.5
