Workbook

Sheet 9548明细
AJ1: 彩盒 | AR1: 说明书 | AV1: 展示架 | BF1: MA-RR-1088 | BG1: MA-RR-1124 | BH1: MA-RR-1143 | BI1: MA-RR-1179 | BJ1: MA-RR-1201 | BK1: MA-RR-1226 | BL1: MA-RR-1261 | BM1: MA-RR-1315 | BN1: MA-RR-1332
A2: 接单期 | B2: 第三方客户名称 | C2: 走货国家 | D2: ZURU PO NO# | E2: 第三方客户 PO NO# | F2: SKU | G2: ITEM# | H2: 货品名称 | I2: PO数量(只) | J2: 内箱装箱数量(只) | K2: 外箱装箱数量(只) | L2: 总箱数 | M2: 计划出货期 | N2: 计划验货期 | O2: 第三方客户公证行验货 | P2: 验货结果 | Q2: ZURU确认走货日期 | R2: 箱唛(收到日期) | S2: 外箱贴纸 | T2: 客供贴纸资料(收到日期及订购日期) | U2: 布标 | V2: 客版资料 | W2: 日期码 | X2: 备注 | Y2: ZURU跟单组员 | Z2: 单价USD | AA2: 金额USD | AB2: 发票号 | AC2: 系统货号 | AD2: 是否入系统 | AE2: 需求数 有硼 | AF2: 需求数 无硼 | AG2: 送货情况 | AH2: 贴纸情况 | AI2: 纸箱情况 | AJ2: MA1语彩盒A版 | AK2: MA1语彩盒B版 | AL2: MA5语彩盒 A版 | AM2: MA5语彩盒 B版 | AN2: MA1语彩盒C版 | AO2: MA5语彩盒 C版 | AP2: MA5语彩盒D版 | AQ2: 客版彩盒 | AR2: 5L 说明书 A版 | AS2: 5L 说明书 B版 | AT2: 5L 说明书 C版 | AU2: 客版说明书 | AV2: 9548SLD-S001 | AW2: 9548EC-S001B版 | AX2: 9548UQ1 客版PDQ | AY2: 9548SLB-S001(66pcs) | AZ2: 9548SLB-S002 | BA2: 合计数量 | BB2: 累计数量 | BC2: 新配比（口水胶） | BD2: 新旧压片 | BE2: MA数量 | BF2: 30000 | BG2: 60000 | BH2: 60000 | BI2: 80000 | BJ2: 100000 | BK2: 120000 | BL2: 40000 | BM2: 40000 | BN2: 40000
A3: 45370 | B3: BJ'S WHOLESALE CLUB, INC. | C3: 美国 | D3: 4500127362 | E3: 115380735 | F3: 4500127362-10 | G3: 9548UQ1-S001 | H3: 鸭妈妈 | I3: 2864 | J3: 0 | K3: 4 | L3: =I3/K3 -> 716 | M3: 45432 | N3: 45428 | P3: PASS | Q3: 6/19出货 | R3: 45370 | S3: 无 | T3: 无 | U3: MA | V3: 客版PDQ | X3: 日期码格式：ZURU INC(BVI) 标准格式 日期：按实际生产日期 Packaging Info: MA UPC版本包装+客版PDQ（PDQ AW翻单PO#4500127386） Remark: 1. 箱唛上体积数和实际要相符，如体积数和PO上有不一致，客人会有罚款。 2. 产品和包装上的日期按照ZURU标准格式。 3. 产品不含以下物质： a. 不含任何的美国优先化学品priority chemicals； b. 不含或者不超过美国缅因州的高度关注化学品Chemicals of High Concern清单中的最低水平(100mg/kg)； c. 不含化学阻燃剂：TDCPP，TCEP，Antimony trioxide，HBCD，TBPH，TBB，SCCP，TCPP，Penta-BDE，Octa-BDE，TBBPA等。 | Y3: Emily Wu | Z3: 7.65 | AA3: =Z3*I3 -> 21909.6 | AB3: 已出货 | AC3: 9548UQ1-S001 | AD3: 已入 | AE3: =I3*0.2 -> 572.8 | AJ3: =I3 -> 2864 | AR3: =I3 -> 2864 | AX3: =I3/4 -> 716 | BA3: =I3 -> 2864 | BB3: =652688+BA3+80332 -> 735884 | BD3: 旧 | BF3: =#REF!+$BF$2+$BG$2-BB3 -> #REF!
A4: 45558 | B4: WAL-MART STORES INC. USA | C4: 美国 | D4: 4500145927 | E4: 0863715001 | F4: 4500145927-30 | G4: 9548SLB-S002 | H4: 鸭妈妈 （卡板装） | I4: 2304 | J4: 1 | K4: 72 | L4: =I4/K4 -> 32 | M4: 45596 | N4: 45593 | O4: 10/31完成自检 | P4: PASS | R4: 45373 | S4: 有 | T4: 客版布标贴纸，10/12客供RFID贴纸 | U4: MA | X4: 日期码格式：ZURU DGYYYYMMDD CHINA（日期避开周末和法定节假日即可） 日期：按实际生产日期 Packaging Info: 1.包装信息：MA A版 UPC版 1L收缩膜，MA 5L A版说明书，MA 5L A版口水胶袋，MA 2L C版车缝布标，客版布标贴纸，客供RFID贴纸（标贴位置严格按照我们签板的 位置图，不可擅自调整位置，贴纸不能有任何破损或折坏，不可淋湿）。 Remark: 2.外箱四面印刷RFID箱唛，正唛左前下角印刷ITF-14格式条码的艾利替代标箱唛，只印刷正唛一面，整个内容尺寸最小10*10cm，加印时需确保条形码能扫描出来，Z URU logo跟MADE IN CHINA四面右下角印刷，外箱印刷日期码，每个slip sheet上面贴一张10*10cm艾利替代标（工厂自行用不干胶打印）和一张普通贴纸（可A4纸 打印），slip sheet打印的普通贴纸的尺寸不能比艾利替代标小。 3.在产品上和包装上要有日期码（避开周末和节假日），以及要有MADE IN CHINA和ZURU字样。 4.产品如有扎带口要剪平，不能刮手。 5.此单以打卡板出货（18*4H=72cartons/72pcs/Slip Sheet） 6.此单需要第三方验货，请自行多备物料。 7.其它信息：3pcs*AAA battery not include。 | Y4: Sandy Xu | Z4: 531.55 | AA4: =Z4*L4 -> 17009.6 | AB4: 已出货 | AC4: 9548SLB-S002 | AD4: 已入 | AE4: =I4*0.2 -> 460.8 | AJ4: =I4 -> 2304 | AR4: =I4 -> 2304 | AZ4: =I4/72 -> 32 | BA4: =I4 -> 2304 | BB4: =BB3+BA4 -> 738188
A5: 45558 | B5: WAL-MART STORES INC. USA | C5: 美国 | D5: 4500145927 | E5: 0863715002 | F5: 4500145927-40 | G5: 9548SLB-S002 | H5: 鸭妈妈 （卡板装） | I5: 504 | J5: 1 | K5: 72 | L5: =I5/K5 -> 7 | M5: 45596 | N5: 45593 | O5: 10/31完成自检 | P5: PASS | R5: 45373 | S5: 有 | T5: 客版布标贴纸，10/12客供RFID贴纸 | U5: MA | X5: 日期码格式：ZURU DGYYYYMMDD CHINA（日期避开周末和法定节假日即可） 日期：按实际生产日期 Packaging Info: 1.包装信息：MA A版 UPC版 1L收缩膜，MA 5L A版说明书，MA 5L A版口水胶袋，MA 2L C版车缝布标，客版布标贴纸，客供RFID贴纸（标贴位置严格按照我们签板的 位置图，不可擅自调整位置，贴纸不能有任何破损或折坏，不可淋湿）。 Remark: 2.外箱四面印刷RFID箱唛，正唛左前下角印刷ITF-14格式条码的艾利替代标箱唛，只印刷正唛一面，整个内容尺寸最小10*10cm，加印时需确保条形码能扫描出来，Z URU logo跟MADE IN CHINA四面右下角印刷，外箱印刷日期码，每个slip sheet上面贴一张10*10cm艾利替代标（工厂自行用不干胶打印）和一张普通贴纸（可A4纸 打印），slip sheet打印的普通贴纸的尺寸不能比艾利替代标小。 3.在产品上和包装上要有日期码（避开周末和节假日），以及要有MADE IN CHINA和ZURU字样。 4.产品如有扎带口要剪平，不能刮手。 5.此单以打卡板出货（18*4H=72cartons/72pcs/Slip Sheet） 6.此单需要第三方验货，请自行多备物料。 7.其它信息：3pcs*AAA battery not include。 | Y5: Sandy Xu | Z5: 533.1556 | AA5: =Z5*L5 -> 3732.0892 | AB5: 已出货 | AC5: 9548SLB-S002 | AD5: 已入 | AE5: =I5*0.2 -> 100.8 | AJ5: =I5 -> 504 | AR5: =I5 -> 504 | AZ5: =I5/72 -> 7 | BA5: =I5 -> 504 | BB5: =BB4+BA5 -> 738692
A6: 45593 | B6: Tesco CE | D6: MPO02967 | G6: 9548-S001 | H6: 鸭妈妈 | I6: 2080 | J6: 0 | K6: 4 | L6: =I6/K6 -> 520 | M6: 45630 | N6: 45626 | P6: PASS | R6: 可用空白周转箱 | S6: 无 | T6: 无 | U6: MA | X6: Remark: ① 2% 损耗；②送货前必需通知我司安排验货. 1. 此单出EU，需满足EU测试标准要求，不含微塑料。 2. 产品及包装需要印UKCA图标，包装需要有ZURU UK LTD/ZURU France地址信息，QC同事请核查，如有问题与跟单确认。 3.可用空白周转箱 4. 如含硼的话， 需用低硼版本(小于300ppm),硼含量需要符合欧洲标准,否则客人会退货有罚款产生 5. 子件送华康组装 9548：最新版MA 1L+23L UPC收缩膜包装 | Y6: Eddie Huang | Z6: 7.069 | AA6: =Z6*I6 -> 14703.52 | AB6: 94398-2.27 | AC6: 9548-S001 | AD6: 已入 | AE6: =I6*0.2 -> 416 | AK6: =I6 -> 2080 | AS6: =I6 -> 2080 | BA6: =I6 -> 2080 | BB6: =BB5+BA6 -> 740772
A7: 45586 | B7: TJX COMPANIES, INC | C7: 美国 | D7: 4500147789 | E7: Marshalls DC#881-124PCS , DC#884-96PCS, DC#886-140PCS , DC#887-116PCS , DC#888-124PCS | F7: 4500147789-30 | G7: 9548-S001 | H7: 鸭妈妈 | I7: 600 | J7: 0 | K7: 4 | L7: =I7/K7 -> 150 | M7: 45649 | N7: 45645 | P7: PASS | R7: 45600 | S7: 无 | T7: 11/19价格贴纸客供 | U7: MA | X7: 日期码格式：ZURU INC(BVI) 标准格式 日期：按实际生产日期 Packaging Info: MA UPC包装+价格贴纸，价格贴纸客供。 Remark: 1. 产品和包装上印刷tracking code信息，格式为ZURU常规格式。 2. 分5个DC出货，每款产品每个DC的箱唛资料不同。具体分DC数量，请参考后面行项目备注。 3. ZURU QC验货。 | Y7: Emily Wu | Z7: 7.6175 | AA7: =Z7*I7 -> 4570.5 | AB7: 94169-1.23 | AC7: 9548-S001 | AD7: 已入 | AE7: =I7*0.2 -> 120 | AK7: =I7 -> 600 | AS7: =I7 -> 600 | BA7: =I7 -> 600 | BB7: =BB6+BA7 -> 741372
A8: 45635 | D8: ZMPO24927 | G8: 9548-S001 | H8: 鸭妈妈 | I8: 120 | J8: 0 | K8: 4 | L8: =I8/K8 -> 30 | M8: 45649 | N8: 45645 | P8: PASS | R8: 45636 | S8: 无 | T8: 无 | U8: MA | X8: Remark：大货最新版本/大货标准箱装箱/箱唛请参照邮件附件；备注： 收到样品订单后尽快安排 ，注意样板品质质量要求要高于大货品质要求 ，送货时必须要附带送货单(没有送货单和QC检验合格报告的仓库一律拒绝收货)，请知悉，谢谢！ | Y8: Angus | Z8: 7.3292 | AA8: =Z8*I8 -> 879.504 | AB8: 94396-2.27 | AC8: 9548-S001 | AD8: 已入 | AE8: =I8*0.2 -> 24 | AK8: =I8 -> 120 | AS8: =I8 -> 120 | BA8: =I8 -> 120 | BB8: =BB7+BA8 -> 741492
A9: 45608 | B9: Amazon CA (Vendor Center) | C9: 加拿大 | D9: 4500150978 | E9: 6B6E7U7Q | F9: 4500150978-60 | G9: 9548-S001-NB | H9: 鸭妈妈 | I9: 16 | J9: 0 | K9: 4 | L9: =I9/K9 -> 4 | M9: 45653 | N9: 45639 | P9: PASS | R9: 45622 | S9: 有 | T9: 11/2外箱客供贴纸+贴纸资料跟翻单#4500146603 | U9: MA | X9: 日期码格式：ZURU INC(BVI) 标准格式 日期：按实际生产日期 Packaging Info: 出口加拿大，包装需要至少2/3L UPC版，无硼版本 #9548: MA 5L 加UPC贴纸，贴纸资料跟翻单#4500146603，UPC：193052064196。 Remark: 1. Amazon FOB订单，出口CA。外箱最长边不能超过25" （超过了，case pack只能为1），不符合要求的大货，一律不接受。 2. 外箱正面印ZURU Logo + SSCC LABEL（客供贴纸)，侧面印item#（订单上显示的SKU#) + carton size(以工厂实际尺寸为准，单位: inch) + MADE IN CHINA， 日期使用ZURU 标准版本 SSCC Label 显示的是客人自己的item#，SSCC Label 贴在外箱正面的正中间，贴一面即可，跟单订购，贴纸离外箱距必须至少3cm，每一 张SSCC label 都是唯一且有不同流水及条码的，没有损耗，绝对不可贴错 ，否则贴错或损坏一张会导致全部都错，千万要注意: SSCC 贴纸务必要在正中间(可以覆 盖Logo <(>&<)> 箱唛)，否则会影响到仓库扫描识别。 3. 日期码使用ZURU标准版本。 4. 如果大货有要求入邮包盒，则对应的邮包盒上面要打上日期码。 5. 按照客户PO# 装柜/箱号顺序装柜，跟单会提前给到装柜计划。在大货生产/仓库存放时，请留意该装柜要求，以便装柜时不混乱（避免装错/装漏/找不到货号等 ）。 6. 出口加拿大，包装需要至少2/3L UPC版，无硼版本。 7.邮包盒上要印刷日期码 | Y9: Kelly/Mia | Z9: 7.3292 | AA9: =Z9*I9 -> 117.2672 | AB9: 未出货 | AC9: 9548-S001-NB-5L | AD9: 已入 | AF9: =I9*0.2 -> 3.2 | AO9: =I9 -> 16 | AS9: =I9 -> 16 | BA9: =I9 -> 16 | BB9: =BB8+BA9 -> 741508
A10: 45617 | B10: TARGET US | C10: 美国 | D10: 4500151904 | E10: 10001053761-3891 | F10: 4500151904-20 | G10: 9548-S001 | H10: 鸭妈妈 | I10: 848 | J10: 0 | K10: 4 | L10: =I10/K10 -> 212 | M10: 45653 | N10: 45649 | R10: 45625 | S10: 有 | T10: 12/6客供外箱贴纸 | U10: MA | X10: 日期码格式：ZURU INC(BVI) 标准格式 日期：按实际生产日期 Packaging Info: 9548：MA 1L包装(UPC版) Remark: 9548： 1. 9548-S001-PETS ALIVE - MAMA <(>&<)> BABY SURPRISE - SERIES 1 - MAMA DUCK -WINDOW BOX-4 PCS/CTN 2. MA 1L包装(UPC版), 产品彩盒上的UPC显示193052064196; 3. 外箱正唛左上角位置粘贴条码箱贴纸，每箱只贴一张，由ZURU订购。来料贴纸上显示的客户DPCI# 086-08-0304， UPC显示10193052064193; 4. 产品和包装上印刷 tracking code信息，格式为ZURU常规格式; 5. 出货方式：货代自提 | Y10: Holly Zheng | Z10: 7.3075 | AA10: =Z10*I10 -> 6196.76 | AC10: 9548-S001 | AD10: 已入 | AE10: =I10*0.2 -> 169.6 | AK10: =I10 -> 848 | AS10: =I10 -> 848 | BA10: =I10 -> 848 | BB10: =BB4+BA10 -> 739036
A11: 45607 | B11: TARGET US | C11: 美国 | D11: 4500150859 | E11: 10001053805-3891 | F11: 4500150859-20 | G11: 9548-S001 | H11: 鸭妈妈 | I11: 848 | J11: 0 | K11: 4 | L11: =I11/K11 -> 212 | M11: 45653 | N11: 45649 | R11: 45622 | S11: 有 | T11: 12/6客供外箱贴纸 | U11: MA | X11: 日期码格式：ZURU INC(BVI) 标准格式 日期：按实际生产日期 Packaging Info: 9548:MA 1L包装(UPC版) Remark: 9548: 1. 9548-S001-PETS ALIVE - MAMA <(>&<)> BABY SURPRISE - SERIES 1 - MAMA DUCK -WINDOW BOX-4 PCS/CTN 2. MA 1L包装(UPC版), 产品彩盒上的UPC显示193052064196; 3. 外箱正唛左上角位置粘贴条码箱贴纸，每箱只贴一张，由ZURU订购。来料贴纸上显示的客户DPCI# 086-08-0304， UPC显示10193052064193; 4. 产品和包装上印刷 tracking code信息，格式为ZURU常规格式; 5. 出货方式：货代自提 | Y11: Holly Zheng | Z11: 7.3075 | AA11: =Z11*I11 -> 6196.76 | AC11: 9548-S001 | AD11: 已入 | AE11: =I11*0.2 -> 169.6 | AK11: =I11 -> 848 | AS11: =I11 -> 848 | BA11: =I11 -> 848 | BB11: =BB10+BA11 -> 739884
A12: 45607 | B12: TARGET US | C12: 美国 | D12: 4500150863 | E12: 10001053812-3890 | F12: 4500150859-20 | G12: 9548-S001 | H12: 鸭妈妈 | I12: 1168 | J12: 0 | K12: 4 | L12: =I12/K12 -> 292 | M12: 45653 | N12: 45639 | R12: 45622 | S12: 有 | T12: 12/6客供外箱贴纸 | U12: MA | X12: 日期码格式：ZURU INC(BVI) 标准格式 日期：按实际生产日期 Packaging Info: 9548: MA 1L包装(UPC版) Remark: 9548: 1. 9548-S001-PETS ALIVE - MAMA <(>&<)> BABY SURPRISE - SERIES 1 - MAMA DUCK -WINDOW BOX-4 PCS/CTN 2. MA 1L包装(UPC版), 产品彩盒上的UPC显示193052064196; 3. 外箱正唛左上角位置粘贴条码箱贴纸，每箱只贴一张，由ZURU订购。来料贴纸上显示的客户DPCI# 086-08-0304， UPC显示10193052064193; 4. 产品和包装上印刷 tracking code信息，格式为ZURU常规格式; 5. 出货方式：货代自提 | Y12: Holly Zheng | Z12: 7.3075 | AA12: =Z12*I12 -> 8535.16 | AC12: 9548-S001 | AD12: 已入 | AE12: =I12*0.2 -> 233.6 | AK12: =I12 -> 1168 | AS12: =I12 -> 1168 | BA12: =I12 -> 1168 | BB12: =BB11+BA12 -> 741052
A13: 45586 | B13: TJX COMPANIES, INC | C13: 美国 | D13: 4500147796 | E13: TJ MAXX DC#891-160PCS , DC#894-136PCS , DC#896-128PCS , DC#897-248PCS , DC#898-128PCS | F13: 4500147796-40 | G13: 9548-S001 | H13: 鸭妈妈 | I13: 800 | J13: 0 | K13: 4 | L13: =I13/K13 -> 200 | M13: 45656 | N13: 45652 | R13: 45600 | S13: 无 | T13: 12/6价格贴纸客供 | U13: MA | X13: 日期码格式：ZURU INC(BVI) 标准格式 日期：按实际生产日期 Packaging Info: MA UPC包装+价格贴纸，价格贴纸客供。 Remark: 1. 产品和包装上印刷tracking code信息，格式为ZURU常规格式。 2. 分5个DC出货，每款产品每个DC的箱唛资料不同。具体分DC数量，请参考后面行项目备注。 3. ZURU QC验货。 | Y13: Emily Wu | Z13: 7.6175 | AA13: =Z13*I13 -> 6094 | AB13: 94170-1.23 | AC13: 9548-S001 | AD13: 已入 | AE13: =I13*0.2 -> 160 | AK13: =I13 -> 800 | AS13: =I13 -> 800 | BA13: =I13 -> 800 | BB13: =BB12+BA13 -> 741852
A14: 45586 | B14: TJX COMPANIES, INC | C14: 美国 | D14: 4500147793 | E14: Marshalls DC#881-124PCS , DC#884-96PCS, DC#886-140PCS , DC#887-116PCS , DC#888-124PCS | F14: 4500147793-40 | G14: 9548-S001 | H14: 鸭妈妈 | I14: 600 | J14: 0 | K14: 4 | L14: =I14/K14 -> 150 | M14: 45656 | N14: 45652 | R14: 45600 | S14: 无 | T14: 12/6价格贴纸客供 | U14: MA | X14: 日期码格式：ZURU INC(BVI) 标准格式 日期：按实际生产日期 Packaging Info: MA UPC包装+价格贴纸，价格贴纸客供。 Remark: 1. 产品和包装上印刷tracking code信息，格式为ZURU常规格式。 2. 分5个DC出货，每款产品每个DC的箱唛资料不同。具体分DC数量，请参考后面行项目备注。 3. ZURU QC验货。 | Y14: Emily Wu | Z14: 7.6175 | AA14: =Z14*I14 -> 4570.5 | AB14: 94171-1.23 | AC14: 9548-S001 | AD14: 已入 | AE14: =I14*0.2 -> 120 | AK14: =I14 -> 600 | AS14: =I14 -> 600 | BA14: =I14 -> 600 | BB14: =BB13+BA14 -> 742452
A15: 45622 | B15: ALL BRANDS TOYS PTY LTD | C15: 澳大利亚 | D15: 4500152355 | E15: 83235 | F15: 4500152355-10 | G15: 9548-S001 | H15: 鸭妈妈 | I15: 1040 | J15: 0 | K15: 4 | L15: =I15/K15 -> 260 | M15: 45656 | N15: 45652 | R15: 45624 | S15: 无 | T15: 进口商贴纸+贴纸翻单4500125432 | U15: MA | X15: 日期码格式：ZURU INC(BVI) 标准格式 日期：按实际生产日期 Packaging Info: 9548:英文MA包装UPC版本（首选1L, 如无1L可选多语含英语）+客人通用进口商贴纸+箱唛，贴纸翻单4500125432 Remark: 1.按实际生产日期; 2.出澳大利亚，请按照相应标准生产; | Y15: Lydia Wu | Z15: 7.6175 | AA15: =Z15*I15 -> 7922.2 | AC15: 9548-S001 | AD15: 已入 | AE15: =I15*0.2 -> 208 | AK15: =I15 -> 1040 | AS15: =I15 -> 1040 | BA15: =I15 -> 1040 | BB15: =BB14+BA15 -> 743492
A16: 45621 | B16: TARGET US | C16: 美国 | D16: 4500152243 | E16: 10001144214-3891 | F16: 4500152243-10 | G16: 9548-S001 | H16: 鸭妈妈 | I16: 6312 | J16: 0 | K16: 4 | L16: =I16/K16 -> 1578 | M16: 45656 | N16: 45652 | R16: 45625 | S16: 有 | T16: 12/6客供外箱贴纸 | U16: MA | X16: 日期码格式：ZURU INC(BVI) 标准格式 日期：按实际生产日期 Packaging Info: MA 1L包装(UPC版) Remark: 1. 9548-S001-PETS ALIVE - MAMA <(>&<)> BABY SURPRISE - SERIES 1 - MAMA DUCK -WINDOW BOX-4 PCS/CTN 2. MA 1L包装(UPC版), 产品彩盒上的UPC显示193052064196; 3. 外箱正唛左上角位置粘贴条码箱贴纸，每箱只贴一张，由ZURU订购。来料贴纸上显示的客户DPCI# 086-08-0304， UPC显示10193052064193; 4. 产品和包装上印刷 tracking code信息，格式为ZURU常规格式; 5. 出货方式：货代自提 | Y16: Holly Zheng | Z16: 7.2151 | AA16: =Z16*I16 -> 45541.711 | AC16: 9548-S001 | AD16: 已入 | AE16: 300 | AK16: =I16 -> 6312 | AS16: =I16 -> 6312 | BA16: =I16 -> 6312 | BB16: =BB15+BA16 -> 749804
A17: 45604 | B17: THE ENTERTAINER | C17: 英国 | D17: 4500150141 | E17: 4500150141-1 | F17: 4500150141-30 | G17: 9548-S001 | H17: 鸭妈妈 | I17: 1272 | J17: 0 | K17: 4 | L17: =I17/K17 -> 318 | M17: 45657 | N17: 45653 | P17: PASS | R17: 45610 | S17: 无 | T17: 条码贴和两国语言说明书翻订单4500148687 | U17: MA | V17: 产品内包装再加多一张2国语言电池说明书 | X17: 日期码格式：ZURU INC(BVI) 标准格式 日期：按实际生产日期 Packaging Info: 9548：MA-1L（含23L warning）包装配套 ,额外加一张条码贴覆盖ZURU条码 ，另外产品内包装再加多一张2国语言电池说明书 ，即产品内含2张说明书 （ZURU标准 说明书1张+2国语言电池说明书）；条码贴和两国语言说明书翻订单4500148687 1 assortment Remark: *MA版本按工厂现有最新库存即可，订单出英国，请注意检查产品及包装应带UKCA图标，包装显示ZURU UK LTD信息，QC同事请查核，如有问题与跟单确认。 *生产日期按实际（法定工作日），按ZURU标准格式即可 ，但是请知悉包装日期码需要早于或者等于外箱日期码 ，不能晚于外箱日期码 *请注意所有订单都需要经过ZURU QC验货并且通过后方可出货 *条码以订单显示为准 ，请安排生产前先核对 ，有问题请提出。 *所有产品按符合欧洲标准走货，需要是不含微塑料版本 。 *涉及到硼的，如可选择情况下应使用低硼版本 （slime 类别低硼一般低于300ppm)，无选择的应与跟单复核再安排 。 | Y17: Sherry Lu | Z17: 7.6175 | AA17: =Z17*I17 -> 9689.46 | AB17: 未出货 | AC17: 9548-S001 | AD17: 已入 | AE17: =I17*0.2 -> 254.4 | AK17: =I17 -> 1272 | AR17: =I17 -> 1272 | BA17: =I17 -> 1272 | BB17: =BB16+BA17 -> 751076
A18: 45614 | B18: TARGET US | C18: 美国 | D18: 4500151467 | E18: 10001064833-3890 | F18: 4500151467-10 | G18: 9548-S001 | H18: 鸭妈妈 | I18: 2016 | J18: 0 | K18: 4 | L18: =I18/K18 -> 504 | M18: 45657 | N18: 45653 | R18: 45625 | S18: 有 | T18: 12/6客供外箱贴纸 | U18: MA | X18: 日期码格式：ZURU INC(BVI) 标准格式 日期：按实际生产日期 Packaging Info: MA 1L包装(UPC版) Remark: 1. 9548-S001-PETS ALIVE - MAMA <(>&<)> BABY SURPRISE - SERIES 1 - MAMA DUCK -WINDOW BOX-4 PCS/CTN 2. MA 1L包装(UPC版), 产品彩盒上的UPC显示193052064196; 3. 外箱正唛左上角位置粘贴条码箱贴纸，每箱只贴一张，由ZURU订购。来料贴纸上显示的客户DPCI# 086-08-0304， UPC显示10193052064193; 4. 产品和包装上印刷 tracking code信息，格式为ZURU常规格式; 5. 出货方式：货代自提 | Y18: Holly Zheng | Z18: 7.2852 | AA18: =Z18*I18 -> 14686.963 | AC18: 9548-S001 | AD18: 已入 | AE18: =I18*0.2 -> 403.2 | AK18: =I18 -> 2016 | AS18: =I18 -> 2016 | BA18: =I18 -> 2016 | BB18: =BB17+BA18 -> 753092
A19: 45625 | B19: Smyths Toys HQ UC IE | C19: 爱尔兰 | D19: 4500153056 | E19: 4400452588 | F19: 4500153056-10 | G19: 9548-S001 | H19: 鸭妈妈 | I19: 1200 | J19: 0 | K19: 4 | L19: =I19/K19 -> 300 | M19: 45659 | N19: 45656 | R19: 45630 | S19: 无 | T19: 无 | U19: MA | X19: 日期码格式：ZURU INC(BVI) 标准格式 日期：按实际生产日期 Packaging Info: 1.9548: MA A 5L EAN版彩盒（23L warning） +MA 5L（9L Warning ）收藏指南+MA 2L 布标+MA5L（9L Warning）_A 胶袋 EAN#4894680033351请先检查条码是否正确再安排做货如有问题请告知 Remark: 1）包装日期码按ZURU格式即可，请确保不迟于外箱日期码，可等于或者早于外箱日期码，必须为法定工作日，印刷前请先检查外箱日期码。 2）订单出英国，请注意检查产品及包装应带UKCA图标（14+产品除外），包装显示ZURU UK LTD/ZURU France地址信息，QC部门请查核，如有问题与跟单确认 3) 需要符合欧洲标准不能含有闪粉和微塑料，否则不和法规会有客诉产生 | Y19: Amy Ding | Z19: 7.3075 | AA19: =Z19*I19 -> 8769 | AC19: 9548-S001-5L | AD19: 已入 | AE19: =I19*0.2 -> 240 | AO19: =I19 -> 1200 | AR19: =I19 -> 1200 | BA19: =I19 -> 1200 | BB19: =BB18+BA19 -> 754292
A20: 45604 | B20: Inventive Toys | C20: 俄罗斯联邦 | D20: 4500150836 | F20: 4500150836-30 | G20: 9548-S001 | H20: 鸭妈妈 | I20: 2108 | J20: 0 | K20: 4 | L20: =I20/K20 -> 527 | M20: 45660 | N20: 45656 | P20: PASS | R20: 45622 | S20: 无 | T20: 12/10进口商贴纸+EAN条码贴纸 | U20: MA | W20: 胶件/收缩膜/彩盒和外箱不需要ZURU 标准日期码 | X20: 日期码格式：外包装/外箱不要打ZURU标准日期码 日期： Packaging Info: 注意 ：外包装 (指: 收缩膜/彩卡/铝箔袋/挂卡/PDQ) /外箱不要打ZURU标准日期码！胶件可以打日期码。 外包装（包括收缩膜/彩卡/PDQ）都不能含Instagram and facebook logo等社交logo; 1L MA 收缩膜 或者彩卡+ 进口商贴纸； MA PDQ + EAN条码贴纸 ， MA指南/说明书（如有）; Remark: 标准配比 ；整单货期2025年1月3 | Y20: Ann Zhang | Z20: 7.5952 | AA20: =Z20*I20 -> 16010.682 | AB20: 94071-1.16 | AC20: 9548-S001 | AD20: 已入 | AE20: =I20*0.2 -> 421.6 | AK20: =I20 -> 2108 | AR20: =I20 -> 2108 | BA20: =I20 -> 2108 | BB20: =BB19+BA20 -> 756400
A21: 45621 | B21: FREDMEYER INC | C21: 美国 | D21: 4500152281 | E21: 000035894679 | F21: 4500152281-10 | G21: 9548-S001 | H21: 鸭妈妈 | I21: 1548 | J21: 0 | K21: 4 | L21: =I21/K21 -> 387 | M21: 45660 | N21: 45656 | P21: PASS | R21: 45621 | S21: 无 | T21: 无 | U21: MA | X21: 日期码格式：ZURU INC(BVI) 标准格式 日期：按实际生产日期 Packaging Info: 1、包装方式：MA UPC优先1L,出口美国 Remark: 2、无测试无验货要求。 3、纸箱4面印ZURU LOGO + 箱唛。 4、日期码请按ZURU标准版执行即可。 5、ZURU OQC验货 | Y21: Vicky Wu | Z21: 7.6175 | AA21: =Z21*I21 -> 11791.89 | AB21: 未出货 | AC21: 9548-S001 | AD21: 已入 | AE21: =I21*0.2 -> 309.6 | AK21: =I21 -> 1548 | AS21: =I21 -> 1548 | BA21: =I21 -> 1548 | BB21: =BB20+BA21 -> 757948
A22: 45632 | B22: KMART AUSTRALIA LTD | C22: 澳大利亚 | D22: 4500153425 | E22: 20549112 | F22: 4500153425-10 | G22: 9548-S001 | H22: 鸭妈妈 | I22: 2000 | J22: 0 | K22: 4 | L22: =I22/K22 -> 500 | M22: 45660 | N22: 45656 | P22: PASS | R22: 45602 | S22: 有 | T22: 外箱SSCC Label+1张防盗贴纸 (贴纸以及位置图翻单PO#4500126567） | U22: MA | X22: 日期码格式：ZURU INC(BVI) 标准格式 日期：按实际生产日期 Packaging Info: 9548: MA英语UPC版本包装（收缩膜和说明书, MA首选1L，如无1L可用多语且含英语的配套多语包装) + 1张防盗贴纸 (贴纸以及位置图翻单PO#4500126567）+ 箱唛 + 外箱SSCC Label Remark: 1.请务必按时完货，验货。并且按期送货入货代指定仓库，如果晚了导致船期Delay将会有罚金产生或者客户要求空运，所产生的罚金和空运费由工厂承担。 2.SSCC 外箱贴纸请同纸箱瓦楞纸方向（竖纹向）垂直，即外箱贴纸横着贴(注意条码不要被胶带粘住），贴1pc，贴1面正唛，封箱胶纸不能挡住贴纸内容。外箱贴纸 离外箱边距离不少于2cm。 3.外箱材质为ZURU标准； 4.此单需使用KMART封箱胶上下工字型封箱;从2019年6月开始，要用KMART 新版封箱胶带，此单要用"ANKO"封箱胶带 5.此单出口澳大利亚，请按相应的澳新标准生产； 6.产品和包装上生产批号的显示格式ZURU标准日期码格式 7.外箱信息不可手写，重量和体积需要与实际的一致(不可手写） 8. 每款item装箱后的G.W.超过10KG或者CBM超过0.13,(9.5KG或者以上，四舍五入后也属于10KG) 需在外箱上加印超 重或者Bulky LOGO，若发现我们资料没有，请 帮忙提醒 1)重量超过10kg但不超过16kg且CBM不超过0.13,10-16kg 超重logo 2）CBM超过0.13且重量少于17kg，bulky logo 3）不属于以上两种情况，需要使用相应重量范围内的超重logo 4）超重logo需要在外箱四面都印刷(箱唛右上角，两面侧唛超重logo需要尽量靠近毛重)，尺寸为:110mm height* 95mm width 9. 实际外箱重量跟印在箱唛上的数据差异不能超3%，尺寸按实际数据印刷 | Y22: Lydia Wu | Z22: 8.2534 | AA22: =Z22*I22 -> 16506.8 | AB22: 未出货 | AC22: 9548-S001 | AD22: 已入 | AE22: =I22*0.2 -> 400 | AK22: =I22 -> 2000 | AS22: =I22 -> 2000 | BA22: =I22 -> 2000 | BB22: =BB21+BA22 -> 759948
A23: 45616 | B23: COOLSHOP(ENTERTAINMENT TRADINGS APS | C23: 丹麦 | D23: 4500151829 | E23: 257441 | F23: 4500151829-50 | G23: 9548-S001-NB | H23: 鸭妈妈 | I23: 368 | J23: 0 | K23: 4 | L23: =I23/K23 -> 92 | M23: 45660 | N23: 45656 | R23: 45626 | S23: 无 | T23: 进口商贴纸+黑白电池说明书(瑞典/挪威/芬兰语翻译) | U23: MA | X23: 日期码格式：ZURU INC(BVI) 标准格式 日期：按实际生产日期 Packaging Info: 5.9548: MA EAN C 5L-23L warning 包装+进口商贴纸+MA B 5L-9L warning说明书+黑白电池说明书(瑞典/挪威/芬兰语翻译) Remark: 1. 包装如含PVC,请改为PET 2. 产品/包装要求无硼无香； 3. 出欧洲，微塑料需合规。 4.带电池出货的产品所用到的电池需要符合欧洲电池新规(EU) 2023-1542 5.关于贴纸，如果贴纸位置图的包装版本与大货不一致，请工厂提前提出。跟单会重新调整确认是否更新贴纸或调整位置图 6.产品/包装不含PFAS成分 7. 产品信息： 9548:3pcs AAA batteries(not included); Boron free Slime ;magnet(inside in the body of baby duck) 8.SKU-客户款号-条码 9548-1254070-4894680033351 | Y23: Sheba Ye | Z23: 7.6392 | AA23: =Z23*I23 -> 2811.2256 | AC23: 9548-S001-NB-5L | AD23: 已入 | AF23: =I23*0.2 -> 73.6 | AO23: =I23 -> 368 | AS23: =I23 -> 368 | BA23: =I23 -> 368 | BB23: =BB22+BA23 -> 760316
A24: 45624 | B24: WABRO | C24: 阿根廷 | D24: 4500152720 | F24: 4500152720-200 | G24: 9548-S001 | H24: 鸭妈妈 | I24: 600 | J24: 0 | K24: 4 | L24: =I24/K24 -> 150 | M24: 45663 | N24: 45659 | P24: PASS | R24: 45629 | S24: 无 | T24: 12/11进口商贴纸 | U24: MA | X24: 日期码格式：ZURU INC(BVI) 标准格式 日期：按实际生产日期 Packaging Info: 9548:MA 5L包装+MA 5L说明书+进口商贴纸+箱唛 | Y24: Ava Liang | Z24: 7.6175 | AA24: =I24*Z24 -> 4570.5 | AC24: 9548-S001-5L | AD24: 已入 | AE24: 300 | AO24: =I24 -> 600 | AS24: =I24 -> 600 | BA24: =I24 -> 600 | BB24: =BB23+BA24 -> 760916
A25: 45617 | B25: TARGET US | C25: 美国 | D25: 4500151907 | E25: 10001053759-3890 | F25: 4500151907-20 | G25: 9548-S001 | H25: 鸭妈妈 | I25: 1168 | J25: 0 | K25: 4 | L25: =I25/K25 -> 292 | M25: 45663 | N25: 45659 | P25: PASS | R25: 45628 | S25: 有 | T25: 12/25客供外箱贴纸 | U25: MA | X25: 日期码格式：ZURU INC(BVI) 标准格式 日期：按实际生产日期 Packaging Info: 9548：MA 1L包装(UPC版) Remark: 9548： 1. 9548-S001-PETS ALIVE - MAMA <(>&<)> BABY SURPRISE - SERIES 1 - MAMA DUCK -WINDOW BOX-4 PCS/CTN 2. MA 1L包装(UPC版), 产品彩盒上的UPC显示193052064196; 3. 外箱正唛左上角位置粘贴条码箱贴纸，每箱只贴一张，由ZURU订购。来料贴纸上显示的客户DPCI# 086-08-0304， UPC显示10193052064193; 4. 产品和包装上印刷 tracking code信息，格式为ZURU常规格式; 5. 出货方式：货代自提 | Y25: Holly Zheng | Z25: 7.3075 | AA25: =Z25*I25 -> 8535.16 | AC25: 9548-S001 | AD25: 已入 | AE25: =I25*0.2 -> 233.6 | AK25: =I25 -> 1168 | AS25: =I25 -> 1168 | BA25: =I25 -> 1168 | BB25: =BB24+BA25 -> 762084
A26: 45617 | B26: TARGET US | C26: 美国 | D26: 4500151906 | E26: 10001053693-3891 | F26: 4500151906-20 | G26: 9548-S001 | H26: 鸭妈妈 | I26: 848 | J26: 0 | K26: 4 | L26: =I26/K26 -> 212 | M26: 45663 | N26: 45659 | P26: PASS | R26: 45628 | S26: 有 | T26: 12/25客供外箱贴纸 | U26: MA | X26: 日期码格式：ZURU INC(BVI) 标准格式 日期：按实际生产日期 Packaging Info: 9548：MA 1L包装(UPC版) Remark: 9548： 1. 9548-S001-PETS ALIVE - MAMA <(>&<)> BABY SURPRISE - SERIES 1 - MAMA DUCK -WINDOW BOX-4 PCS/CTN 2. MA 1L包装(UPC版), 产品彩盒上的UPC显示193052064196; 3. 外箱正唛左上角位置粘贴条码箱贴纸，每箱只贴一张，由ZURU订购。来料贴纸上显示的客户DPCI# 086-08-0304， UPC显示10193052064193; 4. 产品和包装上印刷 tracking code信息，格式为ZURU常规格式; 5. 出货方式：货代自提 | Y26: Holly Zheng | Z26: 7.3075 | AA26: 10961.25 | AB26: 94061-1.16 | AC26: 9548-S001 | AD26: 已入 | AE26: 300 | AK26: =I26 -> 848 | AS26: =I26 -> 848 | BA26: =I26 -> 848 | BB26: =BB25+BA26 -> 762932
A27: 45609 | B27: ROSS PROCUREMENT.INC | C27: 美国 | D27: 4500151215 | E27: 60194304 | F27: 4500151215-10 | G27: 9548-S001 | H27: 鸭妈妈 | I27: 1500 | J27: 0 | K27: 4 | L27: =I27/K27 -> 375 | M27: 45664 | N27: 45660 | P27: PASS | R27: 45610 | S27: 无 | T27: 12/2客供价格贴纸 | U27: MA | X27: 日期码格式： 标准格式 日期：按实际生产日期 Packaging Info: 1.ZURU MA UPC 现有版本包装 + 客供价格贴纸，出口美国 , 优先使用MA 1L 最新版本 。 Remark: 1.ZURU MA UPC 现有版本包装 + 客供价格贴纸，出口美国 , 优先使用MA 1L 最新版本 。 2.价格贴纸位于包装正面右下角，不挡住重要信息即可，可适当调整 ，价格贴纸由跟单提供。 3.标准日期码格式，产品和包装必须有日期码 。 4.同个产品同个货期不可出现不同的包装。 5. 跟单提供ROSS通用的箱唛模版，工厂按实际45 PO上客户PO/Item号/装箱数 提供箱唛排版来确认 | Y27: Minny Peng | Z27: 7.3075 | AA27: 10961.25 | AB27: 94103-1.18 | AC27: 9548-S001 | AD27: 已入 | AE27: 300 | AK27: =I27 -> 1500 | AS27: =I27 -> 1500 | BA27: =I27 -> 1500 | BB27: =BB26+BA27 -> 764432
A28: 45615 | B28: WAL-MART STORES INC. USA | C28: 美国 | D28: 4500151682 | E28: 0876497060 | F28: 4500151682-10 | G28: 9548SLB-S002 | H28: 鸭妈妈 （卡板装） | I28: 504 | J28: 1 | K28: 72 | L28: =I28/K28 -> 7 | M28: 45664 | N28: 45660 | P28: PASS | R28: 45373 | S28: 有 | T28: 客版布标贴纸+11/11客供RFID贴纸 | U28: MA | X28: 日期码格式：ZURU DGYYYYMMDD CHINA（日期避开周末和法定节假日即可） 日期：按实际生产日期 Packaging Info: 9548 1.包装信息：MA B版 UPC版 1L包装，MA 5L B版说明书，MA 5L B版口水胶袋，MA 2L C版车缝布标，客版布标贴纸，客供RFID贴纸（标贴位置严格按照我们签板的 位置图，不可擅自调整位置，贴纸不能有任何破损或折坏，不可淋湿）。 Remark: 2.外箱四面印刷RFID箱唛，正唛左前下角印刷ITF-14格式条码的艾利替代标箱唛，只印刷正唛一面，整个内容尺寸最小10*10cm，加印时需确保条形码能扫描出来，Z URU logo跟MADE IN CHINA四面右下角印刷，外箱印刷日期码，每个slip sheet上面贴一张10*10cm艾利替代标（工厂自行用不干胶打印）和一张普通贴纸（可A4纸 打印），slip sheet打印的普通贴纸的尺寸不能比艾利替代标小。 3.在产品上和包装上要有日期码（避开周末和节假日），以及要有MADE IN CHINA和ZURU字样。 4.产品如有扎带口要剪平，不能刮手。 5.此单以打卡板出货（18*4H=72cartons/72pcs/Slip Sheet） 6.此单需要第三方验货，请自行多备物料。 7.其它信息：3pcs*AAA battery not include。 | Y28: Sandy Xu | Z28: 23.842 | AA28: =Z28*L28 -> 166.894 | AB28: 94095-1.18 | AC28: 9548SLB-S002 | AD28: 已入 | AE28: =I28*0.2 -> 100.8 | AK28: =I28 -> 504 | AS28: =I28 -> 504 | AZ28: =I28/72 -> 7 | BA28: =I28 -> 504 | BB28: =BB27+BA28 -> 764936
A29: 45615 | B29: WAL-MART STORES INC. USA | C29: 美国 | D29: 4500151682 | E29: 0876497079 | F29: 4500151682-20 | G29: 9548SLB-S002 | H29: 鸭妈妈 （卡板装） | I29: 1152 | J29: 1 | K29: 72 | L29: =I29/K29 -> 16 | M29: 45664 | N29: 45660 | P29: PASS | R29: 45373 | S29: 有 | T29: 客版布标贴纸+11/11客供RFID贴纸 | U29: MA | X29: 日期码格式：ZURU DGYYYYMMDD CHINA（日期避开周末和法定节假日即可） 日期：按实际生产日期 Packaging Info: 9548 1.包装信息：MA B版 UPC版 1L包装，MA 5L B版说明书，MA 5L B版口水胶袋，MA 2L C版车缝布标，客版布标贴纸，客供RFID贴纸（标贴位置严格按照我们签板的 位置图，不可擅自调整位置，贴纸不能有任何破损或折坏，不可淋湿）。 Remark: 2.外箱四面印刷RFID箱唛，正唛左前下角印刷ITF-14格式条码的艾利替代标箱唛，只印刷正唛一面，整个内容尺寸最小10*10cm，加印时需确保条形码能扫描出来，Z URU logo跟MADE IN CHINA四面右下角印刷，外箱印刷日期码，每个slip sheet上面贴一张10*10cm艾利替代标（工厂自行用不干胶打印）和一张普通贴纸（可A4纸 打印），slip sheet打印的普通贴纸的尺寸不能比艾利替代标小。 3.在产品上和包装上要有日期码（避开周末和节假日），以及要有MADE IN CHINA和ZURU字样。 4.产品如有扎带口要剪平，不能刮手。 5.此单以打卡板出货（18*4H=72cartons/72pcs/Slip Sheet） 6.此单需要第三方验货，请自行多备物料。 7.其它信息：3pcs*AAA battery not include。 | Y29: Sandy Xu | Z29: 44.6867 | AA29: =Z29*L29 -> 714.9872 | AB29: 94138-1.21 | AC29: 9548SLB-S002 | AD29: 已入 | AE29: =I29*0.2 -> 230.4 | AK29: =I29 -> 1152 | AS29: =I29 -> 1152 | AZ29: =I29/72 -> 16 | BA29: =I29 -> 1152 | BB29: =BB28+BA29 -> 766088
A30: 45625 | B30: Smyths Toys HQ UC UK | C30: 英国 | D30: 4500153057 | E30: 4400452593 | F30: 4500153057-20 | G30: 9548-S001 | H30: 鸭妈妈 | I30: 1160 | J30: 0 | K30: 4 | L30: =I30/K30 -> 290 | M30: 45666 | N30: 45663 | P30: PASS | R30: 45630 | S30: 无 | T30: 无 | U30: MA | X30: 日期码格式：ZURU INC(BVI) 标准格式 日期：按实际生产日期 Packaging Info: 1.9548: MA A 5L EAN版彩盒（23L warning） +MA 5L（9L Warning ）收藏指南+MA 2L 布标+MA5L（9L Warning）_A 胶袋 EAN#4894680033351请先检查条码是否正确再安排做货如有问题请告知 | Y30: Amy Ding | Z30: 7.6175 | AA30: 10961.25 | AB30: 94098-1.18 | AC30: 9548-S001-5L | AD30: 已入 | AE30: 300 | AO30: =I30 -> 1160 | AS30: =I30 -> 1160 | BA30: =I30 -> 1160 | BB30: =BB29+BA30 -> 767248
A31: 45630 | B31: Smyths Toys HQ UC UK | C31: 爱尔兰英国 | D31: 4500153276 | E31: 4400453582 | F31: 4500153276-10 | G31: 9548-S001 | H31: 鸭妈妈 | I31: 4000 | J31: 0 | K31: 4 | L31: =I31/K31 -> 1000 | M31: 45666 | N31: 45663 | P31: PASS | R31: 45636 | S31: 无 | T31: 无 | U31: MA | X31: 日期码格式：ZURU INC(BVI) 标准格式 日期：按实际生产日期 Packaging Info: 9548: MA A 5L EAN版彩盒（23L warning） +MA 5L（9L Warning ）收藏指南+MA 2L 布标+MA5L（9L Warning）_A 胶袋 EAN#4894680033351请先检查条码是否正确再安排做货如有问题请告知 Remark: 1）包装日期码按ZURU格式即可，请确保不迟于外箱日期码，可等于或者早于外箱日期码，必须为法定工作日，印刷前请先检查外箱日期码。 2）订单出英国，请注意检查产品及包装应带UKCA图标（14+产品除外），包装显示ZURU UK LTD/ZURU France地址信息，QC部门请查核，如有问题与跟单确认 3) 需要符合欧洲标准不能含有闪粉和微塑料，否则不和法规会有客诉产生 | Y31: Amy Ding | Z31: 7.5952 | AA31: 10961.25 | AB31: 94117-1.20 | AC31: 9548-S001-5L | AD31: 已入 | AE31: 300 | AO31: =I31 -> 4000 | AS31: =I31 -> 4000 | BA31: =I31 -> 4000 | BB31: =BB30+BA31 -> 771248
A32: 45630 | B32: Smyths Toys HQ UC UK | C32: 爱尔兰英国 | D32: 4500153276 | E32: 4400453584 | F32: 4500153276-20 | G32: 9548-S001 | H32: 鸭妈妈 | I32: 1000 | J32: 0 | K32: 4 | L32: =I32/K32 -> 250 | M32: 45666 | N32: 45663 | P32: PASS | R32: 45636 | S32: 无 | T32: 无 | U32: MA | X32: 日期码格式：ZURU INC(BVI) 标准格式 日期：按实际生产日期 Packaging Info: 9548: MA A 5L EAN版彩盒（23L warning） +MA 5L（9L Warning ）收藏指南+MA 2L 布标+MA5L（9L Warning）_A 胶袋 EAN#4894680033351请先检查条码是否正确再安排做货如有问题请告知 Remark: 1）包装日期码按ZURU格式即可，请确保不迟于外箱日期码，可等于或者早于外箱日期码，必须为法定工作日，印刷前请先检查外箱日期码。 2）订单出英国，请注意检查产品及包装应带UKCA图标（14+产品除外），包装显示ZURU UK LTD/ZURU France地址信息，QC部门请查核，如有问题与跟单确认 3) 需要符合欧洲标准不能含有闪粉和微塑料，否则不和法规会有客诉产生 | Y32: Amy Ding | Z32: 7.6175 | AA32: 10961.25 | AC32: 9548-S001-5L | AD32: 已入 | AE32: 300 | AO32: =I32 -> 1000 | AS32: =I32 -> 1000 | BA32: =I32 -> 1000 | BB32: =BB31+BA32 -> 772248
A33: 45631 | B33: Ambiental Paraguay | C33: 巴拉圭 | D33: 4500153347 | F33: 4500153347-60 | G33: 9548-S001 | H33: 鸭妈妈 | I33: 300 | J33: 0 | K33: 4 | L33: =I33/K33 -> 75 | M33: 45667 | N33: 45663 | P33: PASS | R33: 45631 | S33: 无 | U33: MA | X33: 日期码格式：ZURU INC(BVI) 标准格式 日期：按实际生产日期 Packaging Info: 9548:MA 1L包装+MA5L 说明书+客户贴纸+箱唛,进口商贴于位置"A" | Y33: Ava Liang | Z33: 7.6392 | AA33: =Z33*I33 -> 2291.76 | AB33: 94049-1.15 | AC33: 9548-S001 | AD33: 已入 | AE33: =I33*0.2 -> 60 | AK33: =I33 -> 300 | AR33: =I33 -> 300 | BA33: =I33 -> 300 | BB33: =BB32+BA33 -> 772548
A34: 45632 | B34: KMART AUSTRALIA LTD | C34: 澳大利亚 | D34: 4500153426 | E34: 20549113 | F34: 4500153426-10 | G34: 9548-S001 | H34: 鸭妈妈 | I34: 2000 | J34: 0 | K34: 4 | L34: =I34/K34 -> 500 | M34: 45667 | N34: 45663 | P34: PASS | R34: 45632 | S34: 有 | T34: 外箱SSCC Label+1张防盗贴纸 (贴纸以及位置图翻单PO#4500126567） | U34: MA | X34: 日期码格式：ZURU INC(BVI) 标准格式 日期：按实际生产日期 Packaging Info: 9548: MA英语UPC版本包装（收缩膜和说明书, MA首选1L，如无1L可用多语且含英语的配套多语包装) + 1张防盗贴纸 (贴纸以及位置图翻单PO#4500126567）+ 箱唛 + 外箱SSCC Label Remark: 1.请务必按时完货，验货。并且按期送货入货代指定仓库，如果晚了导致船期Delay将会有罚金产生或者客户要求空运，所产生的罚金和空运费由工厂承担。 2.SSCC 外箱贴纸请同纸箱瓦楞纸方向（竖纹向）垂直，即外箱贴纸横着贴(注意条码不要被胶带粘住），贴1pc，贴1面正唛，封箱胶纸不能挡住贴纸内容。外箱贴纸 离外箱边距离不少于2cm。 3.外箱材质为ZURU标准； 4.此单需使用KMART封箱胶上下工字型封箱;从2019年6月开始，要用KMART 新版封箱胶带，此单要用"ANKO"封箱胶带 5.此单出口澳大利亚，请按相应的澳新标准生产； 6.产品和包装上生产批号的显示格式ZURU标准日期码格式 7.外箱信息不可手写，重量和体积需要与实际的一致(不可手写） 8. 每款item装箱后的G.W.超过10KG或者CBM超过0.13,(9.5KG或者以上，四舍五入后也属于10KG) 需在外箱上加印超 重或者Bulky LOGO，若发现我们资料没有，请 帮忙提醒 1)重量超过10kg但不超过16kg且CBM不超过0.13,10-16kg 超重logo 2）CBM超过0.13且重量少于17kg，bulky logo 3）不属于以上两种情况，需要使用相应重量范围内的超重logo 4）超重logo需要在外箱四面都印刷(箱唛右上角，两面侧唛超重logo需要尽量靠近毛重)，尺寸为:110mm height* 95mm width 9. 实际外箱重量跟印在箱唛上的数据差异不能超3%，尺寸按实际数据印刷 | Y34: Lydia Wu | Z34: 8.2534 | AA34: =Z34*I34 -> 16506.8 | AC34: 9548-S001 | AD34: 已入 | AE34: =I34*0.2 -> 400 | AK34: =I34 -> 2000 | AS34: =I34 -> 2000 | BA34: =I34 -> 2000 | BB34: =BB33+BA34 -> 774548
A35: 45631 | B35: ALL BRANDS TOYS PTY LTD | C35: 澳大利亚 | D35: 4500153356 | E35: 83275 | F35: 4500153356-10 | G35: 9548-S001 | H35: 鸭妈妈 | I35: 720 | J35: 0 | K35: 4 | L35: =I35/K35 -> 180 | M35: 45667 | N35: 45663 | P35: PASS | R35: 45631 | S35: 无 | T35: 客人通用进口商贴纸+贴纸翻单4500125432 | U35: MA | X35: 日期码格式：ZURU INC(BVI) 标准格式 日期：按实际生产日期 Packaging Info: 9548:英文MA包装UPC版本（首选1L, 如无1L可选多语含英语）+客人通用进口商贴纸+箱唛，贴纸翻单4500125432 Remark: 1.按实际生产日期; 2.出澳大利亚，请按照相应标准生产; | Y35: Lydia Wu | Z35: 7.6175 | AA35: =Z35*I35 -> 5484.6 | AB35: 94039-1.15 | AC35: 9548-S001 | AD35: 已入 | AE35: =I35*0.2 -> 144 | AK35: =I35 -> 720 | AS35: =I35 -> 720 | BA35: =I35 -> 720 | BB35: =BB34+BA35 -> 775268
A36: 45629 | B36: APOLLO D.O.O. | C36: 斯洛文尼亚 | D36: 4500153179 | F36: 4500153179-20 | G36: 9548-S001 | H36: 鸭妈妈 | I36: 440 | J36: 0 | K36: 4 | L36: =I36/K36 -> 110 | M36: 45667 | N36: 45663 | R36: 45629 | S36: 无 | T36: 12/11UPC条码+进口商贴纸+客版说明书资料 | U36: MA | V36: 客版指南(翻4500126983) | X36: 日期码格式：ZURU INC(BVI) 标准格式 日期：按实际生产日期 Packaging Info: 9548: MA最新包装含UPC条码; 进口商贴纸+客版指南(翻4500126983) Remark: 此单出欧洲斯洛文尼亚， 需满足EU测试标准要求，不能含微塑料，需出无闪粉版本 9548:3pcs AAA batteries(not included) | Y36: Sharon | Z36: 7.6392 | AA36: =Z36*I36 -> 3361.248 | AB36: 94148-1.22 | AC36: 9548-S001-客版斯洛文尼亚 | AD36: 已入 | AE36: 300 | AK36: =I36 -> 440 | AU36: =I36 -> 440 | BA36: =I36 -> 440 | BB36: =BB46+BA36 -> 753840
A37: 45523 | B37: DM LLC | C37: 俄罗斯 | D37: 4500143263 | E37: 出Bekasovo 2 | F37: 4500143263-20 | G37: 9548-S001 | H37: 鸭妈妈 | I37: 460 | J37: 0 | K37: 4 | L37: =I37/K37 -> 115 | M37: 45667 | N37: 45663 | P37: PASS | R37: 45594 | S37: 无 | T37: 进口商贴纸（翻4500143236）+EAN条码贴纸（翻4500143236） | U37: MA | W37: 外包装(指: 收缩膜/彩卡/吊牌/PDQ)/外箱不要打ZURU标准日期码！ | X37: 日期码格式：注意:外包装(指: 收缩膜/彩卡/吊牌/PDQ)/外箱不要打ZURU标准日期码！ 日期： Packaging Info: 出Bekasovo 2 和Ural 2 个港口； LC 货期不可延期有罚款 ； 1.9548： 1L MA 收缩膜 or 彩卡+进口商贴纸（翻4500143236）+EAN条码贴纸（翻4500143236）; MA 说明书/指南（如有）; 注意 ：外包装 (指: 收缩膜/彩卡/吊牌/PDQ) /外箱不要打ZURU标准日期码！ Remark: 标准配比 | Y37: Ann Zhang | Z37: 7.6175 | AA37: =Z37*I37 -> 3504.05 | AB37: 94706-4.7 | AC37: 9548-S001 | AD37: 已入 | AE37: =I37*0.2 -> 92 | AK37: =I37 -> 460 | AS37: =I37 -> 460 | BA37: =I37 -> 460 | BB37: =BB13+BA37 -> 742312
A38: 45523 | B38: DM LLC | C38: 俄罗斯 | D38: 4500143263 | E38: 出Ural | F38: 4500143263-50 | G38: 9548-S001 | H38: 鸭妈妈 | I38: 224 | J38: 0 | K38: 4 | L38: =I38/K38 -> 56 | M38: 45667 | N38: 45663 | P38: PASS | R38: 45594 | S38: 无 | T38: 进口商贴纸（翻4500143236）+EAN条码贴纸（翻4500143236） | U38: MA | W38: 外包装(指: 收缩膜/彩卡/吊牌/PDQ)/外箱不要打ZURU标准日期码！ | X38: 日期码格式：注意:外包装(指: 收缩膜/彩卡/吊牌/PDQ)/外箱不要打ZURU标准日期码！ 日期： Packaging Info: 出Bekasovo 2 和Ural 2 个港口； LC 货期不可延期有罚款 ； 1.9548： 1L MA 收缩膜 or 彩卡+进口商贴纸（翻4500143236）+EAN条码贴纸（翻4500143236）; MA 说明书/指南（如有）; 注意 ：外包装 (指: 收缩膜/彩卡/吊牌/PDQ) /外箱不要打ZURU标准日期码！ Remark: 标准配比 | Y38: Ann Zhang | Z38: 7.6175 | AA38: =Z38*I38 -> 1706.32 | AB38: 94706-4.7 | AC38: 9548-S001 | AD38: 已入 | AE38: =I38*0.2 -> 44.8 | AK38: =I38 -> 224 | AS38: =I38 -> 224 | BA38: =I38 -> 224 | BB38: =BB37+BA38 -> 742536
A39: 45607 | B39: ZURU France | C39: 法国 | D39: 4500149708 | E39: 5200005612 | F39: 4500149708-40 | G39: 9548-S005-NB-MTS | H39: 鸭妈妈 | I39: 552 | J39: 0 | K39: 3 | L39: =I39/K39 -> 184 | M39: 45670 | N39: 45666 | P39: PASS | R39: 45635 | S39: 无 | T39: 无 | U39: MA | X39: 日期码格式：ZURU INC(BVI) 标准格式 日期：按实际生产日期 Packaging Info: 3.9548:最新MA 5L EAN彩卡+最新MA5L说明书+MA5L袋子+MA2L布标 Remark: 1.法国国家内销单，需要通过ZURU 验货结果后才能出货 (工厂需要主动提前同ZURU QC预约验货避免延期出货造成不必要麻烦)； 2.本订单所有 具有 baby items / assorted items 的款式，零售包装上都要用 母 EAN; 3. 若有特定款有特殊外箱条码要求时,需要明确列出产品款对应的具体外箱条码号码/条码类型 (若无,可以忽略此需求) 4. 所有出口欧洲的产品, 法规规定禁止在包装和共公众用的印刷品中使用矿物油中含有的物质, 包装印刷油墨中含有的MOAH/MOSH的质量浓度不能超过1%, 否则出 货到法国被抽检出现问题, 供应商需要对此负责; 5. date code: 外箱/产品/包装 保持一致，完货后提供date code 信息以便我们保存记录做批次管理; 6. 装柜时需要按照款式号码从小到大一款款依次装,避免终端仓库卸货混乱.若一个柜子涉及到几个不同国家内销单,装柜时需要一个国家装完后再装另一个国家的 产品,依次装柜,避免终端仓库因不同国家不同库位位置卸货混乱. (此点需要同工厂装柜人员强调) | Y39: Jade Wang | Z39: 7.5194 | AA39: =Z39*I39 -> 4150.7088 | AB39: 94099-1.18 | AC39: 9548-S005-NB-MTS | AD39: 已入 | AE39: =I39*0.2 -> 110.4 | AF39: =I39 -> 552 | AO39: =I39 -> 552 | AS39: =I39 -> 552 | BA39: =I39 -> 552 | BB39: =BB38+BA39 -> 743088
A40: 45637 | B40: MTA Trade | C40: 哈萨克斯坦 | D40: 4500153567 | F40: 4500153567-10 | G40: 9548-S001 | H40: 鸭妈妈 | I40: 280 | J40: 0 | K40: 4 | L40: =I40/K40 -> 70 | M40: 45670 | N40: 45666 | P40: PASS | R40: 45639 | S40: 无 | T40: 12/13进口商贴纸 | U40: MA | X40: 日期码格式：ZURU INC(BVI) 标准格式 日期：按实际生产日期 Packaging Info: 9548：1L MA UPC 彩卡+进口商贴纸, MA说明书/指南（如有） Remark: 标准配比 | Y40: Ann Zhang | Z40: 7.3292 | AA40: =Z40*I40 -> 2052.176 | AC40: 9548-S001 | AD40: 已入 | AE40: =I40*0.2 -> 56 | AK40: =I40 -> 280 | AS40: =I40 -> 280 | BA40: =I40 -> 280 | BB40: =BB39+BA40 -> 743368
A41: 45642 | B41: TARGET US | C41: 美国 | D41: 4500154083 | E41: 10001053751-3891 | F41: 4500154083-20 | G41: 9548-S001 | H41: 鸭妈妈 | I41: 848 | J41: 0 | K41: 4 | L41: =I41/K41 -> 212 | M41: 45671 | N41: 45667 | R41: 45651 | S41: 有 | T41: 1/3客供外箱贴纸 | U41: MA | X41: 日期码格式：ZURU INC(BVI) 标准格式 日期：按实际生产日期 Packaging Info: 9548: MA 1L包装(UPC版) Remark: 9548: 1. 9548-S001-PETS ALIVE - MAMA <(>&<)> BABY SURPRISE - SERIES 1 - MAMA DUCK -WINDOW BOX-4 PCS/CTN 2. MA 1L包装(UPC版), 产品彩盒上的UPC显示193052064196; 3. 外箱正唛左上角位置粘贴条码箱贴纸，每箱只贴一张，由ZURU订购。来料贴纸上显示的客户DPCI# 086-08-0304， UPC显示10193052064193; 4. 产品和包装上印刷 tracking code信息，格式为ZURU常规格式; 5. 出货方式：货代自提 | Y41: Holly Zheng | Z41: 7.3075 | AA41: =Z41*I41 -> 6196.76 | AB41: 94079-1.17 | AC41: 9548-S001 | AD41: 已入 | AE41: =I41*0.2 -> 169.6 | AK41: =I41 -> 848 | AS41: =I41 -> 848 | BA41: =I41 -> 848 | BB41: =BB70+BA41 -> 781540
A42: 45621 | B42: TARGET US | C42: 美国 | D42: 4500152263 | E42: 10001144217-3891 | F42: 4500152263-10 | G42: 9548-S001 | H42: 鸭妈妈 | I42: 2104 | J42: 0 | K42: 4 | L42: =I42/K42 -> 526 | M42: 45671 | N42: 45667 | R42: 45628 | S42: 有 | T42: 1/3客供外箱贴纸 | U42: MA | X42: 日期码格式：ZURU INC(BVI) 标准格式 日期：按实际生产日期 Packaging Info: MA 1L包装(UPC版) Remark: 1. 9548-S001-PETS ALIVE - MAMA <(>&<)> BABY SURPRISE - SERIES 1 - MAMA DUCK -WINDOW BOX-4 PCS/CTN 2. MA 1L包装(UPC版), 产品彩盒上的UPC显示193052064196; 3. 外箱正唛左上角位置粘贴条码箱贴纸，每箱只贴一张，由ZURU订购。来料贴纸上显示的客户DPCI# 086-08-0304， UPC显示10193052064193; 4. 产品和包装上印刷 tracking code信息，格式为ZURU常规格式; 5. 出货方式：货代自提 | Y42: Holly Zheng | Z42: 7.2852 | AA42: =Z42*I42 -> 15328.061 | AB42: 94119-1.20 | AC42: 9548-S001 | AD42: 已入 | AE42: =I42*0.2 -> 420.8 | AK42: =I42 -> 2104 | AS42: =I42 -> 2104 | BA42: =I42 -> 2104 | BB42: =BB41+BA42 -> 783644
A43: 45630 | B43: SEARS MEXICO | C43: 墨西哥 | D43: 4500153293 | F43: 4500153293-20 | G43: 9548-S001 | H43: 鸭妈妈 | I43: 400 | J43: 0 | K43: 4 | L43: =I43/K43 -> 100 | M43: 45671 | N43: 45708 | P43: PASS | R43: 45651 | S43: 无 | T43: 2/7进口商贴纸 | U43: MA | X43: 日期码格式：ZURU INC(BVI) 标准格式 日期：按实际生产日期 Packaging Info: 9548: MA 多语EAN包装+UPC贴纸+MA 多语收藏指南+进口商贴纸+箱唛 Remark: 9548：3pcs AAA batteries(not included) | Y43: Zoe Luo | Z43: 7.6392 | AA43: =Z43*I43 -> 3055.68 | AB43: 94489-3.7 | AC43: 9548-S001-5L | AD43: 已入 | AE43: =I43*0.2 -> 80 | AM43: =I43 -> 400 | AO43: =I43 -> 400 | AR43: =I43 -> 400 | BA43: =I43 -> 400 | BB43: =BB38+BA43 -> 742936
A44: 45635 | B44: BINGO GLOBAL GROUP FOR TRADING SUPP | C44: 埃及 | D44: 4500153513 | F44: 4500153513-10 | G44: 9548-S001 | H44: 鸭妈妈 | I44: 600 | J44: 0 | K44: 4 | L44: =I44/K44 -> 150 | M44: 45672 | N44: 45668 | P44: PASS | R44: 45639 | S44: 有 | T44: 12/16进口商贴纸 | U44: MA | X44: 日期码格式：ZURU INC(BVI) 标准格式 日期：按实际生产日期 Packaging Info: 9548:5L MA EAN包装+进口商贴纸;MA说明书 Remark: 标准产品标准配比 | Y44: Lena Huang | Z44: 7.6175 | AA44: =Z44*I44 -> 4570.5 | AB44: 94081-1.17 | AC44: 9548-S001-5L | AD44: 已入 | AE44: =I44*0.2 -> 120 | AO44: =I44 -> 600 | AS44: =I44 -> 600 | BA44: =I44 -> 600 | BB44: =BB43+BA44 -> 743536
A45: 45642 | B45: TARGET US | C45: 美国 | D45: 4500154099 | E45: 10001053692-3890 | F45: 4500154099-20 | G45: 9548-S001 | H45: 鸭妈妈 | I45: 1168 | J45: 0 | K45: 4 | L45: =I45/K45 -> 292 | M45: 45672 | N45: 45668 | R45: 45651 | S45: 有 | T45: 1/3客供外箱贴纸 | U45: MA | X45: 日期码格式：ZURU INC(BVI) 标准格式 日期：按实际生产日期 Packaging Info: 9548: MA 1L包装(UPC版) Remark: 9548: 1. 9548-S001-PETS ALIVE - MAMA <(><<)>(><(>&<)><(><<)>)> BABY SURPRISE - SERIES 1 - MAMA DUCK -WINDOW BOX-4 PCS/CTN 2. MA 1L包装(UPC版), 产品彩盒上的UPC显示193052064196; 3. 外箱正唛左上角位置粘贴条码箱贴纸，每箱只贴一张，由ZURU订购。来料贴纸上显示的客户DPCI# 086-08-0304， UPC显示10193052064193; 4. 产品和包装上印刷 tracking code信息，格式为ZURU常规格式; 5. 出货方式：货代自提 | Y45: Holly Zheng | Z45: 7.3075 | AA45: =Z45*I45 -> 8535.16 | AB45: 94080-1.17 | AC45: 9548-S001 | AD45: 已入 | AE45: =I45*0.2 -> 233.6 | AK45: =I45 -> 1168 | AS45: =I45 -> 1168 | BA45: =I45 -> 1168 | BB45: =BB44+BA45 -> 744704
A46: 45621 | B46: TARGET US | C46: 美国 | D46: 4500152253 | E46: 10001144213-3890 | F46: 4500152253-10 | G46: 9548-S001 | H46: 鸭妈妈 | I46: 8696 | J46: 0 | K46: 4 | L46: =I46/K46 -> 2174 | M46: 45674 | N46: 45670 | R46: 45628 | S46: 有 | T46: 1/3客供外箱贴纸 | U46: MA | X46: 日期码格式：ZURU INC(BVI) 标准格式 日期：按实际生产日期 Packaging Info: MA 1L包装(UPC版) Remark: 1. 9548-S001-PETS ALIVE - MAMA <(>&<)> BABY SURPRISE - SERIES 1 - MAMA DUCK -WINDOW BOX-4 PCS/CTN 2. MA 1L包装(UPC版), 产品彩盒上的UPC显示193052064196; 3. 外箱正唛左上角位置粘贴条码箱贴纸，每箱只贴一张，由ZURU订购。来料贴纸上显示的客户DPCI# 086-08-0304， UPC显示10193052064193; 4. 产品和包装上印刷 tracking code信息，格式为ZURU常规格式; 5. 出货方式：货代自提 | Y46: Holly Zheng | Z46: 7.2151 | AA46: =Z46*I46 -> 62742.51 | AB46: 94118-1.20 | AC46: 9548-S001 | AD46: 已入 | AE46: =I46*0.2 -> 1739.2 | AK46: =I46 -> 8696 | AS46: =I46 -> 8696 | BA46: =I46 -> 8696 | BB46: =BB45+BA46 -> 753400
A47: 45586 | B47: TJX COMPANIES, INC | C47: 美国 | D47: 4500147803 | E47: TJ MAXX DC#891-160PCS , DC#894-136PCS , DC#896-128PCS , DC#897-248PCS , DC#898-128PCS | F47: 4500147803-40 | G47: 9548-S001 | H47: 鸭妈妈 | I47: 800 | J47: 0 | K47: 4 | L47: =I47/K47 -> 200 | M47: 45677 | N47: 45673 | P47: PASS | R47: 45600 | S47: 无 | T47: 12/20价格贴纸客供 | U47: MA | X47: 日期码格式：ZURU INC(BVI) 标准格式 日期：按实际生产日期 Packaging Info: MA UPC包装+价格贴纸，价格贴纸客供。 Remark: 1. 产品和包装上印刷tracking code信息，格式为ZURU常规格式。 2. 分5个DC出货，每款产品每个DC的箱唛资料不同。具体分DC数量，请参考后面行项目备注。 3. ZURU QC验货。 | Y47: Emily Wu | Z47: 7.6175 | AA47: =Z47*I47 -> 6094 | AB47: 94279-2.18 | AC47: 9548-S001 | AD47: 已入 | AE47: =I47*0.2 -> 160 | AK47: =I47 -> 800 | AS47: =I47 -> 800 | BA47: =I47 -> 800 | BB47: =BB46+BA47 -> 754200
A48: 45586 | B48: TJX COMPANIES, INC | C48: 美国 | D48: 4500147800 | E48: Marshalls DC#881-124PCS , DC#884-96PCS, DC#886-140PCS , DC#887-116PCS , DC#888-124PCS | F48: 4500147800-40 | G48: 9548-S001 | H48: 鸭妈妈 | I48: 600 | J48: 0 | K48: 4 | L48: =I48/K48 -> 150 | M48: 45677 | N48: 45673 | P48: PASS | R48: 45600 | S48: 无 | T48: 12/20价格贴纸客供 | U48: MA | X48: 日期码格式：ZURU INC(BVI) 标准格式 日期：按实际生产日期 Packaging Info: MA UPC包装+价格贴纸，价格贴纸客供。 Remark: 1. 产品和包装上印刷tracking code信息，格式为ZURU常规格式。 2. 分5个DC出货，每款产品每个DC的箱唛资料不同。具体分DC数量，请参考后面行项目备注。 3. ZURU QC验货。 | Y48: Emily Wu | Z48: 7.6175 | AA48: =Z48*I48 -> 4570.5 | AB48: 94277-2.18 | AC48: 9548-S001 | AD48: 已入 | AE48: =I48*0.2 -> 120 | AK48: =I48 -> 600 | AS48: =I48 -> 600 | BA48: =I48 -> 600 | BB48: =BB47+BA48 -> 754800
A49: 45642 | B49: TARGET US | C49: 美国 | D49: 4500154154 | E49: 10001144216-3890 | F49: 4500154154-10 | G49: 9548-S001 | H49: 鸭妈妈 | I49: 2900 | J49: 0 | K49: 4 | L49: =I49/K49 -> 725 | M49: 45679 | N49: 45675 | P49: PASS | R49: 45651 | S49: 有 | T49: 1/13客供外箱贴纸 | U49: MA | X49: 日期码格式：ZURU INC(BVI) 标准格式 日期：按实际生产日期 Packaging Info: MA 1L包装(UPC版) Remark: 1. 9548-S001-PETS ALIVE - MAMA <(>&<)> BABY SURPRISE - SERIES 1 - MAMA DUCK -WINDOW BOX-4 PCS/CTN 2. MA 1L包装(UPC版), 产品彩盒上的UPC显示193052064196; 3. 外箱正唛左上角位置粘贴条码箱贴纸，每箱只贴一张，由ZURU订购。来料贴纸上显示的客户DPCI# 086-08-0304， UPC显示10193052064193; 4. 产品和包装上印刷 tracking code信息，格式为ZURU常规格式; 5. 出货方式：货代自提 | Y49: Holly Zheng | Z49: 7.2852 | AA49: =Z49*I49 -> 21127.08 | AB49: 94225-2.12 | AC49: 9548-S001 | AD49: 已入 | AE49: =I49*0.2 -> 580 | AK49: =I49 -> 2900 | AS49: =I49 -> 2900 | BA49: =I49 -> 2900 | BB49: =BB65+BA49 -> 783880
A50: 45643 | B50: Toynova GmbH | C50: 德国 | D50: 4500154198 | F50: 4500154198-50 | G50: 9548-S001 | H50: 鸭妈妈 | I50: 200 | J50: 0 | K50: 4 | L50: =I50/K50 -> 50 | M50: 45695 | N50: 45691 | P50: PASS | R50: 45645 | S50: 无 | T50: 12/23EAN条码贴纸 | U50: MA | X50: 日期码格式：ZURU INC(BVI) 标准格式 日期：按实际生产日期 Packaging Info: 9548：MA C 版5L EAN 彩盒+EAN条码贴纸+MA B版说明书+MA 5L 史莱姆袋子+MA 布标 Remark: "1.需要在完货当天提供验货图片供客人放货 2.此单出德国，需准时出货 3.此单出欧洲需要出无闪粉版本 4.此单符合欧洲 8 PAH 标准即可" | Y50: Amy Xiao | Z50: 7.6392 | AA50: =Z50*I50 -> 1527.84 | AB50: 94209-2.11 | AC50: 9548-S001-5L | AD50: 已入 | AE50: =I50*0.2 -> 40 | AO50: =I50 -> 200 | AS50: =I50 -> 200 | BA50: =I50 -> 200 | BB50: =BB49+BA50 -> 784080
A51: 45625 | B51: THE ENTERTAINER | C51: 英国 | D51: 4500152538 | E51: 4500152538-3: FB12155 | F51: 4500152538-200 | G51: 9548-S001 | H51: 鸭妈妈 | I51: 1200 | J51: 0 | K51: 4 | L51: =I51/K51 -> 300 | M51: 45696 | N51: 45692 | P51: PASS | R51: 45624 | S51: 无 | T51: 两国语言说明书翻订单4500150141 | U51: MA | V51: 产品内包装再加多一张2国语言电池说明书 | X51: 日期码格式：ZURU INC(BVI) 标准格式 日期：按实际生产日期 Packaging Info: 9548：MA-1L（含23L warning）包装配套 ,额外加一张条码贴覆盖ZURU条码 ，另外产品内包装再加多一张2国语言电池说明书 ，即产品内含2张说明书 （ZURU标准 说明书1张+2国语言电池说明书）；条码贴翻订单4500126257，两国语言说明书翻订单4500150141 1 assortment 订单对应客户4个PO号 ，备注有显示 ，注意分开做货/验货/装柜 ，混装有罚款。 Remark: *MA版本按工厂现有最新库存即可，订单出英国，请注意检查产品及包装应带UKCA图标，包装显示ZURU UK LTD信息，QC同事请查核，如有问题与跟单确认。 *生产日期按实际（法定工作日），按ZURU标准格式即可 ，但是请知悉包装日期码需要早于或者等于外箱日期码 ，不能晚于外箱日期码 *请注意所有订单都需要经过ZURU QC验货并且通过后方可出货 *条码以订单显示为准 ，请安排生产前先核对 ，有问题请提出。 *所有产品按符合欧洲标准走货，需要是不含微塑料版本 。 *涉及到硼的，如可选择情况下应使用低硼版本 （slime 类别低硼一般低于300ppm)，无选择的应与跟单复核再安排 。 | Y51: Amy Ding | Z51: 7.6175 | AA51: =Z51*I51 -> 9141 | AB51: 94275-2.18 | AC51: 9548-S001 | AD51: 已入 | AE51: =I51*0.2 -> 240 | AK51: =I51 -> 1200 | AR51: =I51 -> 1200 | BA51: =I51 -> 1200 | BB51: =BB50+BA51 -> 785280
A52: 45667 | B52: TARGET US | C52: 美国 | D52: 4500154982 | E52: 10001144211-3890 | F52: 4500154982-10 | G52: 9548-S001 | H52: 鸭妈妈 | I52: 3012 | J52: 0 | K52: 4 | L52: =I52/K52 -> 753 | M52: 45702 | N52: 45698 | P52: PASS | R52: 45667 | S52: 有 | T52: 1/17客供外箱贴纸 | U52: MA | X52: 日期码格式：ZURU INC(BVI) 标准格式 日期：按实际生产日期 Packaging Info: MA 1L包装(UPC版) Remark: 1. 9548-S001-PETS ALIVE - MAMA <(>&<)> BABY SURPRISE - SERIES 1 - MAMA DUCK -WINDOW BOX-4 PCS/CTN 2. MA 1L包装(UPC版), 产品彩盒上的UPC显示193052064196; 3. 外箱正唛左上角位置粘贴条码箱贴纸，每箱只贴一张，由ZURU订购。来料贴纸上显示的客户DPCI# 086-08-0304， UPC显示10193052064193; 4. 产品和包装上印刷 tracking code信息，格式为ZURU常规格式; 5. 出货方式：货代自提 | Y52: Holly Zheng | Z52: 7.2852 | AA52: =Z52*I52 -> 21943.022 | AB52: 94260-2.17 | AC52: 9548-S001 | AD52: 已入 | AE52: =I52*0.2 -> 602.4 | AK52: =I52 -> 3012 | AS52: =I52 -> 3012 | BA52: =I52 -> 3012 | BB52: =BB51+BA52 -> 788292
A53: 45642 | B53: TARGET US | C53: 美国 | D53: 4500154105 | E53: 10001053748-3890 | F53: 4500154105-20 | G53: 9548-S001 | H53: 鸭妈妈 | I53: 1168 | J53: 0 | K53: 4 | L53: =I53/K53 -> 292 | M53: 45703 | N53: 45699 | P53: PASS | R53: 45664 | S53: 有 | T53: 1/17客供外箱贴纸 | U53: MA | X53: 日期码格式：ZURU INC(BVI) 标准格式 日期：按实际生产日期 Packaging Info: 9548: MA 1L包装(UPC版) Remark: 9548: 1. 9548-S001-PETS ALIVE - MAMA <(><<)>(><(>&<)><(><<)>)> BABY SURPRISE - SERIES 1 - MAMA DUCK -WINDOW BOX-4 PCS/CTN 2. MA 1L包装(UPC版), 产品彩盒上的UPC显示193052064196; 3. 外箱正唛左上角位置粘贴条码箱贴纸，每箱只贴一张，由ZURU订购。来料贴纸上显示的客户DPCI# 086-08-0304， UPC显示10193052064193; 4. 产品和包装上印刷 tracking code信息，格式为ZURU常规格式; 5. 出货方式：货代自提 | Y53: Holly Zheng | Z53: 7.3075 | AA53: =Z53*I53 -> 8535.16 | AB53: 94263-2.17 | AC53: 9548-S001 | AD53: 已入 | AE53: =I53*0.2 -> 233.6 | AK53: =I53 -> 1168 | AS53: =I53 -> 1168 | BA53: =I53 -> 1168 | BB53: =BB52+BA53 -> 789460
A54: 45657 | B54: TARGET US | C54: 美国 | D54: 4500154981 | E54: 10001053729-3891 | F54: 4500154981-20 | G54: 9548-S001 | H54: 鸭妈妈 | I54: 848 | J54: 0 | K54: 4 | L54: =I54/K54 -> 212 | M54: 45703 | N54: 45699 | P54: PASS | R54: 45667 | S54: 有 | T54: 1/17客供外箱贴纸 | U54: MA | X54: 日期码格式：ZURU INC(BVI) 标准格式 日期：按实际生产日期 Packaging Info: 9548: MA 1L包装(UPC版) Remark: 9548: 1. 9548-S001-PETS ALIVE - MAMA <(>&<)> BABY SURPRISE - SERIES 1 - MAMA DUCK -WINDOW BOX-4 PCS/CTN 2. MA 1L包装(UPC版), 产品彩盒上的UPC显示193052064196; 3. 外箱正唛左上角位置粘贴条码箱贴纸，每箱只贴一张，由ZURU订购。来料贴纸上显示的客户DPCI# 086-08-0304， UPC显示10193052064193; 此订单所有型号： 1. 产品和包装上印刷 tracking code信息，格式为ZURU常规格式; 2. 出货方式：货代自提 | Y54: Holly Zheng | Z54: 7.3075 | AA54: =Z54*I54 -> 6196.76 | AB54: 94273-2.18 | AC54: 9548-S001 | AD54: 已入 | AE54: =I54*0.2 -> 169.6 | AK54: =I54 -> 848 | AS54: =I54 -> 848 | BA54: =I54 -> 848 | BB54: =BB53+BA54 -> 790308
A55: 45657 | B55: WAL-MART CANADA CORP. | C55: 加拿大 | D55: 4500155078 | E55: 9650909459 | F55: 4500155078-10 | G55: 9548-S002-NB | H55: 鸭妈妈 | I55: 1000 | J55: 0 | K55: 1 | L55: =I55/K55 -> 1000 | M55: 45705 | N55: 45701 | P55: PASS | R55: 45615 | S55: 无 | T55: UPC条码贴纸 UPC贴纸翻单: 4500126662 | U55: MA | X55: 日期码格式：ZURU INC(BVI) 标准格式 日期：按实际生产日期 Packaging Info: #9548: MA5L彩盒+UPC条码贴纸 (UPC:193052064196)+MA5L说明书+MA5L复合袋+MA2L布标 (UPC贴纸翻单: 4500126662) Remark: 1. #9548必须在原来错误的EAN条码上用黑色粗头笔涂黑直至不能扫描，再贴上正确的UPC; 2. #9548 须使用无硼版本的slime; 3. 此单有箱唛; 4. 此单需要第三方验货，烦请多备包装物料。 ********************* a. 请确保产品符合1999年版本的加拿大环境保护法(CEPA)和2012年禁止某些有毒物质法规的要求。该产品不含任何在加拿大禁用的化学物质，包括但不限于有毒物 质清单中列出的化学物质，并且在为加拿大沃尔玛生产产品期间没有使用任何禁用化学物质。 Supplier certify that the products comply with the requirements of Canadian Environmental Protection Act, 1999 (CEPA), Prohibition of Certain To xic Substances Regulations, 2012. The products do not contain any chemicals that are banned in Canada, including but not limited to those listed in the Toxic Substances List and no banned chemicals were used during the manufacturing of product for Walmart Canada. 附件列表： (1) Letter of Guarantee for Canada banned chemicals - (1-5CA) b. 请确保产品在均质材料中的汞浓度不超过0.1%（按重量计）。 Supplier certify that the WAL-MART vendor products does not have a mercury concentration of more than 0.1% by weight in homogeneous material. 附件列表： (1) Letter of Guarantee for Mercury COC c. 请确保产品的塑料材料不含以下物质（SOR 2011-17 27B): Supplier certify that the plastic materials do not contain the following substances(SOR 2011-17 27B): (a) carbon tetrachloride or any substance that contains it; (b) methyl alcohol or any substance thay contains >1.0%; (c) petroleum distillates or any substance that contains >10% weight to volume of petroleum distillates; (d) benzene; (e) turpentine or any substance that contains >10% weight to volume of turpentine; (f) boric acid or salts of boric acid; or (g) ethyl ether. 附件列表： (1) Letter of Guarantee for WM CA-Other prohibited substances in plastic(less than 3 years) | Y55: Monica Zhou | Z55: 7.3479 | AA55: =Z55*I55 -> 7347.9 | AB55: 94303-2.20 | AC55: 9548-S002-NB-5L | AD55: 已入 | AF55: =I55*0.2 -> 200 | AO55: =I55 -> 1000 | AS55: =I55 -> 1000 | BA55: =I55 -> 1000 | BB55: =BB63+BA55 -> 780960
A56: 45651 | B56: Zhuyu(Shenzhen)Trading Co.,Ltd. | C56: 中国 | D56: 4500154728 | E56: 5000001743 | F56: 4500154728-60 | G56: 9548-S001 | H56: 鸭妈妈 | I56: 1200 | J56: 0 | K56: 4 | L56: =I56/K56 -> 300 | M56: 45705 | N56: 45701 | P56: PASS | R56: 翻单： 4500152175 | S56: 无 | T56: 翻单： 4500152175 | U56: MA+布标贴纸 | V56: 中文说明书 | X56: 日期码格式：ZURU INC(BVI) 标准格式 日期：按实际生产日期 Packaging Info: 物料要求 SKU 所有款号务必使用带有CCC 标识的AW 5 9548 MA+中文3C贴纸年龄贴（8+）+中文布标(可用布标贴纸)+中文说明书 翻单： 4500152175 Remark: 2.外箱材质如下： 1）毛重小于5kg 外箱纸质 K=B 爆破:1000Kpa 边压:4400N/M; 2）毛重大于5kg 外箱纸质 K636K 爆破:1400Kpa 边压:6300N/M; 3. 产品/销售包装/外箱日期码要一致， 4.芯片码横向平贴在上半部分蛋壳/彩盒内侧立面处，注意事项请见跟单提供文档资料。 5.此产品务必满足国内6P 测试标准，因为可能会被市场监督局抽查，如有问题产生，工厂要负全责 6. 这张订单做出厂价，我司自行安排车辆去贵司提货，贵司需要配合提供出口报关 | Y56: Tina Chen | Z56: 7.3075 | AA56: =Z56*I56 -> 8769 | AB56: 94261-2.17 | AC56: 9548-S001-中国 | AD56: 已入 | AE56: =I56*0.2 -> 240 | AK56: =I56 -> 1200 | AU56: =I56 -> 1200 | BA56: =I56 -> 1200 | BB56: =BB47+BA56 -> 755400
A57: 45637 | B57: Smyths Toys HQ UC UK | C57: 英国 | D57: 4500153746 | E57: 4400455159 | F57: 4500153746-10 | G57: 9548-S001 | H57: 鸭妈妈 | I57: 7496 | J57: 0 | K57: 4 | L57: =I57/K57 -> 1874 | M57: 45705 | N57: 45701 | P57: PASS | R57: 45637 | S57: 无 | T57: 无 | U57: MA | X57: 日期码格式：ZURU INC(BVI) 标准格式 日期：按实际生产日期 Packaging Info: 1.9548: MA A 5L EAN版彩盒 +MA 5L(9L Warning)收藏指南+MA 2L 布标+MA5L(9L Warning) 胶袋 EAN#4894680033351请先检查条码是否正确再安排做货如有问题请告知 Remark: 1）包装日期码按ZURU格式即可，请确保不迟于外箱日期码，可等于或者早于外箱日期码，必须为法定工作日，印刷前请先检查外箱日期码。 2）订单出英国，请注意检查产品及包装应带UKCA图标（14+产品除外），包装显示ZURU UK LTD/ZURU France地址信息，QC部门请查核，如有问题与跟单确认 3) 需要符合欧洲标准不能含有闪粉和微塑料，否则不和法规会有客诉产生 | Y57: Ula Zhao | Z57: 7.5251 | AA57: =Z57*I57 -> 56408.15 | AB57: 94328-2.24 | AC57: 9548-S001-5L | AD57: 已入 | AE57: =I57*0.2 -> 1499.2 | AO57: =I57 -> 7496 | AS57: =I57 -> 7496 | BA57: =I57 -> 7496 | BB57: =BB29+BA57 -> 773584
A58: 45630 | B58: WAL-MART STORES INC. USA | C58: 美国 | D58: 4500153277 | E58: 0881132647 ELWOOD | F58: 4500153277-10 | G58: 9548SLB-S002 | H58: 鸭妈妈 （卡板装） | I58: 504 | J58: 1 | K58: 72 | L58: =I58/K58 -> 7 | M58: 45706 | N58: 45702 | P58: PASS | R58: 45373 | S58: 有 | T58: 12/25客版布标贴纸+客供RFID贴纸 | U58: MA | X58: 日期码格式：ZURU DGYYYYMMDD CHINA(日期避开周末和法定节假日即可） 日期：按实际生产日期 Packaging Info: 9548 1.包装信息：MA B版 UPC版 1L包装，MA 5L B版说明书，MA 5L B版口水胶袋，MA 2L C版车缝布标，客版布标贴纸，客供RFID贴纸（标贴位置严格按照我们签板的 位置图，不可擅自调整位置，贴纸不能有任何破损或折坏，不可淋湿）。 Remark: 9548 1.包装信息：MA B版 UPC版 1L包装，MA 5L B版说明书，MA 5L B版口水胶袋，MA 2L C版车缝布标，客版布标贴纸，客供RFID贴纸（标贴位置严格按照我们签板的 位置图，不可擅自调整位置，贴纸不能有任何破损或折坏，不可淋湿）。 2.外箱四面印刷RFID箱唛，正唛左前下角印刷ITF-14格式条码的艾利替代标箱唛，只印刷正唛一面，整个内容尺寸最小10*10cm，加印时需确保条形码能扫描出来，Z URU logo跟MADE IN CHINA四面右下角印刷，外箱印刷日期码，每个slip sheet上面贴一张10*10cm艾利替代标（工厂自行用不干胶打印）和一张普通贴纸（可A4纸 打印），slip sheet打印的普通贴纸的尺寸不能比艾利替代标小。 3.在产品上和包装上要有日期码（避开周末和节假日），以及要有MADE IN CHINA和ZURU字样。 4.产品如有扎带口要剪平，不能刮手。 5.此单以打卡板出货（18*4H=72cartons/72pcs/Slip Sheet） 6.此单需要第三方验货，请自行多备物料。 7.其它信息：3pcs*AAA battery not include。 | Y58: Maggie Xie | Z58: 44.6867 | AA58: =Z58*L58 -> 312.8069 | AB58: 94421-3.4 | AC58: 9548SLB-S002 | AD58: 已入 | AE58: =I58*0.2 -> 100.8 | AK58: =I58 -> 504 | AS58: =I58 -> 504 | AZ58: =I58/72 -> 7 | BA58: =I58 -> 504 | BB58: =BB57+BA58 -> 774088
A59: 45630 | B59: WAL-MART STORES INC. USA | C59: 美国 | D59: 4500153277 | E59: 0881132715 EASTVALE | F59: 4500153277-20 | G59: 9548SLB-S002 | H59: 鸭妈妈 （卡板装） | I59: 504 | J59: 1 | K59: 72 | L59: =I59/K59 -> 7 | M59: 45706 | N59: 45702 | P59: PASS | R59: 45373 | S59: 有 | T59: 12/25客版布标贴纸+客供RFID贴纸 | U59: MA | X59: 日期码格式：ZURU DGYYYYMMDD CHINA(日期避开周末和法定节假日即可） 日期：按实际生产日期 Packaging Info: 9548 1.包装信息：MA B版 UPC版 1L包装，MA 5L B版说明书，MA 5L B版口水胶袋，MA 2L C版车缝布标，客版布标贴纸，客供RFID贴纸（标贴位置严格按照我们签板的 位置图，不可擅自调整位置，贴纸不能有任何破损或折坏，不可淋湿）。 Remark: 9548 1.包装信息：MA B版 UPC版 1L包装，MA 5L B版说明书，MA 5L B版口水胶袋，MA 2L C版车缝布标，客版布标贴纸，客供RFID贴纸（标贴位置严格按照我们签板的 位置图，不可擅自调整位置，贴纸不能有任何破损或折坏，不可淋湿）。 2.外箱四面印刷RFID箱唛，正唛左前下角印刷ITF-14格式条码的艾利替代标箱唛，只印刷正唛一面，整个内容尺寸最小10*10cm，加印时需确保条形码能扫描出来，Z URU logo跟MADE IN CHINA四面右下角印刷，外箱印刷日期码，每个slip sheet上面贴一张10*10cm艾利替代标（工厂自行用不干胶打印）和一张普通贴纸（可A4纸 打印），slip sheet打印的普通贴纸的尺寸不能比艾利替代标小。 3.在产品上和包装上要有日期码（避开周末和节假日），以及要有MADE IN CHINA和ZURU字样。 4.产品如有扎带口要剪平，不能刮手。 5.此单以打卡板出货（18*4H=72cartons/72pcs/Slip Sheet） 6.此单需要第三方验货，请自行多备物料。 7.其它信息：3pcs*AAA battery not include。 | Y59: Maggie Xie | Z59: 44.6867 | AA59: =Z59*L59 -> 312.8069 | AB59: 94469-3.6 | AC59: 9548SLB-S002 | AD59: 已入 | AE59: =I59*0.2 -> 100.8 | AK59: =I59 -> 504 | AS59: =I59 -> 504 | AZ59: =I59/72 -> 7 | BA59: =I59 -> 504 | BB59: =BB58+BA59 -> 774592
A60: 45649 | B60: ZURU Germany GMBH | C60: 德国 | D60: 4500154528 | E60: 5200005872 | F60: 4500154528-10 | G60: 9548-S005-MTS | H60: 鸭妈妈 | I60: 1200 | J60: 0 | K60: 3 | L60: =I60/K60 -> 400 | M60: 45706 | N60: 45702 | P60: PASS | R60: 45620 | S60: 无 | T60: 通用WEEE说明书纸 | U60: MA | X60: 日期码格式：ZURU INC(BVI) 标准格式 日期：按实际生产日期 Packaging Info: 9548：最新MA 5L EAN 包装+MA5L+5L Warning_A版Slime Polybag+通用WEEE说明书纸 Remark: 1.德国内销单，需要通过ZURU 验货结果后才能出货 (工厂需要主动提前同ZURU QC预约验货避免延期出货造成不必要麻烦)； 2. 若有特定款有特殊外箱条码要求时,需要明确列出产品款对应的具体外箱条码号码/条码类型 (若无,可以忽略此需求) 3.所有出口欧洲的产品, 法规规定禁止在包装和共公众用的印刷品中使用矿物油中含有的物质, 包装印刷油墨中含有的MOAH/MOSH的质量浓度不能超过1%, 否则出货 到法国被抽检出现问题, 供应商需要对此负责; 4. date code: 外箱日期码要晚于产品日期码 5. 装柜时需要按照款式号码从小到大一款款依次装,避免终端仓库卸货混乱.若一个柜子涉及到几个不同国家内销单,装柜时需要一个国家装完后再装另一个国家的 产品,依次装柜,避免终端仓库因不同国家不同库位位置卸货混乱. (此点需要同工厂装柜人员强调) | Y60: SD82 | Z60: 7.5417 | AA60: =Z60*I60 -> 9050.04 | AB60: 94304-2.20 | AC60: 9548-S005-MTS-5L | AD60: 已入 | AE60: =I60*0.2 -> 240 | AM60: =I60 -> 1200 | AR60: =I60 -> 1200 | BA60: =I60 -> 1200 | BB60: =BB61+BA60 -> 776792
A61: 45609 | B61: Intertoys B.V. | C61: 荷兰 | D61: 4500150999 | E61: 4500152441 | F61: 4500150999-10 | G61: 9548-S001 | H61: 鸭妈妈 | I61: 1000 | J61: 0 | K61: 4 | L61: =I61/K61 -> 250 | M61: 45706 | N61: 45702 | O61: 请在12/20日前寄出每个item 2pcs 到罗湖办公室 | P61: PASS | R61: 45609 | S61: 无 | T61: 款号条码贴纸+NL警语贴纸（翻单PO#4500134601） | U61: MA | X61: 日期码格式：ZURU INC(BVI) 标准格式 日期：按实际生产日期 Packaging Info: 9548: MA C版 5L EAN 彩盒(含23L 警语）+款号条码贴纸，MA 5L 说明书（含9L 警语），MA 5L Slime polybag+NL警语贴纸（翻单PO#4500134601），MA 布标 Remark: 1. STD配比 2. 出欧洲，微塑料需合规（如item本身不含微塑料 则忽略此要求） 3. 客人款号： 9548 2001571 4. 大货样 请在12/20日前寄出每个item 2pcs 到罗湖办公室 | Y61: Sandy Shao | Z61: 7.3075 | AA61: =Z61*I61 -> 7307.5 | AB61: 94338-2.25 | AC61: 9548-S001-5L | AD61: 已入 | AE61: =I61*0.2 -> 200 | AO61: =I61 -> 1000 | AR61: =I61 -> 1000 | BA61: =I61 -> 1000 | BB61: =BB59+BA61 -> 775592
A62: 45667 | B62: TARGET US | C62: 美国 | D62: 4500155686 | E62: 10001053726-3890 | F62: 4500155686-20 | G62: 9548-S001 | H62: 鸭妈妈 | I62: 1168 | J62: 0 | K62: 4 | L62: =I62/K62 -> 292 | M62: 45707 | N62: 45703 | P62: PASS | R62: 45668 | S62: 有 | T62: 1/17客供外箱贴纸 | U62: MA | X62: 日期码格式：ZURU INC(BVI) 标准格式 日期：按实际生产日期 Packaging Info: 9548: MA 1L包装(UPC版) Remark: 9548: 1. 9548-S001-PETS ALIVE - MAMA <(>&<)> BABY SURPRISE - SERIES 1 - MAMA DUCK -WINDOW BOX-4 PCS/CTN 2. MA 1L包装(UPC版), 产品彩盒上的UPC显示193052064196; 3. 外箱正唛左上角位置粘贴条码箱贴纸，每箱只贴一张，由ZURU订购。来料贴纸上显示的客户DPCI# 086-08-0304， UPC显示10193052064193; 3. 外箱正唛左上角位置粘贴条码箱贴纸，每箱只贴一张，由ZURU订购。来料贴纸上显示的客户DPCI#086-08-2605,UPC显示10193052064902; 此订单所有型号： 1. 产品和包装上印刷 tracking code信息，格式为ZURU常规格式; 2. 出货方式：货代自提 | Y62: Holly Zheng | Z62: 7.3075 | AA62: =Z62*I62 -> 8535.16 | AB62: 94331-2.24 | AC62: 9548-S001 | AD62: 已入 | AE62: =I62*0.2 -> 233.6 | AK62: =I62 -> 1168 | AS62: =I62 -> 1168 | BA62: =I62 -> 1168 | BB62: =BB60+BA62 -> 777960
A63: 45663 | B63: I-VISION TOYS.INC | C63: 韩国 | D63: 4500155354 | E63: IVI-1224MM | F63: 4500155354-10 | G63: 9548-S001-NB | H63: 鸭妈妈 | I63: 2000 | J63: 0 | K63: 4 | L63: =I63/K63 -> 500 | M63: 45713 | N63: 45709 | P63: PASS | R63: 箱唛翻单4500148437 | S63: 无 | T63: 韩语贴纸（新稿）， | U63: MA | V63: 客版韩语说明书（新稿） | X63: 日期码格式：ZURU INC(BVI) 标准格式 日期：按实际生产日期 Packaging Info: 由于韩国法律法规要求，吸塑需PET材质，产品需符合韩国KC测试标准。 9548需出新版 无硼，无MIT防腐剂成分的口水胶， 大货品质需严格跟到上单4500148437一致 9548:MA 1L UPC PKG, +韩语贴纸（新稿）， +客版韩语说明书（新稿）箱唛翻单4500148437 请确保大货包装的生产年月 信息跟到到贴纸上的一致。 生产日信息不做特别要求，可安排统一日期，但必须确保生产年份"2025" 月份"02" Remark: | Y63: Doris Shou | Z63: 7.6157 | AA63: =Z63*I63 -> 15231.4 | AB63: 94407-2.28 | AC63: 9548-S001-NB | AD63: 已入 | AF63: =I63*0.2 -> 400 | AK63: =I63 -> 2000 | AU63: =I63 -> 2000 | BA63: =I63 -> 2000 | BB63: =BB62+BA63 -> 779960
A64: 45643 | B64: MCD BRANDS SAS | C64: 乌拉圭 | D64: 4500153776 | F64: 4500153776-110 | G64: 9548-S001 | H64: 鸭妈妈 | I64: 120 | J64: 0 | K64: 4 | L64: =I64/K64 -> 30 | M64: 45715 | N64: =M64-3 -> 45712 | P64: PASS | R64: 45667 | S64: 无 | T64: 1/13进口商贴纸 | U64: MA | X64: 日期码格式：ZURU INC(BVI) 标准格式 日期：按实际生产日期 Packaging Info: 9548:MA 5L 包装+进口商贴纸+箱唛 Remark: 进口商贴纸请多备料5pcs,出货后需要寄给客户 | Y64: Ava Liang | Z64: 7.6392 | AA64: =Z64*I64 -> 916.704 | AB64: 94577-3.18 | AC64: 9548-S001-5L | AD64: 已入 | AE64: =I64*0.2 -> 24 | AO64: =I64 -> 120 | AS64: =I64 -> 120 | BA64: =I64 -> 120 | BB64: =BB63+BA64 -> 780080
A65: 45660 | B65: THE ENTERTAINER | C65: 英国 | D65: 4500154847 | E65: FB12131 | F65: 4500154847-90 | G65: 9548-S001 | H65: 鸭妈妈 | I65: 900 | J65: 0 | K65: 4 | L65: =I65/K65 -> 225 | M65: 45716 | N65: 45712 | P65: PASS | R65: 45664 | S65: 无 | T65: 条码贴（翻单4500139632）+两国语言说明书 | U65: MA | V65: 产品内包装再加多一张2国语言电池说明书 | X65: 日期码格式：ZURU INC(BVI) 标准格式 日期：按实际生产日期 Packaging Info: 9548: MA-1L（含23L warning）包装配套 ,额外加一张条码贴（翻单4500139632）覆盖ZURU条码 ，另外产品内包装再加多一张2国语言电池说明书 ，即产品内含2张 说明书 （ZURU标准说明书1张+2国语言电池说明书） Remark: *MA版本按工厂现有最新库存即可，订单出英国，请注意检查产品及包装应带UKCA图标，包装显示ZURU UK LTD信息，QC同事请查核，如有问题与跟单确认 *生产日期按实际（法定工作日），按ZURU标准格式即可 ，但是请知悉包装日期码需要早于或者等于外箱日期码 ，不能晚于外箱日期码 *请注意所有订单都需要经过ZURU QC验货并且通过后方可出货 *条码以订单显示为准 ，请安排生产前先核对 ，有问题请提出。 *所有产品按符合欧洲标准走货，需要是不含微塑料版本 。 *涉及到硼的，如可选择情况下应使用低硼版本 （slime 类别低硼一般低于300ppm)，无选择的应与跟单复核再安排 。 *条码以订单显示为准 ，请安排生产前先核对 ，有问题请提出。 *订单对应客户2个PO号 ，备注有显示 ，注意分开做货/验货/装柜 ，混装有罚款。 *样板： 请在1/20前每款寄出2pcs大货样到罗湖办公室 7B Sandy Shao收 | Y65: Sandy Shao | Z65: 7.6175 | AA65: =Z65*I65 -> 6855.75 | AB65: 94436-3.4 | AC65: 9548-S001 | AD65: 已入 | AE65: =I65*0.2 -> 180 | AK65: =I65 -> 900 | AS65: =I65 -> 900 | BA65: =I65 -> 900 | BB65: =BB64+BA65 -> 780980
A66: 45672 | B66: SUCKOT SAC | C66: 秘鲁 | D66: 4500155723 | F66: 4500155723-100 | G66: 9548-S001 | H66: 鸭妈妈 | I66: 500 | J66: 0 | K66: 4 | L66: =I66/K66 -> 125 | M66: 45720 | N66: 45716 | P66: PASS | R66: 45674 | S66: 无 | T66: 1/16进口商贴纸+UPC贴纸 | U66: MA | X66: 日期码格式：ZURU INC(BVI) 标准格式 日期：按实际生产日期 Packaging Info: 9548：MA 多语 EAN包装+UPC贴纸+MA 多语说明书+进口商贴纸+箱唛 Remark: 9548: 3pcs AAA batteries(not included) | Y66: Zoe Luo | Z66: 7.6175 | AA66: =Z66*I66 -> 3808.75 | AB66: 94426-3.4 | AC66: 9548-S001-5L | AD66: 已入 | AE66: =I66*0.2 -> 100 | AO66: =I66 -> 500 | AS66: =I66 -> 500 | BA66: =I66 -> 500 | BB66: =BB65+BA66 -> 781480
A67: 45649 | B67: PPTOYS PTE LTD (SG) | C67: 新加坡 | D67: 4500154572 | E67: ZU24120901SG | F67: 4500154572-10 | G67: 9548-S001 | H67: 鸭妈妈 | I67: 600 | J67: 0 | K67: 4 | L67: =I67/K67 -> 150 | M67: 45723 | N67: 45719 | P67: PASS | R67: 45664 | S67: 无 | T67: 贴纸AW、位置图翻单4500135387+进口商标贴纸 | U67: MA | X67: 日期码格式：ZURU INC(BVI) 标准格式 日期：按实际生产日期 Packaging Info: MA UPC包装（优先1L)+1张进口商贴纸 贴纸AW、位置图翻单如下： 9548-4500135387 所有item的贴纸图稿一模一样，请一起订购节省成本。 Remark: 9548-1 assorment，3pcs AAA batteries(not included) | Y67: Emma Wu | Z67: 7.3075 | AA67: =Z67*I67 -> 4384.5 | AB67: 94491-3.7 | AC67: 9548-S001 | AD67: 已入 | AE67: =I67*0.2 -> 120 | AK67: =I67 -> 600 | AS67: =I67 -> 600 | BA67: =I67 -> 600 | BB67: =BB69+BA67 -> 777456
A68: 45670 | B68: PRO & PACIFIC CO.,LTD | C68: 台湾 | D68: 4500155779 | E68: ZU24122701 | F68: 4500155779-10 | G68: 9548-S001 | H68: 鸭妈妈 | I68: 480 | J68: 0 | K68: 4 | L68: =I68/K68 -> 120 | M68: 45724 | N68: 45720 | P68: PASS | R68: 45671 | S68: 无 | T68: 1/21进口商贴纸 | U68: MA | X68: 日期码格式：ZURU INC(BVI) 标准格式 日期：按实际生产日期 Packaging Info: MA UPC包装（优先1L)+1张进口商贴纸 贴纸AW、位置图待提供 Remark: 9548-1 assorment,3pcs AAA batteries(not included) | Y68: Emma Wu | Z68: 7.3292 | AA68: =Z68*I68 -> 3518.016 | AB68: 94536-3.13 | AC68: 9548-S001 | AD68: 已入 | AE68: =I68*0.2 -> 96 | AK68: =I68 -> 480 | AS68: =I68 -> 480 | BA68: =I68 -> 480 | BB68: =BB67+BA68 -> 777936
A69: 45714 | B69: THE WAREHOUSE LIMITED | C69: 新西兰 | D69: 4500156569 | F69: 4500156569-30 | G69: 9548-S001 | H69: 鸭妈妈 | I69: 64 | J69: 0 | K69: 4 | L69: =I69/K69 -> 16 | M69: 45725 | N69: 45712 | P69: PASS | R69: 无 | S69: 有 | T69: 无 | U69: MA | V69: 需要增加外箱贴纸 | X69: 日期码格式：ZURU INC(BVI) 标准格式 日期：按实际生产日期 Packaging Info: MA UPC 英语包装（优先1L英语版本，或者3L/5L含英语都可） 此客人不接受易掉落或者剥落或者可直接触碰的闪粉，可降解也不行，但可以接受符合欧洲微塑料标准的珠光粉或者闪片。 9548：外箱四个面要加一张大黄贴："ZURU Product for NZ test " Remark:9548： 3PCS AAA BATTERIES(NOT INCLUDED) | Y69: Abby Liang | Z69: 7.6392 | AA69: =Z69*I69 -> 488.9088 | AB69: 94694-4.3 | AC69: 9548-S001 | AD69: 已入 | AE69: =I69*0.2 -> 12.8 | AK69: =I69 -> 64 | AS69: =I69 -> 64 | BA69: =I69 -> 64 | BB69: =BB60+BA69 -> 776856
A70: 45637 | B70: THE WAREHOUSE LIMITED | C70: 新西兰 | D70: 4500153723 | E70: 28659771 | F70: 4500153723-40 | G70: 9548-S001 | H70: 鸭妈妈 | I70: 200 | J70: 0 | K70: 4 | L70: =I70/K70 -> 50 | M70: 45726 | N70: 45722 | P70: PASS | R70: 45638 | S70: 无 | T70: 无 | U70: MA | X70: 日期码格式：ZURU INC(BVI) 标准格式 日期：按实际生产日期 Packaging Info: MA UPC 英语包装（优先1L英语版本，或者3L/5L含英语都可） 此客人不接受易掉落或者剥落或者可直接触碰的闪粉，可降解也不行，但可以接受符合欧洲微塑料标准的珠光粉或者闪片。 Remark: 9548: 3pcs AAA batteries(not included) | Y70: Abby Liang | Z70: 7.6392 | AA70: =Z70*I70 -> 1527.84 | AB70: 94598-3.21 | AC70: 9548-S001 | AD70: 已入 | AE70: =I70*0.2 -> 40 | AK70: =I70 -> 200 | AS70: =I70 -> 200 | BA70: =I70 -> 200 | BB70: =BB86+BA70 -> 780692
A71: 45637 | B71: THE WAREHOUSE LIMITED | C71: 新西兰 | D71: 4500153609 | E71: 28662059 | F71: 4500153609-40 | G71: 9548-S001 | H71: 鸭妈妈 | I71: 600 | J71: 0 | K71: 4 | L71: =I71/K71 -> 150 | M71: 45726 | N71: 45722 | P71: PASS | R71: 45638 | S71: 无 | T71: 无 | U71: MA | X71: 日期码格式：ZURU INC(BVI) 标准格式 日期：按实际生产日期 Packaging Info: MA UPC 英语包装（优先1L英语版本，或者3L/5L含英语都可） 此客人不接受易掉落或者剥落或者可直接触碰的闪粉，可降解也不行，但可以接受符合欧洲微塑料标准的珠光粉或者闪片。 Remark: 9548: 3pcs AAA batteries(not included) | Y71: Abby Liang | Z71: 7.6175 | AA71: =Z71*I71 -> 4570.5 | AB71: 94582-3.19 | AC71: 9548-S001 | AD71: 已入 | AE71: =I71*0.2 -> 120 | AK71: =I71 -> 600 | AS71: =I71 -> 600 | BA71: =I71 -> 600 | BB71: =BB68+BA71 -> 778536
A72: 45712 | D72: ZMPO250136 | G72: 9548-S001 | H72: 鸭妈妈 | I72: 120 | J72: 0 | K72: 4 | L72: =I72/K72 -> 30 | M72: 45726 | N72: 45722 | R72: 45712 | S72: 无 | T72: 无 | U72: MA | X72: Remark：大货最新版本/大货标准箱装箱/箱唛请参照邮件附件；备注： 收到样品订单后尽快安排 ，注意样板品质质量要求要高于大货品质要求 ，送货时必须要附带送货单(没有送货单和QC检验合格报告的仓库一律拒绝收货)，请知悉，谢谢！ | Y72: Angus | AC72: 9548-S001-5L | AD72: 已入 | AE72: =I72*0.2 -> 24 | AO72: =I72 -> 120 | AS72: =I72 -> 120 | BA72: =I72 -> 120 | BB72: =BB47+BA72 -> 754320
A73: 45674 | B73: ZURU Germany GMBH | C73: 德国 | D73: 4500156082 | E73: 5200006028 | F73: 4500156082-80 | G73: 9548-S005-NB-MTS | H73: 鸭妈妈 | I73: 402 | J73: 0 | K73: 3 | L73: =I73/K73 -> 134 | M73: 45729 | N73: 45726 | P73: PASS | R73: 45679 | S73: 无 | T73: 无 | U73: MA | V73: 2/10 PL/HU/SK/CZ/RO收藏指南黑白书纸 | X73: 日期码格式：ZURU INC(BVI) 标准格式 日期：按实际生产日期 Packaging Info: 9548:MA最新版5L+23L Warning EAN包装+MA最新版5L收藏指南+PL/HU/SK/CZ/RO收藏指南黑白书纸+MA最新版5L复合袋+MA最新版2L布标; Remark: 1.波兰内销单，需要通过ZURU 验货结果后才能出货 (工厂需要主动提前同ZURU QC预约验货避免延期出货造成不必要麻烦)； 2. 若有特定款有特殊外箱条码要求时,需要明确列出产品款对应的具体外箱条码号码/条码类型 (若无,可以忽略此需求) 3.所有出口欧洲的产品, 法规规定禁止在包装和共公众用的印刷品中使用矿物油中含有的物质, 包装印刷油墨中含有的MOAH/MOSH的质量浓度不能超过1%, 否则出货 到法国被抽检出现问题, 供应商需要对此负责; 4. date code: 外箱日期码要晚于或等于产品日期码，不能早于产品的日期码 5. 所有电子产品身上需要加字唛，为ZURU FRANCE 地址 (如无电子产品，或者产品布标有此地址，可忽略此信息) ZURU France 1/3, Rue d'Argenteuil 95210 SAINT-GRATIEN, FRANCE 6. 装柜时需要按照款式号码从小到大一款款依次装,避免终端仓库卸货混乱.若一个柜子涉及到几个不同国家内销单,装柜时需要一个国家装完后再装另一个国家的 产品,依次装柜,避免终端仓库因不同国家不同库位位置卸货混乱. (此点需要同工厂装柜人员强调) | Y73: SD82 | Z73: 7.5194 | AA73: =Z73*I73 -> 3022.7988 | AB73: 94597-3.21 | AC73: 9548-S005-NB-MTS | AD73: 已入 | AE73: =I73*0.2 -> 80.4 | AF73: =I73 -> 402 | AO73: =I73 -> 402 | AS73: =I73 -> 402 | BA73: =I73 -> 402 | BB73: =BB79+BA73 -> 782254
A74: 45681 | B74: I-VISION TOYS.INC | C74: 韩国 | D74: 4500156431 | E74: IVI-0117MM | F74: 4500156431-10 | G74: 9548-S001-NB | H74: 鸭妈妈 | I74: 2880 | J74: 0 | K74: 4 | L74: =I74/K74 -> 720 | M74: 45729 | N74: 45726 | P74: PASS | R74: 箱唛翻单4500148437 | S74: 无 | T74: 2/8韩语贴纸（新稿）， | U74: MA | V74: 客版韩语说明书翻单4500148437 | X74: 日期码格式：ZURU INC(BVI) 标准格式 日期：按实际生产日期 Packaging Info: 9548:MA 1L UPC PKG, +韩语贴纸（新稿）， +客版韩语说明书和箱唛翻单4500148437 请确保大货包装的生产年月 信息跟到到贴纸上的一致。生产年份"2025" 月份"03" 谢谢！ Remark: 由于韩国法律法规要求，吸塑需PET材质，产品需符合韩国KC测试标准。 9548需出新版 无硼，无MIT防腐剂成分的口水胶， 大货品质需严格跟到测试办一致 | Y74: Doris Shou | Z74: 7.2852 | AA74: =Z74*I74 -> 20981.376 | AB74: 94552-3.14 | AC74: 9548-S001-NB | AD74: 已入 | AF74: =I74 -> 2880 | AK74: =I74 -> 2880 | AU74: =I74 -> 2880 | BA74: =I74 -> 2880 | BB74: =BB80+BA74 -> 783312
A75: 45677 | B75: Bol.com | C75: 新西兰 | D75: 4500156115 | E75: 7631985 | F75: 4500156115-370 | G75: 9548-S001 | H75: 鸭妈妈 | I75: 800 | J75: 0 | K75: 4 | L75: =I75/K75 -> 200 | M75: 45730 | N75: 45726 | P75: PASS | R75: 45678 | S75: 无 | T75: 无 | U75: MA | X75: 日期码格式：ZURU INC(BVI) 标准格式 日期：按实际生产日期 Packaging Info: BOL NL(9548) 12. 9548：4 PCS/CTN, With Boron Slime ;magnet(inside in the body of baby duck), 3PCS AAA BATTERIES(NOT INCLUDED), one assortment; MA 5L(23L warn ing EAN)C彩盒+MA 5L(9L warning)B说明书+MA 5L(5L warning) B Slime胶袋+MA 2L C布标 13. 验货时间不迟于2025/3/17. Remark: 1. 出欧洲产品不可含闪粉或者微塑料，若所涉产品无闪粉或不含微塑料可忽略此点； 2. 5 Surprise or Mini Brands涉及包装是2个及2个以上的球入PVC桶包装时，单个球上若有UPC#或者EAN#，请用白色贴纸覆盖住； 3. 箱唛资料按照提供的要求去做即可，无需再发回我方确认； 4.柜货产品务必拉网且要拉紧，拉网要求： A: 网要结实同时网格要细，纸箱不能从网格处跌落下来 B: 打网固定8-10个点。请提供拉网的装柜照片给船务确认 后柜子再离厂。" | Y75: Crystal Chen | Z75: 7.3075 | AA75: =Z75*I75 -> 5846 | AB75: 94548-3.14 | AC75: 9548-S001-5L | AD75: 已入 | AE75: =I75*0.2 -> 160 | AO75: =I75 -> 800 | AS75: =I75 -> 800 | BA75: =I75 -> 800 | BB75: =BB73+BA75 -> 783054
A76: 45680 | B76: MEIJER | C76: 美国 | D76: 4500156523 | E76: 客户PO 216819044 | F76: 4500156523-10 | G76: 9548-S002 | H76: 鸭妈妈 | I76: 780 | J76: 0 | K76: 1 | L76: =I76/K76 -> 780 | M76: 45730 | N76: 45726 | P76: PASS | R76: 45700 | S76: 无 | T76: 无 | U76: MA | X76: 日期码格式：ZURU INC(BVI) 标准格式 日期：按实际生产日期 Packaging Info: 1. MA 1L 包装 2. 客人指定箱唛排版 Remark: 出货前 Zuru QC 验货 | Y76: Sophia Zhou | Z76: 7.3479 | AA76: =Z76*I76 -> 5731.362 | AB76: ZB00001-3.18 | AC76: 9548-S002 | AD76: 已入 | AE76: =I76*0.2 -> 156 | AK76: =I76 -> 780 | AS76: =I76 -> 780 | BA76: =I76 -> 780 | BB76: =BB69+BA76 -> 777636
A77: 45680 | B77: MEIJER | C77: 美国 | D77: 4500156523 | E77: 客户PO 216819045 | F77: 4500156523-20 | G77: 9548-S002 | H77: 鸭妈妈 | I77: 420 | J77: 0 | K77: 1 | L77: =I77/K77 -> 420 | M77: 45730 | N77: 45726 | P77: PASS | R77: 45700 | S77: 无 | T77: 无 | U77: MA | X77: 日期码格式：ZURU INC(BVI) 标准格式 日期：按实际生产日期 Packaging Info: 1. MA 1L 包装 2. 客人指定箱唛排版 Remark: 出货前 Zuru QC 验货 | Y77: Sophia Zhou | Z77: 7.3696 | AA77: =Z77*I77 -> 3095.232 | AB77: ZB00001-3.18 | AC77: 9548-S002 | AD77: 已入 | AE77: =I77*0.2 -> 84 | AK77: =I77 -> 420 | AS77: =I77 -> 420 | BA77: =I77 -> 420 | BB77: =BB70+BA77 -> 781112
A78: 45698 | B78: ZURU LLC | C78: 美国 | D78: 4500157072 | E78: 5200006121 | F78: 4500157072-10 | G78: 9548-S001-MTS | H78: 鸭妈妈 | I78: 1500 | J78: 0 | K78: 4 | L78: =I78/K78 -> 375 | M78: 45730 | N78: 45726 | P78: PASS | R78: 45698 | S78: 无 | T78: 无 | U78: MA | X78: 日期码格式：ZURU INC(BVI) 标准格式 日期：按实际生产日期 Packaging Info: #9548 MA 1L UPC版本，出口美国。 Remark: 1.Amazon domestic 订单。出口美国。外箱最长边不能超过25" （超过了，case pack只能为1），不符合要求的大货，一律不接受。 2.无第三方验货/测试要求。 3.日期码使用ZURU标准版本。 | Y78: SD24 | Z78: 7.6175 | AA78: =Z78*I78 -> 11426.25 | AB78: ZB00055 | AC78: 9548-S001 | AD78: 已入 | AE78: =I78*0.2 -> 300 | AK78: =I78 -> 1500 | AS78: =I78 -> 1500 | BA78: =I78 -> 1500 | BB78: =BB76+BA78 -> 779136
A79: 45681 | B79: ARGOS LIMITED | C79: 英国 | D79: 4500156552 | E79: 137086 | F79: 4500156552-10 | G79: 9548-S001 | H79: 鸭妈妈 | I79: 2000 | J79: 0 | K79: 4 | L79: =I79/K79 -> 500 | M79: 45735 | N79: 45731 | P79: PASS | R79: 45694 | S79: 无 | T79: 2/14客人白色Cat.label 1张覆盖ZURU条码 | U79: MA | X79: 日期码格式：ZURU INC(BVI) 标准格式 日期：按实际生产日期 Packaging Info: 1. MA 1L UPC包装+客人白色Cat.label 1张覆盖ZURU条码 注意Cat.label (要求易撕类贴纸，但是粘性不能过低），同时此贴纸每个订单都是不相同的(会显示客户对应的订单号），切勿翻旧订单购买，该贴纸由工厂自行 购买。 Remark: *MA包装按最新版本安排即可 *包装日期码按ZURU格式即可，请确保不迟于外箱日期码，可等于或者早于外箱日期码，必须为法定工作日。 *外箱尺寸任何一条边长度超过75cm或者每箱重量超过10KG,需要在外箱上加三脚架符号，有问题请与ZURU跟单同事核实。 *订单必须经过ZURU QC验货并且通过后方可出货。 *订单出英国，请注意检查产品及包装应带UKCA图标，包装显示ZURU UK LTD信息，QC同事请查核，如有问题与跟单确认。 *条码扫描会显示客户7位数产品号 ，忽略订单显示的MA条码 *所有产品按符合欧洲标准走货，微塑料需合规。 *涉及到硼的，需要符合欧洲标准 *客户不接受PVC材质包装 | Y79: Sheba Ye | Z79: 7.2852 | AA79: =Z79*I79 -> 14570.4 | AB79: 94615-3.24 | AC79: 9548-S001 | AD79: 已入 | AE79: =I79*0.2 -> 400 | AK79: =I79 -> 2000 | AS79: =I79 -> 2000 | BA79: =I79 -> 2000 | BB79: =BB90+BA79 -> 781852
A80: 45694 | B80: ZETA | C80: 阿塞拜疆 | D80: 4500156829 | F80: 4500156829-10 | G80: 9548-S001 | H80: 鸭妈妈 | I80: 120 | J80: 0 | K80: 4 | L80: =I80/K80 -> 30 | M80: 45736 | N80: 45733 | P80: PASS | R80: 45698 | S80: 无 | T80: 无 | U80: MA | X80: 日期码格式：ZURU INC(BVI) 标准格式 日期：按实际生产日期 Packaging Info: 1. 无进口商贴纸 2. 1L MA 包装/PDQ Remark: 标准配比 | Y80: Ann Zhang | Z80: 7.3292 | AA80: =Z80*I80 -> 879.504 | AC80: 9548-S001 | AD80: 已入 | AE80: =I80*0.2 -> 24 | AK80: =I80 -> 120 | AS80: =I80 -> 120 | BA80: =I80 -> 120 | BB80: =BB91+BA80 -> 780432
A81: 45693 | B81: Fun Time Enterprises Incorporated | C81: 菲律宾 | D81: 4500156746 | E81: ZUR-F250103-02 | F81: 4500156746-10 | G81: 9548-S001 | H81: 鸭妈妈 | I81: 504 | J81: 0 | K81: 4 | L81: =I81/K81 -> 126 | M81: 45737 | N81: 45733 | P81: PASS | R81: 45694 | S81: 无 | T81: 无 | U81: MA | X81: 日期码格式：ZURU INC(BVI) 标准格式 日期：按实际生产日期 Packaging Info: MA 1L PKG Remark: | Y81: Doris Shou | Z81: 7.6175 | AA81: =Z81*I81 -> 3839.22 | AB81: 94642-3.26 | AC81: 9548-S001 | AD81: 已入 | AE81: =I81*0.2 -> 100.8 | AK81: =I81 -> 504 | AS81: =I81 -> 504 | BA81: =I81 -> 504 | BB81: =BB68+BA81 -> 778440
A82: 45695 | B82: ANVOL LTD. | C82: 爱沙尼亚 | D82: 4500156940 | F82: 4500156940-20 | G82: 9548-S001 | H82: 鸭妈妈 | I82: 360 | J82: 0 | K82: 4 | L82: =I82/K82 -> 90 | M82: 45737 | N82: 45733 | P82: PASS | R82: 45695 | S82: 无 | T82: 进口商贴纸 | U82: MA | X82: 日期码格式：ZURU INC(BVI) 标准格式 日期：按实际生产日期 Packaging Info: 9548：B 版1L MA 包装+进口商贴纸；B 版 5L MA 收藏指南 Remark: 9548: 3PCS AAA BATTERIES(NOT INCLUDED) 1、若产品有比例使用ZURU STD 比例 2、所有item 均用MA UPC 条码，若包装不是UPC 条码的请告知 3、此单出欧洲需满足EU测试标准要求 | Y82: Snowy | Z82: 7.6392 | AA82: =Z82*I82 -> 2750.112 | AB82: 94626-3.24 | AC82: 9548-S001 | AD82: 已入 | AE82: =I82*0.2 -> 72 | AK82: =I82 -> 360 | AS82: =I82 -> 360 | BA82: =I82 -> 360 | BB82: =BB69+BA82 -> 777216
A83: 45698 | B83: Ambiental Paraguay | C83: 巴拉圭 | D83: 4500156544 | F83: 4500156544-50 | G83: 9548-S001 | H83: 鸭妈妈 | I83: 500 | J83: 0 | K83: 4 | L83: =I83/K83 -> 125 | M83: 45737 | N83: 45733 | P83: PASS | R83: 45698 | S83: 无 | T83: 2/20进口商贴纸（进口商贴纸+UPC贴纸合并为一张） | U83: MA | X83: 日期码格式：ZURU INC(BVI) 标准格式 日期：按实际生产日期 Packaging Info: 9548:MA 3L EAN包装+进口商贴纸（进口商贴纸+UPC贴纸合并为一张）+箱唛 Remark: | Y83: Ava Liang | Z83: 7.6175 | AA83: =Z83*I83 -> 3808.75 | AB83: 94726-4.8 | AC83: 9548-S001-5L | AD83: 已入 | AE83: =I83*0.2 -> 100 | AO83: =I83 -> 500 | AS83: =I83 -> 500 | BA83: =I83 -> 500 | BB83: =BB81+BA83 -> 778940
A84: 45714 | B84: WAL-MART CANADA CORP. | C84: 加拿大 | D84: 4500158644 | E84: 9900922889 | F84: 4500158644-20 | G84: 9548-S002-NB | H84: 鸭妈妈 | I84: 1200 | J84: 0 | K84: 1 | L84: =I84/K84 -> 1200 | M84: 45744 | N84: 45740 | P84: PASS | R84: 45715 | S84: 无 | T84: UPC贴纸翻单: 4500126662 | U84: MA | X84: 日期码格式：ZURU INC(BVI) 标准格式 日期：按实际生产日期 Packaging Info: #9548: MA5L彩盒+UPC条码贴纸 (UPC:193052064196)+MA5L说明书+MA5L复合袋+MA2L布标 (UPC贴纸翻单: 4500126662) Remark: 1. 此单有箱唛； 2. 此单有第三方验货，烦请多备包装物料； 3. #9548 须使用无硼版本的slime; 4. #9548需于2025/3/28安排抽办测试，抽办数量：大货5pcs+散件4 sets； 5. 必须在原来错误的EAN条码上用黑色粗头笔涂黑直至不能扫描，再贴上正确的UPC; ********************* a. 请确保产品符合1999年版本的加拿大环境保护法(CEPA)和2012年禁止某些有毒物质法规的要求。该产品不含任何在加拿大禁用的化学物质，包括但不限于有毒物 质清单中列出的化学物质，并且在为加拿大沃尔玛生产产品期间没有使用任何禁用化学物质。 Supplier certify that the products comply with the requirements of Canadian Environmental Protection Act, 1999 (CEPA), Prohibition of Certain To xic Substances Regulations, 2012. The products do not contain any chemicals that are banned in Canada, including but not limited to those listed in the Toxic Substances List and no banned chemicals were used during the manufacturing of product for Walmart Canada. 附件列表： (1) Letter of Guarantee for Canada banned chemicals - (1-5CA) b. 请确保产品在均质材料中的汞浓度不超过0.1%（按重量计）。 Supplier certify that the WAL-MART vendor products does not have a mercury concentration of more than 0.1% by weight in homogeneous material. 附件列表： (1) Letter of Guarantee for Mercury COC c. 请确保产品的塑料材料不含以下物质（SOR 2011-17 27B): Supplier certify that the plastic materials do not contain the following substances(SOR 2011-17 27B): (a) carbon tetrachloride or any substance that contains it; (b) methyl alcohol or any substance thay contains >1.0%; (c) petroleum distillates or any substance that contains >10% weight to volume of petroleum distillates; (d) benzene; (e) turpentine or any substance that contains >10% weight to volume of turpentine; (f) boric acid or salts of boric acid; or (g) ethyl ether. 附件列表： (1) Letter of Guarantee for WM CA-Other prohibited substances in plastic(less than 3 years) | Y84: Monica Zhou | Z84: 7.6459 | AA84: =Z84*I84 -> 9175.08 | AB84: 94653-3.27 | AC84: 9548-S002-NB-5L | AD84: 已入 | AF84: =I84 -> 1200 | AO84: =I84 -> 1200 | AS84: =I84 -> 1200 | BA84: =I84 -> 1200 | BB84: =BB95+BA84 -> 779692
A85: 45712 | B85: IMPORTADORA CHICOCOS | C85: 玻利维亚 | D85: 4500158356 | F85: 4500158356-90 | G85: 9548-S001 | H85: 鸭妈妈 | I85: 120 | J85: 0 | K85: 4 | L85: =I85/K85 -> 30 | M85: 45744 | N85: 45740 | P85: PASS | R85: 45714 | S85: 无 | T85: 3/4UPC贴纸 | U85: MA | X85: 日期码格式：ZURU INC(BVI) 标准格式 日期：按实际生产日期 Packaging Info: 9548; MA 3L EAN包装+UPC贴纸+MA多语收藏指南+箱唛 Remark: 9548: 3PCS AAA BATTERIES(NOT INCLUDED) | Y85: Ava Liang | Z85: 7.6392 | AA85: =Z85*I85 -> 916.704 | AB85: 94687-4.1 | AC85: 9548-S001-5L | AD85: 已入 | AE85: =I85*0.2 -> 24 | AO85: =I85 -> 120 | AS85: =I85 -> 120 | BA85: =I85 -> 120 | BB85: =BB92+BA85 -> 780324
A86: 45701 | B86: TJX COMPANIES, INC | C86: 美国 | D86: 4500157304 | E86: TJ MAXX DC#891-152PCS , DC#894-92PCS, DC#896-52PCS, DC#897-76PCS, DC#898-428PCS | F86: 4500157304-10 | G86: 9548-S001 | H86: 鸭妈妈 | I86: 800 | J86: 0 | K86: 4 | L86: =I86/K86 -> 200 | M86: 45747 | N86: 45743 | P86: PASS | R86: 45701 | S86: 无 | T86: 3/6客供价格贴纸 | U86: MA | X86: 日期码格式：ZURU INC(BVI) 标准格式 日期：按实际生产日期 Packaging Info: MA UPC包装+价格贴纸，价格贴纸客供。 Remark: 1. 产品和包装上印刷tracking code信息，格式为ZURU常规格式。 2. 分4-5个DC出货，每款产品每个DC的箱唛资料不同。具体分DC数量，请参考后面行项目备注。 3. ZURU QC验货。 | Y86: Emily Wu | Z86: 7.3075 | AA86: =Z86*I86 -> 5846 | AB86: ZB00095-4.2 ZB00115-4.9 ZB00120-4.10 | AC86: 9548-S001 | AD86: 已入 | AE86: =I86*0.2 -> 160 | AK86: =I86 -> 800 | AS86: =I86 -> 800 | BA86: =I86 -> 800 | BB86: =BB84+BA86 -> 780492
A87: 45701 | B87: TJX COMPANIES, INC | C87: 美国 | D87: 4500157303 | E87: Marshalls DC#881-128PCS , DC#884-96PCS, DC#886-140PCS , DC#887-116PCS , DC#888-120PCS | F87: 4500157303-10 | G87: 9548-S001 | H87: 鸭妈妈 | I87: 600 | J87: 0 | K87: 4 | L87: =I87/K87 -> 150 | M87: 45747 | N87: 45743 | P87: PASS | R87: 45701 | S87: 无 | T87: 3/4客供价格贴纸 | U87: MA | X87: 日期码格式：ZURU INC(BVI) 标准格式 日期：按实际生产日期 Packaging Info: MA UPC包装+价格贴纸，价格贴纸客供。 Remark: 1. 产品和包装上印刷tracking code信息，格式为ZURU常规格式。 2. 分5个DC出货，每款产品每个DC的箱唛资料不同。具体分DC数量，请参考后面行项目备注。 3. ZURU QC验货。 | Y87: Emily Wu | Z87: 7.3075 | AA87: =Z87*I87 -> 4384.5 | AB87: ZB00087-4.1 ZB00094-4.2 ZB00114-4.9 ZB00121-4.10 | AC87: 9548-S001 | AD87: 已入 | AE87: =I87*0.2 -> 120 | AK87: =I87 -> 600 | AS87: =I87 -> 600 | BA87: =I87 -> 600 | BB87: =BB94+BA87 -> 783904
A88: 45666 | B88: THE ENTERTAINER | C88: 英国 | D88: 4500155272 | E88: FB12159 | F88: 4500155272-30 | G88: 9548-S001 | H88: 鸭妈妈 | I88: 700 | J88: 0 | K88: 4 | L88: =I88/K88 -> 175 | M88: 45747 | N88: 45743 | P88: PASS | R88: 45666 | S88: 无 | T88: 条码贴（翻单4500139632）+两国语言说明书 | U88: MA | V88: 产品内包装再加多一张2国语言电池说明书 | X88: 日期码格式：ZURU INC(BVI) 标准格式 日期：按实际生产日期 Packaging Info: 9548: MA-1L（含23L warning）包装配套 ,额外加一张条码贴（翻单4500139632）覆盖ZURU条码 ，另外产品内包装再加多一张2国语言电池说明书 ，即产品内含2张说明书 （ZURU标准说明书1张+2国语言电池说明书）" Remark: *MA版本按工厂现有最新库存即可，订单出英国，请注意检查产品及包装应带UKCA图标，包装显示ZURU UK LTD信息，QC同事请查核，如有问题与跟单确认 *生产日期按实际（法定工作日），按ZURU标准格式即可 ，但是请知悉包装日期码需要早于或者等于外箱日期码 ，不能晚于外箱日期码 *请注意所有订单都需要经过ZURU QC验货并且通过后方可出货 *条码以订单显示为准 ，请安排生产前先核对 ，有问题请提出。 *所有产品按符合欧洲标准走货，需要是不含微塑料版本 。 *涉及到硼的，如可选择情况下应使用低硼版本 （slime 类别低硼一般低于300ppm)，无选择的应与跟单复核再安排 。 *条码以订单显示为准 ，请安排生产前先核对 ，有问题请提出。 * 大货样： 每个item 请在2/25 之前寄出2pcs 样板+1套散件到罗湖办公室7A Sandy Shao 收 | Y88: Sandy Shao | Z88: 7.6175 | AA88: =Z88*I88 -> 5332.25 | AB88: 94684-4.1 | AC88: 9548-S001 | AD88: 已入 | AE88: =I88*0.2 -> 140 | AK88: =I88 -> 700 | AS88: =I88 -> 700 | BA88: =I88 -> 700 | BB88: =BB77+BA88 -> 781812
A89: 45709 | B89: KMART AUSTRALIA LTD(NEW ZEALAND) | C89: 新西兰 | D89: 4500158157 | E89: 20650321 | F89: 4500158157-40 | G89: 9548-S001 | H89: 鸭妈妈 | I89: 88 | J89: 0 | K89: 4 | L89: =I89/K89 -> 22 | M89: 45747 | N89: 45743 | P89: PASS | R89: 45709 | S89: 有 | T89: 1张防盗贴纸 (贴纸以及位置图翻单PO#4500126567）+外箱SSCC Label | U89: MA | X89: 日期码格式：ZURU INC(BVI) 标准格式 日期：按实际生产日期 Packaging Info: 9548: MA英语UPC版本包装（收缩膜和说明书, MA首选1L，如无1L可用多语且含英语的配套多语包装) + 1张防盗贴纸 (贴纸以及位置图翻单PO#4500126567）+ 箱唛 + 外箱SSCC Label Remark: 1.请务必按时完货，验货。并且按期送货入货代指定仓库，如果晚了导致船期Delay将会有罚金产生或者客户要求空运，所产生的罚金和空运费由工厂承担。 2.SSCC 外箱贴纸请同纸箱瓦楞纸方向（竖纹向）垂直，即外箱贴纸横着贴(注意条码不要被胶带粘住），贴1pc，贴1面正唛，封箱胶纸不能挡住贴纸内容。外箱贴纸 离外箱边距离不少于2cm。 3.外箱材质为ZURU标准； 4.此单需使用KMART封箱胶上下工字型封箱;从2019年6月开始，要用KMART 新版封箱胶带，此单要用"ANKO"封箱胶带 5.此单出口新西兰，请按相应的澳新标准生产； 6.产品和包装上生产批号的显示格式ZURU标准日期码格式 7.外箱信息不可手写，重量和体积需要与实际的一致(不可手写） 8. 每款item装箱后的G.W.超过10KG或者CBM超过0.13,(9.5KG或者以上，四舍五入后也属于10KG) 需在外箱上加印超 重或者Bulky LOGO，若发现我们资料没有，请 帮忙提醒 1)重量超过10kg但不超过16kg且CBM不超过0.13,10-16kg 超重logo 2）CBM超过0.13且重量少于17kg，bulky logo 3）不属于以上两种情况，需要使用相应重量范围内的超重logo 4）超重logo需要在外箱四面都印刷(箱唛右上角，两面侧唛超重logo需要尽量靠近毛重)，尺寸为:110mm height* 95mm width 9. 实际外箱重量跟印在箱唛上的数据差异不能超3%，尺寸按实际数据印刷 | Y89: Lydia Wu | Z89: 8.2974 | AA89: =Z89*I89 -> 730.1712 | AB89: 94692-4.2 | AC89: 9548-S001 | AD89: 已入 | AE89: =I89*0.2 -> 17.6 | AK89: =I89 -> 88 | AS89: =I89 -> 88 | BA89: =I89 -> 88 | BB89: =BB80+BA89 -> 780520
A90: 45709 | B90: KMART AUSTRALIA LTD | C90: 澳大利亚 | D90: 4500158156 | E90: 20650320 | F90: 4500158156-40 | G90: 9548-S001 | H90: 鸭妈妈 | I90: 1412 | J90: 0 | K90: 4 | L90: =I90/K90 -> 353 | M90: 45747 | N90: 45743 | P90: PASS | R90: 45709 | S90: 有 | T90: 1张防盗贴纸 (贴纸以及位置图翻单PO#4500126567）+外箱SSCC Label | U90: MA | X90: 日期码格式：ZURU INC(BVI) 标准格式 日期：按实际生产日期 Packaging Info: 9548: MA英语UPC版本包装（收缩膜和说明书, MA首选1L，如无1L可用多语且含英语的配套多语包装) + 1张防盗贴纸 (贴纸以及位置图翻单PO#4500126567）+ 箱唛 + 外箱SSCC Label Remark: 1.请务必按时完货，验货。并且按期送货入货代指定仓库，如果晚了导致船期Delay将会有罚金产生或者客户要求空运，所产生的罚金和空运费由工厂承担。 2.SSCC 外箱贴纸请同纸箱瓦楞纸方向（竖纹向）垂直，即外箱贴纸横着贴(注意条码不要被胶带粘住），贴1pc，贴1面正唛，封箱胶纸不能挡住贴纸内容。外箱贴纸 离外箱边距离不少于2cm。 3.外箱材质为ZURU标准； 4.此单需使用KMART封箱胶上下工字型封箱;从2019年6月开始，要用KMART 新版封箱胶带，此单要用"ANKO"封箱胶带 5.此单出口澳大利亚，请按相应的澳新标准生产； 6.产品和包装上生产批号的显示格式ZURU标准日期码格式 7.外箱信息不可手写，重量和体积需要与实际的一致(不可手写） 8. 每款item装箱后的G.W.超过10KG或者CBM超过0.13,(9.5KG或者以上，四舍五入后也属于10KG) 需在外箱上加印超 重或者Bulky LOGO，若发现我们资料没有，请 帮忙提醒 1)重量超过10kg但不超过16kg且CBM不超过0.13,10-16kg 超重logo 2）CBM超过0.13且重量少于17kg，bulky logo 3）不属于以上两种情况，需要使用相应重量范围内的超重logo 4）超重logo需要在外箱四面都印刷(箱唛右上角，两面侧唛超重logo需要尽量靠近毛重)，尺寸为:110mm height* 95mm width 9. 实际外箱重量跟印在箱唛上的数据差异不能超3%，尺寸按实际数据印刷 | Y90: Lydia Wu | Z90: 8.2757 | AA90: =Z90*I90 -> 11685.288 | AB90: 94691-4.2 | AC90: 9548-S001 | AD90: 已入 | AE90: =I90*0.2 -> 282.4 | AK90: =I90 -> 1412 | AS90: =I90 -> 1412 | BA90: =I90 -> 1412 | BB90: =BB81+BA90 -> 779852
A91: 45611 | B91: DM LLC | C91: 俄罗斯联邦 | D91: 4500151398 | E91: 出Ural | F91: 4500151398-70 | G91: 9548-S001 | H91: 鸭妈妈 | I91: 1372 | J91: 0 | K91: 4 | L91: =I91/K91 -> 343 | M91: 45750 | N91: 45747 | P91: PASS | R91: 45615 | S91: 无 | T91: 11/25进口商贴纸+ EAN条码贴纸 | U91: MA | W91: 外包装(指: 收缩膜/彩卡/吊牌/PDQ)/外箱不要打ZURU标准日期码！ | X91: 日期码格式：外包装/外箱不要打ZURU标准日期码 日期：按实际生产日期 Packaging Info: 注意 ：外包装 (指: 收缩膜/彩卡/铝箔袋/挂卡/PDQ) /外箱不要打ZURU标准日期码！胶件可以打日期码。 9548 : 1L MA 收缩膜 or 彩卡 + 进口商贴纸+ EAN条码贴纸，MA 指南 /说明书（如有）； Remark: 标准配比 出BEKASOVO 2 和Ural 2 个港口； 货期不可延， 有罚金 。 Order | Y91: Ann Zhang | Z91: 7.3097 | AA91: =Z91*I91 -> 10028.908 | AB91: 94894-4.30 | AC91: 9548-S001 | AD91: 已入 | AE91: 274.4 | AK91: =I91 -> 1372 | AS91: =I91 -> 1372 | BA91: =I91 -> 1372 | BB91: =BB83+BA91 -> 780312
A92: 45611 | B92: DM LLC | C92: 俄罗斯联邦 | D92: 4500151398 | E92: 出Ural | F92: 4500151398-150 | G92: 9548-S001 | H92: 鸭妈妈 | I92: 512 | J92: 0 | K92: 4 | L92: =I92/K92 -> 128 | M92: 45750 | N92: 45747 | P92: PASS | R92: 45615 | S92: 无 | T92: 11/25进口商贴纸+ EAN条码贴纸 | U92: MA | W92: 外包装(指: 收缩膜/彩卡/吊牌/PDQ)/外箱不要打ZURU标准日期码！ | X92: 日期码格式：外包装/外箱不要打ZURU标准日期码 日期：按实际生产日期 Packaging Info: 注意 ：外包装 (指: 收缩膜/彩卡/铝箔袋/挂卡/PDQ) /外箱不要打ZURU标准日期码！胶件可以打日期码。 9548 : 1L MA 收缩膜 or 彩卡 + 进口商贴纸+ EAN条码贴纸，MA 指南 /说明书（如有）； Remark: 标准配比 出BEKASOVO 2 和Ural 2 个港口； 货期不可延， 有罚金 。 Order | Y92: Ann Zhang | Z92: 7.3096 | AA92: =Z92*I92 -> 3742.5152 | AB92: 94894-4.30 | AC92: 9548-S001 | AD92: 已入 | AE92: 102.4 | AK92: =I92 -> 512 | AS92: =I92 -> 512 | BA92: =I92 -> 512 | BB92: =BB84+BA92 -> 780204
A93: 45708 | B93: DIAMANT TOYS LTD | C93: 以色列 | D93: 4500153742 | E93: 56053 | F93: 4500153742-30 | G93: 9548-S001 | H93: 鸭妈妈 | I93: 752 | J93: 0 | K93: 4 | L93: =I93/K93 -> 188 | M93: 45761 | N93: 45757 | P93: PASS | R93: 45708 | S93: 无 | T93: 进口商贴纸翻4500144128+彩色贴纸翻4500144128 | U93: MA | X93: 日期码格式：ZURU INC(BVI) 标准格式 日期：按实际生产日期 Packaging Info: 9548：1L MA包装+进口商贴纸翻4500144128+彩色贴纸翻4500144128; MA说明书 Remark: | Y93: Lena Huang | Z93: 7.6175 | AA93: =Z93*I93 -> 5728.36 | AB93: 94787-4.27 | AC93: 9548-S001 | AD93: 已入 | AE93: =I93*0.2 -> 150.4 | AK93: =I93 -> 752 | AS93: =I93 -> 752 | BA93: =I93 -> 752 | BB93: =BB90+BA93 -> 780604
A94: 45726 | B94: ZURU LLC | C94: 美国 | D94: 4500159706 | E94: 5200006347 | F94: 4500159706-20 | G94: 9548-S001-MTS | H94: 鸭妈妈 | I94: 2700 | J94: 0 | K94: 4 | L94: =I94/K94 -> 675 | M94: 45761 | N94: 45757 | P94: PASS | R94: 45727 | S94: 无 | T94: 无 | U94: MA | X94: 日期码格式：ZURU INC(BVI) 标准格式 日期：按实际生产日期 Packaging Info: #9548 MA 1L UPC版本，出口美国。 Remark: 1.Amazon domestic 订单。出口美国。外箱最长边不能超过25" （超过了，case pack只能为1），不符合要求的大货，一律不接受。 2.无第三方验货/测试要求。 3.日期码使用ZURU标准版本。 | Y94: Kelly Shen/Mia Pan/P | Z94: 7.1344 | AA94: =Z94*I94 -> 19262.88 | AB94: ZB00142-4.16 | AC94: 9548-S001 | AD94: 已入 | AE94: =I94*0.2 -> 540 | AK94: =I94 -> 2700 | AS94: =I94 -> 2700 | BA94: =I94 -> 2700 | BB94: =BB93+BA94 -> 783304
A95: 45714 | B95: Walmart Central America-GT | C95: 危地马拉 | D95: 4500158447 | F95: 4500158447-60 | G95: 9548-S001 | H95: 鸭妈妈 | I95: 52 | J95: 0 | K95: 4 | L95: =I95/K95 -> 13 | M95: 45763 | N95: 45759 | P95: PASS | R95: 45740 | S95: 无 | T95: UPC贴纸+进口商贴纸贴纸翻单PO4500158302 | U95: MA | X95: 日期码格式：ZURU INC(BVI) 标准格式 日期：按实际生产日期 Packaging Info: 4. 9548：MA 5L EAN包装+UPC贴纸+MA 多语说明书+进口商贴纸+箱唛 以上所有贴纸翻单PO4500158302 Remark: 1.使用双坑外箱 2.请注意产品包装条形码必须是UPC 3.无第三方验货 | Y95: Ever Li | Z95: 7.6392 | AA95: =Z95*I95 -> 397.2384 | AB95: 94923-5.5 | AC95: 9548-S001-5L | AD95: 已入 | AE95: =I95*0.2 -> 10.4 | AO95: =I95 -> 52 | AS95: =I95 -> 52 | BA95: =I95 -> 52 | BB95: =BB81+BA95 -> 778492
A96: 45714 | B96: Walmart Central America-CR | C96: 哥斯达黎加 | D96: 4500158535 | F96: 4500158535-60 | G96: 9548-S001 | H96: 鸭妈妈 | I96: 40 | J96: 0 | K96: 4 | L96: =I96/K96 -> 10 | M96: 45763 | N96: 45759 | P96: PASS | R96: 45740 | S96: 无 | T96: UPC贴纸+进口商贴纸贴纸翻单PO4500158302 | U96: MA | X96: 日期码格式：ZURU INC(BVI) 标准格式 日期：按实际生产日期 Packaging Info: 4. 9548：MA 5L EAN包装+UPC贴纸+MA 多语说明书+进口商贴纸+箱唛 以上贴纸翻单PO 4500158302 Remark: 1.使用双坑外箱 2.请注意产品包装条形码必须是UPC 3.无第三方验货 | Y96: Ever Li | Z96: 7.6392 | AA96: =Z96*I96 -> 305.568 | AB96: 94882-4.29 | AC96: 9548-S001-5L | AD96: 已入 | AE96: =I96*0.2 -> 8 | AO96: =I96 -> 40 | AS96: =I96 -> 40 | BA96: =I96 -> 40 | BB96: =BB87+BA96 -> 783944
A97: 45712 | B97: Walmart Central America | C97: 萨尔瓦多 | D97: 4500158302 | F97: 4500158302-60 | G97: 9548-S001 | H97: 鸭妈妈 | I97: 24 | J97: 0 | K97: 4 | L97: =I97/K97 -> 6 | M97: 45763 | N97: 45759 | P97: PASS | R97: 45740 | S97: 无 | T97: 3/21UPC贴纸+进口商贴纸 | U97: MA | X97: 日期码格式：ZURU INC(BVI) 标准格式 日期：按实际生产日期 Packaging Info: 4. 9548：MA 5L EAN包装+UPC贴纸+MA 多语说明书+进口商贴纸+箱唛 Remark: 1.使用双坑外箱 2.请注意产品包装条形码必须是UPC 3.无第三方验货 | Y97: Ever Li | Z97: 7.6392 | AA97: =Z97*I97 -> 183.3408 | AB97: 94865-4.28 | AC97: 9548-S001-5L | AD97: 已入 | AE97: =I97*0.2 -> 4.8 | AO97: =I97 -> 24 | AS97: =I97 -> 24 | BA97: =I97 -> 24 | BB97: =BB95+BA97 -> 778516
A98: 45701 | B98: TJX COMPANIES, INC | C98: 美国 | D98: 4500157312 | E98: Marshalls DC#881-156PCS , DC#884-176PCS , DC#886-128PCS , DC#887-140PCS | F98: 4500157312-40 | G98: 9548-S001 | H98: 鸭妈妈 | I98: 600 | J98: 0 | K98: 4 | L98: =I98/K98 -> 150 | M98: 45765 | N98: =M98-4 -> 45761 | P98: PASS | R98: 45705 | S98: 无 | T98: 3/21客供价格贴纸 | U98: MA | X98: 日期码格式：ZURU INC(BVI) 标准格式 日期：按实际生产日期 Packaging Info: MA UPC包装+价格贴纸，价格贴纸客供。 Remark: 1. 产品和包装上印刷tracking code信息，格式为ZURU常规格式。 2. 分4-5个DC出货，每款产品每个DC的箱唛资料不同。具体分DC数量，请参考后面行项目备注。 3. ZURU QC验货。 | Y98: Emily Wu | Z98: 7.6175 | AA98: =Z98*I98 -> 4570.5 | AB98: ZB00177-4.25 ZB00197-4.29 | AC98: 9548-S001 | AD98: 已入 | AE98: =I98*0.2 -> 120 | AK98: =I98 -> 600 | AS98: =I98 -> 600 | BA98: =I98 -> 600 | BB98: =BB109+BA98 -> 783316
A99: 45701 | B99: TJX COMPANIES, INC | C99: 美国 | D99: 4500157314 | E99: TJ MAXX DC#891-204PCS , DC#894-124PCS , DC#896-108PCS , DC#897-160PCS , DC#898-204PCS | F99: 4500157314-40 | G99: 9548-S001 | H99: 鸭妈妈 | I99: 800 | J99: 0 | K99: 4 | L99: =I99/K99 -> 200 | M99: 45765 | N99: =M99-4 -> 45761 | P99: PASS | R99: 45705 | S99: 无 | T99: 3/21客供价格贴纸 | U99: MA | X99: 日期码格式：ZURU INC(BVI) 标准格式 日期：按实际生产日期 Packaging Info: MA UPC包装+价格贴纸，价格贴纸客供。 Remark: 1. 产品和包装上印刷tracking code信息，格式为ZURU常规格式。 2. 分5个DC出货，每款产品每个DC的箱唛资料不同。具体分DC数量，请参考后面行项目备注。 3. ZURU QC验货。 | Y99: Emily Wu | Z99: 7.6175 | AA99: =Z99*I99 -> 6094 | AB99: ZB00176-4.25 ZB00196-4.29 | AC99: 9548-S001 | AD99: 已入 | AE99: =I99*0.2 -> 160 | AK99: =I99 -> 800 | AS99: =I99 -> 800 | BA99: =I99 -> 800 | BB99: =BB110+BA99 -> 784968
A100: 45723 | B100: AMAZON UK | C100: 英国 | D100: 4500159542 | E100: Amazon UK:6O1E2OTI | F100: 4500159542-10 | G100: 9548-S001 | H100: 鸭妈妈 | I100: 676 | J100: 0 | K100: 4 | L100: =I100/K100 -> 169 | M100: 45765 | N100: =M100-4 -> 45761 | P100: PASS | R100: 空白外箱（加印带Zuru字样的最新logo，除了邮包盒直接做外箱的产品） + SSCC LABEL一张, 无箱唛，MADE IN CHINA 外箱只印一正一侧 | S100: 有 | T100: 4张贴纸(1张UPC#<(>, <)>参考翻单PO#4500136617；1张IT/FR环保标，参考翻单PO#4500126747；1张ES回收环保标志1号，参考翻单PO#4500143120；1张ZURU邮箱，参考翻单PO#4500155164 )； | U100: MA | X100: 日期码格式：ZURU INC(BVI) 标准格式 日期：按实际生产日期 Packaging Info: Amazon UK(9548/92104G/71126/9279EG/9543BD) 1. 9548：MAMA DUCK, 1pc/window box, 4windowboxes/ctn; MA 5L(23L warning)A 开窗彩盒+MA 5L(9L warning)收藏指南+MA 其他最新包装+4张贴纸(1张UPC#<(>, <)>参考翻单PO#4500136617；1张IT/FR环保标，参考翻单PO#4500126747；1张ES回收环保标志1号，参考翻单PO#4500143120；1张ZURU邮箱，参考翻单PO#4500155164 )； 6.最迟验货不得晚于2025/4/21; Remark: 1.空白外箱（加印带Zuru字样的最新logo，除了邮包盒直接做外箱的产品） + SSCC LABEL一张, 无箱唛，MADE IN CHINA 外箱只印一正一侧。箱唛资料按照给定的 标准去做即可，无需发回我方再行审批(新标准将另行通知)。 (SSCC LABEL竖贴在外箱正面的正中间，贴一面即可,贴纸离外箱边距必须至少3.2CM。如竖贴无法满足要求，则横贴。如横贴也无法满足要求，则竖贴，遮到ZURU lo go无影响), SSCC贴纸由工厂直接跟勤得采购或者工厂自行采购，每一张SSCC Label都是唯一且有不同流水及条码，且需要检查条码是否能正常扫描，另外，此贴纸 印刷不可出现模糊，溢出及粘胶不牢易脱落等现象，如工厂不按此要求导致贴纸有任何问题产生的罚款将由工厂承担一切责任 。 2.出往UK的产品+包装务必打上UKCA logo ，否则客人会退货且当地会有罚款。 3.订单必须经过ZURU QC验货并且通过后方可出货。 4.法国订单要求包装不使用矿物油，请按要求提供以下其中一份文件再出货 ，产品出到法国被相关部门抽检出现包装不符合此要求的，供应商需要为此承担责任， 故此请严格把关。 -油墨物质""由1 ~ 7个芳香环组成的MOAH""的包装检测报告，要求限值≤1.0%； -包装材料清单，包括包装油墨或物质的信息； -油墨制造商的证书； 5.每一批次出货只能有一个生产日期，不可多个生产日期混在同一批次出货；且邮包盒上必须统一加上日期码；外箱对于日期码没有硬性规定； 6.涉及到相关款式会有闪粉的或者微塑料的，请统一默认出无闪粉或者不含微塑料版本； 7.邮包盒及外箱封箱必须是工字型封箱方式； 8.5 Surprise or Mini Brands涉及包装是2个及2个以上的球入PVC桶包装时，单个球上若有UPC#或者EAN#，请用白色贴纸覆盖住； | Y100: Crystal Chen | Z100: 7.4599 | AA100: =Z100*I100 -> 5042.8924 | AB100: 94872-4.29 | AC100: 9548-S001 | AD100: 已入 | AE100: =I100*0.2 -> 135.2 | AK100: =I100 -> 676 | AS100: =I100 -> 676 | BA100: =I100 -> 676 | BB100: =BB87+BA100 -> 784580
...

Sheet MA
B2: 9548鸭妈妈 IC MA
B3: 日期 | C3: MA订单号码 | D3: ITEM | E3: 名称 | F3: MA数量 | G3: 要求交货日期 | H3: IC 供应商 | I3: IC编号 | J3: 备注
A4: 46079 | B4: TJX CANADA | C4: 加拿大 | D4: 9548-S001-NB | E4: 40320898 | F4: 720 | G4: 新布标格式 | H4: 30000 | I4: 46052 | J4: 日期码格式：标准格式 日期：按实际生产日期 92125 MA 多语EAN版本+UPC贴纸193052083951 77731 英法客版铜版纸，upc 193052085115, MA 2L 收缩膜 多语多明书 25251 英法客版包装 UPC 845218016418 翻单4500166055 25252 客版英法彩盒和说明书。UPC号码845218016425 25253 英法客版 UPC 845218016432，彩盒翻单4500158924，说明书翻单4500166055 7153 英法客版包装 翻单4500131680， 7149 UPC193052033499 7150UPC 193052033406 MA 多语说明书 92119 无硼版本 MA 3L B 版收缩膜 +UPC 贴纸 UPC 193052078391， B 版5L 收藏指南 9258 无硼版本 MA 3L B 版收缩膜 UPC 5L多语言收藏指南193052037640 9296 无硼版本 MA 3L 收缩膜+ 多语说明书 ， UPC 193052057129 9298 无硼版本 MA C 版3L 收缩膜 +UPC 贴纸 UPC 193052057426， B 版5L 收藏指南 9548 无硼版本 MA D 版本 5L 包装+D 版本 5L 收藏指南 +UPC 贴纸 UPC 193052064196 出加拿大 有客供价格贴 每行对应不同的客户PO，唛头要一一对应， 放唛头时跟单会提供清单 Zuru验货.日期跟踪码：产品外包装及产品本身都必须有日期跟踪码，ZURU标准格式 日期码 | M4: 46135
A5: 46079 | B5: TJX CANADA | C5: 加拿大 | D5: 9548-S001-NB | E5: 布料MA | F5: 180 | G5: 新布标格式 | H5: 30000 | I5: 46052 | J5: 日期码格式：标准格式 日期：按实际生产日期 92125 MA 多语EAN版本+UPC贴纸193052083951 77731 英法客版铜版纸，upc 193052085115, MA 2L 收缩膜 多语多明书 25251 英法客版包装 UPC 845218016418 翻单4500166055 25252 客版英法彩盒和说明书。UPC号码845218016425 25253 英法客版 UPC 845218016432，彩盒翻单4500158924，说明书翻单4500166055 7153 英法客版包装 翻单4500131680， 7149 UPC193052033499 7150UPC 193052033406 MA 多语说明书 92119 无硼版本 MA 3L B 版收缩膜 +UPC 贴纸 UPC 193052078391， B 版5L 收藏指南 9258 无硼版本 MA 3L B 版收缩膜 UPC 5L多语言收藏指南193052037640 9296 无硼版本 MA 3L 收缩膜+ 多语说明书 ， UPC 193052057129 9298 无硼版本 MA C 版3L 收缩膜 +UPC 贴纸 UPC 193052057426， B 版5L 收藏指南 9548 无硼版本 MA D 版本 5L 包装+D 版本 5L 收藏指南 +UPC 贴纸 UPC 193052064196 出加拿大 有客供价格贴 每行对应不同的客户PO，唛头要一一对应， 放唛头时跟单会提供清单 Zuru验货.日期跟踪码：产品外包装及产品本身都必须有日期跟踪码，ZURU标准格式 日期码 | M5: 46135
A6: 46079 | B6: TJX CANADA | C6: 加拿大 | D6: 9548-S001 | E6: 布料MA | F6: 296 | G6: 新布标格式 | H6: 30000 | I6: 46052 | J6: 日期码格式：标准格式 日期：按实际生产日期 92125 MA 多语EAN版本+UPC贴纸193052083951 77731 英法客版铜版纸，upc 193052085115, MA 2L 收缩膜 多语多明书 25251 英法客版包装 UPC 845218016418 翻单4500166055 25252 客版英法彩盒和说明书。UPC号码845218016425 25253 英法客版 UPC 845218016432，彩盒翻单4500158924，说明书翻单4500166055 7153 英法客版包装 翻单4500131680， 7149 UPC193052033499 7150UPC 193052033406 MA 多语说明书 92119 无硼版本 MA 3L B 版收缩膜 +UPC 贴纸 UPC 193052078391， B 版5L 收藏指南 9258 无硼版本 MA 3L B 版收缩膜 UPC 5L多语言收藏指南193052037640 9296 无硼版本 MA 3L 收缩膜+ 多语说明书 ， UPC 193052057129 9298 无硼版本 MA C 版3L 收缩膜 +UPC 贴纸 UPC 193052057426， B 版5L 收藏指南 9548 无硼版本 MA D 版本 5L 包装+D 版本 5L 收藏指南 +UPC 贴纸 UPC 193052064196 出加拿大 有客供价格贴 每行对应不同的客户PO，唛头要一一对应， 放唛头时跟单会提供清单 Zuru验货.日期跟踪码：产品外包装及产品本身都必须有日期跟踪码，ZURU标准格式 日期码 | M6: 46135
B7: 45229 | C7: MA_RR_988 | D7: 9548 | E7: IC | F7: 3000 | G7: 45239 | H7: 矽源特 | I7: CST2307019-6
B8: 45280 | C8: MA_RR_1039 | D8: 9548 | E8: IC | F8: 27000 | G8: 45290 | H8: 矽源特 | I8: CST2307019-6B
B9: 45286 | C9: MA_RR_1051 | D9: 9548 | E9: IC | F9: 30000 | G9: 45301 | H9: 矽源特 | I9: CST2307019-6B
B10: 45315 | C10: MA_RR_1074 | D10: 9548 | E10: IC | F10: 15000 | G10: 45350 | H10: 矽源特 | I10: CST2307019-6B
B11: 45350 | C11: MA_RR_1104 | D11: 9548 | E11: IC | F11: 25000 | G11: 45365 | H11: 矽源特 | I11: CST2307019-6B
B12: 45371 | C12: MA_RR_1126 | D12: 9548 | E12: IC | F12: 80000 | G12: 45385 | H12: 矽源特 | I12: CST2307019-6B
B13: 45385 | C13: MA_RR_1155 | D13: 9548 | E13: IC | F13: 80000 | G13: 45400 | H13: 矽源特 | I13: CST2307019-6B
B14: 45420 | C14: MA_RR_1199 | D14: 9548 | E14: IC | F14: 100000 | G14: 45435 | H14: 矽源特 | I14: CST2307019-6B
B15: 45427 | C15: MA_RR_1224 | D15: 9548 | E15: IC | F15: 160000 | G15: 45442 | H15: 矽源特 | I15: CST2307019-6B
B16: 45455 | C16: MA_RR_1259 | D16: 9548 | E16: IC | F16: 40000 | G16: 45485 | H16: 矽源特 | I16: CST2307019-6B
B17: 45483 | C17: MA_RR_1317 | D17: 9548 | E17: IC | F17: 40000 | G17: 45513 | H17: 矽源特 | I17: CST2307019-6B
B18: 45504 | C18: MA_RR_1339 | D18: 9548 | E18: IC | F18: 50000 | G18: 45534 | H18: 矽源特 | I18: CST2307019-6B
... B23: 45625 | C23: MA_RR_1464 | D23: 9548 | E23: IC | F23: 30000 | G23: 45635 | H23: 矽源特 | I23: CST2307019-6B
C24: MA_RR_1497 | D24: 9548 | E24: IC | F24: 50000 | G24: 45660 | H24: 矽源特 | I24: CST2307019-6B
B25: 45677 | C25: MA_RR_1526 | D25: 9548 | E25: IC | F25: 30000 | G25: 45701 | H25: 矽源特 | I25: CST2307019-6B
B26: 45714 | C26: MA_RR_1568 | D26: 9548 | E26: IC | F26: 50000 | G26: 45724 | H26: 矽源特 | I26: CST2307019-6B
B27: 45719 | C27: MA_RR_1581 | D27: 9548 | E27: IC | F27: 80000 | G27: 45729 | H27: 矽源特 | I27: CST2307019-6B
B28: 45742 | C28: MA_RR_1605 | D28: 9548 | E28: IC | F28: 40000 | G28: 45754 | H28: 矽源特 | I28: CST2307019-6B
B29: 45804 | C29: MA_RR_1699 | D29: 9548 | E29: IC | F29: 20000 | G29: 45816 | H29: 矽源特 | I29: CST2307019-6B
B30: 45835 | C30: MA_RR_1757 | D30: 9548 | E30: IC | F30: 60000 | G30: 45847 | H30: 矽源特 | I30: CST2307019-6B
B31: 45866 | C31: MA_RR_1812 | D31: 9548 | E31: IC | F31: 30000 | G31: 45878 | H31: 矽源特 | I31: CST2307019-6B
B32: 46031 | C32: MA_RR_2052 | D32: 9548 | E32: IC | F32: 60000 | G32: 46043 | H32: 矽源特 | I32: CST2307019-6B
E33: 合计 | F33: =SUM(F7:F32) -> 1330000
E34: 半成品MA数 | F34: =H68 -> 1240000
E35: 接单总数 | F35: ='9548明细'!AE427+I35 -> 217094.27 | H35: 2024年剩余数 | I35: 143286.27
E36: 按实单扣数的IC MA剩余 | F36: =F33-F35 -> 1112905.7
E37: 按半成品MA扣数的IC MA剩余 | F37: =F33-F34 -> 90000
B42: 9548鸭妈妈 半成品生产MA | K42: 口水胶 | L42: 无硼口水胶 | M42: 布料MA剩余： | N42: =H99-H68 -> 30000
B43: 日期 | C43: MA订单号码 | D43: ITEM | E43: 名称 | H43: 合计 | I43: 要求完成日期 | J43: 备注
B44: 45294 | C44: MA-RR-1054 | D44: 9548 | E44: MAMA & BABY SURPRISE - SERIES 1 - MAMA DUCK | H44: 30000 | I44: 45361 | K44: =21428*0.34286+8572*0.2 -> 9061.2041 | N44: 口水胶日期码4/18
B45: 45344 | C45: MA-RR-1088 | D45: 9548 | E45: MAMA & BABY SURPRISE - SERIES 1 - MAMA DUCK | H45: 30000 | I45: 45402 | J45: 新布标 | K45: =H45*0.2 -> 6000 | N45: 口水胶日期码4/26
B46: 45365 | D46: 9548 | L46: 10000 | M46: （300kg） | N46: 无硼 口水胶日期码4/30
B47: 45371 | C47: MA-RR-1124 | D47: 9548 | E47: MAMA & BABY SURPRISE - SERIES 1 - MAMA DUCK | H47: 60000 | I47: 45448 | J47: 新布标 | K47: =H47*0.2 -> 12000 | N47: 口水胶日期码5/6
B48: 45389 | C48: MA-RR-1143 | D48: 9548 | E48: MAMA & BABY SURPRISE - SERIES 1 - MAMA DUCK | H48: 60000 | I48: 45485 | J48: 生产5/2新日期码格式布标 | K48: =H48*0.2 -> 12000 | N48: 口水胶日期码5/30
B49: 45405 | C49: MA-RR-1179 | D49: 9548 | E49: MAMA & BABY SURPRISE - SERIES 1 - MAMA DUCK | H49: 80000 | I49: 45485 | J49: 生产5/25新日期码格式布标 | K49: =H49*0.2 -> 16000 | N49: 口水胶日期码5/30
B50: 45420 | C50: MA-RR-1201 | D50: 9548 | E50: MAMA & BABY SURPRISE - SERIES 1 - MAMA DUCK | H50: 100000 | I50: 45512 | J50: 生产6/3新日期码格式布标 | K50: =H50*0.2 -> 20000
B51: 45427 | C51: MA-RR-1226 | D51: 9548 | E51: MAMA & BABY SURPRISE - SERIES 1 - MAMA DUCK | H51: 120000 | I51: 45542 | J51: 生产6/3新日期码格式布标 | K51: =H51*0.2 -> 24000
B52: 45455 | C52: MA-RR-1261 | D52: 9548 | E52: MAMA & BABY SURPRISE - SERIES 1 - MAMA DUCK | H52: 40000 | I52: 45547 | J52: 生产7/3新日期码格式布标 | K52: =H52*0.2 -> 8000
B53: 45483 | C53: MA-RR-1315 | D53: 9548 | E53: MAMA & BABY SURPRISE - SERIES 1 - MAMA DUCK | H53: 40000 | I53: 45555 | J53: 新布标 (日期码2024/7/3) | K53: =H53*0.2 -> 8000
B54: 45498 | C54: MA-RR-1332 | D54: 9548 | E54: MAMA & BABY SURPRISE - SERIES 1 - MAMA DUCK | H54: 40000 | I54: 45573 | J54: 新布标 (日期码2024/8/1) | K54: =H54*0.2 -> 8000
B55: 45504 | C55: MA-RR-1341 | D55: 9548 | E55: MAMA & BABY SURPRISE - SERIES 1 - MAMA DUCK | H55: 50000 | I55: 45583 | J55: 新布标 (日期码2024/8/1) | K55: =H55*0.2 -> 10000 | M55: 订贴纸2000
B56: 45511 | C56: MA-RR-1347 | D56: 9548 | E56: MAMA & BABY SURPRISE - SERIES 1 - MAMA DUCK | H56: 50000 | I56: 45595 | J56: 新布标 (日期码2024/9/2) | K56: =H56*0.2 -> 10000 | M56: 订贴纸10000
B57: 45549 | C57: MA-RR-1377 | D57: 9548 | E57: MAMA & BABY SURPRISE - SERIES 1 - MAMA DUCK | H57: 50000 | I57: 45608 | J57: 新布标 (日期码2024/9/2) | K57: =H57*0.2 -> 10000 | M57: 订贴纸10000
B58: 45576 | C58: MA-RR-1376 | D58: 9548 | E58: MAMA & BABY SURPRISE - SERIES 1 - MAMA DUCK | H58: 50000 | I58: 45618 | J58: 新布标日期码2024/10/15，暂留10K作为客版布标 | K58: =H58*0.2 -> 10000 | M58: 订贴纸10000
B59: 45593 | C59: MA-RR-1431 | D59: 9548 | E59: MAMA & BABY SURPRISE - SERIES 1 - MAMA DUCK | H59: 80000 | I59: 45651 | J59: 新布标日期码2024/10/15， 常留5K待做客版布标 | K59: =H59*0.2 -> 16000
B60: 45661 | C60: MA_RR_1505 | D60: 9548 | E60: MAMA & BABY SURPRISE - SERIES 1 - MAMA DUCK | H60: 40000 | I60: 45731 | J60: 新布标日期码2025/1/6， 常留5K待做客版布标 | K60: =H60*0.2 -> 8000 | L60: 10000
B61: 45708 | C61: MA-RR-1561 | D61: 9548 | E61: MAMA & BABY SURPRISE - SERIES 1 - MAMA DUCK | H61: 40000 | I61: 45748 | J61: 新布标日期码2025/2/20， 常留5K待做客版布标 | K61: =H61*0.2 -> 8000
B62: 45719 | C62: MA-RR-1582 | D62: 9548 | E62: MAMA & BABY SURPRISE - SERIES 1 - MAMA DUCK | H62: 120000 | I62: 45785 | J62: 新布标日期码2025/3/20，常留5K待做客版布标 | K62: =H62*0.2 -> 24000
B63: 45806 | C63: MA-RR-1707 | D63: 9548 | E63: MAMA & BABY SURPRISE - SERIES 1 - MAMA DUCK | H63: 40000 | I63: 45870 | K63: =H63*0.2 -> 8000
B64: 45828 | C64: MA-RR-1742 | D64: 9548 | E64: MAMA & BABY SURPRISE - SERIES 1 - MAMA DUCK | H64: 60000 | I64: 45887 | J64: 新布标日期码2025/7/1，常留5K待做客版布标 | K64: =H64*0.2 -> 12000 | L64: 10000
B65: 45850 | C65: MA-RR-1791 | D65: 9548 | E65: MAMA & BABY SURPRISE - SERIES 1 - MAMA DUCK | H65: 30000 | I65: 45910 | J65: 新布标日期码2025/3/20，常留5K待做客版布标 | K65: =H65*0.2 -> 6000 | M65: 多备8
B66: 46017 | C66: MA-RR-2028 | D66: 9548 | E66: MAMA & BABY SURPRISE - SERIES 1 - MAMA DUCK | H66: 30000 | I66: 45748
E68: MA合计 | F68: 0 | G68: =SUM(G44:G50) -> 0 | H68: =SUM(H44:H67) -> 1240000 | K68: =SUM(K43:K67) -> 245061.2 | L68: =SUM(L43:L62) -> 20000
G69: 接单总数 | H69: ='9548明细'!I427+O69 -> 1188868 | K69: ='9548明细'!AE427+O70 -> 217094.27 | L69: ='9548明细'!AF427 -> 27484.4 | N69: 2024年删除后剩余 | O69: 733020
G70: MA剩余 | H70: =H68-H69 -> 51132 | K70: =K68-K69 -> 27966.935 | L70: =L68-L69 -> -7484.4 | N70: 2024年删除后剩余 | O70: 143286.27
G71: MA剩余占MA数比率 | H71: =H70/H68 -> 0.041235484
B76: 9548鸭妈妈 车缝MA
B77: 日期 | C77: MA订单号码 | D77: ITEM | E77: 名称 | F77: MA布标 （可按此数量订购MA布标并车缝） | G77: WM布标 | H77: 合计 | I77: 要求完成日期 | J77: 备注
B78: 45237 | C78: MA-RR-1002 | D78: 9548 | E78: 布料MA | F78: 30000 | H78: =SUM(F78:G78) -> 30000 | I78: 45272 | K78: （旧）日期码3/4
B79: 45344 | C79: MA_RR_1087 | D79: 9548 | E79: 布料MA | F79: 30000 | G79: 新布标格式 | H79: =SUM(F79:G79) -> 30000 | I79: 45377 | K79: wm 布标 | L79: 日期码4/1
B80: 45359 | C80: MA_RR_1107 | D80: 9548 | E80: 布料MA | F80: 60000 | G80: 新布标格式 | H80: =SUM(F80:G80) -> 60000 | I80: 45394 | K80: 日期码4/22
B81: 45371 | C81: MA-RR-1125 | D81: 9548 | E81: 布料MA | F81: 60000 | G81: 新布标格式 | H81: =SUM(F81:G81) -> 60000 | I81: 45405 | K81: 日期码5/6
B82: 45389 | C82: MA-RR-1144 | D82: 9548 | E82: 布料MA | F82: 80000 | G82: 新布标格式 | H82: =SUM(F82:G82) -> 80000 | I82: 45424 | K82: 日期码5/30
B83: 45405 | C83: MA-RR-1180 | D83: 9548 | E83: 布料MA | F83: 60000 | G83: 新布标格式 | H83: =SUM(F83:G83) -> 60000 | I83: 45440 | K83: 日期码5/30
B84: 45420 | C84: MA-RR-1200 | D84: 9548 | E84: 布料MA | F84: 80000 | G84: 新布标格式 | H84: =SUM(F84:G84) -> 80000 | I84: 45455 | J84: C版布标 | K84: 日期码6/24
B85: 45427 | C85: MA-RR-1225 | D85: 9548 | E85: 布料MA | F85: 120000 | G85: 新布标格式 | H85: =SUM(F85:G85) -> 120000 | I85: 45462 | J85: C版布标 | K85: 日期码7/10
B86: 45454 | C86: MA_RR_1260 | D86: 9548 | E86: 布料MA | F86: 40000 | G86: 新布标格式 | H86: =SUM(F86:G86) -> 40000 | I86: 45489 | J86: C版布标 | K86: 日期码8/30
B87: 45483 | C87: MA_RR_1316 | D87: 9548 | E87: 布料MA | F87: 40000 | G87: 新布标格式 | H87: =SUM(F87:G87) -> 40000 | I87: 45518 | J87: C版布标 | K87: 日期码8/30
B88: 45498 | C88: MA_RR_1333 | D88: 9548 | E88: 布料MA | F88: 80000 | G88: 新布标格式 | H88: =SUM(F88:G88) -> 80000 | I88: 45533 | J88: C版布标
B89: 45511 | C89: MA_RR_1349 | D89: 9548 | E89: 布料MA | F89: 70000 | G89: 新布标格式 | H89: =SUM(F89:G89) -> 70000 | I89: 45546 | J89: C版布标
B90: 45549 | C90: MA_RR_1375 | D90: 9548 | E90: 布料MA | F90: 50000 | G90: 新布标格式 | H90: =SUM(F90:G90) -> 50000 | I90: 45584 | J90: C版布标
B91: 45593 | C91: MA_RR_1432 | D91: 9548 | E91: 布料MA | F91: 80000 | G91: 新布标格式 | H91: =SUM(F91:G91) -> 80000 | I91: 45628 | J91: C版布标
B92: 45618 | C92: MA RR 1432 | D92: 9548 | E92: 布料MA | F92: 80000 | G92: 新布标格式 | H92: =SUM(F92:G92) -> 80000 | I92: 45653 | J92: C版布标
C93: MA_RR_1506 | D93: 9548 | E93: 布料MA | F93: 40000 | G93: 新布标格式 | H93: 40000 | I93: 45695 | J93: C版布标
B94: 45708 | C94: MA_RR_1548 | D94: 9548 | E94: 布料MA | F94: 60000 | G94: 新布标格式 | H94: 60000 | I94: 45742 | J94: C版布标
B95: 45719 | C95: MA_RR_1580 | D95: 9548 | E95: 布料MA | F95: 60000 | G95: 新布标格式 | H95: 60000 | I95: 45754 | J95: C版布标
B96: 45806 | C96: MA_RR_1708 | D96: 9548 | E96: 布料MA | F96: 60000 | G96: 新布标格式 | H96: 60000 | I96: 45841 | J96: C版布标
B97: 45828 | C97: MA_RR_1741 | D97: 9548 | E97: 布料MA | F97: 60000 | G97: 新布标格式 | H97: 60000 | I97: 45887 | J97: B版布标
B98: 46017 | C98: MA_RR_2027 | D98: 9548 | E98: 布料MA | F98: 30000 | G98: 新布标格式 | H98: 30000 | I98: 46052 | J98: B版布标
E99: MA合计 | F99: =SUM(F78:F98) -> 1270000 | G99: =SUM(G78:G84) -> 0 | H99: =SUM(H78:H98) -> 1270000
G100: 接单总数 | H100: =H69 -> 1188868
G101: MA剩余 | H101: =H99-H100 -> 81132
G102: MA剩余占MA数比率 | H102: =H101/H99 -> 0.063883465
K105: =H100-取消单!BB15 -> 401516

Sheet 彩盒MA
B2: 9548 彩盒/说明书 MA
B3: 放MA日期 | C3: 名称 | D3: MA订单号码 | E3: 货号 | F3: 数量 | G3: 语言 | H3: 版本号 | I3: 1L 标准版彩盒A版 | J3: 1L 标准版彩盒B版 | K3: 5L 标准版彩盒A版 | L3: 5L 标准版彩盒B版 | M3: 1L标准版彩盒C版 | N3: 5L 标准版彩盒C版 | O3: 5L 标准版彩盒D版 | P3: 5L 说明书 | Q3: 5L 说明书 B版 | R3: 5L说明书 C版 | S3: 客版彩盒 | T3: 客版说明书 | U3: Endcap EC展架 | V3: SLD展示架
B4: 45359 | C4: Window Box+PET box 彩盒+透明盒 | D4: 1000018820 | E4: 9548 | F4: 30000 | G4: 1L+23L | H4: A | I4: 30000
B5: 45359 | C5: Instruction+Warning 说明书 | D5: 1000018821 | E5: 9548 | F5: 30000 | G5: 5L | H5: A | P5: 30000
B6: 45370 | C6: Window Box+PET box 彩盒+透明盒 | D6: 1000018994 | E6: 9548 | F6: 30000 | G6: 5L | H6: A | K6: 30000
B7: 45370 | C7: Window Box+PET box 彩盒+透明盒 | D7: 1000018995 | E7: 9548 | F7: 50000 | G7: 1L+23L | H7: A | I7: 50000
B8: 45370 | C8: Instruction+Warning 说明书 | D8: 1000018996 | E8: 9548 | F8: 100000 | G8: 5L | H8: A | P8: 100000
B9: 45384 | C9: BJ's new order PDQ | D9: 1000019290 | E9: 9548 | F9: 5728 | G9: 1L | H9: N/A | S9: 5728
B10: 45394 | C10: Endcap EC展架 | D10: 1000019556 | E10: 9548 | F10: 400 | G10: 3L | H10: A | U10: 400
B11: 45394 | C11: （4500125999）Instruction Sheet | D11: 1000019545 | E11: 9548 | F11: 3000 | G11: 芬兰 | H11: 客版 | T11: 3000 | W11: Luna用于4500126092-120pcs; 4500130794-700pcs; 4500131147-2256pcs;
B12: 45405 | C12: Window Box+PET box 彩盒+透明盒 | D12: 1000019769 | E12: 9548 | F12: 100000 | G12: 1L+23L | H12: A | I12: =F12 -> 100000
B13: 45405 | C13: Instruction+Warning 说明书 | D13: 1000019770 | E13: 9548 | F13: 80000 | G13: 5L | H13: A | P13: =F13 -> 80000
B14: 45425 | C14: Window Box+PET box 彩盒+透明盒 | D14: 1000020238 | E14: 9548 | F14: 60000 | G14: 1L+23L | H14: A | I14: =F14 -> 60000
B15: 45425 | C15: Window Box+PET box 彩盒+透明盒 | D15: 1000020239 | E15: 9548 | F15: 30000 | G15: 5L | H15: A | K15: =F15 -> 30000
B16: 45425 | C16: Instruction+Warning 说明书 | D16: 1000020240 | E16: 9548 | F16: 50000 | G16: 5L | H16: A | P16: =F16 -> 50000
B17: 45443 | C17: Window Box+PET box 彩盒+透明盒 | D17: 1000020666 | E17: 9548 | F17: 80000 | G17: 1L+23L | H17: A | I17: =F17 -> 80000
B18: 45443 | C18: Instruction+Warning 说明书 | D18: 1000020659 | E18: 9548 | F18: 80000 | G18: 5L | H18: A | P18: =F18 -> 80000
B19: 45447 | C19: （4500125999）Instruction Sheet | D19: 1000020745 | E19: 9548 | F19: 3460 | G19: 芬兰 | H19: 客版 | T19: =F19 -> 3460 | W19: Luna用于4500131331-360pcs; 4500131352-500pcs;4500131615-684pcs；4500129328-300pcs；4500132947-360pcs; 4500129340-556pcs;4500125999-300pcs 4500135130-120pcs 4500137072-120pcs 剩余用于后续订单：1100022520-84pcs
B20: 45467 | C20: Window Box+PET box 彩盒+透明盒 | D20: 1000021275 | E20: 9548 | F20: 50000 | G20: 1L+23L | H20: A | I20: =F20 -> 50000 | W20: 剩余700客版说明书125999
B21: 45467 | C21: Window Box+PET box 彩盒+透明盒 | D21: 1000021276 | E21: 9548 | F21: 30000 | G21: 5L | H21: B | L21: =F21 -> 30000
B22: 45467 | C22: Instruction+Warning 说明书 | D22: 1000021277 | E22: 9548 | F22: 80000 | G22: 5L | H22: A | P22: =F22 -> 80000
B23: 45496 | C23: （4500125999）Instruction Sheet | D23: 1000022060 | E23: 9548 | F23: 3000 | G23: 芬兰 | H23: 客版 | T23: =F23 -> 3000 | W23: Luna用于PO 4500140612(200PCS)+SOK PO4500139712(300pcs)，剩余数量后续订单消耗
B24: 45502 | C24: 中文版说明书 | D24: 1000022144 | E24: 9548 | F24: 3000 | G24: 中文 | H24: 客版 | T24: 3000 | W24: Dona用于订单4500140818
B25: 45503 | C25: Window Box+PET box 彩盒+透明盒 | D25: 1000022167 | E25: 9548 | F25: 100000 | G25: 1L+23L | H25: A | I25: =F25 -> 100000
B26: 45503 | C26: Window Box+PET box 彩盒+透明盒 | D26: 1000022168 | E26: 9548 | F26: 30000 | G26: 5L | H26: B | L26: =F26 -> 30000
B27: 45503 | C27: Instruction+Warning 说明书 | D27: 1000022169 | E27: 9548 | F27: 100000 | G27: 5L | H27: A | P27: =F27 -> 100000
B28: 45517 | C28: Window Box+PET box 彩盒+透明盒 | D28: 1000022482 | E28: 9548 | F28: 50000 | G28: 1L+23L | H28: A | I28: =F28 -> 50000
B29: 45517 | C29: Instruction+Warning 说明书 | D29: 1000022483 | E29: 9548 | F29: 100000 | G29: 5L | H29: A | P29: =F29 -> 100000
B30: 45558 | C30: Window Box+PET box 彩盒+透明盒 | D30: 1000023317 | E30: 9548 | F30: 20000 | G30: 1L+23L | H30: B | J30: =F30 -> 20000
B31: 45558 | C31: Window Box+PET box 彩盒+透明盒 | D31: 1000023318 | E31: 9548 | F31: 20000 | G31: 5L | H31: C | N31: =F31 -> 20000
B32: 45580 | C32: Window Box+PET box 彩盒+透明盒 | D32: 1000023697 | E32: 9548 | F32: 50000 | G32: 1L+23L | H32: B | I32: 10000 | J32: =F32-I32 -> 40000
B33: 45580 | C33: Instruction+Warning 说明书 | D33: 1000023698 | E33: 9548 | F33: 50000 | G33: 5L | H33: B | Q33: =F33 -> 50000
B34: 45604 | C34: Window Box+PET box 彩盒+透明盒 | D34: 1000024299 | E34: 9548 | F34: 50000 | G34: 1L+23L | H34: B | J34: 50000
B35: 45604 | C35: Instruction+Warning 说明书 | D35: 1000024300 | E35: 9548 | F35: 80000 | G35: 5L | H35: B | Q35: 80000
B36: 45631 | C36: Window Box+PET box 彩盒+透明盒 | D36: 1000024919 | E36: 9548 | F36: 60000 | G36: 1L+23L | H36: B | J36: 60000
B37: 45631 | C37: Window Box+PET box 彩盒+透明盒 | D37: 1000024920 | E37: 9548 | F37: 20000 | G37: 5L | H37: C | N37: 20000
B38: 45631 | C38: Instruction+Warning 说明书 | D38: 1000024922 | E38: 9548 | F38: 60000 | G38: 5L | H38: B | Q38: 60000
B39: 45673 | C39: Window Box+PET box彩盒+透明盒 | D39: 1000025575 | E39: 9548 | F39: 20000 | G39: 1L+23L | H39: B | J39: 20000
B40: 45673 | C40: Instruction+Warning说明书 | D40: 1000025576 | E40: 9548 | F40: 30000 | G40: 5L | H40: C | Q40: 30000
B41: 45734 | C41: Window Box+PET box 彩盒+透明盒 | D41: 1000026364 | E41: 9548 | F41: 30000 | G41: 5L | H41: C | N41: 30000
B42: 45734 | C42: Instruction+Warning 说明书 | D42: 1000026365 | E42: 9548 | F42: 30000 | G42: 5L | H42: B | Q42: 30000
B43: 45750 | C43: Window Box+PET box 彩盒+透明盒 | D43: 1000026906 | E43: 9548 | F43: 50000 | G43: 1L+23L | H43: B | J43: 50000
B44: 45750 | C44: Instruction+Warning 说明书 | D44: 1000026907 | E44: 9548 | F44: 50000 | G44: 5L | H44: B | Q44: 50000
B45: 45813 | C45: Window Box+PET box 彩盒+透明盒 | D45: 1000028742 | E45: 9548 | F45: 100000 | G45: 1L+23L | H45: B | J45: =F45 -> 100000
B46: 45813 | C46: Window Box+PET box 彩盒+透明盒 | D46: 1000028743 | E46: 9548 | F46: 30000 | G46: 5L | H46: C | N46: =F46 -> 30000
B47: 45813 | C47: Instruction+Warning 说明书 | D47: 1000028744 | E47: 9548 | F47: 50000 | G47: 5L | H47: B | Q47: =F47 -> 50000
B48: 45839 | C48: Window Box+PET box 彩盒+透明盒 | D48: 1000029546 | E48: 9548 | F48: 60000 | G48: 1L+23L | H48: B | J48: =F48 -> 60000
B49: 45839 | C49: Instruction+Warning 说明书 | D49: 1000029548 | E49: 9548 | F49: 120000 | G49: 5L | H49: B | Q49: =F49 -> 120000
B50: 45812 | C50: 9548SLD | D50: 1000028657 | E50: 9548SLD | F50: 3000 | G50: 通用 | V50: =F50 -> 3000
B51: 45869 | C51: Window Box+PET box 彩盒+透明盒 | D51: 1000030542 | E51: 9548 | F51: 30000 | G51: 5L | H51: D | O51: =F51 -> 30000
B52: 45869 | C52: Instruction+Warning 说明书 | D52: 1000030524 | E52: 9548 | F52: 30000 | G52: 5L | H52: C | R52: =F52 -> 30000
B53: 45881 | C53: Window Box+PET box 彩盒+透明盒 | D53: 1000030927 | E53: 9548 | F53: 10000 | G53: 1L+23L | H53: B | M53: 10000
B54: 46015 | C54: Window Box+PET box 彩盒+透明盒 | D54: 1000035219 | E54: 9548 | F54: 20000 | G54: 1L+23L | H54: D | M54: 20000
B55: 46015 | C55: Instruction+Warning 说明书 | D55: 1000035220 | E55: 9548 | F55: 30000 | G55: 5L | H55: C | R55: 30000
H56: 合计 | I56: =SUM(I4:I40) -> 530000 | J56: =SUM(J4:J53) -> 400000 | K56: =SUM(K4:K39) -> 60000 | L56: =SUM(L4:L40) -> 60000 | M56: =SUM(M41:M55) -> 30000 | N56: =SUM(N4:N47)+L59 -> 105688 | O56: =SUM(O51:O52) -> 30000 | P56: =SUM(P4:P40) -> 620000 | Q56: =SUM(Q4:Q50) -> 470000 | R56: =SUM(R41:R55) -> 60000 | S56: =SUM(S4:S40) -> 5728 | T56: =SUM(T4:T40) -> 12460 | U56: =SUM(U4:U40) -> 400 | V56: =SUM(V28:V50) -> 3000
H57: 接单总数 | I57: ='9548明细'!AJ427+I66 -> 532587 | J57: ='9548明细'!AK427+J66 -> 409222 | K57: ='9548明细'!AL427 -> 0 | L57: ='9548明细'!AM427+L66 -> 54312 | M57: ='9548明细'!AN427 -> 28464 | N57: ='9548明细'!AO427+N66 -> 91950 | O57: ='9548明细'!AP427 -> 2000 | P57: ='9548明细'!AR427+P66 -> 623868 | Q57: ='9548明细'!AS427+Q66 -> 485232 | R57: ='9548明细'!AT427 -> 11720 | S57: ='9548明细'!AX427+S66 -> 7728 | T57: ='9548明细'!AU427+T66 -> 57308 | U57: ='9548明细'!AV427+U66 -> 3322 | V57: ='9548明细'!AV430 -> 2478
H59: 彩盒MA剩余 | I59: =I56-I57 -> -2587 | J59: =J56-J57 -> -9222 | K59: =K56-K57 -> 60000 | L59: =L56-L57 -> 5688 | M59: =M56-M57 -> 1536 | N59: =N56-N57 -> 13738 | P59: =P56-P57 -> -3868 | Q59: =Q56-Q57 -> -15232 | R59: =R56-R57 -> 48280 | S59: =S56-S57 -> -2000 | T59: =T56-T57 -> -44848 | U59: =U56-U57 -> -2922 | V59: =V56-V57 -> 522
I60: 3000 | L60: 600
I66: 526915 | J66: 86012 | K66: 59993 | L66: 52712 | N66: 7148 | P66: 609516 | Q66: 81480 | S66: 7012 | T66: 41784 | U66: 322

Sheet 取消单
A1: 接单期 | B1: 第三方客户名称 | C1: 走货国家 | D1: ZURU PO NO# | E1: 第三方客户 PO NO# | F1: SKU | G1: ITEM# | H1: 货品名称 | I1: PO数量(只) | J1: 内箱装箱数量(只) | K1: 外箱装箱数量(只) | L1: 总箱数 | M1: 计划出货期 | N1: 计划验货期 | O1: 第三方客户公证行验货 | P1: 验货结果 | Q1: ZURU确认走货日期 | R1: 箱唛(收到日期) | S1: 外箱贴纸 | T1: 客供贴纸资料(收到日期及订购日期) | U1: 客版资料 | V1: 备注 | W1: ZURU跟单组员 | X1: 单价USD | Y1: 金额USD | Z1: 发票号 | AA1: 系统货号 | AB1: 是否入系统 | AC1: 需求数 有硼 | AD1: 需求数 无硼 | AE1: 送货情况 | AF1: 贴纸情况 | AG1: 纸箱情况 | AH1: MA1语彩盒 | AI1: MA5语彩盒 | AJ1: 客版彩盒 | AK1: 5L 说明书 | AL1: 客版说明书 | AM1: 9548EC-S001 | AN1: 9548UQ1 客版PDQ | AO1: 9548SLB-S001 | AP1: 9548SLB-S002 | AQ1: 布标 | AR1: 合计数量 | AS1: 累计数量 | AT1: 新配比（口水胶） | AU1: MA数量 | AV1: 30000 | AW1: 30000 | AX1: 60000
A2: 45721 | B2: KMART AUSTRALIA LTD | C2: 澳大利亚 | D2: 4500159287 | E2: 20672972 | F2: 4500159287-20 | G2: 9548-S001 | H2: 鸭妈妈 | I2: 1500 | J2: 0 | K2: 4 | L2: 375 | M2: 3/13取消订单 | N2: 3/13取消订单 | R2: 45733 | S2: 有 | T2: 1张防盗贴纸 (贴纸以及位置图翻单PO#4500157612）+外箱SSCC Label | U2: MA | X2: 日期码格式：ZURU INC(BVI) 标准格式 日期：按实际生产日期 Packaging Info: 9561: MA英语UPC版本包装（收缩膜和说明书, MA首选1L，如无1L可用多语且含英语的配套多语包装) + 1张包装纽扣电池警告语贴纸 + 1张说明书纽扣电池警告语 贴纸 （贴纸及位置图翻单: PO#4500157612）+ 1张防盗贴纸+ 箱唛 + 外箱SSCC Label 配比信息：3pcs mini turtles: 4pcs mini tutles: 5pcs mini turtles= 87:10:3 9548: MA英语UPC版本包装（收缩膜和说明书, MA首选1L，如无1L可用多语且含英语的配套多语包装) + 1张防盗贴纸 (贴纸以及位置图翻单PO#4500126567）+ 箱唛 + 外箱SSCC Label Remark: 1.请务必按时完货，验货。并且按期送货入货代指定仓库，如果晚了导致船期Delay将会有罚金产生或者客户要求空运，所产生的罚金和空运费由工厂承担。 2.SSCC 外箱贴纸请同纸箱瓦楞纸方向（竖纹向）垂直，即外箱贴纸横着贴(注意条码不要被胶带粘住），贴1pc，贴1面正唛，封箱胶纸不能挡住贴纸内容。外箱贴纸 离外箱边距离不少于2cm。 3.外箱材质为ZURU标准； 4.此单需使用KMART封箱胶上下工字型封箱;从2019年6月开始，要用KMART 新版封箱胶带，此单要用"ANKO"封箱胶带 5.此单出口澳大利亚，请按相应的澳新标准生产； 6.产品和包装上生产批号的显示格式ZURU标准日期码格式 7.外箱信息不可手写，重量和体积需要与实际的一致(不可手写） 8. 每款item装箱后的G.W.超过10KG或者CBM超过0.13,(9.5KG或者以上，四舍五入后也属于10KG) 需在外箱上加印超 重或者Bulky LOGO，若发现我们资料没有，请 帮忙提醒 1)重量超过10kg但不超过16kg且CBM不超过0.13,10-16kg 超重logo 2）CBM超过0.13且重量少于17kg，bulky logo 3）不属于以上两种情况，需要使用相应重量范围内的超重logo 4）超重logo需要在外箱四面都印刷(箱唛右上角，两面侧唛超重logo需要尽量靠近毛重)，尺寸为:110mm height* 95mm width 9. 实际外箱重量跟印在箱唛上的数据差异不能超3%，尺寸按实际数据印刷 | Y2: Lydia Wu | Z2: 8.2757 | AA2: 12413.55 | AC2: 9548-S001 | AD2: 已入 | AE2: 300 | AF2: 1500 | AL2: 1500 | AS2: 1500 | AT2: 834976
A3: 45747 | B3: Mid-States Distributing, LLC | C3: 美国 | D3: 4500161570 | E3: Murdoch's Southern DC PO 671605134 | F3: 4500161570-190 | G3: 9548-S001 | H3: 鸭妈妈 | I3: 100 | J3: 0 | K3: 4 | L3: =I3/K3 -> 25 | M3: 45818 | N3: 45814 | O3: 暂停生产 | R3: 欠 | S3: 无 | T3: 无 | U3: MA | X3: 日期码格式：ZURU INC(BVI) 标准格式 日期：按实际生产日期 Packaging Info: 1.使用 MA UPC版本包装，优先1L，出口美国。 Remark: 1.产品和包装上印刷tracking code信息，格式为ZURU常规。 2.ZURU QC验货 | Y3: Cara Li | Z3: 8.1258 | AA3: =Z3*I3 -> 812.58 | AC3: 9548-S001 | AD3: 已入 | AE3: =I3*0.2 -> 20 | AK3: =I3 -> 100 | AQ3: =I3 -> 100 | AX3: =I3 -> 100 | AY3: ='9548明细'!BB90+AX3 -> 779952
A4: 45747 | B4: Mid-States Distributing, LLC | C4: 美国 | D4: 4500161570 | E4: Murdoch's TX DC PO 671605136 | F4: 4500161570-210 | G4: 9548-S001 | H4: 鸭妈妈 | I4: 40 | J4: 0 | K4: 4 | L4: =I4/K4 -> 10 | M4: 45818 | N4: 45814 | O4: 暂停生产 | R4: 欠 | S4: 无 | T4: 无 | U4: MA | X4: 日期码格式：ZURU INC(BVI) 标准格式 日期：按实际生产日期 Packaging Info: 1.使用 MA UPC版本包装，优先1L，出口美国。 Remark: 1.产品和包装上印刷tracking code信息，格式为ZURU常规。 2.ZURU QC验货 | Y4: Cara Li | Z4: 8.1258 | AA4: =Z4*I4 -> 325.032 | AC4: 9548-S001 | AD4: 已入 | AE4: =I4*0.2 -> 8 | AK4: =I4 -> 40 | AQ4: =I4 -> 40 | AX4: =I4 -> 40 | AY4: ='9548明细'!BB98+AX4 -> 783356
A5: 45747 | B5: Mid-States Distributing, LLC | C5: 美国 | D5: 4500161570 | E5: Murdoch's Norther DC PO 671605135 | F5: 4500161570-200 | G5: 9548-S001 | H5: 鸭妈妈 | I5: 76 | J5: 0 | K5: 4 | L5: =I5/K5 -> 19 | M5: 45818 | N5: 45814 | O5: 暂停生产 | R5: 欠 | S5: 无 | T5: 无 | U5: MA | X5: 日期码格式：ZURU INC(BVI) 标准格式 日期：按实际生产日期 Packaging Info: 1.使用 MA UPC版本包装，优先1L，出口美国。 Remark: 1.产品和包装上印刷tracking code信息，格式为ZURU常规。 2.ZURU QC验货 | Y5: Cara Li | Z5: 8.1258 | AA5: =Z5*I5 -> 617.5608 | AC5: 9548-S001 | AD5: 已入 | AE5: =I5*0.2 -> 15.2 | AK5: =I5 -> 76 | AQ5: =I5 -> 76 | AX5: =I5 -> 76 | AY5: ='9548明细'!BB97+AX5 -> 778592
A6: 45771 | B6: ZURU Germany GMBH | C6: 德国 | D6: 4500164783 | E6: 5200006663 | F6: 4500164783-100 | G6: 9548-S005-NB-MTS | H6: 鸭妈妈 | I6: 600 | J6: 0 | K6: 3 | L6: =I6/K6 -> 200 | M6: 45804 | N6: 45800 | R6: 45772 | S6: 无 | T6: WEEE 30L 带电说明书+1张意大利回 收贴纸（翻4500133324） | U6: MA | X6: 日期码格式：ZURU INC(BVI) 标准格式 日期：按实际生产日期 Packaging Info: 10.9548：MA 3L（23L warning）EAN彩盒+MA 5L（9L Warning ）收藏指南+黑白5L（PL+HU+CZ+SK+RO)说明书（翻4500133324）+WEEE 30L 带电说明书+1张意大利回 收贴纸（翻4500133324）+MA5L（9L Warning）胶袋+1*5L 黑白slime 说明书； Remark: 1.波兰内销单，需要通过ZURU 验货结果后才能出货 (工厂需要主动提前同ZURU QC预约验货避免延期出货造成不必要麻烦)； 2. 若有特定款有特殊外箱条码要求时,需要明确列出产品款对应的具体外箱条码号码/条码类型 (若无,可以忽略此需求) 3.所有出口欧洲的产品, 法规规定禁止在包装和共公众用的印刷品中使用矿物油中含有的物质, 包装印刷油墨中含有的MOAH/MOSH的质量浓度不能超过1%, 否则出货 到法国被抽检出现问题, 供应商需要对此负责; 4. date code: 外箱日期码要晚于或等于产品日期码，不能早于产品的日期码 5. 所有电子产品身上需要加字唛，为ZURU FRANCE 地址 (如无电子产品，或者产品布标有此地址，可忽略此信息) ZURU France 1/3, Rue d'Argenteuil 95210 SAINT-GRATIEN, FRANCE 6. 装柜时需要按照款式号码从小到大一款款依次装,避免终端仓库卸货混乱.若一个柜子涉及到几个不同国家内销单,装柜时需要一个国家装完后再装另一个国家的 产品,依次装柜,避免终端仓库因不同国家不同库位位置卸货混乱. (此点需要同工厂装柜人员强调) | Y6: Amy Xiao | Z6: 7.5194 | AA6: =Z6*I6 -> 4511.64 | AC6: 9548-S005-NB-MTS | AD6: 已入 | AN6: =I6 -> 600 | AQ6: =I6 -> 600 | AX6: =I6 -> 600 | AY6: ='9548明细'!BB137+AX6 -> 1784
A7: 45803 | B7: KMART AUSTRALIA LTD(NEW ZEALAND) | C7: 新西兰 | D7: 4500166290 | E7: 20858536 | F7: 4500166290-60 | G7: 9548-S001 | H7: 鸭妈妈 | I7: 44 | J7: 0 | K7: 4 | L7: =I7/K7 -> 11 | M7: 45845 | N7: 45841 | O7: 6.5取消 | U7: MA | X7: 日期码格式：ZURU INC(BVI) 标准格式 日期：按实际生产日期 Packaging Info: 9548: MA英语UPC版本包装（收缩膜和说明书, MA首选1L，如无1L可用多语且含英语的配套多语包装) + 1张防盗贴纸 (贴纸以及位置图翻单PO#4500126567）+ 箱唛 + 外箱SSCC Label Remark: 1.请务必按时完货，验货。并且按期送货入货代指定仓库，如果晚了导致船期Delay将会有罚金产生或者客户要求空运，所产生的罚金和空运费由工厂承担。 2.SSCC 外箱贴纸请同纸箱瓦楞纸方向（竖纹向）垂直，即外箱贴纸横着贴(注意条码不要被胶带粘住），贴1pc，贴1面正唛，封箱胶纸不能挡住贴纸内容。外箱贴纸 离外箱边距离不少于2cm。 3.外箱材质为ZURU标准； 4.此单需使用KMART封箱胶上下工字型封箱;从2019年6月开始，要用KMART 新版封箱胶带，此单要用"ANKO"封箱胶带 5.此单出口新西兰，请按相应的澳新标准生产； 6.产品和包装上生产批号的显示格式ZURU标准日期码格式 7.外箱信息不可手写，重量和体积需要与实际的一致(不可手写） 8. 每款item装箱后的G.W.超过10KG或者CBM超过0.13,(9.5KG或者以上，四舍五入后也属于10KG) 需在外箱上加印超 重或者Bulky LOGO，若发现我们资料没有，请 帮忙提醒 1)重量超过10kg但不超过16kg且CBM不超过0.13,10-16kg 超重logo 2）CBM超过0.13且重量少于17kg，bulky logo 3）不属于以上两种情况，需要使用相应重量范围内的超重logo 4）超重logo需要在外箱四面都印刷(箱唛右上角，两面侧唛超重logo需要尽量靠近毛重)，尺寸为:110mm height* 95mm width 9. 实际外箱重量跟印在箱唛上的数据差异不能超3%，尺寸按实际数据印刷 | Y7: Lydia Wu | Z7: 8.1258 | AA7: =Z7*I7 -> 357.5352 | AE7: =I7*0.2 -> 8.8 | AZ7: =I7 -> 44 | BA7: ='9548明细'!BB182+AZ7 -> 795764
A8: 45803 | B8: KMART AUSTRALIA LTD | C8: 澳大利亚 | D8: 4500166289 | E8: 20858535 | F8: 4500166289-70 | G8: 9548-S001 | H8: 鸭妈妈 | I8: 1456 | J8: 0 | K8: 4 | L8: =I8/K8 -> 364 | M8: 45845 | N8: 45841 | O8: 取消 | U8: MA | X8: 日期码格式：ZURU INC(BVI) 标准格式 日期：按实际生产日期 Packaging Info: 9548: MA英语UPC版本包装（收缩膜和说明书, MA首选1L，如无1L可用多语且含英语的配套多语包装) + 1张防盗贴纸 (贴纸以及位置图翻单PO#4500126567）+ 箱唛 + 外箱SSCC Label Remark: 1.请务必按时完货，验货。并且按期送货入货代指定仓库，如果晚了导致船期Delay将会有罚金产生或者客户要求空运，所产生的罚金和空运费由工厂承担。 2.SSCC 外箱贴纸请同纸箱瓦楞纸方向（竖纹向）垂直，即外箱贴纸横着贴(注意条码不要被胶带粘住），贴1pc，贴1面正唛，封箱胶纸不能挡住贴纸内容。外箱贴纸 离外箱边距离不少于2cm。 3.外箱材质为ZURU标准； 4.此单需使用KMART封箱胶上下工字型封箱;从2019年6月开始，要用KMART 新版封箱胶带，此单要用"ANKO"封箱胶带 5.此单出口澳大利亚，请按相应的澳新标准生产； 6.产品和包装上生产批号的显示格式ZURU标准日期码格式 7.外箱信息不可手写，重量和体积需要与实际的一致(不可手写） 8. 每款item装箱后的G.W.超过10KG或者CBM超过0.13,(9.5KG或者以上，四舍五入后也属于10KG) 需在外箱上加印超 重或者Bulky LOGO，若发现我们资料没有，请 帮忙提醒 1)重量超过10kg但不超过16kg且CBM不超过0.13,10-16kg 超重logo 2）CBM超过0.13且重量少于17kg，bulky logo 3）不属于以上两种情况，需要使用相应重量范围内的超重logo 4）超重logo需要在外箱四面都印刷(箱唛右上角，两面侧唛超重logo需要尽量靠近毛重)，尺寸为:110mm height* 95mm width 9. 实际外箱重量跟印在箱唛上的数据差异不能超3%，尺寸按实际数据印刷 | Y8: Lydia Wu | Z8: 8.1045 | AA8: =Z8*I8 -> 11800.152 | AE8: =I8*0.2 -> 291.2 | AZ8: =I8 -> 1456 | BA8: ='9548明细'!BB145+AZ8 -> 787600
A9: 45912 | B9: KMART AUSTRALIA LTD(NEW ZEALAND) | C9: 新西兰 | D9: 4500179341 | E9: 21105434 | F9: 4500179341-70 | G9: 9548-S001 | H9: 鸭妈妈 | I9: 48 | J9: 0 | K9: 4 | L9: =I9/K9 -> 12 | M9: 45957 | N9: 45953 | U9: MA | X9: 日期码格式：ZURU INC(BVI) 标准格式 日期：按实际生产日期 Packaging Info: 9548: MA英语UPC版本包装（收缩膜和说明书, MA首选1L，如无1L可用多语且含英语的配套多语包装) + 1张防盗贴纸 (贴纸以及位置图翻单PO#4500126567）+ 箱唛 + 外箱SSCC Label Remark: 1.请务必按时完货，验货。并且按期送货入货代指定仓库，如果晚了导致船期Delay将会有罚金产生或者客户要求空运，所产生的罚金和空运费由工厂承担。 2.SSCC 外箱贴纸请同纸箱瓦楞纸方向（竖纹向）垂直，即外箱贴纸横着贴(注意条码不要被胶带粘住），贴1pc，贴1面正唛，封箱胶纸不能挡住贴纸内容。外箱贴纸 离外箱边距离不少于2cm。 3.外箱材质为ZURU标准； 4.此单需使用KMART封箱胶上下工字型封箱;从2019年6月开始，要用KMART 新版封箱胶带，此单要用"ANKO"封箱胶带 5.此单出口新西兰，请按相应的澳新标准生产； 6.产品和包装上生产批号的显示格式ZURU标准日期码格式 7.外箱信息不可手写，重量和体积需要与实际的一致(不可手写） 8. 每款item装箱后的G.W.超过10KG或者CBM超过0.13,(9.5KG或者以上，四舍五入后也属于10KG) 需在外箱上加印超 重或者Bulky LOGO，若发现我们资料没有，请 帮忙提醒 1)重量超过10kg但不超过16kg且CBM不超过0.13,10-16kg 超重logo 2）CBM超过0.13且重量少于17kg，bulky logo 3）不属于以上两种情况，需要使用相应重量范围内的超重logo 4）超重logo需要在外箱四面都印刷(箱唛右上角，两面侧唛超重logo需要尽量靠近毛重)，尺寸为:110mm height* 95mm width 9. 实际外箱重量跟印在箱唛上的数据差异不能超3%，尺寸按实际数据印刷 | Y9: Lydia Wu | Z9: 8.1258 | AA9: =Z9*I9 -> 390.0384 | BA9: =I9 -> 48 | BB9: ='9548明细'!BB177+BA9 -> 788480
A10: 45912 | B10: KMART AUSTRALIA LTD | C10: 澳大利亚 | D10: 4500179340 | E10: 21105432 | F10: 4500179340-70 | G10: 9548-S001 | H10: 鸭妈妈 | I10: 1452 | J10: 0 | K10: 4 | L10: =I10/K10 -> 363 | M10: 45957 | N10: 45953 | U10: MA | X10: 日期码格式：ZURU INC(BVI) 标准格式 日期：按实际生产日期 Packaging Info: 9548: MA英语UPC版本包装（收缩膜和说明书, MA首选1L，如无1L可用多语且含英语的配套多语包装) + 1张防盗贴纸 (贴纸以及位置图翻单PO#4500126567）+ 箱唛 + 外箱SSCC Label Remark: 1.请务必按时完货，验货。并且按期送货入货代指定仓库，如果晚了导致船期Delay将会有罚金产生或者客户要求空运，所产生的罚金和空运费由工厂承担。 2.SSCC 外箱贴纸请同纸箱瓦楞纸方向（竖纹向）垂直，即外箱贴纸横着贴(注意条码不要被胶带粘住），贴1pc，贴1面正唛，封箱胶纸不能挡住贴纸内容。外箱贴纸 离外箱边距离不少于2cm。 3.外箱材质为ZURU标准； 4.此单需使用KMART封箱胶上下工字型封箱;从2019年6月开始，要用KMART 新版封箱胶带，此单要用"ANKO"封箱胶带 5.此单出口澳大利亚，请按相应的澳新标准生产； 6.产品和包装上生产批号的显示格式ZURU标准日期码格式 7.外箱信息不可手写，重量和体积需要与实际的一致(不可手写） 8. 每款item装箱后的G.W.超过10KG或者CBM超过0.13,(9.5KG或者以上，四舍五入后也属于10KG) 需在外箱上加印超 重或者Bulky LOGO，若发现我们资料没有，请 帮忙提醒 1)重量超过10kg但不超过16kg且CBM不超过0.13,10-16kg 超重logo 2）CBM超过0.13且重量少于17kg，bulky logo 3）不属于以上两种情况，需要使用相应重量范围内的超重logo 4）超重logo需要在外箱四面都印刷(箱唛右上角，两面侧唛超重logo需要尽量靠近毛重)，尺寸为:110mm height* 95mm width 9. 实际外箱重量跟印在箱唛上的数据差异不能超3%，尺寸按实际数据印刷 | Y10: Lydia Wu | Z10: 8.1045 | AA10: =Z10*I10 -> 11767.734 | BA10: =I10 -> 1452 | BB10: ='9548明细'!BB178+BA10 -> 783364
A12: 45774 | B12: WALMART INC. | C12: 美国 | D12: 4500165176 | E12: 0923153980 | F12: 4500165176-20 | G12: 9548-S002 | H12: 鸭妈妈 | I12: 110 | J12: 0 | K12: 1 | L12: =I12/K12 -> 110 | M12: 45854 | N12: =M12-4 -> 45850 | O12: 客人取消 | P12: PASS | R12: 45738 | S12: 无 | T12: 客版布标贴纸，5/12客供RFID贴纸（标贴位置严格按照我们签板的 位置图，不可擅自调整位置，贴纸不能有任何破损或折坏，不可淋湿）。 | U12: MA | X12: 日期码格式：ZURU DGYYYYMMDD CHINA(日期避开周末和法定节假日即可） 日期：按实际生产日期 Packaging Info: 9548 1.包装信息：MA B版 UPC版 1L包装，MA 5L B版说明书，MA 5L B版口水胶袋，MA 2L C版车缝布标，客版布标贴纸，客供RFID贴纸（标贴位置严格按照我们签板的 位置图，不可擅自调整位置，贴纸不能有任何破损或折坏，不可淋湿）。 Remark: 9548 1.包装信息：MA B版 UPC版 1L包装，MA 5L B版说明书，MA 5L B版口水胶袋，MA 2L C版车缝布标，客版布标贴纸，客供RFID贴纸（标贴位置严格按照我们签板的 位置图，不可擅自调整位置，贴纸不能有任何破损或折坏，不可淋湿）。 2. 外箱印刷带条码的RFID箱唛：RFID紫色色带+WM Dept.图标+RFID图标+ITF-14条码+粉色艾利贴纸（不干胶打印），四面右下角印刷ZURU logo, ITFF条码只印刷在 正唛一面，在加印的时候确保条形码能扫描出来，1张粉红色贴纸贴在正唛对角线，外箱侧面任一角落加印："MADE IN CHINA" 字样； 3.在产品上和包装上要有日期码（避开周末和节假日），以及要有MADE IN CHINA和ZURU字样。 4.产品如有扎带口要剪平，不能刮手。 5. 此单以散箱出货，9548：1pcs/CTN 6.此单需要第三方验货，请自行多备物料。 7.其它信息：3pcs*AAA battery not include。 | Y12: Maggie Xie | Z12: 4.5054 | AA12: =Z12*I12 -> 495.594 | AC12: 9548-S002 | AD12: 已入 | AE12: =I12*0.2 -> 22 | AK12: =I12 -> 110 | AS12: =I12 -> 110 | BA12: =I12 -> 110 | BB12: =取消单!BB16+BA12 -> 778942
A13: 45774 | B13: WALMART INC. | C13: 美国 | D13: 4500165176 | E13: 0923153985 | F13: 4500165176-10 | G13: 9548-S002 | H13: 鸭妈妈 | I13: 88 | J13: 0 | K13: 1 | L13: =I13/K13 -> 88 | M13: 45859 | N13: =M13-4 -> 45855 | O13: 客人取消 | P13: PASS | R13: 45738 | S13: 无 | T13: 客版布标贴纸，5/12客供RFID贴纸（标贴位置严格按照我们签板的 位置图，不可擅自调整位置，贴纸不能有任何破损或折坏，不可淋湿）。 | U13: MA | X13: 日期码格式：ZURU DGYYYYMMDD CHINA(日期避开周末和法定节假日即可） 日期：按实际生产日期 Packaging Info: 9548 1.包装信息：MA B版 UPC版 1L包装，MA 5L B版说明书，MA 5L B版口水胶袋，MA 2L C版车缝布标，客版布标贴纸，客供RFID贴纸（标贴位置严格按照我们签板的 位置图，不可擅自调整位置，贴纸不能有任何破损或折坏，不可淋湿）。 Remark: 9548 1.包装信息：MA B版 UPC版 1L包装，MA 5L B版说明书，MA 5L B版口水胶袋，MA 2L C版车缝布标，客版布标贴纸，客供RFID贴纸（标贴位置严格按照我们签板的 位置图，不可擅自调整位置，贴纸不能有任何破损或折坏，不可淋湿）。 2. 外箱印刷带条码的RFID箱唛：RFID紫色色带+WM Dept.图标+RFID图标+ITF-14条码+粉色艾利贴纸（不干胶打印），四面右下角印刷ZURU logo, ITFF条码只印刷在 正唛一面，在加印的时候确保条形码能扫描出来，1张粉红色贴纸贴在正唛对角线，外箱侧面任一角落加印："MADE IN CHINA" 字样； 3.在产品上和包装上要有日期码（避开周末和节假日），以及要有MADE IN CHINA和ZURU字样。 4.产品如有扎带口要剪平，不能刮手。 5. 此单以散箱出货，9548：1pcs/CTN 6.此单需要第三方验货，请自行多备物料。 7.其它信息：3pcs*AAA battery not include。 | Y13: Maggie Xie | Z13: 4.5054 | AA13: =Z13*I13 -> 396.4752 | AC13: 9548-S002 | AD13: 已入 | AE13: =I13*0.2 -> 17.6 | AK13: =I13 -> 88 | AS13: =I13 -> 88 | BA13: =I13 -> 88 | BB13: ='9548明细'!BB135+BA13 -> 88
A14: 45611 | B14: DM LLC | C14: 俄罗斯联邦 | D14: 4500151414 | E14: 出Bekasovo 2 | F14: 4500151414-80 | G14: 9548-S001 | H14: 鸭妈妈 | I14: 340 | J14: 0 | K14: 4 | L14: =I14/K14 -> 85 | M14: 45847 | N14: 45843 | P14: PASS | R14: 45615 | S14: 无 | T14: 进口商贴纸翻4500151398+ EAN条码贴纸翻4500151398 | U14: MA | W14: 外包装(指: 收缩膜/彩卡/吊牌/PDQ)/外箱不要打ZURU标准日期码！ | X14: 日期码格式：外包装/外箱不要打ZURU标准日期码 日期： Packaging Info: 注意 ：外包装 (指: 收缩膜/彩卡/铝箔袋/挂卡/PDQ) /外箱不要打ZURU标准日期码！胶件可以打日期码。 9548 : 1L MA 收缩膜 or 彩卡 + 进口商贴纸翻4500151398+ EAN条码贴纸翻4500151398，MA 指南 /说明书（如有）； Remark: | Y14: Ann Zhang | Z14: 7.6392 | AA14: =Z14*I14 -> 2597.328 | AC14: 9548-S001 | AD14: 已入 | AE14: =I14*0.2 -> 68 | AK14: =I14 -> 340 | AS14: =I14 -> 340 | BA14: =I14 -> 340 | BB14: ='9548明细'!BB152+BA14 -> 786320
A15: 45611 | B15: DM LLC | C15: 俄罗斯联邦 | D15: 4500151414 | E15: 出Ural | F15: 4500151414-170 | G15: 9548-S001 | H15: 鸭妈妈 | I15: 148 | J15: 0 | K15: 4 | L15: =I15/K15 -> 37 | M15: 45847 | N15: 45843 | P15: PASS | R15: 45615 | S15: 无 | T15: 进口商贴纸翻4500151398+ EAN条码贴纸翻4500151398 | U15: MA | W15: 外包装(指: 收缩膜/彩卡/吊牌/PDQ)/外箱不要打ZURU标准日期码！ | X15: 日期码格式：外包装/外箱不要打ZURU标准日期码 日期： Packaging Info: 注意 ：外包装 (指: 收缩膜/彩卡/铝箔袋/挂卡/PDQ) /外箱不要打ZURU标准日期码！胶件可以打日期码。 9548 : 1L MA 收缩膜 or 彩卡 + 进口商贴纸翻4500151398+ EAN条码贴纸翻4500151398，MA 指南 /说明书（如有）； Remark: | Y15: Ann Zhang | Z15: 7.3292 | AA15: =Z15*I15 -> 1084.7216 | AC15: 9548-S001 | AD15: 已入 | AE15: =I15*0.2 -> 29.6 | AK15: =I15 -> 148 | AS15: =I15 -> 148 | BA15: =I15 -> 148 | BB15: ='9548明细'!BB153+BA15 -> 787352
A16: 45611 | B16: DM LLC | C16: 俄罗斯联邦 | D16: 4500151404 | E16: 出Bekasovo 2 | F16: 4500151404-70 | G16: 9548-S001 | H16: 鸭妈妈 | I16: 340 | J16: 0 | K16: 4 | L16: =I16/K16 -> 85 | M16: 45817 | N16: 45813 | P16: PASS | R16: 45615 | S16: 无 | T16: 进口商贴纸翻4500151398+ EAN条码贴纸翻4500151398 | U16: MA | W16: 外包装(指: 收缩膜/彩卡/吊牌/PDQ)/外箱不要打ZURU标准日期码！ | X16: 日期码格式：外包装/外箱不要打ZURU标准日期码 日期： Packaging Info: 注意 ：外包装 (指: 收缩膜/彩卡/铝箔袋/挂卡/PDQ) /外箱不要打ZURU标准日期码！胶件可以打日期码。 9548 : 1L MA 收缩膜 or 彩卡 + 进口商贴纸翻4500151398+ EAN条码贴纸翻4500151398，MA 指南 /说明书（如有）； Remark: 标准配比 出BEKASOVO 2 和Ural 2 个港口； 货期不可延， 有罚金 。 | Y16: Ann Zhang | Z16: 7.3075 | AA16: =Z16*I16 -> 2484.55 | AC16: 9548-S001 | AD16: 已入 | AE16: =I16*0.2 -> 68 | AK16: =I16 -> 340 | AS16: =I16 -> 340 | BA16: =I16 -> 340 | BB16: ='9548明细'!BB95+BA16 -> 778832
A17: 45611 | B17: DM LLC | C17: 俄罗斯联邦 | D17: 4500151404 | E17: 出Ural | F17: 4500151404-150 | G17: 9548-S001 | H17: 鸭妈妈 | I17: 168 | J17: 0 | K17: 4 | L17: =I17/K17 -> 42 | M17: 45817 | N17: 45813 | P17: PASS | R17: 45615 | S17: 无 | T17: 进口商贴纸翻4500151398+ EAN条码贴纸翻4500151398 | U17: MA | W17: 外包装(指: 收缩膜/彩卡/吊牌/PDQ)/外箱不要打ZURU标准日期码！ | X17: 日期码格式：外包装/外箱不要打ZURU标准日期码 日期： Packaging Info: 注意 ：外包装 (指: 收缩膜/彩卡/铝箔袋/挂卡/PDQ) /外箱不要打ZURU标准日期码！胶件可以打日期码。 9548 : 1L MA 收缩膜 or 彩卡 + 进口商贴纸翻4500151398+ EAN条码贴纸翻4500151398，MA 指南 /说明书（如有）； Remark: 标准配比 出BEKASOVO 2 和Ural 2 个港口； 货期不可延， 有罚金 。 | Y17: Ann Zhang | Z17: 7.3075 | AA17: =Z17*I17 -> 1227.66 | AC17: 9548-S001 | AD17: 已入 | AE17: =I17*0.2 -> 33.6 | AK17: =I17 -> 168 | AS17: =I17 -> 168 | BA17: =I17 -> 168 | BB17: ='9548明细'!BB96+BA17 -> 784112
A21: 45821 | B21: KMART AUSTRALIA LTD | C21: 澳大利亚 | D21: 4500169286 | E21: 20926265 | F21: 4500169286-70 | G21: 9548-S001 | H21: 鸭妈妈 | I21: 2096 | J21: 0 | K21: 4 | L21: =I21/K21 -> 524 | M21: 45859 | N21: 45855 | R21: 欠 | S21: 有 | T21: 6/18 1张防盗贴纸 (贴纸以及位置图翻单PO#4500126567 | U21: MA | X21: 日期码格式：ZURU INC(BVI) 标准格式 日期：按实际生产日期 Packaging Info: 9548: MA英语UPC版本包装（收缩膜和说明书, MA首选1L，如无1L可用多语且含英语的配套多语包装) + 1张防盗贴纸 (贴纸以及位置图翻单PO#4500126567）+ 箱唛 + 外箱SSCC Label Remark: 1.请务必按时完货，验货。并且按期送货入货代指定仓库，如果晚了导致船期Delay将会有罚金产生或者客户要求空运，所产生的罚金和空运费由工厂承担。 2.SSCC 外箱贴纸请同纸箱瓦楞纸方向（竖纹向）垂直，即外箱贴纸横着贴(注意条码不要被胶带粘住），贴1pc，贴1面正唛，封箱胶纸不能挡住贴纸内容。外箱贴纸 离外箱边距离不少于2cm。 3.外箱材质为ZURU标准； 4.此单需使用KMART封箱胶上下工字型封箱;从2019年6月开始，要用KMART 新版封箱胶带，此单要用"ANKO"封箱胶带 5.此单出口澳大利亚，请按相应的澳新标准生产； 6.产品和包装上生产批号的显示格式ZURU标准日期码格式 7.外箱信息不可手写，重量和体积需要与实际的一致(不可手写） 8. 每款item装箱后的G.W.超过10KG或者CBM超过0.13,(9.5KG或者以上，四舍五入后也属于10KG) 需在外箱上加印超 重或者Bulky LOGO，若发现我们资料没有，请 帮忙提醒 1)重量超过10kg但不超过16kg且CBM不超过0.13,10-16kg 超重logo 2）CBM超过0.13且重量少于17kg，bulky logo 3）不属于以上两种情况，需要使用相应重量范围内的超重logo 4）超重logo需要在外箱四面都印刷(箱唛右上角，两面侧唛超重logo需要尽量靠近毛重)，尺寸为:110mm height* 95mm width 9. 实际外箱重量跟印在箱唛上的数据差异不能超3%，尺寸按实际数据印刷 | Y21: Lydia Wu | Z21: 8.0826 | AA21: =Z21*I21 -> 16941.13 | AC21: 9548-S001 | AD21: 已入 | AE21: =I21*0.2 -> 419.2 | AK21: =I21 -> 2096 | AS21: =I21 -> 2096 | BA21: =I21 -> 2096 | BB21: ='9548明细'!BB186+BA21 -> 790388
