Workbook
Name cavity: '[1]Form-003'!#REF!
Name Code: '[2]CQS Code(rev 38)'!$B$7:$E$1000
Name cycle.time: '[1]Form-003'!#REF!
Name GDE: [3]基础表!#REF!
Name mold.color: '[1]Form-003'!#REF!
Name mold.cost: '[1]Form-003'!#REF!
Name mold.height: '[1]Form-003'!#REF!
Name mold.length: '[1]Form-003'!#REF!
Name mold.material: '[1]Form-003'!#REF!
Name mold.name: '[1]Form-003'!#REF!
Name mold.number: '[1]Form-003'!#REF!
Name mold.partweight: '[1]Form-003'!#REF!
Name mold.usage: '[1]Form-003'!#REF!
Name mold.width: '[1]Form-003'!#REF!
Name new_sum: #REF!
Name part.list: '[1]Form-003'!#REF!
Name PI_IN: #REF!
Name PI_SUM: #REF!
Name PI_SUM_SALES: #REF!
Name Prepared.By: '[1]Form-003'!#REF!
Name Ref.Number: '[1]Form-003'!#REF!
Name Revised.By: '[1]Form-003'!#REF!
Name sd: [3]基础表!#REF!
Name tool.plan: '[1]Form-003'!#REF!
Name up: '[1]Form-003'!#REF!
Name Vendor: '[1]Form-003'!#REF!
Name 类别: [3]基础表!#REF!
Name 类别1: [3]基础表!#REF!
Name 领料单: [3]基础表!#REF!
Name 收料单: [3]基础表!#REF!
Name 一部: [3]基础表!#REF!

Sheet 77555旧排期
A1: ZURU （77555 迷你房子）生产排期表 | F1: 变更原因:根据市场要求，Mini Home出货需取消UV胶→ 根据美国市场要求，Mini Home出货需取消UV胶 更后内容: 3款稀有款出货不带UV胶- 3款稀有款出美国市场不带UV胶 目前美国市场的订单需要移除UV胶水出货，需要采用新版本的收缩膜和收藏指南，待10月底客人通知切换 | AG1: 第一张MA是订购A版本，第二张MA订购B版本，A和B版本区别在于德语的警语不一样，A版本不能出德国
AJ2: 收縮膜 | AQ2: 134013 | AS2: 收藏指南 | AY2: GQ6 | AZ2: GQ6 | BA2: GQ4 | BB2: FD GQ7 | BC2: GQ1 | BF2: GQ2 | BI2: GQ3 | BJ2: SQ1 | BK2: 不带底座 | BL2: 3L | BM2: 1L | BN2: 3L | BO2: 77556 圆筒 | BR2: 77584 圆筒
A3: 香港接单日期 | B3: 第三方客户名称 | C3: 走货国家 | D3: ZURU PO NO# | E3: 第三方客户 PO NO# | F3: SKU | G3: ITEM# | H3: 中文名 | I3: PO数量 (pcs) | J3: 内箱装箱数量(pcs) | K3: 外箱装箱数量(pcs) | L3: 总箱数 | M3: 客PO期 | N3: 验货期 | O3: 第三方验货期 | P3: 驗貨結果 | Q3: S/0船期 | R3: 箱唛资料(收到日期) | S3: 外箱贴纸 | T3: 客供贴纸AI(收到日期) | U3: 备注 | V3: ZURU 跟单 | W3: 单价USD | X3: 金额USD | Y3: 發票號 | Z3: 系统货号 | AA3: 是否入系统 | AB3: 系统出单 | AC3: 送货情况 | AD3: 欠数 | AE3: 贴纸 | AF3: 错误印刷内容3L内收缩膜 | AG3: 纸袋A/B | AH3: 球数 | AI3: 散件/空PDQ | AJ3: MA 1语 | AK3: MA 3语 | AL3: 1L-B版本 | AM3: 无UPC版本 | AN3: DG 客版 | AO3: TG客版 | AP3: WMCA客版 | AQ3: MGS客版 | AR3: GP 客版 | AS3: MA 5L语 | AT3: 5L-B版本 | AU3: 外挂收藏指南+中文说明书（每一款都不同，请做好区分） | AV3: wm us客版 | AW3: ESAL 客版 | AX3: GP 客版 | AY3: WMM 客版 | AZ3: 取消UV胶版本 | BA3: 1L | BB3: 客版 | BC3: 1L | BD3: 1L-B版本 | BE3: 3L | BF3: 1L | BG3: 1L-B版本 | BH3: 3L | BI3: 客版 | BJ3: 客版 | BK3: 77555SK-S001 | BL3: SK-S002 60PCS | BM3: SK1-S002 30PCS | BN3: SK1-S002 30PCS | BO3: 圆筒 | BP3: 铜板纸 | BQ3: 贴纸 | BR3: 圆筒 | BS3: 铜板纸 | BT3: 贴纸
A4: 45293 | B4: ZURU | C4: 库有 | D4: ZPO2401001 | E4: PP订单 | G4: 77555GQ2-S001 | H4: 迷你房子 | I4: 630 | K4: 50 | L4: =I4/K4 -> 12.6 | M4: 45315 | N4: 45315 | P4: PASS | R4: 周转箱 | S4: 无 | T4: 无 | U4: 请留意PP当天需要至少有2箱成品完成，如有必要请提前准备好半成品，谢谢！ | V4: Lynn | Y4: 84832-5.20 | Z4: # | AH4: =I4 -> 630 | BH4: =I4/25 -> 25.2
A5: 45293 | B5: ZURU | C5: 库有 | D5: ZMPO24010 | E5: PP | G5: 77555-S001 | H5: 迷你房子 | I5: 1000 | K5: 50 | L5: =I5/K5 -> 20 | M5: 45293 | P5: PASS | R5: 周转箱 | S5: 无 | T5: 无 | U5: 跟PP订单一起安排/麻烦按款号装箱 | V5: sally li | Y5: 84831-5.20 | Z5: # | AG5: A | AH5: =I5 -> 1000
A6: 45293 | B6: ZURU | C6: 库有 | D6: ZMPO24010 | E6: PP | G6: 77555-S001 | H6: 30套散件 | I6: 30 | K6: 50 | L6: =I6/K6 -> 0.6 | M6: 45293 | P6: PASS | R6: 周转箱 | S6: 无 | T6: 无 | U6: 跟PP订单一起安排/只需要全套散件，麻烦用胶袋分装好一套为一袋 | V6: sally li | Y6: 84831-5.20 | Z6: # | AC6: 30 | AI6: =I6 -> 30
A7: 45293 | B7: ZURU | C7: 库有 | D7: ZMPO24010 | E7: PP | G7: 77555GQ2-S001 | H7: 10个空PDQ | I7: 10 | K7: 50 | L7: =I7/K7 -> 0.2 | M7: 45293 | P7: PASS | R7: 周转箱 | S7: 无 | T7: 无 | U7: 跟PP订单一起安排/只需空PDQ+吸塑+展示公仔 | V7: sally li | Y7: 84831-5.20 | Z7: # | AI7: =I7 -> 10
A8: 45348 | B8: ZURU | C8: 库有 | D8: ZMPO24128 | G8: 77555GQ2-S001 | H8: 30套 | I8: 30 | K8: 50 | L8: =I8/K8 -> 0.6 | M8: 45357 | N8: 45353 | R8: 周转箱 | S8: 无 | T8: 无 | U8: 左图中4款小散件需要组装好+配套吸塑 | V8: sally li | Y8: 84848-5.21 | Z8: # | AC8: 30 | AI8: =I8 -> 30
A9: 45350 | B9: ZURU | C9: 库有 | D9: ZMPO24135 | G9: 77555-S001 | H9: 50套散件 | I9: 50 | J9: 0 | K9: 24 | L9: =I9/K9 -> 2.0833333 | M9: 45371 | N9: 45367 | R9: 周转箱 | S9: 无 | T9: 无 | U9: 大货最新版本/只需要齐全套散件，麻烦用胶袋分装好一套为一袋 | V9: sally li | Y9: 84849-5.21 | Z9: # | AC9: 30 | AI9: =I9 -> 50
A10: 45350 | B10: ZURU | C10: 库有 | D10: ZMPO24135 | G10: 77555-S001 | H10: 迷你房子 | I10: 1000 | J10: 0 | K10: 24 | L10: =I10/K10 -> 41.666667 | M10: 45371 | N10: 45367 | P10: pass | R10: 周转箱 | S10: 无 | T10: 无 | U10: 大货最新版本/款号数量平均/麻烦按款号装箱/并在外箱上注明款号/请用大货/箱唛请参照邮件附件 | V10: sally li | Y10: 84849-5.21 | Z10: 77555-S001 | AA10: 已入 | AB10: 系统出单 | AC10: 1000 | AG10: A | AH10: =I10 -> 1000 | AJ10: =I10 -> 1000 | AS10: =I10 -> 1000
A11: 45350 | B11: ZURU | C11: 库有 | D11: ZMPO24135 | G11: 77555GQ1-S001 | H11: 迷你房子 | I11: 650 | J11: 0 | K11: 13 | L11: =I11/K11 -> 50 | M11: 45371 | N11: 45367 | P11: pass | R11: 周转箱 | S11: 无 | T11: 无 | U11: 大货最新版本/PDQ里面的产品按大货比例入PDQ/大货标准箱装箱/箱唛参照邮件附件 | V11: sally li | Y11: 84849-5.21 | Z11: # | AC11: 650 | AG11: A | AH11: =I11 -> 650 | AJ11: =I11 -> 650 | AS11: =I11 -> 650 | BC11: =I11/13 -> 50
A12: 45350 | B12: ZURU | C12: 库有 | D12: ZMPO24135 | G12: 77555GQ2-S001 | H12: 迷你房子25pcsGQ2*2/箱 | I12: 2000 | K12: 50 | L12: =I12/K12 -> 40 | M12: 45371 | N12: 45367 | P12: pass | R12: 周转箱 | S12: 无 | T12: 无 | U12: 大货最新版本/PDQ里面的产品按大货比例入PDQ/大货标准箱装箱/箱唛参照邮件附件 | V12: sally li | Y12: 84849-5.21 | Z12: 77555GQ2-S001 | AA12: 已入 | AB12: 系统出单 | AC12: 2000 | AG12: A | AH12: =I12 -> 2000 | AJ12: =I12 -> 2000 | AS12: =I12 -> 2000 | BF12: =I12/25 -> 80
A13: 45363 | B13: ZURU | C13: 库有 | D13: ZMPO24189 | G13: 77555SK-S002 | H13: 迷你房子展示架 | I13: 480 | J13: 0 | K13: 60 | L13: =I13/K13 -> 8 | M13: 45381 | N13: 45377 | P13: pass | R13: 周转箱 | S13: 无 | T13: 无 | U13: 大货最新版本/产品按大货比例入展示架/箱唛请参照邮件附件 | V13: sally li | Y13: 85334-6.13 | Z13: # | AC13: 480 | AG13: A | AH13: =I13 -> 480 | AJ13: =I13 -> 480 | AS13: =I13 -> 480 | BL13: =I13/60 -> 8
A14: 45341 | B14: COLES SUPERMARKETS | C14: 澳大利亚 | D14: 4500124295 | E14: 43092050 SYD | F14: 4500124295-10 | G14: 77555GQ4-S001 | H14: 迷你房子GQ4/6pcs/箱 | I14: 768 | J14: 0 | K14: 6 | L14: =I14/K14 -> 128 | M14: 45392 | N14: 45388 | P14: pass | Q14: 4/15 交仓 | R14: 45328 | S14: 无 | T14: 无 | U14: 日期码格式：ZURU INC(BVI) 标准格式 日期：按实际生产日期 Packaging Info: 1. 包装 MA UPC PACKAGING Remark: 1.此单出口澳大利亚，请按相应的澳新标准生产； 2.产品和包装上生产批号请按我司标准 | V14: Lillian Li | W14: 1.6 | X14: =W14*I14 -> 1228.8 | Y14: 84798-5.17 | Z14: 77555GQ4-S001 | AA14: 已入 | AB14: 系统出单 | AC14: 768 | AD14: =AC14-I14 -> 0 | AE14: 无 | AG14: A | AH14: =I14 -> 768 | AJ14: =I14 -> 768 | AS14: =I14 -> 768 | BA14: =I14/6 -> 128
A15: 45341 | B15: COLES SUPERMARKETS | C15: 澳大利亚 | D15: 4500124295 | E15: 43092054 MEL | F15: 4500124295-30 | G15: 77555GQ4-S001 | H15: 迷你房子GQ4/6pcs/箱 | I15: 1578 | J15: 0 | K15: 6 | L15: =I15/K15 -> 263 | M15: 45392 | N15: 45388 | P15: pass | Q15: 4/15 交仓 | R15: 45328 | S15: 无 | T15: 无 | U15: 日期码格式：ZURU INC(BVI) 标准格式 日期：按实际生产日期 Packaging Info: 1. 包装 MA UPC PACKAGING Remark: 1.此单出口澳大利亚，请按相应的澳新标准生产； 2.产品和包装上生产批号请按我司标准 | V15: Lillian Li | W15: 1.6 | X15: =W15*I15 -> 2524.8 | Y15: 84798-5.17 | Z15: 77555GQ4-S001 | AA15: 已入 | AB15: 系统出单 | AC15: 1578 | AD15: =AC15-I15 -> 0 | AE15: 无 | AG15: A | AH15: =I15 -> 1578 | AJ15: =I15 -> 1578 | AS15: =I15 -> 1578 | BA15: =I15/6 -> 263
A16: 45341 | B16: COLES SUPERMARKETS | C16: 澳大利亚 | D16: 4500124295 | E16: 43102295 BNE | F16: 4500124295-50 | G16: 77555GQ4-S001 | H16: 迷你房子GQ4/6pcs/箱 | I16: 1098 | J16: 0 | K16: 6 | L16: =I16/K16 -> 183 | M16: 45392 | N16: 45388 | P16: pass | Q16: 4/15 交仓 | R16: 45328 | S16: 无 | T16: 无 | U16: 日期码格式：ZURU INC(BVI) 标准格式 日期：按实际生产日期 Packaging Info: 1. 包装 MA UPC PACKAGING Remark: 1.此单出口澳大利亚，请按相应的澳新标准生产； 2.产品和包装上生产批号请按我司标准 | V16: Lillian Li | W16: 1.6 | X16: =W16*I16 -> 1756.8 | Y16: 84798-5.17 | Z16: 77555GQ4-S001 | AA16: 已入 | AB16: 系统出单 | AC16: 1098 | AD16: =AC16-I16 -> 0 | AE16: 无 | AG16: A | AH16: =I16 -> 1098 | AJ16: =I16 -> 1098 | AS16: =I16 -> 1098 | BA16: =I16/6 -> 183
A17: 45355 | B17: KMART AUSTRALIA LTD(NEW ZEALAND) | C17: 新西兰 | D17: 4500125859 | E17: 19946678 | F17: 4500125859-10 | G17: 77555GQ1-S002 | H17: 迷你房子GQ1/13PCS/箱 | I17: 702 | J17: 0 | K17: 13 | L17: =I17/K17 -> 54 | M17: 45392 | N17: 45388 | P17: pass | R17: 45365 | S17: 有 | T17: 3/19箱唛贴纸 防盗贴纸翻单125858 | U17: 日期码格式：ZURU INC(BVI) 标准格式 日期：按实际生产日期 Packaging Info: 1.77555GQ1:MA英语UPC版本包装（首选1LUPC，如果无1L可用多语含英语UPC版本）+防盗贴纸+箱唛+箱唛贴纸(1PCS/CTN).防盗贴纸及其位置图请跟回PO#4500125858; Remark: 1,请务必按时完货，验货并请按期送货入货代指定仓库，如果晚了导致船期Delay将会有罚金产生或者客户要求空运，所产生的罚金和空运费由工厂承担。 2.SSCC 外箱贴纸请同纸箱瓦楞纸方向（竖纹向）垂直，即外箱贴纸横着贴(注意条码不要被胶带粘住），贴1pc，贴1面正唛，封箱胶纸不能挡住贴纸内容。每pcs外 箱贴纸都是唯一的，不可重复粘贴，否则会有罚款产生。 3.外箱材质为ZURU标准； 4.此单需使用KMART封箱胶上下工字型封箱;从2019年6月开始，要用KMART 新版封箱胶带，此单要用"ANKO"封箱胶带 5.此单出口新西兰，请按相应的澳新标准生产； 6.产品和包装上生产批号的显示格式ZURU标准日期码格式 7.RATIO: | V17: Sara Wang | W17: 1.55 | X17: =W17*I17 -> 1088.1 | Y17: 84792-5.17 | Z17: 77555GQ1-S002 | AA17: 已入 | AB17: 系统出单 | AC17: 702 | AD17: =AC17-I17 -> 0 | AE17: OK | AG17: A | AH17: =I17 -> 702 | AJ17: =I17 -> 702 | AS17: =I17 -> 702 | BC17: =I17/13 -> 54
A18: 45355 | B18: KMART AUSTRALIA LTD | C18: 澳大利亚 | D18: 4500125858 | E18: 19946677 | F18: 4500125858-10 | G18: 77555GQ1-S002 | H18: 迷你房子GQ1/13PCS/箱 | I18: 4914 | J18: 0 | K18: 13 | L18: =I18/K18 -> 378 | M18: 45392 | N18: 45388 | P18: pass | R18: 45365 | S18: 有 | T18: 3/19箱唛贴纸 防盗贴纸自行订购 | U18: 日期码格式：ZURU INC(BVI) 标准格式 日期：按实际生产日期 Packaging Info: 1.77555GQ1:MA英语UPC版本包装（首选1LUPC，如果无1L可用多语含英语UPC版本）+防盗贴纸+箱唛+箱唛贴纸(1PCS/CTN).防盗贴纸贴在球顶部空白处，大货生产前请返回位置图确认; Remark: 1,请务必按时完货，验货并请按期送货入货代指定仓库，如果晚了导致船期Delay将会有罚金产生或者客户要求空运，所产生的罚金和空运费由工厂承担。 2.SSCC 外箱贴纸请同纸箱瓦楞纸方向（竖纹向）垂直，即外箱贴纸横着贴(注意条码不要被胶带粘住），贴1pc，贴1面正唛，封箱胶纸不能挡住贴纸内容。每pcs外 箱贴纸都是唯一的，不可重复粘贴，否则会有罚款产生。 3.外箱材质为ZURU标准； 4.此单需使用KMART封箱胶上下工字型封箱;从2019年6月开始，要用KMART 新版封箱胶带，此单要用"ANKO"封箱胶带 5.此单出口澳大利亚，请按相应的澳新标准生产； 6.产品和包装上生产批号的显示格式ZURU标准日期码格式 7.RATIO: | V18: Sara Wang | W18: 1.55 | X18: =W18*I18 -> 7616.7 | Y18: 84784-5.17 | Z18: 77555GQ1-S002 | AA18: 已入 | AB18: 系统出单 | AC18: 4914 | AD18: =AC18-I18 -> 0 | AE18: OK | AG18: A | AH18: =I18 -> 4914 | AJ18: =I18 -> 4914 | AS18: =I18 -> 4914 | BC18: =I18/13 -> 378
A19: 45355 | B19: KMART AUSTRALIA LTD | C19: 澳大利亚 | D19: 4500125858 | E19: 19949062 | F19: 4500125858-20 | G19: 77555GQ1-S002 | H19: 迷你房子GQ1/13PCS/箱 | I19: 4914 | J19: 0 | K19: 13 | L19: =I19/K19 -> 378 | M19: 45392 | N19: 45388 | P19: pass | R19: 45365 | S19: 有 | T19: 3/19箱唛贴纸 防盗贴纸自行订购 | U19: 日期码格式：ZURU INC(BVI) 标准格式 日期：按实际生产日期 Packaging Info: 1.77555GQ1:MA英语UPC版本包装（首选1LUPC，如果无1L可用多语含英语UPC版本）+防盗贴纸+箱唛+箱唛贴纸(1PCS/CTN).防盗贴纸贴在球顶部空白处，大货生产前请返回位置图确认; Remark: 1,请务必按时完货，验货并请按期送货入货代指定仓库，如果晚了导致船期Delay将会有罚金产生或者客户要求空运，所产生的罚金和空运费由工厂承担。 2.SSCC 外箱贴纸请同纸箱瓦楞纸方向（竖纹向）垂直，即外箱贴纸横着贴(注意条码不要被胶带粘住），贴1pc，贴1面正唛，封箱胶纸不能挡住贴纸内容。每pcs外 箱贴纸都是唯一的，不可重复粘贴，否则会有罚款产生。 3.外箱材质为ZURU标准； 4.此单需使用KMART封箱胶上下工字型封箱;从2019年6月开始，要用KMART 新版封箱胶带，此单要用"ANKO"封箱胶带 5.此单出口澳大利亚，请按相应的澳新标准生产； 6.产品和包装上生产批号的显示格式ZURU标准日期码格式 7.RATIO: | V19: Sara Wang | W19: 1.55 | X19: =W19*I19 -> 7616.7 | Y19: 84784-5.17 | Z19: 77555GQ1-S002 | AA19: 已入 | AB19: 系统出单 | AC19: 4914 | AD19: =AC19-I19 -> 0 | AE19: OK | AG19: A | AH19: =I19 -> 4914 | AJ19: =I19 -> 4914 | AS19: =I19 -> 4914 | BC19: =I19/13 -> 378
A20: 45358 | B20: THE ENTERTAINER | C20: 英国 | D20: 4500126251 | F20: 4500126251-20 | G20: 77555GQ1-S002 | H20: 迷你房子GQ1/13PCS/箱 | I20: 21489 | J20: 0 | K20: 13 | L20: =I20/K20 -> 1653 | M20: 45394 | N20: 45390 | P20: pass | Q20: 4/19 截SI | R20: 45370 | S20: 无 | T20: 3/19条码贴 | U20: 日期码格式：ZURU INC(BVI) 标准格式 日期：按实际生产日期 Packaging Info: MA-3L 配套包装 ，额外加一张条码贴覆盖ZURU条码 按ZURU标准比例 Remark: *包装日期码按ZURU格式即可，请确保不迟于外箱日期码，可等于或者早于外箱日期码，必须为法定工作日。 *订单必须经过ZURU QC验货并且通过后方可出货。 *MA版本按工厂现有最新库存即可，请注意检查产品及包装应带UKCA图标，包装显示ZURU UK LTD信息，QC同事请查核，如有问题与跟单确认。 *条码以订单为准，请做货前先核对再安排生产 。 *所有产品按符合欧洲标准走货，不能出带闪粉版本 ，需要是不含微塑料版本 。 *订单出英国和西班牙市场 ，外包装必须要有英文和西班牙文警告语。 | V20: Sherry Lu | W20: 1.55 | X20: =W20*I20 -> 33307.95 | Y20: 84791-5.17 | Z20: 77555GQ2-S001-3L | AA20: 已入 | AB20: 系统出单 | AC20: 21489 | AD20: =AC20-I20 -> 0 | AE20: ok | AF20: 可接受 | AG20: A | AH20: =I20 -> 21489 | AK20: =I20 -> 21489 | AS20: =I20 -> 21489 | BE20: =I20/13 -> 1653
A21: 45351 | B21: Smyths Toys HQ UC UK | C21: 英国 | D21: 4500125676 | E21: 4400386226 | F21: 4500125676-10 | G21: 77555GQ2-S001 | H21: 迷你房子25pcsGQ2*2/箱 | I21: 8500 | J21: 0 | K21: 50 | L21: =I21/K21 -> 170 | M21: 45394 | N21: 45390 | P21: pass | Q21: 4/15 截SI | R21: 45356 | S21: 无 | T21: 贴纸以及位置图翻#450012567 | U21: 日期码格式：ZURU INC(BVI) 标准格式 日期：按实际生产日期 Packaging Info: 1.77555GQ2:MA 3L最新收缩膜+德国callout贴纸/荷兰警告语+MA 5L收藏指南+MA3LPDQ，贴纸以及位置图翻#4500125672 EAN#4894680033429 Remark: 1）包装日期码按ZURU格式即可，请确保不迟于外箱日期码，可等于或者早于外箱日期码，必须为法定工作日，印刷前请先检查外箱日期码。 2）订单出英国，请注意检查产品及包装应带UKCA图标（14+产品除外），包装显示ZURU UK LTD/ZURU France地址信息，QC部门请查核，如有问题与跟单确认 3）订单必须经过ZURU QC验货并且通过后方可出货 4) 需要符合欧洲标准不能含有闪粉和微塑料，否则不和法规会有客诉产生 | V21: Sheba Ye | W21: 1.54 | X21: =W21*I21 -> 13090 | Y21: 84789-5.17 | Z21: 77555GQ2-S001-3L | AA21: 已入 | AB21: 系统出单 | AC21: 8500 | AD21: =AC21-I21 -> 0 | AE21: ok | AF21: 可接受 | AG21: A | AH21: =I21 -> 8500 | AK21: =I21 -> 8500 | AS21: =I21 -> 8500 | BH21: =I21/25 -> 340
A22: 45351 | B22: Smyths Toys HQ UC IE | C22: 爱尔兰 | D22: 4500125672 | E22: 4400386225 | F22: 4500125672-10 | G22: 77555GQ2-S001 | H22: 迷你房子25pcsGQ2*2/箱 | I22: 2500 | J22: 0 | K22: 50 | L22: =I22/K22 -> 50 | M22: 45394 | N22: 45390 | P22: pass | R22: 45356 | S22: 无 | T22: 贴纸以及位置图翻#450012567 | U22: 日期码格式：ZURU INC(BVI) 标准格式 日期：按实际生产日期 Packaging Info: 1.77555GQ2:MA 3L最新收缩膜+德国callout贴纸/荷兰警告语+MA 5L收藏指南+MA3LPDQ UPC:4894680033429 Remark: 1）包装日期码按ZURU格式即可，请确保不迟于外箱日期码，可等于或者早于外箱日期码，必须为法定工作日，印刷前请先检查外箱日期码。 2）订单出英国，请注意检查产品及包装应带UKCA图标（14+产品除外），包装显示ZURU UK LTD/ZURU France地址信息，QC部门请查核，如有问题与跟单确认 3）订单必须经过ZURU QC验货并且通过后方可出货 4) 需要符合欧洲标准不能含有闪粉和微塑料，否则不和法规会有客诉产生 | V22: Sheba Ye | W22: 1.54 | X22: =W22*I22 -> 3850 | Y22: 84788-5.17 | Z22: 77555GQ2-S001-3L | AA22: 已入 | AB22: 系统出单 | AC22: 2500 | AD22: =AC22-I22 -> 0 | AE22: ok | AF22: 可接受 | AG22: A | AH22: =I22 -> 2500 | AK22: =I22 -> 2500 | AS22: =I22 -> 2500 | BH22: =I22/25 -> 100
A23: 45358 | B23: KMART AUSTRALIA LTD(NEW ZEALAND) | C23: 新西兰 | D23: 4500126301 | E23: 19961307 | F23: 4500126301-10 | G23: 77555GQ1-S002 | H23: 迷你房子GQ1/13PCS/箱 | I23: 1001 | J23: 0 | K23: 13 | L23: =I23/K23 -> 77 | M23: 45397 | N23: 45393 | P23: pass | R23: 45369 | S23: 有 | T23: 3/25箱唛贴纸 防盗贴纸翻单125858 | U23: 日期码格式：ZURU INC(BVI) 标准格式 日期：按实际生产日期 Packaging Info: 77555GQ1:MA英语UPC版本包装（首选1LUPC，如果无1L可用多语含英语UPC版本）+防盗贴纸+箱唛+箱唛贴纸(1PCS/CTN).防盗贴纸及其位置图请跟回PO#4500125858; Remark: 1,请务必按时完货，验货并请按期送货入货代指定仓库，如果晚了导致船期Delay将会有罚金产生或者客户要求空运，所产生的罚金和空运费由工厂承担。 2.SSCC 外箱贴纸请同纸箱瓦楞纸方向（竖纹向）垂直，即外箱贴纸横着贴(注意条码不要被胶带粘住），贴1pc，贴1面正唛，封箱胶纸不能挡住贴纸内容。每pcs外 箱贴纸都是唯一的，不可重复粘贴，否则会有罚款产生。 3.外箱材质为ZURU标准； 4.此单需使用KMART封箱胶上下工字型封箱;从2019年6月开始，要用KMART 新版封箱胶带，此单要用"ANKO"封箱胶带 5.此单出口新西兰，请按相应的澳新标准生产； 6.产品和包装上生产批号的显示格式ZURU标准日期码格式 7.77555GQ1先以FCL下单，实际出货方式为LCL | V23: Sara Wang | W23: 1.55 | X23: =W23*I23 -> 1551.55 | Y23: 84794-5.17 | Z23: 77555GQ1-S002 | AA23: 已入 | AB23: 系统出单 | AC23: 1001 | AD23: =AC23-I23 -> 0 | AE23: ok | AG23: A | AH23: =I23 -> 1001 | AJ23: =I23 -> 1001 | AS23: =I23 -> 1001 | BC23: =I23/13 -> 77
A24: 45358 | B24: KMART AUSTRALIA LTD | C24: 澳大利亚 | D24: 4500126300 | E24: 19949063 | F24: 4500126300-10 | G24: 77555GQ1-S002 | H24: 迷你房子GQ1/13PCS/箱 | I24: 2574 | J24: 0 | K24: 13 | L24: =I24/K24 -> 198 | M24: 45397 | N24: 45393 | P24: pass | R24: 45369 | S24: 有 | T24: 3/25箱唛贴纸 防盗贴纸翻单125858 | U24: 日期码格式：ZURU INC(BVI) 标准格式 日期：按实际生产日期 Packaging Info: 77555GQ1:MA英语UPC版本包装（首选1LUPC，如果无1L可用多语含英语UPC版本）+防盗贴纸+箱唛+箱唛贴纸(1PCS/CTN).防盗贴纸及其位置图请跟回PO#4500125858; Remark: 1,请务必按时完货，验货并请按期送货入货代指定仓库，如果晚了导致船期Delay将会有罚金产生或者客户要求空运，所产生的罚金和空运费由工厂承担。 2.SSCC 外箱贴纸请同纸箱瓦楞纸方向（竖纹向）垂直，即外箱贴纸横着贴(注意条码不要被胶带粘住），贴1pc，贴1面正唛，封箱胶纸不能挡住贴纸内容。每pcs外 箱贴纸都是唯一的，不可重复粘贴，否则会有罚款产生。 3.外箱材质为ZURU标准； 4.此单需使用KMART封箱胶上下工字型封箱;从2019年6月开始，要用KMART 新版封箱胶带，此单要用"ANKO"封箱胶带 5.此单出口澳大利亚，请按相应的澳新标准生产； 6.产品和包装上生产批号的显示格式ZURU标准日期码格式 7.77555GQ1先以FCL下单，实际出货方式为LCL | V24: Sara Wang | W24: 1.55 | X24: =W24*I24 -> 3989.7 | Y24: 84793-5.17 | Z24: 77555GQ1-S002 | AA24: 已入 | AB24: 系统出单 | AC24: 2574 | AD24: =AC24-I24 -> 0 | AE24: ok | AG24: A | AH24: =I24 -> 2574 | AJ24: =I24 -> 2574 | AS24: =I24 -> 2574 | BC24: =I24/13 -> 198
A25: 45358 | B25: KMART AUSTRALIA LTD | C25: 澳大利亚 | D25: 4500126300 | E25: 19961306 | F25: 4500126300-20 | G25: 77555GQ1-S002 | H25: 迷你房子GQ1/13PCS/箱 | I25: 3679 | J25: 0 | K25: 13 | L25: =I25/K25 -> 283 | M25: 45397 | N25: 45393 | P25: pass | R25: 45369 | S25: 有 | T25: 3/25箱唛贴纸 防盗贴纸翻单125858 | U25: 日期码格式：ZURU INC(BVI) 标准格式 日期：按实际生产日期 Packaging Info: 77555GQ1:MA英语UPC版本包装（首选1LUPC，如果无1L可用多语含英语UPC版本）+防盗贴纸+箱唛+箱唛贴纸(1PCS/CTN).防盗贴纸及其位置图请跟回PO#4500125858; Remark: 1,请务必按时完货，验货并请按期送货入货代指定仓库，如果晚了导致船期Delay将会有罚金产生或者客户要求空运，所产生的罚金和空运费由工厂承担。 2.SSCC 外箱贴纸请同纸箱瓦楞纸方向（竖纹向）垂直，即外箱贴纸横着贴(注意条码不要被胶带粘住），贴1pc，贴1面正唛，封箱胶纸不能挡住贴纸内容。每pcs外 箱贴纸都是唯一的，不可重复粘贴，否则会有罚款产生。 3.外箱材质为ZURU标准； 4.此单需使用KMART封箱胶上下工字型封箱;从2019年6月开始，要用KMART 新版封箱胶带，此单要用"ANKO"封箱胶带 5.此单出口澳大利亚，请按相应的澳新标准生产； 6.产品和包装上生产批号的显示格式ZURU标准日期码格式 7.77555GQ1先以FCL下单，实际出货方式为LCL | V25: Sara Wang | W25: 1.55 | X25: =W25*I25 -> 5702.45 | Y25: 84793-5.17 | Z25: 77555GQ1-S002 | AA25: 已入 | AB25: 系统出单 | AC25: 3679 | AD25: =AC25-I25 -> 0 | AE25: ok | AG25: A | AH25: =I25 -> 3679 | AJ25: =I25 -> 3679 | AS25: =I25 -> 3679 | BC25: =I25/13 -> 283
A26: 45356 | B26: Zuru Germany GMBH | C26: 德国 | D26: 4500126061 | E26: 5200004188 | F26: 4500126061-60 | G26: 77555GQ1-S002-MTS | H26: 迷你房子GQ1/13PCS/箱 | I26: 4810 | J26: 0 | K26: 13 | L26: =I26/K26 -> 370 | M26: 45398 | N26: 45394 | P26: pass | Q26: 4/28 交仓 | R26: 45358 | S26: 无 | T26: 3/12环保标贴纸 | U26: 日期码格式：ZURU INC(BVI) 标准格式 日期：按实际生产日期 Packaging Info: 6.77555GQ1：MA 3L EAN版本收缩膜+一张法国和意大利环保标贴纸+MA 5L A版收藏指南； Remark: 1.德国内销单，ZURU 验货后即可出货； 2.外箱EAN 14 条码参考： 6.77555GQ1：30193052064265 3.所有出口欧洲的产品, 法规规定禁止在包装和共公众用的印刷品中使用矿物油中含有的物质, 包装印刷油墨中含有的MOAH/MOSH的质量浓度不能超过1%, 否则出货 到法国被抽检出现问题, 供应商需要对此负责; 4. date code: 外箱/产品/包装 保持一致，完货后提供date code 信息以便我们保存记录做批次管理； | V26: SD45 | W26: 1.55 | X26: =W26*I26 -> 7455.5 | Y26: 84902-5.25 | Z26: 77555GQ1-S002-3L | AA26: 已入 | AB26: 系统出单 | AC26: 4810 | AD26: =AC26-I26 -> 0 | AE26: ok | AF26: 可接受 | AG26: 跟单同意用A版本 | AH26: =I26 -> 4810 | AK26: =I26 -> 4810 | AS26: =I26 -> 4810 | BE26: =I26/13 -> 370
A27: 45364 | B27: Multihexa Sdn Bhd | C27: 马来西亚 | D27: 4500126802 | F27: 4500126802-80 | G27: 77555GQ2-S001 | H27: 迷你房子25pcsGQ2*2/箱 | I27: 3000 | J27: 0 | K27: 50 | L27: =I27/K27 -> 60 | M27: 45401 | N27: 45397 | P27: pass | Q27: 4/25 截SI | R27: 45371 | S27: 无 | T27: 45373 | U27: 日期码格式：ZURU INC(BVI) 标准格式 日期：按实际生产日期 Packaging Info: 1.MA UPC包装（优先1L)+1张进口商贴纸 77555GQ2-贴纸AW、位置图待提供 Remark: 77555GQ2-Contains UV Glue | V27: Emma Wu | W27: 1.54 | X27: =W27*I27 -> 4620 | Y27: 84876-2-5.22 | Z27: 77555GQ2-S001 | AA27: 已入 | AB27: 系统出单 | AC27: 3000 | AD27: =AC27-I27 -> 0 | AE27: OK | AG27: A | AH27: =I27 -> 3000 | AJ27: =I27 -> 3000 | AS27: =I27 -> 3000 | BF27: =I27/25 -> 120
A28: 45362 | B28: TARGET AUSTRALIA PTY LTD | C28: 澳大利亚 | D28: 4500125613 | E28: 2342413 | F28: 4500125613-50 | G28: 77555GQ1-S002 | H28: 迷你房子GQ1/13PCS/箱 | I28: 3211 | J28: 0 | K28: 13 | L28: =I28/K28 -> 247 | M28: 45404 | N28: 45400 | P28: PASS | Q28: 4/25入仓 | R28: 45376 | S28: 有 | T28: 4/3外箱贴纸 | U28: 日期码格式：ZURU INC(BVI) 标准格式 日期：按实际生产日期 Packaging Info: 1.77555GQ1:MA英语UPC 版本包装 (优先1L，如无1L，可用3L),箱唛+外箱贴纸 Remark: 1.客人要求箱唛不可出现手写内容（流水号除外），箱唛印的重量和实际差异不超3%，且不可手写; 2.此单去澳大利亚，请按相应澳新标准生产; 3.使用TARGET客版封箱胶封顶，顶部两侧以及底部均用普通封箱胶，工字型封箱 4.外箱需要贴客户的SSCC LABEL，SSCC LABEL 由ZURU在货期前两周提供文档,由工厂订购，请贴在正唛右下角（封箱胶纸不能挡住贴纸内容。）； 5.产品和包装上要有tracking label信息：格式为Zuru标准格式（可以自行调整具体年月日生产日期,避开节假期日） 6.请务必按时完货，验货PASS后请按时送货入货代指定仓库，如果晚了导致船期Delay将会有罚金产生或者客户要求空运，所产生的罚金和空运费由工厂承担 7.Ratio： 77555GQ1先以FCL下单，实际出货方式为LCL | V28: Sara Wang | W28: 1.55 | X28: =W28*L28 -> 382.85 | Y28: 84922-5.25 | Z28: 77555GQ1-S002 | AA28: 已入 | AB28: 系统出单 | AC28: 3211 | AD28: =AC28-I28 -> 0 | AE28: ok | AG28: A | AH28: =I28 -> 3211 | AJ28: =I28 -> 3211 | AS28: =I28 -> 3211 | BC28: =I28/13 -> 247
A29: 45363 | B29: KMART AUSTRALIA LTD | C29: 澳大利亚 | D29: 4500126567 | E29: 19949064 | F29: 4500126567-40 | G29: 77555GQ1-S002 | H29: 迷你房子GQ1/13PCS/箱 | I29: 3432 | J29: 0 | K29: 13 | L29: =I29/K29 -> 264 | M29: 45404 | N29: 45400 | P29: PASS | Q29: 4月23日-4月26日交仓 | R29: 45377 | S29: 有 | T29: 4/3箱唛贴纸 防盗贴纸翻单125858 | U29: 日期码格式：ZURU INC(BVI) 标准格式 日期：按实际生产日期 Packaging Info: 1.77555GQ1:MA英语UPC版本包装（首选1LUPC，如果无1L可用多语含英语UPC版本）+防盗贴纸+箱唛+箱唛贴纸(1PCS /CTN).77555GQ1防盗贴纸及其位置图请跟回PO#4500125858; Remark: 1,请务必按时完货，验货并请按期送货入货代指定仓库，如果晚了导致船期Delay将会有罚金产生或者客户要求空运，所产生的罚金和空运费由工厂承担。 2.SSCC 外箱贴纸请同纸箱瓦楞纸方向（竖纹向）垂直，即外箱贴纸横着贴(注意条码不要被胶带粘住），贴1pc，贴1面正唛，封箱胶纸不能挡住贴纸内容。每pcs外 箱贴纸都是唯一的，不可重复粘贴，否则会有罚款产生。 3.外箱材质为ZURU标准； 4.此单需使用KMART封箱胶上下工字型封箱;从2019年6月开始，要用KMART 新版封箱胶带，此单要用"ANKO"封箱胶带 5.此单出口澳大利亚，请按相应的澳新标准生产； 6.产品和包装上生产批号的显示格式ZURU标准日期码格式 7.RATIO: 8.77555GQ1:先以FCL下单，实际出货方式为LCL | V29: Sara Wang | W29: 1.55 | X29: =W29*I29 -> 5319.6 | Y29: 84919-5.25 | Z29: 77555GQ1-S002 | AA29: 已入 | AB29: 系统出单 | AC29: 3432 | AD29: =AC29-I29 -> 0 | AE29: ok | AG29: A | AH29: =I29 -> 3432 | AJ29: =I29 -> 3432 | AS29: =I29 -> 3432 | BC29: =I29/13 -> 264
A30: 45351 | B30: THE FARMERS' TRADING COMPANY LIMITE | C30: 新西兰 | D30: 4500125725 | F30: 4500125725-10 | G30: 77555GQ1-S002 | H30: 迷你房子GQ1/13PCS/箱 | I30: 1950 | J30: 0 | K30: 13 | L30: =I30/K30 -> 150 | M30: 45405 | N30: 45401 | P30: PASS | R30: 45359 | S30: 无 | T30: 3/19价格贴纸 | U30: 日期码格式：ZURU INC(BVI) 标准格式 日期：按实际生产日期 Packaging Info: 1.MA PKG，优先1 L+可移材质价格贴纸 Remark: Contains UV Glue | V30: Coral Wu | W30: 1.55 | X30: =W30*I30 -> 3022.5 | Y30: 84790-5.17 | Z30: 77555GQ1-S002 | AA30: 已入 | AB30: 系统出单 | AC30: 1950 | AD30: =AC30-I30 -> 0 | AE30: ok | AG30: A | AH30: =I30 -> 1950 | AJ30: =I30 -> 1950 | AS30: =I30 -> 1950 | BC30: =I30/13 -> 150
A31: 45322 | B31: MTA Trade | C31: 哈萨克斯坦 | D31: 4500124111 | F31: 4500124111-10 | G31: 77555GQ1-S001 | H31: 迷你房子 | I31: 13104 | J31: 0 | K31: 52 | L31: =I31/K31 -> 252 | M31: 45405 | N31: =M31-4 -> 45401 | P31: PASS | Q31: 4/24走货 | R31: 45327 | S31: 无 | T31: 45327 | U31: 日期码格式：ZURU INC(BVI) 标准格式 日期：按实际生产日期 Packaging Info: 1. 1L MA 最新收缩膜+ 进口商贴纸， MA 指南。 Remark: | V31: Ann Zhang | W31: 1.5 | X31: =W31*I31 -> 19656 | Y31: 84743-5.14 | Z31: 77555GQ1-S001 | AA31: 已入 | AB31: 系统出单 | AC31: 13104 | AD31: =AC31-I31 -> 0 | AE31: ok | AG31: A | AH31: =I31 -> 13104 | AJ31: =I31 -> 13104 | AS31: =I31 -> 13104 | BC31: =I31/13 -> 1008
A32: 45364 | B32: SMYTHS TOYS HQ UC | C32: 法国 | D32: 4500126738 | E32: 236396 | F32: 4500126738-10 | G32: 77555GQ2-S001 | H32: 迷你房子25pcsGQ2*2/箱 | I32: 3500 | J32: 0 | K32: 50 | L32: =I32/K32 -> 70 | M32: 45405 | N32: =M32-4 -> 45401 | P32: pass | Q32: 4/23截SI | R32: 45365 | S32: 无 | T32: 贴纸翻单125672 | U32: 日期码格式：ZURU INC(BVI) 标准格式 日期：按实际生产日期 Packaging Info: 1.77555GQ2:MA 3L 收缩膜+1张德国CALLOUT<(>&<)>荷兰警告语贴纸(含法国回收logo)翻4500125672+MA 3L PDQ Remark: 1、此单出法国，所有包装都需要含有法语<(>&<)>法国回收logo, 需要满足Zuru Standard欧洲标准测试要求； 2、请准时出货，推期会有罚款； 3、出法国的产品需不含微塑料； 4、有出口法国的产品, 法规规定禁止在包装和公众用的印刷品中使用含有矿物油的物质，包装印刷油墨中含有的MOAH/MOSH的质量浓度不能超过1%, 否则出货到法 国被抽检出现问题, 供应商需要对此负责。 | V32: Ula Zhao | W32: 1.54 | X32: =W32*I32 -> 5390 | Y32: 84964-5.28 | Z32: 77555GQ2-S001-3L | AA32: 已入 | AB32: 系统出单 | AC32: 3500 | AD32: =AC32-I32 -> 0 | AE32: ok | AF32: 可接受 | AG32: A | AH32: =I32 -> 3500 | AK32: =I32 -> 3500 | AS32: =I32 -> 3500 | BH32: =I32/25 -> 140
A33: 45365 | B33: KMART AUSTRALIA LTD(NEW ZEALAND) | C33: 新西兰 | D33: 4500126643 | E33: 19972864 | F33: 4500126643-20 | G33: 77555GQ1-S002 | H33: 迷你房子GQ1/13PCS/箱 | I33: 754 | J33: 0 | K33: 13 | L33: =I33/K33 -> 58 | M33: 45406 | N33: 45402 | P33: pass | Q33: 4/29交仓 | R33: 45377 | S33: 有 | T33: 4/3箱唛贴纸 防盗贴纸翻单125858 | U33: 日期码格式：ZURU INC(BVI) 标准格式 日期：按实际生产日期 Packaging Info: 2.77555GQ1:MA英语UPC版本包装（首选1LUPC，如果无1L可用多语含英语UPC版本）+防盗贴纸+箱唛+箱唛贴纸(1PCS/CTN);77555GQ1防盗贴纸及位置图跟 回PO#4500125858; Remark: 1,请务必按时完货，验货并请按期送货入货代指定仓库，如果晚了导致船期Delay将会有罚金产生或者客户要求空运，所产生的罚金和空运费由工厂承担。 2.SSCC 外箱贴纸请同纸箱瓦楞纸方向（竖纹向）垂直，即外箱贴纸横着贴(注意条码不要被胶带粘住），贴1pc，贴1面正唛，封箱胶纸不能挡住贴纸内容。每pcs外 箱贴纸都是唯一的，不可重复粘贴，否则会有罚款产生。 3.外箱材质为ZURU标准； 4.此单需使用KMART封箱胶上下工字型封箱;从2019年6月开始，要用KMART 新版封箱胶带，此单要用"ANKO"封箱胶带 5.此单出口新西兰，请按相应的澳新标准生产； 6.产品和包装上生产批号的显示格式ZURU标准日期码格式 7.RATIO: 77515GQ1-S003:3PCS AG13 Batteries(Included); | V33: Sara Wang | W33: 1.55 | X33: =W33*I33 -> 1168.7 | Y33: 84785-5.17 | Z33: 77555GQ1-S002 | AA33: 已入 | AB33: 系统出单 | AC33: 754 | AD33: =AC33-I33 -> 0 | AE33: ok | AG33: A | AH33: =I33 -> 754 | AJ33: =I33 -> 754 | AS33: =I33 -> 754 | BC33: =I33/13 -> 58
A34: 45362 | B34: WAL-MART CANADA CORP. | C34: 加拿大 | D34: 4500126515 | E34: 2300874228 | F34: 4500126515-30 | G34: 77555GQ2-S002 | H34: 迷你房子 | I34: 15050 | J34: 0 | K34: 25 | L34: =I34/K34 -> 602 | M34: 45406 | N34: 45402 | O34: 4/24抽办10% | P34: pass | Q34: 5/24 截SI | R34: 45366 | S34: 无 | T34: 无 | U34: 日期码格式：ZURU INC(BVI) 标准格式 日期：按实际生产日期 Packaging Info: #77555GQ2: MA3L,PDQ(25装)+客版3L,UPC条码收缩膜(UPC: 193052064264)+MA5L收藏指南 Remark: 2. 带电池的产品需使用英法双语电池(纽扣电池除外)； 3. 此单有箱唛; 4. 此单需要第三方验货，烦请多备包装物; 5. 此单需安排大货样进行签办，样品数量见下： - #77555GQ2: 2pcsPDQ+3pcs大货球+2套光身办； 6. 此单##77555,2024/4/24需安排抽办进行产中测试；抽办数量：#77555: 各4pcs大货球+4套光身办； ********************* a. 请确保产品符合1999年版本的加拿大环境保护法(CEPA)和2012年禁止某些有毒物质法规的要求。该产品不含任何在加拿大禁用的化学物质，包括但不限于有毒物 质清单中列出的化学物质，并且在为加拿大沃尔玛生产产品期间没有使用任何禁用化学物质。 Supplier certify that the products comply with the requirements of Canadian Environmental Protection Act, 1999 (CEPA), Prohibition of Certain To xic Substances Regulations, 2012. The products do not contain any chemicals that are banned in Canada, including but not limited to those listed in the Toxic Substances List and no banned chemicals were used during the manufacturing of product for Walmart Canada. 附件列表： (1) Letter of Guarantee for Canada banned chemicals - (1-5CA) b. 请确保产品在均质材料中的汞浓度不超过0.1%（按重量计）。 Supplier certify that the WAL-MART vendor products does not have a mercury concentration of more than 0.1% by weight in homogeneous material. 附件列表： (1) Letter of Guarantee for Mercury COC c. 请确保产品的塑料材料不含以下物质（SOR 2011-17 27B): Supplier certify that the plastic materials do not contain the following substances(SOR 2011-17 27B): (a) carbon tetrachloride or any substance that contains it; (b) methyl alcohol or any substance thay contains >1.0%; (c) petroleum distillates or any substance that contains >10% weight to volume of petroleum distillates; (d) benzene; (e) turpentine or any substance that contains >10% weight to volume of turpentine; (f) boric acid or salts of boric acid; or (g) ethyl ether. 附件列表： (1) Letter of Guarantee for WM CA-Other prohibited substances in plastic(less than 3 years) | V34: Monica Zhou | W34: 1.59 | X34: =W34*I34 -> 23929.5 | Y34: 84951-5.27 | Z34: 77555GQ2-S002-3L-CA | AA34: 已入 | AB34: 系统出单 | AC34: 15050 | AD34: =AC34-I34 -> 0 | AE34: 无 | AF34: NO | AG34: A | AH34: =I34 -> 15050 | AP34: =I34 -> 15050 | AS34: =I34 -> 15050 | BH34: =I34/25 -> 602
A35: 45365 | B35: KMART AUSTRALIA LTD | C35: 澳大利亚 | D35: 4500126609 | E35: 19972863 | F35: 4500126609-40 | G35: 77555GQ1-S002 | H35: 迷你房子GQ1/13PCS/箱 | I35: 8346 | J35: 0 | K35: 13 | L35: =I35/K35 -> 642 | M35: 45406 | N35: 45402 | P35: pass | Q35: 4/29交仓 | R35: 45377 | S35: 有 | T35: 4/3箱唛贴纸 防盗贴纸翻单125858 | U35: 日期码格式：ZURU INC(BVI) 标准格式 日期：按实际生产日期 Packaging Info: 1.77555GQ1:MA英语UPC版本包装（首选1LUPC，如果无1L可用多语含英语UPC版本）+防盗贴纸+箱唛+箱唛贴纸(1PCS /CTN);77555GQ1防盗贴纸及位置图跟回PO#4500125858; Remark: 1,请务必按时完货，验货并请按期送货入货代指定仓库，如果晚了导致船期Delay将会有罚金产生或者客户要求空运，所产生的罚金和空运费由工厂承担。 2.SSCC 外箱贴纸请同纸箱瓦楞纸方向（竖纹向）垂直，即外箱贴纸横着贴(注意条码不要被胶带粘住），贴1pc，贴1面正唛，封箱胶纸不能挡住贴纸内容。每pcs外 箱贴纸都是唯一的，不可重复粘贴，否则会有罚款产生。 3.外箱材质为ZURU标准； 4.此单需使用KMART封箱胶上下工字型封箱;从2019年6月开始，要用KMART 新版封箱胶带，此单要用"ANKO"封箱胶带 5.此单出口澳大利亚，请按相应的澳新标准生产； 6.产品和包装上生产批号的显示格式ZURU标准日期码格式 7.RATIO: | V35: Sara Wang | W35: 1.55 | X35: =W35*I35 -> 12936.3 | Y35: 84783-2-5.17 | Z35: 77555GQ1-S002 | AA35: 已入 | AB35: 系统出单 | AC35: 8346 | AD35: =AC35-I35 -> 0 | AE35: ok | AG35: A | AH35: =I35 -> 8346 | AJ35: =I35 -> 8346 | AS35: =I35 -> 8346 | BC35: =I35/13 -> 642
A36: 45343 | B36: UPD, INC. | C36: 美国 | D36: 4500124932 | E36: 32275 | F36: 4500124932-20 | G36: 77555GQ2-S001 | H36: 迷你房子25pcsGQ2*2/箱 | I36: 4500 | J36: 0 | K36: 50 | L36: =I36/K36 -> 90 | M36: 45408 | N36: 45404 | P36: pass | Q36: 4/30 截SI | R36: 45345 | S36: 无 | T36: 无 | U36: 日期码格式：ZURU INC(BVI) 标准格式 日期：按实际生产日期 Packaging Info: 1. 包装方式：MA UPC 优先1L 最新包装，出口美国 Remark: 2. 外箱箱唛红色和黑色双色印刷 3. 产品和包装上印刷tracking code信息，格式为ZURU常规 | V36: Iris.yuan | W36: 1.54 | X36: =W36*I36 -> 6930 | Y36: 84787-5.17 | Z36: 77555GQ2-S001 | AA36: 已入 | AB36: 系统出单 | AC36: 4500 | AD36: =AC36-I36 -> 0 | AE36: 无 | AG36: A | AH36: =I36 -> 4500 | AJ36: =I36 -> 4500 | AS36: =I36 -> 4500 | BF36: =I36/25 -> 180
A37: 45366 | B37: Zuru Germany GMBH | C37: 德国 | D37: 4500126972 | E37: 5200004262 | F37: 4500126972-10 | G37: 77555SK1-S002-MTS | H37: 迷你房子展示架 | I37: 3000 | J37: 0 | K37: 30 | L37: =I37/K37 -> 100 | M37: 45402 | N37: 45407 | P37: pass | Q37: 4/26 截SI | R37: 45366 | S37: 无 | T37: 贴纸翻单 | U37: 日期码格式：ZURU INC(BVI) 标准格式 日期：按实际生产日期 Packaging Info: 1.77555SK1：MA 3L 展示架+MA 3L+5L Warnign-A 版EAN 收缩膜+一张意大利环保标贴纸（翻单4500126061）+MA 5L收藏指南； Remark: "1.德国内销单，ZURU 验货后即可出货； 2.外箱EAN 14 条码参考： 77555SK1：40193052064262 3.所有出口欧洲的产品, 法规规定禁止在包装和共公众用的印刷品中使用矿物油中含有的物质, 包装印刷油墨中含有的MOAH/MOSH的质量浓度不能超过1%, 否则出货 到法国被抽检出现问题, 供应商需要对此负责; 4. date code: 外箱/产品/包装 保持一致，完货后提供date code 信息以便我们保存记录做批次管理；" | V37: SD45 | W37: 56.598 | X37: =W37*L37 -> 5659.8 | Y37: 85032-5.31 | Z37: 77555SK1-S002-3L | AA37: 已入 | AB37: 系统出单 | AC37: 3000 | AD37: =AC37-I37 -> 0 | AE37: ok | AF37: 可接受 | AG37: 跟单同意用A版本 | AH37: =I37 -> 3000 | AK37: =I37 -> 3000 | AS37: =I37 -> 3000 | BN37: =I37/30 -> 100
A38: 45342 | B38: AMAZON UK | C38: 英国 | D38: 4500124874 | E38: 15NB9NCZ | F38: 4500124874-280 | G38: 77555-S001 | H38: 迷你房子 | I38: 888 | J38: 0 | K38: 24 | L38: =I38/K38 -> 37 | M38: 45412 | N38: 45408 | P38: pass | Q38: 5/12 截SI | R38: 空白外箱（加印带Zuru字样的最新logo | S38: 有 | T38: 3/28 SSCC | U38: 日期码格式：ZURU INC(BVI) 标准格式 日期：按实际生产日期 Packaging Info: Amazon UK: 4. 77555: 24 PCS/CTN; MA 1L A收缩膜+1张贴纸(含IT/FR sorting label+法德意西警告语)+MA 其他最新包装； 13. 验货时间不迟于2024/5/6； Remark: "1.空白外箱（加印带Zuru字样的最新logo，除了邮包盒直接做外箱的产品） + SSCC LABEL一张, 无箱唛. (SSCC LABEL贴在外箱正面的正中间，贴一面即可,贴纸离外箱边距必须至少3CM),SSCC贴纸由工厂直接跟勤得采购或者工厂自行采购，每一张SSCC Label都是唯一且 有不同流水及条码，且需要检查条码是否能正常扫描，另外，此贴纸印刷不可出现模糊，溢出及粘胶不牢易脱落等现象，如工厂不按此要求导致贴纸有任何问题产生 的罚款将由工厂承担一切责任 。’MADE IN CHINA 外箱只印一正一侧。 2. 出往UK的产品+包装务必打上UKCA logo ，否则客人会退货且当地会有罚款。 3.订单必须经过ZURU QC验货并且通过后方可出货。 4.法国订单要求包装不使用矿物油，请按要求提供以下其中一份文件再出货 ，产品出到法国被相关部门抽检出现包装不符合此要求的，供应商需要为此承担责任， 故此请严格把关 。 -油墨物质""由1 ~ 7个芳香环组成的MOAH""的包装检测报告，要求限值≤1.0%; -包装材料清单，包括包装油墨或物质的信息 -油墨制造商的证书。 5 . 每一批次出货只能有一个生产日期，不可多个生产日期混在同一批次出货； 6. 涉及到相关款式会有闪粉的或者微塑料的，请统一默认出无闪粉或者不含微塑料版本;" | V38: Crystal Chen | W38: 1.18 | X38: =W38*I38 -> 1047.84 | Y38: 84893-3-5.23 | Z38: 77555-S001 | AA38: 已入 | AB38: 系统出单 | AC38: 888 | AD38: =AC38-I38 -> 0 | AE38: OK | AG38: A | AH38: =I38 -> 888 | AJ38: =I38 -> 888 | AS38: =I38 -> 888
A39: 45356 | B39: Amazon EU SARL, Ndl Deutschland | C39: 德国 | D39: 4500125765 | E39: 86OS76HQ | F39: 4500125765-20 | G39: 77555-S001 | H39: 迷你房子 | I39: 648 | J39: 0 | K39: 24 | L39: =I39/K39 -> 27 | M39: 45412 | N39: 45408 | P39: pass | Q39: 5/12走货 | R39: 空白外箱（加印带Zuru字样的最新logo | S39: 有 | T39: 3/28 SSCC | U39: 日期码格式：ZURU INC(BVI) 标准格式 日期：按实际生产日期 Packaging Info: Amazon DE 2. 77555: 24 PCS/CTN; MA 1L A收缩膜+1张贴纸(含IT/FR sorting label+法德意西警告语)+MA 其他最新包装；参考翻单PO#4500124874; 15. 验货日期不得晚于2024/5/6 Remark: "1.空白外箱（加印带Zuru字样的最新logo，除了邮包盒直接做外箱的产品） + SSCC LABEL一张, 无箱唛. (SSCC LABEL贴在外箱正面的正中间，贴一面即可,贴纸离外箱边距必须至少3CM),SSCC贴纸由工厂直接跟勤得采购或者工厂自行采购，每一张SSCC Label都是唯一且 有不同流水及条码，且需要检查条码是否能正常扫描，另外，此贴纸印刷不可出现模糊，溢出及粘胶不牢易脱落等现象，如工厂不按此要求导致贴纸有任何问题产生 的罚款将由工厂承担一切责任 。’MADE IN CHINA 外箱只印一正一侧。 2. 出往UK的产品+包装务必打上UKCA logo ，否则客人会退货且当地会有罚款。 3.订单必须经过ZURU QC验货并且通过后方可出货。 4.法国订单要求包装不使用矿物油，请按要求提供以下其中一份文件再出货 ，产品出到法国被相关部门抽检出现包装不符合此要求的，供应商需要为此承担责任， 故此请严格把关 。 -油墨物质""由1 ~ 7个芳香环组成的MOAH""的包装检测报告，要求限值≤1.0%; -包装材料清单，包括包装油墨或物质的信息 -油墨制造商的证书。 5 . 每一批次出货只能有一个生产日期，不可多个生产日期混在同一批次出货； 6. 涉及到相关款式会有闪粉的或者微塑料的，请统一默认出无闪粉或者不含微塑料版本;" | V39: Crystal Chen | W39: 1.18 | X39: =W39*I39 -> 764.64 | Y39: 84892-5.23 | Z39: 77555-S001 | AA39: 已入 | AB39: 系统出单 | AC39: 648 | AD39: =AC39-I39 -> 0 | AE39: ok | AG39: B | AH39: =I39 -> 648 | AJ39: =I39 -> 648 | AS39: =I39 -> 648
A40: 45356 | B40: AMAZON FR | C40: 法国 | D40: 4500125756 | E40: 7DWFS9RB | F40: 4500125756-130 | G40: 77555-S001 | H40: 迷你房子 | I40: 624 | J40: 0 | K40: 24 | L40: =I40/K40 -> 26 | M40: 45412 | N40: 45408 | P40: pass | Q40: 5/12 截SI | R40: 空白外箱（加印带Zuru字样的最新logo | S40: 有 | T40: 3/28 SSCC | U40: 日期码格式： ZURU INC(BVI) 标准格式 日期：按实际生产日期 Packaging Info: Amazon FR: 13. 77555 2pcs/pvc tube, 12tubes/ctn; MA 1L A收缩膜+MA 其他最新包装+客版3L(5L warning)PVC tube彩卡+1张贴纸(含IT sorting label)；参考翻 单PO#4500124874; 14. 验货日期不得晚于2024/5/6 Remark: "1.空白外箱（加印带Zuru字样的最新logo，除了邮包盒直接做外箱的产品） + SSCC LABEL一张, 无箱唛. (SSCC LABEL贴在外箱正面的正中间，贴一面即可,贴纸离外箱边距必须至少3CM),SSCC贴纸由工厂直接跟勤得采购或者工厂自行采购，每一张SSCC Label都是唯一且 有不同流水及条码，且需要检查条码是否能正常扫描，另外，此贴纸印刷不可出现模糊，溢出及粘胶不牢易脱落等现象，如工厂不按此要求导致贴纸有任何问题产生 的罚款将由工厂承担一切责任 。’MADE IN CHINA 外箱只印一正一侧。 2. 出往UK的产品+包装务必打上UKCA logo ，否则客人会退货且当地会有罚款。 3.订单必须经过ZURU QC验货并且通过后方可出货。 4.法国订单要求包装不使用矿物油，请按要求提供以下其中一份文件再出货 ，产品出到法国被相关部门抽检出现包装不符合此要求的，供应商需要为此承担责任， 故此请严格把关 。 -油墨物质""由1 ~ 7个芳香环组成的MOAH""的包装检测报告，要求限值≤1.0%; -包装材料清单，包括包装油墨或物质的信息 -油墨制造商的证书。 5 . 每一批次出货只能有一个生产日期，不可多个生产日期混在同一批次出货； 6. 涉及到相关款式会有闪粉的或者微塑料的，请统一默认出无闪粉或者不含微塑料版本;" | V40: Crystal Chen | W40: 1.18 | X40: =W40*I40 -> 736.32 | Y40: 84996-2-5.29 | Z40: 77555-S001 | AA40: 已入 | AB40: 系统出单 | AC40: 624 | AD40: =AC40-I40 -> 0 | AE40: ok | AG40: A | AH40: =I40 -> 624 | AJ40: =I40 -> 624 | AS40: =I40 -> 624
A41: 45356 | B41: Amazon ES | C41: 西班牙 | D41: 4500125759 | E41: 1GGHBQLY | F41: 4500125759-160 | G41: 77555-S001 | H41: 迷你房子 | I41: 504 | J41: 0 | K41: 24 | L41: =I41/K41 -> 21 | M41: 45412 | N41: 45408 | P41: pass | Q41: 5/8 截SI | R41: 空白外箱（加印带Zuru字样的最新logo | S41: 有 | T41: 3/28 SSCC | U41: 日期码格式：ZURU INC(BVI) 标准格式 日期：按实际生产日期 Packaging Info: Amazon ES 11. 77555: 24 PCS/CTN; MA 1L A收缩膜+1张贴纸(含IT/FR sorting label+法德意西警告语)+MA 其他最新包装；参考翻单PO#4500124874; 装；参考翻单PO#4500124874; 14. 验货日期不得晚于2024/5/6 Remark: "1.空白外箱（加印带Zuru字样的最新logo，除了邮包盒直接做外箱的产品） + SSCC LABEL一张, 无箱唛. (SSCC LABEL贴在外箱正面的正中间，贴一面即可,贴纸离外箱边距必须至少3CM),SSCC贴纸由工厂直接跟勤得采购或者工厂自行采购，每一张SSCC Label都是唯一且 有不同流水及条码，且需要检查条码是否能正常扫描，另外，此贴纸印刷不可出现模糊，溢出及粘胶不牢易脱落等现象，如工厂不按此要求导致贴纸有任何问题产生 的罚款将由工厂承担一切责任 。’MADE IN CHINA 外箱只印一正一侧。 2. 出往UK的产品+包装务必打上UKCA logo ，否则客人会退货且当地会有罚款。 3.订单必须经过ZURU QC验货并且通过后方可出货。 4.法国订单要求包装不使用矿物油，请按要求提供以下其中一份文件再出货 ，产品出到法国被相关部门抽检出现包装不符合此要求的，供应商需要为此承担责任， 故此请严格把关 。 -油墨物质""由1 ~ 7个芳香环组成的MOAH""的包装检测报告，要求限值≤1.0%; -包装材料清单，包括包装油墨或物质的信息 -油墨制造商的证书。 5 . 每一批次出货只能有一个生产日期，不可多个生产日期混在同一批次出货； 6. 涉及到相关款式会有闪粉的或者微塑料的，请统一默认出无闪粉或者不含微塑料版本;" | V41: Crystal Chen | W41: 1.18 | X41: =W41*I41 -> 594.72 | Y41: 84998-5.29 | Z41: 77555-S001 | AA41: 已入 | AB41: 系统出单 | AC41: 504 | AD41: =AC41-I41 -> 0 | AE41: ok | AG41: A | AH41: =I41 -> 504 | AJ41: =I41 -> 504 | AS41: =I41 -> 504
A42: 45366 | B42: THE WAREHOUSE LIMITED | C42: 新西兰 | D42: 4500127059 | E42: cus po#28351566 | F42: 4500127059-10 | G42: 77555SK-S002 | H42: 迷你房子展示架 | I42: 2760 | J42: 0 | K42: 60 | L42: =I42/K42 -> 46 | M42: 45402 | N42: 45409 | P42: pass | Q42: 4/30 截SI | R42: 45366 | S42: 无 | T42: 无 | U42: 日期码格式：ZURU INC(BVI) 标准格式 日期：按实际生产日期 Packaging Info: MA PKG, 优先1L Remark: 1.此单出两个港口， 10行出AKL，20行出LYT 2.non-glitter version 3.Contains UV Glue | V42: Coral Wu | W42: 102.396 | X42: =W42*L42 -> 4710.216 | Y42: 85033-5.31 | Z42: 77555SK-S002 | AA42: 已入 | AB42: 系统出单 | AC42: 2760 | AD42: =AC42-I42 -> 0 | AE42: 无 | AG42: A | AH42: =I42 -> 2760 | AJ42: =I42 -> 2760 | AS42: =I42 -> 2760 | BL42: =I42/60 -> 46
A43: 45366 | B43: THE WAREHOUSE LIMITED | C43: 新西兰 | D43: 4500127059 | E43: cus po#28351567 | F43: 4500127059-20 | G43: 77555SK-S002 | H43: 迷你房子展示架 | I43: 900 | J43: 0 | K43: 60 | L43: =I43/K43 -> 15 | M43: 45402 | N43: 45409 | P43: pass | Q43: 4/30 截SI | R43: 45366 | S43: 无 | T43: 无 | U43: 日期码格式：ZURU INC(BVI) 标准格式 日期：按实际生产日期 Packaging Info: MA PKG, 优先1L Remark: 1.此单出两个港口， 10行出AKL，20行出LYT 2.non-glitter version 3.Contains UV Glue | V43: Coral Wu | W43: 102.396 | X43: =W43*L43 -> 1535.94 | Y43: 85033-5.31 | Z43: 77555SK-S002 | AA43: 已入 | AB43: 系统出单 | AC43: 900 | AD43: =AC43-I43 -> 0 | AE43: 无 | AG43: A | AH43: =I43 -> 900 | AJ43: =I43 -> 900 | AS43: =I43 -> 900 | BL43: =I43/60 -> 15
A44: 45341 | B44: TARGET US | C44: 美国 | D44: 4500124427 | E44: 0086-6047144-3890 | F44: 4500124427-10 | G44: 77555GQ2-S002 | H44: 迷你房子 | I44: 11000 | J44: 0 | K44: 25 | L44: =I44/K44 -> 440 | M44: 45412 | N44: 45408 | P44: pass | Q44: 5/14 截SI | R44: 45373 | S44: 有 | T44: 4/6客供 | U44: 日期码格式：ZURU INC(BVI) 标准格式 日期：按实际生产日期 Packaging Info: 产品包装MA 1L (UPC 版), MA 1L 收缩膜, MA 1L PDQ; Remark: 1. 77555GQ2-S002-MINI BRANDS-HOME MINI BRANDS-SERIES 1-CAPSULE,25PCS/Gravity PDQ, 25PCS/PDQ/CTN 2. 产品包装MA 1L (UPC 版), MA 1L 收缩膜(产品UPC 显示 193052064264), MA 1L PDQ; 3. 外箱正唛左上角位置粘贴条码箱贴纸，每箱只贴一张，由ZURU订购。来料贴纸上显示的客户DPCI# 086-02-1571， UPC显示10193052064261; 4. 外箱正唛箱唛内容右侧需贴一张Event label，内容显示Toys Set Date：7/21/2024，工厂自行订购 5. 产品和包装上印刷 tracking code信息，格式为ZURU常规格式; 6. 出货方式：货代自提 | V44: Holly Zheng | W44: 1.55 | X44: =W44*I44 -> 17050 | Y44: 84861-5.22 | Z44: 77555GQ2-S002 | AA44: 已入 | AB44: 系统出单 | AC44: 11000 | AD44: =AC44-I44 -> 0 | AE44: ok | AG44: A | AH44: =I44 -> 11000 | AJ44: =I44 -> 11000 | AS44: =I44 -> 11000 | BF44: =I44/25 -> 440
A45: 45342 | B45: AMAZON UK | C45: 英国 | D45: 4500124874 | E45: 2HAGJO5P | F45: 4500124874-190 | G45: 77584-S001 | H45: 迷你房子*2 | I45: 1524 | J45: 0 | K45: 12 | L45: =I45/K45 -> 127 | M45: 45412 | N45: 45408 | P45: pass | Q45: 5/12 截SI | R45: 空白外箱（加印带Zuru字样的最新logo | S45: 有 | T45: 3/28 SSCC | U45: 日期码格式：ZURU INC(BVI) 标准格式 日期：按实际生产日期 Packaging Info: Amazon UK: 5. 77584: 77555 2pcs/pvc tube, 12tubes/ctn; MA 1L A收缩膜+MA 其他最新包装+客版PVC tube彩卡； 13. 验货时间不迟于2024/5/6； Remark: "1.空白外箱（加印带Zuru字样的最新logo，除了邮包盒直接做外箱的产品） + SSCC LABEL一张, 无箱唛. (SSCC LABEL贴在外箱正面的正中间，贴一面即可,贴纸离外箱边距必须至少3CM),SSCC贴纸由工厂直接跟勤得采购或者工厂自行采购，每一张SSCC Label都是唯一且 有不同流水及条码，且需要检查条码是否能正常扫描，另外，此贴纸印刷不可出现模糊，溢出及粘胶不牢易脱落等现象，如工厂不按此要求导致贴纸有任何问题产生 的罚款将由工厂承担一切责任 。’MADE IN CHINA 外箱只印一正一侧。 2. 出往UK的产品+包装务必打上UKCA logo ，否则客人会退货且当地会有罚款。 3.订单必须经过ZURU QC验货并且通过后方可出货。 4.法国订单要求包装不使用矿物油，请按要求提供以下其中一份文件再出货 ，产品出到法国被相关部门抽检出现包装不符合此要求的，供应商需要为此承担责任， 故此请严格把关 。 -油墨物质""由1 ~ 7个芳香环组成的MOAH""的包装检测报告，要求限值≤1.0%; -包装材料清单，包括包装油墨或物质的信息 -油墨制造商的证书。 5 . 每一批次出货只能有一个生产日期，不可多个生产日期混在同一批次出货； 6. 涉及到相关款式会有闪粉的或者微塑料的，请统一默认出无闪粉或者不含微塑料版本;" | V45: Crystal Chen | W45: 3 | X45: =W45*I45 -> 4572 | Y45: 84893-2-5.23 | Z45: 77584-S001-3L | AA45: 已入 | AB45: 系统出单 | AC45: 1524 | AD45: =AC45-I45 -> 0 | AE45: OK | AG45: A | AH45: =I45*2 -> 3048 | AJ45: =I45*2 -> 3048 | AS45: =I45*2 -> 3048 | BR45: =I45 -> 1524 | BS45: =I45 -> 1524 | BT45: =I45 -> 1524 | BV45: 按单
A46: 45356 | B46: Amazon EU SARL, Ndl Deutschland | C46: 德国 | D46: 4500125765 | E46: 1JTS9KEL | F46: 4500125765-220 | G46: 77584-S001 | H46: 迷你房子*2 | I46: 1512 | J46: 0 | K46: 12 | L46: =I46/K46 -> 126 | M46: 45412 | N46: 45408 | P46: pass | Q46: 5/12走货 | R46: 空白外箱（加印带Zuru字样的最新logo | S46: 有 | T46: 3/28 SSCC | U46: 日期码格式：ZURU INC(BVI) 标准格式 日期：按实际生产日期 Packaging Info: Amazon DE 12. 77584: 77555 2pcs/pvc tube, 12tubes/ctn; MA 1L A收缩膜+MA 其他最新包装+客版3L(5L warning)PVC tube彩卡+1张贴纸(含IT sorting label)；参考翻 单PO#4500124874; 装；参考翻单PO#4500124874; 15. 验货日期不得晚于2024/5/6 Remark: "1.空白外箱（加印带Zuru字样的最新logo，除了邮包盒直接做外箱的产品） + SSCC LABEL一张, 无箱唛. (SSCC LABEL贴在外箱正面的正中间，贴一面即可,贴纸离外箱边距必须至少3CM),SSCC贴纸由工厂直接跟勤得采购或者工厂自行采购，每一张SSCC Label都是唯一且 有不同流水及条码，且需要检查条码是否能正常扫描，另外，此贴纸印刷不可出现模糊，溢出及粘胶不牢易脱落等现象，如工厂不按此要求导致贴纸有任何问题产生 的罚款将由工厂承担一切责任 。’MADE IN CHINA 外箱只印一正一侧。 2. 出往UK的产品+包装务必打上UKCA logo ，否则客人会退货且当地会有罚款。 3.订单必须经过ZURU QC验货并且通过后方可出货。 4.法国订单要求包装不使用矿物油，请按要求提供以下其中一份文件再出货 ，产品出到法国被相关部门抽检出现包装不符合此要求的，供应商需要为此承担责任， 故此请严格把关 。 -油墨物质""由1 ~ 7个芳香环组成的MOAH""的包装检测报告，要求限值≤1.0%; -包装材料清单，包括包装油墨或物质的信息 -油墨制造商的证书。 5 . 每一批次出货只能有一个生产日期，不可多个生产日期混在同一批次出货； 6. 涉及到相关款式会有闪粉的或者微塑料的，请统一默认出无闪粉或者不含微塑料版本;" | V46: Crystal Chen | W46: 3 | X46: =W46*I46 -> 4536 | Y46: 84892-2-5.23 | Z46: 77584-S001-3L | AA46: 已入 | AB46: 系统出单 | AC46: 1512 | AD46: =AC46-I46 -> 0 | AE46: ok | AG46: B | AH46: =I46*2 -> 3024 | AJ46: =I46*2 -> 3024 | AS46: =I46*2 -> 3024 | BR46: =I46 -> 1512 | BS46: =I46 -> 1512 | BT46: =I46 -> 1512 | BV46: 按单
A47: 45356 | B47: AMAZON FR | C47: 法国 | D47: 4500125756 | E47: 637Z7ANX | F47: 4500125756-180 | G47: 77584-S001 | H47: 迷你房子*2 | I47: 936 | J47: 0 | K47: 12 | L47: =I47/K47 -> 78 | M47: 45412 | N47: 45408 | P47: pass | Q47: 5/12 截SI | R47: 空白外箱（加印带Zuru字样的最新logo | S47: 有 | T47: 3/28 SSCC | U47: 日期码格式： ZURU INC(BVI) 标准格式 日期：按实际生产日期 Packaging Info: Amazon FR:; 13. 77584: 2pcs/pvc tube, 12tubes/ctn; MA 1L A收缩膜+MA 其他最新包装+客版3L(5L warning)PVC tube彩卡+1张贴纸(含IT sorting label)；参考翻 单PO#4500124874; 14. 验货日期不得晚于2024/5/6 Remark: "1.空白外箱（加印带Zuru字样的最新logo，除了邮包盒直接做外箱的产品） + SSCC LABEL一张, 无箱唛. (SSCC LABEL贴在外箱正面的正中间，贴一面即可,贴纸离外箱边距必须至少3CM),SSCC贴纸由工厂直接跟勤得采购或者工厂自行采购，每一张SSCC Label都是唯一且 有不同流水及条码，且需要检查条码是否能正常扫描，另外，此贴纸印刷不可出现模糊，溢出及粘胶不牢易脱落等现象，如工厂不按此要求导致贴纸有任何问题产生 的罚款将由工厂承担一切责任 。’MADE IN CHINA 外箱只印一正一侧。 2. 出往UK的产品+包装务必打上UKCA logo ，否则客人会退货且当地会有罚款。 3.订单必须经过ZURU QC验货并且通过后方可出货。 4.法国订单要求包装不使用矿物油，请按要求提供以下其中一份文件再出货 ，产品出到法国被相关部门抽检出现包装不符合此要求的，供应商需要为此承担责任， 故此请严格把关 。 -油墨物质""由1 ~ 7个芳香环组成的MOAH""的包装检测报告，要求限值≤1.0%; -包装材料清单，包括包装油墨或物质的信息 -油墨制造商的证书。 5 . 每一批次出货只能有一个生产日期，不可多个生产日期混在同一批次出货； 6. 涉及到相关款式会有闪粉的或者微塑料的，请统一默认出无闪粉或者不含微塑料版本;" | V47: Crystal Chen | W47: 3 | X47: =W47*I47 -> 2808 | Y47: 84996-3-5.29 | Z47: 77584-S001-3L | AA47: 已入 | AB47: 系统出单 | AC47: 936 | AD47: =AC47-I47 -> 0 | AE47: ok | AG47: A | AH47: =I47*2 -> 1872 | AJ47: =I47*2 -> 1872 | AS47: =I47*2 -> 1872 | BR47: =I47 -> 936 | BS47: =I47 -> 936 | BT47: =I47 -> 936 | BV47: 按单
A48: 45356 | B48: Amazon ES | C48: 西班牙 | D48: 4500125759 | E48: 67P5TL9P | F48: 4500125759-60 | G48: 77584-S001 | H48: 迷你房子*2 | I48: 504 | J48: 0 | K48: 12 | L48: =I48/K48 -> 42 | M48: 45412 | N48: 45408 | P48: pass | Q48: 5/8 截SI | R48: 空白外箱（加印带Zuru字样的最新logo | S48: 有 | T48: 3/28 SSCC | U48: 日期码格式：ZURU INC(BVI) 标准格式 日期：按实际生产日期 Packaging Info: Amazon ES 6. 77584: 77555 2pcs/pvc tube, 12tubes/ctn; MA 1L A收缩膜+MA 其他最新包装+客版3L(5L warning)PVC tube彩卡+1张贴纸(含IT sorting label)；参考翻单P O#4500124874; 14. 验货日期不得晚于2024/5/6 Remark: "1.空白外箱（加印带Zuru字样的最新logo，除了邮包盒直接做外箱的产品） + SSCC LABEL一张, 无箱唛. (SSCC LABEL贴在外箱正面的正中间，贴一面即可,贴纸离外箱边距必须至少3CM),SSCC贴纸由工厂直接跟勤得采购或者工厂自行采购，每一张SSCC Label都是唯一且 有不同流水及条码，且需要检查条码是否能正常扫描，另外，此贴纸印刷不可出现模糊，溢出及粘胶不牢易脱落等现象，如工厂不按此要求导致贴纸有任何问题产生 的罚款将由工厂承担一切责任 。’MADE IN CHINA 外箱只印一正一侧。 2. 出往UK的产品+包装务必打上UKCA logo ，否则客人会退货且当地会有罚款。 3.订单必须经过ZURU QC验货并且通过后方可出货。 4.法国订单要求包装不使用矿物油，请按要求提供以下其中一份文件再出货 ，产品出到法国被相关部门抽检出现包装不符合此要求的，供应商需要为此承担责任， 故此请严格把关 。 -油墨物质""由1 ~ 7个芳香环组成的MOAH""的包装检测报告，要求限值≤1.0%; -包装材料清单，包括包装油墨或物质的信息 -油墨制造商的证书。 5 . 每一批次出货只能有一个生产日期，不可多个生产日期混在同一批次出货； 6. 涉及到相关款式会有闪粉的或者微塑料的，请统一默认出无闪粉或者不含微塑料版本;" | V48: Crystal Chen | W48: 3 | X48: =W48*I48 -> 1512 | Y48: 84998-5.29 | Z48: 77584-S001-3L | AA48: 已入 | AB48: 系统出单 | AC48: 504 | AD48: =AC48-I48 -> 0 | AE48: OK | AG48: A | AH48: =I48*2 -> 1008 | AJ48: =I48*2 -> 1008 | AS48: =I48*2 -> 1008 | BR48: =I48 -> 504 | BS48: =I48 -> 504 | BT48: =I48 -> 504 | BV48: 按单
A49: 45369 | B49: MEIJER | C49: 美国 | D49: 4500126973 | E49: Meijer客户PO 215730893 | F49: 4500126973-60 | G49: 77555GQ1-S002 | H49: 迷你房子GQ1/13PCS/箱 | I49: 2535 | J49: 0 | K49: 13 | L49: =I49/K49 -> 195 | M49: 45418 | N49: 45414 | P49: pass | R49: 45380 | S49: 无 | T49: 无 | U49: 日期码格式：ZURU INC(BVI) 标准格式 日期：按实际生产日期 Packaging Info: 1. MA UPC 包装 2. 客人指定箱唛排版 Remark: 出货前 Zuru QC 验货 | V49: Sophia Zhou | W49: 1.55 | X49: =W49*I49 -> 3929.25 | Y49: ok | Z49: 77555GQ1-S002 | AA49: 已入 | AB49: 系统出单 | AC49: 2535 | AD49: =AC49-I49 -> 0 | AE49: 无 | AG49: A | AH49: =I49 -> 2535 | AJ49: =I49 -> 2535 | AS49: =I49 -> 2535 | BC49: =I49/13 -> 195
A50: 45369 | B50: MEIJER | C50: 美国 | D50: 4500126975 | E50: Meijer客户PO 215730899 | F50: 4500126975-60 | G50: 77555GQ1-S002 | H50: 迷你房子GQ1/13PCS/箱 | I50: 1365 | J50: 0 | K50: 13 | L50: =I50/K50 -> 105 | M50: 45418 | N50: 45414 | P50: pass | Q50: 5/9 截SI | R50: 45380 | S50: 无 | T50: 无 | U50: 日期码格式：ZURU INC(BVI) 标准格式 日期：按实际生产日期 Packaging Info: 1. MA UPC 包装 2. 客人指定箱唛排版 Remark: 出货前 Zuru QC 验货 | V50: Sophia Zhou | W50: 1.55 | X50: =W50*I50 -> 2115.75 | Y50: ok | Z50: 77555GQ1-S002 | AA50: 已入 | AB50: 系统出单 | AC50: 1365 | AD50: =AC50-I50 -> 0 | AE50: 无 | AG50: A | AH50: =I50 -> 1365 | AJ50: =I50 -> 1365 | AS50: =I50 -> 1365 | BC50: =I50/13 -> 105
A51: 45376 | B51: KMART AUSTRALIA LTD(NEW ZEALAND) | C51: 新西兰 | D51: 4500127870 | E51: 19985123 | F51: 4500127870-10 | G51: 77555GQ1-S002 | H51: 迷你房子GQ1/13PCS/箱 | I51: 520 | J51: 0 | K51: 13 | L51: =I51/K51 -> 40 | M51: 45418 | N51: 45414 | P51: pass | R51: 45384 | S51: 有 | T51: 4/17箱唛贴纸 防盗贴纸翻单125858 | U51: 日期码格式：ZURU INC(BVI) 标准格式 日期：按实际生产日期 Packaging Info: 77555GQ1:MA英语UPC版本包装（首选1LUPC，如果无1L可用多语含英语UPC版本）+防盗贴纸+箱唛+箱唛贴纸(1PCS/CTN).防盗贴纸及其位置图请跟回PO#4500125858; Remark: 1,请务必按时完货，验货并请按期送货入货代指定仓库，如果晚了导致船期Delay将会有罚金产生或者客户要求空运，所产生的罚金和空运费由工厂承担。 2.SSCC 外箱贴纸请同纸箱瓦楞纸方向（竖纹向）垂直，即外箱贴纸横着贴(注意条码不要被胶带粘住），贴1pc，贴1面正唛，封箱胶纸不能挡住贴纸内容。每pcs外 箱贴纸都是唯一的，不可重复粘贴，否则会有罚款产生。 3.外箱材质为ZURU标准； 4.此单需使用KMART封箱胶上下工字型封箱;从2019年6月开始，要用KMART 新版封箱胶带，此单要用"ANKO"封箱胶带 5.此单出口新西兰，请按相应的澳新标准生产； 6.产品和包装上生产批号的显示格式ZURU标准日期码格式 7.77555GQ1先以FCL下单，实际出货方式为LCL | V51: Sara Wang | W51: 1.55 | X51: =W51*I51 -> 806 | Y51: 84786-5.17 | Z51: 77555GQ1-S002 | AA51: 已入 | AB51: 系统出单 | AC51: 520 | AD51: =AC51-I51 -> 0 | AE51: ok | AG51: A | AH51: =I51 -> 520 | AJ51: =I51 -> 520 | AS51: =I51 -> 520 | BC51: =I51/13 -> 40
A52: 45376 | B52: KMART AUSTRALIA LTD | C52: 澳大利亚 | D52: 4500127869 | E52: 19985122 | F52: 4500127869-30 | G52: 77555GQ1-S002 | H52: 迷你房子GQ1/13PCS/箱 | I52: 6565 | J52: 0 | K52: 13 | L52: =I52/K52 -> 505 | M52: 45418 | N52: 45414 | P52: pass | Q52: 5/8交仓 | R52: 45384 | S52: 有 | T52: 4/17箱唛贴纸 防盗贴纸翻单125858 | U52: 日期码格式：ZURU INC(BVI) 标准格式 日期：按实际生产日期 Packaging Info: 3.77555GQ1:MA英语UPC版本包装（首选1LUPC，如果无1L可用多语含英语UPC版本）+防盗贴纸+箱唛+箱唛贴纸(1PCS/CTN).防盗贴纸及其位置图请跟回PO#4500125858; Remark: 1,请务必按时完货，验货并请按期送货入货代指定仓库，如果晚了导致船期Delay将会有罚金产生或者客户要求空运，所产生的罚金和空运费由工厂承担。 2.SSCC 外箱贴纸请同纸箱瓦楞纸方向（竖纹向）垂直，即外箱贴纸横着贴(注意条码不要被胶带粘住），贴1pc，贴1面正唛，封箱胶纸不能挡住贴纸内容。每pcs外 箱贴纸都是唯一的，不可重复粘贴，否则会有罚款产生。 3.外箱材质为ZURU标准； 4.此单需使用KMART封箱胶上下工字型封箱;从2019年6月开始，要用KMART 新版封箱胶带，此单要用"ANKO"封箱胶带 5.此单出口澳大利亚，请按相应的澳新标准生产； 6.产品和包装上生产批号的显示格式ZURU标准日期码格式 7.RATIO: 8. 77555GQ1先以FCL下单，实际出货方式为LCL | V52: Sara Wang | W52: 1.55 | X52: =W52*I52 -> 10175.75 | Y52: 84795-5.17 | Z52: 77555GQ1-S002 | AA52: 已入 | AB52: 系统出单 | AC52: 6565 | AD52: =AC52-I52 -> 0 | AE52: ok | AG52: A | AH52: =I52 -> 6565 | AJ52: =I52 -> 6565 | AS52: =I52 -> 6565 | BC52: =I52/13 -> 505
A53: 45391 | B53: WAL-MART STORES INC. USA | C53: 美国 | D53: 4500129394 | E53: 0829160148 | F53: 4500129394-10 | G53: 77555SLB-S002 | H53: 迷你房子 | I53: 1152 | J53: 0 | K53: 1152 | L53: =I53/K53 -> 1 | M53: 45419 | N53: 45415 | O53: 抽板时间5/7 5/17 BV | P53: pass | Q53: 6/11 截SI | R53: 45399 | S53: 有 | T53: 4/26艾利贴纸+普通贴纸+RFID贴纸 | U53: 日期码格式：ZURU DGYYYYMMDD CHINA(日期避开周末和法定节假日即可） 日期：按实际生产日期 Packaging Info: 77555SLB-S002 1.包装要求： MA 1L收缩膜+ 客版 收藏指南+客版 1L PDQ 每pcs产品上要贴1张RFID贴纸，贴纸由ZURU提供，贴纸位置请严格按照我们签回的签板； Remark: 77555SLB-S002 1.包装要求： MA 1L收缩膜+ 客版 收藏指南+客版 1L PDQ 每pcs产品上要贴1张RFID贴纸，贴纸由ZURU提供，贴纸位置请严格按照我们签回的签板； 2. 外箱印刷带条码的RFID箱唛：RFID紫色色带+WM Dept.图标+RFID图标+ITF-14条码，四面右下角印刷ZURU logo, ITFF条码只印刷在正唛一面，在加印的时候确保 条形码能扫描出来，外箱侧面任一角落加印："MADE IN CHINA" 字样； 3. 每个slip sheet上面贴一张艾利贴纸（不干胶贴纸）和一张普通贴纸（A4纸），slip sheet打印的普通贴纸的尺寸不能比艾利贴纸小，普通贴纸内容见附件； 4. 在产品上和包装上要有日期码、以及要有MADE IN CHINA和ZURU字样； 5. 产品如有扎带口要剪平，不能刮手。 6. 此单需要抽板和验货，预计抽板时间5/7，请多备料 7. 以slip sheet出货， 12pcs/CTN，77555SLB-S002:1152pcs/96CTN/Slip Sheet | V53: Iris Huang | W53: 1749.5232 | X53: =W53*L53 -> 1749.5232 | Y53: 85327-6.13 | Z53: 77555SLB-S002 | AA53: 已入 | AB53: 系统出单 | AC53: 1152 | AD53: =AC53-I53 -> 0 | AE53: OK | AH53: =I53 -> 1152 | AJ53: =AH53 -> 1152 | AV53: =I53 -> 1152 | AY53: =I53/12 -> 96 | BU53: 4/10 已放 | BV53: 104976 | BW53: 0
A54: 45341 | B54: TARGET US | C54: 美国 | D54: 4500124422 | E54: 0086-7418417-3890 | F54: 4500124422-10 | G54: 77555GQ2-S002 | H54: 迷你房子 | I54: 54000 | J54: 0 | K54: 25 | L54: =I54/K54 -> 2160 | M54: 45412 | N54: 45408 | P54: pass | Q54: 5/12出货 | R54: 45373 | S54: 有 | T54: 4/6客供 | U54: 日期码格式：ZURU INC(BVI) 标准格式 日期：按实际生产日期 Packaging Info: 产品包装MA 1L (UPC 版), MA 1L 收缩膜, MA 1L PDQ; Remark: 1. 77555GQ2-S002-MINI BRANDS-HOME MINI BRANDS-SERIES 1-CAPSULE,25PCS/Gravity PDQ, 25PCS/PDQ/CTN 2. 产品包装MA 1L (UPC 版), MA 1L 收缩膜(产品UPC 显示 193052064264), MA 1L PDQ; 3. 外箱正唛左上角位置粘贴条码箱贴纸，每箱只贴一张，由ZURU订购。来料贴纸上显示的客户DPCI# 086-02-1571， UPC显示10193052064261; 4. 外箱正唛箱唛内容右侧需贴一张Event label，内容显示Toys Set Date：7/21/2024，工厂自行订购 5. 产品和包装上印刷 tracking code信息，格式为ZURU常规格式; 6. 出货方式：货代自提 | V54: Holly Zheng | W54: 1.55 | X54: =W54*I54 -> 83700 | Y54: 84862-5.22 | Z54: 77555GQ2-S002 | AA54: 已入 | AB54: 系统出单 | AC54: =2625+15750+7500+28125 -> 54000 | AD54: =AC54-I54 -> 0 | AE54: ok | AG54: A | AH54: =I54 -> 54000 | AJ54: =I54 -> 54000 | AS54: =I54 -> 54000 | BF54: =I54/25 -> 2160
A55: 45404 | B55: ZURU | D55: ZMPO24287 | G55: 77555-S001 | H55: 迷你房子 | I55: 11款散件每款各300PCS | J55: 0 | K55: 24 | L55: =I55/K55 -> #VALUE! | M55: 45418 | N55: 45414 | R55: 45404 | S55: 无 | T55: 无 | U55: 左图中11款散件每款各300PCS/共308PCS/麻烦同款装一个袋子/箱唛参照邮件附件 | Y55: 85014-5.29 | Z55: # | AC55: 3300 | AD55: =AC55-I55 -> #VALUE!
A56: 45404 | B56: ZURU | D56: ZMPO24287 | G56: 77555-S001 | H56: 迷你房子 | I56: 2款散件每款各300PCS | J56: 0 | K56: 24 | L56: =I56/K56 -> #VALUE! | M56: 45418 | N56: 45414 | R56: 45404 | S56: 无 | T56: 无 | U56: 左图中2款散件每款各300PCS/共600PCS/麻烦同款装一个袋子/箱唛参照邮件附件 | Y56: 85014-5.29 | Z56: # | AC56: 600 | AD56: =AC56-I56 -> #VALUE!
A57: 45404 | B57: ZURU | D57: ZMPO24287 | G57: 77555-S001 | H57: 迷你房子 | I57: 300 | J57: 0 | K57: 24 | L57: =I57/K57 -> 12.5 | M57: 45418 | N57: 45414 | P57: pass | R57: 45404 | S57: 无 | T57: 无 | U57: 左图中款散件/此款散件是要组装好的/箱唛参照邮件附件 | Y57: 85014-5.29 | Z57: # | AC57: 300 | AD57: =AC57-I57 -> 0
A58: 45391 | B58: WAL-MART STORES INC. USA | C58: 美国 | D58: 4500129393 | E58: 0829160147 | F58: 4500129393-10 | G58: 77555SLB-S002 | H58: 迷你房子 | I58: 1152 | J58: 0 | K58: 1152 | L58: =I58/K58 -> 1 | M58: 45429 | N58: 45425 | O58: 5/17 BV | P58: pass | Q58: 5/20交仓 | R58: 45399 | S58: 有 | T58: 4/26艾利贴纸+普通贴纸+RFID贴纸 | U58: 日期码格式：ZURU DGYYYYMMDD CHINA(日期避开周末和法定节假日即可） 日期：按实际生产日期 Packaging Info: 77555SLB-S002 1.包装要求： MA 1L收缩膜+ 客版 收藏指南+客版 1L PDQ 每pcs产品上要贴1张RFID贴纸，贴纸由ZURU提供，贴纸位置请严格按照我们签回的签板； Remark: 77555SLB-S002 1.包装要求： MA 1L收缩膜+ 客版 收藏指南+客版 1L PDQ 每pcs产品上要贴1张RFID贴纸，贴纸由ZURU提供，贴纸位置请严格按照我们签回的签板； 2. 外箱印刷带条码的RFID箱唛：RFID紫色色带+WM Dept.图标+RFID图标+ITF-14条码，四面右下角印刷ZURU logo, ITFF条码只印刷在正唛一面，在加印的时候确保 条形码能扫描出来，外箱侧面任一角落加印："MADE IN CHINA" 字样； 3. 每个slip sheet上面贴一张艾利贴纸（不干胶贴纸）和一张普通贴纸（A4纸），slip sheet打印的普通贴纸的尺寸不能比艾利贴纸小，普通贴纸内容见附件； 4. 在产品上和包装上要有日期码、以及要有MADE IN CHINA和ZURU字样； 5. 产品如有扎带口要剪平，不能刮手。 6. 此单需要验货，请多备料 7. 以slip sheet出货， 12pcs/CTN，77555SLB-S002:1152pcs/96CTN/Slip Sheet | V58: Estate Chen | W58: 1749.5232 | X58: =W58*L58 -> 1749.5232 | Y58: 84888-5.23 | Z58: 77555SLB-S002 | AA58: 已入 | AB58: 系统出单 | AC58: 1152 | AD58: =AC58-I58 -> 0 | AE58: OK | AH58: =I58 -> 1152 | AJ58: =AH58 -> 1152 | AV58: =I58 -> 1152 | AY58: =I58/12 -> 96 | BU58: 4/10 已放 | BW58: 0
A59: 45391 | B59: WAL-MART STORES INC. USA | C59: 美国 | D59: 4500129395 | E59: 0829160146 | F59: 4500129395-10 | G59: 77555SLB-S002 | H59: 迷你房子 | I59: 1152 | J59: 0 | K59: 1152 | L59: =I59/K59 -> 1 | M59: 45429 | N59: 45425 | O59: 5/24 BV | P59: pass | Q59: 5/31 截SI | R59: 45399 | S59: 有 | T59: 4/26艾利贴纸+普通贴纸+RFID贴纸 | U59: 日期码格式：ZURU DGYYYYMMDD CHINA(日期避开周末和法定节假日即可） 日期：按实际生产日期 Packaging Info: 77555SLB-S002 1.包装要求： MA 1L收缩膜+ 客版 收藏指南+客版 1L PDQ 每pcs产品上要贴1张RFID贴纸，贴纸由ZURU提供，贴纸位置请严格按照我们签回的签板； Remark: 77555SLB-S002 1.包装要求： MA 1L收缩膜+ 客版 收藏指南+客版 1L PDQ 每pcs产品上要贴1张RFID贴纸，贴纸由ZURU提供，贴纸位置请严格按照我们签回的签板； 2. 外箱印刷带条码的RFID箱唛：RFID紫色色带+WM Dept.图标+RFID图标+ITF-14条码，四面右下角印刷ZURU logo, ITFF条码只印刷在正唛一面，在加印的时候确保 条形码能扫描出来，外箱侧面任一角落加印："MADE IN CHINA" 字样； 3. 每个slip sheet上面贴一张艾利贴纸（不干胶贴纸）和一张普通贴纸（A4纸），slip sheet打印的普通贴纸的尺寸不能比艾利贴纸小，普通贴纸内容见附件； 4. 在产品上和包装上要有日期码、以及要有MADE IN CHINA和ZURU字样； 5. 产品如有扎带口要剪平，不能刮手。 6. 此单需要验货，请多备料 7. 以slip sheet出货， 12pcs/CTN，77555SLB-S002:1152pcs/96CTN/Slip Sheet | V59: Estate Chen | W59: 1749.5232 | X59: =W59*L59 -> 1749.5232 | Y59: 85028-5.30 | Z59: 77555SLB-S002 | AA59: 已入 | AB59: 系统出单 | AC59: 1152 | AD59: =AC59-I59 -> 0 | AE59: OK | AH59: =I59 -> 1152 | AJ59: =AH59 -> 1152 | AV59: =I59 -> 1152 | AY59: =I59/12 -> 96 | BU59: 4/10 已放 | BW59: 0
A60: 45391 | B60: WAL-MART STORES INC. USA | C60: 美国 | D60: 4500129396 | E60: 0829160179 | F60: 4500129396-10 | G60: 77555SLB-S002 | H60: 迷你房子 | I60: 1152 | J60: 0 | K60: 1152 | L60: =I60/K60 -> 1 | M60: 45429 | N60: 45425 | O60: 5/17 BV | P60: pass | Q60: 5/24 截SI | R60: 45399 | S60: 有 | T60: 4/26艾利贴纸+普通贴纸+RFID贴纸 | U60: 日期码格式：ZURU DGYYYYMMDD CHINA(日期避开周末和法定节假日即可） 日期：按实际生产日期 Packaging Info: 77555SLB-S002 1.包装要求： MA 1L收缩膜+ 客版 收藏指南+客版 1L PDQ 每pcs产品上要贴1张RFID贴纸，贴纸由ZURU提供，贴纸位置请严格按照我们签回的签板； Remark: 77555SLB-S002 1.包装要求： MA 1L收缩膜+ 客版 收藏指南+客版 1L PDQ 每pcs产品上要贴1张RFID贴纸，贴纸由ZURU提供，贴纸位置请严格按照我们签回的签板； 2. 外箱印刷带条码的RFID箱唛：RFID紫色色带+WM Dept.图标+RFID图标+ITF-14条码，四面右下角印刷ZURU logo, ITFF条码只印刷在正唛一面，在加印的时候确保 条形码能扫描出来，外箱侧面任一角落加印："MADE IN CHINA" 字样； 3. 每个slip sheet上面贴一张艾利贴纸（不干胶贴纸）和一张普通贴纸（A4纸），slip sheet打印的普通贴纸的尺寸不能比艾利贴纸小，普通贴纸内容见附件； 4. 在产品上和包装上要有日期码、以及要有MADE IN CHINA和ZURU字样； 5. 产品如有扎带口要剪平，不能刮手。 6. 此单需要验货，请多备料 7. 以slip sheet出货， 12pcs/CTN，77555SLB-S002:1152pcs/96CTN/Slip Sheet | V60: Iris Huang | W60: 1749.5232 | X60: =W60*L60 -> 1749.5232 | Y60: 85139-6.5 | Z60: 77555SLB-S002 | AA60: 已入 | AB60: 系统出单 | AC60: 1152 | AD60: =AC60-I60 -> 0 | AE60: OK | AH60: =I60 -> 1152 | AJ60: =AH60 -> 1152 | AV60: =I60 -> 1152 | AY60: =I60/12 -> 96 | BU60: 4/10 已放 | BW60: 0
A61: 45391 | B61: WAL-MART STORES INC. USA | C61: 美国 | D61: 4500129396 | E61: 0829160166 | F61: 4500129396-20 | G61: 77555SLB-S002 | H61: 迷你房子 | I61: 1152 | J61: 0 | K61: 1152 | L61: =I61/K61 -> 1 | M61: 45429 | N61: 45425 | O61: 5/17 BV | P61: pass | Q61: 6/4 截SI | R61: 45399 | S61: 有 | T61: 4/26艾利贴纸+普通贴纸+RFID贴纸 | U61: 日期码格式：ZURU DGYYYYMMDD CHINA(日期避开周末和法定节假日即可） 日期：按实际生产日期 Packaging Info: 77555SLB-S002 1.包装要求： MA 1L收缩膜+ 客版 收藏指南+客版 1L PDQ 每pcs产品上要贴1张RFID贴纸，贴纸由ZURU提供，贴纸位置请严格按照我们签回的签板； Remark: 77555SLB-S002 1.包装要求： MA 1L收缩膜+ 客版 收藏指南+客版 1L PDQ 每pcs产品上要贴1张RFID贴纸，贴纸由ZURU提供，贴纸位置请严格按照我们签回的签板； 2. 外箱印刷带条码的RFID箱唛：RFID紫色色带+WM Dept.图标+RFID图标+ITF-14条码，四面右下角印刷ZURU logo, ITFF条码只印刷在正唛一面，在加印的时候确保 条形码能扫描出来，外箱侧面任一角落加印："MADE IN CHINA" 字样； 3. 每个slip sheet上面贴一张艾利贴纸（不干胶贴纸）和一张普通贴纸（A4纸），slip sheet打印的普通贴纸的尺寸不能比艾利贴纸小，普通贴纸内容见附件； 4. 在产品上和包装上要有日期码、以及要有MADE IN CHINA和ZURU字样； 5. 产品如有扎带口要剪平，不能刮手。 6. 此单需要验货，请多备料 7. 以slip sheet出货， 12pcs/CTN，77555SLB-S002:1152pcs/96CTN/Slip Sheet | V61: Iris Huang | W61: 1749.5232 | X61: =W61*L61 -> 1749.5232 | Y61: 85139-6.5 | Z61: 77555SLB-S002 | AA61: 已入 | AB61: 系统出单 | AC61: 1152 | AD61: =AC61-I61 -> 0 | AE61: OK | AH61: =I61 -> 1152 | AJ61: =AH61 -> 1152 | AV61: =I61 -> 1152 | AY61: =I61/12 -> 96 | BU61: 4/10 已放 | BW61: 0
A62: 45363 | B62: Importadora Sudamericana & Generac | C62: 阿根廷 | D62: 4500126680 | F62: 4500126680-20 | G62: 77555GQ2-S001 | H62: 迷你房子25pcsGQ2*2/箱 | I62: 2100 | J62: 0 | K62: 50 | L62: =I62/K62 -> 42 | M62: 45418 | N62: 45418 | P62: pass | Q62: 5/12走货 | R62: 45385 | S62: 无 | T62: 4/7进口商贴纸 | U62: 日期码格式：ZURU INC(BVI) 标准格式 日期：按实际生产日期 Packaging Info: 77555:MA 1L包装+进口商贴纸+箱唛 Remark: | V62: Ava Liang | W62: 1.54 | X62: =W62*I62 -> 3234 | Y62: 84796-5.17 | Z62: 77555GQ2-S001 | AA62: 已入 | AB62: 系统出单 | AC62: 2100 | AD62: =AC62-I62 -> 0 | AE62: ok | AG62: A | AH62: =I62 -> 2100 | AJ62: =I62 -> 2100 | AS62: =I62 -> 2100 | BF62: =I62/25 -> 84
A63: 45362 | B63: ROFU Kinderland Spielwarenhandelsge | C63: 德国 | D63: 4500126384 | E63: 236941 | F63: 4500126384-110 | G63: 77555GQ1-S001 | H63: 迷你房子 | I63: 1560 | J63: 0 | K63: 52 | L63: =I63/K63 -> 30 | M63: 45425 | N63: 45421 | P63: pass | Q63: 5/15 截SI | R63: 45362 | S63: 无 | T63: 4/20客供价格贴纸 3/21EAN 条码贴+德语警告语贴 | U63: 日期码格式：ZURU INC(BVI) 标准格式 日期：按实际生产日期 Packaging Info: 77555GQ1:MA 1L 收缩膜+EAN 条码贴纸+德语警告语贴纸+客供价格贴纸+MA 5L 收藏指南+MA B版纸袋+德语警告语贴纸+MA 1L PDQ Remark: 1. 无闪粉版本 2. 此单需要传验货图片给客户，待客人放货后才能安排走货，请在5/13前提供验货图片 3.需准时完成生产，推期出货会有罚款。 | V63: Amy Xiao | W63: 1.5 | X63: =W63*I63 -> 2340 | Y63: 85071-5.31 | Z63: 77555GQ1-S001 | AA63: 已入 | AB63: 系统出单 | AC63: 1560 | AD63: =AC63-I63 -> 0 | AE63: ok | AG63: B | AH63: =I63 -> 1560 | AJ63: =I63 -> 1560 | AS63: =I63 -> 1560 | BC63: =I63/13 -> 120
A64: 45383 | B64: KMART AUSTRALIA LTD(NEW ZEALAND) | C64: 新西兰 | D64: 4500128518 | E64: 19995924 | F64: 4500128518-50 | G64: 77555GQ1-S002 | H64: 迷你房子GQ1/13PCS/箱 | I64: 351 | J64: 0 | K64: 13 | L64: =I64/K64 -> 27 | M64: 45425 | N64: 45421 | P64: pass | Q64: 5/15 交仓 | R64: 45394 | S64: 有 | T64: 4/22箱唛贴纸 防盗贴纸翻单125858 | U64: 日期码格式：ZURU INC(BVI) 标准格式 日期：按实际生产日期 Packaging Info: 1.77555GQ1:MA英语UPC版本包装（首选1LUPC，如果无1L可用多语含英语UPC版本）+防盗贴纸+箱唛+箱唛贴纸(1PC/CTN).;77555GQ1防盗贴纸及其位置图请跟回PO#4500125858; Remark: 1,请务必按时完货，验货并请按期送货入货代指定仓库，如果晚了导致船期Delay将会有罚金产生或者客户要求空运，所产生的罚金和空运费由工厂承担。 2.SSCC 外箱贴纸请同纸箱瓦楞纸方向（竖纹向）垂直，即外箱贴纸横着贴(注意条码不要被胶带粘住），贴1pc，贴1面正唛，封箱胶纸不能挡住贴纸内容。每pcs外 箱贴纸都是唯一的，不可重复粘贴，否则会有罚款产生。 3.外箱材质为ZURU标准； 4.此单需使用KMART封箱胶上下工字型封箱;从2019年6月开始，要用KMART 新版封箱胶带，此单要用"ANKO"封箱胶带 5.此单出口新西兰，请按相应的澳新标准生产； 6.产品和包装上生产批号的显示格式ZURU标准日期码格式 7.RATIO: | V64: Sara Wang | W64: 1.55 | X64: =W64*I64 -> 544.05 | Y64: 85137-6.5 | Z64: 77555GQ1-S002 | AA64: 已入 | AB64: 系统出单 | AC64: 351 | AD64: =AC64-I64 -> 0 | AE64: ok | AH64: =I64 -> 351 | AJ64: =I64 -> 351 | AS64: =I64 -> 351 | BC64: =I64/13 -> 27
A65: 45383 | B65: KMART AUSTRALIA LTD | C65: 澳大利亚 | D65: 4500128517 | E65: 19995923 | F65: 4500128517-50 | G65: 77555GQ1-S002 | H65: 迷你房子GQ1/13PCS/箱 | I65: 5499 | J65: 0 | K65: 13 | L65: =I65/K65 -> 423 | M65: 45425 | N65: 45421 | P65: pass | Q65: 5/15 交仓 | R65: 45394 | S65: 有 | T65: 4/22箱唛贴纸 防盗贴纸翻单125858 | U65: 日期码格式：ZURU INC(BVI) 标准格式 日期：按实际生产日期 Packaging Info: 1.77555GQ1:MA英语UPC版本包装（首选1LUPC，如果无1L可用多语含英语UPC版本）+防盗贴纸+箱唛+箱唛贴纸(1PC/CTN).77555GQ1防盗贴纸及其位置图请跟回PO#4500125858; Remark: 1,请务必按时完货，验货并请按期送货入货代指定仓库，如果晚了导致船期Delay将会有罚金产生或者客户要求空运，所产生的罚金和空运费由工厂承担。 2.SSCC 外箱贴纸请同纸箱瓦楞纸方向（竖纹向）垂直，即外箱贴纸横着贴(注意条码不要被胶带粘住），贴1pc，贴1面正唛，封箱胶纸不能挡住贴纸内容。每pcs外 箱贴纸都是唯一的，不可重复粘贴，否则会有罚款产生。 3.外箱材质为ZURU标准； 4.此单需使用KMART封箱胶上下工字型封箱;从2019年6月开始，要用KMART 新版封箱胶带，此单要用"ANKO"封箱胶带 5.此单出口澳大利亚，请按相应的澳新标准生产； 6.产品和包装上生产批号的显示格式ZURU标准日期码格式 7.RATIO: 77555GQ1先以FCL下单，实际出货方式为LCL | V65: Sara Wang | W65: 1.55 | X65: =W65*I65 -> 8523.45 | Y65: 85136-6.5 | Z65: 77555GQ1-S002 | AA65: 已入 | AB65: 系统出单 | AC65: 5499 | AD65: =AC65-I65 -> 0 | AE65: OK | AH65: =I65 -> 5499 | AJ65: =I65 -> 5499 | AS65: =I65 -> 5499 | BC65: =I65/13 -> 423
A66: 45356 | B66: IMPORTADORA CHICOCOS | C66: 玻利维亚 | D66: 4500126134 | F66: 4500126134-100 | G66: 77555GQ2-S001 | H66: 迷你房子25pcsGQ2*2/箱 | I66: 850 | J66: 0 | K66: 50 | L66: =I66/K66 -> 17 | M66: 45429 | N66: 45425 | P66: pass | Q66: 5/16 截SI | R66: 45380 | S66: 无 | T66: 无 | U66: 日期码格式：ZURU INC(BVI) 标准格式 日期：按实际生产日期 Packaging Info: 77555GQ2::MA 1L包装+箱唛，无进口商贴纸 | V66: Ava Liang | W66: 1.54 | X66: =W66*I66 -> 1309 | Y66: 84797-2-5.17 | Z66: 77555GQ2-S001 | AA66: 已入 | AB66: 系统出单 | AC66: 850 | AD66: =AC66-I66 -> 0 | AE66: 无 | AG66: A | AH66: =I66 -> 850 | AJ66: =I66 -> 850 | AS66: =I66 -> 850 | BF66: =I66/25 -> 34
A67: 45369 | B67: B&M RETAIL LIMITED | C67: 英国 | D67: 4500127087 | E67: 4500127087-1 01422807/1 | F67: 4500127087-10 | G67: 77555GQ2-S002 | H67: 迷你房子 | I67: 14800 | J67: 0 | K67: 25 | L67: =I67/K67 -> 592 | M67: 45425 | N67: 45425 | P67: pass | Q67: 5/20 截SI | R67: 45371 | S67: 无 | T67: 无 | U67: 日期码格式：ZURU INC(BVI) 标准格式 日期：按实际生产日期 Packaging Info: MA-1L配套包装 订单对应客户2个PO ，备注有显示 ，注意分开做货走柜，混装会有罚款，请注意。 Remark: *MA版本按工厂现有最新库存即可，订单出英国，请注意检查产品及包装应带UKCA图标，包装显示ZURU UK LTD信息，QC同事请查核，如有问题与跟单确认。 *生产日期按实际的（法定工作日），按ZURU标准格式即可 ，但是请知悉包装日期码需要早于或者等于外箱日期码 ，不能晚于外箱日期码 *请注意所有订单都需要经过ZURU QC验货并且通过后方可出货 *条码以订单显示为准 ，请安排生产前先核对 ，有问题请提出。 *所有产品按符合欧洲标准走货，需要是不含微塑料版本 。 *涉及到硼的，请使用低硼版本 | V67: Sherry Lu | W67: 1.59 | X67: =W67*I67 -> 23532 | Y67: 84863-5.22 | Z67: 77555GQ2-S002 | AA67: 已入 | AB67: 系统出单 | AC67: 14800 | AD67: =AC67-I67 -> 0 | AE67: 无 | AG67: A | AH67: =I67 -> 14800 | AJ67: =I67 -> 14800 | AS67: =I67 -> 14800 | BF67: =I67/25 -> 592
A68: 45383 | B68: COOP NORGE HANDEL AS - DOM | C68: 挪威 | D68: 4500128658 | E68: 32314283 | F68: 4500128658-10 | G68: 77555GQ1-S002 | H68: 迷你房子GQ1/13PCS/箱 | I68: 3250 | J68: 0 | K68: 13 | L68: =I68/K68 -> 250 | M68: 45422 | N68: 45425 | O68: 5/16第三方已出样板 | P68: pass | Q68: 6/2出货 | R68: 45383 | S68: 无 | T68: 4/24警告语贴纸 | U68: 日期码格式：ZURU INC(BVI) 标准格式 日期：按实际生产日期 Packaging Info: 77555GQ1:MA EAN 3L+1警告语贴纸 Remark: 1/ 工厂货号77555GQ1-客户货号7223866-彩盒条码4894680033429-外箱条码10193052064261 2/ 配比： 3/ 产品和包装要求无硼无香，包装不能含有PVC 4/ 如有微塑料，必须合规欧洲标准，闪粉也是微塑料的一种，目前仅接受三张方式1.去除，2.用可降解材料，和3. 永久封印在固体。 5/ 此订单有第三方验货，每款各需要3套签样，请4-25前寄出并告知单号 | V68: Zoe Zhou | W68: 1.55 | X68: =W68*I68 -> 5037.5 | Y68: 85142-6.5 | Z68: 77555GQ1-S002-3L | AA68: 已入 | AB68: 系统出单 | AC68: 3250 | AD68: =AC68-I68 -> 0 | AE68: ok | AF68: 可接受 | AH68: =I68 -> 3250 | AK68: =I68 -> 3250 | AS68: =I68 -> 3250 | BE68: =I68/13 -> 250
A69: 45369 | B69: B&M RETAIL LIMITED | C69: 英国 | D69: 4500127087 | E69: 4500127087-2 01422809/1 | F69: 4500127087-20 | G69: 77555GQ2-S002 | H69: 迷你房子 | I69: 14800 | J69: 0 | K69: 25 | L69: =I69/K69 -> 592 | M69: 45425 | N69: 45425 | P69: pass | Q69: 5/20 截SI | R69: 45371 | S69: 无 | T69: 无 | U69: 日期码格式：ZURU INC(BVI) 标准格式 日期：按实际生产日期 Packaging Info: MA-1L配套包装 订单对应客户2个PO ，备注有显示 ，注意分开做货走柜，混装会有罚款，请注意。 Remark: *MA版本按工厂现有最新库存即可，订单出英国，请注意检查产品及包装应带UKCA图标，包装显示ZURU UK LTD信息，QC同事请查核，如有问题与跟单确认。 *生产日期按实际的（法定工作日），按ZURU标准格式即可 ，但是请知悉包装日期码需要早于或者等于外箱日期码 ，不能晚于外箱日期码 *请注意所有订单都需要经过ZURU QC验货并且通过后方可出货 *条码以订单显示为准 ，请安排生产前先核对 ，有问题请提出。 *所有产品按符合欧洲标准走货，需要是不含微塑料版本 。 *涉及到硼的，请使用低硼版本 | V69: Sherry Lu | W69: 1.59 | X69: =W69*I69 -> 23532 | Y69: 84863-5.22 | Z69: 77555GQ2-S002 | AA69: 已入 | AB69: 系统出单 | AC69: 14800 | AD69: =AC69-I69 -> 0 | AE69: 无 | AG69: A | AH69: =I69 -> 14800 | AJ69: =I69 -> 14800 | AS69: =I69 -> 14800 | BF69: =I69/25 -> 592
A70: 45373 | B70: ASDA STORES LTD | C70: 英国 | D70: 4500127552 | F70: 4500127552-50 | G70: 77555SLB-S001 | H70: 迷你房子 | I70: 14625 | J70: 0 | K70: 975 | L70: =I70/K70 -> 15 | M70: 45425 | N70: 45425 | P70: pass | Q70: 5/21 截SI | R70: 45392 | S70: 无 | T70: 4/10slip sheet贴纸 | U70: 日期码格式：ZURU INC(BVI) 标准格式 日期：按实际生产日期 Packaging Info: 5.77555SLB 77555GQ1-S002：MA最新1L UPC包装 UPC#193052064264, 请先检查条码是否正确再安排做货； Slip sheet:13pcs/PDQ/CTN 15*5H=75CTN/SLB=975pcs/Slip Sheet,一共需要15套slip sheet; Slip Sheet打包好后，需要在正唛、侧唛右下角各贴一张slip sheet贴纸，直接用A4纸打印出来即可，贴纸尺寸160mm width x 140mm high； Slip Sheet尺寸限制为100*115*130CM，一旦实际SLIP SHEET尺寸超过这个尺寸，请提前通知ZURU跟单，需同客人确认才能量产和出货; Remark: 1. 产品及包装需要印UKCA图标，包装需要有ZURU UK LTD/ZURU France地址信息，QC同事请核查，如有问题与跟单确认 2. 产品/包装/外箱都需要打ZURU格式日期码，日期必须为法定工作日。 3. 需要符合欧洲标准不能含有闪粉和微塑料，否则不和法规会有客诉产生 | V70: Sheba Ye | W70: 1489.935 | X70: =W70*L70 -> 22349.025 | Y70: 84889-2-5.23 | Z70: 77555SLB-S001 | AA70: 已入 | AB70: 系统出单 | AC70: 14625 | AD70: =AC70-I70 -> 0 | AG70: A | AH70: =I70 -> 14625 | AJ70: =I70 -> 14625 | AS70: =I70 -> 14625 | BC70: =I70/13 -> 1125
A71: 45376 | B71: ZURU LLC | C71: 美国 | D71: 4500127809 | E71: 5200004336 | F71: 4500127809-20 | G71: 77555-S001-MTS | H71: 迷你房子 | I71: 2496 | J71: 0 | K71: 24 | L71: =I71/K71 -> 104 | M71: 45425 | N71: 45425 | P71: pass | Q71: 5/27 截SI | R71: 45384 | S71: 无 | T71: 无 | U71: 日期码格式：ZURU INC(BVI) 标准格式 日期：按实际生产日期 Packaging Info: 77555：MA1L 收缩膜+5L收藏指南 Remark: 1.Amazon domestic 订单，外箱加印箱唛 （跟单提供）。出口美国。外箱最长边不能超过25" （超过了，case pack只能为1). QC验货要检查这一点，不符合要求 的大货，一律不接受。 2.无第三方验货/测试要求。 3.日期码使用ZURU标准版本。 | V71: SD24 | W71: 1.18 | X71: =W71*L71 -> 122.72 | Y71: 84948-5.27 | Z71: 77555-S001 | AA71: 已入 | AB71: 系统出单 | AC71: 2496 | AD71: =AC71-I71 -> 0 | AE71: 无 | AG71: A | AH71: =I71 -> 2496 | AJ71: =I71 -> 2496 | AS71: =I71 -> 2496
A72: 45376 | B72: ZURU LLC | C72: 美国 | D72: 4500127809 | E72: 5200004336 | F72: 4500127809-30 | G72: 77584-S001-MTS | H72: 迷你房子 | I72: 1776 | J72: 0 | K72: 12 | L72: =I72/K72 -> 148 | M72: 45425 | N72: 45425 | P72: pass | Q72: 5/27 截SI | R72: 45384 | S72: 无 | T72: 无 | U72: 日期码格式：ZURU INC(BVI) 标准格式 日期：按实际生产日期 Packaging Info: 77584：2PK 77555入PVC圆桶，77555 MA 1L不带UPC，跟单提供空白贴纸覆盖UPC，铜版纸图稿跟Amazon UK/EU PO 4500124874 Remark: 1.Amazon domestic 订单，外箱加印箱唛 （跟单提供）。出口美国。外箱最长边不能超过25" （超过了，case pack只能为1). QC验货要检查这一点，不符合要求 的大货，一律不接受。 2.无第三方验货/测试要求。 3.日期码使用ZURU标准版本。 | V72: SD24 | W72: 3 | X72: =W72*L72 -> 444 | Y72: 84948-5.27 | Z72: 77584-S001-3L | AA72: 已入 | AB72: 系统出单 | AC72: 1776 | AD72: =AC72-I72 -> 0 | AE72: ok | AG72: A | AH72: =I72*2 -> 3552 | AJ72: =I72*2 -> 3552 | AS72: =I72*2 -> 3552 | BR72: =I72 -> 1776 | BS72: =I72 -> 1776 | BT72: =I72 -> 1776 | BV72: 4/10已放 | BW72: 5496 | BX72: =BW72-I72 -> 3720
A73: 45411 | B73: AMAZON.COM.DEDC,LLC | C73: 美国 | D73: 4500132026 | E73: 8EIBP2ZW | F73: 4500132026-10 | G73: 77584-S001 | H73: 迷你房子*2 | I73: 360 | J73: 0 | K73: 12 | L73: =I73/K73 -> 30 | M73: 45428 | N73: 45425 | O73: 消耗127809减少的物料 | P73: pass | Q73: 5/20 出货 | R73: 外箱正面印ZURU Logo+侧面印item#（订单上显示的SKU#)+carton size(以工厂实际尺寸为准,单位: inch) +MADE IN CHINA | S73: 有 | T73: 55/10SSCC Label+UPC贴纸 | U73: 日期码格式：ZURU INC(BVI) 标准格式 日期：按实际生产日期 Packaging Info:77584：2PK 77555入PVC圆桶，77555 MA 1L+空白贴纸覆盖UPC，空白贴纸+铜版纸图稿跟翻单4500127809。 Remark: 1.Amazon FOB订单，出口US。 2.日期码使用ZURU标准版本。 3.如果大货有要求入邮包盒，则对应的邮包盒上面要打上日期码。 4.箱尺寸要求：外箱最长边不能超过25" （超过了，case pack只能为1），不符合要求的大货，一律不接受。 5.外箱箱唛要求： ①外箱正面印ZURU Logo+SSCC Label（客供贴纸，由跟单订购)。关于 SSCC Label 请注意： SSCC Label 显示的是客人自己的item#。每一张SSCC label 都是唯一且有不同流水及条码的，没有损耗，绝对不可贴错 。如果贴错或损坏任何一张，都会导致全 部都错，千万要注意！ SSCC Label 必须贴在外箱正面的正中间位置（贴一面即可），并且贴纸离外箱边距必须至少3cm(可以覆盖Logo<(>&<)>箱唛)，否则会影响到客户那边仓库的扫描识 别。 ②外箱侧面印item#（订单上显示的SKU#)+carton size(以工厂实际尺寸为准,单位: inch) +MADE IN CHINA,日期使用ZURU 标准版本。 6.装柜要求：按照客户PO# 装柜/箱号顺序装柜，跟单会提前给到装柜计划。 在大货生产/仓库存放时，请留意该装柜要求，以便装柜时不混乱（避免装错/装漏/找不到货号等）。 | V73: Agnes Zheng | W73: 3 | X73: =W73*I73 -> 1080 | Y73: 85590-6.27 | Z73: 77584-S001-3L | AA73: 已入 | AB73: 系统出单 | AC73: 360 | AD73: =AC73-I73 -> 0 | AE73: ok | AH73: =I73*2 -> 720 | AJ73: =I73*2 -> 720 | AS73: =I73*2 -> 720 | BR73: =I73 -> 360 | BS73: =I73 -> 360 | BT73: =I73 -> 360 | BV73: 4/10已放 | BW73: 5496 | BX73: =BX72-I73 -> 3360
A74: 45411 | B74: AMAZON.COM.DEDC,LLC | C74: 美国 | D74: 4500132026 | E74: 4GIJ32CH | F74: 4500132026-20 | G74: 77584-S001 | H74: 迷你房子*2 | I74: 456 | J74: 0 | K74: 12 | L74: =I74/K74 -> 38 | M74: 45428 | N74: 45425 | O74: 消耗127809减少的物料 | P74: pass | Q74: 5/20 出货 | R74: 外箱正面印ZURU Logo+侧面印item#（订单上显示的SKU#)+carton size(以工厂实际尺寸为准,单位: inch) +MADE IN CHINA | S74: 有 | T74: 55/10SSCC Label+UPC贴纸 | U74: 日期码格式：ZURU INC(BVI) 标准格式 日期：按实际生产日期 Packaging Info:77584：2PK 77555入PVC圆桶，77555 MA 1L+空白贴纸覆盖UPC，空白贴纸+铜版纸图稿跟翻单4500127809。 Remark: 1.Amazon FOB订单，出口US。 2.日期码使用ZURU标准版本。 3.如果大货有要求入邮包盒，则对应的邮包盒上面要打上日期码。 4.箱尺寸要求：外箱最长边不能超过25" （超过了，case pack只能为1），不符合要求的大货，一律不接受。 5.外箱箱唛要求： ①外箱正面印ZURU Logo+SSCC Label（客供贴纸，由跟单订购)。关于 SSCC Label 请注意： SSCC Label 显示的是客人自己的item#。每一张SSCC label 都是唯一且有不同流水及条码的，没有损耗，绝对不可贴错 。如果贴错或损坏任何一张，都会导致全 部都错，千万要注意！ SSCC Label 必须贴在外箱正面的正中间位置（贴一面即可），并且贴纸离外箱边距必须至少3cm(可以覆盖Logo<(>&<)>箱唛)，否则会影响到客户那边仓库的扫描识 别。 ②外箱侧面印item#（订单上显示的SKU#)+carton size(以工厂实际尺寸为准,单位: inch) +MADE IN CHINA,日期使用ZURU 标准版本。 6.装柜要求：按照客户PO# 装柜/箱号顺序装柜，跟单会提前给到装柜计划。 在大货生产/仓库存放时，请留意该装柜要求，以便装柜时不混乱（避免装错/装漏/找不到货号等）。 | V74: Agnes Zheng | W74: 3 | X74: =W74*I74 -> 1368 | Y74: 85590-6.27 | Z74: 77584-S001-3L | AA74: 已入 | AB74: 系统出单 | AC74: 456 | AD74: =AC74-I74 -> 0 | AE74: ok | AH74: =I74*2 -> 912 | AJ74: =I74*2 -> 912 | AS74: =I74*2 -> 912 | BR74: =I74 -> 456 | BS74: =I74 -> 456 | BT74: =I74 -> 456 | BV74: 4/10已放 | BW74: 5496 | BX74: =BX73-I74 -> 2904
A75: 45411 | B75: AMAZON.COM.DEDC,LLC | C75: 美国 | D75: 4500132026 | E75: 8HFU6MIU | F75: 4500132026-30 | G75: 77584-S001 | H75: 迷你房子*2 | I75: 1404 | J75: 0 | K75: 12 | L75: =I75/K75 -> 117 | M75: 45428 | N75: 45425 | O75: 消耗127809减少的物料 | P75: pass | Q75: 5/20 出货 | R75: 外箱正面印ZURU Logo+侧面印item#（订单上显示的SKU#)+carton size(以工厂实际尺寸为准,单位: inch) +MADE IN CHINA | S75: 有 | T75: 55/10SSCC Label+UPC贴纸 | U75: 日期码格式：ZURU INC(BVI) 标准格式 日期：按实际生产日期 Packaging Info:77584：2PK 77555入PVC圆桶，77555 MA 1L+空白贴纸覆盖UPC，空白贴纸+铜版纸图稿跟翻单4500127809。 Remark: 1.Amazon FOB订单，出口US。 2.日期码使用ZURU标准版本。 3.如果大货有要求入邮包盒，则对应的邮包盒上面要打上日期码。 4.箱尺寸要求：外箱最长边不能超过25" （超过了，case pack只能为1），不符合要求的大货，一律不接受。 5.外箱箱唛要求： ①外箱正面印ZURU Logo+SSCC Label（客供贴纸，由跟单订购)。关于 SSCC Label 请注意： SSCC Label 显示的是客人自己的item#。每一张SSCC label 都是唯一且有不同流水及条码的，没有损耗，绝对不可贴错 。如果贴错或损坏任何一张，都会导致全 部都错，千万要注意！ SSCC Label 必须贴在外箱正面的正中间位置（贴一面即可），并且贴纸离外箱边距必须至少3cm(可以覆盖Logo<(>&<)>箱唛)，否则会影响到客户那边仓库的扫描识 别。 ②外箱侧面印item#（订单上显示的SKU#)+carton size(以工厂实际尺寸为准,单位: inch) +MADE IN CHINA,日期使用ZURU 标准版本。 6.装柜要求：按照客户PO# 装柜/箱号顺序装柜，跟单会提前给到装柜计划。 在大货生产/仓库存放时，请留意该装柜要求，以便装柜时不混乱（避免装错/装漏/找不到货号等）。 | V75: Agnes Zheng | W75: 3 | X75: =W75*I75 -> 4212 | Y75: 85590-6.27 | Z75: 77584-S001-3L | AA75: 已入 | AB75: 系统出单 | AC75: 1404 | AD75: =AC75-I75 -> 0 | AE75: ok | AH75: =I75*2 -> 2808 | AJ75: =I75*2 -> 2808 | AS75: =I75*2 -> 2808 | BR75: =I75 -> 1404 | BS75: =I75 -> 1404 | BT75: =I75 -> 1404 | BV75: 4/10已放 | BW75: 5496 | BX75: =BX74-I75 -> 1500
A76: 45411 | B76: AMAZON.COM.DEDC,LLC | C76: 美国 | D76: 4500132026 | E76: 1WBLV82L | F76: 4500132026-40 | G76: 77584-S001 | H76: 迷你房子*2 | I76: 1500 | J76: 0 | K76: 12 | L76: =I76/K76 -> 125 | M76: 45428 | N76: 45425 | O76: 消耗127809减少的物料 | P76: pass | Q76: 5/20 出货 | R76: 外箱正面印ZURU Logo+侧面印item#（订单上显示的SKU#)+carton size(以工厂实际尺寸为准,单位: inch) +MADE IN CHINA | S76: 有 | T76: 55/10SSCC Label+UPC贴纸 | U76: 日期码格式：ZURU INC(BVI) 标准格式 日期：按实际生产日期 Packaging Info:77584：2PK 77555入PVC圆桶，77555 MA 1L+空白贴纸覆盖UPC，空白贴纸+铜版纸图稿跟翻单4500127809。 Remark: 1.Amazon FOB订单，出口US。 2.日期码使用ZURU标准版本。 3.如果大货有要求入邮包盒，则对应的邮包盒上面要打上日期码。 4.箱尺寸要求：外箱最长边不能超过25" （超过了，case pack只能为1），不符合要求的大货，一律不接受。 5.外箱箱唛要求： ①外箱正面印ZURU Logo+SSCC Label（客供贴纸，由跟单订购)。关于 SSCC Label 请注意： SSCC Label 显示的是客人自己的item#。每一张SSCC label 都是唯一且有不同流水及条码的，没有损耗，绝对不可贴错 。如果贴错或损坏任何一张，都会导致全 部都错，千万要注意！ SSCC Label 必须贴在外箱正面的正中间位置（贴一面即可），并且贴纸离外箱边距必须至少3cm(可以覆盖Logo<(>&<)>箱唛)，否则会影响到客户那边仓库的扫描识 别。 ②外箱侧面印item#（订单上显示的SKU#)+carton size(以工厂实际尺寸为准,单位: inch) +MADE IN CHINA,日期使用ZURU 标准版本。 6.装柜要求：按照客户PO# 装柜/箱号顺序装柜，跟单会提前给到装柜计划。 在大货生产/仓库存放时，请留意该装柜要求，以便装柜时不混乱（避免装错/装漏/找不到货号等）。 | V76: Agnes Zheng | W76: 3 | X76: =W76*I76 -> 4500 | Y76: 85590-6.27 | Z76: 77584-S001-3L | AA76: 已入 | AB76: 系统出单 | AC76: 1500 | AD76: =AC76-I76 -> 0 | AE76: ok | AH76: =I76*2 -> 3000 | AJ76: =I76*2 -> 3000 | AS76: =I76*2 -> 3000 | BR76: =I76 -> 1500 | BS76: =I76 -> 1500 | BT76: =I76 -> 1500 | BV76: 4/10已放 | BW76: 5496 | BX76: =BX75-I76 -> 0
A77: 45372 | B77: TOY KINGDOM (PTY) LTD | C77: 南非 | D77: 4500127529 | F77: 4500127529-10 | G77: 77555GQ1-S001 | H77: 迷你房子 | I77: 520 | J77: 0 | K77: 52 | L77: =I77/K77 -> 10 | M77: 45436 | N77: 45432 | P77: pass | Q77: 5/23 截SI | R77: 45373 | S77: 无 | T77: 无 | U77: 日期码格式：ZURU INC(BVI) 标准格式 日期：按实际生产日期 Packaging Info: MA PKG, 优先1L Remark: Order | V77: Doris Shou | W77: 1.5 | X77: =W77*I77 -> 780 | Y77: 85031-5.31 | Z77: 77555GQ1-S001 | AA77: 已入 | AB77: 系统出单 | AC77: 520 | AD77: =AC77-I77 -> 0 | AE77: 无 | AG77: A | AH77: =I77 -> 520 | AJ77: =I77 -> 520 | AS77: =I77 -> 520 | BC77: =I77/13 -> 40
A78: 45372 | B78: TOY KINGDOM (PTY) LTD | C78: 南非 | D78: 4500127529 | F78: 4500127529-10 | G78: 77555SK1-S002 | H78: 迷你房子展示架 | I78: 600 | J78: 0 | K78: 30 | L78: =I78/K78 -> 20 | M78: 45436 | N78: 45432 | P78: pass | Q78: 5/23 截SI | R78: 45373 | S78: 无 | T78: 无 | U78: 日期码格式：ZURU INC(BVI) 标准格式 日期：按实际生产日期 Packaging Info: MA PKG, 优先1L Remark: Order | V78: Doris Shou | W78: 56.598 | X78: =W78*L78 -> 1131.96 | Y78: 85031-5.31 | Z78: 77555SK1-S002-3L | AA78: 已入 | AB78: 系统出单 | AC78: 600 | AD78: =AC78-I78 -> 0 | AE78: 无 | AF78: NO | AG78: A | AH78: =I78 -> 600 | AK78: =I78 -> 600 | AS78: =I78 -> 600 | BN78: =I78/30 -> 20
A79: 45362 | B79: WAL-MART CANADA CORP. | C79: 加拿大 | D79: 4500126515 | E79: 2300875199 | F79: 4500126515-40 | G79: 77555GQ2-S002 | H79: 迷你房子 | I79: 4825 | J79: 0 | K79: 25 | L79: =I79/K79 -> 193 | M79: 45427 | N79: 45425 | P79: pass | Q79: 5/24 截SI | R79: 45366 | S79: 无 | T79: 无 | U79: 日期码格式：ZURU INC(BVI) 标准格式 日期：按实际生产日期 Packaging Info: #77555GQ2: MA3L,PDQ(25装)+客版3L,UPC条码收缩膜(UPC: 193052064264)+MA5L收藏指南 Remark: 2. 带电池的产品需使用英法双语电池(纽扣电池除外)； 3. 此单有箱唛; 4. 此单需要第三方验货，烦请多备包装物; 5. 此单需安排大货样进行签办，样品数量见下： - #77555GQ2: 2pcsPDQ+3pcs大货球+2套光身办； 6. 此单##77555,2024/4/24需安排抽办进行产中测试；抽办数量：#77555: 各4pcs大货球+4套光身办； ********************* a. 请确保产品符合1999年版本的加拿大环境保护法(CEPA)和2012年禁止某些有毒物质法规的要求。该产品不含任何在加拿大禁用的化学物质，包括但不限于有毒物 质清单中列出的化学物质，并且在为加拿大沃尔玛生产产品期间没有使用任何禁用化学物质。 Supplier certify that the products comply with the requirements of Canadian Environmental Protection Act, 1999 (CEPA), Prohibition of Certain To xic Substances Regulations, 2012. The products do not contain any chemicals that are banned in Canada, including but not limited to those listed in the Toxic Substances List and no banned chemicals were used during the manufacturing of product for Walmart Canada. 附件列表： (1) Letter of Guarantee for Canada banned chemicals - (1-5CA) b. 请确保产品在均质材料中的汞浓度不超过0.1%（按重量计）。 Supplier certify that the WAL-MART vendor products does not have a mercury concentration of more than 0.1% by weight in homogeneous material. 附件列表： (1) Letter of Guarantee for Mercury COC c. 请确保产品的塑料材料不含以下物质（SOR 2011-17 27B): Supplier certify that the plastic materials do not contain the following substances(SOR 2011-17 27B): (a) carbon tetrachloride or any substance that contains it; (b) methyl alcohol or any substance thay contains >1.0%; (c) petroleum distillates or any substance that contains >10% weight to volume of petroleum distillates; (d) benzene; (e) turpentine or any substance that contains >10% weight to volume of turpentine; (f) boric acid or salts of boric acid; or (g) ethyl ether. 附件列表： (1) Letter of Guarantee for WM CA-Other prohibited substances in plastic(less than 3 years) | V79: Monica Zhou | W79: 1.59 | X79: =W79*I79 -> 7671.75 | Y79: 84951-5.27 | Z79: 77555GQ2-S002-3L-CA | AA79: 已入 | AB79: 系统出单 | AC79: 4825 | AD79: =AC79-I79 -> 0 | AE79: 无 | AF79: NO | AG79: A | AH79: =I79 -> 4825 | AP79: =I79 -> 4825 | AS79: =I79 -> 4825 | BH79: =I79/25 -> 193
A80: 45385 | B80: TARGET US | C80: 美国 | D80: 4500128705 | E80: 5457827 | F80: 4500128705-10 | G80: 77555GQ2-S002 | H80: 迷你房子 | I80: 28000 | J80: 0 | K80: 25 | L80: =I80/K80 -> 1120 | M80: 45429 | N80: 45432 | P80: pass | Q80: 5/27 客上柜 | R80: 45394 | S80: 有 | T80: 5/2客供条码箱贴纸 | U80: 日期码格式：ZURU INC(BVI) 标准格式 日期：按实际生产日期 Packaging Info: 产品MA包装 (UPC 版), MA 1L 收缩膜, MA 1L PDQ; Remark: 1. 77555GQ2-S002-MINI BRANDS-HOME MINI BRANDS-SERIES 1-CAPSULE,25PCS/Gravity PDQ, 25PCS/PDQ/CTN 2. 产品MA包装 (UPC 版), MA 1L 收缩膜(产品UPC 显示 193052064264), MA 1L PDQ; 3. 外箱正唛左上角位置粘贴条码箱贴纸，每箱只贴一张，由ZURU订购。来料贴纸上显示的客户DPCI# 086-02-1571， UPC显示10193052064261; 4. 产品和包装上印刷 tracking code信息，格式为ZURU常规格式; 5. 出货方式：货代自提 | V80: Holly Zheng | W80: 1.55 | X80: =W80*I80 -> 43400 | Y80: 84949-5.27 | Z80: 77555GQ2-S002 | AA80: 已入 | AB80: 系统出单 | AC80: 28000 | AD80: =AC80-I80 -> 0 | AE80: OK | AH80: =I80 -> 28000 | AJ80: =I80 -> 28000 | AS80: =I80 -> 28000 | BF80: =I80/25 -> 1120
A81: 45390 | B81: KMART AUSTRALIA LTD | C81: 澳大利亚 | D81: 4500129060 | E81: 20015725 | F81: 4500129060-30 | G81: 77555GQ1-S002 | H81: 迷你房子GQ1/13PCS/箱 | I81: 3848 | J81: 0 | K81: 13 | L81: =I81/K81 -> 296 | M81: 45432 | N81: 45432 | P81: pass | Q81: 5/22 交仓 | R81: 45405 | S81: 有 | T81: 翻单125858 | U81: 日期码格式：ZURU INC(BVI) 标准格式 日期：按实际生产日期 Packaging Info: 3.77555GQ1:MA英语UPC版本包装（首选1LUPC，如果无1L可用多语含英语UPC版本）+防盗贴纸+箱唛+箱唛贴纸(1PCS/CTN).77 555GQ1防盗贴纸及其位置图请跟回PO#4500125858; Remark: 1,请务必按时完货，验货并且按期送货入货代指定仓库，如果晚了导致船期Delay将会有罚金产生或者客户要求空运，所产生的罚金和空运费由工厂承担 2，SSCC外箱贴纸请同纸箱瓦楞纸方向（竖纹向）垂直，即外箱贴纸横着贴(注意条码不要被胶带粘住）; 3.外箱材质为ZURU标准； 4.此单需使用KMART封箱胶上下工字型封箱;从2019年6月起，用客户新版封箱胶带。此单需用客户新版"ANKO"封箱胶 5.此单出口澳大利亚，请按相应澳新标准生产； 6.产品和包装上生产批号的显示格式ZURU标准日期码格式 7，外箱内容不可手写 8, 箱唛+外箱贴纸 9. 10.77555GQ1:先以FCL下单，实际出货方式为LCL | V81: Sara Wang | W81: 1.55 | X81: =W81*I81 -> 5964.4 | Y81: 85059-5.31 | Z81: 77555GQ1-S002 | AA81: 已入 | AB81: 系统出单 | AC81: 3848 | AD81: =AC81-I81 -> 0 | AE81: ok | AH81: =I81 -> 3848 | AJ81: =I81 -> 3848 | AS81: =I81 -> 3848 | BC81: =I81/13 -> 296
A82: 45355 | B82: HKS Global Resources | C82: 美国 | D82: 4500125354 | E82: ship to Japan | F82: 4500125354-70 | G82: 77555GQ2-S001 | H82: 迷你房子25pcsGQ2*2/箱 | I82: 50 | J82: 0 | K82: 50 | L82: =I82/K82 -> 1 | M82: 45432 | N82: 45433 | P82: pass | Q82: 5/25-27交仓 | R82: 45391 | S82: 有 | T82: 4/26UCC贴纸 4/9UPC 贴纸 | U82: 日期码格式：ZURU INC(BVI) 标准格式 日期：按实际生产日期 Packaging Info: ZURU MA 1L 最新包装+ UPC贴纸.UPC文档跟单提供，工厂采购；出口美国和日本。 Remark: 1. 日期跟踪码：产品包装及产品本身都必须有日期跟踪码，并且确保两者的日期跟踪码要一致；ZURU标准格式日期码(请自行调整具体年月日生产期，但不能为周 末）。 2. 外箱贴纸： 外箱除了需要印刷箱唛外，还需额外加贴Packing Slip 和 UCC 贴纸 各一张 Packing Slip: 每款产品第一箱的外箱都需在1面正唛右上角处贴上Packing Slip（跟单提供资料；工厂用A4纸打印）,见箱唛资料详细内容。 UCC贴纸：每个外箱的1面正唛右下角需贴一张UCC贴纸，贴纸尺寸为4*6 inch, PDF文档跟单提供,工厂采购。 注意：Packing Slip 和 UCC 贴纸 需出现在同一面上 3. 需要提供ZURU QC验货图片及验货报告给客户才能放SO出货，请QC验货时尽可能拍详细的图片。 4. 需在5月10日前寄出2套大货样给客户确认才可出货. 5. 该订单包含5个客户PO，分别出5个不同DC,详细见订单最右边栏的remarks ship to Japan ship to CHINO ship to SUFFOLK ship to Warsaw, NC (DC 60001) ship to San Bernardino, CA (DC 70001) | V82: Mila Yao | W82: 1.54 | X82: =W82*I82 -> 77 | Y82: 84995-5.29 | Z82: 77555GQ2-S001 | AA82: 已入 | AB82: 系统出单 | AC82: 50 | AD82: =AC82-I82 -> 0 | AE82: ok | AG82: A | AH82: =I82 -> 50 | AJ82: =I82 -> 50 | AS82: =I82 -> 50 | BF82: =I82/25 -> 2
A83: 45355 | B83: HKS Global Resources | C83: 美国 | D83: 4500125354 | E83: ship to CHINO | F83: 4500125354-180 | G83: 77555GQ2-S001 | H83: 迷你房子25pcsGQ2*2/箱 | I83: 150 | J83: 0 | K83: 50 | L83: =I83/K83 -> 3 | M83: 45432 | N83: 45433 | P83: pass | Q83: 5/25-27交仓 | R83: 45391 | S83: 有 | T83: 4/26UCC贴纸 4/9UPC 贴纸 | U83: 日期码格式：ZURU INC(BVI) 标准格式 日期：按实际生产日期 Packaging Info: ZURU MA 1L 最新包装+ UPC贴纸.UPC文档跟单提供，工厂采购；出口美国和日本。 Remark: 1. 日期跟踪码：产品包装及产品本身都必须有日期跟踪码，并且确保两者的日期跟踪码要一致；ZURU标准格式日期码(请自行调整具体年月日生产期，但不能为周 末）。 2. 外箱贴纸： 外箱除了需要印刷箱唛外，还需额外加贴Packing Slip 和 UCC 贴纸 各一张 Packing Slip: 每款产品第一箱的外箱都需在1面正唛右上角处贴上Packing Slip（跟单提供资料；工厂用A4纸打印）,见箱唛资料详细内容。 UCC贴纸：每个外箱的1面正唛右下角需贴一张UCC贴纸，贴纸尺寸为4*6 inch, PDF文档跟单提供,工厂采购。 注意：Packing Slip 和 UCC 贴纸 需出现在同一面上 3. 需要提供ZURU QC验货图片及验货报告给客户才能放SO出货，请QC验货时尽可能拍详细的图片。 4. 需在5月10日前寄出2套大货样给客户确认才可出货. 5. 该订单包含5个客户PO，分别出5个不同DC,详细见订单最右边栏的remarks ship to Japan ship to CHINO ship to SUFFOLK ship to Warsaw, NC (DC 60001) ship to San Bernardino, CA (DC 70001) | V83: Mila Yao | W83: 1.54 | X83: =W83*I83 -> 231 | Y83: 84995-5.29 | Z83: 77555GQ2-S001 | AA83: 已入 | AB83: 系统出单 | AC83: 150 | AD83: =AC83-I83 -> 0 | AE83: ok | AG83: A | AH83: =I83 -> 150 | AJ83: =I83 -> 150 | AS83: =I83 -> 150 | BF83: =I83/25 -> 6
A84: 45355 | B84: HKS Global Resources | C84: 美国 | D84: 4500125354 | E84: ship to SUFFOLK | F84: 4500125354-290 | G84: 77555GQ2-S001 | H84: 迷你房子25pcsGQ2*2/箱 | I84: 350 | J84: 0 | K84: 50 | L84: =I84/K84 -> 7 | M84: 45432 | N84: 45433 | P84: pass | Q84: 5/25-27交仓 | R84: 45391 | S84: 有 | T84: 4/26UCC贴纸 4/9UPC 贴纸 | U84: 日期码格式：ZURU INC(BVI) 标准格式 日期：按实际生产日期 Packaging Info: ZURU MA 1L 最新包装+ UPC贴纸.UPC文档跟单提供，工厂采购；出口美国和日本。 Remark: 1. 日期跟踪码：产品包装及产品本身都必须有日期跟踪码，并且确保两者的日期跟踪码要一致；ZURU标准格式日期码(请自行调整具体年月日生产期，但不能为周 末）。 2. 外箱贴纸： 外箱除了需要印刷箱唛外，还需额外加贴Packing Slip 和 UCC 贴纸 各一张 Packing Slip: 每款产品第一箱的外箱都需在1面正唛右上角处贴上Packing Slip（跟单提供资料；工厂用A4纸打印）,见箱唛资料详细内容。 UCC贴纸：每个外箱的1面正唛右下角需贴一张UCC贴纸，贴纸尺寸为4*6 inch, PDF文档跟单提供,工厂采购。 注意：Packing Slip 和 UCC 贴纸 需出现在同一面上 3. 需要提供ZURU QC验货图片及验货报告给客户才能放SO出货，请QC验货时尽可能拍详细的图片。 4. 需在5月10日前寄出2套大货样给客户确认才可出货. 5. 该订单包含5个客户PO，分别出5个不同DC,详细见订单最右边栏的remarks ship to Japan ship to CHINO ship to SUFFOLK ship to Warsaw, NC (DC 60001) ship to San Bernardino, CA (DC 70001) | V84: Mila Yao | W84: 1.54 | X84: =W84*I84 -> 539 | Y84: 84995-5.29 | Z84: 77555GQ2-S001 | AA84: 已入 | AB84: 系统出单 | AC84: 350 | AD84: =AC84-I84 -> 0 | AE84: ok | AG84: A | AH84: =I84 -> 350 | AJ84: =I84 -> 350 | AS84: =I84 -> 350 | BF84: =I84/25 -> 14
A85: 45355 | B85: HKS Global Resources | C85: 美国 | D85: 4500125354 | E85: 100PCS FOR PO#2750639 SHIP TO Warsaw, NC FCL (DC60001);200PCS FOR Po#2750640 SHIP TO San Bernardino,CA (DC 70001) | F85: 4500125354-360 | G85: 77555GQ2-S001 | H85: 迷你房子25pcsGQ2*2/箱 | I85: 300 | J85: 0 | K85: 50 | L85: =I85/K85 -> 6 | M85: 45432 | N85: 45433 | P85: pass | Q85: 5/25-27交仓 | R85: 45404 | S85: 有 | T85: 4/26UCC贴纸 4/9UPC 贴纸 | U85: 日期码格式：ZURU INC(BVI) 标准格式 日期：按实际生产日期 Packaging Info: ZURU MA 1L 最新包装+ UPC贴纸.UPC文档跟单提供，工厂采购；出口美国和日本。 Remark: 1. 日期跟踪码：产品包装及产品本身都必须有日期跟踪码，并且确保两者的日期跟踪码要一致；ZURU标准格式日期码(请自行调整具体年月日生产期，但不能为周 末）。 2. 外箱贴纸： 外箱除了需要印刷箱唛外，还需额外加贴Packing Slip 和 UCC 贴纸 各一张 Packing Slip: 每款产品第一箱的外箱都需在1面正唛右上角处贴上Packing Slip（跟单提供资料；工厂用A4纸打印）,见箱唛资料详细内容。 UCC贴纸：每个外箱的1面正唛右下角需贴一张UCC贴纸，贴纸尺寸为4*6 inch, PDF文档跟单提供,工厂采购。 注意：Packing Slip 和 UCC 贴纸 需出现在同一面上 3. 需要提供ZURU QC验货图片及验货报告给客户才能放SO出货，请QC验货时尽可能拍详细的图片。 4. 需在5月10日前寄出2套大货样给客户确认才可出货. 5. 该订单包含5个客户PO，分别出5个不同DC,详细见订单最右边栏的remarks ship to Japan ship to CHINO ship to SUFFOLK ship to Warsaw, NC (DC 60001) ship to San Bernardino, CA (DC 70001) | V85: Mila Yao | W85: 1.54 | X85: =W85*I85 -> 462 | Y85: 84995-5.29 | Z85: 77555GQ2-S001 | AA85: 已入 | AB85: 系统出单 | AC85: 300 | AD85: =AC85-I85 -> 0 | AE85: ok | AG85: A | AH85: =I85 -> 300 | AJ85: =I85 -> 300 | AS85: =I85 -> 300 | BF85: =I85/25 -> 12
A86: 45391 | B86: WAL-MART STORES INC. USA | C86: 美国 | D86: 4500129386 | E86: 0829160197 | F86: 4500129386-10 | G86: 77555GQ6-S001 | H86: 迷你房子 | I86: 9672 | J86: 0 | K86: 12 | L86: =I86/K86 -> 806 | M86: 45434 | N86: 45434 | O86: 5/25 BV | P86: pass | Q86: 5/28 截SI | R86: 45399 | S86: 有 | T86: 4/26艾利贴纸+普通贴纸+RFID贴纸 | U86: 日期码格式：ZURU DGYYYYMMDD CHINA(日期避开周末和法定节假日即可） 日期：按实际生产日期 Packaging Info: 77555GQ6-S001 1.包装要求： MA 1L收缩膜+ 客版 收藏指南+客版 1L PDQ 每pcs产品上要贴1张RFID贴纸，贴纸由ZURU提供，贴纸位置请严格按照我们签回的签板； Remark: 77555GQ6-S001 1.包装要求： MA 1L收缩膜+ 客版 收藏指南+客版 1L PDQ 每pcs产品上要贴1张RFID贴纸，贴纸由ZURU提供，贴纸位置请严格按照我们签回的签板； 2. 外箱印刷带条码的RFID箱唛：RFID紫色色带+WM Dept.图标+RFID图标+ITF-14条码+粉色艾利贴纸（不干胶打印），四面右下角印刷ZURU logo, ITFF条码只印刷在 正唛一面，在加印的时候确保条形码能扫描出来，外箱侧面任一角落加印："MADE IN CHINA" 字样； 3. 在产品上和包装上要有日期码、以及要有MADE IN CHINA和ZURU字样； 4. 产品如有扎带口要剪平，不能刮手。 5. 此单需要验货，请多备料 6. 此单以loose carton出货，12pcs/PDQ/CTN | V86: Iris Huang | W86: 1.55 | X86: =W86*I86 -> 14991.6 | Y86: 85009-5.29 | Z86: 77555GQ6-S001 | AA86: 已入 | AB86: 系统出单 | AC86: 9672 | AD86: =AC86-I86 -> 0 | AE86: OK | AH86: =I86 -> 9672 | AJ86: =I86 -> 9672 | AV86: =I86 -> 9672 | AY86: =I86/12 -> 806 | BU86: 4/10 已放 | BW86: 0
A87: 45391 | B87: WAL-MART STORES INC. USA | C87: 美国 | D87: 4500129387 | E87: 0829160188 | F87: 4500129387-10 | G87: 77555GQ6-S001 | H87: 迷你房子 | I87: 11328 | J87: 0 | K87: 12 | L87: =I87/K87 -> 944 | M87: 45434 | N87: 45430 | O87: 5/25 BV | P87: pass | Q87: 5/27 截SI | R87: 45399 | S87: 有 | T87: 4/26艾利贴纸+普通贴纸+RFID贴纸 | U87: 日期码格式：ZURU DGYYYYMMDD CHINA(日期避开周末和法定节假日即可） 日期：按实际生产日期 Packaging Info: 77555GQ6-S001 1.包装要求： MA 1L收缩膜+ 客版 收藏指南+客版 1L PDQ 每pcs产品上要贴1张RFID贴纸，贴纸由ZURU提供，贴纸位置请严格按照我们签回的签板； Remark: 77555GQ6-S001 1.包装要求： MA 1L收缩膜+ 客版 收藏指南+客版 1L PDQ 每pcs产品上要贴1张RFID贴纸，贴纸由ZURU提供，贴纸位置请严格按照我们签回的签板； 2. 外箱印刷带条码的RFID箱唛：RFID紫色色带+WM Dept.图标+RFID图标+ITF-14条码+粉色艾利贴纸（不干胶打印），四面右下角印刷ZURU logo, ITFF条码只印刷在 正唛一面，在加印的时候确保条形码能扫描出来，外箱侧面任一角落加印："MADE IN CHINA" 字样； 3. 在产品上和包装上要有日期码、以及要有MADE IN CHINA和ZURU字样； 4. 产品如有扎带口要剪平，不能刮手。 5. 此单需要验货，请多备料 6. 此单以loose carton出货，12pcs/PDQ/CTN | V87: Iris Huang | W87: 1.55 | X87: =W87*I87 -> 17558.4 | Y87: 84950-5.27 | Z87: 77555GQ6-S001 | AA87: 已入 | AB87: 系统出单 | AC87: 11328 | AD87: =AC87-I87 -> 0 | AE87: OK | AH87: =I87 -> 11328 | AJ87: =I87 -> 11328 | AV87: =I87 -> 11328 | AY87: =I87/12 -> 944 | BU87: 4/10 已放 | BW87: 0
A88: 45391 | B88: WAL-MART STORES INC. USA | C88: 美国 | D88: 4500129397 | E88: 0829160168 | F88: 4500129397-20 | G88: 77555SLB-S002 | H88: 迷你房子 | I88: 1152 | J88: 0 | K88: 1152 | L88: =I88/K88 -> 1 | M88: 45434 | N88: 45430 | O88: 5/25 BV | P88: pass | Q88: 6/7 截SI | R88: 45399 | S88: 有 | T88: 4/26艾利贴纸+普通贴纸+RFID贴纸 | U88: 日期码格式：ZURU DGYYYYMMDD CHINA(日期避开周末和法定节假日即可） 日期：按实际生产日期 Packaging Info: 77555SLB-S002 1.包装要求： MA 1L收缩膜+ 客版 收藏指南+客版 1L PDQ 每pcs产品上要贴1张RFID贴纸，贴纸由ZURU提供，贴纸位置请严格按照我们签回的签板； Remark: 77555SLB-S002 1.包装要求： MA 1L收缩膜+ 客版 收藏指南+客版 1L PDQ 每pcs产品上要贴1张RFID贴纸，贴纸由ZURU提供，贴纸位置请严格按照我们签回的签板； 2. 外箱印刷带条码的RFID箱唛：RFID紫色色带+WM Dept.图标+RFID图标+ITF-14条码，四面右下角印刷ZURU logo, ITFF条码只印刷在正唛一面，在加印的时候确保 条形码能扫描出来，外箱侧面任一角落加印："MADE IN CHINA" 字样； 3. 每个slip sheet上面贴一张艾利贴纸（不干胶贴纸）和一张普通贴纸（A4纸），slip sheet打印的普通贴纸的尺寸不能比艾利贴纸小，普通贴纸内容见附件； 4. 在产品上和包装上要有日期码、以及要有MADE IN CHINA和ZURU字样； 5. 产品如有扎带口要剪平，不能刮手。 6. 此单需要验货，请多备料 7. 以slip sheet出货， 12pcs/CTN，77555SLB-S002:1152pcs/96CTN/Slip Sheet | V88: Iris Huang | W88: 1749.5232 | X88: =W88*L88 -> 1749.5232 | Y88: 85328-6.13 | Z88: 77555SLB-S002 | AA88: 已入 | AB88: 系统出单 | AC88: 1152 | AD88: =AC88-I88 -> 0 | AE88: OK | AH88: =I88 -> 1152 | AJ88: =AH88 -> 1152 | AV88: =I88 -> 1152 | AY88: =I88/12 -> 96 | BU88: 4/10 已放 | BW88: 0
A89: 45371 | B89: ASIA GOAL LIMITED | C89: 香港 | D89: 4500127515 | E89: to HK | F89: 4500127515-10 | G89: 77555GQ1-S001 | H89: 迷你房子 | I89: 1300 | J89: 0 | K89: 52 | L89: =I89/K89 -> 25 | M89: 45432 | N89: 45433 | P89: pass | Q89: 6/3 截SI | R89: 45372 | S89: 无 | T89: 4/10客供警语贴纸 | U89: 日期码格式：ZURU INC(BVI) 标准格式 日期：按实际生产日期 Packaging Info: 77555GQ1出香港：MA 1L PKG+客供警语贴纸(一张贴球底部，一张贴收藏指南）详情参考HK客供贴纸位置图 77555GQ1出台湾：MA 1L PKG+警语贴纸（由工厂安排订购） Remark: 77555GQ1出香港：1,300pcs 77555GQ1出台湾：1,820pcs | V89: Doris Shou | W89: 1.69 | X89: =W89*I89 -> 2197 | Y89: 85347-6.14 | Z89: 77555GQ1-S001 | AA89: 已入 | AB89: 系统出单 | AC89: 1300 | AD89: =AC89-I89 -> 0 | AE89: ok | AG89: A | AH89: =I89 -> 1300 | AJ89: =I89 -> 1300 | AS89: =I89 -> 1300 | BC89: =I89/13 -> 100
A90: 45371 | B90: ASIA GOAL LIMITED | C90: 香港 | D90: 4500127515 | E90: to TW | F90: 4500127515-20 | G90: 77555GQ1-S001 | H90: 迷你房子 | I90: 1820 | J90: 0 | K90: 52 | L90: =I90/K90 -> 35 | M90: 45432 | N90: 45433 | P90: pass | Q90: 6/3 截SI | R90: 45372 | S90: 无 | T90: 4/10客供警语贴纸 | U90: 日期码格式：ZURU INC(BVI) 标准格式 日期：按实际生产日期 Packaging Info: 77555GQ1出香港：MA 1L PKG+客供警语贴纸(一张贴球底部，一张贴收藏指南）详情参考HK客供贴纸位置图 77555GQ1出台湾：MA 1L PKG+警语贴纸（由工厂安排订购） Remark: 77555GQ1出香港：1,300pcs 77555GQ1出台湾：1,820pcs | V90: Doris Shou | W90: 1.69 | X90: =W90*I90 -> 3075.8 | Y90: 85072-6.3 | Z90: 77555GQ1-S001 | AA90: 已入 | AB90: 系统出单 | AC90: 1820 | AD90: =AC90-I90 -> 0 | AE90: ok | AG90: A | AH90: =I90 -> 1820 | AJ90: =I90 -> 1820 | AS90: =I90 -> 1820 | BC90: =I90/13 -> 140
A91: 45418 | B91: ZURU | C91: 库有 | D91: ZMPO24319 | G91: 77555-S001 | H91: 迷你房子 | I91: 800 | J91: 0 | K91: 24 | L91: =I91/K91 -> 33.333333 | M91: 45432 | N91: 45433 | P91: pass | U91: 大货最新版本/数量平均/麻烦按款号装箱/并在外箱上注明款号/大货标准箱装箱/箱唛请参照邮件附件;备注：请在外箱箱唛上备注新西兰柜子样板，收到样品订单后尽快安排,注意样板品质质量要求要高于大货品质要求 ，送货时必须要附带送货单(没有送货单和QC检验合格报告的仓库一律拒绝收货)，请知悉，谢谢！ | Y91: 85426-6.19 | Z91: 77555-S001 | AA91: 已入 | AB91: 系统出单 | AC91: 800 | AD91: =AC91-I91 -> 0 | AH91: =I91 -> 800 | AJ91: =I91 -> 800 | AS91: =I91 -> 800
A92: 45385 | B92: COLES SUPERMARKETS | C92: 澳大利亚 | D92: 4500129001 | E92: 43559006 | F92: 4500129001-10 | G92: 77555GQ4-S001 | H92: 迷你房子GQ4/6pcs/箱 | I92: 504 | J92: 0 | K92: 6 | L92: =I92/K92 -> 84 | M92: 45433 | N92: 45433 | P92: pass | Q92: 5/27出货 | R92: 箱唛请按照4500124295 更新ZURU logo 即可 | S92: 无 | T92: 无 | U92: 日期码格式：ZURU INC(BVI) 标准格式 日期：按实际生产日期 Packaging Info: 1. MA UPC PACKAGING Remark: 1. 此单出澳大利亚，请按澳洲标准生产并满足当地法规要求 | V92: Lillian Li | W92: 1.6 | X92: =W92*I92 -> 806.4 | Y92: 85010-5.29 | Z92: 77555GQ4-S001 | AA92: 已入 | AB92: 系统出单 | AC92: 504 | AD92: =AC92-I92 -> 0 | AE92: 无 | AH92: =I92 -> 504 | AJ92: =I92 -> 504 | AS92: =I92 -> 504 | BA92: =I92/6 -> 84
A93: 45385 | B93: COLES SUPERMARKETS | C93: 澳大利亚 | D93: 4500129001 | E93: 43559007 | F93: 4500129001-20 | G93: 77555GQ4-S001 | H93: 迷你房子GQ4/6pcs/箱 | I93: 996 | J93: 0 | K93: 6 | L93: =I93/K93 -> 166 | M93: 45433 | N93: 45433 | P93: pass | Q93: 5/27出货 | R93: 箱唛请按照4500124295 更新ZURU logo 即可 | S93: 无 | T93: 无 | U93: 日期码格式：ZURU INC(BVI) 标准格式 日期：按实际生产日期 Packaging Info: 1. MA UPC PACKAGING Remark: 1. 此单出澳大利亚，请按澳洲标准生产并满足当地法规要求 | V93: Lillian Li | W93: 1.6 | X93: =W93*I93 -> 1593.6 | Y93: 85010-5.29 | Z93: 77555GQ4-S001 | AA93: 已入 | AB93: 系统出单 | AC93: 996 | AD93: =AC93-I93 -> 0 | AE93: 无 | AH93: =I93 -> 996 | AJ93: =I93 -> 996 | AS93: =I93 -> 996 | BA93: =I93/6 -> 166
A94: 45385 | B94: COLES SUPERMARKETS | C94: 澳大利亚 | D94: 4500129001 | E94: 43559008 | F94: 4500129001-30 | G94: 77555GQ4-S001 | H94: 迷你房子GQ4/6pcs/箱 | I94: 504 | J94: 0 | K94: 6 | L94: =I94/K94 -> 84 | M94: 45433 | N94: 45433 | P94: pass | Q94: 5/27出货 | R94: 箱唛请按照4500124295 更新ZURU logo 即可 | S94: 无 | T94: 无 | U94: 日期码格式：ZURU INC(BVI) 标准格式 日期：按实际生产日期 Packaging Info: 1. MA UPC PACKAGING Remark: 1. 此单出澳大利亚，请按澳洲标准生产并满足当地法规要求 | V94: Lillian Li | W94: 1.6 | X94: =W94*I94 -> 806.4 | Y94: 85010-5.29 | Z94: 77555GQ4-S001 | AA94: 已入 | AB94: 系统出单 | AC94: 504 | AD94: =AC94-I94 -> 0 | AE94: 无 | AH94: =I94 -> 504 | AJ94: =I94 -> 504 | AS94: =I94 -> 504 | BA94: =I94/6 -> 84
A95: 45391 | B95: WAL-MART STORES INC. USA | C95: 美国 | D95: 4500129386 | E95: 0829160190 | F95: 4500129386-20 | G95: 77555GQ6-S001 | H95: 迷你房子 | I95: 12696 | J95: 0 | K95: 12 | L95: =I95/K95 -> 1058 | M95: 45434 | N95: 45430 | O95: 5/28 BV | P95: pass | Q95: 5/30 截SI | R95: 45399 | S95: 有 | T95: 4/26艾利贴纸+普通贴纸+RFID贴纸 | U95: 日期码格式：ZURU DGYYYYMMDD CHINA(日期避开周末和法定节假日即可） 日期：按实际生产日期 Packaging Info: 77555GQ6-S001 1.包装要求： MA 1L收缩膜+ 客版 收藏指南+客版 1L PDQ 每pcs产品上要贴1张RFID贴纸，贴纸由ZURU提供，贴纸位置请严格按照我们签回的签板； Remark: 77555GQ6-S001 1.包装要求： MA 1L收缩膜+ 客版 收藏指南+客版 1L PDQ 每pcs产品上要贴1张RFID贴纸，贴纸由ZURU提供，贴纸位置请严格按照我们签回的签板； 2. 外箱印刷带条码的RFID箱唛：RFID紫色色带+WM Dept.图标+RFID图标+ITF-14条码+粉色艾利贴纸（不干胶打印），四面右下角印刷ZURU logo, ITFF条码只印刷在 正唛一面，在加印的时候确保条形码能扫描出来，外箱侧面任一角落加印："MADE IN CHINA" 字样； 3. 在产品上和包装上要有日期码、以及要有MADE IN CHINA和ZURU字样； 4. 产品如有扎带口要剪平，不能刮手。 5. 此单需要验货，请多备料 6. 此单以loose carton出货，12pcs/PDQ/CTN | V95: Iris Huang | W95: 1.55 | X95: =W95*I95 -> 19678.8 | Y95: 85324-6.13 | Z95: 77555GQ6-S001 | AA95: 已入 | AB95: 系统出单 | AC95: 12696 | AD95: =AC95-I95 -> 0 | AE95: OK | AH95: =I95 -> 12696 | AJ95: =I95 -> 12696 | AV95: =I95 -> 12696 | AY95: =I95/12 -> 1058 | BU95: 4/10 已放 | BW95: 0
A96: 45391 | B96: WAL-MART STORES INC. USA | C96: 美国 | D96: 4500129397 | E96: 0829160139 | F96: 4500129397-10 | G96: 77555SLB-S002 | H96: 迷你房子 | I96: 1152 | J96: 0 | K96: 1152 | L96: =I96/K96 -> 1 | M96: 45434 | N96: 45430 | O96: 5/28 BV | P96: pass | Q96: 6/7 截SI | R96: 45399 | S96: 有 | T96: 4/26艾利贴纸+普通贴纸+RFID贴纸 | U96: 日期码格式：ZURU DGYYYYMMDD CHINA(日期避开周末和法定节假日即可） 日期：按实际生产日期 Packaging Info: 77555SLB-S002 1.包装要求： MA 1L收缩膜+ 客版 收藏指南+客版 1L PDQ 每pcs产品上要贴1张RFID贴纸，贴纸由ZURU提供，贴纸位置请严格按照我们签回的签板； Remark: 77555SLB-S002 1.包装要求： MA 1L收缩膜+ 客版 收藏指南+客版 1L PDQ 每pcs产品上要贴1张RFID贴纸，贴纸由ZURU提供，贴纸位置请严格按照我们签回的签板； 2. 外箱印刷带条码的RFID箱唛：RFID紫色色带+WM Dept.图标+RFID图标+ITF-14条码，四面右下角印刷ZURU logo, ITFF条码只印刷在正唛一面，在加印的时候确保 条形码能扫描出来，外箱侧面任一角落加印："MADE IN CHINA" 字样； 3. 每个slip sheet上面贴一张艾利贴纸（不干胶贴纸）和一张普通贴纸（A4纸），slip sheet打印的普通贴纸的尺寸不能比艾利贴纸小，普通贴纸内容见附件； 4. 在产品上和包装上要有日期码、以及要有MADE IN CHINA和ZURU字样； 5. 产品如有扎带口要剪平，不能刮手。 6. 此单需要验货，请多备料 7. 以slip sheet出货， 12pcs/CTN，77555SLB-S002:1152pcs/96CTN/Slip Sheet | V96: Iris Huang | W96: 1749.5232 | X96: =W96*L96 -> 1749.5232 | Y96: 85413-6.19 | Z96: 77555SLB-S002 | AA96: 已入 | AB96: 系统出单 | AC96: 1152 | AD96: =AC96-I96 -> 0 | AE96: OK | AH96: =I96 -> 1152 | AJ96: =AH96 -> 1152 | AV96: =I96 -> 1152 | AY96: =I96/12 -> 96 | BU96: 4/10 已放 | BW96: 0
A97: 45391 | B97: WAL-MART STORES INC. USA | C97: 美国 | D97: 4500129388 | E97: 0829160196 | F97: 4500129388-10 | G97: 77555GQ6-S001 | H97: 迷你房子 | I97: 14736 | J97: 0 | K97: 12 | L97: =I97/K97 -> 1228 | M97: 45436 | N97: 45432 | O97: 5/30 BV | P97: pass | Q97: 6/11 截SI | R97: 45399 | S97: 有 | T97: 4/26艾利贴纸+普通贴纸+RFID贴纸 | U97: 日期码格式：ZURU DGYYYYMMDD CHINA(日期避开周末和法定节假日即可） 日期：按实际生产日期 Packaging Info: 77555GQ6-S001 1.包装要求： MA 1L收缩膜+ 客版 收藏指南+客版 1L PDQ 每pcs产品上要贴1张RFID贴纸，贴纸由ZURU提供，贴纸位置请严格按照我们签回的签板； Remark: 77555GQ6-S001 1.包装要求： MA 1L收缩膜+ 客版 收藏指南+客版 1L PDQ 每pcs产品上要贴1张RFID贴纸，贴纸由ZURU提供，贴纸位置请严格按照我们签回的签板； 2. 外箱印刷带条码的RFID箱唛：RFID紫色色带+WM Dept.图标+RFID图标+ITF-14条码+粉色艾利贴纸（不干胶打印），四面右下角印刷ZURU logo, ITFF条码只印刷在 正唛一面，在加印的时候确保条形码能扫描出来，外箱侧面任一角落加印："MADE IN CHINA" 字样； 3. 在产品上和包装上要有日期码、以及要有MADE IN CHINA和ZURU字样； 4. 产品如有扎带口要剪平，不能刮手。 5. 此单需要验货，请多备料 6. 此单以loose carton出货，12pcs/PDQ/CTN | V97: Iris Huang | W97: 1.55 | X97: =W97*I97 -> 22840.8 | Y97: 85325-6.13 | Z97: 77555GQ6-S001 | AA97: 已入 | AB97: 系统出单 | AC97: 14736 | AD97: =AC97-I97 -> 0 | AE97: OK | AH97: =I97 -> 14736 | AJ97: =I97 -> 14736 | AV97: =I97 -> 14736 | AY97: =I97/12 -> 1228 | BU97: 4/10 已放 | BW97: 0
A98: 45391 | B98: WAL-MART STORES INC. USA | C98: 美国 | D98: 4500129398 | E98: 0829160142 | F98: 4500129398-10 | G98: 77555SLB-S002 | H98: 迷你房子 | I98: 2304 | J98: 0 | K98: 1152 | L98: =I98/K98 -> 2 | M98: 45436 | N98: 45432 | O98: 5/30 BV | P98: pass | Q98: 5/31 截SI | R98: 45399 | S98: 有 | T98: 4/26艾利贴纸+普通贴纸+RFID贴纸 | U98: 日期码格式：ZURU DGYYYYMMDD CHINA(日期避开周末和法定节假日即可） 日期：按实际生产日期 Packaging Info: 77555SLB-S002 1.包装要求： MA 1L收缩膜+ 客版 收藏指南+客版 1L PDQ 每pcs产品上要贴1张RFID贴纸，贴纸由ZURU提供，贴纸位置请严格按照我们签回的签板； Remark: 77555SLB-S002 1.包装要求： MA 1L收缩膜+ 客版 收藏指南+客版 1L PDQ 每pcs产品上要贴1张RFID贴纸，贴纸由ZURU提供，贴纸位置请严格按照我们签回的签板； 2. 外箱印刷带条码的RFID箱唛：RFID紫色色带+WM Dept.图标+RFID图标+ITF-14条码，四面右下角印刷ZURU logo, ITFF条码只印刷在正唛一面，在加印的时候确保 条形码能扫描出来，外箱侧面任一角落加印："MADE IN CHINA" 字样； 3. 每个slip sheet上面贴一张艾利贴纸（不干胶贴纸）和一张普通贴纸（A4纸），slip sheet打印的普通贴纸的尺寸不能比艾利贴纸小，普通贴纸内容见附件； 4. 在产品上和包装上要有日期码、以及要有MADE IN CHINA和ZURU字样； 5. 产品如有扎带口要剪平，不能刮手。 6. 此单需要验货，请多备料 7. 以slip sheet出货， 12pcs/CTN，77555SLB-S002:1152pcs/96CTN/Slip Sheet | V98: Iris Huang | W98: 1749.5232 | X98: =W98*L98 -> 3499.0464 | Y98: 85140-6.5 | Z98: 77555SLB-S002 | AA98: 已入 | AB98: 系统出单 | AC98: 2304 | AD98: =AC98-I98 -> 0 | AE98: OK | AH98: =I98 -> 2304 | AJ98: =I98 -> 2304 | AV98: =I98 -> 2304 | AY98: =I98/12 -> 192 | BU98: 4/10 已放 | BW98: 0
A99: 45391 | B99: WAL-MART STORES INC. USA | C99: 美国 | D99: 4500129398 | E99: 0829160144 | F99: 4500129398-20 | G99: 77555SLB-S002 | H99: 迷你房子 | I99: 1152 | J99: 0 | K99: 1152 | L99: =I99/K99 -> 1 | M99: 45436 | N99: 45432 | O99: 5/30 BV | P99: pass | Q99: 6/1 截SI | R99: 45399 | S99: 有 | T99: 4/26艾利贴纸+普通贴纸+RFID贴纸 | U99: 日期码格式：ZURU DGYYYYMMDD CHINA(日期避开周末和法定节假日即可） 日期：按实际生产日期 Packaging Info: 77555SLB-S002 1.包装要求： MA 1L收缩膜+ 客版 收藏指南+客版 1L PDQ 每pcs产品上要贴1张RFID贴纸，贴纸由ZURU提供，贴纸位置请严格按照我们签回的签板； Remark: 77555SLB-S002 1.包装要求： MA 1L收缩膜+ 客版 收藏指南+客版 1L PDQ 每pcs产品上要贴1张RFID贴纸，贴纸由ZURU提供，贴纸位置请严格按照我们签回的签板； 2. 外箱印刷带条码的RFID箱唛：RFID紫色色带+WM Dept.图标+RFID图标+ITF-14条码，四面右下角印刷ZURU logo, ITFF条码只印刷在正唛一面，在加印的时候确保 条形码能扫描出来，外箱侧面任一角落加印："MADE IN CHINA" 字样； 3. 每个slip sheet上面贴一张艾利贴纸（不干胶贴纸）和一张普通贴纸（A4纸），slip sheet打印的普通贴纸的尺寸不能比艾利贴纸小，普通贴纸内容见附件； 4. 在产品上和包装上要有日期码、以及要有MADE IN CHINA和ZURU字样； 5. 产品如有扎带口要剪平，不能刮手。 6. 此单需要验货，请多备料 7. 以slip sheet出货， 12pcs/CTN，77555SLB-S002:1152pcs/96CTN/Slip Sheet | V99: Iris Huang | W99: 1749.5232 | X99: =W99*L99 -> 1749.5232 | Y99: 85029-5.30 | Z99: 77555SLB-S002 | AA99: 已入 | AB99: 系统出单 | AC99: 1152 | AD99: =AC99-I99 -> 0 | AE99: OK | AH99: =I99 -> 1152 | AJ99: =I99 -> 1152 | AV99: =I99 -> 1152 | AY99: =I99/12 -> 96 | BU99: 4/10 已放 | BW99: 0
A100: 45391 | B100: WAL-MART STORES INC. USA | C100: 美国 | D100: 4500129398 | E100: 0829160165 | F100: 4500129398-30 | G100: 77555SLB-S002 | H100: 迷你房子 | I100: 1152 | J100: 0 | K100: 1152 | L100: =I100/K100 -> 1 | M100: 45436 | N100: 45432 | O100: 5/30 BV | P100: pass | Q100: 6/7 截SI | R100: 45399 | S100: 有 | T100: 4/26艾利贴纸+普通贴纸+RFID贴纸 | U100: 日期码格式：ZURU DGYYYYMMDD CHINA(日期避开周末和法定节假日即可） 日期：按实际生产日期 Packaging Info: 77555SLB-S002 1.包装要求： MA 1L收缩膜+ 客版 收藏指南+客版 1L PDQ 每pcs产品上要贴1张RFID贴纸，贴纸由ZURU提供，贴纸位置请严格按照我们签回的签板； Remark: 77555SLB-S002 1.包装要求： MA 1L收缩膜+ 客版 收藏指南+客版 1L PDQ 每pcs产品上要贴1张RFID贴纸，贴纸由ZURU提供，贴纸位置请严格按照我们签回的签板； 2. 外箱印刷带条码的RFID箱唛：RFID紫色色带+WM Dept.图标+RFID图标+ITF-14条码，四面右下角印刷ZURU logo, ITFF条码只印刷在正唛一面，在加印的时候确保 条形码能扫描出来，外箱侧面任一角落加印："MADE IN CHINA" 字样； 3. 每个slip sheet上面贴一张艾利贴纸（不干胶贴纸）和一张普通贴纸（A4纸），slip sheet打印的普通贴纸的尺寸不能比艾利贴纸小，普通贴纸内容见附件； 4. 在产品上和包装上要有日期码、以及要有MADE IN CHINA和ZURU字样； 5. 产品如有扎带口要剪平，不能刮手。 6. 此单需要验货，请多备料 7. 以slip sheet出货， 12pcs/CTN，77555SLB-S002:1152pcs/96CTN/Slip Sheet | V100: Iris Huang | W100: 1749.5232 | X100: =W100*L100 -> 1749.5232 | Y100: 85029-5.30 | Z100: 77555SLB-S002 | AA100: 已入 | AB100: 系统出单 | AC100: 1152 | AD100: =AC100-I100 -> 0 | AE100: OK | AH100: =I100 -> 1152 | AJ100: =I100 -> 1152 | AV100: =I100 -> 1152 | AY100: =I100/12 -> 96 | BU100: 4/10 已放 | BW100: 0
...

Sheet 77555 迷你房子 旧排期
A1: ZURU （77555 迷你房子）生产排期表 | F1: 77555 MA 3LB版收缩膜，收藏指南，纸袋，GQ1，GQ2，小产品上的贴纸更新B版本，6.1号之后出加拿大的3L都需要双语logo，目前SK没有单就还没有更新 | AE1: 第一张MA是订购A版本，第二张MA订购B版本，A和B版本区别在于德语的警语不一样，A版本不能出德国
AI2: 收縮膜 | AX2: 134013 | AZ2: 收藏指南 | BG2: GQ6 | BH2: GQ6 | BI2: GQ4 | BJ2: FD GQ7 | BK2: GQ1 | BP2: GQ2 | BS2: GQ3 | BT2: SQ1 | BU2: 不带底座 | BV2: 3L | BW2: 1L | BX2: 3L | BY2: 77556 圆筒 | CC2: 77584 圆筒 | CL2: 总MA | CM2: ='生产MA '!S4 -> 5380000
A3: 香港接单日期 | B3: 第三方客户名称 | C3: 走货国家 | D3: ZURU PO NO# | E3: 第三方客户 PO NO# | F3: SKU | G3: ITEM# | H3: 中文名 | I3: PO数量 (pcs) | J3: 内箱装箱数量(pcs) | K3: 外箱装箱数量(pcs) | L3: 总箱数 | M3: 客PO期 | N3: 验货期 | O3: 第三方验货期 | P3: 驗貨結果 | Q3: S/0船期 | R3: 箱唛资料(收到日期) | S3: 外箱贴纸 | T3: 客供贴纸AI(收到日期) | U3: 备注 | V3: ZURU 跟单 | W3: 单价USD | X3: 金额USD | Y3: 發票號 | Z3: 系统货号 | AA3: 是否入系统 | AB3: 系统出单 | AC3: 送货情况 | AD3: 欠数 | AE3: 贴纸 | AG3: 球数 | AH3: 散件/空PDQ/空球壳 | AI3: MA 1语 | AJ3: MA 3语 | AK3: 1L-B版本 | AL3: 3L-B版本 | AM3: 无UPC版本 | AN3: DG 客版 | AO3: DG 新客版 | AP3: DG 更新客版 | AQ3: DG 更新-1客版 | AR3: DG 更新-2客版 | AS3: DG 更新-3客版 | AT3: DG 更新-4客版 | AU3: DG 更新-5客版 | AV3: TG客版 | AW3: WMCA客版 | AX3: MGS客版 | AY3: GP 客版 | AZ3: MA 5L语 | BA3: 5L-B版本 | BB3: 外挂收藏指南+中文说明书（每一款都不同，请做好区分） | BC3: wm us客版 | BD3: 韩语客版 | BE3: ESAL 客版 | BF3: GP 客版 | BG3: WMM 客版 | BH3: 取消UV胶版本 | BI3: 1L | BJ3: 客版 | BK3: 1L | BL3: 韩语客版 | BM3: 3L | BN3: 1L-B版本 | BO3: 3L-B版本 | BP3: 1L | BQ3: 1L-B版本 | BR3: 3L | BS3: 客版 | BT3: 客版 | BU3: 77555SK-S001 | BV3: SK-S002 60PCS | BW3: SK1-S002 30PCS | BX3: SK1-S002 30PCS | BY3: 圆筒 | BZ3: 铜板纸 | CA3: 新版铜版纸 | CB3: 贴纸 | CC3: 圆筒 | CD3: 铜板纸 | CE3: 新铜版纸 | CF3: 贴纸 | CL3: 已删减实单 | CM3: 2616809 | CN3: MA剩余 | CO3: =CM2-CM3 -> 2763191
A4: 45377 | B4: ZURU | C4: 库有 | D4: ZMPO24230 | G4: 77584-S001 | H4: 迷你房子*2 | I4: 6 | J4: 0 | K4: 12 | L4: =I4/K4 -> 0.5 | M4: 45392 | N4: 45388 | R4: 45377 | S4: 无 | T4: 无 | U4: 大货最新版本/UPC-193052066497 | V4: sally li | Z4: # | AA4: # | AC4: 6 | AD4: =AC4-I4 -> 0 | AI4: =I4*2 -> 12 | AZ4: =I4*2 -> 12 | CC4: =I4 -> 6 | CD4: =I4 -> 6 | CF4: =I4 -> 6 | CH4: 按单 | CO4: =CO3-AG4 -> 2763191
A5: 45428 | B5: ZURU | C5: 库有 | D5: ZMPO24385 | G5: 77555-S001 | H5: 迷你房子 | I5: 1000 | J5: 0 | K5: 24 | L5: =I5/K5 -> 41.666667 | M5: 45449 | N5: 45467 | P5: PASS | R5: 45428 | S5: 无 | T5: 无 | U5: 大货最新版本/款号数量平均/麻烦按款号装箱/并在外箱上注明款号/请用大货/箱唛请参照邮件附件；备注： 收到样品订单后尽快安排 ，注意样板品质质量要求要高于大货品质质量 ，送货时必须要附带送货单(没有送货单和QC检验合格报告的仓库一律拒绝收货)，请知悉，谢谢！ | Y5: 94391-2.27 | Z5: 77555-S001 | AA5: 已入 | AB5: 系统出单 | AC5: 1000 | AD5: =AC5-I5 -> 0 | AG5: =I5 -> 1000 | AI5: =I5 -> 1000 | AZ5: =I5 -> 1000 | CO5: =CO4-AG5 -> 2762191
A6: 45428 | B6: ZURU | C6: 库有 | D6: ZMPO24385 | G6: 77555-S001 | H6: 迷你房子 | I6: 100套散件 | J6: 0 | K6: 24 | L6: =I6/K6 -> #VALUE! | M6: 45449 | N6: 45467 | P6: 已送库有 | R6: 45428 | S6: 无 | T6: 无 | U6: 大货最新版本/只需要齐全套散件，麻烦用胶袋分装好一套为一袋；大货最新版本/只需要齐全套散件，麻烦用胶袋分装好一套为一袋 | Y6: 94391-2.27 | Z6: # | AA6: # | AC6: 100 | CO6: =CO5-AG6 -> 2762191
A7: 45491 | D7: ZMPO24559 | G7: 77555-S001 | H7: 迷你房子 | I7: 80套散件 | J7: 0 | K7: 24 | L7: =I7/K7 -> #VALUE! | M7: 45514 | N7: 45510 | P7: 已送库有 | R7: 7、18 | S7: 无 | T7: 无 | U7: 大货最新版本/只需要齐全套散件，麻烦用胶袋分装好一套为一袋；备注：收到样品订单后尽快安排 ，注意样板品质质量要求要高于大货品质要求 ，送货时必须要附带送货单(没有送货单和QC检验合格报告的仓库一律拒绝收货)，请知悉，谢谢！ | Y7: 94390-2.27 | Z7: # | AA7: # | AC7: 80 | AE7: 无 | CO7: =CO6-AG7 -> 2762191
A8: 45528 | B8: ZURU | C8: 库有 | D8: ZMPO24659 | G8: 77555-S001 | H8: 迷你房子 | I8: 60 | J8: 0 | K8: 24 | L8: =I8/K8 -> 2.5 | M8: 45559 | N8: 45555 | P8: 已送库有 | R8: 8、24 | S8: 无 | T8: 无 | U8: 大货最新版本/只需要齐全套散件，麻烦用胶袋分装好一套为一袋；备注： 收到样品订单后尽快安排 ，注意样板品质质量要求要高于大货品质质量 ，送货时必须要附带送货单(没有送货单和QC检验合格报告的仓库一律拒绝收货)，请知悉，谢谢！ | Y8: 94392-2.27 | Z8: # | AA8: # | AC8: 60 | AE8: 无 | CO8: =CO7-AG8 -> 2762191
A9: 45604 | B9: WAL-MART CANADA CORP. | C9: 加拿大 | D9: MPO03008 | E9: PO #4500150686 | G9: 77555-S001-MSLD118 | H9: 迷你房子-此款展示架Demo与展示架 MSLD96相同 配套387pcs | I9: 18144 | J9: 0 | K9: 24 | L9: =I9/K9 -> 756 | M9: 45632 | N9: 45628 | P9: PASS | Q9: 12/19 送库有 | R9: 周转箱 | S9: 无 | T9: 无 | U9: Remark: 1.#77555: 客版3L收缩膜(UPC: 193052064264)+MA5L收藏指南+MA配件袋+MA5L,UV胶水贴纸+MA23L说明书——客版收缩膜翻单PO: 4500126515； 2.Demo: 按照每款387pcs数量配套组装好交货 | V9: Willow Xu/Monica Zhou | W9: 0.8173 | X9: =W9*I9 -> 14829.091 | Y9: 94205-2.10 | Z9: 77555-S001-MSLD118 | AA9: 已入 | AB9: 系统出单 | AC9: =9720+8424 -> 18144 | AD9: =AC9-I9 -> 0 | AE9: 无 | AG9: =I9 -> 18144 | AW9: =I9 -> 18144 | AZ9: =I9 -> 18144 | CO9: =CO8-AG9 -> 2744047
A10: 45629 | D10: ZMPO24903 | G10: 77555SK1-S002 | H10: 迷你房子展示架 | I10: 1套空展示架 | J10: 0 | K10: 30 | L10: =I10/K10 -> #VALUE! | M10: 45632 | N10: 45628 | P10: 已寄出 | R10: 无 | S10: 无 | T10: 无 | U10: Remark：大货最新版本/麻烦配齐展示架上应有的物料（如展示架Demo+吸塑等物料） 备注： 收到样品订单后尽快安排 ，注意样板品质质量要求要高于大货品质质量 ，送货时必须要附带送货单(没有送货单和QC检验合格报告的仓库一律拒绝收货)，请知悉，谢谢！ | V10: Angus | Y10: 七 | Z10: # | AA10: # | CO10: =CO9-AG10 -> 2744047
A11: 45593 | B11: Miniso Depot CA Inc. | C11: 美国 | D11: 4500149149 | E11: 4333541366 | F11: 4500149149-20 | G11: 77555GQ2-S002 | H11: 迷你房子 | I11: 7100 | J11: 0 | K11: 25 | L11: =I11/K11 -> 284 | M11: 45645 | N11: 45642 | P11: pass | Q11: 1/3 截SI | R11: 45614 | S11: 无 | T11: UPC 条码贴纸翻单4500140602 | U11: 日期码格式：ZURU INC(BVI) 标准格式 日期：按实际生产日期 Packaging Info: 1. 包装方式：MA UPC 优先1L 最新包装，出口美国； 2. 产品和包装上印刷tracking code信息，格式为ZURU常规. Remark: 1.#77555GQ2-S002 PDQ上需要贴一张UPC 条码贴纸, UPC显示：193052064264；翻单4500140602，工厂自行采购； | V11: Iris Yuan | W11: 0.9082 | X11: =W11*I11 -> 6448.22 | Y11: 94158-1.23 | Z11: 77555GQ2-S002 | AA11: 已入 | AB11: 系统出单 | AC11: 7100 | AD11: =AC11-I11 -> 0 | AE11: ok | AG11: =I11 -> 7100 | AI11: =I11 -> 7100 | AZ11: =I11 -> 7100 | BP11: =I11/25 -> 284 | CO11: =CO10-AG11 -> 2736947
A12: 45593 | B12: Miniso Depot CA Inc. | C12: 美国 | D12: 4500149149 | E12: 4333541367 | F12: 4500149149-40 | G12: 77555GQ2-S002 | H12: 迷你房子 | I12: 6550 | J12: 0 | K12: 25 | L12: =I12/K12 -> 262 | M12: 45645 | N12: 45642 | P12: pass | Q12: 1/6 截SI | R12: 45614 | S12: 无 | T12: UPC 条码贴纸翻单4500140602 | U12: 日期码格式：ZURU INC(BVI) 标准格式 日期：按实际生产日期 Packaging Info: 1. 包装方式：MA UPC 优先1L 最新包装，出口美国； 2. 产品和包装上印刷tracking code信息，格式为ZURU常规. Remark: 1.#77555GQ2-S002 PDQ上需要贴一张UPC 条码贴纸, UPC显示：193052064264；翻单4500140602，工厂自行采购； | V12: Iris Yuan | W12: 0.9265 | X12: =W12*I12 -> 6068.575 | Y12: 94158-1.23 | Z12: 77555GQ2-S002 | AA12: 已入 | AB12: 系统出单 | AC12: 6550 | AD12: =AC12-I12 -> 0 | AE12: ok | AG12: =I12 -> 6550 | AI12: =I12 -> 6550 | AZ12: =I12 -> 6550 | BP12: =I12/25 -> 262 | CO12: =CO11-AG12 -> 2730397
A13: 45604 | B13: AMAZON.COM.DEDC,LLC | C13: 美国 | D13: 4500150761 | E13: 2R58Q8TS | F13: 4500150761-40 | G13: 77555-S001 | H13: 迷你房子 | I13: 1104 | J13: 0 | K13: 24 | L13: =I13/K13 -> 46 | M13: 45650 | N13: 45646 | P13: pass | Q13: 1/2 截SI | R13: 45604 | S13: 有 | T13: 12/2 SSCC Label | U13: 日期码格式：ZURU INC(BVI) 标准格式 日期：按实际生产日期 Packaging Info: #77555：MA1L 收缩膜+5L收藏指南。 Remark: 1. Amazon FOB订单，出口US。 2. 日期码使用ZURU标准版本。 3. 如果大货有要求入邮包盒，则对应的邮包盒上面要打上日期码。 4. 箱尺寸要求：外箱最长边不能超过25" （超过了，case pack只能为1），不符合要求的大货，一律不接受。 5. 外箱箱唛要求： ①外箱正面印ZURU Logo+SSCC Label（客供贴纸，由跟单订购)。关于 SSCC Label 请注意： SSCC Label 显示的是客人自己的item#。每一张SSCC label 都是唯一且有不同流水及条码的，没有损耗，绝对不可贴错 。如果贴错或损坏任何一张，都会导致全 部都错，千万要注意！ SSCC Label 必须贴在外箱正面的正中间位置（贴一面即可），并且贴纸离外箱边距必须至少3cm(可以覆盖Logo<(>&<)>箱唛)，否则会影响到客户那边仓库的扫描识 别。 ②外箱侧面印item#（订单上显示的SKU#)+carton size(以工厂实际尺寸为准,单位: inch) +MADE IN CHINA,日期使用ZURU 标准版本。 6. 装柜要求：按照客户PO# 装柜/箱号顺序装柜，跟单会提前给到装柜计划。 在大货生产/仓库存放时，请留意该装柜要求，以便装柜时不混乱（避免装错/装漏/找不到货号等）。 | V13: Kelly Shen | W13: 0.8484 | X13: =W13*I13 -> 936.6336 | Y13: 七 88846-1.2 | Z13: 77555-S001 | AA13: 已入 | AB13: 系统出单 | AC13: 1104 | AD13: =AC13-I13 -> 0 | AE13: ok | AG13: =I13 -> 1104 | AI13: =I13 -> 1104 | AZ13: =I13 -> 1104 | CO13: =CO12-AG13 -> 2729293
A14: 45604 | B14: AMAZON.COM.DEDC,LLC | C14: 美国 | D14: 4500150761 | E14: 3NQCKGVA | F14: 4500150761-50 | G14: 77555-S001 | H14: 迷你房子 | I14: 336 | J14: 0 | K14: 24 | L14: =I14/K14 -> 14 | M14: 45650 | N14: 45646 | P14: pass | Q14: 1/2 截SI | R14: 45604 | S14: 有 | T14: 12/2 SSCC Label | U14: 日期码格式：ZURU INC(BVI) 标准格式 日期：按实际生产日期 Packaging Info: #77555：MA1L 收缩膜+5L收藏指南。 Remark: 1. Amazon FOB订单，出口US。 2. 日期码使用ZURU标准版本。 3. 如果大货有要求入邮包盒，则对应的邮包盒上面要打上日期码。 4. 箱尺寸要求：外箱最长边不能超过25" （超过了，case pack只能为1），不符合要求的大货，一律不接受。 5. 外箱箱唛要求： ①外箱正面印ZURU Logo+SSCC Label（客供贴纸，由跟单订购)。关于 SSCC Label 请注意： SSCC Label 显示的是客人自己的item#。每一张SSCC label 都是唯一且有不同流水及条码的，没有损耗，绝对不可贴错 。如果贴错或损坏任何一张，都会导致全 部都错，千万要注意！ SSCC Label 必须贴在外箱正面的正中间位置（贴一面即可），并且贴纸离外箱边距必须至少3cm(可以覆盖Logo<(>&<)>箱唛)，否则会影响到客户那边仓库的扫描识 别。 ②外箱侧面印item#（订单上显示的SKU#)+carton size(以工厂实际尺寸为准,单位: inch) +MADE IN CHINA,日期使用ZURU 标准版本。 6. 装柜要求：按照客户PO# 装柜/箱号顺序装柜，跟单会提前给到装柜计划。 在大货生产/仓库存放时，请留意该装柜要求，以便装柜时不混乱（避免装错/装漏/找不到货号等）。 | V14: Kelly Shen | W14: 0.8484 | X14: =W14*I14 -> 285.0624 | Y14: 七 88846-1.2 | Z14: 77555-S001 | AA14: 已入 | AB14: 系统出单 | AC14: 336 | AD14: =AC14-I14 -> 0 | AE14: ok | AG14: =I14 -> 336 | AI14: =I14 -> 336 | AZ14: =I14 -> 336 | CO14: =CO13-AG14 -> 2728957
A15: 45604 | B15: AMAZON.COM.DEDC,LLC | C15: 美国 | D15: 4500150761 | E15: 36RPZOPS | F15: 4500150761-60 | G15: 77555-S001 | H15: 迷你房子 | I15: 384 | J15: 0 | K15: 24 | L15: =I15/K15 -> 16 | M15: 45650 | N15: 45646 | P15: pass | Q15: 1/2 截SI | R15: 45604 | S15: 有 | T15: 12/2 SSCC Label | U15: 日期码格式：ZURU INC(BVI) 标准格式 日期：按实际生产日期 Packaging Info: #77555：MA1L 收缩膜+5L收藏指南。 Remark: 1. Amazon FOB订单，出口US。 2. 日期码使用ZURU标准版本。 3. 如果大货有要求入邮包盒，则对应的邮包盒上面要打上日期码。 4. 箱尺寸要求：外箱最长边不能超过25" （超过了，case pack只能为1），不符合要求的大货，一律不接受。 5. 外箱箱唛要求： ①外箱正面印ZURU Logo+SSCC Label（客供贴纸，由跟单订购)。关于 SSCC Label 请注意： SSCC Label 显示的是客人自己的item#。每一张SSCC label 都是唯一且有不同流水及条码的，没有损耗，绝对不可贴错 。如果贴错或损坏任何一张，都会导致全 部都错，千万要注意！ SSCC Label 必须贴在外箱正面的正中间位置（贴一面即可），并且贴纸离外箱边距必须至少3cm(可以覆盖Logo<(>&<)>箱唛)，否则会影响到客户那边仓库的扫描识 别。 ②外箱侧面印item#（订单上显示的SKU#)+carton size(以工厂实际尺寸为准,单位: inch) +MADE IN CHINA,日期使用ZURU 标准版本。 6. 装柜要求：按照客户PO# 装柜/箱号顺序装柜，跟单会提前给到装柜计划。 在大货生产/仓库存放时，请留意该装柜要求，以便装柜时不混乱（避免装错/装漏/找不到货号等）。 | V15: Kelly Shen | W15: 0.8484 | X15: =W15*I15 -> 325.7856 | Y15: 七 88846-1.2 | Z15: 77555-S001 | AA15: 已入 | AB15: 系统出单 | AC15: 384 | AD15: =AC15-I15 -> 0 | AE15: ok | AG15: =I15 -> 384 | AI15: =I15 -> 384 | AZ15: =I15 -> 384 | CO15: =CO14-AG15 -> 2728573
A16: 45604 | B16: AMAZON.COM.DEDC,LLC | C16: 美国 | D16: 4500150745 | E16: 2MCXNKGF | F16: 4500150745-10 | G16: 77555-S001 | H16: 迷你房子 | I16: 72 | J16: 0 | K16: 24 | L16: =I16/K16 -> 3 | M16: 45650 | N16: 45646 | P16: pass | Q16: 12、28 交仓 | R16: 45604 | S16: 有 | T16: 12/2 SSCC Label | U16: 日期码格式：ZURU INC(BVI) 标准格式 日期：按实际生产日期 Packaging Info: #77555：MA1L 收缩膜+5L收藏指南。 Remark: 1. Amazon FOB订单，出口US。 2. 日期码使用ZURU标准版本。 3. 如果大货有要求入邮包盒，则对应的邮包盒上面要打上日期码。 4. 箱尺寸要求：外箱最长边不能超过25" （超过了，case pack只能为1），不符合要求的大货，一律不接受。 5. 外箱箱唛要求： ①外箱正面印ZURU Logo+SSCC Label（客供贴纸，由跟单订购)。关于 SSCC Label 请注意： SSCC Label 显示的是客人自己的item#。每一张SSCC label 都是唯一且有不同流水及条码的，没有损耗，绝对不可贴错 。如果贴错或损坏任何一张，都会导致全 部都错，千万要注意！ SSCC Label 必须贴在外箱正面的正中间位置（贴一面即可），并且贴纸离外箱边距必须至少3cm(可以覆盖Logo<(>&<)>箱唛)，否则会影响到客户那边仓库的扫描识 别。 ②外箱侧面印item#（订单上显示的SKU#)+carton size(以工厂实际尺寸为准,单位: inch) +MADE IN CHINA,日期使用ZURU 标准版本。 6. 装柜要求：按照客户PO# 装柜/箱号顺序装柜，跟单会提前给到装柜计划。 在大货生产/仓库存放时，请留意该装柜要求，以便装柜时不混乱（避免装错/装漏/找不到货号等）。 | V16: Kelly Shen | W16: 0.8778 | X16: =W16*I16 -> 63.2016 | Y16: 七 88838-1.2 | Z16: 77555-S001 | AA16: 已入 | AB16: 系统出单 | AC16: 72 | AD16: =AC16-I16 -> 0 | AE16: ok | AG16: =I16 -> 72 | AI16: =I16 -> 72 | AZ16: =I16 -> 72 | CO16: =CO15-AG16 -> 2728501
A17: 45621 | B17: WAL-MART STORES INC. USA | C17: 美国 | D17: 4500152241 | E17: 0877286357 ELWOOD | F17: 4500152241-30 | G17: 77555SLB-S002 | H17: 迷你房子 | I17: 1152 | J17: 0 | K17: 1152 | L17: =I17/K17 -> 1 | M17: 45649 | N17: 45645 | O17: 12/23 BV | P17: pass | Q17: 1/7 截SI | R17: 翻单 | S17: 有 | T17: 12/6 RFID贴纸 | U17: 日期码格式：ZURU DGYYYYMMDD CHINA(日期避开周末和法定节假日即可） 日期：按实际生产日期 Tracking Code: Packaging Info: 77555SLB-S002 1.包装要求： MA 1L收缩膜+ 客版 收藏指南+客版 1L PDQ，翻单：4500129394 每pcs产品上要贴1张RFID贴纸，贴纸由ZURU提供，贴纸位置请严格按照我们签回的签板； Remark: 77555SLB-S002 1.包装要求： MA 1L收缩膜+ 客版 收藏指南+客版 1L PDQ，翻单：4500129394 每pcs产品上要贴1张RFID贴纸，贴纸由ZURU提供，贴纸位置请严格按照我们签回的签板； 2. 外箱印刷带条码的RFID箱唛：RFID紫色色带+WM Dept.图标+RFID图标+ITF-14条码，四面右下角印刷ZURU logo, ITFF条码只印刷在正唛一面，在加印的时候确保 条形码能扫描出来，外箱侧面任一角落加印："MADE IN CHINA" 字样； 3. 每个slip sheet上面贴一张艾利贴纸（不干胶贴纸）和一张普通贴纸（A4纸），slip sheet打印的普通贴纸的尺寸不能比艾利贴纸小，普通贴纸内容见附件； 4. 在产品上和包装上要有日期码、以及要有MADE IN CHINA和ZURU字样； 5. 产品如有扎带口要剪平，不能刮手。 6. 此单需要验货，请多备料 7. 以slip sheet出货， 77555SLB-S002:1152pcs/96CTN/Slip Sheet | V17: Maggie Xie | W17: 1011.5343 | X17: =W17*L17 -> 1011.5343 | Y17: 七 88860-1.3 | Z17: 77555SLB-S002 | AA17: 已入 | AB17: 系统出单 | AC17: 1152 | AD17: =AC17-I17 -> 0 | AE17: OK | AG17: =I17 -> 1152 | AI17: =I17 -> 1152 | BC17: =I17 -> 1152 | BG17: =I17/12 -> 96 | CG17: 11/25 已放 | CI17: 0 | CO17: =CO16-AG17 -> 2727349
A18: 45621 | B18: WAL-MART STORES INC. USA | C18: 美国 | D18: 4500152241 | E18: 0877286383 STATESBORO | F18: 4500152241-40 | G18: 77555SLB-S002 | H18: 迷你房子 | I18: 2304 | J18: 0 | K18: 1152 | L18: =I18/K18 -> 2 | M18: 45649 | N18: 45645 | O18: 12/23 BV | P18: pass | Q18: 1/10 截SI | R18: 翻单 | S18: 有 | T18: 12/6 RFID贴纸 | U18: 日期码格式：ZURU DGYYYYMMDD CHINA(日期避开周末和法定节假日即可） 日期：按实际生产日期 Tracking Code: Packaging Info: 77555SLB-S002 1.包装要求： MA 1L收缩膜+ 客版 收藏指南+客版 1L PDQ，翻单：4500129394 每pcs产品上要贴1张RFID贴纸，贴纸由ZURU提供，贴纸位置请严格按照我们签回的签板； Remark: 77555SLB-S002 1.包装要求： MA 1L收缩膜+ 客版 收藏指南+客版 1L PDQ，翻单：4500129394 每pcs产品上要贴1张RFID贴纸，贴纸由ZURU提供，贴纸位置请严格按照我们签回的签板； 2. 外箱印刷带条码的RFID箱唛：RFID紫色色带+WM Dept.图标+RFID图标+ITF-14条码，四面右下角印刷ZURU logo, ITFF条码只印刷在正唛一面，在加印的时候确保 条形码能扫描出来，外箱侧面任一角落加印："MADE IN CHINA" 字样； 3. 每个slip sheet上面贴一张艾利贴纸（不干胶贴纸）和一张普通贴纸（A4纸），slip sheet打印的普通贴纸的尺寸不能比艾利贴纸小，普通贴纸内容见附件； 4. 在产品上和包装上要有日期码、以及要有MADE IN CHINA和ZURU字样； 5. 产品如有扎带口要剪平，不能刮手。 6. 此单需要验货，请多备料 7. 以slip sheet出货， 77555SLB-S002:1152pcs/96CTN/Slip Sheet | V18: Maggie Xie | W18: 1011.5343 | X18: =W18*L18 -> 2023.0686 | Y18: 七 88945-1.8 | Z18: 77555SLB-S002 | AA18: 已入 | AB18: 系统出单 | AC18: 2304 | AD18: =AC18-I18 -> 0 | AE18: OK | AG18: =I18 -> 2304 | AI18: =I18 -> 2304 | BC18: =I18 -> 2304 | BG18: =I18/12 -> 192 | CG18: 11/25 已放 | CI18: 0 | CO18: =CO17-AG18 -> 2725045
A19: 45621 | B19: WAL-MART STORES INC. USA | C19: 美国 | D19: 4500152241 | E19: 0877286397 EASTVALE | F19: 4500152241-50 | G19: 77555SLB-S002 | H19: 迷你房子 | I19: 3456 | J19: 0 | K19: 1152 | L19: =I19/K19 -> 3 | M19: 45649 | N19: 45645 | O19: 12/23 BV | P19: pass | Q19: 1/4 截仓 | R19: 翻单 | S19: 有 | T19: 12/6 RFID贴纸 | U19: 日期码格式：ZURU DGYYYYMMDD CHINA(日期避开周末和法定节假日即可） 日期：按实际生产日期 Tracking Code: Packaging Info: 77555SLB-S002 1.包装要求： MA 1L收缩膜+ 客版 收藏指南+客版 1L PDQ，翻单：4500129394 每pcs产品上要贴1张RFID贴纸，贴纸由ZURU提供，贴纸位置请严格按照我们签回的签板； Remark: 77555SLB-S002 1.包装要求： MA 1L收缩膜+ 客版 收藏指南+客版 1L PDQ，翻单：4500129394 每pcs产品上要贴1张RFID贴纸，贴纸由ZURU提供，贴纸位置请严格按照我们签回的签板； 2. 外箱印刷带条码的RFID箱唛：RFID紫色色带+WM Dept.图标+RFID图标+ITF-14条码，四面右下角印刷ZURU logo, ITFF条码只印刷在正唛一面，在加印的时候确保 条形码能扫描出来，外箱侧面任一角落加印："MADE IN CHINA" 字样； 3. 每个slip sheet上面贴一张艾利贴纸（不干胶贴纸）和一张普通贴纸（A4纸），slip sheet打印的普通贴纸的尺寸不能比艾利贴纸小，普通贴纸内容见附件； 4. 在产品上和包装上要有日期码、以及要有MADE IN CHINA和ZURU字样； 5. 产品如有扎带口要剪平，不能刮手。 6. 此单需要验货，请多备料 7. 以slip sheet出货， 77555SLB-S002:1152pcs/96CTN/Slip Sheet | V19: Maggie Xie | W19: 1011.5343 | X19: =W19*L19 -> 3034.6029 | Y19: 七 88875-1.4 | Z19: 77555SLB-S002 | AA19: 已入 | AB19: 系统出单 | AC19: 3456 | AD19: =AC19-I19 -> 0 | AE19: OK | AG19: =I19 -> 3456 | AI19: =I19 -> 3456 | BC19: =I19 -> 3456 | BG19: =I19/12 -> 288 | CG19: 11/25 已放 | CI19: 0 | CO19: =CO18-AG19 -> 2721589
A20: 45621 | B20: WAL-MART STORES INC. USA | C20: 美国 | D20: 4500152241 | E20: 0877286399 HOUSTON | F20: 4500152241-60 | G20: 77555SLB-S002 | H20: 迷你房子 | I20: 5760 | J20: 0 | K20: 1152 | L20: =I20/K20 -> 5 | M20: 45649 | N20: 45645 | O20: 12/23 BV | P20: pass | Q20: 12/30 截SI | R20: 翻单 | S20: 有 | T20: 12/6 RFID贴纸 | U20: 日期码格式：ZURU DGYYYYMMDD CHINA(日期避开周末和法定节假日即可） 日期：按实际生产日期 Tracking Code: Packaging Info: 77555SLB-S002 1.包装要求： MA 1L收缩膜+ 客版 收藏指南+客版 1L PDQ，翻单：4500129394 每pcs产品上要贴1张RFID贴纸，贴纸由ZURU提供，贴纸位置请严格按照我们签回的签板； Remark: 77555SLB-S002 1.包装要求： MA 1L收缩膜+ 客版 收藏指南+客版 1L PDQ，翻单：4500129394 每pcs产品上要贴1张RFID贴纸，贴纸由ZURU提供，贴纸位置请严格按照我们签回的签板； 2. 外箱印刷带条码的RFID箱唛：RFID紫色色带+WM Dept.图标+RFID图标+ITF-14条码，四面右下角印刷ZURU logo, ITFF条码只印刷在正唛一面，在加印的时候确保 条形码能扫描出来，外箱侧面任一角落加印："MADE IN CHINA" 字样； 3. 每个slip sheet上面贴一张艾利贴纸（不干胶贴纸）和一张普通贴纸（A4纸），slip sheet打印的普通贴纸的尺寸不能比艾利贴纸小，普通贴纸内容见附件； 4. 在产品上和包装上要有日期码、以及要有MADE IN CHINA和ZURU字样； 5. 产品如有扎带口要剪平，不能刮手。 6. 此单需要验货，请多备料 7. 以slip sheet出货， 77555SLB-S002:1152pcs/96CTN/Slip Sheet | V20: Maggie Xie | W20: 1011.5343 | X20: =W20*L20 -> 5057.6715 | Y20: 七 88875-1.4 | Z20: 77555SLB-S002 | AA20: 已入 | AB20: 系统出单 | AC20: 5760 | AD20: =AC20-I20 -> 0 | AE20: OK | AG20: =I20 -> 5760 | AI20: =I20 -> 5760 | BC20: =I20 -> 5760 | BG20: =I20/12 -> 480 | CG20: 11/25 已放 | CI20: 0 | CO20: =CO19-AG20 -> 2715829
A21: 45621 | B21: WAL-MART STORES INC. USA | C21: 美国 | D21: 4500152241 | E21: 0877286420 SUFFOLK | F21: 4500152241-70 | G21: 77555SLB-S002 | H21: 迷你房子 | I21: 10368 | J21: 0 | K21: 1152 | L21: =I21/K21 -> 9 | M21: 45649 | N21: 45645 | O21: 12/23 BV | P21: pass | R21: 翻单 | S21: 有 | T21: 12/6 RFID贴纸 | U21: 日期码格式：ZURU DGYYYYMMDD CHINA(日期避开周末和法定节假日即可） 日期：按实际生产日期 Tracking Code: Packaging Info: 77555SLB-S002 1.包装要求： MA 1L收缩膜+ 客版 收藏指南+客版 1L PDQ，翻单：4500129394 每pcs产品上要贴1张RFID贴纸，贴纸由ZURU提供，贴纸位置请严格按照我们签回的签板； Remark: 77555SLB-S002 1.包装要求： MA 1L收缩膜+ 客版 收藏指南+客版 1L PDQ，翻单：4500129394 每pcs产品上要贴1张RFID贴纸，贴纸由ZURU提供，贴纸位置请严格按照我们签回的签板； 2. 外箱印刷带条码的RFID箱唛：RFID紫色色带+WM Dept.图标+RFID图标+ITF-14条码，四面右下角印刷ZURU logo, ITFF条码只印刷在正唛一面，在加印的时候确保 条形码能扫描出来，外箱侧面任一角落加印："MADE IN CHINA" 字样； 3. 每个slip sheet上面贴一张艾利贴纸（不干胶贴纸）和一张普通贴纸（A4纸），slip sheet打印的普通贴纸的尺寸不能比艾利贴纸小，普通贴纸内容见附件； 4. 在产品上和包装上要有日期码、以及要有MADE IN CHINA和ZURU字样； 5. 产品如有扎带口要剪平，不能刮手。 6. 此单需要验货，请多备料 7. 以slip sheet出货， 77555SLB-S002:1152pcs/96CTN/Slip Sheet | V21: Maggie Xie | W21: 1011.5343 | X21: =W21*L21 -> 9103.8087 | Y21: 七 88840-1.2 | Z21: 77555SLB-S002 | AA21: 已入 | AB21: 系统出单 | AC21: 10368 | AD21: =AC21-I21 -> 0 | AE21: OK | AG21: =I21 -> 10368 | AI21: =I21 -> 10368 | BC21: =I21 -> 10368 | BG21: =I21/12 -> 864 | CG21: 11/25 已放 | CI21: 0 | CK21: 指南 | CL21: PDQ | CO21: =CO20-AG21 -> 2705461
A22: 45608 | B22: ZURU France | C22: 法国 | D22: 4500151007 | E22: 5200005637 | F22: 4500151007-10 | G22: 77555GQ1-S002-MTS | H22: 迷你房子GQ1/13PCS/箱 | I22: 1560 | J22: 0 | K22: 13 | L22: =I22/K22 -> 120 | M22: 45650 | N22: 45646 | P22: pass | Q22: 12/24 截SI | R22: 45618 | S22: 无 | T22: 11、13 环保标贴纸 | U22: 日期码格式：ZURU INC(BVI) 标准格式 日期：按实际生产日期 Packaging Info: 77555GQ1: MA 3L +5L warning EAN版本收缩膜+一张法国意大利西班牙环保标贴纸+MA 5L A版收藏指南； Remark: 1. 西班牙国家内销单，需要通过ZURU 验货结果后才能出货 (工厂需要主动提前同ZURU QC预约验货避免延期出货造成不必要麻烦)； 2. 本订单所有 具有 baby items / assorted items 的款式，零售包装上都要用 母 EAN; 3. 若有特定款有特殊外箱条码要求时,需要明确列出产品款对应的具体外箱条码号码/条码类型 (若无,可以忽略此需求) 4. 所有出口欧洲的产品, 法规规定禁止在包装和共公众用的印刷品中使用矿物油中含有的物质, 包装印刷油墨中含有的MOAH/MOSH的质量浓度不能超过1%, 否则出 货到法国被抽检出现问题, 供应商需要对此负责; 5. date code: 外箱/产品/包装 保持一致，完货后提供date code 信息以便我们保存记录做批次管理; 6. 装柜时需要按照款式号码从小到大一款款依次装,避免终端仓库卸货混乱.若一个柜子涉及到几个不同国家内销单,装柜时需要一个国家装完后再装另一个国家的 产品,依次装柜,避免终端仓库因不同国家不同库位位置卸货混乱. (此点需要同工厂装柜人员强调) | V22: SD83 | W22: 0.8797 | X22: =W22*I22 -> 1372.332 | Y22: 七 88839-1.2 | Z22: 77555GQ1-S002-3L | AA22: 已入 | AB22: 系统出单 | AC22: 1560 | AD22: =AC22-I22 -> 0 | AE22: OK | AG22: =I22 -> 1560 | AJ22: =I22 -> 1560 | AZ22: =I22 -> 1560 | BM22: =I22/13 -> 120 | CO22: =CO21-AG22 -> 2703901
A23: 45590 | B23: Amazon EU SARL, Ndl Deutschland | C23: 德国 | D23: 4500148999 | E23: 4WZA5DAX | F23: 4500148999-10 | G23: 77584-S001 | H23: 迷你房子 | I23: 504 | J23: 0 | K23: 12 | L23: =I23/K23 -> 42 | M23: 45651 | N23: 45647 | P23: 自检 | Q23: 1/4 入仓 | R23: 空白外箱（加印带Zuru字样的最新logo，除了邮包盒直接做外箱的产品） | S23: 有 | T23: 11/21SSCC LABEL+空白贴纸+IT sorting label翻单124874+ES回收标志1号翻单145205+12/2 ZURU邮箱贴 | U23: 日期码格式：ZURU INC(BVI) 标准格式 日期：按实际生产日期 Packaging Info: Amazon DE 77584 1.77584: 77555 2pcs/pvc tube, 12tubes/ctn; MA 3L (5L WARNING) 收缩膜（EAN#请用空白贴纸覆盖）+MA 其他最新包装+客版3L(5L warning)PVC tube彩卡(参 考翻单PO#4500131987)+3张贴纸(1张IT sorting label, 参考翻单PO#4500124874；1张ES回收标志1号，参考翻单PO#4500145205；1张ZURU邮箱)； 5. ZURU 验货最迟不得晚于2024/12/26 Remark: 1.空白外箱（加印带Zuru字样的最新logo，除了邮包盒直接做外箱的产品） + SSCC LABEL一张, 无箱唛. (SSCC LABEL贴在外箱正面的正中间，贴一面即可,贴纸离外箱边距必须至少3.2CM),SSCC贴纸由工厂直接跟勤得采购或者工厂自行采购，每一张SSCC Label都是唯一 且有不同流水及条码，且需要检查条码是否能正常扫描，另外，此贴纸印刷不可出现模糊，溢出及粘胶不牢易脱落等现象，如工厂不按此要求导致贴纸有任何问题产 生的罚款将由工厂承担一切责任 。’MADE IN CHINA 外箱只印一正一侧。 2. 出往UK的产品+包装务必打上UKCA logo ，否则客人会退货且当地会有罚款。 3.订单必须经过ZURU QC验货并且通过后方可出货。 4.法国订单要求包装不使用矿物油，请按要求提供以下其中一份文件再出货 ，产品出到法国被相关部门抽检出现包装不符合此要求的，供应商需要为此承担责任， 故此请严格把关 。 -油墨物质""由1 ~ 7个芳香环组成的MOAH""的包装检测报告，要求限值≤1.0%; -包装材料清单，包括包装油墨或物质的信息 -油墨制造商的证书。 5 . 每一批次出货只能有一个生产日期，不可多个生产日期混在同一批次出货；且邮包盒上必须统一加上日期码； 6. 涉及到相关款式会有闪粉的或 者微塑料的，请统一默认出无闪粉或者不含微塑料 版本; 7 .邮包盒及外箱封箱必须是工字型封箱方式； 8 . 5 Surprise or Mini Brands涉及包装是2个及2个以上的球入PVC桶包装时，单个球上若有UPC#或者EAN#，请用白色贴纸覆盖住； | V23: Zoe Chen | W23: 2.4352 | X23: =W23*I23 -> 1227.3408 | Y23: 七 88946-1.8 | Z23: 77584-S001-3L-1 | AA23: 已入 | AB23: 系统出单 | AC23: =492+12 -> 504 | AD23: =AC23-I23 -> 0 | AE23: ok | AG23: =I23*2 -> 1008 | AJ23: =AG23 -> 1008 | AZ23: =I23*2 -> 1008 | CC23: =I23 -> 504 | CD23: =I23 -> 504 | CF23: =I23 -> 504 | CH23: 10/25已放 | CI23: 5000 | CJ23: =CI23-I23 -> 4496 | CO23: =CO22-AG23 -> 2702893
A24: 45607 | B24: TARGET US | C24: 美国 | D24: 4500150929 | E24: 10001033427-3890 | F24: 4500150929-10 | G24: 77555GQ2-S002 | H24: 迷你房子 | I24: 37525 | J24: 0 | K24: 25 | L24: =I24/K24 -> 1501 | M24: 45651 | N24: 45647 | P24: pass | Q24: 1/6 客自提 | R24: 45621 | S24: 有 | T24: 12/6条码箱贴纸 | U24: 日期码格式：ZURU INC(BVI) 标准格式 日期：按实际生产日期 Tracking Code: Packaging Info: 产品MA包装 (UPC 版), MA 1L 收缩膜, MA 1L PDQ; Remark: 1. 77555GQ2-S002-MINI BRANDS-HOME MINI BRANDS-SERIES 1-CAPSULE,25PCS/Gravity PDQ, 25PCS/PDQ/CTN 2. 产品MA包装 (UPC 版), MA 1L 收缩膜，收缩膜上的UPC显示 193052064264, MA 1L PDQ; 3. 外箱正唛左上角位置粘贴条码箱贴纸，每箱只贴一张，由ZURU订购。来料贴纸上显示的客户DPCI# 086-02-1571， UPC显示10193052064261; 4. 产品和包装上印刷 tracking code信息，格式为ZU | V24: Holly Zheng | W24: 0.8967 | X24: =W24*I24 -> 33648.668 | Y24: 七 88894-1.6 | Z24: 77555GQ2-S002 | AA24: 已入 | AB24: 系统出单 | AC24: =7875+29650 -> 37525 | AD24: =AC24-I24 -> 0 | AE24: ok | AG24: =I24 -> 37525 | AI24: =I24 -> 37525 | AZ24: =I24 -> 37525 | BP24: =I24/25 -> 1501 | CO24: =CO23-AG24 -> 2665368
A25: 45644 | B25: WALGREEN CO. | C25: 美国 | D25: MPO03152 | E25: 此MPO订单替换原手工单MPOWAL034 | G25: 77555-S001 | H25: 迷你房子8个球按配比分隔开/箱 | I25: 42616 | J25: 0 | K25: 24 | L25: =I25/K25 -> 1775.6667 | M25: 45667 | N25: 45663 | P25: pass | Q25: 8504pcs 1/10 送库有 | R25: 周转箱 | S25: 无 | T25: 10/24 WIC贴纸 | U25: Remark:1.此MPO订单替换原手工单MPOWAL034 2.订单要求参考MPOWAL034 3.分三批送货 第-批 77485-8528pcs 77555-8528pcs(已送货)第二批77485-25584pcs77555-25584pcs(已送货)第三批 77485-8504pcs77555-8504pcs(待安排送货) | V25: Cara Li | W25: 0.8115 | X25: =W25*I25 -> 34582.884 | Y25: 94402-2.27 94410-2.28 | Z25: 77555-S001 | AA25: 已入 | AB25: 系统出单 | AC25: 11月份送回的 | AG25: =I25 -> 42616 | AI25: =I25 -> 42616 | AZ25: =I25 -> 42616 | CO25: =CO24-AG25 -> 2622752
A26: 45586 | B26: ROSS PROCUREMENT.INC | C26: 美国 | D26: 4500148421 | E26: 60190475 | F26: 4500148421-30 | G26: 77584-S001 | H26: 迷你房子 | I26: 6000 | J26: 0 | K26: 12 | L26: =I26/K26 -> 500 | M26: 45653 | N26: 45649 | P26: pass | Q26: 1/3 截SI | R26: 45588 | S26: 无 | T26: 11/20 客供价格贴纸 | U26: 日期码格式： 标准格式 日期：按实际生产日期 Packaging Info: URU MA UPC 收缩膜+客版铜版纸+PVC桶 + 客供价格贴纸，出口美国 , 优先使用MA 1L 最新版本 。 Remark: 1.ZURU MA UPC 收缩膜+客版铜版纸+PVC桶 + 客供价格贴纸，出口美国 , 优先使用MA 1L 最新版本 。 2.价格贴纸位于包装正面右下角，不挡住重要信息即可，可适当调整 ，价格贴纸由跟单提供。 3.标准日期码格式，产品和包装必须有日期码 。 4.同个产品同个货期不可出现不同的包装。 5. PVC 桶中球不能出现完全相同的ASSORTMENT ， 即同一个PVC 中球里的ASSORTMENT 需要不同。 以免消费者失望。 6.PVC 桶上加上 MINI BRANDS 的LOGO 贴纸 （ ZURU 统一要求的） 7.收缩膜可使用标版带UPC条码MA，无需白色贴纸覆盖。 | V26: Sophia Zhou | W26: 2.3775 | X26: =W26*I26 -> 14265 | Y26: 七 88928-1.7 | Z26: 77584-S001-3L | AA26: 已入 | AB26: 系统出单 | AC26: =5988+12 -> 6000 | AD26: =AC26-I26 -> 0 | AE26: ok | AG26: =I26*2 -> 12000 | AI26: =I26*2 -> 12000 | AZ26: =I26*2 -> 12000 | CC26: =I26 -> 6000 | CD26: =I26 -> 6000 | CF26: =I26 -> 6000 | CH26: 按实单 | CO26: =CO25-AG26 -> 2610752
A27: 45601 | B27: DD’S DISCOUNTS | C27: 美国 | D27: 4500150183 | E27: 70054027 | F27: 4500150183-10 | G27: 77584-S001 | H27: 迷你房子 | I27: 600 | J27: 0 | K27: 12 | L27: =I27/K27 -> 50 | M27: 45653 | N27: 45649 | P27: 自检 | Q27: 1/7交仓 | R27: 11、5 | S27: 无 | T27: 11/20 客供价格贴纸 | U27: 日期码格式：ZURU INC(BVI) 标准格式 日期：按实际生产日期 Packaging Info: 1.ZURU MA UPC 现有版本包装 + 客供价格贴纸，出口美国 , 优先使用MA 1L 最新版本 。 Remark: 1.ZURU MA UPC 现有版本包装 + 客供价格贴纸，出口美国 , 优先使用MA 1L 最新版本 。 2.价格贴纸位于包装正面右下角，不挡住重要信息即可，可适当调整 ，价格贴纸由跟单提供。 3.标准日期码格式，产品和包装必须有日期码 。 4.同个产品同个货期不可出现不同的包装。 5. 跟单提供ROSS通用的箱唛模版，工厂按实际45 PO上客户PO/Item号/装箱数 提供箱唛排版来确认。 6. PVC 桶中球不能出现完全相同的ASSORTMENT ， 即同一个PVC 中球里的ASSORTMENT 需要不同。 以免消费者失望。 7.PVC 桶上加上 5 surprise 的LOGO 贴纸 （ ZURU 统一要求的） 8.收缩膜可使用标版带UPC条码MA，无需白色贴纸覆盖。 | V27: Taylor Liao | W27: 2.4352 | X27: =W27*I27 -> 1461.12 | Y27: 七 88927-1.7 | Z27: 77584-S001-3L | AA27: 已入 | AB27: 系统出单 | AC27: 600 | AD27: =AC27-I27 -> 0 | AE27: ok | AG27: =I27*2 -> 1200 | AI27: =I27*2 -> 1200 | AZ27: =I27*2 -> 1200 | CC27: =I27 -> 600 | CD27: =I27 -> 600 | CF27: =I27 -> 600 | CH27: 10/25已放 | CJ27: =CJ23-I27 -> 3896 | CO27: =CO26-AG27 -> 2609552
A28: 45607 | B28: TARGET US | C28: 美国 | D28: 4500150926 | E28: 10001033543-3891 | F28: 4500150926-20 | G28: 77555GQ2-S002 | H28: 迷你房子 | I28: 19700 | J28: 0 | K28: 25 | L28: =I28/K28 -> 788 | M28: 45653 | N28: 45649 | P28: pass | R28: 45621 | S28: 有 | T28: 12/6条码箱贴纸 | U28: 日期码格式：ZURU INC(BVI) 标准格式 日期：按实际生产日期 Packaging Info: 77555GQ2：产品MA包装 (UPC 版), MA 1L 收缩膜，MA 1L PDQ; Remark: 77555GQ2: 1. 77555GQ2-S002-MINI BRANDS-HOME MINI BRANDS-SERIES 1-CAPSULE,25PCS/Gravity PDQ, 25PCS/PDQ/CTN 2. 产品MA包装 (UPC 版), MA 1L 收缩膜，收缩膜上的UPC显示 193052064264, MA 1L PDQ; 3. 外箱正唛左上角位置粘贴条码箱贴纸，每箱只贴一张，由ZURU订购。来料贴纸上显示的客户DPCI# 086-02-1571， UPC显示10193052064261; 此订单所有型号： 1. 产品和包装上印刷 tracking code信息，格式为ZURU常规格式; 2. 出货方式：货代自提 | V28: Holly Zheng | W28: 0.9024 | X28: =W28*I28 -> 17777.28 | Y28: 七 88960-1.9 | Z28: 77555GQ2-S002 | AA28: 已入 | AB28: 系统出单 | AC28: 19700 | AD28: =AC28-I28 -> 0 | AE28: ok | AG28: =I28 -> 19700 | AI28: =I28 -> 19700 | AZ28: =I28 -> 19700 | BP28: =I28/25 -> 788 | CO28: =CO27-AG28 -> 2589852
A29: 45638 | D29: ZMPO24948 | E29: MPO03008 | G29: 77555-S002 | H29: 迷你房子 | I29: 48 | J29: 0 | K29: 12 | L29: =I29/K29 -> 4 | M29: 45650 | N29: 45650 | P29: 已送库有 | R29: 空白箱 | S29: 无 | T29: 无 | U29: Remark：客版3L收缩膜(UPC: 193052064264)+MA5L收藏指南+MA配件袋+MA5L,UV胶水贴纸+MA23L说明书；----工厂PO:MPO03008- 备注：收到样品订单后尽快安排,注意样板品质质量要求要高于大货品质要求 ，送货时必须要附带送货单(没有送货单和QC检验合格报告的仓库一律拒绝收货)，请知悉，谢谢！ | V29: Angus | Z29: # | AA29: # | AC29: 48 | AD29: =AC29-I29 -> 0 | AE29: 无 | AG29: =I29 -> 48 | AW29: =I29 -> 48 | AZ29: =I29 -> 48 | CO29: =CO28-AG29 -> 2589804
A30: 45604 | B30: ASDA STORES LTD | C30: 英国 | D30: 4500150696 | E30: 2950866100 | F30: 4500150696-50 | G30: 77555SLB-S001 | H30: 迷你房子 | I30: 975 | J30: 0 | K30: 975 | L30: =I30/K30 -> 1 | M30: 45656 | N30: 45652 | P30: 自检 | Q30: 1/8 截SI | R30: 45625 | S30: 有 | T30: slip sheet贴纸 | U30: 日期码格式：ZURU INC(BVI) 标准格式 日期：按实际生产日期 Packaging Info: 77555GQ1-S002：MA最新1L UPC包装 UPC#193052064264, 请先检查条码是否正确再安排做货； Slip sheet:13pcs/PDQ/CTN 15*5H=75CTN/SLB=975pcs/Slip Sheet,一共需要1套slip sheet; Slip Sheet打包好后，需要在正唛、侧唛右下角各贴一张slip sheet贴纸，直接用A4纸打印出来即可，贴纸尺寸160mm width x 140mm high； Slip Sheet尺寸限制为100*115*130CM，一旦实际SLIP SHEET尺寸超过这个尺寸，请提前通知ZURU跟单，需同客人确认才能量产和出货; Remark: 1. 产品及包装需要印UKCA图标，包装需要有ZURU UK LTD/ZURU France地址信息，QC同事请核查，如有问题与跟单确认 2. 产品/包装/外箱都需要打ZURU格式日期码，日期必须为法定工作日。 3. 需要符合欧洲标准不能含有闪粉和微塑料，否则不合法规会有客诉产生 | V30: Amy Ding | W30: 877.958 | X30: =W30*I30 -> 856009.05 | Y30: 七 88944-1.8 | Z30: 77555SLB-S001 | AA30: 已入 | AB30: 系统出单 | AC30: 975 | AD30: =AC30-I30 -> 0 | AE30: 无 | AG30: =I30 -> 975 | AI30: =I30*2 -> 1950 | AZ30: =I30*2 -> 1950 | BK30: =I30/13 -> 75 | CO30: =CO29-AG30 -> 2588829
A31: 45604 | B31: THE ENTERTAINER | C31: 英国 | D31: 4500150141 | E31: 4500150141-2 | F31: 4500150141-60 | G31: 77555GQ1-S002 | H31: 迷你房子GQ1/13PCS/箱 | I31: 1625 | J31: 0 | K31: 13 | L31: =I31/K31 -> 125 | M31: 45657 | N31: 45653 | P31: 自检 | Q31: 1/4 截SI | R31: 45610 | S31: 无 | T31: 条码贴翻订单4500144795 | U31: 日期码格式：ZURU INC(BVI) 标准格式 日期：按实际生产日期 Tracking Code: Packaging Info: 77555GQ1：MA最新1L配套包装+客户EAN条码贴一张覆盖ZURU 原条码，条码贴翻订单4500144795。 订单对应客户2个PO号 ，备注有显示 ，注意分开做货/验货/装柜 ，混装有罚款。 Remark: *MA版本按工厂现有最新库存即可，订单出英国，请注意检查产品及包装应带UKCA图标，包装显示ZURU UK LTD信息，QC同事请查核，如有问题与跟单确认。 *生产日期按实际（法定工作日），按ZURU标准格式即可 ，但是请知悉包装日期码需要早于或者等于外箱日期码 ，不能晚于外箱日期码 *请注意所有订单都需要经过ZURU QC验货并且通过后方可出货 *条码以订单显示为准 ，请安排生产前先核对 ，有问题请提出。 *所有产品按符合欧洲标准走货，需要是不含微塑料版本 。 *涉及到硼的，如可选择情况下应使用低硼版本 （slime 类别低硼一般低于300ppm)，无选择的应与跟单复核再安排 。 | V31: Sherry Lu | W31: 0.8972 | X31: =W31*I31 -> 1457.95 | Y31: 七 88877-1.4 | Z31: 77555GQ1-S002 | AA31: 已入 | AB31: 系统出单 | AC31: 1625 | AD31: =AC31-I31 -> 0 | AE31: OK | AG31: =I31 -> 1625 | AI31: =I31 -> 1625 | AZ31: =I31 -> 1625 | BK31: =I31/13 -> 125 | CO31: =CO30-AG31 -> 2587204
A32: 45618 | B32: CRG | C32: 哥斯达黎加 | D32: 4500152087 | E32: ZU01-25 | F32: 4500152087-90 | G32: 77555GQ2-S001 | H32: 迷你房子25pcsGQ2*2/箱 | I32: 3600 | J32: 0 | K32: 50 | L32: =I32/K32 -> 72 | M32: 45660 | N32: 45656 | P32: pass | Q32: 1/8 截SI | R32: 45623 | S32: 无 | T32: 12/10进口商贴纸 | U32: 日期码格式：ZURU INC(BVI) 标准格式 日期：按实际生产日期 Packaging Info:77555GQ2:MA 1L包装+进口商贴纸+箱唛 Remark: | V32: Ava Liang | W32: 0.9318 | X32: =W32*I32 -> 3354.48 | Y32: 88961-1.9 | Z32: 77555GQ2-S001 | AA32: 已入 | AB32: 系统出单 | AC32: 3600 | AD32: =AC32-I32 -> 0 | AE32: ok | AG32: =I32 -> 3600 | AI32: =I32 -> 3600 | AZ32: =I32 -> 3600 | BP32: =I32/25 -> 144 | CO32: =CO31-AG32 -> 2583604
A33: 45618 | B33: TARGET US | C33: 美国 | D33: 4500152133 | E33: 10001033542-3890 | F33: 4500152133-20 | G33: 77555GQ2-S002 | H33: 迷你房子 | I33: 27125 | J33: 0 | K33: 25 | L33: =I33/K33 -> 1085 | M33: 45657 | N33: 45657 | P33: pass | Q33: 1/6 客上柜 | R33: 45630 | S33: 有 | T33: 12/19 条码箱贴纸 | U33: 日期码格式：ZURU INC(BVI) 标准格式 日期：按实际生产日期 Tracking Code: Packaging Info: 77555GQ2: 产品MA包装 (UPC 版), MA 1L 收缩膜，收缩膜上的UPC显示 193052064264, MA 1L PDQ; Remark: 77555GQ2: 1. 77555GQ2-S002-MINI BRANDS-HOME MINI BRANDS-SERIES 1-CAPSULE,25PCS/Gravity PDQ, 25PCS/PDQ/CTN 2. 产品MA包装 (UPC 版), MA 1L 收缩膜，收缩膜上的UPC显示 193052064264, MA 1L PDQ; 3. 外箱正唛左上角位置粘贴条码箱贴纸，每箱只贴一张，由ZURU订购。来料贴纸上显示的客户DPCI# 086-02-1571， UPC显示10193052064261; 此订单所有型号： 1. 产品和包装上印刷 tracking code信息，格式为ZURU常规格式; 2. 出货方式：货代自提 | V33: Holly Zheng | W33: 0.8967 | X33: =W33*I33 -> 24322.987 | Y33: 七 88895-1.6 | Z33: 77555GQ2-S002 | AA33: 已入 | AB33: 系统出单 | AC33: 27125 | AD33: =AC33-I33 -> 0 | AE33: ok | AG33: =I33 -> 27125 | AI33: =I33 -> 27125 | AZ33: =I33 -> 27125 | BP33: =I33/25 -> 1085 | CO33: =CO32-AG33 -> 2556479
A34: 45623 | B34: HEB GROCERY COMPANY, LP | C34: 美国 | D34: 4500152429 | E34: PO#60X356498 | F34: 4500152429-40 | G34: 77555GQ1-S002 | H34: 迷你房子GQ1/13PCS/箱 | I34: 13897 | J34: 0 | K34: 13 | L34: =I34/K34 -> 1069 | M34: 45665 | N34: 45661 | O34: 1/9 第三方抽办+验货 | P34: pass | Q34: 1/24 截SI 已出样板 | R34: 45623 | S34: 无 | T34: 无 | U34: 日期码格式：ZURU INC(BVI) 标准格式 日期：按实际生产日期 Packaging Info: 1. ZURU MA UPC版本，出口美国. Remark: 2. 日期跟踪码：ZURU标准格式日期码，产品包装及产品本身都必须有ZURU标准格式日期码，并且确保两者格式和时间保持一致(请自行调整具体年月日生产期，但不能为周末）。 针对你们目前没办法保持日期码一致的做法是： * 大货：可以按照实际生产的日期码打，毛绒布标和蛋壳上的日期码格式和时间这次特例可以不保持一致出货；但到时需手动贴一套公仔的布标贴纸，使布标跟蛋壳 日期码格式和时间一样，拍照给我们发给实验室review 日期码，让实验室知道订单大货出的日期码格式和时间是跟抽板指定款的保持一样。 * 指定款抽板：需手动贴布标贴纸，保证布标跟蛋壳上的日期码格式和时间都一样，且这个时间要跟大货的时间一样。 3. 大货样 #77555GQ1, #92104TQ2签样同旧单4500131931, 但如订单最终出货有物料变更，须提前告知跟单决定是否重新寄签样。 4. 验货+ 抽板 （同一天进行） 预约1月9日第三方（利丰）到工厂做100%大货现场验货和抽板，验货需打印EPM出来跟客户回签样板供第三方验货参考。 PS:EPM是跟单提供。 抽板： 5. 出货配比：ZURU 标版配比 6. ZURU QA 验货时需拍齐每款角色的产品和产品包装上的日期码照片（供实验室review） | V34: Elsa Zheng | W34: 0.8799 | X34: =W34*I34 -> 12227.97 | Y34: 94152-1.22 | Z34: 77555GQ1-S002 | AA34: 已入 | AB34: 系统出单 | AC34: 13897 | AD34: =AC34-I34 -> 0 | AE34: 无 | AG34: =I34 -> 13897 | AI34: =I34 -> 13897 | AZ34: =I34 -> 13897 | BK34: =I34/13 -> 1069 | CO34: =CO33-AG34 -> 2542582
A35: 45615 | B35: VM INTERNATIONAL | C35: 美国 | D35: 4500151779 | F35: 4500151779-50 | G35: 77555GQ2-S002 | H35: 迷你房子 | I35: 2100 | J35: 0 | K35: 25 | L35: =I35/K35 -> 84 | M35: 45666 | N35: 45663 | P35: pass | Q35: 1/16 截SI | R35: 12、12 | S35: 无 | T35: 无 | U35: Packaging Info: 1. ZURU MA UPC版本，出口美国. | V35: Iris Yuan | W35: 0.9381 | X35: =W35*I35 -> 1970.01 | Y35: 94112-1.18 | Z35: 77555GQ2-S002 | AA35: 已入 | AB35: 系统出单 | AC35: 2100 | AD35: =AC35-I35 -> 0 | AE35: 无 | AG35: =I35 -> 2100 | AI35: =I35 -> 2100 | AZ35: =I35 -> 2100 | BP35: =I35/25 -> 84 | CO35: =CO34-AG35 -> 2540482
A36: 45632 | B36: WAL-MART STORES INC. USA | C36: 美国 | D36: 4500153486 | E36: 0881410116 STATESBORO | F36: 4500153486-10 | G36: 77555SLB-S002 | H36: 迷你房子 | I36: 2304 | J36: 0 | K36: 1152 | L36: =I36/K36 -> 2 | M36: 45663 | N36: 45663 | O36: 1/8 BV | P36: pass | Q36: 1/20 截SI | R36: 翻单 | S36: 有 | T36: 12/19 RFID | U36: Remark: 2. 日期跟踪码：ZURU标准格式日期码，产品包装及产品本身都必须有ZURU标准格式日期码，并且确保两者格式和时间保持一致(请自行调整具体年月日生产期，但不能为周末）。 | V36: Maggie Xie | W36: 112.0403 | X36: =W36*L36 -> 224.0806 | Y36: 88991-1.11 | Z36: 77555SLB-S002 | AA36: 已入 | AB36: 系统出单 | AC36: 2304 | AD36: =AC36-I36 -> 0 | AE36: ok | AG36: =I36 -> 2304 | AI36: =I36 -> 2304 | BC36: =I36 -> 2304 | BG36: =I36/12 -> 192 | CG36: 12/6已放收藏指南和PDQ MA | CH36: 20000 | CI36: 500 | CK36: =CH36-BC36 -> 17696 | CL36: =CI36-BG36 -> 308 | CO36: =CO35-AG36 -> 2538178
A37: 45632 | B37: WAL-MART STORES INC. USA | C37: 美国 | D37: 4500153486 | E37: 0881410128 HOUSTON | F37: 4500153486-20 | G37: 77555SLB-S002 | H37: 迷你房子 | I37: 2304 | J37: 0 | K37: 1152 | L37: =I37/K37 -> 2 | M37: 45663 | N37: 45663 | O37: 1/8 BV | P37: pass | Q37: 1/14 截SI | R37: 翻单 | S37: 有 | T37: 12/19 RFID | U37: 针对你们目前没办法保持日期码一致的做法是： | V37: Maggie Xie | W37: 112.0403 | X37: =W37*L37 -> 224.0806 | Y37: 94110-1.18 | Z37: 77555SLB-S002 | AA37: 已入 | AB37: 系统出单 | AC37: 2304 | AD37: =AC37-I37 -> 0 | AE37: ok | AG37: =I37 -> 2304 | AI37: =I37 -> 2304 | BC37: =I37 -> 2304 | BG37: =I37/12 -> 192 | CG37: 12/6已放收藏指南和PDQ MA | CK37: =CK36-BC37 -> 15392 | CL37: =CL36-BG37 -> 116 | CO37: =CO36-AG37 -> 2535874
A38: 45632 | B38: WAL-MART STORES INC. USA | C38: 美国 | D38: 4500153486 | E38: 0881410129 SUFFOLK | F38: 4500153486-30 | G38: 77555SLB-S002 | H38: 迷你房子 | I38: 1152 | J38: 0 | K38: 1152 | L38: =I38/K38 -> 1 | M38: 45663 | N38: 45663 | O38: 1/8 BV | P38: pass | Q38: 1/21 截SI | R38: 翻单 | S38: 有 | T38: 12/19 RFID | U38: * 大货：可以按照实际生产的日期码打，毛绒布标和蛋壳上的日期码格式和时间这次特例可以不保持一致出货；但到时需手动贴一套公仔的布标贴纸，使布标跟蛋壳 | V38: Maggie Xie | W38: 112.0403 | X38: =W38*L38 -> 112.0403 | Y38: 94110-1.18 | Z38: 77555SLB-S002 | AA38: 已入 | AB38: 系统出单 | AC38: 1152 | AD38: =AC38-I38 -> 0 | AE38: ok | AG38: =I38 -> 1152 | AI38: =I38 -> 1152 | BC38: =I38 -> 1152 | BG38: =I38/12 -> 96 | CG38: 12/6已放收藏指南和PDQ MA | CK38: =CK37-BC38 -> 14240 | CL38: =CL37-BG38 -> 20 | CM38: 余数 | CO38: =CO37-AG38 -> 2534722
A39: 45623 | B39: Amazon CA (Vendor Center) | C39: 加拿大 | D39: 4500152544 | E39: 7VXLX7NF | F39: 4500152544-40 | G39: 77555-S001 | H39: 迷你房子 | I39: 24 | J39: 0 | K39: 24 | L39: =I39/K39 -> 1 | M39: 45670 | N39: 45666 | P39: 自检 | Q39: 1/16 交仓 | R39: 11、27 | S39: 有 | T39: 12/20 SSCC Label+UPC贴纸跟翻单#4500132673 | U39: 日期码格式和时间一样，拍照给我们发给实验室review 日期码，让实验室知道订单大货出的日期码格式和时间是跟抽板指定款的保持一样。 | V39: Kelly/Mia | W39: 0.8346 | X39: =W39*I39 -> 20.0304 | Y39: 94134-1.21 | Z39: 77555-S001-3L | AA39: 已入 | AB39: 系统出单 | AC39: 24 | AD39: =AC39-I39 -> 0 | AE39: ok | AG39: =I39 -> 24 | AJ39: =I39 -> 24 | AZ39: =I39 -> 24 | CO39: =CO38-AG39 -> 2534698
A40: 45623 | B40: Amazon CA (Vendor Center) | C40: 加拿大 | D40: 4500152544 | E40: 8UHHLGLU | F40: 4500152544-120 | G40: 77555-S001 | H40: 迷你房子 | I40: 24 | J40: 0 | K40: 24 | L40: =I40/K40 -> 1 | M40: 45670 | N40: 45666 | P40: 自检 | Q40: 1/16 交仓 | R40: 11、27 | S40: 有 | T40: 12/20 SSCC Label+UPC贴纸跟翻单#4500132673 | U40: * 指定款抽板：需手动贴布标贴纸，保证布标跟蛋壳上的日期码格式和时间都一样，且这个时间要跟大货的时间一样。 | V40: Kelly/Mia | W40: 0.8346 | X40: =W40*I40 -> 20.0304 | Y40: 94134-1.21 | Z40: 77555-S001-3L | AA40: 已入 | AB40: 系统出单 | AC40: 24 | AD40: =AC40-I40 -> 0 | AE40: ok | AG40: =I40 -> 24 | AJ40: =I40 -> 24 | AZ40: =I40 -> 24 | CO40: =CO39-AG40 -> 2534674
A41: 45623 | B41: Amazon CA (Vendor Center) | C41: 加拿大 | D41: 4500152544 | E41: 475ILV4U | F41: 4500152544-200 | G41: 77555-S001 | H41: 迷你房子 | I41: 24 | J41: 0 | K41: 24 | L41: =I41/K41 -> 1 | M41: 45670 | N41: 45666 | P41: 自检 | Q41: 1/16 交仓 | R41: 11、27 | S41: 有 | T41: 12/20 SSCC Label+UPC贴纸跟翻单#4500132673 | U41: 3. 大货样 | V41: Kelly/Mia | W41: 0.8346 | X41: =W41*I41 -> 20.0304 | Y41: 94134-1.21 | Z41: 77555-S001-3L | AA41: 已入 | AB41: 系统出单 | AC41: 24 | AD41: =AC41-I41 -> 0 | AE41: ok | AG41: =I41 -> 24 | AJ41: =I41 -> 24 | AZ41: =I41 -> 24 | CO41: =CO40-AG41 -> 2534650
A42: 45623 | B42: Amazon CA (Vendor Center) | C42: 加拿大 | D42: 4500152544 | E42: 3RMEYMQW | F42: 4500152544-220 | G42: 77555-S001 | H42: 迷你房子 | I42: 24 | J42: 0 | K42: 24 | L42: =I42/K42 -> 1 | M42: 45670 | N42: 45666 | P42: 自检 | Q42: 1/16 交仓 | R42: 11、27 | S42: 有 | T42: 12/20 SSCC Label+UPC贴纸跟翻单#4500132673 | U42: #9283签样同旧单4500105770, 但如订单最终出货有物料变更，须提前告知跟单决定是否重新寄签样。 | V42: Kelly/Mia | W42: 0.8346 | X42: =W42*I42 -> 20.0304 | Y42: 94134-1.21 | Z42: 77555-S001-3L | AA42: 已入 | AB42: 系统出单 | AC42: 24 | AD42: =AC42-I42 -> 0 | AE42: ok | AG42: =I42 -> 24 | AJ42: =I42 -> 24 | AZ42: =I42 -> 24 | CO42: =CO41-AG42 -> 2534626
A43: 45604 | B43: ESAL ENTERPRISES FZC | C43: 卡塔尔 | D43: 4500150683 | E43: QATAR | F43: 4500150683-90 | G43: 77555GQ2-S001 | H43: 迷你房子25pcsGQ2*2/箱 | I43: 250 | J43: 0 | K43: 50 | L43: =I43/K43 -> 5 | M43: 45671 | N43: 45667 | P43: 自检 | Q43: 1/19截SI | R43: 11、28 | S43: 无 | T43: 进口商贴纸148906 | U43: #92105签样同旧单4500131084, 但如订单最终出货有物料变更，须提前告知跟单决定是否重新寄签样。 | V43: Lena Huang | W43: 0.9376 | X43: =W43*I43 -> 234.4 | Y43: 94135-1.21 | Z43: 77555GQ2-S001 | AA43: 已入 | AB43: 系统出单 | AC43: 250 | AD43: =AC43-I43 -> 0 | AE43: ok | AG43: =I43 -> 250 | AI43: =I43 -> 250 | AZ43: =I43 -> 250 | BP43: =I43/25 -> 10 | CO43: =CO42-AG43 -> 2534376
A44: 45604 | B44: ESAL ENTERPRISES FZC | C44: 卡塔尔 | D44: 4500150683 | E44: QATAR | F44: 4500150683-100 | G44: 77555SK-S002 | H44: 迷你房子展示架 | I44: 600 | J44: 0 | K44: 60 | L44: =I44/K44 -> 10 | M44: 45671 | N44: 45667 | P44: 自检 | Q44: 1/19截SI | R44: 11、28 | S44: 无 | T44: 进口商贴纸翻148906 | U44: #77555GQ1, #92104TQ2签样同旧单4500131931, 但如订单最终出货有物料变更，须提前告知跟单决定是否重新寄签样。 | V44: Lena Huang | W44: 67.8712 | X44: =W44*L44 -> 678.712 | Y44: 94135-1.21 | Z44: 77555SK-S002 | AA44: 已入 | AB44: 系统出单 | AC44: 600 | AD44: =AC44-I44 -> 0 | AE44: ok | AG44: =I44 -> 600 | AI44: =I44 -> 600 | AZ44: =I44 -> 600 | BV44: =I44/60 -> 10 | CO44: =CO43-AG44 -> 2533776
A45: 45603 | B45: DD’S DISCOUNTS | C45: 美国 | D45: 4500150510 | E45: 70054033 | F45: 4500150510-20 | G45: 77584-S001 | H45: 迷你房子 | I45: 600 | J45: 0 | K45: 12 | L45: =I45/K45 -> 50 | M45: 45673 | N45: 45671 | P45: 自检 | R45: 45610 | S45: 无 | T45: 12/19 客供价格贴纸 | U45: #9296签样同旧单4500147274, 但如订单最终出货有物料变更，须提前告知跟单决定是否重新寄签样。 | V45: Taylor Liao | W45: 2.3963 | X45: =W45*I45 -> 1437.78 | Y45: 94559-3.14 | Z45: 77584-S001-3L | AA45: 已入 | AB45: 系统出单 | AC45: 600 | AD45: =AC45-I45 -> 0 | AE45: ok | AG45: =I45*2 -> 1200 | AI45: =I45*2 -> 1200 | AZ45: =I45*2 -> 1200 | CC45: =I45 -> 600 | CD45: =I45 -> 600 | CF45: =I45 -> 600 | CH45: 10/25已放 | CJ45: =CJ27-I45 -> 3296 | CO45: =CO44-AG45 -> 2532576
A46: 45632 | B46: MILLS FLEET FARM | C46: 美国 | D46: MPO03108 | E46: PO#4500153457 | G46: 77555-S001-MSLD121 | H46: 迷你房子8个球按配比分隔开/箱 | I46: 640 | J46: 0 | K46: 24 | L46: =I46/K46 -> 26.666667 | M46: 45670 | N46: 45666 | O46: 日期跟踪码要一致，统一打2025年1月16日 | P46: 自检 | Q46: 1月21日送到库有混装 | R46: 周转箱 备注上:客供子件给Mis FleetFarmPon4500153457##MSLD121-S001混装用 | S46: 无 | T46: 无 | U46: #9298TQ2 需在12月18日前寄出2齐套样板给到利丰重新签样，以下是收件人信息： | V46: Mila Yao | W46: 0.8346 | X46: =W46*I46 -> 534.144 | Y46: 94409-2.28 | Z46: 77555-S001 | AA46: 已入 | AB46: 系统出单 | AC46: 640 | AD46: =AC46-I46 -> 0 | AG46: =I46 -> 640 | AI46: =I46 -> 640 | AZ46: =I46 -> 640 | CO46: =CO45-AG46 -> 2531936
A47: 45639 | B47: CENTRO CUESTA NACIONAL | C47: 多米尼加 | D47: 4500153864 | E47: 24-1067175JDO | F47: 4500153864-70 | G47: 77555GQ2-S001 | H47: 迷你房子25pcsGQ2*2/箱 | I47: 1200 | J47: 0 | K47: 50 | L47: =I47/K47 -> 24 | M47: 45677 | N47: 45673 | P47: 自检 | Q47: 1/22 截SI | R47: 45639 | S47: 无 | T47: 12/18 UPC 贴纸 | U47: Li <(>&<)> Fung | V47: Zoe Luo | W47: 0.9376 | X47: =W47*I47 -> 1125.12 | Y47: 94113-1.18 | Z47: 77555GQ2-S001-3L | AA47: 已入 | AB47: 系统出单 | AC47: 1200 | AD47: =AC47-I47 -> 0 | AE47: ok | AG47: =I47 -> 1200 | AJ47: =I47 -> 1200 | AZ47: =I47 -> 1200 | BR47: =I47/25 -> 48 | CO47: =CO46-AG47 -> 2530736
A48: 45623 | B48: Army & Air Force Exchange Service | C48: 美国 | D48: 4500152559 | E48: 0092242910 | F48: 4500152559-10 | G48: MEC251-77555-S001 | H48: 混装（77555+77515） | I48: 510 | J48: 0 | K48: 30 | L48: =I48/K48 -> 17 | M48: 45660 | N48: 45663 | P48: pass | Q48: 1/8 截SI | R48: 45630 | S48: 有 | T48: 12/5 UPC贴纸 | U48: 深圳市福田区绒花路8号深福保大厦附楼3楼。 | V48: Yilia | W48: 75.5207 | X48: =W48*L48 -> 1283.8519 | Y48: 88990-1.11 | Z48: MEC251-77555-S001 | AA48: 已入 | AB48: 系统出单 | AC48: 510 | AD48: =AC48-I48 -> 0 | AE48: 东莞贴 | AG48: =I48 -> 510 | AI48: =I48 -> 510 | AZ48: =I48 -> 510 | CO48: =CO47-AG48 -> 2530226
A49: 45623 | B49: Army & Air Force Exchange Service | C49: 美国 | D49: 4500152559 | E49: 0092242914 | F49: 4500152559-20 | G49: MEC251-77555-S001 | H49: 混装（77555+77515） | I49: 420 | J49: 0 | K49: 30 | L49: =I49/K49 -> 14 | M49: 45660 | N49: 45663 | P49: pass | Q49: 1/8 截SI | R49: 45630 | S49: 有 | T49: 12/5 UPC贴纸 | U49: 收件人： Yoland Dai 电话：+0755 8825 3756 | V49: Yilia | W49: 75.5207 | X49: =W49*L49 -> 1057.2898 | Y49: 88990-1.11 | Z49: MEC251-77555-S001 | AA49: 已入 | AB49: 系统出单 | AC49: 420 | AD49: =AC49-I49 -> 0 | AE49: 东莞贴 | AG49: =I49 -> 420 | AI49: =I49 -> 420 | AZ49: =I49 -> 420 | CO49: =CO48-AG49 -> 2529806
A50: 45623 | B50: Army & Air Force Exchange Service | C50: 美国 | D50: 4500152559 | E50: 92242913 | F50: 4500152559-30 | G50: MEC251-77555-S001 | H50: 混装（77555+77515） | I50: 960 | J50: 0 | K50: 30 | L50: =I50/K50 -> 32 | M50: 45660 | N50: 45663 | P50: pass | Q50: 1/8 截SI | R50: 45630 | S50: 有 | T50: 12/5 UPC贴纸 12/13 UCC | U50: 4. 验货+ 抽板 （同一天进行） | V50: Yilia | W50: 75.5207 | X50: =W50*L50 -> 2416.6624 | Y50: 94050-1.15 | Z50: MEC251-77555-S001 | AA50: 已入 | AB50: 系统出单 | AC50: 960 | AD50: =AC50-I50 -> 0 | AE50: 东莞贴 | AG50: =I50 -> 960 | AI50: =I50 -> 960 | AZ50: =I50 -> 960 | CO50: =CO49-AG50 -> 2528846
A51: 45623 | B51: Army & Air Force Exchange Service | C51: 美国 | D51: 4500152559 | E51: 92242911 | F51: 4500152559-40 | G51: MEC251-77555-S001 | H51: 混装（77555+77515） | I51: 1110 | J51: 0 | K51: 30 | L51: =I51/K51 -> 37 | M51: 45660 | N51: 45663 | P51: pass | Q51: 1/8 截SI | R51: 45630 | S51: 有 | T51: 12/5 UPC贴纸 12/13 UCC | U51: 预约1月9日第三方（利丰）到工厂做100%大货现场验货和抽板，验货需打印EPM出来跟客户回签样板供第三方验货参考。 | V51: Yilia | W51: 75.3677 | X51: =W51*L51 -> 2788.6049 | Y51: 88990-1.11 | Z51: MEC251-77555-S001 | AA51: 已入 | AB51: 系统出单 | AC51: 1110 | AD51: =AC51-I51 -> 0 | AE51: 东莞贴 | AG51: =I51 -> 1110 | AI51: =I51 -> 1110 | AZ51: =I51 -> 1110 | CO51: =CO50-AG51 -> 2527736
A52: 45623 | B52: Army & Air Force Exchange Service | C52: 美国 | D52: 4500152559 | E52: 92242912 | F52: 4500152559-50 | G52: MEC251-77555-S001 | H52: 混装（77555+77515） | I52: 750 | J52: 0 | K52: 30 | L52: =I52/K52 -> 25 | M52: 45660 | N52: 45663 | P52: pass | Q52: 1/8 截SI | R52: 45630 | S52: 有 | T52: 12/5 UPC贴纸 12/13 UCC | U52: PS:EPM是跟单提供。 | V52: Yilia | W52: 75.5207 | X52: =W52*L52 -> 1888.0175 | Y52: 94050-1.15 | Z52: MEC251-77555-S001 | AA52: 已入 | AB52: 系统出单 | AC52: 750 | AD52: =AC52-I52 -> 0 | AE52: 东莞贴 | AG52: =I52 -> 750 | AI52: =I52 -> 750 | AZ52: =I52 -> 750 | CO52: =CO51-AG52 -> 2526986
A53: 45602 | B53: THE NORTH WEST COMPANY LP | C53: 加拿大 | D53: 4500150392 | E53: 739919 | F53: 4500150392-20 | G53: 77555GQ1-S002 | H53: 迷你房子GQ1/13PCS/箱 | I53: 442 | J53: 0 | K53: 13 | L53: =I53/K53 -> 34 | M53: 45667 | N53: 45663 | P53: 自检 | Q53: 1/8 截SI | R53: 45614 | S53: 无 | T53: 11/6UPC贴纸 | U53: 抽板： | V53: Summer Mo | W53: 0.8972 | X53: =W53*I53 -> 396.5624 | Y53: 94031-1.14 | Z53: 77555GQ1-S002-3L | AA53: 已入 | AB53: 系统出单 | AC53: 442 | AD53: =AC53-I53 -> 0 | AE53: ok | AG53: =I53 -> 442 | AJ53: =I53 -> 442 | AZ53: =I53 -> 442 | BM53: =I53/13 -> 34 | CO53: =CO52-AG53 -> 2526544
A54: 45625 | B54: TIENDAS CHEDRAUI, S.A. DE C.V. | C54: 墨西哥 | D54: 4500153048 | F54: 4500153048-40 | G54: 77555GQ2-S001 | H54: 迷你房子25pcsGQ2*2/箱 | I54: 2800 | J54: 0 | K54: 50 | L54: =I54/K54 -> 56 | M54: 45667 | N54: 45663 | P54: pass | Q54: 1/14 截SI | R54: 12、13 | S54: 无 | T54: 12/12 UPC贴纸+进口商贴纸 | U54: 因#9283,#9298TQ2,#92105,#92104TQ2，#92107,# 9296的ZURU测试报告上被客户指定实验室发现产品和产品包装上的日期码不一致，所以这款寄样给实验室的是按照 | V54: Ever Li | W54: 0.9193 | X54: =W54*I54 -> 2574.04 | Y54: 94048-1.15 | Z54: 77555GQ2-S001-3L | AA54: 已入 | AB54: 系统出单 | AC54: 2800 | AD54: =AC54-I54 -> 0 | AE54: ok | AG54: =I54 -> 2800 | AJ54: =I54 -> 2800 | AZ54: =I54 -> 2800 | BR54: =I54/25 -> 112 | CO54: =CO53-AG54 -> 2523744
A55: 45631 | B55: Ambiental Paraguay | C55: 巴拉圭 | D55: 4500153347 | F55: 4500153347-70 | G55: 77555GQ1-S001 | H55: 迷你房子 | I55: 1248 | J55: 0 | K55: 52 | L55: =I55/K55 -> 24 | M55: 45667 | N55: 45663 | P55: 自检 | Q55: 1/11 截SI | R55: 45631 | S55: 无 | T55: 12/5 进口商贴纸 | U55: 利丰验货员现场针对指定款随机抽板6PCS（须带包装）;其他利丰验货员现场针对指定款随机抽板6PCS。 | V55: Ava Liang | W55: 0.8944 | X55: =W55*I55 -> 1116.2112 | Y55: 94049-1.15 | Z55: 77555GQ1-S001 | AA55: 已入 | AB55: 系统出单 | AC55: 1248 | AD55: =AC55-I55 -> 0 | AE55: ok | AG55: =I55 -> 1248 | AI55: =I55 -> 1248 | AZ55: =I55 -> 1248 | BK55: =I55/13 -> 96 | CO55: =CO54-AG55 -> 2522496
A56: 45621 | B56: KMART AUSTRALIA LTD(NEW ZEALAND) | C56: 新西兰 | D56: 4500152293 | E56: 20478301 | F56: 4500152293-10 | G56: 77555GQ1-S002 | H56: 迷你房子GQ1/13PCS/箱 | I56: 494 | J56: 0 | K56: 13 | L56: =I56/K56 -> 38 | M56: 45663 | N56: 45663 | P56: 自检 | R56: 消耗4500144899外箱 | S56: 有 | T56: 12/16 SSCC Label | U56: 工厂需把抽板寄到以下MTS 地址做测试，测试通过后才能出货；如产品有油漆的工厂需额外准备5G/色的油漆涂在同材质胶件上(面积类似A4纸大小)一并寄出； | V56: Lydia Wu | W56: 0.9343 | X56: =W56*I56 -> 461.5442 | Y56: 88992-1.11 | Z56: 77555GQ1-S002 | AA56: 已入 | AB56: 系统出单 | AC56: 494 | AD56: =AC56-I56 -> 0 | AE56: ok | AG56: =I56 -> 494 | AI56: =I56 -> 494 | AZ56: =I56 -> 494 | BK56: =I56/13 -> 38 | CO56: =CO55-AG56 -> 2522002
A57: 45621 | B57: KMART AUSTRALIA LTD(NEW ZEALAND) | C57: 新西兰 | D57: 4500152293 | E57: 20478301 | F57: 4500152293-50 | G57: 77555GQ1-S002 | H57: 迷你房子GQ1/13PCS/箱 | I57: 169 | J57: 0 | K57: 13 | L57: =I57/K57 -> 13 | M57: 45663 | N57: 45663 | P57: 自检 | R57: 消耗4500145062外箱 | S57: 有 | T57: 12/16 SSCC Label | U57: 实验室收件地址： | V57: Lydia Wu | W57: 0.9343 | X57: =W57*I57 -> 157.8967 | Y57: 88992-1.11 | Z57: 77555GQ1-S002 | AA57: 已入 | AB57: 系统出单 | AC57: 169 | AD57: =AC57-I57 -> 0 | AE57: ok | AG57: =I57 -> 169 | AI57: =I57 -> 169 | AZ57: =I57 -> 169 | BK57: =I57/13 -> 13 | CO57: =CO56-AG57 -> 2521833
A58: 45621 | B58: KMART AUSTRALIA LTD | C58: 澳大利亚 | D58: 4500152292 | E58: 20357441 | F58: 4500152292-50 | G58: 77555GQ1-S002 | H58: 迷你房子 | I58: 1014 | J58: 0 | K58: 13 | L58: =I58/K58 -> 78 | M58: 45663 | N58: 45663 | P58: 自检 | R58: 消耗4500144899外箱 | S58: 有 | T58: 12/16 SSCC Label | U58: 东莞现代产品整理服务有限公司（MTS） | V58: Lydia Wu | W58: 0.9343 | X58: =W58*I58 -> 947.3802 | Y58: 88993-1.11 | Z58: 77555GQ1-S002 | AA58: 已入 | AB58: 系统出单 | AC58: 1014 | AD58: =AC58-I58 -> 0 | AE58: ok | AG58: =I58 -> 1014 | AI58: =I58 -> 1014 | AZ58: =I58 -> 1014 | BK58: =I58/13 -> 78 | CO58: =CO57-AG58 -> 2520819
A59: 45621 | B59: KMART AUSTRALIA LTD | C59: 澳大利亚 | D59: 4500152292 | E59: 20357441 | F59: 4500152292-110 | G59: 77555GQ1-S002 | H59: 迷你房子 | I59: 1339 | J59: 0 | K59: 13 | L59: =I59/K59 -> 103 | M59: 45663 | N59: 45663 | P59: 自检 | R59: 消耗4500145062外箱 | S59: 有 | T59: 12/16 SSCC Label | U59: 广东省东莞市寮步镇新旧围村良平路76号 | V59: Lydia Wu | W59: 0.9343 | X59: =W59*I59 -> 1251.0277 | Y59: 88993-1.11 | Z59: 77555GQ1-S002 | AA59: 已入 | AB59: 系统出单 | AC59: 1339 | AD59: =AC59-I59 -> 0 | AE59: ok | AG59: =I59 -> 1339 | AI59: =I59 -> 1339 | AZ59: =I59 -> 1339 | BK59: =I59/13 -> 103 | CO59: =CO58-AG59 -> 2519480
A60: 45623 | B60: AMAZON.COM.DEDC,LLC | C60: 美国 | D60: 4500152657 | E60: 5DENHXYZ | F60: 4500152657-30 | G60: 77584-S001 | H60: 迷你房子 | I60: 2364 | J60: 0 | K60: 12 | L60: =I60/K60 -> 197 | M60: 45664 | N60: 45664 | P60: pass | Q60: 2/13 截SI | R60: 45623 | S60: 有 | T60: 12/20 SSCC Label | U60: 收件人：Cherry Wang （汪单） | V60: Kelly Shen | W60: 2.4237 | X60: =W60*I60 -> 5729.6268 | Y60: 94229-2.12 | Z60: 77584-S001-3L-2 | AA60: 已入 | AB60: 系统出单 | AC60: 2364 | AD60: =AC60-I60 -> 0 | AE60: ok | AG60: =I60*2 -> 4728 | AM60: =I60*2 -> 4728 | AZ60: =I60*2 -> 4728 | CC60: =I60 -> 2364 | CD60: =I60 -> 2364 | CF60: =I60 -> 2364 | CH60: 按实单 | CO60: =CO59-AG60 -> 2514752
A61: 45623 | B61: AMAZON.COM.DEDC,LLC | C61: 美国 | D61: 4500152379 | E61: 5SYQ2I1V | F61: 4500152379-150 | G61: 77555-S001 | H61: 迷你房子 | I61: 264 | J61: 0 | K61: 24 | L61: =I61/K61 -> 11 | M61: 45664 | N61: 45664 | P61: 自检 | Q61: 2/10 截SI | R61: 45623 | S61: 有 | T61: 12/20 SSCC Label | U61: Tel: +86 769- 8112 0818 ext.893 | V61: Kelly Shen | W61: 0.8484 | X61: =W61*I61 -> 223.9776 | Y61: 94201-2.10 | Z61: 77555-S001 | AA61: 已入 | AB61: 系统出单 | AC61: 264 | AD61: =AC61-I61 -> 0 | AE61: ok | AG61: =I61 -> 264 | AI61: =I61 -> 264 | AZ61: =I61 -> 264 | CO61: =CO60-AG61 -> 2514488
A62: 45623 | B62: AMAZON.COM.DEDC,LLC | C62: 美国 | D62: 4500152379 | E62: 7BA5SZFC | F62: 4500152379-160 | G62: 77584-S001 | H62: 迷你房子 | I62: 936 | J62: 0 | K62: 12 | L62: =I62/K62 -> 78 | M62: 45664 | N62: 45664 | P62: pass | Q62: 2/10 截SI | R62: 45623 | S62: 有 | T62: 12/20 SSCC Label | U62: 抽板有随样文件TRF（跟单提供），工厂在寄样时打印出来放纸箱内随样寄走。 | V62: Kelly Shen | W62: 2.3775 | X62: =W62*I62 -> 2225.34 | Y62: 94201-2.10 | Z62: 77584-S001-3L-2 | AA62: 已入 | AB62: 系统出单 | AC62: 936 | AD62: =AC62-I62 -> 0 | AE62: ok | AG62: =I62*2 -> 1872 | AM62: =I62*2 -> 1872 | AZ62: =I62*2 -> 1872 | CC62: =I62 -> 936 | CD62: =I62 -> 936 | CF62: =I62 -> 936 | CH62: 按实单 | CO62: =CO61-AG62 -> 2512616
A63: 45623 | B63: AMAZON.COM.DEDC,LLC | C63: 美国 | D63: 4500152379 | E63: 3AI1LJXX | F63: 4500152379-170 | G63: 77584-S001 | H63: 迷你房子 | I63: 3012 | J63: 0 | K63: 12 | L63: =I63/K63 -> 251 | M63: 45664 | N63: 45664 | P63: pass | Q63: 2/10 截SI | R63: 45623 | S63: 有 | T63: 12/20 SSCC Label | U63: 5. 出货配比：ZURU 标版配比 | V63: Kelly Shen | W63: 2.3775 | X63: =W63*I63 -> 7161.03 | Y63: 94201-2.10 | Z63: 77584-S001-3L-2 | AA63: 已入 | AB63: 系统出单 | AC63: 3012 | AD63: =AC63-I63 -> 0 | AE63: ok | AG63: =I63*2 -> 6024 | AM63: =I63*2 -> 6024 | AZ63: =I63*2 -> 6024 | CC63: =I63 -> 3012 | CD63: =I63 -> 3012 | CF63: =I63 -> 3012 | CH63: 按实单 | CO63: =CO62-AG63 -> 2506592
A64: 45623 | B64: AMAZON.COM.DEDC,LLC | C64: 美国 | D64: 4500152379 | E64: 593L16CP | F64: 4500152379-180 | G64: 77584-S001 | H64: 迷你房子 | I64: 1200 | J64: 0 | K64: 12 | L64: =I64/K64 -> 100 | M64: 45664 | N64: 45664 | P64: pass | Q64: 2/10 截SI | R64: 45623 | S64: 有 | T64: 12/20 SSCC Label | U64: 6. ZURU QA 验货时需拍齐每款角色的产品和产品包装上的日期码照片（供实验室review） | V64: Kelly Shen | W64: 2.3775 | X64: =W64*I64 -> 2853 | Y64: 94201-2.10 | Z64: 77584-S001-3L-2 | AA64: 已入 | AB64: 系统出单 | AC64: 1200 | AD64: =AC64-I64 -> 0 | AE64: ok | AG64: =I64*2 -> 2400 | AM64: =I64*2 -> 2400 | AZ64: =I64*2 -> 2400 | CC64: =I64 -> 1200 | CD64: =I64 -> 1200 | CF64: =I64 -> 1200 | CH64: 按实单 | CO64: =CO63-AG64 -> 2504192
A65: 45623 | B65: AMAZON.COM.DEDC,LLC | C65: 美国 | D65: 4500152439 | E65: 3CKHAHHY | F65: 4500152439-30 | G65: 77555-S001 | H65: 迷你房子 | I65: 480 | J65: 0 | K65: 24 | L65: =I65/K65 -> 20 | M65: 45666 | N65: 45666 | P65: 自检 | Q65: 1/14 截SI | R65: 45623 | S65: 有 | T65: 12/20 SSCC Label | U65: 日期码格式： 标准格式 日期：按实际生产日期 Packaging Info: #77555：MA1L 收缩膜+5L收藏指南。 Remark: 1. Amazon FOB订单，出口US。 2. 日期码使用ZURU标准版本。 3. 如果大货有要求入邮包盒，则对应的邮包盒上面要打上日期码。 4. 箱尺寸要求：外箱最长边不能超过25"(超过了，case pack只能为1)，不符合要求的大货，一律不接受。 5. 外箱箱唛要求： ①外箱正面印ZURU Logo+SSCC Label(客供贴纸，由跟单订购)。关于 SSCC Label 请注意： SSCC Label显示的是客人自己的item#。每一张SSCC label都是唯一且有不同流水及条码的，没有损耗，绝对不可贴错。如果贴错或损坏任何一张，都会导致全部都 错，千万要注意！SSCC Label必须贴在外箱正面的正中间位置(贴一面即可)，并且贴纸离外箱边距必须至少3cm(可以覆盖Logo<(>&<)>箱唛)，否则会影响到客户那边 仓库的扫描识别。 ②外箱侧面印item#(订单上显示的SKU#)+carton size(以工厂实际尺寸为准，单位: inch)+MADE IN CHINA，日期使用ZURU 标准版本。 6. 装柜要求：按照客户PO#装柜/箱号顺序装柜，跟单会提前给到装柜计划。 在大货生产/仓库存放时，请留意该装柜要求，以便装柜时不混乱(避免装错/装漏/找不到货号等)。 | V65: Kelly Shen | W65: 0.8346 | X65: =W65*I65 -> 400.608 | Y65: 94019-1.13 | Z65: 77555-S001 | AA65: 已入 | AB65: 系统出单 | AC65: 480 | AD65: =AC65-I65 -> 0 | AE65: ok | AG65: =I65 -> 480 | AI65: =I65 -> 480 | AZ65: =I65 -> 480 | CO65: =CO64-AG65 -> 2503712
A66: 45623 | B66: AMAZON.COM.DEDC,LLC | C66: 美国 | D66: 4500152439 | E66: 12NWJ69P | F66: 4500152439-40 | G66: 77555-S001 | H66: 迷你房子 | I66: 312 | J66: 0 | K66: 24 | L66: =I66/K66 -> 13 | M66: 45666 | N66: 45666 | P66: 自检 | Q66: 1/14 截SI | R66: 45623 | S66: 有 | T66: 12/20 SSCC Label | U66: 日期码格式： 标准格式 日期：按实际生产日期 Packaging Info: #77555：MA1L 收缩膜+5L收藏指南。 Remark: 1. Amazon FOB订单，出口US。 2. 日期码使用ZURU标准版本。 3. 如果大货有要求入邮包盒，则对应的邮包盒上面要打上日期码。 4. 箱尺寸要求：外箱最长边不能超过25"(超过了，case pack只能为1)，不符合要求的大货，一律不接受。 5. 外箱箱唛要求： ①外箱正面印ZURU Logo+SSCC Label(客供贴纸，由跟单订购)。关于 SSCC Label 请注意： SSCC Label显示的是客人自己的item#。每一张SSCC label都是唯一且有不同流水及条码的，没有损耗，绝对不可贴错。如果贴错或损坏任何一张，都会导致全部都 错，千万要注意！SSCC Label必须贴在外箱正面的正中间位置(贴一面即可)，并且贴纸离外箱边距必须至少3cm(可以覆盖Logo<(>&<)>箱唛)，否则会影响到客户那边 仓库的扫描识别。 ②外箱侧面印item#(订单上显示的SKU#)+carton size(以工厂实际尺寸为准，单位: inch)+MADE IN CHINA，日期使用ZURU 标准版本。 6. 装柜要求：按照客户PO#装柜/箱号顺序装柜，跟单会提前给到装柜计划。 在大货生产/仓库存放时，请留意该装柜要求，以便装柜时不混乱(避免装错/装漏/找不到货号等)。 | V66: Kelly Shen | W66: 0.8346 | X66: =W66*I66 -> 260.3952 | Y66: 94019-1.13 | Z66: 77555-S001 | AA66: 已入 | AB66: 系统出单 | AC66: 312 | AD66: =AC66-I66 -> 0 | AE66: ok | AG66: =I66 -> 312 | AI66: =I66 -> 312 | AZ66: =I66 -> 312 | CO66: =CO65-AG66 -> 2503400
A67: 45623 | B67: AMAZON.COM.DEDC,LLC | C67: 美国 | D67: 4500152439 | E67: 8ST75SLE | F67: 4500152439-50 | G67: 77555-S001 | H67: 迷你房子 | I67: 264 | J67: 0 | K67: 24 | L67: =I67/K67 -> 11 | M67: 45666 | N67: 45666 | P67: 自检 | Q67: 1/14 截SI | R67: 45623 | S67: 有 | T67: 12/20 SSCC Label | U67: 日期码格式： 标准格式 日期：按实际生产日期 Packaging Info: #77555：MA1L 收缩膜+5L收藏指南。 Remark: 1. Amazon FOB订单，出口US。 2. 日期码使用ZURU标准版本。 3. 如果大货有要求入邮包盒，则对应的邮包盒上面要打上日期码。 4. 箱尺寸要求：外箱最长边不能超过25"(超过了，case pack只能为1)，不符合要求的大货，一律不接受。 5. 外箱箱唛要求： ①外箱正面印ZURU Logo+SSCC Label(客供贴纸，由跟单订购)。关于 SSCC Label 请注意： SSCC Label显示的是客人自己的item#。每一张SSCC label都是唯一且有不同流水及条码的，没有损耗，绝对不可贴错。如果贴错或损坏任何一张，都会导致全部都 错，千万要注意！SSCC Label必须贴在外箱正面的正中间位置(贴一面即可)，并且贴纸离外箱边距必须至少3cm(可以覆盖Logo<(>&<)>箱唛)，否则会影响到客户那边 仓库的扫描识别。 ②外箱侧面印item#(订单上显示的SKU#)+carton size(以工厂实际尺寸为准，单位: inch)+MADE IN CHINA，日期使用ZURU 标准版本。 6. 装柜要求：按照客户PO#装柜/箱号顺序装柜，跟单会提前给到装柜计划。 在大货生产/仓库存放时，请留意该装柜要求，以便装柜时不混乱(避免装错/装漏/找不到货号等)。 | V67: Kelly Shen | W67: 0.8484 | X67: =W67*I67 -> 223.9776 | Y67: 94019-1.13 | Z67: 77555-S001 | AA67: 已入 | AB67: 系统出单 | AC67: 264 | AD67: =AC67-I67 -> 0 | AE67: ok | AG67: =I67 -> 264 | AI67: =I67 -> 264 | AZ67: =I67 -> 264 | CO67: =CO66-AG67 -> 2503136
A68: 45623 | B68: AMAZON.COM.DEDC,LLC | C68: 美国 | D68: 4500152439 | E68: 8NFCSKBL | F68: 4500152439-60 | G68: 77584-S001 | H68: 迷你房子 | I68: 3408 | J68: 0 | K68: 12 | L68: =I68/K68 -> 284 | M68: 45666 | N68: 45666 | P68: pass | Q68: 1/14 截SI | R68: 45623 | S68: 有 | T68: 12/20 SSCC Label | U68: 日期码格式： 标准格式 日期：按实际生产日期 Packaging Info: #77584：2PK 77555入PVC圆桶，77555 MA 1L不带UPC，3L铜版纸图稿跟回PO#4500134367。 Remark: 1. Amazon FOB订单，出口US。 2. 日期码使用ZURU标准版本。 3. 如果大货有要求入邮包盒，则对应的邮包盒上面要打上日期码。 4. 箱尺寸要求：外箱最长边不能超过25"(超过了，case pack只能为1)，不符合要求的大货，一律不接受。 5. 外箱箱唛要求： ①外箱正面印ZURU Logo+SSCC Label(客供贴纸，由跟单订购)。关于 SSCC Label 请注意： SSCC Label显示的是客人自己的item#。每一张SSCC label都是唯一且有不同流水及条码的，没有损耗，绝对不可贴错。如果贴错或损坏任何一张，都会导致全部都 错，千万要注意！SSCC Label必须贴在外箱正面的正中间位置(贴一面即可)，并且贴纸离外箱边距必须至少3cm(可以覆盖Logo<(>&<)>箱唛)，否则会影响到客户那边 仓库的扫描识别。 ②外箱侧面印item#(订单上显示的SKU#)+carton size(以工厂实际尺寸为准，单位: inch)+MADE IN CHINA，日期使用ZURU 标准版本。 6. 装柜要求：按照客户PO#装柜/箱号顺序装柜，跟单会提前给到装柜计划。 在大货生产/仓库存放时，请留意该装柜要求，以便装柜时不混乱(避免装错/装漏/找不到货号等)。 | V68: Kelly Shen | W68: 2.4006 | X68: =W68*I68 -> 8181.2448 | Y68: 94033-1.14 | Z68: 77584-S001-3L-2 | AA68: 已入 | AB68: 系统出单 | AC68: 3408 | AD68: =AC68-I68 -> 0 | AE68: ok | AG68: =I68*2 -> 6816 | AM68: =I68*2 -> 6816 | AZ68: =I68*2 -> 6816 | CC68: =I68 -> 3408 | CD68: =I68 -> 3408 | CF68: =I68 -> 3408 | CH68: 按实单 | CO68: =CO67-AG68 -> 2496320
A69: 45623 | B69: AMAZON.COM.DEDC,LLC | C69: 美国 | D69: 4500152472 | E69: 1VI3G9RP | F69: 4500152472-10 | G69: 77555-S001 | H69: 迷你房子 | I69: 48 | J69: 0 | K69: 24 | L69: =I69/K69 -> 2 | M69: 45666 | N69: 45666 | P69: 自检 | Q69: 1/20 截SI | R69: 45623 | S69: 有 | T69: 12/20 SSCC Label | U69: 日期码格式：ZURU INC(BVI) 标准格式 日期：按实际生产日期 Tracking Code: Packaging Info: #77555：MA1L 收缩膜+5L收藏指南。 Remark: 1. Amazon FOB订单，出口US。 2. 日期码使用ZURU标准版本。 3. 如果大货有要求入邮包盒，则对应的邮包盒上面要打上日期码。 4. 箱尺寸要求：外箱最长边不能超过25"(超过了，case pack只能为1)，不符合要求的大货，一律不接受。 5. 外箱箱唛要求： ①外箱正面印ZURU Logo+SSCC Label(客供贴纸，由跟单订购)。关于 SSCC Label 请注意： SSCC Label显示的是客人自己的item#。每一张SSCC label都是唯一且有不同流水及条码的，没有损耗，绝对不可贴错。如果贴错或损坏任何一张，都会导致全部都 错，千万要注意！SSCC Label必须贴在外箱正面的正中间位置(贴一面即可)，并且贴纸离外箱边距必须至少3cm(可以覆盖Logo<(>&<)>箱唛)，否则会影响到客户那边 仓库的扫描识别。 ②外箱侧面印item#(订单上显示的SKU#)+carton size(以工厂实际尺寸为准，单位: inch)+MADE IN CHINA，日期使用ZURU 标准版本。 6. 装柜要求：按照客户PO#装柜/箱号顺序装柜，跟单会提前给到装柜计划。 在大货生产/仓库存放时，请留意该装柜要求，以便装柜时不混乱(避免装错/装漏/找不到货号等)。 | V69: Kelly Shen | W69: 0.8346 | X69: =W69*I69 -> 40.0608 | Y69: 94109-1.18 | Z69: 77555-S001 | AA69: 已入 | AB69: 系统出单 | AC69: 48 | AD69: =AC69-I69 -> 0 | AE69: ok | AG69: =I69 -> 48 | AZ69: =I69 -> 48 | CO69: =CO68-AG69 -> 2496272
A70: 45630 | B70: Newell Brands UK Ltd | C70: 英国 | D70: 4500153228 | E70: Sistema X Mini Brands UK 5300283729 | F70: 4500153228-10 | G70: 77754-S001 | H70: HOMEM-S1-012/013/014-015(1个装一个纸袋*1000入大胶袋/款*4/箱） | I70: 4000 | J70: 0 | K70: 4000 | L70: =I70/K70 -> 1 | M70: 45670 | N70: 45666 | P70: pass | R70: 45630 | S70: 无 | T70: 无 | U70: 日期码格式：ZURU INC(BVI) 标准格式 日期：按实际生产日期 Packaging Info: 1. 77754: 1PCS/PAPER BAG, 1000PCS/POLYBAG, 4000PCS/4POLYBAG/CTN；minis from 77555: 400ml Klip it plus+1.65L Bento Lunch+656ml Soup Mug+800ml Wat er Bottle; POLYBAG需要打孔加印刷英国防窒息警示信息; 2. 最迟验货不得晚于2025/01/13; Remark: 1. 箱唛资料按照跟单给到的文件生产，生产前需要给到跟单审核排版; | V70: Crystal Chen | W70: 0.084 | X70: =W70*I70 -> 336 | Y70: 94053-1.16 | Z70: 77754-S001 | AA70: 已入 | AB70: 系统出单 | AC70: 4000 | AD70: =AC70-I70 -> 0 | CO70: =CO69-AG70 -> 2496272
A71: 45603 | B71: ROSS PROCUREMENT.INC | C71: 美国 | D71: 4500150464 | E71: 60190494 | F71: 4500150464-40 | G71: 77584-S001 | H71: 迷你房子 | I71: 5004 | J71: 0 | K71: 12 | L71: =I71/K71 -> 417 | M71: 45672 | N71: 45667 | P71: pass | Q71: 3/7 截SI | R71: 45610 | S71: 无 | T71: 12/19 客供价格贴纸 | U71: 日期码格式：ZURU INC(BVI) 标准格式 日期：按实际生产日期 Packaging Info: 1.ZURU MA UPC 收缩膜+客版铜版纸+PVC桶 + 客供价格贴纸，出口美国 , 优先使用MA 1L 最新版本 。 Remark: 1.ZURU MA UPC 收缩膜+客版铜版纸+PVC桶 + 客供价格贴纸，出口美国 , 优先使用MA 1L 最新版本 。 2.价格贴纸位于包装正面右下角，不挡住重要信息即可，可适当调整 ，价格贴纸由跟单提供。 3.标准日期码格式，产品和包装必须有日期码 。 4.同个产品同个货期不可出现不同的包装。 5. PVC 桶中球不能出现完全相同的ASSORTMENT ， 即同一个PVC 中球里的ASSORTMENT 需要不同。 以免消费者失望。 6.PVC 桶上加上 MINI BRANDS 的LOGO 贴纸 （ ZURU 统一要求的） 7.收缩膜可使用标版带UPC条码MA，无需白色贴纸覆盖。 | V71: Sophia Zhou | W71: 2.3386 | X71: =W71*I71 -> 11702.354 | Y71: 94486-3.7 | Z71: 77584-S001-3L | AA71: 已入 | AB71: 系统出单 | AC71: 5004 | AD71: =AC71-I71 -> 0 | AE71: ok | AG71: =I71*2 -> 10008 | AI71: =I71*2 -> 10008 | AZ71: =I71*2 -> 10008 | CC71: =I71 -> 5004 | CD71: =I71 -> 5004 | CF71: =I71 -> 5004 | CH71: 按实单 | CO71: =CO70-AG71 -> 2486264
A72: 45616 | B72: MAGGIO 3 SRL | C72: 意大利 | D72: 4500151811 | F72: 4500151811-50 | G72: 77555GQ1-S001 | H72: 迷你房子 | I72: 4160 | J72: 0 | K72: 52 | L72: =I72/K72 -> 80 | M72: 45672 | N72: 45667 | P72: pass | Q72: 1/16 截SI | R72: 45618 | S72: 无 | T72: 12/12 进口商地址贴纸+PDQ贴纸 | U72: 日期码格式：ZURU INC(BVI) 标准格式 日期：按实际生产日期 Packaging Info: 77555GQ1- MA 3L+5L EAN收缩膜（+1*意大利sorting logo含进口商地址贴纸）+MA 5L 收藏指南 +MA多语 PAPER BAG +MA 3L PDQ(+1*PDQ条码贴纸) 产品条码 4894680033429 Remark: 1.此单出意大利，需符合EU标准，不能含微塑料，如果有slime等化学品需要不含硼 2.需保证按期1/15前完货，延期罚款 3.贴纸切勿盖住意大利警告语文字(QC 务必检查） | V72: Amy Xiao | W72: 0.8886 | X72: =W72*I72 -> 3696.576 | Y72: 94070-1.16 | Z72: 77555GQ1-S001－3L | AA72: 已入 | AB72: 系统出单 | AC72: 4160 | AD72: =AC72-I72 -> 0 | AE72: ok | AG72: =I72 -> 4160 | AJ72: =I72 -> 4160 | AZ72: =I72 -> 4160 | BM72: =I72/13 -> 320 | CO72: =CO71-AG72 -> 2482104
A73: 45639 | B73: CANDIDE IND E COM LTDA | C73: 巴西 | D73: 4500153860 | F73: 4500153860-10 | G73: 77555GQ2-S001 | H73: 迷你房子25pcsGQ2*2/箱 | I73: 5000 | J73: 0 | K73: 50 | L73: =I73/K73 -> 100 | M73: 45674 | N73: 45670 | O73: 封箱胶带要用客版CANDIDE版本 | P73: pass | Q73: 1/15 截SI | R73: 45644 | S73: 无 | T73: 12/19 进口商贴纸+UPC贴纸 | U73: 日期码格式：ZURU INC(BVI) 标准格式 日期：按实际生产日期 Packaging Info: 77555GQ2:MA 1L包装+进口商贴纸+箱唛+UPC贴纸 封箱胶带要用客版CANDIDE版本 | V73: Ava Liang | W73: 0.9077 | X73: =W73*I73 -> 4538.5 | Y73: 94121-1.20 | Z73: 77555GQ2-S001 | AA73: 已入 | AB73: 系统出单 | AC73: 5000 | AD73: =AC73-I73 -> 0 | AG73: =I73 -> 5000 | AI73: =I73 -> 5000 | AZ73: =I73 -> 5000 | BP73: =I73/25 -> 200 | CO73: =CO72-AG73 -> 2477104
A74: 45624 | B74: WALGREEN CO. | C74: 美国 | D74: 4500152753 | E74: 4550084927 | F74: 4500152753-10 | G74: 77555GQ4-S001 | H74: 迷你房子GQ4/6pcs/箱 | I74: 828 | J74: 0 | K74: 6 | L74: =I74/K74 -> 138 | M74: 45677 | N74: 45673 | O74: 标准格式：DG20250120 | P74: pass | Q74: 1/21 交仓 | R74: 45624 | S74: 无 | T74: 12/12 WIC贴纸+PDQ折页 （同PO 4500142744） | U74: 日期码格式：ZURU INC(BVI) 标准格式:DG20250120 日期：01-20-2025 Tracking Code: Packaging Info: Remark: 客版1L PDQ + MA 1L包装 + WIC贴纸（WIC#744432）+ MA 收藏指南 + PDQ折页 （同PO 4500142744） 产品和包装上面要有ZURU 标准格式TRACKING CODE， DG20250120 | V74: Cara Li | W74: 0.9232 | X74: =W74*I74 -> 764.4096 | Y74: 94143-1.21 | Z74: 77555GQ4-S001 | AA74: 已入 | AB74: 系统出单 | AC74: 828 | AD74: =AC74-I74 -> 0 | AE74: ok | AG74: =I74 -> 828 | AI74: =I74 -> 828 | AZ74: =I74 -> 828 | BI74: =I74/6 -> 138 | CO74: =CO73-AG74 -> 2476276
A75: 45624 | B75: WALGREEN CO. | C75: 美国 | D75: 4500152753 | E75: 4550084924 | F75: 4500152753-20 | G75: 77555GQ4-S001 | H75: 迷你房子GQ4/6pcs/箱 | I75: 2142 | J75: 0 | K75: 6 | L75: =I75/K75 -> 357 | M75: 45677 | N75: 45673 | O75: 标准格式：DG20250120 | P75: pass | Q75: 1/21 交仓 | R75: 45624 | S75: 无 | T75: 12/12 WIC贴纸+PDQ折页 （同PO 4500142744） | U75: 日期码格式：ZURU INC(BVI) 标准格式:DG20250120 日期：01-20-2025 Tracking Code: Packaging Info: Remark: 客版1L PDQ + MA 1L包装 + WIC贴纸（WIC#744432）+ MA 收藏指南 + PDQ折页 （同PO 4500142744） 产品和包装上面要有ZURU 标准格式TRACKING CODE， DG20250120 | V75: Cara Li | W75: 0.9232 | X75: =W75*I75 -> 1977.4944 | Y75: 94143-1.21 | Z75: 77555GQ4-S001 | AA75: 已入 | AB75: 系统出单 | AC75: 2142 | AD75: =AC75-I75 -> 0 | AE75: ok | AG75: =I75 -> 2142 | AI75: =I75 -> 2142 | AZ75: =I75 -> 2142 | BI75: =I75/6 -> 357 | CO75: =CO74-AG75 -> 2474134
A76: 45624 | B76: WALGREEN CO. | C76: 美国 | D76: 4500152753 | E76: 4550084925 | F76: 4500152753-30 | G76: 77555GQ4-S001 | H76: 迷你房子GQ4/6pcs/箱 | I76: 1224 | J76: 0 | K76: 6 | L76: =I76/K76 -> 204 | M76: 45677 | N76: 45673 | O76: 标准格式：DG20250120 | P76: pass | Q76: 1/21 交仓 | R76: 45624 | S76: 无 | T76: 12/12 WIC贴纸+PDQ折页 （同PO 4500142744） | U76: 日期码格式：ZURU INC(BVI) 标准格式:DG20250120 日期：01-20-2025 Tracking Code: Packaging Info: Remark: 客版1L PDQ + MA 1L包装 + WIC贴纸（WIC#744432）+ MA 收藏指南 + PDQ折页 （同PO 4500142744） 产品和包装上面要有ZURU 标准格式TRACKING CODE， DG20250120 | V76: Cara Li | W76: 0.9232 | X76: =W76*I76 -> 1129.9968 | Y76: 94143-1.21 | Z76: 77555GQ4-S001 | AA76: 已入 | AB76: 系统出单 | AC76: 1224 | AD76: =AC76-I76 -> 0 | AE76: ok | AG76: =I76 -> 1224 | AI76: =I76 -> 1224 | AZ76: =I76 -> 1224 | BI76: =I76/6 -> 204 | CO76: =CO75-AG76 -> 2472910
A77: 45624 | B77: WALGREEN CO. | C77: 美国 | D77: 4500152753 | E77: 4550084928 | F77: 4500152753-40 | G77: 77555GQ4-S001 | H77: 迷你房子GQ4/6pcs/箱 | I77: 1512 | J77: 0 | K77: 6 | L77: =I77/K77 -> 252 | M77: 45677 | N77: 45673 | O77: 标准格式：DG20250120 | P77: pass | Q77: 1/21 交仓 | R77: 45624 | S77: 无 | T77: 12/12 WIC贴纸+PDQ折页 （同PO 4500142744） | U77: 日期码格式：ZURU INC(BVI) 标准格式:DG20250120 日期：01-20-2025 Tracking Code: Packaging Info: Remark: 客版1L PDQ + MA 1L包装 + WIC贴纸（WIC#744432）+ MA 收藏指南 + PDQ折页 （同PO 4500142744） 产品和包装上面要有ZURU 标准格式TRACKING CODE， DG20250120 | V77: Cara Li | W77: 0.9232 | X77: =W77*I77 -> 1395.8784 | Y77: 94143-1.21 | Z77: 77555GQ4-S001 | AA77: 已入 | AB77: 系统出单 | AC77: 1512 | AD77: =AC77-I77 -> 0 | AE77: ok | AG77: =I77 -> 1512 | AI77: =I77 -> 1512 | AZ77: =I77 -> 1512 | BI77: =I77/6 -> 252 | CO77: =CO76-AG77 -> 2471398
A78: 45624 | B78: WALGREEN CO. | C78: 美国 | D78: 4500152753 | E78: 4550084923 | F78: 4500152753-50 | G78: 77555GQ4-S001 | H78: 迷你房子GQ4/6pcs/箱 | I78: 1086 | J78: 0 | K78: 6 | L78: =I78/K78 -> 181 | M78: 45677 | N78: 45673 | O78: 标准格式：DG20250120 | P78: pass | Q78: 1/21 交仓 | R78: 45624 | S78: 无 | T78: 12/12 WIC贴纸+PDQ折页 （同PO 4500142744） | U78: 日期码格式：ZURU INC(BVI) 标准格式:DG20250120 日期：01-20-2025 Tracking Code: Packaging Info: Remark: 客版1L PDQ + MA 1L包装 + WIC贴纸（WIC#744432）+ MA 收藏指南 + PDQ折页 （同PO 4500142744） 产品和包装上面要有ZURU 标准格式TRACKING CODE， DG20250120 | V78: Cara Li | W78: 0.9232 | X78: =W78*I78 -> 1002.5952 | Y78: 94143-1.21 | Z78: 77555GQ4-S001 | AA78: 已入 | AB78: 系统出单 | AC78: 1086 | AD78: =AC78-I78 -> 0 | AE78: ok | AG78: =I78 -> 1086 | AI78: =I78 -> 1086 | AZ78: =I78 -> 1086 | BI78: =I78/6 -> 181 | CO78: =CO77-AG78 -> 2470312
A79: 45624 | B79: WALGREEN CO. | C79: 美国 | D79: 4500152753 | E79: 4550084926 | F79: 4500152753-60 | G79: 77555GQ4-S001 | H79: 迷你房子GQ4/6pcs/箱 | I79: 942 | J79: 0 | K79: 6 | L79: =I79/K79 -> 157 | M79: 45677 | N79: 45673 | O79: 标准格式：DG20250120 | P79: pass | Q79: 1/21 交仓 | R79: 45624 | S79: 无 | T79: 12/12 WIC贴纸+PDQ折页 （同PO 4500142744） | U79: 日期码格式：ZURU INC(BVI) 标准格式:DG20250120 日期：01-20-2025 Tracking Code: Packaging Info: Remark: 客版1L PDQ + MA 1L包装 + WIC贴纸（WIC#744432）+ MA 收藏指南 + PDQ折页 （同PO 4500142744） 产品和包装上面要有ZURU 标准格式TRACKING CODE， DG20250120 | V79: Cara Li | W79: 0.9232 | X79: =W79*I79 -> 869.6544 | Y79: 94143-1.21 | Z79: 77555GQ4-S001 | AA79: 已入 | AB79: 系统出单 | AC79: 942 | AD79: =AC79-I79 -> 0 | AE79: ok | AG79: =I79 -> 942 | AI79: =I79 -> 942 | AZ79: =I79 -> 942 | BI79: =I79/6 -> 157 | CO79: =CO78-AG79 -> 2469370
A80: 45624 | B80: WALGREEN CO. | C80: 美国 | D80: 4500152753 | E80: 4550084922 | F80: 4500152753-70 | G80: 77555GQ4-S001 | H80: 迷你房子GQ4/6pcs/箱 | I80: 3156 | J80: 0 | K80: 6 | L80: =I80/K80 -> 526 | M80: 45677 | N80: 45673 | O80: 标准格式：DG20250120 | P80: pass | Q80: 1/21 交仓 | R80: 45624 | S80: 无 | T80: 12/12 WIC贴纸+PDQ折页 （同PO 4500142744） | U80: 日期码格式：ZURU INC(BVI) 标准格式:DG20250120 日期：01-20-2025 Tracking Code: Packaging Info: Remark: 客版1L PDQ + MA 1L包装 + WIC贴纸（WIC#744432）+ MA 收藏指南 + PDQ折页 （同PO 4500142744） 产品和包装上面要有ZURU 标准格式TRACKING CODE， DG20250120 | V80: Cara Li | W80: 0.9174 | X80: =W80*I80 -> 2895.3144 | Y80: 94143-1.21 | Z80: 77555GQ4-S001 | AA80: 已入 | AB80: 系统出单 | AC80: 3156 | AD80: =AC80-I80 -> 0 | AE80: ok | AG80: =I80 -> 3156 | AI80: =I80 -> 3156 | AZ80: =I80 -> 3156 | BI80: =I80/6 -> 526 | CO80: =CO79-AG80 -> 2466214
A81: 45639 | B81: CORPORACION FAVORITA C.A. | C81: 厄瓜多尔 | D81: 4500153836 | E81: 24-1067174JEC | F81: 4500153836-10 | G81: 77555GQ2-S001 | H81: 迷你房子25pcsGQ2*2/箱 | I81: 4200 | J81: 0 | K81: 50 | L81: =I81/K81 -> 84 | M81: 45677 | N81: 45673 | O81: 指定日期格式2025-01 外箱箱唛，产品批号需要与进口商贴纸保持一致。 | P81: pass | Q81: 1/21 截SI | R81: 45639 | S81: 无 | T81: UPC 贴纸翻单153864+12/17 进口商贴纸 | U81: 日期码格式：LOTE 格式：例如2025-01 日期： Packaging Info: 77555GQ2：MA 5L 收藏指南+MA 3L 包装+UPC 贴纸+MA 3L PDQ 包装+进口商贴纸+箱唛 Remark: 客户有LOTE 格式：例如2025-01. ，外箱箱唛，产品批号需要与进口商贴纸保持一致。 | V81: Zoe Luo | W81: 0.9135 | X81: =W81*I81 -> 3836.7 | Y81: 94144-1.21 | Z81: 77555GQ2-S001-3L | AA81: 已入 | AB81: 系统出单 | AC81: =4150+50 -> 4200 | AD81: =AC81-I81 -> 0 | AE81: OK | AG81: =I81 -> 4200 | AJ81: =I81 -> 4200 | AZ81: =I81 -> 4200 | BR81: =I81/25 -> 168 | CO81: =CO80-AG81 -> 2462014
A82: 45639 | B82: ASDA STORES LTD | C82: 英国 | D82: 4500151765 | E82: 2950866128 | F82: 4500151765-30 | G82: 77555SLB-S001 | H82: 迷你房子 | I82: 1950 | J82: 0 | K82: 975 | L82: =I82/K82 -> 2 | M82: 45705 | N82: 45701 | P82: 自检 | Q82: 2/26 截SI | R82: 45651 | S82: 有 | T82: slip sheet贴纸 | U82: 日期码格式：ZURU INC(BVI) 标准格式 日期：按实际生产日期 Packaging Info: 3.77555SLB 77555GQ1-S002：MA最新1L UPC包装 UPC#193052064264, 请先检查条码是否正确再安排做货； Slip sheet:13pcs/PDQ/CTN 15*5H=75CTN/SLB=975pcs/Slip Sheet,一共需要1套slip sheet; Slip Sheet打包好后，需要在正唛、侧唛右下角各贴一张slip sheet贴纸，直接用A4纸打印出来即可，贴纸尺寸160mm width x 140mm high； Slip Sheet尺寸限制为100*115*130CM，一旦实际SLIP SHEET尺寸超过这个尺寸，请提前通知ZURU跟单，需同客人确认才能量产和出货; Remark: 1. 产品及包装需要印UKCA图标，包装需要有ZURU UK LTD/ZURU France地址信息，QC同事请核查，如有问题与跟单确认。 2. 产品/包装/外箱都需要打ZURU格式日期码，日期必须为法定工作日。 3. 需要符合欧洲标准不能含有闪粉和微塑料，否则不合法规会有客诉产生 | V82: Amy Ding | W82: 71.2584 | X82: =W82*L82 -> 142.5168 | Y82: 94349-2.25 | Z82: 77555SLB-S001 | AA82: 已入 | AB82: 系统出单 | AC82: 1950 | AD82: =AC82-I82 -> 0 | AE82: 无 | AG82: =I82 -> 1950 | AI82: =I82*2 -> 3900 | AZ82: =I82*2 -> 3900 | BK82: =I82/13 -> 150 | CO82: =CO81-AG82 -> 2460064
A83: 45623 | B83: THE ENTERTAINER | C83: 英国 | D83: 4500152538 | E83: 4500152538-2: FB12127 | F83: 4500152538-40 | G83: 77555GQ1-S002 | H83: 迷你房子GQ1/13PCS/箱 | I83: 962 | J83: 0 | K83: 13 | L83: =I83/K83 -> 74 | M83: 45696 | N83: 45679 | P83: pass | Q83: 2/19 截SI | R83: 45624 | S83: 无 | T83: EAN条码贴翻144795 | U83: 日期码格式：ZURU INC(BVI) 标准格式 日期：按实际生产日期 Packaging Info: 77555GQ1：MA最新1L配套包装+客户EAN条码贴一张覆盖ZURU原条码，条码贴翻订单4500144795。 Remark: *MA版本按工厂现有最新库存即可，订单出英国，请注意检查产品及包装应带UKCA图标，包装显示ZURU UK LTD信息，QC同事请查核，如有问题与跟单确认。 *生产日期按实际（法定工作日），按ZURU标准格式即可 ，但是请知悉包装日期码需要早于或者等于外箱日期码 ，不能晚于外箱日期码 *请注意所有订单都需要经过ZURU QC验货并且通过后方可出货 *条码以订单显示为准 ，请安排生产前先核对 ，有问题请提出。 *所有产品按符合欧洲标准走货，需要是不含微塑料版本 。 *涉及到硼的，如可选择情况下应使用低硼版本 （slime 类别低硼一般低于300ppm)，无选择的应与跟单复核再安排 。 | V83: Amy Ding | W83: 0.8972 | X83: =W83*I83 -> 863.1064 | Y83: 94275-2.18 | Z83: 77555GQ1-S002 | AA83: 已入 | AB83: 系统出单 | AC83: 962 | AD83: =AC83-I83 -> 0 | AE83: ok | AG83: =I83 -> 962 | AI83: =I83 -> 962 | AZ83: =I83 -> 962 | BK83: =I83/13 -> 74 | CO83: =CO82-AG83 -> 2459102
A84: 45623 | B84: THE ENTERTAINER | C84: 英国 | D84: 4500152538 | E84: 4500152538-3: FB12155 | F84: 4500152538-130 | G84: 77555GQ1-S002 | H84: 迷你房子GQ1/13PCS/箱 | I84: 988 | J84: 0 | K84: 13 | L84: =I84/K84 -> 76 | M84: 45696 | N84: 45679 | P84: pass | Q84: 2/19 截SI | R84: 45624 | S84: 无 | T84: EAN条码贴翻144795 | U84: 日期码格式：ZURU INC(BVI) 标准格式 日期：按实际生产日期 Packaging Info: 77555GQ1：MA最新1L配套包装+客户EAN条码贴一张覆盖ZURU原条码，条码贴翻订单4500144795。 Remark: *MA版本按工厂现有最新库存即可，订单出英国，请注意检查产品及包装应带UKCA图标，包装显示ZURU UK LTD信息，QC同事请查核，如有问题与跟单确认。 *生产日期按实际（法定工作日），按ZURU标准格式即可 ，但是请知悉包装日期码需要早于或者等于外箱日期码 ，不能晚于外箱日期码 *请注意所有订单都需要经过ZURU QC验货并且通过后方可出货 *条码以订单显示为准 ，请安排生产前先核对 ，有问题请提出。 *所有产品按符合欧洲标准走货，需要是不含微塑料版本 。 *涉及到硼的，如可选择情况下应使用低硼版本 （slime 类别低硼一般低于300ppm)，无选择的应与跟单复核再安排 。 | V84: Amy Ding | W84: 0.8972 | X84: =W84*I84 -> 886.4336 | Y84: 94275-2.18 | Z84: 77555GQ1-S002 | AA84: 已入 | AB84: 系统出单 | AC84: 988 | AD84: =AC84-I84 -> 0 | AE84: ok | AG84: =I84 -> 988 | AI84: =I84 -> 988 | AZ84: =I84 -> 988 | BK84: =I84/13 -> 76 | CO84: =CO83-AG84 -> 2458114
A85: 45623 | B85: THE ENTERTAINER | C85: 英国 | D85: 4500152538 | E85: 4500152538-4: FB12134 | F85: 4500152538-230 | G85: 77555GQ1-S002 | H85: 迷你房子GQ1/13PCS/箱 | I85: 988 | J85: 0 | K85: 13 | L85: =I85/K85 -> 76 | M85: 45696 | N85: 45679 | P85: pass | Q85: 2/19 截SI | R85: 45624 | S85: 无 | T85: EAN条码贴翻144795 | U85: 日期码格式：ZURU INC(BVI) 标准格式 日期：按实际生产日期 Packaging Info: 77555GQ1：MA最新1L配套包装+客户EAN条码贴一张覆盖ZURU原条码，条码贴翻订单4500144795。 Remark: *MA版本按工厂现有最新库存即可，订单出英国，请注意检查产品及包装应带UKCA图标，包装显示ZURU UK LTD信息，QC同事请查核，如有问题与跟单确认。 *生产日期按实际（法定工作日），按ZURU标准格式即可 ，但是请知悉包装日期码需要早于或者等于外箱日期码 ，不能晚于外箱日期码 *请注意所有订单都需要经过ZURU QC验货并且通过后方可出货 *条码以订单显示为准 ，请安排生产前先核对 ，有问题请提出。 *所有产品按符合欧洲标准走货，需要是不含微塑料版本 。 *涉及到硼的，如可选择情况下应使用低硼版本 （slime 类别低硼一般低于300ppm)，无选择的应与跟单复核再安排 。 | V85: Amy Ding | W85: 0.8972 | X85: =W85*I85 -> 886.4336 | Y85: 94275-2.18 | Z85: 77555GQ1-S002 | AA85: 已入 | AB85: 系统出单 | AC85: 988 | AD85: =AC85-I85 -> 0 | AE85: ok | AG85: =I85 -> 988 | AI85: =I85 -> 988 | AZ85: =I85 -> 988 | BK85: =I85/13 -> 76 | CO85: =CO84-AG85 -> 2457126
A86: 45632 | B86: Whirlpool Corporation | C86: 荷兰/澳大利亚 | D86: 4500153360 | E86: Ship To: US/Global Team | F86: 4500153360-10 | G86: 77679-S001 | H86: HOMEM-S1-001/002/003/004-005/006/007(1个装一个纸袋*500/箱） | I86: 24000 | J86: 0 | K86: 500 | L86: =I86/K86 -> 48 | M86: 45674 | N86: 45675 | O86: HOMEM-S1-001: 6500pcs HOMEM-S1-002: 4500pcs HOMEM-S1-003: 2500pcs HOMEM-S1-004: 3000pc HOMEM-S1-005: 3000pcs HOMEM-S1-006: 2500pcs HOMEM-S1-007: 2000pcs | P86: pass | Q86: 1/22 走快递 | R86: 45632 | S86: 无 | T86: 无 | U86: 日期码格式：ZURU INC(BVI) 标准格式 日期：按实际生产日期 Tracking Code: Packaging Info: 1、包装方式：1minis/纸袋（同MA)，500纸袋/外箱，每个外箱的Minis 为同一种，不得混Minis入箱。 按每行出至不同国家。 2、去往US/Global Team的数量, 还需要2个外箱入一大外箱，大外箱尾箱为Stand Mixer (HOMEM-S1-001)+Countertop Oven (HOMEM-S1-006)，Blender (HOMEM-S1- 002)+Coffee Grinder (HOMEM-S1-003)混箱，其余大外箱不得混箱。--原SHIP TO BRAZIL的12CTN无需入大外箱 3、去往Europe Team的36箱货物确认需打托，托盘材质为PP,尺寸W1200 x D1000cm ，Max. height 150cm；共2托（6CTN HOMEM-S1-001+12CTN HOMEM-S1-002为一拖 ；6CTN HOMEM-S1-001+12CTN HOMEM-S1-005为一拖） Remark: 2、无测试与第三方验货要求。 3、纸箱4面印ZURU LOGO + 箱唛(见附件） 4、日期码请按ZURU标准版执行即可。 5、ZURU QC验货。 6、RATIO:不同出货地址的Ratio不同. 1)Ship to Whirlpool Corporation-US/Global Team Ratio: Stand Mixer (HOMEM-S1-001): 6500pcs Blender (HOMEM-S1-002) : 4500pcs Coffee Grinder (HOMEM-S1-003) : 2500pcs Espresso Machine (HOMEM-S1-004) : 3000pc Food Processor (HOMEM-S1-005) : 3000pcs Countertop Oven (HOMEM-S1-006) : 2500pcs Microwave (HOMEM-S1-007) : 2000pcs 2)Ship to Whirlpool Corporation-Brazil Team, Ratio: Stand Mixer (HOMEM-S1-001): 2000pcs Blender (HOMEM-S1-002): 2000pcs Food Processor (HOMEM-S1-005):2000pcs 3)Ship to Whirlpool Corporation-Mexico Team, Ratio: Stand Mixer (HOMEM-S1-001): 2000pcs Blender (HOMEM-S1-002) : 2000pcs Food Processor (HOMEM-S1-005): 2000pcs Countertop Oven (HOMEM-S1-006) : 2000pcs 4)Ship to Whirlpool Corporation-Europe Team,Ratio: Stand Mixer (HOMEM-S1-001): 6000pcs Blender (HOMEM-S1-002) : 6000pcs Food Processor (HOMEM-S1-005) : 6000pcs 5)Ship to Whirlpool Corporation-Australia Team,Ratio: Stand Mixer (HOMEM-S1-001): 2000pcs Blender (HOMEM-S1-002): 2000pcs Food Processor (HOMEM-S1-005): 2000pcs | V86: Vicky Wu | W86: 0.3389 | X86: =W86*I86 -> 8133.6 | Y86: 94147-1.22 | Z86: 77679-S001 | AA86: 已入 | AB86: 系统出单 | AC86: 24000 | AD86: =AC86-I86 -> 0 | CO86: =CO85-AG86 -> 2457126
A87: 45632 | B87: Whirlpool Corporation | C87: 荷兰/澳大利亚 | D87: 4500153360 | E87: Ship TO: Brazil Team | F87: 4500153360-60 | G87: 77679-S001 | H87: HOMEM-S1-001/002/003/004-005/006/007(1个装一个纸袋*500/箱） | I87: 6000 | J87: 0 | K87: 500 | L87: =I87/K87 -> 12 | M87: 45674 | N87: 45675 | O87: HOMEM-S1-001: 2000pcs HOMEM-S1-002: 2000pcs HOMEM-S1-005:2000pcs | P87: pass | Q87: 1/22 走快递 | R87: 45632 | S87: 无 | T87: 无 | U87: 日期码格式：ZURU INC(BVI) 标准格式 日期：按实际生产日期 Tracking Code: Packaging Info: 1、包装方式：1minis/纸袋（同MA)，500纸袋/外箱，每个外箱的Minis 为同一种，不得混Minis入箱。 按每行出至不同国家。 2、去往US/Global Team的数量, 还需要2个外箱入一大外箱，大外箱尾箱为Stand Mixer (HOMEM-S1-001)+Countertop Oven (HOMEM-S1-006)，Blender (HOMEM-S1- 002)+Coffee Grinder (HOMEM-S1-003)混箱，其余大外箱不得混箱。--原SHIP TO BRAZIL的12CTN无需入大外箱 3、去往Europe Team的36箱货物确认需打托，托盘材质为PP,尺寸W1200 x D1000cm ，Max. height 150cm；共2托（6CTN HOMEM-S1-001+12CTN HOMEM-S1-002为一拖 ；6CTN HOMEM-S1-001+12CTN HOMEM-S1-005为一拖） Remark: 2、无测试与第三方验货要求。 3、纸箱4面印ZURU LOGO + 箱唛(见附件） 4、日期码请按ZURU标准版执行即可。 5、ZURU QC验货。 6、RATIO:不同出货地址的Ratio不同. 1)Ship to Whirlpool Corporation-US/Global Team Ratio: Stand Mixer (HOMEM-S1-001): 6500pcs Blender (HOMEM-S1-002) : 4500pcs Coffee Grinder (HOMEM-S1-003) : 2500pcs Espresso Machine (HOMEM-S1-004) : 3000pc Food Processor (HOMEM-S1-005) : 3000pcs Countertop Oven (HOMEM-S1-006) : 2500pcs Microwave (HOMEM-S1-007) : 2000pcs 2)Ship to Whirlpool Corporation-Brazil Team, Ratio: Stand Mixer (HOMEM-S1-001): 2000pcs Blender (HOMEM-S1-002): 2000pcs Food Processor (HOMEM-S1-005):2000pcs 3)Ship to Whirlpool Corporation-Mexico Team, Ratio: Stand Mixer (HOMEM-S1-001): 2000pcs Blender (HOMEM-S1-002) : 2000pcs Food Processor (HOMEM-S1-005): 2000pcs Countertop Oven (HOMEM-S1-006) : 2000pcs 4)Ship to Whirlpool Corporation-Europe Team,Ratio: Stand Mixer (HOMEM-S1-001): 6000pcs Blender (HOMEM-S1-002) : 6000pcs Food Processor (HOMEM-S1-005) : 6000pcs 5)Ship to Whirlpool Corporation-Australia Team,Ratio: Stand Mixer (HOMEM-S1-001): 2000pcs Blender (HOMEM-S1-002): 2000pcs Food Processor (HOMEM-S1-005): 2000pcs | V87: Vicky Wu | W87: 0.3389 | X87: =W87*I87 -> 2033.4 | Y87: 94147-1.22 | Z87: 77679-S001 | AA87: 已入 | AB87: 系统出单 | AC87: 6000 | AD87: =AC87-I87 -> 0 | CO87: =CO86-AG87 -> 2457126
A88: 45632 | B88: Whirlpool Corporation | C88: 荷兰/澳大利亚 | D88: 4500153360 | E88: Ship To: Mexico Team | F88: 4500153360-30 | G88: 77679-S001 | H88: HOMEM-S1-001/002/003/004-005/006/007(1个装一个纸袋*500/箱） | I88: 8000 | J88: 0 | K88: 500 | L88: =I88/K88 -> 16 | M88: 45674 | N88: 45675 | O88: HOMEM-S1-001: 2000pcs HOMEM-S1-002: 2000pcs HOMEM-S1-005: 2000pcs HOMEM-S1-006: 2000pcs | P88: pass | Q88: 1/22 走快递 | R88: 45632 | S88: 无 | T88: 无 | U88: 日期码格式：ZURU INC(BVI) 标准格式 日期：按实际生产日期 Tracking Code: Packaging Info: 1、包装方式：1minis/纸袋（同MA)，500纸袋/外箱，每个外箱的Minis 为同一种，不得混Minis入箱。 按每行出至不同国家。 2、去往US/Global Team的数量, 还需要2个外箱入一大外箱，大外箱尾箱为Stand Mixer (HOMEM-S1-001)+Countertop Oven (HOMEM-S1-006)，Blender (HOMEM-S1- 002)+Coffee Grinder (HOMEM-S1-003)混箱，其余大外箱不得混箱。--原SHIP TO BRAZIL的12CTN无需入大外箱 3、去往Europe Team的36箱货物确认需打托，托盘材质为PP,尺寸W1200 x D1000cm ，Max. height 150cm；共2托（6CTN HOMEM-S1-001+12CTN HOMEM-S1-002为一拖 ；6CTN HOMEM-S1-001+12CTN HOMEM-S1-005为一拖） Remark: 2、无测试与第三方验货要求。 3、纸箱4面印ZURU LOGO + 箱唛(见附件） 4、日期码请按ZURU标准版执行即可。 5、ZURU QC验货。 6、RATIO:不同出货地址的Ratio不同. 1)Ship to Whirlpool Corporation-US/Global Team Ratio: Stand Mixer (HOMEM-S1-001): 6500pcs Blender (HOMEM-S1-002) : 4500pcs Coffee Grinder (HOMEM-S1-003) : 2500pcs Espresso Machine (HOMEM-S1-004) : 3000pc Food Processor (HOMEM-S1-005) : 3000pcs Countertop Oven (HOMEM-S1-006) : 2500pcs Microwave (HOMEM-S1-007) : 2000pcs 2)Ship to Whirlpool Corporation-Brazil Team, Ratio: Stand Mixer (HOMEM-S1-001): 2000pcs Blender (HOMEM-S1-002): 2000pcs Food Processor (HOMEM-S1-005):2000pcs 3)Ship to Whirlpool Corporation-Mexico Team, Ratio: Stand Mixer (HOMEM-S1-001): 2000pcs Blender (HOMEM-S1-002) : 2000pcs Food Processor (HOMEM-S1-005): 2000pcs Countertop Oven (HOMEM-S1-006) : 2000pcs 4)Ship to Whirlpool Corporation-Europe Team,Ratio: Stand Mixer (HOMEM-S1-001): 6000pcs Blender (HOMEM-S1-002) : 6000pcs Food Processor (HOMEM-S1-005) : 6000pcs 5)Ship to Whirlpool Corporation-Australia Team,Ratio: Stand Mixer (HOMEM-S1-001): 2000pcs Blender (HOMEM-S1-002): 2000pcs Food Processor (HOMEM-S1-005): 2000pcs | V88: Vicky Wu | W88: 0.3389 | X88: =W88*I88 -> 2711.2 | Y88: 94147-1.22 | Z88: 77679-S001 | AA88: 已入 | AB88: 系统出单 | AC88: 8000 | AD88: =AC88-I88 -> 0 | CO88: =CO87-AG88 -> 2457126
A89: 45632 | B89: Whirlpool Corporation | C89: 荷兰/澳大利亚 | D89: 4500153360 | E89: Ship TO: Europe Team | F89: 4500153360-40 | G89: 77679-S001 | H89: HOMEM-S1-001/002/003/004-005/006/007(1个装一个纸袋*500/箱）6箱001+12箱002装/板，6箱001+12箱005装/拖 | I89: 18000 | J89: 0 | K89: 500 | L89: =I89/K89 -> 36 | M89: 45674 | N89: 45675 | O89: HOMEM-S1-001: 6000pcs HOMEM-S1-002: 6000pcs HOMEM-S1-005: 6000pcs | P89: pass | Q89: 1/22 走飞机 需打卡板，蓝色胶卡板尺寸W1200 x D1000cm ，限高150cm；共2托（6CTN HOMEM-S1-001+12CTN HOMEM-S1-002为一拖，6CTN HOMEM-S1-001+12CTN HOMEM-S1-005为一拖） | R89: 45632 | S89: 无 | T89: 无 | U89: 日期码格式：ZURU INC(BVI) 标准格式 日期：按实际生产日期 Tracking Code: Packaging Info: 1、包装方式：1minis/纸袋（同MA)，500纸袋/外箱，每个外箱的Minis 为同一种，不得混Minis入箱。 按每行出至不同国家。 2、去往US/Global Team的数量, 还需要2个外箱入一大外箱，大外箱尾箱为Stand Mixer (HOMEM-S1-001)+Countertop Oven (HOMEM-S1-006)，Blender (HOMEM-S1- 002)+Coffee Grinder (HOMEM-S1-003)混箱，其余大外箱不得混箱。--原SHIP TO BRAZIL的12CTN无需入大外箱 3、去往Europe Team的36箱货物确认需打托，托盘材质为PP,尺寸W1200 x D1000cm ，Max. height 150cm；共2托（6CTN HOMEM-S1-001+12CTN HOMEM-S1-002为一拖 ；6CTN HOMEM-S1-001+12CTN HOMEM-S1-005为一拖） Remark: 2、无测试与第三方验货要求。 3、纸箱4面印ZURU LOGO + 箱唛(见附件） 4、日期码请按ZURU标准版执行即可。 5、ZURU QC验货。 6、RATIO:不同出货地址的Ratio不同. 1)Ship to Whirlpool Corporation-US/Global Team Ratio: Stand Mixer (HOMEM-S1-001): 6500pcs Blender (HOMEM-S1-002) : 4500pcs Coffee Grinder (HOMEM-S1-003) : 2500pcs Espresso Machine (HOMEM-S1-004) : 3000pc Food Processor (HOMEM-S1-005) : 3000pcs Countertop Oven (HOMEM-S1-006) : 2500pcs Microwave (HOMEM-S1-007) : 2000pcs 2)Ship to Whirlpool Corporation-Brazil Team, Ratio: Stand Mixer (HOMEM-S1-001): 2000pcs Blender (HOMEM-S1-002): 2000pcs Food Processor (HOMEM-S1-005):2000pcs 3)Ship to Whirlpool Corporation-Mexico Team, Ratio: Stand Mixer (HOMEM-S1-001): 2000pcs Blender (HOMEM-S1-002) : 2000pcs Food Processor (HOMEM-S1-005): 2000pcs Countertop Oven (HOMEM-S1-006) : 2000pcs 4)Ship to Whirlpool Corporation-Europe Team,Ratio: Stand Mixer (HOMEM-S1-001): 6000pcs Blender (HOMEM-S1-002) : 6000pcs Food Processor (HOMEM-S1-005) : 6000pcs 5)Ship to Whirlpool Corporation-Australia Team,Ratio: Stand Mixer (HOMEM-S1-001): 2000pcs Blender (HOMEM-S1-002): 2000pcs Food Processor (HOMEM-S1-005): 2000pcs | V89: Vicky Wu | W89: 0.3389 | X89: =W89*I89 -> 6100.2 | Y89: 94147-1.22 | Z89: 77679-S001 | AA89: 已入 | AB89: 系统出单 | AC89: 18000 | AD89: =AC89-I89 -> 0 | CO89: =CO88-AG89 -> 2457126
A90: 45632 | B90: Whirlpool Corporation | C90: 荷兰/澳大利亚 | D90: 4500153360 | E90: Ship TO: Australia Team | F90: 4500153360-50 | G90: 77679-S001 | H90: HOMEM-S1-001/002/003/004-005/006/007(1个装一个纸袋*500/箱） | I90: 6000 | J90: 0 | K90: 500 | L90: =I90/K90 -> 12 | M90: 45674 | N90: 45675 | O90: HOMEM-S1-001: 2000pcs HOMEM-S1-002: 2000pcs HOMEM-S1-005: 2000pcs | P90: pass | Q90: 1/22 走快递 | R90: 45632 | S90: 无 | T90: 无 | U90: 日期码格式：ZURU INC(BVI) 标准格式 日期：按实际生产日期 Tracking Code: Packaging Info: 1、包装方式：1minis/纸袋（同MA)，500纸袋/外箱，每个外箱的Minis 为同一种，不得混Minis入箱。 按每行出至不同国家。 2、去往US/Global Team的数量, 还需要2个外箱入一大外箱，大外箱尾箱为Stand Mixer (HOMEM-S1-001)+Countertop Oven (HOMEM-S1-006)，Blender (HOMEM-S1- 002)+Coffee Grinder (HOMEM-S1-003)混箱，其余大外箱不得混箱。--原SHIP TO BRAZIL的12CTN无需入大外箱 3、去往Europe Team的36箱货物确认需打托，托盘材质为PP,尺寸W1200 x D1000cm ，Max. height 150cm；共2托（6CTN HOMEM-S1-001+12CTN HOMEM-S1-002为一拖 ；6CTN HOMEM-S1-001+12CTN HOMEM-S1-005为一拖） Remark: 2、无测试与第三方验货要求。 3、纸箱4面印ZURU LOGO + 箱唛(见附件） 4、日期码请按ZURU标准版执行即可。 5、ZURU QC验货。 6、RATIO:不同出货地址的Ratio不同. 1)Ship to Whirlpool Corporation-US/Global Team Ratio: Stand Mixer (HOMEM-S1-001): 6500pcs Blender (HOMEM-S1-002) : 4500pcs Coffee Grinder (HOMEM-S1-003) : 2500pcs Espresso Machine (HOMEM-S1-004) : 3000pc Food Processor (HOMEM-S1-005) : 3000pcs Countertop Oven (HOMEM-S1-006) : 2500pcs Microwave (HOMEM-S1-007) : 2000pcs 2)Ship to Whirlpool Corporation-Brazil Team, Ratio: Stand Mixer (HOMEM-S1-001): 2000pcs Blender (HOMEM-S1-002): 2000pcs Food Processor (HOMEM-S1-005):2000pcs 3)Ship to Whirlpool Corporation-Mexico Team, Ratio: Stand Mixer (HOMEM-S1-001): 2000pcs Blender (HOMEM-S1-002) : 2000pcs Food Processor (HOMEM-S1-005): 2000pcs Countertop Oven (HOMEM-S1-006) : 2000pcs 4)Ship to Whirlpool Corporation-Europe Team,Ratio: Stand Mixer (HOMEM-S1-001): 6000pcs Blender (HOMEM-S1-002) : 6000pcs Food Processor (HOMEM-S1-005) : 6000pcs 5)Ship to Whirlpool Corporation-Australia Team,Ratio: Stand Mixer (HOMEM-S1-001): 2000pcs Blender (HOMEM-S1-002): 2000pcs Food Processor (HOMEM-S1-005): 2000pcs | V90: Vicky Wu | W90: 0.3389 | X90: =W90*I90 -> 2033.4 | Y90: 94147-1.22 | Z90: 77679-S001 | AA90: 已入 | AB90: 系统出单 | AC90: 6000 | AD90: =AC90-I90 -> 0 | CO90: =CO89-AG90 -> 2457126
A91: 45624 | B91: FAMILY DOLLAR SERVICES, INC, | C91: 美国 | D91: 4500152838 | E91: To be advised | F91: 4500152838-10 | G91: 77555GQ7-S001 | H91: 迷你房子GQ7/6PCS/箱 | I91: 93138 | J91: 0 | K91: 6 | L91: =I91/K91 -> 15523 | M91: 45698 | N91: 45679 | O91: 此单指定日期码：DG20250113 | P91: pass | Q91: 2/17 截SI | R91: 45642 | S91: 有 | T91: 12/18 彩色贴纸 12/25 客供防盗贴纸 | U91: 日期码格式：ZURU INC(BVI) 标准格式 日期：2025-01-13 Packaging Info: 1)客版PDQ，最新版ZURU MA UPC包装(去掉社交媒体标志，优先1L)，出口美国。如有说明书请使用ZURU MA说明书，优先放1L英语。 2)ZURU标准日期码格式：工厂城市缩写+生产年月日。此单指定日期码：DG20250113。 3)外箱箱唛正侧相邻两面粘贴产品彩色贴纸，每箱两张彩色贴纸, 彩色产品贴纸待跟单提供。如侧唛位置放不下彩贴和唛头信息，可改为放两个正唛。无论是正唛+ 侧唛或者是两个正唛，唛头信息和彩贴需放在同一个面，需要工厂根据外箱尺寸建议预估的彩贴尺寸给跟单。箱唛需排版给跟单确认。 4) 每个球贴一张客供防盗贴，贴在收缩膜上，防盗贴由跟单采购，供应商直接发货到工厂。防盗贴贴纸位置由跟单提供。 Remark: 客户PO#32610787 客户SKU#1096263 1) Item#77555GQ7-S001 2) 样品 产前样5套：产前样5套要求在2024/12/12前寄给深圳办公室跟单Jenny Liu，需转寄给美国客户确认，客户确认了产前样之后，会寄回一套给工厂，工厂需按照已确 认的产前样安 排大货生产。做产前样前需和跟单确认产品包装日期码和产品上日期码的打码位置+格式，要求是和大货一样的日期码，指定大货日期码为：DG20250 113） 。此单客版PDQ需等客户确认产前样后才可以开始大货印刷。 大货样2套：大货样2套需在大货物料到厂后开始上线第一天寄出给深圳办公室；大货样需要同大货一个产线， 所有东西完全同大货一样, 1套我们需转寄客人审批出 货；1套跟单需留样（请尽量安排早点寄出以便客人早点批出货！） 1套样板 =6pcs球带1个客版PDQ(球带客供防盗贴)+1套光身样散件 6 PCS/ PDQ = 6个球入一个PDQ 3) 此单无第三方验货+抽样测试，ZURU QC验货PASS后，跟单得到客户的approval之后方可安排出货 4)大货外箱材积绝对不可大于下述数据，材积只接受3%的变小；重量正负不得超过以下列出数据的5%，接受外箱以印章方式印上实际毛重。 大货外箱尺寸请保持： 21.3 x 12.8 x 30.1 cm(即8.39 x 5.04 x 11.85 inch)，材积必须不能大于0.2896CubeFeet（即0.0082CBM); 外箱毛重 1.9 LBS（即0.84 K GS）。 5) 大货配比： Item#77555GQ7-S001 S001-MINI BRANDS-HOME MINI BRANDS-SERIES 1-CAPSULE,6pcs/Gravity PDQ,6PCS/PDQ/CTN UPC:193052064264 Contains UV Glue. 1FACING 6PCS/PDQ/CTN;1W*2D*3H=6PCS/PDQ 6) 客户Family Dollar不允许少数出货，必须按照PO上的数量出货，也不允许延期，否则会有罚款。 7) 客户要求:"产品和包装不能含有PFAS 物质以及1,4 dioxane",请确保产品可以过美国标准测试。 | V91: Jenny Liu/Andro | W91: 0.9416 | X91: =W91*I91 -> 87698.741 | Y91: 94281-2.19 | Z91: 77555GQ7-S001 | AA91: 已入 | AB91: 系统出单 | AC91: =7272+55512+30354 -> 93138 | AD91: =AC91-I91 -> 0 | AE91: ok | AG91: =I91 -> 93138 | AI91: =I91 -> 93138 | AZ91: =I91 -> 93138 | BJ91: =I91/6 -> 15523 | CO91: =CO90-AG91 -> 2363988
A92: 45656 | B92: Amazon CA (Vendor Center) | C92: 加拿大 | D92: 4500154964 | E92: 3WJ8O9PR | F92: 4500154964-210 | G92: 77584-S001 | H92: 迷你房子 | I92: 12 | J92: 0 | K92: 12 | L92: =I92/K92 -> 1 | M92: 45712 | N92: 45708 | P92: 自检 | Q92: 2/27 交仓 | R92: 46021 | S92: 无 | T92: 2/8 SSCC Label+空白贴纸翻单132623 | U92: 日期码格式：ZURU INC(BVI) 标准格式 日期：按实际生产日期 Packaging Info: #77584：2PK MA 3L#77555入PVC圆桶，77555 3L收缩膜，空白贴纸覆盖EAN条码，空白贴纸跟返单4500132623， 3L铜版纸图稿跟Amazon UK/EU PO 4500134367；跟A mazon us 合并订料; Remark: 1. Amazon FOB订单，出口CA。外箱最长边不能超过25" （超过了，case pack只能为1），不符合要求的大货，一律不接受。 2. 外箱正面印ZURU Logo + SSCC LABEL（客供贴纸)，侧面印item#（订单上显示的SKU#) + carton size(以工厂实际尺寸为准，单位: inch) + MADE IN CHINA， 日期使用ZURU 标准版本 SSCC Label 显示的是客人自己的item#，SSCC Label 贴在外箱正面的正中间，贴一面即可，跟单订购，贴纸离外箱距必须至少3cm，每一 张SSCC label 都是唯一且有不同流水及条码的，没有损耗，绝对不可贴错 ，否则贴错或损坏一张会导致全部都错，千万要注意: SSCC 贴纸务必要在正中间(可以覆 盖Logo <(>&<)> 箱唛)，否则会影响到仓库扫描识别。 3. 日期码使用ZURU标准版本。 4. 如果大货有要求入邮包盒，则对应的邮包盒上面要打上日期码。 5. 按照客户PO# 装柜/箱号顺序装柜，跟单会提前给到装柜计划。在大货生产/仓库存放时，请留意该装柜要求，以便装柜时不混乱（避免装错/装漏/找不到货号等 ）。 6. 出口加拿大，包装需要至少2/3L UPC版，无硼版本。 7.邮包盒上要印刷日期码 | V92: Kelly/Mia | W92: 2.3963 | X92: =W92*I92 -> 28.7556 | Y92: 94433-3.4 | Z92: 77584-S001-3L-1 | AA92: 已入 | AB92: 系统出单 | AC92: 12 | AD92: =AC92-I92 -> 0 | AE92: ok | AG92: =I92*2 -> 24 | AJ92: =AG92 -> 24 | AZ92: =AJ92 -> 24 | CC92: =I92 -> 12 | CD92: =I92 -> 12 | CF92: =I92 -> 12 | CH92: 10/25已放 | CJ92: =CJ45-I92 -> 3284 | CO92: =CO91-AG92 -> 2363964
A93: 45656 | B93: Amazon CA (Vendor Center) | C93: 加拿大 | D93: 4500154964 | E93: 5F5H79CR | F93: 4500154964-220 | G93: 77555-S001 | H93: 迷你房子 | I93: 24 | J93: 0 | K93: 24 | L93: =I93/K93 -> 1 | M93: 45712 | N93: 45708 | P93: 自检 | Q93: 2/27 交仓 | R93: 46021 | S93: 无 | T93: 2/8SSCC Label+UPC贴纸翻单132673 | U93: 日期码格式：ZURU INC(BVI) 标准格式 日期：按实际生产日期 Packaging Info: #77555：MA 3L 收缩膜加UPC贴纸覆盖原EAN条码，UPC贴纸跟翻单#4500132673。收藏指南MA 5L. Remark: 1. Amazon FOB订单，出口CA。外箱最长边不能超过25" （超过了，case pack只能为1），不符合要求的大货，一律不接受。 2. 外箱正面印ZURU Logo + SSCC LABEL（客供贴纸)，侧面印item#（订单上显示的SKU#) + carton size(以工厂实际尺寸为准，单位: inch) + MADE IN CHINA， 日期使用ZURU 标准版本 SSCC Label 显示的是客人自己的item#，SSCC Label 贴在外箱正面的正中间，贴一面即可，跟单订购，贴纸离外箱距必须至少3cm，每一 张SSCC label 都是唯一且有不同流水及条码的，没有损耗，绝对不可贴错 ，否则贴错或损坏一张会导致全部都错，千万要注意: SSCC 贴纸务必要在正中间(可以覆 盖Logo <(>&<)> 箱唛)，否则会影响到仓库扫描识别。 3. 日期码使用ZURU标准版本。 4. 如果大货有要求入邮包盒，则对应的邮包盒上面要打上日期码。 5. 按照客户PO# 装柜/箱号顺序装柜，跟单会提前给到装柜计划。在大货生产/仓库存放时，请留意该装柜要求，以便装柜时不混乱（避免装错/装漏/找不到货号等 ）。 6. 出口加拿大，包装需要至少2/3L UPC版，无硼版本。 7.邮包盒上要印刷日期码 | V93: Kelly/Mia | W93: 0.8346 | X93: =W93*I93 -> 20.0304 | Y93: 94433-3.4 | Z93: 77555-S001-3L | AA93: 已入 | AB93: 系统出单 | AC93: 24 | AD93: =AC93-I93 -> 0 | AE93: ok | AG93: =I93 -> 24 | AJ93: =I93 -> 24 | AZ93: =I93 -> 24 | CO93: =CO92-AG93 -> 2363940
A94: 45644 | B94: COLES SUPERMARKETS | C94: 澳大利亚 | D94: 4500153570 | E94: 港口：MEL PO#45704314 | F94: 4500153570-40 | G94: 77555GQ4-S001 | H94: 迷你房子GQ4/6pcs/箱 | I94: 1140 | J94: 0 | K94: 6 | L94: =I94/K94 -> 190 | M94: 45713 | N94: 45709 | P94: pass | Q94: 3/3 交仓 | R94: 箱唛翻单4500124295(ZURU LOGO使用新版 ) | S94: 无 | T94: 无 | U94: 日期码格式：ZURU INC(BVI) 标准格式 日期：按实际生产日期 Packaging Info: 2.77555GQ4: MA UPC 包装，箱唛翻单4500124295(ZURU LOGO使用新版 ) Remark: 1.此单出口澳大利亚，请按相应的澳新标准生产； 2.产品和包装上生产批号请按我司标准 3.比例： 4.当同一PO或item有多个批次代码时，每个批次代码的纸箱必须分组在一起，且明显分开 | V94: Lydia Wu | W94: 0.9971 | X94: =W94*I94 -> 1136.694 | Y94: 94432-3.4 | Z94: 77555GQ4-S001 | AA94: 已入 | AB94: 系统出单 | AC94: 1140 | AD94: =AC94-I94 -> 0 | AE94: 无 | AG94: =I94 -> 1140 | AI94: =I94 -> 1140 | AZ94: =I94 -> 1140 | BI94: =I94/6 -> 190 | CO94: =CO93-AG94 -> 2362800
A95: 45644 | B95: COLES SUPERMARKETS | C95: 澳大利亚 | D95: 4500153570 | E95: 港口：SYD PO#45682458 | F95: 4500153570-50 | G95: 77555GQ4-S001 | H95: 迷你房子GQ4/6pcs/箱 | I95: 864 | J95: 0 | K95: 6 | L95: =I95/K95 -> 144 | M95: 45713 | N95: 45709 | P95: pass | Q95: 3/3 交仓 | R95: 箱唛翻单4500124295(ZURU LOGO使用新版 ) | S95: 无 | T95: 无 | U95: 日期码格式：ZURU INC(BVI) 标准格式 日期：按实际生产日期 Packaging Info: 2.77555GQ4: MA UPC 包装，箱唛翻单4500124295(ZURU LOGO使用新版 ) Remark: 1.此单出口澳大利亚，请按相应的澳新标准生产； 2.产品和包装上生产批号请按我司标准 3.比例： 4.当同一PO或item有多个批次代码时，每个批次代码的纸箱必须分组在一起，且明显分开 | V95: Lydia Wu | W95: 0.9971 | X95: =W95*I95 -> 861.4944 | Y95: 94432-3.4 | Z95: 77555GQ4-S001 | AA95: 已入 | AB95: 系统出单 | AC95: 864 | AD95: =AC95-I95 -> 0 | AE95: 无 | AG95: =I95 -> 864 | AI95: =I95 -> 864 | AZ95: =I95 -> 864 | BI95: =I95/6 -> 144 | CO95: =CO94-AG95 -> 2361936
A96: 45657 | B96: AMAZON.COM.DEDC,LLC | C96: 美国 | D96: 4500155020 | E96: 64VCQLUP | F96: 4500155020-40 | G96: 77584-S001 | H96: 迷你房子 | I96: 1692 | J96: 0 | K96: 12 | L96: =I96/K96 -> 141 | M96: 45715 | N96: 45710 | P96: pass | R96: 46022 | S96: 有 | T96: 2/8 SSCC Label | U96: 日期码格式：ZURU INC(BVI) 标准格式 日期：按实际生产日期 Packaging Info: #77584:2PK 77555入PVC圆桶，77555 MA 1L不带UPC， 3L铜版纸图稿跟回PO#4500134367； Remark: 1. Amazon FOB订单，出口US。 2. 日期码使用ZURU标准版本。 3. 如果大货有要求入邮包盒，则对应的邮包盒上面要打上日期码。 4. 箱尺寸要求：外箱最长边不能超过25" （超过了，case pack只能为1），不符合要求的大货，一律不接受。 5. 外箱箱唛要求： ①外箱正面印ZURU Logo+SSCC Label（客供贴纸，由跟单订购)。关于 SSCC Label 请注意： SSCC Label 显示的是客人自己的item#。每一张SSCC label 都是唯一且有不同流水及条码的，没有损耗，绝对不可贴错 。如果贴错或损坏任何一张，都会导致全 部都错，千万要注意！ SSCC Label 必须贴在外箱正面的正中间位置（贴一面即可），并且贴纸离外箱边距必须至少3cm(可以覆盖Logo<(>&<)>箱唛)，否则会影响到客户那边仓库的扫描识 别。 ②外箱侧面印item#（订单上显示的SKU#)+carton size(以工厂实际尺寸为准,单位: inch) +MADE IN CHINA,日期使用ZURU 标准版本。 6. 装柜要求：按照客户PO# 装柜/箱号顺序装柜，跟单会提前给到装柜计划。 在大货生产/仓库存放时，请留意该装柜要求，以便装柜时不混乱（避免装错/装漏/找不到货号等）。 | V96: Kelly Shen/Mia Pan | W96: 2.4352 | X96: =W96*I96 -> 4120.3584 | Y96: 94452-3.5 | Z96: 77584-S001-3L-2 | AA96: 已入 | AB96: 系统出单 | AC96: 1692 | AD96: =AC96-I96 -> 0 | AE96: OK | AG96: =I96*2 -> 3384 | AM96: =AG96 -> 3384 | AZ96: =AM96 -> 3384 | CC96: =I96 -> 1692 | CD96: =I96 -> 1692 | CF96: =I96 -> 1692 | CH96: 10/25已放 | CJ96: =CJ92-I96 -> 1592 | CO96: =CO95-AG96 -> 2358552
A97: 45645 | B97: COMERCIAL JOMAN S.L | C97: 西班牙 | D97: 4500154349 | F97: 4500154349-10 | G97: 77555GQ2-S001 | H97: 迷你房子25pcsGQ2*2/箱 | I97: 600 | J97: 0 | K97: 50 | L97: =I97/K97 -> 12 | M97: 45716 | N97: 45712 | P97: pass | Q97: 3/4截SI | R97: 45664 | S97: 无 | T97: 1/8警语贴纸 | U97: 日期码格式：ZURU INC(BVI) 标准格式 日期：按实际生产日期 Packaging Info: 1.77555GQ2:最新MA 3L EAN 版本包装+一张客户警语贴纸（含环保标）+MA 5L 收藏指南+MA 3L PDQ； Remark: 西班牙订单，需要符合EU标准，不能含微塑料/闪粉； | V97: Sherry Chen | W97: 0.9376 | X97: =W97*I97 -> 562.56 | Y97: 94434-3.4 | Z97: 77555GQ2-S001-3L | AA97: 已入 | AB97: 系统出单 | AC97: 600 | AD97: =AC97-I97 -> 0 | AE97: OK | AG97: =I97 -> 600 | AJ97: =I97 -> 600 | AZ97: =I97 -> 600 | BR97: =I97/25 -> 24 | CO97: =CO96-AG97 -> 2357952
A98: 45651 | B98: G.T. WHOLESALE LIMITED | C98: 加拿大 | D98: 4500154717 | E98: 2892616-00 | F98: 4500154717-10 | G98: 77555GQ2-S002 | H98: 迷你房子 | I98: 3200 | J98: 0 | K98: 25 | L98: =I98/K98 -> 128 | M98: 45716 | N98: 45712 | O98: 已出样板 | P98: pass | Q98: 3/11 截SI | R98: 45651 | S98: 无 | T98: 1/8 UPC贴纸+进口商贴纸 | U98: 日期码格式： 标准格式 日期：按实际生产日期 Packaging Info: 77555GQ2 MA 多语EAN+UPC贴纸, UPC号码193052064264 Remark: 出口加拿大， 有 进口商贴纸 2/21前寄出大货样2套 Zuru验货 需要单个产品称重的图片和整箱产品称重的图片，还需要产品上made in China的晒字图片，包装上的警告语的清晰图片，以及单个产品的尺寸测量图片 和外箱的尺寸测量图片 日期跟踪码：产品外包装必须有日期跟踪码，ZURU标准格式日期码 | V98: Summer Mo | W98: 0.9323 | X98: =W98*I98 -> 2983.36 | Y98: 94510-3.11 | Z98: 77555GQ2-S002-3L | AA98: 已入 | AB98: 系统出单 | AC98: 3200 | AD98: =AC98-I98 -> 0 | AE98: ok | AG98: =I98 -> 3200 | AJ98: =I98 -> 3200 | AZ98: =I98 -> 3200 | BR98: =I98/25 -> 128 | CO98: =CO97-AG98 -> 2354752
A99: 45660 | B99: THE ENTERTAINER | C99: 英国 | D99: 4500154847 | E99: FB12131 | F99: 4500154847-40 | G99: 77555GQ1-S002 | H99: 迷你房子GQ1/13PCS/箱 | I99: 1170 | J99: 0 | K99: 13 | L99: =I99/K99 -> 90 | M99: 45716 | N99: 45712 | O99: 已出 样板 | P99: pass | Q99: 3/4截SI | R99: 45660 | S99: 无 | T99: EAN条码翻单144795 | U99: 日期码格式：ZURU INC(BVI) 标准格式 日期：按实际生产日期 Packaging Info: 77555GQ1: MA最新1L配套包装+客户EAN条码(翻单4500144795)覆盖ZURU 原条码,MA PDQ Remark: *MA版本按工厂现有最新库存即可，订单出英国，请注意检查产品及包装应带UKCA图标，包装显示ZURU UK LTD信息，QC同事请查核，如有问题与跟单确认 *生产日期按实际（法定工作日），按ZURU标准格式即可 ，但是请知悉包装日期码需要早于或者等于外箱日期码 ，不能晚于外箱日期码 *请注意所有订单都需要经过ZURU QC验货并且通过后方可出货 *条码以订单显示为准 ，请安排生产前先核对 ，有问题请提出。 *所有产品按符合欧洲标准走货，需要是不含微塑料版本 。 *涉及到硼的，如可选择情况下应使用低硼版本 （slime 类别低硼一般低于300ppm)，无选择的应与跟单复核再安排 。 *条码以订单显示为准 ，请安排生产前先核对 ，有问题请提出。 *订单对应客户2个PO号 ，备注有显示 ，注意分开做货/验货/装柜 ，混装有罚款。 *样板： 请在1/20前每款寄出2pcs大货样到罗湖办公室 7B Sandy Shao收 | V99: Sandy Shao | W99: 0.8797 | X99: =W99*I99 -> 1029.249 | Y99: 94436-3.4 | Z99: 77555GQ1-S002 | AA99: 已入 | AB99: 系统出单 | AC99: 1170 | AD99: =AC99-I99 -> 0 | AE99: ok | AG99: =I99 -> 1170 | AI99: =I99 -> 1170 | AZ99: =I99 -> 1170 | BK99: =I99/13 -> 90 | CO99: =CO98-AG99 -> 2353582
A100: 45653 | B100: WAL-MART STORES INC. USA | C100: 美国 | D100: 4500154934 | E100: 0885773862 SUFFOLK | F100: 4500154934-10 | G100: 77555SLB-S002 | H100: 迷你房子 | I100: 2304 | J100: 0 | K100: 1152 | L100: =I100/K100 -> 2 | M100: 45719 | N100: 45715 | O100: 3/3 BV | P100: pass | Q100: 3/18截SI | R100: 翻单 | S100: 有 | T100: 1/3 RFID | U100: 日期码格式：ZURU DGYYYYMMDD CHINA(日期避开周末和法定节假日即可） 日期：按实际生产日期 Packaging Info: 77555SLB-S002 1.包装要求： MA 1L收缩膜+ 客版 收藏指南+客版 1L PDQ，翻单：4500129394 每pcs产品上要贴1张RFID贴纸，贴纸由ZURU提供，贴纸位置请严格按照我们签回的签板； Remark: 77555SLB-S002 1.包装要求： MA 1L收缩膜+ 客版 收藏指南+客版 1L PDQ，翻单：4500129394 每pcs产品上要贴1张RFID贴纸，贴纸由ZURU提供，贴纸位置请严格按照我们签回的签板； 2. 外箱印刷带条码的RFID箱唛：RFID紫色色带+WM Dept.图标+RFID图标+ITF-14条码，四面右下角印刷ZURU logo, ITFF条码只印刷在正唛一面，在加印的时候确保 条形码能扫描出来，外箱侧面任一角落加印："MADE IN CHINA" 字样； 3. 每个slip sheet上面贴一张艾利贴纸（不干胶贴纸）和一张普通贴纸（A4纸），slip sheet打印的普通贴纸的尺寸不能比艾利贴纸小，普通贴纸内容见附件； 4. 在产品上和包装上要有日期码、以及要有MADE IN CHINA和ZURU字样； 5. 产品如有扎带口要剪平，不能刮手。 6. 此单需要验货，请多备料 7. 以slip sheet出货， 77555SLB-S002:1152pcs/96CTN/Slip Sheet | V100: Maggie Xie | W100: 112.0403 | X100: =W100*L100 -> 224.0806 | Y100: 94572-3.17 | Z100: 77555SLB-S002 | AA100: 已入 | AB100: 系统出单 | AC100: 2304 | AD100: =AC100-I100 -> 0 | AE100: ok | AG100: =I100 -> 2304 | AI100: =I100 -> 2304 | BC100: =I100 -> 2304 | BG100: =I100/12 -> 192 | CG100: 12/27 已放 | CH100: 500 | CI100: =CH100+CL38-BG100 -> 328 | CO100: =CO99-AG100 -> 2351278
...

Sheet 77555 迷你房子
A1: ZURU （77555 迷你房子）生产排期表 | F1: 77555 MA 3LB版收缩膜，收藏指南，纸袋，GQ1，GQ2，小产品上的贴纸更新B版本，6.1号之后出加拿大的3L都需要双语logo，目前SK没有单就还没有更新 | AE1: 第一张MA是订购A版本，第二张MA订购B版本，A和B版本区别在于德语的警语不一样，A版本不能出德国
AI2: 收縮膜 | AY2: 134013 | BA2: 收藏指南 | BH2: GQ6 | BI2: GQ6 | BJ2: GQ4 | BK2: FD GQ7 | BL2: GQ1 | BQ2: GQ2 | BT2: GQ3 | BU2: SQ1 | BV2: 不带底座 | BW2: 3L | BX2: 1L | BY2: 3L | BZ2: 77556 圆筒 | CD2: 77584 圆筒 | CN2: 总MA | CO2: ='生产MA '!S4 -> 5380000
A3: 香港接单日期 | B3: 第三方客户名称 | C3: 走货国家 | D3: ZURU PO NO# | E3: 第三方客户 PO NO# | F3: SKU | G3: ITEM# | H3: 中文名 | I3: PO数量 (pcs) | J3: 内箱装箱数量(pcs) | K3: 外箱装箱数量(pcs) | L3: 总箱数 | M3: 客PO期 | N3: 验货期 | O3: 第三方验货期 | P3: 驗貨結果 | Q3: S/0船期 | R3: 箱唛资料(收到日期) | S3: 外箱贴纸 | T3: 客供贴纸AI(收到日期) | U3: 备注 | V3: ZURU 跟单 | W3: 单价USD | X3: 金额USD | Y3: 發票號 | Z3: 系统货号 | AA3: 是否入系统 | AB3: 系统出单 | AC3: 送货情况 | AD3: 欠数 | AE3: 贴纸 | AG3: 球数 | AH3: 散件/空PDQ/空球壳 | AI3: MA 1语 | AJ3: MA 3语 | AK3: 1L-B版本 | AL3: 3L-B版本 | AM3: 无UPC版本 | AN3: DG 客版 | AO3: DG 新客版 | AP3: DG 更新客版 | AQ3: DG 更新-1客版 | AR3: DG 更新-2客版 | AS3: DG 更新-3客版 | AT3: DG 更新-4客版 | AU3: DG 更新-5客版 | AV3: DG 更新-6客版 | AW3: TG客版 | AX3: WMCA客版 | AY3: MGS客版 | AZ3: GP 客版 | BA3: MA 5L语 | BB3: 5L-B版本 | BC3: 外挂收藏指南+中文说明书（每一款都不同，请做好区分） | BD3: wm us客版 | BE3: 韩语客版 | BF3: ESAL 客版 | BG3: GP 客版 | BH3: WMM 客版 | BI3: 取消UV胶版本 | BJ3: 1L | BK3: 客版 | BL3: 1L | BM3: 韩语客版 | BN3: 3L | BO3: 1L-B版本 | BP3: 3L-B版本 | BQ3: 1L | BR3: 1L-B版本 | BS3: 3L | BT3: 客版 | BU3: 客版 | BV3: 77555SK-S001 | BW3: SK-S002 60PCS | BX3: SK1-S002 30PCS | BY3: SK1-S002 30PCS | BZ3: 圆筒 | CA3: 铜板纸 | CB3: 新版铜版纸 | CC3: 贴纸 | CD3: 圆筒 | CE3: 铜板纸 | CF3: 新铜版纸 | CG3: C版铜版纸 | CH3: 贴纸 | CN3: 已删减实单 | CO3: =AG129+AG130 -> 4467873 | CP3: MA剩余 | CQ3: =CO2-CO3 -> 912127
A4: 45954 | B4: SINGLETON TRADING LTD | C4: 英国 | D4: 4500183147 | E4: CUS PO#12113 | F4: 4500183147-10 | G4: 77555GQ3-S003 | H4: 迷你房子8PCS/GQ3*4/箱 | I4: 14496 | J4: 0 | K4: 32 | L4: =I4/K4 -> 453 | M4: 45992 | N4: 45988 | O4: 指定日期码: DG20251120 | P4: pass | R4: 45954 | S4: 无 | T4: 无 | U4: 日期码格式：ZURU INC(BVI) 标准格式 日期： Packaging Info: 最新MA-3L EAN包装+客版1L PDQ(翻PO#4500164261)；按ZURU标准配比 Remark: *包装日期码按ZURU格式即可, 见指定日期码: DG20251120 (工厂需复核生产地名缩写是否正确) *订单出英国，请注意检查产品及包装应带UKCA图标（14+产品除外），包装显示ZURU UK LTD地址信息，QC部门请查核，如有问题与跟单确认 *订单必须经过ZURU QC验货并且通过后方可出货。 *条码以订单显示为准 ，请安排生产前先核对 ，有问题请提出。 *微塑料需符合欧洲标准，否则不合法规会有客诉产生 | V4: Sandy Shao | W4: 0.8604 | X4: =W4*I4 -> 12472.358 | Z4: 77555GQ3-S003 | AA4: 已入 | AB4: 系统出单 | AC4: =14272+224 -> 14496 | AD4: =AC4-I4 -> 0 | AE4: 无 | AG4: =I4 -> 14496 | AL4: =I4 -> 14496 | BB4: =I4 -> 14496 | BT4: =I4/8 -> 1812 | CQ4: =CQ3-AG4 -> 897631
A5: 45992 | D5: ZMPO251050 | F5: ZMPO251050-20 | G5: 77555-S001 | H5: 20套散件 | I5: 20 | J5: 0 | K5: 24 | L5: =I5/K5 -> 0.83333333 | M5: 46003 | N5: 46006 | R5: 空白箱 | S5: 无 | T5: 无 | U5: Remark：大货最新版本/只需要齐全套散件，. 每款散件不要用纸袋子装，用透明塑胶袋装即可/麻烦用胶袋分装好一套为一袋； 备注：收到样品订单后尽快安排 ，注意样板品质质量要求要高于大货品质要求 ，送货时必须要附带送货单(没有送货单和QC检验合格报告的仓库一律拒绝收货)，请知悉，谢谢！ | Z5: # | AC5: 20 | AD5: =AC5-I5 -> 0 | AH5: =I5 -> 20 | CQ5: =CQ4-AG5 -> 897631
A6: 45952 | B6: DISTRIBUIDORA LIVERPOOL S.A DE C.V. | C6: 墨西哥 | D6: 4500182578 | E6: 62050798 | F6: 4500182578-80 | G6: 77555GQ2-S001 | H6: 迷你房子25pcsGQ2*2/箱 | I6: 900 | J6: 0 | K6: 50 | L6: =I6/K6 -> 18 | M6: 46006 | N6: 46006 | O6: 有第三方监柜 | P6: 自检 | Q6: 1/15 截SI | R6: 45971 | S6: 无 | T6: 11/28 UPC贴纸+进口商贴纸+12/1价标贴纸（客供） | U6: 日期码格式：ZURU INC(BVI) 标准格式 日期：按实际生产日期 Packaging Info: 77555GQ2:MA 多语 EAN 包装+UPC贴纸+进口商贴纸+价标贴纸+箱唛 Remark: 1.此单价格贴纸（ZURU定购).-无位置图，价标贴纸贴于产品背面右上角空白处（不遮挡西班牙语处），如有特殊情况，请重新确认位置图。 2.此单有第三方监柜，不用额外准备备品，会在大货中每款拆1pc，拆了包装的产品会由监装员用客供胶带封好或在外箱上写上""opened by telescope” MOTHER UPC Barcode: | V6: Ava Liang | W6: 0.9003 | X6: =W6*I6 -> 810.27 | Z6: 77555GQ2-S001-3L | AA6: 已入 | AB6: 系统出单 | AC6: 900 | AD6: =AC6-I6 -> 0 | AE6: OK | AG6: =I6 -> 900 | AL6: =I6 -> 900 | BB6: =I6 -> 900 | BS6: =I6/25 -> 36 | CQ6: =CQ5-AG6 -> 896731
A7: 45897 | B7: DISTRIBUIDORA LIVERPOOL S.A DE C.V. | C7: 墨西哥 | D7: 4500177857 | E7: 62007522 | F7: 4500177857-50 | G7: 77555GQ2-S001 | H7: 迷你房子25pcsGQ2*2/箱 | I7: 1800 | J7: 0 | K7: 50 | L7: =I7/K7 -> 36 | M7: 46006 | N7: 46006 | P7: 自检 | Q7: 1/10 截SI | R7: 45951 | S7: 无 | T7: 11/28 UPC贴纸+进口商贴纸+12/1价标贴纸（客供） | U7: 日期码格式：ZURU INC(BVI) 标准格式 日期：按实际生产日期 Packaging Info:77555TQ2:MA 多语EAN包装+UPC贴纸+进口商贴纸+价标贴纸+箱唛 Remark: 1.此单价格贴纸（ZURU定购).-无位置图，价标贴纸贴于产品背面右上角空白处（不遮挡西班牙语处），如有特殊情况，请重新确认位置图。 2.此单有第三方监柜，不用额外准备备品，会在大货中每款拆1pc，拆了包装的产品会由监装员用客供胶带封好或在外箱上写上""opened by telescope” | V7: Ava Liang | W7: 0.9182 | X7: =W7*I7 -> 1652.76 | Z7: 77555GQ2-S001-3L | AA7: 已入 | AB7: 系统出单 | AC7: 1800 | AD7: =AC7-I7 -> 0 | AE7: ok | AG7: =I7 -> 1800 | AL7: =I7 -> 1800 | BB7: =I7 -> 1800 | BS7: =I7/25 -> 72 | CQ7: =CQ6-AG7 -> 894931
A8: 45980 | B8: WALMART INC. | C8: 美国 | D8: 4500186197 | E8: 0959970250 | F8: 4500186197-10 | G8: 77555SLB-S002 | H8: 迷你房子 | I8: 1152 | J8: 0 | K8: 1152 | L8: =I8/K8 -> 1 | M8: 46013 | N8: 46009 | O8: 12/22 BV | P8: 自检 | Q8: 1/5截SI | R8: 翻单 | S8: 有 | T8: 12/1 RFID | U8: 日期码格式：ZURU DGYYYYMMDD CHINA(日期避开周末和法定节假日即可） 日期：按实际生产日期 Packaging Info: 77555SLB-S002 1.包装要求： MA 1L收缩膜+ 客版 收藏指南+客版 1L PDQ，翻单：4500129394 每pcs产品上要贴1张RFID贴纸，贴纸由ZURU提供，贴纸位置请严格按照我们签回的签板； Remark: 77555SLB-S002 1.包装要求： MA 1L收缩膜+ 客版 收藏指南+客版 1L PDQ，翻单：4500129394 每pcs产品上要贴1张RFID贴纸，贴纸由ZURU提供，贴纸位置请严格按照我们签回的签板； 2. 外箱印刷带条码的RFID箱唛：RFID紫色色带+WM Dept.图标+RFID图标+ITF-14条码，四面右下角印刷ZURU logo, ITFF条码只印刷在正唛一面，在加印的时候确保 条形码能扫描出来，外箱侧面任一角落加印："MADE IN CHINA" 字样； 3. 每个slip sheet上面贴一张艾利贴纸（不干胶贴纸）和一张普通贴纸（A4纸），slip sheet打印的普通贴纸的尺寸不能比艾利贴纸小，普通贴纸内容见附件； 4. 在产品上和包装上要有日期码、以及要有MADE IN CHINA和ZURU字样； 5. 产品如有扎带口要剪平，不能刮手。 6. 此单需要验货，请多备料 7. 以slip sheet出货， 77555SLB-S002:1152pcs/96CTN/Slip Sheet | V8: Maggie Xie | W8: 606.22 | X8: =W8*L8 -> 606.22 | Z8: 77555SLB-S002 | AA8: 已入 | AB8: 系统出单 | AC8: 1152 | AD8: =AC8-I8 -> 0 | AE8: ok | AG8: =I8 -> 1152 | AI8: =I8 -> 1152 | BD8: =I8 -> 1152 | BH8: =I8/12 -> 96 | CQ8: =CQ7-AG8 -> 893779
A9: 45980 | B9: WALMART INC. | C9: 美国 | D9: 4500186197 | E9: 0959970260 | F9: 4500186197-20 | G9: 77555SLB-S002 | H9: 迷你房子 | I9: 1152 | J9: 0 | K9: 1152 | L9: =I9/K9 -> 1 | M9: 46013 | N9: 46009 | O9: 12/22 BV | P9: 自检 | Q9: 1/4 截SI | R9: 翻单 | S9: 有 | T9: 12/1 RFID | U9: 日期码格式：ZURU DGYYYYMMDD CHINA(日期避开周末和法定节假日即可） 日期：按实际生产日期 Packaging Info: 77555SLB-S002 1.包装要求： MA 1L收缩膜+ 客版 收藏指南+客版 1L PDQ，翻单：4500129394 每pcs产品上要贴1张RFID贴纸，贴纸由ZURU提供，贴纸位置请严格按照我们签回的签板； Remark: 77555SLB-S002 1.包装要求： MA 1L收缩膜+ 客版 收藏指南+客版 1L PDQ，翻单：4500129394 每pcs产品上要贴1张RFID贴纸，贴纸由ZURU提供，贴纸位置请严格按照我们签回的签板； 2. 外箱印刷带条码的RFID箱唛：RFID紫色色带+WM Dept.图标+RFID图标+ITF-14条码，四面右下角印刷ZURU logo, ITFF条码只印刷在正唛一面，在加印的时候确保 条形码能扫描出来，外箱侧面任一角落加印："MADE IN CHINA" 字样； 3. 每个slip sheet上面贴一张艾利贴纸（不干胶贴纸）和一张普通贴纸（A4纸），slip sheet打印的普通贴纸的尺寸不能比艾利贴纸小，普通贴纸内容见附件； 4. 在产品上和包装上要有日期码、以及要有MADE IN CHINA和ZURU字样； 5. 产品如有扎带口要剪平，不能刮手。 6. 此单需要验货，请多备料 7. 以slip sheet出货， 77555SLB-S002:1152pcs/96CTN/Slip Sheet | V9: Maggie Xie | W9: 606.22 | X9: =W9*L9 -> 606.22 | Z9: 77555SLB-S002 | AA9: 已入 | AB9: 系统出单 | AC9: 1152 | AD9: =AC9-I9 -> 0 | AE9: ok | AG9: =I9 -> 1152 | AI9: =I9 -> 1152 | BD9: =I9 -> 1152 | BH9: =I9/12 -> 96 | CQ9: =CQ8-AG9 -> 892627
A10: 45980 | B10: WALMART INC. | C10: 美国 | D10: 4500186197 | E10: 0959970267 | F10: 4500186197-30 | G10: 77555SLB-S002 | H10: 迷你房子 | I10: 1152 | J10: 0 | K10: 1152 | L10: =I10/K10 -> 1 | M10: 46013 | N10: 46009 | O10: 12/22 BV | P10: 自检 | Q10: 1/9 截SI | R10: 翻单 | S10: 有 | T10: 12/1 RFID | U10: 日期码格式：ZURU DGYYYYMMDD CHINA(日期避开周末和法定节假日即可） 日期：按实际生产日期 Packaging Info: 77555SLB-S002 1.包装要求： MA 1L收缩膜+ 客版 收藏指南+客版 1L PDQ，翻单：4500129394 每pcs产品上要贴1张RFID贴纸，贴纸由ZURU提供，贴纸位置请严格按照我们签回的签板； Remark: 77555SLB-S002 1.包装要求： MA 1L收缩膜+ 客版 收藏指南+客版 1L PDQ，翻单：4500129394 每pcs产品上要贴1张RFID贴纸，贴纸由ZURU提供，贴纸位置请严格按照我们签回的签板； 2. 外箱印刷带条码的RFID箱唛：RFID紫色色带+WM Dept.图标+RFID图标+ITF-14条码，四面右下角印刷ZURU logo, ITFF条码只印刷在正唛一面，在加印的时候确保 条形码能扫描出来，外箱侧面任一角落加印："MADE IN CHINA" 字样； 3. 每个slip sheet上面贴一张艾利贴纸（不干胶贴纸）和一张普通贴纸（A4纸），slip sheet打印的普通贴纸的尺寸不能比艾利贴纸小，普通贴纸内容见附件； 4. 在产品上和包装上要有日期码、以及要有MADE IN CHINA和ZURU字样； 5. 产品如有扎带口要剪平，不能刮手。 6. 此单需要验货，请多备料 7. 以slip sheet出货， 77555SLB-S002:1152pcs/96CTN/Slip Sheet | V10: Maggie Xie | W10: 606.22 | X10: =W10*L10 -> 606.22 | Z10: 77555SLB-S002 | AA10: 已入 | AB10: 系统出单 | AC10: =1140+12 -> 1152 | AD10: =AC10-I10 -> 0 | AE10: ok | AG10: =I10 -> 1152 | AI10: =I10 -> 1152 | BD10: =I10 -> 1152 | BH10: =I10/12 -> 96 | CQ10: =CQ9-AG10 -> 891475
A11: 45980 | B11: WALMART INC. | C11: 美国 | D11: 4500186197 | E11: 0959970272 | F11: 4500186197-50 | G11: 77555SLB-S002 | H11: 迷你房子 | I11: 2304 | J11: 0 | K11: 1152 | L11: =I11/K11 -> 2 | M11: 46013 | N11: 46009 | O11: 12/22 BV | P11: 自检 | Q11: 1/4 截仓 | R11: 翻单 | S11: 有 | T11: 12/1 RFID | U11: 日期码格式：ZURU DGYYYYMMDD CHINA(日期避开周末和法定节假日即可） 日期：按实际生产日期 Packaging Info: 77555SLB-S002 1.包装要求： MA 1L收缩膜+ 客版 收藏指南+客版 1L PDQ，翻单：4500129394 每pcs产品上要贴1张RFID贴纸，贴纸由ZURU提供，贴纸位置请严格按照我们签回的签板； Remark: 77555SLB-S002 1.包装要求： MA 1L收缩膜+ 客版 收藏指南+客版 1L PDQ，翻单：4500129394 每pcs产品上要贴1张RFID贴纸，贴纸由ZURU提供，贴纸位置请严格按照我们签回的签板； 2. 外箱印刷带条码的RFID箱唛：RFID紫色色带+WM Dept.图标+RFID图标+ITF-14条码，四面右下角印刷ZURU logo, ITFF条码只印刷在正唛一面，在加印的时候确保 条形码能扫描出来，外箱侧面任一角落加印："MADE IN CHINA" 字样； 3. 每个slip sheet上面贴一张艾利贴纸（不干胶贴纸）和一张普通贴纸（A4纸），slip sheet打印的普通贴纸的尺寸不能比艾利贴纸小，普通贴纸内容见附件； 4. 在产品上和包装上要有日期码、以及要有MADE IN CHINA和ZURU字样； 5. 产品如有扎带口要剪平，不能刮手。 6. 此单需要验货，请多备料 7. 以slip sheet出货， 77555SLB-S002:1152pcs/96CTN/Slip Sheet | V11: Maggie Xie | W11: 606.215 | X11: =W11*L11 -> 1212.43 | Z11: 77555SLB-S002 | AA11: 已入 | AB11: 系统出单 | AC11: 2304 | AD11: =AC11-I11 -> 0 | AE11: ok | AG11: =I11 -> 2304 | AI11: =I11 -> 2304 | BD11: =I11 -> 2304 | BH11: =I11/12 -> 192 | CQ11: =CQ10-AG11 -> 889171
A12: 45964 | B12: PRENATAL RETAIL GROUP SPAIN S.L. | C12: 西班牙 | D12: 4500183350 | E12: 2000008516 | F12: 4500183350-10 | G12: 77555GQ1-S002 | H12: 迷你房子GQ1/13PCS/箱 | I12: 1248 | J12: 0 | K12: 13 | L12: =I12/K12 -> 96 | M12: 46016 | N12: 46013 | O12: 12/26 客验 | P12: 自检 | Q12: 1/21截SI | R12: 45979 | S12: 无 | T12: 11/26 进口商折叠贴纸+产品贴纸 | U12: 日期码格式：LOT2552 日期： Packaging Info: 1. 77555: 最新MA 3L EAN收缩膜+一张进口商折叠贴纸（含葡萄牙警语+西班牙环保标）+一张葡萄牙语警语贴纸（贴在收藏指南上）+一张产品贴纸+最新MA 3L PDQ Remark: 1. 订单出欧洲国家-西班牙，产品不能含有闪粉/微塑料，请确保所有包装都有西班牙环保标。 2. 客人格式日期码 LOT2552，包装（含收缩膜等）/产品/外箱 请保持一致。 3. 新品需提供2套大货样品给客人，客人会签回一套，验货后验货员需要封1套板寄给香港办公室，请多备料。 4. 需要符合欧洲标准不能含有闪粉和微塑料，否则不合法规会有客诉产生。 5. 硼含量需要符合欧洲标准，否则不合法规会有客诉产生 6. 此客户需要第三方验货，请在约三方验货前必须PASS ZURU验货。 | V12: Christine He | W12: 0.8615 | X12: =W12*I12 -> 1075.152 | Z12: 77555GQ1-S002-3L | AA12: 已入 | AB12: 系统出单 | AC12: 1248 | AD12: =AC12-I12 -> 0 | AE12: ok | AG12: =I12 -> 1248 | AL12: =I12 -> 1248 | BB12: =I12 -> 1248 | BP12: =I12/13 -> 96 | CQ12: =CQ11-AG12 -> 887923
A13: 45979 | B13: PPTOYS PTE LTD (SG) | C13: 新加坡 | D13: 4500184690 | E13: ZU25092601SG | F13: 4500184690-30 | G13: 77555GQ1-S001 | H13: 迷你房子 | I13: 5200 | J13: 0 | K13: 52 | L13: =I13/K13 -> 100 | M13: 46014 | N13: 46013 | P13: pass | Q13: 1/6 截SI | R13: 45979 | S13: 无 | T13: 进口商贴纸翻单4500154572 | U13: 日期码格式：ZURU INC(BVI) 标准格式 日期：按实际生产日期 Packaging Info: MA UPC包装(优先1L)+进口商贴纸,整单的贴纸图稿和位置图翻 77555GQ1-4500154572 Remark: | V13: Emma Wu | W13: 0.8646 | X13: =W13*I13 -> 4495.92 | Z13: 77555GQ1-S001 | AA13: 已入 | AB13: 系统出单 | AC13: 5200 | AD13: =AC13-I13 -> 0 | AE13: ok | AG13: =I13 -> 5200 | AI13: =I13 -> 5200 | BB13: =I13 -> 5200 | BL13: =I13/13 -> 400 | CQ13: =CQ12-AG13 -> 882723
A14: 45979 | B14: GREENBRIER INTERNATIONAL, INC | C14: 美国 | D14: 4500186021 | E14: 00014211505 | F14: 4500186021-10 | G14: 77555GQ1-S002 | H14: 迷你房子GQ1/13PCS/箱 | I14: 175006 | J14: 0 | K14: 13 | L14: =I14/K14 -> 13462 | M14: 46017 | N14: 46013 | P14: pass | Q14: 12/29部分交仓-1/6 部分入仓,1/10 截SI,1/12 截SI | R14: 45979 | S14: 有 | T14: 11/20彩色贴和荧光贴 | U14: 日期码格式：ZURU INC(BVI) 标准格式 日期：按实际生产日期 Packaging Info: Remark: 1.包材：ZURU MA UPC收缩膜（优选1L，如没有1L，请告知是几L） + ZURU MA PDQ （优选1L）+ 如果有说明书或指南，请优选ZURU MA 1L + 客版外箱彩色贴和荧 光贴 。产品本身和产品包装均不含客户价格标签或者价格信息。 2.产品需符合美国最新测试要求，特别是符合CHCC测试要求. 3.出美国，产品和包装上必须有ZURU标准格式的日期码，2者需保持一致并且早于CRD的日期并且不能为周末。 4.UPC ,ZURU MA UPC# # 77555GQ1-S002<(>,<)>客户SKU#423380,UPC#193052064264 <(>,<)>MINI BRANDS HOME SERIES 1 Q2 5.客版外箱唛头，外箱上贴产品彩贴+glow荧光贴纸。贴在外箱正侧相对两面，贴纸尺寸大小可以根据外箱大小调整，贴纸AWS跟单邮件发送，外箱尺寸不能大于目 前SPEC和SAP中的数据。唛头排版格式跟单邮件发送。 6.样板需求：需要11月25前寄出2FULL PDQ带产品的样板给Hailey/Minny转寄美国客户走签样流程。不可延迟。 7.无第三方验货+抽样测试，如客户QC抽中此单做验货，会邮件通知，货物需放huiyou厂做客验。请务必按期在12月26日前完成100%大货生产并入箱，以及完成ZURU QC的验货。 8.确认样被买手批准 + ZURU测试报告被批准 + 以及验货pass后会收到客户的shipping approval和货代的SO，方可出货。不接受任何理由的延迟，会带来很重的lat e罚款。 | V14: Hailey Yu | W14: 0.5298 | X14: =W14*I14 -> 92718.179 | Z14: 77555GQ1-S002 | AA14: 已入 | AB14: 系统出单 | AC14: =42120+53820+30420+42016+6630 -> 175006 | AD14: =AC14-I14 -> 0 | AE14: ok | AG14: =I14 -> 175006 | AI14: =I14 -> 175006 | BB14: =I14 -> 175006 | BL14: =I14/13 -> 13462 | CQ14: =CQ13-AG14 -> 707717
