Workbook

Sheet 77593旧排期
A1: ZURU 5 surprise Dino S6（恐龙系列）生产排期表 #77489 | I1: 1.球壳 转为95mm 2半球壳 ,材料：20%PCR PP +80%PP原料 2.因考虑到某些地区对微塑胶（闪粉，闪粉喷油等）的限制，内部产品会同步做以下变更：---Slime 取消闪粉 3.更改为95mm 球壳后款号更新，请参考以下款号 4.PDQ，SK 刀线均有变化（请留意部分会带有demo）GQ2/SK/SK1有demo | AJ1: 普通款暴龙+卡车 | AL1: 双刺龙 | AR1: 普通款暴龙
I2: 欧洲国家有: (共有43个国家组成) 。芬兰、瑞典、挪威、冰岛、丹麦 法罗群岛(丹)、爱沙尼亚、拉脱维亚、立陶宛、白俄罗斯、俄罗斯、乌克兰、摩尔多瓦、波兰、捷克、斯洛伐克、匈牙利、德国、奥地利、瑞士、列支敦士登、英国、爱尔兰、荷兰、比利时、卢森堡、法国、摩纳哥、罗马尼亚、保加利亚、塞尔维亚、马其顿、阿尔巴尼亚、希腊、斯洛文尼亚、克罗地亚、波斯尼亚和墨塞哥维那、意大利、梵蒂冈、圣马力诺、马耳他、西班牙、葡萄牙、安道尔。 | AG2: 95MM收縮膜 | AI2: 95MM收藏指南 | AJ2: SK展示架 | AK2: 带底座 | AL2: 77593GQ2 | AN2: 77593GQ1 | AP2: 77593GQ5 | AQ2: SK1展示架 | AT2: 77614 2PK圆筒 | AW2: WM GQ4 | AX2: 口水胶 | AZ2: MA比例 | BA2: 0.125 | BB2: 0.10416667 | BC2: 0.020833333 | BD2: 0.125 | BE2: 0.125 | BF2: 0.125 | BG2: 0.125 | BH2: 0.125 | BI2: 0.125 | BJ2: MA | BK2: ='77489 77593生产MA'!E15-BA51-BA53-'77489 77593生产MA'!I29 -> 12327.625 | BL2: ='77489 77593生产MA'!F15-BB51-BB53-'77489 77593生产MA'!I30-'77489 77593生产MA'!I31-'77489 77593生产MA'!J33-'77489 77593生产MA'!K33-'77489 77593生产MA'!J35-'77489 77593生产MA'!K35 -> 10449.521 | BM2: ='77489 77593生产MA'!G15-BD53-BD51 -> 12340.625 | BN2: ='77489 77593生产MA'!H15-BC53-BC51 -> 1965.1042 | BO2: ='77489 77593生产MA'!I15-BE51-BE53-'77489 77593生产MA'!J34-'77489 77593生产MA'!K34 -> 10462.625 | BP2: ='77489 77593生产MA'!J15-BF51-BF53 -> 12340.625 | BQ2: ='77489 77593生产MA'!K15-BG51-BG53 -> 12340.625 | BR2: ='77489 77593生产MA'!L15-BH51-BH53-'77489 77593生产MA'!K32-'77489 77593生产MA'!J32 -> 12740.625 | BS2: ='77489 77593生产MA'!M15-BI51-BI53 -> 12340.625
A3: 香港接单日期 | B3: 第三方客户名称 | C3: 走货国家 | D3: ZURU PO NO# | E3: 第三方客户 PO NO# | F3: SKU | G3: ITEM# | H3: 中文名 | I3: PO数量 (pcs) | J3: 内箱装箱数量(pcs) | K3: 外箱装箱数量(pcs) | L3: 总箱数 | M3: 客PO期 | N3: 验货期 | O3: 第三方验货期 | P3: 验货结果 | Q3: 船期 | R3: 箱唛资料(收到日期) | S3: 外箱贴纸 | T3: 客供贴纸AI(收到日期) | U3: 备注 | V3: ZURU 跟单 | W3: 单价USD | X3: 金额USD | Y3: 发票号 | Z3: 已送情况 | AA3: 欠数 | AB3: 贴纸 情况 | AC3: 是否入系统 | AD3: 系统货号 | AE3: 是否入系统 | AF3: 77593-95mm球壳 | AG3: MA 1L | AH3: MA 3L | AI3: MA 5L | AJ3: MA 1L | AL3: MA 1L | AM3: MA 3L | AN3: MA 1L | AO3: MA 3L | AP3: FD客版 | AQ3: MA 3L | AR3: MA 1L | AS3: 带底座 | AT3: 圆筒 | AU3: 彩纸 3L | AV3: 彩纸 1L | AW3: 客版 | AX3: 有硼无闪粉 | AY3: 无硼无闪粉 | BA3: Pterosaur 翼龙 | BB3: T-Rex 暴龙 | BC3: T-Rex (Rare) 暴龙（特别款） | BD3: Stegosaurus 剑龙 | BE3: Dilophosaurus 双棘龙 | BF3: Brontosaurus 雷龙 | BG3: Amargasaurus 阿玛加龙 | BH3: Truck 卡车 | BI3: Armed Helicoper 武装飞机 | BK3: Pterosaur 翼龙 | BL3: T-Rex 暴龙 | BM3: Stegosaurus 剑龙 | BN3: T-Rex (Rare) 暴龙（特别款） | BO3: Dilophosaurus 双棘龙 | BP3: Brontosaurus 雷龙 | BQ3: Amargasaurus 阿玛加龙 | BR3: Truck 卡车 | BS3: Armed Helicoper 武装飞机
A4: 45323 | B4: ZURU | C4: 库有 | D4: ZMPO24101 | G4: 77593SK-S002 | H4: S4迷你恐龙展示架带球 | I4: 480 | J4: 0 | K4: 60 | L4: =I4/K4 -> 8 | M4: 45359 | N4: 45355 | P4: 自检 | R4: 45323 | S4: 无 | T4: 无 | U4: 大货最新版本/产品请按大货比例入展架/箱唛参照邮件附件 | Y4: 97435-1.8 | Z4: 480 | AA4: =Z4-I4 -> 0 | AD4: 77593SK-S002 | AE4: 已入 | AF4: =I4 -> 480 | AG4: =AF4 -> 480 | AI4: =AG4 -> 480 | AJ4: =L4 -> 8 | AK4: =AJ4 -> 8 | AX4: =AF4 -> 480 | BA4: =I4*$BA$2 -> 60 | BB4: =I4*$BB$2 -> 50 | BC4: =I4*$BC$2 -> 10 | BD4: =I4*$BD$2 -> 60 | BE4: =I4*$BE$2 -> 60 | BF4: =I4*$BF$2 -> 60 | BG4: =I4*$BG$2 -> 60 | BH4: =I4*$BH$2 -> 60 | BI4: =I4*$BI$2 -> 60 | BK4: =BK2-BA4 -> 12267.625 | BL4: =BL2-BB4 -> 10399.521 | BM4: =BM2-BD4 -> 12280.625 | BN4: =BN2-BC4 -> 1955.1042 | BO4: =BO2-BE4 -> 10402.625 | BP4: =BP2-BF4 -> 12280.625 | BQ4: =BQ2-BG4 -> 12280.625 | BR4: =BR2-BH4 -> 12680.625 | BS4: =BS2-BI4 -> 12280.625
A5: 45323 | B5: ZURU | C5: 库有 | D5: ZMPO24101 | G5: 77593SK1-S002 | H5: S4迷你恐龙展示架带球 | I5: 240 | J5: 0 | K5: 30 | L5: =I5/K5 -> 8 | M5: 45359 | N5: 45355 | P5: 自检 | R5: 45323 | S5: 无 | T5: 无 | U5: 大货最新版本/产品请按大货比例入展架/箱唛参照邮件附件 | Y5: 97435-1.8 | Z5: 240 | AA5: =Z5-I5 -> 0 | AD5: 77593SK1-S002 | AE5: 已入 | AF5: =I5 -> 240 | AQ5: =L5 -> 8 | AS5: =AQ5 -> 8 | AX5: =AF5 -> 240 | BA5: =I5*$BA$2 -> 30 | BB5: =I5*$BB$2 -> 25 | BC5: =I5*$BC$2 -> 5 | BD5: =I5*$BD$2 -> 30 | BE5: =I5*$BE$2 -> 30 | BF5: =I5*$BF$2 -> 30 | BG5: =I5*$BG$2 -> 30 | BH5: =I5*$BH$2 -> 30 | BI5: =I5*$BI$2 -> 30 | BK5: =BK4-BA5 -> 12237.625 | BL5: =BL4-BB5 -> 10374.521 | BM5: =BM4-BD5 -> 12250.625 | BN5: =BN4-BC5 -> 1950.1042 | BO5: =BO4-BE5 -> 10372.625 | BP5: =BP4-BF5 -> 12250.625 | BQ5: =BQ4-BG5 -> 12250.625 | BR5: =BR4-BH5 -> 12650.625 | BS5: =BS4-BI5 -> 12250.625
A6: 45463 | B6: DM LLC | C6: 俄罗斯 | D6: 4500137881 | E6: Ural | F6: 4500137881-110 | G6: 77593GQ1-S001 | H6: S4迷你恐龙13PCS/GQ1*4 | I6: 312 | J6: 0 | K6: 52 | L6: =I6/K6 -> 6 | M6: 45498 | N6: 45502 | O6: 彩卡/收缩膜/PDQ/外箱不要打ZURU标准日期码！ | P6: 自检 | Q6: 已有计划船期等SO出货 | R6: 45469 | S6: 无 | T6: 7/8进口商贴纸+EAN条码贴纸 | U6: 日期码格式：彩卡/收缩膜/PDQ/外箱不要打ZURU标准日期码！ 日期： Packaging Info: 77593GQ1: 优先1L MA 收缩膜+进口商贴纸+EAN条码贴纸; MA PDQ/指南/说明书(如有); 注意 ：彩卡/收缩膜/PDQ/外箱不要打ZURU标准日期码！！ Remark: 1. 出 Bekasovo 2和Ural; | V6: Ann Zhang | W6: 0.9801 | X6: =W6*I6 -> 305.7912 | Y6: 88869-1.4 | Z6: 312 | AA6: =Z6-I6 -> 0 | AD6: 77593GQ1-S001 | AE6: 已入 | AF6: =I6 -> 312 | AG6: =AF6 -> 312 | AI6: =AG6 -> 312 | AN6: =I6/13 -> 24 | AX6: =I6 -> 312 | BA6: =I6*$BA$2 -> 39 | BB6: =I6*$BB$2 -> 32.5 | BC6: =I6*$BC$2 -> 6.5 | BD6: =I6*$BD$2 -> 39 | BE6: =I6*$BE$2 -> 39 | BF6: =I6*$BF$2 -> 39 | BG6: =I6*$BG$2 -> 39 | BH6: =I6*$BH$2 -> 39 | BI6: =I6*$BI$2 -> 39 | BK6: =BK5-BA6 -> 12198.625 | BL6: =BL5-BB6 -> 10342.021 | BM6: =BM5-BD6 -> 12211.625 | BN6: =BN5-BC6 -> 1943.6042 | BO6: =BO5-BE6 -> 10333.625 | BP6: =BP5-BF6 -> 12211.625 | BQ6: =BQ5-BG6 -> 12211.625 | BR6: =BR5-BH6 -> 12611.625 | BS6: =BS5-BI6 -> 12211.625
A7: 45564 | B7: DM LLC | C7: 俄罗斯 | D7: 4500163959 | E7: 包装要求参考4 500146630，出 Bekasovo 2 | F7: 4500146630-10 | G7: 77593GQ1-S001 | H7: S4迷你恐龙13PCS/GQ1*4 | I7: 676 | J7: 0 | K7: 52 | L7: =I7/K7 -> 13 | M7: 45667 | N7: 45663 | O7: 彩卡/收缩膜/PDQ/外箱不要打ZURU标准日期码！ | P7: pass | Q7: 4/28 截SI | R7: 45574 | S7: 无 | T7: 进口商贴纸+EAN条码贴纸翻单146595 | U7: 日期码格式：外包装/外箱不要打ZURU标准日期码 日期： Packaging Info: 取代4500150271/4500157991/4500146630/4500159461/4500158543中 对应的款 ; 包装要求参考4500150271/4500157991/4500146630/4500159461/4500158543 Remark: | V7: Ann Zhang | W7: 0.9638 | X7: =W7*I7 -> 651.5288 | Y7: 94862-4.28 | Z7: 676 | AA7: =Z7-I7 -> 0 | AD7: 77593GQ1-S001 | AE7: 已入 | AF7: =I7 -> 676 | AG7: =AF7 -> 676 | AI7: =AG7 -> 676 | AN7: =I7/13 -> 52 | AX7: =I7 -> 676 | BA7: =I7*$BA$2 -> 84.5 | BB7: =I7*$BB$2 -> 70.416667 | BC7: =I7*$BC$2 -> 14.083333 | BD7: =I7*$BD$2 -> 84.5 | BE7: =I7*$BE$2 -> 84.5 | BF7: =I7*$BF$2 -> 84.5 | BG7: =I7*$BG$2 -> 84.5 | BH7: =I7*$BH$2 -> 84.5 | BI7: =I7*$BI$2 -> 84.5 | BK7: =BK6-BA7 -> 12114.125 | BL7: =BL6-BB7 -> 10271.604 | BM7: =BM6-BD7 -> 12127.125 | BN7: =BN6-BC7 -> 1929.5208 | BO7: =BO6-BE7 -> 10249.125 | BP7: =BP6-BF7 -> 12127.125 | BQ7: =BQ6-BG7 -> 12127.125 | BR7: =BR6-BH7 -> 12527.125 | BS7: =BS6-BI7 -> 12127.125
A8: 45541 | B8: T.J.MORRIS LTD | C8: 英国 | D8: 4500144734 | E8: 11039548 | F8: 4500144734-20 | G8: 77593GQ2-S002 | H8: S4迷你恐龙24PCS入GQ2*2/箱 | I8: 9456 | J8: 0 | K8: 24 | L8: =I8/K8 -> 394 | M8: 45656 | N8: 45652 | P8: pass | Q8: 1/4 截单 | R8: 45614 | S8: 无 | T8: 无 | U8: 日期码格式：ZURU INC(BVI) 标准格式 日期：按实际生产日期 Packaging Info: 2.77593GQ2: MA 1L UPC包装，UPC#193052066206请先检查条码是否正确再安排做货，如有问题请告知 5.配比都跟MA配比 Remark: 1.产品及包装需要印UKCA图标，包装需要有ZURU UK LTD/ZURU France地址信息，QC同事请核查，如有问题与跟单确认。 2. 需要符合欧洲标准不能含有闪粉和微塑料，否则不和法规会有客诉产生 | V8: Sheba Ye | W8: 0.9854 | X8: =W8*I8 -> 9317.9424 | Y8: 88923-1.7 | Z8: =9432+24 -> 9456 | AA8: =Z8-I8 -> 0 | AD8: 77593GQ2-S002 | AE8: 已入 | AF8: =I8 -> 9456 | AG8: =I8 -> 9456 | AI8: =I8 -> 9456 | AL8: =I8/24 -> 394 | AX8: =I8 -> 9456 | BA8: =I8*$BA$2 -> 1182 | BB8: =I8*$BB$2 -> 985 | BC8: =I8*$BC$2 -> 197 | BD8: =I8*$BD$2 -> 1182 | BE8: =I8*$BE$2 -> 1182 | BF8: =I8*$BF$2 -> 1182 | BG8: =I8*$BG$2 -> 1182 | BH8: =I8*$BH$2 -> 1182 | BI8: =I8*$BI$2 -> 1182 | BK8: =BK7-BA8 -> 10932.125 | BL8: =BL7-BB8 -> 9286.6042 | BM8: =BM7-BD8 -> 10945.125 | BN8: =BN7-BC8 -> 1732.5208 | BO8: =BO7-BE8 -> 9067.125 | BP8: =BP7-BF8 -> 10945.125 | BQ8: =BQ7-BG8 -> 10945.125 | BR8: =BR7-BH8 -> 11345.125 | BS8: =BS7-BI8 -> 10945.125
A9: 45604 | B9: Inventive Toys | C9: 俄罗斯联邦 | D9: 4500150836 | F9: 4500150836-10 | G9: 77593GQ1-S001 | H9: S4迷你恐龙13PCS/GQ1*4 | I9: 2028 | J9: 0 | K9: 52 | L9: =I9/K9 -> 39 | M9: 45660 | N9: 45656 | O9: 外包装 (指: 收缩膜/彩卡/铝箔袋/挂卡/PDQ) /外箱不要打ZURU标准日期码 | P9: 自检 | Q9: 1/9 装柜 | R9: 11、26 | S9: 无 | T9: 12/9 进口商贴纸+ EAN条码贴纸 | U9: 日期码格式：外包装/外箱不要打ZURU标准日期码 日期： Packaging Info: 注意 ：外包装 (指: 收缩膜/彩卡/铝箔袋/挂卡/PDQ) /外箱不要打ZURU标准日期码！胶件可以打日期码。 外包装（包括收缩膜/彩卡/PDQ）都不能含Instagram and facebook logo等社交logo; 1L MA 收缩膜 或者彩卡+ 进口商贴纸； MA PDQ + EAN条码贴纸 ， MA指南/说明书（如有）; Remark: 标准配比 ；整单货期2025年1月3 | V9: Ann Zhang | W9: 0.963 | X9: =W9*I9 -> 1952.964 | Y9: 94071-1.16 | Z9: 2028 | AA9: =Z9-I9 -> 0 | AD9: 77593GQ1-S001 | AE9: 已入 | AF9: =I9 -> 2028 | AG9: =AF9 -> 2028 | AI9: =AG9 -> 2028 | AN9: =I9/13 -> 156 | AX9: =I9 -> 2028 | BA9: =I9*$BA$2 -> 253.5 | BB9: =I9*$BB$2 -> 211.25 | BC9: =I9*$BC$2 -> 42.25 | BD9: =I9*$BD$2 -> 253.5 | BE9: =I9*$BE$2 -> 253.5 | BF9: =I9*$BF$2 -> 253.5 | BG9: =I9*$BG$2 -> 253.5 | BH9: =I9*$BH$2 -> 253.5 | BI9: =I9*$BI$2 -> 253.5 | BK9: =BK8-BA9 -> 10678.625 | BL9: =BL8-BB9 -> 9075.3542 | BM9: =BM8-BD9 -> 10691.625 | BN9: =BN8-BC9 -> 1690.2708 | BO9: =BO8-BE9 -> 8813.625 | BP9: =BP8-BF9 -> 10691.625 | BQ9: =BQ8-BG9 -> 10691.625 | BR9: =BR8-BH9 -> 11091.625 | BS9: =BS8-BI9 -> 10691.625
A10: 45608 | B10: FAMILY DOLLAR SERVICES, INC, | C10: 美国 | D10: 4500151082 | E10: 30583154 | F10: 4500151082-10 | G10: 77593GQ5-S001 | H10: S4迷你恐龙8PCS/GQ5 | I10: 6056 | J10: 0 | K10: 8 | L10: =I10/K10 -> 757 | M10: 45660 | N10: 45656 | O10: 指定日期码:DG20241220 | P10: pass | Q10: 1/14 截SI | R10: 45609 | S10: 有 | T10: 外箱彩贴翻单PO#4500135943 | U10: 日期码格式：ZURU INC(BVI) 标准格式 日期：2024-12-20 Packaging Info: 1）客版PDQ(翻单PO#4500135943), 最新版ZURU MA UPC包装(去掉社交媒体标志，优先1L)，出口美国。如有说明书请使用ZURU MA说明书，优先放1L英语。8pcs/PDQ /CTN。 2）ZURU标准日期码格式：工厂城市缩写+生产年月日，此单指定日期码:DG20241220 3）外箱正侧唛两面都需粘贴产品彩色贴纸，外箱彩贴每箱两张，客版外箱彩贴翻单PO#4500135943。如侧唛位置放不下彩贴和唛头信息，可改为放两个正唛。无论 是正唛+侧唛或者是两个正唛，唛头信息和彩贴需放在同一个面。箱唛需排版给跟单确认。 4) 每个球贴一张客供防盗贴，贴在收缩膜上，防盗贴由跟单采购，供应商直接发货到工厂。防盗贴贴纸位置与PO#4500144246一致。 Remark: 客户PO#30583154 客户SKU#1003737 1）Item#77593GQ5- S001 2）此单无第三方验货+抽样测试，ZURU QC验货PASS后，跟单得到客户的approval之后方可安排出货 3）大货外箱材积绝对不可大于下述数据，材积只接受3%的变小；重量正负不得超过以下列出数据的5%，接受外箱以印章方式印上实际毛重。 大货外箱尺寸请保持：21.0 x 20.6 x 21.2 cm (即8.27 x8.11 x 8.35 inch)，材积必须不能大于0.3249CubeFeet（即0.0092SSCBM); 外箱毛重 2.6LBS（即1.20 KG S） 4）大货配比： #77593GQ5-S001 S001-5 SURPRISE-DINO STRIKE-SERIES 6-CAPSULE,2Facing8pcs/Gravity PDQ,8pcs/1PDQ/CTN。 UPC:193052066206 8pcs/PDQ/CTN,2W*2D*2H=8PCS/PDQ, Contain Slime,with borax; Capsule size: 3.74 inch x 3.74 inch x 3.74 inch 5）客户Family Dollar不允许少数出货，必须按照PO上的数量出货，也不允许延期，否则会有罚款。 6）客户要求:"产品和包装不能含有PFAS 物质以及1,4 dioxane" ，请确保产品可以过美国标准测试。 | V10: Jenny Liu/Andro | W10: 1.0363 | X10: =L10*W10 -> 784.4791 | Y10: 94042-1.15 | Z10: 6056 | AA10: =Z10-I10 -> 0 | AD10: 77593GQ5-S001 | AE10: 已入 | AF10: =I10 -> 6056 | AG10: =AF10 -> 6056 | AI10: =AG10 -> 6056 | AP10: =I10/8 -> 757 | AX10: =I10 -> 6056 | BA10: =I10*$BA$2 -> 757 | BB10: =I10*$BB$2 -> 630.83333 | BC10: =I10*$BC$2 -> 126.16667 | BD10: =I10*$BD$2 -> 757 | BE10: =I10*$BE$2 -> 757 | BF10: =I10*$BF$2 -> 757 | BG10: =I10*$BG$2 -> 757 | BH10: =I10*$BH$2 -> 757 | BI10: =I10*$BI$2 -> 757 | BK10: =BK9-BA10 -> 9921.625 | BL10: =BL9-BB10 -> 8444.5208 | BM10: =BM9-BD10 -> 9934.625 | BN10: =BN9-BC10 -> 1564.1042 | BO10: =BO9-BE10 -> 8056.625 | BP10: =BP9-BF10 -> 9934.625 | BQ10: =BQ9-BG10 -> 9934.625 | BR10: =BR9-BH10 -> 10334.625 | BS10: =BS9-BI10 -> 9934.625
A11: 45614 | B11: JSC 􀂫Grand-Trade􀂻 | C11: 俄罗斯联邦 | D11: 4500151353 | E11: PGT-658704 | F11: 4500151353-20 | G11: 77593GQ1-S002 | H11: S4迷你恐龙13PCS/GQ1*4 | I11: 1313 | J11: 0 | K11: 13 | L11: =I11/K11 -> 101 | M11: 45660 | N11: 45656 | P11: pass | Q11: 1/6 截SI | R11: 45614 | S11: 有 | T11: 12/2进口商贴纸+ EAN条码贴纸+背景贴纸+外箱贴纸+空白贴纸 | U11: 日期码格式：ZURU INC(BVI) 标准格式 日期：按实际生产日期 Packaging Info: 注意： 此客户不允许包装/产品/PDQ 上显示recycled material / plastic 字眼， 如有请告知跟单需要加贴纸覆盖； 1.77593GQ1 ： 1L MA 收缩膜+ 进口商贴纸(覆盖内膜上的recycled plastic)+ EAN 条码贴纸， 1L MA PDQ+ 背景贴纸覆盖recycled Plastic ， MA 指南 + 空白贴纸（覆盖指南上的recycled plastic信息） 2. 需要安排loading inspection (装柜现场监柜)； 3. 外箱侧唛右上角各一张贴纸（一共2张） ； Remark: 标准配比，整单货期2025年1月3 . | V11: Ann Zhang | W11: 0.9839 | X11: =W11*I11 -> 1291.8607 | Y11: 88957-1.9 | Z11: 1313 | AA11: =Z11-I11 -> 0 | AD11: 77593GQ1-S002 | AE11: 已入 | AF11: =I11 -> 1313 | AG11: =AF11 -> 1313 | AI11: =I11 -> 1313 | AN11: =I11/13 -> 101 | AX11: =I11 -> 1313 | BA11: =I11*$BA$2 -> 164.125 | BB11: =I11*$BB$2 -> 136.77083 | BC11: =I11*$BC$2 -> 27.354167 | BD11: =I11*$BD$2 -> 164.125 | BE11: =I11*$BE$2 -> 164.125 | BF11: =I11*$BF$2 -> 164.125 | BG11: =I11*$BG$2 -> 164.125 | BH11: =I11*$BH$2 -> 164.125 | BI11: =I11*$BI$2 -> 164.125 | BK11: =BK10-BA11 -> 9757.5 | BL11: =BL10-BB11 -> 8307.75 | BM11: =BM10-BD11 -> 9770.5 | BN11: =BN10-BC11 -> 1536.75 | BO11: =BO10-BE11 -> 7892.5 | BP11: =BP10-BF11 -> 9770.5 | BQ11: =BQ10-BG11 -> 9770.5 | BR11: =BR10-BH11 -> 10170.5 | BS11: =BS10-BI11 -> 9770.5
A12: 45617 | B12: Importadora Sudamericana & Generac | C12: 阿根廷 | D12: 4500151881 | E12: LEGAJO 4117 | F12: 4500151881-20 | G12: 77593GQ5-S001 | H12: S4迷你恐龙8PCS/GQ5 | I12: 6000 | J12: 0 | K12: 8 | L12: =I12/K12 -> 750 | M12: 45660 | N12: 45656 | P12: pass | Q12: 1/7 截SI | R12: 45629 | S12: 无 | T12: 12/12 进口商贴纸 | U12: 日期码格式：ZURU INC(BVI) 标准格式 日期：按实际生产日期 Packaging Info: MA 1L包装+进口商贴纸+箱唛 | V12: Ava Liang | W12: 0.9957 | X12: =L12*W12 -> 746.775 | Y12: 88870-1.4 | Z12: 6000 | AA12: =Z12-I12 -> 0 | AD12: 77593GQ5-S001 | AE12: 已入 | AF12: =I12 -> 6000 | AG12: =AF12 -> 6000 | AI12: =AG12 -> 6000 | AP12: =I12/8 -> 750 | AX12: =I12 -> 6000 | BA12: =I12*$BA$2 -> 750 | BB12: =I12*$BB$2 -> 625 | BC12: =I12*$BC$2 -> 125 | BD12: =I12*$BD$2 -> 750 | BE12: =I12*$BE$2 -> 750 | BF12: =I12*$BF$2 -> 750 | BG12: =I12*$BG$2 -> 750 | BH12: =I12*$BH$2 -> 750 | BI12: =I12*$BI$2 -> 750 | BK12: =BK11-BA12 -> 9007.5 | BL12: =BL11-BB12 -> 7682.75 | BM12: =BM11-BD12 -> 9020.5 | BN12: =BN11-BC12 -> 1411.75 | BO12: =BO11-BE12 -> 7142.5 | BP12: =BP11-BF12 -> 9020.5 | BQ12: =BQ11-BG12 -> 9020.5 | BR12: =BR11-BH12 -> 9420.5 | BS12: =BS11-BI12 -> 9020.5
A13: 45603 | B13: ROSS PROCUREMENT.INC | C13: 美国 | D13: 4500150464 | E13: 60190494 | F13: 4500150464-10 | G13: 77614-S001 | H13: S4迷你恐龙2PK圆筒*12/箱 | I13: 1008 | J13: 0 | K13: 12 | L13: =I13/K13 -> 84 | M13: 45672 | N13: 45667 | P13: 自检 | Q13: 3/7 截SI | R13: 45610 | S13: 无 | T13: 12/19 客供价格贴纸 | U13: 日期码格式：ZURU INC(BVI) 标准格式 日期：按实际生产日期 Packaging Info: 1.ZURU MA UPC 收缩膜+客版铜版纸+PVC桶 + 客供价格贴纸，出口美国 , 优先使用MA 1L 最新版本 。 Remark: 1.ZURU MA UPC 收缩膜+客版铜版纸+PVC桶 + 客供价格贴纸，出口美国 , 优先使用MA 1L 最新版本 。 2.价格贴纸位于包装正面右下角，不挡住重要信息即可，可适当调整 ，价格贴纸由跟单提供。 3.标准日期码格式，产品和包装必须有日期码 。 4.同个产品同个货期不可出现不同的包装。 5. PVC 桶中球不能出现完全相同的ASSORTMENT ， 即同一个PVC 中球里的ASSORTMENT 需要不同。 以免消费者失望。 6.PVC 桶上加上 MINI BRANDS 的LOGO 贴纸 （ ZURU 统一要求的） 7.收缩膜可使用标版带UPC条码MA，无需白色贴纸覆盖。 | V13: Sophia Zhou | W13: 2.2427 | X13: =W13*I13 -> 2260.6416 | Y13: 94486-3.7 | Z13: 1008 | AA13: =Z13-I13 -> 0 | AD13: 77614-S001-1 | AE13: 已入 | AF13: =I13*2 -> 2016 | AG13: =AF13 -> 2016 | AI13: =AF13 -> 2016 | AT13: =I13 -> 1008 | AU13: =AT13 -> 1008 | AX13: =I13*2 -> 2016 | BA13: =I13*$BA$2*2 -> 252 | BB13: =I13*$BB$2*2 -> 210 | BC13: =I13*$BC$2*2 -> 42 | BD13: =I13*$BD$2*2 -> 252 | BE13: =I13*$BE$2*2 -> 252 | BF13: =I13*$BF$2*2 -> 252 | BG13: =I13*$BG$2*2 -> 252 | BH13: =I13*$BH$2*2 -> 252 | BI13: =I13*$BI$2*2 -> 252 | BK13: =BK12-BA13 -> 8755.5 | BL13: =BL12-BB13 -> 7472.75 | BM13: =BM12-BD13 -> 8768.5 | BN13: =BN12-BC13 -> 1369.75 | BO13: =BO12-BE13 -> 6890.5 | BP13: =BP12-BF13 -> 8768.5 | BQ13: =BQ12-BG13 -> 8768.5 | BR13: =BR12-BH13 -> 9168.5 | BS13: =BS12-BI13 -> 8768.5
A14: 45651 | B14: TOYS "R" US – JAPAN, LTD | C14: 日本 | D14: 4500154748 | E14: 47:0003113610 | F14: 4500154748-10 | G14: 77593GQ2-S001 | H14: S4迷你恐龙24PCS入GQ2*2/箱-干燥剂 | I14: 4800 | J14: 0 | K14: 48 | L14: =I14/K14 -> 100 | M14: 45716 | N14: 45712 | P14: pass | Q14: 3/7 截SI | R14: 45652 | S14: 无 | T14: 1/21日语贴纸 | U14: 日期码格式：ZURU INC(BVI) 标准格式 日期：按实际生产日期 Packaging Info: MA 1L PKG+1张日语贴纸（新稿）， MA 1L PDQ， MA 5L收藏指南 Remark: 出日本首单需安排样板测试， 请按邮件要求先寄出MA包装的样板做测试。 大货的产品内容和MA包装版本以及产品品质需严格跟到寄出的测试版。 | V14: Doris Shou | W14: 0.9808 | X14: =W14*I14 -> 4707.84 | Y14: 94461-3.6 | Z14: 4800 | AA14: =Z14-I14 -> 0 | AD14: 77593GQ2-S001 | AE14: 已入 | AF14: =I14 -> 4800 | AG14: =I14 -> 4800 | AI14: =I14 -> 4800 | AL14: =I14/24 -> 200 | AX14: =I14 -> 4800 | BA14: =I14*$BA$2 -> 600 | BB14: =I14*$BB$2 -> 500 | BC14: =I14*$BC$2 -> 100 | BD14: =I14*$BD$2 -> 600 | BE14: =I14*$BE$2 -> 600 | BF14: =I14*$BF$2 -> 600 | BG14: =I14*$BG$2 -> 600 | BH14: =I14*$BH$2 -> 600 | BI14: =I14*$BI$2 -> 600 | BK14: =BK13-BA14 -> 8155.5 | BL14: =BL13-BB14 -> 6972.75 | BM14: =BM13-BD14 -> 8168.5 | BN14: =BN13-BC14 -> 1269.75 | BO14: =BO13-BE14 -> 6290.5 | BP14: =BP13-BF14 -> 8168.5 | BQ14: =BQ13-BG14 -> 8168.5 | BR14: =BR13-BH14 -> 8568.5 | BS14: =BS13-BI14 -> 8168.5
A15: 45696 | B15: Importadora Sudamericana & Generac | C15: 阿根廷 | D15: 4500156986 | F15: 4500156986-20 | G15: 77593GQ5-S001 | H15: S4迷你恐龙8PCS/GQ5 | I15: 9600 | J15: 0 | K15: 8 | L15: =I15/K15 -> 1200 | M15: 45736 | N15: 45733 | P15: PASS | Q15: 3/24 截SI | R15: 45707 | S15: 无 | T15: 3/3 进口商贴纸 | U15: 日期码格式：ZURU INC(BVI) 标准格式 日期：按实际生产日期 Packaging Info: MA 3LEAN包装+进口商贴纸+UPC贴纸+箱唛，进口商贴纸翻单PO4500151881 77593GQ5 PDQ 翻单PO 4500151082,77595GQ3 PDQ 翻单 PO 4500144251 Remark: | V15: Ava Liang | W15: 0.9957 | X15: =W15*I15 -> 9558.72 | Y15: 94631-3.25 | Z15: =4792+4800+8 -> 9600 | AA15: =Z15-I15 -> 0 | AD15: 77593GQ5-S001-3L | AE15: 已入 | AF15: =I15 -> 9600 | AH15: =I15 -> 9600 | AI15: =I15 -> 9600 | AP15: =I15/8 -> 1200 | AX15: =I15 -> 9600 | BA15: =I15*$BA$2 -> 1200 | BB15: =I15*$BB$2 -> 1000 | BC15: =I15*$BC$2 -> 200 | BD15: =I15*$BD$2 -> 1200 | BE15: =I15*$BE$2 -> 1200 | BF15: =I15*$BF$2 -> 1200 | BG15: =I15*$BG$2 -> 1200 | BH15: =I15*$BH$2 -> 1200 | BI15: =I15*$BI$2 -> 1200 | BK15: =BK14-BA15 -> 6955.5 | BL15: =BL14-BB15 -> 5972.75 | BM15: =BM14-BD15 -> 6968.5 | BN15: =BN14-BC15 -> 1069.75 | BO15: =BO14-BE15 -> 5090.5 | BP15: =BP14-BF15 -> 6968.5 | BQ15: =BQ14-BG15 -> 6968.5 | BR15: =BR14-BH15 -> 7368.5 | BS15: =BS14-BI15 -> 6968.5
A16: 45702 | B16: Hermanex Europe BV | C16: 新西兰 | D16: 4500157700 | F16: 4500157700-10 | G16: 77593SK1-S002 | H16: S4迷你恐龙展示架带球 | I16: 6570 | J16: 0 | K16: 30 | L16: =I16/K16 -> 219 | M16: 45741 | N16: 45737 | P16: pass | Q16: 3/27 截SI | R16: 45706 | S16: 无 | T16: 2/18 NL警语贴纸 | U16: 日期码格式：ZURU INC(BVI) 标准格式 日期：按实际生产日期 Packaging Info: 77593SK1: MA 3L A版本 EAN 收缩膜+NL警语贴纸(含FR, ES环保LOGO)，MA 5L Slime Poly Bag+NL警语贴纸，MA 5L收藏指南，MA说明书，MA 袋子，MA 3L A版展架( 消耗Slow Moving库存，With Base) Remark: | V16: Eddie Huang | W16: 36.2614 | X16: =W16*L16 -> 7941.2466 | Y16: 94652-3.27 | Z16: 6570 | AA16: =Z16-I16 -> 0 | AD16: 77593SK1-S002-3L | AE16: 已入 | AF16: =I16 -> 6570 | AH16: =I16 -> 6570 | AI16: =I16 -> 6570 | AQ16: =I16/30 -> 219 | AS16: =AQ16 -> 219 | AX16: =I16 -> 6570 | BA16: =I16*$BA$2 -> 821.25 | BB16: =I16*$BB$2 -> 684.375 | BC16: =I16*$BC$2 -> 136.875 | BD16: =I16*$BD$2 -> 821.25 | BE16: =I16*$BE$2 -> 821.25 | BF16: =I16*$BF$2 -> 821.25 | BG16: =I16*$BG$2 -> 821.25 | BH16: =I16*$BH$2 -> 821.25 | BI16: =I16*$BI$2 -> 821.25 | BK16: =BK15-BA16 -> 6134.25 | BL16: =BL15-BB16 -> 5288.375 | BM16: =BM15-BD16 -> 6147.25 | BN16: =BN15-BC16 -> 932.875 | BO16: =BO15-BE16 -> 4269.25 | BP16: =BP15-BF16 -> 6147.25 | BQ16: =BQ15-BG16 -> 6147.25 | BR16: =BR15-BH16 -> 6547.25 | BS16: =BS15-BI16 -> 6147.25
A17: 45705 | B17: Royal Foods LLC | C17: 阿塞拜疆 | D17: 4500157780 | F17: 4500157780-10 | G17: 77593GQ1-S001 | H17: S4迷你恐龙13PCS/GQ1*4 | I17: 156 | J17: 0 | K17: 52 | L17: =I17/K17 -> 3 | M17: 45741 | N17: 45737 | P17: 自检 | Q17: 4/7 截SI | R17: 45705 | S17: 无 | T17: 无 | U17: 日期码格式：ZURU INC(BVI) 标准格式 日期：按实际生产日期 Packaging Info: 1. 无进口商贴纸； 2. 77593GQ1 ： 1L MA UPC 包装， MA PDQ/说明书/指南（如有）； Remark: 标准配比 | V17: Ann Zhang | W17: 0.967 | X17: =W17*I17 -> 150.852 | Y17: 94710-4.7 | Z17: 156 | AA17: =Z17-I17 -> 0 | AD17: 77593GQ1-S001 | AE17: 已入 | AF17: =I17 -> 156 | AG17: =AF17 -> 156 | AI17: =I17 -> 156 | AN17: =I17/13 -> 12 | AX17: =I17 -> 156 | BA17: =I17*$BA$2 -> 19.5 | BB17: =I17*$BB$2 -> 16.25 | BC17: =I17*$BC$2 -> 3.25 | BD17: =I17*$BD$2 -> 19.5 | BE17: =I17*$BE$2 -> 19.5 | BF17: =I17*$BF$2 -> 19.5 | BG17: =I17*$BG$2 -> 19.5 | BH17: =I17*$BH$2 -> 19.5 | BI17: =I17*$BI$2 -> 19.5 | BK17: =BK16-BA17 -> 6114.75 | BL17: =BL16-BB17 -> 5272.125 | BM17: =BM16-BD17 -> 6127.75 | BN17: =BN16-BC17 -> 929.625 | BO17: =BO16-BE17 -> 4249.75 | BP17: =BP16-BF17 -> 6127.75 | BQ17: =BQ16-BG17 -> 6127.75 | BR17: =BR16-BH17 -> 6527.75 | BS17: =BS16-BI17 -> 6127.75
A18: 45740 | D18: ZMPO250257 | G18: 77593-S001 | I18: 11空球 | J18: 0 | K18: 24 | L18: =I18/K18 -> #VALUE! | M18: 45749 | N18: =M18-4 -> 45745 | R18: 空白箱 | S18: 无 | T18: 无 | U18: Remark：大货最新版本/11PCS空球要用大货收缩膜收缩好；备注： 收到样品订单后尽快安排 ，注意样板品质质量要求要高于大货品质质量 ，送货时必须要附带送货单(没有送货单和QC检验合格报告的仓库一律拒绝收货)，请知悉，谢谢！ | V18: Angus | Y18: 94918-4.30 | Z18: 11 | AD18: # | AE18: #
A19: 45740 | D19: ZMPO250257 | G19: 77593-S001 | I19: 18套散件 | J19: 0 | K19: 24 | L19: =I19/K19 -> #VALUE! | M19: 45749 | N19: =M19-4 -> 45745 | R19: 空白箱 | S19: 无 | T19: 无 | U19: Remark：大货最新版本/只需要齐全套散件，每款散件不要用纸袋子装，用透明塑胶袋装即可/麻烦用胶袋分装好一套为一袋；备注： 收到样品订单后尽快安排 ，注意样板品质质量要求要高于大货品质质量 ，送货时必须要附带送货单(没有送货单和QC检验合格报告的仓库一律拒绝收货)，请知悉，谢谢！ | V19: Angus | Y19: 94918-4.30 | Z19: 18 | AD19: # | AE19: #
A20: 45712 | B20: Walmart Central America | C20: 萨尔瓦多 | D20: 4500158302 | F20: 4500158302-10 | G20: 77593GQ2-S001 | H20: S4迷你恐龙24PCS入GQ2*2/箱 | I20: 576 | J20: 0 | K20: 48 | L20: =I20/K20 -> 12 | M20: 45763 | N20: 45758 | P20: pass | Q20: 4/28 截SI | R20: 3/24 双坑纸箱 | S20: 无 | T20: 3/21进口商贴纸+UPC贴纸 | U20: 日期码格式：ZURU INC(BVI) 标准格式 日期：按实际生产日期 Packaging Info: 1. 77593GQ2：MA 3L EAN包装+UPC贴纸+MA 3L PDQ包装+MA多语收藏指南+进口商贴纸+箱唛 Remark: 1.使用双坑外箱 2.请注意产品包装条形码必须是UPC 3.无第三方验货 | V20: Ever Li | W20: 0.9947 | X20: =W20*I20 -> 572.9472 | Y20: 94865-4.28 | Z20: 576 | AA20: =Z20-I20 -> 0 | AD20: 77593GQ2-S001-3L | AE20: 已入 | AF20: =I20 -> 576 | AH20: =I20 -> 576 | AI20: =I20 -> 576 | AM20: =I20/24 -> 24 | AX20: =I20 -> 576 | BA20: =I20*$BA$2 -> 72 | BB20: =I20*$BB$2 -> 60 | BC20: =I20*$BC$2 -> 12 | BD20: =I20*$BD$2 -> 72 | BE20: =I20*$BE$2 -> 72 | BF20: =I20*$BF$2 -> 72 | BG20: =I20*$BG$2 -> 72 | BH20: =I20*$BH$2 -> 72 | BI20: =I20*$BI$2 -> 72 | BK20: =BK17-BA20 -> 6042.75 | BL20: =BL17-BB20 -> 5212.125 | BM20: =BM17-BD20 -> 6055.75 | BN20: =BN17-BC20 -> 917.625 | BO20: =BO17-BE20 -> 4177.75 | BP20: =BP17-BF20 -> 6055.75 | BQ20: =BQ17-BG20 -> 6055.75 | BR20: =BR17-BH20 -> 6455.75 | BS20: =BS17-BI20 -> 6055.75
A21: 45712 | B21: Walmart Central America-NI | C21: 尼加拉瓜 | D21: 4500158358 | F21: 4500158358-10 | G21: 77593GQ2-S001 | H21: S4迷你恐龙24PCS入GQ2*2/箱 | I21: 192 | J21: 0 | K21: 48 | L21: =I21/K21 -> 4 | M21: 45763 | N21: 45758 | P21: pass | Q21: 4/28 截SI | R21: 3/24 双坑纸箱 | S21: 无 | T21: 进口商贴纸+UPC贴纸翻单158302 | U21: 日期码格式：ZURU INC(BVI) 标准格式 日期：按实际生产日期 Packaging Info: 1. 77593GQ2：MA 3L EAN包装+UPC贴纸+MA 3L PDQ包装+MA多语收藏指南+进口商贴纸+箱唛 所有贴纸翻单PO 4500158302 Remark: 1.使用双坑外箱 2.请注意产品包装条形码必须是UPC 3.无第三方验货 | V21: Ever Li | W21: 0.9947 | X21: =W21*I21 -> 190.9824 | Y21: 94934-5.6 | Z21: 192 | AA21: =Z21-I21 -> 0 | AD21: 77593GQ2-S001-3L | AE21: 已入 | AF21: =I21 -> 192 | AH21: =I21 -> 192 | AI21: =I21 -> 192 | AM21: =I21/24 -> 8 | AX21: =I21 -> 192 | BA21: =I21*$BA$2 -> 24 | BB21: =I21*$BB$2 -> 20 | BC21: =I21*$BC$2 -> 4 | BD21: =I21*$BD$2 -> 24 | BE21: =I21*$BE$2 -> 24 | BF21: =I21*$BF$2 -> 24 | BG21: =I21*$BG$2 -> 24 | BH21: =I21*$BH$2 -> 24 | BI21: =I21*$BI$2 -> 24 | BK21: =BK20-BA21 -> 6018.75 | BL21: =BL20-BB21 -> 5192.125 | BM21: =BM20-BD21 -> 6031.75 | BN21: =BN20-BC21 -> 913.625 | BO21: =BO20-BE21 -> 4153.75 | BP21: =BP20-BF21 -> 6031.75 | BQ21: =BQ20-BG21 -> 6031.75 | BR21: =BR20-BH21 -> 6431.75 | BS21: =BS20-BI21 -> 6031.75
A22: 45712 | B22: Walmart Central America-HN | C22: 洪都拉斯 | D22: 4500158415 | F22: 4500158415-10 | G22: 77593GQ2-S001 | H22: S4迷你恐龙24PCS入GQ2*2/箱 | I22: 384 | J22: 0 | K22: 48 | L22: =I22/K22 -> 8 | M22: 45763 | N22: 45758 | P22: pass | Q22: 4/29 截SI | R22: 3/24 双坑纸箱 | S22: 无 | T22: 进口商贴纸+UPC贴纸翻单158302 | U22: 日期码格式：ZURU INC(BVI) 标准格式 日期：按实际生产日期 Packaging Info: 1. 77593GQ2：MA 3L EAN包装+UPC贴纸+MA 3L PDQ包装+MA多语收藏指南+进口商贴纸+箱唛 以上所有贴纸翻单PO4500158302 Remark: 1.使用双坑外箱 2.请注意产品包装条形码必须是UPC 3.无第三方验货 | V22: Ever Li | W22: 0.9947 | X22: =W22*I22 -> 381.9648 | Y22: 94891-4.30 | Z22: 384 | AA22: =Z22-I22 -> 0 | AD22: 77593GQ2-S001-3L | AE22: 已入 | AF22: =I22 -> 384 | AH22: =I22 -> 384 | AI22: =I22 -> 384 | AM22: =I22/24 -> 16 | AX22: =I22 -> 384 | BA22: =I22*$BA$2 -> 48 | BB22: =I22*$BB$2 -> 40 | BC22: =I22*$BC$2 -> 8 | BD22: =I22*$BD$2 -> 48 | BE22: =I22*$BE$2 -> 48 | BF22: =I22*$BF$2 -> 48 | BG22: =I22*$BG$2 -> 48 | BH22: =I22*$BH$2 -> 48 | BI22: =I22*$BI$2 -> 48 | BK22: =BK21-BA22 -> 5970.75 | BL22: =BL21-BB22 -> 5152.125 | BM22: =BM21-BD22 -> 5983.75 | BN22: =BN21-BC22 -> 905.625 | BO22: =BO21-BE22 -> 4105.75 | BP22: =BP21-BF22 -> 5983.75 | BQ22: =BQ21-BG22 -> 5983.75 | BR22: =BR21-BH22 -> 6383.75 | BS22: =BS21-BI22 -> 5983.75
A23: 45714 | B23: Walmart Central America-CR | C23: 哥斯达黎加 | D23: 4500158535 | F23: 4500158535-10 | G23: 77593GQ2-S001 | H23: S4迷你恐龙24PCS入GQ2*2/箱 | I23: 1440 | J23: 0 | K23: 48 | L23: =I23/K23 -> 30 | M23: 45763 | N23: 45758 | P23: pass | Q23: 4/29 截SI | R23: 3/24 双坑纸箱 | S23: 无 | T23: 进口商贴纸+UPC贴纸翻单158302 | U23: 日期码格式：ZURU INC(BVI) 标准格式 日期：按实际生产日期 Packaging Info: 1. 77593GQ2：MA 3L EAN包装+UPC贴纸+MA 3L PDQ包装+MA多语收藏指南+进口商贴纸+箱唛 以上贴纸翻单PO 4500158302 Remark: 1.使用双坑外箱 2.请注意产品包装条形码必须是UPC 3.无第三方验货 | V23: Ever Li | W23: 0.9907 | X23: =W23*I23 -> 1426.608 | Y23: 94882-4.29 | Z23: 1440 | AA23: =Z23-I23 -> 0 | AD23: 77593GQ2-S001-3L | AE23: 已入 | AF23: =I23 -> 1440 | AH23: =I23 -> 1440 | AI23: =I23 -> 1440 | AM23: =I23/24 -> 60 | AX23: =I23 -> 1440 | BA23: =I23*$BA$2 -> 180 | BB23: =I23*$BB$2 -> 150 | BC23: =I23*$BC$2 -> 30 | BD23: =I23*$BD$2 -> 180 | BE23: =I23*$BE$2 -> 180 | BF23: =I23*$BF$2 -> 180 | BG23: =I23*$BG$2 -> 180 | BH23: =I23*$BH$2 -> 180 | BI23: =I23*$BI$2 -> 180 | BK23: =BK22-BA23 -> 5790.75 | BL23: =BL22-BB23 -> 5002.125 | BM23: =BM22-BD23 -> 5803.75 | BN23: =BN22-BC23 -> 875.625 | BO23: =BO22-BE23 -> 3925.75 | BP23: =BP22-BF23 -> 5803.75 | BQ23: =BQ22-BG23 -> 5803.75 | BR23: =BR22-BH23 -> 6203.75 | BS23: =BS22-BI23 -> 5803.75
A24: 45714 | B24: Walmart Central America-GT | C24: 危地马拉 | D24: 4500158447 | F24: 4500158447-10 | G24: 77593GQ2-S001 | H24: S4迷你恐龙24PCS入GQ2*2/箱 | I24: 1056 | J24: 0 | K24: 48 | L24: =I24/K24 -> 22 | M24: 45763 | N24: 45758 | P24: pass | Q24: 4/28 截SI | R24: 3/24 双坑纸箱 | S24: 无 | T24: 进口商贴纸+UPC贴纸翻单158302 | U24: 日期码格式：ZURU INC(BVI) 标准格式 日期：按实际生产日期 Packaging Info: 1. 77593GQ2：MA 3L EAN包装+UPC贴纸+MA 3L PDQ包装+MA多语收藏指南+进口商贴纸+箱唛 以上所有贴纸翻单PO4500158302 Remark: 1.使用双坑外箱 2.请注意产品包装条形码必须是UPC 3.无第三方验货 | V24: Ever Li | W24: 0.9907 | X24: =W24*I24 -> 1046.1792 | Y24: 94923-5.5 | Z24: =1008+48 -> 1056 | AA24: =Z24-I24 -> 0 | AD24: 77593GQ2-S001-3L | AE24: 已入 | AF24: =I24 -> 1056 | AH24: =I24 -> 1056 | AI24: =I24 -> 1056 | AM24: =I24/24 -> 44 | AX24: =I24 -> 1056 | BA24: =I24*$BA$2 -> 132 | BB24: =I24*$BB$2 -> 110 | BC24: =I24*$BC$2 -> 22 | BD24: =I24*$BD$2 -> 132 | BE24: =I24*$BE$2 -> 132 | BF24: =I24*$BF$2 -> 132 | BG24: =I24*$BG$2 -> 132 | BH24: =I24*$BH$2 -> 132 | BI24: =I24*$BI$2 -> 132 | BK24: =BK23-BA24 -> 5658.75 | BL24: =BL23-BB24 -> 4892.125 | BM24: =BM23-BD24 -> 5671.75 | BN24: =BN23-BC24 -> 853.625 | BO24: =BO23-BE24 -> 3793.75 | BP24: =BP23-BF24 -> 5671.75 | BQ24: =BQ23-BG24 -> 5671.75 | BR24: =BR23-BH24 -> 6071.75 | BS24: =BS23-BI24 -> 5671.75
A25: 45755 | B25: NUEVOS ALMACENES, S.A. | C25: 危地马拉 | D25: 4500162922 | E25: 4504192366 | F25: 4500162922-80 | G25: 77593GQ2-S001 | H25: S4迷你恐龙24PCS入GQ2*2/箱 | I25: 3168 | J25: 0 | K25: 48 | L25: =I25/K25 -> 66 | M25: 45792 | N25: 45789 | O25: 5/16 第三方 | P25: pass | Q25: 5/17 出货 | R25: 45762 | S25: 无 | T25: 4/8 UPC贴纸 | U25: 日期码格式：ZURU INC(BVI) 标准格式 日期：按实际生产日期 Packaging Info:77593GQ2:MA 3L EAN包装+UPC贴纸+箱唛，无进口商贴纸 Remark: 订单需第三方（QIMA)验货，无需签板，请多备料。 外箱上的箱唛资料会显示日期30-MAY-2025,产品/包装/外箱可以按ZURU 标准日期码打，也可以跟回外箱日期码，工厂自行选择,两者均可接受 | V25: Ava Liang | W25: 0.961 | X25: =W25*I25 -> 3044.448 | Y25: 95154-5.30 | Z25: 3168 | AA25: 0 | AD25: 77593GQ2-S001-3L | AE25: 已入 | AF25: =I25 -> 3168 | AH25: =I25 -> 3168 | AI25: =I25 -> 3168 | AM25: =I25/24 -> 132 | AX25: =I25 -> 3168 | BA25: =I25*$BA$2 -> 396 | BB25: =I25*$BB$2 -> 330 | BC25: =I25*$BC$2 -> 66 | BD25: =I25*$BD$2 -> 396 | BE25: =I25*$BE$2 -> 396 | BF25: =I25*$BF$2 -> 396 | BG25: =I25*$BG$2 -> 396 | BH25: =I25*$BH$2 -> 396 | BI25: =I25*$BI$2 -> 396 | BK25: =BK24-BA25 -> 5262.75 | BL25: =BL24-BB25 -> 4562.125 | BM25: =BM24-BD25 -> 5275.75 | BN25: =BN24-BC25 -> 787.625 | BO25: =BO24-BE25 -> 3397.75 | BP25: =BP24-BF25 -> 5275.75 | BQ25: =BQ24-BG25 -> 5275.75 | BR25: =BR24-BH25 -> 5675.75 | BS25: =BS24-BI25 -> 5275.75
A26: 45757 | B26: SUBURBIA S DE R. L. DE C. V. | C26: 墨西哥 | D26: 4500162850 | E26: 6000056637 | F26: 4500162850-50 | G26: 77593GQ2-S001 | H26: S4迷你恐龙24PCS入GQ2*2/箱 | I26: 480 | J26: 0 | K26: 48 | L26: =I26/K26 -> 10 | M26: 45821 | N26: 45818 | O26: 有监柜要求，需要每款多准备一套完整物料，用于监柜 | P26: 自检 | Q26: 6/13 截SI | R26: 外箱只需四面印Zuru logo | S26: 有 | T26: 5/9进口商贴纸+价标贴纸+说明书贴纸+5/26HU贴纸和ASN贴纸客供 | U26: 日期码格式：ZURU INC(BVI) 标准格式 日期：按实际生产日期 Packaging Info: 77593GQ2：MA 多语 EAN 包装+MA 多语PDQ+MA多语说明书+进口商贴纸+价标贴纸+说明书贴纸 1. 外箱只需四面印Zuru logo，再加2张贴纸，1张Hu贴纸（条码贴），1张ASN贴纸（尺寸6.5cm*6.3cm,潘通色号2597C），都贴于侧唛，只需贴1面(HU贴纸和ASN贴 纸客供） 2. 一个外箱对应一个HU’S(条形码),不可以混条码包装 3.含有说明书需要增加说明书贴纸 4.价格贴纸覆盖原有包装的条形码 Remark: 此单有监柜要求，需要每款多准备一套完整物料，用于监柜，不可以随大货走 | V26: Ever Li | W26: 0.9931 | X26: =W26*I26 -> 476.688 | Y26: 95265-6.11 | Z26: 480 | AA26: 0 | AD26: 77593GQ2-S001-3L | AE26: 已入 | AF26: =I26 -> 480 | AH26: =I26 -> 480 | AI26: =I26 -> 480 | AM26: =I26/24 -> 20 | AX26: =I26 -> 480 | BA26: =I26*$BA$2 -> 60 | BB26: =I26*$BB$2 -> 50 | BC26: =I26*$BC$2 -> 10 | BD26: =I26*$BD$2 -> 60 | BE26: =I26*$BE$2 -> 60 | BF26: =I26*$BF$2 -> 60 | BG26: =I26*$BG$2 -> 60 | BH26: =I26*$BH$2 -> 60 | BI26: =I26*$BI$2 -> 60 | BK26: =BK25-BA26 -> 5202.75 | BL26: =BL25-BB26 -> 4512.125 | BM26: =BM25-BD26 -> 5215.75 | BN26: =BN25-BC26 -> 777.625 | BO26: =BO25-BE26 -> 3337.75 | BP26: =BP25-BF26 -> 5215.75 | BQ26: =BQ25-BG26 -> 5215.75 | BR26: =BR25-BH26 -> 5615.75 | BS26: =BS25-BI26 -> 5215.75
A27: 45792 | B27: Sirius Sales (PTY) Ltd | C27: 南非 | D27: 4500166516 | F27: 4500166516-20 | G27: 77593GQ2-S001 | H27: S4迷你恐龙24PCS入GQ2*2/箱 | I27: 2400 | J27: 0 | K27: 48 | L27: =I27/K27 -> 50 | M27: 45838 | N27: 45834 | P27: pass | Q27: 7/1 入仓 | R27: 45796 | S27: 无 | T27: 无 | U27: 日期码格式：ZURU INC(BVI) 标准格式 日期：按实际生产日期 Packaging Info: 1. MA UPC PKG(优先1L) Remark: | V27: Doris Shou | W27: 0.9892 | X27: =W27*I27 -> 2374.08 | Y27: 95520-7.1 | Z27: =2352+48 -> 2400 | AA27: =Z27-I27 -> 0 | AD27: 77593GQ2-S001 | AE27: 已入 | AF27: =I27 -> 2400 | AG27: =I27 -> 2400 | AI27: =I27 -> 2400 | AL27: =I27/24 -> 100 | AX27: =I27 -> 2400 | BA27: =I27*$BA$2 -> 300 | BB27: =I27*$BB$2 -> 250 | BC27: =I27*$BC$2 -> 50 | BD27: =I27*$BD$2 -> 300 | BE27: =I27*$BE$2 -> 300 | BF27: =I27*$BF$2 -> 300 | BG27: =I27*$BG$2 -> 300 | BH27: =I27*$BH$2 -> 300 | BI27: =I27*$BI$2 -> 300 | BK27: =BK26-BA27 -> 4902.75 | BL27: =BL26-BB27 -> 4262.125 | BM27: =BM26-BD27 -> 4915.75 | BN27: =BN26-BC27 -> 727.625 | BO27: =BO26-BE27 -> 3037.75 | BP27: =BP26-BF27 -> 4915.75 | BQ27: =BQ26-BG27 -> 4915.75 | BR27: =BR26-BH27 -> 5315.75 | BS27: =BS26-BI27 -> 4915.75
A28: 45803 | B28: Hermanex Europe BV | C28: 荷兰 | D28: 4500167892 | E28: 91-21747 | F28: 4500167892-10 | G28: 77593SK-S002 | H28: S4迷你恐龙展示架带球 | I28: 7440 | J28: 0 | K28: 60 | L28: =I28/K28 -> 124 | M28: 45839 | N28: =M28-4 -> 45835 | P28: pass | Q28: 7/5 送外厂 | R28: 45803 | S28: 无 | T28: 6/4 NL警语贴纸 | U28: 日期码格式：ZURU INC(BVI) 标准格式 日期：按实际生产日期 Packaging Info: 77593SK-S002: MA A版3L EAN收缩膜+NL警语贴纸，MA A版 5L slime polybag+NL警语贴纸，MA A版 5L收藏指南，MA A版1L带Base展架（消耗slow moving库存） Remark: 1.出欧洲荷兰，须符合欧洲微塑料法规（如item本身不含微塑料，则忽略此要求） 2.条码 4894680034709 | V28: Nicole Ye | W28: 70.3426 | X28: =W28*L28 -> 8722.4824 | Y28: 95578-7.7 | Z28: 7440 | AA28: 0 | AD28: 77593SK-S002-3L | AE28: 已入 | AF28: =I28 -> 7440 | AH28: =I28 -> 7440 | AI28: =AH28 -> 7440 | AJ28: =L28 -> 124 | AK28: =AJ28 -> 124 | AX28: =I28 -> 7440 | BA28: =I28*$BA$2 -> 930 | BB28: =I28*$BB$2 -> 775 | BC28: =I28*$BC$2 -> 155 | BD28: =I28*$BD$2 -> 930 | BE28: =I28*$BE$2 -> 930 | BF28: =I28*$BF$2 -> 930 | BG28: =I28*$BG$2 -> 930 | BH28: =I28*$BH$2 -> 930 | BI28: =I28*$BI$2 -> 930 | BK28: =BK27-BA28 -> 3972.75 | BL28: =BL27-BB28 -> 3487.125 | BM28: =BM27-BD28 -> 3985.75 | BN28: =BN27-BC28 -> 572.625 | BO28: =BO27-BE28 -> 2107.75 | BP28: =BP27-BF28 -> 3985.75 | BQ28: =BQ27-BG28 -> 3985.75 | BR28: =BR27-BH28 -> 4385.75 | BS28: =BS27-BI28 -> 3985.75
A29: 45834 | B29: TJX CANADA | C29: 加拿大 | D29: 4500171335 | E29: 40276731 40276790 | F29: 4500171335-140 | G29: 77593GQ2-S002-NB | H29: S4迷你恐龙24PCS入GQ2*2/箱 | I29: 912 | J29: 0 | K29: 24 | L29: =I29/K29 -> 38 | M29: 45870 | N29: =M29-4 -> 45866 | P29: 自检 | Q29: 8/4 截SI | R29: 45835 | S29: 无 | T29: 6/26 UPC 贴纸+7/16客供价格贴 | U29: 日期码格式：ZURU INC(BVI) 标准格式 日期：按实际生产日期 Packaging Info: 77593GQ2 无硼版本， 标版多语包装/说明书+多语PDQ , 加UPC 贴纸， UPC 193052066206 Remark: 出加拿大 有客供价格贴 每行对应不同的客户PO，唛头要一一对应， 放唛头时跟单会提供清单 Zuru验货.日期跟踪码：产品外包装及产品本身都必须有日期跟踪码，ZURU标准格式 日期码 | V29: Summer Mo | W29: 0.9892 | X29: =W29*I29 -> 902.1504 | Y29: 95906-8.4 | Z29: =888+24 -> 912 | AA29: =Z29-I29 -> 0 | AD29: 77593GQ2-S002-NB | AE29: 已入 | AF29: =I29 -> 912 | AH29: =I29 -> 912 | AI29: =I29 -> 912 | AM29: =I29/24 -> 38 | AY29: =I29 -> 912 | BA29: =I29*$BA$2 -> 114 | BB29: =I29*$BB$2 -> 95 | BC29: =I29*$BC$2 -> 19 | BD29: =I29*$BD$2 -> 114 | BE29: =I29*$BE$2 -> 114 | BF29: =I29*$BF$2 -> 114 | BG29: =I29*$BG$2 -> 114 | BH29: =I29*$BH$2 -> 114 | BI29: =I29*$BI$2 -> 114 | BK29: =BK28-BA29 -> 3858.75 | BL29: =BL28-BB29 -> 3392.125 | BM29: =BM28-BD29 -> 3871.75 | BN29: =BN28-BC29 -> 553.625 | BO29: =BO28-BE29 -> 1993.75 | BP29: =BP28-BF29 -> 3871.75 | BQ29: =BQ28-BG29 -> 3871.75 | BR29: =BR28-BH29 -> 4271.75 | BS29: =BS28-BI29 -> 3871.75
A30: 45834 | B30: TJX CANADA | C30: 加拿大 | D30: 4500171335 | E30: 40276731 40276790 | F30: 4500171335-240 | G30: 77593GQ2-S002-NB | H30: S4迷你恐龙24PCS入GQ2*2/箱 | I30: 288 | J30: 0 | K30: 24 | L30: =I30/K30 -> 12 | M30: 45870 | N30: =M30-4 -> 45866 | P30: 自检 | Q30: 8/4 截SI | R30: 45835 | S30: 无 | T30: 6/26 UPC 贴纸+7/16客供价格贴 | U30: 日期码格式：ZURU INC(BVI) 标准格式 日期：按实际生产日期 Packaging Info: 77593GQ2 无硼版本， 标版多语包装/说明书+多语PDQ , 加UPC 贴纸， UPC 193052066206 Remark: 出加拿大 有客供价格贴 每行对应不同的客户PO，唛头要一一对应， 放唛头时跟单会提供清单 Zuru验货.日期跟踪码：产品外包装及产品本身都必须有日期跟踪码，ZURU标准格式 日期码 | V30: Summer Mo | W30: 0.9708 | X30: =W30*I30 -> 279.5904 | Y30: 95906-8.4 | Z30: =240+48 -> 288 | AA30: =Z30-I30 -> 0 | AD30: 77593GQ2-S002-NB | AE30: 已入 | AF30: =I30 -> 288 | AH30: =I30 -> 288 | AI30: =I30 -> 288 | AM30: =I30/24 -> 12 | AY30: =I30 -> 288 | BA30: =I30*$BA$2 -> 36 | BB30: =I30*$BB$2 -> 30 | BC30: =I30*$BC$2 -> 6 | BD30: =I30*$BD$2 -> 36 | BE30: =I30*$BE$2 -> 36 | BF30: =I30*$BF$2 -> 36 | BG30: =I30*$BG$2 -> 36 | BH30: =I30*$BH$2 -> 36 | BI30: =I30*$BI$2 -> 36 | BK30: =BK29-BA30 -> 3822.75 | BL30: =BL29-BB30 -> 3362.125 | BM30: =BM29-BD30 -> 3835.75 | BN30: =BN29-BC30 -> 547.625 | BO30: =BO29-BE30 -> 1957.75 | BP30: =BP29-BF30 -> 3835.75 | BQ30: =BQ29-BG30 -> 3835.75 | BR30: =BR29-BH30 -> 4235.75 | BS30: =BS29-BI30 -> 3835.75
A31: 45834 | B31: TJX CANADA | C31: 加拿大 | D31: 4500171335 | E31: 40276731 40276790 | F31: 4500171335-330 | G31: 77593GQ2-S002-NB | H31: S4迷你恐龙24PCS入GQ2*2/箱 | I31: 1080 | J31: 0 | K31: 24 | L31: =I31/K31 -> 45 | M31: 45870 | N31: =M31-4 -> 45866 | P31: 自检 | Q31: 8/4 截SI | R31: 45835 | S31: 无 | T31: 6/26 UPC 贴纸+7/16客供价格贴 | U31: 日期码格式：ZURU INC(BVI) 标准格式 日期：按实际生产日期 Packaging Info: 77593GQ2 无硼版本， 标版多语包装/说明书+多语PDQ , 加UPC 贴纸， UPC 193052066206 Remark: 出加拿大 有客供价格贴 每行对应不同的客户PO，唛头要一一对应， 放唛头时跟单会提供清单 Zuru验货.日期跟踪码：产品外包装及产品本身都必须有日期跟踪码，ZURU标准格式 日期码 | V31: Summer Mo | W31: 0.9708 | X31: =W31*I31 -> 1048.464 | Y31: 95906-8.4 | Z31: 1080 | AA31: =Z31-I31 -> 0 | AD31: 77593GQ2-S002-NB | AE31: 已入 | AF31: =I31 -> 1080 | AH31: =I31 -> 1080 | AI31: =I31 -> 1080 | AM31: =I31/24 -> 45 | AY31: =I31 -> 1080 | BA31: =I31*$BA$2 -> 135 | BB31: =I31*$BB$2 -> 112.5 | BC31: =I31*$BC$2 -> 22.5 | BD31: =I31*$BD$2 -> 135 | BE31: =I31*$BE$2 -> 135 | BF31: =I31*$BF$2 -> 135 | BG31: =I31*$BG$2 -> 135 | BH31: =I31*$BH$2 -> 135 | BI31: =I31*$BI$2 -> 135 | BK31: =BK30-BA31 -> 3687.75 | BL31: =BL30-BB31 -> 3249.625 | BM31: =BM30-BD31 -> 3700.75 | BN31: =BN30-BC31 -> 525.125 | BO31: =BO30-BE31 -> 1822.75 | BP31: =BP30-BF31 -> 3700.75 | BQ31: =BQ30-BG31 -> 3700.75 | BR31: =BR30-BH31 -> 4100.75 | BS31: =BS30-BI31 -> 3700.75
A32: 45834 | B32: TJX CANADA | C32: 加拿大 | D32: 4500171335 | E32: 40276731 40276790 | F32: 4500171335-420 | G32: 77593GQ2-S002-NB | H32: S4迷你恐龙24PCS入GQ2*2/箱 | I32: 384 | J32: 0 | K32: 24 | L32: =I32/K32 -> 16 | M32: 45870 | N32: =M32-4 -> 45866 | P32: 自检 | Q32: 8/4 截SI | R32: 45835 | S32: 无 | T32: 6/26 UPC 贴纸+7/16客供价格贴 | U32: 日期码格式：ZURU INC(BVI) 标准格式 日期：按实际生产日期 Packaging Info: 77593GQ2 无硼版本， 标版多语包装/说明书+多语PDQ , 加UPC 贴纸， UPC 193052066206 Remark: 出加拿大 有客供价格贴 每行对应不同的客户PO，唛头要一一对应， 放唛头时跟单会提供清单 Zuru验货.日期跟踪码：产品外包装及产品本身都必须有日期跟踪码，ZURU标准格式 日期码 | V32: Summer Mo | W32: 0.9892 | X32: =W32*I32 -> 379.8528 | Y32: 95906-8.4 | Z32: 384 | AA32: =Z32-I32 -> 0 | AD32: 77593GQ2-S002-NB | AE32: 已入 | AF32: =I32 -> 384 | AH32: =I32 -> 384 | AI32: =I32 -> 384 | AM32: =I32/24 -> 16 | AY32: =I32 -> 384 | BA32: =I32*$BA$2 -> 48 | BB32: =I32*$BB$2 -> 40 | BC32: =I32*$BC$2 -> 8 | BD32: =I32*$BD$2 -> 48 | BE32: =I32*$BE$2 -> 48 | BF32: =I32*$BF$2 -> 48 | BG32: =I32*$BG$2 -> 48 | BH32: =I32*$BH$2 -> 48 | BI32: =I32*$BI$2 -> 48 | BK32: =BK31-BA32 -> 3639.75 | BL32: =BL31-BB32 -> 3209.625 | BM32: =BM31-BD32 -> 3652.75 | BN32: =BN31-BC32 -> 517.125 | BO32: =BO31-BE32 -> 1774.75 | BP32: =BP31-BF32 -> 3652.75 | BQ32: =BQ31-BG32 -> 3652.75 | BR32: =BR31-BH32 -> 4052.75 | BS32: =BS31-BI32 -> 3652.75
A33: 45834 | B33: TJX CANADA | C33: 加拿大 | D33: 4500171335 | E33: 40276731 40276790 | F33: 4500171335-510 | G33: 77593GQ2-S002-NB | H33: S4迷你恐龙24PCS入GQ2*2/箱 | I33: 408 | J33: 0 | K33: 24 | L33: =I33/K33 -> 17 | M33: 45870 | N33: =M33-4 -> 45866 | P33: 自检 | Q33: 8/4 截SI | R33: 45835 | S33: 无 | T33: 6/26 UPC 贴纸+7/16客供价格贴 | U33: 日期码格式：ZURU INC(BVI) 标准格式 日期：按实际生产日期 Packaging Info: 77593GQ2 无硼版本， 标版多语包装/说明书+多语PDQ , 加UPC 贴纸， UPC 193052066206 Remark: 出加拿大 有客供价格贴 每行对应不同的客户PO，唛头要一一对应， 放唛头时跟单会提供清单 Zuru验货.日期跟踪码：产品外包装及产品本身都必须有日期跟踪码，ZURU标准格式 日期码 | V33: Summer Mo | W33: 0.9892 | X33: =W33*I33 -> 403.5936 | Y33: 95906-8.4 | Z33: 408 | AA33: =Z33-I33 -> 0 | AD33: 77593GQ2-S002-NB | AE33: 已入 | AF33: =I33 -> 408 | AH33: =I33 -> 408 | AI33: =I33 -> 408 | AM33: =I33/24 -> 17 | AY33: =I33 -> 408 | BA33: =I33*$BA$2 -> 51 | BB33: =I33*$BB$2 -> 42.5 | BC33: =I33*$BC$2 -> 8.5 | BD33: =I33*$BD$2 -> 51 | BE33: =I33*$BE$2 -> 51 | BF33: =I33*$BF$2 -> 51 | BG33: =I33*$BG$2 -> 51 | BH33: =I33*$BH$2 -> 51 | BI33: =I33*$BI$2 -> 51 | BK33: =BK32-BA33 -> 3588.75 | BL33: =BL32-BB33 -> 3167.125 | BM33: =BM32-BD33 -> 3601.75 | BN33: =BN32-BC33 -> 508.625 | BO33: =BO32-BE33 -> 1723.75 | BP33: =BP32-BF33 -> 3601.75 | BQ33: =BQ32-BG33 -> 3601.75 | BR33: =BR32-BH33 -> 4001.75 | BS33: =BS32-BI33 -> 3601.75
A34: 45834 | B34: TJX CANADA | C34: 加拿大 | D34: 4500171342 | E34: 40279125 45276449 | F34: 4500171342-70 | G34: 77593GQ2-S002-NB | H34: S4迷你恐龙24PCS入GQ2*2/箱 | I34: 144 | J34: 0 | K34: 24 | L34: =I34/K34 -> 6 | M34: 45870 | N34: =M34-4 -> 45866 | P34: 自检 | Q34: 8/4 截SI | R34: 45835 | S34: 无 | T34: 6/26 UPC 贴纸+7/16客供价格贴 | U34: 日期码格式：ZURU INC(BVI) 标准格式 日期：按实际生产日期 Packaging Info: 77593GQ2 无硼版本， 标版多语包装/说明书+多语PDQ , 加UPC 贴纸， UPC 193052066206 Remark: 出加拿大 有客供价格贴 每行对应不同的客户PO，唛头要一一对应， 放唛头时跟单会提供清单 Zuru验货.日期跟踪码：产品外包装及产品本身都必须有日期跟踪码，ZURU标准格式 日期码 | V34: Summer Mo | W34: 0.9931 | X34: =W34*I34 -> 143.0064 | Y34: 96596-8.4 | Z34: 144 | AA34: =Z34-I34 -> 0 | AD34: 77593GQ2-S002-NB | AE34: 已入 | AF34: =I34 -> 144 | AH34: =I34 -> 144 | AI34: =I34 -> 144 | AM34: =I34/24 -> 6 | AY34: =I34 -> 144 | BA34: =I34*$BA$2 -> 18 | BB34: =I34*$BB$2 -> 15 | BC34: =I34*$BC$2 -> 3 | BD34: =I34*$BD$2 -> 18 | BE34: =I34*$BE$2 -> 18 | BF34: =I34*$BF$2 -> 18 | BG34: =I34*$BG$2 -> 18 | BH34: =I34*$BH$2 -> 18 | BI34: =I34*$BI$2 -> 18 | BK34: =BK33-BA34 -> 3570.75 | BL34: =BL33-BB34 -> 3152.125 | BM34: =BM33-BD34 -> 3583.75 | BN34: =BN33-BC34 -> 505.625 | BO34: =BO33-BE34 -> 1705.75 | BP34: =BP33-BF34 -> 3583.75 | BQ34: =BQ33-BG34 -> 3583.75 | BR34: =BR33-BH34 -> 3983.75 | BS34: =BS33-BI34 -> 3583.75
A35: 45838 | B35: NASA PANAMA | C35: 巴拿马 | D35: 4500172103 | F35: 4500172103-160 | G35: 77593GQ2-S001 | H35: S4迷你恐龙24PCS入GQ2*2/箱 | I35: 528 | J35: 0 | K35: 48 | L35: =I35/K35 -> 11 | M35: 45874 | N35: 45870 | P35: 自检 | Q35: 8/14 截SI | R35: 45845 | S35: 无 | T35: 7/25 UPC | U35: 日期码格式：ZURU INC(BVI) 标准格式 日期：按实际生产日期 Packaging Info: 请确保包装上的条形码是UPC，如果是babyUPC，需要用mother UPC覆盖，如有不一致，请及时提出。谢谢! 77593GQ2: MA多语EAN 包装+MA 多语PDQ+UPC贴纸+ MA多语说明书+箱唛 Remark: | V35: Aimee Huang | W35: 0.9892 | X35: =W35*I35 -> 522.2976 | Y35: 96595-4-9.30 | Z35: 528 | AA35: =Z35-I35 -> 0 | AD35: 77593GQ2-S001-3L | AE35: 已入 | AF35: =I35 -> 528 | AH35: =I35 -> 528 | AI35: =I35 -> 528 | AM35: =I35/24 -> 22 | AX35: =I35 -> 528 | BA35: =I35*$BA$2 -> 66 | BB35: =I35*$BB$2 -> 55 | BC35: =I35*$BC$2 -> 11 | BD35: =I35*$BD$2 -> 66 | BE35: =I35*$BE$2 -> 66 | BF35: =I35*$BF$2 -> 66 | BG35: =I35*$BG$2 -> 66 | BH35: =I35*$BH$2 -> 66 | BI35: =I35*$BI$2 -> 66 | BK35: =BK34-BA35 -> 3504.75 | BL35: =BL34-BB35 -> 3097.125 | BM35: =BM34-BD35 -> 3517.75 | BN35: =BN34-BC35 -> 494.625 | BO35: =BO34-BE35 -> 1639.75 | BP35: =BP34-BF35 -> 3517.75 | BQ35: =BQ34-BG35 -> 3517.75 | BR35: =BR34-BH35 -> 3917.75 | BS35: =BS34-BI35 -> 3517.75
A36: 45841 | B36: HOBBY LOBBY STORES, INC. | C36: 美国 | D36: 4500171299 | E36: W0726956 | F36: 4500171299-20 | G36: 77593GQ1-S001 | H36: S4迷你恐龙13PCS/GQ1*4 | I36: 1820 | J36: 0 | K36: 52 | L36: =I36/K36 -> 35 | M36: 45882 | N36: 45882 | P36: pass | Q36: 8/20 截SI | R36: 45841 | S36: 有 | T36: 7/3价格贴纸+外箱条码贴纸 | U36: 日期码格式：ZURU INC(BVI) 标准格式 日期：按实际生产日期 Packaging Info: 1. MA UPC版包装，优先1L，需要加贴价格贴纸, 贴在产品包装正面右上角(价格贴纸文档跟单提供)，出美国。 2. 外箱正唛(2面)右下角贴条码贴纸各贴1张(即1面1张共2张),贴纸大小：2.75 x 1.5 inch。(跟单提供文档，工厂采购) Remark: 1. 产品外包装及产品本身都必须有日期跟踪码，格式为：ZURU 标准日期码。 2. ZURU QC验货，无测试。 3. 产品配比按照MA标准配比执行。 | V36: Yvonne Feng | W36: 0.5759 | X36: =W36*I36 -> 1048.138 | Y36: ZB01390-8.21 | Z36: 1820 | AA36: =Z36-I36 -> 0 | AD36: 77593GQ1-S001 | AE36: 已入 | AF36: =I36 -> 1820 | AG36: =AF36 -> 1820 | AI36: =I36 -> 1820 | AN36: =I36/13 -> 140 | AX36: =I36 -> 1820 | BA36: =I36*$BA$2 -> 227.5 | BB36: =I36*$BB$2 -> 189.58333 | BC36: =I36*$BC$2 -> 37.916667 | BD36: =I36*$BD$2 -> 227.5 | BE36: =I36*$BE$2 -> 227.5 | BF36: =I36*$BF$2 -> 227.5 | BG36: =I36*$BG$2 -> 227.5 | BH36: =I36*$BH$2 -> 227.5 | BI36: =I36*$BI$2 -> 227.5 | BK36: =BK35-BA36 -> 3277.25 | BL36: =BL35-BB36 -> 2907.5417 | BM36: =BM35-BD36 -> 3290.25 | BN36: =BN35-BC36 -> 456.70833 | BO36: =BO35-BE36 -> 1412.25 | BP36: =BP35-BF36 -> 3290.25 | BQ36: =BQ35-BG36 -> 3290.25 | BR36: =BR35-BH36 -> 3690.25 | BS36: =BS35-BI36 -> 3290.25
A37: 45825 | B37: DISTRIBUIDORA COMERCIAL DEL NORTE | C37: 厄瓜多尔 | D37: 4500170167 | E37: 2025-0893 | F37: 4500170167-90 | G37: 77593GQ2-S001 | H37: S4迷你恐龙24PCS入GQ2*2/箱 | I37: 2016 | J37: 0 | K37: 48 | L37: =I37/K37 -> 42 | M37: 45891 | N37: 45887 | P37: 自检 | Q37: 8/24 截SI | R37: 45827 | S37: 无 | T37: 7/23进口商贴纸+Mother UPC贴纸 | U37: 日期码格式：ZURU INC(BVI) 标准格式 日期：按实际生产日期 Packaging Info: 77593GQ2:MA 多语 EAN 包装+Mother UPC贴纸+MA 多语PDQ+MA多语说明书+进口商贴纸+箱唛 Mother UPC：193052074867 Remark: ; | V37: Ava Liang | W37: 0.9708 | X37: =W37*I37 -> 1957.1328 | Y37: 96147-2-8.25 | Z37: =1968+48 -> 2016 | AA37: =Z37-I37 -> 0 | AD37: 77593GQ2-S001-3L | AE37: 已入 | AF37: =I37 -> 2016 | AH37: =I37 -> 2016 | AI37: =I37 -> 2016 | AM37: =I37/24 -> 84 | AX37: =I37 -> 2016 | BA37: =I37*$BA$2 -> 252 | BB37: =I37*$BB$2 -> 210 | BC37: =I37*$BC$2 -> 42 | BD37: =I37*$BD$2 -> 252 | BE37: =I37*$BE$2 -> 252 | BF37: =I37*$BF$2 -> 252 | BG37: =I37*$BG$2 -> 252 | BH37: =I37*$BH$2 -> 252 | BI37: =I37*$BI$2 -> 252 | BK37: =BK36-BA37 -> 3025.25 | BL37: =BL36-BB37 -> 2697.5417 | BM37: =BM36-BD37 -> 3038.25 | BN37: =BN36-BC37 -> 414.70833 | BO37: =BO36-BE37 -> 1160.25 | BP37: =BP36-BF37 -> 3038.25 | BQ37: =BQ36-BG37 -> 3038.25 | BR37: =BR36-BH37 -> 3438.25 | BS37: =BS36-BI37 -> 3038.25
A38: 45889 | B38: HOBBY LOBBY STORES, INC. | C38: 美国 | D38: 4500176896 | E38: W0734381 | F38: 4500176896-20 | G38: 77593GQ1-S001 | H38: S4迷你恐龙13PCS/GQ1*4 | I38: 2860 | J38: 0 | K38: 52 | L38: =I38/K38 -> 55 | M38: 45923 | N38: 45919 | P38: pass | R38: 45889 | S38: 有 | T38: 8/20价格贴纸+外箱条码贴纸 | U38: 日期码格式：ZURU INC(BVI) 标准格式 日期：按实际生产日期 Packaging Info: 1. MA UPC版包装，优先1L，需要加贴价格贴纸, 贴在产品包装正面右上角(价格贴纸文档跟单提供)，出美国。 2. 外箱正唛(2面)右下角贴条码贴纸各贴1张(即1面1张共2张),贴纸大小：2.75 x 1.5 inch。(跟单提供文档，工厂采购) Remark: 1. 产品外包装及产品本身都必须有日期跟踪码，格式为：ZURU 标准日期码。 2. ZURU QC验货，无测试。 3. 产品配比按照MA标准配比执行。 | V38: Yvonne Feng | W38: 0.5759 | X38: =W38*I38 -> 1647.074 | Y38: ZB02550-10.22 | Z38: =2808+52 -> 2860 | AA38: =Z38-I38 -> 0 | AD38: 77593GQ1-S001 | AE38: 已入 | AF38: =I38 -> 2860 | AG38: =AF38 -> 2860 | AI38: =I38 -> 2860 | AN38: =I38/13 -> 220 | AX38: =I38 -> 2860 | BA38: =I38*$BA$2 -> 357.5 | BB38: =I38*$BB$2 -> 297.91667 | BC38: =I38*$BC$2 -> 59.583333 | BD38: =I38*$BD$2 -> 357.5 | BE38: =I38*$BE$2 -> 357.5 | BF38: =I38*$BF$2 -> 357.5 | BG38: =I38*$BG$2 -> 357.5 | BH38: =I38*$BH$2 -> 357.5 | BI38: =I38*$BI$2 -> 357.5 | BK38: =BK37-BA38 -> 2667.75 | BL38: =BL37-BB38 -> 2399.625 | BM38: =BM37-BD38 -> 2680.75 | BN38: =BN37-BC38 -> 355.125 | BO38: =BO37-BE38 -> 802.75 | BP38: =BP37-BF38 -> 2680.75 | BQ38: =BQ37-BG38 -> 2680.75 | BR38: =BR37-BH38 -> 3080.75 | BS38: =BS37-BI38 -> 2680.75
A39: 45918 | B39: HOBBY LOBBY STORES, INC. | C39: 美国 | D39: 4500179747 | E39: W0738938 | F39: 4500179747-20 | G39: 77593GQ1-S001 | H39: S4迷你恐龙13PCS/GQ1*4 | I39: 5200 | J39: 0 | K39: 52 | L39: =I39/K39 -> 100 | M39: 45958 | N39: 45954 | P39: pass | Q39: 11/6 截SI | R39: 45926 | S39: 有 | T39: 9/28价格贴纸+外箱条码贴纸 | U39: 日期码格式：ZURU INC(BVI) 标准格式 日期：按实际生产日期 Packaging Info: 1. MA UPC版包装，优先1L，需要加贴价格贴纸, 贴在产品包装正面右上角(价格贴纸文档跟单提供)，出美国。 2. 外箱正唛(2面)右下角贴条码贴纸各贴1张(即1面1张共2张),贴纸大小：2.75 x 1.5 inch。(跟单提供文档，工厂采购) Remark: 1. 产品外包装及产品本身都必须有日期跟踪码，格式为：ZURU 标准日期码。 2. ZURU QC验货，无测试。 3. 产品配比按照MA标准配比执行。 | V39: Yvonne Feng | W39: 0.5675 | X39: =W39*I39 -> 2951 | Y39: ZB03096-11.25 | Z39: =5096+104 -> 5200 | AA39: =Z39-I39 -> 0 | AD39: 77593GQ1-S001 | AE39: 已入 | AF39: =I39 -> 5200 | AG39: =AF39 -> 5200 | AI39: =I39 -> 5200 | AN39: =I39/13 -> 400 | AX39: =I39 -> 5200 | BA39: =I39*$BA$2 -> 650 | BB39: =I39*$BB$2 -> 541.66667 | BC39: =I39*$BC$2 -> 108.33333 | BD39: =I39*$BD$2 -> 650 | BE39: =I39*$BE$2 -> 650 | BF39: =I39*$BF$2 -> 650 | BG39: =I39*$BG$2 -> 650 | BH39: =I39*$BH$2 -> 650 | BI39: =I39*$BI$2 -> 650 | BK39: =BK38-BA39 -> 2017.75 | BL39: =BL38-BB39 -> 1857.9583 | BM39: =BM38-BD39 -> 2030.75 | BN39: =BN38-BC39 -> 246.79167 | BO39: =BO38-BE39 -> 152.75 | BP39: =BP38-BF39 -> 2030.75 | BQ39: =BQ38-BG39 -> 2030.75 | BR39: =BR38-BH39 -> 2430.75 | BS39: =BS38-BI39 -> 2030.75
A40: 45922 | B40: ROFU KINDERLAND SPIELWARENHANDELSGE | C40: 德国 | D40: 4500180040 | E40: 249680 | F40: 4500180040-10 | G40: 77593-S001-NB | H40: S4迷你恐龙24PCS入GQ2/箱 | I40: 5760 | J40: 0 | K40: 24 | L40: =I40/K40 -> 240 | M40: 45968 | N40: 45964 | P40: pass | Q40: 11/11 截SI | R40: 45940 | S40: 无 | T40: 11/17客供价格贴纸 | U40: 日期码格式：ZURU INC(BVI) 标准格式 日期：按实际生产日期 Packaging Info: 77593-S001(需更改无硼版本): 最新MA 3L+5LEAN包装+客供价格贴纸+5L警语收藏指南+5L Slime 袋 Remark: "1. 出口欧洲，微塑料需符合法规； 2. 所有电子产品身上需要加字唛，为ZURU FRANCE 地址 (如无电子产品/产品布标有此地址/产品太小无法增加，可忽略此信息) ZURU FRANCE 33 rue Paul Meurice 75020 Paris, France. 3. 所有出往德国订单的电子产品需增加一张客版WEEE声明说明书，区分带电池(WEEE 带电池走货 通用30L 说明书)和不带电池版本(WEEE 不带电池走货 通用30L 说 明书) 4. 此单需要在CRD前一天预约ZURU QC验货提供验货图片给客户确认才能出货 5. 需准时完成生产，推期出货会有罚款。 6. 此客户要求含布标的毛绒公仔，需要额外贴一张布标贴纸，区分电子产品（带电布标贴纸)和非电子产品(不带电布标贴纸)" | V40: Winnie zhong | W40: 0.9005 | X40: =W40*I40 -> 5186.88 | Y40: 96946-11.15 | Z40: 5760 | AA40: 0 | AD40: 77593-S001-NB | AE40: 已入 | AF40: =I40 -> 5760 | AH40: =I40 -> 5760 | AI40: =I40 -> 5760 | AO40: =I40/24 -> 240 | AY40: =I40 -> 5760 | BA40: =I40*$BA$2 -> 720 | BB40: =I40*$BB$2 -> 600 | BC40: =I40*$BC$2 -> 120 | BD40: =I40*$BD$2 -> 720 | BE40: =I40*$BE$2 -> 720 | BF40: =I40*$BF$2 -> 720 | BG40: =I40*$BG$2 -> 720 | BH40: =I40*$BH$2 -> 720 | BI40: =I40*$BI$2 -> 720 | BK40: =BK39-BA40 -> 1297.75 | BL40: =BL39-BB40 -> 1257.9583 | BM40: =BM39-BD40 -> 1310.75 | BN40: =BN39-BC40 -> 126.79167 | BO40: =BO39-BE40 -> -567.25 | BP40: =BP39-BF40 -> 1310.75 | BQ40: =BQ39-BG40 -> 1310.75 | BR40: =BR39-BH40 -> 1710.75 | BS40: =BS39-BI40 -> 1310.75
A41: 46008 | B41: HOBBY LOBBY STORES, INC. | C41: 美国 | D41: 4500188454 | E41: W0750693 | F41: 4500188454-70 | G41: 77593GQ1-S001 | H41: S4迷你恐龙13PCS/GQ1*4 | I41: 1820 | J41: 0 | K41: 52 | L41: =I41/K41 -> 35 | M41: 46045 | N41: 46042 | R41: 46008 | S41: 有 | T41: 12/17价格贴纸+外箱贴纸 | U41: 日期码格式：ZURU INC(BVI) 标准格式 日期：按实际生产日期 Packaging Info: 1. MA UPC版包装，优先1L，需要加贴价格贴纸, 贴在产品包装正面右上角(价格贴纸文档跟单提供)，出美国。 2. 外箱正唛(2面)右下角贴条码贴纸各贴1张(即1面1张共2张),贴纸大小：2.75 x 1.5 inch。(跟单提供文档，工厂采购) Remark: 1. 产品外包装及产品本身都必须有日期跟踪码，格式为：ZURU 标准日期码。 2. ZURU QC验货，无测试。 3. 产品配比按照MA标准配比执行。 | V41: Eleven Zhang | W41: 0.5759 | X41: =W41*I41 -> 1048.138 | AD41: 77593GQ1-S001 | AE41: 已入 | AF41: =I41 -> 1820 | AG41: =AF41 -> 1820 | AI41: =I41 -> 1820 | AN41: =I41/13 -> 140 | AX41: =I41 -> 1820 | BA41: =I41*$BA$2 -> 227.5 | BB41: =I41*$BB$2 -> 189.58333 | BC41: =I41*$BC$2 -> 37.916667 | BD41: =I41*$BD$2 -> 227.5 | BE41: =I41*$BE$2 -> 227.5 | BF41: =I41*$BF$2 -> 227.5 | BG41: =I41*$BG$2 -> 227.5 | BH41: =I41*$BH$2 -> 227.5 | BI41: =I41*$BI$2 -> 227.5 | BK41: =BK40-BA41 -> 1070.25 | BL41: =BL40-BB41 -> 1068.375 | BM41: =BM40-BD41 -> 1083.25 | BN41: =BN40-BC41 -> 88.875 | BO41: =BO40-BE41 -> -794.75 | BP41: =BP40-BF41 -> 1083.25 | BQ41: =BQ40-BG41 -> 1083.25 | BR41: =BR40-BH41 -> 1483.25 | BS41: =BS40-BI41 -> 1083.25
A42: 46008 | B42: NASA PANAMA | C42: 巴拿马 | D42: 4500189203 | F42: 4500189203-40 | G42: 77593GQ2-S001 | H42: S4迷你恐龙24PCS入GQ2*2/箱 | I42: 672 | J42: 0 | K42: 48 | L42: =I42/K42 -> 14 | M42: 46045 | N42: 46045 | R42: 欠 | S42: 无 | T42: 欠UPC贴纸 | U42: 日期码格式：ZURU INC(BVI) 标准格式 日期：按实际生产日期 Packaging Info: 请确保包装上的条形码是UPC，如果是babyUPC，需要用mother UPC覆盖，如有不一致，请及时提出。谢谢! 77593GQ2,,MA 多语EAN包装+UPC贴纸+MA多语收藏指南+MA PDQ+箱唛,, Remark: Common: Equal ratio | V42: Aimee Huang | W42: 0.9931 | X42: =W42*I42 -> 667.3632 | AD42: 77593GQ2-S001-3L | AE42: 已入 | AF42: =I42 -> 672 | AH42: =I42 -> 672 | AI42: =I42 -> 672 | AM42: =I42/24 -> 28 | AX42: =I42 -> 672 | BA42: =I42*$BA$2 -> 84 | BB42: =I42*$BB$2 -> 70 | BC42: =I42*$BC$2 -> 14 | BD42: =I42*$BD$2 -> 84 | BE42: =I42*$BE$2 -> 84 | BF42: =I42*$BF$2 -> 84 | BG42: =I42*$BG$2 -> 84 | BH42: =I42*$BH$2 -> 84 | BI42: =I42*$BI$2 -> 84
A43: 46027 | B43: TOYZOONA LIMITED | C43: 肯尼亚 | D43: 4500190681 | F43: 4500190681-30 | G43: 77593GQ2-S001 | H43: S4迷你恐龙24PCS入GQ2*2/箱 | I43: 288 | J43: 0 | K43: 48 | L43: =I43/K43 -> 6 | M43: 46057 | N43: =M43-4 -> 46053 | U43: 日期码格式：ZURU INC(BVI) 标准格式 日期：按实际生产日期 Packaging Info: MA PKG , 优先1L (需留意此单外箱上无客户名称） Remark: 此单按EXW +送货运费实报实销，需赶年前出货，请留意船务出货通知。 | V43: Chelsea Luo | W43: 0.9747 | X43: =W43*I43 -> 280.7136 | BA43: =I43*$BA$2 -> 36 | BB43: =I43*$BB$2 -> 30 | BC43: =I43*$BC$2 -> 6 | BD43: =I43*$BD$2 -> 36 | BE43: =I43*$BE$2 -> 36 | BF43: =I43*$BF$2 -> 36 | BG43: =I43*$BG$2 -> 36 | BH43: =I43*$BH$2 -> 36 | BI43: =I43*$BI$2 -> 36
X49: =SUM(X4:X48)*7.75 -> 591886.23 | AF49: =SUM(AF4:AF48)+AF51+AF53 -> 649110 | AG49: =SUM(AG4:AG48)+AG51+AG53 -> 570989 | AH49: =SUM(AH4:AH48)+AH51+AH53 -> 77881 | AI49: =SUM(AI4:AI48)+AI51+AI53 -> 648870 | AJ49: =SUM(AJ4:AJ48)+AJ51+AJ53 -> 500 | AK49: =SUM(AK4:AK48)+AK51+AK53 -> 500 | AL49: =SUM(AL4:AL48)+AL51+AL53 -> 6084 | AM49: =SUM(AM4:AM48)+AM51+AM53 -> 1494 | ... AY49: =SUM(AY4:AY48)+AY51+AY53 -> 31322 | BA49: =SUM(BA4:BA48)+BA51+BA53 -> 144036.75 | BB49: =SUM(BB4:BB48)+BB51+BB53 -> 120048.96 | BC49: =SUM(BC4:BC48)+BC51+BC53 -> 24097.792 | BD49: =SUM(BD4:BD48)+BD51+BD53 -> 144036.75 | BE49: =SUM(BE4:BE48)+BE51+BE53 -> 144036.75 | BF49: =SUM(BF4:BF48)+BF51+BF53 -> 144036.75 | BG49: =SUM(BG4:BG48)+BG51+BG53 -> 144036.75 | BH49: =SUM(BH4:BH48)+BH51+BH53 -> 144036.75 | BI49: =SUM(BI4:BI48)+BI51+BI53 -> 144036.75
H50: 24年年存+25年实际 | BK50: =MIN(BK4:BK47) -> 1070.25 | BL50: =MIN(BL4:BL47) -> 1068.375 | BM50: =MIN(BM4:BM47) -> 1083.25 | BN50: =MIN(BN4:BN47) -> 88.875 | BO50: =MIN(BO4:BO47) -> -794.75 | BP50: =MIN(BP4:BP47) -> 1083.25 | BQ50: =MIN(BQ4:BQ47) -> 1083.25 | BR50: =MIN(BR4:BR47) -> 1483.25 | BS50: =MIN(BS4:BS47) -> 1083.25
H51: =SUM(AF4:AF46) -> 90731 | AE51: 23年已删 | AX51: 0 | AY51: 4068 | BA51: 30159 | BB51: 25142.5 | BC51: 5076.5 | BD51: 30159 | BE51: 30159 | BF51: 30159 | BG51: 30159 | BH51: 30159 | BI51: 30159
X52: =SUM(X25:X26)*7.75 -> 27288.804
AE53: 24年已删 | AF53: 558379 | AG53: 523596 | AH53: 34783 | AI53: 558379 | AJ53: 368 | AK53: 368 | AL53: 5390 | AM53: 922 | AN53: 3615 | AO53: 485 | AP53: 23814 | AQ53: 73 | AR53: 0 | AS53: 73 | AT53: 8184 | AU53: 4752 | AV53: 3432 | AW53: 6233 | AX53: 779929 | AY53: 18278 | BA53: 102500.38 | BB53: 85425.313 | BC53: 17125.062 | BD53: 102500.38 | BE53: 102500.38 | BF53: 102500.38 | BG53: 102500.38 | BH53: 102500.38 | BI53: 102500.38 | BK53: =BK50-'77489 77593生产MA'!E17 -> 120 | BL53: =BL50-'77489 77593生产MA'!F17 -> 100 | BM53: =BM50-'77489 77593生产MA'!G17 -> 120 | BN53: =BN50-'77489 77593生产MA'!H17 -> 20 | BO53: =BO50-'77489 77593生产MA'!I17 -> 120 | BP53: =BP50-'77489 77593生产MA'!J17 -> 120 | BQ53: =BQ50-'77489 77593生产MA'!K17 -> 120 | BR53: =BR50-'77489 77593生产MA'!L17 -> 120 | BS53: =BS50-'77489 77593生产MA'!M17 -> 120
AJ56: =SUM(AJ4:AJ47) -> 132 | AL56: =SUM(AL4:AL47) -> 694 | AM56: =SUM(AM4:AM47) -> 572 | AQ56: =SUM(AQ4:AQ47) -> 227 | AR56: =SUM(AR4:AR47) -> 0 | BA56: =SUM(BA4:BA45) -> 11377.375 | BB56: =SUM(BB4:BB45) -> 9481.1458 | BC56: =SUM(BC4:BC45) -> 1896.2292 | BD56: =SUM(BD4:BD45) -> 11377.375 | BE56: =SUM(BE4:BE45) -> 11377.375 | BF56: =SUM(BF4:BF45) -> 11377.375 | BG56: =SUM(BG4:BG45) -> 11377.375 | BH56: =SUM(BH4:BH45) -> 11377.375 | BI56: =SUM(BI4:BI45) -> 11377.375
AY59: 生产报数 | BA59: =SUM(BA53,BA51,BA4:BA40) -> 143689.25 | BB59: =SUM(BB53,BB51,BB4:BB40) -> 119759.38 | BC59: =SUM(BC53,BC51,BC4:BC40) -> 24039.875 | BD59: =SUM(BD53,BD51,BD4:BD40) -> 143689.25 | BE59: =SUM(BE53,BE51,BE4:BE40) -> 143689.25 | BF59: =SUM(BF53,BF51,BF4:BF40) -> 143689.25 | BG59: =SUM(BG53,BG51,BG4:BG40) -> 143689.25 | BH59: =SUM(BH53,BH51,BH4:BH40) -> 143689.25 | BI59: =SUM(BI53,BI51,BI4:BI40) -> 143689.25

Sheet 77593 
A1: ZURU 5 surprise Dino S6（恐龙系列）生产排期表 #77489 | I1: 1.球壳 转为95mm 2半球壳 ,材料：20%PCR PP +80%PP原料 2.因考虑到某些地区对微塑胶（闪粉，闪粉喷油等）的限制，内部产品会同步做以下变更：---Slime 取消闪粉 3.更改为95mm 球壳后款号更新，请参考以下款号 4.PDQ，SK 刀线均有变化（请留意部分会带有demo）GQ2/SK/SK1有demo | AJ1: 普通款暴龙+卡车 | AL1: 双刺龙 | AR1: 普通款暴龙
I2: 欧洲国家有: (共有43个国家组成) 。芬兰、瑞典、挪威、冰岛、丹麦 法罗群岛(丹)、爱沙尼亚、拉脱维亚、立陶宛、白俄罗斯、俄罗斯、乌克兰、摩尔多瓦、波兰、捷克、斯洛伐克、匈牙利、德国、奥地利、瑞士、列支敦士登、英国、爱尔兰、荷兰、比利时、卢森堡、法国、摩纳哥、罗马尼亚、保加利亚、塞尔维亚、马其顿、阿尔巴尼亚、希腊、斯洛文尼亚、克罗地亚、波斯尼亚和墨塞哥维那、意大利、梵蒂冈、圣马力诺、马耳他、西班牙、葡萄牙、安道尔。 | AG2: 95MM收縮膜 | AI2: 95MM收藏指南 | AJ2: SK展示架 | AK2: 带底座 | AL2: 77593GQ2 | AN2: 77593GQ1 | AP2: 77593GQ5 | AQ2: SK1展示架 | AT2: 77614 2PK圆筒 | AW2: WM GQ4 | AX2: 口水胶 | AZ2: MA比例 | BA2: 0.125 | BB2: 0.10416667 | BC2: 0.020833333 | BD2: 0.125 | BE2: 0.125 | BF2: 0.125 | BG2: 0.125 | BH2: 0.125 | BI2: 0.125 | BJ2: MA | BK2: ='77489 77593生产MA'!E15-BA15-BA17-'77489 77593生产MA'!I29-BA19 -> 1297.75 | BL2: ='77489 77593生产MA'!F15-BB15-BB17-'77489 77593生产MA'!I30-'77489 77593生产MA'!I31-'77489 77593生产MA'!J33-'77489 77593生产MA'!K33-'77489 77593生产MA'!J35-'77489 77593生产MA'!K35-BB19 -> 1257.9583 | BM2: ='77489 77593生产MA'!G15-BD17-BD15-BD19 -> 1310.75 | BN2: ='77489 77593生产MA'!H15-BC17-BC15-BC19 -> 126.79167 | BO2: ='77489 77593生产MA'!I15-BE15-BE17-'77489 77593生产MA'!J34-'77489 77593生产MA'!K34-BE19 -> -567.25 | BP2: ='77489 77593生产MA'!J15-BF15-BF17-BF19 -> 1310.75 | BQ2: ='77489 77593生产MA'!K15-BG15-BG17-BG19 -> 1310.75 | BR2: ='77489 77593生产MA'!L15-BH15-BH17-'77489 77593生产MA'!K32-'77489 77593生产MA'!J32-BH19 -> 1710.75 | BS2: ='77489 77593生产MA'!M15-BI15-BI17-BI19 -> 1310.75
A3: 香港接单日期 | B3: 第三方客户名称 | C3: 走货国家 | D3: ZURU PO NO# | E3: 第三方客户 PO NO# | F3: SKU | G3: ITEM# | H3: 中文名 | I3: PO数量 (pcs) | J3: 内箱装箱数量(pcs) | K3: 外箱装箱数量(pcs) | L3: 总箱数 | M3: 客PO期 | N3: 验货期 | O3: 第三方验货期 | P3: 验货结果 | Q3: 船期 | R3: 箱唛资料(收到日期) | S3: 外箱贴纸 | T3: 客供贴纸AI(收到日期) | U3: 备注 | V3: ZURU 跟单 | W3: 单价USD | X3: 金额USD | Y3: 发票号 | Z3: 已送情况 | AA3: 欠数 | AB3: 贴纸 情况 | AC3: 是否入系统 | AD3: 系统货号 | AE3: 是否入系统 | AF3: 77593-95mm球壳 | AG3: MA 1L | AH3: MA 3L | AI3: MA 5L | AJ3: MA 1L | AL3: MA 1L | AM3: MA 3L | AN3: MA 1L | AO3: MA 3L | AP3: FD客版 | AQ3: MA 3L | AR3: MA 1L | AS3: 带底座 | AT3: 圆筒 | AU3: 彩纸 3L | AV3: 彩纸 1L | AW3: 客版 | AX3: 有硼无闪粉 | AY3: 无硼无闪粉 | BA3: Pterosaur 翼龙 | BB3: T-Rex 暴龙 | BC3: T-Rex (Rare) 暴龙（特别款） | BD3: Stegosaurus 剑龙 | BE3: Dilophosaurus 双棘龙 | BF3: Brontosaurus 雷龙 | BG3: Amargasaurus 阿玛加龙 | BH3: Truck 卡车 | BI3: Armed Helicoper 武装飞机 | BK3: Pterosaur 翼龙 | BL3: T-Rex 暴龙 | BM3: Stegosaurus 剑龙 | BN3: T-Rex (Rare) 暴龙（特别款） | BO3: Dilophosaurus 双棘龙 | BP3: Brontosaurus 雷龙 | BQ3: Amargasaurus 阿玛加龙 | BR3: Truck 卡车 | BS3: Armed Helicoper 武装飞机
A4: 46008 | B4: HOBBY LOBBY STORES, INC. | C4: 美国 | D4: 4500188454 | E4: W0750693 | F4: 4500188454-70 | G4: 77593GQ1-S001 | H4: S4迷你恐龙13PCS/GQ1*4 | I4: 1820 | J4: 0 | K4: 52 | L4: =I4/K4 -> 35 | M4: 46045 | N4: 46042 | P4: 自检 | Q4: 2/5 截SI | R4: 46008 | S4: 有 | T4: 12/17价格贴纸+外箱贴纸 | U4: 日期码格式：ZURU INC(BVI) 标准格式 日期：按实际生产日期 Packaging Info: 1. MA UPC版包装，优先1L，需要加贴价格贴纸, 贴在产品包装正面右上角(价格贴纸文档跟单提供)，出美国。 2. 外箱正唛(2面)右下角贴条码贴纸各贴1张(即1面1张共2张),贴纸大小：2.75 x 1.5 inch。(跟单提供文档，工厂采购) Remark: 1. 产品外包装及产品本身都必须有日期跟踪码，格式为：ZURU 标准日期码。 2. ZURU QC验货，无测试。 3. 产品配比按照MA标准配比执行。 | V4: Eleven Zhang | W4: 0.5759 | X4: =W4*I4 -> 1048.138 | Z4: 1820 | AB4: ok | AD4: 77593GQ1-S001 | AE4: 已入 | AF4: =I4 -> 1820 | AG4: =AF4 -> 1820 | AI4: =I4 -> 1820 | AN4: =I4/13 -> 140 | AX4: =I4 -> 1820 | BA4: =I4*$BA$2 -> 227.5 | BB4: =I4*$BB$2 -> 189.58333 | BC4: =I4*$BC$2 -> 37.916667 | BD4: =I4*$BD$2 -> 227.5 | BE4: =I4*$BE$2 -> 227.5 | BF4: =I4*$BF$2 -> 227.5 | BG4: =I4*$BG$2 -> 227.5 | BH4: =I4*$BH$2 -> 227.5 | BI4: =I4*$BI$2 -> 227.5 | BK4: =BK2-BA4 -> 1070.25 | BL4: =BL2-BB4 -> 1068.375 | BM4: =BM2-BD4 -> 1083.25 | BN4: =BN2-BC4 -> 88.875 | BO4: =BO2-BE4 -> -794.75 | BP4: =BP2-BF4 -> 1083.25 | BQ4: =BQ2-BG4 -> 1083.25 | BR4: =BR2-BH4 -> 1483.25 | BS4: =BS2-BI4 -> 1083.25
A5: 46008 | B5: NASA PANAMA | C5: 巴拿马 | D5: 4500189203 | F5: 4500189203-40 | G5: 77593GQ2-S001 | H5: S4迷你恐龙24PCS入GQ2*2/箱 | I5: 672 | J5: 0 | K5: 48 | L5: =I5/K5 -> 14 | M5: 46052 | N5: 46048 | P5: 自检 | Q5: 2/2 截SI | R5: 46028 | S5: 无 | T5: 1/6UPC贴纸 | U5: 日期码格式：ZURU INC(BVI) 标准格式 日期：按实际生产日期 Packaging Info: 请确保包装上的条形码是UPC，如果是babyUPC，需要用mother UPC覆盖，如有不一致，请及时提出。谢谢! 77593GQ2,,MA 多语EAN包装+UPC贴纸+MA多语收藏指南+MA PDQ+箱唛,, Remark: Common: Equal ratio | V5: Aimee Huang | W5: 0.9931 | X5: =W5*I5 -> 667.3632 | Z5: 672 | AB5: ok | AD5: 77593GQ2-S001-3L | AE5: 已入 | AF5: =I5 -> 672 | AH5: =I5 -> 672 | AI5: =I5 -> 672 | AM5: =I5/24 -> 28 | AX5: =I5 -> 672 | BA5: =I5*$BA$2 -> 84 | BB5: =I5*$BB$2 -> 70 | BC5: =I5*$BC$2 -> 14 | BD5: =I5*$BD$2 -> 84 | BE5: =I5*$BE$2 -> 84 | BF5: =I5*$BF$2 -> 84 | BG5: =I5*$BG$2 -> 84 | BH5: =I5*$BH$2 -> 84 | BI5: =I5*$BI$2 -> 84 | BK5: =BK4-BA5 -> 986.25 | BL5: =BL4-BB5 -> 998.375 | BM5: =BM4-BD5 -> 999.25 | BN5: =BN4-BC5 -> 74.875 | BO5: =BO4-BE5 -> -878.75 | BP5: =BP4-BF5 -> 999.25 | BQ5: =BQ4-BG5 -> 999.25 | BR5: =BR4-BH5 -> 1399.25 | BS5: =BS4-BI5 -> 999.25
A6: 46027 | B6: TOYZOONA LIMITED | C6: 肯尼亚 | D6: 4500190681 | F6: 4500190681-30 | G6: 77593GQ2-S001 | H6: S4迷你恐龙24PCS入GQ2*2/箱 | I6: 288 | J6: 0 | K6: 48 | L6: =I6/K6 -> 6 | M6: 46057 | N6: =M6-4 -> 46053 | P6: 自检 | Q6: 2/9 自提 | R6: 46027 | S6: 无 | T6: 无 | U6: 日期码格式：ZURU INC(BVI) 标准格式 日期：按实际生产日期 Packaging Info: MA PKG , 优先1L (需留意此单外箱上无客户名称） Remark: 此单按EXW +送货运费实报实销，需赶年前出货，请留意船务出货通知。 | V6: Chelsea Luo | W6: 0.9747 | X6: =W6*I6 -> 280.7136 | Z6: =240+48 -> 288 | AD6: 77593GQ2-S001 | AE6: 已入 | AF6: =I6 -> 288 | AG6: =AF6 -> 288 | AI6: =I6 -> 288 | AL6: =I6/24 -> 12 | AX6: =I6 -> 288 | BA6: =I6*$BA$2 -> 36 | BB6: =I6*$BB$2 -> 30 | BC6: =I6*$BC$2 -> 6 | BD6: =I6*$BD$2 -> 36 | BE6: =I6*$BE$2 -> 36 | BF6: =I6*$BF$2 -> 36 | BG6: =I6*$BG$2 -> 36 | BH6: =I6*$BH$2 -> 36 | BI6: =I6*$BI$2 -> 36 | BK6: =BK5-BA6 -> 950.25 | BL6: =BL5-BB6 -> 968.375 | BM6: =BM5-BD6 -> 963.25 | BN6: =BN5-BC6 -> 68.875 | BO6: =BO5-BE6 -> -914.75 | BP6: =BP5-BF6 -> 963.25 | BQ6: =BQ5-BG6 -> 963.25 | BR6: =BR5-BH6 -> 1363.25 | BS6: =BS5-BI6 -> 963.25
A7: 46055 | B7: HOBBY LOBBY STORES, INC. | C7: 美国 | D7: 4500192693 | E7: W0758454 | F7: 4500192693-60 | G7: 77593GQ1-S001 | H7: S4迷你恐龙13PCS/GQ1*4 | I7: 3380 | J7: 0 | K7: 52 | L7: =I7/K7 -> 65 | M7: 46115 | N7: 46111 | R7: 46059 | S7: 有 | T7: 2/6价格贴纸+外箱条码贴纸 | U7: 日期码格式：ZURU INC(BVI) 标准格式 日期：按实际生产日期 Packaging Info: 1. MA 优先1L UPC版包装,需要加贴价格贴纸, 贴在产品包装正面右上角(价格贴纸文档跟单提供)，出美国。 2. 外箱正唛(2面)右下角贴条码贴纸各贴1张(即1面1张共2张),贴纸大小：2.75 x 1.5 inch。(跟单提供文档，工厂采购) Remark: 1. 产品外包装及产品本身都必须有日期跟踪码，格式为：ZURU 标准日期码。 2. ZURU QC验货，无测试。 3. 产品配比按照MA标准配比执行。 | V7: Eleven Zhang | W7: 0.5701 | X7: =W7*I7 -> 1926.938 | AF7: =I7 -> 3380 | AG7: =AF7 -> 3380 | AI7: =I7 -> 3380 | AN7: =I7/13 -> 260 | AX7: =I7 -> 3380 | BA7: =I7*$BA$2 -> 422.5 | BB7: =I7*$BB$2 -> 352.08333 | BC7: =I7*$BC$2 -> 70.416667 | BD7: =I7*$BD$2 -> 422.5 | BE7: =I7*$BE$2 -> 422.5 | BF7: =I7*$BF$2 -> 422.5 | BG7: =I7*$BG$2 -> 422.5 | BH7: =I7*$BH$2 -> 422.5 | BI7: =I7*$BI$2 -> 422.5 | BK7: =BK6-BA7 -> 527.75 | BL7: =BL6-BB7 -> 616.29167 | BM7: =BM6-BD7 -> 540.75 | BN7: =BN6-BC7 -> -1.5416667 | BO7: =BO6-BE7 -> -1337.25 | BP7: =BP6-BF7 -> 540.75 | BQ7: =BQ6-BG7 -> 540.75 | BR7: =BR6-BH7 -> 940.75 | BS7: =BS6-BI7 -> 540.75
X13: =SUM(X4:X12)*7.75 -> 30404.434 | AF13: =SUM(AF4:AF12)+AF15+AF17+AF19 -> 652778 | AG13: =SUM(AG4:AG12)+AG15+AG17+AG19 -> 574657 | AH13: =SUM(AH4:AH12)+AH15+AH17+AH19 -> 77881 | AI13: =SUM(AI4:AI12)+AI15+AI17+AI19 -> 652538 | AJ13: =SUM(AJ4:AJ12)+AJ15+AJ17+AJ19 -> 500 | AK13: =SUM(AK4:AK12)+AK15+AK17+AK19 -> 500 | AL13: =SUM(AL4:AL12)+AL15+AL17+AL19 -> 6096 | AM13: =SUM(AM4:AM12)+AM15+AM17+AM19 -> 1494 | ... BI13: =SUM(BI4:BI12)+BI15+BI17+BI19 -> 144459.25
H14: 25年年存+26年实际 | BK14: =MIN(BK4:BK11) -> 527.75 | BL14: =MIN(BL4:BL11) -> 616.29167 | BM14: =MIN(BM4:BM11) -> 540.75 | BN14: =MIN(BN4:BN11) -> -1.5416667 | BO14: =MIN(BO4:BO11) -> -1337.25 | BP14: =MIN(BP4:BP11) -> 540.75 | BQ14: =MIN(BQ4:BQ11) -> 540.75 | BR14: =MIN(BR4:BR11) -> 940.75 | BS14: =MIN(BS4:BS11) -> 540.75
H15: =SUM(AF4:AF10) -> 6160 | AE15: 23年已删 | AX15: 0 | AY15: 4068 | BA15: 30159 | BB15: 25142.5 | BC15: 5076.5 | BD15: 30159 | BE15: 30159 | BF15: 30159 | BG15: 30159 | BH15: 30159 | BI15: 30159
X16: =SUM(#REF!)*7.75 -> #REF!
AE17: 24年已删 | AF17: 558379 | AG17: 523596 | AH17: 34783 | AI17: 558379 | AJ17: 368 | AK17: 368 | AL17: 5390 | AM17: 922 | AN17: 3615 | AO17: 485 | AP17: 23814 | AQ17: 73 | AR17: 0 | AS17: 73 | AT17: 8184 | AU17: 4752 | AV17: 3432 | AW17: 6233 | AX17: 779929 | AY17: 18278 | BA17: 102500.38 | BB17: 85425.313 | BC17: 17125.062 | BD17: 102500.38 | BE17: 102500.38 | BF17: 102500.38 | BG17: 102500.38 | BH17: 102500.38 | BI17: 102500.38 | BK17: =BK14-'77489 77593生产MA'!E17 -> -422.5 | BL17: =BL14-'77489 77593生产MA'!F17 -> -352.08333 | BM17: =BM14-'77489 77593生产MA'!G17 -> -422.5 | BN17: =BN14-'77489 77593生产MA'!H17 -> -70.416667 | BO17: =BO14-'77489 77593生产MA'!I17 -> -422.5 | BP17: =BP14-'77489 77593生产MA'!J17 -> -422.5 | BQ17: =BQ14-'77489 77593生产MA'!K17 -> -422.5 | BR17: =BR14-'77489 77593生产MA'!L17 -> -422.5 | BS17: =BS14-'77489 77593生产MA'!M17 -> -422.5
AE19: 25年已删 | AF19: 88239 | AG19: 45573 | AH19: 42426 | AI19: 87999 | AJ19: 132 | AK19: 132 | AL19: 694 | AM19: 544 | AN19: 1105 | AO19: 240 | AP19: 2707 | AQ19: 227 | AR19: 0 | AS19: 227 | AT19: 1008 | AU19: 1008 | AV19: 0 | AW19: 0 | AX19: 79263 | AY19: 8976 | AZ19: 0 | BA19: 11029.875 | BB19: 9191.5625 | BC19: 1838.3125 | BD19: 11029.875 | BE19: 11029.875 | BF19: 11029.875 | BG19: 11029.875 | BH19: 11029.875 | BI19: 11029.875
AJ20: =SUM(AJ4:AJ11) -> 0 | AL20: =SUM(AL4:AL11) -> 12 | AM20: =SUM(AM4:AM11) -> 28 | AQ20: =SUM(AQ4:AQ11) -> 0 | AR20: =SUM(AR4:AR11) -> 0 | BA20: =SUM(BA4:BA9) -> 770 | BB20: =SUM(BB4:BB9) -> 641.66667 | BC20: =SUM(BC4:BC9) -> 128.33333 | BD20: =SUM(BD4:BD9) -> 770 | BE20: =SUM(BE4:BE9) -> 770 | BF20: =SUM(BF4:BF9) -> 770 | BG20: =SUM(BG4:BG9) -> 770 | BH20: =SUM(BH4:BH9) -> 770 | BI20: =SUM(BI4:BI9) -> 770

Sheet 77489 77593生产MA
A1: ZURU 77489 Dino Strike S6 生产MA扣数
A2: MA訂單號 | B2: 日期 | C2: 85MM 球 | D2: 95MM 球 | E2: Pterosaur 翼龙 | F2: T-Rex 暴龙 | G2: Stegosaurus 剑龙 | H2: T-Rex (Rare) 暴龙（特别款） | I2: Dilophosaurus 双棘龙 | J2: Brontosaurus 雷龙 | K2: Amargasaurus 阿玛加龙 | L2: Truck 卡车 | M2: Armed Helicoper 武装飞机 | N2: 9款合計 | O2: Slime有硼 | P2: Slime无硼 | Q2: Slime无硼-无闪粉 | R2: Slime有硼-无闪粉 | S2: 要求完成时间 | T2: 口水胶原MOQ 5W，客人沟通确认最终可按2W接单
A3: MA-RR-907 | B3: 45095 | C3: 160000 | E3: 20000 | F3: 16666.667 | G3: 20000 | H3: 3333.3333 | I3: 20000 | J3: 20000 | K3: 20000 | L3: 20000 | M3: 20000 | N3: =SUM(E3:M3) -> 160000 | O3: 110000 | S3: 45145 | T3: 85MMM球壳
A4: MA-RR-907 | B4: 45095 | O4: 50000 | S4: 新增口水胶 | T4: 85MMM球壳
A5: MA-RR-980 | B5: 45196 | C5: 160000 | E5: 20000 | F5: 16666.667 | G5: 20000 | H5: 3333.3333 | I5: 20000 | J5: 20000 | K5: 20000 | L5: 20000 | M5: 20000 | N5: =SUM(E5:M5) -> 160000 | O5: 85000 | P5: 15000 | R5: 60000 | S5: 45246 | T5: 85MMM球壳
A6: MA-RR-1025 | B6: 45268 | C6: 100000 | E6: 25000 | F6: 20833.333 | G6: 25000 | H6: 4166.6667 | I6: 25000 | J6: 25000 | K6: 25000 | L6: 25000 | M6: 25000 | N6: =SUM(E6:M6) -> 200000 | Q6: 15000 | R6: 100000 | S6: 45304 | T6: 85MMM球壳
A7: MA-RR-1025 | D7: 50000 | E7: 103 | F7: 700 | I7: 2000 | L7: 500 | N7: =SUM(E7:M7) -> 3303 | S7: 45304 | T7: 增加95MM球壳50K，增加对应DEMO公仔数量
A8: MA-RR-1085 | B8: 45345 | C8: 100000 | D8: 110000 | E8: 20000 | F8: 16666.667 | G8: 20000 | H8: 3333.3333 | I8: 20000 | J8: 20000 | K8: 20000 | L8: 20000 | M8: 20000 | N8: =SUM(E8:M8) -> 160000 | Q8: 20000 | R8: =135000+70000 -> 205000 | S8: 45381
A9: MA-RR-1184 | B9: 45407 | D9: 160000 | E9: 20000 | F9: 16666.667 | G9: 20000 | H9: 3333.3333 | I9: 20000 | J9: 20000 | K9: 20000 | L9: 20000 | M9: 20000 | N9: =SUM(E9:M9) -> 160000 | R9: =60000+120000 -> 180000 | S9: 45448
A10: MA-RR-1298 | B10: 45470 | D10: 160000 | E10: 20000 | F10: 16666.667 | G10: 20000 | H10: 3333.3333 | I10: 20000 | J10: 20000 | K10: 20000 | L10: 20000 | M10: 20000 | N10: =SUM(E10:M10) -> 160000 | R10: 100000 | S10: 45549
B11: 45470 | I11: 700 | N11: =SUM(E11:M11) -> 700
A12: MA-RR-1363 | B12: 45532 | D12: 160000 | E12: 20000 | F12: 16666.667 | G12: 20000 | H12: 3333.3333 | I12: 20000 | J12: 20000 | K12: 20000 | L12: 20000 | M12: 20000 | N12: =SUM(E12:M12) -> 160000 | R12: =160000+60000 -> 220000 | S12: 45599
F13: 500 | I13: 3000 | L13: 400 | N13: =SUM(E13:M13) -> 3900
N14: =SUM(E14:M14) -> 0
B15: MA合計 | C15: =SUM(C3:C14) -> 520000 | D15: =SUM(D3:D14) -> 640000 | E15: =SUM(E3:E14) -> 145103 | F15: =SUM(F3:F14) -> 122033.33 | G15: =SUM(G3:G14) -> 145000 | H15: =SUM(H3:H14) -> 24166.667 | I15: =SUM(I3:I14) -> 150700 | J15: =SUM(J3:J14) -> 145000 | ... R15: =SUM(R3:R14) -> 865000
B16: 接单数量 | C16: 503096 | D16: ='77593旧排期'!AF49 -> 649110 | E16: ='77593旧排期'!BA49+I29 -> 144152.75 | F16: ='77593旧排期'!BB49+I30+J33+J35+K33+K35+I31 -> 121064.96 | G16: ='77593旧排期'!BD49 -> 144036.75 | H16: ='77593旧排期'!BC49 -> 24097.792 | I16: ='77593旧排期'!BE49+J34+K34 -> 151614.75 | J16: ='77593旧排期'!BF49 -> 144036.75 | K16: ='77593旧排期'!BG49 -> 144036.75 | L16: ='77593旧排期'!BH49+J32+K32 -> 144536.75 | M16: ='77593旧排期'!BI49 -> 144036.75 | N16: =SUM(E16:M16) -> 1161614 | O16: 244996 | P16: 14720 | Q16: ='77593旧排期'!AY49 -> 31322 | R16: ='77593旧排期'!AX49 -> 861684
B17: MA半成品剩余数 | C17: =C15-C16 -> 16904 | D17: =D15-D16 -> -9110 | E17: =E15-E16 -> 950.25 | F17: =F15-F16 -> 968.375 | G17: =G15-G16 -> 963.25 | H17: =H15-H16 -> 68.875 | I17: =I15-I16 -> -914.75 | J17: =J15-J16 -> 963.25 | ... R17: =R15-R16 -> 3316
C18: 清零
D19: 实际库存 | E19: 1740 | F19: 1640 | G19: 2640 | H19: 440 | I19: 2240 | J19: 2240 | K19: 2640 | L19: 2540 | M19: 2640 | N19: 合计放订口水胶 | P19: =O15+P15+Q15+R15 -> 1160000
F21: 库存合计数 | G21: =SUM(E19:M19) -> 18760 | N21: 剩余未订购口水胶数 | P21: =N15-P19 -> 7903
E22: 0.125 | F22: 0.10416667 | G22: 0.125 | H22: 0.020833333 | I22: 0.125 | J22: 0.125 | K22: 0.125 | L22: 0.125 | M22: 0.125
C23: 能接单合计 | D23: 13900 | E23: =$D$23*E22 -> 1737.5 | F23: =$D$23*F22 -> 1447.9167 | G23: =$D$23*G22 -> 1737.5 | H23: =$D$23*H22 -> 289.58333 | I23: =$D$23*I22 -> 1737.5 | J23: =$D$23*J22 -> 1737.5 | K23: =$D$23*K22 -> 1737.5 | L23: =$D$23*L22 -> 1737.5 | M23: =$D$23*M22 -> 1737.5
E25: =E23-E19 -> -2.5 | F25: =F23-F19 -> -192.08333 | G25: =G23-G19 -> -902.5 | H25: =H23-H19 -> -150.41667 | I25: =I23-I19 -> -502.5 | J25: =J23-J19 -> -502.5 | K25: =K23-K19 -> -902.5 | L25: =L23-L19 -> -802.5 | M25: =M23-M19 -> -902.5
G27: 展示公仔
G28: ITEM | H28: 名称 | I28: 23年已删掉 | J28: 24年已删 | K28: 25年
G29: 77489SK | H29: 翼龙 | I29: 116
H30: 普通暴龙 | I30: 116
G31: 77489SK1 | H31: 普通款暴龙 | I31: 100
G32: 77593SK | H32: 卡车 | J32: 368 | K32: ='77593旧排期'!AJ56 -> 132
H33: 普通款暴龙 | J33: 368 | K33: =K32 -> 132
G34: 77593GQ2 | H34: 双刺龙 | J34: 6312 | K34: ='77593旧排期'!AL56+'77593旧排期'!AM56 -> 1266
G35: 77593SK1 | H35: 普通款暴龙 | J35: 73 | K35: ='77593旧排期'!AR56+'77593旧排期'!AQ56 -> 227
G36: 合计 | I36: =SUM(I29:I35) -> 332 | J36: =SUM(J29:J35) -> 7121 | K36: =SUM(K29:K35) -> 1757 | M36: =SUM(I36:K36) -> 9210

Sheet 77489 77593包装MA
A1: 5 surprise Dino S6（恐龙系列）MA包裝扣数表 | X1: 5 surprise Dino S6 77593（恐龙系列）MA包裝扣数表
A2: 日期 | B2: MA PO | C2: 货号 | D2: 包材 | E2: 数量 | F2: 版本 | G2: ZURU跟进负责人员 | H2: 收縮膜 | J2: 收藏指南 | K2: GQ2 PDQ盒 | M2: GQ1 PDQ盒 | O2: 77523 2 PK | S2: SK展示架 | X2: 日期 | Y2: MA PO | Z2: 货号 | AA2: 包材 | AB2: 数量 | AC2: 版本 | AD2: ZURU跟进负责人员 | AE2: 收縮膜 | AG2: 收藏指南 | AH2: SK展示架 | AJ2: SK1展示架 | AM2: GQ2 | AO2: GQ1 | AQ2: GQ4 | AR2: 77614 2PK
H3: MA 1L A版本 | I3: MA 3L A版本 | J3: MA 5L A版本 | K3: MA 1L | L3: MA 3L | M3: MA 1L | N3: MA 3L | O3: 无UPC条码收缩膜 | P3: PVC圆筒 | Q3: 彩纸 | R3: SK1 | S3: MA 1L | T3: 底座 | V3: 备注 | AE3: MA 1L A版本 | AF3: MA 3L A版本 | AG3: MA 5L A版本 | AH3: MA 1L | AI3: 底座 | AJ3: MA 1L | AK3: MA 3L | AL3: 底座 | AM3: MA 1L | AN3: MA 3L | AO3: MA 1L | AP3: MA 3L | AQ3: WM客版 | AR3: 圆筒 | AS3: 彩纸1L | AT3: 彩纸3L | AV3: 备注
A4: 45142 | B4: 1000015853 | C4: 77489 | D4: shrink wrap | E4: 70000 | F4: A 1L | G4: Philo Yuan | H4: =E4 -> 70000 | X4: 45302 | Y4: 1000018190 | Z4: 77593 | AA4: collector guide | AB4: 30000 | AC4: 5L | AD4: Philo Yuan | AG4: =AB4 -> 30000 | AV4: 说明书请对应每款公仔的Ratio配套订，不单独建MA number
A5: 45142 | B5: 1000015854 | C5: 77489 | D5: collector guide | E5: 70000 | F5: A 5L | G5: Philo Yuan | J5: =E5 -> 70000 | V5: 说明书请对应每款公仔的Ratio配套订，不单独建MA number | X5: 45302 | Y5: 1000018192 | Z5: 77593 | AA5: shrink wrap | AB5: 30000 | AC5: 1L | AD5: Philo Yuan | AE5: =AB5 -> 30000
A6: 45142 | B6: 1000015855 | C6: 77489GQ1 | D6: PDQ 12pcs | E6: 1000 | F6: A 1L | G6: Philo Yuan | M6: =E6 -> 1000 | X6: 45352 | Y6: 1000018720 | Z6: 77593GQ2 | AA6: PDQ 24 pcs | AB6: 748 | AC6: 1L | AD6: Philo Yuan | AM6: =AB6 -> 748
A7: 45148 | B7: 1000015926 | C7: 77489GQ2 | D7: PDQ 24 pcs | E7: 1000 | F7: A 1L | G7: Philo Yuan | K7: =E7 -> 1000 | X7: 45358 | Y7: 1000018817 | Z7: 77614 | AA7: PVC Tube(2PK) | AB7: 2280 | AC7: 客版 | AR7: =AB7 -> 2280 | AV7: Crystal用于#4500125765-504pcs；#4500125759-504pcs；#4500125756-504pcs；#4500124874-768pcs
A8: 45161 | B8: 1000016130 | C8: 77489GQ2 | D8: PDQ 24 pcs | E8: 500 | F8: A 1L | G8: Philo Yuan | K8: =E8 -> 500 | X8: 45358 | Y8: 1000018818 | Z8: 77614 | AA8: Art Paper | AB8: 2280 | AC8: 1L | AS8: =AB8 -> 2280 | AV8: Crystal用于#4500125765-504pcs；#4500125759-504pcs；#4500125756-504pcs；#4500124874-768pcs
A9: 45161 | B9: 1000016131 | C9: 77489SK-S001 | D9: Sidekick | E9: 300 | F9: A 1L | G9: Philo Yuan | S9: =E9 -> 300 | X9: 45358 | Y9: 1000018819 | Z9: 77614 | AA9: Sticker | AB9: 2280 | AC9: 客版 | AV9: Crystal用于#4500125765-504pcs；#4500125759-504pcs；#4500125756-504pcs；#4500124874-768pcs
A10: 45161 | B10: 1000016132 | C10: 77489SK-S002 | D10: Base | E10: 200 | F10: A 1L | G10: Philo Yuan | T10: =E10 -> 200 | X10: 45372 | Y10: 1000019034 | Z10: 77593GQ1 | AA10: PDQ 13 pcs | AB10: 500 | AC10: 1L | AD10: Philo Yuan | AO10: =AB10 -> 500
A11: 45196 | B11: 1000016557 | C11: 77489 | D11: shrink wrap | E11: 90000 | F11: A 1L | G11: Philo Yuan | H11: =E11 -> 90000 | X11: 45383 | Y11: 1000019252 | Z11: 77593GQ4 | AA11: PDQ 13 | AB11: 6143 | AC11: 1L | AD11: Daisy.Li | AQ11: 6143 | AV11: Maggie 用于订单 4500128532 4500128533 4500128867 4500128863 4500128865 4500128864 4500128866
A12: 45196 | B12: 1000016561 | C12: 77489 | D12: shrink wrap | E12: 10000 | F12: A 3L | G12: Philo Yuan | I12: =E12 -> 10000 | X12: 45392 | Y12: 1000019480 | Z12: 77614 | AA12: PVC Tube(2PK) | AB12: 1000 | AC12: 客版 | AD12: Peggy Wu | AR12: =AB12 -> 1000 | AV12: Agnes用于#4500127793，剩余数量可用于其他订单4500128123
A13: 45196 | B13: 1000016558 | C13: 77489 | D13: collector guide | E13: 100000 | F13: A 5L | G13: Philo Yuan | J13: =E13 -> 100000 | V13: 说明书请对应每款公仔的Ratio配套订，不单独建MA number | X13: 45392 | Y13: 1000019482 | Z13: 77614 | AA13: Art Paper | AB13: 1000 | AC13: 客版 | AD13: Peggy Wu | AS13: =AB13 -> 1000 | AV13: Agnes用于#4500127793，剩余数量可用于其他订单4500128123
A14: 45196 | B14: 1000016559 | C14: 77489GQ1 | D14: PDQ 12pcs | E14: 10000 | F14: A 1L | G14: Philo Yuan | M14: =E14 -> 10000 | X14: 45392 | Y14: 1000019483 | Z14: 77614 | AA14: Sticker | AB14: 1000 | AC14: 客版 | AD14: Peggy Wu | AR14: 152 | AS14: 152 | AV14: Agnes用于#4500127793，剩余数量可用于其他订单
A15: 45196 | B15: 1000016560 | C15: 77489GQ1 | D15: PDQ 12pcs | E15: 500 | F15: A 3L | G15: Philo Yuan | N15: =E15 -> 500 | X15: 45394 | Y15: 1000019569 | Z15: 77593 | AA15: collector guide | AB15: 100000 | AC15: 5L | AD15: Philo Yuan | AG15: =AB15 -> 100000 | AV15: 说明书请对应每款公仔的Ratio配套订，不单独建MA number
A16: 45231 | B16: 10000017007 | C16: 77489 | D16: shrink wrap | E16: 80000 | F16: A 1L | G16: Philo Yuan | H16: =E16 -> 80000 | X16: 45394 | Y16: 1000019570 | Z16: 77593 | AA16: shrink wrap | AB16: 70000 | AC16: 1L | AD16: Philo Yuan | AE16: =AB16 -> 70000
A17: 45231 | B17: 10000017008 | C17: 77489 | D17: collector guide | E17: 85000 | F17: A 5L | G17: Philo Yuan | J17: =E17 -> 85000 | V17: 说明书请对应每款公仔的Ratio配套订，不单独建MA number | X17: 45394 | Y17: 1000019583 | Z17: 77593 | AA17: shrink wrap | AB17: 30000 | AC17: 3L | AD17: Philo Yuan | AF17: =AB17 -> 30000
A18: 45231 | B18: 10000017009 | C18: 77489GQ1 | D18: PDQ 12pcs | E18: 3000 | F18: A 1L | G18: Philo Yuan | M18: =E18 -> 3000 | X18: 45394 | Y18: 1000019571 | Z18: 77593GQ2 | AA18: PDQ 24 pcs | AB18: 500 | AC18: 1L | AD18: Philo Yuan | AM18: =AB18 -> 500
A19: 45231 | B19: 10000017010 | C19: 77489GQ1 | D19: PDQ 12pcs | E19: 500 | F19: A 3L | G19: Philo Yuan | N19: =E19 -> 500 | X19: 45394 | Y19: 1000019584 | Z19: 77593GQ2 | AA19: PDQ 24 pcs | AB19: 500 | AC19: 3L | AD19: Philo Yuan | AN19: =AB19 -> 500
A20: 45231 | B20: 10000017011 | C20: 77489GQ2 | D20: PDQ 24 pcs | E20: 500 | F20: A 1L | G20: Philo Yuan | K20: =E20 -> 500 | X20: 45401 | Y20: 1000019689 | Z20: 77593 | AA20: shrink wrap | AB20: 30000 | AC20: 1L | AD20: Philo Yuan | AE20: =AB20 -> 30000
A21: 45232 | B21: 1000017037 | C21: 77523 | D21: PVC Tube | E21: 2608 | F21: 1L | G21: Crystal | P21: =E21 -> 2608 | V21: Crystal用于#4500114791-512pcs;#4500114794 -512pcs;#4500114776-512pcs;#4500114788-560pcs;#4500114790-512pcs | X21: 45407 | Y21: 1000019840 | Z21: 77593GQ4 | AA21: PDQ | AB21: 500 | AC21: N/A | AD21: Daisy.Li | AQ21: =AB21 -> 500 | AV21: Maggie 用于订单 4500131238
A22: 45232 | B22: 1000017038 | C22: 77523 | D22: Art Paper | E22: 2608 | F22: 1L | G22: Crystal | Q22: =E22 -> 2608 | V22: Crystal用于#4500114791-512pcs;#4500114794 -512pcs;#4500114776-512pcs;#4500114788-560pcs;#4500114790-512pcs | X22: 45419 | Y22: 1000020079 | Z22: 77593 | AA22: collector guide | AB22: 50000 | AC22: 5L | AD22: Philo Yuan | AG22: =AB22 -> 50000
A23: 45232 | B23: 1000017039 | C23: 77523 | D23: Lid sticker | E23: 2608 | F23: 1L | G23: Crystal | V23: Crystal用于#4500114791-512pcs;#4500114794 -512pcs;#4500114776-512pcs;#4500114788-560pcs;#4500114790-512pcs | X23: 45419 | Y23: 1000020080 | Z23: 77593 | AA23: shrink wrap | AB23: 50000 | AC23: 1L | AD23: Philo Yuan | AE23: =AB23 -> 50000
A24: 45232 | B24: 1000017102 | C24: 77523 | D24: Shrink Wrap | E24: 5216 | F24: 1L | G24: Jenny Shen | O24: =E24 -> 5216 | V24: Crystal用于#4500114791-512pcs;#4500114794 -512pcs;#4500114776-512pcs;#4500114788-560pcs;#4500114790-512pcs | X24: 45419 | Y24: 1000020081 | Z24: 77593GQ1 | AA24: PDQ 13 pcs | AB24: 500 | AC24: 1L | AD24: Philo Yuan | AO24: =AB24 -> 500
A25: 45253 | B25: 1000017412 | C25: 77489 | D25: shrink wrap | E25: 30000 | F25: 1L | G25: Philo Yuan | H25: =E25 -> 30000 | X25: 45419 | Y25: 1000020104 | Z25: 77593GQ1 | AA25: PDQ 13 pcs | AB25: 500 | AC25: 3L | AD25: Philo Yuan | AP25: =AB25 -> 500
A26: 45253 | B26: 1000017413 | C26: 77489 | D26: collector guide | E26: 30000 | F26: 5L | G26: Philo Yuan | J26: =E26 -> 30000 | V26: 说明书请对应每款公仔的Ratio配套订，不单独建MA number | X26: 45446 | Y26: 此单按单订购不另建MA PO | Z26: 77614 | AA26: PVC Tube(2PK) | AB26: 504 | AD26: Jenny Shen | AR26: =AB26 -> 504 | AV26: Crystal用于订单4500134977
A27: 45253 | B27: 1000017414 | C27: 77489GQ1 | D27: PDQ 12pcs | E27: 1043 | F27: 1L | G27: Philo Yuan | M27: =E27 -> 1043 | X27: 45446 | Y27: 此单按单订购不另建MA PO | Z27: 77614 | AA27: Art Paper（2PK) | AB27: 504 | AC27: 3L | AD27: Jenny Shen | AT27: =AB27 -> 504 | AV27: Crystal用于订单4500134977
A28: 45253 | B28: 1000017417 | C28: 77489GQ2 | D28: PDQ 24 pcs | E28: 500 | F28: 1L | G28: Philo Yuan | K28: =E28 -> 500 | X28: 45446 | Y28: 此单按单订购不另建MA PO | Z28: 77614 | AA28: Lid sticker(2PK) | AB28: 504 | AD28: Jenny Shen | AV28: Crystal用于订单4500134977
A29: 45253 | B29: 1000017416 | C29: 77489SK1 | D29: Sidekick | E29: 100 | F29: 1L | G29: Philo Yuan | R29: =E29 -> 100 | X29: 45449 | Y29: 此单按单订购不另建MA PO | Z29: 77614 | AA29: Sticker | AB29: 1020 | AD29: Violet Chen | AV29: Cora用于订单Bealls outlet 4500131027
A30: 45257 | B30: 1000017461 | C30: 77523 | D30: Art Paper（2PK) | E30: 2368 | F30: 1L | G30: Peggy Wu | Q30: =E30 -> 2368 | V30: 用于Yvonne 4500116752/4500118409/4500116774 | X30: 45449 | Y30: 此单按单订购不另建MA PO | Z30: 77614 | AA30: Art Paper | AB30: 1020 | AC30: 1L | AD30: Violet Chen | AT30: =AB30 -> 1020 | AV30: Cora用于订单Bealls outlet 4500131027
A31: 45257 | B31: 1000017462 | C31: 77523 | D31: PVC Tube(2PK) | E31: 2368 | F31: 1/3L共用 | G31: Peggy Wu | P31: =E31 -> 2368 | V31: 用于Yvonne 4500116752/4500118409/4500116774 | X31: 45456 | Y31: 1000021039 | Z31: 77593 | AA31: shrink wrap | AB31: 90000 | AC31: 1L | AD31: Philo Yuan | AE31: =AB31 -> 90000
A32: 45257 | B32: 1000017463 | C32: 77523 | D32: Shrink Wrap(without UPC) | E32: 4736 | F32: 1L without UPC | G32: Peggy Wu | O32: =E32 -> 4736 | V32: 用于Yvonne 4500116752/4500118409/4500116774 | X32: 45456 | Y32: 1000021040 | Z32: 77593 | AA32: collector guide | AB32: 100000 | AC32: 5L | AD32: Philo Yuan | AG32: =AB32 -> 100000
A33: 45261 | B33: 1000017613 | C33: 77489GQ1 | D33: PDQ 12pcs | E33: 2192 | F33: 1L | G33: Philo Yuan | M33: =E33 -> 2192 | X33: 45456 | Y33: 1000021041 | Z33: 77593GQ1 | AA33: PDQ 13 pcs | AB33: 785 | AC33: 1L | AD33: Philo Yuan | AO33: =AB33 -> 785
A34: 45273 | B34: 1000017790 | C34: 77489 | D34: collector guide | E34: 100000 | F34: 5L | G34: Philo Yuan | J34: =E34 -> 100000 | V34: 说明书请对应每款公仔的Ratio配套订，不单独建MA number | X34: 45470 | Y34: 1000021339 | Z34: 77593 | AA34: collector guide | AB34: 20000 | AC34: 5L | AD34: Philo Yuan | AG34: =AB34 -> 20000
A35: 45273 | B35: 1000017791 | C35: 77489 | D35: shrink wrap | E35: 70000 | F35: 1L | G35: Philo Yuan | H35: =E35 -> 70000 | X35: 45470 | Y35: 1000021340 | Z35: 77593 | AA35: shrink wrap | AB35: 20000 | AC35: 1L | AD35: Philo Yuan | AE35: =AB35 -> 20000
A36: 45273 | B36: 1000017792 | C36: 77489 | D36: shrink wrap | E36: 30000 | F36: 3L | G36: Philo Yuan | I36: =E36 -> 30000 | X36: 45470 | Y36: 1000021341 | Z36: 77593GQ1 | AA36: PDQ 13 pcs | AB36: 500 | AC36: 1L | AD36: Philo Yuan | AO36: =AB36 -> 500
A37: 45273 | B37: 1000017793 | C37: 77489GQ1 | D37: PDQ 12pcs | E37: 5586 | F37: 1L | G37: Philo Yuan | M37: =E37 -> 5586 | X37: 45470 | Y37: 1000021342 | Z37: 77593GQ2 | AA37: PDQ 24 pcs | AB37: 500 | AC37: 1L | AD37: Philo Yuan | AM37: =AB37 -> 500
A38: 45273 | B38: 1000017803 | C38: 77489GQ2 | D38: PDQ 24 pcs | E38: 1256 | F38: 3L | G38: Philo Yuan | L38: =E38 -> 1256 | X38: 45484 | Y38: 1000021796 | Z38: 77593 | AA38: collector guide | AB38: 50000 | AC38: 5L | AD38: Philo Yuan | AG38: =AB38 -> 50000
A39: 45285 | B39: 1000017952 | C39: 77489GQ2 | D39: PDQ 24 pcs | E39: 55 | F39: 3L | G39: Philo Yuan | L39: =E39 -> 55 | V39: 本次放订为12/13号MA数量补数 | X39: 45484 | Y39: 1000021797 | Z39: 77593 | AA39: shrink wrap | AB39: 50000 | AC39: 1L | AD39: Philo Yuan | AE39: =AB39 -> 50000
A40: 45286 | B40: 1000017988 | C40: 77523 | D40: Art Paper（2PK) | E40: 624 | F40: N/A | G40: Peggy Wu | Q40: =E40 -> 624 | V40: 用于Yvonne 4500121474/4500121471/4500121472/4500121474/4500121476 | X40: 45484 | Y40: 1000021798 | Z40: 77593GQ2 | AA40: PDQ 24 pcs | AB40: 759 | AC40: 1L | AD40: Philo Yuan | AM40: =AB40 -> 759
A41: 45286 | B41: 1000017989 | C41: 77523 | D41: PVC Tube(2PK) | E41: 624 | F41: N/A | G41: Peggy Wu | P41: =E41 -> 624 | V41: 用于Yvonne 4500121474/4500121471/4500121472/4500121474/4500121476 | X41: 45483 | Y41: 1000021712 | Z41: 77614 | AA41: Art Paper | AB41: 2052 | AC41: 3L | AD41: Violet Chen | AV41: Mia用于4500139220 CA/4500139232 CA/4500139401/4500139475
A42: 45286 | B42: 1000017990 | C42: 77489（for 77523） | D42: Shrink Wrap(without UPC) | E42: 1248 | F42: N/A | G42: Peggy Wu | O42: =E42 -> 1248 | V42: 用于Yvonne 4500121474/4500121471/4500121472/4500121474/4500121476 | X42: 45483 | Y42: 1000021713 | Z42: 77614 | AA42: PVC Tube(2PK) | AB42: 2052 | AD42: Violet Chen | AV42: Mia用于4500139220 CA/4500139232 CA/4500139401/4500139475
A43: 45306 | B43: 此单按单订购不另建MA PO | C43: 77523 | D43: Art Paper（2PK) | E43: 800 | F43: N/A | G43: Peggy Wu | Q43: =E43 -> 800 | V43: 用于Yvonne 4500122523 | X43: 45483 | Y43: 1000021714 | Z43: 77614 | AA43: Lid sticker(2PK) | AB43: 2052 | AD43: Violet Chen | AV43: Mia用于4500139220 CA/4500139232 CA/4500139401/4500139475
A44: 45306 | B44: 此单按单订购不另建MA PO | C44: 77523 | D44: PVC Tube(2PK) | E44: 800 | F44: N/A | G44: Peggy Wu | P44: =E44 -> 800 | V44: 用于Yvonne 4500122523 | X44: 45490 | Y44: 1000021923 | Z44: 77593GQ2 | AA44: PDQ 24 pcs | AB44: 1176 | AC44: 1L | AD44: Philo Yuan | AM44: =AB44 -> 1176
A45: 45306 | B45: 此单按单订购不另建MA PO | C45: 77489（for 77523） | D45: Shrink Wrap(without UPC) | E45: 1600 | F45: N/A | G45: Peggy Wu | O45: =E45 -> 1600 | V45: 用于Yvonne 4500122523 | X45: 45497 | Y45: 1000022084 | Z45: 77593 | AA45: collector guide | AB45: 20000 | AC45: 5L | AD45: Philo Yuan | AG45: =AB45 -> 20000
A46: 45308 | B46: 1000018300 | C46: 77489 | D46: collector guide | E46: 35000 | F46: 5L | G46: Philo Yuan | J46: =E46 -> 35000 | X46: 45497 | Y46: 1000022085 | Z46: 77593 | AA46: shrink wrap | AB46: 20000 | AC46: 1L | AD46: Philo Yuan | AE46: =AB46 -> 20000
A47: 45308 | B47: 1000018301 | C47: 77489 | D47: shrink wrap | E47: 20000 | F47: 1L | G47: Philo Yuan | H47: =E47 -> 20000 | X47: 45497 | Y47: 1000022086 | Z47: 77593GQ1 | AA47: PDQ 13 pcs | AB47: 500 | AC47: 1L | AD47: Philo Yuan | AO47: =AB47 -> 500
A48: 45308 | B48: 1000018302 | C48: 77489 | D48: shrink wrap | E48: 1988 | F48: 3L | G48: Philo Yuan | I48: =E48 -> 1988 | X48: 45497 | Y48: 1000022089 | Z48: 77593SK-S001 | AA48: Sidekick | AB48: 300 | AC48: 1L | AD48: Philo Yuan | AH48: =AB48 -> 300
A49: 45308 | B49: 1000018303 | C49: 77489GQ2 | D49: PDQ 24 pcs | E49: 107 | F49: 3L | G49: Philo Yuan | L49: =E49 -> 107 | X49: 45497 | Y49: 1000022090 | Z49: 77593SK-S002 | AA49: Base | AB49: 300 | AC49: 1L | AD49: Philo Yuan | AI49: =AB49 -> 300 | AV49: 仅采购底座
A50: 消耗多的15072pcs | I50: 15072 | X50: 45497 | Y50: 1000022091 | Z50: 77593SK1-S001 | AA50: Sidekick | AB50: 300 | AC50: 3L | AD50: Philo Yuan | AK50: =AB50 -> 300
A51: 45372 | B51: 1000019028 | C51: 77489 | D51: collector guide | E51: 30000 | F51: 5L | G51: Philo Yuan | J51: =E51 -> 30000 | X51: 45497 | Y51: 1000022092 | Z51: 77593SK1-S002 | AA51: Base | AB51: 300 | AC51: 3L | AD51: Philo Yuan | AL51: =AB51 -> 300 | AV51: 仅采购底座
A52: 45372 | B52: 1000019029 | C52: 77489GQ1 | D52: PDQ 12pcs | E52: 500 | F52: 1L | G52: Philo Yuan | M52: =E52 -> 500 | X52: 45523 | Y52: 1000022639 | Z52: 77593 | AA52: collector guide | AB52: 20000 | AC52: 5L | AD52: Philo Yuan | AG52: =AB52 -> 20000 | AV52: 说明书请对应每款公仔的Ratio配套订，不单独建MA number
A53: 45401 | B53: 1000019686 | C53: 77489 | D53: collector guide | E53: 20000 | F53: 5L | G53: Philo Yuan | J53: =E53 -> 20000 | X53: 45523 | Y53: 1000022640 | Z53: 77593 | AA53: shrink wrap | AB53: 20000 | AC53: 1L | AD53: Philo Yuan | AE53: =AB53 -> 20000
A54: 45401 | B54: 1000019687 | C54: 77489 | D54: shrink wrap | E54: 20000 | F54: 1L | G54: Philo Yuan | H54: =E54 -> 20000 | X54: 45545 | Y54: 1000023096 | Z54: 77593GQ1 | AA54: PDQ 13 pcs | AB54: 500 | AC54: 1L | AD54: Philo Yuan | AO54: =AB54 -> 500
A55: 45401 | B55: 1000019688 | C55: 77489GQ1 | D55: PDQ 12pcs | E55: 1146 | F55: 1L | G55: Philo Yuan | M55: =E55 -> 1146 | X55: 45545 | Y55: 1000023097 | Z55: 77593SK-S001 | AA55: Sidekick | AB55: 200 | AC55: 1L | AD55: Philo Yuan | AH55: =AB55 -> 200
X56: 45545 | Y56: 1000023098 | Z56: 77593SK-S002 | AA56: Base | AB56: 200 | AC56: 1L | AD56: Philo Yuan | AI56: =AB56 -> 200
X57: 45554 | Y57: 1000023233 | Z57: 77593 | AA57: collector guide | AB57: 100000 | AC57: 5L | AD57: Philo Yuan | AG57: =AB57 -> 100000
X58: 45554 | Y58: 1000023234 | Z58: 77593 | AA58: shrink wrap | AB58: 100000 | AC58: 1L | AD58: Philo Yuan | AE58: =AB58 -> 100000
X59: 45560 | Y59: 1000023363 | Z59: 77593GQ2 | AA59: PDQ 24 pcs | AB59: 500 | AC59: 1L | AD59: Philo Yuan | AM59: =AB59 -> 500
X60: 45564 | Y60: 1000023485 | Z60: 77593GQ1 | AA60: PDQ 13 pcs | AB60: 500 | AC60: 1L | AD60: Philo Yuan | AO60: =AB60 -> 500
X61: 45604 | Y61: 1000024310 | Z61: 77593 | AA61: collector guide | AB61: 90000 | AC61: 5L | AD61: Philo Yuan | AG61: =AB61 -> 90000
X62: 45604 | Y62: 1000024311 | Z62: 77593 | AA62: shrink wrap | AB62: 70000 | AC62: 1L | AD62: Philo Yuan | AE62: =AB62 -> 70000
X63: 45604 | Y63: 1000024312 | Z63: 77593 | AA63: shrink wrap | AB63: 20000 | AC63: 3L | AD63: Philo Yuan | AF63: =AB63 -> 20000
X64: 45604 | Y64: 1000024313 | Z64: 77593GQ2 | AA64: PDQ 24 pcs | AB64: 1601 | AC64: 1L | AD64: Philo Yuan | AM64: =AB64 -> 1601
X65: 45604 | Y65: 1000024314 | Z65: 77593GQ2 | AA65: PDQ 24 pcs | AB65: 500 | AC65: 3L | AD65: Philo Yuan | AN65: =AB65 -> 500
X66: 45624 | Y66: 1000024797 | Z66: 77593 | AA66: collector guide | AB66: 20000 | AC66: 5L | AD66: Philo Yuan | AG66: =AB66 -> 20000
X67: 45624 | Y67: 1000024798 | Z67: 77593 | AA67: shrink wrap | AB67: 20000 | AC67: 1L | AD67: Philo Yuan | AE67: =AB67 -> 20000
X68: 45624 | Y68: 1000024799 | Z68: 77593GQ1 | AA68: PDQ 13 pcs | AB68: 500 | AC68: 1L | AD68: Philo Yuan | AO68: =AB68 -> 500
X69: 45653 | Y69: 1000025345 | Z69: 77593 | AA69: collector guide | AB69: 20000 | AC69: 5L | AD69: Linda Li | AG69: =AB69 -> 20000
X70: 45653 | Y70: 1000025346 | Z70: 77593GQ2 | AA70: PDQ 24 pcs | AB70: 500 | AC70: 1L | AD70: Linda Li | AM70: =AB70 -> 500
X71: 45714 | Z71: 77593 | AA71: collector guide | AB71: 20000 | AC71: 5L | AD71: Linda Li | AG71: =AB71 -> 20000 | AV71: 最后一次放订，请根据实际库存补齐MA欠数订购
X72: 45714 | Z72: 77593 | AA72: shrink wrap | AB72: 20000 | AC72: 3L | AD72: Linda Li | AF72: =AB72 -> 20000 | AV72: 最后一次放订，请根据实际库存补齐MA欠数订购
G75: 合计MA数量 | H75: =SUM(H4:H74) -> 380000 | I75: =SUM(I4:I74) -> 57060 | J75: =SUM(J4:J74) -> 470000 | K75: =SUM(K4:K74) -> 2500 | L75: =SUM(L4:L74) -> 1418 | M75: =SUM(M4:M74) -> 24467 | N75: =SUM(N4:N74) -> 1000 | O75: =SUM(O4:O74) -> 12800 | ... T75: =SUM(T4:T74) -> 200 | AD75: 合计MA数量 | AE75: =SUM(AE4:AE74) -> 570000 | AF75: =SUM(AF4:AF74) -> 70000 | AG75: =SUM(AG4:AG74) -> 640000 | AH75: =SUM(AH4:AH74) -> 500 | AI75: =SUM(AI4:AI74) -> 500 | AJ75: =SUM(AJ4:AJ74) -> 0 | AK75: =SUM(AK4:AK74) -> 300 | AL75: =SUM(AL4:AL74) -> 300 | ... AT75: =SUM(AT4:AT74) -> 1524
A76: 接单数量 | H76: 382596 | I76: 56604 | J76: 446360 | K76: 2419 | L76: 1418 | M76: 25301 | N76: 999 | O76: 12800 | P76: 6400 | Q76: 6400 | R76: 100 | S76: 116 | T76: 116 | X76: 接单数量 | AE76: ='77593旧排期'!AG49 -> 570989 | AF76: ='77593旧排期'!AH49 -> 77881 | AG76: ='77593旧排期'!AI49 -> 648870 | AH76: ='77593旧排期'!AJ49 -> 500 | AI76: ='77593旧排期'!AK49 -> 500 | AJ76: ='77593旧排期'!AR49 -> 0 | AK76: ='77593旧排期'!AQ49 -> 300 | AL76: ='77593旧排期'!AS49 -> 300 | AM76: ='77593旧排期'!AL49 -> 6084 | AN76: ='77593旧排期'!AM49 -> 1494 | AO76: ='77593旧排期'!AN49 -> 4860 | AP76: ='77593旧排期'!AO49 -> 725 | AQ76: ='77593旧排期'!AW49 -> 6233 | AR76: ='77593旧排期'!AT49 -> 9192 | AS76: ='77593旧排期'!AV49 -> 3432 | AT76: ='77593旧排期'!AU49 -> 5760
A77: MA库存数 | H77: =H75-H76 -> -2596 | I77: =I75-I76 -> 456 | J77: =J75-J76 -> 23640 | K77: =K75-K76 -> 81 | L77: =L75-L76 -> 0 | M77: =M75-M76 -> -834 | N77: =N75-N76 -> 1 | O77: =O75-O76 -> 0 | ... T77: =T75-T76 -> 84 | X77: MA库存数 | AE77: =AE75-AE76 -> -989 | AF77: =AF75-AF76 -> -7881 | AG77: =AG75-AG76 -> -8870 | AH77: =AH75-AH76 -> 0 | AI77: =AI75-AI76 -> 0 | AJ77: =AJ75-AJ76 -> 0 | AK77: =AK75-AK76 -> 0 | AL77: =AL75-AL76 -> 0 | ... AT77: =AT75-AT76 -> -4236
AU79: GQ5客版
AD80: 截止7/15 实际库存 | AE80: 16000 | AF80: 9700 | AI80: 100 | AJ80: 80 | AK80: 13 | AM80: 421 | AN80: 599 | AO80: 1712 | AP80: 65 | AQ80: 354 | AU80: 160
AL81: GQ2吸塑盒 | AM81: 643
AL82: GQ2吸塑托 | AM82: 280
AL83: 卡纸 | AM83: 652

Sheet 取消单
A1: 香港接单日期 | B1: 第三方客户名称 | C1: 走货国家 | D1: ZURU PO NO# | E1: 第三方客户 PO NO# | F1: ITEM# | G1: 中文名 | H1: PO数量 (pcs) | I1: 内箱装箱数量(pcs) | J1: 外箱装箱数量(pcs) | K1: 总箱数 | L1: ZURU订单走货日期 | M1: ZURU验货 日期 | N1: 第三方客户公证行验货 | O1: 驗貨結果 | P1: ZURU确认走货日期 | Q1: 箱唛资料(收到日期) | R1: 外箱贴纸 | S1: 客供贴纸AI(收到日期) | T1: 备注 | U1: ZURU 跟单 | V1: 单价USD | W1: 金额USD | X1: 發票號 | Y1: 是否入系统 | Z1: 完货情况 | AA1: 已送情况 | AB1: 欠数 | AC1: 贴纸 情况 | AD1: MA 1语收缩膜 A版本 | AE1: MA 1语收缩膜 B版本 | AF1: MA 3语收缩膜 A版本 | AG1: 客版 收缩膜 | AH1: MA 1语收藏指南 A版本 | AI1: MA 3语收藏指南 A版本 | AJ1: 客版 收藏指南 | AK1: MA 1語说明书 A版本 | AL1: MA 3語说明书 A版本 | AM1: 客版 說明書 | AN1: GQ2 24pcs装 MA PDQ | AO1: GQ2 24pcs装 英法文版本 | AP1: GQ2 50pcs装 MA PDQ | AQ1: GQ1 1语 A版本 | AR1: GQ1 1语 B版本 | AS1: GQ1 英法文版本 | AT1: GQ1 1语 客版中文 | AU1: SQ1-S001 MA 1L版本 | AV1: SQ2 1语版本 | AW1: SQ3 1语版本 | AX1: SK1-S001 Target专用 | AY1: SK-S001 无底座展示架 | AZ1: SK-S002 有底座展示架 1语 | BA1: SK-S002 有底座展示架 3语 | BB1: Pterosaur 翼龙 | BC1: Amargasaurus 阿玛加龙 | BD1: T-Rex 暴龙 | BE1: T-Rex (Rare) 暴龙（特别款） | BF1: Brontosaurus 雷龙 | BG1: Dilophosaurus 双棘龙 | BH1: Stegosaurus 剑龙 | BI1: Armed Helicoper 武装飞机 | BJ1: Truck 卡车 | BK1: Truck (Rare) 卡车特别款 | BL1: 生產狀態 | BM1: 毛絨狀態
A2: 44385 | B2: TESCO UK | D2: 4500056761 | E2: Sheba | F2: 惊喜球PDQ | G2: 7794SQ2-S002 | H2: 2160 | I2: 12 | J2: 48 | K2: =H2/J2 -> 45 | L2: 0 | M2: =L2*H2 -> 0 | N2: 2021/11/1 2021/9/10取消订单 | P2: 2021/11/4 2021/9/10取消订单 | S2: 英国 | U2: 未生产 | V2: 暂停生产 | Y2: 欠 | Z2: 欠 | AR2: =H2/12 -> 180 | BH2: 日期码格式：ZURU 标准格式 日期：按实际生产日期 Remark: 2.7794SQ2:MA收缩膜A1L版 + EAN条码（EAN#4894680011694)+一张UKCA Mark贴纸贴在收缩膜上+一张防盗标贴纸贴在球的顶部+一张UKCA Mark贴纸贴在产品上(位置 图靠近CE Mark不遮住任何信息，若产品上已经有了UKCA Mark标志则不需要额外加此贴纸在产品上，需要发图片给跟单参考)+MA说明书/收藏指南1L版+客版PDQ 1L版 (3Facing12pcs/PDQ)+一张ITF贴纸（内箱正唛一面贴一张ITF贴纸，此贴纸工厂自行采购) +两张BD贴纸(外箱正唛/侧唛右上角各贴一张,该贴纸由ZURU跟单提供）IT F/BD贴纸大小为11*5.8CM，箱嘪排版时请保留足够的位置; -EAN贴纸和位置图，ITF贴纸，客版PDQ翻PO#4500048108，UKCA Mark贴纸位置图待提供; 4.裝櫃必須按TPND順序 (條形碼貼紙或正嘜必須要朝外向車門外)
A3: 44379 | B3: TESCO UK | D3: 4500056671 | E3: Sheba | F3: 惊喜球PDQ | G3: 7794SQ2-S002 | H3: 2880 | I3: 12 | J3: 48 | K3: =H3/J3 -> 60 | L3: 0 | M3: =L3*H3 -> 0 | N3: 2021/10/4 2021/9/10取消订单 | P3: 2021/10/8 2021/9/10取消订单 | S3: 英国 | U3: 未生产 | V3: 暂停生产 | Y3: 欠 | Z3: 8/9 客供BD贴纸 | AR3: =H3/12 -> 240 | BH3: 日期码格式：ZURU 标准格式 日期：按实际生产日期 Remark: 5.7794SQ2:MA收缩膜A1L版 + EAN条码（EAN#4894680011694)+一张防盗标贴纸+MA说明书/收藏指南1L版+客版PDQ 1L版(3Facing12pcs/PDQ)+一张ITF贴纸（内箱正唛 一面贴一张ITF贴纸，此贴纸工厂自行采购) +两张BD贴纸(外箱正唛/侧唛右上角各贴一张,该贴纸由ZURU跟单提供）ITF/BD贴纸大小为11*5.8CM，箱嘪排版时请保留 足够的位置;-翻PO#4500048108; 6.裝櫃必須按TPND順序 (條形碼貼紙或正嘜必須要朝外向車門外)
A4: 44266 | B4: WAL-MART CANADA CORP. | C4: 4501009936 | D4: 4500047323 | E4: WM TEAM | F4: 惊喜球 | G4: 7794GQ1-S001 | H4: 3000 | I4: 0 | J4: 12 | K4: =H4/J4 -> 250 | L4: 0 | M4: =L4*H4 -> 0 | N4: 2021/8/9 2021/9/10取消订单 | O4: 8/12 自检 | P4: 2021/6/27 2021/9/10取消订单 | S4: 加拿大 | T4: pass | U4: 已完货 | V4: 3000 | Y4: 44322 | Z4: 无 | AO4: =H4/12 -> 250 | BH4: 日期码格式： ZURU DGYYYYMMDD CHINA(日期避开周末和法定节假日即可） 日期：按实际生产日期 Remark: 1.包装方式：MA 3L A版本收缩膜+MA 3L A版本收藏指南+MA 3L A版本说明书+客版3L 12pcs装PDQ,翻单：4500047320 2.此单需要第三方验货，烦请多备包装物料 3.此单有箱唛待提供 4.T-rex/ Stegosaurus/ Brontosaurus/ Dilophosaurus/ Pterosaur/ Amargasaurus/ Helicopter/ Truck, 1 rare T-rex or truck per 48pcs.2 rares in 96 PCS
A5: 44266 | B5: WAL-MART CANADA CORP. | C5: 4501009937 | D5: 4500047325 | E5: WM TEAM | F5: 惊喜球 | G5: 7794GQ1-S001 | H5: 3000 | I5: 0 | J5: 12 | K5: =H5/J5 -> 250 | L5: 0 | M5: =L5*H5 -> 0 | N5: 2021/7/26 2021.5.25取消订单 | P5: 2021/7/28 2021.5.25取消订单 | R5: 5.24取消 | S5: 加拿大 | T5: 5.24取消 | Y5: 44322 | Z5: 无 | AO5: =H5/12 -> 250 | BH5: 日期码格式： ZURU DGYYYYMMDD CHINA(日期避开周末和法定节假日即可） 日期：按实际生产日期 Remark: 1.包装方式：MA 3L A版本收缩膜+MA 3L A版本收藏指南+MA 3L A版本说明书+客版3L 12pcs装PDQ,翻单：4500047320 2.此单需要第三方验货，烦请多备包装物料 3.此单有箱唛待提供 4.T-rex/ Stegosaurus/ Brontosaurus/ Dilophosaurus/ Pterosaur/ Amargasaurus/ Helicopter/ Truck, 1 rare T-rex or truck per 48pcs.2 rares in 96 PCS
A6: 44288 | B6: Wal-mart Dotcom | C6: TBA | D6: MO8888881 | E6: Estate | F6: 惊喜球3PK PVC圆筒装 | G6: 77110-S001 | H6: 804 | I6: 0 | J6: 12 | K6: =H6/J6 -> 67 | L6: 0 | M6: 0 | N6: 44327 | O6: 取消单，转实单 | P6: 44330 | R6: 取消单，转实单 | S6: 美国 | Y6: 空白箱+ZURU logo | Z6: 欠外箱贴纸 | BH6: 1.77110：MA1L 包装+MA1L收藏指南+MA说明书+PVC圆筒，翻单4500039604 2.空白外箱（需四面右下角有ZURU的Logo)+白色艾利贴纸，白色贴纸照以往的包装操作贴在主唛左前下角。3.在产品上和包装上和外箱上要有日期码ZURU DGYYYYMMDD CHINA、MADE IN CHINA和ZURU字样。 5.产品信息：77110:T-rex/ Stegosaurus/ Brontosaurus/ Dilophosaurus/ Pterosaur/ Amargasaurus/ Helicopter/ Truck, 1 rare T-rex or truck per 16pcs.2 rares in 32 PCS
A7: 44266 | B7: WAL-MART CANADA CORP. | C7: 4501009935 | D7: 4500047320 | E7: WM TEAM | F7: 惊喜球 | G7: 7794GQ1-S001 | H7: 3000 | I7: 0 | J7: 12 | K7: =H7/J7 -> 250 | L7: 0 | M7: =L7*H7 -> 0 | N7: 2021/5/14 2021/9/10取消订单 | O7: 5/14抽办 6/2 BV验货 HOLD | P7: 2021/5/17 2021/9/10取消订单 | Q7: 6/5-6/8 截仓 | S7: 加拿大 | T7: pass | U7: 已完货 | V7: 3000 | Y7: 44306 | Z7: 无 | AO7: =H7/12 -> 250 | BH7: 日期码格式： ZURU DGYYYYMMDD CHINA(日期避开周末和法定节假日即可） 日期：按实际生产日期 Remark: 1.包装方式：MA 3L A版本收缩膜+MA 3L A版本收藏指南+MA 3L A版本说明书+客版3L 12pcs装PDQ 2.此单需要第三方验货，烦请多备包装物料 3.此单有箱唛待提供 4.此单需要签板，烦请多备样板（4pcs球+2套完整的配件+1pcsPDQ) 5.此单需要产中抽板测试，完成大货的10%，会抽走4套给到实验室测试 6.T-rex/ Stegosaurus/ Brontosaurus/ Dilophosaurus/ Pterosaur/ Amargasaurus/ Helicopter/ Truck, 1 rare T-rex or truck per 48pcs.2 rares in 96 PCS
A8: 44490 | B8: UPD INC | C8: 28553 | D8: 4500064122 | E8: Cara | F8: 惊喜球PDQ | G8: 7794GQ2-S002 | H8: 3600 | I8: 0 | J8: 48 | K8: =H8/J8 -> 75 | L8: 0 | M8: 0 | N8: 2021/11/27 2021/10/29日取消订单 | P8: 2021/12/1 2021/10/29日取消订单 | S8: 美国 | AX8: =H8/96*12 -> 450 | AY8: =H8/96*12 -> 450 | AZ8: =H8/96*11 -> 412.5 | BA8: =H8/96*1 -> 37.5 | BB8: =H8/96*12 -> 450 | BC8: =H8/96*12 -> 450 | BD8: =H8/96*12 -> 450 | BE8: =H8/96*12 -> 450 | BF8: =H8/96*11 -> 412.5 | BG8: =H8/96*1 -> 37.5 | BH8: 日期码格式：ZURU 标准格式 日期：按实际生产日期 Remark: 1. MA UPC 最新包装 2. 外箱箱唛红色和黑色双色印刷。 3. 产品和包装上印刷tracking code信息，格式为ZURU常规。 4 我司QC 验货合格后方可出货 5. 整柜出货
A9: 44476 | B9: Wal-mart US | D9: MO20210930 | F9: 迷你恐龙卡板装 | G9: 77200GQ2-S001 77200SLB-S001 | H9: 1440 | I9: 24 | J9: =H9/I9 -> 60 | K9: =J9/60 -> 1 | L9: 0 | M9: 0 | N9: 2021/11/15 2021/10/12日转实单 | P9: 2021/11/18 2021/10/12日转实单 | S9: 库有 | X9: 欠 | Y9: 欠 | Z9: =H9 -> 1440 | AC9: =H9 -> 1440 | AF9: =H9 -> 1440 | AI9: =H9/24 -> 60 | AX9: =H9/96*12 -> 180 | AY9: =H9/96*12 -> 180 | AZ9: =H9/96*11 -> 165 | BA9: =H9/96*1 -> 15 | BB9: =H9/96*12 -> 180 | BC9: =H9/96*12 -> 180 | BD9: =H9/96*12 -> 180 | BE9: =H9/96*12 -> 180 | BF9: =H9/96*11 -> 165 | BG9: =H9/96*1 -> 15 | BH9: 1.包装要求： 77200：MA 1L收缩膜+MA收藏指南+MA说明书+MA PDQ 2. 在原来的空白外箱基础上增加了UPC内容，在加印的时候确保条形码能扫描出来（需四面右下角有ZURU的Logo）,UPC内容待提供，外箱侧面任一角落加印：“MADE IN CHINA” 字样； 3.每个slip sheet上面贴一张艾利贴纸和一张普通贴纸（可A4纸打印），slip sheet打印的普通贴纸的尺寸不能比艾利贴纸小，普通贴纸内容见附件。 4. 在产品上和包装上要有日期码、以及要有MADE IN CHINA和ZURU字样； 5. 产品如有扎带口要剪平，不能刮手。 6. 此单需要验货，请自行多备包装物料。 7.77200：24pcs/PDQ/CTN.60箱/slip sheet，此单以slip sheet出货
A10: 44476 | B10: Wal-mart US | D10: MO20210930 | F10: 迷你恐龙卡板装 | G10: 77200GQ2-S001 77200SLB-S001 | H10: 1440 | I10: 24 | J10: =H10/I10 -> 60 | K10: =J10/60 -> 1 | L10: 0 | M10: 0 | N10: 2021/11/15 2021/10/12日转实单 | P10: 2021/11/18 2021/10/12日转实单 | S10: 库有 | X10: 欠 | Y10: 欠 | Z10: =H10 -> 1440 | AC10: =H10 -> 1440 | AF10: =H10 -> 1440 | AI10: =H10/24 -> 60 | AX10: =H10/96*12 -> 180 | AY10: =H10/96*12 -> 180 | AZ10: =H10/96*11 -> 165 | BA10: =H10/96*1 -> 15 | BB10: =H10/96*12 -> 180 | BC10: =H10/96*12 -> 180 | BD10: =H10/96*12 -> 180 | BE10: =H10/96*12 -> 180 | BF10: =H10/96*11 -> 165 | BG10: =H10/96*1 -> 15 | BH10: 1.包装要求： 77200：MA 1L收缩膜+MA收藏指南+MA说明书+MA PDQ 2. 在原来的空白外箱基础上增加了UPC内容，在加印的时候确保条形码能扫描出来（需四面右下角有ZURU的Logo）,UPC内容待提供，外箱侧面任一角落加印：“MADE IN CHINA” 字样； 3.每个slip sheet上面贴一张艾利贴纸和一张普通贴纸（可A4纸打印），slip sheet打印的普通贴纸的尺寸不能比艾利贴纸小，普通贴纸内容见附件。 4. 在产品上和包装上要有日期码、以及要有MADE IN CHINA和ZURU字样； 5. 产品如有扎带口要剪平，不能刮手。 6. 此单需要验货，请自行多备包装物料。 7.77200：24pcs/PDQ/CTN.60箱/slip sheet，此单以slip sheet出货
A11: 44476 | B11: Wal-mart US | D11: MO20210930 | F11: 迷你恐龙卡板装 | G11: 77200GQ2-S001 77200SLB-S001 | H11: 1440 | I11: 24 | J11: =H11/I11 -> 60 | K11: =J11/60 -> 1 | L11: 0 | M11: 0 | N11: 2021/11/15 2021/10/12日转实单 | P11: 2021/11/18 2021/10/12日转实单 | S11: 库有 | X11: 欠 | Y11: 欠 | Z11: =H11 -> 1440 | AC11: =H11 -> 1440 | AF11: =H11 -> 1440 | AI11: =H11/24 -> 60 | AX11: =H11/96*12 -> 180 | AY11: =H11/96*12 -> 180 | AZ11: =H11/96*11 -> 165 | BA11: =H11/96*1 -> 15 | BB11: =H11/96*12 -> 180 | BC11: =H11/96*12 -> 180 | BD11: =H11/96*12 -> 180 | BE11: =H11/96*12 -> 180 | BF11: =H11/96*11 -> 165 | BG11: =H11/96*1 -> 15 | BH11: 1.包装要求： 77200：MA 1L收缩膜+MA收藏指南+MA说明书+MA PDQ 2. 在原来的空白外箱基础上增加了UPC内容，在加印的时候确保条形码能扫描出来（需四面右下角有ZURU的Logo）,UPC内容待提供，外箱侧面任一角落加印：“MADE IN CHINA” 字样； 3.每个slip sheet上面贴一张艾利贴纸和一张普通贴纸（可A4纸打印），slip sheet打印的普通贴纸的尺寸不能比艾利贴纸小，普通贴纸内容见附件。 4. 在产品上和包装上要有日期码、以及要有MADE IN CHINA和ZURU字样； 5. 产品如有扎带口要剪平，不能刮手。 6. 此单需要验货，请自行多备包装物料。 7.77200：24pcs/PDQ/CTN.60箱/slip sheet，此单以slip sheet出货
A12: 44476 | B12: Wal-mart US | D12: MO20210930 | F12: 迷你恐龙卡板装 | G12: 77200GQ2-S001 77200SLB-S001 | H12: 1440 | I12: 24 | J12: =H12/I12 -> 60 | K12: =J12/60 -> 1 | L12: 0 | M12: 0 | N12: 2021/11/15 2021/10/12日转实单 | P12: 2021/11/18 2021/10/12日转实单 | S12: 库有 | X12: 欠 | Y12: 欠 | Z12: =H12 -> 1440 | AC12: =H12 -> 1440 | AF12: =H12 -> 1440 | AI12: =H12/24 -> 60 | AX12: =H12/96*12 -> 180 | AY12: =H12/96*12 -> 180 | AZ12: =H12/96*11 -> 165 | BA12: =H12/96*1 -> 15 | BB12: =H12/96*12 -> 180 | BC12: =H12/96*12 -> 180 | BD12: =H12/96*12 -> 180 | BE12: =H12/96*12 -> 180 | BF12: =H12/96*11 -> 165 | BG12: =H12/96*1 -> 15 | BH12: 1.包装要求： 77200：MA 1L收缩膜+MA收藏指南+MA说明书+MA PDQ 2. 在原来的空白外箱基础上增加了UPC内容，在加印的时候确保条形码能扫描出来（需四面右下角有ZURU的Logo）,UPC内容待提供，外箱侧面任一角落加印：“MADE IN CHINA” 字样； 3.每个slip sheet上面贴一张艾利贴纸和一张普通贴纸（可A4纸打印），slip sheet打印的普通贴纸的尺寸不能比艾利贴纸小，普通贴纸内容见附件。 4. 在产品上和包装上要有日期码、以及要有MADE IN CHINA和ZURU字样； 5. 产品如有扎带口要剪平，不能刮手。 6. 此单需要验货，请自行多备包装物料。 7.77200：24pcs/PDQ/CTN.60箱/slip sheet，此单以slip sheet出货
A13: 44476 | B13: Wal-mart US | D13: MO20210930 | F13: 迷你恐龙卡板装 | G13: 77200GQ2-S001 77200SLB-S001 | H13: 1440 | I13: 24 | J13: =H13/I13 -> 60 | K13: =J13/60 -> 1 | L13: 0 | M13: 0 | N13: 2021/11/15 2021/10/12日转实单 | P13: 2021/11/18 2021/10/12日转实单 | S13: 库有 | X13: 欠 | Y13: 欠 | Z13: =H13 -> 1440 | AC13: =H13 -> 1440 | AF13: =H13 -> 1440 | AI13: =H13/24 -> 60 | AX13: =H13/96*12 -> 180 | AY13: =H13/96*12 -> 180 | AZ13: =H13/96*11 -> 165 | BA13: =H13/96*1 -> 15 | BB13: =H13/96*12 -> 180 | BC13: =H13/96*12 -> 180 | BD13: =H13/96*12 -> 180 | BE13: =H13/96*12 -> 180 | BF13: =H13/96*11 -> 165 | BG13: =H13/96*1 -> 15 | BH13: 1.包装要求： 77200：MA 1L收缩膜+MA收藏指南+MA说明书+MA PDQ 2. 在原来的空白外箱基础上增加了UPC内容，在加印的时候确保条形码能扫描出来（需四面右下角有ZURU的Logo）,UPC内容待提供，外箱侧面任一角落加印：“MADE IN CHINA” 字样； 3.每个slip sheet上面贴一张艾利贴纸和一张普通贴纸（可A4纸打印），slip sheet打印的普通贴纸的尺寸不能比艾利贴纸小，普通贴纸内容见附件。 4. 在产品上和包装上要有日期码、以及要有MADE IN CHINA和ZURU字样； 5. 产品如有扎带口要剪平，不能刮手。 6. 此单需要验货，请自行多备包装物料。 7.77200：24pcs/PDQ/CTN.60箱/slip sheet，此单以slip sheet出货
A14: 44476 | B14: Wal-mart US | D14: MO20210930 | F14: 迷你恐龙卡板装 | G14: 77200GQ2-S001 77200SLB-S001 | H14: 1440 | I14: 24 | J14: =H14/I14 -> 60 | K14: =J14/60 -> 1 | L14: 0 | M14: 0 | N14: 2021/11/15 2021/10/12日转实单 | P14: 2021/11/18 2021/10/12日转实单 | S14: 库有 | X14: 欠 | Y14: 欠 | Z14: =H14 -> 1440 | AC14: =H14 -> 1440 | AF14: =H14 -> 1440 | AI14: =H14/24 -> 60 | AX14: =H14/96*12 -> 180 | AY14: =H14/96*12 -> 180 | AZ14: =H14/96*11 -> 165 | BA14: =H14/96*1 -> 15 | BB14: =H14/96*12 -> 180 | BC14: =H14/96*12 -> 180 | BD14: =H14/96*12 -> 180 | BE14: =H14/96*12 -> 180 | BF14: =H14/96*11 -> 165 | BG14: =H14/96*1 -> 15 | BH14: 1.包装要求： 77200：MA 1L收缩膜+MA收藏指南+MA说明书+MA PDQ 2. 在原来的空白外箱基础上增加了UPC内容，在加印的时候确保条形码能扫描出来（需四面右下角有ZURU的Logo）,UPC内容待提供，外箱侧面任一角落加印：“MADE IN CHINA” 字样； 3.每个slip sheet上面贴一张艾利贴纸和一张普通贴纸（可A4纸打印），slip sheet打印的普通贴纸的尺寸不能比艾利贴纸小，普通贴纸内容见附件。 4. 在产品上和包装上要有日期码、以及要有MADE IN CHINA和ZURU字样； 5. 产品如有扎带口要剪平，不能刮手。 6. 此单需要验货，请自行多备包装物料。 7.77200：24pcs/PDQ/CTN.60箱/slip sheet，此单以slip sheet出货
A15: 44476 | B15: Wal-mart US | D15: MO20210930 | F15: 迷你恐龙卡板装 | G15: 77200GQ2-S001 77200SLB-S001 | H15: 1440 | I15: 24 | J15: =H15/I15 -> 60 | K15: =J15/60 -> 1 | L15: 0 | M15: 0 | N15: 2021/11/15 2021/10/12日转实单 | P15: 2021/11/18 2021/10/12日转实单 | S15: 库有 | X15: 欠 | Y15: 欠 | Z15: =H15 -> 1440 | AC15: =H15 -> 1440 | AF15: =H15 -> 1440 | AI15: =H15/24 -> 60 | AX15: =H15/96*12 -> 180 | AY15: =H15/96*12 -> 180 | AZ15: =H15/96*11 -> 165 | BA15: =H15/96*1 -> 15 | BB15: =H15/96*12 -> 180 | BC15: =H15/96*12 -> 180 | BD15: =H15/96*12 -> 180 | BE15: =H15/96*12 -> 180 | BF15: =H15/96*11 -> 165 | BG15: =H15/96*1 -> 15 | BH15: 1.包装要求： 77200：MA 1L收缩膜+MA收藏指南+MA说明书+MA PDQ 2. 在原来的空白外箱基础上增加了UPC内容，在加印的时候确保条形码能扫描出来（需四面右下角有ZURU的Logo）,UPC内容待提供，外箱侧面任一角落加印：“MADE IN CHINA” 字样； 3.每个slip sheet上面贴一张艾利贴纸和一张普通贴纸（可A4纸打印），slip sheet打印的普通贴纸的尺寸不能比艾利贴纸小，普通贴纸内容见附件。 4. 在产品上和包装上要有日期码、以及要有MADE IN CHINA和ZURU字样； 5. 产品如有扎带口要剪平，不能刮手。 6. 此单需要验货，请自行多备包装物料。 7.77200：24pcs/PDQ/CTN.60箱/slip sheet，此单以slip sheet出货
A16: 44476 | B16: Wal-mart US | D16: MO20210930 | F16: 迷你恐龙卡板装 | G16: 77200GQ2-S001 77200SLB-S001 | H16: 1440 | I16: 24 | J16: =H16/I16 -> 60 | K16: =J16/60 -> 1 | L16: 0 | M16: 0 | N16: 2021/11/15 2021/10/12日转实单 | P16: 2021/11/18 2021/10/12日转实单 | S16: 库有 | X16: 欠 | Y16: 欠 | Z16: =H16 -> 1440 | AC16: =H16 -> 1440 | AF16: =H16 -> 1440 | AI16: =H16/24 -> 60 | AX16: =H16/96*12 -> 180 | AY16: =H16/96*12 -> 180 | AZ16: =H16/96*11 -> 165 | BA16: =H16/96*1 -> 15 | BB16: =H16/96*12 -> 180 | BC16: =H16/96*12 -> 180 | BD16: =H16/96*12 -> 180 | BE16: =H16/96*12 -> 180 | BF16: =H16/96*11 -> 165 | BG16: =H16/96*1 -> 15 | BH16: 1.包装要求： 77200：MA 1L收缩膜+MA收藏指南+MA说明书+MA PDQ 2. 在原来的空白外箱基础上增加了UPC内容，在加印的时候确保条形码能扫描出来（需四面右下角有ZURU的Logo）,UPC内容待提供，外箱侧面任一角落加印：“MADE IN CHINA” 字样； 3.每个slip sheet上面贴一张艾利贴纸和一张普通贴纸（可A4纸打印），slip sheet打印的普通贴纸的尺寸不能比艾利贴纸小，普通贴纸内容见附件。 4. 在产品上和包装上要有日期码、以及要有MADE IN CHINA和ZURU字样； 5. 产品如有扎带口要剪平，不能刮手。 6. 此单需要验货，请自行多备包装物料。 7.77200：24pcs/PDQ/CTN.60箱/slip sheet，此单以slip sheet出货
A17: 44476 | B17: Wal-mart US | D17: MO20210930 | F17: 迷你恐龙卡板装 | G17: 77200GQ2-S001 77200SLB-S001 | H17: 1440 | I17: 24 | J17: =H17/I17 -> 60 | K17: =J17/60 -> 1 | L17: 0 | M17: 0 | N17: 2021/11/15 2021/10/12日转实单 | P17: 2021/11/18 2021/10/12日转实单 | S17: 库有 | X17: 欠 | Y17: 欠 | Z17: =H17 -> 1440 | AC17: =H17 -> 1440 | AF17: =H17 -> 1440 | AI17: =H17/24 -> 60 | AX17: =H17/96*12 -> 180 | AY17: =H17/96*12 -> 180 | AZ17: =H17/96*11 -> 165 | BA17: =H17/96*1 -> 15 | BB17: =H17/96*12 -> 180 | BC17: =H17/96*12 -> 180 | BD17: =H17/96*12 -> 180 | BE17: =H17/96*12 -> 180 | BF17: =H17/96*11 -> 165 | BG17: =H17/96*1 -> 15 | BH17: 1.包装要求： 77200：MA 1L收缩膜+MA收藏指南+MA说明书+MA PDQ 2. 在原来的空白外箱基础上增加了UPC内容，在加印的时候确保条形码能扫描出来（需四面右下角有ZURU的Logo）,UPC内容待提供，外箱侧面任一角落加印：“MADE IN CHINA” 字样； 3.每个slip sheet上面贴一张艾利贴纸和一张普通贴纸（可A4纸打印），slip sheet打印的普通贴纸的尺寸不能比艾利贴纸小，普通贴纸内容见附件。 4. 在产品上和包装上要有日期码、以及要有MADE IN CHINA和ZURU字样； 5. 产品如有扎带口要剪平，不能刮手。 6. 此单需要验货，请自行多备包装物料。 7.77200：24pcs/PDQ/CTN.60箱/slip sheet，此单以slip sheet出货
A18: 44476 | B18: Wal-mart US | D18: MO20210930 | F18: 迷你恐龙卡板装 | G18: 77200GQ2-S001 77200SLB-S001 | H18: 1440 | I18: 24 | J18: =H18/I18 -> 60 | K18: =J18/60 -> 1 | L18: 0 | M18: 0 | N18: 2021/11/15 2021/10/12日转实单 | P18: 2021/11/18 2021/10/12日转实单 | S18: 库有 | X18: 欠 | Y18: 欠 | Z18: =H18 -> 1440 | AC18: =H18 -> 1440 | AF18: =H18 -> 1440 | AI18: =H18/24 -> 60 | AX18: =H18/96*12 -> 180 | AY18: =H18/96*12 -> 180 | AZ18: =H18/96*11 -> 165 | BA18: =H18/96*1 -> 15 | BB18: =H18/96*12 -> 180 | BC18: =H18/96*12 -> 180 | BD18: =H18/96*12 -> 180 | BE18: =H18/96*12 -> 180 | BF18: =H18/96*11 -> 165 | BG18: =H18/96*1 -> 15 | BH18: 1.包装要求： 77200：MA 1L收缩膜+MA收藏指南+MA说明书+MA PDQ 2. 在原来的空白外箱基础上增加了UPC内容，在加印的时候确保条形码能扫描出来（需四面右下角有ZURU的Logo）,UPC内容待提供，外箱侧面任一角落加印：“MADE IN CHINA” 字样； 3.每个slip sheet上面贴一张艾利贴纸和一张普通贴纸（可A4纸打印），slip sheet打印的普通贴纸的尺寸不能比艾利贴纸小，普通贴纸内容见附件。 4. 在产品上和包装上要有日期码、以及要有MADE IN CHINA和ZURU字样； 5. 产品如有扎带口要剪平，不能刮手。 6. 此单需要验货，请自行多备包装物料。 7.77200：24pcs/PDQ/CTN.60箱/slip sheet，此单以slip sheet出货
A19: 44476 | B19: Wal-mart US | D19: MO20210930 | F19: 迷你恐龙卡板装 | G19: 77200GQ2-S001 77200SLB-S001 | H19: 1440 | I19: 24 | J19: =H19/I19 -> 60 | K19: =J19/60 -> 1 | L19: 0 | M19: 0 | N19: 2021/11/15 2021/10/12日转实单 | P19: 2021/11/18 2021/10/12日转实单 | S19: 库有 | X19: 欠 | Y19: 欠 | Z19: =H19 -> 1440 | AC19: =H19 -> 1440 | AF19: =H19 -> 1440 | AI19: =H19/24 -> 60 | AX19: =H19/96*12 -> 180 | AY19: =H19/96*12 -> 180 | AZ19: =H19/96*11 -> 165 | BA19: =H19/96*1 -> 15 | BB19: =H19/96*12 -> 180 | BC19: =H19/96*12 -> 180 | BD19: =H19/96*12 -> 180 | BE19: =H19/96*12 -> 180 | BF19: =H19/96*11 -> 165 | BG19: =H19/96*1 -> 15 | BH19: 1.包装要求： 77200：MA 1L收缩膜+MA收藏指南+MA说明书+MA PDQ 2. 在原来的空白外箱基础上增加了UPC内容，在加印的时候确保条形码能扫描出来（需四面右下角有ZURU的Logo）,UPC内容待提供，外箱侧面任一角落加印：“MADE IN CHINA” 字样； 3.每个slip sheet上面贴一张艾利贴纸和一张普通贴纸（可A4纸打印），slip sheet打印的普通贴纸的尺寸不能比艾利贴纸小，普通贴纸内容见附件。 4. 在产品上和包装上要有日期码、以及要有MADE IN CHINA和ZURU字样； 5. 产品如有扎带口要剪平，不能刮手。 6. 此单需要验货，请自行多备包装物料。 7.77200：24pcs/PDQ/CTN.60箱/slip sheet，此单以slip sheet出货
A20: 44476 | B20: Wal-mart US | D20: MO20210930 | F20: 迷你恐龙卡板装 | G20: 77200GQ2-S001 77200SLB-S001 | H20: 1440 | I20: 24 | J20: =H20/I20 -> 60 | K20: =J20/60 -> 1 | L20: 0 | M20: 0 | N20: 2021/11/15 2021/10/12日转实单 | P20: 2021/11/18 2021/10/12日转实单 | S20: 库有 | X20: 欠 | Y20: 欠 | Z20: =H20 -> 1440 | AC20: =H20 -> 1440 | AF20: =H20 -> 1440 | AI20: =H20/24 -> 60 | AX20: =H20/96*12 -> 180 | AY20: =H20/96*12 -> 180 | AZ20: =H20/96*11 -> 165 | BA20: =H20/96*1 -> 15 | BB20: =H20/96*12 -> 180 | BC20: =H20/96*12 -> 180 | BD20: =H20/96*12 -> 180 | BE20: =H20/96*12 -> 180 | BF20: =H20/96*11 -> 165 | BG20: =H20/96*1 -> 15 | BH20: 1.包装要求： 77200：MA 1L收缩膜+MA收藏指南+MA说明书+MA PDQ 2. 在原来的空白外箱基础上增加了UPC内容，在加印的时候确保条形码能扫描出来（需四面右下角有ZURU的Logo）,UPC内容待提供，外箱侧面任一角落加印：“MADE IN CHINA” 字样； 3.每个slip sheet上面贴一张艾利贴纸和一张普通贴纸（可A4纸打印），slip sheet打印的普通贴纸的尺寸不能比艾利贴纸小，普通贴纸内容见附件。 4. 在产品上和包装上要有日期码、以及要有MADE IN CHINA和ZURU字样； 5. 产品如有扎带口要剪平，不能刮手。 6. 此单需要验货，请自行多备包装物料。 7.77200：24pcs/PDQ/CTN.60箱/slip sheet，此单以slip sheet出货
... A22: 44476 | B22: Wal-mart US | D22: MO20210930 | F22: 迷你恐龙卡板装 | G22: 77200GQ2-S001 77200SLB-S001 | H22: 1440 | I22: 24 | J22: =H22/I22 -> 60 | K22: =J22/60 -> 1 | L22: 0 | M22: 0 | N22: 2021/11/15 2021/10/12日转实单 | P22: 2021/11/18 2021/10/12日转实单 | S22: 库有 | X22: 欠 | Y22: 欠 | Z22: =H22 -> 1440 | AC22: =H22 -> 1440 | AF22: =H22 -> 1440 | AI22: =H22/24 -> 60 | AX22: =H22/96*12 -> 180 | AY22: =H22/96*12 -> 180 | AZ22: =H22/96*11 -> 165 | BA22: =H22/96*1 -> 15 | BB22: =H22/96*12 -> 180 | BC22: =H22/96*12 -> 180 | BD22: =H22/96*12 -> 180 | BE22: =H22/96*12 -> 180 | BF22: =H22/96*11 -> 165 | BG22: =H22/96*1 -> 15 | BH22: 1.包装要求： 77200：MA 1L收缩膜+MA收藏指南+MA说明书+MA PDQ 2. 在原来的空白外箱基础上增加了UPC内容，在加印的时候确保条形码能扫描出来（需四面右下角有ZURU的Logo）,UPC内容待提供，外箱侧面任一角落加印：“MADE IN CHINA” 字样； 3.每个slip sheet上面贴一张艾利贴纸和一张普通贴纸（可A4纸打印），slip sheet打印的普通贴纸的尺寸不能比艾利贴纸小，普通贴纸内容见附件。 4. 在产品上和包装上要有日期码、以及要有MADE IN CHINA和ZURU字样； 5. 产品如有扎带口要剪平，不能刮手。 6. 此单需要验货，请自行多备包装物料。 7.77200：24pcs/PDQ/CTN.60箱/slip sheet，此单以slip sheet出货
A23: 44462 | B23: WAL-MART CANADA CORP. | C23: 7100618883 | D23: 4500061791 | E23: WM TEAM | F23: 迷你恐龙 | G23: 77200GQ1-S001 | H23: 504 | I23: 0 | J23: 12 | K23: =H23/J23 -> 42 | L23: 0 | M23: =H23*L23 -> 0 | N23: 2021/12/4 2021/10/28日取消订单 | P23: 2021/12/8 2021/10/28日取消订单 | S23: 加拿大 | X23: 欠 | Y23: 欠 | AA23: =H23 -> 504 | AD23: =H23 -> 504 | AG23: =H23 -> 504 | AO23: =H23/12 -> 42 | AX23: =H23/96*12 -> 63 | AY23: =H23/96*12 -> 63 | AZ23: =H23/96*11 -> 57.75 | BA23: =H23/96*1 -> 5.25 | BB23: =H23/96*12 -> 63 | BC23: =H23/96*12 -> 63 | BD23: =H23/96*12 -> 63 | BE23: =H23/96*12 -> 63 | BF23: =H23/96*11 -> 57.75 | BG23: =H23/96*1 -> 5.25 | BH23: 日期码格式：ZURU 标准格式 日期：按实际生产日期 Remark: 1.包装方式：MA3L 说明书+MA3L 收藏指南+客版2L PDQ+MA3L 收缩膜（翻单：4500059991 2.有箱唛待提供 3.有第三方验货，烦请多包备包装物料
A24: 44455 | B24: TARGET US | C24: 0087-3652533-0581 | D24: 4500060612 | E24: Holly Zheng/ Cherish Yao | F24: 迷你恐龙 | G24: 77200GQ1-S001 | H24: 12000 | I24: 0 | J24: 12 | K24: =H24/J24 -> 1000 | L24: 0 | M24: =H24*L24 -> 0 | N24: 2022/3/11 2021/12/16日取消订单 | P24: 2022/3/15 2021/12/16日取消订单 | S24: 美国 | X24: 欠 | Y24: 欠 | Z24: =H24 -> 12000 | AC24: =H24 -> 12000 | AF24: =H24 -> 12000 | AN24: =H24/12 -> 1000 | AX24: =H24/96*12 -> 1500 | AY24: =H24/96*12 -> 1500 | AZ24: =H24/96*11 -> 1375 | BA24: =H24/96*1 -> 125 | BB24: =H24/96*12 -> 1500 | BC24: =H24/96*12 -> 1500 | BD24: =H24/96*12 -> 1500 | BE24: =H24/96*12 -> 1500 | BF24: =H24/96*11 -> 1375 | BG24: =H24/96*1 -> 125 | BH24: 日期码格式：ZURU 标准格式 日期：按实际生产日期 Remark: 1. 77200GQ1-S001: 12pcs/Gravity PDQ , 12pcs/CTN, MA 1L 收缩膜+说明书，客版PDQ, 产品UPC 显示193052033024 2. 产品和包装上均要印刷tracking code信息，格式为ZURU常规格式。 3. 外箱正唛右上角位置粘贴条码箱贴纸，每箱只贴一张由ZURU订购。来料显示DPCI 087-16-9780,UPC 显示10193052033021.外箱贴人工费用$11.1 已经加在订单中. 4. 出货方式：货代自提
A25: 44455 | B25: TARGET US | C25: 0087-1739920-0581 | D25: 4500060613 | E25: Holly Zheng/ Cherish Yao | F25: 迷你恐龙 | G25: 77200GQ1-S001 | H25: 6000 | I25: 0 | J25: 12 | K25: =H25/J25 -> 500 | L25: 0 | M25: =H25*L25 -> 0 | N25: 2022/3/25 2021/12/16日取消订单 | P25: 2022/3/29 2021/12/16日取消订单 | S25: 美国 | X25: 欠 | Y25: 欠 | Z25: =H25 -> 6000 | AC25: =H25 -> 6000 | AF25: =H25 -> 6000 | AN25: =H25/12 -> 500 | AX25: =H25/96*12 -> 750 | AY25: =H25/96*12 -> 750 | AZ25: =H25/96*11 -> 687.5 | BA25: =H25/96*1 -> 62.5 | BB25: =H25/96*12 -> 750 | BC25: =H25/96*12 -> 750 | BD25: =H25/96*12 -> 750 | BE25: =H25/96*12 -> 750 | BF25: =H25/96*11 -> 687.5 | BG25: =H25/96*1 -> 62.5 | BH25: 日期码格式：ZURU 标准格式 日期：按实际生产日期 Remark: 1. 77200GQ1-S001: 12pcs/Gravity PDQ , 12pcs/CTN, MA 1L 收缩膜+说明书，客版PDQ, 产品UPC 显示193052033024 2. 产品和包装上均要印刷tracking code信息，格式为ZURU常规格式。 3. 外箱正唛右上角位置粘贴条码箱贴纸，每箱只贴一张由ZURU订购。来料显示DPCI 087-16-9780,UPC 显示10193052033021.外箱贴人工费用$5.55已经加在订单中. 4. 出货方式：货代自提
A26: 44455 | B26: TARGET US | C26: 0087-9687827-0581 | D26: 4500060614 | E26: Holly Zheng/ Cherish Yao | F26: 迷你恐龙 | G26: 77200GQ1-S001 | H26: 15300 | I26: 0 | J26: 12 | K26: =H26/J26 -> 1275 | L26: 0 | M26: =H26*L26 -> 0 | N26: 2022/4/8 2021/12/16日取消订单 | P26: 2022/4/12 2021/12/16日取消订单 | S26: 美国 | X26: 欠 | Y26: 欠 | Z26: =H26 -> 15300 | AC26: =H26 -> 15300 | AF26: =H26 -> 15300 | AN26: =H26/12 -> 1275 | AX26: =H26/96*12 -> 1912.5 | AY26: =H26/96*12 -> 1912.5 | AZ26: =H26/96*11 -> 1753.125 | BA26: =H26/96*1 -> 159.375 | BB26: =H26/96*12 -> 1912.5 | BC26: =H26/96*12 -> 1912.5 | BD26: =H26/96*12 -> 1912.5 | BE26: =H26/96*12 -> 1912.5 | BF26: =H26/96*11 -> 1753.125 | BG26: =H26/96*1 -> 159.375 | BH26: 日期码格式：ZURU 标准格式 日期：按实际生产日期 Remark: 1. 77200GQ1-S001: 12pcs/Gravity PDQ , 12pcs/CTN, MA 1L 收缩膜+说明书，客版PDQ, 产品UPC 显示193052033024 2. 产品和包装上均要印刷tracking code信息，格式为ZURU常规格式。 3. 外箱正唛右上角位置粘贴条码箱贴纸，每箱只贴一张由ZURU订购。来料显示DPCI 087-16-9780,UPC 显示10193052033021.外箱贴人工费用$14.15 已经加在订单中 . 4. 出货方式：货代自提
A27: 44455 | B27: TARGET US | C27: 0087-4527037-0581 | D27: 4500060611 | E27: Holly Zheng/ Cherish Yao | F27: 迷你恐龙 | G27: 77200GQ1-S001 | H27: 48000 | I27: 0 | J27: 12 | K27: =H27/J27 -> 4000 | L27: 0 | M27: =H27*L27 -> 0 | N27: 2022/2/26 2021/12/16日取消订单 | P27: 2022/3/1 2021/12/16日取消订单 | S27: 美国 | X27: 欠 | Y27: 欠 | Z27: =H27 -> 48000 | AC27: =H27 -> 48000 | AF27: =H27 -> 48000 | AN27: =H27/12 -> 4000 | AX27: =H27/96*12 -> 6000 | AY27: =H27/96*12 -> 6000 | AZ27: =H27/96*11 -> 5500 | BA27: =H27/96*1 -> 500 | BB27: =H27/96*12 -> 6000 | BC27: =H27/96*12 -> 6000 | BD27: =H27/96*12 -> 6000 | BE27: =H27/96*12 -> 6000 | BF27: =H27/96*11 -> 5500 | BG27: =H27/96*1 -> 500 | BH27: 日期码格式：ZURU 标准格式 日期：按实际生产日期 Remark: 1. 77200GQ1-S001: 12pcs/Gravity PDQ , 12pcs/CTN, MA 1L 收缩膜+说明书，客版PDQ, 产品UPC 显示193052033024 2. 产品和包装上均要印刷tracking code信息，格式为ZURU常规格式。 3. 外箱正唛右上角位置粘贴条码箱贴纸，每箱只贴一张由ZURU订购。来料显示DPCI 087-16-9780,UPC 显示10193052033021.外箱贴人工费用$44.4 已经加在订单中. 4. 出货方式：货代自提
A28: 44630 | B28: ROSS PROCUREMENT.INC | C28: 美国 | D28: 4500072769 | E28: 70010222 | F28: 77118-S001 | G28: 2PK PVC筒装 | H28: 4320 | I28: 0 | J28: 16 | K28: =H28/J28 -> 270 | L28: 2022/7/8 2022/4/9日取消订单 | M28: 2022/7/4 2022/4/9日取消订单 | Q28: 欠 | R28: 无 | S28: 欠 | T28: 日期码格式：ZURU 标准格式 日期：按实际生产日期 Remark: 1.ZURU MA + UPC 现有版本包装 + 客供价格贴纸，出口美国。 2.价格贴纸位于包装正面右下角，不挡住重要信息即可，可适当调整 ，价格贴纸由跟单提供。 3.标准日期码格式，产品和包装必须有日期码，所有日期码必须一致(但日期不可为周末)。 4.同个产品同个货期不可出现不同的包装。 5.包装版本： ZURU现有 MA + UPC 版本。 | U28: Maggie | V28: 2.5173 | W28: =V28*H28 -> 10874.736 | AB28: =AA28-H28 -> -4320 | AD28: =H28*2 -> 8640 | AH28: =H28*2 -> 8640 | AK28: =H28*2 -> 8640 | BB28: =H28/96*12*2 -> 1080 | BC28: =H28/96*12*2 -> 1080 | BD28: =H28/96*11*2 -> 990 | BE28: =H28/96*1*2 -> 90 | BF28: =H28/96*12*2 -> 1080 | BG28: =H28/96*12*2 -> 1080 | BH28: =H28/96*12*2 -> 1080 | BI28: =H28/96*12*2 -> 1080 | BJ28: =H28/96*11*2 -> 990 | BK28: =H28/96*1*2 -> 90
A29: 44651 | B29: KROGER (KRG LLC) | C29: 美国 | D29: 4500074831 | E29: 500-38488- | F29: 77200GQ2-S002 | G29: 迷你恐龙 | H29: 2880 | I29: 0 | J29: 24 | K29: =H29/J29 -> 120 | L29: 2022/5/16 2022/4/18日取消订单 | M29: 换单到4500075251 | Q29: 44651 | R29: 无 | S29: 无 | T29: 日期码格式：ZURU 标准格式 日期：按实际生产日期 Remark: 1、ZURU标准 MA UPC 版本，出口美国。 2、无测试无验货要求。 3、纸箱4面印ZURU LOGO + 箱唛。 4、日期码请按ZURU标准版执行即可。 5、ZURU QC验货。 | U29: Angela Xu | V29: 1.2468 | W29: =H29*V29 -> 3590.784 | AA29: =Z29-H29 -> -2880 | AD29: =H29 -> 2880 | AI29: =H29 -> 2880 | AN29: =H29 -> 2880 | AR29: =H29/24 -> 120 | BH29: =H29/96*12 -> 360 | BI29: =H29/96*12 -> 360 | BJ29: =H29/96*11 -> 330 | BK29: =H29/96*1 -> 30 | BL29: =H29/96*12 -> 360 | BM29: =H29/96*12 -> 360 | BN29: =H29/96*12 -> 360 | BO29: =H29/96*12 -> 360 | BP29: =H29/96*11 -> 330 | BQ29: =H29/96*1 -> 30
A30: 44651 | B30: KROGER (KRG LLC) | C30: 美国 | D30: 4500074834 | E30: 600-78123- | F30: 77200GQ2-S002 | G30: 迷你恐龙 | H30: 4800 | I30: 0 | J30: 24 | K30: =H30/J30 -> 200 | L30: 2022/5/16 2022/4/18日取消订单 | M30: 换单到4500075264 | Q30: 44651 | R30: 无 | S30: 无 | T30: 日期码格式：ZURU 标准格式 日期：按实际生产日期 Remark: 1、ZURU标准 MA UPC 版本，出口美国。 2、无测试无验货要求。 3、纸箱4面印ZURU LOGO + 箱唛。 4、日期码请按ZURU标准版执行即可。 5、ZURU QC验货。 | U30: Angela Xu | V30: 1.2387 | W30: =H30*V30 -> 5945.76 | AA30: =Z30-H30 -> -4800 | AD30: =H30 -> 4800 | AI30: =H30 -> 4800 | AN30: =H30 -> 4800 | AR30: =H30/24 -> 200 | BH30: =H30/96*12 -> 600 | BI30: =H30/96*12 -> 600 | BJ30: =H30/96*11 -> 550 | BK30: =H30/96*1 -> 50 | BL30: =H30/96*12 -> 600 | BM30: =H30/96*12 -> 600 | BN30: =H30/96*12 -> 600 | BO30: =H30/96*12 -> 600 | BP30: =H30/96*11 -> 550 | BQ30: =H30/96*1 -> 50
A31: 44651 | B31: KROGER (KRG LLC) | C31: 美国 | D31: 4500074837 | E31: 600-10782- | F31: 77200GQ2-S002 | G31: 迷你恐龙 | H31: 1920 | I31: 0 | J31: 24 | K31: =H31/J31 -> 80 | L31: 2022/5/16 2022/4/18日取消订单 | M31: 换单到4500075267 | Q31: 44651 | R31: 无 | S31: 无 | T31: 日期码格式：ZURU 标准格式 日期：按实际生产日期 Remark: 1、ZURU标准 MA UPC 版本，出口美国。 2、无测试无验货要求。 3、纸箱4面印ZURU LOGO + 箱唛。 4、日期码请按ZURU标准版执行即可。 5、ZURU QC验货。 | U31: Angela Xu | V31: 1.2468 | W31: =H31*V31 -> 2393.856 | AA31: =Z31-H31 -> -1920 | AD31: =H31 -> 1920 | AI31: =H31 -> 1920 | AN31: =H31 -> 1920 | AR31: =H31/24 -> 80 | BH31: =H31/96*12 -> 240 | BI31: =H31/96*12 -> 240 | BJ31: =H31/96*11 -> 220 | BK31: =H31/96*1 -> 20 | BL31: =H31/96*12 -> 240 | BM31: =H31/96*12 -> 240 | BN31: =H31/96*12 -> 240 | BO31: =H31/96*12 -> 240 | BP31: =H31/96*11 -> 220 | BQ31: =H31/96*1 -> 20
A32: 44623 | B32: LUDERIX INTERNATIONAL SAS | C32: 法国 | D32: 4500071170 | E32: 4500845200 | F32: 77200GQ2-S001 | G32: 迷你恐龙 | H32: 816 | I32: 0 | J32: 48 | K32: =H32/J32 -> 17 | L32: 2022/7/8 2022/5/6日取消订单 | M32: 2022/7/4 2022/5/6日取消订单 | Q32: 欠 | R32: 无 | S32: 欠 | T32: 日期码格式：ZURU 标准格式 日期：按实际生产日期 Remark: 1.请多备料，每款2-4套左右 4.77200GQ2：MA3L B版收缩膜+MA3LPDQ+MA3L B版收藏指南+MA 3L A版说明书+1张警语贴纸+1张条码贴纸 | U32: Mary Zhong | V32: 1.2553 | W32: =H32*V32 -> 1024.3248 | AA32: =Z32-H32 -> -816 | AE32: =H32 -> 816 | AJ32: =H32 -> 816 | AO32: =H32 -> 816 | AS32: =H32/24 -> 34 | BH32: =H32/96*12 -> 102 | BI32: =H32/96*12 -> 102 | BJ32: =H32/96*11 -> 93.5 | BK32: =H32/96*1 -> 8.5 | BL32: =H32/96*12 -> 102 | BM32: =H32/96*12 -> 102 | BN32: =H32/96*12 -> 102 | BO32: =H32/96*12 -> 102 | BP32: =H32/96*11 -> 93.5 | BQ32: =H32/96*1 -> 8.5
A33: 44684 | B33: BARNES & NOBLE PURCHASING, INC. | C33: 美国 | D33: 4500077833 | E33: PO#2255414 | F33: 77239-S001 | G33: 两个球圆筒装 | H33: 2736 | I33: 0 | J33: 16 | K33: =H33/J33 -> 171 | L33: 44720 | M33: 取消单 | Q33: 欠 | R33: 有 | S33: 欠 | T33: 日期码格式：ZURU 标准格式 日期：按实际生产日期 Remark: 1. 包装：ZURU MA包装 + 价格贴纸（价格贴纸及位置图资料跟单提供，工厂自行采购） ；出口美国； #77239 价贴金额都是$15.99(跟单提供资料，工厂采购） 2.日期跟踪码：产品外包装及产品本身都必须有日期跟踪码，并且确保两者的日期跟踪码要一致；ZURU标准格式日期码(请自行调整具体年月日生产期，但不能为周 末）。 3. 订单外箱 *只需在外箱四个面的左上角印ZURU LOGO； MADE IN CHINA 字样印刷3面，一面留空贴外箱贴纸； *外箱正面需要额外加贴2张外箱贴（外箱贴资料有跟单提供，工厂采购）； *外箱贴位置：shipping label贴于外箱正面左下角；product label 贴于外箱正面右下角，2张贴纸都需距离外箱边缘至少3CM。 5.此单共包含2个客户PO: PO#2255414 和 PO#2255415 | U33: Elsa Zheng | V33: 2.8862 | W33: =H33*V33 -> 7896.6432 | AD33: =H33 -> 2736 | AI33: =H33 -> 2736 | AN33: =H33 -> 2736 | BH33: =H33/96*12*2 -> 684 | BI33: =H33/96*12*2 -> 684 | BJ33: =H33/96*11*2 -> 627 | BK33: =H33/96*1*2 -> 57 | BL33: =H33/96*12*2 -> 684 | BM33: =H33/96*12*2 -> 684 | BN33: =H33/96*12*2 -> 684 | BO33: =H33/96*12*2 -> 684 | BP33: =H33/96*11*2 -> 627 | BQ33: =H33/96*1*2 -> 57
A34: 44684 | B34: BARNES & NOBLE PURCHASING, INC. | C34: 美国 | D34: 4500077833 | E34: PO#2255415 | F34: 77239-S001 | G34: 两个球圆筒装 | H34: 912 | I34: 0 | J34: 16 | K34: =H34/J34 -> 57 | L34: 44720 | M34: 44716 | Q34: 44688 | R34: 有 | S34: 欠 | T34: 日期码格式：ZURU 标准格式 日期：按实际生产日期 Remark: 1. 包装：ZURU MA包装 + 价格贴纸（价格贴纸及位置图资料跟单提供，工厂自行采购） ；出口美国； #77239 价贴金额都是$15.99(跟单提供资料，工厂采购） 2.日期跟踪码：产品外包装及产品本身都必须有日期跟踪码，并且确保两者的日期跟踪码要一致；ZURU标准格式日期码(请自行调整具体年月日生产期，但不能为周 末）。 3. 订单外箱 *只需在外箱四个面的左上角印ZURU LOGO； MADE IN CHINA 字样印刷3面，一面留空贴外箱贴纸； *外箱正面需要额外加贴2张外箱贴（外箱贴资料有跟单提供，工厂采购）； *外箱贴位置：shipping label贴于外箱正面左下角；product label 贴于外箱正面右下角，2张贴纸都需距离外箱边缘至少3CM。 5.此单共包含2个客户PO: PO#2255414 和 PO#2255415 | U34: Elsa Zheng | V34: 2.8862 | W34: =H34*V34 -> 2632.2144 | AD34: =H34 -> 912 | AI34: =H34 -> 912 | AN34: =H34 -> 912 | BH34: =H34/96*12*2 -> 228 | BI34: =H34/96*12*2 -> 228 | BJ34: =H34/96*11*2 -> 209 | BK34: =H34/96*1*2 -> 19 | BL34: =H34/96*12*2 -> 228 | BM34: =H34/96*12*2 -> 228 | BN34: =H34/96*12*2 -> 228 | BO34: =H34/96*12*2 -> 228 | BP34: =H34/96*11*2 -> 209 | BQ34: =H34/96*1*2 -> 19
A35: 44690 | B35: HEB GROCERY COMPANY, LP | C35: 美国 | D35: 4500078402 | E35: 60X439424 | F35: 77200GQ1-S001 | G35: 迷你恐龙 | H35: 2928 | I35: 0 | J35: 12 | K35: =H35/J35 -> 244 | L35: 2022/6/17 2022/6/6日取消订单 | M35: 2022/6/13 2022/6/6日取消订单 | N35: 44732 | Q35: 44699 | R35: 无 | S35: 无 | T35: 日期码格式：ZURU 标准格式 日期：按实际生产日期 Remark: 1.#77200GQ1 客版PDQ，其他都是ZURU标准MA包装 UPC版本-1L.出口美国. 2.#77200GQ1如果产品同旧单4500061704一样，没有变化，则此单不需要再提供大货签样,如有变化需重新提供大货签样：8个球+3个PDQ. 3.要求大货完成时间2022年6月17日，预定2022年6月20日-利丰100%大货验货加抽板，需准备6套测试样品。除抽板之外，如果产品有油漆的需要额外准备5G的油漆 涂在同 材质的胶件上，面积类似A4纸大小。 4.产品和包装上需要印刷tracking code信息,格式为ZURU常规。 5.#77200GQ1: 12pcs/Gravity PDQ,12pcs/CTN,参考旧单#4500061704. | U35: Kelly / Emily Wu | V35: 1.3211 | W35: =H35*V35 -> 3868.1808 | AD35: =H35 -> 2928 | AI35: =H35 -> 2928 | AN35: =H35 -> 2928 | AZ35: =H35/12 -> 244 | BK35: =H35/96*12 -> 366 | BL35: =H35/96*12 -> 366 | BM35: =H35/96*11 -> 335.5 | BN35: =H35/96*1 -> 30.5 | BO35: =H35/96*12 -> 366 | BP35: =H35/96*12 -> 366 | BQ35: =H35/96*12 -> 366 | BR35: =H35/96*12 -> 366 | BS35: =H35/96*11 -> 335.5 | BT35: =H35/96*1 -> 30.5
A36: 44748 | B36: Wal-mart US | C36: ZURU | D36: MO20220706 | E36: TBA | F36: 77361GQ2-S002 | G36: 迷你恐龙球 | H36: 15000 | I36: 0 | J36: 625 | K36: =H36/J36 -> 24 | L36: 44781 | M36: 取消订单 | Q36: 欠 | R36: 有 | S36: 欠 | T36: 1. 包装要求： 77361：MA 1L收缩膜+MA 1L收藏指南+MA 说明书+MA PDQ 每pcs产品要贴一张RFID贴纸，RFID贴纸由ZURU提供，贴纸位置要严格按照客人签板 2.空白外箱（四面右下角需印Zuru Logo)+白色艾利贴纸+粉红色艾利贴纸；请注意外箱上有2张贴纸（1张常规贴纸+1张粉红色贴纸），白色艾利贴纸还是按照以往的包装操作贴在主唛左前下角；1张粉红色贴纸贴在对角线，外箱任一侧面角落备注："MADE IN CHINA" 字样。 3. 在产品上和包装上要有日期码、以及要有MADE IN CHINA和ZURU字样； 4. 产品如有扎带口要剪平，不能刮手。 5. 此单需要抽板验货，抽板期初定8/1，请自行多备包装物料。 | U36: TBA | AC36: =H36 -> 15000 | AF36: 15000 | AI36: =H36 -> 15000 | AL36: =H36/24 -> 625 | AW36: =H36*#REF! -> #REF! | AX36: =H36*#REF! -> #REF! | AY36: =H36*#REF! -> #REF! | AZ36: =H36*#REF! -> #REF! | BA36: =H36*#REF! -> #REF! | BB36: =H36*#REF! -> #REF! | BC36: =H36*#REF! -> #REF! | BD36: =H36*#REF! -> #REF! | BE36: =H36*#REF! -> #REF! | BF36: =H36*#REF! -> #REF! | BG36: =H36*#REF! -> #REF! | BH36: =H36*#REF! -> #REF! | BI36: =H36*#REF! -> #REF!
A37: 44748 | B37: Wal-mart US | C37: ZURU | D37: MO20220706 | E37: TBA | F37: 77361GQ2-S002 | G37: 迷你恐龙球 | H37: 30000 | I37: 0 | J37: 1250 | K37: =H37/J37 -> 24 | L37: 44795 | M37: 取消订单 | Q37: 欠 | R37: 有 | S37: 欠 | T37: 1. 包装要求： 77361：MA 1L收缩膜+MA 1L收藏指南+MA 说明书+MA PDQ 每pcs产品要贴一张RFID贴纸，RFID贴纸由ZURU提供，贴纸位置要严格按照客人签板 2.空白外箱（四面右下角需印Zuru Logo)+白色艾利贴纸+粉红色艾利贴纸；请注意外箱上有2张贴纸（1张常规贴纸+1张粉红色贴纸），白色艾利贴纸还是按照以往的包装操作贴在主唛左前下角；1张粉红色贴纸贴在对角线，外箱任一侧面角落备注："MADE IN CHINA" 字样。 3. 在产品上和包装上要有日期码、以及要有MADE IN CHINA和ZURU字样； 4. 产品如有扎带口要剪平，不能刮手。 5. 此单需要抽板验货，抽板期初定8/1，请自行多备包装物料。 | U37: TBA | AC37: =H37 -> 30000 | AF37: 15000 | AI37: =H37 -> 30000 | AL37: =H37/24 -> 1250 | AW37: =H37*#REF! -> #REF! | AX37: =H37*#REF! -> #REF! | AY37: =H37*#REF! -> #REF! | AZ37: =H37*#REF! -> #REF! | BA37: =H37*#REF! -> #REF! | BB37: =H37*#REF! -> #REF! | BC37: =H37*#REF! -> #REF! | BD37: =H37*#REF! -> #REF! | BE37: =H37*#REF! -> #REF! | BF37: =H37*#REF! -> #REF! | BG37: =H37*#REF! -> #REF! | BH37: =H37*#REF! -> #REF! | BI37: =H37*#REF! -> #REF!
A38: 44748 | B38: Wal-mart US | C38: ZURU | D38: MO20220706 | E38: TBA | F38: 77361GQ2-S002 | G38: 迷你恐龙球 | H38: 20016 | I38: 0 | J38: 834 | K38: =H38/J38 -> 24 | L38: 44799 | M38: 取消订单 | Q38: 欠 | R38: 有 | S38: 欠 | T38: 1. 包装要求： 77361：MA 1L收缩膜+MA 1L收藏指南+MA 说明书+MA PDQ 每pcs产品要贴一张RFID贴纸，RFID贴纸由ZURU提供，贴纸位置要严格按照客人签板 2.空白外箱（四面右下角需印Zuru Logo)+白色艾利贴纸+粉红色艾利贴纸；请注意外箱上有2张贴纸（1张常规贴纸+1张粉红色贴纸），白色艾利贴纸还是按照以往的包装操作贴在主唛左前下角；1张粉红色贴纸贴在对角线，外箱任一侧面角落备注："MADE IN CHINA" 字样。 3. 在产品上和包装上要有日期码、以及要有MADE IN CHINA和ZURU字样； 4. 产品如有扎带口要剪平，不能刮手。 5. 此单需要抽板验货，抽板期初定8/1，请自行多备包装物料。 | U38: TBA | AC38: =H38 -> 20016 | AF38: 15000 | AI38: =H38 -> 20016 | AL38: =H38/24 -> 834 | AW38: =H38*#REF! -> #REF! | AX38: =H38*#REF! -> #REF! | AY38: =H38*#REF! -> #REF! | AZ38: =H38*#REF! -> #REF! | BA38: =H38*#REF! -> #REF! | BB38: =H38*#REF! -> #REF! | BC38: =H38*#REF! -> #REF! | BD38: =H38*#REF! -> #REF! | BE38: =H38*#REF! -> #REF! | BF38: =H38*#REF! -> #REF! | BG38: =H38*#REF! -> #REF! | BH38: =H38*#REF! -> #REF! | BI38: =H38*#REF! -> #REF!
A39: 44748 | B39: Wal-mart US | C39: ZURU | D39: MO20220706 | E39: TBA | F39: 77361GQ2-S002 | G39: 迷你恐龙球 | H39: 15000 | I39: 0 | J39: 625 | K39: =H39/J39 -> 24 | L39: 44803 | M39: 取消订单 | Q39: 欠 | R39: 有 | S39: 欠 | T39: 1. 包装要求： 77361：MA 1L收缩膜+MA 1L收藏指南+MA 说明书+MA PDQ 每pcs产品要贴一张RFID贴纸，RFID贴纸由ZURU提供，贴纸位置要严格按照客人签板 2.空白外箱（四面右下角需印Zuru Logo)+白色艾利贴纸+粉红色艾利贴纸；请注意外箱上有2张贴纸（1张常规贴纸+1张粉红色贴纸），白色艾利贴纸还是按照以往的包装操作贴在主唛左前下角；1张粉红色贴纸贴在对角线，外箱任一侧面角落备注："MADE IN CHINA" 字样。 3. 在产品上和包装上要有日期码、以及要有MADE IN CHINA和ZURU字样； 4. 产品如有扎带口要剪平，不能刮手。 5. 此单需要抽板验货，抽板期初定8/1，请自行多备包装物料。 | U39: TBA | AC39: =H39 -> 15000 | AF39: 15000 | AI39: =H39 -> 15000 | AL39: =H39/24 -> 625 | AW39: =H39*#REF! -> #REF! | AX39: =H39*#REF! -> #REF! | AY39: =H39*#REF! -> #REF! | AZ39: =H39*#REF! -> #REF! | BA39: =H39*#REF! -> #REF! | BB39: =H39*#REF! -> #REF! | BC39: =H39*#REF! -> #REF! | BD39: =H39*#REF! -> #REF! | BE39: =H39*#REF! -> #REF! | BF39: =H39*#REF! -> #REF! | BG39: =H39*#REF! -> #REF! | BH39: =H39*#REF! -> #REF! | BI39: =H39*#REF! -> #REF!
A40: 44748 | B40: Wal-mart US | C40: ZURU | D40: MO20220706 | E40: TBA | F40: 77361GQ2-S002 | G40: 迷你恐龙球 | H40: 15000 | I40: 0 | J40: 625 | K40: =H40/J40 -> 24 | L40: 44804 | M40: 取消订单 | Q40: 欠 | R40: 有 | S40: 欠 | T40: 1. 包装要求： 77361：MA 1L收缩膜+MA 1L收藏指南+MA 说明书+MA PDQ 每pcs产品要贴一张RFID贴纸，RFID贴纸由ZURU提供，贴纸位置要严格按照客人签板 2.空白外箱（四面右下角需印Zuru Logo)+白色艾利贴纸+粉红色艾利贴纸；请注意外箱上有2张贴纸（1张常规贴纸+1张粉红色贴纸），白色艾利贴纸还是按照以往的包装操作贴在主唛左前下角；1张粉红色贴纸贴在对角线，外箱任一侧面角落备注："MADE IN CHINA" 字样。 3. 在产品上和包装上要有日期码、以及要有MADE IN CHINA和ZURU字样； 4. 产品如有扎带口要剪平，不能刮手。 5. 此单需要抽板验货，抽板期初定8/1，请自行多备包装物料。 | U40: TBA | AC40: =H40 -> 15000 | AF40: 15000 | AI40: =H40 -> 15000 | AL40: =H40/24 -> 625 | AW40: =H40*#REF! -> #REF! | AX40: =H40*#REF! -> #REF! | AY40: =H40*#REF! -> #REF! | AZ40: =H40*#REF! -> #REF! | BA40: =H40*#REF! -> #REF! | BB40: =H40*#REF! -> #REF! | BC40: =H40*#REF! -> #REF! | BD40: =H40*#REF! -> #REF! | BE40: =H40*#REF! -> #REF! | BF40: =H40*#REF! -> #REF! | BG40: =H40*#REF! -> #REF! | BH40: =H40*#REF! -> #REF! | BI40: =H40*#REF! -> #REF!
A41: 44643 | B41: Gamestop Texas Ltd | C41: 美国 | D41: 4500074065 | E41: 363358 | F41: 77200GQ1-S001 | G41: 迷你恐龙 | H41: 7200 | I41: 0 | J41: 12 | K41: =H41/J41 -> 600 | L41: 2022/6/20 2022/7/1日取消订单 | M41: 2022/6/23 2022/7/1日取消订单 | N41: 6/24 HOLD 外箱电脑纹格式与客人资料不符 | O41: pass | Q41: 44693 | R41: 无 | S41: 无 | T41: 日期码格式：ZURU 标准格式 日期：按实际生产日期 Remark: 1.#77200GQ1除PDQ是客版外，其他都是ZURU标准MA包装, UPC版本，出口美国. #77200GQ1客版PDQ,12PCS/PDQ, 12PCS/CTN.PDQ资料可参考HEB-PO#4500071096. 2.100%完成大货后安排第三方ITS验货，要求验货地址为验厂报告上的地址，不能随意更换验货地址。 3.产品和包装上需要印刷tracking code信息且两者印刷的内容必须一致,格式为ZURU常规. | U41: Kelly / Emily Wu | V41: 1.3096 | W41: =H41*V41 -> 9429.12 | Z41: 7200 | AA41: =Z41-H41 -> 0 | AD41: =H41 -> 7200 | AI41: =H41 -> 7200 | AN41: =H41 -> 7200 | AZ41: =H41/12 -> 600 | BL41: =H41/96*12 -> 900 | BM41: =H41/96*12 -> 900 | BN41: =H41/96*11 -> 825 | BO41: =H41/96*1 -> 75 | BP41: =H41/96*12 -> 900 | BQ41: =H41/96*12 -> 900 | BR41: =H41/96*12 -> 900 | BS41: =H41/96*12 -> 900 | BT41: =H41/96*11 -> 825 | BU41: =H41/96*1 -> 75
A42: 44643 | B42: Gamestop Texas Ltd | C42: 美国 | D42: 4500074061 | E42: 363356 | F42: 77200GQ1-S001 | G42: 迷你恐龙 | H42: 11112 | I42: 0 | J42: 12 | K42: =H42/J42 -> 926 | L42: 2022/6/20 2022/7/1日取消订单 | M42: 2022/6/23 2022/7/1日取消订单 | N42: 6/24 HOLD 外箱电脑纹格式与客人资料不符 | O42: pass | Q42: 44693 | R42: 无 | S42: 无 | T42: 日期码格式：ZURU 标准格式 日期：按实际生产日期 Remark: 1.#77200GQ1除PDQ是客版外，其他都是ZURU标准MA包装, UPC版本，出口美国. #77200GQ1客版PDQ,12PCS/PDQ, 12PCS/CTN.PDQ资料可参考HEB-PO#4500071096. 2.100%完成大货后安排第三方ITS验货，要求验货地址为验厂报告上的地址，不能随意更换验货地址。 3.产品和包装上需要印刷tracking code信息且两者印刷的内容必须一致,格式为ZURU常规. | U42: Kelly / Emily Wu | V42: 1.2847 | W42: =H42*V42 -> 14275.586 | Z42: 11112 | AA42: =Z42-H42 -> 0 | AD42: =H42 -> 11112 | AI42: =H42 -> 11112 | AN42: =H42 -> 11112 | AZ42: =H42/12 -> 926 | BL42: =H42/96*12 -> 1389 | BM42: =H42/96*12 -> 1389 | BN42: =H42/96*11 -> 1273.25 | BO42: =H42/96*1 -> 115.75 | BP42: =H42/96*12 -> 1389 | BQ42: =H42/96*12 -> 1389 | BR42: =H42/96*12 -> 1389 | BS42: =H42/96*12 -> 1389 | BT42: =H42/96*11 -> 1273.25 | BU42: =H42/96*1 -> 115.75
A43: 44643 | B43: Gamestop Texas Ltd | C43: 美国 | D43: 4500074063 | E43: 363357 | F43: 77200GQ1-S001 | G43: 迷你恐龙 | H43: 11712 | I43: 0 | J43: 12 | K43: =H43/J43 -> 976 | L43: 2022/6/20 2022/7/1日取消订单 | M43: 2022/6/23 2022/7/1日取消订单 | N43: 6/24 HOLD 外箱电脑纹格式与客人资料不符 | O43: pass | Q43: 44693 | R43: 无 | S43: 无 | T43: 日期码格式：ZURU 标准格式 日期：按实际生产日期 Remark: 1.#77200GQ1除PDQ是客版外，其他都是ZURU标准MA包装, UPC版本，出口美国. #77200GQ1客版PDQ,12PCS/PDQ, 12PCS/CTN.PDQ资料可参考HEB-PO#4500071096. 2.100%完成大货后安排第三方ITS验货，要求验货地址为验厂报告上的地址，不能随意更换验货地址。 3.产品和包装上需要印刷tracking code信息且两者印刷的内容必须一致,格式为ZURU常规. | U43: Kelly / Emily Wu | V43: 1.2847 | W43: =H43*V43 -> 15046.406 | Z43: 11712 | AA43: =Z43-H43 -> 0 | AD43: =H43 -> 11712 | AI43: =H43 -> 11712 | AN43: =H43 -> 11712 | AZ43: =H43/12 -> 976 | BL43: =H43/96*12 -> 1464 | BM43: =H43/96*12 -> 1464 | BN43: =H43/96*11 -> 1342 | BO43: =H43/96*1 -> 122 | BP43: =H43/96*12 -> 1464 | BQ43: =H43/96*12 -> 1464 | BR43: =H43/96*12 -> 1464 | BS43: =H43/96*12 -> 1464 | BT43: =H43/96*11 -> 1342 | BU43: =H43/96*1 -> 122
A44: 44712 | B44: BASILE GIOCATTOLI SRL | C44: 意大利 | D44: 4500080204 | F44: 77200GQ2-S001 | G44: 迷你恐龙 | H44: 1200 | I44: 0 | J44: 48 | K44: =H44/J44 -> 25 | L44: 44772 | M44: 2022/7/26 8/3取消1200PCS | O44: Pass | P44: 8/4 截SI | Q44: 44720 | R44: 无 | S44: 44727 | T44: 日期码格式：ZURU 标准格式 日期：按实际生产日期 Remark: #77200GQ2：MA 1L收缩膜/收藏指南/说明书/PDQ+警告语贴纸+EAN贴纸+环保标贴纸 | U44: Andy.Xi | V44: 1.2417 | W44: =H44*V44 -> 1490.04 | Z44: 1200 | AA44: 0 | AD44: =H44 -> 1200 | AI44: =H44 -> 1200 | AN44: =H44 -> 1200 | AT44: =H44/24 -> 50 | BL44: =H44/96*12 -> 150 | BM44: =H44/96*12 -> 150 | BN44: =H44/96*11 -> 137.5 | BO44: =H44/96*1 -> 12.5 | BP44: =H44/96*12 -> 150 | BQ44: =H44/96*12 -> 150 | BR44: =H44/96*12 -> 150 | BS44: =H44/96*12 -> 150 | BT44: =H44/96*11 -> 137.5 | BU44: =H44/96*1 -> 12.5
A45: 44694 | B45: SAINSBURY'S SUPERMARKET LTD | C45: 英国 | D45: 4500078950 | F45: 77200GQ1-S001 | G45: 迷你恐龙 | H45: 1992 | I45: 0 | J45: 12 | K45: =H45/J45 -> 166 | L45: 2022/7/8 2022/7/27日 取消 | M45: 暂停备料和生产 2022/7/27日 取消 | Q45: 44698 | R45: 无 | S45: 无 | T45: 日期码格式：ZURU 标准格式 日期：按实际生产日期 Remark: 1）77200GQ1：MA-1L最新包装，ZURU标准客版PDQ-1L,按ZURU标准比例即可 3）胶带最少宽度要保证6.0CM,厚度最少0.05毫米,外箱不可以打钉/扎带；以工字型封箱 4）如果重量超过5KGS，箱唛需加黄色警示图标志 ，有疑问请与Sherry联系。 5）订单必须经过ZURU QC验货并且通过后方可出货 6）订单出英国，请注意检查产品及包装应带UKCA图标，包装显示ZURU UK LTD信息，QC同事请查核，如有问题与跟单确认。 | U45: SD07 | V45: 1.2853 | W45: =I45*V45 -> 0 | AA45: =Z45-I45 -> 0 | AD45: =H45 -> 1992 | AI45: =H45 -> 1992 | AN45: =H45 -> 1992 | AT45: =H45/24 -> 83 | BL45: =H45/96*12 -> 249 | BM45: =H45/96*12 -> 249 | BN45: =H45/96*11 -> 228.25 | BO45: =H45/96*1 -> 20.75 | BP45: =H45/96*12 -> 249 | BQ45: =H45/96*12 -> 249 | BR45: =H45/96*12 -> 249 | BS45: =H45/96*12 -> 249 | BT45: =H45/96*11 -> 228.25 | BU45: =H45/96*1 -> 20.75
A46: 44691 | B46: WAL-MART STORES INC. USA | C46: 美国 | D46: 4500078601 | E46: 1227470442 | G46: 77200GQ2-S001 77200SLB-S001 | H46: 迷你恐龙卡板装 | I46: 1440 | J46: 24 | K46: 60 | L46: =I46/J46/K46 -> 1 | M46: 2022/6/15 2022/7/7日取消订单 | N46: 2022/6/28 2022/7/7日取消订单 | O46: 6/29 BV验货 | P46: pass | R46: 在原来的空白外箱基础上增加了UPC和箱唛内容 | S46: 有 | T46: 44707 | U46: 日期码格式：ZURU DGYYYYMMDD CHINA(日期避开周末和法定节假日即可） 日期：按实际生产日期 Remark: 77200SLB： 1. 包装要求： 77200： MA 1L B版本收缩膜+MA收藏指南+MA说明书+MA PDQ 每pcs产品上要贴1张RFID贴纸，贴纸由ZURU提供，贴纸位置请严格按照我们签回的签板； 2. 在原来的空白外箱基础上增加了UPC和箱唛内容，在加印的时候确保条形码能扫描出来（需四面右下角有ZURU的Logo），UPC和箱唛内容待提供，外箱侧面任一角 落加印："MADE IN CHINA" 字样； 3. 每个slip sheet上面贴一张艾利贴纸和一张普通贴纸（可A4纸打印），slip sheet打印的普通贴纸的尺寸不能比艾利贴纸小，普通贴纸内容见附件； 4. 在产品上和包装上要有日期码、以及要有MADE IN CHINA和ZURU字样； 5. 此单以slip sheet出货， 24pcs/PDQ/CTN. 60箱/slip sheet； 6. 此单需要验货，请多备料。 | V46: WM TEAM | W46: 1843.9387 | X46: =W46*L46 -> 1843.9387 | AA46: 1440 | AB46: =AA46-I46 -> 0 | BM46: =I46/96*12 -> 180 | BN46: =I46/96*12 -> 180 | BO46: =I46/96*11 -> 165 | BP46: =I46/96*1 -> 15 | BQ46: =I46/96*12 -> 180 | BR46: =I46/96*12 -> 180 | BS46: =I46/96*12 -> 180 | BT46: =I46/96*12 -> 180 | BU46: =I46/96*11 -> 165 | BV46: =I46/96*1 -> 15
A47: 44691 | B47: WAL-MART STORES INC. USA | C47: 美国 | D47: 4500078605 | E47: 1227470027 | G47: 77200GQ2-S002 | H47: 迷你恐龙 | I47: 1464 | J47: 0 | K47: 24 | L47: =I47/K47 -> 61 | M47: 2022/6/15 2022/7/7日取消订单 | N47: 2022/7/1 2022/7/7日取消订单 | O47: 7/4 BV验货 | P47: Pass | R47: 44699 | S47: 有 | T47: 44707 | U47: 日期码格式：ZURU DGYYYYMMDD CHINA(日期避开周末和法定节假日即可） 日期：按实际生产日期 Remark: 77200GQ2： 1. 包装要求： 77200： MA 1L B版本收缩膜+MA收藏指南+MA说明书+MA PDQ 每pcs产品上要贴1张RFID贴纸，贴纸由ZURU提供，贴纸位置请严格按照我们签回的签板； 2. 外箱箱唛+白色艾利贴纸；外箱四面右下角需印ZURU Logo；箱唛资料待提供；常规贴纸还是按照以往的包装操作贴在主唛左前下角；外箱侧面任一角落备注："M ADE IN CHINA" 字样； 3. 在产品上和包装上要有日期码、以及要有MADE IN CHINA和ZURU字样； 4. 此单以bulk carton出货，不以slip sheet出货； 5. 77200：24pcs/PDQ/CTN. 6. 此单需要验货，请多备料。 | V47: WM TEAM | W47: 1.2457 | X47: =I47*W47 -> 1823.7048 | AA47: 1464 | AB47: =AA47-I47 -> 0 | BM47: =I47/96*12 -> 183 | BN47: =I47/96*12 -> 183 | BO47: =I47/96*11 -> 167.75 | BP47: =I47/96*1 -> 15.25 | BQ47: =I47/96*12 -> 183 | BR47: =I47/96*12 -> 183 | BS47: =I47/96*12 -> 183 | BT47: =I47/96*12 -> 183 | BU47: =I47/96*11 -> 167.75 | BV47: =I47/96*1 -> 15.25
A48: 44691 | B48: WAL-MART STORES INC. USA | C48: 美国 | D48: 4500078605 | E48: 1227470028 | G48: 77200GQ2-S002 | H48: 迷你恐龙 | I48: 1560 | J48: 0 | K48: 24 | L48: =I48/K48 -> 65 | M48: 2022/6/15 2022/7/7日取消订单 | N48: 2022/7/1 2022/7/7日取消订单 | O48: 7/4 BV验货 | P48: Pass | R48: 44699 | S48: 有 | T48: 44707 | U48: 日期码格式：ZURU DGYYYYMMDD CHINA(日期避开周末和法定节假日即可） 日期：按实际生产日期 Remark: 77200GQ2： 1. 包装要求： 77200： MA 1L B版本收缩膜+MA收藏指南+MA说明书+MA PDQ 每pcs产品上要贴1张RFID贴纸，贴纸由ZURU提供，贴纸位置请严格按照我们签回的签板； 2. 外箱箱唛+白色艾利贴纸；外箱四面右下角需印ZURU Logo；箱唛资料待提供；常规贴纸还是按照以往的包装操作贴在主唛左前下角；外箱侧面任一角落备注："M ADE IN CHINA" 字样； 3. 在产品上和包装上要有日期码、以及要有MADE IN CHINA和ZURU字样； 4. 此单以bulk carton出货，不以slip sheet出货； 5. 77200：24pcs/PDQ/CTN. 6. 此单需要验货，请多备料。 | V48: WM TEAM | W48: 1.2457 | X48: =I48*W48 -> 1943.292 | AA48: 1560 | AB48: =AA48-I48 -> 0 | BM48: =I48/96*12 -> 195 | BN48: =I48/96*12 -> 195 | BO48: =I48/96*11 -> 178.75 | BP48: =I48/96*1 -> 16.25 | BQ48: =I48/96*12 -> 195 | BR48: =I48/96*12 -> 195 | BS48: =I48/96*12 -> 195 | BT48: =I48/96*12 -> 195 | BU48: =I48/96*11 -> 178.75 | BV48: =I48/96*1 -> 16.25
A49: 44691 | B49: WAL-MART STORES INC. USA | C49: 美国 | D49: 4500078605 | E49: 1227470031 | G49: 77200GQ2-S002 | H49: 迷你恐龙 | I49: 1608 | J49: 0 | K49: 24 | L49: =I49/K49 -> 67 | M49: 2022/6/15 2022/7/7日取消订单 | N49: 2022/7/1 2022/7/7日取消订单 | O49: 7/4 BV验货 | P49: Pass | R49: 44699 | S49: 有 | T49: 44707 | U49: 日期码格式：ZURU DGYYYYMMDD CHINA(日期避开周末和法定节假日即可） 日期：按实际生产日期 Remark: 77200GQ2： 1. 包装要求： 77200： MA 1L B版本收缩膜+MA收藏指南+MA说明书+MA PDQ 每pcs产品上要贴1张RFID贴纸，贴纸由ZURU提供，贴纸位置请严格按照我们签回的签板； 2. 外箱箱唛+白色艾利贴纸；外箱四面右下角需印ZURU Logo；箱唛资料待提供；常规贴纸还是按照以往的包装操作贴在主唛左前下角；外箱侧面任一角落备注："M ADE IN CHINA" 字样； 3. 在产品上和包装上要有日期码、以及要有MADE IN CHINA和ZURU字样； 4. 此单以bulk carton出货，不以slip sheet出货； 5. 77200：24pcs/PDQ/CTN. 6. 此单需要验货，请多备料。 | V49: WM TEAM | W49: 1.2457 | X49: =I49*W49 -> 2003.0856 | AA49: 1608 | AB49: =AA49-I49 -> 0 | BM49: =I49/96*12 -> 201 | BN49: =I49/96*12 -> 201 | BO49: =I49/96*11 -> 184.25 | BP49: =I49/96*1 -> 16.75 | BQ49: =I49/96*12 -> 201 | BR49: =I49/96*12 -> 201 | BS49: =I49/96*12 -> 201 | BT49: =I49/96*12 -> 201 | BU49: =I49/96*11 -> 184.25 | BV49: =I49/96*1 -> 16.75
A50: 44691 | B50: WAL-MART STORES INC. USA | C50: 美国 | D50: 4500078605 | E50: 1227470032 | G50: 77200GQ2-S002 | H50: 迷你恐龙 | I50: 1272 | J50: 0 | K50: 24 | L50: =I50/K50 -> 53 | M50: 2022/6/15 2022/7/7日取消订单 | N50: 2022/7/1 2022/7/7日取消订单 | O50: 7/4 BV验货 | P50: Pass | R50: 44699 | S50: 有 | T50: 44707 | U50: 日期码格式：ZURU DGYYYYMMDD CHINA(日期避开周末和法定节假日即可） 日期：按实际生产日期 Remark: 77200GQ2： 1. 包装要求： 77200： MA 1L B版本收缩膜+MA收藏指南+MA说明书+MA PDQ 每pcs产品上要贴1张RFID贴纸，贴纸由ZURU提供，贴纸位置请严格按照我们签回的签板； 2. 外箱箱唛+白色艾利贴纸；外箱四面右下角需印ZURU Logo；箱唛资料待提供；常规贴纸还是按照以往的包装操作贴在主唛左前下角；外箱侧面任一角落备注："M ADE IN CHINA" 字样； 3. 在产品上和包装上要有日期码、以及要有MADE IN CHINA和ZURU字样； 4. 此单以bulk carton出货，不以slip sheet出货； 5. 77200：24pcs/PDQ/CTN. 6. 此单需要验货，请多备料。 | V50: WM TEAM | W50: 1.2457 | X50: =I50*W50 -> 1584.5304 | AA50: 1272 | AB50: =AA50-I50 -> 0 | BM50: =I50/96*12 -> 159 | BN50: =I50/96*12 -> 159 | BO50: =I50/96*11 -> 145.75 | BP50: =I50/96*1 -> 13.25 | BQ50: =I50/96*12 -> 159 | BR50: =I50/96*12 -> 159 | BS50: =I50/96*12 -> 159 | BT50: =I50/96*12 -> 159 | BU50: =I50/96*11 -> 145.75 | BV50: =I50/96*1 -> 13.25
A51: 44691 | B51: WAL-MART STORES INC. USA | C51: 美国 | D51: 4500078605 | E51: 1227470033 | G51: 77200GQ2-S002 | H51: 迷你恐龙 | I51: 936 | J51: 0 | K51: 24 | L51: =I51/K51 -> 39 | M51: 2022/6/15 2022/7/7日取消订单 | N51: 2022/7/1 2022/7/7日取消订单 | O51: 7/4 BV验货 | P51: Pass | R51: 44699 | S51: 有 | T51: 44707 | U51: 日期码格式：ZURU DGYYYYMMDD CHINA(日期避开周末和法定节假日即可） 日期：按实际生产日期 Remark: 77200GQ2： 1. 包装要求： 77200： MA 1L B版本收缩膜+MA收藏指南+MA说明书+MA PDQ 每pcs产品上要贴1张RFID贴纸，贴纸由ZURU提供，贴纸位置请严格按照我们签回的签板； 2. 外箱箱唛+白色艾利贴纸；外箱四面右下角需印ZURU Logo；箱唛资料待提供；常规贴纸还是按照以往的包装操作贴在主唛左前下角；外箱侧面任一角落备注："M ADE IN CHINA" 字样； 3. 在产品上和包装上要有日期码、以及要有MADE IN CHINA和ZURU字样； 4. 此单以bulk carton出货，不以slip sheet出货； 5. 77200：24pcs/PDQ/CTN. 6. 此单需要验货，请多备料。 | V51: WM TEAM | W51: 1.2457 | X51: =I51*W51 -> 1165.9752 | AA51: 936 | AB51: =AA51-I51 -> 0 | BM51: =I51/96*12 -> 117 | BN51: =I51/96*12 -> 117 | BO51: =I51/96*11 -> 107.25 | BP51: =I51/96*1 -> 9.75 | BQ51: =I51/96*12 -> 117 | BR51: =I51/96*12 -> 117 | BS51: =I51/96*12 -> 117 | BT51: =I51/96*12 -> 117 | BU51: =I51/96*11 -> 107.25 | BV51: =I51/96*1 -> 9.75
A52: 44691 | B52: WAL-MART STORES INC. USA | C52: 美国 | D52: 4500078605 | E52: 1227470083 | G52: 77200GQ2-S002 | H52: 迷你恐龙 | I52: 1272 | J52: 0 | K52: 24 | L52: =I52/K52 -> 53 | M52: 2022/6/15 2022/7/7日取消订单 | N52: 2022/7/1 2022/7/7日取消订单 | O52: 7/4 BV验货 | P52: Pass | R52: 44699 | S52: 有 | T52: 44707 | U52: 日期码格式：ZURU DGYYYYMMDD CHINA(日期避开周末和法定节假日即可） 日期：按实际生产日期 Remark: 77200GQ2： 1. 包装要求： 77200： MA 1L B版本收缩膜+MA收藏指南+MA说明书+MA PDQ 每pcs产品上要贴1张RFID贴纸，贴纸由ZURU提供，贴纸位置请严格按照我们签回的签板； 2. 外箱箱唛+白色艾利贴纸；外箱四面右下角需印ZURU Logo；箱唛资料待提供；常规贴纸还是按照以往的包装操作贴在主唛左前下角；外箱侧面任一角落备注："M ADE IN CHINA" 字样； 3. 在产品上和包装上要有日期码、以及要有MADE IN CHINA和ZURU字样； 4. 此单以bulk carton出货，不以slip sheet出货； 5. 77200：24pcs/PDQ/CTN. 6. 此单需要验货，请多备料。 | V52: WM TEAM | W52: 1.2457 | X52: =I52*W52 -> 1584.5304 | AA52: 1272 | AB52: =AA52-I52 -> 0 | BM52: =I52/96*12 -> 159 | BN52: =I52/96*12 -> 159 | BO52: =I52/96*11 -> 145.75 | BP52: =I52/96*1 -> 13.25 | BQ52: =I52/96*12 -> 159 | BR52: =I52/96*12 -> 159 | BS52: =I52/96*12 -> 159 | BT52: =I52/96*12 -> 159 | BU52: =I52/96*11 -> 145.75 | BV52: =I52/96*1 -> 13.25
A53: 44691 | B53: WAL-MART STORES INC. USA | C53: 美国 | D53: 4500078601 | E53: 1227470439 | G53: 77200GQ2-S001 77200SLB-S001 | H53: 迷你恐龙卡板装 | I53: 1440 | J53: 24 | K53: 60 | L53: =I53/J53/K53 -> 1 | M53: 2022/6/15 2022/7/7日取消订单 | N53: 2022/7/1 2022/7/7日取消订单 | O53: 7/4 BV验货 | P53: pass | R53: 在原来的空白外箱基础上增加了UPC和箱唛内容 | S53: 有 | T53: 44707 | U53: 日期码格式：ZURU DGYYYYMMDD CHINA(日期避开周末和法定节假日即可） 日期：按实际生产日期 Remark: 77200SLB： 1. 包装要求： 77200： MA 1L B版本收缩膜+MA收藏指南+MA说明书+MA PDQ 每pcs产品上要贴1张RFID贴纸，贴纸由ZURU提供，贴纸位置请严格按照我们签回的签板； 2. 在原来的空白外箱基础上增加了UPC和箱唛内容，在加印的时候确保条形码能扫描出来（需四面右下角有ZURU的Logo），UPC和箱唛内容待提供，外箱侧面任一角 落加印："MADE IN CHINA" 字样； 3. 每个slip sheet上面贴一张艾利贴纸和一张普通贴纸（可A4纸打印），slip sheet打印的普通贴纸的尺寸不能比艾利贴纸小，普通贴纸内容见附件； 4. 在产品上和包装上要有日期码、以及要有MADE IN CHINA和ZURU字样； 5. 此单以slip sheet出货， 24pcs/PDQ/CTN. 60箱/slip sheet； 6. 此单需要验货，请多备料。 | V53: WM TEAM | W53: 1843.9387 | X53: =W53*L53 -> 1843.9387 | AA53: 1440 | AB53: =AA53-I53 -> 0 | BM53: =I53/96*12 -> 180 | BN53: =I53/96*12 -> 180 | BO53: =I53/96*11 -> 165 | BP53: =I53/96*1 -> 15 | BQ53: =I53/96*12 -> 180 | BR53: =I53/96*12 -> 180 | BS53: =I53/96*12 -> 180 | BT53: =I53/96*12 -> 180 | BU53: =I53/96*11 -> 165 | BV53: =I53/96*1 -> 15
A54: 44691 | B54: WAL-MART STORES INC. USA | C54: 美国 | D54: 4500078601 | E54: 1227470443 | G54: 77200GQ2-S001 77200SLB-S001 | H54: 迷你恐龙卡板装 | I54: 1440 | J54: 24 | K54: 60 | L54: =I54/J54/K54 -> 1 | M54: 2022/6/15 2022/7/7日取消订单 | N54: 2022/7/1 2022/7/7日取消订单 | O54: 7/4 BV验货 | P54: pass | R54: 在原来的空白外箱基础上增加了UPC和箱唛内容 | S54: 有 | T54: 44707 | U54: 日期码格式：ZURU DGYYYYMMDD CHINA(日期避开周末和法定节假日即可） 日期：按实际生产日期 Remark: 77200SLB： 1. 包装要求： 77200： MA 1L B版本收缩膜+MA收藏指南+MA说明书+MA PDQ 每pcs产品上要贴1张RFID贴纸，贴纸由ZURU提供，贴纸位置请严格按照我们签回的签板； 2. 在原来的空白外箱基础上增加了UPC和箱唛内容，在加印的时候确保条形码能扫描出来（需四面右下角有ZURU的Logo），UPC和箱唛内容待提供，外箱侧面任一角 落加印："MADE IN CHINA" 字样； 3. 每个slip sheet上面贴一张艾利贴纸和一张普通贴纸（可A4纸打印），slip sheet打印的普通贴纸的尺寸不能比艾利贴纸小，普通贴纸内容见附件； 4. 在产品上和包装上要有日期码、以及要有MADE IN CHINA和ZURU字样； 5. 此单以slip sheet出货， 24pcs/PDQ/CTN. 60箱/slip sheet； 6. 此单需要验货，请多备料。 | V54: WM TEAM | W54: 1843.9387 | X54: =W54*L54 -> 1843.9387 | AA54: 1440 | AB54: =AA54-I54 -> 0 | BM54: =I54/96*12 -> 180 | BN54: =I54/96*12 -> 180 | BO54: =I54/96*11 -> 165 | BP54: =I54/96*1 -> 15 | BQ54: =I54/96*12 -> 180 | BR54: =I54/96*12 -> 180 | BS54: =I54/96*12 -> 180 | BT54: =I54/96*12 -> 180 | BU54: =I54/96*11 -> 165 | BV54: =I54/96*1 -> 15
A55: 44697 | B55: WAL-MART STORES INC. USA | C55: 美国 | D55: 4500079062 | E55: 4231913381 | G55: 77200GQ2-S001 77200SLB-S001 | H55: 迷你恐龙卡板装 | I55: 1440 | J55: 24 | K55: 60 | L55: =I55/J55/K55 -> 1 | M55: 2022/6/22 2022/7/7日取消订单 | N55: 2022/7/2 2022/7/7日取消订单 | O55: 7/4 BV验货 | P55: Pass | R55: 在原来的空白外箱基础上增加了UPC和箱唛内容 | S55: 有 | T55: 44707 | U55: 日期码格式：ZURU DGYYYYMMDD CHINA(日期避开周末和法定节假日即可） 日期：按实际生产日期 Remark: 77200SLB： 1. 包装要求： 77200： MA 1L B版本收缩膜+MA收藏指南+MA说明书+MA PDQ 每pcs产品上要贴1张RFID贴纸，贴纸由ZURU提供，贴纸位置请严格按照我们签回的签板； 2. 在原来的空白外箱基础上增加了UPC和箱唛内容，在加印的时候确保条形码能扫描出来（需四面右下角有ZURU的Logo），UPC和箱唛内容待提供，外箱侧面任一角 落加印："MADE IN CHINA" 字样； 3. 每个slip sheet上面贴一张艾利贴纸和一张普通贴纸（可A4纸打印），slip sheet打印的普通贴纸的尺寸不能比艾利贴纸小，普通贴纸内容见附件； 4. 在产品上和包装上要有日期码、以及要有MADE IN CHINA和ZURU字样； 5. 此单以slip sheet出货， 24pcs/PDQ/CTN. 60箱/slip sheet； 6. 此单需要验货，请多备料。 | V55: SD08 | W55: 1843.9387 | X55: =W55*L55 -> 1843.9387 | AA55: 1440 | AB55: =AA55-I55 -> 0 | BM55: =I55/96*12 -> 180 | BN55: =I55/96*12 -> 180 | BO55: =I55/96*11 -> 165 | BP55: =I55/96*1 -> 15 | BQ55: =I55/96*12 -> 180 | BR55: =I55/96*12 -> 180 | BS55: =I55/96*12 -> 180 | BT55: =I55/96*12 -> 180 | BU55: =I55/96*11 -> 165 | BV55: =I55/96*1 -> 15
A56: 44697 | B56: WAL-MART STORES INC. USA | C56: 美国 | D56: 4500079062 | E56: 4231913382 | G56: 77200GQ2-S001 77200SLB-S001 | H56: 迷你恐龙卡板装 | I56: 1440 | J56: 24 | K56: 60 | L56: =I56/J56/K56 -> 1 | M56: 2022/6/22 2022/7/7日取消订单 | N56: 2022/7/2 2022/7/7日取消订单 | O56: 7/4 BV验货 | P56: Pass | R56: 在原来的空白外箱基础上增加了UPC和箱唛内容 | S56: 有 | T56: 44707 | U56: 日期码格式：ZURU DGYYYYMMDD CHINA(日期避开周末和法定节假日即可） 日期：按实际生产日期 Remark: 77200SLB： 1. 包装要求： 77200： MA 1L B版本收缩膜+MA收藏指南+MA说明书+MA PDQ 每pcs产品上要贴1张RFID贴纸，贴纸由ZURU提供，贴纸位置请严格按照我们签回的签板； 2. 在原来的空白外箱基础上增加了UPC和箱唛内容，在加印的时候确保条形码能扫描出来（需四面右下角有ZURU的Logo），UPC和箱唛内容待提供，外箱侧面任一角 落加印："MADE IN CHINA" 字样； 3. 每个slip sheet上面贴一张艾利贴纸和一张普通贴纸（可A4纸打印），slip sheet打印的普通贴纸的尺寸不能比艾利贴纸小，普通贴纸内容见附件； 4. 在产品上和包装上要有日期码、以及要有MADE IN CHINA和ZURU字样； 5. 此单以slip sheet出货， 24pcs/PDQ/CTN. 60箱/slip sheet； 6. 此单需要验货，请多备料。 | V56: SD08 | W56: 1843.9387 | X56: =W56*L56 -> 1843.9387 | AA56: 1440 | AB56: =AA56-I56 -> 0 | BM56: =I56/96*12 -> 180 | BN56: =I56/96*12 -> 180 | BO56: =I56/96*11 -> 165 | BP56: =I56/96*1 -> 15 | BQ56: =I56/96*12 -> 180 | BR56: =I56/96*12 -> 180 | BS56: =I56/96*12 -> 180 | BT56: =I56/96*12 -> 180 | BU56: =I56/96*11 -> 165 | BV56: =I56/96*1 -> 15
A57: 44697 | B57: WAL-MART STORES INC. USA | C57: 美国 | D57: 4500079062 | E57: 4231913384 | G57: 77200GQ2-S001 77200SLB-S001 | H57: 迷你恐龙卡板装 | I57: 1440 | J57: 24 | K57: 60 | L57: =I57/J57/K57 -> 1 | M57: 2022/6/22 2022/7/7日取消订单 | N57: 2022/7/2 2022/7/7日取消订单 | O57: 7/4 BV验货 | P57: Pass | R57: 在原来的空白外箱基础上增加了UPC和箱唛内容 | S57: 有 | T57: 44707 | U57: 日期码格式：ZURU DGYYYYMMDD CHINA(日期避开周末和法定节假日即可） 日期：按实际生产日期 Remark: 77200SLB： 1. 包装要求： 77200： MA 1L B版本收缩膜+MA收藏指南+MA说明书+MA PDQ 每pcs产品上要贴1张RFID贴纸，贴纸由ZURU提供，贴纸位置请严格按照我们签回的签板； 2. 在原来的空白外箱基础上增加了UPC和箱唛内容，在加印的时候确保条形码能扫描出来（需四面右下角有ZURU的Logo），UPC和箱唛内容待提供，外箱侧面任一角 落加印："MADE IN CHINA" 字样； 3. 每个slip sheet上面贴一张艾利贴纸和一张普通贴纸（可A4纸打印），slip sheet打印的普通贴纸的尺寸不能比艾利贴纸小，普通贴纸内容见附件； 4. 在产品上和包装上要有日期码、以及要有MADE IN CHINA和ZURU字样； 5. 此单以slip sheet出货， 24pcs/PDQ/CTN. 60箱/slip sheet； 6. 此单需要验货，请多备料。 | V57: SD08 | W57: 1843.9387 | X57: =W57*L57 -> 1843.9387 | AA57: 1440 | AB57: =AA57-I57 -> 0 | BM57: =I57/96*12 -> 180 | BN57: =I57/96*12 -> 180 | BO57: =I57/96*11 -> 165 | BP57: =I57/96*1 -> 15 | BQ57: =I57/96*12 -> 180 | BR57: =I57/96*12 -> 180 | BS57: =I57/96*12 -> 180 | BT57: =I57/96*12 -> 180 | BU57: =I57/96*11 -> 165 | BV57: =I57/96*1 -> 15
A58: 44691 | B58: WAL-MART STORES INC. USA | C58: 美国 | D58: 4500078628 | E58: 1227470084 | G58: 77200GQ2-S002 | H58: 迷你恐龙 | I58: 936 | J58: 0 | K58: 24 | L58: =I58/K58 -> 39 | M58: 2022/6/25 2022/7/7日取消订单 | N58: 2022/6/30 2022/7/7日取消订单 | O58: 7/4 BV验货 | P58: Pass | R58: 44699 | S58: 有 | T58: 44707 | U58: 日期码格式：ZURU DGYYYYMMDD CHINA(日期避开周末和法定节假日即可） 日期：按实际生产日期 Remark: 77200GQ2： 1. 包装要求： 77200： MA 1L B版本收缩膜+MA收藏指南+MA说明书+MA PDQ 每pcs产品上要贴1张RFID贴纸，贴纸由ZURU提供，贴纸位置请严格按照我们签回的签板； 2. 外箱箱唛+白色艾利贴纸；外箱四面右下角需印ZURU Logo；箱唛资料待提供；常规贴纸还是按照以往的包装操作贴在主唛左前下角；外箱侧面任一角落备注："M ADE IN CHINA" 字样； 3. 在产品上和包装上要有日期码、以及要有MADE IN CHINA和ZURU字样； 4. 此单以bulk carton出货，不以slip sheet出货； 5. 77200：24pcs/PDQ/CTN. 6. 此单需要验货，请多备料。 | V58: SD08 | W58: 1.2897 | X58: =I58*W58 -> 1207.1592 | AA58: 936 | AB58: =AA58-I58 -> 0 | BM58: =I58/96*12 -> 117 | BN58: =I58/96*12 -> 117 | BO58: =I58/96*11 -> 107.25 | BP58: =I58/96*1 -> 9.75 | BQ58: =I58/96*12 -> 117 | BR58: =I58/96*12 -> 117 | BS58: =I58/96*12 -> 117 | BT58: =I58/96*12 -> 117 | BU58: =I58/96*11 -> 107.25 | BV58: =I58/96*1 -> 9.75
A59: 44691 | B59: WAL-MART STORES INC. USA | C59: 美国 | D59: 4500078634 | E59: 8727369870 | G59: 77200GQ2-S001 77200SLB-S001 | H59: 迷你恐龙卡板装 | I59: 1440 | J59: 24 | K59: 60 | L59: =I59/J59/K59 -> 1 | M59: 2022/6/28 2022/7/7日取消订单 | N59: 2022/7/6 2022/7/7日取消订单 | O59: 7/8 BV验货 | R59: 在原来的空白外箱基础上增加了UPC和箱唛内容 | S59: 有 | T59: 44707 | U59: 日期码格式：ZURU DGYYYYMMDD CHINA(日期避开周末和法定节假日即可） 日期：按实际生产日期 Remark: 77200SLB： 1. 包装要求： 77200： MA 1L B版本收缩膜+MA收藏指南+MA说明书+MA PDQ 每pcs产品上要贴1张RFID贴纸，贴纸由ZURU提供，贴纸位置请严格按照我们签回的签板； 2. 在原来的空白外箱基础上增加了UPC和箱唛内容，在加印的时候确保条形码能扫描出来（需四面右下角有ZURU的Logo），UPC和箱唛内容待提供，外箱侧面任一角 落加印："MADE IN CHINA" 字样； 3. 每个slip sheet上面贴一张艾利贴纸和一张普通贴纸（可A4纸打印），slip sheet打印的普通贴纸的尺寸不能比艾利贴纸小，普通贴纸内容见附件； 4. 在产品上和包装上要有日期码、以及要有MADE IN CHINA和ZURU字样； 5. 此单以slip sheet出货， 24pcs/PDQ/CTN. 60箱/slip sheet； 6. 此单需要验货，请多备料。 | V59: SD35 | W59: 1843.9387 | X59: =W59*L59 -> 1843.9387 | AA59: 1440 | AB59: =AA59-I59 -> 0 | BM59: =I59/96*12 -> 180 | BN59: =I59/96*12 -> 180 | BO59: =I59/96*11 -> 165 | BP59: =I59/96*1 -> 15 | BQ59: =I59/96*12 -> 180 | BR59: =I59/96*12 -> 180 | BS59: =I59/96*12 -> 180 | BT59: =I59/96*12 -> 180 | BU59: =I59/96*11 -> 165 | BV59: =I59/96*1 -> 15
A60: 44798 | B60: WAL-MART STORES INC. USA | C60: 美国 | D60: 4500085499 | E60: 9028493605 | F60: 50-77361-STD PRODUCT | G60: 77361SLB-S001 | H60: 迷你恐龙球 卡板装 | I60: 1440 | J60: 0 | K60: 1440 | L60: =I60/K60 -> 1 | M60: 44868 | N60: 9/30取消 | R60: 44810 | S60: 有 | T60: 44817 | U60: 日期码格式：ZURU DGYYYYMMDD CHINA(日期避开周末和法定节假日即可） 日期：按实际生产日期 Packaging Info: 77361: MA 1L收缩膜+MA 1LPDQ+MA 说明书+MA 收藏指南, 翻单：4500084631 Remark: 1. 包装要求 77361: MA 1L收缩膜+MA 1LPDQ+MA 说明书+MA 收藏指南, 翻单：4500084631 每pcs产品上要贴1张RFID贴纸，贴纸由ZURU提供，贴纸位置请严格按照我们签回的签板； 2. 在原来的空白外箱基础上增加了UPC内容+RFID箱唛，在加印的时候确保条形码能扫描出来（需四面右下角有ZURU的Logo），UPC内容待和RFID箱唛提供，外箱侧 面任一角落加印："MADE IN CHINA" 字样； 3. 每个slip sheet上面贴一张艾利贴纸和一张普通贴纸（可A4纸打印），slip sheet打印的普通贴纸的尺寸不能比艾利贴纸小，普通贴纸内容见附件； 4. 在产品上和包装上要有日期码、以及要有MADE IN CHINA和ZURU字样； 5. 产品如有扎带口要剪平，不能刮手。 6. 此单需要验货，请多备料 7. 此单以slip sheet出货， 77361：24pcs/PDQ/CTN；1440pcs/60CTN/Slip Sheet | V60: WM TEAM | W60: 1616.8202 | X60: =W60*L60 -> 1616.8202 | AB60: =AA60-I60 -> -1440 | AD60: =I60 -> 1440 | AG60: =I60 -> 1440 | AJ60: =I60 -> 1440 | AM60: =I60/24 -> 60 | AY60: =I60*#REF! -> #REF! | AZ60: =I60*#REF! -> #REF! | BA60: =I60*#REF! -> #REF! | BB60: =I60*#REF! -> #REF! | BC60: =I60*#REF! -> #REF! | BD60: =I60*#REF! -> #REF! | BE60: =I60*#REF! -> #REF! | BF60: =I60*#REF! -> #REF! | BG60: =I60*#REF! -> #REF! | BH60: =I60*#REF! -> #REF! | BI60: =I60*#REF! -> #REF! | BJ60: =I60*#REF! -> #REF! | BK60: =I60*#REF! -> #REF!
A61: 44798 | B61: WAL-MART STORES INC. USA | C61: 美国 | D61: 4500085500 | E61: 9028493607 | F61: 20-77361SLB-S001 | G61: 77361SLB-S001 | H61: 迷你恐龙球 卡板装 | I61: 2880 | J61: 0 | K61: 1440 | L61: =I61/K61 -> 2 | M61: 44873 | N61: 9/30取消 | R61: 44810 | S61: 有 | T61: 44817 | U61: 日期码格式：ZURU DGYYYYMMDD CHINA(日期避开周末和法定节假日即可） 日期：按实际生产日期 Packaging Info: 77361: MA 1L收缩膜+MA 1LPDQ+MA 说明书+MA 收藏指南, 翻单：4500084631 Remark: 1. 包装要求 77361: MA 1L收缩膜+MA 1LPDQ+MA 说明书+MA 收藏指南, 翻单：4500084631 每pcs产品上要贴1张RFID贴纸，贴纸由ZURU提供，贴纸位置请严格按照我们签回的签板； 2. 在原来的空白外箱基础上增加了UPC内容+RFID箱唛，在加印的时候确保条形码能扫描出来（需四面右下角有ZURU的Logo），UPC内容待和RFID箱唛提供，外箱侧 面任一角落加印："MADE IN CHINA" 字样； 3. 每个slip sheet上面贴一张艾利贴纸和一张普通贴纸（可A4纸打印），slip sheet打印的普通贴纸的尺寸不能比艾利贴纸小，普通贴纸内容见附件； 4. 在产品上和包装上要有日期码、以及要有MADE IN CHINA和ZURU字样； 5. 产品如有扎带口要剪平，不能刮手。 6. 此单需要验货，请多备料 7. 此单以slip sheet出货， 77361：24pcs/PDQ/CTN；1440pcs/60CTN/Slip Sheet | V61: WM TEAM | W61: 1616.8202 | X61: =W61*L61 -> 3233.6404 | AB61: =AA61-I61 -> -2880 | AD61: =I61 -> 2880 | AG61: =I61 -> 2880 | AJ61: =I61 -> 2880 | AM61: =I61/24 -> 120 | AY61: =I61*#REF! -> #REF! | AZ61: =I61*#REF! -> #REF! | BA61: =I61*#REF! -> #REF! | BB61: =I61*#REF! -> #REF! | BC61: =I61*#REF! -> #REF! | BD61: =I61*#REF! -> #REF! | BE61: =I61*#REF! -> #REF! | BF61: =I61*#REF! -> #REF! | BG61: =I61*#REF! -> #REF! | BH61: =I61*#REF! -> #REF! | BI61: =I61*#REF! -> #REF! | BJ61: =I61*#REF! -> #REF! | BK61: =I61*#REF! -> #REF!
A62: 44798 | B62: WAL-MART STORES INC. USA | C62: 美国 | D62: 4500085501 | E62: 9028493599 | F62: 20-77361SLB-S001 | G62: 77361SLB-S001 | H62: 迷你恐龙球 卡板装 | I62: 1440 | J62: 0 | K62: 1440 | L62: =I62/K62 -> 1 | M62: 44877 | N62: 9/30取消 | R62: 44810 | S62: 有 | T62: 44817 | U62: 日期码格式：ZURU DGYYYYMMDD CHINA(日期避开周末和法定节假日即可） 日期：按实际生产日期 Packaging Info: 77361: MA 1L收缩膜+MA 1LPDQ+MA 说明书+MA 收藏指南, 翻单：4500084631 Remark: 1. 包装要求 77361: MA 1L收缩膜+MA 1LPDQ+MA 说明书+MA 收藏指南, 翻单：4500084631 每pcs产品上要贴1张RFID贴纸，贴纸由ZURU提供，贴纸位置请严格按照我们签回的签板； 2. 在原来的空白外箱基础上增加了UPC内容+RFID箱唛，在加印的时候确保条形码能扫描出来（需四面右下角有ZURU的Logo），UPC内容待和RFID箱唛提供，外箱侧 面任一角落加印："MADE IN CHINA" 字样； 3. 每个slip sheet上面贴一张艾利贴纸和一张普通贴纸（可A4纸打印），slip sheet打印的普通贴纸的尺寸不能比艾利贴纸小，普通贴纸内容见附件； 4. 在产品上和包装上要有日期码、以及要有MADE IN CHINA和ZURU字样； 5. 产品如有扎带口要剪平，不能刮手。 6. 此单需要验货，请多备料 7. 此单以slip sheet出货， 77361：24pcs/PDQ/CTN；1440pcs/60CTN/Slip Sheet | V62: WM TEAM | W62: 1616.8202 | X62: =W62*L62 -> 1616.8202 | AB62: =AA62-I62 -> -1440 | AD62: =I62 -> 1440 | AG62: =I62 -> 1440 | AJ62: =I62 -> 1440 | AM62: =I62/24 -> 60 | AY62: =I62*#REF! -> #REF! | AZ62: =I62*#REF! -> #REF! | BA62: =I62*#REF! -> #REF! | BB62: =I62*#REF! -> #REF! | BC62: =I62*#REF! -> #REF! | BD62: =I62*#REF! -> #REF! | BE62: =I62*#REF! -> #REF! | BF62: =I62*#REF! -> #REF! | BG62: =I62*#REF! -> #REF! | BH62: =I62*#REF! -> #REF! | BI62: =I62*#REF! -> #REF! | BJ62: =I62*#REF! -> #REF! | BK62: =I62*#REF! -> #REF!
A63: 44798 | B63: WAL-MART STORES INC. USA | C63: 美国 | D63: 4500085502 | E63: 9028493603 | F63: 10-77361SLB-S001 | G63: 77361SLB-S001 | H63: 迷你恐龙球 卡板装 | I63: 1440 | J63: 0 | K63: 1440 | L63: =I63/K63 -> 1 | M63: 44880 | N63: 9/30取消 | R63: 44810 | S63: 有 | T63: 44817 | U63: 日期码格式：ZURU DGYYYYMMDD CHINA(日期避开周末和法定节假日即可） 日期：按实际生产日期 Packaging Info: 77361: MA 1L收缩膜+MA 1LPDQ+MA 说明书+MA 收藏指南, 翻单：4500084631 Remark: 1. 包装要求 77361: MA 1L收缩膜+MA 1LPDQ+MA 说明书+MA 收藏指南, 翻单：4500084631 每pcs产品上要贴1张RFID贴纸，贴纸由ZURU提供，贴纸位置请严格按照我们签回的签板； 2. 在原来的空白外箱基础上增加了UPC内容+RFID箱唛，在加印的时候确保条形码能扫描出来（需四面右下角有ZURU的Logo），UPC内容待和RFID箱唛提供，外箱侧 面任一角落加印："MADE IN CHINA" 字样； 3. 每个slip sheet上面贴一张艾利贴纸和一张普通贴纸（可A4纸打印），slip sheet打印的普通贴纸的尺寸不能比艾利贴纸小，普通贴纸内容见附件； 4. 在产品上和包装上要有日期码、以及要有MADE IN CHINA和ZURU字样； 5. 产品如有扎带口要剪平，不能刮手。 6. 此单需要验货，请多备料 7. 此单以slip sheet出货， 77361：24pcs/PDQ/CTN；1440pcs/60CTN/Slip Sheet | V63: WM TEAM | W63: 1616.8202 | X63: =W63*L63 -> 1616.8202 | AB63: =AA63-I63 -> -1440 | AD63: =I63 -> 1440 | AG63: =I63 -> 1440 | AJ63: =I63 -> 1440 | AM63: =I63/24 -> 60 | AY63: =I63*#REF! -> #REF! | AZ63: =I63*#REF! -> #REF! | BA63: =I63*#REF! -> #REF! | BB63: =I63*#REF! -> #REF! | BC63: =I63*#REF! -> #REF! | BD63: =I63*#REF! -> #REF! | BE63: =I63*#REF! -> #REF! | BF63: =I63*#REF! -> #REF! | BG63: =I63*#REF! -> #REF! | BH63: =I63*#REF! -> #REF! | BI63: =I63*#REF! -> #REF! | BJ63: =I63*#REF! -> #REF! | BK63: =I63*#REF! -> #REF!
A64: 44798 | B64: WAL-MART STORES INC. USA | C64: 美国 | D64: 4500085503 | E64: 9028493596 | F64: 20-77361SLB-S001 | G64: 77361SLB-S001 | H64: 迷你恐龙球 卡板装 | I64: 1440 | J64: 0 | K64: 1440 | L64: =I64/K64 -> 1 | M64: 44882 | N64: 9/30取消 | R64: 44810 | S64: 有 | T64: 44817 | U64: 日期码格式：ZURU DGYYYYMMDD CHINA(日期避开周末和法定节假日即可） 日期：按实际生产日期 Packaging Info: 77361: MA 1L收缩膜+MA 1LPDQ+MA 说明书+MA 收藏指南, 翻单：4500084631 Remark: 1. 包装要求 77361: MA 1L收缩膜+MA 1LPDQ+MA 说明书+MA 收藏指南, 翻单：4500084631 每pcs产品上要贴1张RFID贴纸，贴纸由ZURU提供，贴纸位置请严格按照我们签回的签板； 2. 在原来的空白外箱基础上增加了UPC内容+RFID箱唛，在加印的时候确保条形码能扫描出来（需四面右下角有ZURU的Logo），UPC内容待和RFID箱唛提供，外箱侧 面任一角落加印："MADE IN CHINA" 字样； 3. 每个slip sheet上面贴一张艾利贴纸和一张普通贴纸（可A4纸打印），slip sheet打印的普通贴纸的尺寸不能比艾利贴纸小，普通贴纸内容见附件； 4. 在产品上和包装上要有日期码、以及要有MADE IN CHINA和ZURU字样； 5. 产品如有扎带口要剪平，不能刮手。 6. 此单需要验货，请多备料 7. 此单以slip sheet出货， 77361：24pcs/PDQ/CTN；1440pcs/60CTN/Slip Sheet | V64: WM TEAM | W64: 1616.8202 | X64: =W64*L64 -> 1616.8202 | AB64: =AA64-I64 -> -1440 | AD64: =I64 -> 1440 | AG64: =I64 -> 1440 | AJ64: =I64 -> 1440 | AM64: =I64/24 -> 60 | AY64: =I64*#REF! -> #REF! | AZ64: =I64*#REF! -> #REF! | BA64: =I64*#REF! -> #REF! | BB64: =I64*#REF! -> #REF! | BC64: =I64*#REF! -> #REF! | BD64: =I64*#REF! -> #REF! | BE64: =I64*#REF! -> #REF! | BF64: =I64*#REF! -> #REF! | BG64: =I64*#REF! -> #REF! | BH64: =I64*#REF! -> #REF! | BI64: =I64*#REF! -> #REF! | BJ64: =I64*#REF! -> #REF! | BK64: =I64*#REF! -> #REF!
A65: 44798 | B65: WAL-MART STORES INC. USA | C65: 美国 | D65: 4500085503 | E65: 9028493601 | F65: 20-77361SLB-S001 | G65: 77361SLB-S001 | H65: 迷你恐龙球 卡板装 | I65: 1440 | J65: 0 | K65: 1440 | L65: =I65/K65 -> 1 | M65: 44882 | N65: 9/30取消 | R65: 44810 | S65: 有 | T65: 44817 | U65: 日期码格式：ZURU DGYYYYMMDD CHINA(日期避开周末和法定节假日即可） 日期：按实际生产日期 Packaging Info: 77361: MA 1L收缩膜+MA 1LPDQ+MA 说明书+MA 收藏指南, 翻单：4500084631 Remark: 1. 包装要求 77361: MA 1L收缩膜+MA 1LPDQ+MA 说明书+MA 收藏指南, 翻单：4500084631 每pcs产品上要贴1张RFID贴纸，贴纸由ZURU提供，贴纸位置请严格按照我们签回的签板； 2. 在原来的空白外箱基础上增加了UPC内容+RFID箱唛，在加印的时候确保条形码能扫描出来（需四面右下角有ZURU的Logo），UPC内容待和RFID箱唛提供，外箱侧 面任一角落加印："MADE IN CHINA" 字样； 3. 每个slip sheet上面贴一张艾利贴纸和一张普通贴纸（可A4纸打印），slip sheet打印的普通贴纸的尺寸不能比艾利贴纸小，普通贴纸内容见附件； 4. 在产品上和包装上要有日期码、以及要有MADE IN CHINA和ZURU字样； 5. 产品如有扎带口要剪平，不能刮手。 6. 此单需要验货，请多备料 7. 此单以slip sheet出货， 77361：24pcs/PDQ/CTN；1440pcs/60CTN/Slip Sheet | V65: WM TEAM | W65: 1616.8202 | X65: =W65*L65 -> 1616.8202 | AB65: =AA65-I65 -> -1440 | AD65: =I65 -> 1440 | AG65: =I65 -> 1440 | AJ65: =I65 -> 1440 | AM65: =I65/24 -> 60 | AY65: =I65*#REF! -> #REF! | AZ65: =I65*#REF! -> #REF! | BA65: =I65*#REF! -> #REF! | BB65: =I65*#REF! -> #REF! | BC65: =I65*#REF! -> #REF! | BD65: =I65*#REF! -> #REF! | BE65: =I65*#REF! -> #REF! | BF65: =I65*#REF! -> #REF! | BG65: =I65*#REF! -> #REF! | BH65: =I65*#REF! -> #REF! | BI65: =I65*#REF! -> #REF! | BJ65: =I65*#REF! -> #REF! | BK65: =I65*#REF! -> #REF!
A66: 44728 | B66: VM INTERNATIONAL | C66: 美国 | D66: 4500081388 | E66: 25036 | F66: 20-77361GQ2-S001 | G66: 77361GQ2-S001 | H66: 迷你恐龙球 | I66: 8880 | J66: 0 | K66: 48 | L66: =I66/K66 -> 185 | M66: 2022/10/15 2022/9/28取消订单 | N66: 换单到4500087853 | O66: 取消订单 | R66: 44804 | S66: 无 | T66: 无 | U66: 码格式：ZURU 标准格式 日期：按实际生产日期 Remark: 1、ZURU MA UPC 现有包装，ZURU 标准日期码，出口美国； 2、无第三方测试和验货； 3、纸箱印ZURU LOGO | V66: Maggie | W66: 1.48 | X66: =W66*I66 -> 13142.4 | AB66: =AA66-AD66 -> -8880 | AD66: =I66 -> 8880 | AG66: =I66 -> 8880 | AJ66: =I66 -> 8880 | AM66: =I66/24 -> 370 | AY66: =I66*#REF! -> #REF! | AZ66: =I66*#REF! -> #REF! | BA66: =I66*#REF! -> #REF! | BB66: =I66*#REF! -> #REF! | BC66: =I66*#REF! -> #REF! | BD66: =I66*#REF! -> #REF! | BE66: =I66*#REF! -> #REF! | BF66: =I66*#REF! -> #REF! | BG66: =I66*#REF! -> #REF! | BH66: =I66*#REF! -> #REF! | BI66: =I66*#REF! -> #REF! | BJ66: =I66*#REF! -> #REF! | BK66: =I66*#REF! -> #REF!
A67: 44823 | B67: G.T. WHOLESALE LIMITED | C67: 加拿大 | D67: 4500086970 | E67: 2667098 | F67: 10-77361GQ2-S002 | G67: 77361GQ2-S002 | H67: 迷你恐龙球 | I67: 336 | J67: 0 | K67: 24 | L67: =I67/K67 -> 14 | M67: 44915 | N67: 2022/12/16 10/21 取消 | R67: 44823 | S67: 无 | T67: 进口商贴纸和位置图翻单4500085009 | U67: 日期码格式：ZURU 标准格式 日期：按实际生产日期 Packaging Info: MA 3L包装 + 进口商贴纸（进口商贴纸和位置图翻单4500085009） Remark: 出加拿大 Zuru验货，验货时需要单个产品称重的图片和整箱产品称重的图片，还需要产品上makeinChina，彩盒上的警告语的清晰图片，以及公仔尺寸的测量图片 日期跟踪码：产品外包装及产品本身都必须有日期跟踪码，ZURU标准格式日期码 | V67: Summer Mo | W67: 1.48 | X67: =W67*I67 -> 497.28 | AE67: =I67 -> 336 | AG67: =I67 -> 336 | AJ67: =I67 -> 336 | AN67: =I67/24 -> 14 | AY67: =I67*#REF! -> #REF! | AZ67: =I67*#REF! -> #REF! | BA67: =I67*#REF! -> #REF! | BB67: =I67*#REF! -> #REF! | BC67: =I67*#REF! -> #REF! | BD67: =I67*#REF! -> #REF! | BE67: =I67*#REF! -> #REF! | BF67: =I67*#REF! -> #REF! | BG67: =I67*#REF! -> #REF! | BH67: =I67*#REF! -> #REF! | BI67: =I67*#REF! -> #REF! | BJ67: =I67*#REF! -> #REF! | BK67: =I67*#REF! -> #REF!
A68: 44810 | B68: G.T. WHOLESALE LIMITED | C68: 加拿大 | D68: 4500085308 | E68: 2667136 | F68: 10-77361GQ2-S002 | G68: 77361GQ2-S002 | H68: 迷你恐龙球 | I68: 456 | J68: 0 | K68: 24 | L68: =I68/K68 -> 19 | M68: 44882 | N68: 2022/11/14 10/21 取消 | R68: 44810 | S68: 无 | T68: 44848 | U68: 日期码格式：ZURU 标准格式 日期：按实际生产日期 Packaging Info: MA 3L包装，标板PDQ Remark: 出加拿大+进口商贴纸 Zuru验货，验货时需要单个产品称重的图片和整箱产品称重的图片，还需要产品上makeinChina，彩盒上的警告语的清晰图片，以及公仔尺寸的测量图片 日期跟踪码：产品外包装及产品本身都必须有日期跟踪码，ZURU标准格式日期码 | V68: Summer Mo | W68: 1.48 | X68: =W68*I68 -> 674.88 | AB68: =AA68-I68 -> -456 | AE68: =I68 -> 456 | AG68: =I68 -> 456 | AJ68: =I68 -> 456 | AN68: =I68/24 -> 19 | AY68: =I68*#REF! -> #REF! | AZ68: =I68*#REF! -> #REF! | BA68: =I68*#REF! -> #REF! | BB68: =I68*#REF! -> #REF! | BC68: =I68*#REF! -> #REF! | BD68: =I68*#REF! -> #REF! | BE68: =I68*#REF! -> #REF! | BF68: =I68*#REF! -> #REF! | BG68: =I68*#REF! -> #REF! | BH68: =I68*#REF! -> #REF! | BI68: =I68*#REF! -> #REF! | BJ68: =I68*#REF! -> #REF! | BK68: =I68*#REF! -> #REF!
A69: 44855 | B69: ZURU France | C69: 法国 | D69: 4500088916 | E69: 5200001145 | F69: 60-77361GQ2-S001 | G69: 77361GQ2-S001 | H69: 迷你恐龙球 | I69: 5232 | J69: 0 | K69: 48 | L69: =I69/K69 -> 109 | M69: 44915 | N69: 2022/12/16 2022/11/11 取消 | S69: 欠 | T69: 无 | U69: 欠 | V69: 日期码格式：DG 20221212 日期： Packaging Info: 6.77361GQ2: MA 3L包装（所有包装都要用MA3L）+1张条码贴纸+1张回收logo贴纸，贴纸都翻4500088856 Remark: 法国内销单,ZURU验货后即可出货。 | W69: Mary Zhong | X69: 1.0925 | Y69: =X69*I69 -> 5715.96 | AA69: 已入 | AC69: =AB69-I69 -> -5232 | AG69: =I69 -> 5232 | AI69: =I69 -> 5232 | AL69: =I69 -> 5232 | AP69: =I69/24 -> 218 | BA69: =I69*#REF! -> #REF! | BB69: =I69*#REF! -> #REF! | BC69: =I69*#REF! -> #REF! | BD69: =I69*#REF! -> #REF! | BE69: =I69*#REF! -> #REF! | BF69: =I69*#REF! -> #REF! | BG69: =I69*#REF! -> #REF! | BH69: =I69*#REF! -> #REF! | BI69: =I69*#REF! -> #REF! | BJ69: =I69*#REF! -> #REF! | BK69: =I69*#REF! -> #REF! | BL69: =I69*#REF! -> #REF! | BM69: =I69*#REF! -> #REF!
A70: 44844 | B70: DOLLAR GENERAL CORPORATION | C70: 美国 | D70: 4500088197 | E70: 1PXSW7 | F70: 10-77200GQ3-S002 | G70: 77200GQ3-S002 | H70: 迷你恐龙 | I70: 157056 | J70: 0 | K70: 48 | L70: =I70/K70 -> 3272 | M70: 44895 | N70: 2022/11/26 2022/11/10 取消 | O70: 12/1 TUV验货，11月30日前完成ZURU QC验货，并当天13点前提供验货报告+大货图片给跟单。 | R70: 取消单 | S70: 44848 | T70: 无 | U70: 无 | V70: 日期码格式：DOLLAR GENERAL 客版格式 日期： Packaging Info: Remark: 1.包装： 客版1L收缩膜（aws跟单稍后提供）+客版1L PDQ ，如有指南请尽力使用ZURU MA 1L版本。 2.日期码：产品和包装上必须有客版格式日期码。 （1）产品上需打客版日期码（打在球瓣上） 内容： DOLGEN32559903L22 L代表ETD 12月。 （2）包装日期码32559903L22（已印在客版收缩膜上了，无需额外做日期码在包装上）。 （3）客版UPC# 430001813345 3. 样板需求：请10月30日左右寄出 6full PDQ + 3套光身样作为产前确认样给深圳跟单转寄客人签样。 4. 抽样+验货事宜： 12月1日早上进行客人指定TUV的100% CT抽测试样（每款每色各12pcs带包装产品 + 5套光身样 +各色足量干漆）+ 100%大货验货。请在11月 30日前完成ZURU QC验货，并当天13点前提供验货报告+大货图片给跟单。 5. 箱唛：此客人要求严格，外箱不接受水贴纸，材积以及重量必须按照以下要求，否则不符会导致验货fail从而影响货期而产生罚款。 大货外箱材积绝对不可大于下述数据，材积只接受3%的变小；重量正负不得超过以下列出数据的5%，接受外箱以印章方式印上实际毛重。 大货外箱尺寸请保持（数据和唛头翻单首单4500074968 #77197GQ3-S001）： #77200GQ3-S002，外箱，54.5*37.1*20.5cm ，材积必须不能大于1.4638CubeFeet（0.0414C BM);外箱毛重13.4LBS（6.1KGS）。 6.此客人不接受任何理由的延期，会有高额罚金产生. 7.如散货入仓需在货车上加防护网. 8.出货配比： #77200GQ3-S002-5 SURPRISE-DINO STRIKE-SERIES 4,8pcs/Gravity PDQ,48pcs/CTN,No Inner,Polybag,STD Color Assortment each PDQ in one polybag 8PCS入一个GQ再入一个内袋，6个内袋48pcs入一个外箱。 9. 内袋需要印警示语，内容如下（内袋aws跟单稍后提供），内袋必须 用胶带封口，客人是以内袋为运输包装分配到每家店里面的： WARNING: To avoid danger of suffocation, keep this bag away from babies and children. Do not use in cribs, beds, strollers or playpens. This ba g is not a toy. | W70: Hailey | X70: 1.2484 | Y70: =I70*X70 -> 196068.71 | AC70: =AB70-I70 -> -157056 | AJ70: =I70 -> 157056 | AL70: =I70 -> 157056 | AQ70: =I70 -> 157056 | BE70: =I70/8 -> 19632 | BO70: =I70/96*12 -> 19632 | BP70: =I70/96*12 -> 19632 | BQ70: =I70/96*11 -> 17996 | BR70: =I70/96*1 -> 1636 | BS70: =I70/96*12 -> 19632 | BT70: =I70/96*12 -> 19632 | BU70: =I70/96*12 -> 19632 | BV70: =I70/96*12 -> 19632 | BW70: =I70/96*11 -> 17996 | BX70: =I70/96*1 -> 1636
A71: 44855 | B71: ZURU France | C71: 法国 | D71: 4500088916 | E71: 5200001145 | F71: 20-77200GQ2-S001 | G71: 77200GQ2-S001 | H71: 迷你恐龙 | I71: 1536 | J71: 0 | K71: 48 | L71: =I71/K71 -> 32 | M71: 44915 | N71: 2022/12/16 11/14 取消 | R71: 湖南生产 | S71: 条码贴纸（翻4500074893）回收logo贴（翻4500074893 | T71: 无 | U71: 无 | V71: 日期码格式：DG 20221212 日期： Packaging Info: 2.77200GQ2:用MA 3L包装+1张条码贴（翻4500074893）+1张回收logo贴纸（翻4500074893）+MA 3L PDQ+MA3L说明书+MA 3L收藏指导书 Remark: 法国内销单,ZURU验货后即可出货。 | W71: Mary Zhong | X71: 1.1909 | Y71: =I71*X71 -> 1829.2224 | AI71: =I71 -> 1536 | AN71: =I71 -> 1536 | AS71: =I71 -> 1536 | AX71: =I71/24 -> 64 | BO71: =I71/96*12 -> 192 | BP71: =I71/96*12 -> 192 | BQ71: =I71/96*11 -> 176 | BR71: =I71/96*1 -> 16 | BS71: =I71/96*12 -> 192 | BT71: =I71/96*12 -> 192 | BU71: =I71/96*12 -> 192 | BV71: =I71/96*12 -> 192 | BW71: =I71/96*11 -> 176 | BX71: =I71/96*1 -> 16
A72: 44855 | B72: ZURU France | C72: 法国 | D72: 4500088916 | E72: 5200001145 | F72: 10-77200-STD PRODUCT | G72: 77200SK-S002 | H72: 迷你恐龙展示架 | I72: 4400 | J72: 0 | K72: 88 | L72: =I72/K72 -> 50 | M72: 44915 | N72: 2022/12/16 11/14 取消 | R72: 湖南生产 | S72: 条码贴纸（翻4500074893）回收logo贴（翻4500074893 | T72: 无 | U72: 无 | V72: 日期码格式：DG 20221212 日期： Packaging Info: 3.77200SK:用MA 3L包装+1张条码贴纸（翻4500074893）+1张回收logo贴（翻4500074893）+MA 3L 展示架+MA3L说明书+MA 3L收藏指导书 4W*2D*11H=88pcs; Remark: 法国内销单,ZURU验货后即可出货。 | W72: Mary Zhong | X72: 139.1863 | Y72: =X72*L72 -> 6959.315 | AI72: =I72 -> 4400 | AN72: =I72 -> 4400 | AS72: =I72 -> 4400 | BN72: =I72/K72 -> 50 | BO72: =I72/96*12 -> 550 | BP72: =I72/96*12 -> 550 | BQ72: =I72/96*11 -> 504.16667 | BR72: =I72/96*1 -> 45.833333 | BS72: =I72/96*12 -> 550 | BT72: =I72/96*12 -> 550 | BU72: =I72/96*12 -> 550 | BV72: =I72/96*12 -> 550 | BW72: =I72/96*11 -> 504.16667 | BX72: =I72/96*1 -> 45.833333
A73: 44700 | B73: SHINE S.A. | C73: 阿根廷 | D73: 4500079551 | F73: 10-7794GQ2-S002 | G73: 7794GQ2-S002 | H73: 惊喜球PDQ | I73: 4800 | J73: 0 | K73: 48 | L73: =I73/K73 -> 100 | M73: 44793 | N73: 取消订单 | P73: PASS | R73: 44775 | S73: 无 | T73: 44777 | U73: 日期码格式：ZURU 标准格式 日期：按实际生产日期 Remark: 1.MA 3L包装+进口商贴纸,箱唛;注明 因为结库存数，此单可以用1L 和3L PDQ，但是装箱的时候要确保，1一箱里面 只能是同一种PDQ， | V73: Ever.Li | W73: 1.0646 | X73: =W73*I73 -> 5110.08 | AB73: 4800 | AC73: =AB73-I73 -> 0 | AG73: =I73 -> 4800 | AM73: =I73 -> 4800 | AS73: =I73 -> 4800 | AW73: =200-171 -> 29 | AX73: =200-29 -> 171 | BL73: =I73/96*12 -> 600 | BM73: =I73/96*12 -> 600 | BN73: =I73/96*11 -> 550 | BO73: =I73/96*1 -> 50 | BP73: =I73/96*12 -> 600 | BQ73: =I73/96*12 -> 600 | BR73: =I73/96*12 -> 600 | BS73: =I73/96*12 -> 600 | BT73: =I73/96*11 -> 550 | BU73: =I73/96*1 -> 50
A74: 44866 | B74: TARGET US | C74: 美国 | D74: 4500089851 | E74: 0087-9976516-0581 | F74: 10-77361GQ1-S001 | H74: 77361GQ1-S001 | I74: 迷你恐龙球 | J74: 9096 | K74: 0 | L74: 12 | M74: =J74/L74 -> 758 | N74: 44929 | O74: 44926 | S74: 湖南生产 | T74: 欠 | U74: 有 | V74: 欠 | W74: 日期码格式：ZURU 标准格式 日期：按实际生产日期 Packaging Info: MA包装+客版PDQ Remark: 1.77361GQ1-S001, 12pcs/Gravity PDQ,12pcs/CTN。MA 1L 包装，客版PDQ(翻单4500083482），产品UPC 193052044976. 2. 外箱正唛右上角位置粘贴条码箱贴纸，每箱只贴一张由ZURU订购,来料显示DPCI 087-16-4771, UPC 10193052044973. 3. 产品和包装上均要印刷tracking code信息，格式为ZURU常规格式。 4. 出货方式：货代自提。 | X74: Holly Zheng/ Cherish | Y74: 1.116 | Z74: =Y74*J74 -> 10151.136 | AB74: 已入 | AG74: =J74 -> 9096 | AJ74: =J74 -> 9096 | AM74: =J74 -> 9096 | AT74: =J74/12 -> 758 | BB74: =J74*#REF! -> #REF! | BC74: =J74*#REF! -> #REF! | BD74: =J74*#REF! -> #REF! | BE74: =J74*#REF! -> #REF! | BF74: =J74*#REF! -> #REF! | BG74: =J74*#REF! -> #REF! | BH74: =J74*#REF! -> #REF! | BI74: =J74*#REF! -> #REF! | BJ74: =J74*#REF! -> #REF! | BK74: =J74*#REF! -> #REF! | BL74: =J74*#REF! -> #REF! | BM74: =J74*#REF! -> #REF! | BN74: =J74*#REF! -> #REF!
A75: 44866 | B75: TARGET US | C75: 美国 | D75: 4500089854 | E75: 0087-9233613-0581 | F75: 10-77361GQ1-S001 | H75: 77361GQ1-S001 | I75: 迷你恐龙球 | J75: 2700 | K75: 0 | L75: 12 | M75: =J75/L75 -> 225 | N75: 44967 | O75: 44963 | S75: 湖南生产 | T75: 欠 | U75: 有 | V75: 欠 | W75: 日期码格式：ZURU 标准格式 日期：按实际生产日期 Packaging Info: MA包装+客版PDQ Remark: 1.77361GQ1-S001, 12pcs/Gravity PDQ,12pcs/CTN。MA 1L 包装，客版PDQ(翻单4500083482），产品UPC 193052044976. 2. 外箱正唛右上角位置粘贴条码箱贴纸，每箱只贴一张由ZURU订购,来料显示DPCI 087-16-4771, UPC 10193052044973. 3. 产品和包装上均要印刷tracking code信息，格式为ZURU常规格式。 4. 出货方式：货代自提。 | X75: Holly Zheng/ Cherish | Y75: 1.1243 | Z75: =Y75*J75 -> 3035.61 | AB75: 已入 | AG75: =J75 -> 2700 | AJ75: =J75 -> 2700 | AM75: =J75 -> 2700 | AT75: =J75/12 -> 225 | BB75: =J75*#REF! -> #REF! | BC75: =J75*#REF! -> #REF! | BD75: =J75*#REF! -> #REF! | BE75: =J75*#REF! -> #REF! | BF75: =J75*#REF! -> #REF! | BG75: =J75*#REF! -> #REF! | BH75: =J75*#REF! -> #REF! | BI75: =J75*#REF! -> #REF! | BJ75: =J75*#REF! -> #REF! | BK75: =J75*#REF! -> #REF! | BL75: =J75*#REF! -> #REF! | BM75: =J75*#REF! -> #REF! | BN75: =J75*#REF! -> #REF!
A76: 44840 | B76: MO20220923 | C76: 美国 | D76: MO20220923 | H76: 77361SLB-S001 | I76: 迷你恐龙球 卡板装 | J76: 24480 | K76: 0 | L76: 1440 | M76: =J76/L76 -> 17 | N76: 44882 | O76: 44900 | S76: 湖南生产 | T76: 欠 | U76: 有 | V76: 欠 | W76: 1. 包装要求： 77361: MA 1L收缩膜+MA 1LPDQ+MA 说明书+MA 收藏指南, 翻单：4500084631 每pcs产品上要贴1张RFID贴纸，贴纸由ZURU提供，贴纸位置请严格按照我们签回的签板； 2. 在原来的空白外箱基础上增加了UPC内容+RFID箱唛，在加印的时候确保条形码能扫描出来（需四面右下角有ZURU的Logo），UPC内容待和RFID箱唛提供，外箱侧面任一角落加印："MADE IN CHINA" 字样； 3. 每个slip sheet上面贴一张艾利贴纸和一张普通贴纸（可A4纸打印），slip sheet打印的普通贴纸的尺寸不能比艾利贴纸小，普通贴纸内容见附件； 3. 在产品上和包装上要有日期码、以及要有MADE IN CHINA和ZURU字样； 4. 产品如有扎带口要剪平，不能刮手。 5. 此单需要验货，请多备料 6. 此单以slip sheet出货， 77361：24pcs/PDQ/CTN；1440pcs/60CTN/Slip Sheet | AB76: 已入 | AD76: =AC76-J76 -> -24480 | AF76: 已入 | AG76: =J76 -> 24480 | AJ76: =J76 -> 24480 | AM76: =J76 -> 24480 | AP76: =J76/24 -> 1020 | AZ76: =J76*#REF! -> #REF! | BA76: =J76*#REF! -> #REF! | BB76: =J76*#REF! -> #REF! | BC76: =J76*#REF! -> #REF! | BD76: =J76*#REF! -> #REF! | BE76: =J76*#REF! -> #REF! | BF76: =J76*#REF! -> #REF! | BG76: =J76*#REF! -> #REF! | BH76: =J76*#REF! -> #REF! | BI76: =J76*#REF! -> #REF! | BJ76: =J76*#REF! -> #REF! | BK76: =J76*#REF! -> #REF! | BL76: =J76*#REF! -> #REF!
A77: 44811 | B77: WAL-MART CANADA CORP. | C77: 加拿大 | D77: 4500086276 | E77: 1200703570 | F77: 10-77361GQ1-S001 | G77: 77361GQ2-S001 | H77: 77361GQ1-S001 | I77: 迷你恐龙球 | J77: 3048 | K77: 0 | L77: 12 | M77: =J77/L77 -> 254 | N77: 44930 | O77: 2022/12/31 2022/12/28取消 | S77: 湖南生产 | T77: 44811 | U77: 无 | V77: 无 | W77: 日期码格式：ZURU 标准格式 日期：按实际生产日期 Packaging Info: #77361: 客版3L,PDQ (12装) +MA3L收缩膜+MA3L收藏指南+MA3L说明书 (翻单：4500086274) Remark: 1.有箱唛待提供 2.有第三方验货，烦请多备包装物料 | X77: WM TEAM | Y77: 1.48 | Z77: =Y77*J77 -> 4511.04 | AB77: 已入 | AD77: =AC77-J77 -> -3048 | AF77: 已入 | AH77: =J77 -> 3048 | AJ77: =J77 -> 3048 | AM77: =J77 -> 3048 | AS77: =J77/12 -> 254 | AZ77: =J77*#REF! -> #REF! | BA77: =J77*#REF! -> #REF! | BB77: =J77*#REF! -> #REF! | BC77: =J77*#REF! -> #REF! | BD77: =J77*#REF! -> #REF! | BE77: =J77*#REF! -> #REF! | BF77: =J77*#REF! -> #REF! | BG77: =J77*#REF! -> #REF! | BH77: =J77*#REF! -> #REF! | BI77: =J77*#REF! -> #REF! | BJ77: =J77*#REF! -> #REF! | BK77: =J77*#REF! -> #REF! | BL77: =J77*#REF! -> #REF!
A78: 44811 | B78: WAL-MART CANADA CORP. | C78: 加拿大 | D78: 4500086276 | E78: 1200703571 | F78: 20-77361GQ1-S001 | G78: 77361GQ2-S001 | H78: 77361GQ1-S001 | I78: 迷你恐龙球 | J78: 2676 | K78: 0 | L78: 12 | M78: =J78/L78 -> 223 | N78: 44935 | O78: 2022/1/5 2022/12/28取消 | S78: 湖南生产 | T78: 44811 | U78: 无 | V78: 无 | W78: 日期码格式：ZURU 标准格式 日期：按实际生产日期 Packaging Info: #77361: 客版3L,PDQ (12装) +MA3L收缩膜+MA3L收藏指南+MA3L说明书 (翻单：4500086274) Remark: 1.有箱唛待提供 2.有第三方验货，烦请多备包装物料 | X78: WM TEAM | Y78: 1.48 | Z78: =Y78*J78 -> 3960.48 | AB78: 已入 | AD78: =AC78-J78 -> -2676 | AF78: 已入 | AH78: =J78 -> 2676 | AJ78: =J78 -> 2676 | AM78: =J78 -> 2676 | AS78: =J78/12 -> 223 | AZ78: =J78*#REF! -> #REF! | BA78: =J78*#REF! -> #REF! | BB78: =J78*#REF! -> #REF! | BC78: =J78*#REF! -> #REF! | BD78: =J78*#REF! -> #REF! | BE78: =J78*#REF! -> #REF! | BF78: =J78*#REF! -> #REF! | BG78: =J78*#REF! -> #REF! | BH78: =J78*#REF! -> #REF! | BI78: =J78*#REF! -> #REF! | BJ78: =J78*#REF! -> #REF! | BK78: =J78*#REF! -> #REF! | BL78: =J78*#REF! -> #REF!
A79: 44855 | B79: ZURU Denmark ApS | C79: 丹麦 | D79: 4500089151 | E79: 5200001151 | F79: 70-77361GQ2-S002 | H79: 77361GQ2-S002 | I79: 迷你恐龙球 | J79: 2640 | K79: 0 | L79: 24 | M79: =J79/L79 -> 110 | N79: 44902 | O79: 2022/12/11 12/6 取消 | S79: 湖南生产 | T79: 44865 | U79: 无 | V79: 44862 | W79: 日期码格式：ZURU 标准格式 日期：按实际生产日期 Packaging Info: 77361GQ2：MA 3L包装+MA明书+EAN条码贴纸+警告语贴纸 Remark: 1. 包装如含PVC,请改为PET，工厂请提出； 贴球面的客版贴纸工厂需要订购合成纸贴纸 2. 产品要求无硼无香 3. 款号- 产品EAN条码-外箱GTIN 77361GQ2-4894680024328-10193052044973 4. 产品信息： | X79: Rose | Y79: 1.1166 | Z79: =Y79*J79 -> 2947.824 | AB79: 已入 | AD79: =AC79-J79 -> -2640 | AF79: 已入 | AH79: =J79 -> 2640 | AJ79: =J79 -> 2640 | AM79: =J79 -> 2640 | AQ79: =J79/24 -> 110 | AZ79: =J79*#REF! -> #REF! | BA79: =J79*#REF! -> #REF! | BB79: =J79*#REF! -> #REF! | BC79: =J79*#REF! -> #REF! | BD79: =J79*#REF! -> #REF! | BE79: =J79*#REF! -> #REF! | BF79: =J79*#REF! -> #REF! | BG79: =J79*#REF! -> #REF! | BH79: =J79*#REF! -> #REF! | BI79: =J79*#REF! -> #REF! | BJ79: =J79*#REF! -> #REF! | BK79: =J79*#REF! -> #REF! | BL79: =J79*#REF! -> #REF!
A80: 44859 | B80: TOKMANNI - DOM | C80: 芬兰 | D80: 4500089344 | F80: 10-77361GQ2-S001 | G80: 77361GQ2-S001-1 | H80: 77361GQ2-S001 | I80: 迷你恐龙球 | J80: 4800 | K80: 0 | L80: 48 | M80: =J80/L80 -> 100 | N80: 44974 | O80: 取消 | S80: 欠 | T80: 无 | U80: 欠 | V80: 日期码格式：ZURU 标准格式 日期：按实际生产日期 Packaging Info: （用于曲面的贴纸请使用合成纸） 77361GQ2:MA 3L 包装/PDQ+1张警告语贴纸+1张EAN条码贴纸 Remark: 1.产品要求无硼无香（如果没有此类问题，请忽略此点） 2.此订单客户每个ITEM都需各3套大货样用于签板，并且有第三方验货，请提前多备料 3.包装不可用PVC材质,要用PET替代 4.此单每款每个外箱都要放一包或者两包干燥剂，请按照供应商建议和干燥剂指引安排，船务通知要做柜时，做柜工厂需准备货柜内的干燥剂，干燥剂需要做柜工厂 自行找指定供应商订购。（参考订单4500079961） | W80: Rose | X80: 1.1082 | Y80: =X80*J80 -> 5319.36 | AA80: 已入 | AC80: =AB80-J80 -> -4800 | AE80: 已入 | AG80: =J80 -> 4800 | AI80: =J80 -> 4800 | AL80: =J80 -> 4800 | AP80: =J80/24 -> 200 | AY80: =J80*#REF! -> #REF! | AZ80: =J80*#REF! -> #REF! | BA80: =J80*#REF! -> #REF! | BB80: =J80*#REF! -> #REF! | BC80: =J80*#REF! -> #REF! | BD80: =J80*#REF! -> #REF! | BE80: =J80*#REF! -> #REF! | BF80: =J80*#REF! -> #REF! | BG80: =J80*#REF! -> #REF! | BH80: =J80*#REF! -> #REF! | BI80: =J80*#REF! -> #REF! | BJ80: =J80*#REF! -> #REF! | BK80: =J80*#REF! -> #REF!
A81: 44957 | B81: ADIR INTERNATIOAL/ CURACAO | C81: 美国 | D81: 4500094129 | E81: AKMRH-A | F81: 4500094129-10 | G81: 77361GQ1-S001-1L | H81: 77361GQ2-S001 | I81: 迷你恐龙球 | J81: 624 | K81: 0 | L81: 48 | M81: =J81/L81 -> 13 | N81: 45034 | O81: 取消订单 | S81: 44998 | T81: 无 | U81: 无 | V81: 日期码格式：ZURU 标准格式 日期：按实际生产日期 Packaging Info: 1.#77361GQ2: MA UPC 包装 Remark: 1. MA UPC包装，出美国 2. ZURU 标准日期码格式 3. 整柜出货 | W81: Cynthia Li | X81: 1.0505 | Y81: =X81*J81 -> 655.512 | AA81: 已入 | AC81: =AB81-J81 -> -624 | AE81: 已入 | AF81: =J81 -> 624 | AI81: =J81 -> 624 | AL81: =AF81 -> 624 | AO81: =J81/24 -> 26 | AY81: =J81*#REF! -> #REF! | AZ81: =J81*#REF! -> #REF! | BA81: =J81*#REF! -> #REF! | BB81: =J81*#REF! -> #REF! | BC81: =J81*#REF! -> #REF! | BD81: =J81*#REF! -> #REF! | BE81: =J81*#REF! -> #REF! | BF81: =J81*#REF! -> #REF! | BG81: =J81*#REF! -> #REF! | BH81: =J81*#REF! -> #REF! | BI81: =J81*#REF! -> #REF! | BJ81: =J81*#REF! -> #REF! | BK81: =J81*#REF! -> #REF!
A82: 44900 | B82: THE WAREHOUSE LIMITED | C82: 新西兰 | D82: 4500091987 | E82: 27125605 | F82: 4500091987-10 | G82: 77200GQ2-S001 | H82: 77200GQ2-S001 | I82: 迷你恐龙 | J82: 2688 | K82: 0 | L82: 48 | M82: =J82/L82 -> 56 | N82: 45092 | O82: 取消订单 | T82: 欠 | U82: 无 | V82: 无 | W82: 日期码格式：ZURU 标准格式 日期：按实际生产日期 Packaging Info: 1.ZURU MA包装， 优先1L Remark: 2.此单去新西兰，请按相应标准生产； 3.请在外箱正反面和侧面（共四面）中间印上ZURU外箱LOGO,箱唛印刷前，请提供箱唛排版供确认； 4.此单分两个港口出货; 10行出AKL,20行出LYT | X82: Coral.wuws | Y82: 1.1294 | Z82: =J82*Y82 -> 3035.8272 | AB82: 已入 | AD82: =AC82-J82 -> -2688 | AF82: 已入 | AH82: =J82 -> 2688 | AM82: =J82 -> 2688 | AR82: =J82 -> 2688 | AX82: =J82/24 -> 112 | BP82: =J82/96*12 -> 336 | BQ82: =J82/96*12 -> 336 | BR82: =J82/96*11 -> 308 | BS82: =J82/96*1 -> 28 | BT82: =J82/96*12 -> 336 | BU82: =J82/96*12 -> 336 | BV82: =J82/96*12 -> 336 | BW82: =J82/96*12 -> 336 | BX82: =J82/96*11 -> 308 | BY82: =J82/96*1 -> 28
A83: 44900 | B83: THE WAREHOUSE LIMITED | C83: 新西兰 | D83: 4500091987 | E83: 27125605 | F83: 4500091987-20 | G83: 77200GQ2-S001 | H83: 77200GQ2-S001 | I83: 迷你恐龙 | J83: 912 | K83: 0 | L83: 48 | M83: =J83/L83 -> 19 | N83: 45092 | O83: 取消订单 | T83: 欠 | U83: 无 | V83: 无 | W83: 日期码格式：ZURU 标准格式 日期：按实际生产日期 Packaging Info: 1.ZURU MA包装， 优先1L Remark: 2.此单去新西兰，请按相应标准生产； 3.请在外箱正反面和侧面（共四面）中间印上ZURU外箱LOGO,箱唛印刷前，请提供箱唛排版供确认； 4.此单分两个港口出货; 10行出AKL,20行出LYT | X83: Coral.wuws | Y83: 1.1529 | Z83: =J83*Y83 -> 1051.4448 | AB83: 已入 | AD83: =AC83-J83 -> -912 | AF83: 已入 | AH83: =J83 -> 912 | AM83: =J83 -> 912 | AR83: =J83 -> 912 | AX83: =J83/24 -> 38 | BP83: =J83/96*12 -> 114 | BQ83: =J83/96*12 -> 114 | BR83: =J83/96*11 -> 104.5 | BS83: =J83/96*1 -> 9.5 | BT83: =J83/96*12 -> 114 | BU83: =J83/96*12 -> 114 | BV83: =J83/96*12 -> 114 | BW83: =J83/96*12 -> 114 | BX83: =J83/96*11 -> 104.5 | BY83: =J83/96*1 -> 9.5
A84: 44573 | B84: ROSS PROCUREMENT.INC | C84: 美国 | D84: 4500069141 | E84: 70007760 | G84: 77118-S001 | H84: 2PK PVC筒装 | I84: 1232 | J84: 0 | K84: 16 | L84: =I84/K84 -> 77 | M84: 44670 | N84: 取消订单 换单到4500073741 | R84: 44602 | S84: 无 | T84: 欠 | U84: 日期码格式：ZURU 标准格式 日期：按实际生产日期 Remark: 1.ZURU MA + UPC 现有版本包装 + 客供价格贴纸，出口美国。 2.价格贴纸位于包装正面右下角，不挡住重要信息即可，可适当调整 ，价格贴纸由跟单提供。 3.标准日期码格式，产品和包装必须有日期码，所有日期码必须一致(但日期不可为周末)。 4.同个产品同个货期不可出现不同的包装。 5.包装版本： ZURU现有 MA + UPC 版本。 | V84: Maggie | W84: 2.6215 | X84: =W84*I84 -> 3229.688 | AA84: 未生产 | AC84: =AB84-I84 -> -1232 | AE84: =I84*2 -> 2464 | AK84: =I84*2 -> 2464 | AQ84: =I84*2 -> 2464 | BL84: =I84/96*12*2 -> 308 | BM84: =I84/96*12*2 -> 308 | BN84: =I84/96*11*2 -> 282.33333 | BO84: =I84/96*1*2 -> 25.666667 | BP84: =I84/96*12*2 -> 308 | BQ84: =I84/96*12*2 -> 308 | BR84: =I84/96*12*2 -> 308 | BS84: =I84/96*12*2 -> 308 | BT84: =I84/96*11*2 -> 282.33333 | BU84: =I84/96*1*2 -> 25.666667
A85: 44573 | B85: ROSS PROCUREMENT.INC | C85: 美国 | D85: 4500069141 | E85: 70007760 | G85: 77110-S001 | H85: 惊喜球3PK PVC圆筒装 | I85: 612 | J85: 0 | K85: 12 | L85: =I85/K85 -> 51 | M85: 44670 | N85: 取消订单 换单到4500073741 | R85: 44602 | S85: 无 | T85: 欠 | U85: 日期码格式：ZURU 标准格式 日期：按实际生产日期 Remark: 1.ZURU MA + UPC 现有版本包装 + 客供价格贴纸，出口美国。 2.价格贴纸位于包装正面右下角，不挡住重要信息即可，可适当调整 ，价格贴纸由跟单提供。 3.标准日期码格式，产品和包装必须有日期码，所有日期码必须一致(但日期不可为周末)。 4.同个产品同个货期不可出现不同的包装。 5.包装版本： ZURU现有 MA + UPC 版本。 | V85: Maggie | W85: 3.7555 | X85: =W85*I85 -> 2298.366 | AA85: 未生产 | AC85: =AB85-I85 -> -612 | AE85: =I85*3 -> 1836 | AK85: =I85*3 -> 1836 | AQ85: =I85*3 -> 1836 | BL85: =I85/96*12*3 -> 229.5 | BM85: =I85/96*12*3 -> 229.5 | BN85: =I85/96*11*3 -> 210.375 | BO85: =I85/96*1*3 -> 19.125 | BP85: =I85/96*12*3 -> 229.5 | BQ85: =I85/96*12*3 -> 229.5 | BR85: =I85/96*12*3 -> 229.5 | BS85: =I85/96*12*3 -> 229.5 | BT85: =I85/96*11*3 -> 210.375 | BU85: =I85/96*1*3 -> 19.125
A86: 44573 | B86: ROSS PROCUREMENT.INC | C86: 美国 | D86: 4500069136 | E86: 70007761 | G86: 77118-S001 | H86: 2PK PVC筒装 | I86: 656 | J86: 0 | K86: 16 | L86: =I86/K86 -> 41 | M86: 44700 | N86: 取消订单 换单到4500073738 | R86: 欠 | S86: 无 | T86: 欠 | U86: 日期码格式：ZURU 标准格式 日期：按实际生产日期 Remark: 1.ZURU MA + UPC 现有版本包装 + 客供价格贴纸，出口美国。 2.价格贴纸位于包装正面右下角，不挡住重要信息即可，可适当调整 ，价格贴纸由跟单提供。 3.标准日期码格式，产品和包装必须有日期码，所有日期码必须一致(但日期不可为周末)。 4.同个产品同个货期不可出现不同的包装。 5.包装版本： ZURU现有 MA + UPC 版本。 | V86: Maggie | W86: 2.6842 | X86: =W86*I86 -> 1760.8352 | AA86: 未生产 | AC86: =AB86-I86 -> -656 | AE86: =I86*2 -> 1312 | AK86: =I86*2 -> 1312 | AQ86: =I86*2 -> 1312 | BL86: =I86/96*12*2 -> 164 | BM86: =I86/96*12*2 -> 164 | BN86: =I86/96*11*2 -> 150.33333 | BO86: =I86/96*1*2 -> 13.666667 | BP86: =I86/96*12*2 -> 164 | BQ86: =I86/96*12*2 -> 164 | BR86: =I86/96*12*2 -> 164 | BS86: =I86/96*12*2 -> 164 | BT86: =I86/96*11*2 -> 150.33333 | BU86: =I86/96*1*2 -> 13.666667
A87: 44573 | B87: ROSS PROCUREMENT.INC | C87: 美国 | D87: 4500069136 | E87: 70007761 | G87: 77110-S001 | H87: 惊喜球3PK PVC圆筒装 | I87: 336 | J87: 0 | K87: 12 | L87: =I87/K87 -> 28 | M87: 44700 | N87: 取消订单 换单到4500073738 | R87: 欠 | S87: 无 | T87: 欠 | U87: 日期码格式：ZURU 标准格式 日期：按实际生产日期 Remark: 1.ZURU MA + UPC 现有版本包装 + 客供价格贴纸，出口美国。 2.价格贴纸位于包装正面右下角，不挡住重要信息即可，可适当调整 ，价格贴纸由跟单提供。 3.标准日期码格式，产品和包装必须有日期码，所有日期码必须一致(但日期不可为周末)。 4.同个产品同个货期不可出现不同的包装。 5.包装版本： ZURU现有 MA + UPC 版本。 | V87: Maggie | W87: 3.7555 | X87: =W87*I87 -> 1261.848 | AA87: 未生产 | AC87: =AB87-I87 -> -336 | AE87: =I87*3 -> 1008 | AK87: =I87*3 -> 1008 | AQ87: =I87*3 -> 1008 | BL87: =I87/96*12*3 -> 126 | BM87: =I87/96*12*3 -> 126 | BN87: =I87/96*11*3 -> 115.5 | BO87: =I87/96*1*3 -> 10.5 | BP87: =I87/96*12*3 -> 126 | BQ87: =I87/96*12*3 -> 126 | BR87: =I87/96*12*3 -> 126 | BS87: =I87/96*12*3 -> 126 | BT87: =I87/96*11*3 -> 115.5 | BU87: =I87/96*1*3 -> 10.5
A88: 45071 | B88: KROGER (KRG LLC) | C88: 美国 | D88: MO05250024 | E88: TBA | F88: MO05250024-80 | G88: 77361GQ2-S002 | H88: 77361GQ2-S002 | I88: 迷你恐龙球 | J88: 144 | K88: 0 | L88: 24 | M88: =J88/L88 -> 6 | N88: 45107 | O88: 取消 | S88: 无 | T88: 无 | U88: 无 | V88: 1.包装方式: MA UPC 优先1L最新版包装，出口美国 2、无测试无验货要求。 3、纸箱4面印ZURU LOGO + 箱唛。 4、日期码请按ZURU标准版执行即可。 5、ZURU QC验货。 6、REMARK: #9279TQ1: Ratio: 7 assortment (6 common + 1 rare); RAGDOLL CA (RARE): AMERICAN SHORTHAIR: CALICO CAT: BLACK CAT: BENGAL CAT: EXOTIC CAT: CHINCHI LLA CAT= 1:9:10:10:10: 10:10 #77354: 5pcs mini inside#7149: 2 assortment average; 2pcs AA battery are not included; Lizard with LED，外箱的GTIN#为：20193052033493 #7149: 2 assortment average; 2pcs AA battery are not included; Lizard with LED，外箱的GTIN#为：20193052033493 #7150: 2 assortment average; 2pcs AAA battery are not included;Snake with LED,外箱的GTIN#为：20193052033400 | W88: Vicky Wu | X88: 1.236 | Y88: =X88*J88 -> 177.984 | AA88: 不入 | AC88: =AB88-J88 -> -144 | AF88: =J88 -> 144 | AI88: =J88 -> 144 | AK88: =J88 -> 144 | AM88: =J88/24 -> 6 | AW88: =J88*#REF! -> #REF! | AX88: =J88*#REF! -> #REF! | AY88: =J88*#REF! -> #REF! | AZ88: =J88*#REF! -> #REF! | BA88: =J88*#REF! -> #REF! | BB88: =J88*#REF! -> #REF! | BC88: =J88*#REF! -> #REF! | BD88: =J88*#REF! -> #REF! | BE88: =J88*#REF! -> #REF! | BF88: =J88*#REF! -> #REF! | BG88: =J88*#REF! -> #REF! | BH88: =J88*#REF! -> #REF! | BI88: =J88*#REF! -> #REF!
A89: 45125 | B89: TARGET US | C89: 美国 | D89: 4500109173 | E89: 0087-0005023-0581 | F89: 4500109173-10 | G89: 77361GQ1-S001-1L-1 | H89: 77361GQ1-S001 | I89: 迷你恐龙球 | J89: 37296 | K89: 0 | L89: 12 | M89: =J89/L89 -> 3108 | N89: 45177 | O89: 8/24取消，无客制物料，纸箱未订购 | S89: 45128 | T89: 有 | U89: 8/16 客供 | V89: 日期码格式：ZURU INC(BVI) 标准格式 日期：按实际生产日期 Packaging Info: MA 1L包装+MA PDQ Remark: 1.77361GQ1-S001, 12pcs/Gravity PDQ,12pcs/CTN。MA 1L 包装+MA PDQ，产品UPC 193052044976. 2. 外箱正唛左上角位置粘贴条码箱贴纸，每箱只贴一张由ZURU订购,来料显示DPCI 087-16-4771, UPC 10193052044973. 3. 产品和包装上均要印刷tracking code信息，格式为ZURU常规格式。 4. 出货方式：货代自提。 | W89: OdooBot | X89: 1.0665 | Y89: =X89*J89 -> 39776.184 | AA89: 已入 | AE89: 已入 | AF89: =J89 -> 37296 | AI89: =J89 -> 37296 | AK89: =J89 -> 37296 | AS89: =J89/12 -> 3108 | AW89: =J89*#REF! -> #REF! | AX89: =J89*#REF! -> #REF! | AY89: =J89*#REF! -> #REF! | AZ89: =J89*#REF! -> #REF! | BA89: =J89*#REF! -> #REF! | BB89: =J89*#REF! -> #REF! | BC89: =J89*#REF! -> #REF! | BD89: =J89*#REF! -> #REF! | BE89: =J89*#REF! -> #REF! | BF89: =J89*#REF! -> #REF! | BG89: =J89*#REF! -> #REF! | BH89: =J89*#REF! -> #REF! | BI89: =J89*#REF! -> #REF!
A90: 45188 | B90: DAS Companies, Inc. | C90: 美国 | D90: 4500113518 | E90: PO#AD1316E-00 0 | F90: 4500113518-10 | H90: 77361GQ1-S001 | I90: 迷你恐龙球 | J90: 6864 | K90: 0 | L90: 12 | M90: =J90/L90 -> 572 | N90: 45237 | O90: 45233 | S90: 45191 | T90: 无 | U90: 无 | V90: 日期码格式：ZURU INC(BVI) 标准格式 日期：按实际生产日期 Packaging Info: ZURU MA UPC包装，(如MA有1L请优先1L) , 出口美国 Remark: 1.ZURU MA UPC 包装收缩膜,PDQ<(>,<)>收藏指南，优选MA 1L ，出口美国. 2.产品和包装需有日期码，除产品不适用外，ZURU标准日期码格式<(>,<)>所有产品日期码必须一致(但日期不可为周末)。 3. 同个产品同个货期不可出现不同的包装 4. 出货配比, ZURU MA 配比。 此单包含2张客户PO#，出货时请留意。 每单箱唛信息也不同。 5. 务必按期完货，同其他厂拼着出货，延迟会有罚款。 | W90: Hailey Yu | X90: 1.03 | Y90: =X90*J90 -> 7069.92 | AF90: =J90 -> 6864 | AI90: =J90 -> 6864 | AK90: =J90 -> 6864 | AS90: =J90/12 -> 572 | AW90: =J90*#REF! -> #REF! | AX90: =J90*#REF! -> #REF! | AY90: =J90*#REF! -> #REF! | AZ90: =J90*#REF! -> #REF! | BA90: =J90*#REF! -> #REF! | BB90: =J90*#REF! -> #REF! | BC90: =J90*#REF! -> #REF! | BD90: =J90*#REF! -> #REF! | BE90: =J90*#REF! -> #REF! | BF90: =J90*#REF! -> #REF! | BG90: =J90*#REF! -> #REF! | BH90: =J90*#REF! -> #REF! | BI90: =J90*#REF! -> #REF!
A91: 45188 | B91: DAS Companies, Inc. | C91: 美国 | D91: 4500113518 | E91: PO#AD1316K-00 0 | F91: 4500113518-50 | H91: 77361GQ1-S001 | I91: 迷你恐龙球 | J91: 9552 | K91: 0 | L91: 12 | M91: =J91/L91 -> 796 | N91: 45237 | O91: 45233 | S91: 45191 | T91: 无 | U91: 无 | V91: 日期码格式：ZURU INC(BVI) 标准格式 日期：按实际生产日期 Packaging Info: ZURU MA UPC包装，(如MA有1L请优先1L) , 出口美国 Remark: 1.ZURU MA UPC 包装收缩膜,PDQ<(>,<)>收藏指南，优选MA 1L ，出口美国. 2.产品和包装需有日期码，除产品不适用外，ZURU标准日期码格式<(>,<)>所有产品日期码必须一致(但日期不可为周末)。 3. 同个产品同个货期不可出现不同的包装 4. 出货配比, ZURU MA 配比。 此单包含2张客户PO#，出货时请留意。 每单箱唛信息也不同。 5. 务必按期完货，同其他厂拼着出货，延迟会有罚款。 | W91: Hailey Yu | X91: 1.03 | Y91: =X91*J91 -> 9838.56 | AF91: =J91 -> 9552 | AI91: =J91 -> 9552 | AK91: =J91 -> 9552 | AS91: =J91/12 -> 796 | AW91: =J91*#REF! -> #REF! | AX91: =J91*#REF! -> #REF! | AY91: =J91*#REF! -> #REF! | AZ91: =J91*#REF! -> #REF! | BA91: =J91*#REF! -> #REF! | BB91: =J91*#REF! -> #REF! | BC91: =J91*#REF! -> #REF! | BD91: =J91*#REF! -> #REF! | BE91: =J91*#REF! -> #REF! | BF91: =J91*#REF! -> #REF! | BG91: =J91*#REF! -> #REF! | BH91: =J91*#REF! -> #REF! | BI91: =J91*#REF! -> #REF!
A92: 45203 | B92: TOYS "R" US (CANADA) LTD. | C92: 加拿大 | D92: 4500114373 | E92: 2401526561 | F92: 4500114373-60 | G92: 77489GQ1-S002-NB | H92: 77489GQ1-S002-NB | I92: S4迷你恐龙GQ1 无硼 | J92: 624 | K92: 0 | L92: 12 | M92: =J92/L92 -> 52 | N92: 45260 | O92: 取消 | P92: 暂定11/30 SGS | S92: 45218 | T92: 无 | U92: 无 | V92: 日期码格式：ZURU INC(BVI) 标准格式 日期：按实际生产日期 Packaging Info: 1.出口加拿大市场。MA UPC 3L 包装。 产品，包装日期吗按Zuru 标准格式。箱唛date code YYYYMMDD格式，产品，包装和箱唛上面的时间要一样。 77489GQ1 UPC#193052057594, 无硼口水胶。 Remark: 2. 需要第三方SGS验货，验货时间暂定2023/11/30，每款每色请备1PC完整带包装样品供验货人员参考。用完后若无损坏可以放回大货里。 | W92: Abby Mai | X92: 1.22 | Y92: =X92*J92 -> 761.28 | AA92: 已入 | AC92: =AB92-J92 -> -624 | AF92: =J92 -> 624 | AK92: =AF92 -> 624 | AM92: =J92 -> 624 | AO92: =J92 -> 624 | AS92: =J92/12 -> 52 | AY92: =J92*0.125 -> 78 | AZ92: =J92*0.1042 -> 65.0208 | BA92: =J92*0.021 -> 13.104 | BB92: =J92*0.125 -> 78 | BC92: =J92*0.125 -> 78 | BD92: =J92*0.125 -> 78 | BE92: =J92*0.125 -> 78 | BF92: =J92*0.125 -> 78 | BG92: =J92*0.125 -> 78
A93: 45203 | B93: TOYS "R" US (CANADA) LTD. | C93: 加拿大 | D93: 4500114373 | E93: 3501526561 | F93: 4500114373-120 | G93: 77489GQ1-S002-NB | H93: 77489GQ1-S002-NB | I93: S4迷你恐龙GQ1 无硼 | J93: 2172 | K93: 0 | L93: 12 | M93: =J93/L93 -> 181 | N93: 45260 | O93: 取消 | P93: 暂定11/30 SGS | S93: 45218 | T93: 无 | U93: 无 | V93: 日期码格式：ZURU INC(BVI) 标准格式 日期：按实际生产日期 Packaging Info: 1.出口加拿大市场。MA UPC 3L 包装。 产品，包装日期吗按Zuru 标准格式。箱唛date code YYYYMMDD格式，产品，包装和箱唛上面的时间要一样。 77489GQ1 UPC#193052057594, 无硼口水胶。 Remark: 2. 需要第三方SGS验货，验货时间暂定2023/11/30，每款每色请备1PC完整带包装样品供验货人员参考。用完后若无损坏可以放回大货里。 | W93: Abby Mai | X93: 1.22 | Y93: =X93*J93 -> 2649.84 | AA93: 已入 | AC93: =AB93-J93 -> -2172 | AF93: =J93 -> 2172 | AK93: =AF93 -> 2172 | AM93: =J93 -> 2172 | AO93: =J93 -> 2172 | AS93: =J93/12 -> 181 | AY93: =J93*0.125 -> 271.5 | AZ93: =J93*0.1042 -> 226.3224 | BA93: =J93*0.021 -> 45.612 | BB93: =J93*0.125 -> 271.5 | BC93: =J93*0.125 -> 271.5 | BD93: =J93*0.125 -> 271.5 | BE93: =J93*0.125 -> 271.5 | BF93: =J93*0.125 -> 271.5 | BG93: =J93*0.125 -> 271.5
A94: 45203 | B94: TOYS "R" US (CANADA) LTD. | C94: 加拿大 | D94: 4500114374 | E94: 2401526574 | F94: 4500114374-40 | G94: 77489GQ1-S002-NB | H94: 77489GQ1-S002-NB | I94: S4迷你恐龙GQ1 无硼 | J94: 420 | K94: 0 | L94: 12 | M94: =J94/L94 -> 35 | N94: 45287 | O94: 取消 | P94: 暂定12/27 SGS | S94: 欠 | T94: 无 | U94: 无 | V94: 日期码格式：ZURU INC(BVI) 标准格式 日期：按实际生产日期 Packaging Info: 1.出口加拿大市场。MA UPC 3L 包装。 产品，包装日期吗按Zuru 标准格式。箱唛date code YYYYMMDD格式，产品，包装和箱唛上面的时间要一样。 77489GQ1 UPC#193052057594, 无硼口水胶。 Remark: 2. 需要第三方SGS验货，验货时间暂定2023/12/27，每款每色请备1PC完整带包装样品供验货人员参考。用完后若无损坏可以放回大货里。 | W94: Abby Mai | X94: 1.22 | Y94: =X94*J94 -> 512.4 | AA94: 已入 | AC94: =AB94-J94 -> -420 | AF94: =J94 -> 420 | AK94: =AF94 -> 420 | AM94: =J94 -> 420 | AO94: =J94 -> 420 | AS94: =J94/12 -> 35 | AY94: =J94*0.125 -> 52.5 | AZ94: =J94*0.1042 -> 43.764 | BA94: =J94*0.021 -> 8.82 | BB94: =J94*0.125 -> 52.5 | BC94: =J94*0.125 -> 52.5 | BD94: =J94*0.125 -> 52.5 | BE94: =J94*0.125 -> 52.5 | BF94: =J94*0.125 -> 52.5 | BG94: =J94*0.125 -> 52.5
A95: 45203 | B95: TOYS "R" US (CANADA) LTD. | C95: 加拿大 | D95: 4500114374 | E95: 3501526574 | F95: 4500114374-80 | G95: 77489GQ1-S002-NB | H95: 77489GQ1-S002-NB | I95: S4迷你恐龙GQ1 无硼 | J95: 1440 | K95: 0 | L95: 12 | M95: =J95/L95 -> 120 | N95: 45287 | O95: 取消 | P95: 暂定12/27 SGS | S95: 欠 | T95: 无 | U95: 无 | V95: 日期码格式：ZURU INC(BVI) 标准格式 日期：按实际生产日期 Packaging Info: 1.出口加拿大市场。MA UPC 3L 包装。 产品，包装日期吗按Zuru 标准格式。箱唛date code YYYYMMDD格式，产品，包装和箱唛上面的时间要一样。 77489GQ1 UPC#193052057594, 无硼口水胶。 Remark: 2. 需要第三方SGS验货，验货时间暂定2023/12/27，每款每色请备1PC完整带包装样品供验货人员参考。用完后若无损坏可以放回大货里。 | W95: Abby Mai | X95: 1.22 | Y95: =X95*J95 -> 1756.8 | AA95: 已入 | AC95: =AB95-J95 -> -1440 | AF95: =J95 -> 1440 | AK95: =AF95 -> 1440 | AM95: =J95 -> 1440 | AO95: =J95 -> 1440 | AS95: =J95/12 -> 120 | AY95: =J95*0.125 -> 180 | AZ95: =J95*0.1042 -> 150.048 | BA95: =J95*0.021 -> 30.24 | BB95: =J95*0.125 -> 180 | BC95: =J95*0.125 -> 180 | BD95: =J95*0.125 -> 180 | BE95: =J95*0.125 -> 180 | BF95: =J95*0.125 -> 180 | BG95: =J95*0.125 -> 180
A96: 45294 | B96: CRACKER BARREL | C96: 美国 | D96: 4500122527 | E96: 81775 | F96: 4500122527-10 | G96: 77593-S002 | H96: S4迷你恐龙6pcs入1内袋*4/箱 | I96: 5016 | J96: 0 | K96: 24 | L96: 209 | M96: 45372 | N96: 取消 | O96: 3/21 ITS的25%大货抽样 | P96: 未出样板 | R96: 45294 | S96: 无 | T96: 贴纸和位置图请参考4500091201 | U96: 日期码格式：ZURU INC(BVI) 标准格式 日期：按实际生产日期 Packaging Info: 1.ZURU标准MA包装( UPC 1L） +客版贴纸和内袋跟单提供文档，工厂自行订购。 出口美国 Remark: 1.ZURU标准MA包装( UPC 1L） +客版贴纸和内袋跟单提供文档，工厂自行订购。 出口美国 2.配比： #77593-S002-5 SURPRISE-DINO STRIKE-SERIES 6-CAPSULE, 6pcs/polybag, 24PCS/4Polybag/CTN; 6pcs into one polybag; 95mm 大球 Dino S6 INNER POLYBAG的美国标准警示语内容为： WARNING: TO AVOID DANGER OF SUFFOCATION, KEEP THIS BAG AWAY FROM BABIES AND CHILDREN. DO NOT USE IN CRIBS, BEDS, CARRIAGES OR PLAY PENS. THIS B AG IS NOT A TOY. KNOT UP BAG BEFORE THROWING AWAY. 3.产品及包装上都要有日期码，日期码是一致的（但不能为周末)，格式为ZURU标准格式。 4.#77593 需在2024年3月20日前完成25%大货，3月21日早上进行ITS的25%大货抽样验货。100%大货可以在2024年4月1日前完成。收到PASS的测试报告后，才可安排入 仓出货。 5.#77593为客户那边的新品，需提供1箱满箱样给客人确认后才能出货。满箱样所有需同大货（产品带贴纸+大货外箱） 。满箱样请在3月20日前寄给ZURU跟单。 25%抽样由客人指定的第三方ITS进行，现场在大货中抽样，具体要求如下面A,B,C ,D所列： A.样板抽取12pcs/色（带包装，大货中抽取）。 B.产品上有涂层的，每种涂层需要提供两张A4大小喷满同种油漆的底材（油漆喷厚一些避免用料不够，否则需客批才能另外补料给实验室）。 C.如有液体材料，每种需提供50ml。 D.抽样前一天会将测式申请表发出，需打印出来随抽样一起寄给ITS | V96: Hailey Yu | W96: 0.9069 | X96: 4549.0104 | AA96: -5016 | AD96: 无BOM | AE96: 5016 | AF96: 5016 | AH96: 5016 | AS96: 5016 | BK96: 627 | BL96: 522.6672 | BM96: 105.336 | BN96: 627 | BO96: 627 | BP96: 627 | BQ96: 627 | BR96: 627 | BS96: 627 | BU96: 45223 | BV96: 38160.911 | BW96: 45231 | BX96: 7435.5547 | BY96: 47231 | BZ96: 45231 | CA96: 45231 | CB96: 45731 | CC96: 45231
A97: 45380 | B97: Amazon CA (Vendor Center) | C97: 加拿大 | D97: 4500128507 | E97: 2CMFGAKT | F97: 4500128507-40 | G97: 77523-S001 | H97: S4迷你恐龙2PK圆筒 | I97: 16 | J97: 0 | K97: 16 | L97: =I97/K97 -> 1 | M97: 45420 | N97: 45416 | O97: 版本需要追客人放 | R97: 45380 | S97: 有 | T97: 欠 | U97: 日期码格式：ZURU INC(BVI) 标准格式 日期：按实际生产日期 Packaging Info: 出口加拿大，包装需要至少2/3L，无硼版本 77523：2PK#77489入PVC圆筒。收藏指南用MA 5L。3L不带UPC版收缩膜，2PK铜版纸图稿跟翻单4500116864。 （两个球的配比不能重复）。 Remark: 1.Amazon FOB订单，出口CA。外箱最长边不能超过25" （超过了，case pack只能为1），不符合要求的大货，一律不接受。 2. 外箱正面印ZURU Logo+SSCC LABEL（客供贴纸), 侧面印item#（订单上显示的SKU#)+carton size(以工厂实际尺寸为准,单位: inch) +MADE IN CHINA,日期使用Z URU 标准版本 SSCC Label 显示的是客人自己的item#, SSCC Label 贴在外箱正面的正中间，贴一面即可，跟单订购，贴纸离外箱距必须至少3cm, 每一张SSCC labe l 都是唯一且有不同流水及条码的，没有损耗，绝对不可贴错 ，否则贴错或损坏一张会导致全部都错，千万要注意. SSCC 贴纸务必要在正中间(可以覆盖Logo <(>&<)> 箱唛), 否则会影响到仓库扫描识别 3.日期码使用ZURU标准版本 LCL散货，直接送货到CDS保税仓 | V97: Agnes Zheng | W97: 2.3708 | X97: =W97*I97 -> 37.9328 | AA97: =Z97-I97 -> -16 | AV97: =I97*2 -> 32 | AX97: =AV97 -> 32 | BF97: =AX97 -> 32 | BH97: =BF97 -> 32 | BO97: =I97 -> 16 | BQ97: =BO97 -> 16 | BU97: =I97*0.125*2 -> 4 | BV97: =I97*0.1042*2 -> 3.3344 | BW97: =I97*0.021*2 -> 0.672 | BX97: =I97*0.125*2 -> 4 | BY97: =I97*0.125*2 -> 4 | BZ97: =I97*0.125*2 -> 4 | CA97: =I97*0.125*2 -> 4 | CB97: =I97*0.125*2 -> 4 | CC97: =I97*0.125*2 -> 4 | CE97: ='77593旧排期'!#REF!-BU97-BS97 -> #REF! | CF97: ='77593旧排期'!#REF!-BV97-BS97-BR97 -> #REF! | CG97: ='77593旧排期'!#REF!-BX97 -> #REF! | CH97: ='77593旧排期'!#REF!-BW97 -> #REF! | CI97: ='77593旧排期'!#REF!-BY97 -> #REF! | CJ97: ='77593旧排期'!#REF!-BZ97 -> #REF! | CK97: ='77593旧排期'!#REF!-CA97 -> #REF! | CL97: ='77593旧排期'!#REF!-CB97 -> #REF! | CM97: ='77593旧排期'!#REF!-CC97 -> #REF!
A98: 45344 | B98: WAL-MART STORES INC. USA | C98: 美国 | D98: 4500125041 | E98: 9331070236 | F98: 4500125041-30 | G98: 77489SLB-S001 | H98: S4迷你恐龙球(GQ1*154卡板装） | I98: 1848 | J98: 0 | K98: 1848 | L98: =I98/K98 -> 1 | M98: 45418 | N98: 4/12取消 | O98: 4/26 BV | R98: 箱唛资料可翻单4500119416 | S98: 有 | T98: 3/6客供 | U98: 日期码格式：ZURU DGYYYYMMDD CHINA(日期避开周末和法定节假日即可） 日期：按实际生产日期 Packaging Info: 1.包装要求： 77489SLB-S001：MA 1L收缩膜+MA 1L PDQ+MA 说明书+MA 收藏指南+MA 纸袋+MA polybag 每pcs产品上要贴1张RFID贴纸，贴纸由ZURU提供，贴纸位置请严格按照我们签回的签板； Remark: 1.包装要求： 77489SLB-S001：MA 1L收缩膜+MA 1L PDQ+MA 说明书+MA 收藏指南+MA 纸袋+MA polybag 每pcs产品上要贴1张RFID贴纸，贴纸由ZURU提供，贴纸位置请严格按照我们签回的签板； 2. 外箱印刷带条码的RFID箱唛：RFID紫色色带+WM Dept.图标+RFID图标+ITF-14条码，四面右下角印刷ZURU logo, ITFF条码只印刷在正唛一面，在加印的时候确保 条形码能扫描出来，外箱侧面任一角落加印："MADE IN CHINA" 字样； 3. 每个slip sheet上面贴一张艾利贴纸（不干胶贴纸）和一张普通贴纸（A4纸），slip sheet打印的普通贴纸的尺寸不能比艾利贴纸小，普通贴纸内容见附件； 4. 在产品上和包装上要有日期码、以及要有MADE IN CHINA和ZURU字样； 5. 产品如有扎带口要剪平，不能刮手。 6. 此单需要验货，请多备料 7. 此单以slip sheet出货， 77489：1848pcs/154CTN/Slip Sheet | V98: Iris Huang | W98: 1765.7621 | X98: =L98*W98 -> 1765.7621 | AA98: =Z98-I98 -> -1848 | AD98: 77489SLB-S001 | AE98: 已入 | AV98: =I98 -> 1848 | AX98: =AV98 -> 1848 | BC98: =AV98 -> 1848 | BH98: =BC98 -> 1848 | BM98: =I98/12 -> 154 | BU98: =I98*0.125 -> 231 | BV98: =I98*0.1042 -> 192.5616 | BW98: =I98*0.021 -> 38.808 | BX98: =I98*0.125 -> 231 | BY98: =I98*0.125 -> 231 | BZ98: =I98*0.125 -> 231 | CA98: =I98*0.125 -> 231 | CB98: =I98*0.125 -> 231 | CC98: =I98*0.125 -> 231 | CE98: ='77593旧排期'!#REF!-BU98-BS98 -> #REF! | CF98: ='77593旧排期'!#REF!-BV98-BS98-BR98 -> #REF! | CG98: ='77593旧排期'!#REF!-BX98 -> #REF! | CH98: ='77593旧排期'!#REF!-BW98 -> #REF! | CI98: ='77593旧排期'!#REF!-BY98 -> #REF! | CJ98: ='77593旧排期'!#REF!-BZ98 -> #REF! | CK98: ='77593旧排期'!#REF!-CA98 -> #REF! | CL98: ='77593旧排期'!#REF!-CB98 -> #REF! | CM98: ='77593旧排期'!#REF!-CC98 -> #REF!
A99: 45344 | B99: WAL-MART STORES INC. USA | C99: 美国 | D99: 4500125036 | E99: 9331070237 | F99: 4500125036-50 | G99: 77489SLB-S001 | H99: S4迷你恐龙球(GQ1*154卡板装） | I99: 1848 | J99: 0 | K99: 1848 | L99: =I99/K99 -> 1 | M99: 45397 | N99: 4/12取消 | O99: 4/16 BV | P99: 客人接受3L的收缩膜 消耗120135的15072PCSMA版本球 | R99: 箱唛资料可翻单4500119416 | S99: 有 | T99: 3/6客供 | U99: 日期码格式：ZURU DGYYYYMMDD CHINA(日期避开周末和法定节假日即可） 日期：按实际生产日期 Packaging Info: 1.包装要求： 77489SLB-S001：MA 1L收缩膜+MA 1L PDQ+MA 说明书+MA 收藏指南+MA 纸袋+MA polybag 每pcs产品上要贴1张RFID贴纸，贴纸由ZURU提供，贴纸位置请严格按照我们签回的签板； Remark: 1.包装要求： 77489SLB-S001：MA 1L收缩膜+MA 1L PDQ+MA 说明书+MA 收藏指南+MA 纸袋+MA polybag 每pcs产品上要贴1张RFID贴纸，贴纸由ZURU提供，贴纸位置请严格按照我们签回的签板； 2. 外箱印刷带条码的RFID箱唛：RFID紫色色带+WM Dept.图标+RFID图标+ITF-14条码，四面右下角印刷ZURU logo, ITFF条码只印刷在正唛一面，在加印的时候确保 条形码能扫描出来，外箱侧面任一角落加印："MADE IN CHINA" 字样； 3. 每个slip sheet上面贴一张艾利贴纸（不干胶贴纸）和一张普通贴纸（A4纸），slip sheet打印的普通贴纸的尺寸不能比艾利贴纸小，普通贴纸内容见附件； 4. 在产品上和包装上要有日期码、以及要有MADE IN CHINA和ZURU字样； 5. 产品如有扎带口要剪平，不能刮手。 6. 此单需要验货，请多备料 7. 此单以slip sheet出货， 77489：1848pcs/154CTN/Slip Sheet | V99: Iris Huang | W99: 1765.7621 | X99: =L99*W99 -> 1765.7621 | AA99: =Z99-I99 -> -1848 | AD99: 77489SLB-S001 | AE99: 已入 | AV99: =I99 -> 1848 | AX99: =AV99 -> 1848 | BC99: =AV99 -> 1848 | BH99: =BC99 -> 1848 | BM99: =I99/12 -> 154 | BU99: =I99*0.125 -> 231 | BV99: =I99*0.1042 -> 192.5616 | BW99: =I99*0.021 -> 38.808 | BX99: =I99*0.125 -> 231 | BY99: =I99*0.125 -> 231 | BZ99: =I99*0.125 -> 231 | CA99: =I99*0.125 -> 231 | CB99: =I99*0.125 -> 231 | CC99: =I99*0.125 -> 231 | CE99: =CE98-BU99-BS99 -> #REF! | CF99: =CF98-BV99-BS99-BR99 -> #REF! | CG99: =CG98-BX99 -> #REF! | CH99: =CH98-BW99 -> #REF! | CI99: =CI98-BY99 -> #REF! | CJ99: =CJ98-BZ99 -> #REF! | CK99: =CK98-CA99 -> #REF! | CL99: =CL98-CB99 -> #REF! | CM99: =CM98-CC99 -> #REF!
A100: 45344 | B100: WAL-MART STORES INC. USA | C100: 美国 | D100: 4500125037 | E100: 9331070234 | F100: 4500125037-30 | G100: 77489SLB-S001 | H100: S4迷你恐龙球(GQ1*154卡板装） | I100: 1848 | J100: 0 | K100: 1848 | L100: =I100/K100 -> 1 | M100: 45401 | N100: 4/12取消 | O100: 4/16 BV | R100: 箱唛资料可翻单4500119416 | S100: 有 | T100: 3/6客供 | U100: 日期码格式：ZURU DGYYYYMMDD CHINA(日期避开周末和法定节假日即可） 日期：按实际生产日期 Packaging Info: 1.包装要求： 77489SLB-S001：MA 1L收缩膜+MA 1L PDQ+MA 说明书+MA 收藏指南+MA 纸袋+MA polybag 每pcs产品上要贴1张RFID贴纸，贴纸由ZURU提供，贴纸位置请严格按照我们签回的签板； Remark: 1.包装要求： 77489SLB-S001：MA 1L收缩膜+MA 1L PDQ+MA 说明书+MA 收藏指南+MA 纸袋+MA polybag 每pcs产品上要贴1张RFID贴纸，贴纸由ZURU提供，贴纸位置请严格按照我们签回的签板； 2. 外箱印刷带条码的RFID箱唛：RFID紫色色带+WM Dept.图标+RFID图标+ITF-14条码，四面右下角印刷ZURU logo, ITFF条码只印刷在正唛一面，在加印的时候确保 条形码能扫描出来，外箱侧面任一角落加印："MADE IN CHINA" 字样； 3. 每个slip sheet上面贴一张艾利贴纸（不干胶贴纸）和一张普通贴纸（A4纸），slip sheet打印的普通贴纸的尺寸不能比艾利贴纸小，普通贴纸内容见附件； 4. 在产品上和包装上要有日期码、以及要有MADE IN CHINA和ZURU字样； 5. 产品如有扎带口要剪平，不能刮手。 6. 此单需要验货，请多备料 7. 此单以slip sheet出货， 77489：1848pcs/154CTN/Slip Sheet | V100: Iris Huang | W100: 1765.7621 | X100: =L100*W100 -> 1765.7621 | AA100: =Z100-I100 -> -1848 | AD100: 77489SLB-S001 | AE100: 已入 | AV100: =I100 -> 1848 | AX100: =AV100 -> 1848 | BC100: =AV100 -> 1848 | BH100: =BC100 -> 1848 | BM100: =I100/12 -> 154 | BU100: =I100*0.125 -> 231 | BV100: =I100*0.1042 -> 192.5616 | BW100: =I100*0.021 -> 38.808 | BX100: =I100*0.125 -> 231 | BY100: =I100*0.125 -> 231 | BZ100: =I100*0.125 -> 231 | CA100: =I100*0.125 -> 231 | CB100: =I100*0.125 -> 231 | CC100: =I100*0.125 -> 231 | CE100: ='77593旧排期'!#REF!-BU100-BS100 -> #REF! | CF100: ='77593旧排期'!#REF!-BV100-BS100-BR100 -> #REF! | CG100: ='77593旧排期'!#REF!-BX100 -> #REF! | CH100: ='77593旧排期'!#REF!-BW100 -> #REF! | CI100: ='77593旧排期'!#REF!-BY100 -> #REF! | CJ100: ='77593旧排期'!#REF!-BZ100 -> #REF! | CK100: ='77593旧排期'!#REF!-CA100 -> #REF! | CL100: ='77593旧排期'!#REF!-CB100 -> #REF! | CM100: ='77593旧排期'!#REF!-CC100 -> #REF!
A101: 45344 | B101: WAL-MART STORES INC. USA | C101: 美国 | D101: 4500125037 | E101: 9331070238 | F101: 4500125037-40 | G101: 77489SLB-S001 | H101: S4迷你恐龙球(GQ1*154卡板装） | I101: 1848 | J101: 0 | K101: 1848 | L101: =I101/K101 -> 1 | M101: 45401 | N101: 4/12取消 | O101: 4/16 BV | R101: 箱唛资料可翻单4500119416 | S101: 有 | T101: 3/6客供 | U101: 日期码格式：ZURU DGYYYYMMDD CHINA(日期避开周末和法定节假日即可） 日期：按实际生产日期 Packaging Info: 1.包装要求： 77489SLB-S001：MA 1L收缩膜+MA 1L PDQ+MA 说明书+MA 收藏指南+MA 纸袋+MA polybag 每pcs产品上要贴1张RFID贴纸，贴纸由ZURU提供，贴纸位置请严格按照我们签回的签板； Remark: 1.包装要求： 77489SLB-S001：MA 1L收缩膜+MA 1L PDQ+MA 说明书+MA 收藏指南+MA 纸袋+MA polybag 每pcs产品上要贴1张RFID贴纸，贴纸由ZURU提供，贴纸位置请严格按照我们签回的签板； 2. 外箱印刷带条码的RFID箱唛：RFID紫色色带+WM Dept.图标+RFID图标+ITF-14条码，四面右下角印刷ZURU logo, ITFF条码只印刷在正唛一面，在加印的时候确保 条形码能扫描出来，外箱侧面任一角落加印："MADE IN CHINA" 字样； 3. 每个slip sheet上面贴一张艾利贴纸（不干胶贴纸）和一张普通贴纸（A4纸），slip sheet打印的普通贴纸的尺寸不能比艾利贴纸小，普通贴纸内容见附件； 4. 在产品上和包装上要有日期码、以及要有MADE IN CHINA和ZURU字样； 5. 产品如有扎带口要剪平，不能刮手。 6. 此单需要验货，请多备料 7. 此单以slip sheet出货， 77489：1848pcs/154CTN/Slip Sheet | V101: Iris Huang | W101: 1765.7621 | X101: =L101*W101 -> 1765.7621 | AA101: =Z101-I101 -> -1848 | AD101: 77489SLB-S001 | AE101: 已入 | AV101: =I101 -> 1848 | AX101: =AV101 -> 1848 | BC101: =AV101 -> 1848 | BH101: =BC101 -> 1848 | BM101: =I101/12 -> 154 | BU101: =I101*0.125 -> 231 | BV101: =I101*0.1042 -> 192.5616 | BW101: =I101*0.021 -> 38.808 | BX101: =I101*0.125 -> 231 | BY101: =I101*0.125 -> 231 | BZ101: =I101*0.125 -> 231 | CA101: =I101*0.125 -> 231 | CB101: =I101*0.125 -> 231 | CC101: =I101*0.125 -> 231 | CE101: =CE100-BU101-BS101 -> #REF! | CF101: =CF100-BV101-BS101-BR101 -> #REF! | CG101: =CG100-BX101 -> #REF! | CH101: =CH100-BW101 -> #REF! | CI101: =CI100-BY101 -> #REF! | CJ101: =CJ100-BZ101 -> #REF! | CK101: =CK100-CA101 -> #REF! | CL101: =CL100-CB101 -> #REF! | CM101: =CM100-CC101 -> #REF!
...
