Workbook
Name cavity: '[1]Form-003'!#REF!
Name Code: '[2]CQS Code(rev 38)'!$B$7:$E$1000
Name cycle.time: '[1]Form-003'!#REF!
Name GDE: [3]基础表!#REF!
Name mold.color: '[1]Form-003'!#REF!
Name mold.cost: '[1]Form-003'!#REF!
Name mold.height: '[1]Form-003'!#REF!
Name mold.length: '[1]Form-003'!#REF!
Name mold.material: '[1]Form-003'!#REF!
Name mold.name: '[1]Form-003'!#REF!
Name mold.number: '[1]Form-003'!#REF!
Name mold.partweight: '[1]Form-003'!#REF!
Name mold.usage: '[1]Form-003'!#REF!
Name mold.width: '[1]Form-003'!#REF!
Name new_sum: #REF!
Name part.list: '[1]Form-003'!#REF!
Name PI_IN: #REF!
Name PI_SUM: #REF!
Name PI_SUM_SALES: #REF!
Name Prepared.By: '[1]Form-003'!#REF!
Name Ref.Number: '[1]Form-003'!#REF!
Name Revised.By: '[1]Form-003'!#REF!
Name sd: [3]基础表!#REF!
Name tool.plan: '[1]Form-003'!#REF!
Name up: '[1]Form-003'!#REF!
Name Vendor: '[1]Form-003'!#REF!
Name 类别: [3]基础表!#REF!
Name 类别1: [3]基础表!#REF!
Name 领料单: [3]基础表!#REF!
Name 收料单: [3]基础表!#REF!
Name 一部: [3]基础表!#REF!
Name GDE: [4]基础表!#REF!
Name new_sum: #REF!
Name PI_IN: #REF!
Name PI_SUM: #REF!
Name PI_SUM_SALES: #REF!
Name sd: [4]基础表!#REF!
Name 类别: [4]基础表!#REF!
Name 类别1: [4]基础表!#REF!
Name 领料单: [4]基础表!#REF!
Name 收料单: [4]基础表!#REF!
Name 一部: [4]基础表!#REF!
Name GDE: [4]基础表!#REF!
Name new_sum: #REF!
Name PI_IN: #REF!
Name PI_SUM: #REF!
Name PI_SUM_SALES: #REF!
Name sd: [4]基础表!#REF!
Name 类别: [4]基础表!#REF!
Name 类别1: [4]基础表!#REF!
Name 领料单: [4]基础表!#REF!
Name 收料单: [4]基础表!#REF!
Name 一部: [4]基础表!#REF!
Name GDE: [5]基础表!#REF!
Name new_sum: #REF!
Name PI_IN: #REF!
Name PI_SUM: #REF!
Name PI_SUM_SALES: #REF!
Name sd: [5]基础表!#REF!
Name 类别: [5]基础表!#REF!

Sheet 77515 旧排期
A1: ZURU （77515 Mini Brands 迷你球DIY厨艺系列）生产排期表 | H1: 77555SK1-S002这款是带底座 | L1: 走KM澳洲和出新西兰的说明书都要加纽扣电池警语贴纸
AG2: 77515 | AK2: 收縮膜 | AO2: 收藏指南 | AS2: PDQ盒 | BK2: 77516
A3: 香港接单日期 | B3: 第三方客户名称 | C3: 走货国家 | D3: ZURU PO NO# | E3: 第三方客户 PO NO# | F3: SKU | G3: ITEM# | H3: 中文名 | I3: PO数量 (pcs) | J3: 内箱装箱数量(pcs) | K3: 外箱装箱数量(pcs) | L3: 总箱数 | M3: 计划出货期 | N3: 计划验货期 | O3: 第三方客户公证行验货 | P3: 驗貨結果 | Q3: S/0船期 | R3: 箱唛资料(收到日期) | S3: 外箱贴纸 | T3: 客供贴纸AI(收到日期) | U3: 备注 | V3: ZURU 跟单 | W3: 单价USD | X3: 金额USD | Y3: 發票號 | Z3: 系统货号 | AA3: 是否入系统 | AB3: 已送情况 | AC3: 欠数 | AD3: 贴纸 | AE3: 生产地点 | AG3: 球数 | AH3: 无香味版本 | AI3: 删除组合10（猪肉） | AJ3: MA 3语 收缩膜 无条码 | AK3: MA 1语收缩膜 | AL3: MA 3语收缩膜 | AM3: 客版收缩膜 | AN3: 客版 3L 收缩膜 | AO3: MA 5L语收藏指南 | AP3: ESAL客版指南/说明书 | AQ3: WM客版 | AR3: 外挂中文收藏指南+中文收藏指南(每一款都不同) | AS3: GQ5-S001 21PCS 1L | AT3: GQ5-S001 21PCS 3L | AU3: WM 客版GQ5 | AV3: WM 客版GQ6 | AW3: GQ6-S001 12PCS 1L | AX3: GQ6-S001 12PCS 3L | AY3: GQ1-S001 13pcs 1L | AZ3: GQ1-S001 13pcs 3L | BA3: GQ2-S001 25pcs 1L | BB3: GQ2-S001 25pcs 3L | BC3: SK-S001 60PCS 1L 不含底座 配挂钩 | BD3: SK-S002 60PCS 1L 含底座 | BE3: SK-S002 60PCS 3L 含底座 | BF3: 77515SK1-S002 30pcs 1L 含底座 | BG3: 77515SK1-S001 30pcs 3L 不带底座 | BH3: SK1底座 | BI3: FD客 77515GQ3 | BJ3: 77515GQ3-S001 客版 8PCS | BK3: 圆筒 | BL3: 3L 彩纸 | BM3: 合计数量
A4: 45252 | B4: ZURU | C4: 库有 | D4: ZMPO23692 | G4: 77515-S001 | H4: DIY厨艺大师 | I4: 1000 | J4: 0 | K4: 24 | L4: =I4/K4 -> 41.666667 | M4: 45252 | N4: 45248 | P4: OK | R4: 周转箱 | S4: 无 | T4: 无 | U4: 跟PP订单一起安排 | Y4: 84014-2.19 | Z4: 无 | AE4: DG | AG4: =I4 -> 1000 | BM4: =AG4+AH4+AI4 -> 1000
A5: 45252 | B5: ZURU | C5: 库有 | D5: ZMPO23692 | G5: 77515-S001 | H5: DIY厨艺大师 | I5: 30套散件 | J5: 0 | K5: 24 | L5: 1 | M5: 45252 | N5: 45248 | P5: OK | R5: 周转箱 | S5: 无 | T5: 无 | U5: 跟PP订单一起安排/只需要全套散件，麻烦用胶袋分装好一套为一袋 | Y5: 84014-2.19 | Z5: 无 | AE5: DG | BM5: =AG5+AH5+AI5 -> 0
A6: 45252 | B6: ZURU | C6: 库有 | D6: ZPO2311001 | G6: 77515-S001 | H6: DIY厨艺大师 | I6: 510 | J6: 0 | K6: 24 | L6: =I6/K6 -> 21.25 | M6: 45272 | N6: 45268 | P6: OK | R6: 周转箱 | S6: 无 | T6: 无 | Z6: 无 | AE6: DG | AG6: =I6 -> 510 | BM6: =AG6+AH6+AI6 -> 510 | BN6: =BN5+BM6 -> 510 | BO6: =$BO$3-BN6 -> -510 | BQ6: =AS6+AT6+BA6+BB6 -> 0 | BR6: =BR5+BQ6 -> 0 | BS6: =$BS$3-BR6 -> 0
A7: 45279 | B7: ZURU | C7: 库有 | D7: ZMPO23783 | G7: 77515-S001 | H7: DIY厨艺大师 | I7: 5套 | J7: 0 | K7: 24 | L7: 1 | M7: 45288 | N7: 45285 | P7: OK | Q7: 3/14 寄深圳 | R7: 周转箱 | S7: 无 | T7: 无 | U7: 左图中散件每款各5PCS | Y7: 84562-4.17 | Z7: 无 | AE7: DG | BM7: =AG7+AH7+AI7 -> 0
A8: 45279 | B8: ZURU | C8: 库有 | D8: ZMPO23783 | G8: 77515-S001 | H8: DIY厨艺大师 | I8: 5套 | J8: 0 | K8: 24 | L8: 1 | M8: 45288 | N8: 45285 | P8: OK | Q8: 3/14 寄深圳 | R8: 周转箱 | S8: 无 | T8: 无 | U8: 左图中每款散件各5PCS | Z8: 无 | AE8: DG | BM8: =AG8+AH8+AI8 -> 0 | BN8: =BN7+BM8 -> 0 | BO8: =$BO$3-BN8 -> 0 | BQ8: =AS8+AT8+BA8+BB8 -> 0 | BR8: =BR7+BQ8 -> 0 | BS8: =$BS$3-BR8 -> 0
A9: 45275 | B9: ZURU | C9: 库有 | D9: ZMPO23775 | G9: 77515-S001 | H9: DIY厨艺大师 | I9: 2000 | J9: 0 | K9: 24 | L9: =I9/K9 -> 83.333333 | M9: 45300 | N9: 45296 | P9: pass | Q9: 3/6 已送500pcs | R9: 周转箱 | S9: 无 | T9: 无 | U9: 大货最新版本/款号平均/请按款号装箱，并在外箱上注明款号/请用大货标准箱装箱24PCS/箱共84箱/箱唛请参照邮件附件 | Y9: 84234-3.14 | Z9: 无 | AE9: DG | AG9: =I9 -> 2000 | AK9: =AG9 -> 2000 | AO9: =AG9 -> 2000 | BM9: =AG9+AH9+AI9 -> 2000
A10: 45275 | B10: ZURU | C10: 库有 | D10: ZMPO23775 | G10: 77515GQ2-S001 | H10: DIY厨艺大师 | I10: 2000 | J10: 0 | K10: 50 | L10: =2000/25 -> 80 | M10: 45300 | N10: 45296 | P10: pass | R10: 周转箱 | S10: 无 | T10: 无 | U10: 80个满PDQ 大货最新版本/大货标准箱装箱/箱唛请参照邮件附件 | Y10: 84234-3.14 | Z10: 无 | AE10: DG | AG10: =80*25 -> 2000 | AK10: =AG10 -> 2000 | AO10: =AG10 -> 2000 | BA10: 80 | BM10: =AG10+AH10+AI10 -> 2000
A11: 45293 | B11: ZURU | C11: 库有 | D11: ZMPO24005 | G11: 77515-S001 | H11: DIY厨艺大师 | I11: 150套散件 | J11: 0 | K11: 24 | L11: 1 | M11: 45307 | N11: 45303 | P11: OK | Q11: 3/14 寄深圳 | R11: 周转箱 | S11: 无 | T11: 无 | U11: 大货订单最新版本/只需要全套散件，麻烦用胶袋分装好一套为一袋 | Y11: 84561-4.17 | Z11: 无 | AE11: DG | AG11: 150 | BM11: =AG11+AH11+AI11 -> 150
A12: 45302 | B12: ZURU | C12: 库有 | D12: ZMPO24030 | G12: 77515-S001 | H12: DIY厨艺大师 | I12: 1400 | J12: 0 | K12: 24 | L12: =I12/K12 -> 58.333333 | M12: 45314 | N12: 45310 | P12: OK | R12: 周转箱 | S12: 无 | T12: 无 | U12: 左图中7款散件每款各200PCS/要做好的散件成品 | Y12: 84661-4.29 | Z12: 无 | AE12: DG | BM12: =AG12+AH12+AI12 -> 0
A13: 45302 | B13: ZURU | C13: 库有 | D13: ZMPO24030 | G13: 77515-S001 | H13: DIY厨艺大师 | I13: 800 | J13: 0 | K13: 24 | L13: =I13/K13 -> 33.333333 | M13: 45314 | N13: 45310 | P13: OK | R13: 周转箱 | S13: 无 | T13: 无 | U13: 左图中4款配件每款散件各200PCS | Y13: 84661-4.29 | Z13: 无 | AE13: DG | BM13: =AG13+AH13+AI13 -> 0
A14: 45315 | B14: ZURU | C14: 库有 | D14: ZMPO24071 | G14: 77515SK1-S002 | H14: DIY厨艺大师 | I14: 5套满展示架 | J14: 0 | K14: 30 | L14: =I14/K14 -> #VALUE! | M14: 45348 | N14: 20024/2/22 | Q14: 3/22 送库有 | R14: 周转箱 | S14: 无 | T14: 无 | U14: 大货订单最新版本/里面产品按大货配比/箱唛参照邮件附件 | Y14: 84558-4.17 | Z14: 无 | AE14: DG | AG14: =5*30 -> 150 | BF14: =5 -> 5 | BH14: =BF14 -> 5 | BM14: =AG14+AH14+AI14 -> 150
A15: 45317 | B15: ZURU | C15: 库有 | D15: ZMPO24079 | G15: 77515-S001 | H15: DIY厨艺大师 | I15: 200套散件 | J15: 0 | K15: 24 | L15: =I15/K15 -> #VALUE! | M15: 45351 | N15: 45348 | R15: 周转箱 | S15: 无 | T15: 无 | U15: 左图中14款酱每款200PCS/共2800PCS/麻烦用胶袋分装好14款一套为一袋 | Z15: 无 | AE15: DG | AG15: 200 | BM15: =AG15+AH15+AI15 -> 200 | BN15: =BN14+BM15 -> 200 | BO15: =$BO$3-BN15 -> -200 | BQ15: =AS15+AT15+BA15+BB15 -> 0 | BR15: =BR14+BQ15 -> 0 | BS15: =$BS$3-BR15 -> 0
A16: 45254 | B16: TARGET US | C16: 美国 | D16: 4500119549 | E16: 0086-7227519-0584 | F16: 4500119549-10 | G16: 77515GQ5-S002 | H16: DIY厨艺大师 | I16: 24465 | J16: 0 | K16: 21 | L16: =I16/K16 -> 1165 | M16: 45320 | N16: 45316 | P16: AOD | Q16: 1/29 客上柜 空运 | R16: 45654 | S16: 有 | T16: 1/9 寄出 | U16: 日期码格式：ZURU INC(BVI) 标准格式 日期：按实际生产日期 Packaging Info: MA PDQ Remark: 1. 77515GQ5-S002-MINI BRAND-MASTER CHEF MINI BRANDS-SERIES 1,21pcs/Gravity PDQ, 21pcs/CTN,No Inner,STD Color Assortment (White drop) 2. MA PDQ, 产品UPC 显示193052061034; 11 assortment have the same ratio； 3. 外箱正唛左上角位置粘贴条码箱贴纸，每箱只贴一张，由ZURU订购。来料贴纸上显示的客户DPCI# 086-02-9598， UPC显示10193052061031; 4. 外箱正唛箱唛内容右侧需贴一张Event label，内容显示 Toys Set Date：3/3/2024，工厂自行订购 5. 产品和包装上印刷 tracking code信息，格式为ZURU常规格式; 6. 出货方式：货代自提。 | V16: Holly Zheng | W16: 1.75 | X16: =I16*W16 -> 42813.75 | Y16: 78917-1.30 | Z16: 77515GQ5-S002 | AA16: 已入 | AE16: DG | AG16: =I16 -> 24465 | AK16: =AG16 -> 24465 | AO16: =AG16 -> 24465 | AS16: =I16/21 -> 1165 | BM16: =AG16+AH16+AI16 -> 24465
A17: 45254 | B17: TARGET US | C17: 美国 | D17: 4500119550 | E17: 0086-5971609-0581 | F17: 4500119550-10 | G17: 77515GQ5-S002 | H17: DIY厨艺大师 | I17: 35532 | J17: 0 | K17: 21 | L17: =I17/K17 -> 1692 | M17: 45320 | N17: 45316 | P17: pass | Q17: 1/29 客上柜 空运 | R17: 45654 | S17: 有 | T17: 1/9 寄出 | U17: 日期码格式：ZURU INC(BVI) 标准格式 日期：按实际生产日期 Packaging Info: MA PDQ Remark: 1. 77515GQ5-S002-MINI BRAND-MASTER CHEF MINI BRANDS-SERIES 1,21pcs/Gravity PDQ, 21pcs/CTN,No Inner,STD Color Assortment (White drop) 2. MA PDQ, 产品UPC 显示193052061034; 11 assortment have the same ratio； 3. 外箱正唛左上角位置粘贴条码箱贴纸，每箱只贴一张，由ZURU订购。来料贴纸上显示的客户DPCI# 086-02-9598， UPC显示10193052061031; 4. 外箱正唛箱唛内容右侧需贴一张Event label，内容显示 Toys Set Date：3/3/2024，工厂自行订购 5. 产品和包装上印刷 tracking code信息，格式为ZURU常规格式; 6. 出货方式：货代自提。 | V17: Holly Zheng | W17: 1.75 | X17: =I17*W17 -> 62181 | Y17: 78916-1.30 | Z17: 77515GQ5-S002 | AA17: 已入 | AE17: DG | AG17: =I17 -> 35532 | AK17: =AG17 -> 35532 | AO17: =AG17 -> 35532 | AS17: =I17/21 -> 1692 | BM17: =AG17+AH17+AI17 -> 35532
A18: 45254 | B18: TARGET US | C18: 美国 | D18: 4500119551 | E18: 0086-6266753-0581 | F18: 4500119551-10 | G18: 77515GQ5-S002 | H18: DIY厨艺大师 | I18: 38955 | J18: 0 | K18: 21 | L18: =I18/K18 -> 1855 | M18: 45320 | N18: 45316 | P18: pass | Q18: 1/30 客上柜 | R18: 45654 | S18: 有 | T18: 1/9 寄出 | U18: 日期码格式：ZURU INC(BVI) 标准格式 日期：按实际生产日期 Packaging Info: MA PDQ Remark: 1. 77515GQ5-S002-MINI BRAND-MASTER CHEF MINI BRANDS-SERIES 1,21pcs/Gravity PDQ, 21pcs/CTN,No Inner,STD Color Assortment (White drop) 2. MA PDQ, 产品UPC 显示193052061034; 11 assortment have the same ratio； 3. 外箱正唛左上角位置粘贴条码箱贴纸，每箱只贴一张，由ZURU订购。来料贴纸上显示的客户DPCI# 086-02-9598， UPC显示10193052061031; 4. 产品和包装上印刷 tracking code信息，格式为ZURU常规格式; 5. 出货方式：货代自提。 | V18: Holly Zheng | W18: 1.75 | X18: =I18*W18 -> 68171.25 | Y18: 78918-1.30 | Z18: 77515GQ5-S002 | AA18: 已入 | AE18: DG | AG18: =I18 -> 38955 | AK18: =AG18 -> 38955 | AO18: =AG18 -> 38955 | AS18: =I18/21 -> 1855 | BM18: =AG18+AH18+AI18 -> 38955
A19: 45254 | B19: TARGET US | C19: 美国 | D19: 4500119557 | E19: 0086-3900914-0581 | F19: 4500119557-10 | G19: 77515GQ5-S002 | H19: DIY厨艺大师 | I19: 45003 | J19: 0 | K19: 21 | L19: =I19/K19 -> 2143 | M19: 45321 | N19: 45317 | P19: pass | Q19: 1/30 客上柜 | R19: 45654 | S19: 有 | T19: 1/9 寄出 | U19: 日期码格式：ZURU INC(BVI) 标准格式 日期：按实际生产日期 Packaging Info: MA PDQ Remark: 1. 77515GQ5-S002-MINI BRAND-MASTER CHEF MINI BRANDS-SERIES 1,21pcs/Gravity PDQ, 21pcs/CTN,No Inner,STD Color Assortment (White drop) 2. MA PDQ, 产品UPC 显示193052061034; 11 assortment have the same ratio； 3. 外箱正唛左上角位置粘贴条码箱贴纸，每箱只贴一张，由ZURU订购。来料贴纸上显示的客户DPCI# 086-02-9598， UPC显示10193052061031; 4. 产品和包装上印刷 tracking code信息，格式为ZURU常规格式; 5. 出货方式：货代自提。 | V19: Holly Zheng | W19: 1.75 | X19: =I19*W19 -> 78755.25 | Y19: 78919-1.30 | Z19: 77515GQ5-S002 | AA19: 已入 | AE19: DG | AG19: =I19 -> 45003 | AK19: =AG19 -> 45003 | AO19: =AG19 -> 45003 | AS19: =I19/21 -> 2143 | BM19: =AG19+AH19+AI19 -> 45003
A20: 45254 | B20: TARGET US | C20: 美国 | D20: 4500119555 | E20: 0086-9221446-0584 | F20: 4500119555-10 | G20: 77515GQ5-S002 | H20: DIY厨艺大师 | I20: 20013 | J20: 0 | K20: 21 | L20: =I20/K20 -> 953 | M20: 45320 | N20: 45316 | P20: pass | Q20: 1/31 客上柜 | R20: 45654 | S20: 有 | T20: 1/9 寄出 | U20: 日期码格式：ZURU INC(BVI) 标准格式 日期：按实际生产日期 Packaging Info: MA PDQ Remark: 1. 77515GQ5-S002-MINI BRAND-MASTER CHEF MINI BRANDS-SERIES 1,21pcs/Gravity PDQ, 21pcs/CTN,No Inner,STD Color Assortment (White drop) 2. MA PDQ, 产品UPC 显示193052061034; 11 assortment have the same ratio； 3. 外箱正唛左上角位置粘贴条码箱贴纸，每箱只贴一张，由ZURU订购。来料贴纸上显示的客户DPCI# 086-02-9598， UPC显示10193052061031; 4. 产品和包装上印刷 tracking code信息，格式为ZURU常规格式; 5. 出货方式：货代自提。 | V20: Holly Zheng | W20: 1.75 | X20: =I20*W20 -> 35022.75 | Y20: 78951-1.31 | Z20: 77515GQ5-S002 | AA20: 已入 | AE20: DG | AG20: =I20 -> 20013 | AK20: =AG20 -> 20013 | AO20: =AG20 -> 20013 | AS20: =I20/21 -> 953 | BM20: =AG20+AH20+AI20 -> 20013
A21: 45254 | B21: TARGET US | C21: 美国 | D21: 4500119558 | E21: 0086-3865926-0581 | F21: 4500119558-10 | G21: 77515GQ5-S002 | H21: DIY厨艺大师 | I21: 29988 | J21: 0 | K21: 21 | L21: =I21/K21 -> 1428 | M21: 45320 | N21: 45316 | P21: pass | Q21: 1/31 客上柜 | R21: 45654 | S21: 有 | T21: 1/9 寄出 | U21: 日期码格式：ZURU INC(BVI) 标准格式 日期：按实际生产日期 Packaging Info: MA PDQ Remark: 1. 77515GQ5-S002-MINI BRAND-MASTER CHEF MINI BRANDS-SERIES 1,21pcs/Gravity PDQ, 21pcs/CTN,No Inner,STD Color Assortment (White drop) 2. MA PDQ, 产品UPC 显示193052061034; 11 assortment have the same ratio； 3. 外箱正唛左上角位置粘贴条码箱贴纸，每箱只贴一张，由ZURU订购。来料贴纸上显示的客户DPCI# 086-02-9598， UPC显示10193052061031; 4. 产品和包装上印刷 tracking code信息，格式为ZURU常规格式; 5. 出货方式：货代自提。 | V21: Holly Zheng | W21: 1.75 | X21: =I21*W21 -> 52479 | Y21: 84011-2.19 | Z21: 77515GQ5-S002 | AA21: 已入 | AE21: DG | AG21: =I21 -> 29988 | AK21: =AG21 -> 29988 | AO21: =AG21 -> 29988 | AS21: =I21/21 -> 1428 | BM21: =AG21+AH21+AI21 -> 29988
A22: 45254 | B22: TARGET US | C22: 美国 | D22: 4500119553 | E22: 0086-1598304-0584 | F22: 4500119553-10 | G22: 77515GQ5-S002 | H22: DIY厨艺大师 | I22: 26040 | J22: 0 | K22: 21 | L22: =I22/K22 -> 1240 | M22: 45320 | N22: 45316 | P22: pass | Q22: 2/2 客上柜 | R22: 45654 | S22: 有 | T22: 1/9 寄出 | U22: 日期码格式：ZURU INC(BVI) 标准格式 日期：按实际生产日期 Packaging Info: MA PDQ Remark: 1. 77515GQ5-S002-MINI BRAND-MASTER CHEF MINI BRANDS-SERIES 1,21pcs/Gravity PDQ, 21pcs/CTN,No Inner,STD Color Assortment (White drop) 2. MA PDQ, 产品UPC 显示193052061034; 11 assortment have the same ratio； 3. 外箱正唛左上角位置粘贴条码箱贴纸，每箱只贴一张，由ZURU订购。来料贴纸上显示的客户DPCI# 086-02-9598， UPC显示10193052061031; 4. 产品和包装上印刷 tracking code信息，格式为ZURU常规格式; 5. 出货方式：货代自提。 | V22: Holly Zheng | W22: 1.75 | X22: =I22*W22 -> 45570 | Y22: 84010-2.19 | Z22: 77515GQ5-S002 | AA22: 已入 | AE22: DG | AG22: =I22 -> 26040 | AK22: =AG22 -> 26040 | AO22: =AG22 -> 26040 | AS22: =I22/21 -> 1240 | BM22: =AG22+AH22+AI22 -> 26040
A23: 45285 | B23: AMAZON.COM.DEDC,LLC | C23: 美国 | D23: 4500122098 | F23: 4500122098-10 | G23: 77515-S001 | H23: DIY厨艺大师 | I23: 9264 | J23: 0 | K23: 24 | L23: =I23/K23 -> 386 | M23: 45321 | N23: 45317 | P23: AOD | Q23: 2/2 交仓 空运订单 | R23: 外箱正面印ZURU Logo+SSCC LABEL（客供贴纸), 侧面印item# | S23: 有 | T23: 45314 | U23: 日期码格式：ZURU INC(BVI) 标准格式 日期：按实际生产日期 Packaging Info: 77515：MA 1L. 加防伪贴纸， 跟单提供。 Remark: 1.Amazon FOB订单，出口US。外箱最长边不能超过25" （超过了，case pack只能为1），不符合要求的大货，一律不接受。 2. 外箱正面印ZURU Logo+SSCC LABEL（客供贴纸), 侧面印item#（订单上显示的SKU#)+carton size(以工厂实际尺寸为准,单位: inch) +MADE IN CHINA,日期使用Z URU 标准版本 SSCC Label 显示的是客人自己的item#, SSCC Label 贴在外箱正面的正中间，贴一面即可，跟单订购，贴纸离外箱距必须至少3cm, 每一张SSCC labe l 都是唯一且有不同流水及条码的，没有损耗，绝对不可贴错 ，否则贴错或损坏一张会导致全部都错，千万要注意. SSCC 贴纸务必要在正中间(可以覆盖Logo <(>&<)> 箱唛), 否则会影响到仓库扫描识别 3.日期码使用ZURU标准版本 邮包盒上要打日期码 4.按照客户PO# 装柜/箱号顺序装柜，跟单会提前给到装柜计划。请大货生产/仓库存放时留意，以便装柜时不混乱（装错/装漏/找不到货号） | V23: Agnes Zheng | W23: 1.19 | X23: =I23*W23 -> 11024.16 | Y23: 84009-2.19 | Z23: 77515-S001 | AA23: 已入 | AE23: DG | AG23: =I23 -> 9264 | AK23: =AG23 -> 9264 | AO23: =AG23 -> 9264 | BM23: =AG23+AH23+AI23 -> 9264
A24: 45271 | B24: MEIJER | C24: 美国 | D24: 4500120916 | E24: 215358810 | F24: 4500120916-10 | G24: 77515GQ1-S003 | H24: DIY厨艺大师 | I24: 416 | J24: 0 | K24: 13 | L24: =I24/K24 -> 32 | M24: 45321 | N24: 45317 | P24: pass | Q24: 2/19入仓 | R24: 45647 | S24: 无 | T24: 无 | U24: 日期码格式：ZURU INC(BVI) 标准格式 日期：按实际生产日期 Packaging Info: 1. MA 1L 包装 2. 客人指定箱唛排版 Remark: 出货前 Zuru QC 验货 | V24: Sophia Zhou | W24: 1.7 | X24: =I24*W24 -> 707.2 | Y24: 84028-2.20 | Z24: 77515GQ1-S003 | AA24: 已入 | AE24: DG | AG24: =I24 -> 416 | AK24: =AG24 -> 416 | AO24: =AG24 -> 416 | AY24: =I24/13 -> 32 | BM24: =AG24+AH24+AI24 -> 416
A25: 45271 | B25: MEIJER | C25: 美国 | D25: 4500120919 | E25: 215358821 | F25: 4500120919-10 | G25: 77515GQ1-S003 | H25: DIY厨艺大师 | I25: 806 | J25: 0 | K25: 13 | L25: =I25/K25 -> 62 | M25: 45321 | N25: 45317 | P25: pass | Q25: 2/19入仓 | R25: 45647 | S25: 无 | T25: 无 | U25: 日期码格式：ZURU INC(BVI) 标准格式 日期：按实际生产日期 Packaging Info: 1. MA 1L 包装 2. 客人指定箱唛排版 Remark: 出货前 Zuru QC 验货 | V25: Sophia Zhou | W25: 1.7 | X25: =I25*W25 -> 1370.2 | Y25: 84029-2.20 | Z25: 77515GQ1-S003 | AA25: 已入 | AE25: DG | AG25: =I25 -> 806 | AK25: =AG25 -> 806 | AO25: =AG25 -> 806 | AY25: =I25/13 -> 62 | BM25: =AG25+AH25+AI25 -> 806
A26: 45271 | B26: MEIJER | C26: 美国 | D26: 4500120905 | E26: 215358737 | F26: 4500120905-10 | G26: 77515GQ1-S003 | H26: DIY厨艺大师 | I26: 4017 | J26: 0 | K26: 13 | L26: =I26/K26 -> 309 | M26: 45321 | N26: 45317 | P26: pass | Q26: 2/19入仓 | R26: 45647 | S26: 无 | T26: 无 | U26: 日期码格式：ZURU INC(BVI) 标准格式 日期：按实际生产日期 Packaging Info: 1. MA 1L 包装 2. 客人指定箱唛排版 Remark: 出货前 Zuru QC 验货 | V26: Sophia Zhou | W26: 1.7 | X26: =I26*W26 -> 6828.9 | Y26: 84023-2.20 | Z26: 77515GQ1-S003 | AA26: 已入 | AE26: DG | AG26: =I26 -> 4017 | AK26: =AG26 -> 4017 | AO26: =AG26 -> 4017 | AY26: =I26/13 -> 309 | BM26: =AG26+AH26+AI26 -> 4017
A27: 45271 | B27: MEIJER | C27: 美国 | D27: 4500120910 | E27: 215358772 | F27: 4500120910-10 | G27: 77515GQ1-S003 | H27: DIY厨艺大师 | I27: 1612 | J27: 0 | K27: 13 | L27: =I27/K27 -> 124 | M27: 45321 | N27: 45317 | P27: pass | Q27: 2/19入仓 | R27: 45647 | S27: 无 | T27: 无 | U27: 日期码格式：ZURU INC(BVI) 标准格式 日期：按实际生产日期 Packaging Info: 1. MA 1L 包装 2. 客人指定箱唛排版 Remark: 出货前 Zuru QC 验货 | V27: Sophia Zhou | W27: 1.7 | X27: =I27*W27 -> 2740.4 | Y27: 84025-2.20 | Z27: 77515GQ1-S003 | AA27: 已入 | AE27: DG | AG27: =I27 -> 1612 | AK27: =AG27 -> 1612 | AO27: =AG27 -> 1612 | AY27: =I27/13 -> 124 | BM27: =AG27+AH27+AI27 -> 1612
A28: 45271 | B28: MEIJER | C28: 美国 | D28: 4500120915 | E28: 215358800 | F28: 4500120915-10 | G28: 77515GQ1-S003 | H28: DIY厨艺大师 | I28: 806 | J28: 0 | K28: 13 | L28: =I28/K28 -> 62 | M28: 45321 | N28: 45317 | P28: pass | Q28: 2/19入仓 | R28: 45647 | S28: 无 | T28: 无 | U28: 日期码格式：ZURU INC(BVI) 标准格式 日期：按实际生产日期 Packaging Info: 1. MA 1L 包装 2. 客人指定箱唛排版 Remark: 出货前 Zuru QC 验货 | V28: Sophia Zhou | W28: 1.7 | X28: =I28*W28 -> 1370.2 | Y28: 84027-2.20 | Z28: 77515GQ1-S003 | AA28: 已入 | AE28: DG | AG28: =I28 -> 806 | AK28: =AG28 -> 806 | AO28: =AG28 -> 806 | AY28: =I28/13 -> 62 | BM28: =AG28+AH28+AI28 -> 806
A29: 45271 | B29: MEIJER | C29: 美国 | D29: 4500120914 | E29: 215358783 | F29: 4500120914-10 | G29: 77515GQ1-S003 | H29: DIY厨艺大师 | I29: 806 | J29: 0 | K29: 13 | L29: =I29/K29 -> 62 | M29: 45321 | N29: 45317 | P29: pass | Q29: 2/19入仓 | R29: 45647 | S29: 无 | T29: 无 | U29: 日期码格式：ZURU INC(BVI) 标准格式 日期：按实际生产日期 Packaging Info: 1. MA 1L 包装 2. 客人指定箱唛排版 Remark: 出货前 Zuru QC 验货 | V29: Sophia Zhou | W29: 1.7 | X29: =I29*W29 -> 1370.2 | Y29: 84026-2.20 | Z29: 77515GQ1-S003 | AA29: 已入 | AE29: DG | AG29: =I29 -> 806 | AK29: =AG29 -> 806 | AO29: =AG29 -> 806 | AY29: =I29/13 -> 62 | BM29: =AG29+AH29+AI29 -> 806
A30: 45271 | B30: MEIJER | C30: 美国 | D30: 4500120920 | E30: 215358830 | F30: 4500120920-10 | G30: 77515GQ1-S003 | H30: DIY厨艺大师 | I30: 416 | J30: 0 | K30: 13 | L30: =I30/K30 -> 32 | M30: 45321 | N30: 45317 | P30: pass | Q30: 2/19入仓 | R30: 45647 | S30: 无 | T30: 无 | U30: 日期码格式：ZURU INC(BVI) 标准格式 日期：按实际生产日期 Packaging Info: 1. MA 1L 包装 2. 客人指定箱唛排版 Remark: 出货前 Zuru QC 验货 | V30: Sophia Zhou | W30: 1.7 | X30: =I30*W30 -> 707.2 | Y30: 84030-2.20 | Z30: 77515GQ1-S003 | AA30: 已入 | AE30: DG | AG30: =I30 -> 416 | AK30: =AG30 -> 416 | AO30: =AG30 -> 416 | AY30: =I30/13 -> 32 | BM30: =AG30+AH30+AI30 -> 416
A31: 45271 | B31: MEIJER | C31: 美国 | D31: 4500120909 | E31: 215358756 | F31: 4500120909-10 | G31: 77515GQ1-S003 | H31: DIY厨艺大师 | I31: 1989 | J31: 0 | K31: 13 | L31: =I31/K31 -> 153 | M31: 45321 | N31: 45317 | P31: pass | Q31: 2/19入仓 | R31: 45647 | S31: 无 | T31: 无 | U31: 日期码格式：ZURU INC(BVI) 标准格式 日期：按实际生产日期 Packaging Info: 1. MA 1L 包装 2. 客人指定箱唛排版 Remark: 出货前 Zuru QC 验货 | V31: Sophia Zhou | W31: 1.7 | X31: =I31*W31 -> 3381.3 | Y31: 84024-2.20 | Z31: 77515GQ1-S003 | AA31: 已入 | AE31: DG | AG31: =I31 -> 1989 | AK31: =AG31 -> 1989 | AO31: =AG31 -> 1989 | AY31: =I31/13 -> 153 | BM31: =AG31+AH31+AI31 -> 1989
A32: 45222 | B32: AMAZON FR | C32: 法国 | D32: 4500116508 | E32: 6MVKQO1E | F32: 4500116508-10 | G32: 77515-S001 | H32: DIY厨艺大师 | I32: 984 | J32: 0 | K32: 24 | L32: =I32/K32 -> 41 | M32: 45324 | N32: 45320 | P32: pass | Q32: 2/19入仓 | R32: 空白外箱（加印带Zuru字样的黑色色带，除了邮包盒直接做外箱的产品 | S32: 有 | T32: 12/5 订外箱贴纸 | U32: 日期码格式：ZURU INC(BVI) 标准格式 日期：按实际生产日期 Packaging Info: Amazon FR: 1. 77515: 24pcs/ctn, no inner; MA 3L A收缩膜包装+3张贴纸(含FR/DE/IT/ES警告语<(>&<)>IT sorting label 贴纸+FR sorting label贴纸+UPC#贴纸）; 2. 验货时间不迟于2024/2/5； Remark: "1.空白外箱（加印带Zuru字样的黑色色带，除了邮包盒直接做外箱的产品） + SSCC LABEL一张, 无箱唛. (SSCC LABEL贴在外箱正面的正中间，贴一面即可,贴纸离外箱边距必须至少3CM),SSCC贴纸由工厂直接跟勤得采购或者工厂自行采购，每一张SSCC Label都是唯一且 有不同流水及条码，且需要检查条码是否能正常扫描，如工厂不按此要求导致贴纸有任何问题产生的罚款将由工厂承担一切责任 。’MADE IN CHINA 外箱只印一正 一侧。 2. 出往UK的产品+包装务必打上UKCA logo ，否则客人会退货且当地会有罚款。 3.订单必须经过ZURU QC验货并且通过后方可出货。 4.法国订单要求包装不使用矿物油，请按要求提供以下其中一份文件再出货 ，产品出到法国被相关部门抽检出现包装不符合此要求的，供应商需要为此承担责任， 故此请严格把关 。 -油墨物质""由1 ~ 7个芳香环组成的MOAH""的包装检测报告，要求限值≤1.0%; 或 -包装材料清单，包括包装油墨或物质的信息 -油墨制造商的证书。 | V32: Crystal Chen | W32: 1.19 | X32: =I32*W32 -> 1170.96 | Y32: 84008-2.19 | Z32: 77515-S001-3L | AA32: 已入 | AE32: DG | AG32: =I32 -> 984 | AL32: =AG32 -> 984 | AO32: =AG32 -> 984 | BM32: =AG32+AH32+AI32 -> 984
A33: 45282 | B33: KMART AUSTRALIA LTD | C33: 澳大利亚 | D33: 4500121356 | E33: 19789620 | F33: 4500121356-70 | G33: 77515GQ1-S003 | H33: DIY厨艺大师 | I33: 5928 | J33: 0 | K33: 13 | L33: =I33/K33 -> 456 | M33: 45342 | N33: 45338 | P33: pass | Q33: 2/22入仓 | R33: 45655 | S33: 有 | T33: 45299 | U33: 日期码格式：ZURU INC(BVI) 标准格式 日期：按实际生产日期 Packaging Info: 3.77515GQ1:MA英语UPC版本包装（首选1LUPC，如果无1L可用多语含英语UPC版本）+防盗贴纸+箱唛+箱唛贴纸(1PCS/CTN),77515防盗贴纸请贴在顶部中央，大货生产前请返回1pcs确认.此外77515含纽扣电池，需要增加电池警告语贴纸，贴纸及其位置图后面提供 Remark: 1,请务必按时完货，验货并请按期送货入货代指定仓库，如果晚了导致船期Delay将会有罚金产生或者客户要求空运，所产生的罚金和空运费由工厂承担。 2.SSCC 外箱贴纸请同纸箱瓦楞纸方向（竖纹向）垂直，即外箱贴纸横着贴(注意条码不要被胶带粘住），贴1pc，贴1面正唛，封箱胶纸不能挡住贴纸内容。每pcs外 箱贴纸都是唯一的，不可重复粘贴，否则会有罚款产生。 3.外箱材质为ZURU标准； 4.此单需使用KMART封箱胶上下工字型封箱;从2019年6月开始，要用KMART 新版封箱胶带，此单要用"ANKO"封箱胶带 5.此单出口澳大利亚，请按相应的澳新标准生产； 6.产品和包装上生产批号的显示格式ZURU标准日期码格式 7. 77515GQ1-S003:3PCS AG13 Batteries(Included) | V33: Sara Wang | W33: 1.7 | X33: =I33*W33 -> 10077.6 | Y33: 84074-2.26 | Z33: 77515GQ1-S003 | AA33: 已入 | AE33: DG | AG33: =I33 -> 5928 | AK33: =AG33 -> 5928 | AO33: =AG33 -> 5928 | AY33: =I33/13 -> 456 | BM33: =AG33+AH33+AI33 -> 5928
A34: 45282 | B34: TARGET US | C34: 美国 | D34: 4500121729 | E34: 0086-1793817-0581 | F34: 4500121729-10 | G34: 77515GQ5-S002 | H34: DIY厨艺大师 | I34: 35007 | J34: 0 | K34: 21 | L34: =I34/K34 -> 1667 | M34: 45342 | N34: 45338 | P34: pass | Q34: 2/22 客上柜 | R34: 45296 | S34: 有 | T34: 1/11 寄出 | U34: 日期码格式：ZURU INC(BVI) 标准格式 日期：按实际生产日期 Packaging Info: 产品包装MA 1L, MA PDQ Remark: 1. 77515GQ5-S002-MINI BRAND-MASTER CHEF MINI BRANDS-SERIES 1,21pcs/Gravity PDQ, 21pcs/CTN,No Inner,STD Color Assortment (White drop) 2. 产品包装MA 1L, MA PDQ, 产品UPC 显示193052061034; 11 assortment have the same ratio； 3. 外箱正唛左上角位置粘贴条码箱贴纸，每箱只贴一张，由ZURU订购。来料贴纸上显示的客户DPCI# 086-02-9598， UPC显示10193052061031; 4. 产品和包装上印刷 tracking code信息，格式为ZURU常规格式; 5. 出货方式：货代自提。 | V34: Holly Zheng | W34: 1.75 | X34: =I34*W34 -> 61262.25 | Y34: 84048-2.22 | Z34: 77515GQ5-S002 | AA34: 已入 | AE34: DG | AG34: =I34 -> 35007 | AK34: =AG34 -> 35007 | AO34: =AG34 -> 35007 | AS34: =I34/21 -> 1667 | BM34: =AG34+AH34+AI34 -> 35007
A35: 45282 | B35: TARGET US | C35: 美国 | D35: 4500121728 | E35: 0086-1260120-0581 | F35: 4500121728-10 | G35: 77515GQ5-S002 | H35: DIY厨艺大师 | I35: 9996 | J35: 0 | K35: 21 | L35: =I35/K35 -> 476 | M35: 45342 | N35: 45338 | P35: pass | Q35: 2/24 客上柜 | R35: 45296 | S35: 有 | T35: 1/11 寄出 | U35: 日期码格式：ZURU INC(BVI) 标准格式 日期：按实际生产日期 Packaging Info: 产品包装MA 1L, MA PDQ Remark: 1. 77515GQ5-S002-MINI BRAND-MASTER CHEF MINI BRANDS-SERIES 1,21pcs/Gravity PDQ, 21pcs/CTN,No Inner,STD Color Assortment (White drop) 2. 产品包装MA 1L, MA PDQ, 产品UPC 显示193052061034; 11 assortment have the same ratio； 3. 外箱正唛左上角位置粘贴条码箱贴纸，每箱只贴一张，由ZURU订购。来料贴纸上显示的客户DPCI# 086-02-9598， UPC显示10193052061031; 4. 产品和包装上印刷 tracking code信息，格式为ZURU常规格式; 5. 出货方式：货代自提。 | V35: Holly Zheng | W35: 1.75 | X35: =I35*W35 -> 17493 | Y35: 84082-2.27 | Z35: 77515GQ5-S002 | AA35: 已入 | AE35: DG | AG35: =I35 -> 9996 | AK35: =AG35 -> 9996 | AO35: =AG35 -> 9996 | AS35: =I35/21 -> 476 | BM35: =AG35+AH35+AI35 -> 9996
A36: 45285 | B36: ZURU | C36: 库有 | D36: MPO02537 | G36: 77515GQ6-S001 | H36: DIY厨艺大师 | I36: 7200 | J36: 0 | K36: 36 | L36: =I36/K36 -> 200 | M36: 45345 | N36: 45341 | P36: pass | Q36: 2/29 送库有组装 | R36: 周转箱 | S36: 无 | T36: 45306 | U36: Remark: 1.77515GQ6: MA 1L收缩膜+1张防盗标贴纸贴在球的顶部（工厂自行订购此贴纸，此防盗贴纸产品款号:10111896/产品名称: 40R ECON YBL DE 8.2 1kr）+MA 1L PDQ+MA 23 L收藏指南/说明书+MA 5L ACCESSORY BAG; UPC#193052061034，请先检查条码是否正确再安排做货; 2. 产品及包装需要印UKCA图标，包装需要有ZURU UK LTD/ZURU France地址信息，QC同事请核查，如有问题与跟单确认 3.每座展示架放3个#77515GQ6 PDQ=12x3=36pcs，请务必按照每座展示架数量配好每个assortment的配比，方便组装厂直接组装展示架，配比跟MA标准款，如有不清楚 的请找客制部和跟单核查 4.外箱可以直接用周转箱或者其他，工厂自行安排即可，请在外箱上写好每箱装多少和总箱数方便点数； 5.送货到库有时请在送货单上备库有客供给TESCO UK PO#/#MSLD76组装展示架用 6.组装厂会安排最终验货，请准备好备品，验货后需要马上安排补货，届时请务必按时送货到库有厂 7.请确保交货数量准确，与收货方交收清楚，如收货方提出任何异常，请立即安排处理解决。 8.以上订单的任何生产要求与资料、要求备品数量等等，请以跟单发给贵司的邮件为准！ 9.子件工厂在交货到母件工厂时，将MPO（有注明45开头订单号）附在送货单上一起送货,或者送货单上备注45开头订单号。 | V36: Sheba | W36: 1.6 | X36: =I36*W36 -> 11520 | Y36: 86012R1-7.16 | Z36: 77515GQ6-S001 | AA36: 已入 | AE36: DG | AG36: =I36 -> 7200 | AK36: =AG36 -> 7200 | AO36: =AG36 -> 7200 | AW36: =I36/12 -> 600 | BM36: =AG36+AH36+AI36 -> 7200
A37: 45258 | B37: Smyths Toys HQ UC UK | C37: 英国 | D37: 4500119795 | E37: 4400364357 | F37: 4500119795-10 | G37: 77515GQ5-S001 | H37: DIY厨艺大师 | I37: 10038 | J37: 0 | K37: 42 | L37: =I37/K37 -> 239 | M37: 45349 | N37: 45345 | P37: pass | Q37: 2/28 出货 | R37: 45287 | S37: 无 | T37: 45299 | U37: 日期码格式：ZURU INC(BVI) 标准格式 日期：按实际生产日期 Packaging Info: 77515GQ5:MA 3L最新收缩膜+贴纸（德国CALLOUT 和荷兰警告语 ）+UPC贴纸（UPC#193052061034） +MA 5L收藏指南+MA3LPDQ Remark: 1）包装日期码按ZURU格式即可，请确保不迟于外箱日期码，可等于或者早于外箱日期码，必须为法定工作日，印刷前请先检查外箱日期码。 2）订单出英国，请注意检查产品及包装应带UKCA图标（14+产品除外），包装显示ZURU UK LTD/ZURU France地址信息，QC部门请查核，如有问题与跟单确认 3）订单必须经过ZURU QC验货并且通过后方可出货。 | V37: Sheba Ye | W37: 1.649 | X37: =I37*W37 -> 16552.662 | Y37: 84103-2.29 | Z37: 77515GQ5-S001-3L | AA37: 已入 | AE37: DG | AG37: =I37 -> 10038 | AL37: =I37 -> 10038 | AO37: =AG37 -> 10038 | AT37: =I37/21 -> 478 | BM37: =AG37+AH37+AI37 -> 10038
A38: 45258 | B38: Smyths Toys HQ UC UK | C38: 爱尔兰 | D38: 4500119796 | E38: 4400364358 | F38: 4500119796-10 | G38: 77515GQ5-S001 | H38: DIY厨艺大师 | I38: 3108 | J38: 0 | K38: 42 | L38: =I38/K38 -> 74 | M38: 45349 | N38: 45345 | P38: pass | Q38: 2/28 出货 | R38: 45287 | S38: 无 | T38: 45299 | U38: 日期码格式：ZURU INC(BVI) 标准格式 日期：按实际生产日期 Packaging Info: 77515GQ5:MA 3L最新收缩膜+贴纸（德国CALLOUT 和荷兰警告语 ）+UPC贴纸（UPC#193052061034） 全部贴纸翻#4500119795+MA 5L收藏指南+MA3LPDQ Remark: 1）包装日期码按ZURU格式即可，请确保不迟于外箱日期码，可等于或者早于外箱日期码，必须为法定工作日，印刷前请先检查外箱日期码。 2）订单出英国，请注意检查产品及包装应带UKCA图标（14+产品除外），包装显示ZURU UK LTD/ZURU France地址信息，QC部门请查核，如有问题与跟单确认 3）订单必须经过ZURU QC验货并且通过后方可出货。 | V38: Sheba Ye | W38: 1.649 | X38: =I38*W38 -> 5125.092 | Y38: 84104-2.29 | Z38: 77515GQ5-S001-3L | AA38: 已入 | AE38: DG | AG38: =I38 -> 3108 | AL38: =I38 -> 3108 | AO38: =AG38 -> 3108 | AT38: =I38/21 -> 148 | BM38: =AG38+AH38+AI38 -> 3108
A39: 45279 | B39: THE ENTERTAINER | C39: 英国 | D39: 4500121348 | E39: FB10932 | F39: 4500121348-30 | G39: 77515GQ5-S001 | H39: DIY厨艺大师 | I39: 14028 | J39: 0 | K39: 42 | L39: =I39/K39 -> 334 | M39: 45350 | N39: 45346 | P39: pass | Q39: 2/29 出货 | R39: 45651 | S39: 无 | T39: 45294 | U39: 日期码格式：ZURU INC(BVI) 标准格式 日期：按实际生产日期 Packaging Info: 77515GQ5-S001:MA-3L+5L warning 配套包装(必须为多语warning 版本，需要在西班牙售卖）+一张条码贴覆盖ZURU条码，另外产品内包装再加多一张9国语言电池说 明书（电池说明书和77489相同） ，即产品内含2张说明书 （ZURU标准说明书1张+9国语言电池说明书） 产品信息：11 assortment have the same ratio Remark: *包装日期码按ZURU格式即可，请确保不迟于外箱日期码，可等于或者早于外箱日期码，必须为法定工作日。 *订单必须经过ZURU QC验货并且通过后方可出货。 *MA版本按工厂现有最新库存即可，请注意检查产品及包装应带UKCA图标，包装显示ZURU UK LTD信息，QC同事请查核，如有问题与跟单确认。 *订单必须经过ZURU QC验货并且通过后方可出货。 *条码以订单为准，请做货前先核对再安排生产 。 *产品会同时在英国和西班牙市场售卖 ，注意按要求使用多语warning 包装版本。 | V39: Sherry Lu | W39: 1.649 | X39: =I39*W39 -> 23132.172 | Y39: 84125-3.2 | Z39: 77515GQ5-S001-3L | AA39: 已入 | AE39: DG | AG39: =I39 -> 14028 | AL39: =I39 -> 14028 | AO39: =AG39 -> 14028 | AT39: =I39/21 -> 668 | BM39: =AG39+AH39+AI39 -> 14028
A40: 45285 | B40: KMART AUSTRALIA LTD(NEW ZEALAND) | C40: 新西兰 | D40: 4500122071 | E40: 19631979 | F40: 4500122071-10 | G40: 77515GQ1-S003 | H40: DIY厨艺大师 | I40: 1495 | J40: 0 | K40: 13 | L40: =I40/K40 -> 115 | M40: 45348 | N40: 20024/2/22 | P40: AOD 漏说明书贴纸 | Q40: 3/1 交仓 | R40: 45294 | S40: 有 | T40: 45307 | U40: 日期码格式：ZURU INC(BVI) 标准格式 日期：按实际生产日期 Packaging Info: 77515GQ1:MA英语UPC版本包装（首选3LUPC，如果无1L可用多语含英语UPC版本）+防盗贴纸+箱唛+箱唛贴纸(1PCS/CTN).此外77515含纽扣电池，需要增加电池警告语 贴纸.防盗贴纸和警告语贴纸以及他们的位置图请跟回PO#4500121356 Remark: 1,请务必按时完货，验货并请按期送货入货代指定仓库，如果晚了导致船期Delay将会有罚金产生或者客户要求空运，所产生的罚金和空运费由工厂承担。 2.SSCC 外箱贴纸请同纸箱瓦楞纸方向（竖纹向）垂直，即外箱贴纸横着贴(注意条码不要被胶带粘住），贴1pc，贴1面正唛，封箱胶纸不能挡住贴纸内容。每pcs外 箱贴纸都是唯一的，不可重复粘贴，否则会有罚款产生。 3.外箱材质为ZURU标准； 4.此单需使用KMART封箱胶上下工字型封箱;从2019年6月开始，要用KMART 新版封箱胶带，此单要用"ANKO"封箱胶带 5.此单出口新西兰，请按相应的澳新标准生产； 6.产品和包装上生产批号的显示格式ZURU标准日期码格式 7.77515GQ1-S003:3PCS AG13 Batteries(Included) | V40: Sara Wang | W40: 1.7 | X40: =I40*W40 -> 2541.5 | Y40: 84124-3.2 | Z40: 77515GQ1-S003-3L | AA40: 已入 | AE40: DG | AG40: =I40 -> 1495 | AL40: =AG40 -> 1495 | AO40: =AG40 -> 1495 | AY40: =I40/13 -> 115 | BM40: =AG40+AH40+AI40 -> 1495
A41: 45285 | B41: KMART AUSTRALIA LTD | C41: 澳大利亚 | D41: 4500122070 | E41: 19631975 | F41: 4500122070-10 | G41: 77515GQ1-S003 | H41: DIY厨艺大师 | I41: 14989 | J41: 0 | K41: 13 | L41: =I41/K41 -> 1153 | M41: 45348 | N41: 20024/2/22 | P41: AOD 漏说明书贴纸 | Q41: 3/1 交仓 | R41: 45294 | S41: 有 | T41: 45307 | U41: 日期码格式：ZURU INC(BVI) 标准格式 日期：按实际生产日期 Packaging Info: 77515GQ1:MA英语UPC版本包装（首选1LUPC，如果无1L可用多语含英语UPC版本）+防盗贴纸+箱唛+箱唛贴纸(1PCS/CTN).此外77515含纽扣电池，需要增加电池警告语 贴纸.防盗贴纸和警告语贴纸以及他们的位置图请跟回PO#4500121356 Remark: 1,请务必按时完货，验货并请按期送货入货代指定仓库，如果晚了导致船期Delay将会有罚金产生或者客户要求空运，所产生的罚金和空运费由工厂承担。 2.SSCC 外箱贴纸请同纸箱瓦楞纸方向（竖纹向）垂直，即外箱贴纸横着贴(注意条码不要被胶带粘住），贴1pc，贴1面正唛，封箱胶纸不能挡住贴纸内容。每pcs外 箱贴纸都是唯一的，不可重复粘贴，否则会有罚款产生。 3.外箱材质为ZURU标准； 4.此单需使用KMART封箱胶上下工字型封箱;从2019年6月开始，要用KMART 新版封箱胶带，此单要用"ANKO"封箱胶带 5.此单出口澳大利亚，请按相应的澳新标准生产； 6.产品和包装上生产批号的显示格式ZURU标准日期码格式 7.77515GQ1-S003:3PCS AG13 Batteries(Included) | V41: Sara Wang | W41: 1.7 | X41: =I41*W41 -> 25481.3 | Y41: 84123-3.2 | Z41: 77515GQ1-S003 | AA41: 已入 | AE41: DG | AG41: =I41 -> 14989 | AK41: =AG41 -> 14989 | AO41: =AG41 -> 14989 | AY41: =I41/13 -> 1153 | BM41: =AG41+AH41+AI41 -> 14989
A42: 45280 | B42: ASDA STORES LTD | C42: 英国 | D42: 4500121807 | E42: 2950863982 | F42: 4500121807-10 | G42: 77515GQ6-S002 | H42: DIY厨艺大师 | I42: 3840 | J42: 0 | K42: 12 | L42: =I42/K42 -> 320 | M42: 45350 | N42: 45346 | P42: pass | Q42: 3/5 出货 | R42: 45295 | S42: 有 | T42: 45295 | U42: 日期码格式：ZURU INC(BVI) 标准格式 日期：按实际生产日期 Packaging Info: 1. 77515: MA 1L收缩膜/PDQ+MA 23L收藏指南/说明书+MA 5L ACCESSORY BAG UPC#193052061034，请先检查条码是否正确再安排做货 11 assortment have the same ratio Remark: 1. 产品及包装需要印UKCA图标，包装需要有ZURU UK LTD/ZURU France地址信息，QC同事请核查，如有问题与跟单确认 2.请在2/29按时提供客人格式自检报告给我们发给客人审批了才能出货 3. 产品/包装/外箱都需要打ZURU格式日期码，日期必须为法定工作日。 | V42: Sheba Ye | W42: 1.53 | X42: =I42*W42 -> 5875.2 | Y42: 84397-3.2 | Z42: 77515GQ6-S002-3L | AA42: 已入 | AE42: DG | AG42: =I42 -> 3840 | AK42: =I42 -> 3840 | AO42: =AG42 -> 3840 | AW42: =I42/12 -> 320 | BM42: =AG42+AH42+AI42 -> 3840
A43: 45288 | B43: ZURU France | C43: 法国 | D43: 4500122374 | E43: 5200003307 | F43: 4500122374-20 | G43: 77515GQ5-S002-MTS | H43: DIY厨艺大师 | I43: 3990 | J43: 0 | K43: 21 | L43: =I43/K43 -> 190 | M43: 45350 | N43: 45346 | P43: pass | Q43: 3/1 出货散货 | R43: 45654 | S43: 无 | T43: 45296 | U43: 日期码格式：ZURU INC(BVI) 标准格式 日期：按实际生产日期 Packaging Info: 1.包装： #77515GQ5 ：MA 3L PDQ/ MA 5L收藏指南/MA 23L说明书/MA 3L EAN版本收缩膜+警告语贴纸+警告语贴纸（共两张贴纸 Remark: 2. 订单出欧洲国家（法国/西班牙），所有产品不能含有闪粉/微塑料！ 3.订单出法国，所有出口法国的产品, 法规规定禁止在包装和共公众用的印刷品中使用矿物油中含有的物质, 包装印刷油墨中含有的MOAH/MOSH的质量浓度不能超过1 %, 否则出货到法国被抽检出现问题, 供应商需要对此负责; 4. 产品信息： #77515GQ5：3PCS AG13 Batteries(Included) | V43: SD05 | W43: 1.8 | X43: =W43*L43 -> 342 | Y43: 84398-3.29 | Z43: 77515GQ5-S002-3L | AA43: 已入 | AE43: DG | AG43: =I43 -> 3990 | AL43: =I43 -> 3990 | AO43: =AG43 -> 3990 | AT43: =I43/21 -> 190 | BM43: =AG43+AH43+AI43 -> 3990
A44: 45288 | B44: ZURU France | C44: 法国 | D44: 4500122374 | E44: 5200003307 | F44: 4500122374-30 | G44: 77515GQ6-S002-MTS | H44: DIY厨艺大师 | I44: 3996 | J44: 0 | K44: 12 | L44: =I44/K44 -> 333 | M44: 45350 | N44: 45346 | P44: pass | Q44: 3/1 出货散货 | R44: 45654 | S44: 无 | T44: 45296 | U44: 日期码格式：ZURU INC(BVI) 标准格式 日期：按实际生产日期 Packaging Info: 1.包装： #77515GQ6：MA 3L PDQ/ MA 5L收藏指南/MA 23L说明书/MA 3L EAN版本收缩膜+警告语贴纸+警告语贴纸（共两张贴纸（共两张贴纸 Remark: 2. 订单出欧洲国家（法国/西班牙），所有产品不能含有闪粉/微塑料！ 3.订单出法国，所有出口法国的产品, 法规规定禁止在包装和共公众用的印刷品中使用矿物油中含有的物质, 包装印刷油墨中含有的MOAH/MOSH的质量浓度不能超过1 %, 否则出货到法国被抽检出现问题, 供应商需要对此负责; 4. 产品信息： #77515GQ6：3PCS AG13 Batteries(Included) | V44: SD05 | W44: 1.53 | X44: =W44*L44 -> 509.49 | Y44: 84398-3.29 | Z44: 77515GQ6-S002-3L | AA44: 已入 | AE44: DG | AG44: =I44 -> 3996 | AL44: =AG44 -> 3996 | AO44: =AG44 -> 3996 | AX44: =I44/12 -> 333 | BM44: =AG44+AH44+AI44 -> 3996
A45: 45293 | B45: AMAZON.COM.DEDC,LLC | C45: 美国 | D45: 4500122521 | E45: 7P9499KK | F45: 4500122521-10 | G45: 77515-S001 | H45: DIY厨艺大师 | I45: 2088 | J45: 0 | K45: 24 | L45: =I45/K45 -> 87 | M45: 45355 | N45: 45351 | P45: pass | Q45: 3/4 散货交仓 | R45: 外箱正面印ZURU Logo+SSCC LABEL（客供贴纸), 侧面印item# | S45: 有 | T45: 45314 | U45: 日期码格式：ZURU INC(BVI) 标准格式 日期：按实际生产日期 Packaging Info: 77515：MA 1L。 加防伪贴纸， 跟单提供。 **请严格按此交期安排生产，此单不能延期** Remark: 1.Amazon FOB订单，出口US。外箱最长边不能超过25" （超过了，case pack只能为1），不符合要求的大货，一律不接受。 2. 外箱正面印ZURU Logo+SSCC LABEL（客供贴纸), 侧面印item#（订单上显示的SKU#)+carton size(以工厂实际尺寸为准,单位: inch) +MADE IN CHINA,日期使用Z URU 标准版本 SSCC Label 显示的是客人自己的item#, SSCC Label 贴在外箱正面的正中间，贴一面即可，跟单订购，贴纸离外箱距必须至少3cm, 每一张SSCC labe l 都是唯一且有不同流水及条码的，没有损耗，绝对不可贴错 ，否则贴错或损坏一张会导致全部都错，千万要注意. SSCC 贴纸务必要在正中间(可以覆盖Logo <(>&<)> 箱唛), 否则会影响到仓库扫描识别 3.日期码使用ZURU标准版本 4.按照客户PO# 装柜/箱号顺序装柜，跟单会提前给到装柜计划。请大货生产/仓库存放时留意，以便装柜时不混乱（装错/装漏/找不到货号） | V45: Agnes Zheng | W45: 1.19 | X45: =I45*W45 -> 2484.72 | Y45: 84139-3.4 | Z45: 77515-S001 | AA45: 已入 | AE45: DG | AG45: =I45 -> 2088 | AK45: =AG45 -> 2088 | AO45: =AG45 -> 2088 | BM45: =AG45+AH45+AI45 -> 2088
A46: 45293 | B46: AMAZON.COM.DEDC,LLC | C46: 美国 | D46: 4500122521 | E46: 71NFZP6A | F46: 4500122521-20 | G46: 77515-S001 | H46: DIY厨艺大师 | I46: 2016 | J46: 0 | K46: 24 | L46: =I46/K46 -> 84 | M46: 45355 | N46: 45351 | P46: pass | Q46: 3/4 散货交仓 | R46: 外箱正面印ZURU Logo+SSCC LABEL（客供贴纸), 侧面印item# | S46: 有 | T46: 45314 | U46: 日期码格式：ZURU INC(BVI) 标准格式 日期：按实际生产日期 Packaging Info: 77515：MA 1L。 加防伪贴纸， 跟单提供。 **请严格按此交期安排生产，此单不能延期** Remark: 1.Amazon FOB订单，出口US。外箱最长边不能超过25" （超过了，case pack只能为1），不符合要求的大货，一律不接受。 2. 外箱正面印ZURU Logo+SSCC LABEL（客供贴纸), 侧面印item#（订单上显示的SKU#)+carton size(以工厂实际尺寸为准,单位: inch) +MADE IN CHINA,日期使用Z URU 标准版本 SSCC Label 显示的是客人自己的item#, SSCC Label 贴在外箱正面的正中间，贴一面即可，跟单订购，贴纸离外箱距必须至少3cm, 每一张SSCC labe l 都是唯一且有不同流水及条码的，没有损耗，绝对不可贴错 ，否则贴错或损坏一张会导致全部都错，千万要注意. SSCC 贴纸务必要在正中间(可以覆盖Logo <(>&<)> 箱唛), 否则会影响到仓库扫描识别 3.日期码使用ZURU标准版本 4.按照客户PO# 装柜/箱号顺序装柜，跟单会提前给到装柜计划。请大货生产/仓库存放时留意，以便装柜时不混乱（装错/装漏/找不到货号） | V46: Agnes Zheng | W46: 1.19 | X46: =I46*W46 -> 2399.04 | Y46: 84139-3.4 | Z46: 77515-S001 | AA46: 已入 | AE46: DG | AG46: =I46 -> 2016 | AK46: =AG46 -> 2016 | AO46: =AG46 -> 2016 | BM46: =AG46+AH46+AI46 -> 2016
A47: 45293 | B47: AMAZON.COM.DEDC,LLC | C47: 美国 | D47: 4500122521 | E47: 6HU3LR5F | F47: 4500122521-30 | G47: 77515-S001 | H47: DIY厨艺大师 | I47: 1344 | J47: 0 | K47: 24 | L47: =I47/K47 -> 56 | M47: 45355 | N47: 45351 | P47: pass | Q47: 3/4 散货交仓 | R47: 外箱正面印ZURU Logo+SSCC LABEL（客供贴纸), 侧面印item# | S47: 有 | T47: 45314 | U47: 日期码格式：ZURU INC(BVI) 标准格式 日期：按实际生产日期 Packaging Info: 77515：MA 1L。 加防伪贴纸， 跟单提供。 **请严格按此交期安排生产，此单不能延期** Remark: 1.Amazon FOB订单，出口US。外箱最长边不能超过25" （超过了，case pack只能为1），不符合要求的大货，一律不接受。 2. 外箱正面印ZURU Logo+SSCC LABEL（客供贴纸), 侧面印item#（订单上显示的SKU#)+carton size(以工厂实际尺寸为准,单位: inch) +MADE IN CHINA,日期使用Z URU 标准版本 SSCC Label 显示的是客人自己的item#, SSCC Label 贴在外箱正面的正中间，贴一面即可，跟单订购，贴纸离外箱距必须至少3cm, 每一张SSCC labe l 都是唯一且有不同流水及条码的，没有损耗，绝对不可贴错 ，否则贴错或损坏一张会导致全部都错，千万要注意. SSCC 贴纸务必要在正中间(可以覆盖Logo <(>&<)> 箱唛), 否则会影响到仓库扫描识别 3.日期码使用ZURU标准版本 4.按照客户PO# 装柜/箱号顺序装柜，跟单会提前给到装柜计划。请大货生产/仓库存放时留意，以便装柜时不混乱（装错/装漏/找不到货号） | V47: Agnes Zheng | W47: 1.19 | X47: =I47*W47 -> 1599.36 | Y47: 84139-3.4 | Z47: 77515-S001 | AA47: 已入 | AE47: DG | AG47: =I47 -> 1344 | AK47: =AG47 -> 1344 | AO47: =AG47 -> 1344 | BM47: =AG47+AH47+AI47 -> 1344
A48: 45293 | B48: AMAZON.COM.DEDC,LLC | C48: 美国 | D48: 4500122521 | E48: 55MVP1TX | F48: 4500122521-40 | G48: 77515-S001 | H48: DIY厨艺大师 | I48: 888 | J48: 0 | K48: 24 | L48: =I48/K48 -> 37 | M48: 45355 | N48: 45351 | P48: pass | Q48: 3/4 散货交仓 | R48: 外箱正面印ZURU Logo+SSCC LABEL（客供贴纸), 侧面印item# | S48: 有 | T48: 45314 | U48: 日期码格式：ZURU INC(BVI) 标准格式 日期：按实际生产日期 Packaging Info: 77515：MA 1L。 加防伪贴纸， 跟单提供。 **请严格按此交期安排生产，此单不能延期** Remark: 1.Amazon FOB订单，出口US。外箱最长边不能超过25" （超过了，case pack只能为1），不符合要求的大货，一律不接受。 2. 外箱正面印ZURU Logo+SSCC LABEL（客供贴纸), 侧面印item#（订单上显示的SKU#)+carton size(以工厂实际尺寸为准,单位: inch) +MADE IN CHINA,日期使用Z URU 标准版本 SSCC Label 显示的是客人自己的item#, SSCC Label 贴在外箱正面的正中间，贴一面即可，跟单订购，贴纸离外箱距必须至少3cm, 每一张SSCC labe l 都是唯一且有不同流水及条码的，没有损耗，绝对不可贴错 ，否则贴错或损坏一张会导致全部都错，千万要注意. SSCC 贴纸务必要在正中间(可以覆盖Logo <(>&<)> 箱唛), 否则会影响到仓库扫描识别 3.日期码使用ZURU标准版本 4.按照客户PO# 装柜/箱号顺序装柜，跟单会提前给到装柜计划。请大货生产/仓库存放时留意，以便装柜时不混乱（装错/装漏/找不到货号） | V48: Agnes Zheng | W48: 1.19 | X48: =I48*W48 -> 1056.72 | Y48: 84139-3.4 | Z48: 77515-S001 | AA48: 已入 | AE48: DG | AG48: =I48 -> 888 | AK48: =AG48 -> 888 | AO48: =AG48 -> 888 | BM48: =AG48+AH48+AI48 -> 888
A49: 45293 | B49: AMAZON.COM.DEDC,LLC | C49: 美国 | D49: 4500122521 | E49: 1TN8Q2LN | F49: 4500122521-50 | G49: 77515-S001 | H49: DIY厨艺大师 | I49: 3120 | J49: 0 | K49: 24 | L49: =I49/K49 -> 130 | M49: 45355 | N49: 45351 | P49: pass | Q49: 3/4 散货交仓 | R49: 外箱正面印ZURU Logo+SSCC LABEL（客供贴纸), 侧面印item# | S49: 有 | T49: 45314 | U49: 日期码格式：ZURU INC(BVI) 标准格式 日期：按实际生产日期 Packaging Info: 77515：MA 1L。 加防伪贴纸， 跟单提供。 **请严格按此交期安排生产，此单不能延期** Remark: 1.Amazon FOB订单，出口US。外箱最长边不能超过25" （超过了，case pack只能为1），不符合要求的大货，一律不接受。 2. 外箱正面印ZURU Logo+SSCC LABEL（客供贴纸), 侧面印item#（订单上显示的SKU#)+carton size(以工厂实际尺寸为准,单位: inch) +MADE IN CHINA,日期使用Z URU 标准版本 SSCC Label 显示的是客人自己的item#, SSCC Label 贴在外箱正面的正中间，贴一面即可，跟单订购，贴纸离外箱距必须至少3cm, 每一张SSCC labe l 都是唯一且有不同流水及条码的，没有损耗，绝对不可贴错 ，否则贴错或损坏一张会导致全部都错，千万要注意. SSCC 贴纸务必要在正中间(可以覆盖Logo <(>&<)> 箱唛), 否则会影响到仓库扫描识别 3.日期码使用ZURU标准版本 4.按照客户PO# 装柜/箱号顺序装柜，跟单会提前给到装柜计划。请大货生产/仓库存放时留意，以便装柜时不混乱（装错/装漏/找不到货号） | V49: Agnes Zheng | W49: 1.19 | X49: =I49*W49 -> 3712.8 | Y49: 84139-3.4 | Z49: 77515-S001 | AA49: 已入 | AE49: DG | AG49: =I49 -> 3120 | AK49: =AG49 -> 3120 | AO49: =AG49 -> 3120 | BM49: =AG49+AH49+AI49 -> 3120
A50: 45293 | B50: AMAZON.COM.DEDC,LLC | C50: 美国 | D50: 4500122521 | E50: 1HGW8XSS | F50: 4500122521-60 | G50: 77515-S001 | H50: DIY厨艺大师 | I50: 6168 | J50: 0 | K50: 24 | L50: =I50/K50 -> 257 | M50: 45355 | N50: 45351 | P50: pass | Q50: 3/4 散货交仓 | R50: 外箱正面印ZURU Logo+SSCC LABEL（客供贴纸), 侧面印item# | S50: 有 | T50: 45314 | U50: 日期码格式：ZURU INC(BVI) 标准格式 日期：按实际生产日期 Packaging Info: 77515：MA 1L。 加防伪贴纸， 跟单提供。 **请严格按此交期安排生产，此单不能延期** Remark: 1.Amazon FOB订单，出口US。外箱最长边不能超过25" （超过了，case pack只能为1），不符合要求的大货，一律不接受。 2. 外箱正面印ZURU Logo+SSCC LABEL（客供贴纸), 侧面印item#（订单上显示的SKU#)+carton size(以工厂实际尺寸为准,单位: inch) +MADE IN CHINA,日期使用Z URU 标准版本 SSCC Label 显示的是客人自己的item#, SSCC Label 贴在外箱正面的正中间，贴一面即可，跟单订购，贴纸离外箱距必须至少3cm, 每一张SSCC labe l 都是唯一且有不同流水及条码的，没有损耗，绝对不可贴错 ，否则贴错或损坏一张会导致全部都错，千万要注意. SSCC 贴纸务必要在正中间(可以覆盖Logo <(>&<)> 箱唛), 否则会影响到仓库扫描识别 3.日期码使用ZURU标准版本 4.按照客户PO# 装柜/箱号顺序装柜，跟单会提前给到装柜计划。请大货生产/仓库存放时留意，以便装柜时不混乱（装错/装漏/找不到货号） | V50: Agnes Zheng | W50: 1.19 | X50: =I50*W50 -> 7339.92 | Y50: 84139-3.4 | Z50: 77515-S001 | AA50: 已入 | AE50: DG | AG50: =I50 -> 6168 | AK50: =AG50 -> 6168 | AO50: =AG50 -> 6168 | BM50: =AG50+AH50+AI50 -> 6168
A51: 45293 | B51: AMAZON.COM.DEDC,LLC | C51: 美国 | D51: 4500122521 | E51: 19R3OPWH | F51: 4500122521-70 | G51: 77515-S001 | H51: DIY厨艺大师 | I51: 1344 | J51: 0 | K51: 24 | L51: =I51/K51 -> 56 | M51: 45355 | N51: 45351 | P51: pass | Q51: 3/4 散货交仓 | R51: 外箱正面印ZURU Logo+SSCC LABEL（客供贴纸), 侧面印item# | S51: 有 | T51: 45314 | U51: 日期码格式：ZURU INC(BVI) 标准格式 日期：按实际生产日期 Packaging Info: 77515：MA 1L。 加防伪贴纸， 跟单提供。 **请严格按此交期安排生产，此单不能延期** Remark: 1.Amazon FOB订单，出口US。外箱最长边不能超过25" （超过了，case pack只能为1），不符合要求的大货，一律不接受。 2. 外箱正面印ZURU Logo+SSCC LABEL（客供贴纸), 侧面印item#（订单上显示的SKU#)+carton size(以工厂实际尺寸为准,单位: inch) +MADE IN CHINA,日期使用Z URU 标准版本 SSCC Label 显示的是客人自己的item#, SSCC Label 贴在外箱正面的正中间，贴一面即可，跟单订购，贴纸离外箱距必须至少3cm, 每一张SSCC labe l 都是唯一且有不同流水及条码的，没有损耗，绝对不可贴错 ，否则贴错或损坏一张会导致全部都错，千万要注意. SSCC 贴纸务必要在正中间(可以覆盖Logo <(>&<)> 箱唛), 否则会影响到仓库扫描识别 3.日期码使用ZURU标准版本 4.按照客户PO# 装柜/箱号顺序装柜，跟单会提前给到装柜计划。请大货生产/仓库存放时留意，以便装柜时不混乱（装错/装漏/找不到货号） | V51: Agnes Zheng | W51: 1.19 | X51: =I51*W51 -> 1599.36 | Y51: 84139-3.4 | Z51: 77515-S001 | AA51: 已入 | AE51: DG | AG51: =I51 -> 1344 | AK51: =AG51 -> 1344 | AO51: =AG51 -> 1344 | BM51: =AG51+AH51+AI51 -> 1344
A52: 45271 | B52: CVS PHARMACY INC | C52: 美国 | D52: 4500119117 | E52: 2510756 | F52: 4500119117-33 | G52: 77515GQ6-S002 | H52: DIY厨艺大师 | I52: 5172 | J52: 0 | K52: 12 | L52: =I52/K52 -> 431 | M52: 45350 | N52: 45346 | O52: 3/1 抽版 | P52: pass | Q52: 3/27 出货 | R52: 45637 | S52: 无 | T52: 45637 | U52: 日期码格式：ZURU INC(BVI) 标准格式 日期：按实际生产日期 Packaging Info: 3款 - ZURU标准MA (优先1L) UPC版本包装, 出口美国 #77515GQ6 - ZURU标准MA (优先1L) UPC版本包装+价格贴纸（贴纸AW由跟单提供,工厂采购）, 出口美国 Remark: 1. 此单要求2024/2/28日完成以下数量供UL实验室做第三方抽板测试,剩下的数量要求2024/3/19全部完成。 #77515GQ6:5172pcs(431ctns) 3. 日期码请按ZURU标准版执行即可。 4. 样板准备：每款大概测试样要12套，大货样3套,具体要求以最终邮件通知为准. 5. ZURU QC 验货。 | V52: Eleven Zhang | W52: 1.53 | X52: =I52*W52 -> 7913.16 | Y52: 84399-3.29 | Z52: 77515GQ6-S002 | AA52: 已入 | AE52: DG | AG52: =I52 -> 5172 | AK52: =AG52 -> 5172 | AO52: =AG52 -> 5172 | AW52: =I52/12 -> 431 | BM52: =AG52+AH52+AI52 -> 5172
A53: 45280 | B53: Distribuidora Liverpool S.A de C.V. | C53: 墨西哥 | D53: 4500121718 | E53: 61821817 | F53: 4500121718-20 | G53: 77515GQ2-S001 | H53: DIY厨艺大师 | I53: 5000 | J53: 0 | K53: 50 | L53: =I53/K53 -> 100 | M53: 45355 | N53: 45351 | P53: pass | Q53: 3/7 出货 | R53: 45293 | S53: 无 | T53: 45323 | U53: 日期码格式：ZURU INC(BVI) 标准格式 日期：按实际生产日期 Packaging Info: 2. 77515GQ2：MA 3L UPC包装+MA 3L PDQ+MA 5L收藏指南+MA 23L Warning instruction+进口商贴纸+价标贴纸+保证书+箱唛 Remark: 2. 77515GQ2：11 assortment have the same ratio；3PCS AG13 Batteries(Include) 3. 此单价格贴纸（ZURU定购). 4. 此单有第三方监柜，每款多备一套备品随货送出 | V53: Ever Li | W53: 1.5806 | X53: =W53*I53 -> 7903 | Y53: 84190-3.9 | Z53: 77515GQ2-S001-3L | AA53: 已入 | AE53: DG | AG53: =I53 -> 5000 | AL53: =I53 -> 5000 | AO53: =I53 -> 5000 | BB53: =I53/25 -> 200 | BM53: =AG53+AH53+AI53 -> 5000
A54: 45288 | B54: KMART AUSTRALIA LTD | C54: 澳大利亚 | D54: 4500122379 | E54: 19631973 | F54: 4500122379-10 | G54: 77515GQ1-S003 | H54: DIY厨艺大师 | I54: 1391 | J54: 0 | K54: 13 | L54: =I54/K54 -> 107 | M54: 45355 | N54: 45351 | P54: pass | Q54: 3/8 交仓 | R54: 45302 | S54: 有 | T54: 45314 | U54: 日期码格式：ZURU INC(BVI) 标准格式 日期：按实际生产日期 Packaging Info: 77515GQ1:MA英语UPC版本包装（首选1LUPC，如果无1L可用多语含英语UPC版本）+防盗贴纸+箱唛+箱唛贴纸(1PCS/CTN).此外77515含纽扣电池，需要增加电池警告语 贴纸.防盗贴纸和警告语贴纸以及他们的位置图请跟回PO#4500121356 Remark: 1,请务必按时完货，验货并请按期送货入货代指定仓库，如果晚了导致船期Delay将会有罚金产生或者客户要求空运，所产生的罚金和空运费由工厂承担。 2.SSCC 外箱贴纸请同纸箱瓦楞纸方向（竖纹向）垂直，即外箱贴纸横着贴(注意条码不要被胶带粘住），贴1pc，贴1面正唛，封箱胶纸不能挡住贴纸内容。每pcs外 箱贴纸都是唯一的，不可重复粘贴，否则会有罚款产生。 3.外箱材质为ZURU标准； 4.此单需使用KMART封箱胶上下工字型封箱;从2019年6月开始，要用KMART 新版封箱胶带，此单要用"ANKO"封箱胶带 5.此单出口澳大利亚，请按相应的澳新标准生产； 6.产品和包装上生产批号的显示格式ZURU标准日期码格式 7.77515GQ1-S003:3PCS AG13 Batteries(Included) | V54: Sara Wang | W54: 1.7 | X54: =I54*W54 -> 2364.7 | Y54: 84191-3.9 | Z54: 77515GQ1-S003 | AA54: 已入 | AE54: DG | AG54: =I54 -> 1391 | AK54: =AG54 -> 1391 | AO54: =AG54 -> 1391 | AY54: =I54/13 -> 107 | BM54: =AG54+AH54+AI54 -> 1391
A55: 45288 | B55: KMART AUSTRALIA LTD(NEW ZEALAND) | C55: 新西兰 | D55: 4500122380 | E55: 19631978 | F55: 4500122380-10 | G55: 77515GQ1-S003 | H55: DIY厨艺大师 | I55: 130 | J55: 0 | K55: 13 | L55: =I55/K55 -> 10 | M55: 45355 | N55: 45351 | P55: pass | Q55: 3/8 交仓 | R55: 45302 | S55: 有 | T55: 45314 | U55: 日期码格式：ZURU INC(BVI) 标准格式 日期：按实际生产日期 Packaging Info: 77515GQ1:MA英语UPC版本包装（首选3LUPC，如果无1L可用多语含英语UPC版本）+防盗贴纸+箱唛+箱唛贴纸(1PCS/CTN).此外77515含纽扣电池，需要增加电池警告语 贴纸.防盗贴纸和警告语贴纸以及他们的位置图请跟回PO#4500121356 Remark: 1,请务必按时完货，验货并请按期送货入货代指定仓库，如果晚了导致船期Delay将会有罚金产生或者客户要求空运，所产生的罚金和空运费由工厂承担。 2.SSCC 外箱贴纸请同纸箱瓦楞纸方向（竖纹向）垂直，即外箱贴纸横着贴(注意条码不要被胶带粘住），贴1pc，贴1面正唛，封箱胶纸不能挡住贴纸内容。每pcs外 箱贴纸都是唯一的，不可重复粘贴，否则会有罚款产生。 3.外箱材质为ZURU标准； 4.此单需使用KMART封箱胶上下工字型封箱;从2019年6月开始，要用KMART 新版封箱胶带，此单要用"ANKO"封箱胶带 5.此单出口新西兰，请按相应的澳新标准生产； 6.产品和包装上生产批号的显示格式ZURU标准日期码格式 7.77515GQ1-S003:3PCS AG13 Batteries(Included) | V55: Sara Wang | W55: 1.7 | X55: =I55*W55 -> 221 | Y55: 84192-3.9 | Z55: 77515GQ1-S003-3L | AA55: 已入 | AE55: DG | AG55: =I55 -> 130 | AL55: =AG55 -> 130 | AO55: =AG55 -> 130 | AY55: =I55/13 -> 10 | BM55: =AG55+AH55+AI55 -> 130
A56: 45299 | B56: TARGET US | C56: 美国 | D56: 4500122727 | E56: 0086-3839033-0581 | F56: 4500122727-10 | G56: 77515GQ5-S002 | H56: DIY厨艺大师 | I56: 9996 | J56: 0 | K56: 21 | L56: =I56/K56 -> 476 | M56: 45356 | N56: 45352 | P56: pass | Q56: 3/11 客上柜 | R56: 45303 | S56: 有 | T56: 45316 | U56: 日期码格式：ZURU INC(BVI) 标准格式 日期：按实际生产日期 Packaging Info: 产品包装MA 1L, MA PDQ Remark: 1. 77515GQ5-S002-MINI BRAND-MASTER CHEF MINI BRANDS-SERIES 1,21pcs/Gravity PDQ, 21pcs/CTN,No Inner,STD Color Assortment (White drop) 2. 产品包装MA 1L, MA PDQ, 产品UPC 显示193052061034; 11 assortment have the same ratio； 3. 外箱正唛左上角位置粘贴条码箱贴纸，每箱只贴一张，由ZURU订购。来料贴纸上显示的客户DPCI# 086-02-9598， UPC显示10193052061031; 4. 产品和包装上印刷 tracking code信息，格式为ZURU常规格式; 5. 出货方式：货代自提。 | V56: Holly Zheng | W56: 1.75 | X56: =I56*W56 -> 17493 | Y56: 84207-3.11 | Z56: 77515GQ5-S002 | AA56: 已入 | AE56: DG | AG56: =I56 -> 9996 | AK56: =AG56 -> 9996 | AO56: =AG56 -> 9996 | AS56: =I56/21 -> 476 | BM56: =AG56+AH56+AI56 -> 9996
A57: 45295 | B57: AMAZON.COM.DEDC,LLC | C57: 美国 | D57: 4500124758 | E57: 22Q1ZMLV | F57: 4500122667-10 | G57: 77515-S001-MTS | H57: DIY厨艺大师 | I57: 624 | J57: 0 | K57: 24 | L57: =I57/K57 -> 26 | M57: 45359 | N57: 45355 | P57: pass | Q57: 3/19 出货 | R57: 外箱正面印ZURU Logo+SSCC LABEL（客供贴纸), 侧面印item# | S57: 有 | T57: 45313 | U57: 日期码格式：ZURU INC(BVI) 标准格式 日期：按实际生产日期 Packaging Info: 77515：MA 1L。 加防伪贴纸， 跟单提供。 Remark: 1.Amazon domestic 订单。出口美国。外箱最长边不能超过25" （超过了，case pack只能为1），不符合要求的大货，一律不接受。 2.无第三方验货/测试要求。 3.日期码使用ZURU标准版本。 | V57: Agnes Zheng | W57: 1.19 | X57: =I57*W57 -> 742.56 | Y57: 84363-3.27 | Z57: 77515-S001 | AA57: 已入 | AE57: DG | AG57: =I57 -> 624 | AK57: =AG57 -> 624 | AO57: =AG57 -> 624 | BM57: =AG57+AH57+AI57 -> 624
A58: 45295 | B58: AMAZON.COM.DEDC,LLC | C58: 美国 | D58: 4500124758 | E58: 22Q1ZMLV | F58: 4500122667-20 | G58: 77515-S001-MTS | H58: DIY厨艺大师 | I58: 648 | J58: 0 | K58: 24 | L58: =I58/K58 -> 27 | M58: 45359 | N58: 45355 | P58: pass | Q58: 3/19 出货 | R58: 外箱正面印ZURU Logo+SSCC LABEL（客供贴纸), 侧面印item# | S58: 有 | T58: 45313 | U58: 日期码格式：ZURU INC(BVI) 标准格式 日期：按实际生产日期 Packaging Info: 77515：MA 1L。 加防伪贴纸， 跟单提供。 Remark: 1.Amazon domestic 订单。出口美国。外箱最长边不能超过25" （超过了，case pack只能为1），不符合要求的大货，一律不接受。 2.无第三方验货/测试要求。 3.日期码使用ZURU标准版本。 | V58: Agnes Zheng | W58: 1.19 | X58: =I58*W58 -> 771.12 | Y58: 84363-3.27 | Z58: 77515-S001 | AA58: 已入 | AE58: DG | AG58: =I58 -> 648 | AK58: =AG58 -> 648 | AO58: =AG58 -> 648 | BM58: =AG58+AH58+AI58 -> 648
A59: 45295 | B59: AMAZON.COM.DEDC,LLC | C59: 美国 | D59: 4500124758 | E59: 22Q1ZMLV | F59: 4500122667-30 | G59: 77515-S001-MTS | H59: DIY厨艺大师 | I59: 48 | J59: 0 | K59: 24 | L59: =I59/K59 -> 2 | M59: 45359 | N59: 45355 | P59: pass | Q59: 3/19 出货 | R59: 外箱正面印ZURU Logo+SSCC LABEL（客供贴纸), 侧面印item# | S59: 有 | T59: 45313 | U59: 日期码格式：ZURU INC(BVI) 标准格式 日期：按实际生产日期 Packaging Info: 77515：MA 1L。 加防伪贴纸， 跟单提供。 Remark: 1.Amazon domestic 订单。出口美国。外箱最长边不能超过25" （超过了，case pack只能为1），不符合要求的大货，一律不接受。 2.无第三方验货/测试要求。 3.日期码使用ZURU标准版本。 | V59: Agnes Zheng | W59: 1.19 | X59: =I59*W59 -> 57.12 | Y59: 84363-3.27 | Z59: 77515-S001 | AA59: 已入 | AE59: DG | AG59: =I59 -> 48 | AK59: =AG59 -> 48 | AO59: =AG59 -> 48 | BM59: =AG59+AH59+AI59 -> 48
A60: 45295 | B60: AMAZON.COM.DEDC,LLC | C60: 美国 | D60: 4500124758 | E60: 22Q1ZMLV | F60: 4500122667-40 | G60: 77515-S001-MTS | H60: DIY厨艺大师 | I60: 2760 | J60: 0 | K60: 24 | L60: =I60/K60 -> 115 | M60: 45359 | N60: 45355 | P60: pass | Q60: 3/19 出货 | R60: 外箱正面印ZURU Logo+SSCC LABEL（客供贴纸), 侧面印item# | S60: 有 | T60: 45313 | U60: 日期码格式：ZURU INC(BVI) 标准格式 日期：按实际生产日期 Packaging Info: 77515：MA 1L。 加防伪贴纸， 跟单提供。 Remark: 1.Amazon domestic 订单。出口美国。外箱最长边不能超过25" （超过了，case pack只能为1），不符合要求的大货，一律不接受。 2.无第三方验货/测试要求。 3.日期码使用ZURU标准版本。 | V60: Agnes Zheng | W60: 1.19 | X60: =I60*W60 -> 3284.4 | Y60: 84363-3.27 | Z60: 77515-S001 | AA60: 已入 | AE60: DG | AG60: =I60 -> 2760 | AK60: =AG60 -> 2760 | AO60: =AG60 -> 2760 | BM60: =AG60+AH60+AI60 -> 2760
A61: 45295 | B61: AMAZON.COM.DEDC,LLC | C61: 美国 | D61: 4500124758 | E61: 22Q1ZMLV | F61: 4500122667-50 | G61: 77515-S001-MTS | H61: DIY厨艺大师 | I61: 672 | J61: 0 | K61: 24 | L61: =I61/K61 -> 28 | M61: 45359 | N61: 45355 | P61: pass | Q61: 3/19 出货 | R61: 外箱正面印ZURU Logo+SSCC LABEL（客供贴纸), 侧面印item# | S61: 有 | T61: 45313 | U61: 日期码格式：ZURU INC(BVI) 标准格式 日期：按实际生产日期 Packaging Info: 77515：MA 1L。 加防伪贴纸， 跟单提供。 Remark: 1.Amazon domestic 订单。出口美国。外箱最长边不能超过25" （超过了，case pack只能为1），不符合要求的大货，一律不接受。 2.无第三方验货/测试要求。 3.日期码使用ZURU标准版本。 | V61: Agnes Zheng | W61: 1.19 | X61: =I61*W61 -> 799.68 | Y61: 84363-3.27 | Z61: 77515-S001 | AA61: 已入 | AE61: DG | AG61: =I61 -> 672 | AK61: =AG61 -> 672 | AO61: =AG61 -> 672 | BM61: =AG61+AH61+AI61 -> 672
A62: 45295 | B62: AMAZON.COM.DEDC,LLC | C62: 美国 | D62: 4500124758 | E62: 22Q1ZMLV | F62: 4500122667-60 | G62: 77515-S001-MTS | H62: DIY厨艺大师 | I62: 2736 | J62: 0 | K62: 24 | L62: =I62/K62 -> 114 | M62: 45359 | N62: 45355 | P62: pass | Q62: 3/19 出货 | R62: 外箱正面印ZURU Logo+SSCC LABEL（客供贴纸), 侧面印item# | S62: 有 | T62: 45313 | U62: 日期码格式：ZURU INC(BVI) 标准格式 日期：按实际生产日期 Packaging Info: 77515：MA 1L。 加防伪贴纸， 跟单提供。 Remark: 1.Amazon domestic 订单。出口美国。外箱最长边不能超过25" （超过了，case pack只能为1），不符合要求的大货，一律不接受。 2.无第三方验货/测试要求。 3.日期码使用ZURU标准版本。 | V62: Agnes Zheng | W62: 1.19 | X62: =I62*W62 -> 3255.84 | Y62: 84363-3.27 | Z62: 77515-S001 | AA62: 已入 | AE62: DG | AG62: =I62 -> 2736 | AK62: =AG62 -> 2736 | AO62: =AG62 -> 2736 | BM62: =AG62+AH62+AI62 -> 2736
A63: 45295 | B63: AMAZON.COM.DEDC,LLC | C63: 美国 | D63: 4500124758 | E63: 22Q1ZMLV | F63: 4500122667-70 | G63: 77515-S001-MTS | H63: DIY厨艺大师 | I63: 960 | J63: 0 | K63: 24 | L63: =I63/K63 -> 40 | M63: 45359 | N63: 45355 | P63: pass | Q63: 3/19 出货 | R63: 外箱正面印ZURU Logo+SSCC LABEL（客供贴纸), 侧面印item# | S63: 有 | T63: 45313 | U63: 日期码格式：ZURU INC(BVI) 标准格式 日期：按实际生产日期 Packaging Info: 77515：MA 1L。 加防伪贴纸， 跟单提供。 Remark: 1.Amazon domestic 订单。出口美国。外箱最长边不能超过25" （超过了，case pack只能为1），不符合要求的大货，一律不接受。 2.无第三方验货/测试要求。 3.日期码使用ZURU标准版本。 | V63: Agnes Zheng | W63: 1.19 | X63: =I63*W63 -> 1142.4 | Y63: 84363-3.27 | Z63: 77515-S001 | AA63: 已入 | AE63: DG | AG63: =I63 -> 960 | AK63: =AG63 -> 960 | AO63: =AG63 -> 960 | BM63: =AG63+AH63+AI63 -> 960
A64: 45295 | B64: AMAZON.COM.DEDC,LLC | C64: 美国 | D64: 4500124758 | E64: 22Q1ZMLV | F64: 4500122667-80 | G64: 77515-S001-MTS | H64: DIY厨艺大师 | I64: 312 | J64: 0 | K64: 24 | L64: =I64/K64 -> 13 | M64: 45359 | N64: 45355 | P64: pass | Q64: 3/19 出货 | R64: 外箱正面印ZURU Logo+SSCC LABEL（客供贴纸), 侧面印item# | S64: 有 | T64: 45313 | U64: 日期码格式：ZURU INC(BVI) 标准格式 日期：按实际生产日期 Packaging Info: 77515：MA 1L。 加防伪贴纸， 跟单提供。 Remark: 1.Amazon domestic 订单。出口美国。外箱最长边不能超过25" （超过了，case pack只能为1），不符合要求的大货，一律不接受。 2.无第三方验货/测试要求。 3.日期码使用ZURU标准版本。 | V64: Agnes Zheng | W64: 1.19 | X64: =I64*W64 -> 371.28 | Y64: 84363-3.27 | Z64: 77515-S001 | AA64: 已入 | AE64: DG | AG64: =I64 -> 312 | AK64: =AG64 -> 312 | AO64: =AG64 -> 312 | BM64: =AG64+AH64+AI64 -> 312
A65: 45282 | B65: Amazon EU SARL, Ndl Deutschland | C65: 英国 | D65: 4500122000 | E65: 1JH3877O | F65: 4500122000-50 | G65: 77515-S001 | H65: DIY厨艺大师 | I65: 504 | J65: 0 | K65: 24 | L65: =I65/K65 -> 21 | M65: 45359 | N65: 45355 | P65: pass | Q65: 3/26 出货 | R65: 空白外箱（加印带Zuru字样的最新logo | S65: 有 | T65: 45651 | U65: 日期码格式：ZURU INC(BVI) 标准格式 日期：按实际生产日期 Packaging Info: Amazon DE/UK: 4. 77515: 24pcs/ctn, no inner; MA 1L 收缩膜包装+1张贴纸(含FR/DE/IT/ES警告语<(>&<)>IT sorting label贴纸+FR sorting label贴纸)+MA 5L A配件袋+MA 5 L A收藏指南+MA23L A警示说明书;参考翻单PO#4500116490； 5. 验货时间不迟于2024/3/11； Remark: "1.空白外箱（加印带Zuru字样的最新logo，除了邮包盒直接做外箱的产品） + SSCC LABEL一张, 无箱唛. (SSCC LABEL贴在外箱正面的正中间，贴一面即可,贴纸离外箱边距必须至少3CM),SSCC贴纸由工厂直接跟勤得采购或者工厂自行采购，每一张SSCC Label都是唯一且 有不同流水及条码，且需要检查条码是否能正常扫描，另外，此贴纸印刷不可出现模糊，溢出及粘胶不牢易脱落等现象，如工厂不按此要求导致贴纸有任何问题产生 的罚款将由工厂承担一切责任 。’MADE IN CHINA 外箱只印一正一侧。 2. 出往UK的产品+包装务必打上UKCA logo ，否则客人会退货且当地会有罚款。 3.订单必须经过ZURU QC验货并且通过后方可出货。 4.法国订单要求包装不使用矿物油，请按要求提供以下其中一份文件再出货 ，产品出到法国被相关部门抽检出现包装不符合此要求的，供应商需要为此承担责任， 故此请严格把关 。 -油墨物质""由1 ~ 7个芳香环组成的MOAH""的包装检测报告，要求限值≤1.0%; -包装材料清单，包括包装油墨或物质的信息 -油墨制造商的证书。 5 . 每一批次出货只能有一个生产日期，不可多个生产日期混在同一批次出货；" 6. 涉及到相关款式会有闪粉的或者微塑料的，请统一默认出无闪粉或者不含微塑料版本;" | V65: Crystal Chen | W65: 1.19 | X65: =I65*W65 -> 599.76 | Y65: 84352-3.26 | Z65: 77515-S001 | AA65: 已入 | AE65: DG | AG65: =I65 -> 504 | AK65: =AG65 -> 504 | AO65: =AG65 -> 504 | BM65: =AG65+AH65+AI65 -> 504
A66: 45289 | B66: BIG W | C66: 澳大利亚 | D66: 4500122443 | E66: 47661066 | F66: 4500122443-10 | G66: 77515GQ6-S001 | H66: DIY厨艺大师 | I66: 1632 | J66: 0 | K66: 48 | L66: =I66/K66 -> 34 | M66: 45359 | N66: 45355 | P66: pass | Q66: 3/14 出货 | R66: 45302 | S66: 无 | T66: 45308 | U66: 日期码格式：080324 日期： Packaging Info: 1.包装 (MA UPC 包装,1L 3L都可接受） 77515GQ6:MA UPC PKG+2张电池警告语贴纸带进口商信息（分别贴在包装正面和说明书上） 2.产品和产品包装上的日期码一致，为080324(dd/mm/yy;进口商贴纸上已经去掉日期码，请按要求在包装上打日期码， 进口商贴纸不覆盖日期码） 3.此单赶客户Dolls <(>&<)> Playsets，不接受延期 Remark: 1.共出4港口， 不同港口数量信息请见订单行项目，并请参考箱唛资料，港口不同，箱唛资料也不同； 2. 箱唛不可出现任何手写内容，重量与实际一致且不可手写 3.此单出澳大利亚，请按澳洲标准生产并满足当地法规要求 77515GQ6：11 assortment have the same ratio；3PCS AG13 Batteries (Included) | V66: Lillian Li | W66: 1.47 | X66: =I66*W66 -> 2399.04 | Y66: 84366-3.27 | Z66: 77515GQ6-S001 | AA66: 已入 | AE66: DG | AG66: =I66 -> 1632 | AK66: =AG66 -> 1632 | AO66: =AG66 -> 1632 | AW66: =AG66/12 -> 136 | BM66: =AG66+AH66+AI66 -> 1632
A67: 45289 | B67: BIG W | C67: 澳大利亚 | D67: 4500122443 | E67: 47661067 | F67: 4500122443-20 | G67: 77515GQ6-S001 | H67: DIY厨艺大师 | I67: 1440 | J67: 0 | K67: 48 | L67: =I67/K67 -> 30 | M67: 45359 | N67: 45355 | P67: pass | Q67: 3/13 交仓 | R67: 45302 | S67: 无 | T67: 45308 | U67: 日期码格式：080324 日期： Packaging Info: 1.包装 (MA UPC 包装,1L 3L都可接受） 77515GQ6:MA UPC PKG+2张电池警告语贴纸带进口商信息（分别贴在包装正面和说明书上） 2.产品和产品包装上的日期码一致，为080324(dd/mm/yy;进口商贴纸上已经去掉日期码，请按要求在包装上打日期码， 进口商贴纸不覆盖日期码） 3.此单赶客户Dolls <(>&<)> Playsets，不接受延期 Remark: 1.共出4港口， 不同港口数量信息请见订单行项目，并请参考箱唛资料，港口不同，箱唛资料也不同； 2. 箱唛不可出现任何手写内容，重量与实际一致且不可手写 3.此单出澳大利亚，请按澳洲标准生产并满足当地法规要求 77515GQ6：11 assortment have the same ratio；3PCS AG13 Batteries (Included) | V67: Lillian Li | W67: 1.47 | X67: =I67*W67 -> 2116.8 | Y67: 84366-3.27 | Z67: 77515GQ6-S001 | AA67: 已入 | AE67: DG | AG67: =I67 -> 1440 | AK67: =AG67 -> 1440 | AO67: =AG67 -> 1440 | AW67: =AG67/12 -> 120 | BM67: =AG67+AH67+AI67 -> 1440
A68: 45289 | B68: BIG W | C68: 澳大利亚 | D68: 4500122443 | E68: 47661068 | F68: 4500122443-30 | G68: 77515GQ6-S001 | H68: DIY厨艺大师 | I68: 1152 | J68: 0 | K68: 48 | L68: =I68/K68 -> 24 | M68: 45359 | N68: 45355 | P68: pass | Q68: 3/14 出货 | R68: 45302 | S68: 无 | T68: 45308 | U68: 日期码格式：080324 日期： Packaging Info: 1.包装 (MA UPC 包装,1L 3L都可接受） 77515GQ6:MA UPC PKG+2张电池警告语贴纸带进口商信息（分别贴在包装正面和说明书上） 2.产品和产品包装上的日期码一致，为080324(dd/mm/yy;进口商贴纸上已经去掉日期码，请按要求在包装上打日期码， 进口商贴纸不覆盖日期码） 3.此单赶客户Dolls <(>&<)> Playsets，不接受延期 Remark: 1.共出4港口， 不同港口数量信息请见订单行项目，并请参考箱唛资料，港口不同，箱唛资料也不同； 2. 箱唛不可出现任何手写内容，重量与实际一致且不可手写 3.此单出澳大利亚，请按澳洲标准生产并满足当地法规要求 77515GQ6：11 assortment have the same ratio；3PCS AG13 Batteries (Included) | V68: Lillian Li | W68: 1.47 | X68: =I68*W68 -> 1693.44 | Y68: 84366-3.27 | Z68: 77515GQ6-S001 | AA68: 已入 | AE68: DG | AG68: =I68 -> 1152 | AK68: =AG68 -> 1152 | AO68: =AG68 -> 1152 | AW68: =AG68/12 -> 96 | BM68: =AG68+AH68+AI68 -> 1152
A69: 45289 | B69: BIG W | C69: 澳大利亚 | D69: 4500122443 | E69: 47661069 | F69: 4500122443-40 | G69: 77515GQ6-S001 | H69: DIY厨艺大师 | I69: 480 | J69: 0 | K69: 48 | L69: =I69/K69 -> 10 | M69: 45359 | N69: 45355 | P69: pass | Q69: 3/13 交仓 | R69: 45302 | S69: 无 | T69: 45308 | U69: 日期码格式：080324 日期： Packaging Info: 1.包装 (MA UPC 包装,1L 3L都可接受） 77515GQ6:MA UPC PKG+2张电池警告语贴纸带进口商信息（分别贴在包装正面和说明书上） 2.产品和产品包装上的日期码一致，为080324(dd/mm/yy;进口商贴纸上已经去掉日期码，请按要求在包装上打日期码， 进口商贴纸不覆盖日期码） 3.此单赶客户Dolls <(>&<)> Playsets，不接受延期 Remark: 1.共出4港口， 不同港口数量信息请见订单行项目，并请参考箱唛资料，港口不同，箱唛资料也不同； 2. 箱唛不可出现任何手写内容，重量与实际一致且不可手写 3.此单出澳大利亚，请按澳洲标准生产并满足当地法规要求 77515GQ6：11 assortment have the same ratio；3PCS AG13 Batteries (Included) | V69: Lillian Li | W69: 1.47 | X69: =I69*W69 -> 705.6 | Y69: 84366-3.27 | Z69: 77515GQ6-S001 | AA69: 已入 | AE69: DG | AG69: =I69 -> 480 | AK69: =AG69 -> 480 | AO69: =AG69 -> 480 | AW69: =AG69/12 -> 40 | BM69: =AG69+AH69+AI69 -> 480
A70: 45302 | B70: ZURU LLC | C70: 美国 | D70: 4500123153 | E70: 5200003424 | F70: 4500123153-20 | G70: 77515-S001-MTS | H70: DIY厨艺大师 | I70: 2496 | J70: 0 | K70: 24 | L70: =I70/K70 -> 104 | M70: 45362 | N70: 45358 | P70: pass | Q70: 走 空运订单 3/12 | R70: 45341 | S70: 无 | T70: 1/19 寄出 | U70: 日期码格式：ZURU INC(BVI) 标准格式 日期：按实际生产日期 Packaging Info: 77515：MA 1L。 加防伪贴纸， 跟单提供。 Remark: 1.Amazon domestic 订单，外箱加印箱唛 （跟单提供）。出口美国。外箱最长边不能超过25" （超过了，case pack只能为1），不符合要求的大货，一律不接受。 2.无第三方验货/测试要求。 3.日期码使用ZURU标准版本。 | V70: SD24 | W70: 1.19 | X70: =I70*W70 -> 2970.24 | Y70: 84224－3.13 | Z70: 77515-S001 | AA70: 已入 | AE70: DG | AG70: =I70 -> 2496 | AK70: =AG70 -> 2496 | AO70: =AG70 -> 2496 | BM70: =AG70+AH70+AI70 -> 2496
A71: 45295 | B71: KMART AUSTRALIA LTD(NEW ZEALAND) | C71: 新西兰 | D71: 4500122607 | E71: 19631977 | F71: 4500122607-10 | G71: 77515GQ1-S003 | H71: DIY厨艺大师 | I71: 130 | J71: 0 | K71: 13 | L71: =I71/K71 -> 10 | M71: 45362 | N71: 45358 | O71: B版本收缩膜 | P71: pass | Q71: 3/15 交仓 | R71: 45303 | S71: 有 | T71: 45341 | U71: 日期码格式：ZURU INC(BVI) 标准格式 日期：按实际生产日期 Packaging Info: 77515GQ1:MA英语UPC版本包装（首选1LUPC，如果无1L可用多语含英语UPC版本）+防盗贴纸+箱唛+箱唛贴纸(1PCS/CTN).此外77515含纽扣电池，需要增加电池警告语 贴纸.防盗贴纸和警告语贴纸以及他们的位置图请跟回PO#4500121356 Remark: 1,请务必按时完货，验货并请按期送货入货代指定仓库，如果晚了导致船期Delay将会有罚金产生或者客户要求空运，所产生的罚金和空运费由工厂承担。 2.SSCC 外箱贴纸请同纸箱瓦楞纸方向（竖纹向）垂直，即外箱贴纸横着贴(注意条码不要被胶带粘住），贴1pc，贴1面正唛，封箱胶纸不能挡住贴纸内容。每pcs外 箱贴纸都是唯一的，不可重复粘贴，否则会有罚款产生。 3.外箱材质为ZURU标准； 4.此单需使用KMART封箱胶上下工字型封箱;从2019年6月开始，要用KMART 新版封箱胶带，此单要用"ANKO"封箱胶带 5.此单出口新西兰，请按相应的澳新标准生产； 6.产品和包装上生产批号的显示格式ZURU标准日期码格式 7.77515GQ1-S003:3PCS AG13 Batteries(Included) | V71: Sara Wang | W71: 1.7 | X71: =I71*W71 -> 221 | Y71: 84268－3.18 | Z71: 77515GQ1-S003 | AA71: 已入 | AE71: DG | AG71: =I71 -> 130 | AK71: =AG71 -> 130 | AO71: =AG71 -> 130 | AY71: =I71/13 -> 10 | BM71: =AG71+AH71+AI71 -> 130
A72: 45295 | B72: KMART AUSTRALIA LTD | C72: 澳大利亚 | D72: 4500122606 | E72: 19631976 | F72: 4500122606-10 | G72: 77515GQ1-S003 | H72: DIY厨艺大师 | I72: 1508 | J72: 0 | K72: 13 | L72: =I72/K72 -> 116 | M72: 45362 | N72: 45358 | P72: pass | Q72: 3/15 交仓 | R72: 45303 | S72: 有 | T72: 45341 | U72: 日期码格式：ZURU INC(BVI) 标准格式 日期：按实际生产日期 Packaging Info: 77515GQ1:MA英语UPC版本包装（首选1LUPC，如果无1L可用多语含英语UPC版本）+防盗贴纸+箱唛+箱唛贴纸(1PCS/CTN).此外77515含纽扣电池，需要增加电池警告语 贴纸.防盗贴纸和警告语贴纸以及他们的位置图请跟回PO#4500121356 Remark: 1,请务必按时完货，验货并请按期送货入货代指定仓库，如果晚了导致船期Delay将会有罚金产生或者客户要求空运，所产生的罚金和空运费由工厂承担。 2.SSCC 外箱贴纸请同纸箱瓦楞纸方向（竖纹向）垂直，即外箱贴纸横着贴(注意条码不要被胶带粘住），贴1pc，贴1面正唛，封箱胶纸不能挡住贴纸内容。每pcs外 箱贴纸都是唯一的，不可重复粘贴，否则会有罚款产生。 3.外箱材质为ZURU标准； 4.此单需使用KMART封箱胶上下工字型封箱;从2019年6月开始，要用KMART 新版封箱胶带，此单要用"ANKO"封箱胶带 5.此单出口澳大利亚，请按相应的澳新标准生产； 6.产品和包装上生产批号的显示格式ZURU标准日期码格式 7.77515GQ1-S003:3PCS AG13 Batteries(Included) | V72: Sara Wang | W72: 1.7 | X72: =I72*W72 -> 2563.6 | Y72: 84267－3.18 | Z72: 77515GQ1-S003 | AA72: 已入 | AE72: DG | AG72: =I72 -> 1508 | AK72: =AG72 -> 1508 | AO72: =AG72 -> 1508 | AY72: =I72/13 -> 116 | BM72: =AG72+AH72+AI72 -> 1508
A73: 45300 | B73: TARGET US | C73: 美国 | D73: 4500122898 | E73: 0086-9283219-0581 | F73: 4500122898-10 | G73: 77515GQ5-S002 | H73: DIY厨艺大师 | I73: 4998 | J73: 0 | K73: 21 | L73: =I73/K73 -> 238 | M73: 45366 | N73: 45362 | P73: pass | Q73: 3/25 客上柜 | R73: 45303 | S73: 有 | T73: 45322 | U73: 日期码格式：ZURU INC(BVI) 标准格式 日期：按实际生产日期 Packaging Info: 产品包装MA 1L, MA PDQ Remark: 1. 77515GQ5-S002-MINI BRAND-MASTER CHEF MINI BRANDS-SERIES 1,21pcs/Gravity PDQ, 21pcs/CTN,No Inner,STD Color Assortment (White drop) 2. 产品包装MA 1L, MA PDQ, 产品UPC 显示193052061034; 11 assortment have the same ratio； 3. 外箱正唛左上角位置粘贴条码箱贴纸，每箱只贴一张，由ZURU订购。来料贴纸上显示的客户DPCI# 086-02-9598， UPC显示10193052061031; 4. 产品和包装上印刷 tracking code信息，格式为ZURU常规格式; 5. 出货方式：货代自提。 | V73: Holly Zheng | W73: 1.75 | X73: =I73*W73 -> 8746.5 | Y73: 84341－3.25 | Z73: 77515GQ5-S002 | AA73: 已入 | AE73: DG | AG73: =I73 -> 4998 | AK73: =AG73 -> 4998 | AO73: =AG73 -> 4998 | AS73: =I73/21 -> 238 | BM73: =AG73+AH73+AI73 -> 4998
A74: 45272 | B74: TOYS "R" US (CANADA) LTD. | C74: 加拿大 | D74: 4500120793 | E74: 2401526863 | F74: 4500120793-10 | G74: 77515GQ5-S002 | H74: DIY厨艺大师 | I74: 567 | J74: 0 | K74: 21 | L74: =I74/K74 -> 27 | M74: 45363 | N74: 45359 | O74: 3/22 第三个验货 | P74: pass | R74: 45343 | S74: 无 | T74: 45344 | U74: 日期码格式：ZURU INC(BVI) 标准格式 日期：按实际生产日期 Packaging Info: 1. 出口加拿大市场，MA 3L UPC 版本包装+小部件警告语贴纸。 UPC#193052061034 2. 产品，布标，包装， 外箱时间一致。 产品，布标，包装 date code 格式为Zuru 标准格式。 外箱date code 格式为YYYYMMDD。 Remark: 3. 需要第三方SGS验货，验货时间2024/03/12，请备1PC完整带包装样品供验货人员参考，可以从大货里拿，用完之后无损坏的话可以放回大货里，没有客户签版。 | V74: Abby Mai | W74: 1.8 | X74: =I74*W74 -> 1020.6 | Y74: 84415－3.30 | Z74: 77515GQ5-S002-3L | AA74: 已入 | AE74: DG | AG74: =I74 -> 567 | AL74: =I74 -> 567 | AO74: =AG74 -> 567 | AT74: =I74/21 -> 27 | BM74: =AG74+AH74+AI74 -> 567
A75: 45272 | B75: TOYS "R" US (CANADA) LTD. | C75: 加拿大 | D75: 4500120793 | E75: 3501526863 | F75: 4500120793-20 | G75: 77515GQ5-S002 | H75: DIY厨艺大师 | I75: 2016 | J75: 0 | K75: 21 | L75: =I75/K75 -> 96 | M75: 45363 | N75: 45359 | O75: 3/22 第三个验货 | P75: pass | R75: 45343 | S75: 无 | T75: 45344 | U75: 日期码格式：ZURU INC(BVI) 标准格式 日期：按实际生产日期 Packaging Info: 1. 出口加拿大市场，MA 3L UPC 版本包装+小部件警告语贴纸。 UPC#193052061034 2. 产品，布标，包装， 外箱时间一致。 产品，布标，包装 date code 格式为Zuru 标准格式。 外箱date code 格式为YYYYMMDD。 Remark: 3. 需要第三方SGS验货，验货时间2024/03/12，请备1PC完整带包装样品供验货人员参考，可以从大货里拿，用完之后无损坏的话可以放回大货里，没有客户签版。 | V75: Abby Mai | W75: 1.8 | X75: =I75*W75 -> 3628.8 | Y75: 84415－3.30 | Z75: 77515GQ5-S002-3L | AA75: 已入 | AE75: DG | AG75: =I75 -> 2016 | AL75: =I75 -> 2016 | AO75: =AG75 -> 2016 | AT75: =I75/21 -> 96 | BM75: =AG75+AH75+AI75 -> 2016
A76: 45300 | B76: B&M RETAIL LIMITED | C76: 英国 | D76: 4500122683 | E76: 4500122683-1 01191224/1 407640 | F76: 4500122683-10 | G76: 77515GQ5-S001 | H76: DIY厨艺大师 | I76: =14028+14028 -> 28056 | J76: 0 | K76: 42 | L76: =I76/K76 -> 668 | M76: 45367 | N76: 45363 | P76: pass | Q76: 3/19 出货 | R76: 45321 | S76: 无 | T76: 无 | U76: 日期码格式：ZURU INC(BVI) 标准格式 日期：按实际生产日期 Packaging Info: 77515GQ5: MA-1L 包装配套 11 assortment have the same ratio Remark: *MA版本按工厂现有最新库存即可，订单出英国，请注意检查产品及包装应带UKCA图标，包装显示ZURU UK LTD信息，QC同事请查核，如有问题与跟单确认。 *生产日期按实际的（法定工作日） ，按ZURU标准格式即可 ，但是请知悉包装日期码需要早于或者等于外箱日期码 ，不能晚于外箱日期码 *请注意所有订单都需要经过ZURU QC验货并且通过后方可出货 *条码以订单显示为准 ，注意做货前先检查以免造成返工 。 | V76: Sherry Lu | W76: 1.649 | X76: =I76*W76 -> 46264.344 | Y76: 84362－3.27 | Z76: 77515GQ5-S001 | AA76: 已入 | AE76: DG | AG76: =I76 -> 28056 | AK76: =I76 -> 28056 | AO76: =AG76 -> 28056 | AS76: =I76/21 -> 1336 | BM76: =AG76+AH76+AI76 -> 28056
A77: 45293 | B77: American Eagle | C77: 美国 | D77: 4500122482 | E77: 1125393 | F77: 4500122482-10 | G77: 77515-S001 | H77: DIY厨艺大师 | I77: 3336 | J77: 0 | K77: 24 | L77: =I77/K77 -> 139 | M77: 45365 | N77: 45362 | P77: pass | Q77: 3/15 交仓 | R77: 45306 | S77: 有 | T77: 45344 | U77: 日期码格式：ZURU INC(BVI) 标准格式 日期：按实际生产日期 Packaging Info: 1. MA 1L UPC 包装+价格贴+客供.COM 贴纸+外箱贴 + 透明胶覆盖.COM 贴纸（跟单提供资料，工厂自行安排） 客户PO#1125393- 3336PCS- MA 1L UPC 包装+价格贴+外箱贴 客户PO#1125394- 672PCS- MA 1L UPC 包装+价格贴+外箱贴+客供.COM 贴纸+ 透明胶覆盖.COM 贴纸 客户PO#1135779- 1608PCS- MA 1L UPC 包装+价格贴+外箱贴 客户PO#1135780- 384PCS- MA 1L UPC 包装+价格贴+外箱贴+客供.COM 贴纸+ 透明胶覆盖.COM 贴纸 Remark: 2. 产品和包装上印刷tracking code信息，格式为ZURU常规 3. 箱子最小的尺寸要求： 30.48 x 22.86 x 10.16cm, 最大的尺寸为 66. 04 X 45.72 X 43.18cm, 外箱的高不能大于宽，否则会有罚款，如外箱达不到要求请告 知跟单，需要调整。 4. 外箱贴纸尺寸4x6英寸，贴纸居中贴在侧面，且距离外箱底部1.5英寸，外箱胶纸不可以覆盖住贴纸上的条形码，不可以有褶皱/刮花导致扫描不出信息，否则会 有罚款. 5. 需ZURU QC 验货合格后方可出货 6. 价格贴的位置为球的顶部/底部空白处，.COM 贴纸位置为球的顶部/底部空白处，（价格贴如在底部，.COM 贴纸则在顶部， 不可以覆盖住重要文字以及图案） | V77: Camellia Lyu | W77: 1.17 | X77: =I77*W77 -> 3903.12 | Y77: 84266－3.18 | Z77: 77515-S001 | AA77: 已入 | AE77: DG | AG77: =I77 -> 3336 | AK77: =AG77 -> 3336 | AO77: =AG77 -> 3336 | BM77: =AG77+AH77+AI77 -> 3336
A78: 45293 | B78: American Eagle | C78: 美国 | D78: 4500122482 | E78: 1125394 | F78: 4500122482-20 | G78: 77515-S001 | H78: DIY厨艺大师 | I78: 672 | J78: 0 | K78: 24 | L78: =I78/K78 -> 28 | M78: 45365 | N78: 45362 | P78: pass | Q78: 3/15 交仓 | R78: 45306 | S78: 有 | T78: 45344 | U78: 日期码格式：ZURU INC(BVI) 标准格式 日期：按实际生产日期 Packaging Info: 1. MA 1L UPC 包装+价格贴+客供.COM 贴纸+外箱贴 + 透明胶覆盖.COM 贴纸（跟单提供资料，工厂自行安排） 客户PO#1125393- 3336PCS- MA 1L UPC 包装+价格贴+外箱贴 客户PO#1125394- 672PCS- MA 1L UPC 包装+价格贴+外箱贴+客供.COM 贴纸+ 透明胶覆盖.COM 贴纸 客户PO#1135779- 1608PCS- MA 1L UPC 包装+价格贴+外箱贴 客户PO#1135780- 384PCS- MA 1L UPC 包装+价格贴+外箱贴+客供.COM 贴纸+ 透明胶覆盖.COM 贴纸 Remark: 2. 产品和包装上印刷tracking code信息，格式为ZURU常规 3. 箱子最小的尺寸要求： 30.48 x 22.86 x 10.16cm, 最大的尺寸为 66. 04 X 45.72 X 43.18cm, 外箱的高不能大于宽，否则会有罚款，如外箱达不到要求请告 知跟单，需要调整。 4. 外箱贴纸尺寸4x6英寸，贴纸居中贴在侧面，且距离外箱底部1.5英寸，外箱胶纸不可以覆盖住贴纸上的条形码，不可以有褶皱/刮花导致扫描不出信息，否则会 有罚款. 5. 需ZURU QC 验货合格后方可出货 6. 价格贴的位置为球的顶部/底部空白处，.COM 贴纸位置为球的顶部/底部空白处，（价格贴如在底部，.COM 贴纸则在顶部， 不可以覆盖住重要文字以及图案） | V78: Camellia Lyu | W78: 1.17 | X78: =I78*W78 -> 786.24 | Y78: 84266－3.18 | Z78: 77515-S001 | AA78: 已入 | AE78: DG | AG78: =I78 -> 672 | AK78: =AG78 -> 672 | AO78: =AG78 -> 672 | BM78: =AG78+AH78+AI78 -> 672
A79: 45293 | B79: American Eagle | C79: 美国 | D79: 4500122482 | E79: 1135779 | F79: 4500122482-30 | G79: 77515-S001 | H79: DIY厨艺大师 | I79: 1608 | J79: 0 | K79: 24 | L79: =I79/K79 -> 67 | M79: 45365 | N79: 45362 | P79: pass | Q79: 3/15 交仓 | R79: 45306 | S79: 有 | T79: 45344 | U79: 日期码格式：ZURU INC(BVI) 标准格式 日期：按实际生产日期 Packaging Info: 1. MA 1L UPC 包装+价格贴+客供.COM 贴纸+外箱贴 + 透明胶覆盖.COM 贴纸（跟单提供资料，工厂自行安排） 客户PO#1125393- 3336PCS- MA 1L UPC 包装+价格贴+外箱贴 客户PO#1125394- 672PCS- MA 1L UPC 包装+价格贴+外箱贴+客供.COM 贴纸+ 透明胶覆盖.COM 贴纸 客户PO#1135779- 1608PCS- MA 1L UPC 包装+价格贴+外箱贴 客户PO#1135780- 384PCS- MA 1L UPC 包装+价格贴+外箱贴+客供.COM 贴纸+ 透明胶覆盖.COM 贴纸 Remark: 2. 产品和包装上印刷tracking code信息，格式为ZURU常规 3. 箱子最小的尺寸要求： 30.48 x 22.86 x 10.16cm, 最大的尺寸为 66. 04 X 45.72 X 43.18cm, 外箱的高不能大于宽，否则会有罚款，如外箱达不到要求请告 知跟单，需要调整。 4. 外箱贴纸尺寸4x6英寸，贴纸居中贴在侧面，且距离外箱底部1.5英寸，外箱胶纸不可以覆盖住贴纸上的条形码，不可以有褶皱/刮花导致扫描不出信息，否则会 有罚款. 5. 需ZURU QC 验货合格后方可出货 6. 价格贴的位置为球的顶部/底部空白处，.COM 贴纸位置为球的顶部/底部空白处，（价格贴如在底部，.COM 贴纸则在顶部， 不可以覆盖住重要文字以及图案） | V79: Camellia Lyu | W79: 1.17 | X79: =I79*W79 -> 1881.36 | Y79: 84266－3.18 | Z79: 77515-S001 | AA79: 已入 | AE79: DG | AG79: =I79 -> 1608 | AK79: =AG79 -> 1608 | AO79: =AG79 -> 1608 | BM79: =AG79+AH79+AI79 -> 1608
A80: 45293 | B80: American Eagle | C80: 美国 | D80: 4500122482 | E80: 1135780 | F80: 4500122482-40 | G80: 77515-S001 | H80: DIY厨艺大师 | I80: 384 | J80: 0 | K80: 24 | L80: =I80/K80 -> 16 | M80: 45365 | N80: 45362 | P80: pass | Q80: 3/15 交仓 | R80: 45306 | S80: 有 | T80: 45344 | U80: 日期码格式：ZURU INC(BVI) 标准格式 日期：按实际生产日期 Packaging Info: 1. MA 1L UPC 包装+价格贴+客供.COM 贴纸+外箱贴 + 透明胶覆盖.COM 贴纸（跟单提供资料，工厂自行安排） 客户PO#1125393- 3336PCS- MA 1L UPC 包装+价格贴+外箱贴 客户PO#1125394- 672PCS- MA 1L UPC 包装+价格贴+外箱贴+客供.COM 贴纸+ 透明胶覆盖.COM 贴纸 客户PO#1135779- 1608PCS- MA 1L UPC 包装+价格贴+外箱贴 客户PO#1135780- 384PCS- MA 1L UPC 包装+价格贴+外箱贴+客供.COM 贴纸+ 透明胶覆盖.COM 贴纸 Remark: 2. 产品和包装上印刷tracking code信息，格式为ZURU常规 3. 箱子最小的尺寸要求： 30.48 x 22.86 x 10.16cm, 最大的尺寸为 66. 04 X 45.72 X 43.18cm, 外箱的高不能大于宽，否则会有罚款，如外箱达不到要求请告 知跟单，需要调整。 4. 外箱贴纸尺寸4x6英寸，贴纸居中贴在侧面，且距离外箱底部1.5英寸，外箱胶纸不可以覆盖住贴纸上的条形码，不可以有褶皱/刮花导致扫描不出信息，否则会 有罚款. 5. 需ZURU QC 验货合格后方可出货 6. 价格贴的位置为球的顶部/底部空白处，.COM 贴纸位置为球的顶部/底部空白处，（价格贴如在底部，.COM 贴纸则在顶部， 不可以覆盖住重要文字以及图案） | V80: Camellia Lyu | W80: 1.17 | X80: =I80*W80 -> 449.28 | Y80: 84266－3.18 | Z80: 77515-S001 | AA80: 已入 | AE80: DG | AG80: =I80 -> 384 | AK80: =AG80 -> 384 | AO80: =AG80 -> 384 | BM80: =AG80+AH80+AI80 -> 384
A81: 45299 | B81: Juguettos Ltd | C81: 西班牙 | D81: 4500122760 | E81: P82514/PC23216 | F81: 4500122760 | G81: 77515GQ5-S002 | H81: DIY厨艺大师 | I81: 3990 | J81: 0 | K81: 21 | L81: =I81/K81 -> 190 | M81: 45366 | N81: 45362 | P81: pass | Q81: 3/20 出货 | R81: 45300 | S81: 无 | T81: 45308 | U81: 日期码格式：ZURU INC(BVI) 标准格式 日期：按实际生产日期 Packaging Info: 1.包装： #77515GQ5：最新MA 3L PDQ/MA 3L EAN版本收缩膜/MA 5L 收藏指南/MA 23L说明书+EAN条码贴纸（分别贴在收缩膜和PDQ上）+进口商贴纸+警告语贴纸 Remark: 2.订单出西班牙，欧洲国家，产品不能含有闪粉/微塑料！ 3.大货样品2套/item，请多备料！ 4. 产品信息：#77515GQ5:3PCS AG13 Batteries(Included) | V81: Andy Xi | W81: 1.8 | X81: =I81*W81 -> 7182 | Y81: 84304－3.20 | Z81: 77515GQ5-S002-3L | AA81: 已入 | AE81: DG | AG81: =I81 -> 3990 | AL81: =I81 -> 3990 | AO81: =AG81 -> 3990 | AT81: =I81/21 -> 190 | BM81: =AG81+AH81+AI81 -> 3990
A82: 45301 | B82: COMERCIAL JOMAN S.L. | C82: 西班牙 | D82: 4500123041 | F82: 4500123041-10 | G82: 77515GQ5-S001 | H82: DIY厨艺大师 | I82: 420 | J82: 0 | K82: 42 | L82: =I82/K82 -> 10 | M82: 45366 | N82: 45362 | P82: pass | Q82: 3/19 出货 | R82: 45301 | S82: 无 | T82: 45307 | U82: 日期码格式：ZURU INC(BVI) 标准格式 日期：按实际生产日期 Packaging Info: 1.包装：#77515GQ5：MA3L PDQ/MA 3L收缩膜（含EAN条码）/MA说明书/收藏指南+进口商贴纸+警告语贴纸 Remark: 2.订单出欧洲国家 西班牙，产品不能含有闪粉/微塑料！ 3.产品信息：#77515GQ5：3PCS AG13 Batteries (included) | V82: Andy Xi | W82: 1.649 | X82: =I82*W82 -> 692.58 | Y82: 84305－3.20 | Z82: 77515GQ5-S001-3L | AA82: 已入 | AE82: DG | AG82: =I82 -> 420 | AL82: =I82 -> 420 | AO82: =AG82 -> 420 | AT82: =I82/21 -> 20 | BM82: =AG82+AH82+AI82 -> 420
A83: 45260 | B83: ToyChamp Belgium nv | C83: 比利时 | D83: 4500119592 | E83: 2023101383 | F83: 45020119592-20 | G83: 77515SK-S002 | H83: DIY厨艺大师 | I83: 5400 | J83: 0 | K83: 60 | L83: =I83/K83 -> 90 | M83: 45369 | N83: 45365 | P83: pass | Q83: 3/18 出货 | R83: 45638 | S83: 无 | T83: 45300 | U83: 日期码格式：ZURU INC(BVI) 标准格式 日期：按实际生产日期 Packaging Info: 77515SK-S002: MA 3L EAN收缩膜（含5L警语）+2张警语贴纸，MA5L配件袋+NL警语贴纸，MA5L收藏指南，MA 23L说明书，MA3L Sidekick(WITH BASE) Remark: 1.配比 77515SK: 11 assortment have the same ratio; 3PCS AG13 Batteries(Included) 2.无闪粉版本 | V83: Sandy Shao | W83: 87.05 | X83: =W83*L83 -> 7834.5 | Y83: 84535－4.15 | Z83: 77515SK-S002-3L | AA83: 已入 | AE83: DG | AG83: =I83 -> 5400 | AL83: =AG83 -> 5400 | AO83: =AG83 -> 5400 | BE83: =I83/60 -> 90 | BM83: =AG83+AH83+AI83 -> 5400
A84: 45218 | B84: Gamestop Texas Ltd | C84: 美国 | D84: 4500116296 | E84: 4500023317 | F84: 4500116296-10 | G84: 77515GQ6-S001 | H84: DIY厨艺大师 | I84: 7632 | J84: 0 | K84: 48 | L84: =I84/K84 -> 159 | M84: 45370 | N84: 45366 | P84: pass | Q84: 3/23 出货 | R84: 45301 | S84: 无 | T84: 无 | U84: 日期码格式：ZURU INC(BVI) 标准格式 日期：按实际生产日期 Packaging Info: 1. ZURU标准MA UPC版包装, 优先1L，出口美国. Remark: 2. 除ZURU标准报告外，客户还要求测Formaldehyde(甲醛)，PH Value,TPCH, 请注意把控原材料质量，避免测试FAIL. 3.#77515GQ6: 12pcs/Gravity PDQ, 48pcs/CTN, 11 assortment have the same ratio. 4.产品和包装上需要印刷tracking code信息,格式为ZURU常规. 5. ZURU QC验货。 | V84: Kelly Shen | W84: 1.41 | X84: =I84*W84 -> 10761.12 | Y84: 84364－3.27 | Z84: 77515GQ6-S001 | AA84: 已入 | AE84: DG | AG84: =I84 -> 7632 | AK84: =AG84 -> 7632 | AO84: =AG84 -> 7632 | AW84: =AG84/12 -> 636 | BM84: =AG84+AH84+AI84 -> 7632
A85: 45218 | B85: Gamestop Texas Ltd | C85: 美国 | D85: 4500116297 | E85: 4500023316 | F85: 4500116297-10 | G85: 77515GQ6-S001 | H85: DIY厨艺大师 | I85: 7680 | J85: 0 | K85: 48 | L85: =I85/K85 -> 160 | M85: 45370 | N85: 45366 | P85: pass | Q85: 3/23 出货 | R85: 45301 | S85: 无 | T85: 无 | U85: 日期码格式：ZURU INC(BVI) 标准格式 日期：按实际生产日期 Packaging Info: 1. ZURU标准MA UPC版包装, 优先1L，出口美国. Remark: 2. 除ZURU标准报告外，客户还要求测Formaldehyde(甲醛)，PH Value,TPCH, 请注意把控原材料质量，避免测试FAIL. 3.#77515GQ6: 12pcs/Gravity PDQ, 48pcs/CTN, 11 assortment have the same ratio. 4.产品和包装上需要印刷tracking code信息,格式为ZURU常规. 5. ZURU QC验货。 | V85: Kelly Shen | W85: 1.41 | X85: =I85*W85 -> 10828.8 | Y85: 84365-3.27 | Z85: 77515GQ6-S001 | AA85: 已入 | AE85: DG | AG85: =I85 -> 7680 | AK85: =AG85 -> 7680 | AO85: =AG85 -> 7680 | AW85: =AG85/12 -> 640 | BM85: =AG85+AH85+AI85 -> 7680
A86: 45184 | B86: FYE | C86: 美国 | D86: 4500113337 | E86: 0000079359 | F86: 4500113337-10 | G86: 77515GQ1-S001 | H86: DIY厨艺大师 | I86: 1196 | J86: 0 | K86: 52 | L86: =I86/K86 -> 23 | M86: 45371 | N86: 45367 | P86: pass | Q86: 3/20 交仓 | R86: 45184 | S86: 无 | T86: 45611 | U86: 日期码格式：ZURU INC(BVI) 标准格式 日期：按实际生产日期 Packaging Info: ZURU MA UPC 包装(优先使用1L) + 客版可移动价格贴纸, 贴纸AWS跟单稍后提供, 工厂自行订购, 出口美国。 Remark: 1.ZURU MA UPC 包装(优先使用1L) + 客版可移动价格贴纸, 贴纸AWS跟单稍后提供, 工厂自行订购, 出口美国。 2.ZURU标准日期码格式,所有产品及包装都必须带有日期码，日期码必须一致(但日期不可为周末)。 3.此单外箱不可有水贴纸。 4.可移价贴需贴在产品包装背面右下角的位置。 All Pre Price Tickets should be placed on the back of the product located in the lower right hand corner of the package #77515GQ1-S001 $14.99 5.出货配比： #77515GQ1-S001-MINI BRANDS-MASTER CHEF MINI BRANDS-SERIES 1-CAPSULE,13PCS/Gravity PDQ, 52PCS/4PDQ/CTN | V86: Hailey Yu | W86: 1.643 | X86: =I86*W86 -> 1965.028 | Y86: 84306-3.20 | Z86: 77515GQ1-S001 | AA86: 已入 | AE86: DG | AG86: =I86 -> 1196 | AK86: =AG86 -> 1196 | AO86: =AG86 -> 1196 | AY86: =AG86/13 -> 92 | BM86: =AG86+AH86+AI86 -> 1196
A87: 45260 | B87: ZURU France | C87: 法国 | D87: 4500119840 | E87: 5200002791 | F87: 4500119840-10 | G87: 77515GQ5-S002-MTS | H87: DIY厨艺大师 | I87: 12012 | J87: 0 | K87: 21 | L87: =I87/K87 -> 572 | M87: 45371 | N87: 45367 | P87: pass | Q87: 3/20 出货 | R87: 45302 | S87: 无 | T87: 45313 | U87: 日期码格式：ZURU INC(BVI) 标准格式 日期：按实际生产日期 Packaging Info: 1.77515GQ5：最新MA 3L+5L warning 收缩膜+一张法国换标标贴纸+一张警语贴纸 MA 收藏指南+MA PDQ； Remark: 1.法国内销单，ZURU 验货后即可出货； 2.外箱EAN 14 条码参考： 77515GQ5：10193052061031 3.所有出口法国的产品, 法规规定禁止在包装和共公众用的印刷品中使用矿物油中含有的物质, 包装印刷油墨中含有的MOAH/MOSH的质量浓度不能超过1%, 否则出货 到法国被抽检出现问题, 供应商需要对此负责; | V87: SD45 | W87: 1.8 | X87: =I87*W87 -> 21621.6 | Y87: 84317-3.21 | Z87: 77515GQ5-S002-3L | AA87: 已入 | AE87: DG | AG87: =I87 -> 12012 | AL87: =I87 -> 12012 | AO87: =AG87 -> 12012 | AT87: =I87/21 -> 572 | BM87: =AG87+AH87+AI87 -> 12012
A88: 45295 | B88: ALL BRANDS TOYS PTY LTD | C88: 澳大利亚 | D88: 4500122597 | E88: 81193 | F88: 4500122597-10 | G88: 77515GQ2-S001 | H88: DIY厨艺大师 | I88: 1950 | J88: 0 | K88: 50 | L88: =I88/K88 -> 39 | M88: 45371 | N88: 45367 | P88: pass | Q88: 3/19 出货 | R88: 45309 | S88: 无 | T88: 45296 | U88: 日期码格式：ZURU INC(BVI) 标准格式 日期：按实际生产日期 Packaging Info: 英文MA包装UPC版本（首选1L,无1L可选多语）+客人通用进口商贴纸(每PCS贴一张进口商贴纸)+箱唛,进口商贴纸请贴在球底部中央;此外77515含纽扣电池，收缩膜 跟说明书上需要各贴1pc警告语贴纸。以上贴纸大货生产时，请先返回图片确认 Remark: 1.按实际生产日期; 2.出澳大利亚，请按照相应标准生产; 3.77515GQ2:3PCS AG13 Batteries(Include); | V88: Sara Wang | W88: 1.57 | X88: =I88*W88 -> 3061.5 | Y88: 84536-4.15 | Z88: 77515GQ2-S001 | AA88: 已入 | AE88: DG | AG88: =I88 -> 1950 | AK88: =I88 -> 1950 | AO88: =I88 -> 1950 | BA88: =I88/25 -> 78 | BM88: =AG88+AH88+AI88 -> 1950
A89: 45295 | B89: ALL BRANDS TOYS PTY LTD | C89: 澳大利亚 | D89: 4500122597 | E89: 81193 | F89: 4500122597-20 | G89: 77515SK-S002 | H89: DIY厨艺大师 | I89: 6000 | J89: 0 | K89: 60 | L89: =I89/K89 -> 100 | M89: 45371 | N89: 45367 | P89: pass | Q89: 3/19 出货 | R89: 45309 | S89: 无 | T89: 45296 | U89: 日期码格式：ZURU INC(BVI) 标准格式 日期：按实际生产日期 Packaging Info: 英文MA包装UPC版本（首选1L,无1L可选多语）+客人通用进口商贴纸(每PCS贴一张进口商贴纸)+箱唛,进口商贴纸请贴在球底部中央;此外77515含纽扣电池，收缩膜 跟说明书上需要各贴1pc警告语贴纸。以上贴纸大货生产时，请先返回图片确认 Remark: 1.按实际生产日期; 2.出澳大利亚，请按照相应标准生产; 3.77515SK:3PCS AG13 Batteries(Include); | V89: Sara Wang | W89: 87.05 | X89: =W89*L89 -> 8705 | Y89: 84536-4.15 | Z89: 77515SK-S002 | AA89: 已入 | AE89: DG | AG89: =I89 -> 6000 | AK89: =AG89 -> 6000 | AO89: =AG89 -> 6000 | BD89: =I89/60 -> 100 | BM89: =AG89+AH89+AI89 -> 6000
A90: 45341 | B90: ZURU France | C90: 法国 | D90: 4500124462 | E90: 5200003807 | F90: 4500124462-10 | G90: 77515SK1-S002-MTS | H90: DIY厨艺大师 | I90: 6000 | J90: 0 | K90: 30 | L90: =I90/K90 -> 200 | M90: 45371 | N90: 45367 | P90: pass | Q90: 3/21 出货 | R90: 45328 | S90: 无 | T90: 45344 | U90: 日期码格式：ZURU INC(BVI) 标准格式 日期：按实际生产日期 Packaging Info: 77515SK1：MA 3L 展示架+{MA 3L+5L warning EAN A版本收缩膜+一张法国和意大利环保标贴纸+一张警语贴纸}MA MA 5L A版收藏指南+MA 23L A版说明书； Remark: "1.西班牙内销单，ZURU 验货后即可出货； 2.外箱EAN 14 条码参考： 77515SK1：14894680032252 3.所有出口欧洲的产品, 法规规定禁止在包装和共公众用的印刷品中使用矿物油中含有的物质, 包装印刷油墨中含有的MOAH/MOSH的质量浓度不能超过1%, 否则出货 到法国被抽检出现问题, 供应商需要对此负责; 4. date code: 外箱/产品/包装 保持一致，完货后提供date code 信息以便我们保存记录做批次管理；" | V90: SD45 | W90: 53.489 | X90: =W90*L90 -> 10697.8 | Y90: 84540R1-4.15 | Z90: 77515SK1-S002-3L | AA90: 已入 | AE90: DG | AG90: =I90 -> 6000 | AL90: =I90 -> 6000 | AO90: =AG90 -> 6000 | BG90: =I90/30 -> 200 | BH90: =BG90 -> 200 | BM90: =AG90+AH90+AI90 -> 6000
A91: 45362 | B91: TOYS "R" US (CANADA) LTD. | C91: 加拿大 | D91: 4500126476 | E91: 2401525626 | F91: 4500126476-10 | G91: 77515GQ5-S002 | H91: DIY厨艺大师 | I91: 546 | J91: 0 | K91: 21 | L91: =I91/K91 -> 26 | M91: 45411 | N91: 45407 | O91: 5/7SGS验货 | P91: 消耗 PO 4500120793 取消的数量 已验货 | Q91: 5/8--5/14期间交仓 外箱要改 | R91: 45362 | S91: 无 | T91: 45344 | U91: 日期码格式：ZURU INC(BVI) 标准格式 日期：按实际生产日期 Packaging Info: 1. 出口加拿大市场，MA 3L UPC 版本包装+小部件警告语贴纸。消耗 PO 4500120793 取消的数量。 2. 产品，布标，包装， 外箱时间一致。 Remark: 3. 需要第三方SGS验货，验货时间2024/04/29，请备1PC完整带包装样品供验货人员参考，可以从大货里拿，用完之后无损坏的话可以放回大货里，没有客户签版。 | V91: Abby Mai | W91: 1.4397 | X91: =I91*W91 -> 786.0762 | Y91: 85661-6.29 | Z91: 77515GQ5-S002-3L | AA91: 已入 | AE91: DG | AG91: =I91 -> 546 | AL91: =I91 -> 546 | AO91: =AG91 -> 546 | AT91: =I91/21 -> 26 | BM91: =AG91+AH91+AI91 -> 546
A92: 45362 | B92: TOYS "R" US (CANADA) LTD. | C92: 加拿大 | D92: 4500126476 | E92: 2401525626 | F92: 4500126476-20 | G92: 77515GQ5-S002 | H92: DIY厨艺大师 | I92: 1785 | J92: 0 | K92: 21 | L92: =I92/K92 -> 85 | M92: 45411 | N92: 45407 | O92: 5/7SGS验货 | P92: 消耗 PO 4500120793 取消的数量 已验货 | Q92: 5/8--5/14期间交仓 外箱要改 | R92: 45362 | S92: 无 | T92: 45344 | U92: 日期码格式：ZURU INC(BVI) 标准格式 日期：按实际生产日期 Packaging Info: 1. 出口加拿大市场，MA 3L UPC 版本包装+小部件警告语贴纸。消耗 PO 4500120793 取消的数量。 2. 产品，布标，包装， 外箱时间一致。 Remark: 3. 需要第三方SGS验货，验货时间2024/04/29，请备1PC完整带包装样品供验货人员参考，可以从大货里拿，用完之后无损坏的话可以放回大货里，没有客户签版。 | V92: Abby Mai | W92: 1.4397 | X92: =I92*W92 -> 2569.8645 | Y92: 85661-6.29 | Z92: 77515GQ5-S002-3L | AA92: 已入 | AE92: DG | AG92: =I92 -> 1785 | AL92: =I92 -> 1785 | AO92: =AG92 -> 1785 | AT92: =I92/21 -> 85 | BM92: =AG92+AH92+AI92 -> 1785
A93: 45302 | B93: TARGET US | C93: 美国 | D93: 4500123068 | E93: 0086-3112754-0581 | F93: 4500123068-10 | G93: 77515GQ5-S002 | H93: DIY厨艺大师 | I93: 9996 | J93: 0 | K93: 21 | L93: =I93/K93 -> 476 | M93: 45370 | N93: 45366 | P93: pass | Q93: 3/25 客上柜 | R93: 45310 | S93: 有 | T93: 45322 | U93: 日期码格式：ZURU INC(BVI) 标准格式 日期：按实际生产日期 Packaging Info: 产品包装MA 1L, MA PDQ Remark: 1. 77515GQ5-S002-MINI BRAND-MASTER CHEF MINI BRANDS-SERIES 1,21pcs/Gravity PDQ, 21pcs/CTN,No Inner,STD Color Assortment (White drop) 2. 产品包装MA 1L, MA PDQ, 产品UPC 显示193052061034; 11 assortment have the same ratio； 3. 外箱正唛左上角位置粘贴条码箱贴纸，每箱只贴一张，由ZURU订购。来料贴纸上显示的客户DPCI# 086-02-9598， UPC显示10193052061031; 4. 产品和包装上印刷 tracking code信息，格式为ZURU常规格式; 5. 出货方式：货代自提。 | V93: Holly Zheng | W93: 1.75 | X93: =I93*W93 -> 17493 | Y93: 84342-3.25 | Z93: 77515GQ5-S002 | AA93: 已入 | AE93: DG | AG93: =I93 -> 9996 | AK93: =AG93 -> 9996 | AO93: =AG93 -> 9996 | AS93: =I93/21 -> 476 | BM93: =AG93+AH93+AI93 -> 9996
A94: 45306 | B94: Bol.com | C94: 荷兰 | D94: 4500123217 | E94: 7322345 | F94: 4500123217-10 | G94: 77515-S001 | H94: DIY厨艺大师 | I94: 600 | J94: 0 | K94: 24 | L94: =I94/K94 -> 25 | M94: 45373 | N94: 45369 | P94: pass | Q94: 3/21 出货 | R94: 45306 | S94: 无 | T94: 45321 | U94: 日期码格式：ZURU INC(BVI) 标准格式 日期：按实际生产日期 Packaging Info: 77515 MA 3L(含5L warning) EAN 收缩膜+ NL 警语贴纸翻单4500119592+ MA 5L配件袋(+NL 警语贴纸翻单4500119592)+MA 5L 收藏指南+ MA 23L 说明书 Remark: 出口欧洲，所有产品需要出无闪粉版本 RBC item 需要用BABY EAN, 配比如下 | V94: Sandy Shao | W94: 1.19 | X94: =I94*W94 -> 714 | Y94: 84353-3.26 | Z94: 77515-S001-3L | AA94: 已入 | AE94: DG | AG94: =I94 -> 600 | AL94: =AG94 -> 600 | AO94: =AG94 -> 600 | BM94: =AG94+AH94+AI94 -> 600
A95: 45348 | B95: ZURU | C95: 库有 | D95: ZMPO24128 | G95: 77515GQ2-S001 | H95: DIY厨艺大师 | I95: 30套 | J95: 0 | K95: 50 | L95: =I95/K95 -> #VALUE! | M95: 45357 | N95: 45353 | R95: 周转箱 | S95: 无 | T95: 无 | U95: 左图中4款小散件需要组装好+配套吸塑 | Y95: 84848-5.21 | Z95: # | AE95: DG | AG95: =30*25 -> 750 | BA95: 30 | BM95: =AG95+AH95+AI95 -> 750
A96: 45323 | B96: ZURU | C96: 库有 | D96: ZMPO24101 | G96: 77515SK-S002 | H96: DIY厨艺大师 | I96: 480 | J96: 0 | K96: 60 | L96: =I96/K96 -> 8 | M96: 45359 | N96: 45355 | P96: pass | Q96: 3/15 送库有 | R96: 周转箱 | S96: 无 | T96: 无 | U96: 大货最新版本/产品请按大货比例入展架/箱唛参照邮件附件 | Y96: 84709-5.9 | Z96: 77515SK-S002 | AA96: 已入 | AE96: DG | AG96: =I96 -> 480 | AK96: =AG96 -> 480 | AO96: =AG96 -> 480 | BD96: =I96/60 -> 8 | BM96: =AG96+AH96+AI96 -> 480
A97: 45323 | B97: ZURU | C97: 库有 | D97: ZMPO24101 | G97: 77515SK1-S002 | H97: DIY厨艺大师 | I97: 240 | J97: 0 | K97: 30 | L97: =I97/K97 -> 8 | M97: 45359 | N97: 45355 | P97: pass | Q97: 3/15 送库有 | R97: 周转箱 | S97: 无 | T97: 无 | U97: 大货最新版本/产品请按大货比例入展架/箱唛参照邮件附件 | Y97: 84709-5.9 | Z97: 77515SK1-S002-1 | AA97: 已入 | AE97: DG | AG97: =I97 -> 240 | AK97: =AG97 -> 240 | AO97: =AG97 -> 240 | BG97: =I97/30 -> 8 | BH97: =BG97 -> 8 | BM97: =AG97+AH97+AI97 -> 240
A98: 45222 | B98: AMAZON UK | C98: 英国 | D98: 4500116507 | E98: 6XJ1JUJK | F98: 4500116507-10 | G98: 77515-S001 | H98: DIY厨艺大师 | I98: 1128 | J98: 0 | K98: 24 | L98: =I98/K98 -> 47 | M98: 45366 | N98: 45362 | P98: pass | Q98: 3/25 入仓 | R98: 空白外箱（加印带Zuru字样的黑色色带，除了邮包盒直接做外箱的产品 | S98: 有 | T98: 12/5 订外箱贴纸 | U98: 日期码格式：ZURU INC(BVI) 标准格式 日期：按实际生产日期 Packaging Info: Amazon UK: 1.77515:24pcs/ctn, no inner; MA 1L 收缩膜包装+2张贴纸(含FR/DE/IT/ES警告语<(>&<)>ITsorting label贴纸+FR sorting label 贴纸）;参考翻单PO#4500116490； 2. 验货时间不迟于2024/3/18； Remark: "1.空白外箱（加印带Zuru字样的最新logo，除了邮包盒直接做外箱的产品） + SSCC LABEL一张, 无箱唛. (SSCC LABEL贴在外箱正面的正中间，贴一面即可,贴纸离外箱边距必须至少3CM),SSCC贴纸由工厂直接跟勤得采购或者工厂自行采购，每一张SSCC Label都是唯一且 有不同流水及条码，且需要检查条码是否能正常扫描，另外，此贴纸印刷不可出现模糊，溢出及粘胶不牢易脱落等现象，如工厂不按此要求导致贴纸有任何问题产生 的罚款将由工厂承担一切责任 。’MADE IN CHINA 外箱只印一正一侧。 2. 出往UK的产品+包装务必打上UKCA logo ，否则客人会退货且当地会有罚款。 3.订单必须经过ZURU QC验货并且通过后方可出货。 4.法国订单要求包装不使用矿物油，请按要求提供以下其中一份文件再出货 ，产品出到法国被相关部门抽检出现包装不符合此要求的，供应商需要为此承担责任， 故此请严格把关 。 -油墨物质""由1 ~ 7个芳香环组成的MOAH""的包装检测报告，要求限值≤1.0%; -包装材料清单，包括包装油墨或物质的信息 -油墨制造商的证书。 5 . 每一批次出货只能有一个生产日期，不可多个生产日期混在同一批次出货； 6. 涉及到相关款式会有闪粉的或者微塑料的，请统一默认出无闪粉或者不含微塑料版本;" | V98: Crystal Chen | W98: 1.19 | X98: =I98*W98 -> 1342.32 | Y98: 84387-3.28 | Z98: 77515-S001 | AA98: 已入 | AE98: DG | AG98: =I98 -> 1128 | AK98: =AG98 -> 1128 | AO98: =AG98 -> 1128 | BM98: =AG98+AH98+AI98 -> 1128
A99: 45222 | B99: AMAZON UK | C99: 英国 | D99: 4500116507 | E99: 6TIMFG9G | F99: 4500116507-20 | G99: 77515-S001 | H99: DIY厨艺大师 | I99: 1200 | J99: 0 | K99: 24 | L99: =I99/K99 -> 50 | M99: 45366 | N99: 45362 | P99: pass | Q99: 3/25 入仓 | R99: 空白外箱（加印带Zuru字样的黑色色带，除了邮包盒直接做外箱的产品 | S99: 有 | T99: 12/5 订外箱贴纸 | U99: 日期码格式：ZURU INC(BVI) 标准格式 日期：按实际生产日期 Packaging Info: Amazon UK: 1.77515:24pcs/ctn, no inner; MA 1L 收缩膜包装+2张贴纸(含FR/DE/IT/ES警告语<(>&<)>ITsorting label贴纸+FR sorting label 贴纸）;参考翻单PO#4500116490； 2. 验货时间不迟于2024/3/18； Remark: "1.空白外箱（加印带Zuru字样的最新logo，除了邮包盒直接做外箱的产品） + SSCC LABEL一张, 无箱唛. (SSCC LABEL贴在外箱正面的正中间，贴一面即可,贴纸离外箱边距必须至少3CM),SSCC贴纸由工厂直接跟勤得采购或者工厂自行采购，每一张SSCC Label都是唯一且 有不同流水及条码，且需要检查条码是否能正常扫描，另外，此贴纸印刷不可出现模糊，溢出及粘胶不牢易脱落等现象，如工厂不按此要求导致贴纸有任何问题产生 的罚款将由工厂承担一切责任 。’MADE IN CHINA 外箱只印一正一侧。 2. 出往UK的产品+包装务必打上UKCA logo ，否则客人会退货且当地会有罚款。 3.订单必须经过ZURU QC验货并且通过后方可出货。 4.法国订单要求包装不使用矿物油，请按要求提供以下其中一份文件再出货 ，产品出到法国被相关部门抽检出现包装不符合此要求的，供应商需要为此承担责任， 故此请严格把关 。 -油墨物质""由1 ~ 7个芳香环组成的MOAH""的包装检测报告，要求限值≤1.0%; -包装材料清单，包括包装油墨或物质的信息 -油墨制造商的证书。 5 . 每一批次出货只能有一个生产日期，不可多个生产日期混在同一批次出货； 6. 涉及到相关款式会有闪粉的或者微塑料的，请统一默认出无闪粉或者不含微塑料版本;" | V99: Crystal Chen | W99: 1.19 | X99: =I99*W99 -> 1428 | Y99: 84387-3.28 | Z99: 77515-S001 | AA99: 已入 | AE99: DG | AG99: =I99 -> 1200 | AK99: =AG99 -> 1200 | AO99: =AG99 -> 1200 | BM99: =AG99+AH99+AI99 -> 1200
A100: 45222 | B100: AMAZON UK | C100: 英国 | D100: 4500116507 | E100: 62ZFPCCY | F100: 4500116507-30 | G100: 77515-S001 | H100: DIY厨艺大师 | I100: 1128 | J100: 0 | K100: 24 | L100: =I100/K100 -> 47 | M100: 45366 | N100: 45362 | P100: pass | Q100: 3/25 入仓 | R100: 空白外箱（加印带Zuru字样的黑色色带，除了邮包盒直接做外箱的产品 | S100: 有 | T100: 12/5 订外箱贴纸 | U100: 日期码格式：ZURU INC(BVI) 标准格式 日期：按实际生产日期 Packaging Info: Amazon UK: 1.77515:24pcs/ctn, no inner; MA 1L 收缩膜包装+2张贴纸(含FR/DE/IT/ES警告语<(>&<)>ITsorting label贴纸+FR sorting label 贴纸）;参考翻单PO#4500116490； 2. 验货时间不迟于2024/3/18； Remark: "1.空白外箱（加印带Zuru字样的最新logo，除了邮包盒直接做外箱的产品） + SSCC LABEL一张, 无箱唛. (SSCC LABEL贴在外箱正面的正中间，贴一面即可,贴纸离外箱边距必须至少3CM),SSCC贴纸由工厂直接跟勤得采购或者工厂自行采购，每一张SSCC Label都是唯一且 有不同流水及条码，且需要检查条码是否能正常扫描，另外，此贴纸印刷不可出现模糊，溢出及粘胶不牢易脱落等现象，如工厂不按此要求导致贴纸有任何问题产生 的罚款将由工厂承担一切责任 。’MADE IN CHINA 外箱只印一正一侧。 2. 出往UK的产品+包装务必打上UKCA logo ，否则客人会退货且当地会有罚款。 3.订单必须经过ZURU QC验货并且通过后方可出货。 4.法国订单要求包装不使用矿物油，请按要求提供以下其中一份文件再出货 ，产品出到法国被相关部门抽检出现包装不符合此要求的，供应商需要为此承担责任， 故此请严格把关 。 -油墨物质""由1 ~ 7个芳香环组成的MOAH""的包装检测报告，要求限值≤1.0%; -包装材料清单，包括包装油墨或物质的信息 -油墨制造商的证书。 5 . 每一批次出货只能有一个生产日期，不可多个生产日期混在同一批次出货； 6. 涉及到相关款式会有闪粉的或者微塑料的，请统一默认出无闪粉或者不含微塑料版本;" | V100: Crystal Chen | W100: 1.19 | X100: =I100*W100 -> 1342.32 | Y100: 84387-3.28 | Z100: 77515-S001 | AA100: 已入 | AE100: DG | AG100: =I100 -> 1128 | AK100: =AG100 -> 1128 | AO100: =AG100 -> 1128 | BM100: =AG100+AH100+AI100 -> 1128
...

Sheet 77515 DIY厨艺大师 旧排期
A1: ZURU （77515 Mini Brands 迷你球DIY厨艺系列）生产排期表 | G1: 走KM澳洲和出新西兰的说明书都要加纽扣电池警语贴纸 | N1: 77515出加拿大的3L都需要双语logo，最新版本77515GQ1 GQ2 GQ5 GQ6 SK SK1 纸袋 收藏指南 收缩膜 | U1: 77555SK1-S002这款是带底座 | AH1: 77515 | AN1: 收縮膜 | AU1: 收藏指南 | BB1: PDQ盒 | BK1: GQ1 | BW1: 77516 | CB1: 总MA | CC1: ='生产MA Summary'!O4 -> 4670000
A2: 香港接单日期 | B2: 第三方客户名称 | C2: 走货国家 | D2: ZURU PO NO# | E2: 第三方客户 PO NO# | F2: SKU | G2: ITEM# | H2: 中文名 | I2: PO数量 (pcs) | J2: 内箱装箱数量(pcs) | K2: 外箱装箱数量(pcs) | L2: 总箱数 | M2: 计划出货期 | N2: 计划验货期 | O2: 第三方客户公证行验货 | P2: 驗貨結果 | Q2: S/0船期 | R2: 箱唛资料(收到日期) | S2: 外箱贴纸 | T2: 客供贴纸AI(收到日期) | U2: 备注 | V2: ZURU 跟单 | W2: 单价USD | X2: 金额USD | Y2: 發票號 | Z2: 系统货号 | AA2: 是否入系统 | AB2: 采购单 | AC2: 已送情况 | AD2: 欠数 | AE2: 贴纸 | AF2: 生产地点 | AH2: 球数 | AI2: 无香味版本 | AJ2: 删除组合10（猪肉） | AK2: MA 3语 收缩膜 无条码 | AL2: 无UPC版本 | AM2: 新无UPC版本-C | AN2: MA 1语收缩膜 | AO2: MA 3语收缩膜 | AP2: MA 1语C版收缩膜 | AQ2: MA 3语C版本收缩膜 | AR2: 客版收缩膜 | AS2: ACTION 客版1L收缩膜+客版15L吊牌+客版UV灯说明书 | AT2: 客版 3L 收缩膜 | AU2: MA 5L语收藏指南 | AV2: MA 5LB版语收藏指南 | AW2: ESAL客版指南/说明书 | AX2: WM客版 | AY2: 外挂中文收藏指南+中文收藏指南(每一款都不同) | AZ2: MA 23L_C_IFUD声明补充说明书 | BA2: WEE带电说明书 | BB2: GQ5-S001 21PCS 1L | BC2: GQ5-S001 21PCS 3L | BD2: GQ5 B3L | BE2: WM 客版GQ5 | BF2: WM 客版GQ6 | BG2: GQ6-S001 12PCS 1L | BH2: GQ6-S001 12PCS 3L | BI2: GQ1-S001 13pcs 1L | BJ2: GQ1-S001 13pcs 3L | BK2: B版 1L | BL2: B版 3L | BM2: GQ2-S001 25pcs 1L | BN2: GQ2-S001 25pcs 3L | BO2: SK-S001 60PCS 1L 不含底座 配挂钩 | BP2: SK-S002 60PCS 1L 含底座 | BQ2: SK-S002 60PCS 3L 含底座 | BR2: 77515SK1-S002 30pcs 1L 含底座 | BS2: 77515SK1-S001 30pcs 3L 不带底座 | BT2: SK1底座 | BU2: FD客 77515GQ3 | BV2: 77515GQ3-S001 客版 8PCS | BW2: 圆筒 | BX2: 3L 彩纸 | BY2: B版本 3L 彩纸 | BZ2: 合计数量 | CB2: 已删减实单 | CC2: 2862563 | CD2: MA剩余 | CE2: =CC1-CC2 -> 1807437
A3: 45252 | B3: ZURU | C3: 库有 | D3: ZPO2311001 | G3: 77515-S001 | H3: DIY厨艺大师 | I3: 510 | J3: 0 | K3: 24 | L3: =I3/K3 -> 21.25 | M3: 45272 | N3: 45268 | P3: OK | R3: 周转箱 | S3: 无 | T3: 无 | Z3: 无 | AF3: DG | AH3: =I3 -> 510 | BZ3: =AH3+AI3+AJ3 -> 510 | CE3: =CE2-AH3-AI3-AJ3 -> 1806927
A4: 45279 | B4: ZURU | C4: 库有 | D4: ZMPO23783 | G4: 77515-S001 | H4: DIY厨艺大师 | I4: 5套 | J4: 0 | K4: 24 | L4: 1 | M4: 45288 | N4: 45285 | P4: OK | Q4: 3/14 寄深圳 | R4: 周转箱 | S4: 无 | T4: 无 | U4: 左图中每款散件各5PCS | Z4: 无 | AF4: DG | BZ4: =AH4+AI4+AJ4 -> 0 | CE4: =CE3-AH4-AI4-AJ4 -> 1806927
A5: 45317 | B5: ZURU | C5: 库有 | D5: ZMPO24079 | G5: 77515-S001 | H5: DIY厨艺大师 | I5: 200套散件 | J5: 0 | K5: 24 | L5: =I5/K5 -> #VALUE! | M5: 45351 | N5: 45348 | R5: 周转箱 | S5: 无 | T5: 无 | U5: 左图中14款酱每款200PCS/共2800PCS/麻烦用胶袋分装好14款一套为一袋 | Z5: 无 | AF5: DG | AH5: 200 | BZ5: =AH5+AI5+AJ5 -> 200 | CE5: =CE4-AH5-AI5-AJ5 -> 1806727
A6: 45350 | B6: ZURU | C6: 库有 | D6: ZMPO24135 | G6: 77515GQ1-S001 | H6: DIY厨艺大师 | I6: 50个满PDQ | J6: 0 | K6: 52 | L6: =I6/K6 -> #VALUE! | M6: 45371 | N6: 45367 | P6: pass | R6: 周转箱 | S6: 无 | T6: 无 | U6: 大货最新版本/PDQ里面的产品按大货比例入PDQ/大货标准箱装箱/箱唛参照邮件附件 | Z6: 77515GQ1-S001 | AA6: 已入 | AC6: 676 | AD6: 0 | AF6: DG | AG6: 在仓库 | AN6: =50*13 -> 650 | AU6: =50*13 -> 650 | BI6: 50 | BZ6: =AH6+AI6+AJ6 -> 0 | CE6: =CE5-AH6-AI6-AJ6 -> 1806727
A7: 45411 | B7: ZURU | C7: 库有 | D7: ZMPO24312 | G7: 77515-S001 | H7: DIY厨艺大师 | I7: 120套 | J7: 0 | K7: 24 | L7: =I7/K7 -> #VALUE! | M7: 45426 | N7: 45422 | U7: 大货订单最新版本/只需要全套散件，麻烦用胶袋分装好一套为一袋；备注：收到样品订单后尽快安排 ，注意样板品质质量要求要高于大货品质要求 ，送货时必须要附带送货单(没有送货单和QC检验合格报告的仓库一律拒绝收货)，请知悉，谢谢！ | Z7: # | AC7: 120 | AD7: 0 | AF7: DG | AG7: 在仓库 | BZ7: =AH7+AI7+AJ7 -> 0 | CE7: =CE6-AH7-AI7-AJ7 -> 1806727
A8: 45491 | B8: ZURU | C8: 库有 | D8: ZMPO24559 | G8: 77515-S001 | H8: DIY厨艺大师 | I8: 80套散件 | J8: 0 | K8: 24 | L8: =I8/K8 -> #VALUE! | M8: 45514 | N8: 45510 | R8: 45491 | S8: 无 | T8: 无 | U8: 大货订单最新版本/只需要全套散件，麻烦用胶袋分装好一套为一袋；备注：收到样品订单后尽快安排 ，注意样板品质质量要求要高于大货品质要求 ，送货时必须要附带送货单(没有送货单和QC检验合格报告的仓库一律拒绝收货)，请知悉，谢谢！ | Z8: # | AC8: 80 | AD8: 0 | AF8: DG | AG8: 在仓库 | BZ8: =AH8+AI8+AJ8 -> 0 | CE8: =CE7-AH8-AI8-AJ8 -> 1806727
A9: 45593 | B9: ZURU | C9: 库有 | D9: ZMPO24801 | G9: 77515-S001 | H9: DIY厨艺大师 | I9: 3000 | J9: 0 | K9: 24 | L9: =I9/K9 -> 125 | M9: 45608 | N9: 45612 | R9: 45593 | S9: 无 | T9: 无 | U9: 只需77198的白色空球，只需用外面透明收缩膜压缩就好，不需要彩色收缩膜 | V9: Angus | Z9: 77515-S001-2 | AA9: 已入 | AC9: 3000 | AD9: =AC9-I9 -> 0 | BZ9: =AH9+AI9+AJ9 -> 0 | CE9: =CE8-AH9-AI9-AJ9 -> 1806727
A10: 45608 | B10: CMS FAMOUS TOYS | C10: 加拿大 | D10: 4500151018 | E10: PO0000475 | F10: 4500151018-40 | G10: 77515GQ1-S003 | H10: DIY厨艺大师 | I10: 1495 | J10: 0 | K10: 13 | L10: =I10/K10 -> 115 | M10: 45651 | N10: 45647 | P10: pass | Q10: 1/2 截SI | R10: 45621 | S10: 无 | T10: 11/25 UPC贴纸 | U10: 日期码格式： 标准格式 日期：按实际生产日期 Tracking Code: Packaging Info: 77515GQ1 MA 多语EAN+UPC贴纸。UPC号码193052061034 Remark: 出加拿大 每款产品都需要加进口商贴纸 Zuru验货.日期跟踪码：产品外包装及产品本身都必须有日期跟踪码，ZURU标准格式日期码 | V10: Summer Mo | W10: 1.4071 | X10: =I10*W10 -> 2103.6145 | Y10: 88842-1.2 | Z10: 77515GQ1-S003-3L | AA10: 已入 | AC10: 1495 | AD10: =AC10-I10 -> 0 | AG10: 在仓库 七 | AH10: =I10 -> 1495 | AO10: =I10 -> 1495 | AU10: =I10 -> 1495 | BJ10: =I10/13 -> 115 | BZ10: =AH10+AI10+AJ10 -> 1495 | CE10: =CE9-AH10-AI10-AJ10 -> 1805232
A11: 45586 | B11: ROSS PROCUREMENT.INC | C11: 美国 | D11: 4500148421 | E11: 60190475 | F11: 4500148421-10 | G11: 77516-S001 | H11: DIY厨艺大师*2 | I11: 6000 | J11: 0 | K11: 12 | L11: =I11/K11 -> 500 | M11: 45653 | N11: 45649 | P11: pass | Q11: 1/3 截SI | R11: 45588 | S11: 无 | T11: 11/20 客供价格贴纸+UPC贴纸 | U11: 日期码格式： 标准格式 日期：按实际生产日期 Packaging Info: URU MA UPC 收缩膜+客版铜版纸+PVC桶 + 客供价格贴纸，出口美国 , 优先使用MA 1L 最新版本 。 Remark: 1.ZURU MA UPC 收缩膜+客版铜版纸+PVC桶 + 客供价格贴纸，出口美国 , 优先使用MA 1L 最新版本 。 2.价格贴纸位于包装正面右下角，不挡住重要信息即可，可适当调整 ，价格贴纸由跟单提供。 3.标准日期码格式，产品和包装必须有日期码 。 4.同个产品同个货期不可出现不同的包装。 5. PVC 桶中球不能出现完全相同的ASSORTMENT ， 即同一个PVC 中球里的ASSORTMENT 需要不同。 以免消费者失望。 6.PVC 桶上加上 MINI BRANDS 的LOGO 贴纸 （ ZURU 统一要求的） 7.收缩膜可使用标版带UPC条码MA，无需白色贴纸覆盖。 8. #77516 可用MA 3L包装，用UPC 贴纸覆盖EAN 条码。 | V11: Sophia Zhou | W11: 3.0438 | X11: =I11*W11 -> 18262.8 | Y11: 88928-1.7 | Z11: 77516-S001-1L | AA11: 已入 | AC11: 6000 | AD11: =AC11-I11 -> 0 | AG11: 在仓库 七 | AH11: =I11*2 -> 12000 | AO11: =AH11 -> 12000 | AU11: =AH11 -> 12000 | BW11: =I11 -> 6000 | BX11: =I11 -> 6000 | BZ11: =AH11+AI11+AJ11 -> 12000 | CE11: =CE10-AH11-AI11-AJ11 -> 1793232
A12: 45614 | B12: Amazon Mexico, S. DE R.L. DE CV | C12: 墨西哥 | D12: 4500151559 | E12: 2YATGWVR | F12: 4500151559-10 | G12: 77515-S001 | H12: DIY厨艺大师 | I12: 24 | J12: 0 | K12: 24 | L12: =I12/K12 -> 1 | M12: 45649 | N12: 45645 | P12: 自检 | Q12: 1/3 交仓 | R12: 空白外箱加印ZURU Logo+MADE IN CHINA | S12: 有 | T12: 12/4UPC贴纸+进口商贴纸+12/6 SSCC贴纸 | U12: 日期码格式：ZURU INC(BVI) 标准格式 日期：按实际生产日期 Packaging Info: 77515: MA 3L+UPC贴纸+进口商贴纸+SSCC贴纸 Remark: Amazon FOB订单，出口Mexico，外箱最长边不能超过25" （超过了，case pack只能为1），不符合要求的大货，一律不接受。 1.空白外箱加印ZURU Logo+MADE IN CHINA+SSCC LABEL(客供贴纸），无shipping mark,日期使用ZURU 标准版本。SSCC Label显示的是客人自己的item#，SSCC Lab el 贴在外箱正面的正中间，贴一面即可，跟单订购，贴纸离外箱距必须至少3cm,每一张SSCC Label都是唯一且有不同流水及条码的，没有损耗，绝对不可贴错，否 则贴错或损坏一张会导致全部都错，千万要注意！ 2. 日期码使用ZURU标准版 3. 客户PO备注在remark处 4.77515: 3PCS AG13 Batteries(Included) | V12: Zoe Luo | W12: 1.3938 | X12: =I12*W12 -> 33.4512 | Y12: 88897-1.6 | Z12: 77515-S001-3L | AA12: 已入 | AC12: 240 | AD12: =AC12-I12 -> 216 | AG12: 在仓库 七 | AH12: =I12 -> 24 | AO12: =I12 -> 24 | AU12: =I12 -> 24 | BZ12: =AH12+AI12+AJ12 -> 24 | CE12: =CE11-AH12-AI12-AJ12 -> 1793208
A13: 45614 | B13: Amazon Mexico, S. DE R.L. DE CV | C13: 墨西哥 | D13: 4500151559 | E13: 64SP3ZYY | F13: 4500151559-100 | G13: 77515-S001 | H13: DIY厨艺大师 | I13: 384 | J13: 0 | K13: 24 | L13: =I13/K13 -> 16 | M13: 45649 | N13: 45645 | P13: 自检 | Q13: 1/3 交仓 | R13: 空白外箱加印ZURU Logo+MADE IN CHINA | S13: 有 | T13: 12/4UPC贴纸+进口商贴纸+12/6 SSCC贴纸 | U13: 日期码格式：ZURU INC(BVI) 标准格式 日期：按实际生产日期 Packaging Info: 77515: MA 3L+UPC贴纸+进口商贴纸+SSCC贴纸 Remark: Amazon FOB订单，出口Mexico，外箱最长边不能超过25" （超过了，case pack只能为1），不符合要求的大货，一律不接受。 1.空白外箱加印ZURU Logo+MADE IN CHINA+SSCC LABEL(客供贴纸），无shipping mark,日期使用ZURU 标准版本。SSCC Label显示的是客人自己的item#，SSCC Lab el 贴在外箱正面的正中间，贴一面即可，跟单订购，贴纸离外箱距必须至少3cm,每一张SSCC Label都是唯一且有不同流水及条码的，没有损耗，绝对不可贴错，否 则贴错或损坏一张会导致全部都错，千万要注意！ 2. 日期码使用ZURU标准版 3. 客户PO备注在remark处 4.77515: 3PCS AG13 Batteries(Included) | V13: Zoe Luo | W13: 1.3938 | X13: =I13*W13 -> 535.2192 | Y13: 88897-1.6 | Z13: 77515-S001-3L | AA13: 已入 | AC13: 384 | AD13: =AC13-I13 -> 0 | AG13: 在仓库 七 | AH13: =I13 -> 384 | AO13: =I13 -> 384 | AU13: =I13 -> 384 | BZ13: =AH13+AI13+AJ13 -> 384 | CE13: =CE12-AH13-AI13-AJ13 -> 1792824
A14: 45621 | B14: WAL-MART STORES INC. USA | C14: 美国 | D14: 4500152220 | E14: RIDGEVILLE SC0881401673 | F14: 4500152220-10 | G14: 77515GQ5-S002 | H14: DIY厨艺大师 | I14: 966 | J14: 0 | K14: 21 | L14: =I14/K14 -> 46 | M14: 45649 | N14: 45645 | O14: 12/23 BV | P14: pass | Q14: 1/6 截SI | R14: 45621 | S14: 有 | T14: 12/6RFID | U14: 日期码格式：ZURU DGYYYYMMDD CHINA(日期避开周末和法定节假日即可） 日期：按实际生产日期 Tracking Code: Packaging Info: 77515GQ5-S002 1.包装要求： MA B版 1L收缩膜+客版 A版 5L收藏指南+MA A版 5L纸袋+MA A版 23L说明书+客版 1L PDQ，翻单：4500142765 每pcs产品上要贴1张RFID贴纸，贴纸由ZURU提供，贴纸位置请严格按照我们签回的签板； Remark: 77515GQ5-S002 1.包装要求： MA B版 1L收缩膜+客版 A版 5L收藏指南+MA A版 5L纸袋+MA A版 23L说明书+客版 1L PDQ，翻单：4500142765 每pcs产品上要贴1张RFID贴纸，贴纸由ZURU提供，贴纸位置请严格按照我们签回的签板； 2. 外箱印刷带条码的RFID箱唛：RFID紫色色带+WM Dept.图标+RFID图标+ITF-14条码，四面右下角印刷ZURU logo, ITFF条码只印刷在正唛一面，在加印的时候确保 条形码能扫描出来，外箱侧面任一角落加印："MADE IN CHINA" 字样； 3. 在产品上和包装上要有日期码、以及要有MADE IN CHINA和ZURU字样； 4. 产品如有扎带口要剪平，不能刮手。 5. 此单需要验货，请多备料 6. 此单以loose carton出货，21pcs/PDQ/CTN | V14: Maggie Xie | W14: 1.4585 | X14: =I14*W14 -> 1408.911 | Z14: 77515GQ5-S002-WM | AA14: 已入 | AC14: 966 | AD14: =AC14-I14 -> 0 | AG14: 在仓库 七 | AH14: =I14 -> 966 | AN14: =I14 -> 966 | AX14: =I14 -> 966 | BE14: =I14/21 -> 46 | BZ14: =AH14+AI14+AJ14 -> 966 | CE14: =CE13-AH14-AI14-AJ14 -> 1791858
A15: 45621 | B15: WAL-MART STORES INC. USA | C15: 美国 | D15: 4500152220 | E15: EASTVALE08814 01675 | F15: 4500152220-20 | G15: 77515GQ5-S002 | H15: DIY厨艺大师 | I15: 1197 | J15: 0 | K15: 21 | L15: =I15/K15 -> 57 | M15: 45649 | N15: 45645 | O15: 12/23 BV | P15: pass | Q15: 1/4 截仓 | R15: 45621 | S15: 有 | T15: 12/6RFID | U15: 日期码格式：ZURU DGYYYYMMDD CHINA(日期避开周末和法定节假日即可） 日期：按实际生产日期 Tracking Code: Packaging Info: 77515GQ5-S002 1.包装要求： MA B版 1L收缩膜+客版 A版 5L收藏指南+MA A版 5L纸袋+MA A版 23L说明书+客版 1L PDQ，翻单：4500142765 每pcs产品上要贴1张RFID贴纸，贴纸由ZURU提供，贴纸位置请严格按照我们签回的签板； Remark: 77515GQ5-S002 1.包装要求： MA B版 1L收缩膜+客版 A版 5L收藏指南+MA A版 5L纸袋+MA A版 23L说明书+客版 1L PDQ，翻单：4500142765 每pcs产品上要贴1张RFID贴纸，贴纸由ZURU提供，贴纸位置请严格按照我们签回的签板； 2. 外箱印刷带条码的RFID箱唛：RFID紫色色带+WM Dept.图标+RFID图标+ITF-14条码，四面右下角印刷ZURU logo, ITFF条码只印刷在正唛一面，在加印的时候确保 条形码能扫描出来，外箱侧面任一角落加印："MADE IN CHINA" 字样； 3. 在产品上和包装上要有日期码、以及要有MADE IN CHINA和ZURU字样； 4. 产品如有扎带口要剪平，不能刮手。 5. 此单需要验货，请多备料 6. 此单以loose carton出货，21pcs/PDQ/CTN | V15: Maggie Xie | W15: 1.4585 | X15: =I15*W15 -> 1745.8245 | Z15: 77515GQ5-S002-WM | AA15: 已入 | AC15: 1197 | AD15: =AC15-I15 -> 0 | AG15: 在仓库 七 | AH15: =I15 -> 1197 | AN15: =I15 -> 1197 | AX15: =I15 -> 1197 | BE15: =I15/21 -> 57 | BZ15: =AH15+AI15+AJ15 -> 1197 | CE15: =CE14-AH15-AI15-AJ15 -> 1790661
A16: 45621 | B16: WAL-MART STORES INC. USA | C16: 美国 | D16: 4500152220 | E16: SUFFOLK088140 1672 | F16: 4500152220-30 | G16: 77515GQ5-S002 | H16: DIY厨艺大师 | I16: 987 | J16: 0 | K16: 21 | L16: =I16/K16 -> 47 | M16: 45649 | N16: 45645 | O16: 12/23 BV | P16: pass | Q16: 1/3 截仓 | R16: 45621 | S16: 有 | T16: 12/6RFID | U16: 日期码格式：ZURU DGYYYYMMDD CHINA(日期避开周末和法定节假日即可） 日期：按实际生产日期 Packaging Info: 77515GQ5-S002 1.包装要求： MA B版 1L收缩膜+客版 A版 5L收藏指南+MA A版 5L纸袋+MA A版 23L说明书+客版 1L PDQ，翻单：4500142765 每pcs产品上要贴1张RFID贴纸，贴纸由ZURU提供，贴纸位置请严格按照我们签回的签板； Remark: 77515GQ5-S002 1.包装要求： MA B版 1L收缩膜+客版 A版 5L收藏指南+MA A版 5L纸袋+MA A版 23L说明书+客版 1L PDQ，翻单：4500142765 每pcs产品上要贴1张RFID贴纸，贴纸由ZURU提供，贴纸位置请严格按照我们签回的签板； 2. 外箱印刷带条码的RFID箱唛：RFID紫色色带+WM Dept.图标+RFID图标+ITF-14条码，四面右下角印刷ZURU logo, ITFF条码只印刷在正唛一面，在加印的时候确保 条形码能扫描出来，外箱侧面任一角落加印："MADE IN CHINA" 字样； 3. 在产品上和包装上要有日期码、以及要有MADE IN CHINA和ZURU字样； 4. 产品如有扎带口要剪平，不能刮手。 5. 此单需要验货，请多备料 6. 此单以loose carton出货，21pcs/PDQ/CTN | V16: Maggie Xie | W16: 1.4585 | X16: =I16*W16 -> 1439.5395 | Y16: 88843-1.2 | Z16: 77515GQ5-S002-WM | AA16: 已入 | AC16: 987 | AD16: =AC16-I16 -> 0 | AG16: 在仓库 七 | AH16: =I16 -> 987 | AN16: =I16 -> 987 | AX16: =I16 -> 987 | BE16: =I16/21 -> 47 | BZ16: =AH16+AI16+AJ16 -> 987 | CE16: =CE15-AH16-AI16-AJ16 -> 1789674
A17: 45607 | B17: TARGET US | C17: 美国 | D17: 4500150926 | E17: 10001033543-3891 | F17: 4500150926-10 | G17: 77515GQ5-S002 | H17: DIY厨艺大师 | I17: 3675 | J17: 0 | K17: 21 | L17: =I17/K17 -> 175 | M17: 45653 | N17: 45649 | P17: pass | Q17: 1/9 客上柜 | R17: 45621 | S17: 有 | T17: 12/6 条码箱贴纸 | U17: 日期码格式：ZURU INC(BVI) 标准格式 日期：按实际生产日期 Packaging Info: 77515GQ5：MA包装, MA 1L 收缩膜, MA 1L PDQ； Remark: 77515GQ5: 1. 77515GQ5-S002-MINI BRAND-MASTER CHEF MINI BRANDS-SERIES 1,21pcs/Gravity PDQ, 21pcs/CTN,No Inner,STD Color Assortment 2. MA包装, MA 1L 收缩膜, MA 1L PDQ；收缩膜上的UPC显示193052061034; 3. 外箱正唛左上角位置粘贴条码箱贴纸，每箱只贴一张，由ZURU订购。来料贴纸上显示的客户DPCI# 086-02-9598， UPC显示10193052061031; 此订单所有型号： 1. 产品和包装上印刷 tracking code信息，格式为ZURU常规格式; 2. 出货方式：货代自提 | V17: Holly Zheng | W17: 1.4397 | X17: =W17*L17 -> 251.9475 | Y17: 88960-1.9 | Z17: 77515GQ5-S002 | AA17: 已入 | AC17: 3675 | AD17: =AC17-I17 -> 0 | AG17: 在仓库 七 | AH17: =I17 -> 3675 | AN17: =AH17 -> 3675 | AU17: =I17 -> 3675 | BB17: =I17/21 -> 175 | BZ17: =AH17+AI17+AJ17 -> 3675 | CE17: =CE16-AH17-AI17-AJ17 -> 1785999
A18: 45621 | B18: London Supply Group SA | C18: 乌拉圭 | D18: 4500152280 | F18: 4500152280-70 | G18: 77515GQ2-S001 | H18: DIY厨艺大师 | I18: 400 | J18: 0 | K18: 50 | L18: =I18/K18 -> 8 | M18: 45660 | N18: 45656 | P18: 自检 | Q18: 1/8 截SI | R18: 45623 | S18: 无 | T18: 无 | U18: 日期码格式：ZURU INC(BVI) 标准格式 日期：按实际生产日期 Tracking Code: Packaging Info: 77515GQ2:MA 1L包装+MA 多语说明（含西语）+箱唛，无进口商贴纸 Remark: | V18: Ava Liang | W18: 1.4395 | X18: =I18*W18 -> 575.8 | Y18: 88896-1.6 | Z18: 77515GQ2-S001 | AA18: 已入 | AC18: 400 | AD18: =AC18-I18 -> 0 | AG18: 在仓库 | AH18: =I18 -> 400 | AN18: =AH18 -> 400 | AU18: =I18 -> 400 | BM18: =I18/25 -> 16 | BZ18: =AH18+AI18+AJ18 -> 400 | CE18: =CE17-AH18-AI18-AJ18 -> 1785599
A19: 45643 | B19: WALGREEN CO. | C19: 北美 | D19: MPO03150 | F19: 实单代替MPOWAL034手工单 | G19: 77515-S001-MSLD109 | H19: DIY厨艺大师 | I19: 31962 | J19: 0 | K19: 24 | L19: =I19/K19 -> 1331.75 | M19: 45667 | N19: 45663 | O19: 指定日期码 | P19: pass | Q19: 1/10 送库有 | R19: 周转箱 | S19: 无 | T19: 10/24 WIC贴纸 | U19: Remark:1.取消手工单MPOWAL034 子件#77515，改下正式单MPO031502.订单要求参考MPOWAL034 3.分三批送货 第一批 77515 -6396pcs(已送货) 第二批 77515--19188pcs(已送货) 第三批 77515--6378pcs(待安排送货) | V19: Cara | W19: 1.3304 | X19: =I19*W19 -> 42522.245 | Y19: 94403-2.27 94411-2.28 | Z19: 77515-S001-3L | AA19: 已入 | AG19: 在仓库6396 | AH19: =I19 -> 31962 | AO19: =I19 -> 31962 | AU19: =I19 -> 31962 | BZ19: =AH19+AI19+AJ19 -> 31962 | CE19: =CE18-AH19-AI19-AJ19 -> 1753637
A20: 45604 | B20: ASDA STORES LTD | C20: 英国 | D20: 4500150696 | F20: 4500150696-40 | G20: 77515SLB-S003 | H20: DIY厨艺大师卡板装 | I20: 975 | K20: 975 | L20: =I20/K20 -> 1 | M20: 45656 | N20: 45652 | P20: pass | Q20: 1/8 截SI | R20: 45625 | S20: 有 | T20: UPC贴纸翻单145734+slip sheet贴纸 | U20: 日期码格式：ZURU INC(BVI) 标准格式 日期：按实际生产日期 Packaging Info: 7.77515SLB-S003 77515GQ1-S003: MA 3L A版PDQ+MA 3L B版收缩膜+1张UPC贴纸(贴纸翻PO#4500145734)+其他MA最新版包装 UPC#193052061034，请先检查条码是否正确再安排做货 Slip sheet：13PCS/PDQ/CTN(Carton SIZE:23*22*33CM),15*5H=75CTN=975PCS/SLIP SHEET;一共需要1套slip sheet； Slip Sheet打包好后，需要在正唛、侧唛右下角各贴一张slip sheet贴纸，直接用A4纸打印出来即可，贴纸尺寸160mm width x 140mm high；Slip Sheet尺寸限制为100*115*130CM，一旦实际SLIP SHEET尺寸超过这个尺寸，请提前通知ZURU跟单，需同客人确认才能量产和出货; Remark: 1. 产品及包装需要印UKCA图标，包装需要有ZURU UK LTD/ZURU France地址信息，QC同事请核查，如有问题与跟单确认 2. 产品/包装/外箱都需要打ZURU格式日期码，日期必须为法定工作日。 3. 需要符合欧洲标准不能含有闪粉和微塑料，否则不合法规会有客诉产生 | V20: Amy Ding | W20: 1294.836 | X20: =W20*L20 -> 1294.836 | Y20: 88944-1.8 | Z20: 77515SLB-S003 | AA20: 已入 | AC20: 975 | AD20: =AC20-I20 -> 0 | AG20: 在仓库 七 | AH20: =I20 -> 975 | AO20: =I20 -> 975 | AU20: =I20 -> 975 | BJ20: =I20/13 -> 75 | BZ20: =AH20+AI20+AJ20 -> 975 | CE20: =CE19-AH20-AI20-AJ20 -> 1752662
A21: 45604 | B21: THE ENTERTAINER | C21: 英国 | D21: 4500150141 | E21: 4500150141-2 | F21: 4500150141-70 | G21: 77515GQ1-S001 | H21: DIY厨艺大师 | I21: 2496 | J21: 0 | K21: 52 | L21: =I21/K21 -> 48 | M21: 45657 | N21: 45653 | O21: 加多一张2国语言电池说明书 | P21: pass | Q21: 1/4 截SI | R21: 45610 | S21: 无 | T21: 条码贴翻订单4500144795 | U21: 日期码格式：ZURU INC(BVI) 标准格式 日期：按实际生产日期 Packaging Info: 77515GQ1：MA最新1L配套包装+客户EAN条码贴一张覆盖ZURU 原条码，条码贴翻订单4500144795。 另外产品内包装再加多一张2国语言电池说明书 ，即产品内含2张说明书 （ZURU标准说明书1张+2国语言电池说明书），两国语言说明书翻订单4500148687 Remark: *MA版本按工厂现有最新库存即可，订单出英国，请注意检查产品及包装应带UKCA图标，包装显示ZURU UK LTD信息，QC同事请查核，如有问题与跟单确认。 *生产日期按实际（法定工作日），按ZURU标准格式即可 ，但是请知悉包装日期码需要早于或者等于外箱日期码 ，不能晚于外箱日期码 *请注意所有订单都需要经过ZURU QC验货并且通过后方可出货 *条码以订单显示为准 ，请安排生产前先核对 ，有问题请提出。 *所有产品按符合欧洲标准走货，需要是不含微塑料版本 。 *涉及到硼的，如可选择情况下应使用低硼版本 （slime 类别低硼一般低于300ppm)，无选择的应与跟单复核再安排 。 Order Modifiable Records Revision # Date: Comment: 1 11- | V21: Sherry Lu | W21: 1.4046 | X21: =I21*W21 -> 3505.8816 | Y21: 88877-1.4 | Z21: 77515GQ1-S001 | AA21: 已入 | AC21: 2496 | AD21: =AC21-I21 -> 0 | AG21: 在仓库 七 | AH21: =I21 -> 2496 | AN21: =AH21 -> 2496 | AU21: =AH21 -> 2496 | BI21: =AH21/13 -> 192 | BZ21: =AH21+AI21+AJ21 -> 2496 | CE21: =CE20-AH21-AI21-AJ21 -> 1750166
A22: 45618 | B22: CRG | C22: 哥斯达黎加 | D22: 4500152087 | E22: ZU01-25 | F22: 4500152087-110 | G22: 77515GQ2-S001 | H22: DIY厨艺大师 | I22: 3600 | J22: 0 | K22: 50 | L22: =I22/K22 -> 72 | M22: 45660 | N22: 45656 | P22: pass | Q22: 1/8 截SI | R22: 45623 | S22: 无 | T22: 12/10 进口商贴纸 | U22: 日期码格式：ZURU INC(BVI) 标准格式 日期：按实际生产日期 Packaging Info: 77515GQ2:MA 1L包装+进口商贴纸+箱唛 Remark: | V22: Ava Liang | W22: 1.4344 | X22: =I22*W22 -> 5163.84 | Y22: 88961-1.9 | Z22: 77515GQ2-S001 | AA22: 已入 | AC22: 3600 | AD22: =AC22-I22 -> 0 | AG22: 在仓库 | AH22: =I22 -> 3600 | AN22: =AH22 -> 3600 | AU22: =I22 -> 3600 | BM22: =I22/25 -> 144 | BZ22: =AH22+AI22+AJ22 -> 3600 | CE22: =CE21-AH22-AI22-AJ22 -> 1746566
A23: 45579 | B23: ASDA STORES LTD | C23: 英国 | D23: 4500147530 | E23: 2950866070 | F23: 4500147530-20 | G23: 77515SLB-S003 | H23: DIY厨艺大师卡板装 | I23: 1950 | J23: 0 | K23: 975 | L23: =I23/K23 -> 2 | M23: 45657 | N23: 45656 | P23: pass | Q23: 1/8 截SI | R23: 45636 | S23: 有 | T23: UPC贴纸翻单145734+slip sheet贴纸 | U23: 日期码格式：ZURU INC(BVI) 标准格式 日期：按实际生产日期 Packaging Info:77515SLB-S003 77515GQ1-S003: MA 3L A版PDQ+MA 3L B版收缩膜+1张UPC贴纸(贴纸翻PO#4500145734)+其他MA最新版包装 UPC#193052061034，请先检查条码是否正确再安排做货 Slip sheet：13PCS/PDQ/CTN(Carton SIZE:23*22*33CM),15*5H=75CTN=975PCS/SLIP SHEET;一共需要2套slip sheet； Slip Sheet打包好后，需要在正唛、侧唛右下角各贴一张slip sheet贴纸，直接用A4纸打印出来即可，贴纸尺寸160mm width x 140mm high；Slip Sheet尺寸限制为 100*115*130CM，一旦实际SLIP SHEET尺寸超过这个尺寸，请提前通知ZURU跟单，需同客人确认才能量产和出货; | V23: Sheba Ye | W23: 1289.8635 | X23: =W23*L23 -> 2579.727 | Y23: 88942-1.8 | Z23: 77515SLB-S003 | AA23: 已入 | AC23: =1924+26 -> 1950 | AD23: =AC23-I23 -> 0 | AG23: 在仓库 七 | AH23: =I23 -> 1950 | AO23: =I23 -> 1950 | AU23: =I23 -> 1950 | BJ23: =I23/13 -> 150 | BZ23: =AH23+AI23+AJ23 -> 1950 | CE23: =CE22-AH23-AI23-AJ23 -> 1744616
A24: 45555 | B24: ASDA STORES LTD | C24: 英国 | D24: 4500145734 | E24: 2950866059 | F24: 4500145734-10 | G24: 77515SLB-S003 | H24: DIY厨艺大师卡板装 | I24: 1950 | J24: 0 | K24: 975 | L24: =I24/K24 -> 2 | M24: 45657 | N24: 45656 | P24: pass | Q24: 1/8 截SI | R24: 45636 | S24: 有 | T24: 9/20 UPC贴纸+slip sheet贴纸 | U24: 日期码格式：ZURU INC(BVI) 标准格式 日期：按实际生产日期 Packaging Info: 77515SLB-S003 77515GQ1-S003: MA 3L A版PDQ+MA 3L B版收缩膜+1张UPC贴纸+其他MA最新版包装 UPC#193052061034，请先检查条码是否正确再安排做货 Slip sheet：13PCS/PDQ/CTN(Carton SIZE:23*22*33CM),15*5H=75CTN=975PCS/SLIP SHEET;一共需要2套slip sheet； Slip Sheet打包好后，需要在正唛、侧唛右下角各贴一张slip sheet贴纸，直接用A4纸打印出来即可，贴纸尺寸160mm width x 140mm high；Slip Sheet尺寸限制为 100*115*130CM，一旦实际SLIP SHEET尺寸超过这个尺寸，请提前通知ZURU跟单，需同客人确认才能量产和出货; Remark: 1. 产品及包装需要印UKCA图标，包装需要有ZURU UK LTD/ZURU France地址信息，QC同事请核查，如有问题与跟单确认 2. 产品/包装/外箱都需要打ZURU格式日期码，日期必须为法定工作日。 3. 需要符合欧洲标准不能含有闪粉和微塑料，否则不合法规会有客诉产生 | V24: Sheba Ye | W24: 1289.8635 | X24: =W24*L24 -> 2579.727 | Y24: 88943-1.8 | Z24: 77515SLB-S003 | AA24: 已入 | AC24: 1950 | AD24: =AC24-I24 -> 0 | AG24: 在仓库 七 | AH24: =I24 -> 1950 | AO24: =I24 -> 1950 | AU24: =I24 -> 1950 | BJ24: =I24/13 -> 150 | BZ24: =AH24+AI24+AJ24 -> 1950 | CE24: =CE23-AH24-AI24-AJ24 -> 1742666
A25: 45618 | B25: TARGET US | C25: 美国 | D25: 4500152133 | E25: 10001033542-3890 | F25: 4500152133-10 | G25: 77515GQ5-S002 | H25: DIY厨艺大师 | I25: 5061 | J25: 0 | K25: 21 | L25: =I25/K25 -> 241 | M25: 45657 | N25: 45657 | P25: pass | Q25: 1/6 客上柜 | R25: 45630 | S25: 有 | T25: 12/19条码箱贴纸 | U25: 日期码格式：ZURU INC(BVI) 标准格式 日期：按实际生产日期 Tracking Code: Packaging Info: 77515GQ5: MA包装, MA 1L 收缩膜, MA 1L PDQ； Remark: 77515GQ5: 1. 77515GQ5-S002-MINI BRAND-MASTER CHEF MINI BRANDS-SERIES 1,21pcs/Gravity PDQ, 21pcs/CTN,No Inner,STD Color Assortment 2. MA包装, MA 1L 收缩膜, MA 1L PDQ；收缩膜上的UPC显示193052061034; 3. 外箱正唛左上角位置粘贴条码箱贴纸，每箱只贴一张，由ZURU订购。来料贴纸上显示的客户DPCI# 086-02-9598， UPC显示10193052061031; 此订单所有型号： 1. 产品和包装上印刷 tracking code信息，格式为ZURU常规格式; 2. 出货方式：货代自提 | V25: Holly Zheng | W25: 1.4585 | X25: =I25*W25 -> 7381.4685 | Y25: 88895-1.6 | Z25: 77515GQ5-S002 | AA25: 已入 | AC25: 5061 | AD25: =AC25-I25 -> 0 | AG25: 在仓库 七 | AH25: =I25 -> 5061 | AN25: =I25 -> 5061 | AU25: =I25 -> 5061 | BB25: =I25/21 -> 241 | BZ25: =AH25+AI25+AJ25 -> 5061 | CE25: =CE24-AH25-AI25-AJ25 -> 1737605
A26: 45621 | B26: KMART AUSTRALIA LTD(NEW ZEALAND) | C26: 新西兰 | D26: 4500152293 | E26: 20478301 | F26: 4500152293-40 | G26: 77515GQ1-S003 | H26: DIY厨艺大师 | I26: 1313 | J26: 0 | K26: 13 | L26: =I26/K26 -> 101 | M26: 45663 | N26: 45663 | P26: pass | Q26: 1/8 交仓 | R26: 45629 | S26: 有 | T26: 12/16 SSCC LABEL（客供贴纸)+纽扣电池警告语贴纸/防盗贴纸翻单121356 | U26: 日期码格式：ZURU INC(BVI) 标准格式 日期：按实际生产日期 Tracking Code: Packaging Info: 77515GQ1:MA英语UPC版本包装（收缩膜和说明书, MA首选1L，如无1L可用多语且含英语的配套多语包装) + 1张说明书纽扣电池警告语贴纸（贴纸以及位置图翻单PO# 4500121356）+ 1张收缩膜纽扣电池警告语贴纸（贴纸以及位置图翻单PO#4500121356）+ 1张防盗贴纸 (贴纸以及位置图翻单PO#4500121356）+ 箱唛 + 外箱SSCC La bel Remark: 1.请务必按时完货，验货。并且按期送货入货代指定仓库，如果晚了导致船期Delay将会有罚金产生或者客户要求空运，所产生的罚金和空运费由工厂承担。 2.SSCC 外箱贴纸请同纸箱瓦楞纸方向（竖纹向）垂直，即外箱贴纸横着贴(注意条码不要被胶带粘住），贴1pc，贴1面正唛，封箱胶纸不能挡住贴纸内容。外箱贴纸 离外箱边距离不少于2cm。 3.外箱材质为ZURU标准； 4.此单需使用KMART封箱胶上下工字型封箱;从2019年6月开始，要用KMART 新版封箱胶带，此单要用"ANKO"封箱胶带 5.此单出口新西兰，请按相应的澳新标准生产； 6.产品和包装上生产批号的显示格式ZURU标准日期码格式 7.外箱信息不可手写，重量和体积需要与实际的一致(不可手写） 8. 每款item装箱后的G.W.超过10KG或者CBM超过0.13,(9.5KG或者以上，四舍五入后也属于10KG) 需在外箱上加印超 重或者Bulky LOGO，若发现我们资料没有，请 帮忙提醒 1)重量超过10kg但不超过16kg且CBM不超过0.13,10-16kg 超重logo 2）CBM超过0.13且重量少于17kg，bulky logo 3）不属于以上两种情况，需要使用相应重量范围内的超重logo 4）超重logo需要在外箱四面都印刷(箱唛右上角，两面侧唛超重logo需要尽量靠近毛重)，尺寸为:110mm height* 95mm width 9. 实际外箱重量跟印在箱唛上的数据差异不能超3%，尺寸按实际数据印刷 | V26: Lydia Wu | W26: 1.4432 | X26: =I26*W26 -> 1894.9216 | Y26: 88992-1.11 | Z26: 77515GQ1-S003 | AA26: 已入 | AC26: 1313 | AD26: =AC26-I26 -> 0 | AG26: 在仓库 | AH26: =I26 -> 1313 | AN26: =I26 -> 1313 | AU26: =I26 -> 1313 | BI26: =I26/13 -> 101 | BZ26: =AH26+AI26+AJ26 -> 1313 | CE26: =CE25-AH26-AI26-AJ26 -> 1736292
A27: 45621 | B27: KMART AUSTRALIA LTD | C27: 澳大利亚 | D27: 4500152292 | E27: 20357441 | F27: 4500152292-100 | G27: 77515GQ1-S003 | H27: DIY厨艺大师 | I27: 195 | J27: 0 | K27: 13 | L27: =I27/K27 -> 15 | M27: 45663 | N27: 45663 | P27: pass | R27: 45629 | S27: 有 | T27: 12/16 SSCC LABEL（客供贴纸)+纽扣电池警告语贴纸/防盗贴纸翻单121356 | U27: 日期码格式：ZURU INC(BVI) 标准格式 日期：按实际生产日期 Tracking Code: Packaging Info: 77515GQ1:MA英语UPC版本包装（收缩膜和说明书, MA首选1L，如无1L可用多语且含英语的配套多语包装) + 1张说明书纽扣电池警告语贴纸（贴纸以及位置图翻单PO# 4500121356）+ 1张收缩膜纽扣电池警告语贴纸（贴纸以及位置图翻单PO#4500121356）+ 1张防盗贴纸 (贴纸以及位置图翻单PO#4500121356）+ 箱唛 + 外箱SSCC La bel Remark: 1.请务必按时完货，验货。并且按期送货入货代指定仓库，如果晚了导致船期Delay将会有罚金产生或者客户要求空运，所产生的罚金和空运费由工厂承担。 2.SSCC 外箱贴纸请同纸箱瓦楞纸方向（竖纹向）垂直，即外箱贴纸横着贴(注意条码不要被胶带粘住），贴1pc，贴1面正唛，封箱胶纸不能挡住贴纸内容。外箱贴纸 离外箱边距离不少于2cm。 3.外箱材质为ZURU标准； 4.此单需使用KMART封箱胶上下工字型封箱;从2019年6月开始，要用KMART 新版封箱胶带，此单要用"ANKO"封箱胶带 5.此单出口澳大利亚，请按相应的澳新标准生产； 6.产品和包装上生产批号的显示格式ZURU标准日期码格式 7.外箱信息不可手写，重量和体积需要与实际的一致(不可手写） 8. 每款item装箱后的G.W.超过10KG或者CBM超过0.13,(9.5KG或者以上，四舍五入后也属于10KG) 需在外箱上加印超 重或者Bulky LOGO，若发现我们资料没有，请 帮忙提醒 1)重量超过10kg但不超过16kg且CBM不超过0.13,10-16kg 超重logo 2）CBM超过0.13且重量少于17kg，bulky logo 3）不属于以上两种情况，需要使用相应重量范围内的超重logo 4）超重logo需要在外箱四面都印刷(箱唛右上角，两面侧唛超重logo需要尽量靠近毛重)，尺寸为:110mm height* 95mm width 9. 实际外箱重量跟印在箱唛上的数据差异不能超3%，尺寸按实际数据印刷 | V27: Lydia Wu | W27: 1.4483 | X27: =I27*W27 -> 282.4185 | Y27: 88993-1.11 | Z27: 77515GQ1-S003 | AA27: 已入 | AC27: 195 | AD27: =AC27-I27 -> 0 | AG27: 在仓库 | AH27: =I27 -> 195 | AN27: =I27 -> 195 | AU27: =I27 -> 195 | BI27: =I27/13 -> 15 | BZ27: =AH27+AI27+AJ27 -> 195 | CE27: =CE26-AH27-AI27-AJ27 -> 1736097
A28: 45610 | B28: ZURU France | C28: 法国 | D28: 4500151118 | E28: 5200005699 | F28: 4500151118-10 | G28: 77515GQ2-S002-NS-MTS | H28: DIY厨艺大师-无香味版本 | I28: 2000 | J28: 0 | K28: 25 | L28: =I28/K28 -> 80 | M28: 45651 | N28: 45651 | O28: 外箱/产品/包装 保持一致 | P28: pass | Q28: 1/3 截SI | R28: 45618 | S28: 无 | T28: 11/22法意西回收贴纸+无香味贴纸 | U28: 日期码格式：ZURU INC(BVI) 标准格式 日期：按实际生产日期 Packaging Info: 1.77515GQ2:最新MA 3L EAN收缩膜+一张法意西回收贴纸+ MA 23L 说明书+MA PDQ+ MA收藏指南加无香贴纸（所有包装如有提示香味都做无香版） Remark: 1. 西班牙国家内销单，需要通过ZURU 验货结果后才能出货 (工厂需要主动提前同ZURU QC预约验货避免延期出货造成不必要麻烦)； 2. 本订单所有 具有 baby items / assorted items 的款式，零售包装上都要用 母 EAN; 3. 若有特定款有特殊外箱条码要求时,需要明确列出产品款对应的具体外箱条码号码/条码类型 (若无,可以忽略此需求) 4. 所有出口欧洲的产品, 法规规定禁止在包装和共公众用的印刷品中使用矿物油中含有的物质, 包装印刷油墨中含有的MOAH/MOSH的质量浓度不能超过1%, 否则出 货到法国被抽检出现问题, 供应商需要对此负责; 5. date code: 外箱/产品/包装 保持一致，完货后提供date code 信息以便我们保存记录做批次管理; 6. 装柜时需要按照款式号码从小到大一款款依次装,避免终端仓库卸货混乱.若一个柜子涉及到几个不同国家内销单,装柜时需要一个国家装完后再装另一个国家的 产品,依次装柜,避免终端仓库因不同国家不同库位位置卸货混乱. (此点需要同工厂装柜人员强调) | V28: Jade Wang | W28: 1.4171 | X28: =I28*W28 -> 2834.2 | Y28: 88841-1.2 | Z28: 77515GQ2-S002-NS | AA28: 已入 | AC28: 2000 | AD28: =AC28-I28 -> 0 | AG28: 在仓库 七 | AI28: =I28 -> 2000 | AO28: =I28 -> 2000 | AU28: =I28 -> 2000 | BN28: =I28/25 -> 80 | BZ28: =AH28+AI28+AJ28 -> 2000 | CE28: =CE27-AH28-AI28-AJ28 -> 1734097
A29: 45611 | B29: ToyChamp Belgium nv | C29: 比利时 | D29: 4500151401 | E29: 2024101316 | F29: 4500151401-10 | G29: 77515GQ5-S001 | H29: DIY厨艺大师 | I29: 2436 | J29: 0 | K29: 42 | L29: =I29/K29 -> 58 | M29: 45657 | N29: 45653 | O29: 说明书+配件袋都要贴贴纸 | P29: pass | Q29: 1/19 截SI | R29: 45617 | S29: 无 | T29: 警语贴纸/说明书贴纸/配件袋贴纸 翻单PO#4500140409 | U29: 日期码格式：ZURU INC(BVI) 标准格式 日期：按实际生产日期 Packaging Info: 77515GQ5: MA B 版3L(warning 5L) EAN 收缩膜+ 1张NL荷兰语警语贴纸 翻单PO#4500140409，MA 5L A版收藏指南，MA B版 23L 说明书+贴纸翻单4500140409，MA 5L B版配件袋+ 贴纸 翻单4500140409， MA 3L PDQ Remark: 1.外箱需要印条码，请确保条码可以清晰扫描，且条码内容正确 2.出欧洲，微塑料需合规（如item本身不含微塑料,则忽略此要求） 3.STD配比 4. 所有产品均需符合REACH 申明 | V29: Amber Zhang | W29: 1.4539 | X29: =I29*W29 -> 3541.7004 | Y29: 94107-118 | Z29: 77515GQ5-S001-3L | AA29: 已入 | AC29: 2436 | AD29: =AC29-I29 -> 0 | AG29: 七 | AH29: =I29 -> 2436 | AO29: =AH29 -> 2436 | AU29: =I29 -> 2436 | BC29: =I29/21 -> 116 | BZ29: =AH29+AI29+AJ29 -> 2436 | CE29: =CE28-AH29-AI29-AJ29 -> 1731661
A30: 45616 | B30: N.V. DREAMLAND | C30: 比利时 | D30: 4500151832 | E30: 4500054541 | F30: 4500151832-20 | G30: 77515GQ5-S001 | H30: DIY厨艺大师 | I30: 1932 | J30: 0 | K30: 42 | L30: =I30/K30 -> 46 | M30: 45657 | N30: 45653 | O30: 说明书+配件袋都要贴贴纸 | P30: 自检 | Q30: 1/6 截SI | R30: 45616 | S30: 无 | T30: 警语贴纸/说明书贴纸/配件袋贴纸 翻单PO#4500140409 | U30: 日期码格式：ZURU INC(BVI) 标准格式 日期：按实际生产日期 Packaging Info: 77515GQ5: MA B 版3L(warning 5L) EAN 收缩膜+ 1张NL荷兰语警语贴纸（翻PO#4500140409)，MA 5L A版收藏指南，MA B版 23L 说明书+贴纸翻单PO#4500140409， MA 5L B版配件袋+ 贴纸 翻单4500140409， MA 3L PDQ Remark: 1.外箱需要印条码，请确保条码可以清晰扫描，且条码内容正确 2.出欧洲，微塑料需合规（如item本身不含微塑料,则忽略此要求） 3.STD配比 4. 所有产品符合REACH申明 | V30: Amber Zhang | W30: 1.4539 | X30: =I30*W30 -> 2808.9348 | Y30: 88874-1.4 | Z30: 77515GQ5-S001-3L | AA30: 已入 | AC30: 1932 | AD30: =AC30-I30 -> 0 | AG30: 在仓库 七 | AH30: =I30 -> 1932 | AO30: =AH30 -> 1932 | AU30: =I30 -> 1932 | BC30: =AH30/21 -> 92 | BZ30: =AH30+AI30+AJ30 -> 1932 | CE30: =CE29-AH30-AI30-AJ30 -> 1729729
A31: 45615 | B31: Wonderland Toys Inc DBA The Zoofy G | C31: 美国 | D31: 4500151635 | E31: 4357 | F31: 4500151635-70 | G31: 77515GQ1-S003 | H31: DIY厨艺大师 | I31: 5369 | J31: 0 | K31: 13 | L31: =I31/K31 -> 413 | M31: 45665 | N31: 45663 | P31: pass | Q31: 1/11 截SI | R31: 45623 | S31: 有 | T31: 11/27价格贴纸+12/16 UCC贴纸 | U31: 日期码格式：ZURU INC(BVI) 标准格式 日期：按实际生产日期 Packaging Info: 1. 出口美国，MA UPC 版本包装，优先1L。 #77515GQ1: PRICER TICK-11.99; 3PCS AG13 Batteries(Included); 2. 产品需要价格贴纸， 贴纸资料后面提供。 3. 外箱需要UCC贴纸。贴纸资料后面提供。 Remark: 4. Zuru QC 验货即可。 | V31: Abby Mai, Lluviazeng | W31: 1.4021 | X31: =I31*W31 -> 7527.8749 | Y31: 94108-1.18 | Z31: 77515GQ1-S003 | AA31: 已入 | AC31: 5369 | AD31: =AC31-I31 -> 0 | AH31: =I31 -> 5369 | AN31: =I31 -> 5369 | AU31: =I31 -> 5369 | BI31: =I31/13 -> 413 | BZ31: =AH31+AI31+AJ31 -> 5369 | CE31: =CE30-AH31-AI31-AJ31 -> 1724360
A32: 45595 | B32: TIENDAS SORIANA, S.A. DE C.V. | C32: 墨西哥 | D32: 4500149669 | F32: 4500149669-50 | G32: 77515GQ2-S001 | H32: DIY厨艺大师 | I32: 4250 | J32: 0 | K32: 50 | L32: =I32/K32 -> 85 | M32: 45664 | N32: 45663 | O32: 另+保证书 | P32: pass | Q32: 1/14 截SI | R32: 45639 | S32: 无 | T32: 12/11 UPC贴纸+1个小的红色logo贴纸+进口商贴纸 | U32: 日期码格式：ZURU INC(BVI) 标准格式 日期：按实际生产日期 Packaging Info:5. 77515GQ2：MA 3L EAN包装+UPC贴纸+MA 多语说明书+MA 3L PDQ包装+1个小的红色logo贴纸+进口商贴纸+保证书+箱唛，3张不同的进口商贴纸分别是贴在彩卡/产 品电池盖/说明书上 Remark: 5. 77515GQ2：3PCS AG13 Batteries(Include) 6. 集装箱及装柜要求：集装箱不能有破洞；不能太脏 7.每个item需要放1整箱在每个集装箱门口 8.装柜的时候要前、中、后拍照 | V32: Ever Li | W32: 1.4344 | X32: =I32*W32 -> 6096.2 | Y32: 94030-1.14 | Z32: 77515GQ2-S001-3L | AA32: 已入 | AC32: 4250 | AD32: =AC32-I32 -> 0 | AG32: 七 | AH32: =I32 -> 4250 | AO32: =I32 -> 4250 | AU32: =I32 -> 4250 | BN32: =I32/25 -> 170 | BZ32: =AH32+AI32+AJ32 -> 4250 | CE32: =CE31-AH32-AI32-AJ32 -> 1720110
A33: 45623 | B33: Army & Air Force Exchange Service | C33: 美国 | D33: 4500152559 | E33: 0092242910 | F33: 4500152559-10 | G33: MEC251-77515-S001 | H33: 混装（77555+77515） | I33: 510 | J33: 0 | K33: 30 | L33: =I33/K33 -> 17 | M33: 45660 | N33: 45663 | P33: pass | Q33: 1/8 截SI | R33: 45630 | S33: 有 | T33: 12/5 UPC | U33: 日期码格式：ZURU INC(BVI) 标准格式 日期：按实际生产日期 Packaging Info: Remark: 1. MA UPC包装(优先1L），出口美国 2. 客户PO# 0092242911 0092242912 0092242913 这3个订单外箱需要贴4x6"UCC 贴纸，只需贴一面（UCC贴纸为客供贴纸）。PO#0092242910 0092242914，这2个 订单外箱不需要UCC贴纸。 3. ZURU QC 验货。 4. 产品和包裝上需印刷tracking code信息，格式为ZURU常规。 5. 展示架上需粘贴 mother UPC 贴纸 （Item# MEC251 的 mother UPC: 193052068019 ） | V33: Yilia | W33: 75.5207 | X33: =W33*L33 -> 1283.8519 | Y33: 88990-1.11 | Z33: MEC251-77515-S001 | AA33: 已入 | AC33: 510 | AD33: =AC33-I33 -> 0 | AH33: =I33 -> 510 | AN33: =AH33 -> 510 | AU33: =AH33 -> 510 | BZ33: =AH33+AI33+AJ33 -> 510 | CE33: =CE32-AH33-AI33-AJ33 -> 1719600
A34: 45623 | B34: Army & Air Force Exchange Service | C34: 美国 | D34: 4500152559 | E34: 0092242914 | F34: 4500152559-20 | G34: MEC251-77515-S001 | H34: 混装（77555+77515） | I34: 420 | J34: 0 | K34: 30 | L34: =I34/K34 -> 14 | M34: 45660 | N34: 45663 | P34: pass | Q34: 1/8 截SI | R34: 45630 | S34: 有 | T34: 12/5 UPC | U34: 日期码格式：ZURU INC(BVI) 标准格式 日期：按实际生产日期 Packaging Info: Remark: 1. MA UPC包装(优先1L），出口美国 2. 客户PO# 0092242911 0092242912 0092242913 这3个订单外箱需要贴4x6"UCC 贴纸，只需贴一面（UCC贴纸为客供贴纸）。PO#0092242910 0092242914，这2个 订单外箱不需要UCC贴纸。 3. ZURU QC 验货。 4. 产品和包裝上需印刷tracking code信息，格式为ZURU常规。 5. 展示架上需粘贴 mother UPC 贴纸 （Item# MEC251 的 mother UPC: 193052068019 ） | V34: Yilia | W34: 75.5207 | X34: =W34*L34 -> 1057.2898 | Y34: 88990-1.11 | Z34: MEC251-77515-S001 | AA34: 已入 | AC34: 420 | AD34: =AC34-I34 -> 0 | AH34: =I34 -> 420 | AN34: =AH34 -> 420 | AU34: =AH34 -> 420 | BZ34: =AH34+AI34+AJ34 -> 420 | CE34: =CE33-AH34-AI34-AJ34 -> 1719180
A35: 45623 | B35: Army & Air Force Exchange Service | C35: 美国 | D35: 4500152559 | E35: 92242913 | F35: 4500152559-30 | G35: MEC251-77515-S001 | H35: 混装（77555+77515） | I35: 960 | J35: 0 | K35: 30 | L35: =I35/K35 -> 32 | M35: 45660 | N35: 45663 | P35: pass | Q35: 1/8 截SI | R35: 45630 | S35: 有 | T35: 12/13 UCC 12/5 UPC | U35: 日期码格式：ZURU INC(BVI) 标准格式 日期：按实际生产日期 Packaging Info: Remark: 1. MA UPC包装(优先1L），出口美国 2. 客户PO# 0092242911 0092242912 0092242913 这3个订单外箱需要贴4x6"UCC 贴纸，只需贴一面（UCC贴纸为客供贴纸）。PO#0092242910 0092242914，这2个 订单外箱不需要UCC贴纸。 3. ZURU QC 验货。 4. 产品和包裝上需印刷tracking code信息，格式为ZURU常规。 5. 展示架上需粘贴 mother UPC 贴纸 （Item# MEC251 的 mother UPC: 193052068019 ） | V35: Yilia | W35: 75.5207 | X35: =W35*L35 -> 2416.6624 | Y35: 94051-1.15 | Z35: MEC251-77515-S001 | AA35: 已入 | AC35: 960 | AD35: =AC35-I35 -> 0 | AH35: =I35 -> 960 | AN35: =AH35 -> 960 | AU35: =AH35 -> 960 | BZ35: =AH35+AI35+AJ35 -> 960 | CE35: =CE34-AH35-AI35-AJ35 -> 1718220
A36: 45623 | B36: Army & Air Force Exchange Service | C36: 美国 | D36: 4500152559 | E36: 92242911 | F36: 4500152559-40 | G36: MEC251-77515-S001 | H36: 混装（77555+77515） | I36: 1110 | J36: 0 | K36: 30 | L36: =I36/K36 -> 37 | M36: 45660 | N36: 45663 | P36: pass | Q36: 1/8 截SI | R36: 45630 | S36: 有 | T36: 12/13 UCC 12/5 UPC | U36: 日期码格式：ZURU INC(BVI) 标准格式 日期：按实际生产日期 Packaging Info: Remark: 1. MA UPC包装(优先1L），出口美国 2. 客户PO# 0092242911 0092242912 0092242913 这3个订单外箱需要贴4x6"UCC 贴纸，只需贴一面（UCC贴纸为客供贴纸）。PO#0092242910 0092242914，这2个 订单外箱不需要UCC贴纸。 3. ZURU QC 验货。 4. 产品和包裝上需印刷tracking code信息，格式为ZURU常规。 5. 展示架上需粘贴 mother UPC 贴纸 （Item# MEC251 的 mother UPC: 193052068019 ） | V36: Yilia | W36: 75.3677 | X36: =W36*L36 -> 2788.6049 | Y36: 88990-1.11 | Z36: MEC251-77515-S001 | AA36: 已入 | AC36: 1110 | AD36: =AC36-I36 -> 0 | AH36: =I36 -> 1110 | AN36: =AH36 -> 1110 | AU36: =AH36 -> 1110 | BZ36: =AH36+AI36+AJ36 -> 1110 | CE36: =CE35-AH36-AI36-AJ36 -> 1717110
A37: 45623 | B37: Army & Air Force Exchange Service | C37: 美国 | D37: 4500152559 | E37: 92242912 | F37: 4500152559-50 | G37: MEC251-77515-S001 | H37: 混装（77555+77515） | I37: 750 | J37: 0 | K37: 30 | L37: =I37/K37 -> 25 | M37: 45660 | N37: 45663 | P37: pass | Q37: 1/8 截SI | R37: 45630 | S37: 有 | T37: 12/13 UCC 12/5 UPC | U37: 日期码格式：ZURU INC(BVI) 标准格式 日期：按实际生产日期 Packaging Info: Remark: 1. MA UPC包装(优先1L），出口美国 2. 客户PO# 0092242911 0092242912 0092242913 这3个订单外箱需要贴4x6"UCC 贴纸，只需贴一面（UCC贴纸为客供贴纸）。PO#0092242910 0092242914，这2个 订单外箱不需要UCC贴纸。 3. ZURU QC 验货。 4. 产品和包裝上需印刷tracking code信息，格式为ZURU常规。 5. 展示架上需粘贴 mother UPC 贴纸 （Item# MEC251 的 mother UPC: 193052068019 ） | V37: Yilia | W37: 75.5207 | X37: =W37*L37 -> 1888.0175 | Y37: 94051-1.15 | Z37: MEC251-77515-S001 | AA37: 已入 | AC37: 750 | AD37: =AC37-I37 -> 0 | AH37: =I37 -> 750 | AN37: =AH37 -> 750 | AU37: =AH37 -> 750 | BZ37: =AH37+AI37+AJ37 -> 750 | CE37: =CE36-AH37-AI37-AJ37 -> 1716360
A38: 45614 | B38: BURLINGTON COAT FACTORY | C38: 美国 | D38: 4500151479 | E38: 383017709 | F38: 4500151479-60 | G38: 77516-S001 | H38: DIY厨艺大师*2 | I38: 2400 | J38: 0 | K38: 12 | L38: =I38/K38 -> 200 | M38: 45663 | N38: 45663 | P38: pass | Q38: 1/13 截SI | R38: 45614 | S38: 无 | T38: 12/13 客供价格贴纸+12/12 外箱贴纸 | U38: 日期码格式：ZURU INC(BVI) 标准格式 日期：按实际生产日期 Packaging Info: 1. ZURU MA （首选1L）UPC版本+客供价格贴纸+外箱贴纸，出口美国 有PVC桶的价格贴纸贴在PVC桶上面 Remark: 2. 产品和包装上印刷ZURU 标准日期码； 3. 纸箱中间靠上沿印刷ZURU LOGO，见箱唛资料 4. 外箱UCC 条码贴纸，尺寸: 4*6inch，贴在其中一面正唛右下角，贴纸距离外箱底部3.5cm, 侧边距离3.5cm。外箱贴纸由跟单提供电子版, 工厂自行安排，不可用 封箱胶覆盖贴纸条码，贴纸需要可以扫描且无损坏. 5. 每个产品有一个价格贴纸，价格贴纸覆盖UPC条码上 （若UPC 条码太大，可以露出ITEM#, 覆盖条码即可）贴的时候要是会覆盖包装上重要的信息和图案，需要 告知跟单。 | V38: Jessi Xu | W38: 3.1012 | X38: =I38*W38 -> 7442.88 | Y38: 94086-1.17 | Z38: 77516-S001-1L | AA38: 已入 | AC38: 2400 | AD38: =AC38-I38 -> 0 | AH38: =I38*2 -> 4800 | AN38: =AH38 -> 4800 | AU38: =AH38 -> 4800 | BW38: =I38 -> 2400 | BX38: =I38 -> 2400 | BZ38: =AH38+AI38+AJ38 -> 4800 | CE38: =CE37-AH38-AI38-AJ38 -> 1711560
A39: 45603 | B39: T. PLANET SHOPS SL | C39: 西班牙 | D39: 4500150460 | F39: 4500150460-10 | G39: 77515SK1-S002 | H39: DIY厨艺大师 | I39: 2010 | J39: 0 | K39: 30 | L39: =I39/K39 -> 67 | M39: 45667 | N39: 45663 | O39: 已出 1套大货样品 | P39: pass | Q39: 1/13 出货 | R39: 45630 | S39: 无 | T39: 12/13 进口商贴纸+产品贴纸 | U39: 日期码格式：ZURU INC(BVI) 标准格式 日期：按实际生产日期 Packaging Info: 77515SK1： 最新MA 3L EAN 收缩膜 +最新MA5L 收藏指南+最新MA 3L 展示架 + 进口商贴纸(含西班牙环保标)+产品贴纸 Remark: 1, 此货出西班牙，请确保所有包装都有西班牙环保标。 2，出货前两周需寄1套大货样品和1套测试样品，请多备料 3, 此客人推期有罚款，请按时完货 3, 出货前要验货图片给客人确认OK后才出货 4, 如有胶袋，需要增加胶袋警告语贴纸 | V39: Jade Wang | W39: 57.6474 | X39: =W39*L39 -> 3862.3758 | Y39: 94069-1.16 | Z39: 77515SK1-S002-3L | AA39: 已入 | AC39: 2010 | AD39: =AC39-I39 -> 0 | AG39: 七 | AH39: =I39 -> 2010 | AO39: =I39 -> 2010 | AU39: =I39 -> 2010 | BS39: =I39/30 -> 67 | BT39: =BS39 -> 67 | BZ39: =AH39+AI39+AJ39 -> 2010 | CE39: =CE38-AH39-AI39-AJ39 -> 1709550
A40: 45622 | B40: MCD BRANDS SAS | C40: 乌拉圭 | D40: 4500152326 | F40: 4500152326-90 | G40: 77515GQ2-S001 | H40: DIY厨艺大师 | I40: 250 | J40: 0 | K40: 50 | L40: =I40/K40 -> 5 | M40: 45663 | N40: 45663 | P40: 自检 | Q40: 1/7 截单 | R40: 45637 | S40: 无 | T40: 12/17进口商贴纸+EAN贴纸 | U40: 日期码格式：ZURU INC(BVI) 标准格式 日期：按实际生产日期 Packaging Info: 77515GQ2:MA 3L包装+进口商贴纸+箱唛+EAN贴纸 Remark: 进口商贴纸请多备料5pcs,出货后需要寄给客户 | V40: Ava Liang | W40: 1.4395 | X40: =I40*W40 -> 359.875 | Y40: 88941-1.8 | Z40: 77515GQ2-S001-3L | AA40: 已入 | AC40: 250 | AD40: =AC40-I40 -> 0 | AH40: =I40 -> 250 | AO40: =I40 -> 250 | AU40: =I40 -> 250 | BN40: =I40/25 -> 10 | BZ40: =AH40+AI40+AJ40 -> 250 | CE40: =CE39-AH40-AI40-AJ40 -> 1709300
A41: 45615 | B41: VM INTERNATIONAL | C41: 美国 | D41: 4500151779 | F41: 4500151779-60 | G41: 77515GQ1-S003 | H41: DIY厨艺大师 | I41: 1092 | J41: 0 | K41: 13 | L41: =I41/K41 -> 84 | M41: 45666 | N41: 45663 | P41: 自检 | Q41: 1/16 截SI | R41: 45637 | S41: 无 | T41: 无 | U41: 日期码格式：ZURU INC(BVI) 标准格式 日期：按实际生产日期 Packaging Info: 1.ZURU 标准日期码格式， 2.无第三方测试和验货，ZURU 内部QC验货即可出货 Remark: 3. 优先 MA 1L UPC包装; 4. 纸箱印ZURU LOGO，出口美国； | V41: Iris Yuan | W41: 1.4071 | X41: =I41*W41 -> 1536.5532 | Y41: 94112-1.18 | Z41: 77515GQ1-S003 | AA41: 已入 | AC41: 1092 | AD41: =AC41-I41 -> 0 | AG41: 在仓库 | AH41: =I41 -> 1092 | AN41: =I41 -> 1092 | AU41: =I41 -> 1092 | BI41: =I41/13 -> 84 | BZ41: =AH41+AI41+AJ41 -> 1092 | CE41: =CE40-AH41-AI41-AJ41 -> 1708208
A42: 45604 | B42: ESAL ENTERPRISES FZC | C42: 卡塔尔 | D42: 4500150683 | E42: QATAR | F42: 4500150683-10 | G42: 77515GQ5-S001-STC | H42: DIY厨艺大师 | I42: 504 | J42: 0 | K42: 42 | L42: =I42/K42 -> 12 | M42: 45667 | N42: 45663 | O42: 10号球的吸塑盒上的pork loin mini产品贴纸删掉pork loin字样 额外+书纸 | P42: 自检 | Q42: 1/19截SI | R42: 11、28 | S42: 无 | T42: 进口商贴纸翻4500128286 | U42: 日期码格式：ZURU INC(BVI) 标准格式 日期：按实际生产日期 Packaging Info:77515GQ5装（含G Mark)+进口商贴纸(含QR code, 阿拉伯警语); 贴纸上的QR code需微信可扫，扫描结果64429；客版指南翻4500128286；客版产品贴纸 （删掉pork loin）单词翻4500148906；MA说明书+额外书纸翻4500128286;3L MA PDQ, PDQ和展架也需要进口商贴纸翻4500128286 MA PDQ, MA展示架，PDQ和展示架也需要进口商贴纸翻4500148906 Remark: 77515:3PCS AG13 Batteries (included) pork loin mini的产品贴纸删掉pork loin字样 | V42: Lena Huang | W42: 1.5571 | X42: =I42*W42 -> 784.7784 | Y42: 94135-1.21 | Z42: 77515GQ5-S001-STC | AA42: 已入 | AC42: 504 | AD42: =AC42-I42 -> 0 | AH42: =I42 -> 504 | AN42: =I42 -> 504 | AW42: =I42 -> 504 | BC42: =I42/21 -> 24 | BZ42: =AH42+AI42+AJ42 -> 504 | CE42: =CE41-AH42-AI42-AJ42 -> 1707704
A43: 45604 | B43: ESAL ENTERPRISES FZC | C43: 卡塔尔 | D43: 4500150683 | E43: QATAR | F43: 4500150683-20 | G43: 77515SK-S002-STC | H43: DIY厨艺大师 | I43: 1800 | J43: 0 | K43: 60 | L43: =I43/K43 -> 30 | M43: 45667 | N43: 45663 | O43: 10号球的吸塑盒上的pork loin mini产品贴纸删掉pork loin字样 额外+书纸 | P43: pass | Q43: 1/19截SI | R43: 11、28 | S43: 无 | T43: 进口商贴纸翻4500128286 | U43: 日期码格式：ZURU INC(BVI) 标准格式 日期：按实际生产日期 Packaging Info:77515SK装（含G Mark)+进口商贴纸(含QR code, 阿拉伯警语); 贴纸上的QR code需微信可扫，扫描结果64429；客版指南翻4500128286；客版产品贴纸 （删掉pork loin）单词翻4500148906；MA说明书+额外书纸翻4500128286;3L MA PDQ, PDQ和展架也需要进口商贴纸翻4500128286 MA PDQ, MA展示架，PDQ和展示架也需要进口商贴纸翻4500148906 Remark: 77515:3PCS AG13 Batteries (included) pork loin mini的产品贴纸删掉pork loin字样 | V43: Lena Huang | W43: 106.1213 | X43: =I43*W43 -> 191018.34 | Y43: 94135-1.21 | Z43: 77515SK-S002-STC | AA43: 已入 | AC43: 1800 | AD43: =AC43-I43 -> 0 | AH43: =I43 -> 1800 | AN43: =I43 -> 1800 | AW43: =I43 -> 1800 | BQ43: =I43/60 -> 30 | BZ43: =AH43+AI43+AJ43 -> 1800 | CE43: =CE42-AH43-AI43-AJ43 -> 1705904
A44: 45607 | B44: ZURU France | C44: 法国 | D44: 4500149708 | E44: 5200005612 | F44: 4500149708-60 | G44: 77515GQ2-S002-NS-MTS | H44: DIY厨艺大师-无香味版本 | I44: 2000 | J44: 0 | K44: 25 | L44: =I44/K44 -> 80 | M44: 45670 | N44: 45666 | O44: 外箱/产品/包装 保持一致 | P44: pass | Q44: 1/16 截SI | R44: 45632 | S44: 说明书贴纸（翻4500151118） | T44: 法国环保标贴纸 翻4500124462+无香贴纸 | U44: 日期码格式：ZURU INC(BVI) 标准格式 日期：按实际生产日期 Packaging Info: 5.77515GQ2:最新MA 3L EAN收缩膜+一张法国环保标贴纸 翻4500124462+ MA 23L 说明书+一张说明书贴纸（翻4500151118）+MA PDQ+MA收藏指南加无香贴纸（所有包装如有提示香味都做无香版）+一张纸袋贴纸（翻4500151118） Remark: 1.法国国家内销单，需要通过ZURU 验货结果后才能出货 (工厂需要主动提前同ZURU QC预约验货避免延期出货造成不必要麻烦)； 2.本订单所有 具有 baby items / assorted items 的款式，零售包装上都要用 母 EAN; 3. 若有特定款有特殊外箱条码要求时,需要明确列出产品款对应的具体外箱条码号码/条码类型 (若无,可以忽略此需求) 4. 所有出口欧洲的产品, 法规规定禁止在包装和共公众用的印刷品中使用矿物油中含有的物质, 包装印刷油墨中含有的MOAH/MOSH的质量浓度不能超过1%, 否则出 货到法国被抽检出现问题, 供应商需要对此负责; 5. date code: 外箱/产品/包装 保持一致，完货后提供date code 信息以便我们保存记录做批次管理; 6. 装柜时需要按照款式号码从小到大一款款依次装,避免终端仓库卸货混乱.若一个柜子涉及到几个不同国家内销单,装柜时需要一个国家装完后再装另一个国家的 产品,依次装柜,避免终端仓库因不同国家不同库位位置卸货混乱. (此点需要同工厂装柜人员强调) | V44: Jade Wang | W44: 1.4171 | X44: =I44*W44 -> 2834.2 | Y44: 94087-1.17 | Z44: 77515GQ2-S002-NS | AA44: 已入 | AC44: 2000 | AD44: =AC44-I44 -> 0 | AI44: =I44 -> 2000 | AO44: =I44 -> 2000 | AU44: =I44 -> 2000 | BN44: =I44/25 -> 80 | BZ44: =AH44+AI44+AJ44 -> 2000 | CE44: =CE43-AH44-AI44-AJ44 -> 1703904
A45: 45603 | B45: DD’S DISCOUNTS | C45: 美国 | D45: 4500150308 | E45: 70054030 | F45: 4500150308-20 | G45: 77516-S001 | H45: DIY厨艺大师*2 | I45: 1008 | J45: 0 | K45: 12 | L45: =I45/K45 -> 84 | M45: 45670 | N45: 45666 | O45: 客人确认可以接受MA 3L 包装，请按MA 3L 做货，另请用空白贴纸覆盖EAN 条码 | P45: pass | R45: 45610 | S45: 无 | T45: 12/2 客供价格贴纸+空白贴纸 | U45: 日期码格式： 标准格式 日期：按实际生产日期 Packaging Info: 1.ZURU MA UPC 收缩膜+客版铜版纸+PVC桶 + 客供价格贴纸，出口美国 , 优先使用MA 1L 最新版本 。 Remark: 1.ZURU MA UPC 收缩膜+客版铜版纸+PVC桶 + 客供价格贴纸，出口美国 , 优先使用MA 1L 最新版本 。 2.价格贴纸位于包装正面右下角，不挡住重要信息即可，可适当调整 ，价格贴纸由跟单提供。 3.标准日期码格式，产品和包装必须有日期码 。 4.同个产品同个货期不可出现不同的包装。 5. PVC 桶中球不能出现完全相同的ASSORTMENT ， 即同一个PVC 中球里的ASSORTMENT 需要不同。 以免消费者失望。 6.PVC 桶上加上 MINI BRANDS 的LOGO 贴纸 （ ZURU 统一要求的） 7.收缩膜可使用标版带UPC条码MA，无需白色贴纸覆盖。 8. #77516 收缩膜用3L+空白贴纸 | V45: Taylor Liao | W45: 3.0641 | X45: =I45*W45 -> 3088.6128 | Y45: 94145-1.21 | Z45: 77516-S001-3L | AA45: 已入 | AC45: 1008 | AD45: =AC45-I45 -> 0 | AH45: =I45*2 -> 2016 | AO45: =AH45 -> 2016 | AU45: =AH45 -> 2016 | BW45: =I45 -> 1008 | BX45: =I45 -> 1008 | BZ45: =AH45+AI45+AJ45 -> 2016 | CE45: =CE44-AH45-AI45-AJ45 -> 1701888
A46: 45603 | B46: ROSS PROCUREMENT.INC | C46: 美国 | D46: 4500150464 | E46: 60190494 | F46: 4500150464-20 | G46: 77516-S001 | H46: DIY厨艺大师*2 | I46: 4800 | J46: 0 | K46: 12 | L46: =I46/K46 -> 400 | M46: 45672 | N46: 45667 | O46: 客人确认可以接受MA 3L 包装，请按MA 3L 做货，另请用空白贴纸覆盖EAN 条码 | P46: pass | Q46: 3/14 交仓 | R46: 45610 | S46: 无 | T46: 12/19 客供价格贴纸+空白贴纸 | U46: 日期码格式：ZURU INC(BVI) 标准格式 日期：按实际生产日期 Packaging Info: 1.ZURU MA UPC 收缩膜+客版铜版纸+PVC桶 + 客供价格贴纸，出口美国 , 优先使用MA 1L 最新版本 。 2.#77516请使用MA 3L 收缩膜+空白贴纸覆盖EAN条码 Remark: 1.ZURU MA UPC 收缩膜+客版铜版纸+PVC桶 + 客供价格贴纸，出口美国 , 优先使用MA 1L 最新版本 。 2.价格贴纸位于包装正面右下角，不挡住重要信息即可，可适当调整 ，价格贴纸由跟单提供。 3.标准日期码格式，产品和包装必须有日期码 。 4.同个产品同个货期不可出现不同的包装。 5. PVC 桶中球不能出现完全相同的ASSORTMENT ， 即同一个PVC 中球里的ASSORTMENT 需要不同。 以免消费者失望。 6.PVC 桶上加上 MINI BRANDS 的LOGO 贴纸 （ ZURU 统一要求的） 7.收缩膜可使用标版带UPC条码MA，无需白色贴纸覆盖。 8.#77516请使用MA 3L 收缩膜+空白贴纸覆盖EAN条码 | V46: Sophia Zhou | W46: 3.054 | X46: =I46*W46 -> 14659.2 | Y46: 94486-3.7 | Z46: 77516-S001-1L | AA46: 已入 | AC46: 4800 | AD46: =AC46-I46 -> 0 | AH46: =I46*2 -> 9600 | AO46: =AH46 -> 9600 | AU46: =AH46 -> 9600 | BW46: =I46 -> 4800 | BX46: =I46 -> 4800 | BZ46: =AH46+AI46+AJ46 -> 9600 | CE46: =CE45-AH46-AI46-AJ46 -> 1692288
A47: 45616 | B47: MAGGIO 3 SRL | C47: 意大利 | D47: 4500151811 | F47: 4500151811-40 | G47: 77515GQ1-S001 | H47: DIY厨艺大师 | I47: 4160 | J47: 0 | K47: 52 | L47: =I47/K47 -> 80 | M47: 45672 | N47: 45667 | P47: pass | Q47: 1/16 截SI | R47: 11、22 | S47: 无 | T47: 12/12 进口商地址贴纸+PDQ条码贴 | U47: 日期码格式：ZURU INC(BVI) 标准格式 日期：按实际生产日期 Packaging Info: 77555GQ1- MA 3L+5L EAN收缩膜（+1*意大利sorting logo含进口商地址贴纸）+MA 5L 收藏指南 +MA多语 PAPER BAG +MA 3L PDQ(+1*PDQ条码贴纸)+MA 23L WARNI NG帽子说明书 产品条码 4894680033429 Remark: 1.此单出意大利，需符合EU标准，不能含微塑料，如果有slime等化学品需要不含硼 2.需保证按期1/15前完货，延期罚款 3.贴纸切勿盖住意大利警告语文字(QC 务必检查） | V47: Amy Xiao | W47: 1.4046 | X47: =I47*W47 -> 5843.136 | Y47: 94070-1.16 | Z47: 77515GQ1-S001-3L | AA47: 已入 | AC47: 4160 | AD47: =AC47-I47 -> 0 | AH47: =I47 -> 4160 | AO47: =I47 -> 4160 | AU47: =AH47 -> 4160 | BJ47: =I47/13 -> 320 | BZ47: =AH47+AI47+AJ47 -> 4160 | CE47: =CE46-AH47-AI47-AJ47 -> 1688128
A48: 45603 | B48: DD’S DISCOUNTS | C48: 美国 | D48: 4500150510 | E48: 70054033 | F48: 4500150510-10 | G48: 77516-S001 | H48: DIY厨艺大师*2 | I48: 1008 | J48: 0 | K48: 12 | L48: =I48/K48 -> 84 | M48: 45673 | N48: 45670 | O48: 客人确认可以接受MA 3L 包装，请按MA 3L 做货，另请用UPC 贴纸覆盖EAN 条码 | P48: pass | R48: 45610 | S48: 无 | T48: 12/19 客供价格贴纸+空白贴纸 | U48: 日期码格式： 标准格式 日期：按实际生产日期 Packaging Info: 1.ZURU MA UPC 收缩膜+客版铜版纸+PVC桶 + 客供价格贴纸，出口美国 , 优先使用MA 1L 最新版本 。 Remark: 1.ZURU MA UPC 收缩膜+客版铜版纸+PVC桶 + 客供价格贴纸，出口美国 , 优先使用MA 1L 最新版本 。 2.价格贴纸位于包装正面右下角，不挡住重要信息即可，可适当调整 ，价格贴纸由跟单提供。 3.标准日期码格式，产品和包装必须有日期码 。 4.同个产品同个货期不可出现不同的包装。 5. PVC 桶中球不能出现完全相同的ASSORTMENT ， 即同一个PVC 中球里的ASSORTMENT 需要不同。 以免消费者失望。 6.PVC 桶上加上 MINI BRANDS 的LOGO 贴纸 （ ZURU 统一要求的） 7.收缩膜可使用标版带UPC条码MA，无需白色贴纸覆盖。 8. #77516 收缩膜用3L+空白贴纸 | V48: Taylor Liao | W48: 2.3963 | X48: =I48*W48 -> 2415.4704 | Y48: 94559-3.14 | Z48: 77516-S001-3L | AA48: 已入 | AC48: 1008 | AD48: =AC48-I48 -> 0 | AH48: =I48*2 -> 2016 | AO48: =AH48 -> 2016 | AU48: =AH48 -> 2016 | BW48: =I48 -> 1008 | BX48: =I48 -> 1008 | BZ48: =AH48+AI48+AJ48 -> 2016 | CE48: =CE47-AH48-AI48-AJ48 -> 1686112
A49: 45635 | B49: BASILE GIOCATTOLI SRL | C49: 意大利 | D49: 4500153469 | F49: 4500153469-10 | G49: 77515GQ1-S001 | H49: DIY厨艺大师 | I49: 520 | J49: 0 | K49: 52 | L49: =I49/K49 -> 10 | M49: 45674 | N49: 45670 | O49: 未出样板 | P49: 自检 | Q49: 1/27 截SI | R49: 45637 | S49: 无 | T49: 12/17 进口商地址贴纸 | U49: 日期码格式：ZURU INC(BVI) 标准格式 日期：按实际生产日期 Packaging Info: 77515GQ1-MA B 3L+5L EAN收缩膜 （+1*意大利sorting logo含进口商地址贴纸）+ MA 5L 收藏指南+MA 3L PDQ+MA 多语bag+ MA 23L WARNING帽子说明书 条码 4 894680032255 Remark: 1.此单出意大利，需符合EU标准，不能含微塑料，如果有slime等化学品需要不含硼； 2.需保证按期1/17前完货，延期罚款；77515需要大货样品1pc+1set散件。 3.贴纸切勿盖住意大利警告语文字(QC 务必检查） | V49: AMY XIAO | W49: 1.4096 | X49: =I49*W49 -> 732.992 | Y49: 94133-1.21 | Z49: 77515GQ1-S001-3L | AA49: 已入 | AC49: 520 | AD49: =AC49-I49 -> 0 | AH49: =I49 -> 520 | AO49: =I49 -> 520 | AU49: =AH49 -> 520 | BJ49: =I49/13 -> 40 | BZ49: =AH49+AI49+AJ49 -> 520 | CE49: =CE48-AH49-AI49-AJ49 -> 1685592
A50: 45635 | B50: MILLS FLEET FARM | C50: 北美 | D50: MPO03111 | E50: PO# 4500153457 | G50: 77515-S001-MSLD121-S001 | H50: DIY厨艺大师6个球按配比分隔开/箱 | I50: 480 | J50: 0 | K50: 24 | L50: =I50/K50 -> 20 | M50: 45677 | N50: 45673 | O50: 日期统一打： 2025年1月16日 | P50: 自检 | Q50: 1/20送库有 | R50: 周转箱 备注上:客供子件给Mis FleetFarmPon4500153457#MSLD121-S001混装用 | S50: 无 | T50: 无 | U50: Remark: 1. 包装： 包 ZURU MA 1L UPC最新包装；出口美国 最 2. 日期跟踪码：产品外包装及产品本身都必须有日期跟踪码，并且确保两者的日期跟踪码要一致； 日 ZURU标准格式日期码 标 (请自行调整具体年月日生产期，但不能为周末）因 请 该单是多工厂混装，为了统一，日期可以统一打 该 2025年1月16日 3. 按照按 Zuru MA 标板配比 标 4. 子件于 子 2025年1月20日送到库有混装，产品包装上需做好标识，以便组装厂识别组装时避免重复率，送货到库有厂时送货单请备注上：客供子件给 日 Mills Fleet Farm PO# 4500153457 # #MSLD121-S001混装用。 | V50: Mila Yao | W50: 1.3507 | X50: =I50*W50 -> 648.336 | Y50: 94399-2.27 | Z50: 77515-S001-MSLD121-S001 | AA50: 已入 | AC50: 480 | AD50: =AC50-I50 -> 0 | AH50: =I50 -> 480 | AN50: =I50 -> 480 | AU50: =I50 -> 480 | BZ50: =AH50+AI50+AJ50 -> 480 | CE50: =CE49-AH50-AI50-AJ50 -> 1685112
A51: 45639 | B51: CENTRO CUESTA NACIONAL | C51: 多米尼加 | D51: 4500153864 | E51: 24-1067175JDO | F51: 4500153864--90 | G51: 77515GQ2-S001 | H51: DIY厨艺大师 | I51: 750 | J51: 0 | K51: 50 | L51: =I51/K51 -> 15 | M51: 45677 | N51: 45673 | O51: 指定日期格式2025-01 | P51: 自检 | Q51: 1/22 截SI | R51: 45639 | S51: 无 | T51: 12/18 UPC 贴纸 | U51: 日期码格式：2025-01 日期： Packaging Info: 77515GQ2：MA 5L 收藏指南+MA 3L 包装+UPC 贴纸+MA 3L PDQ 包装+箱唛 Remark: 77515GQ2: 3PCS AG13 BATTERIES(INCLUDE) | V51: Zoe Luo | W51: 1.4225 | X51: =I51*W51 -> 1066.875 | Y51: 94113-1.18 | Z51: 77515GQ2-S001-3L | AA51: 已入 | AC51: 750 | AD51: =AC51-I51 -> 0 | AH51: =I51 -> 750 | AO51: =I51 -> 750 | AU51: =I51 -> 750 | BN51: =I51/25 -> 30 | BZ51: =AH51+AI51+AJ51 -> 750 | CE51: =CE50-AH51-AI51-AJ51 -> 1684362
A52: 45639 | B52: CORPORACION FAVORITA C.A. | C52: 厄瓜多尔 | D52: 4500153836 | E52: 24-1067174JEC | F52: 4500153836-30 | G52: 77515GQ2-S001 | H52: DIY厨艺大师 | I52: 4600 | J52: 0 | K52: 50 | L52: =I52/K52 -> 92 | M52: 45677 | N52: 45673 | O52: 外箱箱唛，产品批号需要与进口商贴纸保持一致。 | P52: pass | Q52: 1/21 截SI 指定日期格式2025-01 | R52: 45639 | S52: 无 | T52: UPC 贴纸翻单153864+12/17 进口商贴纸 | U52: 日期码格式：LOTE 格式：例如2025-01 日期： Packaging Info: 77515GQ2：MA 5L 收藏指南+MA 3L 包装+UPC 贴纸+MA 3L PDQ 包装+进口商贴纸+箱唛 Remark: 77515GQ2: 3PCS AG13 BATTERIES(INCLUDE) 客户有LOTE 格式：例如2025-01. ，外箱箱唛，产品批号需要与进口商贴纸保持一致。 | V52: Zoe Luo | W52: 1.4344 | X52: =I52*W52 -> 6598.24 | Y52: 94144-1.21 | Z52: 77515GQ2-S001-3L | AA52: 已入 | AC52: 4600 | AD52: =AC52-I52 -> 0 | AH52: =I52 -> 4600 | AO52: =I52 -> 4600 | AU52: =I52 -> 4600 | BN52: =I52/25 -> 184 | BZ52: =AH52+AI52+AJ52 -> 4600 | CE52: =CE51-AH52-AI52-AJ52 -> 1679762
A53: 45560 | B53: SUBURBIA S DE R. L. DE C. V. | C53: 墨西哥 | D53: 4500145574 | F53: 4500145574-40 | G53: 77515GQ2-S001 | H53: DIY厨艺大师 | I53: 1500 | J53: 0 | K53: 50 | L53: =I53/K53 -> 30 | M53: 45649 | N53: 45671 | O53: 有监柜要求，需要每款多准备一套完整物料 | P53: pass | Q53: 1/17 截SI | R53: 外箱只需四面印Zuru logo | S53: 有 | T53: 12/24进口商贴纸+价标贴纸+11/29客供 Hu贴纸+ASN贴纸 | U53: 日期码格式：ZURU INC(BVI) 标准格式 日期：按实际生产日期 Packaging Info: 77515GQ2；MA 3L 包装+UPC贴纸+MA 多语收藏指南+MA 3L PDQ包装+进口商贴纸+价标贴纸； 1.外箱只需四面印Zuru logo，再加2张贴纸，1张Hu贴纸（条码贴），1张ASN贴纸（尺寸6.5cm*6.3cm,潘通色号2597C），都贴于侧唛，只需贴1面(备注HU'S <(>& <)> ASN贴纸客供） 2. 一个外箱对应一个HU’S(条形码),不可以混条码包装 3.含有说明书需要增加说明书贴纸 4.价格贴纸覆盖原有彩盒的条形码 Remark: 77515GQ2：3PCS AG13 Batteries(Include) 此单有监柜要求，需要每款多准备一套完整物料，用于监柜，不可以随大货走 | V53: Zoe Luo | W53: 1.4344 | X53: =I53*W53 -> 2151.6 | Y53: 94085-1.17 | Z53: 77515GQ2-S001-3L | AA53: 已入 | AC53: 1500 | AD53: =AC53-I53 -> 0 | AG53: 七 | AH53: =I53 -> 1500 | AO53: =I53 -> 1500 | AU53: =I53 -> 1500 | BN53: =I53/25 -> 60 | BZ53: =AH53+AI53+AJ53 -> 1500 | CE53: =CE52-AH53-AI53-AJ53 -> 1678262
A54: 45631 | B54: Prénatal Retail Group Asia Pacific | C54: 意大利 | D54: 4500153302 | E54: 2000006814 | F54: 4500153302-20 | G54: 77515GQ2-S001 | H54: DIY厨艺大师 | I54: 2750 | J54: 0 | K54: 50 | L54: =I54/K54 -> 55 | M54: 45672 | N54: 45672 | O54: 1/16 第三方 | P54: pass | Q54: 1/24 截SI 客人日期码：LOT2503，产品/包装/外箱 请保持一致 已出样板 | R54: 45637 | S54: 无 | T54: 12/27 进口商贴纸+产品贴纸+12/31 黑白纸电池说明书 | U54: 日期码格式：LOT2503 日期： Packaging Info: 77515：最新MA 3L+5L warning EAN收缩膜+MA PDQ+1*进口商贴纸+1*产品贴纸+客版说明书 Remark: 1.RATIO 同MA 一致。 2.大货样品2套/item，用于客人验货签板。验货后还会抽办1套/item，请多备料。 3.客人日期码：LOT2503，产品/包装/外箱 请保持一致,无须ZURU日期码 4.产品均符合EU微塑料法规要求：不能含有微塑料/闪粉 5. SMASHERS 或含Slime产品，所有化合物使用无硼版本出意大利。 6. 本订单所有 具有 baby items / assorted items 的款式，零售包装上都要用 母 EAN; 7，此客户需要第三方验货，请在约三方验货前必须PASS ZURU验货。 | V54: Jade Wang | W54: 1.4174 | X54: =I54*W54 -> 3897.85 | Y54: 94151-1.22 | Z54: 77515GQ2-S001-3L | AA54: 已入 | AC54: 2750 | AD54: =AC54-I54 -> 0 | AH54: =I54 -> 2750 | AO54: =I54 -> 2750 | AU54: =I54 -> 2750 | BN54: =I54/25 -> 110 | BZ54: =AH54+AI54+AJ54 -> 2750 | CE54: =CE53-AH54-AI54-AJ54 -> 1675512
A55: 45638 | B55: COMERCIAL JOMAN S.L. | C55: 西班牙 | D55: 4500153788 | F55: 4500153788-60 | G55: 77515GQ2-S001 | H55: DIY厨艺大师 | I55: 1200 | J55: 0 | K55: 50 | L55: =I55/K55 -> 24 | M55: 45687 | N55: 45677 | P55: pass | Q55: 2/11 截单 | R55: 45642 | S55: 无 | T55: 12/17 进口商贴纸 | U55: 日期码格式：ZURU INC(BVI) 标准格式 日期：按实际生产日期 Packaging Info: 6.77515GQ2：最新MA 3L EAN 版本包装+一张进口商贴纸（含环保标）+MA 23L说明书； Remark: 订单出西班牙，不能含微塑料/闪粉； | V55: Sherry Chen | W55: 1.4344 | X55: =I55*W55 -> 1721.28 | Y55: 94218-2.11 | Z55: 77515GQ2-S001-3L | AA55: 已入 | AC55: 1200 | AD55: =AC55-I55 -> 0 | AH55: =I55 -> 1200 | AO55: =I55 -> 1200 | AU55: =I55 -> 1200 | BN55: =I55/25 -> 48 | BZ55: =AH55+AI55+AJ55 -> 1200 | CE55: =CE54-AH55-AI55-AJ55 -> 1674312
A56: 45616 | B56: SAINSBURY'S SUPERMARKET LTD | C56: 英国 | D56: 4500151646 | E56: PO#2698218-SK U#143951575 | F56: 4500151646-20 | G56: 77515GQ1-S003 | H56: DIY厨艺大师 | I56: 3003 | J56: 0 | K56: 13 | L56: =I56/K56 -> 231 | M56: 45695 | N56: 45679 | P56: pass | Q56: 2/11 出货 | R56: 45642 | S56: 无 | T56: 11/22 UPC贴纸 | U56: 日期码格式：ZURU INC(BVI) 标准格式 日期：按实际生产日期 Packaging Info: -77515GQ1: 收缩膜和PDQ 用3L 版本+UPC 贴纸，其他通用版本ok 订单对应客户1个PO号 ，备注有显示 Remark: *胶带最少宽度要保证6.0CM,厚度最少0.05毫米,外箱不可以打钉/扎带；以工字型封箱； *如果重量超过5KGS，箱唛需加黄色警示图标志 ，有疑问请与ZURU跟单同事联系,十分重要！ *订单出英国，请注意检查产品及包装应带UKCA图标，包装显示ZURU UK LTD信息，QC同事请查核，如有问题与跟单确认。 *MA版本按工厂现有最新库存即可，订单出英国，请注意检查产品及包装应带UKCA图标，包装显示ZURU UK LTD信息，QC同事请查核，如有问题与跟单确认。 *生产日期按实际的（法定工作日），按ZURU标准格式即可 ，但是请知悉包装日期码需要早于或者等于外箱日期码 ，不能晚于外箱日期码 *请注意所有订单都需要经过ZURU QC验货并且通过后方可出货 *产品条码以订单显示为准 ，请安排生产前先核对再生产或者与Sherry 复核再安排 。 *外箱上的条码请确保清晰可扫描 ，否则到目的仓无法扫描入仓由工厂承担责任 。 *所有产品按符合欧洲标准走货，需要是不含微塑料版本 。 *涉及到硼的，请使用低硼版本 *客户不接受PVC材质 | V56: Zoe Chen | W56: 1.4071 | X56: =I56*W56 -> 4225.5213 | Y56: 94219-2.11 | Z56: 77515GQ1-S003-3L | AA56: 已入 | AC56: 3003 | AD56: =AC56-I56 -> 0 | AH56: =I56 -> 3003 | AO56: =I56 -> 3003 | AU56: =I56 -> 3003 | BJ56: =I56/13 -> 231 | BZ56: =AH56+AI56+AJ56 -> 3003 | CE56: =CE55-AH56-AI56-AJ56 -> 1671309
A57: 45642 | B57: TARGET US | C57: 美国 | D57: 4500154167 | E57: 10001033544-3890 | F57: 4500154167-10 | G57: 77515GQ5-S002 | H57: DIY厨艺大师 | I57: 3507 | J57: 0 | K57: 21 | L57: =I57/K57 -> 167 | M57: 45695 | N57: 45679 | P57: pass | Q57: 2/12 预计客上柜 | R57: 45650 | S57: 有 | T57: 1/3 条码箱贴纸 | U57: 日期码格式：ZURU INC(BVI) 标准格式 日期：按实际生产日期 Packaging Info: MA包装, MA 1L 收缩膜, MA 1L PDQ； Remark: 1. 77515GQ5-S002-MINI BRAND-MASTER CHEF MINI BRANDS-SERIES 1,21pcs/Gravity PDQ, 21pcs/CTN,No Inner,STD Color Assortment 2. MA包装, MA 1L 收缩膜, MA 1L PDQ；收缩膜上的UPC显示193052061034; 3. 外箱正唛左上角位置粘贴条码箱贴纸，每箱只贴一张，由ZURU订购。来料贴纸上显示的客户DPCI# 086-02-9598， UPC显示10193052061031; 4. 产品和包装上印刷 tracking code信息，格式为ZURU常规格式; 5. 出货方式：货代自提。 | V57: Holly Zheng | W57: 1.4397 | X57: =I57*W57 -> 5049.0279 | Y57: 94238-2.13 | Z57: 77515GQ5-S002 | AA57: 已入 | AC57: 3507 | AD57: =AC57-I57 -> 0 | AH57: =I57 -> 3507 | AN57: =I57 -> 3507 | AU57: =I57 -> 3507 | BB57: =I57/21 -> 167 | BZ57: =AH57+AI57+AJ57 -> 3507 | CE57: =CE56-AH57-AI57-AJ57 -> 1667802
A58: 45623 | B58: THE ENTERTAINER | C58: 英国 | D58: 4500152538 | E58: 4500152538-2: FB12127 | F58: 4500152538-50 | G58: 77515GQ1-S001 | H58: DIY厨艺大师 | I58: 1144 | J58: 0 | K58: 52 | L58: =I58/K58 -> 22 | M58: 45696 | N58: 45679 | P58: pass | Q58: 2/19 截SI | R58: 45624 | S58: 无 | T58: EAN条码贴翻144795 | U58: 日期码格式：ZURU INC(BVI) 标准格式 日期：按实际生产日期 Packaging Info: 77515GQ1：MA最新1L配套包装+客户EAN条码贴一张覆盖ZURU 原条码，条码贴翻订单4500144795。 另外产品内包装再加多一张2国语言电池说明书 ，即产品内含2张说明书 （ZURU标准说明书1张+2国语言电池说明书），两国语言说明书翻订单4500148687 Remark: *MA版本按工厂现有最新库存即可，订单出英国，请注意检查产品及包装应带UKCA图标，包装显示ZURU UK LTD信息，QC同事请查核，如有问题与跟单确认。 *生产日期按实际（法定工作日），按ZURU标准格式即可 ，但是请知悉包装日期码需要早于或者等于外箱日期码 ，不能晚于外箱日期码 *请注意所有订单都需要经过ZURU QC验货并且通过后方可出货 *条码以订单显示为准 ，请安排生产前先核对 ，有问题请提出。 *所有产品按符合欧洲标准走货，需要是不含微塑料版本 。 *涉及到硼的，如可选择情况下应使用低硼版本 （slime 类别低硼一般低于300ppm)，无选择的应与跟单复核再安排 。 | V58: Amy Ding | W58: 1.4046 | X58: =I58*W58 -> 1606.8624 | Y58: 94275-2.18 | Z58: 77515GQ1-S001 | AA58: 已入 | AC58: 1144 | AD58: =AC58-I58 -> 0 | AH58: =I58 -> 1144 | AN58: =I58 -> 1144 | AU58: =I58 -> 1144 | BI58: =I58/13 -> 88 | BZ58: =AH58+AI58+AJ58 -> 1144 | CE58: =CE57-AH58-AI58-AJ58 -> 1666658
A59: 45623 | B59: THE ENTERTAINER | C59: 英国 | D59: 4500152538 | E59: 4500152538-3: FB12155 | F59: 4500152538-140 | G59: 77515GQ1-S001 | H59: DIY厨艺大师 | I59: 1456 | J59: 0 | K59: 52 | L59: =I59/K59 -> 28 | M59: 45696 | N59: 45679 | P59: pass | Q59: 2/19 截SI | R59: 45624 | S59: 无 | T59: EAN条码贴翻144795 | U59: 日期码格式：ZURU INC(BVI) 标准格式 日期：按实际生产日期 Packaging Info: 77515GQ1：MA最新1L配套包装+客户EAN条码贴一张覆盖ZURU 原条码，条码贴翻订单4500144795。 另外产品内包装再加多一张2国语言电池说明书 ，即产品内含2张说明书 （ZURU标准说明书1张+2国语言电池说明书），两国语言说明书翻订单4500148687 Remark: *MA版本按工厂现有最新库存即可，订单出英国，请注意检查产品及包装应带UKCA图标，包装显示ZURU UK LTD信息，QC同事请查核，如有问题与跟单确认。 *生产日期按实际（法定工作日），按ZURU标准格式即可 ，但是请知悉包装日期码需要早于或者等于外箱日期码 ，不能晚于外箱日期码 *请注意所有订单都需要经过ZURU QC验货并且通过后方可出货 *条码以订单显示为准 ，请安排生产前先核对 ，有问题请提出。 *所有产品按符合欧洲标准走货，需要是不含微塑料版本 。 *涉及到硼的，如可选择情况下应使用低硼版本 （slime 类别低硼一般低于300ppm)，无选择的应与跟单复核再安排 。 | V59: Amy Ding | W59: 1.4046 | X59: =I59*W59 -> 2045.0976 | Y59: 94275-2.18 | Z59: 77515GQ1-S001 | AA59: 已入 | AC59: 1456 | AD59: =AC59-I59 -> 0 | AH59: =I59 -> 1456 | AN59: =I59 -> 1456 | AU59: =I59 -> 1456 | BI59: =I59/13 -> 112 | BZ59: =AH59+AI59+AJ59 -> 1456 | CE59: =CE58-AH59-AI59-AJ59 -> 1665202
A60: 45623 | B60: THE ENTERTAINER | C60: 英国 | D60: 4500152538 | E60: 4500152538-4: FB12134 | F60: 4500152538-240 | G60: 77515GQ1-S001 | H60: DIY厨艺大师 | I60: 1300 | J60: 0 | K60: 52 | L60: =I60/K60 -> 25 | M60: 45696 | N60: 45679 | P60: pass | Q60: 2/19 截SI | R60: 45624 | S60: 无 | T60: EAN条码贴翻144795 | U60: 日期码格式：ZURU INC(BVI) 标准格式 日期：按实际生产日期 Packaging Info: 77515GQ1：MA最新1L配套包装+客户EAN条码贴一张覆盖ZURU 原条码，条码贴翻订单4500144795。 另外产品内包装再加多一张2国语言电池说明书 ，即产品内含2张说明书 （ZURU标准说明书1张+2国语言电池说明书），两国语言说明书翻订单4500148687 Remark: *MA版本按工厂现有最新库存即可，订单出英国，请注意检查产品及包装应带UKCA图标，包装显示ZURU UK LTD信息，QC同事请查核，如有问题与跟单确认。 *生产日期按实际（法定工作日），按ZURU标准格式即可 ，但是请知悉包装日期码需要早于或者等于外箱日期码 ，不能晚于外箱日期码 *请注意所有订单都需要经过ZURU QC验货并且通过后方可出货 *条码以订单显示为准 ，请安排生产前先核对 ，有问题请提出。 *所有产品按符合欧洲标准走货，需要是不含微塑料版本 。 *涉及到硼的，如可选择情况下应使用低硼版本 （slime 类别低硼一般低于300ppm)，无选择的应与跟单复核再安排 。 | V60: Amy Ding | W60: 1.4046 | X60: =I60*W60 -> 1825.98 | Y60: 94275-2.18 | Z60: 77515GQ1-S001 | AA60: 已入 | AC60: 1300 | AD60: =AC60-I60 -> 0 | AH60: =I60 -> 1300 | AN60: =I60 -> 1300 | AU60: =I60 -> 1300 | BI60: =I60/13 -> 100 | BZ60: =AH60+AI60+AJ60 -> 1300 | CE60: =CE59-AH60-AI60-AJ60 -> 1663902
A61: 45632 | B61: THE FARMERS' TRADING COMPANY LIMITE | C61: 新西兰 | D61: 4500153390 | E61: 4503999972 | F61: 4500153390-20 | G61: 77515GQ1-S003 | H61: DIY厨艺大师 | I61: 1040 | J61: 0 | K61: 13 | L61: =I61/K61 -> 80 | M61: 45702 | N61: 45698 | P61: pass | Q61: 2/27 截SI | R61: 45632 | S61: 无 | T61: 12/16 价格贴纸+电池警告语贴纸 | U61: 日期码格式：ZURU INC(BVI) 标准格式 日期：按实际生产日期 Packaging Info: MA UPC英语包装（优先1L英语版本,或者3L/L含英语即可）+可移动材质的价格贴纸（价格贴纸要切虚线) 77515GQ1: 包装正面和说明书都需要加电池警告语贴纸（法规要求） Remark: 77515GQ1: 3PCS AG13 Batteries(Included) | V61: Abby Liang | W61: 1.4071 | X61: =I61*W61 -> 1463.384 | Y61: 94350-2.25 | Z61: 77515GQ1-S003 | AA61: 已入 | AC61: 1040 | AD61: =AC61-I61 -> 0 | AH61: =I61 -> 1040 | AN61: =I61 -> 1040 | AU61: =I61 -> 1040 | BI61: =I61/13 -> 80 | BZ61: =AH61+AI61+AJ61 -> 1040 | CE61: =CE60-AH61-AI61-AJ61 -> 1662862
A62: 45615 | B62: DD’S DISCOUNTS | C62: 美国 | D62: 4500151537 | E62: 70054036 | F62: 4500151537-20 | G62: 77516-S001 | H62: DIY厨艺大师*2 | I62: 504 | J62: 0 | K62: 12 | L62: =I62/K62 -> 42 | M62: 45705 | N62: 45701 | P62: pass | Q62: 3/21 截SI | R62: 45616 | S62: 无 | T62: 1/3客供价格贴纸+空白贴纸 | U62: 日期码格式： 标准格式 日期：按实际生产日期 Packaging Info: 1.ZURU MA UPC 收缩膜+客版铜版纸+PVC桶 + 客供价格贴纸，出口美国 , 优先使用MA 1L 最新版本 。 2.#77516请使用MA 3L 收缩膜+空白贴纸覆盖EAN条码 Remark: 1.ZURU MA UPC 收缩膜+客版铜版纸+PVC桶 + 客供价格贴纸，出口美国 , 优先使用MA 1L 最新版本 。 2.价格贴纸位于包装正面右下角，不挡住重要信息即可，可适当调整 ，价格贴纸由跟单提供。 3.标准日期码格式，产品和包装必须有日期码 。 4.同个产品同个货期不可出现不同的包装。 5. PVC 桶中球不能出现完全相同的ASSORTMENT ， 即同一个PVC 中球里的ASSORTMENT 需要不同。 以免消费者失望。 6.PVC 桶上加上 MINI BRANDS 的LOGO 贴纸 （ ZURU 统一要求的） 7.收缩膜可使用标版带UPC条码MA，无需白色贴纸覆盖。 8.#77516请使用MA 3L 收缩膜+空白贴纸覆盖EAN条码 | V62: Taylor Liao | W62: 3.1012 | X62: =I62*W62 -> 1563.0048 | Y62: ZB00019-3.20 | Z62: 77516-S001-1L | AA62: 已入 | AC62: 504 | AD62: =AC62-I62 -> 0 | AH62: =I62*2 -> 1008 | AO62: =AH62 -> 1008 | AU62: =AH62 -> 1008 | BW62: =I62 -> 504 | BX62: =I62 -> 504 | BZ62: =AH62+AI62+AJ62 -> 1008 | CE62: =CE61-AH62-AI62-AJ62 -> 1661854
A63: 45651 | B63: AMIC TRADING (PTY) LTD | C63: 南非 | D63: 4500154694 | E63: 6006-005226 | F63: 4500154694-30 | G63: 77515GQ6-S001 | H63: DIY厨艺大师 | I63: 816 | J63: 0 | K63: 48 | L63: =I63/K63 -> 17 | M63: 45713 | N63: =M63-4 -> 45709 | P63: PASS | Q63: 2/27 截SI | R63: 45651 | S63: 无 | T63: 1/2 进口商贴纸 | U63: 日期码格式：ZURU INC(BVI) 标准格式 日期：按实际生产日期 Packaging Info: MA PKG, 优先1L +1张进口商贴纸（贴条码附近空白处，不得遮挡日期码） 该客户只有一款进口商贴纸，所有款通用，进口商贴纸AW可翻此客户旧订单 Remark: | V63: Doris Shou | W63: 1.3917 | X63: =I63*W63 -> 1135.6272 | Y63: 94351-2.25 | Z63: 77515GQ6-S001 | AA63: 已入 | AC63: 816 | AD63: =AC63-I63 -> 0 | AH63: =I63 -> 816 | AN63: =I63 -> 816 | AU63: =I63 -> 816 | BG63: =I63/12 -> 68 | BZ63: =AH63+AI63+AJ63 -> 816 | CE63: =CE62-AH63-AI63-AJ63 -> 1661038
A64: 45653 | B64: Amazon Italy | C64: 意大利 | D64: 4500154891 | E64: Amazon IT: 6MR547DO | F64: 4500154891-20 | G64: 77515-S001 | H64: DIY厨艺大师 | I64: 2016 | J64: 0 | K64: 24 | L64: =I64/K64 -> 84 | M64: 45716 | N64: 45712 | P64: PASS | Q64: 3/10 入仓 | R64: 空白外箱（加印带Zuru字样的最新logo，除了邮包盒直接做外箱的产品） | S64: 有 | T64: ZURU邮箱贴纸翻单154803 +1张UPC#，1张IT/FR sorting label，1张ES回收环保标志1号翻单PO#4500142613+1/10 防伪贴纸+12/30 SSCC | U64: 日期码格式：ZURU INC(BVI) 标准格式 日期：按实际生产日期 Packaging Info: Amazon IT(92104D/77515) 2. 77515：24pcs/ctn, no inner; MA 3L(5L warning EAN#) B收缩膜+4张贴纸(1张UPC#，1张IT/FR sorting label，1张ES回收环保标志1号，参考翻单PO#4500142 613；1张ZURU邮箱贴纸，参考翻单PO#4500154803）+MA 5L B配件袋+MA 5L A收藏指南+MA23L B警示说明书+其他最新版MA包装+1张防伪贴纸(具体位置参考USA同款 订单)； 3. 最迟验货不得晚于2025/02/28; Remark: 1.空白外箱（加印带Zuru字样的最新logo，除了邮包盒直接做外箱的产品） + SSCC LABEL一张, 无箱唛，MADE IN CHINA 外箱只印一正一侧。箱唛资料按照给定的 标准去做即可，无需发回我方再行审批(新标准将另行通知)。 (SSCC LABEL竖贴在外箱正面的正中间，贴一面即可,贴纸离外箱边距必须至少3.2CM。如竖贴无法满足要求，则横贴。如横贴也无法满足要求，则竖贴，遮到ZURU lo go无影响), SSCC贴纸由工厂直接跟勤得采购或者工厂自行采购，每一张SSCC Label都是唯一且有不同流水及条码，且需要检查条码是否能正常扫描，另外，此贴纸 印刷不可出现模糊，溢出及粘胶不牢易脱落等现象，如工厂不按此要求导致贴纸有任何问题产生的罚款将由工厂承担一切责任 。 2.出往UK的产品+包装务必打上UKCA logo ，否则客人会退货且当地会有罚款。 3.订单必须经过ZURU QC验货并且通过后方可出货。 4.法国订单要求包装不使用矿物油，请按要求提供以下其中一份文件再出货 ，产品出到法国被相关部门抽检出现包装不符合此要求的，供应商需要为此承担责任， 故此请严格把关。 -油墨物质""由1 ~ 7个芳香环组成的MOAH""的包装检测报告，要求限值≤1.0%； -包装材料清单，包括包装油墨或物质的信息； -油墨制造商的证书； 5.每一批次出货只能有一个生产日期，不可多个生产日期混在同一批次出货；且邮包盒上必须统一加上日期码；外箱对于日期码没有硬性规定； 6.涉及到相关款式会有闪粉的或者微塑料的，请统一默认出无闪粉或者不含微塑料版本； 7.邮包盒及外箱封箱必须是工字型封箱方式； 8.5 Surprise or Mini Brands涉及包装是2个及2个以上的球入PVC桶包装时，单个球上若有UPC#或者EAN#，请用白色贴纸覆盖住 | V64: Mandy Hu | W64: 1.3595 | X64: =I64*W64 -> 2740.752 | Y64: 94547-3.14 | Z64: 77515-S001-3L | AA64: 已入 | AC64: 2016 | AD64: =AC64-I64 -> 0 | AH64: =I64 -> 2016 | AO64: =I64 -> 2016 | AU64: =I64 -> 2016 | BZ64: =AH64+AI64+AJ64 -> 2016 | CE64: =CE63-AH64-AI64-AJ64 -> 1659022
A65: 45652 | B65: AMAZON UK | C65: 德国 | D65: 4500154803 | E65: Amazon DE: 4TWZBWOK | F65: 4500154803-30 | G65: 77515-S001-PKC | H65: DIY厨艺大师1PCS/胶袋带印刷 | I65: 504 | J65: 0 | K65: 24 | L65: =I65/K65 -> 21 | M65: 45716 | N65: 45712 | P65: 自检 | Q65: 3/10 入仓 | R65: 空白外箱（加印带Zuru字样的最新logo，除了邮包盒直接做外箱的产品） | S65: 有 | T65: 12/26 ZURU邮箱贴纸 +1张UPC#，1张IT/FR sorting label，1张ES回收环保标志1号翻单PO#4500142613+1/10 防伪贴纸+12/30 SSCC | U65: 日期码格式：ZURU INC(BVI) 标准格式 日期：按实际生产日期 Packaging Info: Amazon UK(9543E)/DE(9543E/77515) 2. 77515：24pcs/ctn, no inner; MA 3L(5L warning EAN#) B收缩膜+4张贴纸(1张UPC#，1张IT/FR sorting label，1张ES回收环保标志1号，参考翻单PO#4500142 613；1张ZURU邮箱贴纸）+MA 5L B配件袋+MA 5L A收藏指南+MA23L B警示说明书+其他最新版MA包装+1张防伪贴纸(具体位置参考USA同款订单) +Polybag(含防窒息5 L警示语+塑料循环标) +1张贴纸(UPC#，参考翻单PO#4500142613，贴在polybag)； 3. 最迟验货不得晚于2025/02/28; *77515胶袋价格：0.128*3000=384RMB； Remark: 1.空白外箱（加印带Zuru字样的最新logo，除了邮包盒直接做外箱的产品） + SSCC LABEL一张, 无箱唛，MADE IN CHINA 外箱只印一正一侧。箱唛资料按照给定的 标准去做即可，无需发回我方再行审批(新标准将另行通知)。 (SSCC LABEL竖贴在外箱正面的正中间，贴一面即可,贴纸离外箱边距必须至少3.2CM。如竖贴无法满足要求，则横贴。如横贴也无法满足要求，则竖贴，遮到ZURU lo go无影响), SSCC贴纸由工厂直接跟勤得采购或者工厂自行采购，每一张SSCC Label都是唯一且有不同流水及条码，且需要检查条码是否能正常扫描，另外，此贴纸 印刷不可出现模糊，溢出及粘胶不牢易脱落等现象，如工厂不按此要求导致贴纸有任何问题产生的罚款将由工厂承担一切责任 。 2.出往UK的产品+包装务必打上UKCA logo ，否则客人会退货且当地会有罚款。 3.订单必须经过ZURU QC验货并且通过后方可出货。 4.法国订单要求包装不使用矿物油，请按要求提供以下其中一份文件再出货 ，产品出到法国被相关部门抽检出现包装不符合此要求的，供应商需要为此承担责任， 故此请严格把关。 -油墨物质""由1 ~ 7个芳香环组成的MOAH""的包装检测报告，要求限值≤1.0%； -包装材料清单，包括包装油墨或物质的信息； -油墨制造商的证书； 5.每一批次出货只能有一个生产日期，不可多个生产日期混在同一批次出货；且邮包盒上必须统一加上日期码；外箱对于日期码没有硬性规定； 6.涉及到相关款式会有闪粉的或者微塑料的，请统一默认出无闪粉或者不含微塑料版本； 7.邮包盒及外箱封箱必须是工字型封箱方式； 8.5 Surprise or Mini Brands涉及包装是2个及2个以上的球入PVC桶包装时，单个球上若有UPC#或者EAN#，请用白色贴纸覆盖住； | V65: Crystal Chen | W65: 1.3645 | X65: =I65*W65 -> 687.708 | Y65: 94665-3.28 | Z65: 77515-S001-PKC | AA65: 已入 | AC65: 504 | AD65: =AC65-I65 -> 0 | AH65: =I65 -> 504 | AO65: =I65 -> 504 | AU65: =I65 -> 504 | BZ65: =AH65+AI65+AJ65 -> 504 | CE65: =CE64-AH65-AI65-AJ65 -> 1658518
A66: 45667 | B66: KROGER (KRG LLC) | C66: 美国 | D66: 4500155435 | E66: PO#600-51058 | F66: 4500155435-70 | G66: 77515GQ2-S002 | H66: DIY厨艺大师 | I66: 5300 | J66: 0 | K66: 25 | L66: =I66/K66 -> 212 | M66: 45717 | N66: 45715 | P66: pass | Q66: 3/3 交仓 | R66: 45667 | S66: 无 | T66: 无 | U66: 日期码格式：ZURU INC(BVI) 标准格式 日期：按实际生产日期 Packaging Info: 1、包装方式：MA UPC优先1L最新版，出口美国 Remark: 2、无测试与第三方验货要求。 3、纸箱4面印ZURU LOGO + 箱唛 4、日期码请按ZURU标准版执行即可。 5、ZURU QC验货。 | V66: Vicky Wu | W66: 1.4116 | X66: =I66*W66 -> 7481.48 | Y66: ZB00067 | Z66: 77515GQ2-S002 | AA66: 已入 | AC66: 5300 | AD66: =AC66-I66 -> 0 | AH66: =I66 -> 5300 | AN66: =I66 -> 5300 | AU66: =I66 -> 5300 | BM66: =I66/25 -> 212 | BZ66: =AH66+AI66+AJ66 -> 5300 | CE66: =CE65-AH66-AI66-AJ66 -> 1653218
A67: 45667 | B67: KROGER (KRG LLC) | C67: 美国 | D67: 4500155435 | E67: PO#500-79871 | F67: 4500155435-80 | G67: 77515GQ2-S002 | H67: DIY厨艺大师 | I67: 2400 | J67: 0 | K67: 25 | L67: =I67/K67 -> 96 | M67: 45717 | N67: 45715 | P67: pass | Q67: 3/3 交仓 | R67: 45667 | S67: 无 | T67: 无 | U67: 日期码格式：ZURU INC(BVI) 标准格式 日期：按实际生产日期 Packaging Info: 1、包装方式：MA UPC优先1L最新版，出口美国 Remark: 2、无测试与第三方验货要求。 3、纸箱4面印ZURU LOGO + 箱唛 4、日期码请按ZURU标准版执行即可。 5、ZURU QC验货。 | V67: Vicky Wu | W67: 1.435 | X67: =I67*W67 -> 3444 | Y67: ZB00067 | Z67: 77515GQ2-S002 | AA67: 已入 | AC67: 2400 | AD67: =AC67-I67 -> 0 | AH67: =I67 -> 2400 | AN67: =I67 -> 2400 | AU67: =I67 -> 2400 | BM67: =I67/25 -> 96 | BZ67: =AH67+AI67+AJ67 -> 2400 | CE67: =CE66-AH67-AI67-AJ67 -> 1650818
A68: 45594 | B68: Distribuidora Liverpool S.A de C.V. | C68: 墨西哥 | D68: 4500149460 | E68: 61900883 | F68: 4500149460-160 | G68: 77515GQ2-S001 | H68: DIY厨艺大师 | I68: 1700 | J68: 0 | K68: 50 | L68: =I68/K68 -> 34 | M68: 45712 | N68: 45712 | O68: 加保证书 有第三方监柜 | P68: pass | Q68: 2/26 截SI | R68: 45660 | S68: 无 | T68: 2/8UPC贴纸+进口商贴纸+2/11价标贴纸+1/7保证书 | U68: 日期码格式：ZURU INC(BVI) 标准格式 日期：按实际生产日期 Packaging Info:77515GQ2:MA 3LEAN包装+MA 23L说明书+UPC贴纸+进口商贴纸+价标贴纸+箱唛+保证书，包装和说明书都需要贴一张进口商贴纸 Remark: 1. 此单价格贴纸（ZURU定购). 2.此单有第三方监柜，不用额外准备备品，会在大货中每款拆1pc，拆了包装的产品会由监装员用客供胶带封好或在外箱上写上""opened by telescope” | V68: Ava Liang | W68: 1.4344 | X68: =I68*W68 -> 2438.48 | Y68: 94382-2.27 | Z68: 77515GQ2-S001-3L | AA68: 已入 | AC68: 1700 | AD68: =AC68-I68 -> 0 | AG68: 七 | AH68: =I68 -> 1700 | AO68: =I68 -> 1700 | AU68: =I68 -> 1700 | BN68: =I68/25 -> 68 | BZ68: =AH68+AI68+AJ68 -> 1700 | CE68: =CE67-AH68-AI68-AJ68 -> 1649118
A69: 45611 | B69: Distribuidora Liverpool S.A de C.V. | C69: 墨西哥 | D69: 4500151307 | F69: 4500151307-100 | G69: 77515GQ2-S001 | H69: DIY厨艺大师 | I69: 750 | J69: 0 | K69: 50 | L69: =I69/K69 -> 15 | M69: 45712 | N69: 45712 | O69: 加保证书 有第三方监柜 | P69: pass | Q69: 2/26 截SI | R69: 45665 | S69: 无 | T69: 2/8 进口商贴纸+2/11价标贴纸+2/8 UPC贴纸+1/7保证书 | U69: 日期码格式：ZURU INC(BVI) 标准格式 日期：按实际生产日期 Packaging Info: 77515GQ2:MA 3LEAN包装+MA 23L说明书+UPC贴纸+进口商贴纸+价标贴纸+箱唛+保证书,包装和说明书都需要加一张进口上贴纸，UPC贴纸/进口商贴纸/保证书翻单PO4500149460 Remark: 1. 此单价格贴纸（ZURU定购). 2.此单有第三方监柜，不用额外准备备品，会在大货中每款拆1pc，拆了包装的产品会由监装员用客供胶带封好或在外箱上写上""opened by telescope” | V69: Ava Liang | W69: 1.4395 | X69: =I69*W69 -> 1079.625 | Y69: 94352-2.25 | Z69: 77515GQ2-S001-3L | AA69: 已入 | AC69: 750 | AD69: =AC69-I69 -> 0 | AH69: =I69 -> 750 | AO69: =I69 -> 750 | AU69: =I69 -> 750 | BN69: =I69/25 -> 30 | BZ69: =AH69+AI69+AJ69 -> 750 | CE69: =CE68-AH69-AI69-AJ69 -> 1648368
A70: 45651 | B70: Distribuidora Liverpool S.A de C.V. | C70: 墨西哥 | D70: 4500154604 | E70: 61900884 | F70: 4500154604-150 | G70: 77515GQ2-S001 | H70: DIY厨艺大师 | I70: 1650 | J70: 0 | K70: 50 | L70: =I70/K70 -> 33 | M70: 45721 | N70: 45717 | O70: 保证书翻单PO4500149460 | P70: pass | Q70: 3/14 截SI | R70: 45695 | S70: 无 | T70: 2/18 价格贴纸+UPC贴纸/进口商贴纸翻单PO4500137056+保证书翻单PO4500149460 | U70: 日期码格式：ZURU INC(BVI) 标准格式 日期：按实际生产日期 Packaging Info: 77515GQ2:MA 3LEAN包装+MA 23L说明书+UPC贴纸+进口商贴纸+价标贴纸+箱唛+保证书，包装和说明书都需要贴一张进口商贴纸，UPC贴纸/进口商贴纸/保证书翻单PO4500149460 Remark: 1. 此单价格贴纸（ZURU定购). 2.此单有第三方监柜，不用额外准备备品，会在大货中每款拆1pc，拆了包装的产品会由监装员用客供胶带封好或在外箱上写上""opened by telescope” | V70: Ava Liang | W70: 1.4344 | X70: =I70*W70 -> 2366.76 | Y70: 94525-3.12 | Z70: 77515GQ2-S001-3L | AA70: 已入 | AC70: 1650 | AD70: =AC70-I70 -> 0 | AH70: =I70 -> 1650 | AO70: =I70 -> 1650 | AU70: =I70 -> 1650 | BN70: =I70/25 -> 66 | BZ70: =AH70+AI70+AJ70 -> 1650 | CE70: =CE69-AH70-AI70-AJ70 -> 1646718
A71: 45651 | B71: Distribuidora Liverpool S.A de C.V. | C71: 墨西哥 | D71: 4500154624 | E71: 61900885 | F71: 4500154624-150 | G71: 77515GQ2-S001 | H71: DIY厨艺大师 | I71: 1650 | J71: 0 | K71: 50 | L71: =I71/K71 -> 33 | M71: 45730 | N71: 45726 | O71: 保证书翻单PO4500149460 | P71: pass | Q71: 3/21 截SI | R71: 45698 | S71: 无 | T71: 2/18价格贴纸+UPC贴纸/进口商贴纸翻单PO4500137056 | U71: 日期码格式：ZURU INC(BVI) 标准格式 日期：按实际生产日期 Packaging Info: 77515GQ2:MA 3LEAN包装+MA 23L说明书+UPC贴纸+进口商贴纸+价标贴纸+箱唛+保证书，包装和说明书都需要贴一张进口商贴纸，UPC贴纸/进口商贴纸/保证书翻单PO4500149460 Remark: 1. 此单价格贴纸（ZURU定购). 2.此单有第三方监柜，不用额外准备备品，会在大货中每款拆1pc，拆了包装的产品会由监装员用客供胶带封好或在外箱上写上""opened by telescope” | V71: Ava Liang | W71: 1.4344 | X71: =I71*W71 -> 2366.76 | Y71: 94698-4.3 | Z71: 77515GQ2-S001-3L | AA71: 已入 | AC71: 1650 | AD71: =AC71-I71 -> 0 | AH71: =I71 -> 1650 | AO71: =I71 -> 1650 | AU71: =I71 -> 1650 | BN71: =I71/25 -> 66 | BZ71: =AH71+AI71+AJ71 -> 1650 | CE71: =CE70-AH71-AI71-AJ71 -> 1645068
A72: 45660 | B72: THE ENTERTAINER | C72: 英国 | D72: 4500154847 | E72: FB12131 | F72: 4500154847-50 | G72: 77515GQ1-S001 | H72: DIY厨艺大师 | I72: 1352 | J72: 0 | K72: 52 | L72: =I72/K72 -> 26 | M72: 45716 | N72: 45712 | O72: 已出样板 | P72: pass | Q72: 3/4 截SI | R72: 45660 | S72: 无 | T72: EAN条码翻单144795 +1/3电池说明书 | U72: 日期码格式：ZURU INC(BVI) 标准格式 日期：按实际生产日期 Packaging Info: 77515GQ1: MA最新1L配套包装+客户EAN条码(翻单4500144795)覆盖ZURU 原条码，另外产品内包装再加多一张2国语言电池说明书 ，即产品内含2张说明书 （ZURU标 准说明书1张+2国语言电池说明书）,MA PDQ Remark: *MA版本按工厂现有最新库存即可，订单出英国，请注意检查产品及包装应带UKCA图标，包装显示ZURU UK LTD信息，QC同事请查核，如有问题与跟单确认 *生产日期按实际（法定工作日），按ZURU标准格式即可 ，但是请知悉包装日期码需要早于或者等于外箱日期码 ，不能晚于外箱日期码 *请注意所有订单都需要经过ZURU QC验货并且通过后方可出货 *条码以订单显示为准 ，请安排生产前先核对 ，有问题请提出。 *所有产品按符合欧洲标准走货，需要是不含微塑料版本 。 *涉及到硼的，如可选择情况下应使用低硼版本 （slime 类别低硼一般低于300ppm)，无选择的应与跟单复核再安排 。 *条码以订单显示为准 ，请安排生产前先核对 ，有问题请提出。 *订单对应客户2个PO号 ，备注有显示 ，注意分开做货/验货/装柜 ，混装有罚款。 *样板： 请在1/20前每款寄出2pcs大货样到罗湖办公室 7B Sandy Shao收 | V72: Sandy Shao | W72: 1.3863 | X72: =I72*W72 -> 1874.2776 | Y72: 94436-3.4 | Z72: 77515GQ1-S001 | AA72: 已入 | AC72: 1352 | AD72: =AC72-I72 -> 0 | AH72: =I72 -> 1352 | AN72: =I72 -> 1352 | AU72: =I72 -> 1352 | BI72: =I72/13 -> 104 | BZ72: =AH72+AI72+AJ72 -> 1352 | CE72: =CE71-AH72-AI72-AJ72 -> 1643716
A73: 45670 | B73: Amazon Italy | C73: 意大利 | D73: 4500155641 | E73: Amazon IT: 77AL2RKU | F73: 4500155641-30 | G73: 77515-S001-PKC | H73: DIY厨艺大师1PCS/胶袋带印刷 | I73: 720 | J73: 0 | K73: 24 | L73: =I73/K73 -> 30 | M73: 45723 | N73: 45719 | P73: pass | Q73: 3/17入仓 | R73: 空白外箱（加印带Zuru字样的最新logo，除了邮包盒直接做外箱的产品） | S73: 有 | T73: ZURU邮箱贴纸翻单154803 +1张UPC#，1张IT/FR sorting label，1张ES回收环保标志1号翻单142613+2/8 防伪贴纸+1/26 SSCC | U73: 日期码格式：ZURU INC(BVI) 标准格式 日期：按实际生产日期 Packaging Info: Amazon IT(92104H/92104D/77515) 3. 77515：24pcs/ctn, no inner; MA 3L(5L warning EAN#) B收缩膜+4张贴纸(1张UPC#，1张IT/FR环保标，1张ES回收环保标志1号，参考翻单PO#4500142613；1张 ZURU邮箱贴纸，参考翻单PO#4500154803）+MA 5L C配件袋+MA 5L A收藏指南+MA23L C警示说明书+其他最新版MA包装+1张防伪贴纸(具体位置参考USA同款订单)+Polybag(含防窒息5L警示语+塑料循环标，参考翻单PO#4500154803)+1张贴纸(UPC#，参考翻单PO#4500142613，贴在polybag)； 4. 最迟验货不得晚于2025/3/10. Remark: 1.空白外箱（加印带Zuru字样的最新logo，除了邮包盒直接做外箱的产品） + SSCC LABEL一张, 无箱唛。 (SSCC LABEL贴在外箱正面的正中间，贴一面即可,贴纸离外箱边距必须至少3.2CM), SSCC贴纸由工厂直接跟勤得采购或者工厂自行采购，每一张SSCC Label都是唯一 且有不同流水及条码，且需要检查条码是否能正常扫描，另外，此贴纸印刷不可出现模糊，溢出及粘胶不牢易脱落等现象，如工厂不按此要求导致贴纸有任何问题产 生的罚款将由工厂承担一切责任 。’MADE IN CHINA 外箱只印一正一侧。 2.出往UK的产品+包装务必打上UKCA logo ，否则客人会退货且当地会有罚款。 3.订单必须经过ZURU QC验货并且通过后方可出货。 4.法国订单要求包装不使用矿物油，请按要求提供以下其中一份文件再出货 ，产品出到法国被相关部门抽检出现包装不符合此要求的，供应商需要为此承担责任， 故此请严格把关。 -油墨物质""由1 ~ 7个芳香环组成的MOAH""的包装检测报告，要求限值≤1.0%； -包装材料清单，包括包装油墨或物质的信息； -油墨制造商的证书； 5.每一批次出货只能有一个生产日期，不可多个生产日期混在同一批次出货；且邮包盒上必须统一加上日期码； 6.涉及到相关款式会有闪粉的或者微塑料的，请统一默认出无闪粉或者不含微塑料版本； 7.邮包盒及外箱封箱必须是工字型封箱方式； 8.5 Surprise or Mini Brands涉及包装是2个及2个以上的球入PVC桶包装时，单个球上若有UPC#或者EAN#，请用白色贴纸覆盖住； 9.箱唛资料按照给定的标准去做即可，无需发回我方再行审批(新标准将另行通知); | V73: Mandy Hu | W73: 1.41 | X73: =I73*W73 -> 1015.2 | Y73: 94600-3.21 | Z73: 77515-S001-PKC | AA73: 已入 | AC73: 720 | AD73: =AC73-I73 -> 0 | AH73: =I73 -> 720 | AO73: =I73 -> 720 | AU73: =I73 -> 720 | BZ73: =AH73+AI73+AJ73 -> 720 | CE73: =CE72-AH73-AI73-AJ73 -> 1642996
A74: 45672 | B74: ZURU France | C74: 法国 | D74: 4500155852 | E74: 5200006018 | F74: 4500155852-20 | G74: 77515GQ2-S002-NS-MTS | H74: DIY厨艺大师-无香味版本 | I74: 1000 | J74: 0 | K74: 25 | L74: =I74/K74 -> 40 | M74: 45720 | N74: 45716 | P74: pass | Q74: 3/14 截SI | R74: 45673 | S74: 无 | T74: 法意西回收贴纸+ 无香贴纸+说明书贴纸+纸袋贴纸 贴纸翻4500151118 | U74: 日期码格式：ZURU INC(BVI) 标准格式 日期：按实际生产日期 Packaging Info: 77515GQ2: 最新MA 3L EAN收缩膜+一张法意西回收贴纸+ MA 23L 说明书+MA PDQ+ MA收藏指南加无香贴纸（所有包装如有提示香味都做无香版）+一张说明书贴纸+ 一张纸袋贴纸 （贴纸翻4500151118） Remark: 1. 西班牙国家内销单，需要通过ZURU 验货结果后才能出货 (工厂需要主动提前同ZURU QC预约验货避免延期出货造成不必要麻烦)； 2. 本订单所有 具有 baby items / assorted items 的款式，零售包装上都要用 母 EAN; 3. 若有特定款有特殊外箱条码要求时,需要明确列出产品款对应的具体外箱条码号码/条码类型 (若无,可以忽略此需求) 4. 所有出口欧洲的产品, 法规规定禁止在包装和共公众用的印刷品中使用矿物油中含有的物质, 包装印刷油墨中含有的MOAH/MOSH的质量浓度不能超过1%, 否则出 货到法国被抽检出现问题, 供应商需要对此负责; 5. Date code: 外箱/产品/包装 保持一致，完货后提供date code 信息以便我们保存记录做批次管理; 6. 装柜时需要按照款式号码从小到大一款款依次装,避免终端仓库卸货混乱.若一个柜子涉及到几个不同国家内销单,装柜时需要一个国家装完后再装另一个国家的 产品,依次装柜,避免终端仓库因不同国家不同库位位置卸货混乱. (此点需要同工厂装柜人员强调) 7，请每款寄一套给Lisa Yang 用于上传西班牙网站, 以下是地址和联系方式，样品相关细节请与Lisa沟通@Lisa Yang - Merchandising <(>&<)> Operations <(> <<)>Lisa.ywx@zuru.com>. Lisa.Yang (+86) 755 6688 1988 – 3327| +86 15012613809 广东省深圳市罗湖区东门南路1006号口岸大楼A座7楼 | V74: SD83 | W74: 1.4171 | X74: =I74*W74 -> 1417.1 | Y74: 94475-3.6 | Z74: 77515GQ2-S002-NS | AA74: 已入 | AC74: 1000 | AD74: =AC74-I74 -> 0 | AI74: =I74 -> 1000 | AO74: =I74 -> 1000 | AU74: =I74 -> 1000 | BN74: =I74/25 -> 40 | BZ74: =AH74+AI74+AJ74 -> 1000 | CE74: =CE73-AH74-AI74-AJ74 -> 1641996
A75: 45677 | B75: Bol.com | C75: 新西兰 | D75: 4500156115 | E75: 7631985 | F75: 4500156115-390 | G75: 77515-S001 | H75: DIY厨艺大师 | I75: 504 | J75: 0 | K75: 24 | L75: =I75/K75 -> 21 | M75: 45730 | N75: 45726 | P75: 自检 | Q75: 3/14 截SI | R75: 45677 | S75: 无 | T75: 翻单4500131176 | U75: 日期码格式：ZURU INC(BVI) 标准格式 日期：按实际生产日期 Packaging Info: BOL NL(77515) 2. 77515: 24pcs/ctn, no inner,3PCS AG13 BATTERIES(INCLUDED), Contain UV Glue and Cream Glue; MA 3L(5L warning EAN)B 收缩膜+1张NL警告语贴纸(贴在 收缩膜上<(>,<)>参考翻单PO#4500131176)+MA 23L B说明书+MA 5L A收藏指南+MA 5L B配件袋； 13. 验货时间不迟于2025/3/17. Remark: 1. 出欧洲产品不可含闪粉或者微塑料，若所涉产品无闪粉或不含微塑料可忽略此点； 2. 5 Surprise or Mini Brands涉及包装是2个及2个以上的球入PVC桶包装时，单个球上若有UPC#或者EAN#，请用白色贴纸覆盖住； 3. 箱唛资料按照提供的要求去做即可，无需再发回我方确认； 4.柜货产品务必拉网且要拉紧，拉网要求： A: 网要结实同时网格要细，纸箱不能从网格处跌落下来 B: 打网固定8-10个点。请提供拉网的装柜照片给船务确认 后柜子再离厂。" | V75: Crystal Chen | W75: 1.3507 | X75: =I75*W75 -> 680.7528 | Y75: 94548-3.14 | Z75: 77515-S001-3L | AA75: 已入 | AC75: 504 | AD75: =AC75-I75 -> 0 | AH75: =I75 -> 504 | AO75: =I75 -> 504 | AU75: =I75 -> 504 | BZ75: =AH75+AI75+AJ75 -> 504 | CE75: =CE74-AH75-AI75-AJ75 -> 1641492
A76: 45672 | B76: PLASTICOSUR S.A. | C76: 西班牙 | D76: 4500155934 | F76: 4500155934-50 | G76: 77515GQ2-S001 | H76: DIY厨艺大师 | I76: 300 | J76: 0 | K76: 50 | L76: =I76/K76 -> 6 | M76: 45731 | N76: 45727 | P76: 自检 | Q76: 3/17 截SI | R76: 45695 | S76: 无 | T76: 2/11进口商贴纸+产品贴纸 | U76: 日期码格式：ZURU INC(BVI) 标准格式 日期：按实际生产日期 Packaging Info: 5.77515GQ2:最新MA 3L EAN版本包装+一张西班牙环保标贴纸； | V76: Miya Fang | W76: 1.4395 | X76: =I76*W76 -> 431.85 | Y76: 94601-3.21 | Z76: 77515GQ2-S001-3L | AA76: 已入 | AC76: 300 | AD76: =AC76-I76 -> 0 | AH76: =I76 -> 300 | AO76: =I76 -> 300 | AU76: =I76 -> 300 | BN76: =I76/25 -> 12 | BZ76: =AH76+AI76+AJ76 -> 300 | CE76: =CE75-AH76-AI76-AJ76 -> 1641192
A77: 45666 | B77: THE ENTERTAINER | C77: 英国 | D77: 4500154984 | E77: FB12133 | F77: 4500154984-10 | G77: 77515GQ1-S001 | H77: DIY厨艺大师 | I77: 1196 | J77: 0 | K77: 52 | L77: =I77/K77 -> 23 | M77: 45740 | N77: 45736 | O77: 加多一张2国语言电池说明书 | Q77: 3/25 截SI | R77: 45666 | S77: 无 | T77: EAN条码翻单144795 | U77: 日期码格式：ZURU INC(BVI) 标准格式 日期：按实际生产日期 Packaging Info: 77515GQ1: MA最新1L配套包装+客户EAN条码(翻单4500144795)覆盖ZURU 原条码，另外产品内包装再加多一张2国语言电池说明书 ，即产品内含2张说明书 （ZURU标 准说明书1张+2国语言电池说明书）,MA PDQ Remark: *MA版本按工厂现有最新库存即可，订单出英国，请注意检查产品及包装应带UKCA图标，包装显示ZURU UK LTD信息，QC同事请查核，如有问题与跟单确认 *生产日期按实际（法定工作日），按ZURU标准格式即可 ，但是请知悉包装日期码需要早于或者等于外箱日期码 ，不能晚于外箱日期码 *请注意所有订单都需要经过ZURU QC验货并且通过后方可出货 *条码以订单显示为准 ，请安排生产前先核对 ，有问题请提出。 *所有产品按符合欧洲标准走货，需要是不含微塑料版本 。 *涉及到硼的，如可选择情况下应使用低硼版本 （slime 类别低硼一般低于300ppm)，无选择的应与跟单复核再安排 。 *条码以订单显示为准 ，请安排生产前先核对 ，有问题请提出。 *订单对应客户1个PO号 ，备注有显示 ，注意分开做货/验货/装柜 ，混装有罚款。 *样板： 请在大货生产前寄出2pcs大货样到罗湖办公室 7B Sandy Shao收 | V77: Sandy Shao | W77: 1.4046 | X77: =I77*W77 -> 1679.9016 | Y77: 94635-3.25 | Z77: 77515GQ1-S001 | AA77: 已入 | AC77: 1196 | AD77: =AC77-I77 -> 0 | AH77: =I77 -> 1196 | AN77: =I77 -> 1196 | AU77: =I77 -> 1196 | BI77: =I77/13 -> 92 | BZ77: =AH77+AI77+AJ77 -> 1196 | CE77: =CE76-AH77-AI77-AJ77 -> 1639996
A78: 45666 | B78: THE ENTERTAINER | C78: 英国 | D78: 4500155272 | E78: FB12159 | F78: 4500155272-20 | G78: 77515GQ1-S001 | H78: DIY厨艺大师 | I78: 2964 | J78: 0 | K78: 52 | L78: =I78/K78 -> 57 | M78: 45747 | N78: 45743 | O78: 加多一张2国语言电池说明书 | P78: pass | Q78: 4/2 截SI 已出样板 | R78: 45666 | S78: 无 | T78: EAN条码翻单144795 | U78: 日期码格式：ZURU INC(BVI) 标准格式 日期：按实际生产日期 Packaging Info: 77515GQ1:MA最新1L配套包装+客户EAN条码(翻单4500144795)覆盖ZURU 原条码，另外产品内包装再加多一张2国语言电池说明书 ，即产品内含2张说明书 （ZURU标准 说明书1张+2国语言电池说明书）,MA PDQ Remark: *MA版本按工厂现有最新库存即可，订单出英国，请注意检查产品及包装应带UKCA图标，包装显示ZURU UK LTD信息，QC同事请查核，如有问题与跟单确认 *生产日期按实际（法定工作日），按ZURU标准格式即可 ，但是请知悉包装日期码需要早于或者等于外箱日期码 ，不能晚于外箱日期码 *请注意所有订单都需要经过ZURU QC验货并且通过后方可出货 *条码以订单显示为准 ，请安排生产前先核对 ，有问题请提出。 *所有产品按符合欧洲标准走货，需要是不含微塑料版本 。 *涉及到硼的，如可选择情况下应使用低硼版本 （slime 类别低硼一般低于300ppm)，无选择的应与跟单复核再安排 。 *条码以订单显示为准 ，请安排生产前先核对 ，有问题请提出。 * 大货样： 每个item 请在2/25 之前寄出2pcs 样板+1套散件到罗湖办公室7A Sandy Shao 收 | V78: Sandy Shao | W78: 1.3863 | X78: =I78*W78 -> 4108.9932 | Y78: 94684-4.1 | Z78: 77515GQ1-S001 | AA78: 已入 | AC78: 2964 | AD78: =AC78-I78 -> 0 | AH78: =I78 -> 2964 | AN78: =I78 -> 2964 | AU78: =I78 -> 2964 | BI78: =I78/13 -> 228 | BZ78: =AH78+AI78+AJ78 -> 2964 | CE78: =CE77-AH78-AI78-AJ78 -> 1637032
A79: 45672 | B79: ZURU Italy SRL | C79: 意大利 | D79: 4500155954 | E79: 5200006012 | F79: 4500155954-10 | G79: 77515SK-S002-NS-MTS | H79: DIY厨艺大师-无香味版本 | I79: 6000 | J79: 0 | K79: 60 | L79: =I79/K79 -> 100 | M79: 45724 | N79: 45720 | P79: pass | Q79: 3/10 截SI | R79: 45673 | S79: 无 | T79: 法意西回收贴纸+ 无香贴纸+说明书贴纸+纸袋贴纸 贴纸翻4500151118 | U79: 日期码格式：ZURU INC(BVI) 标准格式 日期：按实际生产日期 Packaging Info: 最新MA 3L EAN收缩膜+一张法意西回收贴纸+ MA 23L 说明书+MA PDQ+ MA收藏指南加无香贴纸（所有包装如有提示香味都做无香版）+一张说明书贴纸+一张纸袋贴纸 （贴纸翻4500151118） Remark: 1.意大利国家内销单，需要通过ZURU 验货结果后才能出货 (工厂需要主动提前同ZURU QC预约验货避免延期出货造成不必要麻烦)； 2. SMASHERS 或含Slime产品，所有化合物使用无硼版本出意大利。 3. 本订单所有 具有 baby items / assorted items 的款式，零售包装上都要用 母 EAN; 4.所有出口欧洲的产品, 法规规定禁止在包装和共公众用的印刷品中使用矿物油中含有的物质, 包装印刷油墨中含有的MOAH/MOSH的质量浓度不能超过1%, 否则出货 到意大利被抽检出现问题, 供应商需要对此负责; 5. Date code: 外箱/产品/包装 保持一致，完货后提供date code 信息以便我们保存记录做批次管理； 6. 装柜时需要按照款式号码从小到大一款款依次装,避免终端仓库卸货混乱.若一个柜子涉及到几个不同国家内销单,装柜时需要一个国家装完后再装另一个国家的 产品,依次装柜,避免终端仓库因不同国家不同库位位置卸货混乱. (此点需要同工厂装柜人员强调)" 7. 意大利订单包装彩卡请确保含法规要求的环保回收logo。 | V79: Jade Wang | W79: 20.9573 | X79: =W79*L79 -> 2095.73 | Y79: 94511-3.11 | Z79: 77515SK-S002-NS | AA79: 已入 | AC79: 6000 | AD79: =AC79-I79 -> 0 | AI79: =I79 -> 6000 | AO79: =I79 -> 6000 | AU79: =I79 -> 6000 | BQ79: =I79/60 -> 100 | BZ79: =AH79+AI79+AJ79 -> 6000 | CE79: =CE78-AH79-AI79-AJ79 -> 1631032
A80: 45719 | D80: ZMPO250165 | G80: 77515-S001 | H80: 空球-收缩内收缩膜 | I80: 3000 | J80: 0 | K80: 24 | L80: =I80/K80 -> 125 | M80: 45727 | N80: 45723 | P80: 自检 | R80: 空白箱 | S80: 无 | T80: 无 | U80: Remark：只需77515的空球，只需用外面透明收缩膜压缩就好，不需要彩色收缩膜;备注： 收到样品订单后尽快安排 ，注意样板品质质量要求要高于大货品质要求 ，送货时必须要附带送货单(没有送货单和QC检验合格报告的仓库一律拒绝收货)，请知悉，谢谢！ | V80: Angus | Y80: 年存 | Z80: 77515-S001-2 | AA80: 已入 | AC80: 3000 | AD80: 0 | CE80: =CE79-AH80-AI80-AJ80 -> 1631032
A81: 45674 | B81: Prenatal Retail Group Spain S.L. | C81: 西班牙 | D81: 4500156067 | E81: 2000007268 | F81: 4500156067-70 | G81: 77515GQ2-S001 | H81: DIY厨艺大师 | I81: 1400 | J81: 0 | K81: 50 | L81: =I81/K81 -> 28 | M81: 45737 | N81: 45733 | O81: 已出样板 | P81: pass | R81: 45707 | S81: 无 | T81: 2/19进口商贴纸+产品贴纸 | U81: 日期码格式：LOT2511 日期： Packaging Info: 7.77515GQ2:最新MA 3L EAN收缩膜+最新MA 23L说明书+最新MA 收藏指南+ 一张进口商贴纸（含葡萄牙警语+西班牙环保标）+一张产品贴纸+一张WEEE说明书纸 Remark: 1. 订单出欧洲国家-西班牙，产品不能含有闪粉/微塑料，请确保所有包装都有西班牙环保标。 2. 客人格式日期码 LOT2511，产品（蛋壳等）/包装（收缩膜等）/外箱都需要印此日期码，请务必保持一致。 3. 新品需提供2套大货样品给客人，客人会签回一套，验货后验货员需要封1套板寄给香港办公室，请多备料。 4. 需要符合欧洲标准不能含有闪粉和微塑料，否则不合法规会有客诉产生。 5. 硼含量需要符合欧洲标准，否则不合法规会有客诉产生 6，此客户需要第三方验货，请在约三方验货前必须PASS ZURU验货。 | V81: Jade Wang | W81: 1.4344 | X81: =I81*W81 -> 2008.16 | Y81: 94699-4.3 | Z81: 77515GQ2-S001-3L | AA81: 已入 | AC81: 1400 | AD81: =AC81-I81 -> 0 | AH81: =I81 -> 1400 | AO81: =I81 -> 1400 | AU81: =I81 -> 1400 | BN81: =I81/25 -> 56 | BZ81: =AH81+AI81+AJ81 -> 1400 | CE81: =CE80-AH81-AI81-AJ81 -> 1629632
A82: 45674 | B82: ZURU Germany GMBH | C82: 德国 | D82: 4500156082 | E82: 5200006028 | F82: 4500156082-100 | G82: 77515SK1-S002-MTS | H82: DIY厨艺大师 | I82: 1800 | J82: 0 | K82: 30 | L82: =I82/K82 -> 60 | M82: 45738 | N82: 45734 | P82: pass | R82: 45678 | S82: 无 | T82: 1/23 警语贴纸 | U82: 日期码格式：ZURU INC(BVI) 标准格式 日期：按实际生产日期 Packaging Info: 77515SK1:MA最新3L+5L warning EAN收缩膜+PL/HU/SK/CZ/RO警语贴纸+MA最新版 3L 展示架 Remark: 1.波兰内销单，需要通过ZURU 验货结果后才能出货 (工厂需要主动提前同ZURU QC预约验货避免延期出货造成不必要麻烦)； 2. 若有特定款有特殊外箱条码要求时,需要明确列出产品款对应的具体外箱条码号码/条码类型 (若无,可以忽略此需求) 3.所有出口欧洲的产品, 法规规定禁止在包装和共公众用的印刷品中使用矿物油中含有的物质, 包装印刷油墨中含有的MOAH/MOSH的质量浓度不能超过1%, 否则出货 到法国被抽检出现问题, 供应商需要对此负责; 4. date code: 外箱日期码要晚于或等于产品日期码，不能早于产品的日期码 5. 所有电子产品身上需要加字唛，为ZURU FRANCE 地址 (如无电子产品，或者产品布标有此地址，可忽略此信息) ZURU France 1/3, Rue d'Argenteuil 95210 SAINT-GRATIEN, FRANCE 6. 装柜时需要按照款式号码从小到大一款款依次装,避免终端仓库卸货混乱.若一个柜子涉及到几个不同国家内销单,装柜时需要一个国家装完后再装另一个国家的 产品,依次装柜,避免终端仓库因不同国家不同库位位置卸货混乱. (此点需要同工厂装柜人员强调) | V82: SD82 | W82: 57.6474 | X82: =L82*W82 -> 3458.844 | Y82: 94560-3.14 | Z82: 77515SK1-S002-3L | AA82: 已入 | AC82: 1800 | AD82: =AC82-I82 -> 0 | AH82: =I82 -> 1800 | AO82: =I82 -> 1800 | AU82: =I82 -> 1800 | BS82: =I82/30 -> 60 | BT82: =BS82 -> 60 | BZ82: =AH82+AI82+AJ82 -> 1800 | CE82: =CE81-AH82-AI82-AJ82 -> 1627832
A83: 45699 | B83: 360 SALES SOLUTIONS INC | C83: 加拿大 | D83: 4500157213 | E83: 2025ZURU10 | F83: 4500157213-10 | G83: 77515GQ6-S002 | H83: DIY厨艺大师 | I83: 3204 | J83: 0 | K83: 12 | L83: =I83/K83 -> 267 | M83: 45740 | N83: =M83-4 -> 45736 | P83: pass | Q83: 3/26 截SI | R83: 45699 | S83: 无 | T83: 2/11UPC贴纸 | U83: 日期码格式： 标准格式 日期：按实际生产日期 Packaging Info: 77515GQ6 MA 多语EAN+UPC贴纸 UPC 193052061034 Remark: 出加拿大 Zuru验货.日期跟踪码：产品外包装及产品本身都必须有日期跟踪码，ZURU标准格式日期码。（箱唛日期码按跟单提供格式） | V83: Summer Mo | W83: 1.3886 | X83: =I83*W83 -> 4449.0744 | Y83: 94638-3.25 | Z83: 77515GQ6-S002-3L | AA83: 已入 | AC83: 3204 | AD83: =AC83-I83 -> 0 | AH83: =I83 -> 3204 | AO83: =I83 -> 3204 | AU83: =I83 -> 3204 | BH83: =I83/12 -> 267 | BZ83: =AH83+AI83+AJ83 -> 3204 | CE83: =CE82-AH83-AI83-AJ83 -> 1624628
A84: 45694 | B84: AMAZON.COM.DEDC,LLC | C84: 美国 | D84: 4500156625 | E84: 6OZZUM1V | F84: 4500156625-30 | G84: 77516-S001 | H84: DIY厨艺大师*2 | I84: 1332 | J84: 0 | K84: 12 | L84: =I84/K84 -> 111 | M84: 45744 | N84: 45740 | P84: PASS | Q84: 3/31交仓 | R84: 45683 | S84: 有 | T84: 2/26 SSCC LABEL（客供贴纸) | U84: 日期码格式：ZURU INC(BVI) 标准格式 日期：按实际生产日期 Packaging Info: #77516: 2PK #77515 入PVC圆筒。收藏指南用MA 5L. 3L不带UPC版收缩膜,3L 2PK铜版纸图稿跟返单4500134367。 （两个球的配比不能重复）。 Remark: 1. Amazon FOB订单，出口US。 2. 日期码使用ZURU标准版本。 3. 如果大货有要求入邮包盒，则对应的邮包盒上面要打上日期码。 4. 箱尺寸要求：外箱最长边不能超过25"(超过了，case pack只能为1)，不符合要求的大货，一律不接受。 5. 外箱箱唛要求： ①外箱正面印ZURU Logo+SSCC Label(客供贴纸，由跟单订购)。关于 SSCC Label 请注意： SSCC Label显示的是客人自己的item#。每一张SSCC label都是唯一且有不同流水及条码的，没有损耗，绝对不可贴错。如果贴错或损坏任何一张，都会导致全部都 错，千万要注意！SSCC Label必须贴在外箱正面的正中间位置(贴一面即可)，并且贴纸离外箱边距必须至少3cm(可以覆盖Logo<(>&<)>箱唛)，否则会影响到客户那边 仓库的扫描识别。 ②外箱侧面印item#(订单上显示的SKU#)+carton size(以工厂实际尺寸为准，单位: inch)+MADE IN CHINA，日期使用ZURU 标准版本。 6. 装柜要求：按照客户PO#装柜/箱号顺序装柜，跟单会提前给到装柜计划。 在大货生产/仓库存放时，请留意该装柜要求，以便装柜时不混乱(避免装错/装漏/找不到货号等)。 | V84: Kelly Shen | W84: 3.0641 | X84: =I84*W84 -> 4081.3812 | Y84: ZB00097-4.2 | Z84: 77516-S001 | AA84: 已入 | AC84: 1332 | AD84: =AC84-I84 -> 0 | AH84: =I84*2 -> 2664 | AK84: =AH84 -> 2664 | AU84: =AH84 -> 2664 | BW84: =I84 -> 1332 | BX84: =I84 -> 1332 | BZ84: =AH84+AI84+AJ84 -> 2664 | CE84: =CE83-AH84-AI84-AJ84 -> 1621964
A85: 45712 | B85: IMPORTADORA CHICOCOS | C85: 玻利维亚 | D85: 4500158356 | F85: 4500158356-120 | G85: 77515GQ2-S001 | H85: DIY厨艺大师 | I85: 700 | J85: 0 | K85: 50 | L85: =I85/K85 -> 14 | M85: 45744 | N85: 45740 | P85: pass | Q85: 4/3 截SI | R85: 45713 | S85: 无 | T85: 2/24 UPC贴纸 | U85: 日期码格式：ZURU INC(BVI) 标准格式 日期：按实际生产日期 Packaging Info: 77515GQ2: MA多语EAN包装+UPC贴纸+MA PDQ包装+箱唛 Remark: 77515GQ2: 3PCS AG13 BATTERIES(INCLUDED) | V85: Ava Liang | W85: 1.4395 | X85: =I85*W85 -> 1007.65 | Y85: 94687-4.1 | Z85: 77515GQ2-S001-3L | AA85: 已入 | AC85: 700 | AD85: =AC85-I85 -> 0 | AH85: =I85 -> 700 | AO85: =I85 -> 700 | AU85: =I85 -> 700 | BN85: =I85/25 -> 28 | BZ85: =AH85+AI85+AJ85 -> 700 | CE85: =CE84-AH85-AI85-AJ85 -> 1621264
A86: 45695 | B86: DD’S DISCOUNTS | C86: 美国 | D86: 4500156877 | E86: 70057987 | F86: 4500156877-10 | G86: 77516-S001 | H86: DIY厨艺大师*2 | I86: 504 | J86: 0 | K86: 12 | L86: =I86/K86 -> 42 | M86: 45737 | N86: =M86-3 -> 45734 | P86: PASS | Q86: 3/28入仓 | R86: 45695 | S86: 无 | T86: 2/26 客供价格贴纸 | U86: 日期码格式：ZURU INC(BVI) 标准格式 日期：按实际生产日期 Packaging Info: 1.ZURU MA UPC 现有版本包装 + 客供价格贴纸，出口美国 , 优先使用MA 1L 最新版本 。 Remark: 1.ZURU MA UPC 现有版本包装 + 客供价格贴纸，出口美国 , 优先使用MA 1L 最新版本 。 2.价格贴纸位于包装正面右下角，不挡住重要信息即可，可适当调整 ，价格贴纸由跟单提供。 3.标准日期码格式，产品和包装必须有日期码 。 4.同个产品同个货期不可出现不同的包装。 5. 跟单提供ROSS通用的箱唛模版，工厂按实际45 PO上客户PO/Item号/装箱数 提供箱唛排版来确认。 6. PVC 桶中球不能出现完全相同的ASSORTMENT ， 即同一个PVC 中球里的ASSORTMENT 需要不同。 以免消费者失望。 7.收缩膜可使用标版带UPC条码MA，无需白色贴纸覆盖。 | V86: Taylor Liao | W86: 3.1012 | X86: =I86*W86 -> 1563.0048 | Y86: ZB00057 | Z86: 77516-S001-1L | AA86: 已入 | AC86: 504 | AD86: =AC86-I86 -> 0 | AH86: =I86*2 -> 1008 | AN86: =AH86 -> 1008 | AU86: =AH86 -> 1008 | BW86: =I86 -> 504 | BX86: =I86 -> 504 | BZ86: =AH86+AI86+AJ86 -> 1008 | CE86: =CE85-AH86-AI86-AJ86 -> 1620256
A87: 45701 | B87: TJX COMPANIES, INC | C87: 美国 | D87: 4500157300 | E87: TJ MAXX DC#891-168PCS , DC#894-132PCS , DC#896-120PCS , DC#897-252PCS , DC#898-132PCS | F87: 4500157300-80 | G87: 77516-S001 | H87: DIY厨艺大师*2 | I87: 804 | J87: 0 | K87: 12 | L87: =I87/K87 -> 67 | M87: 45742 | N87: 45738 | P87: PASS | Q87: 3/10 截SI | R87: 45701 | S87: 无 | T87: 3/6 价格贴纸客供+空白贴纸 | U87: 日期码格式：ZURU INC(BVI) 标准格式 日期：按实际生产日期 Packaging Info: MA UPC包装+价格贴纸，价格贴纸客供。#77516球的收缩膜用无条码版本或者加空白贴纸覆盖条码信息。 Remark: 1. 产品和包装上印刷tracking code信息，格式为ZURU常规格式。 2. 分5个DC出货，每款产品每个DC的箱唛资料不同。具体分DC数量，请参考后面行项目备注。 3. ZURU QC验货。 | V87: Emily Wu | W87: 3.1012 | X87: =I87*W87 -> 2493.3648 | Y87: ZB00060 ZB00074 ZB00099-4.3 | Z87: 77516-S001-1L | AA87: 已入 | AC87: 804 | AD87: =AC87-I87 -> 0 | AH87: =I87*2 -> 1608 | AN87: =AH87 -> 1608 | AU87: =AH87 -> 1608 | BW87: =I87 -> 804 | BX87: =BW87 -> 804 | BZ87: =AH87+AI87+AJ87 -> 1608 | CE87: =CE86-AH87-AI87-AJ87 -> 1618648
A88: 45701 | B88: TJX COMPANIES, INC | C88: 美国 | D88: 4500157297 | E88: Marshalls DC#881-132PCS , DC#884-96PCS, DC#886-132PCS , DC#887-120PCS , DC#888-120PCS | F88: 4500157297-80 | G88: 77516-S001 | H88: DIY厨艺大师*2 | I88: 600 | J88: 0 | K88: 12 | L88: =I88/K88 -> 50 | M88: 45742 | N88: 45738 | P88: PASS | Q88: 3/27 截SI | R88: 45701 | S88: 无 | T88: 3/4 价格贴纸客供+空白贴纸 | U88: 日期码格式：ZURU INC(BVI) 标准格式 日期：按实际生产日期 Packaging Info: MA UPC包装+价格贴纸，价格贴纸客供。#77516球的收缩膜用无条码版本或者加空白贴纸覆盖条码信息。 Remark: 1. 产品和包装上印刷tracking code信息，格式为ZURU常规格式。 2. 分5个DC出货，每款产品每个DC的箱唛资料不同。具体分DC数量，请参考后面行项目备注。 3. ZURU QC验货。 | V88: Emily Wu | W88: 3.1012 | X88: =I88*W88 -> 1860.72 | Y88: ZB00053 ZB00100-4.3 | Z88: 77516-S001-1L | AA88: 已入 | AC88: 600 | AD88: =AC88-I88 -> 0 | AH88: =I88*2 -> 1200 | AN88: =AH88 -> 1200 | AU88: =AH88 -> 1200 | BW88: =I88 -> 600 | BX88: =BW88 -> 600 | BZ88: =AH88+AI88+AJ88 -> 1200 | CE88: =CE87-AH88-AI88-AJ88 -> 1617448
A89: 45722 | B89: Coop Danmark A/S | C89: 丹麦 | D89: 4500158843 | E89: 4508171305 | F89: 4500158843-20 | G89: 77515GQ1-S003-NS | H89: DIY厨艺大师 | I89: 364 | J89: 0 | K89: 13 | L89: =I89/K89 -> 28 | M89: 45744 | N89: 45740 | P89: PASS | Q89: 3-29截仓 | R89: 45722 | S89: 无 | T89: 警告语贴纸(翻单4500133308)+收藏指南无香贴纸(翻单4500133308)+地址贴纸(翻单4500133308） | U89: 日期码格式：ZURU INC(BVI) 标准格式 日期：按实际生产日期 Packaging Info: 77515GQ2-3L EAN包装+警告语贴纸(翻单4500133308)+收藏指南无香贴纸(翻单4500133308)+地址贴纸(翻单4500133308） Remark: 1. 包装如含PVC,请改为PET 2. 产品/包装要求无硼无香； 3. 出欧洲，微塑料需合规。 4.带电池出货的产品所用到的电池需要符合欧洲电池新规(EU) 2023-1542 5.关于贴纸，如果贴纸位置图的包装版本与大货不一致，请工厂提前提出。跟单会重新调整确认是否更新贴纸或调整位置图 6.产品/包装不含PFAS成分 7. 产品信息： | V89: Luna Lin | W89: 1.4483 | X89: =I89*W89 -> 527.1812 | Y89: 94674-3.31 | Z89: 77515GQ1-S003-NB | AA89: 已入 | AC89: 364 | AD89: =AC89-I89 -> 0 | AI89: =I89 -> 364 | AO89: =I89 -> 364 | AU89: =I89 -> 364 | BJ89: =I89/13 -> 28 | BZ89: =AH89+AI89+AJ89 -> 364 | CE89: =CE88-AH89-AI89-AJ89 -> 1617084
A90: 45701 | B90: DD’S DISCOUNTS | C90: 美国 | D90: 4500157194 | E90: 70057991 | F90: 4500157194-10 | G90: 77516-S001 | H90: DIY厨艺大师*2 | I90: 504 | J90: 0 | K90: 12 | L90: =I90/K90 -> 42 | M90: 45783 | N90: 45779 | O90: 4/30通知出货 | P90: 自检 | Q90: 5/9 截SI | R90: 45701 | S90: 无 | T90: 3/4客供价格贴纸 | U90: 日期码格式：ZURU INC(BVI) 标准格式 日期：按实际生产日期 Packaging Info: 1.ZURU MA UPC 现有版本包装 + 客供价格贴纸，出口美国 , 优先使用MA 1L 最新版本 。 Remark: 1.ZURU MA UPC 现有版本包装 + 客供价格贴纸，出口美国 , 优先使用MA 1L 最新版本 。 2.价格贴纸位于包装正面右下角，不挡住重要信息即可，可适当调整 ，价格贴纸由跟单提供。 3.标准日期码格式，产品和包装必须有日期码 。 4.同个产品同个货期不可出现不同的包装。 5. 跟单提供ROSS通用的箱唛模版，工厂按实际45 PO上客户PO/Item号/装箱数 提供箱唛排版来确认。 6. PVC 桶中球不能出现完全相同的ASSORTMENT ， 即同一个PVC 中球里的ASSORTMENT 需要不同。 以免消费者失望。 7.PVC 桶上加上 MINI BRAND 的LOGO 贴纸 （ ZURU 统一要求的） 8.收缩膜可使用标版带UPC条码MA，无需白色贴纸覆盖。 | V90: Taylor Liao | W90: 3.1012 | X90: =I90*W90 -> 1563.0048 | Y90: ZB00224-5.9/ZB00224-5.9 | Z90: 77516-S001-1L | AA90: 已入 | AC90: 504 | AD90: =AC90-I90 -> 0 | AH90: =I90*2 -> 1008 | AN90: =AH90 -> 1008 | AU90: =AH90 -> 1008 | BW90: =I90 -> 504 | BX90: =I90 -> 504 | BZ90: =AH90+AI90+AJ90 -> 1008 | CE90: =CE89-AH90-AI90-AJ90 -> 1616076
A91: 45721 | B91: CatchMe.lk (PVT) LTD | C91: 斯里兰卡 | D91: 4500159239 | F91: 4500159239-30 | G91: 77515GQ1-S001 | H91: DIY厨艺大师 | I91: 416 | J91: 0 | K91: 52 | L91: =I91/K91 -> 8 | M91: 45758 | N91: =M91-4 -> 45754 | P91: pass | Q91: 4/18 交仓 | R91: 45721 | S91: 无 | T91: 无 | U91: 日期码格式：ZURU INC(BVI) 标准格式 日期：按实际生产日期 Packaging Info: MA PKG, 优先1L(UPC 条码） Remark: 出斯里兰卡，需送货到汕头仓库 | V91: Doris Shou | W91: 1.3914 | X91: =I91*W91 -> 578.8224 | Y91: 94841-4.25 | Z91: 77515GQ1-S001 | AA91: 已入 | AC91: 416 | AD91: =AC91-I91 -> 0 | AH91: =I91 -> 416 | AN91: =I91 -> 416 | AU91: =I91 -> 416 | BI91: =I91/13 -> 32 | BZ91: =AH91+AI91+AJ91 -> 416 | CE91: =CE90-AH91-AI91-AJ91 -> 1615660
A92: 45712 | B92: Walmart Central America | C92: 萨尔瓦多 | D92: 4500158302 | F92: 4500158302-20 | G92: 77515GQ2-S001 | H92: DIY厨艺大师 | I92: 600 | J92: 0 | K92: 50 | L92: =I92/K92 -> 12 | M92: 45763 | N92: 45759 | P92: pass | Q92: 4/28 截SI | R92: 3/24 双坑纸箱 | S92: 无 | T92: 3/21进口商贴纸+UPC贴纸 | U92: 日期码格式：ZURU INC(BVI) 标准格式 日期：按实际生产日期 Packaging Info: 2. 77515GQ2：MA 3L EAN包装+UPC贴纸+MA 多语说明书+MA 3L PDQ包装+进口商贴纸+箱唛 Remark: 1.使用双坑外箱 2.请注意产品包装条形码必须是UPC 3.无第三方验货 | V92: Ever Li | W92: 1.4395 | X92: =I92*W92 -> 863.7 | Y92: 94865-4.28 | Z92: 77515GQ2-S001-3L | AA92: 已入 | AC92: 600 | AD92: =AC92-I92 -> 0 | AH92: =I92 -> 600 | AO92: =I92 -> 600 | AU92: =I92 -> 600 | BN92: =I92/25 -> 24 | BZ92: =AH92+AI92+AJ92 -> 600 | CE92: =CE91-AH92-AI92-AJ92 -> 1615060
A93: 45714 | B93: Walmart Central America-GT | C93: 危地马拉 | D93: 4500158447 | F93: 4500158447-20 | G93: 77515GQ2-S001 | H93: DIY厨艺大师 | I93: 1100 | J93: 0 | K93: 50 | L93: =I93/K93 -> 22 | M93: 45763 | N93: 45759 | P93: pass | Q93: 4/28 截SI | R93: 3/24 双坑纸箱 | S93: 无 | T93: 进口商贴纸+UPC贴纸翻单158302 | U93: 日期码格式：ZURU INC(BVI) 标准格式 日期：按实际生产日期 Packaging Info: 2. 77515GQ2：MA 3L EAN包装+UPC贴纸+MA 多语说明书+MA 3L PDQ包装+进口商贴纸+箱唛 以上所有贴纸翻单PO4500158302 Remark: 1.使用双坑外箱 2.请注意产品包装条形码必须是UPC 3.无第三方验货 | V93: Ever Li | W93: 1.4171 | X93: =I93*W93 -> 1558.81 | Y93: 94923-5.5 | Z93: 77515GQ2-S001-3L | AA93: 已入 | AC93: 1100 | AD93: =AC93-I93 -> 0 | AH93: =I93 -> 1100 | AO93: =I93 -> 1100 | AU93: =I93 -> 1100 | BN93: =I93/25 -> 44 | BZ93: =AH93+AI93+AJ93 -> 1100 | CE93: =CE92-AH93-AI93-AJ93 -> 1613960
A94: 45714 | B94: Walmart Central America-CR | C94: 哥斯达黎加 | D94: 4500158535 | F94: 4500158535-20 | G94: 77515GQ2-S001 | H94: DIY厨艺大师 | I94: 1500 | J94: 0 | K94: 50 | L94: =I94/K94 -> 30 | M94: 45763 | N94: 45759 | P94: pass | Q94: 4/29 截SI | R94: 3/24 双坑纸箱 | S94: 无 | T94: 进口商贴纸+UPC贴纸翻单158302 | U94: 日期码格式：ZURU INC(BVI) 标准格式 日期：按实际生产日期 Packaging Info: 2. 77515GQ2：MA 3L EAN包装+UPC贴纸+MA 多语说明书+MA 3L PDQ包装+进口商贴纸+箱唛 以上贴纸翻单PO 4500158302 Remark: 1.使用双坑外箱 2.请注意产品包装条形码必须是UPC 3.无第三方验货 | V94: Ever Li | W94: 1.4344 | X94: =I94*W94 -> 2151.6 | Y94: 94882-4.29 | Z94: 77515GQ2-S001-3L | AA94: 已入 | AC94: 1500 | AD94: =AC94-I94 -> 0 | AH94: =I94 -> 1500 | AO94: =I94 -> 1500 | AU94: =I94 -> 1500 | BN94: =I94/25 -> 60 | BZ94: =AH94+AI94+AJ94 -> 1500 | CE94: =CE93-AH94-AI94-AJ94 -> 1612460
A95: 45712 | B95: Walmart Central America-HN | C95: 洪都拉斯 | D95: 4500158415 | F95: 4500158415-20 | G95: 77515GQ2-S001 | H95: DIY厨艺大师 | I95: 400 | J95: 0 | K95: 50 | L95: =I95/K95 -> 8 | M95: 45763 | N95: 45759 | P95: pass | Q95: 4/29 截SI | R95: 3/24 双坑纸箱 | S95: 无 | T95: 进口商贴纸+UPC贴纸翻单158302 | U95: 日期码格式：ZURU INC(BVI) 标准格式 日期：按实际生产日期 Packaging Info: 2. 77515GQ2：MA 3L EAN包装+UPC贴纸+MA 多语说明书+MA 3L PDQ包装+进口商贴纸+箱唛 以上所有贴纸翻单PO4500158302 Remark: 1.使用双坑外箱 2.请注意产品包装条形码必须是UPC 3.无第三方验货 | V95: Ever Li | W95: 1.4395 | X95: =I95*W95 -> 575.8 | Y95: 94891-4.30 | Z95: 77515GQ2-S001-3L | AA95: 已入 | AC95: 400 | AD95: =AC95-I95 -> 0 | AH95: =I95 -> 400 | AO95: =I95 -> 400 | AU95: =I95 -> 400 | BN95: =I95/25 -> 16 | BZ95: =AH95+AI95+AJ95 -> 400 | CE95: =CE94-AH95-AI95-AJ95 -> 1612060
A96: 45701 | B96: DD’S DISCOUNTS | C96: 美国 | D96: 4500157202 | E96: 70057992 | F96: 4500157202-10 | G96: 77516-S001 | H96: DIY厨艺大师*2 | I96: 1008 | J96: 0 | K96: 12 | L96: =I96/K96 -> 84 | M96: 45783 | N96: 45779 | O96: 4/30通知出货 | P96: pass | Q96: 5/9 截SI | R96: 45701 | S96: 无 | T96: 3/4客供价格贴纸 | U96: 日期码格式：ZURU INC(BVI) 标准格式 日期：按实际生产日期 Packaging Info: 1.ZURU MA UPC 现有版本包装 + 客供价格贴纸，出口美国 , 优先使用MA 1L 最新版本 。 Remark: 1.ZURU MA UPC 现有版本包装 + 客供价格贴纸，出口美国 , 优先使用MA 1L 最新版本 。 2.价格贴纸位于包装正面右下角，不挡住重要信息即可，可适当调整 ，价格贴纸由跟单提供。 3.标准日期码格式，产品和包装必须有日期码 。 4.同个产品同个货期不可出现不同的包装。 5. 跟单提供ROSS通用的箱唛模版，工厂按实际45 PO上客户PO/Item号/装箱数 提供箱唛排版来确认。 6. PVC 桶中球不能出现完全相同的ASSORTMENT ， 即同一个PVC 中球里的ASSORTMENT 需要不同。 以免消费者失望。 7.PVC 桶上加上 MINI BRAND 的LOGO 贴纸 （ ZURU 统一要求的） 8.收缩膜可使用标版带UPC条码MA，无需白色贴纸覆盖。 | V96: Taylor Liao | W96: 3.1012 | X96: =I96*W96 -> 3126.0096 | Y96: ZB00225-5.9/ZB00225-5.9 | Z96: 77516-S001-1L | AA96: 已入 | AC96: 1008 | AD96: =AC96-I96 -> 0 | AH96: =I96*2 -> 2016 | AN96: =AH96 -> 2016 | AU96: =AH96 -> 2016 | BW96: =I96 -> 1008 | BX96: =I96 -> 1008 | BZ96: =AH96+AI96+AJ96 -> 2016 | CE96: =CE95-AH96-AI96-AJ96 -> 1610044
A97: 45720 | B97: TJX CANADA | C97: 加拿大 | D97: 4500158873 | E97: 客户PO 30369558 | F97: 4500158873-150 | G97: 77516-S001 | H97: DIY厨艺大师*2 | I97: 444 | J97: 0 | K97: 12 | L97: =I97/K97 -> 37 | M97: 45768 | N97: 45764 | P97: pass | Q97: 4/22 截SI | R97: 45720 | S97: 无 | T97: 无 | U97: 日期码格式： 标准格式 日期：按实际生产日期 Packaging Info: 77516 MA 3L EAN版本包装+多语（含英法）铜版纸UPC版本 UPC 193052061041 Remark: 出加拿大 有客供价格贴 每行对应不同的客户PO， 客户PO已分别备注 Zuru验货.日期跟踪码：产品外包装及产品本身都必须有日期跟踪码，ZURU标准格式 日期码 日期码 | V97: Summer Mo | W97: 3.0641 | X97: =I97*W97 -> 1360.4604 | Z97: 77516-S001-3L | AA97: 已入 | AC97: 444 | AD97: =AC97-I97 -> 0 | AH97: =I97*2 -> 888 | AO97: =AH97 -> 888 | AU97: =AH97 -> 888 | BW97: =I97 -> 444 | BX97: =I97 -> 444 | BZ97: =AH97+AI97+AJ97 -> 888 | CE97: =CE96-AH97-AI97-AJ97 -> 1609156
A98: 45720 | B98: TJX CANADA | C98: 加拿大 | D98: 4500158873 | E98: 客户PO 30369740 | F98: 4500158873-250 | G98: 77516-S001 | H98: DIY厨艺大师*2 | I98: 156 | J98: 0 | K98: 12 | L98: =I98/K98 -> 13 | M98: 45768 | N98: 45764 | P98: pass | Q98: 4/22 截SI | R98: 45720 | S98: 无 | T98: 无 | U98: 日期码格式： 标准格式 日期：按实际生产日期 Packaging Info: 77516 MA 3L EAN版本包装+多语（含英法）铜版纸UPC版本 UPC 193052061041 Remark: 出加拿大 有客供价格贴 每行对应不同的客户PO， 客户PO已分别备注 Zuru验货.日期跟踪码：产品外包装及产品本身都必须有日期跟踪码，ZURU标准格式 日期码 日期码 | V98: Summer Mo | W98: 3.1012 | X98: =I98*W98 -> 483.7872 | Z98: 77516-S001-3L | AA98: 已入 | AC98: 156 | AD98: =AC98-I98 -> 0 | AH98: =I98*2 -> 312 | AO98: =AH98 -> 312 | AU98: =AH98 -> 312 | BW98: =I98 -> 156 | BX98: =I98 -> 156 | BZ98: =AH98+AI98+AJ98 -> 312 | CE98: =CE97-AH98-AI98-AJ98 -> 1608844
A99: 45733 | B99: Distruibuciones Universales, SA - D | C99: 洪都拉斯 | D99: 4500160421 | F99: 4500160421-100 | G99: 77515GQ2-S001 | H99: DIY厨艺大师 | I99: 400 | J99: 0 | K99: 50 | L99: =I99/K99 -> 8 | M99: 45768 | N99: 45764 | P99: 自检 | Q99: 4/22 截SI | R99: 45736 | S99: 无 | T99: 3/25 UPC贴纸 | U99: 日期码格式：ZURU INC(BVI) 标准格式 日期：按实际生产日期 Packaging Info: 77515GQ2: MA多语EAN包装+UPC贴纸+MA多语收藏指南+MA多语PDQ+箱唛 Remark: 77515GQ2: 3PCS AG13 BATTERIES(INCLUDED) | V99: Ava Liang | W99: 1.4395 | X99: =I99*W99 -> 575.8 | Y99: 94795-4.18 | Z99: 77515GQ2-S001-3L | AA99: 已入 | AC99: 400 | AD99: 0 | AH99: =I99 -> 400 | AO99: =I99 -> 400 | AU99: =I99 -> 400 | BN99: =I99/25 -> 16 | BZ99: =AH99+AI99+AJ99 -> 400 | CE99: =CE98-AH99-AI99-AJ99 -> 1608444
A100: 45730 | B100: Simba Toys VN | C100: 越南 | D100: 4500160287 | F100: 4500160287-40 | G100: 77515-S001 | H100: DIY厨艺大师 | I100: 504 | J100: 0 | K100: 24 | L100: =I100/K100 -> 21 | M100: 45794 | N100: =M100-4 -> 45790 | P100: pass | Q100: 5/24 截SI | R100: 45742 | S100: 无 | T100: 4/8 进口商贴纸 | U100: 日期码格式：ZURU INC(BVI) 标准格式 日期：按实际生产日期 Packaging Info: 其他item-MA EAN包装(语言包含英语就行)+1张进口商贴纸, 贴纸资料待提供 Remark: 77515-3PCS AG13 BATTERIES(INCLUDED) | V100: Emma Wu | W100: 1.3754 | X100: =I100*W100 -> 693.2016 | Z100: 77515-S001-3L | AA100: 已入 | AC100: 504 | AD100: =AC100-I100 -> 0 | AH100: =I100 -> 504 | AO100: =I100 -> 504 | AU100: =I100 -> 504 | BZ100: =AH100+AI100+AJ100 -> 504 | CE100: =CE99-AH100-AI100-AJ100 -> 1607940
...

Sheet 77515 DIY厨艺大师
A1: ZURU （77515 Mini Brands 迷你球DIY厨艺系列）生产排期表 | G1: 走KM澳洲和出新西兰的说明书都要加纽扣电池警语贴纸 | N1: 77515出加拿大的3L都需要双语logo，最新版本77515GQ1 GQ2 GQ5 GQ6 SK SK1 纸袋 收藏指南 收缩膜 | U1: 77555SK1-S002这款是带底座 | AH1: 77515 | AN1: 收縮膜 | AU1: 收藏指南 | BB1: PDQ盒 | BK1: GQ1 | BW1: 77516 | CB1: 总MA | CC1: ='生产MA Summary'!O4 -> 4670000
A2: 香港接单日期 | B2: 第三方客户名称 | C2: 走货国家 | D2: ZURU PO NO# | E2: 第三方客户 PO NO# | F2: SKU | G2: ITEM# | H2: 中文名 | I2: PO数量 (pcs) | J2: 内箱装箱数量(pcs) | K2: 外箱装箱数量(pcs) | L2: 总箱数 | M2: 计划出货期 | N2: 计划验货期 | O2: 第三方客户公证行验货 | P2: 驗貨結果 | Q2: S/0船期 | R2: 箱唛资料(收到日期) | S2: 外箱贴纸 | T2: 客供贴纸AI(收到日期) | U2: 备注 | V2: ZURU 跟单 | W2: 单价USD | X2: 金额USD | Y2: 發票號 | Z2: 系统货号 | AA2: 是否入系统 | AB2: 采购单 | AC2: 已送情况 | AD2: 欠数 | AE2: 贴纸 | AF2: 生产地点 | AH2: 球数 | AI2: 无香味版本 | AJ2: 删除组合10（猪肉） | AK2: MA 3语 收缩膜 无条码 | AL2: 无UPC版本 | AM2: 新无UPC版本-C | AN2: MA 1语收缩膜 | AO2: MA 3语收缩膜 | AP2: MA 1语C版收缩膜 | AQ2: MA 3语C版本收缩膜 | AR2: 客版收缩膜 | AS2: ACTION 客版1L收缩膜+客版15L吊牌+客版UV灯说明书 | AT2: 客版 3L 收缩膜 | AU2: MA 5L语收藏指南 | AV2: MA 5LB版语收藏指南 | AW2: ESAL客版指南/说明书 | AX2: WM客版 | AY2: 外挂中文收藏指南+中文收藏指南(每一款都不同) | AZ2: MA 23L_C_IFUD声明补充说明书 | BA2: WEE带电说明书 | BB2: GQ5-S001 21PCS 1L | BC2: GQ5-S001 21PCS 3L | BD2: GQ5 B3L | BE2: WM 客版GQ5 | BF2: WM 客版GQ6 | BG2: GQ6-S001 12PCS 1L | BH2: GQ6-S001 12PCS 3L | BI2: GQ1-S001 13pcs 1L | BJ2: GQ1-S001 13pcs 3L | BK2: B版 1L | BL2: B版 3L | BM2: GQ2-S001 25pcs 1L | BN2: GQ2-S001 25pcs 3L | BO2: SK-S001 60PCS 1L 不含底座 配挂钩 | BP2: SK-S002 60PCS 1L 含底座 | BQ2: SK-S002 60PCS 3L 含底座 | BR2: 77515SK1-S002 30pcs 1L 含底座 | BS2: 77515SK1-S001 30pcs 3L 不带底座 | BT2: SK1底座 | BU2: FD客 77515GQ3 | BV2: 77515GQ3-S001 客版 8PCS | BW2: 圆筒 | BX2: 3L 彩纸 | BY2: B版本 3L 彩纸 | BZ2: 合计数量 | CB2: 已删减实单 | CC2: =AH57+AH58+AI57+AJ57+AI58+AJ58 -> 3966263 | CD2: MA剩余 | CE2: =CC1-CC2 -> 703737
A3: 45719 | D3: ZMPO250165 | G3: 77515-S001 | H3: 空球-收缩内收缩膜 | I3: 3000 | J3: 0 | K3: 24 | L3: =I3/K3 -> 125 | M3: 45727 | N3: 45723 | P3: 自检 | R3: 空白箱 | S3: 无 | T3: 无 | U3: Remark：只需77515的空球，只需用外面透明收缩膜压缩就好，不需要彩色收缩膜;备注： 收到样品订单后尽快安排 ，注意样板品质质量要求要高于大货品质要求 ，送货时必须要附带送货单(没有送货单和QC检验合格报告的仓库一律拒绝收货)，请知悉，谢谢！ | V3: Angus | Z3: 77515-S001-2 | AA3: 已入 | AC3: 3000 | AD3: 0 | CE3: =CE2-AH3-AI3-AJ3 -> 703737
A4: 45975 | B4: COOP FAGHANDEL (NON-FOOD) | C4: 挪威 | D4: 4500185718 | E4: 32727064 | F4: 4500185718-10 | G4: 77515GQ1-S003-NS | H4: DIY厨艺大师 | I4: 1300 | J4: 0 | K4: 13 | L4: =I4/K4 -> 100 | M4: 46017 | N4: 46013 | O4: 已出样板 | P4: pass | Q4: 1/21 截SI | R4: 45975 | S4: 无 | T4: 警告语贴纸(翻单4500128658）+气味贴纸翻单4500125111 | U4: 日期码格式：ZURU INC(BVI) 标准格式 日期：按实际生产日期 Packaging Info: 77515GQ1: MA EAN 3L + MA PDQ +1张警告语贴纸(翻单4500128658）+收藏指南A版本+1张收藏指南上的气味贴纸 （气味贴纸翻单4500125111）+黑白说明书库存 C版 23L + IFUD声明+带电款增加WEEE 30L B 说明书 2/ 配比： 77515GQ1: 去掉香味款 MASCM-S1-007，调整比例出货，10款MINI 尽量平均分配 3/ 产品和包装要求无硼无香，包装不能含有PVC 4/ 如有微塑料，必须符合规欧洲标准+增加IFUD声明 5/ 带电池出货的产品，需要符合欧洲电池新规(EU)2023-1542，+增加对应WEEE 说明书 6/ 此单有第三方验货，签样用于翻单，如大货包装已经跟签样不符，请及时补签样； 77515签样请重新安排两套或两个完整球+两套完整散件，9296签样用于4500128658，9285验货样请用4500158122 | V4: Zoe Zhou | W4: 1.3618 | X4: =I4*W4 -> 1770.34 | Z4: 77515GQ1-S003-NS-3L | AA4: 已入 | AB4: 是 | AC4: 1300 | AI4: =I4 -> 1300 | AQ4: =I4 -> 1300 | AU4: =I4 -> 1300 | AZ4: =I4 -> 1300 | BA4: =I4 -> 1300 | BL4: =I4/13 -> 100 | BZ4: =AH4+AI4+AJ4 -> 1300 | CE4: =CE3-AH4-AI4-AJ4 -> 702437
A5: 45960 | B5: TJX COMPANIES, INC | C5: 美国 | D5: 4500183805 | E5: Marshalls PO#533219,SKU #892552 DC#881-216PCS , DC#884-168PCS , DC#886-216PCS , DC#887-204PCS , DC#888-192PCS | F5: 4500183805-40 | G5: 77516-S001 | H5: DIY厨艺大师*2 | I5: 996 | J5: 0 | K5: 12 | L5: =I5/K5 -> 83 | M5: 46022 | N5: 46018 | O5: 消耗取消单4500156588成品,待客人最终确认 | P5: 自检 | Q5: 1/8 截SI | R5: 45965 | S5: 无 | T5: 12/15 价格贴纸 | U5: 日期码格式：ZURU INC(BVI) 标准格式 日期：按实际生产日期 Packaging Info: MA UPC包装+价格贴纸，价格贴纸客供。 2PK的球用无条码收缩膜或加空白贴纸覆盖原条码 Remark: 1. 产品和包装上印刷tracking code信息，格式为ZURU常规格式。 2. 分5个DC出货，每款产品每个DC的箱唛资料不同。具体分DC数量，请参考后面行项目备注。 3. ZURU QC验货。 | V5: Emily Wu | W5: 1.8222 | X5: =W5*I5 -> 1814.9112 | Z5: 77516-S001 | AA5: 已入 | AB5: 1 | AE5: ok | AH5: =I5*2 -> 1992 | AK5: =I5*2 -> 1992 | AU5: =I5*2 -> 1992 | BW5: =I5 -> 996 | BX5: =I5 -> 996 | BZ5: =I5 -> 996 | CE5: =CE4-AH5-AI5-AJ5 -> 700445
A6: 45960 | B6: TJX COMPANIES, INC | C6: 美国 | D6: 4500183809 | E6: TJ MAXX PO#533283,SKU #170937 DC#891-264PCS , DC#894-180PCS , DC#896-288PCS , DC#897-228PCS , DC#898-240PCS | F6: 4500183809-40 | G6: 77516-S001 | H6: DIY厨艺大师*2 | I6: 1200 | J6: 0 | K6: 12 | L6: =I6/K6 -> 100 | M6: 46022 | N6: 46018 | O6: 消耗取消单4500156588成品,待客人最终确认 | P6: 自检 | Q6: 1/8 装柜 | R6: 45965 | S6: 无 | T6: 12/15 价格贴纸 | U6: 日期码格式：ZURU INC(BVI) 标准格式 日期：按实际生产日期 Packaging Info: MA UPC包装+价格贴纸，价格贴纸客供。 2PK的球用无条码收缩膜或加空白贴纸覆盖原条码 Remark: 1. 产品和包装上印刷tracking code信息，格式为ZURU常规格式。 2. 分5个DC出货，每款产品每个DC的箱唛资料不同。具体分DC数量，请参考后面行项目备注。 3. ZURU QC验货。 | V6: Emily Wu | W6: 1.8004 | X6: =W6*I6 -> 2160.48 | Z6: 77516-S001 | AA6: 已入 | AB6: 1 | AE6: ok | AH6: =I6*2 -> 2400 | AK6: =I6*2 -> 2400 | AU6: =I6*2 -> 2400 | BW6: =I6 -> 1200 | BX6: =I6 -> 1200 | BZ6: =I6 -> 1200 | CE6: =CE5-AH6-AI6-AJ6 -> 698045
A7: 45988 | B7: TJX COMPANIES, INC | C7: 美国 | D7: 4500187232 | E7: 765820 | F7: 4500187232-20 | G7: 77516-S001 | H7: DIY厨艺大师*2 | I7: 1200 | J7: 0 | K7: 12 | L7: =I7/K7 -> 100 | M7: 46029 | N7: 46027 | P7: 自检 | Q7: 1/9 装柜 | R7: 45973 | S7: 无 | T7: 12/15 价格贴纸 | U7: 日期码格式：ZURU INC(BVI) 标准格式 日期：按实际生产日期 Packaging Info: MA UPC包装(优先1L)+价格贴纸，价格贴纸客供。2PK的球用无条码收缩膜或加空白贴纸覆盖原条码。 价格贴纸贴在产品正面无遮挡任何文字或图案的地方，优先正面右上角。如有疑问/位置不够，请找我们确认位置。之前确认过的款就无需再重复确认了。 Remark: 1. 产品和包装上印刷tracking code信息，格式为ZURU常规格式。 2. ZURU QC验货。 3. 分5个DC出货，每款产品每个DC的箱唛资料不同，具体DC数量如下： item#77516: TJ MAXX PO#765820,SKU#178313 DC#891-240PCS, DC#894-204PCS, DC#896-192PCS, DC#897-372PCS, DC#898-192PCS; | V7: Emily Wu | W7: 1.8004 | X7: =W7*I7 -> 2160.48 | Z7: 77516-S001 | AA7: 已入 | AB7: 1 | AC7: 1200 | AE7: ok | AH7: =I7*2 -> 2400 | AM7: =I7*2 -> 2400 | AU7: =I7*2 -> 2400 | BW7: =I7 -> 1200 | BY7: =BW7 -> 1200 | BZ7: =AH7+AI7+AJ7 -> 2400 | CE7: =CE6-AH7-AI7-AJ7 -> 695645
A8: 45988 | B8: TJX COMPANIES, INC | C8: 美国 | D8: 4500187228 | E8: 765819 | F8: 4500187228-20 | G8: 77516-S001 | H8: DIY厨艺大师*2 | I8: 996 | J8: 0 | K8: 12 | L8: =I8/K8 -> 83 | M8: 46029 | N8: 46027 | P8: 自检 | Q8: 1/9 装柜 | R8: 45973 | S8: 无 | T8: 12/15 价格贴纸 | U8: 日期码格式：ZURU INC(BVI) 标准格式 日期：按实际生产日期 Packaging Info: MA UPC包装(优先1L)+价格贴纸，价格贴纸客供。2PK的球用无条码收缩膜或加空白贴纸覆盖原条码。 价格贴纸贴在产品正面无遮挡任何文字或图案的地方，优先正面右上角。如有疑问/位置不够，请找我们确认位置。之前确认过的款就无需再重复确认了。 Remark: 1. 产品和包装上印刷tracking code信息，格式为ZURU常规格式。 2. ZURU QC验货。 3. 每款都只分1个DC出货，明细如下： item#77516: Marshalls PO#765819,SKU#899662 DC#882-996PCS; | V8: Emily Wu | W8: 1.8004 | X8: =W8*I8 -> 1793.1984 | Z8: 77516-S001 | AA8: 已入 | AB8: 1 | AC8: 996 | AE8: ok | AH8: =I8*2 -> 1992 | AM8: =I8*2 -> 1992 | AU8: =I8*2 -> 1992 | BW8: =I8 -> 996 | BY8: =BW8 -> 996 | BZ8: =AH8+AI8+AJ8 -> 1992 | CE8: =CE7-AH8-AI8-AJ8 -> 693653
A9: 46027 | B9: TOYZOONA LIMITED | C9: 肯尼亚 | D9: 4500190681 | F9: 4500190681-40 | G9: 77515GQ5-S001 | H9: DIY厨艺大师 | I9: 294 | J9: 0 | K9: 42 | L9: =I9/K9 -> 7 | M9: 46057 | N9: =M9-4 -> 46053 | P9: 自检 | Q9: 2/9 自提 | R9: 46028 | S9: 无 | T9: 无 | U9: 日期码格式：ZURU INC(BVI) 标准格式 日期：按实际生产日期 Packaging Info: MA PKG , 优先1L (需留意此单外箱上无客户名称） Remark: 此单按EXW +送货运费实报实销，需赶年前出货，请留意船务出货通知。 | V9: Chelsea Luo | W9: 1.4091 | X9: =I9*W9 -> 414.2754 | Z9: 77515GQ5-S001 | AA9: 已入 | AB9: 1 | AC9: 294 | AH9: =I9 -> 294 | AP9: =I9 -> 294 | AV9: =I9 -> 294 | BB9: =I9/21 -> 14 | BZ9: =AH9+AI9+AJ9 -> 294 | CE9: =CE8-AH9-AI9-AJ9 -> 693359
A10: 46015 | B10: TJX COMPANIES, INC | C10: 美国 | D10: 4500189850 | E10: 951854 | F10: 4500189850-30 | G10: 77516-S001 | H10: DIY厨艺大师*2 | I10: 996 | J10: 0 | K10: 12 | L10: =I10/K10 -> 83 | M10: 46058 | N10: 46055 | P10: pass | Q10: 年底出货 | R10: 46015 | S10: 无 | T10: 1/15 价格贴纸 | U10: 日期码格式：ZURU INC(BVI) 标准格式 日期：按实际生产日期 Packaging Info: MA UPC包装(优先1L)+价格贴纸，价格贴纸客供。2PK的球用无条码收缩膜或加空白贴纸覆盖原条码。 价格贴纸贴在产品正面无遮挡任何文字或图案的地方，优先正面右上角。如有疑问/位置不够，请找我们确认位置。之前确认过的款就无需再重复确认了。 Remark: 1. 产品和包装上印刷tracking code信息，格式为ZURU常规格式。 2. ZURU QC验货。 3. 分5个DC出货，每款产品每个DC的箱唛资料不同，具体DC数量如下： item#77516: Marshalls PO#951854,SKU#903554 DC#881-216PCS, DC#884-168PCS, DC#886-216PCS, DC#887-192PCS, DC#888-204PCS | V10: Emily Wu | W10: 1.8222 | X10: =W10*I10 -> 1814.9112 | Z10: 77516-S001 | AA10: 已入 | AB10: 1 | AC10: 996 | AE10: ok | AH10: =I10*2 -> 1992 | AM10: =I10*2 -> 1992 | AU10: =I10*2 -> 1992 | BW10: =I10 -> 996 | BY10: =BW10 -> 996 | BZ10: =AH10+AI10+AJ10 -> 1992 | CE10: =CE9-AH10-AI10-AJ10 -> 691367
A11: 46015 | B11: TJX COMPANIES, INC | C11: 美国 | D11: 4500189851 | E11: 951857 | F11: 4500189851-30 | G11: 77516-S001 | H11: DIY厨艺大师*2 | I11: 1200 | J11: 0 | K11: 12 | L11: =I11/K11 -> 100 | M11: 46058 | N11: 46055 | P11: pass | Q11: 预计2月底或者3月初出货 | R11: 46015 | S11: 无 | T11: 1/15 价格贴纸 | U11: 日期码格式：ZURU INC(BVI) 标准格式 日期：按实际生产日期 Packaging Info: MA UPC包装(优先1L)+价格贴纸，价格贴纸客供。2PK的球用无条码收缩膜或加空白贴纸覆盖原条码。 价格贴纸贴在产品正面无遮挡任何文字或图案的地方，优先正面右上角。如有疑问/位置不够，请找我们确认位置。之前确认过的款就无需再重复确认了。 Remark: 1. 产品和包装上印刷tracking code信息，格式为ZURU常规格式。 2. ZURU QC验货。 3. 分5个DC出货，每款产品每个DC的箱唛资料不同，具体DC数量如下： item#77516: TJ MAXX PO#951857,SKU#182162 DC#891-264PCS, DC#894-204PCS, DC#896-168PCS, DC#897-336PCS, DC#898-228PCS | V11: Emily Wu | W11: 1.8004 | X11: =W11*I11 -> 2160.48 | Z11: 77516-S001 | AA11: 已入 | AB11: 1 | AC11: 1200 | AE11: ok | AH11: =I11*2 -> 2400 | AM11: =I11*2 -> 2400 | AU11: =I11*2 -> 2400 | BW11: =I11 -> 1200 | BY11: =BW11 -> 1200 | BZ11: =AH11+AI11+AJ11 -> 2400 | CE11: =CE10-AH11-AI11-AJ11 -> 688967
A12: 46016 | B12: AMAZON CA (VENDOR CENTER) | C12: 加拿大 | D12: 4500190061 | E12: 1OVOU1WR | F12: 4500190061-210 | G12: 77515-S001 | H12: DIY厨艺大师 | I12: 96 | J12: 0 | K12: 24 | L12: =I12/K12 -> 4 | M12: 46059 | N12: 46055 | P12: 自检 | Q12: 3/2 截SI | R12: 46016 | S12: 有 | T12: 1/26客供防伪贴纸+1/27 SSCC贴纸，UPC贴纸跟返单4500132623 | U12: 日期码格式：ZURU INC(BVI) 标准格式 日期：按实际生产日期 Packaging Info: 出口加拿大，包装需要至少2/3L UPC版，无硼版本。 #77515：MA 3L C 版本加UPC贴纸覆盖原EAN条码，C版本收缩膜、纸袋、说明书， B版本收藏指南， UPC贴纸跟返单4500132623。 加客供防伪贴纸， 跟单提供； Remark: 1. Amazon FOB订单，出口CA。外箱最长边不能超过25" （超过了，case pack只能为1），不符合要求的大货，一律不接受。 2. 外箱正面印ZURU Logo + SSCC LABEL（客供贴纸)，侧面印item#（订单上显示的SKU#) + carton size(以工厂实际尺寸为准，单位: inch) + MADE IN CHINA， 日期使用ZURU 标准版本 SSCC Label 显示的是客人自己的item#，SSCC Label 贴在外箱正面的正中间，贴一面即可，跟单订购，贴纸离外箱距必须至少3cm，每一 张SSCC label 都是唯一且有不同流水及条码的，没有损耗，绝对不可贴错 ，否则贴错或损坏一张会导致全部都错，千万要注意: SSCC 贴纸务必要在正中间(可以覆 盖Logo <(>&<)> 箱唛)，否则会影响到仓库扫描识别。 3. 日期码使用ZURU标准版本。 4. 如果大货有要求入邮包盒，则对应的邮包盒上面要打上日期码。 5. 按照客户PO# 装柜/箱号顺序装柜，跟单会提前给到装柜计划。在大货生产/仓库存放时，请留意该装柜要求，以便装柜时不混乱（避免装错/装漏/找不到货号等 ）。 6. 出口加拿大，包装需要至少2/3L UPC版，无硼版本。 7.邮包盒上要印刷日期码 | V12: Kelly Shen | W12: 1.3228 | X12: =I12*W12 -> 126.9888 | Z12: 77515-S001-3L | AA12: 已入 | AB12: 1 | AC12: 96 | AE12: ok | AH12: =I12 -> 96 | AQ12: =AH12 -> 96 | AV12: =I12 -> 96 | BZ12: =AH12+AI12+AJ12 -> 96 | CE12: =CE11-AH12-AI12-AJ12 -> 688871
A13: 46016 | B13: AMAZON CA (VENDOR CENTER) | C13: 加拿大 | D13: 4500190061 | E13: 2L2AXI9L | F13: 4500190061-220 | G13: 77515-S001 | H13: DIY厨艺大师 | I13: 48 | J13: 0 | K13: 24 | L13: =I13/K13 -> 2 | M13: 46059 | N13: 46055 | P13: 自检 | Q13: 3/2 截SI | R13: 46016 | S13: 有 | T13: 1/26客供防伪贴纸+1/27 SSCC贴纸，UPC贴纸跟返单4500132623 | U13: 日期码格式：ZURU INC(BVI) 标准格式 日期：按实际生产日期 Packaging Info: 出口加拿大，包装需要至少2/3L UPC版，无硼版本。 #77515：MA 3L C 版本加UPC贴纸覆盖原EAN条码，C版本收缩膜、纸袋、说明书， B版本收藏指南， UPC贴纸跟返单4500132623。 加客供防伪贴纸， 跟单提供； Remark: 1. Amazon FOB订单，出口CA。外箱最长边不能超过25" （超过了，case pack只能为1），不符合要求的大货，一律不接受。 2. 外箱正面印ZURU Logo + SSCC LABEL（客供贴纸)，侧面印item#（订单上显示的SKU#) + carton size(以工厂实际尺寸为准，单位: inch) + MADE IN CHINA， 日期使用ZURU 标准版本 SSCC Label 显示的是客人自己的item#，SSCC Label 贴在外箱正面的正中间，贴一面即可，跟单订购，贴纸离外箱距必须至少3cm，每一 张SSCC label 都是唯一且有不同流水及条码的，没有损耗，绝对不可贴错 ，否则贴错或损坏一张会导致全部都错，千万要注意: SSCC 贴纸务必要在正中间(可以覆 盖Logo <(>&<)> 箱唛)，否则会影响到仓库扫描识别。 3. 日期码使用ZURU标准版本。 4. 如果大货有要求入邮包盒，则对应的邮包盒上面要打上日期码。 5. 按照客户PO# 装柜/箱号顺序装柜，跟单会提前给到装柜计划。在大货生产/仓库存放时，请留意该装柜要求，以便装柜时不混乱（避免装错/装漏/找不到货号等 ）。 6. 出口加拿大，包装需要至少2/3L UPC版，无硼版本。 7.邮包盒上要印刷日期码 | V13: Kelly Shen | W13: 1.3228 | X13: =I13*W13 -> 63.4944 | Z13: 77515-S001-3L | AA13: 已入 | AB13: 1 | AC13: 48 | AE13: ok | AH13: =I13 -> 48 | AQ13: =AH13 -> 48 | AV13: =I13 -> 48 | BZ13: =AH13+AI13+AJ13 -> 48 | CE13: =CE12-AH13-AI13-AJ13 -> 688823
A14: 46016 | B14: AMAZON CA (VENDOR CENTER) | C14: 加拿大 | D14: 4500190061 | E14: 43TI58KU | F14: 4500190061-230 | G14: 77515-S001 | H14: DIY厨艺大师 | I14: 24 | J14: 0 | K14: 24 | L14: =I14/K14 -> 1 | M14: 46059 | N14: 46055 | P14: 自检 | Q14: 3/2 截SI | R14: 46016 | S14: 有 | T14: 1/26客供防伪贴纸+1/27 SSCC贴纸，UPC贴纸跟返单4500132623 | U14: 日期码格式：ZURU INC(BVI) 标准格式 日期：按实际生产日期 Packaging Info: 出口加拿大，包装需要至少2/3L UPC版，无硼版本。 #77515：MA 3L C 版本加UPC贴纸覆盖原EAN条码，C版本收缩膜、纸袋、说明书， B版本收藏指南， UPC贴纸跟返单4500132623。 加客供防伪贴纸， 跟单提供； Remark: 1. Amazon FOB订单，出口CA。外箱最长边不能超过25" （超过了，case pack只能为1），不符合要求的大货，一律不接受。 2. 外箱正面印ZURU Logo + SSCC LABEL（客供贴纸)，侧面印item#（订单上显示的SKU#) + carton size(以工厂实际尺寸为准，单位: inch) + MADE IN CHINA， 日期使用ZURU 标准版本 SSCC Label 显示的是客人自己的item#，SSCC Label 贴在外箱正面的正中间，贴一面即可，跟单订购，贴纸离外箱距必须至少3cm，每一 张SSCC label 都是唯一且有不同流水及条码的，没有损耗，绝对不可贴错 ，否则贴错或损坏一张会导致全部都错，千万要注意: SSCC 贴纸务必要在正中间(可以覆 盖Logo <(>&<)> 箱唛)，否则会影响到仓库扫描识别。 3. 日期码使用ZURU标准版本。 4. 如果大货有要求入邮包盒，则对应的邮包盒上面要打上日期码。 5. 按照客户PO# 装柜/箱号顺序装柜，跟单会提前给到装柜计划。在大货生产/仓库存放时，请留意该装柜要求，以便装柜时不混乱（避免装错/装漏/找不到货号等 ）。 6. 出口加拿大，包装需要至少2/3L UPC版，无硼版本。 7.邮包盒上要印刷日期码 | V14: Kelly Shen | W14: 1.3228 | X14: =I14*W14 -> 31.7472 | Z14: 77515-S001-3L | AA14: 已入 | AB14: 1 | AC14: 24 | AE14: ok | AH14: =I14 -> 24 | AQ14: =AH14 -> 24 | AV14: =I14 -> 24 | BZ14: =AH14+AI14+AJ14 -> 24 | CE14: =CE13-AH14-AI14-AJ14 -> 688799
A15: 46016 | B15: AMAZON CA (VENDOR CENTER) | C15: 加拿大 | D15: 4500190061 | E15: 4ZFR2SBS | F15: 4500190061-240 | G15: 77515-S001 | H15: DIY厨艺大师 | I15: 48 | J15: 0 | K15: 24 | L15: =I15/K15 -> 2 | M15: 46059 | N15: 46055 | P15: 自检 | Q15: 3/2 截SI | R15: 46016 | S15: 有 | T15: 1/26客供防伪贴纸+1/27 SSCC贴纸，UPC贴纸跟返单4500132623 | U15: 日期码格式：ZURU INC(BVI) 标准格式 日期：按实际生产日期 Packaging Info: 出口加拿大，包装需要至少2/3L UPC版，无硼版本。 #77515：MA 3L C 版本加UPC贴纸覆盖原EAN条码，C版本收缩膜、纸袋、说明书， B版本收藏指南， UPC贴纸跟返单4500132623。 加客供防伪贴纸， 跟单提供； Remark: 1. Amazon FOB订单，出口CA。外箱最长边不能超过25" （超过了，case pack只能为1），不符合要求的大货，一律不接受。 2. 外箱正面印ZURU Logo + SSCC LABEL（客供贴纸)，侧面印item#（订单上显示的SKU#) + carton size(以工厂实际尺寸为准，单位: inch) + MADE IN CHINA， 日期使用ZURU 标准版本 SSCC Label 显示的是客人自己的item#，SSCC Label 贴在外箱正面的正中间，贴一面即可，跟单订购，贴纸离外箱距必须至少3cm，每一 张SSCC label 都是唯一且有不同流水及条码的，没有损耗，绝对不可贴错 ，否则贴错或损坏一张会导致全部都错，千万要注意: SSCC 贴纸务必要在正中间(可以覆 盖Logo <(>&<)> 箱唛)，否则会影响到仓库扫描识别。 3. 日期码使用ZURU标准版本。 4. 如果大货有要求入邮包盒，则对应的邮包盒上面要打上日期码。 5. 按照客户PO# 装柜/箱号顺序装柜，跟单会提前给到装柜计划。在大货生产/仓库存放时，请留意该装柜要求，以便装柜时不混乱（避免装错/装漏/找不到货号等 ）。 6. 出口加拿大，包装需要至少2/3L UPC版，无硼版本。 7.邮包盒上要印刷日期码 | V15: Kelly Shen | W15: 1.3228 | X15: =I15*W15 -> 63.4944 | Z15: 77515-S001-3L | AA15: 已入 | AB15: 1 | AC15: 48 | AE15: ok | AH15: =I15 -> 48 | AQ15: =AH15 -> 48 | AV15: =I15 -> 48 | BZ15: =AH15+AI15+AJ15 -> 48 | CE15: =CE14-AH15-AI15-AJ15 -> 688751
A16: 46016 | B16: AMAZON CA (VENDOR CENTER) | C16: 加拿大 | D16: 4500190061 | E16: 4ZL7IVLS | F16: 4500190061-250 | G16: 77515-S001 | H16: DIY厨艺大师 | I16: 24 | J16: 0 | K16: 24 | L16: =I16/K16 -> 1 | M16: 46059 | N16: 46055 | P16: 自检 | Q16: 3/2 截SI | R16: 46016 | S16: 有 | T16: 1/26客供防伪贴纸+1/27 SSCC贴纸，UPC贴纸跟返单4500132623 | U16: 日期码格式：ZURU INC(BVI) 标准格式 日期：按实际生产日期 Packaging Info: 出口加拿大，包装需要至少2/3L UPC版，无硼版本。 #77515：MA 3L C 版本加UPC贴纸覆盖原EAN条码，C版本收缩膜、纸袋、说明书， B版本收藏指南， UPC贴纸跟返单4500132623。 加客供防伪贴纸， 跟单提供； Remark: 1. Amazon FOB订单，出口CA。外箱最长边不能超过25" （超过了，case pack只能为1），不符合要求的大货，一律不接受。 2. 外箱正面印ZURU Logo + SSCC LABEL（客供贴纸)，侧面印item#（订单上显示的SKU#) + carton size(以工厂实际尺寸为准，单位: inch) + MADE IN CHINA， 日期使用ZURU 标准版本 SSCC Label 显示的是客人自己的item#，SSCC Label 贴在外箱正面的正中间，贴一面即可，跟单订购，贴纸离外箱距必须至少3cm，每一 张SSCC label 都是唯一且有不同流水及条码的，没有损耗，绝对不可贴错 ，否则贴错或损坏一张会导致全部都错，千万要注意: SSCC 贴纸务必要在正中间(可以覆 盖Logo <(>&<)> 箱唛)，否则会影响到仓库扫描识别。 3. 日期码使用ZURU标准版本。 4. 如果大货有要求入邮包盒，则对应的邮包盒上面要打上日期码。 5. 按照客户PO# 装柜/箱号顺序装柜，跟单会提前给到装柜计划。在大货生产/仓库存放时，请留意该装柜要求，以便装柜时不混乱（避免装错/装漏/找不到货号等 ）。 6. 出口加拿大，包装需要至少2/3L UPC版，无硼版本。 7.邮包盒上要印刷日期码 | V16: Kelly Shen | W16: 1.3228 | X16: =I16*W16 -> 31.7472 | Z16: 77515-S001-3L | AA16: 已入 | AB16: 1 | AC16: 24 | AE16: ok | AH16: =I16 -> 24 | AQ16: =AH16 -> 24 | AV16: =I16 -> 24 | BZ16: =AH16+AI16+AJ16 -> 24 | CE16: =CE15-AH16-AI16-AJ16 -> 688727
A17: 46016 | B17: AMAZON CA (VENDOR CENTER) | C17: 加拿大 | D17: 4500190061 | E17: 3ZRO7B9Y | F17: 4500190061-260 | G17: 77515-S001 | H17: DIY厨艺大师 | I17: 72 | J17: 0 | K17: 24 | L17: =I17/K17 -> 3 | M17: 46059 | N17: 46055 | P17: 自检 | Q17: 3/2 截SI | R17: 46016 | S17: 有 | T17: 1/26客供防伪贴纸+1/27 SSCC贴纸，UPC贴纸跟返单4500132623 | U17: 日期码格式：ZURU INC(BVI) 标准格式 日期：按实际生产日期 Packaging Info: 出口加拿大，包装需要至少2/3L UPC版，无硼版本。 #77515：MA 3L C 版本加UPC贴纸覆盖原EAN条码，C版本收缩膜、纸袋、说明书， B版本收藏指南， UPC贴纸跟返单4500132623。 加客供防伪贴纸， 跟单提供； Remark: 1. Amazon FOB订单，出口CA。外箱最长边不能超过25" （超过了，case pack只能为1），不符合要求的大货，一律不接受。 2. 外箱正面印ZURU Logo + SSCC LABEL（客供贴纸)，侧面印item#（订单上显示的SKU#) + carton size(以工厂实际尺寸为准，单位: inch) + MADE IN CHINA， 日期使用ZURU 标准版本 SSCC Label 显示的是客人自己的item#，SSCC Label 贴在外箱正面的正中间，贴一面即可，跟单订购，贴纸离外箱距必须至少3cm，每一 张SSCC label 都是唯一且有不同流水及条码的，没有损耗，绝对不可贴错 ，否则贴错或损坏一张会导致全部都错，千万要注意: SSCC 贴纸务必要在正中间(可以覆 盖Logo <(>&<)> 箱唛)，否则会影响到仓库扫描识别。 3. 日期码使用ZURU标准版本。 4. 如果大货有要求入邮包盒，则对应的邮包盒上面要打上日期码。 5. 按照客户PO# 装柜/箱号顺序装柜，跟单会提前给到装柜计划。在大货生产/仓库存放时，请留意该装柜要求，以便装柜时不混乱（避免装错/装漏/找不到货号等 ）。 6. 出口加拿大，包装需要至少2/3L UPC版，无硼版本。 7.邮包盒上要印刷日期码 | V17: Kelly Shen | W17: 1.3228 | X17: =I17*W17 -> 95.2416 | Z17: 77515-S001-3L | AA17: 已入 | AB17: 1 | AC17: 72 | AE17: ok | AH17: =I17 -> 72 | AQ17: =AH17 -> 72 | AV17: =I17 -> 72 | BZ17: =AH17+AI17+AJ17 -> 72 | CE17: =CE16-AH17-AI17-AJ17 -> 688655
A18: 46016 | B18: AMAZON CA (VENDOR CENTER) | C18: 加拿大 | D18: 4500190061 | E18: 7ADPTYFE | F18: 4500190061-270 | G18: 77515-S001 | H18: DIY厨艺大师 | I18: 24 | J18: 0 | K18: 24 | L18: =I18/K18 -> 1 | M18: 46059 | N18: 46055 | P18: 自检 | Q18: 3/2 截SI | R18: 46016 | S18: 有 | T18: 1/26客供防伪贴纸+1/27 SSCC贴纸，UPC贴纸跟返单4500132623 | U18: 日期码格式：ZURU INC(BVI) 标准格式 日期：按实际生产日期 Packaging Info: 出口加拿大，包装需要至少2/3L UPC版，无硼版本。 #77515：MA 3L C 版本加UPC贴纸覆盖原EAN条码，C版本收缩膜、纸袋、说明书， B版本收藏指南， UPC贴纸跟返单4500132623。 加客供防伪贴纸， 跟单提供； Remark: 1. Amazon FOB订单，出口CA。外箱最长边不能超过25" （超过了，case pack只能为1），不符合要求的大货，一律不接受。 2. 外箱正面印ZURU Logo + SSCC LABEL（客供贴纸)，侧面印item#（订单上显示的SKU#) + carton size(以工厂实际尺寸为准，单位: inch) + MADE IN CHINA， 日期使用ZURU 标准版本 SSCC Label 显示的是客人自己的item#，SSCC Label 贴在外箱正面的正中间，贴一面即可，跟单订购，贴纸离外箱距必须至少3cm，每一 张SSCC label 都是唯一且有不同流水及条码的，没有损耗，绝对不可贴错 ，否则贴错或损坏一张会导致全部都错，千万要注意: SSCC 贴纸务必要在正中间(可以覆 盖Logo <(>&<)> 箱唛)，否则会影响到仓库扫描识别。 3. 日期码使用ZURU标准版本。 4. 如果大货有要求入邮包盒，则对应的邮包盒上面要打上日期码。 5. 按照客户PO# 装柜/箱号顺序装柜，跟单会提前给到装柜计划。在大货生产/仓库存放时，请留意该装柜要求，以便装柜时不混乱（避免装错/装漏/找不到货号等 ）。 6. 出口加拿大，包装需要至少2/3L UPC版，无硼版本。 7.邮包盒上要印刷日期码 | V18: Kelly Shen | W18: 1.3228 | X18: =I18*W18 -> 31.7472 | Z18: 77515-S001-3L | AA18: 已入 | AB18: 1 | AC18: 24 | AE18: ok | AH18: =I18 -> 24 | AQ18: =AH18 -> 24 | AV18: =I18 -> 24 | BZ18: =AH18+AI18+AJ18 -> 24 | CE18: =CE17-AH18-AI18-AJ18 -> 688631
A19: 45971 | B19: AMAZON.COM SERVICES LLC | C19: 美国 | D19: 4500184784 | E19: 6PY2KI7D | F19: 4500184784-10 | G19: 77516-S001 | H19: DIY厨艺大师*2 | I19: 216 | J19: 0 | K19: 12 | L19: =I19/K19 -> 18 | M19: 46077 | N19: 46062 | P19: 自检 | Q19: 3/5 截SI | R19: 45971 | S19: 有 | T19: 1/27SSCC Label(客供贴纸 | U19: 日期码格式：ZURU INC(BVI) 标准格式 日期：按实际生产日期 Packaging Info: #77516: 2PK #77515 入PVC圆筒。收藏指南用MA 5L. 3L不带UPC版收缩膜,3L 2PK的3L铜版纸B版本。 （两个球的配比不能重复）。 Remark: 1. Amazon MDDP订单，出口US。 2. 日期码使用ZURU标准版本。 3. 如果大货有要求入邮包盒，则对应的邮包盒上面要打上日期码。 4. 箱尺寸要求：外箱最长边不能超过25"(超过了，case pack只能为1)，不符合要求的大货，一律不接受。 5. 外箱箱唛要求： ①外箱正面印ZURU Logo+SSCC Label(客供贴纸，由跟单订购)。关于 SSCC Label 请注意： SSCC Label显示的是客人自己的item#。每一张SSCC label都是唯一且有不同流水及条码的，没有损耗，绝对不可贴错。如果贴错或损坏任何一张，都会导致全部都 错，千万要注意！SSCC Label必须贴在外箱正面的正中间位置(贴一面即可)，并且贴纸离外箱边距必须至少3cm(可以覆盖Logo<(>&<)>箱唛)，否则会影响到客户那边 仓库的扫描识别。 ②外箱侧面印item#(订单上显示的SKU#)+carton size(以工厂实际尺寸为准，单位: inch)+MADE IN CHINA，日期使用ZURU 标准版本。 6. 装柜要求：按照客户PO#装柜/箱号顺序装柜，跟单会提前给到装柜计划。 在大货生产/仓库存放时，请留意该装柜要求，以便装柜时不混乱(避免装错/装漏/找不到货号等)。 | V19: Kelly Shen/Mia Pan/P | W19: 1.8222 | X19: =W19*I19 -> 393.5952 | Z19: 77516-S001 | AA19: 已入 | AB19: 1 | AC19: 216 | AE19: ok | AH19: =I19*2 -> 432 | AK19: =I19*2 -> 432 | AU19: =I19*2 -> 432 | BW19: =I19 -> 216 | BY19: =BW19 -> 216 | BZ19: =AH19+AI19+AJ19 -> 432 | CE19: =CE18-AH19-AI19-AJ19 -> 688199
